Workbook

Sheet TERadj
A1: record_id | B1: company | C1: region | D1: country | E1: region2 | F1: date | G1: regionalstrategyasiapacific_vehicletype_total | H1: regionalstrategyeurope_vehicletype_total | I1: regionalstrategynorthamerica_vehicletype_total | J1: regionalstrategyglobal_vehicletype_total | K1: regionalstrategysouthamerica_vehicletype_total | L1: regionalstrategyafrica_vehicletype_total | M1: nonlistedrealestate | N1: regionalstrategy_nonlistedfunds_total | O1: regionalstrategy_separateaccountsdirect_total | P1: regionalstrategy_separateaccountsindirect_total | Q1: regionalstrategy_jvs_total | R1: regionalstrategy_fundsoffunds_total | S1: regionalstrategy_debt_total | T1: investordomicileasiapacific_nonlistedfunds | U1: investordomicileeurope_nonlistedfunds | V1: investordomicilenorthamerica_nonlistedfunds | W1: investordomicilesouthamerica_nonlistedfunds | X1: investordomicileafrica_nonlistedfunds | Y1: investordomicileasiapacific_separateaccountsdirect | Z1: investordomicileeurope_separateaccountsdirect | AA1: investordomicilenorthamerica_separateaccountsdirect | AB1: investordomicilesouthamerica_separateaccountsdirect | AC1: investordomicileafrica_separateaccountsdirect | AD1: investordomicileasiapacific_separateaccountsindirect | AE1: investordomicileeurope_separateaccountsindirect | AF1: investordomicilenorthamerica_separateaccountsindirect | AG1: investordomicilesouthamerica_separateaccountsindirect | AH1: investordomicileafrica_separateaccountsindirect | AI1: investordomicileasiapacific_jvs | AJ1: investordomicileeurope_jvs | AK1: investordomicilenorthamerica_jvs | AL1: investordomicilesouthamerica_jvs | AM1: investordomicileafrica_jvs | AN1: investordomicileasiapacific_fundsoffunds | AO1: investordomicileeurope_fundsoffunds | AP1: investordomicilenorthamerica_fundsoffunds | AQ1: investordomicilesouthamerica_fundsoffunds | AR1: investordomicileafrica_fundsoffunds | AS1: investordomicileasiapacific_debt | AT1: investordomicileeurope_debt | AU1: investordomicilenorthamerica_debt | AV1: investordomicilesouthamerica_debt | AW1: investordomicileafrica_debt | AX1: capitalraisingactivity_nonlistedrealestatevehicles | AY1: nocapitalraisingactivity_reason | AZ1: percentmethod_placementagent | BA1: percentmethod_investorscontactingdirectly | BB1: percentmethod_relationshipwithinvestors | BC1: percentmethod_other | BD1: capitalraisingactivity_development | BE1: capitalraisingactivity_impactregulation | BF1: capitalinvested_nonlistedrealestate | BG1: nov_regionalstrategyasiapacific_vehicletype_total | BH1: nov_regionalstrategyeurope_vehicletype_total | BI1: nov_regionalstrategynorthamerica_vehicletype_total | BJ1: nov_regionalstrategyglobal_vehicletype_total | BK1: nov_regionalstrategysouthamerica_vehicletype_total | BL1: nov_regionalstrategyafrica_vehicletype_total | BM1: nov_regionalstrategy_vehicletype_total | BN1: regionalstrategy_vehicletype_total | BO1: nov_regionalstrategy_nonlistedfunds_total | BP1: nov_regionalstrategy_separateaccountsdirect_total | BQ1: nov_regionalstrategy_separateaccountsindirect_total | BR1: nov_regionalstrategy_jvs_total | BS1: nov_regionalstrategy_fundsoffunds_total | BT1: nov_regionalstrategy_debt_total | BU1: regionalstrategyasiapacific_nonlistedfunds | BV1: regionalstrategyeurope_nonlistedfunds | BW1: regionalstrategynorthamerica_nonlistedfunds | BX1: regionalstrategyglobal_nonlistedfunds | BY1: regionalstrategysouthamerica_nonlistedfunds | BZ1: regionalstrategyafrica_nonlistedfunds | CA1: regionalstrategyasiapacific_separateaccountsdirect | CB1: regionalstrategyeurope_separateaccountsdirect | CC1: regionalstrategynorthamerica_separateaccountsdirect | CD1: regionalstrategyglobal_separateaccountsdirect | CE1: regionalstrategysouthamerica_separateaccountsdirect | CF1: regionalstrategyafrica_separateaccountsdirect | CG1: regionalstrategyasiapacific_separateaccountsindirect | CH1: regionalstrategyeurope_separateaccountsindirect | CI1: regionalstrategynorthamerica_separateaccountsindirect | CJ1: regionalstrategyglobal_separateaccountsindirect | CK1: regionalstrategysouthamerica_separateaccountsindirect | CL1: regionalstrategyafrica_separateaccountsindirect | CM1: regionalstrategyasiapacific_jvs | CN1: regionalstrategyeurope_jvs | CO1: regionalstrategynorthamerica_jvs | CP1: regionalstrategyglobal_jvs | CQ1: regionalstrategysouthamerica_jvs | CR1: regionalstrategyafrica_jvs | CS1: regionalstrategyasiapacific_fundsoffunds | CT1: regionalstrategyeurope_fundsoffunds | CU1: regionalstrategynorthamerica_fundsoffunds | CV1: regionalstrategyglobal_fundsoffunds | CW1: regionalstrategysouthamerica_fundsoffunds | CX1: regionalstrategyafrica_fundsoffunds | CY1: regionalstrategyasiapacific_debt | CZ1: regionalstrategyeurope_debt | DA1: regionalstrategynorthamerica_debt | DB1: regionalstrategyglobal_debt | DC1: regionalstrategysouthamerica_debt | DD1: regionalstrategyafrica_debt | DE1: regionalstrategyasiapacific_operatingplatforms | DF1: regionalstrategyeurope_operatingplatforms | DG1: regionalstrategynorthamerica_operatingplatforms | DH1: regionalstrategyglobal_operatingplatforms | DI1: regionalstrategysouthamerica_operatingplatforms | DJ1: regionalstrategyafrica_operatingplatforms | DK1: nov_regionalstrategyasiapacific_nonlistedfunds | DL1: nov_regionalstrategyeurope_nonlistedfunds | DM1: nov_regionalstrategynorthamerica_nonlistedfunds | DN1: nov_regionalstrategyglobal_nonlistedfunds | DO1: nov_regionalstrategysouthamerica_nonlistedfunds | DP1: nov_regionalstrategyafrica_nonlistedfunds | DQ1: nov_regionalstrategyasiapacific_separateaccountsdirect | DR1: nov_regionalstrategyeurope_separateaccountsdirect | DS1: nov_regionalstrategynorthamerica_separateaccountsdirect | DT1: nov_regionalstrategyglobal_separateaccountsdirect | DU1: nov_regionalstrategysouthamerica_separateaccountsdirect | DV1: nov_regionalstrategyafrica_separateaccountsdirect | DW1: nov_regionalstrategyasiapacific_separateaccountsindirect | DX1: nov_regionalstrategyeurope_separateaccountsindirect | DY1: nov_regionalstrategynorthamerica_separateaccountsindirect | DZ1: nov_regionalstrategyglobal_separateaccountsindirect | EA1: nov_regionalstrategysouthamerica_separateaccountsindirect | EB1: nov_regionalstrategyafrica_separateaccountsindirect | EC1: nov_regionalstrategyasiapacific_jvs | ED1: nov_regionalstrategyeurope_jvs | EE1: nov_regionalstrategynorthamerica_jvs | EF1: nov_regionalstrategyglobal_jvs | EG1: nov_regionalstrategysouthamerica_jvs | EH1: nov_regionalstrategyafrica_jvs | EI1: nov_regionalstrategyasiapacific_fundsoffunds | EJ1: nov_regionalstrategyeurope_fundsoffunds | EK1: nov_regionalstrategynorthamerica_fundsoffunds | EL1: nov_regionalstrategyglobal_fundsoffunds | EM1: nov_regionalstrategysouthamerica_fundsoffunds | EN1: nov_regionalstrategyafrica_fundsoffunds | EO1: nov_regionalstrategyasiapacific_debt | EP1: nov_regionalstrategyeurope_debt | EQ1: nov_regionalstrategynorthamerica_debt | ER1: nov_regionalstrategyglobal_debt | ES1: nov_regionalstrategysouthamerica_debt | ET1: nov_regionalstrategyafrica_debt | EU1: pensionfunds_vehicletype_total | EV1: insurancecompanies_vehicletype_total | EW1: sovereignwealthfunds_vehicletype_total | EX1: governmentinstitutions_vehicletype_total | EY1: charitiesfoundationsnonprofitorganizations_vehicletype_total | EZ1: fundsoffunds_vehicletype_total | FA1: highnetworthindividualsfamilyoffices_vehicletype_total | FB1: otherinvestortype_vehicletype_total | FC1: pensionfunds_nonlistedfunds | FD1: insurancecompanies_nonlistedfunds | FE1: sovereignwealthfunds_nonlistedfunds | FF1: governmentinstitutions_nonlistedfunds | FG1: charitiesfoundationsnonprofitorganizations_nonlistedfunds | FH1: fundsoffunds_nonlistedfunds | FI1: highnetworthindividualsfamilyoffices_nonlistedfunds | FJ1: otherinvestortype_nonlistedfunds | FK1: pensionfunds_separateaccountsdirect | FL1: insurancecompanies_separateaccountsdirect | FM1: sovereignwealthfunds_separateaccountsdirect | FN1: governmentinstitutions_separateaccountsdirect | FO1: charitiesfoundationsnonprofitorganizations_separateaccountsdirect | FP1: fundsoffunds_separateaccountsdirect | FQ1: highnetworthindividualsfamilyoffices_separateaccountsdirect | FR1: otherinvestortype_separateaccountsdirect | FS1: pensionfunds_separateaccountsindirect | FT1: insurancecompanies_separateaccountsindirect | FU1: sovereignwealthfunds_separateaccountsindirect | FV1: governmentinstitutions_separateaccountsindirect | FW1: charitiesfoundationsnonprofitorganizations_separateaccountsindirect | FX1: fundsoffunds_separateaccountsindirect | FY1: highnetworthindividualsfamilyoffices_separateaccountsindirect | FZ1: otherinvestortype_separateaccountsindirect | GA1: pensionfunds_jvs | GB1: insurancecompanies_jvs | GC1: sovereignwealthfunds_jvs | GD1: governmentinstitutions_jvs | GE1: charitiesfoundationsnonprofitorganizations_jvs | GF1: fundsoffunds_jvs | GG1: highnetworthindividualsfamilyoffices_jvs | GH1: otherinvestortype_jvs | GI1: pensionfunds_fundsoffunds | GJ1: insurancecompanies_fundsoffunds | GK1: sovereignwealthfunds_fundsoffunds | GL1: governmentinstitutions_fundsoffunds | GM1: charitiesfoundationsnonprofitorganizations_fundsoffunds | GN1: fundsoffunds_fundsoffunds | GO1: highnetworthindividualsfamilyoffices_fundsoffunds | GP1: otherinvestortype_fundsoffunds | GQ1: pensionfunds_debt | GR1: insurancecompanies_debt | GS1: sovereignwealthfunds_debt | GT1: governmentinstitutions_debt | GU1: charitiesfoundationsnonprofitorganizations_debt | GV1: fundsoffunds_debt | GW1: highnetworthindividualsfamilyoffices_debt | GX1: otherinvestortype_debt | GY1: investordomicileasiapacific_vehicletype_total | GZ1: investordomicileeurope_vehicletype_total | HA1: investordomicilenorthamerica_vehicletype_total | HB1: investordomicilesouthamerica_vehicletype_total | HC1: investordomicileafrica_vehicletype_total | HD1: global_pensionfunds_vehicletype_total | HE1: global_insurancecompanies_vehicletype_total | HF1: global_sovereignwealthfunds_vehicletype_total | HG1: global_governmentinstitutions_vehicletype_total | HH1: global_charitiesfoundationsnonprofitorganizations_vehicletype_total | HI1: global_fundsoffunds_vehicletype_total | HJ1: global_highnetworthindividualsfamilyoffices_vehicletype_total | HK1: global_otherinvestortype_vehicletype_total | HL1: global_investortype_nonlistedfunds_total | HM1: global_investortype_separateaccountsdirect_total | HN1: global_investortype_separateaccountsindirect_total | HO1: global_investortype_jvs_total | HP1: global_investortype_fundsoffunds_total | HQ1: global_investortype_debt_total | HR1: global_investortype_operatingplatforms_total | HS1: global_investordomicileasiapacific_vehicletype_total | HT1: global_investordomicileeurope_vehicletype_total | HU1: global_investordomicilenorthamerica_vehicletype_total | HV1: global_investordomicilesouthamerica_vehicletype_total | HW1: global_investordomicileafrica_vehicletype_total | HX1: global_nonlistedfunds_singlesectoroffice | HY1: global_nonlistedfunds_singlesectorretail | HZ1: global_nonlistedfunds_singlesectorindustrial_logistics | IA1: global_nonlistedfunds_singlesectorresidential_multifamily_apartments | IB1: global_nonlistedfunds_singlesectorstudenthousing | IC1: global_nonlistedfunds_singlesectorseniorliving_agedcare_healthcare | ID1: global_nonlistedfunds_singlesectorhotel_leisure | IE1: global_nonlistedfunds_singlesectorother | IF1: global_nonlistedfunds_multisectormainsectors | IG1: global_nonlistedfunds_multisectoralternativesectors | IH1: global_nonlistedfunds_multisectormixmainalternativesectors | II1: global_separateaccountsdirect_singlesectoroffice | IJ1: global_separateaccountsdirect_singlesectorretail | IK1: global_separateaccountsdirect_singlesectorindustrial_logistics | IL1: global_separateaccountsdirect_singlesectorresidential_multifamily_apartments | IM1: global_separateaccountsdirect_singlesectorstudenthousing | IN1: global_separateaccountsdirect_singlesectorseniorliving_agedcare_healthcare | IO1: global_separateaccountsdirect_singlesectorhotel_leisure | IP1: global_separateaccountsdirect_singlesectorother | IQ1: global_separateaccountsdirect_multisectormainsectors | IR1: global_separateaccountsdirect_multisectoralternativesectors | IS1: global_separateaccountsdirect_multisectormixmainalternativesectors | IT1: global_separateaccountsindirect_singlesectoroffice | IU1: global_separateaccountsindirect_singlesectorretail | IV1: global_separateaccountsindirect_singlesectorindustrial_logistics | IW1: global_separateaccountsindirect_singlesectorresidential_multifamily_apartments | IX1: global_separateaccountsindirect_singlesectorstudenthousing | IY1: global_separateaccountsindirect_singlesectorseniorliving_agedcare_healthcare | IZ1: global_separateaccountsindirect_singlesectorhotel_leisure | JA1: global_separateaccountsindirect_singlesectorother | JB1: global_separateaccountsindirect_multisectormainsectors | JC1: global_separateaccountsindirect_multisectoralternativesectors | JD1: global_separateaccountsindirect_multisectormixmainalternativesectors | JE1: global_jvs_singlesectoroffice | JF1: global_jvs_singlesectorretail | JG1: global_jvs_singlesectorindustrial_logistics | JH1: global_jvs_singlesectorresidential_multifamily_apartments | JI1: global_jvs_singlesectorstudenthousing | JJ1: global_jvs_singlesectorseniorliving_agedcare_healthcare | JK1: global_jvs_singlesectorhotel_leisure | JL1: global_jvs_singlesectorother | JM1: global_jvs_multisectormainsectors | JN1: global_jvs_multisectoralternativesectors | JO1: global_jvs_multisectormixmainalternativesectors | JP1: global_fundsoffunds_singlesectoroffice | JQ1: global_fundsoffunds_singlesectorretail | JR1: global_fundsoffunds_singlesectorindustrial_logistics | JS1: global_fundsoffunds_singlesectorresidential_multifamily_apartments | JT1: global_fundsoffunds_singlesectorstudenthousing | JU1: global_fundsoffunds_singlesectorseniorliving_agedcare_healthcare | JV1: global_fundsoffunds_singlesectorhotel_leisure | JW1: global_fundsoffunds_singlesectorother | JX1: global_fundsoffunds_multisectormainsectors | JY1: global_fundsoffunds_multisectoralternativesectors | JZ1: global_fundsoffunds_multisectormixmainalternativesectors | KA1: global_debt_singlesectoroffice | KB1: global_debt_singlesectorretail | KC1: global_debt_singlesectorindustrial_logistics | KD1: global_debt_singlesectorresidential_multifamily_apartments | KE1: global_debt_singlesectorstudenthousing | KF1: global_debt_singlesectorseniorliving_agedcare_healthcare | KG1: global_debt_singlesectorhotel_leisure | KH1: global_debt_singlesectorother | KI1: global_debt_multisectormainsectors | KJ1: global_debt_multisectoralternativesectors | KK1: global_debt_multisectormixmainalternativesectors | KL1: global_investordomicileasiapacific_nonlistedfunds | KM1: global_investordomicileeurope_nonlistedfunds | KN1: global_investordomicilenorthamerica_nonlistedfunds | KO1: global_investordomicilesouthamerica_nonlistedfunds | KP1: global_investordomicileafrica_nonlistedfunds | KQ1: global_investordomicileasiapacific_separateaccountsdirect | KR1: global_investordomicileeurope_separateaccountsdirect | KS1: global_investordomicilenorthamerica_separateaccountsdirect | KT1: global_investordomicilesouthamerica_separateaccountsdirect | KU1: global_investordomicileafrica_separateaccountsdirect | KV1: global_investordomicileasiapacific_separateaccountsindirect | KW1: global_investordomicileeurope_separateaccountsindirect | KX1: global_investordomicilenorthamerica_separateaccountsindirect | KY1: global_investordomicilesouthamerica_separateaccountsindirect | KZ1: global_investordomicileafrica_separateaccountsindirect | LA1: global_investordomicileasiapacific_jvs | LB1: global_investordomicileeurope_jvs | LC1: global_investordomicilenorthamerica_jvs | LD1: global_investordomicilesouthamerica_jvs | LE1: global_investordomicileafrica_jvs | LF1: global_investordomicileasiapacific_fundsoffunds | LG1: global_investordomicileeurope_fundsoffunds | LH1: global_investordomicilenorthamerica_fundsoffunds | LI1: global_investordomicilesouthamerica_fundsoffunds | LJ1: global_investordomicileafrica_fundsoffunds | LK1: global_investordomicileasiapacific_debt | LL1: global_investordomicileeurope_debt | LM1: global_investordomicilenorthamerica_debt | LN1: global_investordomicilesouthamerica_debt | LO1: global_investordomicileafrica_debt | LP1: global_nonlistedfunds_singlecountry | LQ1: global_nonlistedfunds_multicountry | LR1: global_countrystrategy_nonlistedfunds_total | LS1: global_separateaccountsdirect_singlecountry | LT1: global_separateaccountsdirect_multicountry | LU1: global_countrystrategy_separateaccountsdirect_total | LV1: global_separateaccountsindirect_singlecountry | LW1: global_separateaccountsindirect_multicountry | LX1: global_countrystrategy_separateaccountsindirect_total | LY1: global_jvs_singlecountry | LZ1: global_jvs_multicountry | MA1: global_countrystrategy_jvs_total | MB1: global_fundsoffunds_singlecountry | MC1: global_fundsoffunds_multicountry | MD1: global_countrystrategy_fundsoffunds_total | ME1: global_debt_singlecountry | MF1: global_debt_multicountry | MG1: global_countrystrategy_debt_total | MH1: global_countrystrategy_operatingplatforms_total | MI1: global_nonlistedfunds_core_seniordebt | MJ1: global_separateaccountsdirect_core_seniordebt | MK1: global_separateaccountsindirect_core_seniordebt | ML1: global_jvs_core_seniordebt | MM1: global_fundsoffunds_core_seniordebt | MN1: global_debt_core_seniordebt | MO1: global_nonlistedvehicles_core_seniordebt_total | MP1: global_nonlistedfunds_valueadded_juniorandsubordinateddebt | MQ1: global_separateaccountsdirect_valueadded_juniorandsubordinateddebt | MR1: global_separateaccountsindirect_valueadded_juniorandsubordinateddebt | MS1: global_jvs_valueadded_juniorandsubordinateddebt | MT1: global_fundsoffunds_valueadded_juniorandsubordinateddebt | MU1: global_debt_valueadded_juniorandsubordinateddebt | MV1: global_nonlistedvehicles_valueadded_juniorandsubordinateddebt_total | MW1: global_nonlistedfunds_opportunistic_mezzaninedebt | MX1: global_separateaccountsdirect_opportunistic_mezzaninedebt | MY1: global_separateaccountsindirect_opportunistic_mezzaninedebt | MZ1: global_jvs_opportunistic_mezzaninedebt | NA1: global_fundsoffunds_opportunistic_mezzaninedebt | NB1: global_debt_opportunistic_mezzaninedebt | NC1: global_nonlistedvehicles_opportunistic_mezzaninedebt_total | ND1: global_nonlistedfunds_mixedstrategies | NE1: global_separateaccountsdirect_mixedstrategies | NF1: global_separateaccountsindirect_mixedstrategies | NG1: global_jvs_mixedstrategies | NH1: global_fundsoffunds_mixedstrategies | NI1: global_debt_mixedstrategies | NJ1: global_nonlistedvehicles_mixedstrategies_total | NK1: europe_pensionfunds_vehicletype_total | NL1: europe_insurancecompanies_vehicletype_total | NM1: europe_sovereignwealthfunds_vehicletype_total | NN1: europe_governmentinstitutions_vehicletype_total | NO1: europe_charitiesfoundationsnonprofitorganizations_vehicletype_total | NP1: europe_fundsoffunds_vehicletype_total | NQ1: europe_highnetworthindividualsfamilyoffices_vehicletype_total | NR1: europe_otherinvestortype_vehicletype_total | NS1: europe_investortype_nonlistedfunds_total | NT1: europe_investortype_separateaccountsdirect_total | NU1: europe_investortype_separateaccountsindirect_total | NV1: europe_investortype_jvs_total | NW1: europe_investortype_fundsoffunds_total | NX1: europe_investortype_debt_total | NY1: europe_investortype_operatingplatforms_total | NZ1: europe_nonlistedfunds_singlecountry | OA1: europe_nonlistedfunds_multicountry | OB1: europe_countrystrategy_nonlistedfunds_total | OC1: europe_separateaccountsdirect_singlecountry | OD1: europe_separateaccountsdirect_multicountry | OE1: europe_countrystrategy_separateaccountsdirect_total | OF1: europe_separateaccountsindirect_singlecountry | OG1: europe_separateaccountsindirect_multicountry | OH1: europe_countrystrategy_separateaccountsindirect_total | OI1: europe_jvs_singlecountry | OJ1: europe_jvs_multicountry | OK1: europe_countrystrategy_jvs_total | OL1: europe_fundsoffunds_singlecountry | OM1: europe_fundsoffunds_multicountry | ON1: europe_countrystrategy_fundsoffunds_total | OO1: europe_debt_singlecountry | OP1: europe_debt_multicountry | OQ1: europe_countrystrategy_debt_total | OR1: europe_countrystrategy_operatingplatforms_total | OS1: europe_investordomicileasiapacific_vehicletype_total | OT1: europe_investordomicileeurope_vehicletype_total | OU1: europe_investordomicilenorthamerica_vehicletype_total | OV1: europe_investordomicilesouthamerica_vehicletype_total | OW1: europe_investordomicileafrica_vehicletype_total | OX1: europe_pensionfunds_nonlistedfunds | OY1: europe_pensionfunds_separateaccountsdirect | OZ1: europe_pensionfunds_separateaccountsindirect | PA1: europe_pensionfunds_jvs | PB1: europe_pensionfunds_fundsoffunds | PC1: europe_pensionfunds_debt | PD1: europe_insurancecompanies_nonlistedfunds | PE1: europe_insurancecompanies_separateaccountsdirect | PF1: europe_insurancecompanies_separateaccountsindirect | PG1: europe_insurancecompanies_jvs | PH1: europe_insurancecompanies_fundsoffunds | PI1: europe_insurancecompanies_debt | PJ1: europe_sovereignwealthfunds_nonlistedfunds | PK1: europe_sovereignwealthfunds_separateaccountsdirect | PL1: europe_sovereignwealthfunds_separateaccountsindirect | PM1: europe_sovereignwealthfunds_jvs | PN1: europe_sovereignwealthfunds_fundsoffunds | PO1: europe_sovereignwealthfunds_debt | PP1: europe_governmentinstitutions_nonlistedfunds | PQ1: europe_governmentinstitutions_separateaccountsdirect | PR1: europe_governmentinstitutions_separateaccountsindirect | PS1: europe_governmentinstitutions_jvs | PT1: europe_governmentinstitutions_fundsoffunds | PU1: europe_governmentinstitutions_debt | PV1: europe_charitiesfoundationsnonprofitorganizations_nonlistedfunds | PW1: europe_charitiesfoundationsnonprofitorganizations_separateaccountsdirect | PX1: europe_charitiesfoundationsnonprofitorganizations_separateaccountsindirect | PY1: europe_charitiesfoundationsnonprofitorganizations_jvs | PZ1: europe_charitiesfoundationsnonprofitorganizations_fundsoffunds | QA1: europe_charitiesfoundationsnonprofitorganizations_debt | QB1: europe_fundsoffunds_nonlistedfunds | QC1: europe_fundsoffunds_separateaccountsdirect | QD1: europe_fundsoffunds_separateaccountsindirect | QE1: europe_fundsoffunds_jvs | QF1: europe_fundsoffunds_fundsoffunds | QG1: europe_fundsoffunds_debt | QH1: europe_highnetworthindividualsfamilyoffices_nonlistedfunds | QI1: europe_highnetworthindividualsfamilyoffices_separateaccountsdirect | QJ1: europe_highnetworthindividualsfamilyoffices_separateaccountsindirect | QK1: europe_highnetworthindividualsfamilyoffices_jvs | QL1: europe_highnetworthindividualsfamilyoffices_fundsoffunds | QM1: europe_highnetworthindividualsfamilyoffices_debt | QN1: europe_otherinvestortype_nonlistedfunds | QO1: europe_otherinvestortype_separateaccountsdirect | QP1: europe_otherinvestortype_separateaccountsindirect | QQ1: europe_otherinvestortype_jvs | QR1: europe_otherinvestortype_fundsoffunds | QS1: europe_otherinvestortype_debt | QT1: europe_nonlistedfunds_singlesectoroffice | QU1: europe_nonlistedfunds_singlesectorretail | QV1: europe_nonlistedfunds_singlesectorindustrial_logistics | QW1: europe_nonlistedfunds_singlesectorresidential_multifamily_apartments | QX1: europe_nonlistedfunds_singlesectorstudenthousing | QY1: europe_nonlistedfunds_singlesectorseniorliving_agedcare_healthcare | QZ1: europe_nonlistedfunds_singlesectorhotel_leisure | RA1: europe_nonlistedfunds_singlesectorother | RB1: europe_nonlistedfunds_multisectormainsectors | RC1: europe_nonlistedfunds_multisectoralternativesectors | RD1: europe_nonlistedfunds_multisectormixmainalternativesectors | RE1: europe_separateaccountsdirect_singlesectoroffice | RF1: europe_separateaccountsdirect_singlesectorretail | RG1: europe_separateaccountsdirect_singlesectorindustrial_logistics | RH1: europe_separateaccountsdirect_singlesectorresidential_multifamily_apartments | RI1: europe_separateaccountsdirect_singlesectorstudenthousing | RJ1: europe_separateaccountsdirect_singlesectorseniorliving_agedcare_healthcare | RK1: europe_separateaccountsdirect_singlesectorhotel_leisure | RL1: europe_separateaccountsdirect_singlesectorother | RM1: europe_separateaccountsdirect_multisectormainsectors | RN1: europe_separateaccountsdirect_multisectoralternativesectors | RO1: europe_separateaccountsdirect_multisectormixmainalternativesectors | RP1: europe_separateaccountsindirect_singlesectoroffice | RQ1: europe_separateaccountsindirect_singlesectorretail | RR1: europe_separateaccountsindirect_singlesectorindustrial_logistics | RS1: europe_separateaccountsindirect_singlesectorresidential_multifamily_apartments | RT1: europe_separateaccountsindirect_singlesectorstudenthousing | RU1: europe_separateaccountsindirect_singlesectorseniorliving_agedcare_healthcare | RV1: europe_separateaccountsindirect_singlesectorhotel_leisure | RW1: europe_separateaccountsindirect_singlesectorother | RX1: europe_separateaccountsindirect_multisectormainsectors | RY1: europe_separateaccountsindirect_multisectoralternativesectors | RZ1: europe_separateaccountsindirect_multisectormixmainalternativesectors | SA1: europe_jvs_singlesectoroffice | SB1: europe_jvs_singlesectorretail | SC1: europe_jvs_singlesectorindustrial_logistics | SD1: europe_jvs_singlesectorresidential_multifamily_apartments | SE1: europe_jvs_singlesectorstudenthousing | SF1: europe_jvs_singlesectorseniorliving_agedcare_healthcare | SG1: europe_jvs_singlesectorhotel_leisure | SH1: europe_jvs_singlesectorother | SI1: europe_jvs_multisectormainsectors | SJ1: europe_jvs_multisectoralternativesectors | SK1: europe_jvs_multisectormixmainalternativesectors | SL1: europe_fundsoffunds_singlesectoroffice | SM1: europe_fundsoffunds_singlesectorretail | SN1: europe_fundsoffunds_singlesectorindustrial_logistics | SO1: europe_fundsoffunds_singlesectorresidential_multifamily_apartments | SP1: europe_fundsoffunds_singlesectorstudenthousing | SQ1: europe_fundsoffunds_singlesectorseniorliving_agedcare_healthcare | SR1: europe_fundsoffunds_singlesectorhotel_leisure | SS1: europe_fundsoffunds_singlesectorother | ST1: europe_fundsoffunds_multisectormainsectors | SU1: europe_fundsoffunds_multisectoralternativesectors | SV1: europe_fundsoffunds_multisectormixmainalternativesectors | SW1: europe_debt_singlesectoroffice | SX1: europe_debt_singlesectorretail | SY1: europe_debt_singlesectorindustrial_logistics | SZ1: europe_debt_singlesectorresidential_multifamily_apartments | TA1: europe_debt_singlesectorstudenthousing | TB1: europe_debt_singlesectorseniorliving_agedcare_healthcare | TC1: europe_debt_singlesectorhotel_leisure | TD1: europe_debt_singlesectorother | TE1: europe_debt_multisectormainsectors | TF1: europe_debt_multisectoralternativesectors | TG1: europe_debt_multisectormixmainalternativesectors | TH1: europe_nonlistedvehicles_singlesectoroffice_total | TI1: europe_nonlistedvehicles_singlesectorretail_total | TJ1: europe_nonlistedvehicles_singlesectorindustrial_logistics_total | TK1: europe_nonlistedvehicles_singlesectorresidential_multifamily_apartments_total | TL1: europe_nonlistedvehicles_singlesectorstudenthousing_total | TM1: europe_nonlistedvehicles_singlesectorseniorliving_agedcare_healthcare_total | TN1: europe_nonlistedvehicles_singlesectorhotel_leisure_total | TO1: europe_nonlistedvehicles_singlesectorother_total | TP1: europe_nonlistedvehicles_multisectormainsectors_total | TQ1: europe_nonlistedvehicles_multisectoralternativesectors_total | TR1: europe_nonlistedvehicles_multisectormixmainalternativesectors_total | TS1: europe_investordomicileasiapacific_nonlistedfunds | TT1: europe_investordomicileeurope_nonlistedfunds | TU1: europe_investordomicilenorthamerica_nonlistedfunds | TV1: europe_investordomicilesouthamerica_nonlistedfunds | TW1: europe_investordomicileafrica_nonlistedfunds | TX1: europe_investordomicileasiapacific_separateaccountsdirect | TY1: europe_investordomicileeurope_separateaccountsdirect | TZ1: europe_investordomicilenorthamerica_separateaccountsdirect | UA1: europe_investordomicilesouthamerica_separateaccountsdirect | UB1: europe_investordomicileafrica_separateaccountsdirect | UC1: europe_investordomicileasiapacific_separateaccountsindirect | UD1: europe_investordomicileeurope_separateaccountsindirect | UE1: europe_investordomicilenorthamerica_separateaccountsindirect | UF1: europe_investordomicilesouthamerica_separateaccountsindirect | UG1: europe_investordomicileafrica_separateaccountsindirect | UH1: europe_investordomicileasiapacific_jvs | UI1: europe_investordomicileeurope_jvs | UJ1: europe_investordomicilenorthamerica_jvs | UK1: europe_investordomicilesouthamerica_jvs | UL1: europe_investordomicileafrica_jvs | UM1: europe_investordomicileasiapacific_fundsoffunds | UN1: europe_investordomicileeurope_fundsoffunds | UO1: europe_investordomicilenorthamerica_fundsoffunds | UP1: europe_investordomicilesouthamerica_fundsoffunds | UQ1: europe_investordomicileafrica_fundsoffunds | UR1: europe_investordomicileasiapacific_debt | US1: europe_investordomicileeurope_debt | UT1: europe_investordomicilenorthamerica_debt | UU1: europe_investordomicilesouthamerica_debt | UV1: europe_investordomicileafrica_debt | UW1: europe_nonlistedfunds_core_seniordebt | UX1: europe_separateaccountsdirect_core_seniordebt | UY1: europe_separateaccountsindirect_core_seniordebt | UZ1: europe_jvs_core_seniordebt | VA1: europe_fundsoffunds_core_seniordebt | VB1: europe_debt_core_seniordebt | VC1: europe_nonlistedfunds_valueadded_juniorandsubordinateddebt | VD1: europe_separateaccountsdirect_valueadded_juniorandsubordinateddebt | VE1: europe_separateaccountsindirect_valueadded_juniorandsubordinateddebt | VF1: europe_jvs_valueadded_juniorandsubordinateddebt | VG1: europe_fundsoffunds_valueadded_juniorandsubordinateddebt | VH1: europe_debt_valueadded_juniorandsubordinateddebt | VI1: europe_nonlistedfunds_opportunistic_mezzaninedebt | VJ1: europe_separateaccountsdirect_opportunistic_mezzaninedebt | VK1: europe_separateaccountsindirect_opportunistic_mezzaninedebt | VL1: europe_jvs_opportunistic_mezzaninedebt | VM1: europe_fundsoffunds_opportunistic_mezzaninedebt | VN1: europe_debt_opportunistic_mezzaninedebt | VO1: europe_nonlistedfunds_mixedstrategies | VP1: europe_separateaccountsdirect_mixedstrategies | VQ1: europe_separateaccountsindirect_mixedstrategies | VR1: europe_jvs_mixedstrategies | VS1: europe_fundsoffunds_mixedstrategies | VT1: europe_debt_mixedstrategies | VU1: global_pensionfunds_nonlistedfunds | VV1: global_insurancecompanies_nonlistedfunds | VW1: global_sovereignwealthfunds_nonlistedfunds | VX1: global_governmentinstitutions_nonlistedfunds | VY1: global_charitiesfoundationsnonprofitorganizations_nonlistedfunds | VZ1: global_fundsoffunds_nonlistedfunds | WA1: global_highnetworthindividualsfamilyoffices_nonlistedfunds | WB1: global_otherinvestortype_nonlistedfunds | WC1: global_pensionfunds_separateaccountsdirect | WD1: global_insurancecompanies_separateaccountsdirect | WE1: global_sovereignwealthfunds_separateaccountsdirect | WF1: global_governmentinstitutions_separateaccountsdirect | WG1: global_charitiesfoundationsnonprofitorganizations_separateaccountsdirect | WH1: global_fundsoffunds_separateaccountsdirect | WI1: global_highnetworthindividualsfamilyoffices_separateaccountsdirect | WJ1: global_otherinvestortype_separateaccountsdirect | WK1: global_pensionfunds_separateaccountsindirect | WL1: global_insurancecompanies_separateaccountsindirect | WM1: global_sovereignwealthfunds_separateaccountsindirect | WN1: global_governmentinstitutions_separateaccountsindirect | WO1: global_charitiesfoundationsnonprofitorganizations_separateaccountsindirect | WP1: global_fundsoffunds_separateaccountsindirect | WQ1: global_highnetworthindividualsfamilyoffices_separateaccountsindirect | WR1: global_otherinvestortype_separateaccountsindirect | WS1: global_pensionfunds_jvs | WT1: global_insurancecompanies_jvs | WU1: global_sovereignwealthfunds_jvs | WV1: global_governmentinstitutions_jvs | WW1: global_charitiesfoundationsnonprofitorganizations_jvs | WX1: global_fundsoffunds_jvs | WY1: global_highnetworthindividualsfamilyoffices_jvs | WZ1: global_otherinvestortype_jvs | XA1: global_pensionfunds_fundsoffunds | XB1: global_insurancecompanies_fundsoffunds | XC1: global_sovereignwealthfunds_fundsoffunds | XD1: global_governmentinstitutions_fundsoffunds | XE1: global_charitiesfoundationsnonprofitorganizations_fundsoffunds | XF1: global_fundsoffunds_fundsoffunds | XG1: global_highnetworthindividualsfamilyoffices_fundsoffunds | XH1: global_otherinvestortype_fundsoffunds | XI1: global_pensionfunds_debt | XJ1: global_insurancecompanies_debt | XK1: global_sovereignwealthfunds_debt | XL1: global_governmentinstitutions_debt | XM1: global_charitiesfoundationsnonprofitorganizations_debt | XN1: global_fundsoffunds_debt | XO1: global_highnetworthindividualsfamilyoffices_debt | XP1: global_otherinvestortype_debt
A2: cr_2025-684 | B2: Blue Vista Management | C2: North America | D2: United States | E2: US | F2: 45700 | G2: 0 | H2: 0 | I2: 144.41968 | J2: 0 | K2: 0 | L2: 0 | M2: 144.41968 | N2: 120.34973 | O2: 0 | P2: 0 | Q2: 24.069946 | R2: 0 | S2: 0 | T2: 28.883936 | U2: 62.58186 | V2: 28.883936 | W2: 0 | X2: 0 | Y2: 0 | Z2: 0 | AA2: 0 | AB2: 0 | AC2: 0 | AD2: 0 | AE2: 0 | AF2: 0 | AG2: 0 | AH2: 0 | AI2: 0 | AJ2: 0 | AK2: 0 | AL2: 0 | AM2: 24.069946 | AN2: 0 | AO2: 0 | AP2: 0 | AQ2: 0 | AR2: 0 | AS2: 0 | AT2: 0 | AU2: 0 | AV2: 0 | AW2: 0 | AX2: 1 | AY2: 0 | AZ2: 0 | BA2: 0 | BB2: 100 | BC2: 0 | BD2: 1 | BE2: 3 | BF2: 72.209839 | BG2: 0 | BH2: 0 | BI2: 2 | BJ2: 0 | BK2: 0 | BL2: 0 | BM2: 2 | BN2: 144.41968 | BO2: 1 | BP2: 0 | BQ2: 0 | BR2: 1 | BS2: 0 | BT2: 0 | BU2: 0 | BV2: 0 | BW2: 120.34973 | BX2: 0 | BY2: 0 | BZ2: 0 | CA2: 0 | CB2: 0 | CC2: 0 | CD2: 0 | CE2: 0 | CF2: 0 | CG2: 0 | CH2: 0 | CI2: 0 | CJ2: 0 | CK2: 0 | CL2: 0 | CM2: 0 | CN2: 0 | CO2: 24.069946 | CP2: 0 | CQ2: 0 | CR2: 0 | CS2: 0 | CT2: 0 | CU2: 0 | CV2: 0 | CW2: 0 | CX2: 0 | CY2: 0 | CZ2: 0 | DA2: 0 | DB2: 0 | DC2: 0 | DD2: 0 | DE2: 0 | DF2: 0 | DG2: 0 | DH2: 0 | DI2: 0 | DJ2: 0 | DK2: 0 | DL2: 0 | DM2: 1 | DN2: 0 | DO2: 0 | DP2: 0 | DQ2: 0 | DR2: 0 | DS2: 0 | DT2: 0 | DU2: 0 | DV2: 0 | DW2: 0 | DX2: 0 | DY2: 0 | DZ2: 0 | EA2: 0 | EB2: 0 | EC2: 0 | ED2: 0 | EE2: 1 | EF2: 0 | EG2: 0 | EH2: 0 | EI2: 0 | EJ2: 0 | EK2: 0 | EL2: 0 | EM2: 0 | EN2: 0 | EO2: 0 | EP2: 0 | EQ2: 0 | ER2: 0 | ES2: 0 | ET2: 0 | EU2: 91.465797 | EV2: 24.069946 | EW2: 0 | EX2: 0 | EY2: 0 | EZ2: 28.883936 | FA2: 0 | FB2: 0 | FC2: 91.465797 | FD2: 0 | FE2: 0 | FF2: 0 | FG2: 0 | FH2: 28.883936 | FI2: 0 | FJ2: 0 | FK2: 0 | FL2: 0 | FM2: 0 | FN2: 0 | FO2: 0 | FP2: 0 | FQ2: 0 | FR2: 0 | FS2: 0 | FT2: 0 | FU2: 0 | FV2: 0 | FW2: 0 | FX2: 0 | FY2: 0 | FZ2: 0 | GA2: 0 | GB2: 24.069946 | GC2: 0 | GD2: 0 | GE2: 0 | GF2: 0 | GG2: 0 | GH2: 0 | GI2: 0 | GJ2: 0 | GK2: 0 | GL2: 0 | GM2: 0 | GN2: 0 | GO2: 0 | GP2: 0 | GQ2: 0 | GR2: 0 | GS2: 0 | GT2: 0 | GU2: 0 | GV2: 0 | GW2: 0 | GX2: 0 | GY2: 28.883936 | GZ2: 62.58186 | HA2: 28.883936 | HB2: 0 | HC2: 24.069946 | HD2: 0 | HE2: 0 | HF2: 0 | HG2: 0 | HH2: 0 | HI2: 0 | HJ2: 0 | HK2: 0 | HL2: 0 | HM2: 0 | HN2: 0 | HO2: 0 | HP2: 0 | HQ2: 0 | HR2: 0 | HS2: 0 | HT2: 0 | HU2: 0 | HV2: 0 | HW2: 0 | HX2: 0 | HY2: 0 | HZ2: 0 | IA2: 0 | IB2: 0 | IC2: 0 | ID2: 0 | IE2: 0 | IF2: 0 | IG2: 0 | IH2: 0 | II2: 0 | IJ2: 0 | IK2: 0 | IL2: 0 | IM2: 0 | IN2: 0 | IO2: 0 | IP2: 0 | IQ2: 0 | IR2: 0 | IS2: 0 | IT2: 0 | IU2: 0 | IV2: 0 | IW2: 0 | IX2: 0 | IY2: 0 | IZ2: 0 | JA2: 0 | JB2: 0 | JC2: 0 | JD2: 0 | JE2: 0 | JF2: 0 | JG2: 0 | JH2: 0 | JI2: 0 | JJ2: 0 | JK2: 0 | JL2: 0 | JM2: 0 | JN2: 0 | JO2: 0 | JP2: 0 | JQ2: 0 | JR2: 0 | JS2: 0 | JT2: 0 | JU2: 0 | JV2: 0 | JW2: 0 | JX2: 0 | JY2: 0 | JZ2: 0 | KA2: 0 | KB2: 0 | KC2: 0 | KD2: 0 | KE2: 0 | KF2: 0 | KG2: 0 | KH2: 0 | KI2: 0 | KJ2: 0 | KK2: 0 | KL2: 0 | KM2: 0 | KN2: 0 | KO2: 0 | KP2: 0 | KQ2: 0 | KR2: 0 | KS2: 0 | KT2: 0 | KU2: 0 | KV2: 0 | KW2: 0 | KX2: 0 | KY2: 0 | KZ2: 0 | LA2: 0 | LB2: 0 | LC2: 0 | LD2: 0 | LE2: 0 | LF2: 0 | LG2: 0 | LH2: 0 | LI2: 0 | LJ2: 0 | LK2: 0 | LL2: 0 | LM2: 0 | LN2: 0 | LO2: 0 | LP2: 0 | LQ2: 0 | LR2: 0 | LS2: 0 | LT2: 0 | LU2: 0 | LV2: 0 | LW2: 0 | LX2: 0 | LY2: 0 | LZ2: 0 | MA2: 0 | MB2: 0 | MC2: 0 | MD2: 0 | ME2: 0 | MF2: 0 | MG2: 0 | MH2: 0 | MI2: 0 | MJ2: 0 | MK2: 0 | ML2: 0 | MM2: 0 | MN2: 0 | MO2: 0 | MP2: 0 | MQ2: 0 | MR2: 0 | MS2: 0 | MT2: 0 | MU2: 0 | MV2: 0 | MW2: 0 | MX2: 0 | MY2: 0 | MZ2: 0 | NA2: 0 | NB2: 0 | NC2: 0 | ND2: 0 | NE2: 0 | NF2: 0 | NG2: 0 | NH2: 0 | NI2: 0 | NJ2: 0 | NK2: 0 | NL2: 0 | NM2: 0 | NN2: 0 | NO2: 0 | NP2: 0 | NQ2: 0 | NR2: 0 | NS2: 0 | NT2: 0 | NU2: 0 | NV2: 0 | NW2: 0 | NX2: 0 | NY2: 0 | NZ2: 0 | OA2: 0 | OB2: 0 | OC2: 0 | OD2: 0 | OE2: 0 | OF2: 0 | OG2: 0 | OH2: 0 | OI2: 0 | OJ2: 0 | OK2: 0 | OL2: 0 | OM2: 0 | ON2: 0 | OO2: 0 | OP2: 0 | OQ2: 0 | OR2: 0 | OS2: 0 | OT2: 0 | OU2: 0 | OV2: 0 | OW2: 0 | OX2: 0 | OY2: 0 | OZ2: 0 | PA2: 0 | PB2: 0 | PC2: 0 | PD2: 0 | PE2: 0 | PF2: 0 | PG2: 0 | PH2: 0 | PI2: 0 | PJ2: 0 | PK2: 0 | PL2: 0 | PM2: 0 | PN2: 0 | PO2: 0 | PP2: 0 | PQ2: 0 | PR2: 0 | PS2: 0 | PT2: 0 | PU2: 0 | PV2: 0 | PW2: 0 | PX2: 0 | PY2: 0 | PZ2: 0 | QA2: 0 | QB2: 0 | QC2: 0 | QD2: 0 | QE2: 0 | QF2: 0 | QG2: 0 | QH2: 0 | QI2: 0 | QJ2: 0 | QK2: 0 | QL2: 0 | QM2: 0 | QN2: 0 | QO2: 0 | QP2: 0 | QQ2: 0 | QR2: 0 | QS2: 0 | QT2: 0 | QU2: 0 | QV2: 0 | QW2: 0 | QX2: 0 | QY2: 0 | QZ2: 0 | RA2: 0 | RB2: 0 | RC2: 0 | RD2: 0 | RE2: 0 | RF2: 0 | RG2: 0 | RH2: 0 | RI2: 0 | RJ2: 0 | RK2: 0 | RL2: 0 | RM2: 0 | RN2: 0 | RO2: 0 | RP2: 0 | RQ2: 0 | RR2: 0 | RS2: 0 | RT2: 0 | RU2: 0 | RV2: 0 | RW2: 0 | RX2: 0 | RY2: 0 | RZ2: 0 | SA2: 0 | SB2: 0 | SC2: 0 | SD2: 0 | SE2: 0 | SF2: 0 | SG2: 0 | SH2: 0 | SI2: 0 | SJ2: 0 | SK2: 0 | SL2: 0 | SM2: 0 | SN2: 0 | SO2: 0 | SP2: 0 | SQ2: 0 | SR2: 0 | SS2: 0 | ST2: 0 | SU2: 0 | SV2: 0 | SW2: 0 | SX2: 0 | SY2: 0 | SZ2: 0 | TA2: 0 | TB2: 0 | TC2: 0 | TD2: 0 | TE2: 0 | TF2: 0 | TG2: 0 | TH2: 0 | TI2: 0 | TJ2: 0 | TK2: 0 | TL2: 0 | TM2: 0 | TN2: 0 | TO2: 0 | TP2: 0 | TQ2: 0 | TR2: 0 | TS2: 0 | TT2: 0 | TU2: 0 | TV2: 0 | TW2: 0 | TX2: 0 | TY2: 0 | TZ2: 0 | UA2: 0 | UB2: 0 | UC2: 0 | UD2: 0 | UE2: 0 | UF2: 0 | UG2: 0 | UH2: 0 | UI2: 0 | UJ2: 0 | UK2: 0 | UL2: 0 | UM2: 0 | UN2: 0 | UO2: 0 | UP2: 0 | UQ2: 0 | UR2: 0 | US2: 0 | UT2: 0 | UU2: 0 | UV2: 0 | UW2: 0 | UX2: 0 | UY2: 0 | UZ2: 0 | VA2: 0 | VB2: 0 | VC2: 0 | VD2: 0 | VE2: 0 | VF2: 0 | VG2: 0 | VH2: 0 | VI2: 0 | VJ2: 0 | VK2: 0 | VL2: 0 | VM2: 0 | VN2: 0 | VO2: 0 | VP2: 0 | VQ2: 0 | VR2: 0 | VS2: 0 | VT2: 0 | VU2: 0 | VV2: 0 | VW2: 0 | VX2: 0 | VY2: 0 | VZ2: 0 | WA2: 0 | WB2: 0 | WC2: 0 | WD2: 0 | WE2: 0 | WF2: 0 | WG2: 0 | WH2: 0 | WI2: 0 | WJ2: 0 | WK2: 0 | WL2: 0 | WM2: 0 | WN2: 0 | WO2: 0 | WP2: 0 | WQ2: 0 | WR2: 0 | WS2: 0 | WT2: 0 | WU2: 0 | WV2: 0 | WW2: 0 | WX2: 0 | WY2: 0 | WZ2: 0 | XA2: 0 | XB2: 0 | XC2: 0 | XD2: 0 | XE2: 0 | XF2: 0 | XG2: 0 | XH2: 0 | XI2: 0 | XJ2: 0 | XK2: 0 | XL2: 0 | XM2: 0 | XN2: 0 | XO2: 0 | XP2: 0
A3: cr_2025-695 | B3: Capitaland Investment | C3: Asia Pacific | D3: Singapore | E3: Asia Pacific | F3: 45723 | G3: 1519.2915 | H3: 0 | I3: 0 | J3: 0 | K3: 0 | L3: 0 | M3: 1519.2915 | N3: 149.8092 | O3: 485.46661 | P3: 0 | Q3: 593.58362 | R3: 0 | S3: 290.43201 | T3: 149.8092 | U3: 0 | V3: 0 | W3: 0 | X3: 0 | Y3: 485.46661 | Z3: 0 | AA3: 0 | AB3: 0 | AC3: 0 | AD3: 0 | AE3: 0 | AF3: 0 | AG3: 0 | AH3: 0 | AI3: 456.49408 | AJ3: 137.08955 | AK3: 0 | AL3: 0 | AM3: 0 | AN3: 0 | AO3: 0 | AP3: 0 | AQ3: 0 | AR3: 0 | AS3: 290.43201 | AT3: 0 | AU3: 0 | AV3: 0 | AW3: 0 | AX3: 1 | AY3: 0 | AZ3: 3 | BA3: 0 | BB3: 97 | BC3: 0 | BD3: 2 | BE3: 3 | BF3: 0 | BG3: 11 | BH3: 0 | BI3: 0 | BJ3: 0 | BK3: 0 | BL3: 0 | BM3: 11 | BN3: 1519.2915 | BO3: 2 | BP3: 2 | BQ3: 0 | BR3: 5 | BS3: 0 | BT3: 2 | BU3: 149.8092 | BV3: 0 | BW3: 0 | BX3: 0 | BY3: 0 | BZ3: 0 | CA3: 485.46661 | CB3: 0 | CC3: 0 | CD3: 0 | CE3: 0 | CF3: 0 | CG3: 0 | CH3: 0 | CI3: 0 | CJ3: 0 | CK3: 0 | CL3: 0 | CM3: 593.58362 | CN3: 0 | CO3: 0 | CP3: 0 | CQ3: 0 | CR3: 0 | CS3: 0 | CT3: 0 | CU3: 0 | CV3: 0 | CW3: 0 | CX3: 0 | CY3: 290.43201 | CZ3: 0 | DA3: 0 | DB3: 0 | DC3: 0 | DD3: 0 | DE3: 0 | DF3: 0 | DG3: 0 | DH3: 0 | DI3: 0 | DJ3: 0 | DK3: 2 | DL3: 0 | DM3: 0 | DN3: 0 | DO3: 0 | DP3: 0 | DQ3: 2 | DR3: 0 | DS3: 0 | DT3: 0 | DU3: 0 | DV3: 0 | DW3: 0 | DX3: 0 | DY3: 0 | DZ3: 0 | EA3: 0 | EB3: 0 | EC3: 5 | ED3: 0 | EE3: 0 | EF3: 0 | EG3: 0 | EH3: 0 | EI3: 0 | EJ3: 0 | EK3: 0 | EL3: 0 | EM3: 0 | EN3: 0 | EO3: 2 | EP3: 0 | EQ3: 0 | ER3: 0 | ES3: 0 | ET3: 0 | EU3: 204.92769 | EV3: 369.57648 | EW3: 0 | EX3: 0 | EY3: 0 | EZ3: 0 | FA3: 200.68781 | FB3: 744.09949 | FC3: 0 | FD3: 0 | FE3: 0 | FF3: 0 | FG3: 0 | FH3: 0 | FI3: 17.66618 | FJ3: 132.14302 | FK3: 0 | FL3: 298.91177 | FM3: 0 | FN3: 0 | FO3: 0 | FP3: 0 | FQ3: 170.30197 | FR3: 16.252886 | FS3: 0 | FT3: 0 | FU3: 0 | FV3: 0 | FW3: 0 | FX3: 0 | FY3: 0 | FZ3: 0 | GA3: 137.08955 | GB3: 70.664719 | GC3: 0 | GD3: 0 | GE3: 0 | GF3: 0 | GG3: 0 | GH3: 385.82938 | GI3: 0 | GJ3: 0 | GK3: 0 | GL3: 0 | GM3: 0 | GN3: 0 | GO3: 0 | GP3: 0 | GQ3: 67.838127 | GR3: 0 | GS3: 0 | GT3: 0 | GU3: 0 | GV3: 0 | GW3: 12.719649 | GX3: 209.87422 | GY3: 1382.2019 | GZ3: 137.08955 | HA3: 0 | HB3: 0 | HC3: 0 | HD3: 0 | HE3: 0 | HF3: 0 | HG3: 0 | HH3: 0 | HI3: 0 | HJ3: 0 | HK3: 0 | HL3: 0 | HM3: 0 | HN3: 0 | HO3: 0 | HP3: 0 | HQ3: 0 | HR3: 0 | HS3: 0 | HT3: 0 | HU3: 0 | HV3: 0 | HW3: 0 | HX3: 0 | HY3: 0 | HZ3: 0 | IA3: 0 | IB3: 0 | IC3: 0 | ID3: 0 | IE3: 0 | IF3: 0 | IG3: 0 | IH3: 0 | II3: 0 | IJ3: 0 | IK3: 0 | IL3: 0 | IM3: 0 | IN3: 0 | IO3: 0 | IP3: 0 | IQ3: 0 | IR3: 0 | IS3: 0 | IT3: 0 | IU3: 0 | IV3: 0 | IW3: 0 | IX3: 0 | IY3: 0 | IZ3: 0 | JA3: 0 | JB3: 0 | JC3: 0 | JD3: 0 | JE3: 0 | JF3: 0 | JG3: 0 | JH3: 0 | JI3: 0 | JJ3: 0 | JK3: 0 | JL3: 0 | JM3: 0 | JN3: 0 | JO3: 0 | JP3: 0 | JQ3: 0 | JR3: 0 | JS3: 0 | JT3: 0 | JU3: 0 | JV3: 0 | JW3: 0 | JX3: 0 | JY3: 0 | JZ3: 0 | KA3: 0 | KB3: 0 | KC3: 0 | KD3: 0 | KE3: 0 | KF3: 0 | KG3: 0 | KH3: 0 | KI3: 0 | KJ3: 0 | KK3: 0 | KL3: 0 | KM3: 0 | KN3: 0 | KO3: 0 | KP3: 0 | KQ3: 0 | KR3: 0 | KS3: 0 | KT3: 0 | KU3: 0 | KV3: 0 | KW3: 0 | KX3: 0 | KY3: 0 | KZ3: 0 | LA3: 0 | LB3: 0 | LC3: 0 | LD3: 0 | LE3: 0 | LF3: 0 | LG3: 0 | LH3: 0 | LI3: 0 | LJ3: 0 | LK3: 0 | LL3: 0 | LM3: 0 | LN3: 0 | LO3: 0 | LP3: 0 | LQ3: 0 | LR3: 0 | LS3: 0 | LT3: 0 | LU3: 0 | LV3: 0 | LW3: 0 | LX3: 0 | LY3: 0 | LZ3: 0 | MA3: 0 | MB3: 0 | MC3: 0 | MD3: 0 | ME3: 0 | MF3: 0 | MG3: 0 | MH3: 0 | MI3: 0 | MJ3: 0 | MK3: 0 | ML3: 0 | MM3: 0 | MN3: 0 | MO3: 0 | MP3: 0 | MQ3: 0 | MR3: 0 | MS3: 0 | MT3: 0 | MU3: 0 | MV3: 0 | MW3: 0 | MX3: 0 | MY3: 0 | MZ3: 0 | NA3: 0 | NB3: 0 | NC3: 0 | ND3: 0 | NE3: 0 | NF3: 0 | NG3: 0 | NH3: 0 | NI3: 0 | NJ3: 0 | NK3: 0 | NL3: 0 | NM3: 0 | NN3: 0 | NO3: 0 | NP3: 0 | NQ3: 0 | NR3: 0 | NS3: 0 | NT3: 0 | NU3: 0 | NV3: 0 | NW3: 0 | NX3: 0 | NY3: 0 | NZ3: 0 | OA3: 0 | OB3: 0 | OC3: 0 | OD3: 0 | OE3: 0 | OF3: 0 | OG3: 0 | OH3: 0 | OI3: 0 | OJ3: 0 | OK3: 0 | OL3: 0 | OM3: 0 | ON3: 0 | OO3: 0 | OP3: 0 | OQ3: 0 | OR3: 0 | OS3: 0 | OT3: 0 | OU3: 0 | OV3: 0 | OW3: 0 | OX3: 0 | OY3: 0 | OZ3: 0 | PA3: 0 | PB3: 0 | PC3: 0 | PD3: 0 | PE3: 0 | PF3: 0 | PG3: 0 | PH3: 0 | PI3: 0 | PJ3: 0 | PK3: 0 | PL3: 0 | PM3: 0 | PN3: 0 | PO3: 0 | PP3: 0 | PQ3: 0 | PR3: 0 | PS3: 0 | PT3: 0 | PU3: 0 | PV3: 0 | PW3: 0 | PX3: 0 | PY3: 0 | PZ3: 0 | QA3: 0 | QB3: 0 | QC3: 0 | QD3: 0 | QE3: 0 | QF3: 0 | QG3: 0 | QH3: 0 | QI3: 0 | QJ3: 0 | QK3: 0 | QL3: 0 | QM3: 0 | QN3: 0 | QO3: 0 | QP3: 0 | QQ3: 0 | QR3: 0 | QS3: 0 | QT3: 0 | QU3: 0 | QV3: 0 | QW3: 0 | QX3: 0 | QY3: 0 | QZ3: 0 | RA3: 0 | RB3: 0 | RC3: 0 | RD3: 0 | RE3: 0 | RF3: 0 | RG3: 0 | RH3: 0 | RI3: 0 | RJ3: 0 | RK3: 0 | RL3: 0 | RM3: 0 | RN3: 0 | RO3: 0 | RP3: 0 | RQ3: 0 | RR3: 0 | RS3: 0 | RT3: 0 | RU3: 0 | RV3: 0 | RW3: 0 | RX3: 0 | RY3: 0 | RZ3: 0 | SA3: 0 | SB3: 0 | SC3: 0 | SD3: 0 | SE3: 0 | SF3: 0 | SG3: 0 | SH3: 0 | SI3: 0 | SJ3: 0 | SK3: 0 | SL3: 0 | SM3: 0 | SN3: 0 | SO3: 0 | SP3: 0 | SQ3: 0 | SR3: 0 | SS3: 0 | ST3: 0 | SU3: 0 | SV3: 0 | SW3: 0 | SX3: 0 | SY3: 0 | SZ3: 0 | TA3: 0 | TB3: 0 | TC3: 0 | TD3: 0 | TE3: 0 | TF3: 0 | TG3: 0 | TH3: 0 | TI3: 0 | TJ3: 0 | TK3: 0 | TL3: 0 | TM3: 0 | TN3: 0 | TO3: 0 | TP3: 0 | TQ3: 0 | TR3: 0 | TS3: 0 | TT3: 0 | TU3: 0 | TV3: 0 | TW3: 0 | TX3: 0 | TY3: 0 | TZ3: 0 | UA3: 0 | UB3: 0 | UC3: 0 | UD3: 0 | UE3: 0 | UF3: 0 | UG3: 0 | UH3: 0 | UI3: 0 | UJ3: 0 | UK3: 0 | UL3: 0 | UM3: 0 | UN3: 0 | UO3: 0 | UP3: 0 | UQ3: 0 | UR3: 0 | US3: 0 | UT3: 0 | UU3: 0 | UV3: 0 | UW3: 0 | UX3: 0 | UY3: 0 | UZ3: 0 | VA3: 0 | VB3: 0 | VC3: 0 | VD3: 0 | VE3: 0 | VF3: 0 | VG3: 0 | VH3: 0 | VI3: 0 | VJ3: 0 | VK3: 0 | VL3: 0 | VM3: 0 | VN3: 0 | VO3: 0 | VP3: 0 | VQ3: 0 | VR3: 0 | VS3: 0 | VT3: 0 | VU3: 0 | VV3: 0 | VW3: 0 | VX3: 0 | VY3: 0 | VZ3: 0 | WA3: 0 | WB3: 0 | WC3: 0 | WD3: 0 | WE3: 0 | WF3: 0 | WG3: 0 | WH3: 0 | WI3: 0 | WJ3: 0 | WK3: 0 | WL3: 0 | WM3: 0 | WN3: 0 | WO3: 0 | WP3: 0 | WQ3: 0 | WR3: 0 | WS3: 0 | WT3: 0 | WU3: 0 | WV3: 0 | WW3: 0 | WX3: 0 | WY3: 0 | WZ3: 0 | XA3: 0 | XB3: 0 | XC3: 0 | XD3: 0 | XE3: 0 | XF3: 0 | XG3: 0 | XH3: 0 | XI3: 0 | XJ3: 0 | XK3: 0 | XL3: 0 | XM3: 0 | XN3: 0 | XO3: 0 | XP3: 0
A4: cr_2025-654 | B4: Amvest | C4: Europe | D4: Netherlands | E4: Europe | F4: 45699 | G4: 0 | H4: 30 | I4: 0 | J4: 0 | K4: 0 | L4: 0 | M4: 30 | N4: 30 | O4: 0 | P4: 0 | Q4: 0 | R4: 0 | S4: 0 | T4: 0 | U4: 30 | V4: 0 | W4: 0 | X4: 0 | Y4: 0 | Z4: 0 | AA4: 0 | AB4: 0 | AC4: 0 | AD4: 0 | AE4: 0 | AF4: 0 | AG4: 0 | AH4: 0 | AI4: 0 | AJ4: 0 | AK4: 0 | AL4: 0 | AM4: 0 | AN4: 0 | AO4: 0 | AP4: 0 | AQ4: 0 | AR4: 0 | AS4: 0 | AT4: 0 | AU4: 0 | AV4: 0 | AW4: 0 | AX4: 1 | AY4: 0 | AZ4: 0 | BA4: 0 | BB4: 100 | BC4: 0 | BD4: 1 | BE4: 2 | BF4: 30 | BG4: 0 | BH4: 1 | BI4: 0 | BJ4: 0 | BK4: 0 | BL4: 0 | BM4: 1 | BN4: 30 | BO4: 1 | BP4: 0 | BQ4: 0 | BR4: 0 | BS4: 0 | BT4: 0 | BU4: 0 | BV4: 30 | BW4: 0 | BX4: 0 | BY4: 0 | BZ4: 0 | CA4: 0 | CB4: 0 | CC4: 0 | CD4: 0 | CE4: 0 | CF4: 0 | CG4: 0 | CH4: 0 | CI4: 0 | CJ4: 0 | CK4: 0 | CL4: 0 | CM4: 0 | CN4: 0 | CO4: 0 | CP4: 0 | CQ4: 0 | CR4: 0 | CS4: 0 | CT4: 0 | CU4: 0 | CV4: 0 | CW4: 0 | CX4: 0 | CY4: 0 | CZ4: 0 | DA4: 0 | DB4: 0 | DC4: 0 | DD4: 0 | DE4: 0 | DF4: 0 | DG4: 0 | DH4: 0 | DI4: 0 | DJ4: 0 | DK4: 0 | DL4: 1 | DM4: 0 | DN4: 0 | DO4: 0 | DP4: 0 | DQ4: 0 | DR4: 0 | DS4: 0 | DT4: 0 | DU4: 0 | DV4: 0 | DW4: 0 | DX4: 0 | DY4: 0 | DZ4: 0 | EA4: 0 | EB4: 0 | EC4: 0 | ED4: 0 | EE4: 0 | EF4: 0 | EG4: 0 | EH4: 0 | EI4: 0 | EJ4: 0 | EK4: 0 | EL4: 0 | EM4: 0 | EN4: 0 | EO4: 0 | EP4: 0 | EQ4: 0 | ER4: 0 | ES4: 0 | ET4: 0 | EU4: 30 | EV4: 0 | EW4: 0 | EX4: 0 | EY4: 0 | EZ4: 0 | FA4: 0 | FB4: 0 | FC4: 30 | FD4: 0 | FE4: 0 | FF4: 0 | FG4: 0 | FH4: 0 | FI4: 0 | FJ4: 0 | FK4: 0 | FL4: 0 | FM4: 0 | FN4: 0 | FO4: 0 | FP4: 0 | FQ4: 0 | FR4: 0 | FS4: 0 | FT4: 0 | FU4: 0 | FV4: 0 | FW4: 0 | FX4: 0 | FY4: 0 | FZ4: 0 | GA4: 0 | GB4: 0 | GC4: 0 | GD4: 0 | GE4: 0 | GF4: 0 | GG4: 0 | GH4: 0 | GI4: 0 | GJ4: 0 | GK4: 0 | GL4: 0 | GM4: 0 | GN4: 0 | GO4: 0 | GP4: 0 | GQ4: 0 | GR4: 0 | GS4: 0 | GT4: 0 | GU4: 0 | GV4: 0 | GW4: 0 | GX4: 0 | GY4: 0 | GZ4: 30 | HA4: 0 | HB4: 0 | HC4: 0 | HD4: 0 | HE4: 0 | HF4: 0 | HG4: 0 | HH4: 0 | HI4: 0 | HJ4: 0 | HK4: 0 | HL4: 0 | HM4: 0 | HN4: 0 | HO4: 0 | HP4: 0 | HQ4: 0 | HR4: 0 | HS4: 0 | HT4: 0 | HU4: 0 | HV4: 0 | HW4: 0 | HX4: 0 | HY4: 0 | HZ4: 0 | IA4: 0 | IB4: 0 | IC4: 0 | ID4: 0 | IE4: 0 | IF4: 0 | IG4: 0 | IH4: 0 | II4: 0 | IJ4: 0 | IK4: 0 | IL4: 0 | IM4: 0 | IN4: 0 | IO4: 0 | IP4: 0 | IQ4: 0 | IR4: 0 | IS4: 0 | IT4: 0 | IU4: 0 | IV4: 0 | IW4: 0 | IX4: 0 | IY4: 0 | IZ4: 0 | JA4: 0 | JB4: 0 | JC4: 0 | JD4: 0 | JE4: 0 | JF4: 0 | JG4: 0 | JH4: 0 | JI4: 0 | JJ4: 0 | JK4: 0 | JL4: 0 | JM4: 0 | JN4: 0 | JO4: 0 | JP4: 0 | JQ4: 0 | JR4: 0 | JS4: 0 | JT4: 0 | JU4: 0 | JV4: 0 | JW4: 0 | JX4: 0 | JY4: 0 | JZ4: 0 | KA4: 0 | KB4: 0 | KC4: 0 | KD4: 0 | KE4: 0 | KF4: 0 | KG4: 0 | KH4: 0 | KI4: 0 | KJ4: 0 | KK4: 0 | KL4: 0 | KM4: 0 | KN4: 0 | KO4: 0 | KP4: 0 | KQ4: 0 | KR4: 0 | KS4: 0 | KT4: 0 | KU4: 0 | KV4: 0 | KW4: 0 | KX4: 0 | KY4: 0 | KZ4: 0 | LA4: 0 | LB4: 0 | LC4: 0 | LD4: 0 | LE4: 0 | LF4: 0 | LG4: 0 | LH4: 0 | LI4: 0 | LJ4: 0 | LK4: 0 | LL4: 0 | LM4: 0 | LN4: 0 | LO4: 0 | LP4: 0 | LQ4: 0 | LR4: 0 | LS4: 0 | LT4: 0 | LU4: 0 | LV4: 0 | LW4: 0 | LX4: 0 | LY4: 0 | LZ4: 0 | MA4: 0 | MB4: 0 | MC4: 0 | MD4: 0 | ME4: 0 | MF4: 0 | MG4: 0 | MH4: 0 | MI4: 0 | MJ4: 0 | MK4: 0 | ML4: 0 | MM4: 0 | MN4: 0 | MO4: 0 | MP4: 0 | MQ4: 0 | MR4: 0 | MS4: 0 | MT4: 0 | MU4: 0 | MV4: 0 | MW4: 0 | MX4: 0 | MY4: 0 | MZ4: 0 | NA4: 0 | NB4: 0 | NC4: 0 | ND4: 0 | NE4: 0 | NF4: 0 | NG4: 0 | NH4: 0 | NI4: 0 | NJ4: 0 | NK4: 30 | NL4: 0 | NM4: 0 | NN4: 0 | NO4: 0 | NP4: 0 | NQ4: 0 | NR4: 0 | NS4: 30 | NT4: 0 | NU4: 0 | NV4: 0 | NW4: 0 | NX4: 0 | NY4: 0 | NZ4: 30 | OA4: 0 | OB4: 30 | OC4: 0 | OD4: 0 | OE4: 0 | OF4: 0 | OG4: 0 | OH4: 0 | OI4: 0 | OJ4: 0 | OK4: 0 | OL4: 0 | OM4: 0 | ON4: 0 | OO4: 0 | OP4: 0 | OQ4: 0 | OR4: 0 | OS4: 0 | OT4: 30 | OU4: 0 | OV4: 0 | OW4: 0 | OX4: 30 | OY4: 0 | OZ4: 0 | PA4: 0 | PB4: 0 | PC4: 0 | PD4: 0 | PE4: 0 | PF4: 0 | PG4: 0 | PH4: 0 | PI4: 0 | PJ4: 0 | PK4: 0 | PL4: 0 | PM4: 0 | PN4: 0 | PO4: 0 | PP4: 0 | PQ4: 0 | PR4: 0 | PS4: 0 | PT4: 0 | PU4: 0 | PV4: 0 | PW4: 0 | PX4: 0 | PY4: 0 | PZ4: 0 | QA4: 0 | QB4: 0 | QC4: 0 | QD4: 0 | QE4: 0 | QF4: 0 | QG4: 0 | QH4: 0 | QI4: 0 | QJ4: 0 | QK4: 0 | QL4: 0 | QM4: 0 | QN4: 0 | QO4: 0 | QP4: 0 | QQ4: 0 | QR4: 0 | QS4: 0 | QT4: 0 | QU4: 0 | QV4: 0 | QW4: 30 | QX4: 0 | QY4: 0 | QZ4: 0 | RA4: 0 | RB4: 0 | RC4: 0 | RD4: 0 | RE4: 0 | RF4: 0 | RG4: 0 | RH4: 0 | RI4: 0 | RJ4: 0 | RK4: 0 | RL4: 0 | RM4: 0 | RN4: 0 | RO4: 0 | RP4: 0 | RQ4: 0 | RR4: 0 | RS4: 0 | RT4: 0 | RU4: 0 | RV4: 0 | RW4: 0 | RX4: 0 | RY4: 0 | RZ4: 0 | SA4: 0 | SB4: 0 | SC4: 0 | SD4: 0 | SE4: 0 | SF4: 0 | SG4: 0 | SH4: 0 | SI4: 0 | SJ4: 0 | SK4: 0 | SL4: 0 | SM4: 0 | SN4: 0 | SO4: 0 | SP4: 0 | SQ4: 0 | SR4: 0 | SS4: 0 | ST4: 0 | SU4: 0 | SV4: 0 | SW4: 0 | SX4: 0 | SY4: 0 | SZ4: 0 | TA4: 0 | TB4: 0 | TC4: 0 | TD4: 0 | TE4: 0 | TF4: 0 | TG4: 0 | TH4: 0 | TI4: 0 | TJ4: 0 | TK4: 30 | TL4: 0 | TM4: 0 | TN4: 0 | TO4: 0 | TP4: 0 | TQ4: 0 | TR4: 0 | TS4: 0 | TT4: 30 | TU4: 0 | TV4: 0 | TW4: 0 | TX4: 0 | TY4: 0 | TZ4: 0 | UA4: 0 | UB4: 0 | UC4: 0 | UD4: 0 | UE4: 0 | UF4: 0 | UG4: 0 | UH4: 0 | UI4: 0 | UJ4: 0 | UK4: 0 | UL4: 0 | UM4: 0 | UN4: 0 | UO4: 0 | UP4: 0 | UQ4: 0 | UR4: 0 | US4: 0 | UT4: 0 | UU4: 0 | UV4: 0 | UW4: 30 | UX4: 0 | UY4: 0 | UZ4: 0 | VA4: 0 | VB4: 0 | VC4: 0 | VD4: 0 | VE4: 0 | VF4: 0 | VG4: 0 | VH4: 0 | VI4: 0 | VJ4: 0 | VK4: 0 | VL4: 0 | VM4: 0 | VN4: 0 | VO4: 0 | VP4: 0 | VQ4: 0 | VR4: 0 | VS4: 0 | VT4: 0 | VU4: 0 | VV4: 0 | VW4: 0 | VX4: 0 | VY4: 0 | VZ4: 0 | WA4: 0 | WB4: 0 | WC4: 0 | WD4: 0 | WE4: 0 | WF4: 0 | WG4: 0 | WH4: 0 | WI4: 0 | WJ4: 0 | WK4: 0 | WL4: 0 | WM4: 0 | WN4: 0 | WO4: 0 | WP4: 0 | WQ4: 0 | WR4: 0 | WS4: 0 | WT4: 0 | WU4: 0 | WV4: 0 | WW4: 0 | WX4: 0 | WY4: 0 | WZ4: 0 | XA4: 0 | XB4: 0 | XC4: 0 | XD4: 0 | XE4: 0 | XF4: 0 | XG4: 0 | XH4: 0 | XI4: 0 | XJ4: 0 | XK4: 0 | XL4: 0 | XM4: 0 | XN4: 0 | XO4: 0 | XP4: 0
A5: cr_2025-644 | B5: Edmond De Rothschild Reim | C5: Europe | D5: Switzerland | E5: Europe | F5: 45720 | G5: 0 | H5: 187.38 | I5: 0 | J5: 0 | K5: 0 | L5: 0 | M5: 187.38 | N5: 99.709999 | O5: 68 | P5: 0 | Q5: 19.67 | R5: 0 | S5: 0 | T5: 0 | U5: 99.709999 | V5: 0 | W5: 0 | X5: 0 | Y5: 0 | Z5: 68 | AA5: 0 | AB5: 0 | AC5: 0 | AD5: 0 | AE5: 0 | AF5: 0 | AG5: 0 | AH5: 0 | AI5: 0 | AJ5: 0 | AK5: 19.67 | AL5: 0 | AM5: 0 | AN5: 0 | AO5: 0 | AP5: 0 | AQ5: 0 | AR5: 0 | AS5: 0 | AT5: 0 | AU5: 0 | AV5: 0 | AW5: 0 | AX5: 1 | AY5: 0 | AZ5: 0 | BA5: 0 | BB5: 100 | BC5: 0 | BD5: 1 | BE5: 3 | BF5: 149.64 | BG5: 0 | BH5: 5 | BI5: 0 | BJ5: 0 | BK5: 0 | BL5: 0 | BM5: 5 | BN5: 187.38 | BO5: 3 | BP5: 1 | BQ5: 0 | BR5: 1 | BS5: 0 | BT5: 0 | BU5: 0 | BV5: 99.709999 | BW5: 0 | BX5: 0 | BY5: 0 | BZ5: 0 | CA5: 0 | CB5: 68 | CC5: 0 | CD5: 0 | CE5: 0 | CF5: 0 | CG5: 0 | CH5: 0 | CI5: 0 | CJ5: 0 | CK5: 0 | CL5: 0 | CM5: 0 | CN5: 19.67 | CO5: 0 | CP5: 0 | CQ5: 0 | CR5: 0 | CS5: 0 | CT5: 0 | CU5: 0 | CV5: 0 | CW5: 0 | CX5: 0 | CY5: 0 | CZ5: 0 | DA5: 0 | DB5: 0 | DC5: 0 | DD5: 0 | DE5: 0 | DF5: 0 | DG5: 0 | DH5: 0 | DI5: 0 | DJ5: 0 | DK5: 0 | DL5: 3 | DM5: 0 | DN5: 0 | DO5: 0 | DP5: 0 | DQ5: 0 | DR5: 1 | DS5: 0 | DT5: 0 | DU5: 0 | DV5: 0 | DW5: 0 | DX5: 0 | DY5: 0 | DZ5: 0 | EA5: 0 | EB5: 0 | EC5: 0 | ED5: 1 | EE5: 0 | EF5: 0 | EG5: 0 | EH5: 0 | EI5: 0 | EJ5: 0 | EK5: 0 | EL5: 0 | EM5: 0 | EN5: 0 | EO5: 0 | EP5: 0 | EQ5: 0 | ER5: 0 | ES5: 0 | ET5: 0 | EU5: 125.8 | EV5: 34.669998 | EW5: 0 | EX5: 0 | EY5: 0 | EZ5: 15 | FA5: 4.1999998 | FB5: 7.71 | FC5: 57.799999 | FD5: 15 | FE5: 0 | FF5: 0 | FG5: 0 | FH5: 15 | FI5: 4.1999998 | FJ5: 7.71 | FK5: 68 | FL5: 0 | FM5: 0 | FN5: 0 | FO5: 0 | FP5: 0 | FQ5: 0 | FR5: 0 | FS5: 0 | FT5: 0 | FU5: 0 | FV5: 0 | FW5: 0 | FX5: 0 | FY5: 0 | FZ5: 0 | GA5: 0 | GB5: 19.67 | GC5: 0 | GD5: 0 | GE5: 0 | GF5: 0 | GG5: 0 | GH5: 0 | GI5: 0 | GJ5: 0 | GK5: 0 | GL5: 0 | GM5: 0 | GN5: 0 | GO5: 0 | GP5: 0 | GQ5: 0 | GR5: 0 | GS5: 0 | GT5: 0 | GU5: 0 | GV5: 0 | GW5: 0 | GX5: 0 | GY5: 0 | GZ5: 167.71001 | HA5: 19.67 | HB5: 0 | HC5: 0 | HD5: 0 | HE5: 0 | HF5: 0 | HG5: 0 | HH5: 0 | HI5: 0 | HJ5: 0 | HK5: 0 | HL5: 0 | HM5: 0 | HN5: 0 | HO5: 0 | HP5: 0 | HQ5: 0 | HR5: 0 | HS5: 0 | HT5: 0 | HU5: 0 | HV5: 0 | HW5: 0 | HX5: 0 | HY5: 0 | HZ5: 0 | IA5: 0 | IB5: 0 | IC5: 0 | ID5: 0 | IE5: 0 | IF5: 0 | IG5: 0 | IH5: 0 | II5: 0 | IJ5: 0 | IK5: 0 | IL5: 0 | IM5: 0 | IN5: 0 | IO5: 0 | IP5: 0 | IQ5: 0 | IR5: 0 | IS5: 0 | IT5: 0 | IU5: 0 | IV5: 0 | IW5: 0 | IX5: 0 | IY5: 0 | IZ5: 0 | JA5: 0 | JB5: 0 | JC5: 0 | JD5: 0 | JE5: 0 | JF5: 0 | JG5: 0 | JH5: 0 | JI5: 0 | JJ5: 0 | JK5: 0 | JL5: 0 | JM5: 0 | JN5: 0 | JO5: 0 | JP5: 0 | JQ5: 0 | JR5: 0 | JS5: 0 | JT5: 0 | JU5: 0 | JV5: 0 | JW5: 0 | JX5: 0 | JY5: 0 | JZ5: 0 | KA5: 0 | KB5: 0 | KC5: 0 | KD5: 0 | KE5: 0 | KF5: 0 | KG5: 0 | KH5: 0 | KI5: 0 | KJ5: 0 | KK5: 0 | KL5: 0 | KM5: 0 | KN5: 0 | KO5: 0 | KP5: 0 | KQ5: 0 | KR5: 0 | KS5: 0 | KT5: 0 | KU5: 0 | KV5: 0 | KW5: 0 | KX5: 0 | KY5: 0 | KZ5: 0 | LA5: 0 | LB5: 0 | LC5: 0 | LD5: 0 | LE5: 0 | LF5: 0 | LG5: 0 | LH5: 0 | LI5: 0 | LJ5: 0 | LK5: 0 | LL5: 0 | LM5: 0 | LN5: 0 | LO5: 0 | LP5: 0 | LQ5: 0 | LR5: 0 | LS5: 0 | LT5: 0 | LU5: 0 | LV5: 0 | LW5: 0 | LX5: 0 | LY5: 0 | LZ5: 0 | MA5: 0 | MB5: 0 | MC5: 0 | MD5: 0 | ME5: 0 | MF5: 0 | MG5: 0 | MH5: 0 | MI5: 0 | MJ5: 0 | MK5: 0 | ML5: 0 | MM5: 0 | MN5: 0 | MO5: 0 | MP5: 0 | MQ5: 0 | MR5: 0 | MS5: 0 | MT5: 0 | MU5: 0 | MV5: 0 | MW5: 0 | MX5: 0 | MY5: 0 | MZ5: 0 | NA5: 0 | NB5: 0 | NC5: 0 | ND5: 0 | NE5: 0 | NF5: 0 | NG5: 0 | NH5: 0 | NI5: 0 | NJ5: 0 | NK5: 125.8 | NL5: 34.669998 | NM5: 0 | NN5: 0 | NO5: 0 | NP5: 15 | NQ5: 4.1999998 | NR5: 7.71 | NS5: 99.709999 | NT5: 68 | NU5: 0 | NV5: 19.67 | NW5: 0 | NX5: 0 | NY5: 0 | NZ5: 57.799999 | OA5: 41.91 | OB5: 99.709999 | OC5: 68 | OD5: 0 | OE5: 68 | OF5: 0 | OG5: 0 | OH5: 0 | OI5: 19.67 | OJ5: 0 | OK5: 19.67 | OL5: 0 | OM5: 0 | ON5: 0 | OO5: 0 | OP5: 0 | OQ5: 0 | OR5: 0 | OS5: 0 | OT5: 167.71001 | OU5: 19.67 | OV5: 0 | OW5: 0 | OX5: 57.799999 | OY5: 68 | OZ5: 0 | PA5: 0 | PB5: 0 | PC5: 0 | PD5: 15 | PE5: 0 | PF5: 0 | PG5: 19.67 | PH5: 0 | PI5: 0 | PJ5: 0 | PK5: 0 | PL5: 0 | PM5: 0 | PN5: 0 | PO5: 0 | PP5: 0 | PQ5: 0 | PR5: 0 | PS5: 0 | PT5: 0 | PU5: 0 | PV5: 0 | PW5: 0 | PX5: 0 | PY5: 0 | PZ5: 0 | QA5: 0 | QB5: 15 | QC5: 0 | QD5: 0 | QE5: 0 | QF5: 0 | QG5: 0 | QH5: 4.1999998 | QI5: 0 | QJ5: 0 | QK5: 0 | QL5: 0 | QM5: 0 | QN5: 7.71 | QO5: 0 | QP5: 0 | QQ5: 0 | QR5: 0 | QS5: 0 | QT5: 0 | QU5: 0 | QV5: 37.709999 | QW5: 0 | QX5: 0 | QY5: 0 | QZ5: 0 | RA5: 0 | RB5: 62 | RC5: 0 | RD5: 0 | RE5: 0 | RF5: 0 | RG5: 0 | RH5: 68 | RI5: 0 | RJ5: 0 | RK5: 0 | RL5: 0 | RM5: 0 | RN5: 0 | RO5: 0 | RP5: 0 | RQ5: 0 | RR5: 0 | RS5: 0 | RT5: 0 | RU5: 0 | RV5: 0 | RW5: 0 | RX5: 0 | RY5: 0 | RZ5: 0 | SA5: 0 | SB5: 0 | SC5: 19.67 | SD5: 0 | SE5: 0 | SF5: 0 | SG5: 0 | SH5: 0 | SI5: 0 | SJ5: 0 | SK5: 0 | SL5: 0 | SM5: 0 | SN5: 0 | SO5: 0 | SP5: 0 | SQ5: 0 | SR5: 0 | SS5: 0 | ST5: 0 | SU5: 0 | SV5: 0 | SW5: 0 | SX5: 0 | SY5: 0 | SZ5: 0 | TA5: 0 | TB5: 0 | TC5: 0 | TD5: 0 | TE5: 0 | TF5: 0 | TG5: 0 | TH5: 0 | TI5: 0 | TJ5: 57.380001 | TK5: 68 | TL5: 0 | TM5: 0 | TN5: 0 | TO5: 0 | TP5: 62 | TQ5: 0 | TR5: 0 | TS5: 0 | TT5: 99.709999 | TU5: 0 | TV5: 0 | TW5: 0 | TX5: 0 | TY5: 68 | TZ5: 0 | UA5: 0 | UB5: 0 | UC5: 0 | UD5: 0 | UE5: 0 | UF5: 0 | UG5: 0 | UH5: 0 | UI5: 0 | UJ5: 19.67 | UK5: 0 | UL5: 0 | UM5: 0 | UN5: 0 | UO5: 0 | UP5: 0 | UQ5: 0 | UR5: 0 | US5: 0 | UT5: 0 | UU5: 0 | UV5: 0 | UW5: 95.510002 | UX5: 68 | UY5: 0 | UZ5: 0 | VA5: 0 | VB5: 0 | VC5: 4.1999998 | VD5: 0 | VE5: 0 | VF5: 19.67 | VG5: 0 | VH5: 0 | VI5: 0 | VJ5: 0 | VK5: 0 | VL5: 0 | VM5: 0 | VN5: 0 | VO5: 0 | VP5: 0 | VQ5: 0 | VR5: 0 | VS5: 0 | VT5: 0 | VU5: 0 | VV5: 0 | VW5: 0 | VX5: 0 | VY5: 0 | VZ5: 0 | WA5: 0 | WB5: 0 | WC5: 0 | WD5: 0 | WE5: 0 | WF5: 0 | WG5: 0 | WH5: 0 | WI5: 0 | WJ5: 0 | WK5: 0 | WL5: 0 | WM5: 0 | WN5: 0 | WO5: 0 | WP5: 0 | WQ5: 0 | WR5: 0 | WS5: 0 | WT5: 0 | WU5: 0 | WV5: 0 | WW5: 0 | WX5: 0 | WY5: 0 | WZ5: 0 | XA5: 0 | XB5: 0 | XC5: 0 | XD5: 0 | XE5: 0 | XF5: 0 | XG5: 0 | XH5: 0 | XI5: 0 | XJ5: 0 | XK5: 0 | XL5: 0 | XM5: 0 | XN5: 0 | XO5: 0 | XP5: 0
A6: cr_2025-691 | B6: Jamestown, L.P | C6: North America | D6: United States | E6: US | F6: 45730 | G6: 0 | H6: 1.338289 | I6: 0.48139894 | J6: 0 | K6: 0 | L6: 0 | M6: 1.338289 | N6: 0.48139894 | O6: 0 | P6: 0 | Q6: 1.338289 | R6: 0 | S6: 0 | T6: 0 | U6: 0 | V6: 0.48139894 | W6: 0 | X6: 0 | Y6: 0 | Z6: 0 | AA6: 0 | AB6: 0 | AC6: 0 | AD6: 0 | AE6: 0 | AF6: 0 | AG6: 0 | AH6: 0 | AI6: 0 | AJ6: 0.85689008 | AK6: 0 | AL6: 0 | AM6: 0 | AN6: 0 | AO6: 0 | AP6: 0 | AQ6: 0 | AR6: 0 | AS6: 0 | AT6: 0 | AU6: 0 | AV6: 0 | AW6: 0 | AX6: 1 | AY6: 0 | AZ6: 0 | BA6: 0 | BB6: 100 | BC6: 0 | BD6: 1 | BE6: 3 | BF6: 0.48139894 | BG6: 0 | BH6: 1 | BI6: 1 | BJ6: 0 | BK6: 0 | BL6: 0 | BM6: 2 | BN6: 1.819688 | BO6: 1 | BP6: 0 | BQ6: 0 | BR6: 1 | BS6: 0 | BT6: 0 | BU6: 0 | BV6: 0 | BW6: 0.48139894 | BX6: 0 | BY6: 0 | BZ6: 0 | CA6: 0 | CB6: 0 | CC6: 0 | CD6: 0 | CE6: 0 | CF6: 0 | CG6: 0 | CH6: 0 | CI6: 0 | CJ6: 0 | CK6: 0 | CL6: 0 | CM6: 0 | CN6: 1.338289 | CO6: 0 | CP6: 0 | CQ6: 0 | CR6: 0 | CS6: 0 | CT6: 0 | CU6: 0 | CV6: 0 | CW6: 0 | CX6: 0 | CY6: 0 | CZ6: 0 | DA6: 0 | DB6: 0 | DC6: 0 | DD6: 0 | DE6: 0 | DF6: 0 | DG6: 0 | DH6: 0 | DI6: 0 | DJ6: 0 | DK6: 0 | DL6: 0 | DM6: 1 | DN6: 0 | DO6: 0 | DP6: 0 | DQ6: 0 | DR6: 0 | DS6: 0 | DT6: 0 | DU6: 0 | DV6: 0 | DW6: 0 | DX6: 0 | DY6: 0 | DZ6: 0 | EA6: 0 | EB6: 0 | EC6: 0 | ED6: 1 | EE6: 0 | EF6: 0 | EG6: 0 | EH6: 0 | EI6: 0 | EJ6: 0 | EK6: 0 | EL6: 0 | EM6: 0 | EN6: 0 | EO6: 0 | EP6: 0 | EQ6: 0 | ER6: 0 | ES6: 0 | ET6: 0 | EU6: 0.27921137 | EV6: 0 | EW6: 0 | EX6: 0.27921137 | EY6: 0 | EZ6: 0 | FA6: 0.48139894 | FB6: 0.28883937 | FC6: 0 | FD6: 0 | FE6: 0 | FF6: 0 | FG6: 0 | FH6: 0 | FI6: 0.48139894 | FJ6: 0 | FK6: 0 | FL6: 0 | FM6: 0 | FN6: 0 | FO6: 0 | FP6: 0 | FQ6: 0 | FR6: 0 | FS6: 0 | FT6: 0 | FU6: 0 | FV6: 0 | FW6: 0 | FX6: 0 | FY6: 0 | FZ6: 0 | GA6: 0.27921137 | GB6: 0 | GC6: 0 | GD6: 0.27921137 | GE6: 0 | GF6: 0 | GG6: 0 | GH6: 0.28883937 | GI6: 0 | GJ6: 0 | GK6: 0 | GL6: 0 | GM6: 0 | GN6: 0 | GO6: 0 | GP6: 0 | GQ6: 0 | GR6: 0 | GS6: 0 | GT6: 0 | GU6: 0 | GV6: 0 | GW6: 0 | GX6: 0 | GY6: 0 | GZ6: 0.85689008 | HA6: 0.48139894 | HB6: 0 | HC6: 0 | HD6: 0 | HE6: 0 | HF6: 0 | HG6: 0 | HH6: 0 | HI6: 0 | HJ6: 0 | HK6: 0 | HL6: 0 | HM6: 0 | HN6: 0 | HO6: 0 | HP6: 0 | HQ6: 0 | HR6: 0 | HS6: 0 | HT6: 0 | HU6: 0 | HV6: 0 | HW6: 0 | HX6: 0 | HY6: 0 | HZ6: 0 | IA6: 0 | IB6: 0 | IC6: 0 | ID6: 0 | IE6: 0 | IF6: 0 | IG6: 0 | IH6: 0 | II6: 0 | IJ6: 0 | IK6: 0 | IL6: 0 | IM6: 0 | IN6: 0 | IO6: 0 | IP6: 0 | IQ6: 0 | IR6: 0 | IS6: 0 | IT6: 0 | IU6: 0 | IV6: 0 | IW6: 0 | IX6: 0 | IY6: 0 | IZ6: 0 | JA6: 0 | JB6: 0 | JC6: 0 | JD6: 0 | JE6: 0 | JF6: 0 | JG6: 0 | JH6: 0 | JI6: 0 | JJ6: 0 | JK6: 0 | JL6: 0 | JM6: 0 | JN6: 0 | JO6: 0 | JP6: 0 | JQ6: 0 | JR6: 0 | JS6: 0 | JT6: 0 | JU6: 0 | JV6: 0 | JW6: 0 | JX6: 0 | JY6: 0 | JZ6: 0 | KA6: 0 | KB6: 0 | KC6: 0 | KD6: 0 | KE6: 0 | KF6: 0 | KG6: 0 | KH6: 0 | KI6: 0 | KJ6: 0 | KK6: 0 | KL6: 0 | KM6: 0 | KN6: 0 | KO6: 0 | KP6: 0 | KQ6: 0 | KR6: 0 | KS6: 0 | KT6: 0 | KU6: 0 | KV6: 0 | KW6: 0 | KX6: 0 | KY6: 0 | KZ6: 0 | LA6: 0 | LB6: 0 | LC6: 0 | LD6: 0 | LE6: 0 | LF6: 0 | LG6: 0 | LH6: 0 | LI6: 0 | LJ6: 0 | LK6: 0 | LL6: 0 | LM6: 0 | LN6: 0 | LO6: 0 | LP6: 0 | LQ6: 0 | LR6: 0 | LS6: 0 | LT6: 0 | LU6: 0 | LV6: 0 | LW6: 0 | LX6: 0 | LY6: 0 | LZ6: 0 | MA6: 0 | MB6: 0 | MC6: 0 | MD6: 0 | ME6: 0 | MF6: 0 | MG6: 0 | MH6: 0 | MI6: 0 | MJ6: 0 | MK6: 0 | ML6: 0 | MM6: 0 | MN6: 0 | MO6: 0 | MP6: 0 | MQ6: 0 | MR6: 0 | MS6: 0 | MT6: 0 | MU6: 0 | MV6: 0 | MW6: 0 | MX6: 0 | MY6: 0 | MZ6: 0 | NA6: 0 | NB6: 0 | NC6: 0 | ND6: 0 | NE6: 0 | NF6: 0 | NG6: 0 | NH6: 0 | NI6: 0 | NJ6: 0 | NK6: 0.27921137 | NL6: 0 | NM6: 0 | NN6: 0.27921137 | NO6: 0 | NP6: 0 | NQ6: 0 | NR6: 0.28883937 | NS6: 0 | NT6: 0 | NU6: 0 | NV6: 0.85689008 | NW6: 0 | NX6: 0 | NY6: 0 | NZ6: 0 | OA6: 0 | OB6: 0 | OC6: 0 | OD6: 0 | OE6: 0 | OF6: 0 | OG6: 0 | OH6: 0 | OI6: 0.85689008 | OJ6: 0 | OK6: 0.85689008 | OL6: 0 | OM6: 0 | ON6: 0 | OO6: 0 | OP6: 0 | OQ6: 0 | OR6: 0 | OS6: 0 | OT6: 0.85689008 | OU6: 0 | OV6: 0 | OW6: 0 | OX6: 0 | OY6: 0 | OZ6: 0 | PA6: 0.27921137 | PB6: 0 | PC6: 0 | PD6: 0 | PE6: 0 | PF6: 0 | PG6: 0 | PH6: 0 | PI6: 0 | PJ6: 0 | PK6: 0 | PL6: 0 | PM6: 0 | PN6: 0 | PO6: 0 | PP6: 0 | PQ6: 0 | PR6: 0 | PS6: 0.27921137 | PT6: 0 | PU6: 0 | PV6: 0 | PW6: 0 | PX6: 0 | PY6: 0 | PZ6: 0 | QA6: 0 | QB6: 0 | QC6: 0 | QD6: 0 | QE6: 0 | QF6: 0 | QG6: 0 | QH6: 0 | QI6: 0 | QJ6: 0 | QK6: 0 | QL6: 0 | QM6: 0 | QN6: 0 | QO6: 0 | QP6: 0 | QQ6: 0.28883937 | QR6: 0 | QS6: 0 | QT6: 0 | QU6: 0 | QV6: 0 | QW6: 0 | QX6: 0 | QY6: 0 | QZ6: 0 | RA6: 0 | RB6: 0 | RC6: 0 | RD6: 0 | RE6: 0 | RF6: 0 | RG6: 0 | RH6: 0 | RI6: 0 | RJ6: 0 | RK6: 0 | RL6: 0 | RM6: 0 | RN6: 0 | RO6: 0 | RP6: 0 | RQ6: 0 | RR6: 0 | RS6: 0 | RT6: 0 | RU6: 0 | RV6: 0 | RW6: 0 | RX6: 0 | RY6: 0 | RZ6: 0 | SA6: 0.85689008 | SB6: 0 | SC6: 0 | SD6: 0 | SE6: 0 | SF6: 0 | SG6: 0 | SH6: 0 | SI6: 0 | SJ6: 0 | SK6: 0 | SL6: 0 | SM6: 0 | SN6: 0 | SO6: 0 | SP6: 0 | SQ6: 0 | SR6: 0 | SS6: 0 | ST6: 0 | SU6: 0 | SV6: 0 | SW6: 0 | SX6: 0 | SY6: 0 | SZ6: 0 | TA6: 0 | TB6: 0 | TC6: 0 | TD6: 0 | TE6: 0 | TF6: 0 | TG6: 0 | TH6: 0.85689008 | TI6: 0 | TJ6: 0 | TK6: 0 | TL6: 0 | TM6: 0 | TN6: 0 | TO6: 0 | TP6: 0 | TQ6: 0 | TR6: 0 | TS6: 0 | TT6: 0 | TU6: 0 | TV6: 0 | TW6: 0 | TX6: 0 | TY6: 0 | TZ6: 0 | UA6: 0 | UB6: 0 | UC6: 0 | UD6: 0 | UE6: 0 | UF6: 0 | UG6: 0 | UH6: 0 | UI6: 0.85689008 | UJ6: 0 | UK6: 0 | UL6: 0 | UM6: 0 | UN6: 0 | UO6: 0 | UP6: 0 | UQ6: 0 | UR6: 0 | US6: 0 | UT6: 0 | UU6: 0 | UV6: 0 | UW6: 0 | UX6: 0 | UY6: 0 | UZ6: 0 | VA6: 0 | VB6: 0 | VC6: 0 | VD6: 0 | VE6: 0 | VF6: 0 | VG6: 0 | VH6: 0 | VI6: 0 | VJ6: 0 | VK6: 0 | VL6: 0 | VM6: 0 | VN6: 0 | VO6: 0 | VP6: 0 | VQ6: 0 | VR6: 0 | VS6: 0 | VT6: 0 | VU6: 0 | VV6: 0 | VW6: 0 | VX6: 0 | VY6: 0 | VZ6: 0 | WA6: 0 | WB6: 0 | WC6: 0 | WD6: 0 | WE6: 0 | WF6: 0 | WG6: 0 | WH6: 0 | WI6: 0 | WJ6: 0 | WK6: 0 | WL6: 0 | WM6: 0 | WN6: 0 | WO6: 0 | WP6: 0 | WQ6: 0 | WR6: 0 | WS6: 0 | WT6: 0 | WU6: 0 | WV6: 0 | WW6: 0 | WX6: 0 | WY6: 0 | WZ6: 0 | XA6: 0 | XB6: 0 | XC6: 0 | XD6: 0 | XE6: 0 | XF6: 0 | XG6: 0 | XH6: 0 | XI6: 0 | XJ6: 0 | XK6: 0 | XL6: 0 | XM6: 0 | XN6: 0 | XO6: 0 | XP6: 0
A7: cr_2025-747 | B7: Sonae Sierra | C7: Europe | D7: Portugal | E7: Europe | F7: 45712 | G7: 0 | H7: 180 | I7: 0 | J7: 0 | K7: 0 | L7: 0 | M7: 180 | N7: 0 | O7: 0 | P7: 53 | Q7: 127 | R7: 0 | S7: 0 | T7: 0 | U7: 0 | V7: 0 | W7: 0 | X7: 0 | Y7: 0 | Z7: 0 | AA7: 0 | AB7: 0 | AC7: 0 | AD7: 0 | AE7: 53 | AF7: 0 | AG7: 0 | AH7: 0 | AI7: 0 | AJ7: 127 | AK7: 0 | AL7: 0 | AM7: 0 | AN7: 0 | AO7: 0 | AP7: 0 | AQ7: 0 | AR7: 0 | AS7: 0 | AT7: 0 | AU7: 0 | AV7: 0 | AW7: 0 | AX7: 1 | AY7: 0 | AZ7: 0 | BA7: 0 | BB7: 100 | BC7: 0 | BD7: 1 | BE7: 2 | BF7: 180 | BG7: 0 | BH7: 2 | BI7: 0 | BJ7: 0 | BK7: 0 | BL7: 0 | BM7: 2 | BN7: 180 | BO7: 0 | BP7: 0 | BQ7: 1 | BR7: 1 | BS7: 0 | BT7: 0 | BU7: 0 | BV7: 0 | BW7: 0 | BX7: 0 | BY7: 0 | BZ7: 0 | CA7: 0 | CB7: 0 | CC7: 0 | CD7: 0 | CE7: 0 | CF7: 0 | CG7: 0 | CH7: 53 | CI7: 0 | CJ7: 0 | CK7: 0 | CL7: 0 | CM7: 0 | CN7: 127 | CO7: 0 | CP7: 0 | CQ7: 0 | CR7: 0 | CS7: 0 | CT7: 0 | CU7: 0 | CV7: 0 | CW7: 0 | CX7: 0 | CY7: 0 | CZ7: 0 | DA7: 0 | DB7: 0 | DC7: 0 | DD7: 0 | DE7: 0 | DF7: 0 | DG7: 0 | DH7: 0 | DI7: 0 | DJ7: 0 | DK7: 0 | DL7: 0 | DM7: 0 | DN7: 0 | DO7: 0 | DP7: 0 | DQ7: 0 | DR7: 0 | DS7: 0 | DT7: 0 | DU7: 0 | DV7: 0 | DW7: 0 | DX7: 1 | DY7: 0 | DZ7: 0 | EA7: 0 | EB7: 0 | EC7: 0 | ED7: 1 | EE7: 0 | EF7: 0 | EG7: 0 | EH7: 0 | EI7: 0 | EJ7: 0 | EK7: 0 | EL7: 0 | EM7: 0 | EN7: 0 | EO7: 0 | EP7: 0 | EQ7: 0 | ER7: 0 | ES7: 0 | ET7: 0 | EU7: 0 | EV7: 0 | EW7: 0 | EX7: 0 | EY7: 0 | EZ7: 0 | FA7: 0 | FB7: 180 | FC7: 0 | FD7: 0 | FE7: 0 | FF7: 0 | FG7: 0 | FH7: 0 | FI7: 0 | FJ7: 0 | FK7: 0 | FL7: 0 | FM7: 0 | FN7: 0 | FO7: 0 | FP7: 0 | FQ7: 0 | FR7: 0 | FS7: 0 | FT7: 0 | FU7: 0 | FV7: 0 | FW7: 0 | FX7: 0 | FY7: 0 | FZ7: 53 | GA7: 0 | GB7: 0 | GC7: 0 | GD7: 0 | GE7: 0 | GF7: 0 | GG7: 0 | GH7: 127 | GI7: 0 | GJ7: 0 | GK7: 0 | GL7: 0 | GM7: 0 | GN7: 0 | GO7: 0 | GP7: 0 | GQ7: 0 | GR7: 0 | GS7: 0 | GT7: 0 | GU7: 0 | GV7: 0 | GW7: 0 | GX7: 0 | GY7: 0 | GZ7: 180 | HA7: 0 | HB7: 0 | HC7: 0 | HD7: 0 | HE7: 0 | HF7: 0 | HG7: 0 | HH7: 0 | HI7: 0 | HJ7: 0 | HK7: 0 | HL7: 0 | HM7: 0 | HN7: 0 | HO7: 0 | HP7: 0 | HQ7: 0 | HR7: 0 | HS7: 0 | HT7: 0 | HU7: 0 | HV7: 0 | HW7: 0 | HX7: 0 | HY7: 0 | HZ7: 0 | IA7: 0 | IB7: 0 | IC7: 0 | ID7: 0 | IE7: 0 | IF7: 0 | IG7: 0 | IH7: 0 | II7: 0 | IJ7: 0 | IK7: 0 | IL7: 0 | IM7: 0 | IN7: 0 | IO7: 0 | IP7: 0 | IQ7: 0 | IR7: 0 | IS7: 0 | IT7: 0 | IU7: 0 | IV7: 0 | IW7: 0 | IX7: 0 | IY7: 0 | IZ7: 0 | JA7: 0 | JB7: 0 | JC7: 0 | JD7: 0 | JE7: 0 | JF7: 0 | JG7: 0 | JH7: 0 | JI7: 0 | JJ7: 0 | JK7: 0 | JL7: 0 | JM7: 0 | JN7: 0 | JO7: 0 | JP7: 0 | JQ7: 0 | JR7: 0 | JS7: 0 | JT7: 0 | JU7: 0 | JV7: 0 | JW7: 0 | JX7: 0 | JY7: 0 | JZ7: 0 | KA7: 0 | KB7: 0 | KC7: 0 | KD7: 0 | KE7: 0 | KF7: 0 | KG7: 0 | KH7: 0 | KI7: 0 | KJ7: 0 | KK7: 0 | KL7: 0 | KM7: 0 | KN7: 0 | KO7: 0 | KP7: 0 | KQ7: 0 | KR7: 0 | KS7: 0 | KT7: 0 | KU7: 0 | KV7: 0 | KW7: 0 | KX7: 0 | KY7: 0 | KZ7: 0 | LA7: 0 | LB7: 0 | LC7: 0 | LD7: 0 | LE7: 0 | LF7: 0 | LG7: 0 | LH7: 0 | LI7: 0 | LJ7: 0 | LK7: 0 | LL7: 0 | LM7: 0 | LN7: 0 | LO7: 0 | LP7: 0 | LQ7: 0 | LR7: 0 | LS7: 0 | LT7: 0 | LU7: 0 | LV7: 0 | LW7: 0 | LX7: 0 | LY7: 0 | LZ7: 0 | MA7: 0 | MB7: 0 | MC7: 0 | MD7: 0 | ME7: 0 | MF7: 0 | MG7: 0 | MH7: 0 | MI7: 0 | MJ7: 0 | MK7: 0 | ML7: 0 | MM7: 0 | MN7: 0 | MO7: 0 | MP7: 0 | MQ7: 0 | MR7: 0 | MS7: 0 | MT7: 0 | MU7: 0 | MV7: 0 | MW7: 0 | MX7: 0 | MY7: 0 | MZ7: 0 | NA7: 0 | NB7: 0 | NC7: 0 | ND7: 0 | NE7: 0 | NF7: 0 | NG7: 0 | NH7: 0 | NI7: 0 | NJ7: 0 | NK7: 0 | NL7: 0 | NM7: 0 | NN7: 0 | NO7: 0 | NP7: 0 | NQ7: 0 | NR7: 180 | NS7: 0 | NT7: 0 | NU7: 53 | NV7: 127 | NW7: 0 | NX7: 0 | NY7: 0 | NZ7: 0 | OA7: 0 | OB7: 0 | OC7: 0 | OD7: 0 | OE7: 0 | OF7: 53 | OG7: 0 | OH7: 53 | OI7: 127 | OJ7: 0 | OK7: 127 | OL7: 0 | OM7: 0 | ON7: 0 | OO7: 0 | OP7: 0 | OQ7: 0 | OR7: 0 | OS7: 0 | OT7: 180 | OU7: 0 | OV7: 0 | OW7: 0 | OX7: 0 | OY7: 0 | OZ7: 0 | PA7: 0 | PB7: 0 | PC7: 0 | PD7: 0 | PE7: 0 | PF7: 0 | PG7: 0 | PH7: 0 | PI7: 0 | PJ7: 0 | PK7: 0 | PL7: 0 | PM7: 0 | PN7: 0 | PO7: 0 | PP7: 0 | PQ7: 0 | PR7: 0 | PS7: 0 | PT7: 0 | PU7: 0 | PV7: 0 | PW7: 0 | PX7: 0 | PY7: 0 | PZ7: 0 | QA7: 0 | QB7: 0 | QC7: 0 | QD7: 0 | QE7: 0 | QF7: 0 | QG7: 0 | QH7: 0 | QI7: 0 | QJ7: 0 | QK7: 0 | QL7: 0 | QM7: 0 | QN7: 0 | QO7: 0 | QP7: 53 | QQ7: 127 | QR7: 0 | QS7: 0 | QT7: 0 | QU7: 0 | QV7: 0 | QW7: 0 | QX7: 0 | QY7: 0 | QZ7: 0 | RA7: 0 | RB7: 0 | RC7: 0 | RD7: 0 | RE7: 0 | RF7: 0 | RG7: 0 | RH7: 0 | RI7: 0 | RJ7: 0 | RK7: 0 | RL7: 0 | RM7: 0 | RN7: 0 | RO7: 0 | RP7: 0 | RQ7: 0 | RR7: 0 | RS7: 0 | RT7: 0 | RU7: 0 | RV7: 53 | RW7: 0 | RX7: 0 | RY7: 0 | RZ7: 0 | SA7: 0 | SB7: 127 | SC7: 0 | SD7: 0 | SE7: 0 | SF7: 0 | SG7: 0 | SH7: 0 | SI7: 0 | SJ7: 0 | SK7: 0 | SL7: 0 | SM7: 0 | SN7: 0 | SO7: 0 | SP7: 0 | SQ7: 0 | SR7: 0 | SS7: 0 | ST7: 0 | SU7: 0 | SV7: 0 | SW7: 0 | SX7: 0 | SY7: 0 | SZ7: 0 | TA7: 0 | TB7: 0 | TC7: 0 | TD7: 0 | TE7: 0 | TF7: 0 | TG7: 0 | TH7: 0 | TI7: 127 | TJ7: 0 | TK7: 0 | TL7: 0 | TM7: 0 | TN7: 53 | TO7: 0 | TP7: 0 | TQ7: 0 | TR7: 0 | TS7: 0 | TT7: 0 | TU7: 0 | TV7: 0 | TW7: 0 | TX7: 0 | TY7: 0 | TZ7: 0 | UA7: 0 | UB7: 0 | UC7: 0 | UD7: 53 | UE7: 0 | UF7: 0 | UG7: 0 | UH7: 0 | UI7: 127 | UJ7: 0 | UK7: 0 | UL7: 0 | UM7: 0 | UN7: 0 | UO7: 0 | UP7: 0 | UQ7: 0 | UR7: 0 | US7: 0 | UT7: 0 | UU7: 0 | UV7: 0 | UW7: 0 | UX7: 0 | UY7: 0 | UZ7: 127 | VA7: 0 | VB7: 0 | VC7: 0 | VD7: 0 | VE7: 53 | VF7: 0 | VG7: 0 | VH7: 0 | VI7: 0 | VJ7: 0 | VK7: 0 | VL7: 0 | VM7: 0 | VN7: 0 | VO7: 0 | VP7: 0 | VQ7: 0 | VR7: 0 | VS7: 0 | VT7: 0 | VU7: 0 | VV7: 0 | VW7: 0 | VX7: 0 | VY7: 0 | VZ7: 0 | WA7: 0 | WB7: 0 | WC7: 0 | WD7: 0 | WE7: 0 | WF7: 0 | WG7: 0 | WH7: 0 | WI7: 0 | WJ7: 0 | WK7: 0 | WL7: 0 | WM7: 0 | WN7: 0 | WO7: 0 | WP7: 0 | WQ7: 0 | WR7: 0 | WS7: 0 | WT7: 0 | WU7: 0 | WV7: 0 | WW7: 0 | WX7: 0 | WY7: 0 | WZ7: 0 | XA7: 0 | XB7: 0 | XC7: 0 | XD7: 0 | XE7: 0 | XF7: 0 | XG7: 0 | XH7: 0 | XI7: 0 | XJ7: 0 | XK7: 0 | XL7: 0 | XM7: 0 | XN7: 0 | XO7: 0 | XP7: 0
A8: cr_2025-703 | B8: Mirvac Group - Sydney, Nsw | C8: Asia Pacific | D8: Australia | E8: Asia Pacific | F8: 45723 | G8: 0 | H8: 0 | I8: 0 | J8: 0 | K8: 0 | L8: 0 | M8: 0 | N8: 0 | O8: 0 | P8: 0 | Q8: 0 | R8: 0 | S8: 0 | T8: 0 | U8: 0 | V8: 0 | W8: 0 | X8: 0 | Y8: 0 | Z8: 0 | AA8: 0 | AB8: 0 | AC8: 0 | AD8: 0 | AE8: 0 | AF8: 0 | AG8: 0 | AH8: 0 | AI8: 0 | AJ8: 0 | AK8: 0 | AL8: 0 | AM8: 0 | AN8: 0 | AO8: 0 | AP8: 0 | AQ8: 0 | AR8: 0 | AS8: 0 | AT8: 0 | AU8: 0 | AV8: 0 | AW8: 0 | AX8: 2 | AY8: 7 | AZ8: 0 | BA8: 0 | BB8: 0 | BC8: 0 | BD8: 1 | BE8: 3 | BF8: 0 | BG8: 0 | BH8: 0 | BI8: 0 | BJ8: 0 | BK8: 0 | BL8: 0 | BM8: 0 | BN8: 0 | BO8: 0 | BP8: 0 | BQ8: 0 | BR8: 0 | BS8: 0 | BT8: 0 | BU8: 0 | BV8: 0 | BW8: 0 | BX8: 0 | BY8: 0 | BZ8: 0 | CA8: 0 | CB8: 0 | CC8: 0 | CD8: 0 | CE8: 0 | CF8: 0 | CG8: 0 | CH8: 0 | CI8: 0 | CJ8: 0 | CK8: 0 | CL8: 0 | CM8: 0 | CN8: 0 | CO8: 0 | CP8: 0 | CQ8: 0 | CR8: 0 | CS8: 0 | CT8: 0 | CU8: 0 | CV8: 0 | CW8: 0 | CX8: 0 | CY8: 0 | CZ8: 0 | DA8: 0 | DB8: 0 | DC8: 0 | DD8: 0 | DE8: 0 | DF8: 0 | DG8: 0 | DH8: 0 | DI8: 0 | DJ8: 0 | DK8: 0 | DL8: 0 | DM8: 0 | DN8: 0 | DO8: 0 | DP8: 0 | DQ8: 0 | DR8: 0 | DS8: 0 | DT8: 0 | DU8: 0 | DV8: 0 | DW8: 0 | DX8: 0 | DY8: 0 | DZ8: 0 | EA8: 0 | EB8: 0 | EC8: 0 | ED8: 0 | EE8: 0 | EF8: 0 | EG8: 0 | EH8: 0 | EI8: 0 | EJ8: 0 | EK8: 0 | EL8: 0 | EM8: 0 | EN8: 0 | EO8: 0 | EP8: 0 | EQ8: 0 | ER8: 0 | ES8: 0 | ET8: 0 | EU8: 0 | EV8: 0 | EW8: 0 | EX8: 0 | EY8: 0 | EZ8: 0 | FA8: 0 | FB8: 0 | FC8: 0 | FD8: 0 | FE8: 0 | FF8: 0 | FG8: 0 | FH8: 0 | FI8: 0 | FJ8: 0 | FK8: 0 | FL8: 0 | FM8: 0 | FN8: 0 | FO8: 0 | FP8: 0 | FQ8: 0 | FR8: 0 | FS8: 0 | FT8: 0 | FU8: 0 | FV8: 0 | FW8: 0 | FX8: 0 | FY8: 0 | FZ8: 0 | GA8: 0 | GB8: 0 | GC8: 0 | GD8: 0 | GE8: 0 | GF8: 0 | GG8: 0 | GH8: 0 | GI8: 0 | GJ8: 0 | GK8: 0 | GL8: 0 | GM8: 0 | GN8: 0 | GO8: 0 | GP8: 0 | GQ8: 0 | GR8: 0 | GS8: 0 | GT8: 0 | GU8: 0 | GV8: 0 | GW8: 0 | GX8: 0 | GY8: 0 | GZ8: 0 | HA8: 0 | HB8: 0 | HC8: 0 | HD8: 0 | HE8: 0 | HF8: 0 | HG8: 0 | HH8: 0 | HI8: 0 | HJ8: 0 | HK8: 0 | HL8: 0 | HM8: 0 | HN8: 0 | HO8: 0 | HP8: 0 | HQ8: 0 | HR8: 0 | HS8: 0 | HT8: 0 | HU8: 0 | HV8: 0 | HW8: 0 | HX8: 0 | HY8: 0 | HZ8: 0 | IA8: 0 | IB8: 0 | IC8: 0 | ID8: 0 | IE8: 0 | IF8: 0 | IG8: 0 | IH8: 0 | II8: 0 | IJ8: 0 | IK8: 0 | IL8: 0 | IM8: 0 | IN8: 0 | IO8: 0 | IP8: 0 | IQ8: 0 | IR8: 0 | IS8: 0 | IT8: 0 | IU8: 0 | IV8: 0 | IW8: 0 | IX8: 0 | IY8: 0 | IZ8: 0 | JA8: 0 | JB8: 0 | JC8: 0 | JD8: 0 | JE8: 0 | JF8: 0 | JG8: 0 | JH8: 0 | JI8: 0 | JJ8: 0 | JK8: 0 | JL8: 0 | JM8: 0 | JN8: 0 | JO8: 0 | JP8: 0 | JQ8: 0 | JR8: 0 | JS8: 0 | JT8: 0 | JU8: 0 | JV8: 0 | JW8: 0 | JX8: 0 | JY8: 0 | JZ8: 0 | KA8: 0 | KB8: 0 | KC8: 0 | KD8: 0 | KE8: 0 | KF8: 0 | KG8: 0 | KH8: 0 | KI8: 0 | KJ8: 0 | KK8: 0 | KL8: 0 | KM8: 0 | KN8: 0 | KO8: 0 | KP8: 0 | KQ8: 0 | KR8: 0 | KS8: 0 | KT8: 0 | KU8: 0 | KV8: 0 | KW8: 0 | KX8: 0 | KY8: 0 | KZ8: 0 | LA8: 0 | LB8: 0 | LC8: 0 | LD8: 0 | LE8: 0 | LF8: 0 | LG8: 0 | LH8: 0 | LI8: 0 | LJ8: 0 | LK8: 0 | LL8: 0 | LM8: 0 | LN8: 0 | LO8: 0 | LP8: 0 | LQ8: 0 | LR8: 0 | LS8: 0 | LT8: 0 | LU8: 0 | LV8: 0 | LW8: 0 | LX8: 0 | LY8: 0 | LZ8: 0 | MA8: 0 | MB8: 0 | MC8: 0 | MD8: 0 | ME8: 0 | MF8: 0 | MG8: 0 | MH8: 0 | MI8: 0 | MJ8: 0 | MK8: 0 | ML8: 0 | MM8: 0 | MN8: 0 | MO8: 0 | MP8: 0 | MQ8: 0 | MR8: 0 | MS8: 0 | MT8: 0 | MU8: 0 | MV8: 0 | MW8: 0 | MX8: 0 | MY8: 0 | MZ8: 0 | NA8: 0 | NB8: 0 | NC8: 0 | ND8: 0 | NE8: 0 | NF8: 0 | NG8: 0 | NH8: 0 | NI8: 0 | NJ8: 0 | NK8: 0 | NL8: 0 | NM8: 0 | NN8: 0 | NO8: 0 | NP8: 0 | NQ8: 0 | NR8: 0 | NS8: 0 | NT8: 0 | NU8: 0 | NV8: 0 | NW8: 0 | NX8: 0 | NY8: 0 | NZ8: 0 | OA8: 0 | OB8: 0 | OC8: 0 | OD8: 0 | OE8: 0 | OF8: 0 | OG8: 0 | OH8: 0 | OI8: 0 | OJ8: 0 | OK8: 0 | OL8: 0 | OM8: 0 | ON8: 0 | OO8: 0 | OP8: 0 | OQ8: 0 | OR8: 0 | OS8: 0 | OT8: 0 | OU8: 0 | OV8: 0 | OW8: 0 | OX8: 0 | OY8: 0 | OZ8: 0 | PA8: 0 | PB8: 0 | PC8: 0 | PD8: 0 | PE8: 0 | PF8: 0 | PG8: 0 | PH8: 0 | PI8: 0 | PJ8: 0 | PK8: 0 | PL8: 0 | PM8: 0 | PN8: 0 | PO8: 0 | PP8: 0 | PQ8: 0 | PR8: 0 | PS8: 0 | PT8: 0 | PU8: 0 | PV8: 0 | PW8: 0 | PX8: 0 | PY8: 0 | PZ8: 0 | QA8: 0 | QB8: 0 | QC8: 0 | QD8: 0 | QE8: 0 | QF8: 0 | QG8: 0 | QH8: 0 | QI8: 0 | QJ8: 0 | QK8: 0 | QL8: 0 | QM8: 0 | QN8: 0 | QO8: 0 | QP8: 0 | QQ8: 0 | QR8: 0 | QS8: 0 | QT8: 0 | QU8: 0 | QV8: 0 | QW8: 0 | QX8: 0 | QY8: 0 | QZ8: 0 | RA8: 0 | RB8: 0 | RC8: 0 | RD8: 0 | RE8: 0 | RF8: 0 | RG8: 0 | RH8: 0 | RI8: 0 | RJ8: 0 | RK8: 0 | RL8: 0 | RM8: 0 | RN8: 0 | RO8: 0 | RP8: 0 | RQ8: 0 | RR8: 0 | RS8: 0 | RT8: 0 | RU8: 0 | RV8: 0 | RW8: 0 | RX8: 0 | RY8: 0 | RZ8: 0 | SA8: 0 | SB8: 0 | SC8: 0 | SD8: 0 | SE8: 0 | SF8: 0 | SG8: 0 | SH8: 0 | SI8: 0 | SJ8: 0 | SK8: 0 | SL8: 0 | SM8: 0 | SN8: 0 | SO8: 0 | SP8: 0 | SQ8: 0 | SR8: 0 | SS8: 0 | ST8: 0 | SU8: 0 | SV8: 0 | SW8: 0 | SX8: 0 | SY8: 0 | SZ8: 0 | TA8: 0 | TB8: 0 | TC8: 0 | TD8: 0 | TE8: 0 | TF8: 0 | TG8: 0 | TH8: 0 | TI8: 0 | TJ8: 0 | TK8: 0 | TL8: 0 | TM8: 0 | TN8: 0 | TO8: 0 | TP8: 0 | TQ8: 0 | TR8: 0 | TS8: 0 | TT8: 0 | TU8: 0 | TV8: 0 | TW8: 0 | TX8: 0 | TY8: 0 | TZ8: 0 | UA8: 0 | UB8: 0 | UC8: 0 | UD8: 0 | UE8: 0 | UF8: 0 | UG8: 0 | UH8: 0 | UI8: 0 | UJ8: 0 | UK8: 0 | UL8: 0 | UM8: 0 | UN8: 0 | UO8: 0 | UP8: 0 | UQ8: 0 | UR8: 0 | US8: 0 | UT8: 0 | UU8: 0 | UV8: 0 | UW8: 0 | UX8: 0 | UY8: 0 | UZ8: 0 | VA8: 0 | VB8: 0 | VC8: 0 | VD8: 0 | VE8: 0 | VF8: 0 | VG8: 0 | VH8: 0 | VI8: 0 | VJ8: 0 | VK8: 0 | VL8: 0 | VM8: 0 | VN8: 0 | VO8: 0 | VP8: 0 | VQ8: 0 | VR8: 0 | VS8: 0 | VT8: 0 | VU8: 0 | VV8: 0 | VW8: 0 | VX8: 0 | VY8: 0 | VZ8: 0 | WA8: 0 | WB8: 0 | WC8: 0 | WD8: 0 | WE8: 0 | WF8: 0 | WG8: 0 | WH8: 0 | WI8: 0 | WJ8: 0 | WK8: 0 | WL8: 0 | WM8: 0 | WN8: 0 | WO8: 0 | WP8: 0 | WQ8: 0 | WR8: 0 | WS8: 0 | WT8: 0 | WU8: 0 | WV8: 0 | WW8: 0 | WX8: 0 | WY8: 0 | WZ8: 0 | XA8: 0 | XB8: 0 | XC8: 0 | XD8: 0 | XE8: 0 | XF8: 0 | XG8: 0 | XH8: 0 | XI8: 0 | XJ8: 0 | XK8: 0 | XL8: 0 | XM8: 0 | XN8: 0 | XO8: 0 | XP8: 0
A9: cr_2025-658 | B9: Swiss Life Asset Managers | C9: Europe | D9: Switzerland | E9: Europe | F9: 45734 | G9: 0 | H9: 3531 | I9: 0 | J9: 0 | K9: 0 | L9: 0 | M9: 3531 | N9: 2142 | O9: 0 | P9: 57 | Q9: 1332 | R9: 0 | S9: 0 | T9: 0 | U9: 2142 | V9: 0 | W9: 0 | X9: 0 | Y9: 0 | Z9: 0 | AA9: 0 | AB9: 0 | AC9: 0 | AD9: 0 | AE9: 57 | AF9: 0 | AG9: 0 | AH9: 0 | AI9: 0 | AJ9: 1332 | AK9: 0 | AL9: 0 | AM9: 0 | AN9: 0 | AO9: 0 | AP9: 0 | AQ9: 0 | AR9: 0 | AS9: 0 | AT9: 0 | AU9: 0 | AV9: 0 | AW9: 0 | AX9: 1 | AY9: 0 | AZ9: 0 | BA9: 0 | BB9: 0 | BC9: 100 | BD9: 1 | BE9: 3 | BF9: 3531 | BG9: 0 | BH9: 46 | BI9: 0 | BJ9: 0 | BK9: 0 | BL9: 0 | BM9: 46 | BN9: 3531 | BO9: 33 | BP9: 0 | BQ9: 2 | BR9: 11 | BS9: 0 | BT9: 0 | BU9: 0 | BV9: 2142 | BW9: 0 | BX9: 0 | BY9: 0 | BZ9: 0 | CA9: 0 | CB9: 0 | CC9: 0 | CD9: 0 | CE9: 0 | CF9: 0 | CG9: 0 | CH9: 57 | CI9: 0 | CJ9: 0 | CK9: 0 | CL9: 0 | CM9: 0 | CN9: 1332 | CO9: 0 | CP9: 0 | CQ9: 0 | CR9: 0 | CS9: 0 | CT9: 0 | CU9: 0 | CV9: 0 | CW9: 0 | CX9: 0 | CY9: 0 | CZ9: 0 | DA9: 0 | DB9: 0 | DC9: 0 | DD9: 0 | DE9: 0 | DF9: 0 | DG9: 0 | DH9: 0 | DI9: 0 | DJ9: 0 | DK9: 0 | DL9: 33 | DM9: 0 | DN9: 0 | DO9: 0 | DP9: 0 | DQ9: 0 | DR9: 0 | DS9: 0 | DT9: 0 | DU9: 0 | DV9: 0 | DW9: 0 | DX9: 2 | DY9: 0 | DZ9: 0 | EA9: 0 | EB9: 0 | EC9: 0 | ED9: 11 | EE9: 0 | EF9: 0 | EG9: 0 | EH9: 0 | EI9: 0 | EJ9: 0 | EK9: 0 | EL9: 0 | EM9: 0 | EN9: 0 | EO9: 0 | EP9: 0 | EQ9: 0 | ER9: 0 | ES9: 0 | ET9: 0 | EU9: 0 | EV9: 0 | EW9: 0 | EX9: 0 | EY9: 0 | EZ9: 0 | FA9: 0 | FB9: 3531 | FC9: 0 | FD9: 0 | FE9: 0 | FF9: 0 | FG9: 0 | FH9: 0 | FI9: 0 | FJ9: 2142 | FK9: 0 | FL9: 0 | FM9: 0 | FN9: 0 | FO9: 0 | FP9: 0 | FQ9: 0 | FR9: 0 | FS9: 0 | FT9: 0 | FU9: 0 | FV9: 0 | FW9: 0 | FX9: 0 | FY9: 0 | FZ9: 57 | GA9: 0 | GB9: 0 | GC9: 0 | GD9: 0 | GE9: 0 | GF9: 0 | GG9: 0 | GH9: 1332 | GI9: 0 | GJ9: 0 | GK9: 0 | GL9: 0 | GM9: 0 | GN9: 0 | GO9: 0 | GP9: 0 | GQ9: 0 | GR9: 0 | GS9: 0 | GT9: 0 | GU9: 0 | GV9: 0 | GW9: 0 | GX9: 0 | GY9: 0 | GZ9: 3531 | HA9: 0 | HB9: 0 | HC9: 0 | HD9: 0 | HE9: 0 | HF9: 0 | HG9: 0 | HH9: 0 | HI9: 0 | HJ9: 0 | HK9: 0 | HL9: 0 | HM9: 0 | HN9: 0 | HO9: 0 | HP9: 0 | HQ9: 0 | HR9: 0 | HS9: 0 | HT9: 0 | HU9: 0 | HV9: 0 | HW9: 0 | HX9: 0 | HY9: 0 | HZ9: 0 | IA9: 0 | IB9: 0 | IC9: 0 | ID9: 0 | IE9: 0 | IF9: 0 | IG9: 0 | IH9: 0 | II9: 0 | IJ9: 0 | IK9: 0 | IL9: 0 | IM9: 0 | IN9: 0 | IO9: 0 | IP9: 0 | IQ9: 0 | IR9: 0 | IS9: 0 | IT9: 0 | IU9: 0 | IV9: 0 | IW9: 0 | IX9: 0 | IY9: 0 | IZ9: 0 | JA9: 0 | JB9: 0 | JC9: 0 | JD9: 0 | JE9: 0 | JF9: 0 | JG9: 0 | JH9: 0 | JI9: 0 | JJ9: 0 | JK9: 0 | JL9: 0 | JM9: 0 | JN9: 0 | JO9: 0 | JP9: 0 | JQ9: 0 | JR9: 0 | JS9: 0 | JT9: 0 | JU9: 0 | JV9: 0 | JW9: 0 | JX9: 0 | JY9: 0 | JZ9: 0 | KA9: 0 | KB9: 0 | KC9: 0 | KD9: 0 | KE9: 0 | KF9: 0 | KG9: 0 | KH9: 0 | KI9: 0 | KJ9: 0 | KK9: 0 | KL9: 0 | KM9: 0 | KN9: 0 | KO9: 0 | KP9: 0 | KQ9: 0 | KR9: 0 | KS9: 0 | KT9: 0 | KU9: 0 | KV9: 0 | KW9: 0 | KX9: 0 | KY9: 0 | KZ9: 0 | LA9: 0 | LB9: 0 | LC9: 0 | LD9: 0 | LE9: 0 | LF9: 0 | LG9: 0 | LH9: 0 | LI9: 0 | LJ9: 0 | LK9: 0 | LL9: 0 | LM9: 0 | LN9: 0 | LO9: 0 | LP9: 0 | LQ9: 0 | LR9: 0 | LS9: 0 | LT9: 0 | LU9: 0 | LV9: 0 | LW9: 0 | LX9: 0 | LY9: 0 | LZ9: 0 | MA9: 0 | MB9: 0 | MC9: 0 | MD9: 0 | ME9: 0 | MF9: 0 | MG9: 0 | MH9: 0 | MI9: 0 | MJ9: 0 | MK9: 0 | ML9: 0 | MM9: 0 | MN9: 0 | MO9: 0 | MP9: 0 | MQ9: 0 | MR9: 0 | MS9: 0 | MT9: 0 | MU9: 0 | MV9: 0 | MW9: 0 | MX9: 0 | MY9: 0 | MZ9: 0 | NA9: 0 | NB9: 0 | NC9: 0 | ND9: 0 | NE9: 0 | NF9: 0 | NG9: 0 | NH9: 0 | NI9: 0 | NJ9: 0 | NK9: 0 | NL9: 0 | NM9: 0 | NN9: 0 | NO9: 0 | NP9: 0 | NQ9: 0 | NR9: 3531 | NS9: 2142 | NT9: 0 | NU9: 57 | NV9: 1332 | NW9: 0 | NX9: 0 | NY9: 0 | NZ9: 1569 | OA9: 573 | OB9: 2142 | OC9: 0 | OD9: 0 | OE9: 0 | OF9: 28 | OG9: 29 | OH9: 57 | OI9: 506 | OJ9: 826 | OK9: 1332 | OL9: 0 | OM9: 0 | ON9: 0 | OO9: 0 | OP9: 0 | OQ9: 0 | OR9: 0 | OS9: 0 | OT9: 3531 | OU9: 0 | OV9: 0 | OW9: 0 | OX9: 0 | OY9: 0 | OZ9: 0 | PA9: 0 | PB9: 0 | PC9: 0 | PD9: 0 | PE9: 0 | PF9: 0 | PG9: 0 | PH9: 0 | PI9: 0 | PJ9: 0 | PK9: 0 | PL9: 0 | PM9: 0 | PN9: 0 | PO9: 0 | PP9: 0 | PQ9: 0 | PR9: 0 | PS9: 0 | PT9: 0 | PU9: 0 | PV9: 0 | PW9: 0 | PX9: 0 | PY9: 0 | PZ9: 0 | QA9: 0 | QB9: 0 | QC9: 0 | QD9: 0 | QE9: 0 | QF9: 0 | QG9: 0 | QH9: 0 | QI9: 0 | QJ9: 0 | QK9: 0 | QL9: 0 | QM9: 0 | QN9: 2142 | QO9: 0 | QP9: 57 | QQ9: 1332 | QR9: 0 | QS9: 0 | QT9: 635 | QU9: 5 | QV9: 231 | QW9: 6 | QX9: 0 | QY9: 222 | QZ9: 0 | RA9: 0 | RB9: 1043 | RC9: 0 | RD9: 0 | RE9: 0 | RF9: 0 | RG9: 0 | RH9: 0 | RI9: 0 | RJ9: 0 | RK9: 0 | RL9: 0 | RM9: 0 | RN9: 0 | RO9: 0 | RP9: 0 | RQ9: 0 | RR9: 0 | RS9: 0 | RT9: 0 | RU9: 0 | RV9: 0 | RW9: 0 | RX9: 57 | RY9: 0 | RZ9: 0 | SA9: 155 | SB9: 0 | SC9: 23 | SD9: 0 | SE9: 0 | SF9: 0 | SG9: 180 | SH9: 0 | SI9: 974 | SJ9: 0 | SK9: 0 | SL9: 0 | SM9: 0 | SN9: 0 | SO9: 0 | SP9: 0 | SQ9: 0 | SR9: 0 | SS9: 0 | ST9: 0 | SU9: 0 | SV9: 0 | SW9: 0 | SX9: 0 | SY9: 0 | SZ9: 0 | TA9: 0 | TB9: 0 | TC9: 0 | TD9: 0 | TE9: 0 | TF9: 0 | TG9: 0 | TH9: 790 | TI9: 5 | TJ9: 254 | TK9: 6 | TL9: 0 | TM9: 222 | TN9: 180 | TO9: 0 | TP9: 2074 | TQ9: 0 | TR9: 0 | TS9: 0 | TT9: 2142 | TU9: 0 | TV9: 0 | TW9: 0 | TX9: 0 | TY9: 0 | TZ9: 0 | UA9: 0 | UB9: 0 | UC9: 0 | UD9: 57 | UE9: 0 | UF9: 0 | UG9: 0 | UH9: 0 | UI9: 1332 | UJ9: 0 | UK9: 0 | UL9: 0 | UM9: 0 | UN9: 0 | UO9: 0 | UP9: 0 | UQ9: 0 | UR9: 0 | US9: 0 | UT9: 0 | UU9: 0 | UV9: 0 | UW9: 2142 | UX9: 0 | UY9: 57 | UZ9: 1332 | VA9: 0 | VB9: 0 | VC9: 0 | VD9: 0 | VE9: 0 | VF9: 0 | VG9: 0 | VH9: 0 | VI9: 0 | VJ9: 0 | VK9: 0 | VL9: 0 | VM9: 0 | VN9: 0 | VO9: 0 | VP9: 0 | VQ9: 0 | VR9: 0 | VS9: 0 | VT9: 0 | VU9: 0 | VV9: 0 | VW9: 0 | VX9: 0 | VY9: 0 | VZ9: 0 | WA9: 0 | WB9: 0 | WC9: 0 | WD9: 0 | WE9: 0 | WF9: 0 | WG9: 0 | WH9: 0 | WI9: 0 | WJ9: 0 | WK9: 0 | WL9: 0 | WM9: 0 | WN9: 0 | WO9: 0 | WP9: 0 | WQ9: 0 | WR9: 0 | WS9: 0 | WT9: 0 | WU9: 0 | WV9: 0 | WW9: 0 | WX9: 0 | WY9: 0 | WZ9: 0 | XA9: 0 | XB9: 0 | XC9: 0 | XD9: 0 | XE9: 0 | XF9: 0 | XG9: 0 | XH9: 0 | XI9: 0 | XJ9: 0 | XK9: 0 | XL9: 0 | XM9: 0 | XN9: 0 | XO9: 0 | XP9: 0
A10: cr_2025-757 | B10: Altera | C10: Europe | D10: Netherlands | E10: Europe | F10: 45713 | G10: 0 | H10: 160 | I10: 0 | J10: 0 | K10: 0 | L10: 0 | M10: 160 | N10: 160 | O10: 0 | P10: 0 | Q10: 0 | R10: 0 | S10: 0 | T10: 0 | U10: 160 | V10: 0 | W10: 0 | X10: 0 | Y10: 0 | Z10: 0 | AA10: 0 | AB10: 0 | AC10: 0 | AD10: 0 | AE10: 0 | AF10: 0 | AG10: 0 | AH10: 0 | AI10: 0 | AJ10: 0 | AK10: 0 | AL10: 0 | AM10: 0 | AN10: 0 | AO10: 0 | AP10: 0 | AQ10: 0 | AR10: 0 | AS10: 0 | AT10: 0 | AU10: 0 | AV10: 0 | AW10: 0 | AX10: 1 | AY10: 0 | AZ10: 0 | BA10: 0 | BB10: 100 | BC10: 0 | BD10: 1 | BE10: 1 | BF10: 23.200001 | BG10: 0 | BH10: 2 | BI10: 0 | BJ10: 0 | BK10: 0 | BL10: 0 | BM10: 2 | BN10: 160 | BO10: 2 | BP10: 0 | BQ10: 0 | BR10: 0 | BS10: 0 | BT10: 0 | BU10: 0 | BV10: 160 | BW10: 0 | BX10: 0 | BY10: 0 | BZ10: 0 | CA10: 0 | CB10: 0 | CC10: 0 | CD10: 0 | CE10: 0 | CF10: 0 | CG10: 0 | CH10: 0 | CI10: 0 | CJ10: 0 | CK10: 0 | CL10: 0 | CM10: 0 | CN10: 0 | CO10: 0 | CP10: 0 | CQ10: 0 | CR10: 0 | CS10: 0 | CT10: 0 | CU10: 0 | CV10: 0 | CW10: 0 | CX10: 0 | CY10: 0 | CZ10: 0 | DA10: 0 | DB10: 0 | DC10: 0 | DD10: 0 | DE10: 0 | DF10: 0 | DG10: 0 | DH10: 0 | DI10: 0 | DJ10: 0 | DK10: 0 | DL10: 2 | DM10: 0 | DN10: 0 | DO10: 0 | DP10: 0 | DQ10: 0 | DR10: 0 | DS10: 0 | DT10: 0 | DU10: 0 | DV10: 0 | DW10: 0 | DX10: 0 | DY10: 0 | DZ10: 0 | EA10: 0 | EB10: 0 | EC10: 0 | ED10: 0 | EE10: 0 | EF10: 0 | EG10: 0 | EH10: 0 | EI10: 0 | EJ10: 0 | EK10: 0 | EL10: 0 | EM10: 0 | EN10: 0 | EO10: 0 | EP10: 0 | EQ10: 0 | ER10: 0 | ES10: 0 | ET10: 0 | EU10: 133 | EV10: 27 | EW10: 0 | EX10: 0 | EY10: 0 | EZ10: 0 | FA10: 0 | FB10: 0 | FC10: 133 | FD10: 27 | FE10: 0 | FF10: 0 | FG10: 0 | FH10: 0 | FI10: 0 | FJ10: 0 | FK10: 0 | FL10: 0 | FM10: 0 | FN10: 0 | FO10: 0 | FP10: 0 | FQ10: 0 | FR10: 0 | FS10: 0 | FT10: 0 | FU10: 0 | FV10: 0 | FW10: 0 | FX10: 0 | FY10: 0 | FZ10: 0 | GA10: 0 | GB10: 0 | GC10: 0 | GD10: 0 | GE10: 0 | GF10: 0 | GG10: 0 | GH10: 0 | GI10: 0 | GJ10: 0 | GK10: 0 | GL10: 0 | GM10: 0 | GN10: 0 | GO10: 0 | GP10: 0 | GQ10: 0 | GR10: 0 | GS10: 0 | GT10: 0 | GU10: 0 | GV10: 0 | GW10: 0 | GX10: 0 | GY10: 0 | GZ10: 160 | HA10: 0 | HB10: 0 | HC10: 0 | HD10: 0 | HE10: 0 | HF10: 0 | HG10: 0 | HH10: 0 | HI10: 0 | HJ10: 0 | HK10: 0 | HL10: 0 | HM10: 0 | HN10: 0 | HO10: 0 | HP10: 0 | HQ10: 0 | HR10: 0 | HS10: 0 | HT10: 0 | HU10: 0 | HV10: 0 | HW10: 0 | HX10: 0 | HY10: 0 | HZ10: 0 | IA10: 0 | IB10: 0 | IC10: 0 | ID10: 0 | IE10: 0 | IF10: 0 | IG10: 0 | IH10: 0 | II10: 0 | IJ10: 0 | IK10: 0 | IL10: 0 | IM10: 0 | IN10: 0 | IO10: 0 | IP10: 0 | IQ10: 0 | IR10: 0 | IS10: 0 | IT10: 0 | IU10: 0 | IV10: 0 | IW10: 0 | IX10: 0 | IY10: 0 | IZ10: 0 | JA10: 0 | JB10: 0 | JC10: 0 | JD10: 0 | JE10: 0 | JF10: 0 | JG10: 0 | JH10: 0 | JI10: 0 | JJ10: 0 | JK10: 0 | JL10: 0 | JM10: 0 | JN10: 0 | JO10: 0 | JP10: 0 | JQ10: 0 | JR10: 0 | JS10: 0 | JT10: 0 | JU10: 0 | JV10: 0 | JW10: 0 | JX10: 0 | JY10: 0 | JZ10: 0 | KA10: 0 | KB10: 0 | KC10: 0 | KD10: 0 | KE10: 0 | KF10: 0 | KG10: 0 | KH10: 0 | KI10: 0 | KJ10: 0 | KK10: 0 | KL10: 0 | KM10: 0 | KN10: 0 | KO10: 0 | KP10: 0 | KQ10: 0 | KR10: 0 | KS10: 0 | KT10: 0 | KU10: 0 | KV10: 0 | KW10: 0 | KX10: 0 | KY10: 0 | KZ10: 0 | LA10: 0 | LB10: 0 | LC10: 0 | LD10: 0 | LE10: 0 | LF10: 0 | LG10: 0 | LH10: 0 | LI10: 0 | LJ10: 0 | LK10: 0 | LL10: 0 | LM10: 0 | LN10: 0 | LO10: 0 | LP10: 0 | LQ10: 0 | LR10: 0 | LS10: 0 | LT10: 0 | LU10: 0 | LV10: 0 | LW10: 0 | LX10: 0 | LY10: 0 | LZ10: 0 | MA10: 0 | MB10: 0 | MC10: 0 | MD10: 0 | ME10: 0 | MF10: 0 | MG10: 0 | MH10: 0 | MI10: 0 | MJ10: 0 | MK10: 0 | ML10: 0 | MM10: 0 | MN10: 0 | MO10: 0 | MP10: 0 | MQ10: 0 | MR10: 0 | MS10: 0 | MT10: 0 | MU10: 0 | MV10: 0 | MW10: 0 | MX10: 0 | MY10: 0 | MZ10: 0 | NA10: 0 | NB10: 0 | NC10: 0 | ND10: 0 | NE10: 0 | NF10: 0 | NG10: 0 | NH10: 0 | NI10: 0 | NJ10: 0 | NK10: 133 | NL10: 27 | NM10: 0 | NN10: 0 | NO10: 0 | NP10: 0 | NQ10: 0 | NR10: 0 | NS10: 160 | NT10: 0 | NU10: 0 | NV10: 0 | NW10: 0 | NX10: 0 | NY10: 0 | NZ10: 160 | OA10: 0 | OB10: 160 | OC10: 0 | OD10: 0 | OE10: 0 | OF10: 0 | OG10: 0 | OH10: 0 | OI10: 0 | OJ10: 0 | OK10: 0 | OL10: 0 | OM10: 0 | ON10: 0 | OO10: 0 | OP10: 0 | OQ10: 0 | OR10: 0 | OS10: 0 | OT10: 160 | OU10: 0 | OV10: 0 | OW10: 0 | OX10: 133 | OY10: 0 | OZ10: 0 | PA10: 0 | PB10: 0 | PC10: 0 | PD10: 27 | PE10: 0 | PF10: 0 | PG10: 0 | PH10: 0 | PI10: 0 | PJ10: 0 | PK10: 0 | PL10: 0 | PM10: 0 | PN10: 0 | PO10: 0 | PP10: 0 | PQ10: 0 | PR10: 0 | PS10: 0 | PT10: 0 | PU10: 0 | PV10: 0 | PW10: 0 | PX10: 0 | PY10: 0 | PZ10: 0 | QA10: 0 | QB10: 0 | QC10: 0 | QD10: 0 | QE10: 0 | QF10: 0 | QG10: 0 | QH10: 0 | QI10: 0 | QJ10: 0 | QK10: 0 | QL10: 0 | QM10: 0 | QN10: 0 | QO10: 0 | QP10: 0 | QQ10: 0 | QR10: 0 | QS10: 0 | QT10: 0 | QU10: 27 | QV10: 0 | QW10: 133 | QX10: 0 | QY10: 0 | QZ10: 0 | RA10: 0 | RB10: 0 | RC10: 0 | RD10: 0 | RE10: 0 | RF10: 0 | RG10: 0 | RH10: 0 | RI10: 0 | RJ10: 0 | RK10: 0 | RL10: 0 | RM10: 0 | RN10: 0 | RO10: 0 | RP10: 0 | RQ10: 0 | RR10: 0 | RS10: 0 | RT10: 0 | RU10: 0 | RV10: 0 | RW10: 0 | RX10: 0 | RY10: 0 | RZ10: 0 | SA10: 0 | SB10: 0 | SC10: 0 | SD10: 0 | SE10: 0 | SF10: 0 | SG10: 0 | SH10: 0 | SI10: 0 | SJ10: 0 | SK10: 0 | SL10: 0 | SM10: 0 | SN10: 0 | SO10: 0 | SP10: 0 | SQ10: 0 | SR10: 0 | SS10: 0 | ST10: 0 | SU10: 0 | SV10: 0 | SW10: 0 | SX10: 0 | SY10: 0 | SZ10: 0 | TA10: 0 | TB10: 0 | TC10: 0 | TD10: 0 | TE10: 0 | TF10: 0 | TG10: 0 | TH10: 0 | TI10: 27 | TJ10: 0 | TK10: 133 | TL10: 0 | TM10: 0 | TN10: 0 | TO10: 0 | TP10: 0 | TQ10: 0 | TR10: 0 | TS10: 0 | TT10: 160 | TU10: 0 | TV10: 0 | TW10: 0 | TX10: 0 | TY10: 0 | TZ10: 0 | UA10: 0 | UB10: 0 | UC10: 0 | UD10: 0 | UE10: 0 | UF10: 0 | UG10: 0 | UH10: 0 | UI10: 0 | UJ10: 0 | UK10: 0 | UL10: 0 | UM10: 0 | UN10: 0 | UO10: 0 | UP10: 0 | UQ10: 0 | UR10: 0 | US10: 0 | UT10: 0 | UU10: 0 | UV10: 0 | UW10: 160 | UX10: 0 | UY10: 0 | UZ10: 0 | VA10: 0 | VB10: 0 | VC10: 0 | VD10: 0 | VE10: 0 | VF10: 0 | VG10: 0 | VH10: 0 | VI10: 0 | VJ10: 0 | VK10: 0 | VL10: 0 | VM10: 0 | VN10: 0 | VO10: 0 | VP10: 0 | VQ10: 0 | VR10: 0 | VS10: 0 | VT10: 0 | VU10: 0 | VV10: 0 | VW10: 0 | VX10: 0 | VY10: 0 | VZ10: 0 | WA10: 0 | WB10: 0 | WC10: 0 | WD10: 0 | WE10: 0 | WF10: 0 | WG10: 0 | WH10: 0 | WI10: 0 | WJ10: 0 | WK10: 0 | WL10: 0 | WM10: 0 | WN10: 0 | WO10: 0 | WP10: 0 | WQ10: 0 | WR10: 0 | WS10: 0 | WT10: 0 | WU10: 0 | WV10: 0 | WW10: 0 | WX10: 0 | WY10: 0 | WZ10: 0 | XA10: 0 | XB10: 0 | XC10: 0 | XD10: 0 | XE10: 0 | XF10: 0 | XG10: 0 | XH10: 0 | XI10: 0 | XJ10: 0 | XK10: 0 | XL10: 0 | XM10: 0 | XN10: 0 | XO10: 0 | XP10: 0
A11: cr_2025-730 | B11: Pinebridge Benson Elliot | C11: Europe | D11: United Kingdom | E11: Europe | F11: 45705 | G11: 0 | H11: 5 | I11: 0 | J11: 0 | K11: 0 | L11: 0 | M11: 5 | N11: 5 | O11: 0 | P11: 0 | Q11: 0 | R11: 0 | S11: 0 | T11: 0 | U11: 0 | V11: 5 | W11: 0 | X11: 0 | Y11: 0 | Z11: 0 | AA11: 0 | AB11: 0 | AC11: 0 | AD11: 0 | AE11: 0 | AF11: 0 | AG11: 0 | AH11: 0 | AI11: 0 | AJ11: 0 | AK11: 0 | AL11: 0 | AM11: 0 | AN11: 0 | AO11: 0 | AP11: 0 | AQ11: 0 | AR11: 0 | AS11: 0 | AT11: 0 | AU11: 0 | AV11: 0 | AW11: 0 | AX11: 1 | AY11: 0 | AZ11: 0 | BA11: 0 | BB11: 100 | BC11: 0 | BD11: 1 | BE11: 3 | BF11: 0 | BG11: 0 | BH11: 1 | BI11: 0 | BJ11: 0 | BK11: 0 | BL11: 0 | BM11: 1 | BN11: 5 | BO11: 1 | BP11: 0 | BQ11: 0 | BR11: 0 | BS11: 0 | BT11: 0 | BU11: 0 | BV11: 5 | BW11: 0 | BX11: 0 | BY11: 0 | BZ11: 0 | CA11: 0 | CB11: 0 | CC11: 0 | CD11: 0 | CE11: 0 | CF11: 0 | CG11: 0 | CH11: 0 | CI11: 0 | CJ11: 0 | CK11: 0 | CL11: 0 | CM11: 0 | CN11: 0 | CO11: 0 | CP11: 0 | CQ11: 0 | CR11: 0 | CS11: 0 | CT11: 0 | CU11: 0 | CV11: 0 | CW11: 0 | CX11: 0 | CY11: 0 | CZ11: 0 | DA11: 0 | DB11: 0 | DC11: 0 | DD11: 0 | DE11: 0 | DF11: 0 | DG11: 0 | DH11: 0 | DI11: 0 | DJ11: 0 | DK11: 0 | DL11: 1 | DM11: 0 | DN11: 0 | DO11: 0 | DP11: 0 | DQ11: 0 | DR11: 0 | DS11: 0 | DT11: 0 | DU11: 0 | DV11: 0 | DW11: 0 | DX11: 0 | DY11: 0 | DZ11: 0 | EA11: 0 | EB11: 0 | EC11: 0 | ED11: 0 | EE11: 0 | EF11: 0 | EG11: 0 | EH11: 0 | EI11: 0 | EJ11: 0 | EK11: 0 | EL11: 0 | EM11: 0 | EN11: 0 | EO11: 0 | EP11: 0 | EQ11: 0 | ER11: 0 | ES11: 0 | ET11: 0 | EU11: 0 | EV11: 5 | EW11: 0 | EX11: 0 | EY11: 0 | EZ11: 0 | FA11: 0 | FB11: 0 | FC11: 0 | FD11: 5 | FE11: 0 | FF11: 0 | FG11: 0 | FH11: 0 | FI11: 0 | FJ11: 0 | FK11: 0 | FL11: 0 | FM11: 0 | FN11: 0 | FO11: 0 | FP11: 0 | FQ11: 0 | FR11: 0 | FS11: 0 | FT11: 0 | FU11: 0 | FV11: 0 | FW11: 0 | FX11: 0 | FY11: 0 | FZ11: 0 | GA11: 0 | GB11: 0 | GC11: 0 | GD11: 0 | GE11: 0 | GF11: 0 | GG11: 0 | GH11: 0 | GI11: 0 | GJ11: 0 | GK11: 0 | GL11: 0 | GM11: 0 | GN11: 0 | GO11: 0 | GP11: 0 | GQ11: 0 | GR11: 0 | GS11: 0 | GT11: 0 | GU11: 0 | GV11: 0 | GW11: 0 | GX11: 0 | GY11: 0 | GZ11: 0 | HA11: 5 | HB11: 0 | HC11: 0 | HD11: 0 | HE11: 0 | HF11: 0 | HG11: 0 | HH11: 0 | HI11: 0 | HJ11: 0 | HK11: 0 | HL11: 0 | HM11: 0 | HN11: 0 | HO11: 0 | HP11: 0 | HQ11: 0 | HR11: 0 | HS11: 0 | HT11: 0 | HU11: 0 | HV11: 0 | HW11: 0 | HX11: 0 | HY11: 0 | HZ11: 0 | IA11: 0 | IB11: 0 | IC11: 0 | ID11: 0 | IE11: 0 | IF11: 0 | IG11: 0 | IH11: 0 | II11: 0 | IJ11: 0 | IK11: 0 | IL11: 0 | IM11: 0 | IN11: 0 | IO11: 0 | IP11: 0 | IQ11: 0 | IR11: 0 | IS11: 0 | IT11: 0 | IU11: 0 | IV11: 0 | IW11: 0 | IX11: 0 | IY11: 0 | IZ11: 0 | JA11: 0 | JB11: 0 | JC11: 0 | JD11: 0 | JE11: 0 | JF11: 0 | JG11: 0 | JH11: 0 | JI11: 0 | JJ11: 0 | JK11: 0 | JL11: 0 | JM11: 0 | JN11: 0 | JO11: 0 | JP11: 0 | JQ11: 0 | JR11: 0 | JS11: 0 | JT11: 0 | JU11: 0 | JV11: 0 | JW11: 0 | JX11: 0 | JY11: 0 | JZ11: 0 | KA11: 0 | KB11: 0 | KC11: 0 | KD11: 0 | KE11: 0 | KF11: 0 | KG11: 0 | KH11: 0 | KI11: 0 | KJ11: 0 | KK11: 0 | KL11: 0 | KM11: 0 | KN11: 0 | KO11: 0 | KP11: 0 | KQ11: 0 | KR11: 0 | KS11: 0 | KT11: 0 | KU11: 0 | KV11: 0 | KW11: 0 | KX11: 0 | KY11: 0 | KZ11: 0 | LA11: 0 | LB11: 0 | LC11: 0 | LD11: 0 | LE11: 0 | LF11: 0 | LG11: 0 | LH11: 0 | LI11: 0 | LJ11: 0 | LK11: 0 | LL11: 0 | LM11: 0 | LN11: 0 | LO11: 0 | LP11: 0 | LQ11: 0 | LR11: 0 | LS11: 0 | LT11: 0 | LU11: 0 | LV11: 0 | LW11: 0 | LX11: 0 | LY11: 0 | LZ11: 0 | MA11: 0 | MB11: 0 | MC11: 0 | MD11: 0 | ME11: 0 | MF11: 0 | MG11: 0 | MH11: 0 | MI11: 0 | MJ11: 0 | MK11: 0 | ML11: 0 | MM11: 0 | MN11: 0 | MO11: 0 | MP11: 0 | MQ11: 0 | MR11: 0 | MS11: 0 | MT11: 0 | MU11: 0 | MV11: 0 | MW11: 0 | MX11: 0 | MY11: 0 | MZ11: 0 | NA11: 0 | NB11: 0 | NC11: 0 | ND11: 0 | NE11: 0 | NF11: 0 | NG11: 0 | NH11: 0 | NI11: 0 | NJ11: 0 | NK11: 0 | NL11: 5 | NM11: 0 | NN11: 0 | NO11: 0 | NP11: 0 | NQ11: 0 | NR11: 0 | NS11: 5 | NT11: 0 | NU11: 0 | NV11: 0 | NW11: 0 | NX11: 0 | NY11: 0 | NZ11: 0 | OA11: 5 | OB11: 5 | OC11: 0 | OD11: 0 | OE11: 0 | OF11: 0 | OG11: 0 | OH11: 0 | OI11: 0 | OJ11: 0 | OK11: 0 | OL11: 0 | OM11: 0 | ON11: 0 | OO11: 0 | OP11: 0 | OQ11: 0 | OR11: 0 | OS11: 0 | OT11: 0 | OU11: 5 | OV11: 0 | OW11: 0 | OX11: 0 | OY11: 0 | OZ11: 0 | PA11: 0 | PB11: 0 | PC11: 0 | PD11: 5 | PE11: 0 | PF11: 0 | PG11: 0 | PH11: 0 | PI11: 0 | PJ11: 0 | PK11: 0 | PL11: 0 | PM11: 0 | PN11: 0 | PO11: 0 | PP11: 0 | PQ11: 0 | PR11: 0 | PS11: 0 | PT11: 0 | PU11: 0 | PV11: 0 | PW11: 0 | PX11: 0 | PY11: 0 | PZ11: 0 | QA11: 0 | QB11: 0 | QC11: 0 | QD11: 0 | QE11: 0 | QF11: 0 | QG11: 0 | QH11: 0 | QI11: 0 | QJ11: 0 | QK11: 0 | QL11: 0 | QM11: 0 | QN11: 0 | QO11: 0 | QP11: 0 | QQ11: 0 | QR11: 0 | QS11: 0 | QT11: 0 | QU11: 0 | QV11: 0 | QW11: 0 | QX11: 0 | QY11: 0 | QZ11: 0 | RA11: 0 | RB11: 0 | RC11: 0 | RD11: 5 | RE11: 0 | RF11: 0 | RG11: 0 | RH11: 0 | RI11: 0 | RJ11: 0 | RK11: 0 | RL11: 0 | RM11: 0 | RN11: 0 | RO11: 0 | RP11: 0 | RQ11: 0 | RR11: 0 | RS11: 0 | RT11: 0 | RU11: 0 | RV11: 0 | RW11: 0 | RX11: 0 | RY11: 0 | RZ11: 0 | SA11: 0 | SB11: 0 | SC11: 0 | SD11: 0 | SE11: 0 | SF11: 0 | SG11: 0 | SH11: 0 | SI11: 0 | SJ11: 0 | SK11: 0 | SL11: 0 | SM11: 0 | SN11: 0 | SO11: 0 | SP11: 0 | SQ11: 0 | SR11: 0 | SS11: 0 | ST11: 0 | SU11: 0 | SV11: 0 | SW11: 0 | SX11: 0 | SY11: 0 | SZ11: 0 | TA11: 0 | TB11: 0 | TC11: 0 | TD11: 0 | TE11: 0 | TF11: 0 | TG11: 0 | TH11: 0 | TI11: 0 | TJ11: 0 | TK11: 0 | TL11: 0 | TM11: 0 | TN11: 0 | TO11: 0 | TP11: 0 | TQ11: 0 | TR11: 5 | TS11: 0 | TT11: 0 | TU11: 5 | TV11: 0 | TW11: 0 | TX11: 0 | TY11: 0 | TZ11: 0 | UA11: 0 | UB11: 0 | UC11: 0 | UD11: 0 | UE11: 0 | UF11: 0 | UG11: 0 | UH11: 0 | UI11: 0 | UJ11: 0 | UK11: 0 | UL11: 0 | UM11: 0 | UN11: 0 | UO11: 0 | UP11: 0 | UQ11: 0 | UR11: 0 | US11: 0 | UT11: 0 | UU11: 0 | UV11: 0 | UW11: 0 | UX11: 0 | UY11: 0 | UZ11: 0 | VA11: 0 | VB11: 0 | VC11: 5 | VD11: 0 | VE11: 0 | VF11: 0 | VG11: 0 | VH11: 0 | VI11: 0 | VJ11: 0 | VK11: 0 | VL11: 0 | VM11: 0 | VN11: 0 | VO11: 0 | VP11: 0 | VQ11: 0 | VR11: 0 | VS11: 0 | VT11: 0 | VU11: 0 | VV11: 0 | VW11: 0 | VX11: 0 | VY11: 0 | VZ11: 0 | WA11: 0 | WB11: 0 | WC11: 0 | WD11: 0 | WE11: 0 | WF11: 0 | WG11: 0 | WH11: 0 | WI11: 0 | WJ11: 0 | WK11: 0 | WL11: 0 | WM11: 0 | WN11: 0 | WO11: 0 | WP11: 0 | WQ11: 0 | WR11: 0 | WS11: 0 | WT11: 0 | WU11: 0 | WV11: 0 | WW11: 0 | WX11: 0 | WY11: 0 | WZ11: 0 | XA11: 0 | XB11: 0 | XC11: 0 | XD11: 0 | XE11: 0 | XF11: 0 | XG11: 0 | XH11: 0 | XI11: 0 | XJ11: 0 | XK11: 0 | XL11: 0 | XM11: 0 | XN11: 0 | XO11: 0 | XP11: 0
A12: cr_2025-651 | B12: Europa Capital | C12: Europe | D12: United Kingdom | E12: Europe | F12: 45698 | G12: 0 | H12: 0 | I12: 0 | J12: 0 | K12: 0 | L12: 0 | M12: 0 | N12: 0 | O12: 0 | P12: 0 | Q12: 0 | R12: 0 | S12: 0 | T12: 0 | U12: 0 | V12: 0 | W12: 0 | X12: 0 | Y12: 0 | Z12: 0 | AA12: 0 | AB12: 0 | AC12: 0 | AD12: 0 | AE12: 0 | AF12: 0 | AG12: 0 | AH12: 0 | AI12: 0 | AJ12: 0 | AK12: 0 | AL12: 0 | AM12: 0 | AN12: 0 | AO12: 0 | AP12: 0 | AQ12: 0 | AR12: 0 | AS12: 0 | AT12: 0 | AU12: 0 | AV12: 0 | AW12: 0 | AX12: 2 | AY12: 6 | AZ12: 0 | BA12: 0 | BB12: 0 | BC12: 0 | BD12: 1 | BE12: 2 | BF12: 0 | BG12: 0 | BH12: 0 | BI12: 0 | BJ12: 0 | BK12: 0 | BL12: 0 | BM12: 0 | BN12: 0 | BO12: 0 | BP12: 0 | BQ12: 0 | BR12: 0 | BS12: 0 | BT12: 0 | BU12: 0 | BV12: 0 | BW12: 0 | BX12: 0 | BY12: 0 | BZ12: 0 | CA12: 0 | CB12: 0 | CC12: 0 | CD12: 0 | CE12: 0 | CF12: 0 | CG12: 0 | CH12: 0 | CI12: 0 | CJ12: 0 | CK12: 0 | CL12: 0 | CM12: 0 | CN12: 0 | CO12: 0 | CP12: 0 | CQ12: 0 | CR12: 0 | CS12: 0 | CT12: 0 | CU12: 0 | CV12: 0 | CW12: 0 | CX12: 0 | CY12: 0 | CZ12: 0 | DA12: 0 | DB12: 0 | DC12: 0 | DD12: 0 | DE12: 0 | DF12: 0 | DG12: 0 | DH12: 0 | DI12: 0 | DJ12: 0 | DK12: 0 | DL12: 0 | DM12: 0 | DN12: 0 | DO12: 0 | DP12: 0 | DQ12: 0 | DR12: 0 | DS12: 0 | DT12: 0 | DU12: 0 | DV12: 0 | DW12: 0 | DX12: 0 | DY12: 0 | DZ12: 0 | EA12: 0 | EB12: 0 | EC12: 0 | ED12: 0 | EE12: 0 | EF12: 0 | EG12: 0 | EH12: 0 | EI12: 0 | EJ12: 0 | EK12: 0 | EL12: 0 | EM12: 0 | EN12: 0 | EO12: 0 | EP12: 0 | EQ12: 0 | ER12: 0 | ES12: 0 | ET12: 0 | EU12: 0 | EV12: 0 | EW12: 0 | EX12: 0 | EY12: 0 | EZ12: 0 | FA12: 0 | FB12: 0 | FC12: 0 | FD12: 0 | FE12: 0 | FF12: 0 | FG12: 0 | FH12: 0 | FI12: 0 | FJ12: 0 | FK12: 0 | FL12: 0 | FM12: 0 | FN12: 0 | FO12: 0 | FP12: 0 | FQ12: 0 | FR12: 0 | FS12: 0 | FT12: 0 | FU12: 0 | FV12: 0 | FW12: 0 | FX12: 0 | FY12: 0 | FZ12: 0 | GA12: 0 | GB12: 0 | GC12: 0 | GD12: 0 | GE12: 0 | GF12: 0 | GG12: 0 | GH12: 0 | GI12: 0 | GJ12: 0 | GK12: 0 | GL12: 0 | GM12: 0 | GN12: 0 | GO12: 0 | GP12: 0 | GQ12: 0 | GR12: 0 | GS12: 0 | GT12: 0 | GU12: 0 | GV12: 0 | GW12: 0 | GX12: 0 | GY12: 0 | GZ12: 0 | HA12: 0 | HB12: 0 | HC12: 0 | HD12: 0 | HE12: 0 | HF12: 0 | HG12: 0 | HH12: 0 | HI12: 0 | HJ12: 0 | HK12: 0 | HL12: 0 | HM12: 0 | HN12: 0 | HO12: 0 | HP12: 0 | HQ12: 0 | HR12: 0 | HS12: 0 | HT12: 0 | HU12: 0 | HV12: 0 | HW12: 0 | HX12: 0 | HY12: 0 | HZ12: 0 | IA12: 0 | IB12: 0 | IC12: 0 | ID12: 0 | IE12: 0 | IF12: 0 | IG12: 0 | IH12: 0 | II12: 0 | IJ12: 0 | IK12: 0 | IL12: 0 | IM12: 0 | IN12: 0 | IO12: 0 | IP12: 0 | IQ12: 0 | IR12: 0 | IS12: 0 | IT12: 0 | IU12: 0 | IV12: 0 | IW12: 0 | IX12: 0 | IY12: 0 | IZ12: 0 | JA12: 0 | JB12: 0 | JC12: 0 | JD12: 0 | JE12: 0 | JF12: 0 | JG12: 0 | JH12: 0 | JI12: 0 | JJ12: 0 | JK12: 0 | JL12: 0 | JM12: 0 | JN12: 0 | JO12: 0 | JP12: 0 | JQ12: 0 | JR12: 0 | JS12: 0 | JT12: 0 | JU12: 0 | JV12: 0 | JW12: 0 | JX12: 0 | JY12: 0 | JZ12: 0 | KA12: 0 | KB12: 0 | KC12: 0 | KD12: 0 | KE12: 0 | KF12: 0 | KG12: 0 | KH12: 0 | KI12: 0 | KJ12: 0 | KK12: 0 | KL12: 0 | KM12: 0 | KN12: 0 | KO12: 0 | KP12: 0 | KQ12: 0 | KR12: 0 | KS12: 0 | KT12: 0 | KU12: 0 | KV12: 0 | KW12: 0 | KX12: 0 | KY12: 0 | KZ12: 0 | LA12: 0 | LB12: 0 | LC12: 0 | LD12: 0 | LE12: 0 | LF12: 0 | LG12: 0 | LH12: 0 | LI12: 0 | LJ12: 0 | LK12: 0 | LL12: 0 | LM12: 0 | LN12: 0 | LO12: 0 | LP12: 0 | LQ12: 0 | LR12: 0 | LS12: 0 | LT12: 0 | LU12: 0 | LV12: 0 | LW12: 0 | LX12: 0 | LY12: 0 | LZ12: 0 | MA12: 0 | MB12: 0 | MC12: 0 | MD12: 0 | ME12: 0 | MF12: 0 | MG12: 0 | MH12: 0 | MI12: 0 | MJ12: 0 | MK12: 0 | ML12: 0 | MM12: 0 | MN12: 0 | MO12: 0 | MP12: 0 | MQ12: 0 | MR12: 0 | MS12: 0 | MT12: 0 | MU12: 0 | MV12: 0 | MW12: 0 | MX12: 0 | MY12: 0 | MZ12: 0 | NA12: 0 | NB12: 0 | NC12: 0 | ND12: 0 | NE12: 0 | NF12: 0 | NG12: 0 | NH12: 0 | NI12: 0 | NJ12: 0 | NK12: 0 | NL12: 0 | NM12: 0 | NN12: 0 | NO12: 0 | NP12: 0 | NQ12: 0 | NR12: 0 | NS12: 0 | NT12: 0 | NU12: 0 | NV12: 0 | NW12: 0 | NX12: 0 | NY12: 0 | NZ12: 0 | OA12: 0 | OB12: 0 | OC12: 0 | OD12: 0 | OE12: 0 | OF12: 0 | OG12: 0 | OH12: 0 | OI12: 0 | OJ12: 0 | OK12: 0 | OL12: 0 | OM12: 0 | ON12: 0 | OO12: 0 | OP12: 0 | OQ12: 0 | OR12: 0 | OS12: 0 | OT12: 0 | OU12: 0 | OV12: 0 | OW12: 0 | OX12: 0 | OY12: 0 | OZ12: 0 | PA12: 0 | PB12: 0 | PC12: 0 | PD12: 0 | PE12: 0 | PF12: 0 | PG12: 0 | PH12: 0 | PI12: 0 | PJ12: 0 | PK12: 0 | PL12: 0 | PM12: 0 | PN12: 0 | PO12: 0 | PP12: 0 | PQ12: 0 | PR12: 0 | PS12: 0 | PT12: 0 | PU12: 0 | PV12: 0 | PW12: 0 | PX12: 0 | PY12: 0 | PZ12: 0 | QA12: 0 | QB12: 0 | QC12: 0 | QD12: 0 | QE12: 0 | QF12: 0 | QG12: 0 | QH12: 0 | QI12: 0 | QJ12: 0 | QK12: 0 | QL12: 0 | QM12: 0 | QN12: 0 | QO12: 0 | QP12: 0 | QQ12: 0 | QR12: 0 | QS12: 0 | QT12: 0 | QU12: 0 | QV12: 0 | QW12: 0 | QX12: 0 | QY12: 0 | QZ12: 0 | RA12: 0 | RB12: 0 | RC12: 0 | RD12: 0 | RE12: 0 | RF12: 0 | RG12: 0 | RH12: 0 | RI12: 0 | RJ12: 0 | RK12: 0 | RL12: 0 | RM12: 0 | RN12: 0 | RO12: 0 | RP12: 0 | RQ12: 0 | RR12: 0 | RS12: 0 | RT12: 0 | RU12: 0 | RV12: 0 | RW12: 0 | RX12: 0 | RY12: 0 | RZ12: 0 | SA12: 0 | SB12: 0 | SC12: 0 | SD12: 0 | SE12: 0 | SF12: 0 | SG12: 0 | SH12: 0 | SI12: 0 | SJ12: 0 | SK12: 0 | SL12: 0 | SM12: 0 | SN12: 0 | SO12: 0 | SP12: 0 | SQ12: 0 | SR12: 0 | SS12: 0 | ST12: 0 | SU12: 0 | SV12: 0 | SW12: 0 | SX12: 0 | SY12: 0 | SZ12: 0 | TA12: 0 | TB12: 0 | TC12: 0 | TD12: 0 | TE12: 0 | TF12: 0 | TG12: 0 | TH12: 0 | TI12: 0 | TJ12: 0 | TK12: 0 | TL12: 0 | TM12: 0 | TN12: 0 | TO12: 0 | TP12: 0 | TQ12: 0 | TR12: 0 | TS12: 0 | TT12: 0 | TU12: 0 | TV12: 0 | TW12: 0 | TX12: 0 | TY12: 0 | TZ12: 0 | UA12: 0 | UB12: 0 | UC12: 0 | UD12: 0 | UE12: 0 | UF12: 0 | UG12: 0 | UH12: 0 | UI12: 0 | UJ12: 0 | UK12: 0 | UL12: 0 | UM12: 0 | UN12: 0 | UO12: 0 | UP12: 0 | UQ12: 0 | UR12: 0 | US12: 0 | UT12: 0 | UU12: 0 | UV12: 0 | UW12: 0 | UX12: 0 | UY12: 0 | UZ12: 0 | VA12: 0 | VB12: 0 | VC12: 0 | VD12: 0 | VE12: 0 | VF12: 0 | VG12: 0 | VH12: 0 | VI12: 0 | VJ12: 0 | VK12: 0 | VL12: 0 | VM12: 0 | VN12: 0 | VO12: 0 | VP12: 0 | VQ12: 0 | VR12: 0 | VS12: 0 | VT12: 0 | VU12: 0 | VV12: 0 | VW12: 0 | VX12: 0 | VY12: 0 | VZ12: 0 | WA12: 0 | WB12: 0 | WC12: 0 | WD12: 0 | WE12: 0 | WF12: 0 | WG12: 0 | WH12: 0 | WI12: 0 | WJ12: 0 | WK12: 0 | WL12: 0 | WM12: 0 | WN12: 0 | WO12: 0 | WP12: 0 | WQ12: 0 | WR12: 0 | WS12: 0 | WT12: 0 | WU12: 0 | WV12: 0 | WW12: 0 | WX12: 0 | WY12: 0 | WZ12: 0 | XA12: 0 | XB12: 0 | XC12: 0 | XD12: 0 | XE12: 0 | XF12: 0 | XG12: 0 | XH12: 0 | XI12: 0 | XJ12: 0 | XK12: 0 | XL12: 0 | XM12: 0 | XN12: 0 | XO12: 0 | XP12: 0
A13: cr_2025-724 | B13: Madigan Capital | C13: Asia Pacific | D13: Australia | E13: Asia Pacific | F13: 45711 | G13: 140.38011 | H13: 0 | I13: 0 | J13: 0 | K13: 0 | L13: 0 | M13: 140.38011 | N13: 0 | O13: 140.38011 | P13: 0 | Q13: 0 | R13: 0 | S13: 0 | T13: 0 | U13: 0 | V13: 0 | W13: 0 | X13: 0 | Y13: 140.38011 | Z13: 0 | AA13: 0 | AB13: 0 | AC13: 0 | AD13: 0 | AE13: 0 | AF13: 0 | AG13: 0 | AH13: 0 | AI13: 0 | AJ13: 0 | AK13: 0 | AL13: 0 | AM13: 0 | AN13: 0 | AO13: 0 | AP13: 0 | AQ13: 0 | AR13: 0 | AS13: 0 | AT13: 0 | AU13: 0 | AV13: 0 | AW13: 0 | AX13: 1 | AY13: 0 | AZ13: 0 | BA13: 0 | BB13: 100 | BC13: 0 | BD13: 1 | BE13: 3 | BF13: 80.643898 | BG13: 2 | BH13: 0 | BI13: 0 | BJ13: 0 | BK13: 0 | BL13: 0 | BM13: 2 | BN13: 140.38011 | BO13: 0 | BP13: 2 | BQ13: 0 | BR13: 0 | BS13: 0 | BT13: 0 | BU13: 0 | BV13: 0 | BW13: 0 | BX13: 0 | BY13: 0 | BZ13: 0 | CA13: 140.38011 | CB13: 0 | CC13: 0 | CD13: 0 | CE13: 0 | CF13: 0 | CG13: 0 | CH13: 0 | CI13: 0 | CJ13: 0 | CK13: 0 | CL13: 0 | CM13: 0 | CN13: 0 | CO13: 0 | CP13: 0 | CQ13: 0 | CR13: 0 | CS13: 0 | CT13: 0 | CU13: 0 | CV13: 0 | CW13: 0 | CX13: 0 | CY13: 0 | CZ13: 0 | DA13: 0 | DB13: 0 | DC13: 0 | DD13: 0 | DE13: 0 | DF13: 0 | DG13: 0 | DH13: 0 | DI13: 0 | DJ13: 0 | DK13: 0 | DL13: 0 | DM13: 0 | DN13: 0 | DO13: 0 | DP13: 0 | DQ13: 2 | DR13: 0 | DS13: 0 | DT13: 0 | DU13: 0 | DV13: 0 | DW13: 0 | DX13: 0 | DY13: 0 | DZ13: 0 | EA13: 0 | EB13: 0 | EC13: 0 | ED13: 0 | EE13: 0 | EF13: 0 | EG13: 0 | EH13: 0 | EI13: 0 | EJ13: 0 | EK13: 0 | EL13: 0 | EM13: 0 | EN13: 0 | EO13: 0 | EP13: 0 | EQ13: 0 | ER13: 0 | ES13: 0 | ET13: 0 | EU13: 0 | EV13: 20.907677 | EW13: 0 | EX13: 0 | EY13: 0 | EZ13: 119.47244 | FA13: 0 | FB13: 0 | FC13: 0 | FD13: 0 | FE13: 0 | FF13: 0 | FG13: 0 | FH13: 0 | FI13: 0 | FJ13: 0 | FK13: 0 | FL13: 20.907677 | FM13: 0 | FN13: 0 | FO13: 0 | FP13: 119.47244 | FQ13: 0 | FR13: 0 | FS13: 0 | FT13: 0 | FU13: 0 | FV13: 0 | FW13: 0 | FX13: 0 | FY13: 0 | FZ13: 0 | GA13: 0 | GB13: 0 | GC13: 0 | GD13: 0 | GE13: 0 | GF13: 0 | GG13: 0 | GH13: 0 | GI13: 0 | GJ13: 0 | GK13: 0 | GL13: 0 | GM13: 0 | GN13: 0 | GO13: 0 | GP13: 0 | GQ13: 0 | GR13: 0 | GS13: 0 | GT13: 0 | GU13: 0 | GV13: 0 | GW13: 0 | GX13: 0 | GY13: 140.38011 | GZ13: 0 | HA13: 0 | HB13: 0 | HC13: 0 | HD13: 0 | HE13: 0 | HF13: 0 | HG13: 0 | HH13: 0 | HI13: 0 | HJ13: 0 | HK13: 0 | HL13: 0 | HM13: 0 | HN13: 0 | HO13: 0 | HP13: 0 | HQ13: 0 | HR13: 0 | HS13: 0 | HT13: 0 | HU13: 0 | HV13: 0 | HW13: 0 | HX13: 0 | HY13: 0 | HZ13: 0 | IA13: 0 | IB13: 0 | IC13: 0 | ID13: 0 | IE13: 0 | IF13: 0 | IG13: 0 | IH13: 0 | II13: 0 | IJ13: 0 | IK13: 0 | IL13: 0 | IM13: 0 | IN13: 0 | IO13: 0 | IP13: 0 | IQ13: 0 | IR13: 0 | IS13: 0 | IT13: 0 | IU13: 0 | IV13: 0 | IW13: 0 | IX13: 0 | IY13: 0 | IZ13: 0 | JA13: 0 | JB13: 0 | JC13: 0 | JD13: 0 | JE13: 0 | JF13: 0 | JG13: 0 | JH13: 0 | JI13: 0 | JJ13: 0 | JK13: 0 | JL13: 0 | JM13: 0 | JN13: 0 | JO13: 0 | JP13: 0 | JQ13: 0 | JR13: 0 | JS13: 0 | JT13: 0 | JU13: 0 | JV13: 0 | JW13: 0 | JX13: 0 | JY13: 0 | JZ13: 0 | KA13: 0 | KB13: 0 | KC13: 0 | KD13: 0 | KE13: 0 | KF13: 0 | KG13: 0 | KH13: 0 | KI13: 0 | KJ13: 0 | KK13: 0 | KL13: 0 | KM13: 0 | KN13: 0 | KO13: 0 | KP13: 0 | KQ13: 0 | KR13: 0 | KS13: 0 | KT13: 0 | KU13: 0 | KV13: 0 | KW13: 0 | KX13: 0 | KY13: 0 | KZ13: 0 | LA13: 0 | LB13: 0 | LC13: 0 | LD13: 0 | LE13: 0 | LF13: 0 | LG13: 0 | LH13: 0 | LI13: 0 | LJ13: 0 | LK13: 0 | LL13: 0 | LM13: 0 | LN13: 0 | LO13: 0 | LP13: 0 | LQ13: 0 | LR13: 0 | LS13: 0 | LT13: 0 | LU13: 0 | LV13: 0 | LW13: 0 | LX13: 0 | LY13: 0 | LZ13: 0 | MA13: 0 | MB13: 0 | MC13: 0 | MD13: 0 | ME13: 0 | MF13: 0 | MG13: 0 | MH13: 0 | MI13: 0 | MJ13: 0 | MK13: 0 | ML13: 0 | MM13: 0 | MN13: 0 | MO13: 0 | MP13: 0 | MQ13: 0 | MR13: 0 | MS13: 0 | MT13: 0 | MU13: 0 | MV13: 0 | MW13: 0 | MX13: 0 | MY13: 0 | MZ13: 0 | NA13: 0 | NB13: 0 | NC13: 0 | ND13: 0 | NE13: 0 | NF13: 0 | NG13: 0 | NH13: 0 | NI13: 0 | NJ13: 0 | NK13: 0 | NL13: 0 | NM13: 0 | NN13: 0 | NO13: 0 | NP13: 0 | NQ13: 0 | NR13: 0 | NS13: 0 | NT13: 0 | NU13: 0 | NV13: 0 | NW13: 0 | NX13: 0 | NY13: 0 | NZ13: 0 | OA13: 0 | OB13: 0 | OC13: 0 | OD13: 0 | OE13: 0 | OF13: 0 | OG13: 0 | OH13: 0 | OI13: 0 | OJ13: 0 | OK13: 0 | OL13: 0 | OM13: 0 | ON13: 0 | OO13: 0 | OP13: 0 | OQ13: 0 | OR13: 0 | OS13: 0 | OT13: 0 | OU13: 0 | OV13: 0 | OW13: 0 | OX13: 0 | OY13: 0 | OZ13: 0 | PA13: 0 | PB13: 0 | PC13: 0 | PD13: 0 | PE13: 0 | PF13: 0 | PG13: 0 | PH13: 0 | PI13: 0 | PJ13: 0 | PK13: 0 | PL13: 0 | PM13: 0 | PN13: 0 | PO13: 0 | PP13: 0 | PQ13: 0 | PR13: 0 | PS13: 0 | PT13: 0 | PU13: 0 | PV13: 0 | PW13: 0 | PX13: 0 | PY13: 0 | PZ13: 0 | QA13: 0 | QB13: 0 | QC13: 0 | QD13: 0 | QE13: 0 | QF13: 0 | QG13: 0 | QH13: 0 | QI13: 0 | QJ13: 0 | QK13: 0 | QL13: 0 | QM13: 0 | QN13: 0 | QO13: 0 | QP13: 0 | QQ13: 0 | QR13: 0 | QS13: 0 | QT13: 0 | QU13: 0 | QV13: 0 | QW13: 0 | QX13: 0 | QY13: 0 | QZ13: 0 | RA13: 0 | RB13: 0 | RC13: 0 | RD13: 0 | RE13: 0 | RF13: 0 | RG13: 0 | RH13: 0 | RI13: 0 | RJ13: 0 | RK13: 0 | RL13: 0 | RM13: 0 | RN13: 0 | RO13: 0 | RP13: 0 | RQ13: 0 | RR13: 0 | RS13: 0 | RT13: 0 | RU13: 0 | RV13: 0 | RW13: 0 | RX13: 0 | RY13: 0 | RZ13: 0 | SA13: 0 | SB13: 0 | SC13: 0 | SD13: 0 | SE13: 0 | SF13: 0 | SG13: 0 | SH13: 0 | SI13: 0 | SJ13: 0 | SK13: 0 | SL13: 0 | SM13: 0 | SN13: 0 | SO13: 0 | SP13: 0 | SQ13: 0 | SR13: 0 | SS13: 0 | ST13: 0 | SU13: 0 | SV13: 0 | SW13: 0 | SX13: 0 | SY13: 0 | SZ13: 0 | TA13: 0 | TB13: 0 | TC13: 0 | TD13: 0 | TE13: 0 | TF13: 0 | TG13: 0 | TH13: 0 | TI13: 0 | TJ13: 0 | TK13: 0 | TL13: 0 | TM13: 0 | TN13: 0 | TO13: 0 | TP13: 0 | TQ13: 0 | TR13: 0 | TS13: 0 | TT13: 0 | TU13: 0 | TV13: 0 | TW13: 0 | TX13: 0 | TY13: 0 | TZ13: 0 | UA13: 0 | UB13: 0 | UC13: 0 | UD13: 0 | UE13: 0 | UF13: 0 | UG13: 0 | UH13: 0 | UI13: 0 | UJ13: 0 | UK13: 0 | UL13: 0 | UM13: 0 | UN13: 0 | UO13: 0 | UP13: 0 | UQ13: 0 | UR13: 0 | US13: 0 | UT13: 0 | UU13: 0 | UV13: 0 | UW13: 0 | UX13: 0 | UY13: 0 | UZ13: 0 | VA13: 0 | VB13: 0 | VC13: 0 | VD13: 0 | VE13: 0 | VF13: 0 | VG13: 0 | VH13: 0 | VI13: 0 | VJ13: 0 | VK13: 0 | VL13: 0 | VM13: 0 | VN13: 0 | VO13: 0 | VP13: 0 | VQ13: 0 | VR13: 0 | VS13: 0 | VT13: 0 | VU13: 0 | VV13: 0 | VW13: 0 | VX13: 0 | VY13: 0 | VZ13: 0 | WA13: 0 | WB13: 0 | WC13: 0 | WD13: 0 | WE13: 0 | WF13: 0 | WG13: 0 | WH13: 0 | WI13: 0 | WJ13: 0 | WK13: 0 | WL13: 0 | WM13: 0 | WN13: 0 | WO13: 0 | WP13: 0 | WQ13: 0 | WR13: 0 | WS13: 0 | WT13: 0 | WU13: 0 | WV13: 0 | WW13: 0 | WX13: 0 | WY13: 0 | WZ13: 0 | XA13: 0 | XB13: 0 | XC13: 0 | XD13: 0 | XE13: 0 | XF13: 0 | XG13: 0 | XH13: 0 | XI13: 0 | XJ13: 0 | XK13: 0 | XL13: 0 | XM13: 0 | XN13: 0 | XO13: 0 | XP13: 0
... A100: cr_2025-775 | B100: Growthpoint Properties Australia | C100: Asia Pacific | D100: Australia | E100: Asia Pacific | F100: 45729 | G100: 49.401855 | H100: 0 | I100: 0 | J100: 0 | K100: 0 | L100: 0 | M100: 49.401855 | N100: 0 | O100: 49.401855 | P100: 0 | Q100: 0 | R100: 0 | S100: 0 | T100: 0 | U100: 0 | V100: 0 | W100: 0 | X100: 0 | Y100: 49.401855 | Z100: 0 | AA100: 0 | AB100: 0 | AC100: 0 | AD100: 0 | AE100: 0 | AF100: 0 | AG100: 0 | AH100: 0 | AI100: 0 | AJ100: 0 | AK100: 0 | AL100: 0 | AM100: 0 | AN100: 0 | AO100: 0 | AP100: 0 | AQ100: 0 | AR100: 0 | AS100: 0 | AT100: 0 | AU100: 0 | AV100: 0 | AW100: 0 | AX100: 1 | AY100: 0 | AZ100: 100 | BA100: 0 | BB100: 0 | BC100: 0 | BD100: 1 | BE100: 3 | BF100: 49.401855 | BG100: 1 | BH100: 0 | BI100: 0 | BJ100: 0 | BK100: 0 | BL100: 0 | BM100: 1 | BN100: 49.401855 | BO100: 0 | BP100: 1 | BQ100: 0 | BR100: 0 | BS100: 0 | BT100: 0 | BU100: 0 | BV100: 0 | BW100: 0 | BX100: 0 | BY100: 0 | BZ100: 0 | CA100: 49.401855 | CB100: 0 | CC100: 0 | CD100: 0 | CE100: 0 | CF100: 0 | CG100: 0 | CH100: 0 | CI100: 0 | CJ100: 0 | CK100: 0 | CL100: 0 | CM100: 0 | CN100: 0 | CO100: 0 | CP100: 0 | CQ100: 0 | CR100: 0 | CS100: 0 | CT100: 0 | CU100: 0 | CV100: 0 | CW100: 0 | CX100: 0 | CY100: 0 | CZ100: 0 | DA100: 0 | DB100: 0 | DC100: 0 | DD100: 0 | DE100: 0 | DF100: 0 | DG100: 0 | DH100: 0 | DI100: 0 | DJ100: 0 | DK100: 0 | DL100: 0 | DM100: 0 | DN100: 0 | DO100: 0 | DP100: 0 | DQ100: 1 | DR100: 0 | DS100: 0 | DT100: 0 | DU100: 0 | DV100: 0 | DW100: 0 | DX100: 0 | DY100: 0 | DZ100: 0 | EA100: 0 | EB100: 0 | EC100: 0 | ED100: 0 | EE100: 0 | EF100: 0 | EG100: 0 | EH100: 0 | EI100: 0 | EJ100: 0 | EK100: 0 | EL100: 0 | EM100: 0 | EN100: 0 | EO100: 0 | EP100: 0 | EQ100: 0 | ER100: 0 | ES100: 0 | ET100: 0 | EU100: 0 | EV100: 0 | EW100: 0 | EX100: 0 | EY100: 0 | EZ100: 0 | FA100: 0 | FB100: 49.401855 | FC100: 0 | FD100: 0 | FE100: 0 | FF100: 0 | FG100: 0 | FH100: 0 | FI100: 0 | FJ100: 0 | FK100: 0 | FL100: 0 | FM100: 0 | FN100: 0 | FO100: 0 | FP100: 0 | FQ100: 0 | FR100: 49.401855 | FS100: 0 | FT100: 0 | FU100: 0 | FV100: 0 | FW100: 0 | FX100: 0 | FY100: 0 | FZ100: 0 | GA100: 0 | GB100: 0 | GC100: 0 | GD100: 0 | GE100: 0 | GF100: 0 | GG100: 0 | GH100: 0 | GI100: 0 | GJ100: 0 | GK100: 0 | GL100: 0 | GM100: 0 | GN100: 0 | GO100: 0 | GP100: 0 | GQ100: 0 | GR100: 0 | GS100: 0 | GT100: 0 | GU100: 0 | GV100: 0 | GW100: 0 | GX100: 0 | GY100: 49.401855 | GZ100: 0 | HA100: 0 | HB100: 0 | HC100: 0 | HD100: 0 | HE100: 0 | HF100: 0 | HG100: 0 | HH100: 0 | HI100: 0 | HJ100: 0 | HK100: 0 | HL100: 0 | HM100: 0 | HN100: 0 | HO100: 0 | HP100: 0 | HQ100: 0 | HR100: 0 | HS100: 0 | HT100: 0 | HU100: 0 | HV100: 0 | HW100: 0 | HX100: 0 | HY100: 0 | HZ100: 0 | IA100: 0 | IB100: 0 | IC100: 0 | ID100: 0 | IE100: 0 | IF100: 0 | IG100: 0 | IH100: 0 | II100: 0 | IJ100: 0 | IK100: 0 | IL100: 0 | IM100: 0 | IN100: 0 | IO100: 0 | IP100: 0 | IQ100: 0 | IR100: 0 | IS100: 0 | IT100: 0 | IU100: 0 | IV100: 0 | IW100: 0 | IX100: 0 | IY100: 0 | IZ100: 0 | JA100: 0 | JB100: 0 | JC100: 0 | JD100: 0 | JE100: 0 | JF100: 0 | JG100: 0 | JH100: 0 | JI100: 0 | JJ100: 0 | JK100: 0 | JL100: 0 | JM100: 0 | JN100: 0 | JO100: 0 | JP100: 0 | JQ100: 0 | JR100: 0 | JS100: 0 | JT100: 0 | JU100: 0 | JV100: 0 | JW100: 0 | JX100: 0 | JY100: 0 | JZ100: 0 | KA100: 0 | KB100: 0 | KC100: 0 | KD100: 0 | KE100: 0 | KF100: 0 | KG100: 0 | KH100: 0 | KI100: 0 | KJ100: 0 | KK100: 0 | KL100: 0 | KM100: 0 | KN100: 0 | KO100: 0 | KP100: 0 | KQ100: 0 | KR100: 0 | KS100: 0 | KT100: 0 | KU100: 0 | KV100: 0 | KW100: 0 | KX100: 0 | KY100: 0 | KZ100: 0 | LA100: 0 | LB100: 0 | LC100: 0 | LD100: 0 | LE100: 0 | LF100: 0 | LG100: 0 | LH100: 0 | LI100: 0 | LJ100: 0 | LK100: 0 | LL100: 0 | LM100: 0 | LN100: 0 | LO100: 0 | LP100: 0 | LQ100: 0 | LR100: 0 | LS100: 0 | LT100: 0 | LU100: 0 | LV100: 0 | LW100: 0 | LX100: 0 | LY100: 0 | LZ100: 0 | MA100: 0 | MB100: 0 | MC100: 0 | MD100: 0 | ME100: 0 | MF100: 0 | MG100: 0 | MH100: 0 | MI100: 0 | MJ100: 0 | MK100: 0 | ML100: 0 | MM100: 0 | MN100: 0 | MO100: 0 | MP100: 0 | MQ100: 0 | MR100: 0 | MS100: 0 | MT100: 0 | MU100: 0 | MV100: 0 | MW100: 0 | MX100: 0 | MY100: 0 | MZ100: 0 | NA100: 0 | NB100: 0 | NC100: 0 | ND100: 0 | NE100: 0 | NF100: 0 | NG100: 0 | NH100: 0 | NI100: 0 | NJ100: 0 | NK100: 0 | NL100: 0 | NM100: 0 | NN100: 0 | NO100: 0 | NP100: 0 | NQ100: 0 | NR100: 0 | NS100: 0 | NT100: 0 | NU100: 0 | NV100: 0 | NW100: 0 | NX100: 0 | NY100: 0 | NZ100: 0 | OA100: 0 | OB100: 0 | OC100: 0 | OD100: 0 | OE100: 0 | OF100: 0 | OG100: 0 | OH100: 0 | OI100: 0 | OJ100: 0 | OK100: 0 | OL100: 0 | OM100: 0 | ON100: 0 | OO100: 0 | OP100: 0 | OQ100: 0 | OR100: 0 | OS100: 0 | OT100: 0 | OU100: 0 | OV100: 0 | OW100: 0 | OX100: 0 | OY100: 0 | OZ100: 0 | PA100: 0 | PB100: 0 | PC100: 0 | PD100: 0 | PE100: 0 | PF100: 0 | PG100: 0 | PH100: 0 | PI100: 0 | PJ100: 0 | PK100: 0 | PL100: 0 | PM100: 0 | PN100: 0 | PO100: 0 | PP100: 0 | PQ100: 0 | PR100: 0 | PS100: 0 | PT100: 0 | PU100: 0 | PV100: 0 | PW100: 0 | PX100: 0 | PY100: 0 | PZ100: 0 | QA100: 0 | QB100: 0 | QC100: 0 | QD100: 0 | QE100: 0 | QF100: 0 | QG100: 0 | QH100: 0 | QI100: 0 | QJ100: 0 | QK100: 0 | QL100: 0 | QM100: 0 | QN100: 0 | QO100: 0 | QP100: 0 | QQ100: 0 | QR100: 0 | QS100: 0 | QT100: 0 | QU100: 0 | QV100: 0 | QW100: 0 | QX100: 0 | QY100: 0 | QZ100: 0 | RA100: 0 | RB100: 0 | RC100: 0 | RD100: 0 | RE100: 0 | RF100: 0 | RG100: 0 | RH100: 0 | RI100: 0 | RJ100: 0 | RK100: 0 | RL100: 0 | RM100: 0 | RN100: 0 | RO100: 0 | RP100: 0 | RQ100: 0 | RR100: 0 | RS100: 0 | RT100: 0 | RU100: 0 | RV100: 0 | RW100: 0 | RX100: 0 | RY100: 0 | RZ100: 0 | SA100: 0 | SB100: 0 | SC100: 0 | SD100: 0 | SE100: 0 | SF100: 0 | SG100: 0 | SH100: 0 | SI100: 0 | SJ100: 0 | SK100: 0 | SL100: 0 | SM100: 0 | SN100: 0 | SO100: 0 | SP100: 0 | SQ100: 0 | SR100: 0 | SS100: 0 | ST100: 0 | SU100: 0 | SV100: 0 | SW100: 0 | SX100: 0 | SY100: 0 | SZ100: 0 | TA100: 0 | TB100: 0 | TC100: 0 | TD100: 0 | TE100: 0 | TF100: 0 | TG100: 0 | TH100: 0 | TI100: 0 | TJ100: 0 | TK100: 0 | TL100: 0 | TM100: 0 | TN100: 0 | TO100: 0 | TP100: 0 | TQ100: 0 | TR100: 0 | TS100: 0 | TT100: 0 | TU100: 0 | TV100: 0 | TW100: 0 | TX100: 0 | TY100: 0 | TZ100: 0 | UA100: 0 | UB100: 0 | UC100: 0 | UD100: 0 | UE100: 0 | UF100: 0 | UG100: 0 | UH100: 0 | UI100: 0 | UJ100: 0 | UK100: 0 | UL100: 0 | UM100: 0 | UN100: 0 | UO100: 0 | UP100: 0 | UQ100: 0 | UR100: 0 | US100: 0 | UT100: 0 | UU100: 0 | UV100: 0 | UW100: 0 | UX100: 0 | UY100: 0 | UZ100: 0 | VA100: 0 | VB100: 0 | VC100: 0 | VD100: 0 | VE100: 0 | VF100: 0 | VG100: 0 | VH100: 0 | VI100: 0 | VJ100: 0 | VK100: 0 | VL100: 0 | VM100: 0 | VN100: 0 | VO100: 0 | VP100: 0 | VQ100: 0 | VR100: 0 | VS100: 0 | VT100: 0 | VU100: 0 | VV100: 0 | VW100: 0 | VX100: 0 | VY100: 0 | VZ100: 0 | WA100: 0 | WB100: 0 | WC100: 0 | WD100: 0 | WE100: 0 | WF100: 0 | WG100: 0 | WH100: 0 | WI100: 0 | WJ100: 0 | WK100: 0 | WL100: 0 | WM100: 0 | WN100: 0 | WO100: 0 | WP100: 0 | WQ100: 0 | WR100: 0 | WS100: 0 | WT100: 0 | WU100: 0 | WV100: 0 | WW100: 0 | WX100: 0 | WY100: 0 | WZ100: 0 | XA100: 0 | XB100: 0 | XC100: 0 | XD100: 0 | XE100: 0 | XF100: 0 | XG100: 0 | XH100: 0 | XI100: 0 | XJ100: 0 | XK100: 0 | XL100: 0 | XM100: 0 | XN100: 0 | XO100: 0 | XP100: 0

Sheet historical
A1: answer_label | B1: year | C1: label | D1: label_2 | E1: value | F1: sample
A2: nocapitalraisingactivity_reason | B2: 2020 | C2: No product available at that moment | E2: 19 | F2: 19
A3: regionalstrategy_separateaccountsindirect_total | B3: 2022 | C3: Separate accounts investing indirectly total | E3: 6.1587626 | F3: 7
A4: regionalstrategy_nonlistedfunds_total | B4: 2016 | C4: Non-listed funds | E4: 60.786155 | F4: 105
A5: nov_regionalstrategy_separateaccountsdirect_total | B5: 2016 | C5: Separate accounts investing directly | E5: 188 | F5: 54
A6: capitalraisingactivity_development | B6: 2019 | C6: No change | E6: 35 | F6: 35
A7: capitalraisingactivity_development | B7: 2017 | C7: Decrease | E7: 18 | F7: 18
A8: capitalraisingactivity_impactregulation | B8: 2021 | C8: Negative impact | E8: 20 | F8: 20
A9: regionalstrategynorthamerica_jvs | B9: 2021 | C9: Joint ventures and club deals | E9: 5.0568371 | F9: 8
A10: regionalstrategynorthamerica_fundsoffunds | B10: 2016 | C10: Funds of funds | E10: 0.28240979 | F10: 2
A11: nov_regionalstrategyasiapacific_jvs | B11: 2018 | C11: Joint ventures and club deals | E11: 34 | F11: 10
A12: nov_regionalstrategyglobal_separateaccountsdirect | B12: 2021 | C12: Separate accounts investing directly | E12: 13 | F12: 4
A13: sovereignwealthfunds_vehicletype_total | B13: 2024 | C13: Sovereign wealth funds | E13: 0.1 | F13: 1
A14: insurancecompanies_debt | B14: 2019 | C14: Non-listed debt products | D14: Insurance companies | E14: 14.489864 | F14: 10
A15: investordomicileeurope_separateaccountsdirect | B15: 2017 | C15: Separate accounts direct | D15: Europe | E15: 13.098967 | F15: 35
A16: investordomicileeurope_fundsoffunds | B16: 2016 | C16: Funds of funds | D16: Europe | E16: 2.2451921 | F16: 6
A17: global_highnetworthindividualsfamilyoffices_vehicletype_total | B17: 2022 | C17: Hign net worth individuals/Family offices | E17: 5.587203 | F17: 4
A18: europe_pensionfunds_nonlistedfunds | B18: 2019 | C18: Pension funds | E18: 10.120656 | F18: 48
A19: europe_investortype_jvs_total | B19: 2020 | C19: Investor type | E19: 2.2009407 | F19: 15
A20: europe_investordomicileeurope_vehicletype_total | B20: 2018 | C20: Europe | E20: 43.429605 | F20: 81
A21: regionalstrategyglobal_vehicletype_total | B21: 2023 | C21: Global | E21: 33.236544 | F21: 10
A22: nov_regionalstrategysouthamerica_vehicletype_total | B22: 2016 | C22: South America | E22: 2 | F22: 2
A23: regionalstrategynorthamerica_jvs | B23: 2015 | C23: Joint ventures and club deals | E23: 6.1948019 | F23: 10
A24: regionalstrategyasiapacific_nonlistedfunds | B24: 2015 | C24: Non-listed funds | E24: 10.284569 | F24: 36
A25: regionalstrategynorthamerica_separateaccountsdirect | B25: 2017 | C25: Separate accounts investing directly | E25: 8.0764782 | F25: 17
A26: nov_regionalstrategysouthamerica_separateaccountsdirect | B26: 2017 | C26: Separate accounts investing directly | E26: 1 | F26: 1
A27: nov_regionalstrategysouthamerica_nonlistedfunds | B27: 2016 | C27: Non-listed funds | E27: 1 | F27: 1
A28: charitiesfoundationsnonprofitorganizations_jvs | B28: 2020 | C28: Joint ventures and club deals | D28: Charities, foundations & nonprofit organisations | E28: 0.0133 | F28: 1
A29: pensionfunds_separateaccountsdirect | B29: 2022 | C29: Separate accounts investing directly | D29: Pension funds | E29: 15.915851 | F29: 23
A30: governmentinstitutions_nonlistedfunds | B30: 2021 | C30: Non-listed fund | D30: Government institutions | E30: 2.3640068 | F30: 10
A31: investordomicileasiapacific_fundsoffunds | B31: 2018 | C31: Funds of funds | D31: Asia Pacific | E31: 1.2406391 | F31: 4
A32: global_highnetworthindividualsfamilyoffices_vehicletype_total | B32: 2021 | C32: Hign net worth individuals/Family offices | E32: 0.49903064 | F32: 2
A33: global_pensionfunds_separateaccountsdirect | B33: 2019 | C33: Pension funds | E33: 1.711 | F33: 1
A34: global_investordomicilenorthamerica_vehicletype_total | B34: 2019 | C34: North America | E34: 4.2909628 | F34: 5
A35: europe_pensionfunds_separateaccountsdirect | B35: 2024 | C35: Pension funds | E35: 0.113 | F35: 2
A36: europe_investordomicilesouthamerica_vehicletype_total | B36: 2021 | C36: South America | E36: 0.034540844 | F36: 3
A37: regionalstrategynorthamerica_nonlistedfunds | B37: 2017 | C37: Non-listed funds | E37: 23.952111 | F37: 30
A38: regionalstrategyeurope_debt | B38: 2019 | C38: Non-listed debt | E38: 4.1036815 | F38: 7
A39: nov_regionalstrategyasiapacific_fundsoffunds | B39: 2018 | C39: Funds of funds | E39: 4 | F39: 3
A40: nov_regionalstrategyeurope_debt | B40: 2020 | C40: Non-listed debt | E40: 29 | F40: 17
A41: nov_regionalstrategyglobal_nonlistedfunds | B41: 2015 | C41: Non-listed funds | E41: 8 | F41: 6
A42: insurancecompanies_separateaccountsdirect | B42: 2023 | C42: Separate accounts investing directly | D42: Insurance companies | E42: 3.8359735 | F42: 7
A43: pensionfunds_separateaccountsdirect | B43: 2023 | C43: Separate accounts investing directly | D43: Pension funds | E43: 3.6214211 | F43: 18
A44: sovereignwealthfunds_jvs | B44: 2020 | C44: Joint ventures and club deals | D44: Sovereign wealth funds | E44: 2.1058473 | F44: 7
A45: investordomicileasiapacific_vehicletype_total | B45: 2024 | C45: Asia Pacific | E45: 0.86357952 | F45: 4
A46: investordomicilenorthamerica_separateaccountsindirect | B46: 2018 | C46: Separate accounts indirect | D46: North America | E46: 0.087428505 | F46: 1
A47: investordomicileeurope_separateaccountsdirect | B47: 2019 | C47: Separate accounts direct | D47: Europe | E47: 21.599112 | F47: 31
A48: global_governmentinstitutions_nonlistedfunds | B48: 2021 | C48: Government institutions | E48: 0.088167953 | F48: 1
A49: global_investordomicileasiapacific_separateaccountsindirect | B49: 2020 | C49: Asia Pacific | E49: 0.76758881 | F49: 1
A50: europe_charitiesfoundationsnonprofitorganizations_nonlistedfunds | B50: 2018 | C50: Charities, foundations & nonprofit organisations | E50: 1.0524246 | F50: 28
A51: europe_insurancecompanies_nonlistedfunds | B51: 2016 | C51: Insurance companies | E51: 4.8829553 | F51: 31
A52: europe_insurancecompanies_jvs | B52: 2023 | C52: Insurance companies | E52: 0.10036917 | F52: 1
A53: europe_governmentinstitutions_debt | B53: 2021 | C53: Government institutions | E53: 0.054803497 | F53: 1
A54: europe_otherinvestortype_nonlistedfunds | B54: 2016 | C54: Other investor type | E54: 3.3563078 | F54: 27
A55: europe_investordomicilenorthamerica_vehicletype_total | B55: 2024 | C55: North America | E55: 0.31 | F55: 2
A56: nov_regionalstrategysouthamerica_vehicletype_total | B56: 2020 | C56: South America | E56: 3 | F56: 3
A57: regionalstrategyasiapacific_fundsoffunds | B57: 2020 | C57: Funds of funds | E57: 0.25 | F57: 2
A58: regionalstrategyasiapacific_separateaccountsdirect | B58: 2020 | C58: Separate accounts investing directly | E58: 3.4595957 | F58: 9
A59: nov_regionalstrategyglobal_separateaccountsdirect | B59: 2018 | C59: Separate accounts investing directly | E59: 4 | F59: 4
A60: insurancecompanies_vehicletype_total | B60: 2020 | C60: Insurance companies | E60: 25.599816 | F60: 42
A61: sovereignwealthfunds_nonlistedfunds | B61: 2022 | C61: Non-listed fund | D61: Sovereign wealth funds | E61: 13.576542 | F61: 20
A62: sovereignwealthfunds_jvs | B62: 2018 | C62: Joint ventures and club deals | D62: Sovereign wealth funds | E62: 1.3898994 | F62: 8
A63: insurancecompanies_jvs | B63: 2024 | C63: Joint ventures and club deals | D63: Insurance companies | E63: 0.024069946 | F63: 1
A64: investordomicileeurope_separateaccountsdirect | B64: 2022 | C64: Separate accounts direct | D64: Europe | E64: 8.2884052 | F64: 18
A65: investordomicileeurope_debt | B65: 2021 | C65: Non-listed debt | D65: Europe | E65: 12.380176 | F65: 16
A66: global_charitiesfoundationsnonprofitorganizations_vehicletype_total | B66: 2021 | C66: Charities, foundations & nonprofit organisations | E66: 0.41527106 | F66: 1
A67: global_governmentinstitutions_separateaccountsindirect | B67: 2023 | C67: Government institutions | E67: 0.44653146 | F67: 1
A68: global_insurancecompanies_debt | B68: 2021 | C68: Insurance companies | E68: 0.245 | F68: 2
A69: europe_highnetworthindividualsfamilyoffices_nonlistedfunds | B69: 2023 | C69: Hign net worth individuals/Family offices | E69: 0.19836782 | F69: 7
A70: europe_charitiesfoundationsnonprofitorganizations_vehicletype_total | B70: 2016 | C70: Charities, foundations & nonprofit organisations | E70: 0.85042402 | F70: 19
A71: europe_insurancecompanies_nonlistedfunds | B71: 2018 | C71: Insurance companies | E71: 5.1483065 | F71: 35
A72: europe_fundsoffunds_jvs | B72: 2019 | C72: Funds of funds | E72: 0.32615031 | F72: 3
A73: nocapitalraisingactivity_reason | B73: 2016 | C73: Other | E73: 27 | F73: 27
A74: regionalstrategy_separateaccountsindirect_total | B74: 2019 | C74: Separate accounts investing indirectly | E74: 6.3008251 | F74: 14
A75: capitalraisingactivity_nonlistedrealestatevehicles | B75: 2016 | C75: No | E75: 32 | F75: 32
A76: regionalstrategy_separateaccountsindirect_total | B76: 2020 | C76: Separate accounts investing indirectly total | E76: 2.2170461 | F76: 7
A77: nov_regionalstrategy_separateaccountsindirect_total | B77: 2020 | C77: Separate accounts investing indirectly total | E77: 22 | F77: 7
... A85: nov_regionalstrategyeurope_separateaccountsdirect | B85: 2021 | C85: Separate accounts investing directly | E85: 90 | F85: 24
A86: fundsoffunds_nonlistedfunds | B86: 2018 | C86: Non-listed fund | D86: Funds of funds | E86: 2.7838712 | F86: 38
A87: investordomicileafrica_vehicletype_total | B87: 2020 | C87: Africa | E87: 0.081541283 | F87: 1
A88: investordomicileafrica_jvs | B88: 2016 | C88: Joint ventures and club deals | D88: Africa | E88: 0.10630626 | F88: 1
A89: investordomicilesouthamerica_nonlistedfunds | B89: 2022 | C89: Non-listed funds | D89: South America | E89: 0.51983417 | F89: 8
A90: global_investordomicilesouthamerica_nonlistedfunds | B90: 2020 | C90: South America | E90: 0.005 | F90: 1
A91: europe_insurancecompanies_debt | B91: 2019 | C91: Insurance companies | E91: 0.52354059 | F91: 4
A92: europe_pensionfunds_separateaccountsdirect | B92: 2021 | C92: Pension funds | E92: 4.7382316 | F92: 14
A93: europe_investordomicilesouthamerica_vehicletype_total | B93: 2016 | C93: South America | E93: 0.04955 | F93: 3
A94: regionalstrategyglobal_vehicletype_total | B94: 2016 | C94: Global | E94: 11.322322 | F94: 14
A95: regionalstrategyeurope_fundsoffunds | B95: 2016 | C95: Funds of funds | E95: 1.2908152 | F95: 4
A96: regionalstrategyeurope_separateaccountsdirect | B96: 2018 | C96: Separate accounts investing directly | E96: 19.228229 | F96: 32
A97: regionalstrategyasiapacific_nonlistedfunds | B97: 2016 | C97: Non-listed funds | E97: 11.123675 | F97: 33
A98: regionalstrategyglobal_separateaccountsdirect | B98: 2019 | C98: Separate accounts investing directly | E98: 3.411484 | F98: 2
A99: nov_regionalstrategyglobal_debt | B99: 2020 | C99: Non-listed debt | E99: 1 | F99: 1
A100: nov_regionalstrategyasiapacific_fundsoffunds | B100: 2020 | C100: Funds of funds | E100: 2 | F100: 2
A101: pensionfunds_fundsoffunds | B101: 2023 | C101: Funds of funds | D101: Pension funds | E101: 0.4048331 | F101: 3
A102: fundsoffunds_separateaccountsdirect | B102: 2019 | C102: Separate accounts investing directly | D102: Funds of funds | E102: 2.5390431 | F102: 4
A103: fundsoffunds_jvs | B103: 2018 | C103: Joint ventures and club deals | D103: Funds of funds | E103: 0.56968463 | F103: 4
A104: investordomicileasiapacific_fundsoffunds | B104: 2017 | C104: Funds of funds | D104: Asia Pacific | E104: 0.71566121 | F104: 4
A105: global_pensionfunds_nonlistedfunds | B105: 2021 | C105: Pension funds | E105: 3.975493 | F105: 2
A106: global_pensionfunds_separateaccountsdirect | B106: 2022 | C106: Pension funds | E106: 3.9024163 | F106: 1
A107: global_investordomicileasiapacific_separateaccountsindirect | B107: 2017 | C107: Asia Pacific | E107: 0.30708839 | F107: 2
...

Sheet KeyFig (1)
A1: Fund manager domicile
B3: region | C3: Number of respondents | E3: region | F3: Number of respondents
B4: Asia Pacific | C4: {=IF(COUNTA(_xlfn._xlws.FILTER('TERadj'!C2:C100, ('TERadj'!C2:C100>0)*('TERadj'!C2:C100="Asia Pacific")))=0, 0, COUNTA(_xlfn._xlws.FILTER('TERadj'!C2:C100, ('TERadj'!C2:C100>0)*('TERadj'!C2:C100="Asia Pacific"))))} -> 0 | E4: Asia Pacific | F4: {=IF(COUNTA(_xlfn._xlws.FILTER('TERadj'!C2:C100, ('TERadj'!C2:C100>0)*('TERadj'!C2:C100="Asia Pacific")))=0, 0, COUNTA(_xlfn._xlws.FILTER('TERadj'!C2:C100, ('TERadj'!C2:C100>0)*('TERadj'!C2:C100="Asia Pacific"))))} -> 0
B5: Europe | C5: {=IF(COUNTA(_xlfn._xlws.FILTER('TERadj'!C2:C100, ('TERadj'!C2:C100>0)*('TERadj'!C2:C100="Europe")))=0, 0, COUNTA(_xlfn._xlws.FILTER('TERadj'!C2:C100, ('TERadj'!C2:C100>0)*('TERadj'!C2:C100="Europe"))))} -> 0 | E5: Europe | F5: {=IF(COUNTA(_xlfn._xlws.FILTER('TERadj'!C2:C100, ('TERadj'!C2:C100>0)*('TERadj'!C2:C100="Europe")))=0, 0, COUNTA(_xlfn._xlws.FILTER('TERadj'!C2:C100, ('TERadj'!C2:C100>0)*('TERadj'!C2:C100="Europe"))))} -> 0
B6: North America | C6: {=IF(COUNTA(_xlfn._xlws.FILTER('TERadj'!C2:C100, ('TERadj'!C2:C100>0)*('TERadj'!C2:C100="North America")))=0, 0, COUNTA(_xlfn._xlws.FILTER('TERadj'!C2:C100, ('TERadj'!C2:C100>0)*('TERadj'!C2:C100="North America"))))} -> 0 | E6: North America | F6: {=IF(COUNTA(_xlfn._xlws.FILTER('TERadj'!C2:C100, ('TERadj'!C2:C100>0)*('TERadj'!C2:C100="North America")))=0, 0, COUNTA(_xlfn._xlws.FILTER('TERadj'!C2:C100, ('TERadj'!C2:C100>0)*('TERadj'!C2:C100="North America"))))} -> 0
B7: South America | C7: {=IF(COUNTA(_xlfn._xlws.FILTER('TERadj'!C2:C100, ('TERadj'!C2:C100>0)*('TERadj'!C2:C100="South America")))=0, 0, COUNTA(_xlfn._xlws.FILTER('TERadj'!C2:C100, ('TERadj'!C2:C100>0)*('TERadj'!C2:C100="South America"))))} -> 0 | E7: South America | F7: {=IF(COUNTA(_xlfn._xlws.FILTER('TERadj'!C2:C100, ('TERadj'!C2:C100>0)*('TERadj'!C2:C100="South America")))=0, 0, COUNTA(_xlfn._xlws.FILTER('TERadj'!C2:C100, ('TERadj'!C2:C100>0)*('TERadj'!C2:C100="South America"))))} -> 0
B8: Africa | C8: {=IF(COUNTA(_xlfn._xlws.FILTER('TERadj'!C2:C100, ('TERadj'!C2:C100>0)*('TERadj'!C2:C100="Africa")))=0, 0, COUNTA(_xlfn._xlws.FILTER('TERadj'!C2:C100, ('TERadj'!C2:C100>0)*('TERadj'!C2:C100="Africa"))))} -> 0 | E8: Africa | F8: {=IF(COUNTA(_xlfn._xlws.FILTER('TERadj'!C2:C100, ('TERadj'!C2:C100>0)*('TERadj'!C2:C100="Africa")))=0, 0, COUNTA(_xlfn._xlws.FILTER('TERadj'!C2:C100, ('TERadj'!C2:C100>0)*('TERadj'!C2:C100="Africa"))))} -> 0
B10: region | C10: Number of respondents
B11: Asia Pacific | C11: {=IF(COUNTA(_xlfn._xlws.FILTER('TERadj'!C2:C100, ('TERadj'!C2:C100>0)*('TERadj'!C2:C100="Asia Pacific")))=0, 0, COUNTA(_xlfn._xlws.FILTER('TERadj'!C2:C100, ('TERadj'!C2:C100>0)*('TERadj'!C2:C100="Asia Pacific"))))} -> 0
B12: Europe | C12: {=IF(COUNTA(_xlfn._xlws.FILTER('TERadj'!C2:C100, ('TERadj'!C2:C100>0)*('TERadj'!C2:C100="Europe")))=0, 0, COUNTA(_xlfn._xlws.FILTER('TERadj'!C2:C100, ('TERadj'!C2:C100>0)*('TERadj'!C2:C100="Europe"))))} -> 0
B13: North America | C13: {=IF(COUNTA(_xlfn._xlws.FILTER('TERadj'!C2:C100, ('TERadj'!C2:C100>0)*('TERadj'!C2:C100="North America")))=0, 0, COUNTA(_xlfn._xlws.FILTER('TERadj'!C2:C100, ('TERadj'!C2:C100>0)*('TERadj'!C2:C100="North America"))))} -> 0
B14: South America | C14: {=IF(COUNTA(_xlfn._xlws.FILTER('TERadj'!C2:C100, ('TERadj'!C2:C100>0)*('TERadj'!C2:C100="South America")))=0, 0, COUNTA(_xlfn._xlws.FILTER('TERadj'!C2:C100, ('TERadj'!C2:C100>0)*('TERadj'!C2:C100="South America"))))} -> 0
B15: Africa | C15: {=IF(COUNTA(_xlfn._xlws.FILTER('TERadj'!C2:C100, ('TERadj'!C2:C100>0)*('TERadj'!C2:C100="Africa")))=0, 0, COUNTA(_xlfn._xlws.FILTER('TERadj'!C2:C100, ('TERadj'!C2:C100>0)*('TERadj'!C2:C100="Africa"))))} -> 0

Sheet KeyFig (2)
A1: Fund manager domicile
B3: country | C3: Number of respondents | E3: country | F3: Number of respondents
B4: Australia | C4: {=IF(COUNTA(_xlfn._xlws.FILTER('TERadj'!D2:D100, ('TERadj'!D2:D100>0)*('TERadj'!D2:D100="Australia")))=0, 0, COUNTA(_xlfn._xlws.FILTER('TERadj'!D2:D100, ('TERadj'!D2:D100>0)*('TERadj'!D2:D100="Australia"))))} -> 0 | E4: Australia | F4: {=IF(COUNTA(_xlfn._xlws.FILTER('TERadj'!D2:D100, ('TERadj'!D2:D100>0)*('TERadj'!D2:D100="Australia")))=0, 0, COUNTA(_xlfn._xlws.FILTER('TERadj'!D2:D100, ('TERadj'!D2:D100>0)*('TERadj'!D2:D100="Australia"))))} -> 0
B5: Belgium | C5: {=IF(COUNTA(_xlfn._xlws.FILTER('TERadj'!D2:D100, ('TERadj'!D2:D100>0)*('TERadj'!D2:D100="Belgium")))=0, 0, COUNTA(_xlfn._xlws.FILTER('TERadj'!D2:D100, ('TERadj'!D2:D100>0)*('TERadj'!D2:D100="Belgium"))))} -> 0 | E5: Belgium | F5: {=IF(COUNTA(_xlfn._xlws.FILTER('TERadj'!D2:D100, ('TERadj'!D2:D100>0)*('TERadj'!D2:D100="Belgium")))=0, 0, COUNTA(_xlfn._xlws.FILTER('TERadj'!D2:D100, ('TERadj'!D2:D100>0)*('TERadj'!D2:D100="Belgium"))))} -> 0
B6: Bermuda | C6: {=IF(COUNTA(_xlfn._xlws.FILTER('TERadj'!D2:D100, ('TERadj'!D2:D100>0)*('TERadj'!D2:D100="Bermuda")))=0, 0, COUNTA(_xlfn._xlws.FILTER('TERadj'!D2:D100, ('TERadj'!D2:D100>0)*('TERadj'!D2:D100="Bermuda"))))} -> 0 | E6: Bermuda | F6: {=IF(COUNTA(_xlfn._xlws.FILTER('TERadj'!D2:D100, ('TERadj'!D2:D100>0)*('TERadj'!D2:D100="Bermuda")))=0, 0, COUNTA(_xlfn._xlws.FILTER('TERadj'!D2:D100, ('TERadj'!D2:D100>0)*('TERadj'!D2:D100="Bermuda"))))} -> 0
B7: Finland | C7: {=IF(COUNTA(_xlfn._xlws.FILTER('TERadj'!D2:D100, ('TERadj'!D2:D100>0)*('TERadj'!D2:D100="Finland")))=0, 0, COUNTA(_xlfn._xlws.FILTER('TERadj'!D2:D100, ('TERadj'!D2:D100>0)*('TERadj'!D2:D100="Finland"))))} -> 0 | E7: Finland | F7: {=IF(COUNTA(_xlfn._xlws.FILTER('TERadj'!D2:D100, ('TERadj'!D2:D100>0)*('TERadj'!D2:D100="Finland")))=0, 0, COUNTA(_xlfn._xlws.FILTER('TERadj'!D2:D100, ('TERadj'!D2:D100>0)*('TERadj'!D2:D100="Finland"))))} -> 0
B8: France | C8: {=IF(COUNTA(_xlfn._xlws.FILTER('TERadj'!D2:D100, ('TERadj'!D2:D100>0)*('TERadj'!D2:D100="France")))=0, 0, COUNTA(_xlfn._xlws.FILTER('TERadj'!D2:D100, ('TERadj'!D2:D100>0)*('TERadj'!D2:D100="France"))))} -> 0 | E8: France | F8: {=IF(COUNTA(_xlfn._xlws.FILTER('TERadj'!D2:D100, ('TERadj'!D2:D100>0)*('TERadj'!D2:D100="France")))=0, 0, COUNTA(_xlfn._xlws.FILTER('TERadj'!D2:D100, ('TERadj'!D2:D100>0)*('TERadj'!D2:D100="France"))))} -> 0
B9: Germany | C9: {=IF(COUNTA(_xlfn._xlws.FILTER('TERadj'!D2:D100, ('TERadj'!D2:D100>0)*('TERadj'!D2:D100="Germany")))=0, 0, COUNTA(_xlfn._xlws.FILTER('TERadj'!D2:D100, ('TERadj'!D2:D100>0)*('TERadj'!D2:D100="Germany"))))} -> 0 | E9: Germany | F9: {=IF(COUNTA(_xlfn._xlws.FILTER('TERadj'!D2:D100, ('TERadj'!D2:D100>0)*('TERadj'!D2:D100="Germany")))=0, 0, COUNTA(_xlfn._xlws.FILTER('TERadj'!D2:D100, ('TERadj'!D2:D100>0)*('TERadj'!D2:D100="Germany"))))} -> 0
B10: Hong Kong | C10: {=IF(COUNTA(_xlfn._xlws.FILTER('TERadj'!D2:D100, ('TERadj'!D2:D100>0)*('TERadj'!D2:D100="Hong Kong")))=0, 0, COUNTA(_xlfn._xlws.FILTER('TERadj'!D2:D100, ('TERadj'!D2:D100>0)*('TERadj'!D2:D100="Hong Kong"))))} -> 0 | E10: Hong Kong | F10: {=IF(COUNTA(_xlfn._xlws.FILTER('TERadj'!D2:D100, ('TERadj'!D2:D100>0)*('TERadj'!D2:D100="Hong Kong")))=0, 0, COUNTA(_xlfn._xlws.FILTER('TERadj'!D2:D100, ('TERadj'!D2:D100>0)*('TERadj'!D2:D100="Hong Kong"))))} -> 0
B11: Ireland | C11: {=IF(COUNTA(_xlfn._xlws.FILTER('TERadj'!D2:D100, ('TERadj'!D2:D100>0)*('TERadj'!D2:D100="Ireland")))=0, 0, COUNTA(_xlfn._xlws.FILTER('TERadj'!D2:D100, ('TERadj'!D2:D100>0)*('TERadj'!D2:D100="Ireland"))))} -> 0 | E11: Ireland | F11: {=IF(COUNTA(_xlfn._xlws.FILTER('TERadj'!D2:D100, ('TERadj'!D2:D100>0)*('TERadj'!D2:D100="Ireland")))=0, 0, COUNTA(_xlfn._xlws.FILTER('TERadj'!D2:D100, ('TERadj'!D2:D100>0)*('TERadj'!D2:D100="Ireland"))))} -> 0
B12: Japan | C12: {=IF(COUNTA(_xlfn._xlws.FILTER('TERadj'!D2:D100, ('TERadj'!D2:D100>0)*('TERadj'!D2:D100="Japan")))=0, 0, COUNTA(_xlfn._xlws.FILTER('TERadj'!D2:D100, ('TERadj'!D2:D100>0)*('TERadj'!D2:D100="Japan"))))} -> 0 | E12: Japan | F12: {=IF(COUNTA(_xlfn._xlws.FILTER('TERadj'!D2:D100, ('TERadj'!D2:D100>0)*('TERadj'!D2:D100="Japan")))=0, 0, COUNTA(_xlfn._xlws.FILTER('TERadj'!D2:D100, ('TERadj'!D2:D100>0)*('TERadj'!D2:D100="Japan"))))} -> 0
B13: Korea, Republic Of | C13: {=IF(COUNTA(_xlfn._xlws.FILTER('TERadj'!D2:D100, ('TERadj'!D2:D100>0)*('TERadj'!D2:D100="Korea, Republic Of")))=0, 0, COUNTA(_xlfn._xlws.FILTER('TERadj'!D2:D100, ('TERadj'!D2:D100>0)*('TERadj'!D2:D100="Korea, Republic Of"))))} -> 0 | E13: Korea, Republic Of | F13: {=IF(COUNTA(_xlfn._xlws.FILTER('TERadj'!D2:D100, ('TERadj'!D2:D100>0)*('TERadj'!D2:D100="Korea, Republic Of")))=0, 0, COUNTA(_xlfn._xlws.FILTER('TERadj'!D2:D100, ('TERadj'!D2:D100>0)*('TERadj'!D2:D100="Korea, Republic Of"))))} -> 0
B14: Luxembourg | C14: {=IF(COUNTA(_xlfn._xlws.FILTER('TERadj'!D2:D100, ('TERadj'!D2:D100>0)*('TERadj'!D2:D100="Luxembourg")))=0, 0, COUNTA(_xlfn._xlws.FILTER('TERadj'!D2:D100, ('TERadj'!D2:D100>0)*('TERadj'!D2:D100="Luxembourg"))))} -> 0 | E14: Luxembourg | F14: {=IF(COUNTA(_xlfn._xlws.FILTER('TERadj'!D2:D100, ('TERadj'!D2:D100>0)*('TERadj'!D2:D100="Luxembourg")))=0, 0, COUNTA(_xlfn._xlws.FILTER('TERadj'!D2:D100, ('TERadj'!D2:D100>0)*('TERadj'!D2:D100="Luxembourg"))))} -> 0
B15: Netherlands | C15: {=IF(COUNTA(_xlfn._xlws.FILTER('TERadj'!D2:D100, ('TERadj'!D2:D100>0)*('TERadj'!D2:D100="Netherlands")))=0, 0, COUNTA(_xlfn._xlws.FILTER('TERadj'!D2:D100, ('TERadj'!D2:D100>0)*('TERadj'!D2:D100="Netherlands"))))} -> 0 | E15: Netherlands | F15: {=IF(COUNTA(_xlfn._xlws.FILTER('TERadj'!D2:D100, ('TERadj'!D2:D100>0)*('TERadj'!D2:D100="Netherlands")))=0, 0, COUNTA(_xlfn._xlws.FILTER('TERadj'!D2:D100, ('TERadj'!D2:D100>0)*('TERadj'!D2:D100="Netherlands"))))} -> 0
B16: Norway | C16: {=IF(COUNTA(_xlfn._xlws.FILTER('TERadj'!D2:D100, ('TERadj'!D2:D100>0)*('TERadj'!D2:D100="Norway")))=0, 0, COUNTA(_xlfn._xlws.FILTER('TERadj'!D2:D100, ('TERadj'!D2:D100>0)*('TERadj'!D2:D100="Norway"))))} -> 0 | E16: Norway | F16: {=IF(COUNTA(_xlfn._xlws.FILTER('TERadj'!D2:D100, ('TERadj'!D2:D100>0)*('TERadj'!D2:D100="Norway")))=0, 0, COUNTA(_xlfn._xlws.FILTER('TERadj'!D2:D100, ('TERadj'!D2:D100>0)*('TERadj'!D2:D100="Norway"))))} -> 0
B17: Portugal | C17: {=IF(COUNTA(_xlfn._xlws.FILTER('TERadj'!D2:D100, ('TERadj'!D2:D100>0)*('TERadj'!D2:D100="Portugal")))=0, 0, COUNTA(_xlfn._xlws.FILTER('TERadj'!D2:D100, ('TERadj'!D2:D100>0)*('TERadj'!D2:D100="Portugal"))))} -> 0 | E17: Portugal | F17: {=IF(COUNTA(_xlfn._xlws.FILTER('TERadj'!D2:D100, ('TERadj'!D2:D100>0)*('TERadj'!D2:D100="Portugal")))=0, 0, COUNTA(_xlfn._xlws.FILTER('TERadj'!D2:D100, ('TERadj'!D2:D100>0)*('TERadj'!D2:D100="Portugal"))))} -> 0
B18: Singapore | C18: {=IF(COUNTA(_xlfn._xlws.FILTER('TERadj'!D2:D100, ('TERadj'!D2:D100>0)*('TERadj'!D2:D100="Singapore")))=0, 0, COUNTA(_xlfn._xlws.FILTER('TERadj'!D2:D100, ('TERadj'!D2:D100>0)*('TERadj'!D2:D100="Singapore"))))} -> 0 | E18: Singapore | F18: {=IF(COUNTA(_xlfn._xlws.FILTER('TERadj'!D2:D100, ('TERadj'!D2:D100>0)*('TERadj'!D2:D100="Singapore")))=0, 0, COUNTA(_xlfn._xlws.FILTER('TERadj'!D2:D100, ('TERadj'!D2:D100>0)*('TERadj'!D2:D100="Singapore"))))} -> 0
B19: Spain | C19: {=IF(COUNTA(_xlfn._xlws.FILTER('TERadj'!D2:D100, ('TERadj'!D2:D100>0)*('TERadj'!D2:D100="Spain")))=0, 0, COUNTA(_xlfn._xlws.FILTER('TERadj'!D2:D100, ('TERadj'!D2:D100>0)*('TERadj'!D2:D100="Spain"))))} -> 0 | E19: Spain | F19: {=IF(COUNTA(_xlfn._xlws.FILTER('TERadj'!D2:D100, ('TERadj'!D2:D100>0)*('TERadj'!D2:D100="Spain")))=0, 0, COUNTA(_xlfn._xlws.FILTER('TERadj'!D2:D100, ('TERadj'!D2:D100>0)*('TERadj'!D2:D100="Spain"))))} -> 0
B20: Sweden | C20: {=IF(COUNTA(_xlfn._xlws.FILTER('TERadj'!D2:D100, ('TERadj'!D2:D100>0)*('TERadj'!D2:D100="Sweden")))=0, 0, COUNTA(_xlfn._xlws.FILTER('TERadj'!D2:D100, ('TERadj'!D2:D100>0)*('TERadj'!D2:D100="Sweden"))))} -> 0 | E20: Sweden | F20: {=IF(COUNTA(_xlfn._xlws.FILTER('TERadj'!D2:D100, ('TERadj'!D2:D100>0)*('TERadj'!D2:D100="Sweden")))=0, 0, COUNTA(_xlfn._xlws.FILTER('TERadj'!D2:D100, ('TERadj'!D2:D100>0)*('TERadj'!D2:D100="Sweden"))))} -> 0
B21: Switzerland | C21: {=IF(COUNTA(_xlfn._xlws.FILTER('TERadj'!D2:D100, ('TERadj'!D2:D100>0)*('TERadj'!D2:D100="Switzerland")))=0, 0, COUNTA(_xlfn._xlws.FILTER('TERadj'!D2:D100, ('TERadj'!D2:D100>0)*('TERadj'!D2:D100="Switzerland"))))} -> 0 | E21: Switzerland | F21: {=IF(COUNTA(_xlfn._xlws.FILTER('TERadj'!D2:D100, ('TERadj'!D2:D100>0)*('TERadj'!D2:D100="Switzerland")))=0, 0, COUNTA(_xlfn._xlws.FILTER('TERadj'!D2:D100, ('TERadj'!D2:D100>0)*('TERadj'!D2:D100="Switzerland"))))} -> 0
B22: United Kingdom | C22: {=IF(COUNTA(_xlfn._xlws.FILTER('TERadj'!D2:D100, ('TERadj'!D2:D100>0)*('TERadj'!D2:D100="United Kingdom")))=0, 0, COUNTA(_xlfn._xlws.FILTER('TERadj'!D2:D100, ('TERadj'!D2:D100>0)*('TERadj'!D2:D100="United Kingdom"))))} -> 0 | E22: United Kingdom | F22: {=IF(COUNTA(_xlfn._xlws.FILTER('TERadj'!D2:D100, ('TERadj'!D2:D100>0)*('TERadj'!D2:D100="United Kingdom")))=0, 0, COUNTA(_xlfn._xlws.FILTER('TERadj'!D2:D100, ('TERadj'!D2:D100>0)*('TERadj'!D2:D100="United Kingdom"))))} -> 0
B23: United States | C23: {=IF(COUNTA(_xlfn._xlws.FILTER('TERadj'!D2:D100, ('TERadj'!D2:D100>0)*('TERadj'!D2:D100="United States")))=0, 0, COUNTA(_xlfn._xlws.FILTER('TERadj'!D2:D100, ('TERadj'!D2:D100>0)*('TERadj'!D2:D100="United States"))))} -> 0 | E23: United States | F23: {=IF(COUNTA(_xlfn._xlws.FILTER('TERadj'!D2:D100, ('TERadj'!D2:D100>0)*('TERadj'!D2:D100="United States")))=0, 0, COUNTA(_xlfn._xlws.FILTER('TERadj'!D2:D100, ('TERadj'!D2:D100>0)*('TERadj'!D2:D100="United States"))))} -> 0
B24: empty | C24: {=IF(COUNTA(_xlfn._xlws.FILTER('TERadj'!D2:D100, ('TERadj'!D2:D100>0)*('TERadj'!D2:D100="empty")))=0, 0, COUNTA(_xlfn._xlws.FILTER('TERadj'!D2:D100, ('TERadj'!D2:D100>0)*('TERadj'!D2:D100="empty"))))} -> 0 | E24: empty | F24: {=IF(COUNTA(_xlfn._xlws.FILTER('TERadj'!D2:D100, ('TERadj'!D2:D100>0)*('TERadj'!D2:D100="empty")))=0, 0, COUNTA(_xlfn._xlws.FILTER('TERadj'!D2:D100, ('TERadj'!D2:D100>0)*('TERadj'!D2:D100="empty"))))} -> 0
B26: country | C26: Number of respondents
B27: Australia | C27: {=IF(COUNTA(_xlfn._xlws.FILTER('TERadj'!D2:D100, ('TERadj'!D2:D100>0)*('TERadj'!D2:D100="Australia")))=0, 0, COUNTA(_xlfn._xlws.FILTER('TERadj'!D2:D100, ('TERadj'!D2:D100>0)*('TERadj'!D2:D100="Australia"))))} -> 0
B28: Belgium | C28: {=IF(COUNTA(_xlfn._xlws.FILTER('TERadj'!D2:D100, ('TERadj'!D2:D100>0)*('TERadj'!D2:D100="Belgium")))=0, 0, COUNTA(_xlfn._xlws.FILTER('TERadj'!D2:D100, ('TERadj'!D2:D100>0)*('TERadj'!D2:D100="Belgium"))))} -> 0
B29: Bermuda | C29: {=IF(COUNTA(_xlfn._xlws.FILTER('TERadj'!D2:D100, ('TERadj'!D2:D100>0)*('TERadj'!D2:D100="Bermuda")))=0, 0, COUNTA(_xlfn._xlws.FILTER('TERadj'!D2:D100, ('TERadj'!D2:D100>0)*('TERadj'!D2:D100="Bermuda"))))} -> 0
B30: Finland | C30: {=IF(COUNTA(_xlfn._xlws.FILTER('TERadj'!D2:D100, ('TERadj'!D2:D100>0)*('TERadj'!D2:D100="Finland")))=0, 0, COUNTA(_xlfn._xlws.FILTER('TERadj'!D2:D100, ('TERadj'!D2:D100>0)*('TERadj'!D2:D100="Finland"))))} -> 0
B31: France | C31: {=IF(COUNTA(_xlfn._xlws.FILTER('TERadj'!D2:D100, ('TERadj'!D2:D100>0)*('TERadj'!D2:D100="France")))=0, 0, COUNTA(_xlfn._xlws.FILTER('TERadj'!D2:D100, ('TERadj'!D2:D100>0)*('TERadj'!D2:D100="France"))))} -> 0
B32: Germany | C32: {=IF(COUNTA(_xlfn._xlws.FILTER('TERadj'!D2:D100, ('TERadj'!D2:D100>0)*('TERadj'!D2:D100="Germany")))=0, 0, COUNTA(_xlfn._xlws.FILTER('TERadj'!D2:D100, ('TERadj'!D2:D100>0)*('TERadj'!D2:D100="Germany"))))} -> 0
B33: Hong Kong | C33: {=IF(COUNTA(_xlfn._xlws.FILTER('TERadj'!D2:D100, ('TERadj'!D2:D100>0)*('TERadj'!D2:D100="Hong Kong")))=0, 0, COUNTA(_xlfn._xlws.FILTER('TERadj'!D2:D100, ('TERadj'!D2:D100>0)*('TERadj'!D2:D100="Hong Kong"))))} -> 0
B34: Ireland | C34: {=IF(COUNTA(_xlfn._xlws.FILTER('TERadj'!D2:D100, ('TERadj'!D2:D100>0)*('TERadj'!D2:D100="Ireland")))=0, 0, COUNTA(_xlfn._xlws.FILTER('TERadj'!D2:D100, ('TERadj'!D2:D100>0)*('TERadj'!D2:D100="Ireland"))))} -> 0
B35: Japan | C35: {=IF(COUNTA(_xlfn._xlws.FILTER('TERadj'!D2:D100, ('TERadj'!D2:D100>0)*('TERadj'!D2:D100="Japan")))=0, 0, COUNTA(_xlfn._xlws.FILTER('TERadj'!D2:D100, ('TERadj'!D2:D100>0)*('TERadj'!D2:D100="Japan"))))} -> 0
B36: Korea, Republic Of | C36: {=IF(COUNTA(_xlfn._xlws.FILTER('TERadj'!D2:D100, ('TERadj'!D2:D100>0)*('TERadj'!D2:D100="Korea, Republic Of")))=0, 0, COUNTA(_xlfn._xlws.FILTER('TERadj'!D2:D100, ('TERadj'!D2:D100>0)*('TERadj'!D2:D100="Korea, Republic Of"))))} -> 0
B37: Luxembourg | C37: {=IF(COUNTA(_xlfn._xlws.FILTER('TERadj'!D2:D100, ('TERadj'!D2:D100>0)*('TERadj'!D2:D100="Luxembourg")))=0, 0, COUNTA(_xlfn._xlws.FILTER('TERadj'!D2:D100, ('TERadj'!D2:D100>0)*('TERadj'!D2:D100="Luxembourg"))))} -> 0
B38: Netherlands | C38: {=IF(COUNTA(_xlfn._xlws.FILTER('TERadj'!D2:D100, ('TERadj'!D2:D100>0)*('TERadj'!D2:D100="Netherlands")))=0, 0, COUNTA(_xlfn._xlws.FILTER('TERadj'!D2:D100, ('TERadj'!D2:D100>0)*('TERadj'!D2:D100="Netherlands"))))} -> 0
B39: Norway | C39: {=IF(COUNTA(_xlfn._xlws.FILTER('TERadj'!D2:D100, ('TERadj'!D2:D100>0)*('TERadj'!D2:D100="Norway")))=0, 0, COUNTA(_xlfn._xlws.FILTER('TERadj'!D2:D100, ('TERadj'!D2:D100>0)*('TERadj'!D2:D100="Norway"))))} -> 0
B40: Portugal | C40: {=IF(COUNTA(_xlfn._xlws.FILTER('TERadj'!D2:D100, ('TERadj'!D2:D100>0)*('TERadj'!D2:D100="Portugal")))=0, 0, COUNTA(_xlfn._xlws.FILTER('TERadj'!D2:D100, ('TERadj'!D2:D100>0)*('TERadj'!D2:D100="Portugal"))))} -> 0
B41: Singapore | C41: {=IF(COUNTA(_xlfn._xlws.FILTER('TERadj'!D2:D100, ('TERadj'!D2:D100>0)*('TERadj'!D2:D100="Singapore")))=0, 0, COUNTA(_xlfn._xlws.FILTER('TERadj'!D2:D100, ('TERadj'!D2:D100>0)*('TERadj'!D2:D100="Singapore"))))} -> 0
B42: Spain | C42: {=IF(COUNTA(_xlfn._xlws.FILTER('TERadj'!D2:D100, ('TERadj'!D2:D100>0)*('TERadj'!D2:D100="Spain")))=0, 0, COUNTA(_xlfn._xlws.FILTER('TERadj'!D2:D100, ('TERadj'!D2:D100>0)*('TERadj'!D2:D100="Spain"))))} -> 0
B43: Sweden | C43: {=IF(COUNTA(_xlfn._xlws.FILTER('TERadj'!D2:D100, ('TERadj'!D2:D100>0)*('TERadj'!D2:D100="Sweden")))=0, 0, COUNTA(_xlfn._xlws.FILTER('TERadj'!D2:D100, ('TERadj'!D2:D100>0)*('TERadj'!D2:D100="Sweden"))))} -> 0
B44: Switzerland | C44: {=IF(COUNTA(_xlfn._xlws.FILTER('TERadj'!D2:D100, ('TERadj'!D2:D100>0)*('TERadj'!D2:D100="Switzerland")))=0, 0, COUNTA(_xlfn._xlws.FILTER('TERadj'!D2:D100, ('TERadj'!D2:D100>0)*('TERadj'!D2:D100="Switzerland"))))} -> 0
B45: United Kingdom | C45: {=IF(COUNTA(_xlfn._xlws.FILTER('TERadj'!D2:D100, ('TERadj'!D2:D100>0)*('TERadj'!D2:D100="United Kingdom")))=0, 0, COUNTA(_xlfn._xlws.FILTER('TERadj'!D2:D100, ('TERadj'!D2:D100>0)*('TERadj'!D2:D100="United Kingdom"))))} -> 0
B46: United States | C46: {=IF(COUNTA(_xlfn._xlws.FILTER('TERadj'!D2:D100, ('TERadj'!D2:D100>0)*('TERadj'!D2:D100="United States")))=0, 0, COUNTA(_xlfn._xlws.FILTER('TERadj'!D2:D100, ('TERadj'!D2:D100>0)*('TERadj'!D2:D100="United States"))))} -> 0
B47: empty | C47: {=IF(COUNTA(_xlfn._xlws.FILTER('TERadj'!D2:D100, ('TERadj'!D2:D100>0)*('TERadj'!D2:D100="empty")))=0, 0, COUNTA(_xlfn._xlws.FILTER('TERadj'!D2:D100, ('TERadj'!D2:D100>0)*('TERadj'!D2:D100="empty"))))} -> 0

Sheet KeyFig (3)
A1: Total equity raised by regional strategy and fund manager domicile
B3: strategy | C3: Asia Pacific | D3: Europe | E3: North America | F3: South America | G3: Africa | I3: strategy | J3: Asia Pacific Sample | K3: Europe Sample | L3: North America Sample | M3: South America Sample | N3: Africa Sample
B4: Asia Pacific strategy | C4: =IF(SUMIFS('TERadj'!G2:G100,'TERadj'!G2:G100,">0",'TERadj'!C2:C100,"Asia Pacific")/1000,SUMIFS('TERadj'!G2:G100,'TERadj'!G2:G100,">0",'TERadj'!C2:C100,"Asia Pacific")/1000,"") -> 0 | D4: =IF(SUMIFS('TERadj'!G2:G100,'TERadj'!G2:G100,">0",'TERadj'!C2:C100,"Europe")/1000,SUMIFS('TERadj'!G2:G100,'TERadj'!G2:G100,">0",'TERadj'!C2:C100,"Europe")/1000,"") -> 0 | E4: =IF(SUMIFS('TERadj'!G2:G100,'TERadj'!G2:G100,">0",'TERadj'!C2:C100,"North America")/1000,SUMIFS('TERadj'!G2:G100,'TERadj'!G2:G100,">0",'TERadj'!C2:C100,"North America")/1000,"") -> 0 | F4: =IF(SUMIFS('TERadj'!G2:G100,'TERadj'!G2:G100,">0",'TERadj'!C2:C100,"South America")/1000,SUMIFS('TERadj'!G2:G100,'TERadj'!G2:G100,">0",'TERadj'!C2:C100,"South America")/1000,"") -> 0 | G4: =IF(SUMIFS('TERadj'!G2:G100,'TERadj'!G2:G100,">0",'TERadj'!C2:C100,"Africa")/1000,SUMIFS('TERadj'!G2:G100,'TERadj'!G2:G100,">0",'TERadj'!C2:C100,"Africa")/1000,"") -> 0 | I4: Asia Pacific strategy | J4: {=IF(COUNT(_xlfn._xlws.FILTER('TERadj'!G2:G100, ('TERadj'!G2:G100>0)*('TERadj'!C2:C100="Asia Pacific"))),COUNT(_xlfn._xlws.FILTER('TERadj'!G2:G100, ('TERadj'!G2:G100>0)*('TERadj'!C2:C100="Asia Pacific"))),"")} -> 0 | K4: {=IF(COUNT(_xlfn._xlws.FILTER('TERadj'!G2:G100, ('TERadj'!G2:G100>0)*('TERadj'!C2:C100="Europe"))),COUNT(_xlfn._xlws.FILTER('TERadj'!G2:G100, ('TERadj'!G2:G100>0)*('TERadj'!C2:C100="Europe"))),"")} -> 0 | L4: {=IF(COUNT(_xlfn._xlws.FILTER('TERadj'!G2:G100, ('TERadj'!G2:G100>0)*('TERadj'!C2:C100="North America"))),COUNT(_xlfn._xlws.FILTER('TERadj'!G2:G100, ('TERadj'!G2:G100>0)*('TERadj'!C2:C100="North America"))),"")} -> 0 | M4: {=IF(COUNT(_xlfn._xlws.FILTER('TERadj'!G2:G100, ('TERadj'!G2:G100>0)*('TERadj'!C2:C100="South America"))),COUNT(_xlfn._xlws.FILTER('TERadj'!G2:G100, ('TERadj'!G2:G100>0)*('TERadj'!C2:C100="South America"))),"")} -> 0 | N4: {=IF(COUNT(_xlfn._xlws.FILTER('TERadj'!G2:G100, ('TERadj'!G2:G100>0)*('TERadj'!C2:C100="Africa"))),COUNT(_xlfn._xlws.FILTER('TERadj'!G2:G100, ('TERadj'!G2:G100>0)*('TERadj'!C2:C100="Africa"))),"")} -> 0
B5: European strategy | C5: =IF(SUMIFS('TERadj'!H2:H100,'TERadj'!H2:H100,">0",'TERadj'!C2:C100,"Asia Pacific")/1000,SUMIFS('TERadj'!H2:H100,'TERadj'!H2:H100,">0",'TERadj'!C2:C100,"Asia Pacific")/1000,"") -> 0 | D5: =IF(SUMIFS('TERadj'!H2:H100,'TERadj'!H2:H100,">0",'TERadj'!C2:C100,"Europe")/1000,SUMIFS('TERadj'!H2:H100,'TERadj'!H2:H100,">0",'TERadj'!C2:C100,"Europe")/1000,"") -> 0 | E5: =IF(SUMIFS('TERadj'!H2:H100,'TERadj'!H2:H100,">0",'TERadj'!C2:C100,"North America")/1000,SUMIFS('TERadj'!H2:H100,'TERadj'!H2:H100,">0",'TERadj'!C2:C100,"North America")/1000,"") -> 0 | F5: =IF(SUMIFS('TERadj'!H2:H100,'TERadj'!H2:H100,">0",'TERadj'!C2:C100,"South America")/1000,SUMIFS('TERadj'!H2:H100,'TERadj'!H2:H100,">0",'TERadj'!C2:C100,"South America")/1000,"") -> 0 | G5: =IF(SUMIFS('TERadj'!H2:H100,'TERadj'!H2:H100,">0",'TERadj'!C2:C100,"Africa")/1000,SUMIFS('TERadj'!H2:H100,'TERadj'!H2:H100,">0",'TERadj'!C2:C100,"Africa")/1000,"") -> 0 | I5: European strategy | J5: {=IF(COUNT(_xlfn._xlws.FILTER('TERadj'!H2:H100, ('TERadj'!H2:H100>0)*('TERadj'!C2:C100="Asia Pacific"))),COUNT(_xlfn._xlws.FILTER('TERadj'!H2:H100, ('TERadj'!H2:H100>0)*('TERadj'!C2:C100="Asia Pacific"))),"")} -> 0 | K5: {=IF(COUNT(_xlfn._xlws.FILTER('TERadj'!H2:H100, ('TERadj'!H2:H100>0)*('TERadj'!C2:C100="Europe"))),COUNT(_xlfn._xlws.FILTER('TERadj'!H2:H100, ('TERadj'!H2:H100>0)*('TERadj'!C2:C100="Europe"))),"")} -> 0 | L5: {=IF(COUNT(_xlfn._xlws.FILTER('TERadj'!H2:H100, ('TERadj'!H2:H100>0)*('TERadj'!C2:C100="North America"))),COUNT(_xlfn._xlws.FILTER('TERadj'!H2:H100, ('TERadj'!H2:H100>0)*('TERadj'!C2:C100="North America"))),"")} -> 0 | M5: {=IF(COUNT(_xlfn._xlws.FILTER('TERadj'!H2:H100, ('TERadj'!H2:H100>0)*('TERadj'!C2:C100="South America"))),COUNT(_xlfn._xlws.FILTER('TERadj'!H2:H100, ('TERadj'!H2:H100>0)*('TERadj'!C2:C100="South America"))),"")} -> 0 | N5: {=IF(COUNT(_xlfn._xlws.FILTER('TERadj'!H2:H100, ('TERadj'!H2:H100>0)*('TERadj'!C2:C100="Africa"))),COUNT(_xlfn._xlws.FILTER('TERadj'!H2:H100, ('TERadj'!H2:H100>0)*('TERadj'!C2:C100="Africa"))),"")} -> 0
B6: North American strategy | C6: =IF(SUMIFS('TERadj'!I2:I100,'TERadj'!I2:I100,">0",'TERadj'!C2:C100,"Asia Pacific")/1000,SUMIFS('TERadj'!I2:I100,'TERadj'!I2:I100,">0",'TERadj'!C2:C100,"Asia Pacific")/1000,"") -> 0 | D6: =IF(SUMIFS('TERadj'!I2:I100,'TERadj'!I2:I100,">0",'TERadj'!C2:C100,"Europe")/1000,SUMIFS('TERadj'!I2:I100,'TERadj'!I2:I100,">0",'TERadj'!C2:C100,"Europe")/1000,"") -> 0 | E6: =IF(SUMIFS('TERadj'!I2:I100,'TERadj'!I2:I100,">0",'TERadj'!C2:C100,"North America")/1000,SUMIFS('TERadj'!I2:I100,'TERadj'!I2:I100,">0",'TERadj'!C2:C100,"North America")/1000,"") -> 0 | F6: =IF(SUMIFS('TERadj'!I2:I100,'TERadj'!I2:I100,">0",'TERadj'!C2:C100,"South America")/1000,SUMIFS('TERadj'!I2:I100,'TERadj'!I2:I100,">0",'TERadj'!C2:C100,"South America")/1000,"") -> 0 | G6: =IF(SUMIFS('TERadj'!I2:I100,'TERadj'!I2:I100,">0",'TERadj'!C2:C100,"Africa")/1000,SUMIFS('TERadj'!I2:I100,'TERadj'!I2:I100,">0",'TERadj'!C2:C100,"Africa")/1000,"") -> 0 | I6: North American strategy | J6: {=IF(COUNT(_xlfn._xlws.FILTER('TERadj'!I2:I100, ('TERadj'!I2:I100>0)*('TERadj'!C2:C100="Asia Pacific"))),COUNT(_xlfn._xlws.FILTER('TERadj'!I2:I100, ('TERadj'!I2:I100>0)*('TERadj'!C2:C100="Asia Pacific"))),"")} -> 0 | K6: {=IF(COUNT(_xlfn._xlws.FILTER('TERadj'!I2:I100, ('TERadj'!I2:I100>0)*('TERadj'!C2:C100="Europe"))),COUNT(_xlfn._xlws.FILTER('TERadj'!I2:I100, ('TERadj'!I2:I100>0)*('TERadj'!C2:C100="Europe"))),"")} -> 0 | L6: {=IF(COUNT(_xlfn._xlws.FILTER('TERadj'!I2:I100, ('TERadj'!I2:I100>0)*('TERadj'!C2:C100="North America"))),COUNT(_xlfn._xlws.FILTER('TERadj'!I2:I100, ('TERadj'!I2:I100>0)*('TERadj'!C2:C100="North America"))),"")} -> 0 | M6: {=IF(COUNT(_xlfn._xlws.FILTER('TERadj'!I2:I100, ('TERadj'!I2:I100>0)*('TERadj'!C2:C100="South America"))),COUNT(_xlfn._xlws.FILTER('TERadj'!I2:I100, ('TERadj'!I2:I100>0)*('TERadj'!C2:C100="South America"))),"")} -> 0 | N6: {=IF(COUNT(_xlfn._xlws.FILTER('TERadj'!I2:I100, ('TERadj'!I2:I100>0)*('TERadj'!C2:C100="Africa"))),COUNT(_xlfn._xlws.FILTER('TERadj'!I2:I100, ('TERadj'!I2:I100>0)*('TERadj'!C2:C100="Africa"))),"")} -> 0
B7: Global strategy | C7: =IF(SUMIFS('TERadj'!J2:J100,'TERadj'!J2:J100,">0",'TERadj'!C2:C100,"Asia Pacific")/1000,SUMIFS('TERadj'!J2:J100,'TERadj'!J2:J100,">0",'TERadj'!C2:C100,"Asia Pacific")/1000,"") -> 0 | D7: =IF(SUMIFS('TERadj'!J2:J100,'TERadj'!J2:J100,">0",'TERadj'!C2:C100,"Europe")/1000,SUMIFS('TERadj'!J2:J100,'TERadj'!J2:J100,">0",'TERadj'!C2:C100,"Europe")/1000,"") -> 0 | E7: =IF(SUMIFS('TERadj'!J2:J100,'TERadj'!J2:J100,">0",'TERadj'!C2:C100,"North America")/1000,SUMIFS('TERadj'!J2:J100,'TERadj'!J2:J100,">0",'TERadj'!C2:C100,"North America")/1000,"") -> 0 | F7: =IF(SUMIFS('TERadj'!J2:J100,'TERadj'!J2:J100,">0",'TERadj'!C2:C100,"South America")/1000,SUMIFS('TERadj'!J2:J100,'TERadj'!J2:J100,">0",'TERadj'!C2:C100,"South America")/1000,"") -> 0 | G7: =IF(SUMIFS('TERadj'!J2:J100,'TERadj'!J2:J100,">0",'TERadj'!C2:C100,"Africa")/1000,SUMIFS('TERadj'!J2:J100,'TERadj'!J2:J100,">0",'TERadj'!C2:C100,"Africa")/1000,"") -> 0 | I7: Global strategy | J7: {=IF(COUNT(_xlfn._xlws.FILTER('TERadj'!J2:J100, ('TERadj'!J2:J100>0)*('TERadj'!C2:C100="Asia Pacific"))),COUNT(_xlfn._xlws.FILTER('TERadj'!J2:J100, ('TERadj'!J2:J100>0)*('TERadj'!C2:C100="Asia Pacific"))),"")} -> 0 | K7: {=IF(COUNT(_xlfn._xlws.FILTER('TERadj'!J2:J100, ('TERadj'!J2:J100>0)*('TERadj'!C2:C100="Europe"))),COUNT(_xlfn._xlws.FILTER('TERadj'!J2:J100, ('TERadj'!J2:J100>0)*('TERadj'!C2:C100="Europe"))),"")} -> 0 | L7: {=IF(COUNT(_xlfn._xlws.FILTER('TERadj'!J2:J100, ('TERadj'!J2:J100>0)*('TERadj'!C2:C100="North America"))),COUNT(_xlfn._xlws.FILTER('TERadj'!J2:J100, ('TERadj'!J2:J100>0)*('TERadj'!C2:C100="North America"))),"")} -> 0 | M7: {=IF(COUNT(_xlfn._xlws.FILTER('TERadj'!J2:J100, ('TERadj'!J2:J100>0)*('TERadj'!C2:C100="South America"))),COUNT(_xlfn._xlws.FILTER('TERadj'!J2:J100, ('TERadj'!J2:J100>0)*('TERadj'!C2:C100="South America"))),"")} -> 0 | N7: {=IF(COUNT(_xlfn._xlws.FILTER('TERadj'!J2:J100, ('TERadj'!J2:J100>0)*('TERadj'!C2:C100="Africa"))),COUNT(_xlfn._xlws.FILTER('TERadj'!J2:J100, ('TERadj'!J2:J100>0)*('TERadj'!C2:C100="Africa"))),"")} -> 0
B8: South American strategy | C8: =IF(SUMIFS('TERadj'!K2:K100,'TERadj'!K2:K100,">0",'TERadj'!C2:C100,"Asia Pacific")/1000,SUMIFS('TERadj'!K2:K100,'TERadj'!K2:K100,">0",'TERadj'!C2:C100,"Asia Pacific")/1000,"") -> 0 | D8: =IF(SUMIFS('TERadj'!K2:K100,'TERadj'!K2:K100,">0",'TERadj'!C2:C100,"Europe")/1000,SUMIFS('TERadj'!K2:K100,'TERadj'!K2:K100,">0",'TERadj'!C2:C100,"Europe")/1000,"") -> 0 | E8: =IF(SUMIFS('TERadj'!K2:K100,'TERadj'!K2:K100,">0",'TERadj'!C2:C100,"North America")/1000,SUMIFS('TERadj'!K2:K100,'TERadj'!K2:K100,">0",'TERadj'!C2:C100,"North America")/1000,"") -> 0 | F8: =IF(SUMIFS('TERadj'!K2:K100,'TERadj'!K2:K100,">0",'TERadj'!C2:C100,"South America")/1000,SUMIFS('TERadj'!K2:K100,'TERadj'!K2:K100,">0",'TERadj'!C2:C100,"South America")/1000,"") -> 0 | G8: =IF(SUMIFS('TERadj'!K2:K100,'TERadj'!K2:K100,">0",'TERadj'!C2:C100,"Africa")/1000,SUMIFS('TERadj'!K2:K100,'TERadj'!K2:K100,">0",'TERadj'!C2:C100,"Africa")/1000,"") -> 0 | I8: South American strategy | J8: {=IF(COUNT(_xlfn._xlws.FILTER('TERadj'!K2:K100, ('TERadj'!K2:K100>0)*('TERadj'!C2:C100="Asia Pacific"))),COUNT(_xlfn._xlws.FILTER('TERadj'!K2:K100, ('TERadj'!K2:K100>0)*('TERadj'!C2:C100="Asia Pacific"))),"")} -> 0 | K8: {=IF(COUNT(_xlfn._xlws.FILTER('TERadj'!K2:K100, ('TERadj'!K2:K100>0)*('TERadj'!C2:C100="Europe"))),COUNT(_xlfn._xlws.FILTER('TERadj'!K2:K100, ('TERadj'!K2:K100>0)*('TERadj'!C2:C100="Europe"))),"")} -> 0 | L8: {=IF(COUNT(_xlfn._xlws.FILTER('TERadj'!K2:K100, ('TERadj'!K2:K100>0)*('TERadj'!C2:C100="North America"))),COUNT(_xlfn._xlws.FILTER('TERadj'!K2:K100, ('TERadj'!K2:K100>0)*('TERadj'!C2:C100="North America"))),"")} -> 0 | M8: {=IF(COUNT(_xlfn._xlws.FILTER('TERadj'!K2:K100, ('TERadj'!K2:K100>0)*('TERadj'!C2:C100="South America"))),COUNT(_xlfn._xlws.FILTER('TERadj'!K2:K100, ('TERadj'!K2:K100>0)*('TERadj'!C2:C100="South America"))),"")} -> 0 | N8: {=IF(COUNT(_xlfn._xlws.FILTER('TERadj'!K2:K100, ('TERadj'!K2:K100>0)*('TERadj'!C2:C100="Africa"))),COUNT(_xlfn._xlws.FILTER('TERadj'!K2:K100, ('TERadj'!K2:K100>0)*('TERadj'!C2:C100="Africa"))),"")} -> 0
B10: strategy | C10: Asia Pacific | D10: Europe | E10: North America | F10: South America | G10: Africa
B11: Asia Pacific strategy | C11: =IF(SUM(J4:J8) > 0, IF(AND(SUM(C4:C8)>0, ISNUMBER(C4)),C4/SUM(C4:C8), ""), "") -> 0 | D11: =IF(SUM(J4:J8) > 0, IF(AND(SUM(D4:D8)>0, ISNUMBER(D4)),D4/SUM(D4:D8), ""), "") -> 0 | E11: =IF(SUM(J4:J8) > 0, IF(AND(SUM(E4:E8)>0, ISNUMBER(E4)),E4/SUM(E4:E8), ""), "") -> 0 | F11: =IF(SUM(J4:J8) > 0, IF(AND(SUM(F4:F8)>0, ISNUMBER(F4)),F4/SUM(F4:F8), ""), "") -> 0 | G11: =IF(SUM(J4:J8) > 0, IF(AND(SUM(G4:G8)>0, ISNUMBER(G4)),G4/SUM(G4:G8), ""), "") -> 0
B12: European strategy | C12: =IF(SUM(J4:J8) > 0, IF(AND(SUM(C4:C8)>0, ISNUMBER(C5)),C5/SUM(C4:C8), ""), "") -> 0 | D12: =IF(SUM(J4:J8) > 0, IF(AND(SUM(D4:D8)>0, ISNUMBER(D5)),D5/SUM(D4:D8), ""), "") -> 0 | E12: =IF(SUM(J4:J8) > 0, IF(AND(SUM(E4:E8)>0, ISNUMBER(E5)),E5/SUM(E4:E8), ""), "") -> 0 | F12: =IF(SUM(J4:J8) > 0, IF(AND(SUM(F4:F8)>0, ISNUMBER(F5)),F5/SUM(F4:F8), ""), "") -> 0 | G12: =IF(SUM(J4:J8) > 0, IF(AND(SUM(G4:G8)>0, ISNUMBER(G5)),G5/SUM(G4:G8), ""), "") -> 0
B13: North American strategy | C13: =IF(SUM(J4:J8) > 0, IF(AND(SUM(C4:C8)>0, ISNUMBER(C6)),C6/SUM(C4:C8), ""), "") -> 0 | D13: =IF(SUM(J4:J8) > 0, IF(AND(SUM(D4:D8)>0, ISNUMBER(D6)),D6/SUM(D4:D8), ""), "") -> 0 | E13: =IF(SUM(J4:J8) > 0, IF(AND(SUM(E4:E8)>0, ISNUMBER(E6)),E6/SUM(E4:E8), ""), "") -> 0 | F13: =IF(SUM(J4:J8) > 0, IF(AND(SUM(F4:F8)>0, ISNUMBER(F6)),F6/SUM(F4:F8), ""), "") -> 0 | G13: =IF(SUM(J4:J8) > 0, IF(AND(SUM(G4:G8)>0, ISNUMBER(G6)),G6/SUM(G4:G8), ""), "") -> 0
B14: Global strategy | C14: =IF(SUM(J4:J8) > 0, IF(AND(SUM(C4:C8)>0, ISNUMBER(C7)),C7/SUM(C4:C8), ""), "") -> 0 | D14: =IF(SUM(J4:J8) > 0, IF(AND(SUM(D4:D8)>0, ISNUMBER(D7)),D7/SUM(D4:D8), ""), "") -> 0 | E14: =IF(SUM(J4:J8) > 0, IF(AND(SUM(E4:E8)>0, ISNUMBER(E7)),E7/SUM(E4:E8), ""), "") -> 0 | F14: =IF(SUM(J4:J8) > 0, IF(AND(SUM(F4:F8)>0, ISNUMBER(F7)),F7/SUM(F4:F8), ""), "") -> 0 | G14: =IF(SUM(J4:J8) > 0, IF(AND(SUM(G4:G8)>0, ISNUMBER(G7)),G7/SUM(G4:G8), ""), "") -> 0
B15: South American strategy | C15: =IF(SUM(J4:J8) > 0, IF(AND(SUM(C4:C8)>0, ISNUMBER(C8)),C8/SUM(C4:C8), ""), "") -> 0 | D15: =IF(SUM(J4:J8) > 0, IF(AND(SUM(D4:D8)>0, ISNUMBER(D8)),D8/SUM(D4:D8), ""), "") -> 0 | E15: =IF(SUM(J4:J8) > 0, IF(AND(SUM(E4:E8)>0, ISNUMBER(E8)),E8/SUM(E4:E8), ""), "") -> 0 | F15: =IF(SUM(J4:J8) > 0, IF(AND(SUM(F4:F8)>0, ISNUMBER(F8)),F8/SUM(F4:F8), ""), "") -> 0 | G15: =IF(SUM(J4:J8) > 0, IF(AND(SUM(G4:G8)>0, ISNUMBER(G8)),G8/SUM(G4:G8), ""), "") -> 0

Sheet KeyFig (4)
A1: Total equity raised (US$ billion)
B3: Year | C3: €/$ billion | E3: Year | F3: €/$ billion
B4: 2015 | C4: 123.45327 | E4: 2015 | F4: 123.45327
B5: 2016 | C5: 121.83674 | E5: 2016 | F5: 121.83674
B6: 2017 | C6: 139.92458 | E6: 2017 | F6: 139.92458
B7: 2018 | C7: 158.35784 | E7: 2018 | F7: 158.35784
B8: 2019 | C8: 196.53999 | E8: 2019 | F8: 196.53999
B9: 2020 | C9: 122.90413 | E9: 2020 | F9: 122.90413
B10: 2021 | C10: 253.76632 | E10: 2021 | F10: 253.76632
B11: 2022 | C11: 246.26624 | E11: 2022 | F11: 246.26624
B12: 2023 | C12: 117.20258 | E12: 2023 | F12: 117.20258
B13: 2024 | C13: =IF(SUMIFS('TERadj'!M2:M100,'TERadj'!M2:M100,">0"),SUMIFS('TERadj'!M2:M100,'TERadj'!M2:M100,">0"),"") -> 0 | E13: 2024 | F13: =IF(SUMIFS('TERadj'!M2:M100,'TERadj'!M2:M100,">0"),SUMIFS('TERadj'!M2:M100,'TERadj'!M2:M100,">0"),"") -> 0
B15: Year | C15: €/$ billion
B16: 2015 | C16: =C4 -> 0
B17: 2016 | C17: =C5 -> 0
B18: 2017 | C18: =C6 -> 0
B19: 2018 | C19: =C7 -> 0
B20: 2019 | C20: =C8 -> 0
B21: 2020 | C21: =C9 -> 0
B22: 2021 | C22: =C10 -> 0
B23: 2022 | C23: =C11 -> 0
B24: 2023 | C24: =C12 -> 0
B25: 2024 | C25: =C13 -> 0

Sheet KeyFig (5)
A1: Equity raised by vehicle type by value
B3: Domicile | C3: 2023 | D3: 2024 | F3: Domicile | G3: 2023 | H3: 2024
B4: Non-listed/commingled real estate funds/private REITs | C4: 26.807484 | D4: =IF(SUMIFS('TERadj'!N2:N100,'TERadj'!N2:N100,">0")/1000,SUMIFS('TERadj'!N2:N100,'TERadj'!N2:N100,">0")/1000,"") -> 0 | F4: Non-listed/commingled real estate funds/private REITs | G4: 26.807484 | H4: =IF(SUMIFS('TERadj'!N2:N100,'TERadj'!N2:N100,">0")/1000,SUMIFS('TERadj'!N2:N100,'TERadj'!N2:N100,">0")/1000,"") -> 0
B5: Separate accounts investing directly into real estate | C5: 12.595026 | D5: =IF(SUMIFS('TERadj'!O2:O100,'TERadj'!O2:O100,">0")/1000,SUMIFS('TERadj'!O2:O100,'TERadj'!O2:O100,">0")/1000,"") -> 0 | F5: Separate accounts investing directly into real estate | G5: 12.595026 | H5: =IF(SUMIFS('TERadj'!O2:O100,'TERadj'!O2:O100,">0")/1000,SUMIFS('TERadj'!O2:O100,'TERadj'!O2:O100,">0")/1000,"") -> 0
B6: Separate accounts investing into indirect vehicles | C6: 2.9165197 | D6: =IF(SUMIFS('TERadj'!P2:P100,'TERadj'!P2:P100,">0")/1000,SUMIFS('TERadj'!P2:P100,'TERadj'!P2:P100,">0")/1000,"") -> 0 | F6: Separate accounts investing into indirect vehicles | G6: 2.9165197 | H6: =IF(SUMIFS('TERadj'!P2:P100,'TERadj'!P2:P100,">0")/1000,SUMIFS('TERadj'!P2:P100,'TERadj'!P2:P100,">0")/1000,"") -> 0
B7: Joint ventures and club deals | C7: 9.1558683 | D7: =IF(SUMIFS('TERadj'!Q2:Q100,'TERadj'!Q2:Q100,">0")/1000,SUMIFS('TERadj'!Q2:Q100,'TERadj'!Q2:Q100,">0")/1000,"") -> 0 | F7: Joint ventures and club deals | G7: 9.1558683 | H7: =IF(SUMIFS('TERadj'!Q2:Q100,'TERadj'!Q2:Q100,">0")/1000,SUMIFS('TERadj'!Q2:Q100,'TERadj'!Q2:Q100,">0")/1000,"") -> 0
B8: Multi Managers | C8: 1.33433 | D8: =IF(SUMIFS('TERadj'!R2:R100,'TERadj'!R2:R100,">0")/1000,SUMIFS('TERadj'!R2:R100,'TERadj'!R2:R100,">0")/1000,"") -> 0 | F8: Multi Managers | G8: 1.33433 | H8: =IF(SUMIFS('TERadj'!R2:R100,'TERadj'!R2:R100,">0")/1000,SUMIFS('TERadj'!R2:R100,'TERadj'!R2:R100,">0")/1000,"") -> 0
B9: Non-listed debt products | C9: 16.279826 | D9: =IF(SUMIFS('TERadj'!S2:S100,'TERadj'!S2:S100,">0")/1000,SUMIFS('TERadj'!S2:S100,'TERadj'!S2:S100,">0")/1000,"") -> 0 | F9: Non-listed debt products | G9: 16.279826 | H9: =IF(SUMIFS('TERadj'!S2:S100,'TERadj'!S2:S100,">0")/1000,SUMIFS('TERadj'!S2:S100,'TERadj'!S2:S100,">0")/1000,"") -> 0
B11: Domicile | C11: 2023 | D11: 2024
B12: Non-listed/commingled real estate funds/private REITs | C12: =IF(AND(SUM(C4:C9)>0, ISNUMBER(C4)),C4/SUM(C4:C9), "") -> 0 | D12: =IF(AND(SUM(D4:D9)>0, ISNUMBER(D4)),D4/SUM(D4:D9), "") -> 0
B13: Separate accounts investing directly into real estate | C13: =IF(AND(SUM(C4:C9)>0, ISNUMBER(C5)),C5/SUM(C4:C9), "") -> 0 | D13: =IF(AND(SUM(D4:D9)>0, ISNUMBER(D5)),D5/SUM(D4:D9), "") -> 0
B14: Separate accounts investing into indirect vehicles | C14: =IF(AND(SUM(C4:C9)>0, ISNUMBER(C6)),C6/SUM(C4:C9), "") -> 0 | D14: =IF(AND(SUM(D4:D9)>0, ISNUMBER(D6)),D6/SUM(D4:D9), "") -> 0
B15: Joint ventures and club deals | C15: =IF(AND(SUM(C4:C9)>0, ISNUMBER(C7)),C7/SUM(C4:C9), "") -> 0 | D15: =IF(AND(SUM(D4:D9)>0, ISNUMBER(D7)),D7/SUM(D4:D9), "") -> 0
B16: Multi Managers | C16: =IF(AND(SUM(C4:C9)>0, ISNUMBER(C8)),C8/SUM(C4:C9), "") -> 0 | D16: =IF(AND(SUM(D4:D9)>0, ISNUMBER(D8)),D8/SUM(D4:D9), "") -> 0
B17: Non-listed debt products | C17: =IF(AND(SUM(C4:C9)>0, ISNUMBER(C9)),C9/SUM(C4:C9), "") -> 0 | D17: =IF(AND(SUM(D4:D9)>0, ISNUMBER(D9)),D9/SUM(D4:D9), "") -> 0

Sheet KeyFig (6)
A1: Equity raised by investor domicile
B3: strategy | C3: Asia Pacific | D3: Europe | E3: North America | F3: South America | G3: Africa | I3: strategy | J3: Asia Pacific Sample | K3: Europe Sample | L3: North America Sample | M3: South America Sample | N3: Africa Sample
B4: Non-listed/commingled real estate funds/private REITs | C4: =IF(SUMIFS('TERadj'!T2:T100,'TERadj'!T2:T100,">0")/1000,SUMIFS('TERadj'!T2:T100,'TERadj'!T2:T100,">0")/1000,"") -> 0 | D4: =IF(SUMIFS('TERadj'!U2:U100,'TERadj'!U2:U100,">0")/1000,SUMIFS('TERadj'!U2:U100,'TERadj'!U2:U100,">0")/1000,"") -> 0 | E4: =IF(SUMIFS('TERadj'!V2:V100,'TERadj'!V2:V100,">0")/1000,SUMIFS('TERadj'!V2:V100,'TERadj'!V2:V100,">0")/1000,"") -> 0 | F4: =IF(SUMIFS('TERadj'!W2:W100,'TERadj'!W2:W100,">0")/1000,SUMIFS('TERadj'!W2:W100,'TERadj'!W2:W100,">0")/1000,"") -> 0 | G4: =IF(SUMIFS('TERadj'!X2:X100,'TERadj'!X2:X100,">0")/1000,SUMIFS('TERadj'!X2:X100,'TERadj'!X2:X100,">0")/1000,"") -> 0 | I4: Non-listed/commingled real estate funds/private REITs | J4: {=IF(COUNT(_xlfn._xlws.FILTER('TERadj'!T2:T100, ('TERadj'!T2:T100>0))),COUNT(_xlfn._xlws.FILTER('TERadj'!T2:T100, ('TERadj'!T2:T100>0))),"")} -> 0 | K4: {=IF(COUNT(_xlfn._xlws.FILTER('TERadj'!U2:U100, ('TERadj'!U2:U100>0))),COUNT(_xlfn._xlws.FILTER('TERadj'!U2:U100, ('TERadj'!U2:U100>0))),"")} -> 0 | L4: {=IF(COUNT(_xlfn._xlws.FILTER('TERadj'!V2:V100, ('TERadj'!V2:V100>0))),COUNT(_xlfn._xlws.FILTER('TERadj'!V2:V100, ('TERadj'!V2:V100>0))),"")} -> 0 | M4: {=IF(COUNT(_xlfn._xlws.FILTER('TERadj'!W2:W100, ('TERadj'!W2:W100>0))),COUNT(_xlfn._xlws.FILTER('TERadj'!W2:W100, ('TERadj'!W2:W100>0))),"")} -> 0 | N4: {=IF(COUNT(_xlfn._xlws.FILTER('TERadj'!X2:X100, ('TERadj'!X2:X100>0))),COUNT(_xlfn._xlws.FILTER('TERadj'!X2:X100, ('TERadj'!X2:X100>0))),"")} -> 0
B5: Separate accounts investing directly into real estate | C5: =IF(SUMIFS('TERadj'!Y2:Y100,'TERadj'!Y2:Y100,">0")/1000,SUMIFS('TERadj'!Y2:Y100,'TERadj'!Y2:Y100,">0")/1000,"") -> 0 | D5: =IF(SUMIFS('TERadj'!Z2:Z100,'TERadj'!Z2:Z100,">0")/1000,SUMIFS('TERadj'!Z2:Z100,'TERadj'!Z2:Z100,">0")/1000,"") -> 0 | E5: =IF(SUMIFS('TERadj'!AA2:AA100,'TERadj'!AA2:AA100,">0")/1000,SUMIFS('TERadj'!AA2:AA100,'TERadj'!AA2:AA100,">0")/1000,"") -> 0 | F5: =IF(SUMIFS('TERadj'!AB2:AB100,'TERadj'!AB2:AB100,">0")/1000,SUMIFS('TERadj'!AB2:AB100,'TERadj'!AB2:AB100,">0")/1000,"") -> 0 | G5: =IF(SUMIFS('TERadj'!AC2:AC100,'TERadj'!AC2:AC100,">0")/1000,SUMIFS('TERadj'!AC2:AC100,'TERadj'!AC2:AC100,">0")/1000,"") -> 0 | I5: Separate accounts investing directly into real estate | J5: {=IF(COUNT(_xlfn._xlws.FILTER('TERadj'!Y2:Y100, ('TERadj'!Y2:Y100>0))),COUNT(_xlfn._xlws.FILTER('TERadj'!Y2:Y100, ('TERadj'!Y2:Y100>0))),"")} -> 0 | K5: {=IF(COUNT(_xlfn._xlws.FILTER('TERadj'!Z2:Z100, ('TERadj'!Z2:Z100>0))),COUNT(_xlfn._xlws.FILTER('TERadj'!Z2:Z100, ('TERadj'!Z2:Z100>0))),"")} -> 0 | L5: {=IF(COUNT(_xlfn._xlws.FILTER('TERadj'!AA2:AA100, ('TERadj'!AA2:AA100>0))),COUNT(_xlfn._xlws.FILTER('TERadj'!AA2:AA100, ('TERadj'!AA2:AA100>0))),"")} -> 0 | M5: {=IF(COUNT(_xlfn._xlws.FILTER('TERadj'!AB2:AB100, ('TERadj'!AB2:AB100>0))),COUNT(_xlfn._xlws.FILTER('TERadj'!AB2:AB100, ('TERadj'!AB2:AB100>0))),"")} -> 0 | N5: {=IF(COUNT(_xlfn._xlws.FILTER('TERadj'!AC2:AC100, ('TERadj'!AC2:AC100>0))),COUNT(_xlfn._xlws.FILTER('TERadj'!AC2:AC100, ('TERadj'!AC2:AC100>0))),"")} -> 0
B6: Separate accounts investing into indirect vehicles | C6: =IF(SUMIFS('TERadj'!AD2:AD100,'TERadj'!AD2:AD100,">0")/1000,SUMIFS('TERadj'!AD2:AD100,'TERadj'!AD2:AD100,">0")/1000,"") -> 0 | D6: =IF(SUMIFS('TERadj'!AE2:AE100,'TERadj'!AE2:AE100,">0")/1000,SUMIFS('TERadj'!AE2:AE100,'TERadj'!AE2:AE100,">0")/1000,"") -> 0 | E6: =IF(SUMIFS('TERadj'!AF2:AF100,'TERadj'!AF2:AF100,">0")/1000,SUMIFS('TERadj'!AF2:AF100,'TERadj'!AF2:AF100,">0")/1000,"") -> 0 | F6: =IF(SUMIFS('TERadj'!AG2:AG100,'TERadj'!AG2:AG100,">0")/1000,SUMIFS('TERadj'!AG2:AG100,'TERadj'!AG2:AG100,">0")/1000,"") -> 0 | G6: =IF(SUMIFS('TERadj'!AH2:AH100,'TERadj'!AH2:AH100,">0")/1000,SUMIFS('TERadj'!AH2:AH100,'TERadj'!AH2:AH100,">0")/1000,"") -> 0 | I6: Separate accounts investing into indirect vehicles | J6: {=IF(COUNT(_xlfn._xlws.FILTER('TERadj'!AD2:AD100, ('TERadj'!AD2:AD100>0))),COUNT(_xlfn._xlws.FILTER('TERadj'!AD2:AD100, ('TERadj'!AD2:AD100>0))),"")} -> 0 | K6: {=IF(COUNT(_xlfn._xlws.FILTER('TERadj'!AE2:AE100, ('TERadj'!AE2:AE100>0))),COUNT(_xlfn._xlws.FILTER('TERadj'!AE2:AE100, ('TERadj'!AE2:AE100>0))),"")} -> 0 | L6: {=IF(COUNT(_xlfn._xlws.FILTER('TERadj'!AF2:AF100, ('TERadj'!AF2:AF100>0))),COUNT(_xlfn._xlws.FILTER('TERadj'!AF2:AF100, ('TERadj'!AF2:AF100>0))),"")} -> 0 | M6: {=IF(COUNT(_xlfn._xlws.FILTER('TERadj'!AG2:AG100, ('TERadj'!AG2:AG100>0))),COUNT(_xlfn._xlws.FILTER('TERadj'!AG2:AG100, ('TERadj'!AG2:AG100>0))),"")} -> 0 | N6: {=IF(COUNT(_xlfn._xlws.FILTER('TERadj'!AH2:AH100, ('TERadj'!AH2:AH100>0))),COUNT(_xlfn._xlws.FILTER('TERadj'!AH2:AH100, ('TERadj'!AH2:AH100>0))),"")} -> 0
B7: Joint ventures and club deals | C7: =IF(SUMIFS('TERadj'!AI2:AI100,'TERadj'!AI2:AI100,">0")/1000,SUMIFS('TERadj'!AI2:AI100,'TERadj'!AI2:AI100,">0")/1000,"") -> 0 | D7: =IF(SUMIFS('TERadj'!AJ2:AJ100,'TERadj'!AJ2:AJ100,">0")/1000,SUMIFS('TERadj'!AJ2:AJ100,'TERadj'!AJ2:AJ100,">0")/1000,"") -> 0 | E7: =IF(SUMIFS('TERadj'!AK2:AK100,'TERadj'!AK2:AK100,">0")/1000,SUMIFS('TERadj'!AK2:AK100,'TERadj'!AK2:AK100,">0")/1000,"") -> 0 | F7: =IF(SUMIFS('TERadj'!AL2:AL100,'TERadj'!AL2:AL100,">0")/1000,SUMIFS('TERadj'!AL2:AL100,'TERadj'!AL2:AL100,">0")/1000,"") -> 0 | G7: =IF(SUMIFS('TERadj'!AM2:AM100,'TERadj'!AM2:AM100,">0")/1000,SUMIFS('TERadj'!AM2:AM100,'TERadj'!AM2:AM100,">0")/1000,"") -> 0 | I7: Joint ventures and club deals | J7: {=IF(COUNT(_xlfn._xlws.FILTER('TERadj'!AI2:AI100, ('TERadj'!AI2:AI100>0))),COUNT(_xlfn._xlws.FILTER('TERadj'!AI2:AI100, ('TERadj'!AI2:AI100>0))),"")} -> 0 | K7: {=IF(COUNT(_xlfn._xlws.FILTER('TERadj'!AJ2:AJ100, ('TERadj'!AJ2:AJ100>0))),COUNT(_xlfn._xlws.FILTER('TERadj'!AJ2:AJ100, ('TERadj'!AJ2:AJ100>0))),"")} -> 0 | L7: {=IF(COUNT(_xlfn._xlws.FILTER('TERadj'!AK2:AK100, ('TERadj'!AK2:AK100>0))),COUNT(_xlfn._xlws.FILTER('TERadj'!AK2:AK100, ('TERadj'!AK2:AK100>0))),"")} -> 0 | M7: {=IF(COUNT(_xlfn._xlws.FILTER('TERadj'!AL2:AL100, ('TERadj'!AL2:AL100>0))),COUNT(_xlfn._xlws.FILTER('TERadj'!AL2:AL100, ('TERadj'!AL2:AL100>0))),"")} -> 0 | N7: {=IF(COUNT(_xlfn._xlws.FILTER('TERadj'!AM2:AM100, ('TERadj'!AM2:AM100>0))),COUNT(_xlfn._xlws.FILTER('TERadj'!AM2:AM100, ('TERadj'!AM2:AM100>0))),"")} -> 0
B8: Multi Managers | C8: =IF(SUMIFS('TERadj'!AN2:AN100,'TERadj'!AN2:AN100,">0")/1000,SUMIFS('TERadj'!AN2:AN100,'TERadj'!AN2:AN100,">0")/1000,"") -> 0 | D8: =IF(SUMIFS('TERadj'!AO2:AO100,'TERadj'!AO2:AO100,">0")/1000,SUMIFS('TERadj'!AO2:AO100,'TERadj'!AO2:AO100,">0")/1000,"") -> 0 | E8: =IF(SUMIFS('TERadj'!AP2:AP100,'TERadj'!AP2:AP100,">0")/1000,SUMIFS('TERadj'!AP2:AP100,'TERadj'!AP2:AP100,">0")/1000,"") -> 0 | F8: =IF(SUMIFS('TERadj'!AQ2:AQ100,'TERadj'!AQ2:AQ100,">0")/1000,SUMIFS('TERadj'!AQ2:AQ100,'TERadj'!AQ2:AQ100,">0")/1000,"") -> 0 | G8: =IF(SUMIFS('TERadj'!AR2:AR100,'TERadj'!AR2:AR100,">0")/1000,SUMIFS('TERadj'!AR2:AR100,'TERadj'!AR2:AR100,">0")/1000,"") -> 0 | I8: Multi Managers | J8: {=IF(COUNT(_xlfn._xlws.FILTER('TERadj'!AN2:AN100, ('TERadj'!AN2:AN100>0))),COUNT(_xlfn._xlws.FILTER('TERadj'!AN2:AN100, ('TERadj'!AN2:AN100>0))),"")} -> 0 | K8: {=IF(COUNT(_xlfn._xlws.FILTER('TERadj'!AO2:AO100, ('TERadj'!AO2:AO100>0))),COUNT(_xlfn._xlws.FILTER('TERadj'!AO2:AO100, ('TERadj'!AO2:AO100>0))),"")} -> 0 | L8: {=IF(COUNT(_xlfn._xlws.FILTER('TERadj'!AP2:AP100, ('TERadj'!AP2:AP100>0))),COUNT(_xlfn._xlws.FILTER('TERadj'!AP2:AP100, ('TERadj'!AP2:AP100>0))),"")} -> 0 | M8: {=IF(COUNT(_xlfn._xlws.FILTER('TERadj'!AQ2:AQ100, ('TERadj'!AQ2:AQ100>0))),COUNT(_xlfn._xlws.FILTER('TERadj'!AQ2:AQ100, ('TERadj'!AQ2:AQ100>0))),"")} -> 0 | N8: {=IF(COUNT(_xlfn._xlws.FILTER('TERadj'!AR2:AR100, ('TERadj'!AR2:AR100>0))),COUNT(_xlfn._xlws.FILTER('TERadj'!AR2:AR100, ('TERadj'!AR2:AR100>0))),"")} -> 0
B9: Non-listed debt products | C9: =IF(SUMIFS('TERadj'!AS2:AS100,'TERadj'!AS2:AS100,">0")/1000,SUMIFS('TERadj'!AS2:AS100,'TERadj'!AS2:AS100,">0")/1000,"") -> 0 | D9: =IF(SUMIFS('TERadj'!AT2:AT100,'TERadj'!AT2:AT100,">0")/1000,SUMIFS('TERadj'!AT2:AT100,'TERadj'!AT2:AT100,">0")/1000,"") -> 0 | E9: =IF(SUMIFS('TERadj'!AU2:AU100,'TERadj'!AU2:AU100,">0")/1000,SUMIFS('TERadj'!AU2:AU100,'TERadj'!AU2:AU100,">0")/1000,"") -> 0 | F9: =IF(SUMIFS('TERadj'!AV2:AV100,'TERadj'!AV2:AV100,">0")/1000,SUMIFS('TERadj'!AV2:AV100,'TERadj'!AV2:AV100,">0")/1000,"") -> 0 | G9: =IF(SUMIFS('TERadj'!AW2:AW100,'TERadj'!AW2:AW100,">0")/1000,SUMIFS('TERadj'!AW2:AW100,'TERadj'!AW2:AW100,">0")/1000,"") -> 0 | I9: Non-listed debt products | J9: {=IF(COUNT(_xlfn._xlws.FILTER('TERadj'!AS2:AS100, ('TERadj'!AS2:AS100>0))),COUNT(_xlfn._xlws.FILTER('TERadj'!AS2:AS100, ('TERadj'!AS2:AS100>0))),"")} -> 0 | K9: {=IF(COUNT(_xlfn._xlws.FILTER('TERadj'!AT2:AT100, ('TERadj'!AT2:AT100>0))),COUNT(_xlfn._xlws.FILTER('TERadj'!AT2:AT100, ('TERadj'!AT2:AT100>0))),"")} -> 0 | L9: {=IF(COUNT(_xlfn._xlws.FILTER('TERadj'!AU2:AU100, ('TERadj'!AU2:AU100>0))),COUNT(_xlfn._xlws.FILTER('TERadj'!AU2:AU100, ('TERadj'!AU2:AU100>0))),"")} -> 0 | M9: {=IF(COUNT(_xlfn._xlws.FILTER('TERadj'!AV2:AV100, ('TERadj'!AV2:AV100>0))),COUNT(_xlfn._xlws.FILTER('TERadj'!AV2:AV100, ('TERadj'!AV2:AV100>0))),"")} -> 0 | N9: {=IF(COUNT(_xlfn._xlws.FILTER('TERadj'!AW2:AW100, ('TERadj'!AW2:AW100>0))),COUNT(_xlfn._xlws.FILTER('TERadj'!AW2:AW100, ('TERadj'!AW2:AW100>0))),"")} -> 0
B10: Operating Platforms | I10: Operating Platforms
B12: strategy | C12: Asia Pacific | D12: Europe | E12: North America | F12: South America | G12: Africa
B13: Non-listed/commingled real estate funds/private REITs | C13: =IF(SUM(J4:J10) > 0, IF(AND(SUM(C4:C10)>0, ISNUMBER(C4)),C4/SUM(C4:C10), ""), "") -> 0 | D13: =IF(SUM(J4:J10) > 0, IF(AND(SUM(D4:D10)>0, ISNUMBER(D4)),D4/SUM(D4:D10), ""), "") -> 0 | E13: =IF(SUM(J4:J10) > 0, IF(AND(SUM(E4:E10)>0, ISNUMBER(E4)),E4/SUM(E4:E10), ""), "") -> 0 | F13: =IF(SUM(J4:J10) > 0, IF(AND(SUM(F4:F10)>0, ISNUMBER(F4)),F4/SUM(F4:F10), ""), "") -> 0 | G13: =IF(SUM(J4:J10) > 0, IF(AND(SUM(G4:G10)>0, ISNUMBER(G4)),G4/SUM(G4:G10), ""), "") -> 0
B14: Separate accounts investing directly into real estate | C14: =IF(SUM(J4:J10) > 0, IF(AND(SUM(C4:C10)>0, ISNUMBER(C5)),C5/SUM(C4:C10), ""), "") -> 0 | D14: =IF(SUM(J4:J10) > 0, IF(AND(SUM(D4:D10)>0, ISNUMBER(D5)),D5/SUM(D4:D10), ""), "") -> 0 | E14: =IF(SUM(J4:J10) > 0, IF(AND(SUM(E4:E10)>0, ISNUMBER(E5)),E5/SUM(E4:E10), ""), "") -> 0 | F14: =IF(SUM(J4:J10) > 0, IF(AND(SUM(F4:F10)>0, ISNUMBER(F5)),F5/SUM(F4:F10), ""), "") -> 0 | G14: =IF(SUM(J4:J10) > 0, IF(AND(SUM(G4:G10)>0, ISNUMBER(G5)),G5/SUM(G4:G10), ""), "") -> 0
B15: Separate accounts investing into indirect vehicles | C15: =IF(SUM(J4:J10) > 0, IF(AND(SUM(C4:C10)>0, ISNUMBER(C6)),C6/SUM(C4:C10), ""), "") -> 0 | D15: =IF(SUM(J4:J10) > 0, IF(AND(SUM(D4:D10)>0, ISNUMBER(D6)),D6/SUM(D4:D10), ""), "") -> 0 | E15: =IF(SUM(J4:J10) > 0, IF(AND(SUM(E4:E10)>0, ISNUMBER(E6)),E6/SUM(E4:E10), ""), "") -> 0 | F15: =IF(SUM(J4:J10) > 0, IF(AND(SUM(F4:F10)>0, ISNUMBER(F6)),F6/SUM(F4:F10), ""), "") -> 0 | G15: =IF(SUM(J4:J10) > 0, IF(AND(SUM(G4:G10)>0, ISNUMBER(G6)),G6/SUM(G4:G10), ""), "") -> 0
B16: Joint ventures and club deals | C16: =IF(SUM(J4:J10) > 0, IF(AND(SUM(C4:C10)>0, ISNUMBER(C7)),C7/SUM(C4:C10), ""), "") -> 0 | D16: =IF(SUM(J4:J10) > 0, IF(AND(SUM(D4:D10)>0, ISNUMBER(D7)),D7/SUM(D4:D10), ""), "") -> 0 | E16: =IF(SUM(J4:J10) > 0, IF(AND(SUM(E4:E10)>0, ISNUMBER(E7)),E7/SUM(E4:E10), ""), "") -> 0 | F16: =IF(SUM(J4:J10) > 0, IF(AND(SUM(F4:F10)>0, ISNUMBER(F7)),F7/SUM(F4:F10), ""), "") -> 0 | G16: =IF(SUM(J4:J10) > 0, IF(AND(SUM(G4:G10)>0, ISNUMBER(G7)),G7/SUM(G4:G10), ""), "") -> 0
B17: Multi Managers | C17: =IF(SUM(J4:J10) > 0, IF(AND(SUM(C4:C10)>0, ISNUMBER(C8)),C8/SUM(C4:C10), ""), "") -> 0 | D17: =IF(SUM(J4:J10) > 0, IF(AND(SUM(D4:D10)>0, ISNUMBER(D8)),D8/SUM(D4:D10), ""), "") -> 0 | E17: =IF(SUM(J4:J10) > 0, IF(AND(SUM(E4:E10)>0, ISNUMBER(E8)),E8/SUM(E4:E10), ""), "") -> 0 | F17: =IF(SUM(J4:J10) > 0, IF(AND(SUM(F4:F10)>0, ISNUMBER(F8)),F8/SUM(F4:F10), ""), "") -> 0 | G17: =IF(SUM(J4:J10) > 0, IF(AND(SUM(G4:G10)>0, ISNUMBER(G8)),G8/SUM(G4:G10), ""), "") -> 0
B18: Non-listed debt products | C18: =IF(SUM(J4:J10) > 0, IF(AND(SUM(C4:C10)>0, ISNUMBER(C9)),C9/SUM(C4:C10), ""), "") -> 0 | D18: =IF(SUM(J4:J10) > 0, IF(AND(SUM(D4:D10)>0, ISNUMBER(D9)),D9/SUM(D4:D10), ""), "") -> 0 | E18: =IF(SUM(J4:J10) > 0, IF(AND(SUM(E4:E10)>0, ISNUMBER(E9)),E9/SUM(E4:E10), ""), "") -> 0 | F18: =IF(SUM(J4:J10) > 0, IF(AND(SUM(F4:F10)>0, ISNUMBER(F9)),F9/SUM(F4:F10), ""), "") -> 0 | G18: =IF(SUM(J4:J10) > 0, IF(AND(SUM(G4:G10)>0, ISNUMBER(G9)),G9/SUM(G4:G10), ""), "") -> 0
B19: Operating Platforms | C19: =IF(SUM(J4:J10) > 0, IF(AND(SUM(C4:C10)>0, ISNUMBER(C10)),C10/SUM(C4:C10), ""), "") -> 0 | D19: =IF(SUM(J4:J10) > 0, IF(AND(SUM(D4:D10)>0, ISNUMBER(D10)),D10/SUM(D4:D10), ""), "") -> 0 | E19: =IF(SUM(J4:J10) > 0, IF(AND(SUM(E4:E10)>0, ISNUMBER(E10)),E10/SUM(E4:E10), ""), "") -> 0 | F19: =IF(SUM(J4:J10) > 0, IF(AND(SUM(F4:F10)>0, ISNUMBER(F10)),F10/SUM(F4:F10), ""), "") -> 0 | G19: =IF(SUM(J4:J10) > 0, IF(AND(SUM(G4:G10)>0, ISNUMBER(G10)),G10/SUM(G4:G10), ""), "") -> 0

Sheet KeyFig (7)
A1: Total equity raised by fund manager domicile
B3: region | C3: Non-listed Real Estate (million) | E3: region | F3: Non-listed Real Estate (million)
B4: Asia Pacific | C4: =IF(SUMIFS('TERadj'!M2:M100,'TERadj'!M2:M100,">0",'TERadj'!C2:C100,"Asia Pacific")/1000,SUMIFS('TERadj'!M2:M100,'TERadj'!M2:M100,">0",'TERadj'!C2:C100,"Asia Pacific")/1000,"") -> 0 | E4: Asia Pacific | F4: =IF(SUMIFS('TERadj'!M2:M100,'TERadj'!M2:M100,">0",'TERadj'!C2:C100,"Asia Pacific")/1000,SUMIFS('TERadj'!M2:M100,'TERadj'!M2:M100,">0",'TERadj'!C2:C100,"Asia Pacific")/1000,"") -> 0
B5: Europe | C5: =IF(SUMIFS('TERadj'!M2:M100,'TERadj'!M2:M100,">0",'TERadj'!C2:C100,"Europe")/1000,SUMIFS('TERadj'!M2:M100,'TERadj'!M2:M100,">0",'TERadj'!C2:C100,"Europe")/1000,"") -> 0 | E5: Europe | F5: =IF(SUMIFS('TERadj'!M2:M100,'TERadj'!M2:M100,">0",'TERadj'!C2:C100,"Europe")/1000,SUMIFS('TERadj'!M2:M100,'TERadj'!M2:M100,">0",'TERadj'!C2:C100,"Europe")/1000,"") -> 0
B6: North America | C6: =IF(SUMIFS('TERadj'!M2:M100,'TERadj'!M2:M100,">0",'TERadj'!C2:C100,"North America")/1000,SUMIFS('TERadj'!M2:M100,'TERadj'!M2:M100,">0",'TERadj'!C2:C100,"North America")/1000,"") -> 0 | E6: North America | F6: =IF(SUMIFS('TERadj'!M2:M100,'TERadj'!M2:M100,">0",'TERadj'!C2:C100,"North America")/1000,SUMIFS('TERadj'!M2:M100,'TERadj'!M2:M100,">0",'TERadj'!C2:C100,"North America")/1000,"") -> 0
B7: South America | C7: =IF(SUMIFS('TERadj'!M2:M100,'TERadj'!M2:M100,">0",'TERadj'!C2:C100,"South America")/1000,SUMIFS('TERadj'!M2:M100,'TERadj'!M2:M100,">0",'TERadj'!C2:C100,"South America")/1000,"") -> 0 | E7: South America | F7: =IF(SUMIFS('TERadj'!M2:M100,'TERadj'!M2:M100,">0",'TERadj'!C2:C100,"South America")/1000,SUMIFS('TERadj'!M2:M100,'TERadj'!M2:M100,">0",'TERadj'!C2:C100,"South America")/1000,"") -> 0
B8: Africa | C8: =IF(SUMIFS('TERadj'!M2:M100,'TERadj'!M2:M100,">0",'TERadj'!C2:C100,"Africa")/1000,SUMIFS('TERadj'!M2:M100,'TERadj'!M2:M100,">0",'TERadj'!C2:C100,"Africa")/1000,"") -> 0 | E8: Africa | F8: =IF(SUMIFS('TERadj'!M2:M100,'TERadj'!M2:M100,">0",'TERadj'!C2:C100,"Africa")/1000,SUMIFS('TERadj'!M2:M100,'TERadj'!M2:M100,">0",'TERadj'!C2:C100,"Africa")/1000,"") -> 0
B10: region | C10: Non-listed Real Estate (million)
B11: Asia Pacific | C11: =IF(SUMIFS('TERadj'!M2:M100,'TERadj'!M2:M100,">0",'TERadj'!C2:C100,"Asia Pacific")/1000,SUMIFS('TERadj'!M2:M100,'TERadj'!M2:M100,">0",'TERadj'!C2:C100,"Asia Pacific")/1000,"") -> 0
B12: Europe | C12: =IF(SUMIFS('TERadj'!M2:M100,'TERadj'!M2:M100,">0",'TERadj'!C2:C100,"Europe")/1000,SUMIFS('TERadj'!M2:M100,'TERadj'!M2:M100,">0",'TERadj'!C2:C100,"Europe")/1000,"") -> 0
B13: North America | C13: =IF(SUMIFS('TERadj'!M2:M100,'TERadj'!M2:M100,">0",'TERadj'!C2:C100,"North America")/1000,SUMIFS('TERadj'!M2:M100,'TERadj'!M2:M100,">0",'TERadj'!C2:C100,"North America")/1000,"") -> 0
B14: South America | C14: =IF(SUMIFS('TERadj'!M2:M100,'TERadj'!M2:M100,">0",'TERadj'!C2:C100,"South America")/1000,SUMIFS('TERadj'!M2:M100,'TERadj'!M2:M100,">0",'TERadj'!C2:C100,"South America")/1000,"") -> 0
B15: Africa | C15: =IF(SUMIFS('TERadj'!M2:M100,'TERadj'!M2:M100,">0",'TERadj'!C2:C100,"Africa")/1000,SUMIFS('TERadj'!M2:M100,'TERadj'!M2:M100,">0",'TERadj'!C2:C100,"Africa")/1000,"") -> 0

Sheet Figure (1)
A1: Global capital raising activity
B3: option | C3: 2015 | D3: 2016 | E3: 2017 | F3: 2018 | G3: 2019 | H3: 2020 | I3: 2021 | J3: 2022 | K3: 2023 | L3: 2024 | N3: option | O3: 2015 | P3: 2016 | Q3: 2017 | R3: 2018 | S3: 2019 | T3: 2020 | U3: 2021 | V3: 2022 | W3: 2023 | X3: 2024
B4: yes | C4: 123 | D4: 130 | E4: 134 | F4: 160 | G4: 125 | H4: 87 | I4: 102 | J4: 96 | K4: 62 | L4: {=IF(COUNT(_xlfn._xlws.FILTER('TERadj'!AX2:AX100, ('TERadj'!AX2:AX100>0)*('TERadj'!AX2:AX100=1))),COUNT(_xlfn._xlws.FILTER('TERadj'!AX2:AX100, ('TERadj'!AX2:AX100>0)*('TERadj'!AX2:AX100=1))),"")} -> 0 | N4: yes | O4: 123 | P4: 130 | Q4: 134 | R4: 160 | S4: 125 | T4: 87 | U4: 102 | V4: 96 | W4: 62 | X4: {=IF(COUNT(_xlfn._xlws.FILTER('TERadj'!AX2:AX100, ('TERadj'!AX2:AX100>0)*('TERadj'!AX2:AX100=1))),COUNT(_xlfn._xlws.FILTER('TERadj'!AX2:AX100, ('TERadj'!AX2:AX100>0)*('TERadj'!AX2:AX100=1))),"")} -> 0
B5: no | C5: 30 | D5: 32 | E5: 41 | F5: 43 | G5: 34 | H5: 40 | I5: 28 | J5: 20 | K5: 21 | L5: {=IF(COUNT(_xlfn._xlws.FILTER('TERadj'!AX2:AX100, ('TERadj'!AX2:AX100>0)*('TERadj'!AX2:AX100=2))),COUNT(_xlfn._xlws.FILTER('TERadj'!AX2:AX100, ('TERadj'!AX2:AX100>0)*('TERadj'!AX2:AX100=2))),"")} -> 0 | N5: no | O5: 30 | P5: 32 | Q5: 41 | R5: 43 | S5: 34 | T5: 40 | U5: 28 | V5: 20 | W5: 21 | X5: {=IF(COUNT(_xlfn._xlws.FILTER('TERadj'!AX2:AX100, ('TERadj'!AX2:AX100>0)*('TERadj'!AX2:AX100=2))),COUNT(_xlfn._xlws.FILTER('TERadj'!AX2:AX100, ('TERadj'!AX2:AX100>0)*('TERadj'!AX2:AX100=2))),"")} -> 0
B7: option | C7: 2015 | D7: 2016 | E7: 2017 | F7: 2018 | G7: 2019 | H7: 2020 | I7: 2021 | J7: 2022 | K7: 2023 | L7: 2024
B8: yes | C8: =IF(SUM(O4:O5) > 2, IF(AND(SUM(C4:C5)>0, ISNUMBER(C4)),C4/SUM(C4:C5), ""), "") -> 0 | D8: =IF(SUM(O4:O5) > 2, IF(AND(SUM(D4:D5)>0, ISNUMBER(D4)),D4/SUM(D4:D5), ""), "") -> 0 | E8: =IF(SUM(O4:O5) > 2, IF(AND(SUM(E4:E5)>0, ISNUMBER(E4)),E4/SUM(E4:E5), ""), "") -> 0 | F8: =IF(SUM(O4:O5) > 2, IF(AND(SUM(F4:F5)>0, ISNUMBER(F4)),F4/SUM(F4:F5), ""), "") -> 0 | G8: =IF(SUM(O4:O5) > 2, IF(AND(SUM(G4:G5)>0, ISNUMBER(G4)),G4/SUM(G4:G5), ""), "") -> 0 | H8: =IF(SUM(O4:O5) > 2, IF(AND(SUM(H4:H5)>0, ISNUMBER(H4)),H4/SUM(H4:H5), ""), "") -> 0 | I8: =IF(SUM(O4:O5) > 2, IF(AND(SUM(I4:I5)>0, ISNUMBER(I4)),I4/SUM(I4:I5), ""), "") -> 0 | J8: =IF(SUM(O4:O5) > 2, IF(AND(SUM(J4:J5)>0, ISNUMBER(J4)),J4/SUM(J4:J5), ""), "") -> 0 | K8: =IF(SUM(O4:O5) > 2, IF(AND(SUM(K4:K5)>0, ISNUMBER(K4)),K4/SUM(K4:K5), ""), "") -> 0 | L8: =IF(SUM(O4:O5) > 2, IF(AND(SUM(L4:L5)>0, ISNUMBER(L4)),L4/SUM(L4:L5), ""), "") -> 0
B9: no | C9: =IF(SUM(O4:O5) > 2, IF(AND(SUM(C4:C5)>0, ISNUMBER(C5)),C5/SUM(C4:C5), ""), "") -> 0 | D9: =IF(SUM(O4:O5) > 2, IF(AND(SUM(D4:D5)>0, ISNUMBER(D5)),D5/SUM(D4:D5), ""), "") -> 0 | E9: =IF(SUM(O4:O5) > 2, IF(AND(SUM(E4:E5)>0, ISNUMBER(E5)),E5/SUM(E4:E5), ""), "") -> 0 | F9: =IF(SUM(O4:O5) > 2, IF(AND(SUM(F4:F5)>0, ISNUMBER(F5)),F5/SUM(F4:F5), ""), "") -> 0 | G9: =IF(SUM(O4:O5) > 2, IF(AND(SUM(G4:G5)>0, ISNUMBER(G5)),G5/SUM(G4:G5), ""), "") -> 0 | H9: =IF(SUM(O4:O5) > 2, IF(AND(SUM(H4:H5)>0, ISNUMBER(H5)),H5/SUM(H4:H5), ""), "") -> 0 | I9: =IF(SUM(O4:O5) > 2, IF(AND(SUM(I4:I5)>0, ISNUMBER(I5)),I5/SUM(I4:I5), ""), "") -> 0 | J9: =IF(SUM(O4:O5) > 2, IF(AND(SUM(J4:J5)>0, ISNUMBER(J5)),J5/SUM(J4:J5), ""), "") -> 0 | K9: =IF(SUM(O4:O5) > 2, IF(AND(SUM(K4:K5)>0, ISNUMBER(K5)),K5/SUM(K4:K5), ""), "") -> 0 | L9: =IF(SUM(O4:O5) > 2, IF(AND(SUM(L4:L5)>0, ISNUMBER(L5)),L5/SUM(L4:L5), ""), "") -> 0

Sheet Figure (2)
A1: Reasons why no capital was raised
B3: option | C3: 2015 | D3: 2016 | E3: 2017 | F3: 2018 | G3: 2019 | H3: 2020 | I3: 2021 | J3: 2022 | K3: 2023 | L3: 2024 | N3: option | O3: 2015 | P3: 2016 | Q3: 2017 | R3: 2018 | S3: 2019 | T3: 2020 | U3: 2021 | V3: 2022 | W3: 2023 | X3: 2024
B4: track record | C4: 1 | D4: 2 | E4: 4 | G4: 1 | K4: 1 | L4: {=IF(COUNT(_xlfn._xlws.FILTER('TERadj'!AY2:AY100, ('TERadj'!AY2:AY100>0)*('TERadj'!AY2:AY100=1))),COUNT(_xlfn._xlws.FILTER('TERadj'!AY2:AY100, ('TERadj'!AY2:AY100>0)*('TERadj'!AY2:AY100=1))),"")} -> 0 | N4: track record | O4: 1 | P4: 2 | Q4: 4 | S4: 1 | W4: 1 | X4: {=IF(COUNT(_xlfn._xlws.FILTER('TERadj'!AY2:AY100, ('TERadj'!AY2:AY100>0)*('TERadj'!AY2:AY100=1))),COUNT(_xlfn._xlws.FILTER('TERadj'!AY2:AY100, ('TERadj'!AY2:AY100>0)*('TERadj'!AY2:AY100=1))),"")} -> 0
B5: alignment of interest | C5: 1 | F5: 1 | G5: 1 | K5: 1 | L5: {=IF(COUNT(_xlfn._xlws.FILTER('TERadj'!AY2:AY100, ('TERadj'!AY2:AY100>0)*('TERadj'!AY2:AY100=2))),COUNT(_xlfn._xlws.FILTER('TERadj'!AY2:AY100, ('TERadj'!AY2:AY100>0)*('TERadj'!AY2:AY100=2))),"")} -> 0 | N5: alignment of interest | O5: 1 | R5: 1 | S5: 1 | W5: 1 | X5: {=IF(COUNT(_xlfn._xlws.FILTER('TERadj'!AY2:AY100, ('TERadj'!AY2:AY100>0)*('TERadj'!AY2:AY100=2))),COUNT(_xlfn._xlws.FILTER('TERadj'!AY2:AY100, ('TERadj'!AY2:AY100>0)*('TERadj'!AY2:AY100=2))),"")} -> 0
B6: fund manager reputation | L6: {=IF(COUNT(_xlfn._xlws.FILTER('TERadj'!AY2:AY100, ('TERadj'!AY2:AY100>0)*('TERadj'!AY2:AY100=3))),COUNT(_xlfn._xlws.FILTER('TERadj'!AY2:AY100, ('TERadj'!AY2:AY100>0)*('TERadj'!AY2:AY100=3))),"")} -> 0 | N6: fund manager reputation | X6: {=IF(COUNT(_xlfn._xlws.FILTER('TERadj'!AY2:AY100, ('TERadj'!AY2:AY100>0)*('TERadj'!AY2:AY100=3))),COUNT(_xlfn._xlws.FILTER('TERadj'!AY2:AY100, ('TERadj'!AY2:AY100>0)*('TERadj'!AY2:AY100=3))),"")} -> 0
B7: associated costs | L7: {=IF(COUNT(_xlfn._xlws.FILTER('TERadj'!AY2:AY100, ('TERadj'!AY2:AY100>0)*('TERadj'!AY2:AY100=4))),COUNT(_xlfn._xlws.FILTER('TERadj'!AY2:AY100, ('TERadj'!AY2:AY100>0)*('TERadj'!AY2:AY100=4))),"")} -> 0 | N7: associated costs | X7: {=IF(COUNT(_xlfn._xlws.FILTER('TERadj'!AY2:AY100, ('TERadj'!AY2:AY100>0)*('TERadj'!AY2:AY100=4))),COUNT(_xlfn._xlws.FILTER('TERadj'!AY2:AY100, ('TERadj'!AY2:AY100>0)*('TERadj'!AY2:AY100=4))),"")} -> 0
B8: corporate governance framework | E8: 4 | G8: 3 | I8: 1 | L8: {=IF(COUNT(_xlfn._xlws.FILTER('TERadj'!AY2:AY100, ('TERadj'!AY2:AY100>0)*('TERadj'!AY2:AY100=5))),COUNT(_xlfn._xlws.FILTER('TERadj'!AY2:AY100, ('TERadj'!AY2:AY100>0)*('TERadj'!AY2:AY100=5))),"")} -> 0 | N8: corporate governance framework | Q8: 4 | S8: 3 | U8: 1 | X8: {=IF(COUNT(_xlfn._xlws.FILTER('TERadj'!AY2:AY100, ('TERadj'!AY2:AY100>0)*('TERadj'!AY2:AY100=5))),COUNT(_xlfn._xlws.FILTER('TERadj'!AY2:AY100, ('TERadj'!AY2:AY100>0)*('TERadj'!AY2:AY100=5))),"")} -> 0
B9: no product available at that moment | H9: 19 | I9: 13 | J9: 12 | K9: 10 | L9: {=IF(COUNT(_xlfn._xlws.FILTER('TERadj'!AY2:AY100, ('TERadj'!AY2:AY100>0)*('TERadj'!AY2:AY100=6))),COUNT(_xlfn._xlws.FILTER('TERadj'!AY2:AY100, ('TERadj'!AY2:AY100>0)*('TERadj'!AY2:AY100=6))),"")} -> 0 | N9: no product available at that moment | T9: 19 | U9: 13 | V9: 12 | W9: 10 | X9: {=IF(COUNT(_xlfn._xlws.FILTER('TERadj'!AY2:AY100, ('TERadj'!AY2:AY100>0)*('TERadj'!AY2:AY100=6))),COUNT(_xlfn._xlws.FILTER('TERadj'!AY2:AY100, ('TERadj'!AY2:AY100>0)*('TERadj'!AY2:AY100=6))),"")} -> 0
B10: other | C10: 27 | D10: 27 | E10: 33 | F10: 38 | G10: 26 | H10: 21 | I10: 14 | J10: 8 | L10: {=IF(COUNT(_xlfn._xlws.FILTER('TERadj'!AY2:AY100, ('TERadj'!AY2:AY100>0)*('TERadj'!AY2:AY100=7))),COUNT(_xlfn._xlws.FILTER('TERadj'!AY2:AY100, ('TERadj'!AY2:AY100>0)*('TERadj'!AY2:AY100=7))),"")} -> 0 | N10: other | O10: 27 | P10: 27 | Q10: 33 | R10: 38 | S10: 26 | T10: 21 | U10: 14 | V10: 8 | X10: {=IF(COUNT(_xlfn._xlws.FILTER('TERadj'!AY2:AY100, ('TERadj'!AY2:AY100>0)*('TERadj'!AY2:AY100=7))),COUNT(_xlfn._xlws.FILTER('TERadj'!AY2:AY100, ('TERadj'!AY2:AY100>0)*('TERadj'!AY2:AY100=7))),"")} -> 0
B12: option | C12: 2015 | D12: 2016 | E12: 2017 | F12: 2018 | G12: 2019 | H12: 2020 | I12: 2021 | J12: 2022 | K12: 2023 | L12: 2024
B13: track record | C13: =IF(SUM(O4:O10) > 2, IF(AND(SUM(C4:C10)>0, ISNUMBER(C4)),C4/SUM(C4:C10), ""), "") -> 0 | D13: =IF(SUM(O4:O10) > 2, IF(AND(SUM(D4:D10)>0, ISNUMBER(D4)),D4/SUM(D4:D10), ""), "") -> 0 | E13: =IF(SUM(O4:O10) > 2, IF(AND(SUM(E4:E10)>0, ISNUMBER(E4)),E4/SUM(E4:E10), ""), "") -> 0 | F13: =IF(SUM(O4:O10) > 2, IF(AND(SUM(F4:F10)>0, ISNUMBER(F4)),F4/SUM(F4:F10), ""), "") -> 0 | G13: =IF(SUM(O4:O10) > 2, IF(AND(SUM(G4:G10)>0, ISNUMBER(G4)),G4/SUM(G4:G10), ""), "") -> 0 | H13: =IF(SUM(O4:O10) > 2, IF(AND(SUM(H4:H10)>0, ISNUMBER(H4)),H4/SUM(H4:H10), ""), "") -> 0 | I13: =IF(SUM(O4:O10) > 2, IF(AND(SUM(I4:I10)>0, ISNUMBER(I4)),I4/SUM(I4:I10), ""), "") -> 0 | J13: =IF(SUM(O4:O10) > 2, IF(AND(SUM(J4:J10)>0, ISNUMBER(J4)),J4/SUM(J4:J10), ""), "") -> 0 | K13: =IF(SUM(O4:O10) > 2, IF(AND(SUM(K4:K10)>0, ISNUMBER(K4)),K4/SUM(K4:K10), ""), "") -> 0 | L13: =IF(SUM(O4:O10) > 2, IF(AND(SUM(L4:L10)>0, ISNUMBER(L4)),L4/SUM(L4:L10), ""), "") -> 0
B14: alignment of interest | C14: =IF(SUM(O4:O10) > 2, IF(AND(SUM(C4:C10)>0, ISNUMBER(C5)),C5/SUM(C4:C10), ""), "") -> 0 | D14: =IF(SUM(O4:O10) > 2, IF(AND(SUM(D4:D10)>0, ISNUMBER(D5)),D5/SUM(D4:D10), ""), "") -> 0 | E14: =IF(SUM(O4:O10) > 2, IF(AND(SUM(E4:E10)>0, ISNUMBER(E5)),E5/SUM(E4:E10), ""), "") -> 0 | F14: =IF(SUM(O4:O10) > 2, IF(AND(SUM(F4:F10)>0, ISNUMBER(F5)),F5/SUM(F4:F10), ""), "") -> 0 | G14: =IF(SUM(O4:O10) > 2, IF(AND(SUM(G4:G10)>0, ISNUMBER(G5)),G5/SUM(G4:G10), ""), "") -> 0 | H14: =IF(SUM(O4:O10) > 2, IF(AND(SUM(H4:H10)>0, ISNUMBER(H5)),H5/SUM(H4:H10), ""), "") -> 0 | I14: =IF(SUM(O4:O10) > 2, IF(AND(SUM(I4:I10)>0, ISNUMBER(I5)),I5/SUM(I4:I10), ""), "") -> 0 | J14: =IF(SUM(O4:O10) > 2, IF(AND(SUM(J4:J10)>0, ISNUMBER(J5)),J5/SUM(J4:J10), ""), "") -> 0 | K14: =IF(SUM(O4:O10) > 2, IF(AND(SUM(K4:K10)>0, ISNUMBER(K5)),K5/SUM(K4:K10), ""), "") -> 0 | L14: =IF(SUM(O4:O10) > 2, IF(AND(SUM(L4:L10)>0, ISNUMBER(L5)),L5/SUM(L4:L10), ""), "") -> 0
B15: fund manager reputation | C15: =IF(SUM(O4:O10) > 2, IF(AND(SUM(C4:C10)>0, ISNUMBER(C6)),C6/SUM(C4:C10), ""), "") -> 0 | D15: =IF(SUM(O4:O10) > 2, IF(AND(SUM(D4:D10)>0, ISNUMBER(D6)),D6/SUM(D4:D10), ""), "") -> 0 | E15: =IF(SUM(O4:O10) > 2, IF(AND(SUM(E4:E10)>0, ISNUMBER(E6)),E6/SUM(E4:E10), ""), "") -> 0 | F15: =IF(SUM(O4:O10) > 2, IF(AND(SUM(F4:F10)>0, ISNUMBER(F6)),F6/SUM(F4:F10), ""), "") -> 0 | G15: =IF(SUM(O4:O10) > 2, IF(AND(SUM(G4:G10)>0, ISNUMBER(G6)),G6/SUM(G4:G10), ""), "") -> 0 | H15: =IF(SUM(O4:O10) > 2, IF(AND(SUM(H4:H10)>0, ISNUMBER(H6)),H6/SUM(H4:H10), ""), "") -> 0 | I15: =IF(SUM(O4:O10) > 2, IF(AND(SUM(I4:I10)>0, ISNUMBER(I6)),I6/SUM(I4:I10), ""), "") -> 0 | J15: =IF(SUM(O4:O10) > 2, IF(AND(SUM(J4:J10)>0, ISNUMBER(J6)),J6/SUM(J4:J10), ""), "") -> 0 | K15: =IF(SUM(O4:O10) > 2, IF(AND(SUM(K4:K10)>0, ISNUMBER(K6)),K6/SUM(K4:K10), ""), "") -> 0 | L15: =IF(SUM(O4:O10) > 2, IF(AND(SUM(L4:L10)>0, ISNUMBER(L6)),L6/SUM(L4:L10), ""), "") -> 0
B16: associated costs | C16: =IF(SUM(O4:O10) > 2, IF(AND(SUM(C4:C10)>0, ISNUMBER(C7)),C7/SUM(C4:C10), ""), "") -> 0 | D16: =IF(SUM(O4:O10) > 2, IF(AND(SUM(D4:D10)>0, ISNUMBER(D7)),D7/SUM(D4:D10), ""), "") -> 0 | E16: =IF(SUM(O4:O10) > 2, IF(AND(SUM(E4:E10)>0, ISNUMBER(E7)),E7/SUM(E4:E10), ""), "") -> 0 | F16: =IF(SUM(O4:O10) > 2, IF(AND(SUM(F4:F10)>0, ISNUMBER(F7)),F7/SUM(F4:F10), ""), "") -> 0 | G16: =IF(SUM(O4:O10) > 2, IF(AND(SUM(G4:G10)>0, ISNUMBER(G7)),G7/SUM(G4:G10), ""), "") -> 0 | H16: =IF(SUM(O4:O10) > 2, IF(AND(SUM(H4:H10)>0, ISNUMBER(H7)),H7/SUM(H4:H10), ""), "") -> 0 | I16: =IF(SUM(O4:O10) > 2, IF(AND(SUM(I4:I10)>0, ISNUMBER(I7)),I7/SUM(I4:I10), ""), "") -> 0 | J16: =IF(SUM(O4:O10) > 2, IF(AND(SUM(J4:J10)>0, ISNUMBER(J7)),J7/SUM(J4:J10), ""), "") -> 0 | K16: =IF(SUM(O4:O10) > 2, IF(AND(SUM(K4:K10)>0, ISNUMBER(K7)),K7/SUM(K4:K10), ""), "") -> 0 | L16: =IF(SUM(O4:O10) > 2, IF(AND(SUM(L4:L10)>0, ISNUMBER(L7)),L7/SUM(L4:L10), ""), "") -> 0
B17: corporate governance framework | C17: =IF(SUM(O4:O10) > 2, IF(AND(SUM(C4:C10)>0, ISNUMBER(C8)),C8/SUM(C4:C10), ""), "") -> 0 | D17: =IF(SUM(O4:O10) > 2, IF(AND(SUM(D4:D10)>0, ISNUMBER(D8)),D8/SUM(D4:D10), ""), "") -> 0 | E17: =IF(SUM(O4:O10) > 2, IF(AND(SUM(E4:E10)>0, ISNUMBER(E8)),E8/SUM(E4:E10), ""), "") -> 0 | F17: =IF(SUM(O4:O10) > 2, IF(AND(SUM(F4:F10)>0, ISNUMBER(F8)),F8/SUM(F4:F10), ""), "") -> 0 | G17: =IF(SUM(O4:O10) > 2, IF(AND(SUM(G4:G10)>0, ISNUMBER(G8)),G8/SUM(G4:G10), ""), "") -> 0 | H17: =IF(SUM(O4:O10) > 2, IF(AND(SUM(H4:H10)>0, ISNUMBER(H8)),H8/SUM(H4:H10), ""), "") -> 0 | I17: =IF(SUM(O4:O10) > 2, IF(AND(SUM(I4:I10)>0, ISNUMBER(I8)),I8/SUM(I4:I10), ""), "") -> 0 | J17: =IF(SUM(O4:O10) > 2, IF(AND(SUM(J4:J10)>0, ISNUMBER(J8)),J8/SUM(J4:J10), ""), "") -> 0 | K17: =IF(SUM(O4:O10) > 2, IF(AND(SUM(K4:K10)>0, ISNUMBER(K8)),K8/SUM(K4:K10), ""), "") -> 0 | L17: =IF(SUM(O4:O10) > 2, IF(AND(SUM(L4:L10)>0, ISNUMBER(L8)),L8/SUM(L4:L10), ""), "") -> 0
B18: no product available at that moment | C18: =IF(SUM(O4:O10) > 2, IF(AND(SUM(C4:C10)>0, ISNUMBER(C9)),C9/SUM(C4:C10), ""), "") -> 0 | D18: =IF(SUM(O4:O10) > 2, IF(AND(SUM(D4:D10)>0, ISNUMBER(D9)),D9/SUM(D4:D10), ""), "") -> 0 | E18: =IF(SUM(O4:O10) > 2, IF(AND(SUM(E4:E10)>0, ISNUMBER(E9)),E9/SUM(E4:E10), ""), "") -> 0 | F18: =IF(SUM(O4:O10) > 2, IF(AND(SUM(F4:F10)>0, ISNUMBER(F9)),F9/SUM(F4:F10), ""), "") -> 0 | G18: =IF(SUM(O4:O10) > 2, IF(AND(SUM(G4:G10)>0, ISNUMBER(G9)),G9/SUM(G4:G10), ""), "") -> 0 | H18: =IF(SUM(O4:O10) > 2, IF(AND(SUM(H4:H10)>0, ISNUMBER(H9)),H9/SUM(H4:H10), ""), "") -> 0 | I18: =IF(SUM(O4:O10) > 2, IF(AND(SUM(I4:I10)>0, ISNUMBER(I9)),I9/SUM(I4:I10), ""), "") -> 0 | J18: =IF(SUM(O4:O10) > 2, IF(AND(SUM(J4:J10)>0, ISNUMBER(J9)),J9/SUM(J4:J10), ""), "") -> 0 | K18: =IF(SUM(O4:O10) > 2, IF(AND(SUM(K4:K10)>0, ISNUMBER(K9)),K9/SUM(K4:K10), ""), "") -> 0 | L18: =IF(SUM(O4:O10) > 2, IF(AND(SUM(L4:L10)>0, ISNUMBER(L9)),L9/SUM(L4:L10), ""), "") -> 0
B19: other | C19: =IF(SUM(O4:O10) > 2, IF(AND(SUM(C4:C10)>0, ISNUMBER(C10)),C10/SUM(C4:C10), ""), "") -> 0 | D19: =IF(SUM(O4:O10) > 2, IF(AND(SUM(D4:D10)>0, ISNUMBER(D10)),D10/SUM(D4:D10), ""), "") -> 0 | E19: =IF(SUM(O4:O10) > 2, IF(AND(SUM(E4:E10)>0, ISNUMBER(E10)),E10/SUM(E4:E10), ""), "") -> 0 | F19: =IF(SUM(O4:O10) > 2, IF(AND(SUM(F4:F10)>0, ISNUMBER(F10)),F10/SUM(F4:F10), ""), "") -> 0 | G19: =IF(SUM(O4:O10) > 2, IF(AND(SUM(G4:G10)>0, ISNUMBER(G10)),G10/SUM(G4:G10), ""), "") -> 0 | H19: =IF(SUM(O4:O10) > 2, IF(AND(SUM(H4:H10)>0, ISNUMBER(H10)),H10/SUM(H4:H10), ""), "") -> 0 | I19: =IF(SUM(O4:O10) > 2, IF(AND(SUM(I4:I10)>0, ISNUMBER(I10)),I10/SUM(I4:I10), ""), "") -> 0 | J19: =IF(SUM(O4:O10) > 2, IF(AND(SUM(J4:J10)>0, ISNUMBER(J10)),J10/SUM(J4:J10), ""), "") -> 0 | K19: =IF(SUM(O4:O10) > 2, IF(AND(SUM(K4:K10)>0, ISNUMBER(K10)),K10/SUM(K4:K10), ""), "") -> 0 | L19: =IF(SUM(O4:O10) > 2, IF(AND(SUM(L4:L10)>0, ISNUMBER(L10)),L10/SUM(L4:L10), ""), "") -> 0

Sheet Figure (3)
A1: Methods of capital raising by fund manager domicile
B3: method | C3: Asia Pacific | D3: Europe | E3: North America | F3: South America | G3: Africa | I3: method | J3: Asia Pacific Sample | K3: Europe Sample | L3: North America Sample | M3: South America Sample | N3: Africa Sample
B4: Placement agent | C4: =IF(SUMIFS('TERadj'!AZ2:AZ100,'TERadj'!AZ2:AZ100,">0",'TERadj'!C2:C100,"Asia Pacific")/1000,SUMIFS('TERadj'!AZ2:AZ100,'TERadj'!AZ2:AZ100,">0",'TERadj'!C2:C100,"Asia Pacific")/1000,"") -> 0 | D4: =IF(SUMIFS('TERadj'!AZ2:AZ100,'TERadj'!AZ2:AZ100,">0",'TERadj'!C2:C100,"Europe")/1000,SUMIFS('TERadj'!AZ2:AZ100,'TERadj'!AZ2:AZ100,">0",'TERadj'!C2:C100,"Europe")/1000,"") -> 0 | E4: =IF(SUMIFS('TERadj'!AZ2:AZ100,'TERadj'!AZ2:AZ100,">0",'TERadj'!C2:C100,"North America")/1000,SUMIFS('TERadj'!AZ2:AZ100,'TERadj'!AZ2:AZ100,">0",'TERadj'!C2:C100,"North America")/1000,"") -> 0 | F4: =IF(SUMIFS('TERadj'!AZ2:AZ100,'TERadj'!AZ2:AZ100,">0",'TERadj'!C2:C100,"South America")/1000,SUMIFS('TERadj'!AZ2:AZ100,'TERadj'!AZ2:AZ100,">0",'TERadj'!C2:C100,"South America")/1000,"") -> 0 | G4: =IF(SUMIFS('TERadj'!AZ2:AZ100,'TERadj'!AZ2:AZ100,">0",'TERadj'!C2:C100,"Africa")/1000,SUMIFS('TERadj'!AZ2:AZ100,'TERadj'!AZ2:AZ100,">0",'TERadj'!C2:C100,"Africa")/1000,"") -> 0 | I4: Placement agent | J4: {=IF(COUNT(_xlfn._xlws.FILTER('TERadj'!AZ2:AZ100, ('TERadj'!AZ2:AZ100>0)*('TERadj'!C2:C100="Asia Pacific"))),COUNT(_xlfn._xlws.FILTER('TERadj'!AZ2:AZ100, ('TERadj'!AZ2:AZ100>0)*('TERadj'!C2:C100="Asia Pacific"))),"")} -> 0 | K4: {=IF(COUNT(_xlfn._xlws.FILTER('TERadj'!AZ2:AZ100, ('TERadj'!AZ2:AZ100>0)*('TERadj'!C2:C100="Europe"))),COUNT(_xlfn._xlws.FILTER('TERadj'!AZ2:AZ100, ('TERadj'!AZ2:AZ100>0)*('TERadj'!C2:C100="Europe"))),"")} -> 0 | L4: {=IF(COUNT(_xlfn._xlws.FILTER('TERadj'!AZ2:AZ100, ('TERadj'!AZ2:AZ100>0)*('TERadj'!C2:C100="North America"))),COUNT(_xlfn._xlws.FILTER('TERadj'!AZ2:AZ100, ('TERadj'!AZ2:AZ100>0)*('TERadj'!C2:C100="North America"))),"")} -> 0 | M4: {=IF(COUNT(_xlfn._xlws.FILTER('TERadj'!AZ2:AZ100, ('TERadj'!AZ2:AZ100>0)*('TERadj'!C2:C100="South America"))),COUNT(_xlfn._xlws.FILTER('TERadj'!AZ2:AZ100, ('TERadj'!AZ2:AZ100>0)*('TERadj'!C2:C100="South America"))),"")} -> 0 | N4: {=IF(COUNT(_xlfn._xlws.FILTER('TERadj'!AZ2:AZ100, ('TERadj'!AZ2:AZ100>0)*('TERadj'!C2:C100="Africa"))),COUNT(_xlfn._xlws.FILTER('TERadj'!AZ2:AZ100, ('TERadj'!AZ2:AZ100>0)*('TERadj'!C2:C100="Africa"))),"")} -> 0
B5: Investors contacting you directly | C5: =IF(SUMIFS('TERadj'!BA2:BA100,'TERadj'!BA2:BA100,">0",'TERadj'!C2:C100,"Asia Pacific")/1000,SUMIFS('TERadj'!BA2:BA100,'TERadj'!BA2:BA100,">0",'TERadj'!C2:C100,"Asia Pacific")/1000,"") -> 0 | D5: =IF(SUMIFS('TERadj'!BA2:BA100,'TERadj'!BA2:BA100,">0",'TERadj'!C2:C100,"Europe")/1000,SUMIFS('TERadj'!BA2:BA100,'TERadj'!BA2:BA100,">0",'TERadj'!C2:C100,"Europe")/1000,"") -> 0 | E5: =IF(SUMIFS('TERadj'!BA2:BA100,'TERadj'!BA2:BA100,">0",'TERadj'!C2:C100,"North America")/1000,SUMIFS('TERadj'!BA2:BA100,'TERadj'!BA2:BA100,">0",'TERadj'!C2:C100,"North America")/1000,"") -> 0 | F5: =IF(SUMIFS('TERadj'!BA2:BA100,'TERadj'!BA2:BA100,">0",'TERadj'!C2:C100,"South America")/1000,SUMIFS('TERadj'!BA2:BA100,'TERadj'!BA2:BA100,">0",'TERadj'!C2:C100,"South America")/1000,"") -> 0 | G5: =IF(SUMIFS('TERadj'!BA2:BA100,'TERadj'!BA2:BA100,">0",'TERadj'!C2:C100,"Africa")/1000,SUMIFS('TERadj'!BA2:BA100,'TERadj'!BA2:BA100,">0",'TERadj'!C2:C100,"Africa")/1000,"") -> 0 | I5: Investors contacting you directly | J5: {=IF(COUNT(_xlfn._xlws.FILTER('TERadj'!BA2:BA100, ('TERadj'!BA2:BA100>0)*('TERadj'!C2:C100="Asia Pacific"))),COUNT(_xlfn._xlws.FILTER('TERadj'!BA2:BA100, ('TERadj'!BA2:BA100>0)*('TERadj'!C2:C100="Asia Pacific"))),"")} -> 0 | K5: {=IF(COUNT(_xlfn._xlws.FILTER('TERadj'!BA2:BA100, ('TERadj'!BA2:BA100>0)*('TERadj'!C2:C100="Europe"))),COUNT(_xlfn._xlws.FILTER('TERadj'!BA2:BA100, ('TERadj'!BA2:BA100>0)*('TERadj'!C2:C100="Europe"))),"")} -> 0 | L5: {=IF(COUNT(_xlfn._xlws.FILTER('TERadj'!BA2:BA100, ('TERadj'!BA2:BA100>0)*('TERadj'!C2:C100="North America"))),COUNT(_xlfn._xlws.FILTER('TERadj'!BA2:BA100, ('TERadj'!BA2:BA100>0)*('TERadj'!C2:C100="North America"))),"")} -> 0 | M5: {=IF(COUNT(_xlfn._xlws.FILTER('TERadj'!BA2:BA100, ('TERadj'!BA2:BA100>0)*('TERadj'!C2:C100="South America"))),COUNT(_xlfn._xlws.FILTER('TERadj'!BA2:BA100, ('TERadj'!BA2:BA100>0)*('TERadj'!C2:C100="South America"))),"")} -> 0 | N5: {=IF(COUNT(_xlfn._xlws.FILTER('TERadj'!BA2:BA100, ('TERadj'!BA2:BA100>0)*('TERadj'!C2:C100="Africa"))),COUNT(_xlfn._xlws.FILTER('TERadj'!BA2:BA100, ('TERadj'!BA2:BA100>0)*('TERadj'!C2:C100="Africa"))),"")} -> 0
B6: Your own direct relationship with investors | C6: =IF(SUMIFS('TERadj'!BB2:BB100,'TERadj'!BB2:BB100,">0",'TERadj'!C2:C100,"Asia Pacific")/1000,SUMIFS('TERadj'!BB2:BB100,'TERadj'!BB2:BB100,">0",'TERadj'!C2:C100,"Asia Pacific")/1000,"") -> 0 | D6: =IF(SUMIFS('TERadj'!BB2:BB100,'TERadj'!BB2:BB100,">0",'TERadj'!C2:C100,"Europe")/1000,SUMIFS('TERadj'!BB2:BB100,'TERadj'!BB2:BB100,">0",'TERadj'!C2:C100,"Europe")/1000,"") -> 0 | E6: =IF(SUMIFS('TERadj'!BB2:BB100,'TERadj'!BB2:BB100,">0",'TERadj'!C2:C100,"North America")/1000,SUMIFS('TERadj'!BB2:BB100,'TERadj'!BB2:BB100,">0",'TERadj'!C2:C100,"North America")/1000,"") -> 0 | F6: =IF(SUMIFS('TERadj'!BB2:BB100,'TERadj'!BB2:BB100,">0",'TERadj'!C2:C100,"South America")/1000,SUMIFS('TERadj'!BB2:BB100,'TERadj'!BB2:BB100,">0",'TERadj'!C2:C100,"South America")/1000,"") -> 0 | G6: =IF(SUMIFS('TERadj'!BB2:BB100,'TERadj'!BB2:BB100,">0",'TERadj'!C2:C100,"Africa")/1000,SUMIFS('TERadj'!BB2:BB100,'TERadj'!BB2:BB100,">0",'TERadj'!C2:C100,"Africa")/1000,"") -> 0 | I6: Your own direct relationship with investors | J6: {=IF(COUNT(_xlfn._xlws.FILTER('TERadj'!BB2:BB100, ('TERadj'!BB2:BB100>0)*('TERadj'!C2:C100="Asia Pacific"))),COUNT(_xlfn._xlws.FILTER('TERadj'!BB2:BB100, ('TERadj'!BB2:BB100>0)*('TERadj'!C2:C100="Asia Pacific"))),"")} -> 0 | K6: {=IF(COUNT(_xlfn._xlws.FILTER('TERadj'!BB2:BB100, ('TERadj'!BB2:BB100>0)*('TERadj'!C2:C100="Europe"))),COUNT(_xlfn._xlws.FILTER('TERadj'!BB2:BB100, ('TERadj'!BB2:BB100>0)*('TERadj'!C2:C100="Europe"))),"")} -> 0 | L6: {=IF(COUNT(_xlfn._xlws.FILTER('TERadj'!BB2:BB100, ('TERadj'!BB2:BB100>0)*('TERadj'!C2:C100="North America"))),COUNT(_xlfn._xlws.FILTER('TERadj'!BB2:BB100, ('TERadj'!BB2:BB100>0)*('TERadj'!C2:C100="North America"))),"")} -> 0 | M6: {=IF(COUNT(_xlfn._xlws.FILTER('TERadj'!BB2:BB100, ('TERadj'!BB2:BB100>0)*('TERadj'!C2:C100="South America"))),COUNT(_xlfn._xlws.FILTER('TERadj'!BB2:BB100, ('TERadj'!BB2:BB100>0)*('TERadj'!C2:C100="South America"))),"")} -> 0 | N6: {=IF(COUNT(_xlfn._xlws.FILTER('TERadj'!BB2:BB100, ('TERadj'!BB2:BB100>0)*('TERadj'!C2:C100="Africa"))),COUNT(_xlfn._xlws.FILTER('TERadj'!BB2:BB100, ('TERadj'!BB2:BB100>0)*('TERadj'!C2:C100="Africa"))),"")} -> 0
