Workbook

Sheet DFsmonkeyCompl
A1: Respondent ID | B1: Collector ID | C1: Start Date | D1: End Date | E1: IP Address | F1: Email Address | G1: First Name | H1: Last Name | I1: Custom Data 1 | J1: Vehicle ID / Name | K1: Did your company raise capital for this vehicle in 2017? | L1: Please state the reason why? | M1: Column13 | N1: What was the total amount of capital raised for this vehicle in 2017? (millions) | O1: How much capital was raised for this vehicle in 2017 from Institutional Investors by investor type? (millions)Please ensure that the total values provided match the values you entered in Q3 | P1: Column16 | Q1: Column17 | R1: Column18 | S1: Column19 | T1: Column20 | U1: Column21 | V1: Column22 | W1: How much capital was raised for this vehicle in 2017 from Institutional Investors by investor domicile? (millions)Please ensure that the total values provided match the values you entered in Q3 - total capital raised | X1: Column24 | Y1: Column25 | Z1: Column26 | AA1: Column27 | AB1: What percentage of the total capital was raised via...?Total figure should sum up to 100% | AC1: Column29 | AD1: Column30 | AE1: Column31 | AF1: How do you expect capital raising activities to develop for non-listed real estate funds over the next two years? | AG1: Would you like the name of your company to be included in the list of participants?
J2: Open-Ended Response | K2: Response | L2: Response | M2: Other (please specify) | N2: Open-Ended Response | O2: Pension funds | P2: Insurance companies | Q2: Sovereign wealth fund | R2: Government institutions | S2: Charities, foundations, non-profit organisations | T2: Fund of funds | U2: High net worth individulas / Family offices | V2: Other (please specify) | W2: Europe | X2: Asia Pacific | Y2: North America | Z2: South America | AA2: Africa | AB2: Placement agent (%) | AC2: Investors contacting you directly (%) | AD2: Your own direct relationship with investors (%) | AE2: Other (%) | AF2: Response | AG2: Response
A3: 6714543559 | B3: 162871627 | C3: 43154.678 | D3: 43154.678 | E3: 108.171.128.175 | J3: LaSalle Residential Finance Fund III | K3: Yes | N3: 264 | O3: 95 | V3: 5 | W3: 100 | AD3: 100 | AF3: No change | AG3: Yes
A4: 6714482559 | B4: 162871627 | C4: 43154.661 | D4: 43154.677 | E4: 108.171.128.175 | J4: LaSalle Real Estate Debt Strategies III | K4: Yes | N4: 804 | O4: 68 | P4: 15 | R4: 10 | V4: 8 | W4: 62 | X4: 35 | Y4: 2 | AB4: 0 | AC4: 0 | AD4: 75 | AE4: 25 | AF4: No change | AG4: Yes
A5: 6713894109 | B5: 162871627 | C5: 43154.419 | D5: 43154.429 | E5: 185.29.113.86 | J5: Brunswick Real Estate Capital II | K5: Yes | N5: 16 | V5: 16 | W5: 16 | AD5: 100 | AF5: Increase | AG5: No
A6: 6711242519 | B6: 162871627 | C6: 43153.413 | D6: 43153.568 | E6: 194.143.182.29 | J6: Pramerica Real Estate Capital VI, LP | K6: Yes | N6: 1017 | O6: 793 | P6: 70 | Q6: 52 | R6: 70 | S6: 31 | V6: 1 | W6: 231 | X6: 47 | Y6: 739 | AD6: 97 | AE6: 3 | AF6: Increase | AG6: Yes
A7: 6708670587 | B7: 162871627 | C7: 43152.483 | D7: 43152.487 | E7: 213.251.23.92 | J7: ICG-Longbow Senior Debt Programme Vintage III | K7: Yes | N7: 370 | O7: 370 | W7: 370 | AD7: 100 | AF7: Increase | AG7: Yes
A8: 6696842089 | B8: 162871627 | C8: 43146.433 | D8: 43146.449 | E8: 192.166.106.126 | J8: DE000DK0AYR6 / Deka Realkredit Klassik | K8: Yes | N8: 68 | V8: 100 | W8: 68 | AC8: 100 | AF8: Increase | AG8: Yes
A9: 6692350030 | B9: 162871627 | C9: 43144.712 | D9: 43144.713 | E9: 194.140.225.246 | J9: SELFII | K9: Yes | N9: 126 | P9: 126 | W9: 126 | AD9: 100 | AF9: Increase | AG9: Yes
A10: 6662314847 | B10: 162871627 | C10: 43130.735 | D10: 43130.736 | E10: 217.10.134.222 | J10: DRC UK Whole Loan Fund | K10: Yes | N10: 211 | O10: 211 | P10: 0 | Q10: 0 | R10: 0 | S10: 0 | T10: 0 | U10: 0 | V10: 0 | W10: 211 | X10: 0 | Y10: 0 | Z10: 0 | AA10: 0 | AB10: 0 | AC10: 0 | AD10: 100 | AE10: 0 | AF10: Increase | AG10: Yes
A11: 6662228763 | B11: 162871627 | C11: 43130.712 | D11: 43130.733 | E11: 217.10.134.222 | J11: DRC European Real Estate Debt Fund III | K11: Yes | N11: 268 | O11: 218 | P11: 33 | Q11: 0 | R11: 0 | S11: 0 | T11: 14 | U11: 0 | V11: 3 | W11: 204 | X11: 0 | Y11: 64 | Z11: 0 | AA11: 0 | AB11: 62 | AC11: 7 | AD11: 31 | AE11: 0 | AF11: Increase | AG11: Yes
A12: 6647044991 | B12: 162871627 | C12: 43123.541 | D12: 43123.543 | E12: 80.169.207.154 | J12: AgFe Real Estate Senior Debt Fund II | K12: No | L12: Other (please specify) | M12: Fundraising environment | AF12: Increase | AG12: Yes

Sheet DFanalysis
A1: VehicleID | B1: ID | C1: LoanStrategy | D1: CountryStrategy | E1: Vintage | F1: RaisedCapital | G1: WhyNo | H1: Currency | I1: EUR | J1: CapitalRaisedTotal | K1: PensionFunds | L1: InsuranceCompanies | M1: SWFs | N1: Government | O1: Charities | P1: FundOfFunds | Q1: HNWI | R1: Other | S1: Europe | T1: APAC | U1: NorthAmerica | V1: SouthAmerica | W1: Africa | X1: PlacementAgent | Y1: InvestorsContacting | Z1: OwnRelationship | AA1: Other2 | AB1: Expectations | AC1: Name
A2: LaSalle Residential Finance Fund III | B2: N/A | C2: Senior | D2: UK | E2: 2017 | F2: Yes | H2: GBP | I2: 1.17356 | J2: 309.81984 | K2: 111.4882 | R2: 5.8678 | S2: 117.356 | Z2: 100 | AB2: No change | AC2: Yes
A3: LaSalle Real Estate Debt Strategies III | B3: N/A | C3: Mixed: Senior + Subordinated | D3: Western Europe excluding Nordics, Southern Europe and UK | E3: 2017 | F3: Yes | H3: GBP | I3: 1.17356 | J3: 943.54224 | K3: 79.80208 | L3: 17.6034 | N3: 11.7356 | R3: 9.38848 | S3: 72.76072 | T3: 41.0746 | U3: 2.34712 | Z3: 75 | AA3: 25 | AB3: No change | AC3: Yes
A4: Brunswick Real Estate Capital II | B4: N/A | C4: Senior | D4: Nordics (Denmark, Finland, Norway and Sweden) | E4: 2016 | F4: Yes | H4: SEK | I4: 0.104811 | J4: 18.77696 | R4: 18.77696 | S4: 18.77696 | Z4: 100 | AB4: Increase | AC4: No
A5: Pramerica Real Estate Capital VI, LP | B5: 17370 | C5: Subordinated: Junior + Mezzanine + Preferred equity | D5: Pan-Europe | E5: 2013 | F5: Yes | H5: GBP | I5: 1.17356 | J5: 1193.5105 | K5: 930.63308 | L5: 82.1492 | M5: 61.02512 | N5: 82.1492 | O5: 36.38036 | R5: 1.17356 | S5: 271.09236 | T5: 55.15732 | U5: 867.26084 | Z5: 97 | AA5: 3 | AB5: Increase | AC5: Yes
A6: ICG-Longbow Senior Debt Programme Vintage III | B6: 18137 | C6: Senior | D6: UK | E6: 2016 | F6: Yes | H6: GBP | I6: 1.17356 | J6: 434.2172 | K6: 434.2172 | S6: 434.2172 | Z6: 100 | AB6: Increase | AC6: Yes
A7: DE000DK0AYR6 / Deka Realkredit Klassik | B7: 17375 | C7: Senior | D7: Western Europe excluding Nordics, Southern Europe and UK | E7: 2009 | F7: Yes | H7: EUR | I7: 1 | J7: 79.80208 | R7: 117.356 | S7: 79.80208 | Y7: 100 | AB7: Increase | AC7: Yes
A8: SELFII | B8: 18134 | C8: Senior | D8: Western Europe excluding Nordics, Southern Europe and UK | E8: 2016 | F8: Yes | H8: EUR | I8: 1 | J8: 147.86856 | L8: 147.86856 | S8: 147.86856 | Z8: 100 | AB8: Increase | AC8: Yes
A9: DRC UK Whole Loan Fund | B9: N/A | C9: Whole loans | D9: Western Europe excluding Nordics, Southern Europe and UK | E9: 2016 | F9: Yes | H9: GBP | I9: 1.17356 | J9: 247.62116 | K9: 247.62116 | S9: 247.62116 | Z9: 100 | AB9: Increase | AC9: Yes
A10: DRC European Real Estate Debt Fund III | B10: 18127 | C10: Senior | D10: Western Europe excluding Nordics, Southern Europe and UK | E10: 2015 | F10: Yes | H10: GBP | I10: 1.17356 | J10: 314.51408 | K10: 255.83608 | L10: 38.72748 | P10: 16.42984 | R10: 3.52068 | S10: 239.40624 | U10: 75.10784 | X10: 62 | Y10: 7 | Z10: 31 | AB10: Increase | AC10: Yes
A11: AgFe Real Estate Senior Debt Fund II | B11: N/A | C11: Mixed: Senior + Subordinated + Preferred equity | D11: UK | E11: 2016 | F11: No | G11: Fundraising environment | H11: GBP | I11: 1.17356 | AB11: Increase | AC11: Yes

Sheet df_headers
A1: question | B1: question_code | C1: answer | D1: answer_code | E1: format
A2: keep | D2: keep | E2: TEXT
A3: Respondent ID | D3: respondentId | E3: TEXT
A4: Collector ID | D4: collectorId | E4: TEXT
A5: Start Date | D5: dateStarted | E5: TEXT
A6: End Date | D6: dateEnded | E6: TEXT
A7: IP Address | D7: ipAddress | E7: TEXT
A8: Email Address | D8: email | E8: TEXT
A9: First Name | D9: firstname | E9: TEXT
A10: Last Name | D10: lastname | E10: TEXT
A11: Custom Data 1 | D11: customData1 | E11: TEXT
A12: Vehicle ID / Name | C12: Open-Ended Response | D12: qfundname | E12: TEXT
A13: ID | D13: universeFundID | E13: TEXT
A14: LoanStrategy | D14: loan_strategy | E14: TEXT
A15: CountryStrategy | D15: country_strategy | E15: TEXT
A16: Vintage | D16: first_closing_year | E16: TEXT
A17: Currency | D17: qcurrency | E17: TEXT
A18: Did your company raise capital for this vehicle in 2017? | B18: q1 | C18: Response | D18: q1 | E18: TEXT
A19: Please state the reason why? | B19: q2 | C19: Response | D19: q2 | E19: TEXT
A20: Please state the reason why? | B20: q2 | C20: Other (please specify) | D20: q2other | E20: TEXT
A21: What was the total amount of capital raised for this vehicle in 2017? (millions) | B21: q3 | C21: Open-Ended Response | D21: q3 | E21: currency
A22: How much capital was raised for this vehicle in 2017 from Institutional Investors by investor type? (millions)Please ensure that the total values provided match the values you entered in Q3 | B22: q4 | C22: Pension funds | D22: q4_1 | E22: currency
A23: How much capital was raised for this vehicle in 2017 from Institutional Investors by investor type? (millions)Please ensure that the total values provided match the values you entered in Q4 | B23: q4 | C23: Insurance companies | D23: q4_2 | E23: currency
A24: How much capital was raised for this vehicle in 2017 from Institutional Investors by investor type? (millions)Please ensure that the total values provided match the values you entered in Q5 | B24: q4 | C24: Sovereign wealth fund | D24: q4_3 | E24: currency
A25: How much capital was raised for this vehicle in 2017 from Institutional Investors by investor type? (millions)Please ensure that the total values provided match the values you entered in Q6 | B25: q4 | C25: Government institutions | D25: q4_4 | E25: currency
A26: How much capital was raised for this vehicle in 2017 from Institutional Investors by investor type? (millions)Please ensure that the total values provided match the values you entered in Q7 | B26: q4 | C26: Charities, foundations, non-profit organisations | D26: q4_5 | E26: currency
A27: How much capital was raised for this vehicle in 2017 from Institutional Investors by investor type? (millions)Please ensure that the total values provided match the values you entered in Q8 | B27: q4 | C27: Fund of funds | D27: q4_6 | E27: currency
A28: How much capital was raised for this vehicle in 2017 from Institutional Investors by investor type? (millions)Please ensure that the total values provided match the values you entered in Q9 | B28: q4 | C28: High net worth individulas / Family offices | D28: q4_7 | E28: currency
A29: How much capital was raised for this vehicle in 2017 from Institutional Investors by investor type? (millions)Please ensure that the total values provided match the values you entered in Q10 | B29: q4 | C29: Other (please specify) | D29: q4_8 | E29: currency
... A40: Would you like the name of your company to be included in the list of participants? | B40: q8 | C40: Response | D40: q8 | E40: TEXT

Sheet df_edited_headers
A1: keep | B1: respondentId | C1: collectorId | D1: dateStarted | E1: dateEnded | F1: ipAddress | G1: email | H1: firstname | I1: lastname | J1: customData1 | K1: qfundname | L1: universeFundID | M1: loan_strategy | N1: country_strategy | O1: first_closing_year | P1: qcurrency | Q1: q1 | R1: q2 | S1: q2other | T1: q3 | U1: q4_1 | V1: q4_2 | W1: q4_3 | X1: q4_4 | Y1: q4_5 | Z1: q4_6 | AA1: q4_7 | AB1: q4_8 | AC1: q5_1 | AD1: q5_2 | AE1: q5_3 | AF1: q5_4 | AG1: q5_5 | AH1: q6_1 | AI1: q6_2 | AJ1: q6_3 | AK1: q6_4 | AL1: q7 | AM1: q8
B2: Respondent ID | C2: Collector ID | D2: Start Date | E2: End Date | F2: IP Address | G2: Email Address | H2: First Name | I2: Last Name | J2: Custom Data 1 | K2: Vehicle ID / Name | L2: ID | M2: LoanStrategy | N2: CountryStrategy | O2: Vintage | P2: Currency | Q2: Did your company raise capital for this vehicle in 2017? | R2: Please state the reason why? | S2: Column13 | T2: What was the total amount of capital raised for this vehicle in 2017? (millions) | U2: How much capital was raised for this vehicle in 2017 from Institutional Investors by investor type? (millions)Please ensure that the total values provided match the values you entered in Q3 | V2: Column16 | W2: Column17 | X2: Column18 | Y2: Column19 | Z2: Column20 | AA2: Column21 | AB2: Column22 | AC2: How much capital was raised for this vehicle in 2017 from Institutional Investors by investor domicile? (millions)Please ensure that the total values provided match the values you entered in Q3 - total capital raised | AD2: Column24 | AE2: Column25 | AF2: Column26 | AG2: Column27 | AH2: What percentage of the total capital was raised via...?Total figure should sum up to 100% | AI2: Column29 | AJ2: Column30 | AK2: Column31 | AL2: How do you expect capital raising activities to develop for non-listed real estate funds over the next two years? | AM2: Would you like the name of your company to be included in the list of participants?
K3: Open-Ended Response | L3: =VLOOKUP(DFsmonkeyCompl9[[#This Row],[Vehicle ID / Name]],DFanalysis!A:E,2,FALSE) -> #N/A | M3: =VLOOKUP(DFsmonkeyCompl9[[#This Row],[Vehicle ID / Name]],DFanalysis!A:F,3,FALSE) -> #N/A | N3: =VLOOKUP(DFsmonkeyCompl9[[#This Row],[Vehicle ID / Name]],DFanalysis!A:G,4,FALSE) -> #N/A | O3: =VLOOKUP(DFsmonkeyCompl9[[#This Row],[Vehicle ID / Name]],DFanalysis!A:H,5,FALSE) -> #N/A | P3: =VLOOKUP(DFsmonkeyCompl9[[#This Row],[Vehicle ID / Name]],DFanalysis!A:I,8,FALSE) -> #N/A | Q3: Response | R3: Response | S3: Other (please specify) | T3: Open-Ended Response | U3: Pension funds | V3: Insurance companies | W3: Sovereign wealth fund | X3: Government institutions | Y3: Charities, foundations, non-profit organisations | Z3: Fund of funds | AA3: High net worth individulas / Family offices | AB3: Other (please specify) | AC3: Europe | AD3: Asia Pacific | AE3: North America | AF3: South America | AG3: Africa | AH3: Placement agent (%) | AI3: Investors contacting you directly (%) | AJ3: Your own direct relationship with investors (%) | AK3: Other (%) | AL3: Response | AM3: Response
A4: yes | B4: 6714543559 | C4: 162871627 | D4: 43154.678 | E4: 43154.678 | F4: 108.171.128.175 | K4: LaSalle Residential Finance Fund III | L4: =VLOOKUP(DFsmonkeyCompl9[[#This Row],[Vehicle ID / Name]],DFanalysis!A:E,2,FALSE) -> N/A | M4: =VLOOKUP(DFsmonkeyCompl9[[#This Row],[Vehicle ID / Name]],DFanalysis!A:F,3,FALSE) -> Senior | N4: =VLOOKUP(DFsmonkeyCompl9[[#This Row],[Vehicle ID / Name]],DFanalysis!A:G,4,FALSE) -> UK | O4: =VLOOKUP(DFsmonkeyCompl9[[#This Row],[Vehicle ID / Name]],DFanalysis!A:H,5,FALSE) -> 2017 | P4: =VLOOKUP(DFsmonkeyCompl9[[#This Row],[Vehicle ID / Name]],DFanalysis!A:I,8,FALSE) -> GBP | Q4: Yes | T4: 264 | U4: 95 | AB4: 5 | AC4: 100 | AJ4: 100 | AL4: No change | AM4: Yes
A5: yes | B5: 6714482559 | C5: 162871627 | D5: 43154.661 | E5: 43154.677 | F5: 108.171.128.175 | K5: LaSalle Real Estate Debt Strategies III | L5: =VLOOKUP(DFsmonkeyCompl9[[#This Row],[Vehicle ID / Name]],DFanalysis!A:E,2,FALSE) -> N/A | M5: =VLOOKUP(DFsmonkeyCompl9[[#This Row],[Vehicle ID / Name]],DFanalysis!A:F,3,FALSE) -> Mixed: Senior + Subordinated | N5: =VLOOKUP(DFsmonkeyCompl9[[#This Row],[Vehicle ID / Name]],DFanalysis!A:G,4,FALSE) -> Western Europe excluding Nordics, Southern Europe and UK | O5: =VLOOKUP(DFsmonkeyCompl9[[#This Row],[Vehicle ID / Name]],DFanalysis!A:H,5,FALSE) -> 2017 | P5: =VLOOKUP(DFsmonkeyCompl9[[#This Row],[Vehicle ID / Name]],DFanalysis!A:I,8,FALSE) -> GBP | Q5: Yes | T5: 804 | U5: 68 | V5: 15 | X5: 10 | AB5: 8 | AC5: 62 | AD5: 35 | AE5: 2 | AH5: 0 | AI5: 0 | AJ5: 75 | AK5: 25 | AL5: No change | AM5: Yes
A6: yes | B6: 6713894109 | C6: 162871627 | D6: 43154.419 | E6: 43154.429 | F6: 185.29.113.86 | K6: Brunswick Real Estate Capital II | L6: =VLOOKUP(DFsmonkeyCompl9[[#This Row],[Vehicle ID / Name]],DFanalysis!A:E,2,FALSE) -> N/A | M6: =VLOOKUP(DFsmonkeyCompl9[[#This Row],[Vehicle ID / Name]],DFanalysis!A:F,3,FALSE) -> Senior | N6: =VLOOKUP(DFsmonkeyCompl9[[#This Row],[Vehicle ID / Name]],DFanalysis!A:G,4,FALSE) -> Nordics (Denmark, Finland, Norway and Sweden) | O6: =VLOOKUP(DFsmonkeyCompl9[[#This Row],[Vehicle ID / Name]],DFanalysis!A:H,5,FALSE) -> 2016 | P6: =VLOOKUP(DFsmonkeyCompl9[[#This Row],[Vehicle ID / Name]],DFanalysis!A:I,8,FALSE) -> SEK | Q6: Yes | T6: 16 | AB6: 16 | AC6: 16 | AJ6: 100 | AL6: Increase | AM6: No
A7: yes | B7: 6711242519 | C7: 162871627 | D7: 43153.413 | E7: 43153.568 | F7: 194.143.182.29 | K7: Pramerica Real Estate Capital VI, LP | L7: =VLOOKUP(DFsmonkeyCompl9[[#This Row],[Vehicle ID / Name]],DFanalysis!A:E,2,FALSE) -> 17370 | M7: =VLOOKUP(DFsmonkeyCompl9[[#This Row],[Vehicle ID / Name]],DFanalysis!A:F,3,FALSE) -> Subordinated: Junior + Mezzanine + Preferred equity | N7: =VLOOKUP(DFsmonkeyCompl9[[#This Row],[Vehicle ID / Name]],DFanalysis!A:G,4,FALSE) -> Pan-Europe | O7: =VLOOKUP(DFsmonkeyCompl9[[#This Row],[Vehicle ID / Name]],DFanalysis!A:H,5,FALSE) -> 2013 | P7: =VLOOKUP(DFsmonkeyCompl9[[#This Row],[Vehicle ID / Name]],DFanalysis!A:I,8,FALSE) -> GBP | Q7: Yes | T7: 1017 | U7: 793 | V7: 70 | W7: 52 | X7: 70 | Y7: 31 | AB7: 1 | AC7: 231 | AD7: 47 | AE7: 739 | AJ7: 97 | AK7: 3 | AL7: Increase | AM7: Yes
A8: yes | B8: 6708670587 | C8: 162871627 | D8: 43152.483 | E8: 43152.487 | F8: 213.251.23.92 | K8: ICG-Longbow Senior Debt Programme Vintage III | L8: =VLOOKUP(DFsmonkeyCompl9[[#This Row],[Vehicle ID / Name]],DFanalysis!A:E,2,FALSE) -> 18137 | M8: =VLOOKUP(DFsmonkeyCompl9[[#This Row],[Vehicle ID / Name]],DFanalysis!A:F,3,FALSE) -> Senior | N8: =VLOOKUP(DFsmonkeyCompl9[[#This Row],[Vehicle ID / Name]],DFanalysis!A:G,4,FALSE) -> UK | O8: =VLOOKUP(DFsmonkeyCompl9[[#This Row],[Vehicle ID / Name]],DFanalysis!A:H,5,FALSE) -> 2016 | P8: =VLOOKUP(DFsmonkeyCompl9[[#This Row],[Vehicle ID / Name]],DFanalysis!A:I,8,FALSE) -> GBP | Q8: Yes | T8: 370 | U8: 370 | AC8: 370 | AJ8: 100 | AL8: Increase | AM8: Yes
A9: yes | B9: 6696842089 | C9: 162871627 | D9: 43146.433 | E9: 43146.449 | F9: 192.166.106.126 | K9: DE000DK0AYR6 / Deka Realkredit Klassik | L9: =VLOOKUP(DFsmonkeyCompl9[[#This Row],[Vehicle ID / Name]],DFanalysis!A:E,2,FALSE) -> 17375 | M9: =VLOOKUP(DFsmonkeyCompl9[[#This Row],[Vehicle ID / Name]],DFanalysis!A:F,3,FALSE) -> Senior | N9: =VLOOKUP(DFsmonkeyCompl9[[#This Row],[Vehicle ID / Name]],DFanalysis!A:G,4,FALSE) -> Western Europe excluding Nordics, Southern Europe and UK | O9: =VLOOKUP(DFsmonkeyCompl9[[#This Row],[Vehicle ID / Name]],DFanalysis!A:H,5,FALSE) -> 2009 | P9: =VLOOKUP(DFsmonkeyCompl9[[#This Row],[Vehicle ID / Name]],DFanalysis!A:I,8,FALSE) -> EUR | Q9: Yes | T9: 68 | AB9: 100 | AC9: 68 | AI9: 100 | AL9: Increase | AM9: Yes
A10: yes | B10: 6692350030 | C10: 162871627 | D10: 43144.712 | E10: 43144.713 | F10: 194.140.225.246 | K10: SELFII | L10: =VLOOKUP(DFsmonkeyCompl9[[#This Row],[Vehicle ID / Name]],DFanalysis!A:E,2,FALSE) -> 18134 | M10: =VLOOKUP(DFsmonkeyCompl9[[#This Row],[Vehicle ID / Name]],DFanalysis!A:F,3,FALSE) -> Senior | N10: =VLOOKUP(DFsmonkeyCompl9[[#This Row],[Vehicle ID / Name]],DFanalysis!A:G,4,FALSE) -> Western Europe excluding Nordics, Southern Europe and UK | O10: =VLOOKUP(DFsmonkeyCompl9[[#This Row],[Vehicle ID / Name]],DFanalysis!A:H,5,FALSE) -> 2016 | P10: =VLOOKUP(DFsmonkeyCompl9[[#This Row],[Vehicle ID / Name]],DFanalysis!A:I,8,FALSE) -> EUR | Q10: Yes | T10: 126 | V10: 126 | AC10: 126 | AJ10: 100 | AL10: Increase | AM10: Yes
A11: yes | B11: 6662314847 | C11: 162871627 | D11: 43130.735 | E11: 43130.736 | F11: 217.10.134.222 | K11: DRC UK Whole Loan Fund | L11: =VLOOKUP(DFsmonkeyCompl9[[#This Row],[Vehicle ID / Name]],DFanalysis!A:E,2,FALSE) -> N/A | M11: =VLOOKUP(DFsmonkeyCompl9[[#This Row],[Vehicle ID / Name]],DFanalysis!A:F,3,FALSE) -> Whole loans | N11: =VLOOKUP(DFsmonkeyCompl9[[#This Row],[Vehicle ID / Name]],DFanalysis!A:G,4,FALSE) -> Western Europe excluding Nordics, Southern Europe and UK | O11: =VLOOKUP(DFsmonkeyCompl9[[#This Row],[Vehicle ID / Name]],DFanalysis!A:H,5,FALSE) -> 2016 | P11: =VLOOKUP(DFsmonkeyCompl9[[#This Row],[Vehicle ID / Name]],DFanalysis!A:I,8,FALSE) -> GBP | Q11: Yes | T11: 211 | U11: 211 | V11: 0 | W11: 0 | X11: 0 | Y11: 0 | Z11: 0 | AA11: 0 | AB11: 0 | AC11: 211 | AD11: 0 | AE11: 0 | AF11: 0 | AG11: 0 | AH11: 0 | AI11: 0 | AJ11: 100 | AK11: 0 | AL11: Increase | AM11: Yes
A12: yes | B12: 6662228763 | C12: 162871627 | D12: 43130.712 | E12: 43130.733 | F12: 217.10.134.222 | K12: DRC European Real Estate Debt Fund III | L12: =VLOOKUP(DFsmonkeyCompl9[[#This Row],[Vehicle ID / Name]],DFanalysis!A:E,2,FALSE) -> 18127 | M12: =VLOOKUP(DFsmonkeyCompl9[[#This Row],[Vehicle ID / Name]],DFanalysis!A:F,3,FALSE) -> Senior | N12: =VLOOKUP(DFsmonkeyCompl9[[#This Row],[Vehicle ID / Name]],DFanalysis!A:G,4,FALSE) -> Western Europe excluding Nordics, Southern Europe and UK | O12: =VLOOKUP(DFsmonkeyCompl9[[#This Row],[Vehicle ID / Name]],DFanalysis!A:H,5,FALSE) -> 2015 | P12: =VLOOKUP(DFsmonkeyCompl9[[#This Row],[Vehicle ID / Name]],DFanalysis!A:I,8,FALSE) -> GBP | Q12: Yes | T12: 268 | U12: 218 | V12: 33 | W12: 0 | X12: 0 | Y12: 0 | Z12: 14 | AA12: 0 | AB12: 3 | AC12: 204 | AD12: 0 | AE12: 64 | AF12: 0 | AG12: 0 | AH12: 62 | AI12: 7 | AJ12: 31 | AK12: 0 | AL12: Increase | AM12: Yes
A13: yes | B13: 6647044991 | C13: 162871627 | D13: 43123.541 | E13: 43123.543 | F13: 80.169.207.154 | K13: AgFe Real Estate Senior Debt Fund II | L13: =VLOOKUP(DFsmonkeyCompl9[[#This Row],[Vehicle ID / Name]],DFanalysis!A:E,2,FALSE) -> N/A | M13: =VLOOKUP(DFsmonkeyCompl9[[#This Row],[Vehicle ID / Name]],DFanalysis!A:F,3,FALSE) -> Mixed: Senior + Subordinated + Preferred equity | N13: =VLOOKUP(DFsmonkeyCompl9[[#This Row],[Vehicle ID / Name]],DFanalysis!A:G,4,FALSE) -> UK | O13: =VLOOKUP(DFsmonkeyCompl9[[#This Row],[Vehicle ID / Name]],DFanalysis!A:H,5,FALSE) -> 2016 | P13: =VLOOKUP(DFsmonkeyCompl9[[#This Row],[Vehicle ID / Name]],DFanalysis!A:I,8,FALSE) -> GBP | Q13: No | R13: Other (please specify) | S13: Fundraising environment | AL13: Increase | AM13: Yes

Sheet FoFsmonkeyCompl
A1: Respondent ID | B1: Collector ID | C1: Start Date | D1: End Date | E1: IP Address | F1: Email Address | G1: First Name | H1: Last Name | I1: Custom Data 1 | J1: Vehicle ID / Name | K1: Did your company raise capital for this vehicle in 2017? | L1: Please state the reason why? | M1: Column13 | N1: What was the total amount of capital raised for this vehicle in 2017? (millions) | O1: How much capital was raised for this vehicle in 2017 from Institutional Investors by investor type? (millions)Please ensure that the total values provided match the values you entered in Q3 | P1: Column16 | Q1: Column17 | R1: Column18 | S1: Column19 | T1: Column20 | U1: Column21 | V1: Column22 | W1: How much capital was raised for this vehicle in 2017 from Institutional Investors by investor domicile? (millions)Please ensure that the total values provided match the values you entered in Q3 | X1: Column24 | Y1: Column25 | Z1: Column26 | AA1: Column27 | AB1: What percentage of the total capital was raised via...?Total figure should sum up to 100% | AC1: Column29 | AD1: Column30 | AE1: Column31 | AF1: How do you expect capital raising activities to develop for non-listed real estate funds over the next two years? | AG1: Would you like the name of your company to be included in the list of participants?
J2: Open-Ended Response | K2: Response | L2: Response | M2: Other (please specify) | N2: Open-Ended Response | O2: Pension funds | P2: Insurance companies | Q2: Sovereign wealth funds | R2: Government institutions | S2: Charities, foundations, non-profit organisations | T2: Fund of funds | U2: High net worth individuals / Family offices | V2: Other | W2: Europe | X2: Asia Pacific | Y2: North America | Z2: South America | AA2: Africa | AB2: Placement agent (%) | AC2: Investors contacting you directly (%) | AD2: Your own direct relationship with investors (%) | AE2: Other (%) | AF2: Response | AG2: Response
A3: 6712340289 | B3: 163310093 | C3: 43153.779 | D3: 43153.795 | E3: 185.69.116.107 | J3: CBRE Global Investment Partners Segregated Accounts | K3: Yes | N3: 1788 | O3: 1368 | P3: 364 | R3: 56 | W3: 1462 | X3: 184 | Y3: 142 | AB3: 100 | AF3: No change | AG3: Yes
A4: 6712315962 | B4: 163310093 | C4: 43153.772 | D4: 43153.775 | E4: 185.69.116.107 | J4: CBRE Global Investment Partners UK Osiris Property Fund | K4: Yes | N4: 12 | O4: 12 | W4: 12 | AB4: 100 | AF4: No change | AG4: Yes
A5: 6712267225 | B5: 163310093 | C5: 43153.49 | D5: 43153.769 | E5: 185.69.116.107 | J5: CBRE Global Investment Partners Global Alpha Fund | K5: Yes | N5: 1054 | O5: 559 | P5: 70 | Q5: 50 | R5: 166 | S5: 77 | T5: 22 | V5: 110 | W5: 521 | X5: 187 | Y5: 346 | AB5: 100 | AF5: No change | AG5: Yes
A6: 6709183679 | B6: 163310093 | C6: 43152.667 | D6: 43152.798 | E6: 185.69.116.107 | J6: CBRE Global Investment Partners Global Alpha Fund | K6: Yes
A7: 6709173161 | B7: 163310093 | C7: 43152.664 | D7: 43152.665 | E7: 185.23.36.251 | J7: Altan IV Global IICIICIL | K7: Yes | N7: 291 | O7: 20 | P7: 20 | U7: 251 | W7: 291 | AD7: 100 | AF7: Increase | AG7: Yes
A8: 6694825905 | B8: 163310093 | C8: 43145.659 | D8: 43145.66 | E8: 77.59.199.231 | J8: Crown Small Cap Real Estate Fund II | K8: No | L8: Other (please specify) | M8: Completing investment period | AF8: Increase | AG8: No
A9: 6692012461 | B9: 163310093 | C9: 43144.623 | D9: 43144.625 | E9: 185.69.116.106 | J9: CBRE Global Investment Partners Global Alpha Fund Series FCP-SIF | K9: Yes
A10: 6689366577 | B10: 163310093 | C10: 43143.606 | D10: 43143.609 | E10: 195.191.225.4 | J10: HI-Immobilien-Multi Manager-Fonds III | K10: Yes | N10: 107 | O10: 7 | V10: 100 | W10: 107 | AD10: 100 | AF10: No change | AG10: Yes
A11: 6689361078 | B11: 163310093 | C11: 43143.604 | D11: 43143.606 | E11: 195.191.225.4 | J11: HI-Immobilien-Multi Manager-Fonds II | K11: Yes | N11: 71 | O11: 19 | P11: 11 | V11: 41 | W11: 71 | AD11: 100 | AF11: No change | AG11: Yes
A12: 6662580095 | B12: 163310093 | C12: 43130.802 | D12: 43130.802 | E12: 77.59.199.231 | J12: Crown Small Cap Real Estate Fund II | K12: No | L12: Other (please specify) | M12: Already raised | AF12: No change | AG12: No
A13: 6661849274 | B13: 163310093 | C13: 43130.611 | D13: 43130.617 | E13: 212.114.207.108 | J13: PATRIZIA Multi Managers Global IV | K13: No

Sheet fof_edited_headers
A1: keep | B1: respondentId | C1: collectorId | D1: dateStarted | E1: dateEnded | F1: ipAddress | G1: email | H1: firstname | I1: lastname | J1: customData1 | K1: qfundname | L1: universeFundID | M1: qstyle | N1: qfundstructure | O1: first_closing_year | P1: qcurrency | Q1: q1 | R1: q2 | S1: q2other | T1: q3 | U1: q4_1 | V1: q4_2 | W1: q4_3 | X1: q4_4 | Y1: q4_5 | Z1: q4_6 | AA1: q4_7 | AB1: q4_8 | AC1: q5_1 | AD1: q5_2 | AE1: q5_3 | AF1: q5_4 | AG1: q5_5 | AH1: q6_1 | AI1: q6_2 | AJ1: q6_3 | AK1: q6_4 | AL1: q7 | AM1: q8
B2: Respondent ID | C2: Collector ID | D2: Start Date | E2: End Date | F2: IP Address | G2: Email Address | H2: First Name | I2: Last Name | J2: Custom Data 1 | K2: Vehicle ID / Name | L2: ID | M2: Style | N2: Structure | O2: Vintage | P2: Currency | Q2: Did your company raise capital for this vehicle in 2017? | R2: Please state the reason why? | S2: Column13 | T2: What was the total amount of capital raised for this vehicle in 2017? (millions) | U2: How much capital was raised for this vehicle in 2017 from Institutional Investors by investor type? (millions)Please ensure that the total values provided match the values you entered in Q3 | V2: Column16 | W2: Column17 | X2: Column18 | Y2: Column19 | Z2: Column20 | AA2: Column21 | AB2: Column22 | AC2: How much capital was raised for this vehicle in 2017 from Institutional Investors by investor domicile? (millions)Please ensure that the total values provided match the values you entered in Q3 | AD2: Column24 | AE2: Column25 | AF2: Column26 | AG2: Column27 | AH2: What percentage of the total capital was raised via...?Total figure should sum up to 100% | AI2: Column29 | AJ2: Column30 | AK2: Column31 | AL2: How do you expect capital raising activities to develop for non-listed real estate funds over the next two years? | AM2: Would you like the name of your company to be included in the list of participants?
K3: Open-Ended Response | L3: =VLOOKUP(FoFsmonkeyCompl10[[#This Row],[Vehicle ID / Name]],FoFsanalysis!A:E,2,FALSE) -> #N/A | M3: =VLOOKUP(FoFsmonkeyCompl10[[#This Row],[Vehicle ID / Name]],FoFsanalysis!A:F,3,FALSE) -> #N/A | N3: =VLOOKUP(FoFsmonkeyCompl10[[#This Row],[Vehicle ID / Name]],FoFsanalysis!A:G,4,FALSE) -> #N/A | O3: =VLOOKUP(FoFsmonkeyCompl10[[#This Row],[Vehicle ID / Name]],FoFsanalysis!A:H,5,FALSE) -> #N/A | P3: =VLOOKUP(FoFsmonkeyCompl10[[#This Row],[Vehicle ID / Name]],FoFsanalysis!A:H,8,FALSE) -> #N/A | Q3: Response | R3: Response | S3: Other (please specify) | T3: Open-Ended Response | U3: Pension funds | V3: Insurance companies | W3: Sovereign wealth funds | X3: Government institutions | Y3: Charities, foundations, non-profit organisations | Z3: Fund of funds | AA3: High net worth individuals / Family offices | AB3: Other | AC3: Europe | AD3: Asia Pacific | AE3: North America | AF3: South America | AG3: Africa | AH3: Placement agent (%) | AI3: Investors contacting you directly (%) | AJ3: Your own direct relationship with investors (%) | AK3: Other (%) | AL3: Response | AM3: Response
A4: yes | B4: 6712340289 | C4: 163310093 | D4: 43153.779 | E4: 43153.795 | F4: 185.69.116.107 | K4: CBRE Global Investment Partners Segregated Accounts | L4: =VLOOKUP(FoFsmonkeyCompl10[[#This Row],[Vehicle ID / Name]],FoFsanalysis!A:E,2,FALSE) -> N/A | M4: =VLOOKUP(FoFsmonkeyCompl10[[#This Row],[Vehicle ID / Name]],FoFsanalysis!A:F,3,FALSE) -> Core | N4: =VLOOKUP(FoFsmonkeyCompl10[[#This Row],[Vehicle ID / Name]],FoFsanalysis!A:G,4,FALSE) -> Open end | P4: =VLOOKUP(FoFsmonkeyCompl10[[#This Row],[Vehicle ID / Name]],FoFsanalysis!A:H,8,FALSE) -> EUR | Q4: Yes | T4: 1788 | U4: 1368 | V4: 364 | X4: 56 | AC4: 1462 | AD4: 184 | AE4: 142 | AH4: 100 | AL4: No change | AM4: Yes
A5: yes | B5: 6712315962 | C5: 163310093 | D5: 43153.772 | E5: 43153.775 | F5: 185.69.116.107 | K5: CBRE Global Investment Partners UK Osiris Property Fund | L5: =VLOOKUP(FoFsmonkeyCompl10[[#This Row],[Vehicle ID / Name]],FoFsanalysis!A:E,2,FALSE) -> 17437 | M5: =VLOOKUP(FoFsmonkeyCompl10[[#This Row],[Vehicle ID / Name]],FoFsanalysis!A:F,3,FALSE) -> Core | N5: =VLOOKUP(FoFsmonkeyCompl10[[#This Row],[Vehicle ID / Name]],FoFsanalysis!A:G,4,FALSE) -> Open end | O5: =VLOOKUP(FoFsmonkeyCompl10[[#This Row],[Vehicle ID / Name]],FoFsanalysis!A:H,5,FALSE) -> 2003 | P5: =VLOOKUP(FoFsmonkeyCompl10[[#This Row],[Vehicle ID / Name]],FoFsanalysis!A:H,8,FALSE) -> GBP | Q5: Yes | T5: 12 | U5: 12 | AC5: 12 | AH5: 100 | AL5: No change | AM5: Yes
A6: yes | B6: 6712267225 | C6: 163310093 | D6: 43153.49 | E6: 43153.769 | F6: 185.69.116.107 | K6: CBRE Global Investment Partners Global Alpha Fund | L6: =VLOOKUP(FoFsmonkeyCompl10[[#This Row],[Vehicle ID / Name]],FoFsanalysis!A:E,2,FALSE) -> 17454 | M6: =VLOOKUP(FoFsmonkeyCompl10[[#This Row],[Vehicle ID / Name]],FoFsanalysis!A:F,3,FALSE) -> Core | N6: =VLOOKUP(FoFsmonkeyCompl10[[#This Row],[Vehicle ID / Name]],FoFsanalysis!A:G,4,FALSE) -> Open end | O6: =VLOOKUP(FoFsmonkeyCompl10[[#This Row],[Vehicle ID / Name]],FoFsanalysis!A:H,5,FALSE) -> 2010 | P6: =VLOOKUP(FoFsmonkeyCompl10[[#This Row],[Vehicle ID / Name]],FoFsanalysis!A:H,8,FALSE) -> USD | Q6: Yes | T6: 1054 | U6: 559 | V6: 70 | W6: 50 | X6: 166 | Y6: 77 | Z6: 22 | AB6: 110 | AC6: 521 | AD6: 187 | AE6: 346 | AH6: 100 | AL6: No change | AM6: Yes
A7: yes | B7: 6709183679 | C7: 163310093 | D7: 43152.667 | E7: 43152.798 | F7: 185.69.116.107 | K7: CBRE Global Investment Partners Global Alpha Fund | L7: =VLOOKUP(FoFsmonkeyCompl10[[#This Row],[Vehicle ID / Name]],FoFsanalysis!A:E,2,FALSE) -> 17454 | M7: =VLOOKUP(FoFsmonkeyCompl10[[#This Row],[Vehicle ID / Name]],FoFsanalysis!A:F,3,FALSE) -> Core | N7: =VLOOKUP(FoFsmonkeyCompl10[[#This Row],[Vehicle ID / Name]],FoFsanalysis!A:G,4,FALSE) -> Open end | O7: =VLOOKUP(FoFsmonkeyCompl10[[#This Row],[Vehicle ID / Name]],FoFsanalysis!A:H,5,FALSE) -> 2010 | P7: =VLOOKUP(FoFsmonkeyCompl10[[#This Row],[Vehicle ID / Name]],FoFsanalysis!A:H,8,FALSE) -> USD | Q7: Yes
A8: yes | B8: 6709173161 | C8: 163310093 | D8: 43152.664 | E8: 43152.665 | F8: 185.23.36.251 | K8: Altan IV Global IICIICIL | L8: =VLOOKUP(FoFsmonkeyCompl10[[#This Row],[Vehicle ID / Name]],FoFsanalysis!A:E,2,FALSE) -> N/A | M8: =VLOOKUP(FoFsmonkeyCompl10[[#This Row],[Vehicle ID / Name]],FoFsanalysis!A:F,3,FALSE) -> Opportunity | N8: =VLOOKUP(FoFsmonkeyCompl10[[#This Row],[Vehicle ID / Name]],FoFsanalysis!A:G,4,FALSE) -> Closed end | O8: =VLOOKUP(FoFsmonkeyCompl10[[#This Row],[Vehicle ID / Name]],FoFsanalysis!A:H,5,FALSE) -> 2017 | P8: =VLOOKUP(FoFsmonkeyCompl10[[#This Row],[Vehicle ID / Name]],FoFsanalysis!A:H,8,FALSE) -> EUR | Q8: Yes | T8: 291 | U8: 20 | V8: 20 | AA8: 251 | AC8: 291 | AJ8: 100 | AL8: Increase | AM8: Yes
A9: yes | B9: 6694825905 | C9: 163310093 | D9: 43145.659 | E9: 43145.66 | F9: 77.59.199.231 | K9: Crown Small Cap Real Estate Fund II | L9: =VLOOKUP(FoFsmonkeyCompl10[[#This Row],[Vehicle ID / Name]],FoFsanalysis!A:E,2,FALSE) -> 17661 | M9: =VLOOKUP(FoFsmonkeyCompl10[[#This Row],[Vehicle ID / Name]],FoFsanalysis!A:F,3,FALSE) -> Oppurtunity | N9: =VLOOKUP(FoFsmonkeyCompl10[[#This Row],[Vehicle ID / Name]],FoFsanalysis!A:G,4,FALSE) -> Closed end | O9: =VLOOKUP(FoFsmonkeyCompl10[[#This Row],[Vehicle ID / Name]],FoFsanalysis!A:H,5,FALSE) -> 2014 | P9: =VLOOKUP(FoFsmonkeyCompl10[[#This Row],[Vehicle ID / Name]],FoFsanalysis!A:H,8,FALSE) -> USD | Q9: No | R9: Other (please specify) | S9: Completing investment period | AL9: Increase | AM9: No
A10: yes | B10: 6692012461 | C10: 163310093 | D10: 43144.623 | E10: 43144.625 | F10: 185.69.116.106 | K10: CBRE Global Investment Partners Global Alpha Fund Series FCP-SIF | L10: =VLOOKUP(FoFsmonkeyCompl10[[#This Row],[Vehicle ID / Name]],FoFsanalysis!A:E,2,FALSE) -> N/A | M10: =VLOOKUP(FoFsmonkeyCompl10[[#This Row],[Vehicle ID / Name]],FoFsanalysis!A:F,3,FALSE) -> Core | N10: =VLOOKUP(FoFsmonkeyCompl10[[#This Row],[Vehicle ID / Name]],FoFsanalysis!A:G,4,FALSE) -> Open end | O10: =VLOOKUP(FoFsmonkeyCompl10[[#This Row],[Vehicle ID / Name]],FoFsanalysis!A:H,5,FALSE) -> 2010 | P10: =VLOOKUP(FoFsmonkeyCompl10[[#This Row],[Vehicle ID / Name]],FoFsanalysis!A:H,8,FALSE) -> USD | Q10: Yes
A11: yes | B11: 6689366577 | C11: 163310093 | D11: 43143.606 | E11: 43143.609 | F11: 195.191.225.4 | K11: HI-Immobilien-Multi Manager-Fonds III | L11: =VLOOKUP(FoFsmonkeyCompl10[[#This Row],[Vehicle ID / Name]],FoFsanalysis!A:E,2,FALSE) -> N/A | M11: =VLOOKUP(FoFsmonkeyCompl10[[#This Row],[Vehicle ID / Name]],FoFsanalysis!A:F,3,FALSE) -> Core | N11: =VLOOKUP(FoFsmonkeyCompl10[[#This Row],[Vehicle ID / Name]],FoFsanalysis!A:G,4,FALSE) -> Open end | O11: =VLOOKUP(FoFsmonkeyCompl10[[#This Row],[Vehicle ID / Name]],FoFsanalysis!A:H,5,FALSE) -> 2017 | P11: =VLOOKUP(FoFsmonkeyCompl10[[#This Row],[Vehicle ID / Name]],FoFsanalysis!A:H,8,FALSE) -> EUR | Q11: Yes | T11: 107 | U11: 7 | AB11: 100 | AC11: 107 | AJ11: 100 | AL11: No change | AM11: Yes
A12: yes | B12: 6689361078 | C12: 163310093 | D12: 43143.604 | E12: 43143.606 | F12: 195.191.225.4 | K12: HI-Immobilien-Multi Manager-Fonds II | L12: =VLOOKUP(FoFsmonkeyCompl10[[#This Row],[Vehicle ID / Name]],FoFsanalysis!A:E,2,FALSE) -> N/A | M12: =VLOOKUP(FoFsmonkeyCompl10[[#This Row],[Vehicle ID / Name]],FoFsanalysis!A:F,3,FALSE) -> Core | N12: =VLOOKUP(FoFsmonkeyCompl10[[#This Row],[Vehicle ID / Name]],FoFsanalysis!A:G,4,FALSE) -> Open end | O12: =VLOOKUP(FoFsmonkeyCompl10[[#This Row],[Vehicle ID / Name]],FoFsanalysis!A:H,5,FALSE) -> 2016 | P12: =VLOOKUP(FoFsmonkeyCompl10[[#This Row],[Vehicle ID / Name]],FoFsanalysis!A:H,8,FALSE) -> EUR | Q12: Yes | T12: 71 | U12: 19 | V12: 11 | AB12: 41 | AC12: 71 | AJ12: 100 | AL12: No change | AM12: Yes
A13: yes | B13: 6662580095 | C13: 163310093 | D13: 43130.802 | E13: 43130.802 | F13: 77.59.199.231 | K13: Crown Small Cap Real Estate Fund II | L13: =VLOOKUP(FoFsmonkeyCompl10[[#This Row],[Vehicle ID / Name]],FoFsanalysis!A:E,2,FALSE) -> 17661 | M13: =VLOOKUP(FoFsmonkeyCompl10[[#This Row],[Vehicle ID / Name]],FoFsanalysis!A:F,3,FALSE) -> Oppurtunity | N13: =VLOOKUP(FoFsmonkeyCompl10[[#This Row],[Vehicle ID / Name]],FoFsanalysis!A:G,4,FALSE) -> Closed end | O13: =VLOOKUP(FoFsmonkeyCompl10[[#This Row],[Vehicle ID / Name]],FoFsanalysis!A:H,5,FALSE) -> 2014 | P13: =VLOOKUP(FoFsmonkeyCompl10[[#This Row],[Vehicle ID / Name]],FoFsanalysis!A:H,8,FALSE) -> USD | Q13: No | R13: Other (please specify) | S13: Already raised | AL13: No change | AM13: No
A14: yes | B14: 6661849274 | C14: 163310093 | D14: 43130.611 | E14: 43130.617 | F14: 212.114.207.108 | K14: PATRIZIA Multi Managers Global IV | L14: =VLOOKUP(FoFsmonkeyCompl10[[#This Row],[Vehicle ID / Name]],FoFsanalysis!A:E,2,FALSE) -> N/A | M14: =VLOOKUP(FoFsmonkeyCompl10[[#This Row],[Vehicle ID / Name]],FoFsanalysis!A:F,3,FALSE) -> Value added | N14: =VLOOKUP(FoFsmonkeyCompl10[[#This Row],[Vehicle ID / Name]],FoFsanalysis!A:G,4,FALSE) -> Open end | O14: =VLOOKUP(FoFsmonkeyCompl10[[#This Row],[Vehicle ID / Name]],FoFsanalysis!A:H,5,FALSE) -> 2016 | P14: =VLOOKUP(FoFsmonkeyCompl10[[#This Row],[Vehicle ID / Name]],FoFsanalysis!A:H,8,FALSE) -> EUR | Q14: No

Sheet fof_headers
A1: question | B1: question_code | C1: answer | D1: answer_code | E1: format
A2: keep | D2: keep | E2: TEXT
A3: Respondent ID | D3: respondentId | E3: TEXT
A4: Collector ID | D4: collectorId | E4: TEXT
A5: Start Date | D5: dateStarted | E5: TEXT
A6: End Date | D6: dateEnded | E6: TEXT
A7: IP Address | D7: ipAddress | E7: TEXT
A8: Email Address | D8: email | E8: TEXT
A9: First Name | D9: firstname | E9: TEXT
A10: Last Name | D10: lastname | E10: TEXT
A11: Custom Data 1 | D11: customData1 | E11: TEXT
A12: Vehicle ID / Name | D12: qfundname | E12: TEXT
A13: ID | D13: universeFundID | E13: TEXT
... A17: Currency | D17: qcurrency | E17: TEXT
A18: Did your company raise capital for this vehicle in 2017? | B18: q1 | C18: Response | D18: q1 | E18: TEXT
A19: Please state the reason why? | B19: q2 | C19: Response | D19: q2 | E19: TEXT
A20: Please state the reason why? | C20: Other (please specify) | D20: q2other | E20: TEXT
A21: What was the total amount of capital raised for this vehicle in 2017? (millions) | B21: q3 | C21: Open-Ended Response | D21: q3 | E21: TEXT
A22: How much capital was raised for this vehicle in 2017 from Institutional Investors by investor type? (millions)Please ensure that the total values provided match the values you entered in Q3 | B22: q4 | C22: Pension funds | D22: q4_1 | E22: currency
A23: How much capital was raised for this vehicle in 2017 from Institutional Investors by investor type? (millions)Please ensure that the total values provided match the values you entered in Q4 | B23: q4 | C23: Insurance companies | D23: q4_2 | E23: currency
A24: How much capital was raised for this vehicle in 2017 from Institutional Investors by investor type? (millions)Please ensure that the total values provided match the values you entered in Q5 | B24: q4 | C24: Sovereign wealth funds | D24: q4_3 | E24: currency
A25: How much capital was raised for this vehicle in 2017 from Institutional Investors by investor type? (millions)Please ensure that the total values provided match the values you entered in Q6 | B25: q4 | C25: Government institutions | D25: q4_4 | E25: currency
A26: How much capital was raised for this vehicle in 2017 from Institutional Investors by investor type? (millions)Please ensure that the total values provided match the values you entered in Q7 | B26: q4 | C26: Charities, foundations, non-profit organisations | D26: q4_5 | E26: currency
A27: How much capital was raised for this vehicle in 2017 from Institutional Investors by investor type? (millions)Please ensure that the total values provided match the values you entered in Q8 | B27: q4 | C27: Fund of funds | D27: q4_6 | E27: currency
A28: How much capital was raised for this vehicle in 2017 from Institutional Investors by investor type? (millions)Please ensure that the total values provided match the values you entered in Q9 | B28: q4 | C28: High net worth individuals / Family offices | D28: q4_7 | E28: currency
A29: How much capital was raised for this vehicle in 2017 from Institutional Investors by investor type? (millions)Please ensure that the total values provided match the values you entered in Q10 | B29: q4 | C29: Other | D29: q4_8 | E29: currency
A30: How much capital was raised for this vehicle in 2017 from Institutional Investors by investor domicile? (millions)Please ensure that the total values provided match the values you entered in Q3 | B30: q5 | C30: Europe | D30: q5_1 | E30: currency
A31: How much capital was raised for this vehicle in 2017 from Institutional Investors by investor domicile? (millions)Please ensure that the total values provided match the values you entered in Q4 | B31: q5 | C31: Asia Pacific | D31: q5_2 | E31: currency
A32: How much capital was raised for this vehicle in 2017 from Institutional Investors by investor domicile? (millions)Please ensure that the total values provided match the values you entered in Q5 | B32: q5 | C32: North America | D32: q5_3 | E32: currency
... A40: Would you like the name of your company to be included in the list of participants? | B40: q8 | C40: Response | D40: q8 | E40: TEXT

Sheet FoFsanalysis
A1: VehicleID | B1: ID | C1: Style | D1: Structure | E1: Vintage | F1: RaisedCapital | G1: WhyNo | H1: Currency | I1: EUR | J1: CapitalRaised | K1: PensionFunds | L1: InsuranceCompanies | M1: SWFs | N1: Government | O1: Charities | P1: FundOfFunds | Q1: HNWI | R1: OtherInvestors | S1: Europe | T1: APAC | U1: NorthAmerica | V1: SouthAmerica | W1: Africa | X1: PlacementAgent | Y1: InvestorsContacting | Z1: OwnRelationship | AA1: OtherAgency | AB1: Expectations | AC1: Name
A2: CBRE Global Investment Partners Segregated Accounts | B2: N/A | C2: Core | D2: Open end | F2: Yes | H2: EUR | I2: 1 | J2: 1788 | K2: 1368 | L2: 364 | N2: 56 | S2: 1462 | T2: 184 | U2: 142 | X2: 100 | AB2: No change | AC2: Yes
A3: CBRE Global Investment Partners UK Osiris Property Fund | B3: 17437 | C3: Core | D3: Open end | E3: 2003 | F3: Yes | H3: GBP | I3: 1.17356 | J3: 12 | K3: 12 | S3: 12 | X3: 100 | AB3: No change | AC3: Yes
A4: CBRE Global Investment Partners Global Alpha Fund | B4: 17454 | C4: Core | D4: Open end | E4: 2010 | F4: Yes | H4: USD | I4: 0.950977 | J4: 1054 | K4: 559 | L4: 70 | M4: 50 | N4: 166 | O4: 77 | P4: 22 | R4: 110 | S4: 521 | T4: 187 | U4: 346 | X4: 100 | AB4: No change | AC4: Yes
A5: CBRE Global Investment Partners Global Alpha Fund | B5: 17454 | C5: Core | D5: Open end | E5: 2010 | F5: Yes | H5: USD | I5: 0.950977
A6: Altan IV Global IICIICIL | B6: N/A | C6: Opportunity | D6: Closed end | E6: 2017 | F6: Yes | H6: EUR | I6: 1 | J6: 291 | K6: 20 | L6: 20 | Q6: 251 | S6: 291 | Z6: 100 | AB6: Increase | AC6: Yes
A7: Crown Small Cap Real Estate Fund II | B7: 17661 | C7: Oppurtunity | D7: Closed end | E7: 2014 | F7: No | G7: Completing investment period | H7: USD | I7: 0.950977 | AB7: Increase | AC7: No
A8: CBRE Global Investment Partners Global Alpha Fund Series FCP-SIF | B8: N/A | C8: Core | D8: Open end | E8: 2010 | F8: Yes | H8: USD | I8: 0.950977
A9: HI-Immobilien-Multi Manager-Fonds III | B9: N/A | C9: Core | D9: Open end | E9: 2017 | F9: Yes | H9: EUR | I9: 1 | J9: 107 | K9: 7 | R9: 100 | S9: 107 | Z9: 100 | AB9: No change | AC9: Yes
A10: HI-Immobilien-Multi Manager-Fonds II | B10: N/A | C10: Core | D10: Open end | E10: 2016 | F10: Yes | H10: EUR | I10: 1 | J10: 71 | K10: 19 | L10: 11 | R10: 41 | S10: 71 | Z10: 100 | AB10: No change | AC10: Yes
A11: Crown Small Cap Real Estate Fund II | B11: 17661 | C11: Oppurtunity | D11: Closed end | E11: 2014 | F11: No | G11: Already raised | H11: USD | I11: 0.950977 | AB11: No change | AC11: No
A12: PATRIZIA Multi Managers Global IV | B12: N/A | C12: Value added | D12: Open end | E12: 2016 | F12: No | H12: EUR | I12: 1
