Workbook
Name RMITeam: [1]ContactDetails!$B$9:$B$13

Sheet DataCompleted
A1: Surveycode | B1: Association_Sample | C1: Company_Sample | D1: REGION1 | E1: DateCompleted_Asia | F1: REGION2 | G1: DateCompleted_Europe | H1: REGION3 | I1: DateCompleted_NorthAmerica | J1: REGION4 | K1: DateCompleted_Global | L1: REGION5 | M1: DateCompleted_SouthAmerica | N1: REGION6 | O1: DateCompleted_Africa | P1: ShowEurope | Q1: ShowAsia | R1: ShowNA | S1: ShowGlobal | T1: ShowSA | U1: ShowAfrica | V1: RecordNo | W1: DateCompleted | X1: IPaddress | Y1: Version | Z1: qName | AA1: qCompany | AB1: mnumber | AC1: qJobtitle | AD1: qEmail | AE1: qTelephone | AF1: qCountry | AG1: qCurrency | AH1: qCurrencyOther | AI1: q1 | AJ1: q2 | AK1: q2other | AL1: q3A_TotalRealEstate | AM1: q3A_NonListedRealEstate | AN1: q3B_TotalRealEstate | AO1: q3B_NonListedRealEstate | AP1: q31_1 | AQ1: q31_2 | AR1: q31_3 | AS1: q31_4 | AT1: q31_5 | AU1: q31_6 | AV1: q3ROW1_hidden | AW1: q32_1 | AX1: q32_2 | AY1: q32_3 | AZ1: q32_4 | BA1: q32_5 | BB1: q32_6 | BC1: q3ROW2_hidden | BD1: q33_1 | BE1: q33_2 | BF1: q33_3 | BG1: q33_4 | BH1: q33_5 | BI1: q33_6 | BJ1: q3ROW3_hidden | BK1: q34_1 | BL1: q34_2 | BM1: q34_3 | BN1: q34_4 | BO1: q34_5 | BP1: q34_6 | BQ1: q3ROW4_hidden | BR1: q35_1 | BS1: q35_2 | BT1: q35_3 | BU1: q35_4 | BV1: q35_5 | BW1: q35_6 | BX1: q3ROW5_hidden | BY1: q36_1 | BZ1: q36_2 | CA1: q36_3 | CB1: q36_4 | CC1: q36_5 | CD1: q36_6 | CE1: q3ROW6_hidden | CF1: q3COL1_hidden | CG1: q3COL2_hidden | CH1: q3COL3_hidden | CI1: q3COL4_hidden | CJ1: q3COL5_hidden | CK1: q3COL6_hidden | CL1: q3GRANDTotal_hidden | CM1: q41_1 | CN1: q41_2 | CO1: q41_3 | CP1: q41_4 | CQ1: q41_5 | CR1: q41_6 | CS1: q4ROW1_hidden | CT1: q42_1 | CU1: q42_2 | CV1: q42_3 | CW1: q42_4 | CX1: q42_5 | CY1: q42_6 | CZ1: q4ROW2_hidden | DA1: q43_1 | DB1: q43_2 | DC1: q43_3 | DD1: q43_4 | DE1: q43_5 | DF1: q43_6 | DG1: q4ROW3_hidden | DH1: q44_1 | DI1: q44_2 | DJ1: q44_3 | DK1: q44_4 | DL1: q44_5 | DM1: q44_6 | DN1: q4ROW4_hidden | DO1: q45_1 | DP1: q45_2 | DQ1: q45_3 | DR1: q45_4 | DS1: q45_5 | DT1: q45_6 | DU1: q4ROW5_hidden | DV1: q46_1 | DW1: q46_2 | DX1: q46_3 | DY1: q46_4 | DZ1: q46_5 | EA1: q46_6 | EB1: q4ROW6_hidden | EC1: q4COL1_hidden | ED1: q4COL2_hidden | EE1: q4COL3_hidden | EF1: q4COL4_hidden | EG1: q4COL5_hidden | EH1: q4COL6_hidden | EI1: q4GRANDTotal_hidden | EJ1: Alert41_1 | EK1: Alert41_2 | EL1: Alert41_3 | EM1: Alert41_4 | EN1: Alert41_5 | EO1: Alert41_6 | EP1: Alert42_1 | EQ1: Alert42_2 | ER1: Alert42_3 | ES1: Alert42_4 | ET1: Alert42_5 | EU1: Alert42_6 | EV1: Alert43_1 | EW1: Alert43_2 | EX1: Alert43_3 | EY1: Alert43_4 | EZ1: Alert43_5 | FA1: Alert43_6 | FB1: Alert44_1 | FC1: Alert44_2 | FD1: Alert44_3 | FE1: Alert44_4 | FF1: Alert44_5 | FG1: Alert44_6 | FH1: Alert45_1 | FI1: Alert45_2 | FJ1: Alert45_3 | FK1: Alert45_4 | FL1: Alert45_5 | FM1: Alert45_6 | FN1: Alert46_1 | FO1: Alert46_2 | FP1: Alert46_3 | FQ1: Alert46_4 | FR1: Alert46_5 | FS1: Alert46_6 | FT1: q51_1 | FU1: q51_2 | FV1: q51_3 | FW1: q51_4 | FX1: q51_5 | FY1: q51_6 | FZ1: q5ROW1_hidden | GA1: q52_1 | GB1: q52_2 | GC1: q52_3 | GD1: q52_4 | GE1: q52_5 | GF1: q52_6 | GG1: q5ROW2_hidden | GH1: q53_1 | GI1: q53_2 | GJ1: q53_3 | GK1: q53_4 | GL1: q53_5 | GM1: q53_6 | GN1: q5ROW3_hidden | GO1: q54_1 | GP1: q54_2 | GQ1: q54_3 | GR1: q54_4 | GS1: q54_5 | GT1: q54_6 | GU1: q5ROW4_hidden | GV1: q55_1 | GW1: q55_2 | GX1: q55_3 | GY1: q55_4 | GZ1: q55_5 | HA1: q55_6 | HB1: q5ROW5_hidden | HC1: q56_1 | HD1: q56_2 | HE1: q56_3 | HF1: q56_4 | HG1: q56_5 | HH1: q56_6 | HI1: q5ROW6_hidden | HJ1: q57_1 | HK1: q57_2 | HL1: q57_3 | HM1: q57_4 | HN1: q57_5 | HO1: q57_6 | HP1: q5ROW7_hidden | HQ1: q5other | HR1: q58_1 | HS1: q58_2 | HT1: q58_3 | HU1: q58_4 | HV1: q58_5 | HW1: q58_6 | HX1: q5ROW8_hidden | HY1: q5COL1_hidden | HZ1: q5COL2_hidden | IA1: q5COL3_hidden | IB1: q5COL4_hidden | IC1: q5COL5_hidden | ID1: q5COL6_hidden | IE1: q5GRANDTotal_hidden | IF1: q61_1 | IG1: q61_2 | IH1: q61_3 | II1: q61_4 | IJ1: q61_5 | IK1: q61_6 | IL1: q6ROW1_hidden | IM1: q62_1 | IN1: q62_2 | IO1: q62_3 | IP1: q62_4 | IQ1: q62_5 | IR1: q62_6 | IS1: q6ROW2_hidden | IT1: q63_1 | IU1: q63_2 | IV1: q63_3 | IW1: q63_4 | IX1: q63_5 | IY1: q63_6 | IZ1: q6ROW3_hidden | JA1: q64_1 | JB1: q64_2 | JC1: q64_3 | JD1: q64_4 | JE1: q64_5 | JF1: q64_6 | JG1: q6ROW4_hidden | JH1: q65_1 | JI1: q65_2 | JJ1: q65_3 | JK1: q65_4 | JL1: q65_5 | JM1: q65_6 | JN1: q6ROW5_hidden | JO1: q6COL1_hidden | JP1: q6COL2_hidden | JQ1: q6COL3_hidden | JR1: q6COL4_hidden | JS1: q6COL5_hidden | JT1: q6COL6_hidden | JU1: q6GRANDTotal_hidden | JV1: q7_1 | JW1: q7_2 | JX1: q7_3 | JY1: q7other | JZ1: q7_4 | KA1: q8 | KB1: q9 | KC1: q91 | KD1: ASIAPACIFIC_apac | KE1: q101_1_apac | KF1: q101_2_apac | KG1: q101_3_apac | KH1: q101_4_apac | KI1: q101_5_apac | KJ1: q101_6_apac | KK1: q10ROW1_hidden_apac | KL1: q102_1_apac | KM1: q102_2_apac | KN1: q102_3_apac | KO1: q102_4_apac | KP1: q102_5_apac | KQ1: q102_6_apac | KR1: q10ROW2_hidden_apac | KS1: q103_1_apac | KT1: q103_2_apac | KU1: q103_3_apac | KV1: q103_4_apac | KW1: q103_5_apac | KX1: q103_6_apac | KY1: q10ROW3_hidden_apac | KZ1: q104_1_apac | LA1: q104_2_apac | LB1: q104_3_apac | LC1: q104_4_apac | LD1: q104_5_apac | LE1: q104_6_apac | LF1: q10ROW4_hidden_apac | LG1: q105_1_apac | LH1: q105_2_apac | LI1: q105_3_apac | LJ1: q105_4_apac | LK1: q105_5_apac | LL1: q105_6_apac | LM1: q10ROW5_hidden_apac | LN1: q106_1_apac | LO1: q106_2_apac | LP1: q106_3_apac | LQ1: q106_4_apac | LR1: q106_5_apac | LS1: q106_6_apac | LT1: q10ROW6_hidden_apac | LU1: q107_1_apac | LV1: q107_2_apac | LW1: q107_3_apac | LX1: q107_4_apac | LY1: q107_5_apac | LZ1: q107_6_apac | MA1: q10ROW7_hidden_apac | MB1: q10other_apac | MC1: q108_1_apac | MD1: q108_2_apac | ME1: q108_3_apac | MF1: q108_4_apac | MG1: q108_5_apac | MH1: q108_6_apac | MI1: q10ROW8_hidden_apac | MJ1: q10COL1_hidden_apac | MK1: q10COL2_hidden_apac | ML1: q10COL3_hidden_apac | MM1: q10COL4_hidden_apac | MN1: q10COL5_hidden_apac | MO1: q10COL6_hidden_apac | MP1: q10GRANDTotal_hidden_apac | MQ1: q111_1_apac | MR1: q111_2_apac | MS1: q111_3_apac | MT1: q111_4_apac | MU1: q111_5_apac | MV1: q111_6_apac | MW1: q11ROW1_hidden_apac | MX1: q112_1_apac | MY1: q112_2_apac | MZ1: q112_3_apac | NA1: q112_4_apac | NB1: q112_5_apac | NC1: q112_6_apac | ND1: q11ROW2_hidden_apac | NE1: q113_1_apac | NF1: q113_2_apac | NG1: q113_3_apac | NH1: q113_4_apac | NI1: q113_5_apac | NJ1: q113_6_apac | NK1: q11ROW3_hidden_apac | NL1: q114_1_apac | NM1: q114_2_apac | NN1: q114_3_apac | NO1: q114_4_apac | NP1: q114_5_apac | NQ1: q114_6_apac | NR1: q11ROW4_hidden_apac | NS1: q115_1_apac | NT1: q115_2_apac | NU1: q115_3_apac | NV1: q115_4_apac | NW1: q115_5_apac | NX1: q115_6_apac | NY1: q11ROW5_hidden_apac | NZ1: q11COL1_hidden_apac | OA1: q11COL2_hidden_apac | OB1: q11COL3_hidden_apac | OC1: q11COL4_hidden_apac | OD1: q11COL5_hidden_apac | OE1: q11COL6_hidden_apac | OF1: q11GRANDTotal_hidden_apac | OG1: EUROPE_europe | OH1: q101_1_europe | OI1: q101_2_europe | OJ1: q101_3_europe | OK1: q101_4_europe | OL1: q101_5_europe | OM1: q101_6_europe | ON1: q10ROW1_hidden_europe | OO1: q102_1_europe | OP1: q102_2_europe | OQ1: q102_3_europe | OR1: q102_4_europe | OS1: q102_5_europe | OT1: q102_6_europe | OU1: q10ROW2_hidden_europe | OV1: q103_1_europe | OW1: q103_2_europe | OX1: q103_3_europe | OY1: q103_4_europe | OZ1: q103_5_europe | PA1: q103_6_europe | PB1: q10ROW3_hidden_europe | PC1: q104_1_europe | PD1: q104_2_europe | PE1: q104_3_europe | PF1: q104_4_europe | PG1: q104_5_europe | PH1: q104_6_europe | PI1: q10ROW4_hidden_europe | PJ1: q105_1_europe | PK1: q105_2_europe | PL1: q105_3_europe | PM1: q105_4_europe | PN1: q105_5_europe | PO1: q105_6_europe | PP1: q10ROW5_hidden_europe | PQ1: q106_1_europe | PR1: q106_2_europe | PS1: q106_3_europe | PT1: q106_4_europe | PU1: q106_5_europe | PV1: q106_6_europe | PW1: q10ROW6_hidden_europe | PX1: q107_1_europe | PY1: q107_2_europe | PZ1: q107_3_europe | QA1: q107_4_europe | QB1: q107_5_europe | QC1: q107_6_europe | QD1: q10ROW7_hidden_europe | QE1: q10other_europe | QF1: q108_1_europe | QG1: q108_2_europe | QH1: q108_3_europe | QI1: q108_4_europe | QJ1: q108_5_europe | QK1: q108_6_europe | QL1: q10ROW8_hidden_europe | QM1: q10COL1_hidden_europe | QN1: q10COL2_hidden_europe | QO1: q10COL3_hidden_europe | QP1: q10COL4_hidden_europe | QQ1: q10COL5_hidden_europe | QR1: q10COL6_hidden_europe | QS1: q10GRANDTotal_hidden_europe | QT1: q111_1_europe | QU1: q111_2_europe | QV1: q111_3_europe | QW1: q111_4_europe | QX1: q111_5_europe | QY1: q111_6_europe | QZ1: q11ROW1_hidden_europe | RA1: q112_1_europe | RB1: q112_2_europe | RC1: q112_3_europe | RD1: q112_4_europe | RE1: q112_5_europe | RF1: q112_6_europe | RG1: q11ROW2_hidden_europe | RH1: q113_1_europe | RI1: q113_2_europe | RJ1: q113_3_europe | RK1: q113_4_europe | RL1: q113_5_europe | RM1: q113_6_europe | RN1: q11ROW3_hidden_europe | RO1: q114_1_europe | RP1: q114_2_europe | RQ1: q114_3_europe | RR1: q114_4_europe | RS1: q114_5_europe | RT1: q114_6_europe | RU1: q11ROW4_hidden_europe | RV1: q115_1_europe | RW1: q115_2_europe | RX1: q115_3_europe | RY1: q115_4_europe | RZ1: q115_5_europe | SA1: q115_6_europe | SB1: q11ROW5_hidden_europe | SC1: q11COL1_hidden_europe | SD1: q11COL2_hidden_europe | SE1: q11COL3_hidden_europe | SF1: q11COL4_hidden_europe | SG1: q11COL5_hidden_europe | SH1: q11COL6_hidden_europe | SI1: q11GRANDTotal_hidden_europe | SJ1: NORTHAMERICA_northamerica | SK1: q101_1_northamerica | SL1: q101_2_northamerica | SM1: q101_3_northamerica | SN1: q101_4_northamerica | SO1: q101_5_northamerica | SP1: q101_6_northamerica | SQ1: q10ROW1_hidden_northamerica | SR1: q102_1_northamerica | SS1: q102_2_northamerica | ST1: q102_3_northamerica | SU1: q102_4_northamerica | SV1: q102_5_northamerica | SW1: q102_6_northamerica | SX1: q10ROW2_hidden_northamerica | SY1: q103_1_northamerica | SZ1: q103_2_northamerica | TA1: q103_3_northamerica | TB1: q103_4_northamerica | TC1: q103_5_northamerica | TD1: q103_6_northamerica | TE1: q10ROW3_hidden_northamerica | TF1: q104_1_northamerica | TG1: q104_2_northamerica | TH1: q104_3_northamerica | TI1: q104_4_northamerica | TJ1: q104_5_northamerica | TK1: q104_6_northamerica | TL1: q10ROW4_hidden_northamerica | TM1: q105_1_northamerica | TN1: q105_2_northamerica | TO1: q105_3_northamerica | TP1: q105_4_northamerica | TQ1: q105_5_northamerica | TR1: q105_6_northamerica | TS1: q10ROW5_hidden_northamerica | TT1: q106_1_northamerica | TU1: q106_2_northamerica | TV1: q106_3_northamerica | TW1: q106_4_northamerica | TX1: q106_5_northamerica | TY1: q106_6_northamerica | TZ1: q10ROW6_hidden_northamerica | UA1: q107_1_northamerica | UB1: q107_2_northamerica | UC1: q107_3_northamerica | UD1: q107_4_northamerica | UE1: q107_5_northamerica | UF1: q107_6_northamerica | UG1: q10ROW7_hidden_northamerica | UH1: q10other_northamerica | UI1: q108_1_northamerica | UJ1: q108_2_northamerica | UK1: q108_3_northamerica | UL1: q108_4_northamerica | UM1: q108_5_northamerica | UN1: q108_6_northamerica | UO1: q10ROW8_hidden_northamerica | UP1: q10COL1_hidden_northamerica | UQ1: q10COL2_hidden_northamerica | UR1: q10COL3_hidden_northamerica | US1: q10COL4_hidden_northamerica | UT1: q10COL5_hidden_northamerica | UU1: q10COL6_hidden_northamerica | UV1: q10GRANDTotal_hidden_northamerica | UW1: q111_1_northamerica | UX1: q111_2_northamerica | UY1: q111_3_northamerica | UZ1: q111_4_northamerica | VA1: q111_5_northamerica | VB1: q111_6_northamerica | VC1: q11ROW1_hidden_northamerica | VD1: q112_1_northamerica | VE1: q112_2_northamerica | VF1: q112_3_northamerica | VG1: q112_4_northamerica | VH1: q112_5_northamerica | VI1: q112_6_northamerica | VJ1: q11ROW2_hidden_northamerica | VK1: q113_1_northamerica | VL1: q113_2_northamerica | VM1: q113_3_northamerica | VN1: q113_4_northamerica | VO1: q113_5_northamerica | VP1: q113_6_northamerica | VQ1: q11ROW3_hidden_northamerica | VR1: q114_1_northamerica | VS1: q114_2_northamerica | VT1: q114_3_northamerica | VU1: q114_4_northamerica | VV1: q114_5_northamerica | VW1: q114_6_northamerica | VX1: q11ROW4_hidden_northamerica | VY1: q115_1_northamerica | VZ1: q115_2_northamerica | WA1: q115_3_northamerica | WB1: q115_4_northamerica | WC1: q115_5_northamerica | WD1: q115_6_northamerica | WE1: q11ROW5_hidden_northamerica | WF1: q11COL1_hidden_northamerica | WG1: q11COL2_hidden_northamerica | WH1: q11COL3_hidden_northamerica | WI1: q11COL4_hidden_northamerica | WJ1: q11COL5_hidden_northamerica | WK1: q11COL6_hidden_northamerica | WL1: q11GRANDTotal_hidden_northamerica | WM1: Global_global | WN1: q101_1_global | WO1: q101_2_global | WP1: q101_3_global | WQ1: q101_4_global | WR1: q101_5_global | WS1: q101_6_global | WT1: q10ROW1_hidden_global | WU1: q102_1_global | WV1: q102_2_global | WW1: q102_3_global | WX1: q102_4_global | WY1: q102_5_global | WZ1: q102_6_global | XA1: q10ROW2_hidden_global | XB1: q103_1_global | XC1: q103_2_global | XD1: q103_3_global | XE1: q103_4_global | XF1: q103_5_global | XG1: q103_6_global | XH1: q10ROW3_hidden_global | XI1: q104_1_global | XJ1: q104_2_global | XK1: q104_3_global | XL1: q104_4_global | XM1: q104_5_global | XN1: q104_6_global | XO1: q10ROW4_hidden_global | XP1: q105_1_global | XQ1: q105_2_global | XR1: q105_3_global | XS1: q105_4_global | XT1: q105_5_global | XU1: q105_6_global | XV1: q10ROW5_hidden_global | XW1: q106_1_global | XX1: q106_2_global | XY1: q106_3_global | XZ1: q106_4_global | YA1: q106_5_global | YB1: q106_6_global | YC1: q10ROW6_hidden_global | YD1: q107_1_global | YE1: q107_2_global | YF1: q107_3_global | YG1: q107_4_global | YH1: q107_5_global | YI1: q107_6_global | YJ1: q10ROW7_hidden_global | YK1: q10other_global | YL1: q108_1_global | YM1: q108_2_global | YN1: q108_3_global | YO1: q108_4_global | YP1: q108_5_global | YQ1: q108_6_global | YR1: q10ROW8_hidden_global | YS1: q10COL1_hidden_global | YT1: q10COL2_hidden_global | YU1: q10COL3_hidden_global | YV1: q10COL4_hidden_global | YW1: q10COL5_hidden_global | YX1: q10COL6_hidden_global | YY1: q10GRANDTotal_hidden_global | YZ1: q111_1_global | ZA1: q111_2_global | ZB1: q111_3_global | ZC1: q111_4_global | ZD1: q111_5_global | ZE1: q111_6_global | ZF1: q11ROW1_hidden_global | ZG1: q112_1_global | ZH1: q112_2_global | ZI1: q112_3_global | ZJ1: q112_4_global | ZK1: q112_5_global | ZL1: q112_6_global | ZM1: q11ROW2_hidden_global | ZN1: q113_1_global | ZO1: q113_2_global | ZP1: q113_3_global | ZQ1: q113_4_global | ZR1: q113_5_global | ZS1: q113_6_global | ZT1: q11ROW3_hidden_global | ZU1: q114_1_global | ZV1: q114_2_global | ZW1: q114_3_global | ZX1: q114_4_global | ZY1: q114_5_global | ZZ1: q114_6_global | AAA1: q11ROW4_hidden_global | AAB1: q115_1_global | AAC1: q115_2_global | AAD1: q115_3_global | AAE1: q115_4_global | AAF1: q115_5_global | AAG1: q115_6_global | AAH1: q11ROW5_hidden_global | AAI1: q11COL1_hidden_global | AAJ1: q11COL2_hidden_global | AAK1: q11COL3_hidden_global | AAL1: q11COL4_hidden_global | AAM1: q11COL5_hidden_global | AAN1: q11COL6_hidden_global | AAO1: q11GRANDTotal_hidden_global | AAP1: SOUTHAMERICA_southamerica | AAQ1: q101_1_southamerica | AAR1: q101_2_southamerica | AAS1: q101_3_southamerica | AAT1: q101_4_southamerica | AAU1: q101_5_southamerica | AAV1: q101_6_southamerica | AAW1: q10ROW1_hidden_southamerica | AAX1: q102_1_southamerica | AAY1: q102_2_southamerica | AAZ1: q102_3_southamerica | ABA1: q102_4_southamerica | ABB1: q102_5_southamerica | ABC1: q102_6_southamerica | ABD1: q10ROW2_hidden_southamerica | ABE1: q103_1_southamerica | ABF1: q103_2_southamerica | ABG1: q103_3_southamerica | ABH1: q103_4_southamerica | ABI1: q103_5_southamerica | ABJ1: q103_6_southamerica | ABK1: q10ROW3_hidden_southamerica | ABL1: q104_1_southamerica | ABM1: q104_2_southamerica | ABN1: q104_3_southamerica | ABO1: q104_4_southamerica | ABP1: q104_5_southamerica | ABQ1: q104_6_southamerica | ABR1: q10ROW4_hidden_southamerica | ABS1: q105_1_southamerica | ABT1: q105_2_southamerica | ABU1: q105_3_southamerica | ABV1: q105_4_southamerica | ABW1: q105_5_southamerica | ABX1: q105_6_southamerica | ABY1: q10ROW5_hidden_southamerica | ABZ1: q106_1_southamerica | ACA1: q106_2_southamerica | ACB1: q106_3_southamerica | ACC1: q106_4_southamerica | ACD1: q106_5_southamerica | ACE1: q106_6_southamerica | ACF1: q10ROW6_hidden_southamerica | ACG1: q107_1_southamerica | ACH1: q107_2_southamerica | ACI1: q107_3_southamerica | ACJ1: q107_4_southamerica | ACK1: q107_5_southamerica | ACL1: q107_6_southamerica | ACM1: q10ROW7_hidden_southamerica | ACN1: q10other_southamerica | ACO1: q108_1_southamerica | ACP1: q108_2_southamerica | ACQ1: q108_3_southamerica | ACR1: q108_4_southamerica | ACS1: q108_5_southamerica | ACT1: q108_6_southamerica | ACU1: q10ROW8_hidden_southamerica | ACV1: q10COL1_hidden_southamerica | ACW1: q10COL2_hidden_southamerica | ACX1: q10COL3_hidden_southamerica | ACY1: q10COL4_hidden_southamerica | ACZ1: q10COL5_hidden_southamerica | ADA1: q10COL6_hidden_southamerica | ADB1: q10GRANDTotal_hidden_southamerica | ADC1: q111_1_southamerica | ADD1: q111_2_southamerica | ADE1: q111_3_southamerica | ADF1: q111_4_southamerica | ADG1: q111_5_southamerica | ADH1: q111_6_southamerica | ADI1: q11ROW1_hidden_southamerica | ADJ1: q112_1_southamerica | ADK1: q112_2_southamerica | ADL1: q112_3_southamerica | ADM1: q112_4_southamerica | ADN1: q112_5_southamerica | ADO1: q112_6_southamerica | ADP1: q11ROW2_hidden_southamerica | ADQ1: q113_1_southamerica | ADR1: q113_2_southamerica | ADS1: q113_3_southamerica | ADT1: q113_4_southamerica | ADU1: q113_5_southamerica | ADV1: q113_6_southamerica | ADW1: q11ROW3_hidden_southamerica | ADX1: q114_1_southamerica | ADY1: q114_2_southamerica | ADZ1: q114_3_southamerica | AEA1: q114_4_southamerica | AEB1: q114_5_southamerica | AEC1: q114_6_southamerica | AED1: q11ROW4_hidden_southamerica | AEE1: q115_1_southamerica | AEF1: q115_2_southamerica | AEG1: q115_3_southamerica | AEH1: q115_4_southamerica | AEI1: q115_5_southamerica | AEJ1: q115_6_southamerica | AEK1: q11ROW5_hidden_southamerica | AEL1: q11COL1_hidden_southamerica | AEM1: q11COL2_hidden_southamerica | AEN1: q11COL3_hidden_southamerica | AEO1: q11COL4_hidden_southamerica | AEP1: q11COL5_hidden_southamerica | AEQ1: q11COL6_hidden_southamerica | AER1: q11GRANDTotal_hidden_southamerica | AES1: AFRICA_africa | AET1: q101_1_africa | AEU1: q101_2_africa | AEV1: q101_3_africa | AEW1: q101_4_africa | AEX1: q101_5_africa | AEY1: q101_6_africa | AEZ1: q10ROW1_hidden_africa | AFA1: q102_1_africa | AFB1: q102_2_africa | AFC1: q102_3_africa | AFD1: q102_4_africa | AFE1: q102_5_africa | AFF1: q102_6_africa | AFG1: q10ROW2_hidden_africa | AFH1: q103_1_africa | AFI1: q103_2_africa | AFJ1: q103_3_africa | AFK1: q103_4_africa | AFL1: q103_5_africa | AFM1: q103_6_africa | AFN1: q10ROW3_hidden_africa | AFO1: q104_1_africa | AFP1: q104_2_africa | AFQ1: q104_3_africa | AFR1: q104_4_africa | AFS1: q104_5_africa | AFT1: q104_6_africa | AFU1: q10ROW4_hidden_africa | AFV1: q105_1_africa | AFW1: q105_2_africa | AFX1: q105_3_africa | AFY1: q105_4_africa | AFZ1: q105_5_africa | AGA1: q105_6_africa | AGB1: q10ROW5_hidden_africa | AGC1: q106_1_africa | AGD1: q106_2_africa | AGE1: q106_3_africa | AGF1: q106_4_africa | AGG1: q106_5_africa | AGH1: q106_6_africa | AGI1: q10ROW6_hidden_africa | AGJ1: q107_1_africa | AGK1: q107_2_africa | AGL1: q107_3_africa | AGM1: q107_4_africa | AGN1: q107_5_africa | AGO1: q107_6_africa | AGP1: q10ROW7_hidden_africa | AGQ1: q10other_africa | AGR1: q108_1_africa | AGS1: q108_2_africa | AGT1: q108_3_africa | AGU1: q108_4_africa | AGV1: q108_5_africa | AGW1: q108_6_africa | AGX1: q10ROW8_hidden_africa | AGY1: q10COL1_hidden_africa | AGZ1: q10COL2_hidden_africa | AHA1: q10COL3_hidden_africa | AHB1: q10COL4_hidden_africa | AHC1: q10COL5_hidden_africa | AHD1: q10COL6_hidden_africa | AHE1: q10GRANDTotal_hidden_africa | AHF1: q111_1_africa | AHG1: q111_2_africa | AHH1: q111_3_africa | AHI1: q111_4_africa | AHJ1: q111_5_africa | AHK1: q111_6_africa | AHL1: q11ROW1_hidden_africa | AHM1: q112_1_africa | AHN1: q112_2_africa | AHO1: q112_3_africa | AHP1: q112_4_africa | AHQ1: q112_5_africa | AHR1: q112_6_africa | AHS1: q11ROW2_hidden_africa | AHT1: q113_1_africa | AHU1: q113_2_africa | AHV1: q113_3_africa | AHW1: q113_4_africa | AHX1: q113_5_africa | AHY1: q113_6_africa | AHZ1: q11ROW3_hidden_africa | AIA1: q114_1_africa | AIB1: q114_2_africa | AIC1: q114_3_africa | AID1: q114_4_africa | AIE1: q114_5_africa | AIF1: q114_6_africa | AIG1: q11ROW4_hidden_africa | AIH1: q115_1_africa | AII1: q115_2_africa | AIJ1: q115_3_africa | AIK1: q115_4_africa | AIL1: q115_5_africa | AIM1: q115_6_africa | AIN1: q11ROW5_hidden_africa | AIO1: q11COL1_hidden_africa | AIP1: q11COL2_hidden_africa | AIQ1: q11COL3_hidden_africa | AIR1: q11COL4_hidden_africa | AIS1: q11COL5_hidden_africa | AIT1: q11COL6_hidden_africa | AIU1: q11GRANDTotal_hidden_africa
A2: C9AAC498C | B2: INREV | C2: Northern Horizon Capital A/S | P2: TRUE | Q2: FALSE | R2: FALSE | S2: FALSE | T2: FALSE | U2: FALSE | V2: 629 | W2: 43520.312 | X2: 46.255.210.106 | Y2: 2019 | Z2: Nerijus Zebrauskas | AA2: Northern Horizon Capital | AB2: =VLOOKUP(MID(AD2,SEARCH("@",AD2,1),LEN(AD2)-SEARCH("@",AD2,1)+1),[2]Sheet1!$D:$F,3,FALSE) -> M174 | AD2: nerijus.zebrauskas@nh-cap.com | AF2: Denmark | AG2: EUR | AI2: 1 | AL2: 73 | AM2: 71 | AN2: 2 | AO2: 0 | AV2: 0 | AW2: 71 | BC2: 71 | BJ2: 0 | BQ2: 0 | BX2: 0 | CE2: 0 | CF2: 71 | CG2: 0 | CH2: 0 | CI2: 0 | CJ2: 0 | CK2: 0 | CL2: 71 | CS2: 0 | CT2: 1 | CZ2: 1 | DG2: 0 | DN2: 0 | DU2: 0 | EB2: 0 | EC2: 1 | ED2: 0 | EE2: 0 | EF2: 0 | EG2: 0 | EH2: 0 | EI2: 1 | EJ2: NO | EK2: NO | EL2: NO | EM2: NO | EN2: NO | EO2: NO | EP2: YES | EQ2: NO | ER2: NO | ES2: NO | ET2: NO | EU2: NO | EV2: NO | EW2: NO | EX2: NO | EY2: NO | EZ2: NO | FA2: NO | FB2: NO | FC2: NO | FD2: NO | FE2: NO | FF2: NO | FG2: NO | FH2: NO | FI2: NO | FJ2: NO | FK2: NO | FL2: NO | FM2: NO | FN2: NO | FO2: NO | FP2: NO | FQ2: NO | FR2: NO | FS2: NO | FT2: 59 | FZ2: 59 | GG2: 0 | GN2: 0 | GU2: 0 | GV2: 6 | HB2: 6 | HI2: 0 | HP2: 0 | HQ2: Other financial vehicles | HR2: 6 | HX2: 6 | HY2: 71 | HZ2: 0 | IA2: 0 | IB2: 0 | IC2: 0 | ID2: 0 | IE2: 71 | IL2: 0 | IM2: 71 | IS2: 71 | IZ2: 0 | JG2: 0 | JN2: 0 | JO2: 71 | JP2: 0 | JQ2: 0 | JR2: 0 | JS2: 0 | JT2: 0 | JU2: 71 | JV2: 34 | JX2: 66 | KA2: 2 | KB2: 3 | KC2: 1 | KD2: START Asia Pacific: | OG2: START Europe: | SJ2: START North America: | WM2: START Global: | AAP2: START SOUTH America: | AES2: START Africa:
A3: C9AEF726V | B3: ANREV | C3: Logos | P3: FALSE | Q3: TRUE | R3: FALSE | S3: FALSE | T3: FALSE | U3: FALSE | V3: 708 | W3: 43510.219 | X3: 49.255.15.22 | Y3: 2019 | Z3: Paul Yeo | AA3: LOGOS | AB3: =VLOOKUP(MID(AD3,SEARCH("@",AD3,1),LEN(AD3)-SEARCH("@",AD3,1)+1),[2]Sheet1!$D:$F,3,FALSE) -> M0318 | AD3: paulyeo@logosproperty.com | AF3: Australia | AG3: AUD | AI3: 1 | AL3: 150 | AM3: 150 | AN3: 150 | AO3: 150 | AP3: 150 | AV3: 150 | BC3: 0 | BJ3: 0 | BQ3: 0 | BX3: 0 | CE3: 0 | CF3: 150 | CG3: 0 | CH3: 0 | CI3: 0 | CJ3: 0 | CK3: 0 | CL3: 150 | CM3: 2 | CS3: 2 | CZ3: 0 | DG3: 0 | DN3: 0 | DU3: 0 | EB3: 0 | EC3: 2 | ED3: 0 | EE3: 0 | EF3: 0 | EG3: 0 | EH3: 0 | EI3: 2 | EJ3: YES | EK3: NO | EL3: NO | EM3: NO | EN3: NO | EO3: NO | EP3: NO | EQ3: NO | ER3: NO | ES3: NO | ET3: NO | EU3: NO | EV3: NO | EW3: NO | EX3: NO | EY3: NO | EZ3: NO | FA3: NO | FB3: NO | FC3: NO | FD3: NO | FE3: NO | FF3: NO | FG3: NO | FH3: NO | FI3: NO | FJ3: NO | FK3: NO | FL3: NO | FM3: NO | FN3: NO | FO3: NO | FP3: NO | FQ3: NO | FR3: NO | FS3: NO | FT3: 100 | FZ3: 100 | GG3: 0 | GN3: 0 | GU3: 0 | HB3: 0 | HI3: 0 | HP3: 0 | HQ3: Financial Institution | HR3: 50 | HX3: 50 | HY3: 150 | HZ3: 0 | IA3: 0 | IB3: 0 | IC3: 0 | ID3: 0 | IE3: 150 | IF3: 150 | IL3: 150 | IS3: 0 | IZ3: 0 | JG3: 0 | JN3: 0 | JO3: 150 | JP3: 0 | JQ3: 0 | JR3: 0 | JS3: 0 | JT3: 0 | JU3: 150 | JX3: 100 | KA3: 1 | KB3: 3 | KC3: 1 | KD3: START Asia Pacific: | OG3: START Europe: | SJ3: START North America: | WM3: START Global: | AAP3: START SOUTH America: | AES3: START Africa:
A4: C9ALB751D | B4: ANREV | C4: Additional Record | P4: FALSE | Q4: TRUE | R4: FALSE | S4: FALSE | T4: FALSE | U4: FALSE | V4: 535 | W4: 43523.355 | X4: 101.78.249.218 | Y4: 2019 | Z4: Kivanch Mehmet | AA4: Charter Hall Group | AB4: =VLOOKUP(MID(AD4,SEARCH("@",AD4,1),LEN(AD4)-SEARCH("@",AD4,1)+1),[2]Sheet1!$D:$F,3,FALSE) -> M03232 | AC4: Head of Wholesale Investor Relations | AD4: Kivanch.Mehmet@charterhall.com.au | AE4: +61 429 362 079 | AF4: Australia | AG4: AUD | AI4: 1 | AL4: 1244 | AM4: 1244 | AN4: 1244 | AO4: 1244 | AP4: 1065 | AS4: 179 | AV4: 1244 | BC4: 0 | BJ4: 0 | BQ4: 0 | BX4: 0 | CE4: 0 | CF4: 1065 | CG4: 0 | CH4: 0 | CI4: 179 | CJ4: 0 | CK4: 0 | CL4: 1244 | CM4: 2 | CP4: 4 | CS4: 6 | CZ4: 0 | DG4: 0 | DN4: 0 | DU4: 0 | EB4: 0 | EC4: 2 | ED4: 0 | EE4: 0 | EF4: 4 | EG4: 0 | EH4: 0 | EI4: 6 | EJ4: YES | EK4: NO | EL4: NO | EM4: YES | EN4: NO | EO4: NO | EP4: NO | EQ4: NO | ER4: NO | ES4: NO | ET4: NO | EU4: NO | EV4: NO | EW4: NO | EX4: NO | EY4: NO | EZ4: NO | FA4: NO | FB4: NO | FC4: NO | FD4: NO | FE4: NO | FF4: NO | FG4: NO | FH4: NO | FI4: NO | FJ4: NO | FK4: NO | FL4: NO | FM4: NO | FN4: NO | FO4: NO | FP4: NO | FQ4: NO | FR4: NO | FS4: NO | FT4: 922 | FW4: 121 | FZ4: 1043 | GA4: 121 | GG4: 121 | GH4: 2 | GK4: 58 | GN4: 60 | GU4: 0 | HB4: 0 | HC4: 20 | HI4: 20 | HP4: 0 | HX4: 0 | HY4: 1065 | HZ4: 0 | IA4: 0 | IB4: 179 | IC4: 0 | ID4: 0 | IE4: 1244 | IF4: 957 | II4: 179 | IL4: 1136 | IM4: 108 | IS4: 108 | IZ4: 0 | JG4: 0 | JN4: 0 | JO4: 1065 | JP4: 0 | JQ4: 0 | JR4: 179 | JS4: 0 | JT4: 0 | JU4: 1244 | JX4: 100 | KA4: 3 | KB4: 3 | KC4: 1 | KD4: START Asia Pacific: | OG4: START Europe: | SJ4: START North America: | WM4: START Global: | AAP4: START SOUTH America: | AES4: START Africa:
A5: C9AQT300Y | B5: INREV | C5: UBS AG | P5: TRUE | Q5: TRUE | R5: TRUE | S5: TRUE | T5: TRUE | U5: FALSE | V5: 642 | W5: 43524.722 | X5: 155.145.208.132 | Y5: 2019 | Z5: Luka Lukic | AA5: UBS Asset Management | AB5: =VLOOKUP(MID(AD5,SEARCH("@",AD5,1),LEN(AD5)-SEARCH("@",AD5,1)+1),[2]Sheet1!$D:$F,3,FALSE) -> M064 | AD5: luka.lukic@ubs.com | AF5: Switzerland | AG5: EUR | AI5: 1 | AL5: 5110.4 | AM5: 5027 | AP5: 17.4 | AQ5: 3.2 | AT5: 66 | AV5: 86.6 | AW5: 363.5 | AX5: 319.4 | BB5: 15.6 | BC5: 698.5 | BD5: 1490.5 | BE5: 516.7 | BF5: 31 | BJ5: 2038.2 | BL5: 106.4 | BM5: 223.8 | BO5: 1845.3 | BQ5: 2175.5 | BW5: 28.4 | BX5: 28.4 | CE5: 0 | CF5: 1871.4 | CG5: 945.7 | CH5: 254.8 | CI5: 0 | CJ5: 1911.3 | CK5: 44 | CL5: 5027.2 | CS5: 0 | CZ5: 0 | DG5: 0 | DN5: 0 | DU5: 0 | EB5: 0 | EC5: 0 | ED5: 0 | EE5: 0 | EF5: 0 | EG5: 0 | EH5: 0 | EI5: 0 | EJ5: YES | EK5: YES | EL5: NO | EM5: NO | EN5: YES | EO5: NO | EP5: YES | EQ5: YES | ER5: NO | ES5: NO | ET5: NO | EU5: YES | EV5: YES | EW5: YES | EX5: YES | EY5: NO | EZ5: NO | FA5: NO | FB5: NO | FC5: YES | FD5: YES | FE5: NO | FF5: YES | FG5: NO | FH5: NO | FI5: NO | FJ5: NO | FK5: NO | FL5: NO | FM5: YES | FN5: NO | FO5: NO | FP5: NO | FQ5: NO | FR5: NO | FS5: NO | FZ5: 0 | GG5: 0 | GN5: 0 | GU5: 0 | HB5: 0 | HI5: 0 | HP5: 0 | HX5: 0 | HY5: 0 | HZ5: 0 | IA5: 0 | IB5: 0 | IC5: 0 | ID5: 0 | IE5: 0 | IL5: 0 | IS5: 0 | IZ5: 0 | JG5: 0 | JN5: 0 | JO5: 0 | JP5: 0 | JQ5: 0 | JR5: 0 | JS5: 0 | JT5: 0 | JU5: 0 | KA5: 1 | KB5: 3 | KC5: 1 | KD5: START Asia Pacific: | OG5: START Europe: | SJ5: START North America: | WM5: START Global: | AAP5: START SOUTH America: | AES5: START Africa:
A6: C9ARC522E | B6: INREV | C6: PlusAlpina Real Estate Advisors GmbH | P6: TRUE | Q6: FALSE | R6: FALSE | S6: FALSE | T6: FALSE | U6: FALSE | V6: 759 | W6: 43524.366 | X6: 94.79.138.90 | Y6: 2019 | Z6: Laura Meindl | AA6: CONREN Land Management GmbH | AB6: =VLOOKUP(MID(AD6,SEARCH("@",AD6,1),LEN(AD6)-SEARCH("@",AD6,1)+1),[2]Sheet1!$D:$F,3,FALSE) -> M690 | AD6: laura.meindl@conrenland.com | AF6: Germany | AG6: EUR | AI6: 1 | AL6: 65 | AM6: 65 | AN6: 16 | AO6: 16 | AV6: 0 | AW6: 65 | BC6: 65 | BJ6: 0 | BQ6: 0 | BX6: 0 | CE6: 0 | CF6: 65 | CG6: 0 | CH6: 0 | CI6: 0 | CJ6: 0 | CK6: 0 | CL6: 65 | CS6: 0 | CT6: 2 | CZ6: 2 | DG6: 0 | DN6: 0 | DU6: 0 | EB6: 0 | EC6: 2 | ED6: 0 | EE6: 0 | EF6: 0 | EG6: 0 | EH6: 0 | EI6: 2 | EJ6: NO | EK6: NO | EL6: NO | EM6: NO | EN6: NO | EO6: NO | EP6: YES | EQ6: NO | ER6: NO | ES6: NO | ET6: NO | EU6: NO | EV6: NO | EW6: NO | EX6: NO | EY6: NO | EZ6: NO | FA6: NO | FB6: NO | FC6: NO | FD6: NO | FE6: NO | FF6: NO | FG6: NO | FH6: NO | FI6: NO | FJ6: NO | FK6: NO | FL6: NO | FM6: NO | FN6: NO | FO6: NO | FP6: NO | FQ6: NO | FR6: NO | FS6: NO | FZ6: 0 | GG6: 0 | GN6: 0 | GU6: 0 | HB6: 0 | HC6: 65 | HI6: 65 | HP6: 0 | HX6: 0 | HY6: 65 | HZ6: 0 | IA6: 0 | IB6: 0 | IC6: 0 | ID6: 0 | IE6: 65 | IL6: 0 | IM6: 65 | IS6: 65 | IZ6: 0 | JG6: 0 | JN6: 0 | JO6: 65 | JP6: 0 | JQ6: 0 | JR6: 0 | JS6: 0 | JT6: 0 | JU6: 65 | JX6: 100 | KA6: 1 | KB6: 3 | KC6: 1 | KD6: START Asia Pacific: | OG6: START Europe: | SJ6: START North America: | WM6: START Global: | AAP6: START SOUTH America: | AES6: START Africa:
A7: C9AWD500U | B7: INREV | C7: Nordika | P7: TRUE | Q7: FALSE | R7: FALSE | S7: FALSE | T7: FALSE | U7: FALSE | V7: 768 | W7: 43516.551 | X7: 95.195.213.146 | Y7: 2019 | Z7: Gabriel Cronstedt | AA7: Nordika Fastigheter | AB7: =VLOOKUP(MID(AD7,SEARCH("@",AD7,1),LEN(AD7)-SEARCH("@",AD7,1)+1),[2]Sheet1!$D:$F,3,FALSE) -> M03188 | AC7: Partner | AD7: gc@nordika.se | AE7: 708870995 | AF7: Sweden | AG7: EUR | AI7: 1 | AL7: 75 | AM7: 75 | AN7: 17 | AO7: 17 | AV7: 0 | AW7: 75 | AX7: 0 | AY7: 0 | AZ7: 0 | BA7: 0 | BB7: 0 | BC7: 75 | BJ7: 0 | BQ7: 0 | BX7: 0 | CE7: 0 | CF7: 75 | CG7: 0 | CH7: 0 | CI7: 0 | CJ7: 0 | CK7: 0 | CL7: 75 | CS7: 0 | CT7: 1 | CZ7: 1 | DG7: 0 | DN7: 0 | DU7: 0 | EB7: 0 | EC7: 1 | ED7: 0 | EE7: 0 | EF7: 0 | EG7: 0 | EH7: 0 | EI7: 1 | EJ7: NO | EK7: NO | EL7: NO | EM7: NO | EN7: NO | EO7: NO | EP7: YES | EQ7: NO | ER7: NO | ES7: NO | ET7: NO | EU7: NO | EV7: NO | EW7: NO | EX7: NO | EY7: NO | EZ7: NO | FA7: NO | FB7: NO | FC7: NO | FD7: NO | FE7: NO | FF7: NO | FG7: NO | FH7: NO | FI7: NO | FJ7: NO | FK7: NO | FL7: NO | FM7: NO | FN7: NO | FO7: NO | FP7: NO | FQ7: NO | FR7: NO | FS7: NO | FT7: 75 | FZ7: 75 | GG7: 0 | GN7: 0 | GU7: 0 | HB7: 0 | HI7: 0 | HP7: 0 | HX7: 0 | HY7: 75 | HZ7: 0 | IA7: 0 | IB7: 0 | IC7: 0 | ID7: 0 | IE7: 75 | IL7: 0 | IM7: 75 | IS7: 75 | IZ7: 0 | JG7: 0 | JN7: 0 | JO7: 75 | JP7: 0 | JQ7: 0 | JR7: 0 | JS7: 0 | JT7: 0 | JU7: 75 | JV7: 0 | JW7: 0 | JX7: 100 | KA7: 1 | KB7: 3 | KC7: 1 | KD7: START Asia Pacific: | OG7: START Europe: | SJ7: START North America: | WM7: START Global: | AAP7: START SOUTH America: | AES7: START Africa:
A8: C9AWJ875T | B8: ANREV | C8: QIC | P8: FALSE | Q8: TRUE | R8: FALSE | S8: FALSE | T8: FALSE | U8: FALSE | V8: 539 | W8: 43517.973 | X8: 165.225.114.92 | Y8: 2019 | Z8: Grant Brady | AA8: QIC | AB8: =VLOOKUP(MID(AD8,SEARCH("@",AD8,1),LEN(AD8)-SEARCH("@",AD8,1)+1),[2]Sheet1!$D:$F,3,FALSE) -> M0350 | AC8: Director – Investment Specialist, Global Real Estate | AD8: g.brady@qic.com | AE8: +61 7 3020 7203 | AF8: Australia | AG8: AUD | AI8: 1 | AL8: 1000 | AM8: 1000 | AN8: 1000 | AO8: 1000 | AP8: 1000 | AV8: 1000 | BC8: 0 | BJ8: 0 | BQ8: 0 | BX8: 0 | CE8: 0 | CF8: 1000 | CG8: 0 | CH8: 0 | CI8: 0 | CJ8: 0 | CK8: 0 | CL8: 1000 | CM8: 2 | CS8: 2 | CZ8: 0 | DG8: 0 | DN8: 0 | DU8: 0 | EB8: 0 | EC8: 2 | ED8: 0 | EE8: 0 | EF8: 0 | EG8: 0 | EH8: 0 | EI8: 2 | EJ8: YES | EK8: NO | EL8: NO | EM8: NO | EN8: NO | EO8: NO | EP8: NO | EQ8: NO | ER8: NO | ES8: NO | ET8: NO | EU8: NO | EV8: NO | EW8: NO | EX8: NO | EY8: NO | EZ8: NO | FA8: NO | FB8: NO | FC8: NO | FD8: NO | FE8: NO | FF8: NO | FG8: NO | FH8: NO | FI8: NO | FJ8: NO | FK8: NO | FL8: NO | FM8: NO | FN8: NO | FO8: NO | FP8: NO | FQ8: NO | FR8: NO | FS8: NO | FT8: 477.3 | FZ8: 477.3 | GG8: 0 | GN8: 0 | GO8: 522.7 | GU8: 522.7 | HB8: 0 | HI8: 0 | HP8: 0 | HX8: 0 | HY8: 1000 | HZ8: 0 | IA8: 0 | IB8: 0 | IC8: 0 | ID8: 0 | IE8: 1000 | IF8: 1000 | IL8: 1000 | IS8: 0 | IZ8: 0 | JG8: 0 | JN8: 0 | JO8: 1000 | JP8: 0 | JQ8: 0 | JR8: 0 | JS8: 0 | JT8: 0 | JU8: 1000 | JX8: 100 | KA8: 1 | KB8: 3 | KC8: 1 | KD8: START Asia Pacific: | OG8: START Europe: | SJ8: START North America: | WM8: START Global: | AAP8: START SOUTH America: | AES8: START Africa:
A9: C9AYY554M | B9: INREV | C9: Steen & Strøm | P9: FALSE | Q9: FALSE | R9: FALSE | S9: FALSE | T9: FALSE | U9: FALSE | V9: 651 | W9: 43490.673 | X9: 213.52.102.35 | Y9: 2019 | Z9: Nils Eivind Risvand | AA9: Steen & Strøm AS | AB9: =VLOOKUP(MID(AD9,SEARCH("@",AD9,1),LEN(AD9)-SEARCH("@",AD9,1)+1),[2]Sheet1!$D:$F,3,FALSE) -> M676 | AC9: Head of Legal | AD9: nils.eivind.risvand@steenstrom.com | AE9: 4793402718 | AF9: Norway | AG9: NOK | AI9: 2 | AJ9: 6 | AK9: No need for capital | AV9: 0 | BC9: 0 | BJ9: 0 | BQ9: 0 | BX9: 0 | CE9: 0 | CF9: 0 | CG9: 0 | CH9: 0 | CI9: 0 | CJ9: 0 | CK9: 0 | CL9: 0 | CS9: 0 | CZ9: 0 | DG9: 0 | DN9: 0 | DU9: 0 | EB9: 0 | EC9: 0 | ED9: 0 | EE9: 0 | EF9: 0 | EG9: 0 | EH9: 0 | EI9: 0 | EJ9: NO | EK9: NO | EL9: NO | EM9: NO | EN9: NO | EO9: NO | EP9: NO | EQ9: NO | ER9: NO | ES9: NO | ET9: NO | EU9: NO | EV9: NO | EW9: NO | EX9: NO | EY9: NO | EZ9: NO | FA9: NO | FB9: NO | FC9: NO | FD9: NO | FE9: NO | FF9: NO | FG9: NO | FH9: NO | FI9: NO | FJ9: NO | FK9: NO | FL9: NO | FM9: NO | FN9: NO | FO9: NO | FP9: NO | FQ9: NO | FR9: NO | FS9: NO | FZ9: 0 | GG9: 0 | GN9: 0 | GU9: 0 | HB9: 0 | HI9: 0 | HP9: 0 | HX9: 0 | HY9: 0 | HZ9: 0 | IA9: 0 | IB9: 0 | IC9: 0 | ID9: 0 | IE9: 0 | IL9: 0 | IS9: 0 | IZ9: 0 | JG9: 0 | JN9: 0 | JO9: 0 | JP9: 0 | JQ9: 0 | JR9: 0 | JS9: 0 | JT9: 0 | JU9: 0 | KA9: 3 | KB9: 3 | KC9: 1 | KD9: START Asia Pacific: | OG9: START Europe: | SJ9: START North America: | WM9: START Global: | AAP9: START SOUTH America: | AES9: START Africa:
A10: C9BVL581A | B10: INREV | C10: Wealthcap Kapitalverwaltungsgesellschaft mbH | P10: TRUE | Q10: FALSE | R10: FALSE | S10: FALSE | T10: FALSE | U10: FALSE | V10: 563 | W10: 43475.475 | X10: 194.145.239.236 | Y10: 2019 | Z10: Sebastian Zehrer | AA10: Wealthcap | AB10: =VLOOKUP(MID(AD10,SEARCH("@",AD10,1),LEN(AD10)-SEARCH("@",AD10,1)+1),[2]Sheet1!$D:$F,3,FALSE) -> M700 | AD10: sebastian.zehrer@wealthcap.com | AF10: Germany | AG10: EUR | AI10: 1 | AL10: 260 | AM10: 0 | AN10: 260 | AO10: 0 | AV10: 0 | AX10: 60 | AY10: 200 | BC10: 260 | BJ10: 0 | BQ10: 0 | BX10: 0 | CE10: 0 | CF10: 0 | CG10: 60 | CH10: 200 | CI10: 0 | CJ10: 0 | CK10: 0 | CL10: 260 | CS10: 0 | CU10: 1 | CV10: 1 | CZ10: 2 | DG10: 0 | DN10: 0 | DU10: 0 | EB10: 0 | EC10: 0 | ED10: 1 | EE10: 1 | EF10: 0 | EG10: 0 | EH10: 0 | EI10: 2 | EJ10: NO | EK10: NO | EL10: NO | EM10: NO | EN10: NO | EO10: NO | EP10: NO | EQ10: YES | ER10: YES | ES10: NO | ET10: NO | EU10: NO | EV10: NO | EW10: NO | EX10: NO | EY10: NO | EZ10: NO | FA10: NO | FB10: NO | FC10: NO | FD10: NO | FE10: NO | FF10: NO | FG10: NO | FH10: NO | FI10: NO | FJ10: NO | FK10: NO | FL10: NO | FM10: NO | FN10: NO | FO10: NO | FP10: NO | FQ10: NO | FR10: NO | FS10: NO | FZ10: 0 | GG10: 0 | GN10: 0 | GU10: 0 | HB10: 0 | HI10: 0 | HP10: 0 | HX10: 0 | HY10: 0 | HZ10: 0 | IA10: 0 | IB10: 0 | IC10: 0 | ID10: 0 | IE10: 0 | IL10: 0 | IN10: 60 | IO10: 200 | IS10: 260 | IZ10: 0 | JG10: 0 | JN10: 0 | JO10: 0 | JP10: 60 | JQ10: 200 | JR10: 0 | JS10: 0 | JT10: 0 | JU10: 260 | JX10: 100 | KA10: 3 | KB10: 3 | KC10: 2 | KD10: START Asia Pacific: | OG10: START Europe: | SJ10: START North America: | WM10: START Global: | AAP10: START SOUTH America: | AES10: START Africa:
A11: C9CAQ433M | B11: INREV | C11: Helaba Invest | D11: Asia | E11: 43517.617 | F11: europe | G11: 43517.617 | P11: TRUE | Q11: TRUE | R11: FALSE | S11: FALSE | T11: FALSE | U11: FALSE | V11: 783 | W11: 43517.617 | X11: 195.191.225.4 | Y11: 2019 | Z11: Tobias Dichtl | AA11: Helaba Invest | AB11: =VLOOKUP(MID(AD11,SEARCH("@",AD11,1),LEN(AD11)-SEARCH("@",AD11,1)+1),[2]Sheet1!$D:$F,3,FALSE) -> M663 | AC11: Portfolio Analyst Research & Strategy | AD11: tobias.dichtl@helaba-invest.de | AE11: 496929970245 | AF11: Germany | AG11: EUR | AI11: 1 | AL11: 2600 | AM11: 2600 | AN11: 1800 | AO11: 1800 | AT11: 200 | AV11: 200 | BA11: 2400 | BC11: 2400 | BJ11: 0 | BQ11: 0 | BX11: 0 | CE11: 0 | CF11: 0 | CG11: 0 | CH11: 0 | CI11: 0 | CJ11: 2600 | CK11: 0 | CL11: 2600 | CQ11: 1 | CS11: 1 | CX11: 9 | CZ11: 9 | DG11: 0 | DN11: 0 | DU11: 0 | EB11: 0 | EC11: 0 | ED11: 0 | EE11: 0 | EF11: 0 | EG11: 10 | EH11: 0 | EI11: 10 | EJ11: NO | EK11: NO | EL11: NO | EM11: NO | EN11: YES | EO11: NO | EP11: NO | EQ11: NO | ER11: NO | ES11: NO | ET11: YES | EU11: NO | EV11: NO | EW11: NO | EX11: NO | EY11: NO | EZ11: NO | FA11: NO | FB11: NO | FC11: NO | FD11: NO | FE11: NO | FF11: NO | FG11: NO | FH11: NO | FI11: NO | FJ11: NO | FK11: NO | FL11: NO | FM11: NO | FN11: NO | FO11: NO | FP11: NO | FQ11: NO | FR11: NO | FS11: NO | FZ11: 0 | GG11: 0 | GN11: 0 | GU11: 0 | HB11: 0 | HI11: 0 | HP11: 0 | HX11: 0 | HY11: 0 | HZ11: 0 | IA11: 0 | IB11: 0 | IC11: 0 | ID11: 0 | IE11: 0 | IL11: 0 | IQ11: 2600 | IS11: 2600 | IZ11: 0 | JG11: 0 | JN11: 0 | JO11: 0 | JP11: 0 | JQ11: 0 | JR11: 0 | JS11: 2600 | JT11: 0 | JU11: 2600 | JV11: 0 | JX11: 100 | KA11: 3 | KB11: 2 | KC11: 1 | KD11: START Asia Pacific: | KI11: 150 | KK11: 150 | KP11: 50 | KR11: 50 | KY11: 0 | LF11: 0 | LM11: 0 | LT11: 0 | MA11: 0 | MI11: 0 | MJ11: 0 | MK11: 0 | ML11: 0 | MM11: 0 | MN11: 200 | MO11: 0 | MP11: 200 | MU11: 200 | MW11: 200 | ND11: 0 | NK11: 0 | NR11: 0 | NY11: 0 | NZ11: 0 | OA11: 0 | OB11: 0 | OC11: 0 | OD11: 200 | OE11: 0 | OF11: 200 | OG11: START Europe: | ON11: 0 | OU11: 0 | PB11: 0 | PI11: 0 | PP11: 0 | PW11: 0 | QD11: 0 | QL11: 0 | QM11: 0 | QN11: 0 | QO11: 0 | QP11: 0 | QQ11: 0 | QR11: 0 | QS11: 0 | QX11: 2400 | QZ11: 2400 | RG11: 0 | RN11: 0 | RU11: 0 | SB11: 0 | SC11: 0 | SD11: 0 | SE11: 0 | SF11: 0 | SG11: 2400 | SH11: 0 | SI11: 2400 | SJ11: START North America: | WM11: START Global: | AAP11: START SOUTH America: | AES11: START Africa:
A12: C9CBD413T | B12: INREV | C12: Frogmore Real Estate Partners Investment Managers Limited | P12: FALSE | Q12: FALSE | R12: FALSE | S12: FALSE | T12: FALSE | U12: FALSE | V12: 745 | W12: 43514.688 | X12: 154.47.76.34 | Y12: 2019 | Z12: Swati | AA12: Frogmore | AB12: =VLOOKUP(MID(AD12,SEARCH("@",AD12,1),LEN(AD12)-SEARCH("@",AD12,1)+1),[2]Sheet1!$D:$F,3,FALSE) -> M490 | AC12: Head of Investor Relations and Client Development | AD12: swatisrivastava@frogmore.co.uk | AF12: United Kingdom | AG12: GBP | AI12: 2 | AJ12: 6 | AK12: We launched our new fourth value add in 2018 | AV12: 0 | BC12: 0 | BJ12: 0 | BQ12: 0 | BX12: 0 | CE12: 0 | CF12: 0 | CG12: 0 | CH12: 0 | CI12: 0 | CJ12: 0 | CK12: 0 | CL12: 0 | CS12: 0 | CZ12: 0 | DG12: 0 | DN12: 0 | DU12: 0 | EB12: 0 | EC12: 0 | ED12: 0 | EE12: 0 | EF12: 0 | EG12: 0 | EH12: 0 | EI12: 0 | EJ12: NO | EK12: NO | EL12: NO | EM12: NO | EN12: NO | EO12: NO | EP12: NO | EQ12: NO | ER12: NO | ES12: NO | ET12: NO | EU12: NO | EV12: NO | EW12: NO | EX12: NO | EY12: NO | EZ12: NO | FA12: NO | FB12: NO | FC12: NO | FD12: NO | FE12: NO | FF12: NO | FG12: NO | FH12: NO | FI12: NO | FJ12: NO | FK12: NO | FL12: NO | FM12: NO | FN12: NO | FO12: NO | FP12: NO | FQ12: NO | FR12: NO | FS12: NO | FZ12: 0 | GG12: 0 | GN12: 0 | GU12: 0 | HB12: 0 | HI12: 0 | HP12: 0 | HX12: 0 | HY12: 0 | HZ12: 0 | IA12: 0 | IB12: 0 | IC12: 0 | ID12: 0 | IE12: 0 | IL12: 0 | IS12: 0 | IZ12: 0 | JG12: 0 | JN12: 0 | JO12: 0 | JP12: 0 | JQ12: 0 | JR12: 0 | JS12: 0 | JT12: 0 | JU12: 0 | KA12: 1 | KB12: 2 | KC12: 1 | KD12: START Asia Pacific: | OG12: START Europe: | SJ12: START North America: | WM12: START Global: | AAP12: START SOUTH America: | AES12: START Africa:
A13: C9CBM470R | B13: INREV | C13: Legal & General Investment Management | P13: TRUE | Q13: FALSE | R13: FALSE | S13: FALSE | T13: FALSE | U13: FALSE | V13: 820 | W13: 43530.766 | X13: 193.200.176.30 | Y13: 2019 | Z13: Savraj Sahota | AA13: Legal & General Investment Management | AB13: =VLOOKUP(MID(AD13,SEARCH("@",AD13,1),LEN(AD13)-SEARCH("@",AD13,1)+1),[2]Sheet1!$D:$F,3,FALSE) -> M465 | AC13: Analyst, Real Assets | AD13: savraj.sahota@lgim.com | AE13: 2031242716 | AF13: United Kingdom | AG13: GBP | AI13: 1 | AL13: 983 | AM13: 829 | AV13: 0 | AW13: 729 | AZ13: 100 | BC13: 829 | BJ13: 0 | BQ13: 0 | BX13: 0 | CE13: 0 | CF13: 729 | CG13: 0 | CH13: 0 | CI13: 100 | CJ13: 0 | CK13: 0 | CL13: 829 | CS13: 0 | CT13: 4 | CW13: 1 | CZ13: 5 | DG13: 0 | DN13: 0 | DU13: 0 | EB13: 0 | EC13: 4 | ED13: 0 | EE13: 0 | EF13: 1 | EG13: 0 | EH13: 0 | EI13: 5 | EJ13: NO | EK13: NO | EL13: NO | EM13: NO | EN13: NO | EO13: NO | EP13: YES | EQ13: NO | ER13: NO | ES13: YES | ET13: NO | EU13: NO | EV13: NO | EW13: NO | EX13: NO | EY13: NO | EZ13: NO | FA13: NO | FB13: NO | FC13: NO | FD13: NO | FE13: NO | FF13: NO | FG13: NO | FH13: NO | FI13: NO | FJ13: NO | FK13: NO | FL13: NO | FM13: NO | FN13: NO | FO13: NO | FP13: NO | FQ13: NO | FR13: NO | FS13: NO | FT13: 652 | FW13: 50 | FZ13: 702 | GD13: 50 | GG13: 50 | GN13: 0 | GU13: 0 | HB13: 0 | HC13: 77 | HI13: 77 | HP13: 0 | HX13: 0 | HY13: 729 | HZ13: 0 | IA13: 0 | IB13: 100 | IC13: 0 | ID13: 0 | IE13: 829 | IL13: 0 | IM13: 729 | IP13: 100 | IS13: 829 | IZ13: 0 | JG13: 0 | JN13: 0 | JO13: 729 | JP13: 0 | JQ13: 0 | JR13: 100 | JS13: 0 | JT13: 0 | JU13: 829 | JX13: 100 | KA13: 3 | KB13: 3 | KC13: 1 | KD13: START Asia Pacific: | OG13: START Europe: | SJ13: START North America: | WM13: START Global: | AAP13: START SOUTH America: | AES13: START Africa:
A14: C9CDF297C | B14: INREV | C14: Grosvenor Europe Limited | F14: europe | G14: 43521.723 | H14: northamerica | I14: 43521.724 | P14: TRUE | Q14: FALSE | R14: TRUE | S14: FALSE | T14: FALSE | U14: FALSE | V14: 581 | W14: 43521.722 | X14: 154.47.76.220 | Y14: 2019 | Z14: James Raynor | AA14: Grosvenor | AB14: =VLOOKUP(MID(AD14,SEARCH("@",AD14,1),LEN(AD14)-SEARCH("@",AD14,1)+1),[2]Sheet1!$D:$F,3,FALSE) -> M052 | AC14: CEO Grosvenor Europe | AD14: james.raynor@grosvenor.com | AF14: United Kingdom | AG14: GBP | AI14: 1 | AL14: 160 | AM14: 160 | AV14: 0 | AZ14: 99 | BC14: 99 | BG14: 61 | BJ14: 61 | BQ14: 0 | BX14: 0 | CE14: 0 | CF14: 0 | CG14: 0 | CH14: 0 | CI14: 160 | CJ14: 0 | CK14: 0 | CL14: 160 | CS14: 0 | CW14: 2 | CZ14: 2 | DD14: 2 | DG14: 2 | DN14: 0 | DU14: 0 | EB14: 0 | EC14: 0 | ED14: 0 | EE14: 0 | EF14: 4 | EG14: 0 | EH14: 0 | EI14: 4 | EJ14: NO | EK14: NO | EL14: NO | EM14: NO | EN14: NO | EO14: NO | EP14: NO | EQ14: NO | ER14: NO | ES14: YES | ET14: NO | EU14: NO | EV14: NO | EW14: NO | EX14: NO | EY14: YES | EZ14: NO | FA14: NO | FB14: NO | FC14: NO | FD14: NO | FE14: NO | FF14: NO | FG14: NO | FH14: NO | FI14: NO | FJ14: NO | FK14: NO | FL14: NO | FM14: NO | FN14: NO | FO14: NO | FP14: NO | FQ14: NO | FR14: NO | FS14: NO | FW14: 15 | FZ14: 15 | GG14: 0 | GN14: 0 | GU14: 0 | HB14: 0 | HI14: 0 | HM14: 145 | HP14: 145 | HX14: 0 | HY14: 0 | HZ14: 0 | IA14: 0 | IB14: 160 | IC14: 0 | ID14: 0 | IE14: 160 | II14: 14 | IL14: 14 | IP14: 85 | IS14: 85 | IW14: 61 | IZ14: 61 | JG14: 0 | JN14: 0 | JO14: 0 | JP14: 0 | JQ14: 0 | JR14: 160 | JS14: 0 | JT14: 0 | JU14: 160 | JX14: 100 | KA14: 1 | KB14: 2 | KC14: 1 | KD14: START Asia Pacific: | OG14: START Europe: | ON14: 0 | OU14: 0 | PB14: 0 | PI14: 0 | PP14: 0 | PW14: 0 | QA14: 99 | QD14: 99 | QL14: 0 | QM14: 0 | QN14: 0 | QO14: 0 | QP14: 99 | QQ14: 0 | QR14: 0 | QS14: 99 | QW14: 85 | QZ14: 85 | RD14: 14 | RG14: 14 | RN14: 0 | RU14: 0 | SB14: 0 | SC14: 0 | SD14: 0 | SE14: 0 | SF14: 99 | SG14: 0 | SH14: 0 | SI14: 99 | SJ14: START North America: | SQ14: 0 | SX14: 0 | TE14: 0 | TL14: 0 | TS14: 0 | TZ14: 0 | UD14: 61 | UG14: 61 | UO14: 0 | UP14: 0 | UQ14: 0 | UR14: 0 | US14: 61 | UT14: 0 | UU14: 0 | UV14: 61 | VC14: 0 | VJ14: 0 | VN14: 61 | VQ14: 61 | VX14: 0 | WE14: 0 | WF14: 0 | WG14: 0 | WH14: 0 | WI14: 61 | WJ14: 0 | WK14: 0 | WL14: 61 | WM14: START Global: | AAP14: START SOUTH America: | AES14: START Africa:
A15: C9CDX506B | B15: INREV | C15: OP Real Estate Asset Management Ltd | P15: TRUE | Q15: FALSE | R15: FALSE | S15: FALSE | T15: FALSE | U15: FALSE | V15: 756 | W15: 43515.469 | X15: 157.124.30.3 | Y15: 2019 | Z15: Pami Pihlström | AA15: OP Real Estate Asset Management | AB15: =VLOOKUP(MID(AD15,SEARCH("@",AD15,1),LEN(AD15)-SEARCH("@",AD15,1)+1),[2]Sheet1!$D:$F,3,FALSE) -> M122 | AC15: CIO | AD15: pami.pihlstrom@op.fi | AE15: +358 10 | AF15: Finland | AG15: EUR | AI15: 1 | AL15: 303 | AM15: 303 | AN15: 250 | AO15: 250 | AV15: 0 | AW15: 293 | BA15: 10 | BC15: 303 | BJ15: 0 | BQ15: 0 | BX15: 0 | CE15: 0 | CF15: 293 | CG15: 0 | CH15: 0 | CI15: 0 | CJ15: 10 | CK15: 0 | CL15: 303 | CS15: 0 | CT15: 5 | CX15: 1 | CZ15: 6 | DG15: 0 | DN15: 0 | DU15: 0 | EB15: 0 | EC15: 5 | ED15: 0 | EE15: 0 | EF15: 0 | EG15: 1 | EH15: 0 | EI15: 6 | EJ15: NO | EK15: NO | EL15: NO | EM15: NO | EN15: NO | EO15: NO | EP15: YES | EQ15: NO | ER15: NO | ES15: NO | ET15: YES | EU15: NO | EV15: NO | EW15: NO | EX15: NO | EY15: NO | EZ15: NO | FA15: NO | FB15: NO | FC15: NO | FD15: NO | FE15: NO | FF15: NO | FG15: NO | FH15: NO | FI15: NO | FJ15: NO | FK15: NO | FL15: NO | FM15: NO | FN15: NO | FO15: NO | FP15: NO | FQ15: NO | FR15: NO | FS15: NO | FT15: 5 | FZ15: 5 | GA15: 6 | GE15: 5 | GG15: 11 | GN15: 0 | GU15: 0 | GV15: 5 | GZ15: 5 | HB15: 10 | HI15: 0 | HJ15: 277 | HP15: 277 | HX15: 0 | HY15: 293 | HZ15: 0 | IA15: 0 | IB15: 0 | IC15: 10 | ID15: 0 | IE15: 303 | IL15: 0 | IM15: 293 | IQ15: 10 | IS15: 303 | IZ15: 0 | JG15: 0 | JN15: 0 | JO15: 293 | JP15: 0 | JQ15: 0 | JR15: 0 | JS15: 10 | JT15: 0 | JU15: 303 | JX15: 100 | KA15: 3 | KB15: 3 | KC15: 1 | KD15: START Asia Pacific: | OG15: START Europe: | SJ15: START North America: | WM15: START Global: | AAP15: START SOUTH America: | AES15: START Africa:
A16: C9CDZ380J | B16: INREV | C16: Delancey Real Estate Asset Management | P16: TRUE | Q16: FALSE | R16: FALSE | S16: FALSE | T16: FALSE | U16: FALSE | V16: 625 | W16: 43520.65 | X16: 154.47.76.16 | Y16: 2019 | Z16: Eric Lemer | AA16: Delancey Real Estate Asset Management | AB16: =VLOOKUP(MID(AD16,SEARCH("@",AD16,1),LEN(AD16)-SEARCH("@",AD16,1)+1),[2]Sheet1!$D:$F,3,FALSE) -> M2715 | AC16: Director, Business Development | AD16: eric.lemer@delancey.com | AE16: =44-797-122-6842 -> -7717 | AF16: United Kingdom | AG16: GBP | AI16: 1 | AL16: 150 | AM16: 150 | AN16: 150 | AO16: 150 | AV16: 0 | AW16: 150 | BC16: 150 | BJ16: 0 | BQ16: 0 | BX16: 0 | CE16: 0 | CF16: 150 | CG16: 0 | CH16: 0 | CI16: 0 | CJ16: 0 | CK16: 0 | CL16: 150 | CS16: 0 | CT16: 1 | CZ16: 1 | DG16: 0 | DN16: 0 | DU16: 0 | EB16: 0 | EC16: 1 | ED16: 0 | EE16: 0 | EF16: 0 | EG16: 0 | EH16: 0 | EI16: 1 | EJ16: NO | EK16: NO | EL16: NO | EM16: NO | EN16: NO | EO16: NO | EP16: YES | EQ16: NO | ER16: NO | ES16: NO | ET16: NO | EU16: NO | EV16: NO | EW16: NO | EX16: NO | EY16: NO | EZ16: NO | FA16: NO | FB16: NO | FC16: NO | FD16: NO | FE16: NO | FF16: NO | FG16: NO | FH16: NO | FI16: NO | FJ16: NO | FK16: NO | FL16: NO | FM16: NO | FN16: NO | FO16: NO | FP16: NO | FQ16: NO | FR16: NO | FS16: NO | FT16: 40 | FZ16: 40 | GG16: 0 | GN16: 0 | GU16: 0 | HB16: 0 | HC16: 80 | HI16: 80 | HJ16: 30 | HP16: 30 | HX16: 0 | HY16: 150 | HZ16: 0 | IA16: 0 | IB16: 0 | IC16: 0 | ID16: 0 | IE16: 150 | IL16: 0 | IM16: 138 | IS16: 138 | IT16: 12 | IZ16: 12 | JG16: 0 | JN16: 0 | JO16: 150 | JP16: 0 | JQ16: 0 | JR16: 0 | JS16: 0 | JT16: 0 | JU16: 150 | JX16: 100 | KA16: 1 | KB16: 2 | KC16: 2 | KD16: START Asia Pacific: | OG16: START Europe: | SJ16: START North America: | WM16: START Global: | AAP16: START SOUTH America: | AES16: START Africa:
A17: C9CFW373W | B17: INREV | C17: Cording Real Estate Group Limited | P17: TRUE | Q17: FALSE | R17: FALSE | S17: FALSE | T17: FALSE | U17: FALSE | V17: 735 | W17: 43517.352 | X17: 195.243.133.82 | Y17: 2019 | Z17: Naomi Vlakancic | AA17: Cording Real Estate Group | AB17: =VLOOKUP(MID(AD17,SEARCH("@",AD17,1),LEN(AD17)-SEARCH("@",AD17,1)+1),[2]Sheet1!$D:$F,3,FALSE) -> M506 | AC17: Head of Investor Relations | AD17: naomi.vlakancic@cordinggroup.com | AE17: +44 (0)20 3206 7911 | AF17: United Kingdom | AG17: EUR | AI17: 1 | AL17: 328 | AM17: 328 | AN17: 268 | AO17: 268 | AV17: 0 | AW17: 202 | AX17: 126 | BC17: 328 | BJ17: 0 | BQ17: 0 | BX17: 0 | CE17: 0 | CF17: 202 | CG17: 126 | CH17: 0 | CI17: 0 | CJ17: 0 | CK17: 0 | CL17: 328 | CS17: 0 | CT17: 4 | CU17: 3 | CZ17: 7 | DG17: 0 | DN17: 0 | DU17: 0 | EB17: 0 | EC17: 4 | ED17: 3 | EE17: 0 | EF17: 0 | EG17: 0 | EH17: 0 | EI17: 7 | EJ17: NO | EK17: NO | EL17: NO | EM17: NO | EN17: NO | EO17: NO | EP17: YES | EQ17: YES | ER17: NO | ES17: NO | ET17: NO | EU17: NO | EV17: NO | EW17: NO | EX17: NO | EY17: NO | EZ17: NO | FA17: NO | FB17: NO | FC17: NO | FD17: NO | FE17: NO | FF17: NO | FG17: NO | FH17: NO | FI17: NO | FJ17: NO | FK17: NO | FL17: NO | FM17: NO | FN17: NO | FO17: NO | FP17: NO | FQ17: NO | FR17: NO | FS17: NO | FT17: 54 | FU17: 36 | FZ17: 90 | GG17: 0 | GN17: 0 | GU17: 0 | HB17: 0 | HC17: 147 | HI17: 147 | HJ17: 91 | HP17: 91 | HX17: 0 | HY17: 292 | HZ17: 36 | IA17: 0 | IB17: 0 | IC17: 0 | ID17: 0 | IE17: 328 | IL17: 0 | IM17: 292 | IN17: 36 | IS17: 328 | IZ17: 0 | JG17: 0 | JN17: 0 | JO17: 292 | JP17: 36 | JQ17: 0 | JR17: 0 | JS17: 0 | JT17: 0 | JU17: 328 | JX17: 100 | KA17: 1 | KB17: 2 | KC17: 1 | KD17: START Asia Pacific: | OG17: START Europe: | SJ17: START North America: | WM17: START Global: | AAP17: START SOUTH America: | AES17: START Africa:
A18: C9CGC870P | B18: ANREV | C18: Pamfleet | P18: FALSE | Q18: TRUE | R18: FALSE | S18: FALSE | T18: FALSE | U18: FALSE | V18: 712 | W18: 43509.165 | X18: 118.200.5.237 | Y18: 2019 | Z18: YC Tang | AA18: Pamfleet | AB18: =VLOOKUP(MID(AD18,SEARCH("@",AD18,1),LEN(AD18)-SEARCH("@",AD18,1)+1),[2]Sheet1!$D:$F,3,FALSE) -> M0125 | AC18: Head of Investor Relations | AD18: yc.tang@pamfleet.com | AE18: 65 6325 0160 | AF18: Hong Kong | AG18: USD | AI18: 1 | AL18: 420 | AM18: 420 | AN18: 0 | AO18: 0 | AP18: 420 | AV18: 420 | BC18: 0 | BJ18: 0 | BQ18: 0 | BX18: 0 | CE18: 0 | CF18: 420 | CG18: 0 | CH18: 0 | CI18: 0 | CJ18: 0 | CK18: 0 | CL18: 420 | CM18: 1 | CS18: 1 | CZ18: 0 | DG18: 0 | DN18: 0 | DU18: 0 | EB18: 0 | EC18: 1 | ED18: 0 | EE18: 0 | EF18: 0 | EG18: 0 | EH18: 0 | EI18: 1 | EJ18: YES | EK18: NO | EL18: NO | EM18: NO | EN18: NO | EO18: NO | EP18: NO | EQ18: NO | ER18: NO | ES18: NO | ET18: NO | EU18: NO | EV18: NO | EW18: NO | EX18: NO | EY18: NO | EZ18: NO | FA18: NO | FB18: NO | FC18: NO | FD18: NO | FE18: NO | FF18: NO | FG18: NO | FH18: NO | FI18: NO | FJ18: NO | FK18: NO | FL18: NO | FM18: NO | FN18: NO | FO18: NO | FP18: NO | FQ18: NO | FR18: NO | FS18: NO | FT18: 150 | FZ18: 150 | GA18: 35 | GG18: 35 | GN18: 0 | GU18: 0 | GV18: 50 | HB18: 50 | HC18: 165 | HI18: 165 | HJ18: 13 | HP18: 13 | HQ18: GP coinvestment | HR18: 7 | HX18: 7 | HY18: 420 | HZ18: 0 | IA18: 0 | IB18: 0 | IC18: 0 | ID18: 0 | IE18: 420 | IF18: 107 | IL18: 107 | IM18: 178 | IS18: 178 | IT18: 135 | IZ18: 135 | JG18: 0 | JN18: 0 | JO18: 420 | JP18: 0 | JQ18: 0 | JR18: 0 | JS18: 0 | JT18: 0 | JU18: 420 | JV18: 19 | JX18: 79 | JY18: GP coinvestment | JZ18: 2 | KA18: 1 | KB18: 2 | KC18: 1 | KD18: START Asia Pacific: | OG18: START Europe: | SJ18: START North America: | WM18: START Global: | AAP18: START SOUTH America: | AES18: START Africa:
A19: C9CJR360D | B19: ANREV | C19: CITIC Capital Holdings Limited | P19: FALSE | Q19: TRUE | R19: FALSE | S19: FALSE | T19: FALSE | U19: FALSE | V19: 635 | W19: 43508.421 | X19: 61.244.118.81 | Y19: 2019 | Z19: Kash Lam | AA19: CITIC Capital | AB19: =VLOOKUP(MID(AD19,SEARCH("@",AD19,1),LEN(AD19)-SEARCH("@",AD19,1)+1),[2]Sheet1!$D:$F,3,FALSE) -> M0107 | AC19: Vice President | AD19: kashlam@citiccapital.com | AE19: 3710 6952 | AF19: Hong Kong | AG19: CNY | AI19: 1 | AL19: 420 | AM19: 420 | AN19: 340 | AO19: 340 | AP19: 420 | AV19: 420 | BC19: 0 | BJ19: 0 | BQ19: 0 | BX19: 0 | CE19: 0 | CF19: 420 | CG19: 0 | CH19: 0 | CI19: 0 | CJ19: 0 | CK19: 0 | CL19: 420 | CM19: 2 | CS19: 2 | CZ19: 0 | DG19: 0 | DN19: 0 | DU19: 0 | EB19: 0 | EC19: 2 | ED19: 0 | EE19: 0 | EF19: 0 | EG19: 0 | EH19: 0 | EI19: 2 | EJ19: YES | EK19: NO | EL19: NO | EM19: NO | EN19: NO | EO19: NO | EP19: NO | EQ19: NO | ER19: NO | ES19: NO | ET19: NO | EU19: NO | EV19: NO | EW19: NO | EX19: NO | EY19: NO | EZ19: NO | FA19: NO | FB19: NO | FC19: NO | FD19: NO | FE19: NO | FF19: NO | FG19: NO | FH19: NO | FI19: NO | FJ19: NO | FK19: NO | FL19: NO | FM19: NO | FN19: NO | FO19: NO | FP19: NO | FQ19: NO | FR19: NO | FS19: NO | FT19: 420 | FZ19: 420 | GG19: 0 | GN19: 0 | GU19: 0 | HB19: 0 | HI19: 0 | HP19: 0 | HX19: 0 | HY19: 420 | HZ19: 0 | IA19: 0 | IB19: 0 | IC19: 0 | ID19: 0 | IE19: 420 | IF19: 420 | IL19: 420 | IS19: 0 | IZ19: 0 | JG19: 0 | JN19: 0 | JO19: 420 | JP19: 0 | JQ19: 0 | JR19: 0 | JS19: 0 | JT19: 0 | JU19: 420 | JX19: 100 | KA19: 3 | KB19: 3 | KC19: 1 | KD19: START Asia Pacific: | OG19: START Europe: | SJ19: START North America: | WM19: START Global: | AAP19: START SOUTH America: | AES19: START Africa:
A20: C9CRE548M | B20: INREV | C20: Sirius Capital Partners | P20: TRUE | Q20: FALSE | R20: FALSE | S20: FALSE | T20: FALSE | U20: FALSE | V20: 592 | W20: 43508.549 | X20: 194.111.75.232 | Y20: 2019 | Z20: Nina Cainberg | AA20: Sirius Capital Partners | AB20: =VLOOKUP(MID(AD20,SEARCH("@",AD20,1),LEN(AD20)-SEARCH("@",AD20,1)+1),[2]Sheet1!$D:$F,3,FALSE) -> M757 | AD20: nina.cainberg@sirius.fi | AF20: Finland | AG20: EUR | AI20: 1 | AL20: 35 | AM20: 35 | AN20: 30 | AO20: 30 | AV20: 0 | AW20: 35 | BC20: 35 | BJ20: 0 | BQ20: 0 | BX20: 0 | CE20: 0 | CF20: 35 | CG20: 0 | CH20: 0 | CI20: 0 | CJ20: 0 | CK20: 0 | CL20: 35 | CS20: 0 | CT20: 1 | CZ20: 1 | DG20: 0 | DN20: 0 | DU20: 0 | EB20: 0 | EC20: 1 | ED20: 0 | EE20: 0 | EF20: 0 | EG20: 0 | EH20: 0 | EI20: 1 | EJ20: NO | EK20: NO | EL20: NO | EM20: NO | EN20: NO | EO20: NO | EP20: YES | EQ20: NO | ER20: NO | ES20: NO | ET20: NO | EU20: NO | EV20: NO | EW20: NO | EX20: NO | EY20: NO | EZ20: NO | FA20: NO | FB20: NO | FC20: NO | FD20: NO | FE20: NO | FF20: NO | FG20: NO | FH20: NO | FI20: NO | FJ20: NO | FK20: NO | FL20: NO | FM20: NO | FN20: NO | FO20: NO | FP20: NO | FQ20: NO | FR20: NO | FS20: NO | FT20: 25 | FZ20: 25 | GG20: 0 | GN20: 0 | GU20: 0 | HB20: 0 | HC20: 5 | HI20: 5 | HJ20: 5 | HP20: 5 | HX20: 0 | HY20: 35 | HZ20: 0 | IA20: 0 | IB20: 0 | IC20: 0 | ID20: 0 | IE20: 35 | IL20: 0 | IM20: 35 | IS20: 35 | IZ20: 0 | JG20: 0 | JN20: 0 | JO20: 35 | JP20: 0 | JQ20: 0 | JR20: 0 | JS20: 0 | JT20: 0 | JU20: 35 | JX20: 100 | KA20: 3 | KB20: 3 | KC20: 1 | KD20: START Asia Pacific: | OG20: START Europe: | SJ20: START North America: | WM20: START Global: | AAP20: START SOUTH America: | AES20: START Africa:
A21: C9CWV526T | B21: INREV | C21: PROJECT Investment AG | P21: FALSE | Q21: FALSE | R21: FALSE | S21: FALSE | T21: FALSE | U21: FALSE | V21: 741 | W21: 43515.463 | X21: 37.60.5.66 | Y21: 2019 | Z21: Uwira Jürgen | AA21: PROJECT Investment AG | AB21: =VLOOKUP(MID(AD21,SEARCH("@",AD21,1),LEN(AD21)-SEARCH("@",AD21,1)+1),[2]Sheet1!$D:$F,3,FALSE) -> M680 | AC21: Managing Director PROJECT Real Estate Trust | AD21: j.uwira@project-investment.de | AE21: 0049 89 599890861 | AF21: Germany | AG21: EUR | AI21: 2 | AJ21: 6 | AK21: Open commitments, to avoid conflicts of interest start of next AIF in 2019 | AV21: 0 | BC21: 0 | BJ21: 0 | BQ21: 0 | BX21: 0 | CE21: 0 | CF21: 0 | CG21: 0 | CH21: 0 | CI21: 0 | CJ21: 0 | CK21: 0 | CL21: 0 | CS21: 0 | CZ21: 0 | DG21: 0 | DN21: 0 | DU21: 0 | EB21: 0 | EC21: 0 | ED21: 0 | EE21: 0 | EF21: 0 | EG21: 0 | EH21: 0 | EI21: 0 | EJ21: NO | EK21: NO | EL21: NO | EM21: NO | EN21: NO | EO21: NO | EP21: NO | EQ21: NO | ER21: NO | ES21: NO | ET21: NO | EU21: NO | EV21: NO | EW21: NO | EX21: NO | EY21: NO | EZ21: NO | FA21: NO | FB21: NO | FC21: NO | FD21: NO | FE21: NO | FF21: NO | FG21: NO | FH21: NO | FI21: NO | FJ21: NO | FK21: NO | FL21: NO | FM21: NO | FN21: NO | FO21: NO | FP21: NO | FQ21: NO | FR21: NO | FS21: NO | FZ21: 0 | GG21: 0 | GN21: 0 | GU21: 0 | HB21: 0 | HI21: 0 | HP21: 0 | HX21: 0 | HY21: 0 | HZ21: 0 | IA21: 0 | IB21: 0 | IC21: 0 | ID21: 0 | IE21: 0 | IL21: 0 | IS21: 0 | IZ21: 0 | JG21: 0 | JN21: 0 | JO21: 0 | JP21: 0 | JQ21: 0 | JR21: 0 | JS21: 0 | JT21: 0 | JU21: 0 | KA21: 1 | KB21: 2 | KC21: 1 | KD21: START Asia Pacific: | OG21: START Europe: | SJ21: START North America: | WM21: START Global: | AAP21: START SOUTH America: | AES21: START Africa:
A22: C9CYV634C | B22: NCREIF | C22: Equus Capital Partners | P22: FALSE | Q22: FALSE | R22: TRUE | S22: FALSE | T22: FALSE | U22: FALSE | V22: 600 | W22: 43481.849 | X22: 204.237.132.2 | Y22: 2019 | Z22: Joseph G Nahas, Jr CRE | AA22: Equus Capital Partners, Ltd. | AB22: =VLOOKUP(MID(AD22,SEARCH("@",AD22,1),LEN(AD22)-SEARCH("@",AD22,1)+1),[2]Sheet1!$D:$F,3,FALSE) -> NC017 | AC22: Sr. Vice President | AD22: jnahas@equuspartners.com | AE22: 215-575-2363 | AF22: United States | AG22: USD | AI22: 1 | AL22: 710 | AM22: 710 | AN22: 561 | AO22: 561 | AV22: 0 | BC22: 0 | BD22: 237 | BE22: 473 | BJ22: 710 | BQ22: 0 | BX22: 0 | CE22: 0 | CF22: 237 | CG22: 473 | CH22: 0 | CI22: 0 | CJ22: 0 | CK22: 0 | CL22: 710 | CS22: 0 | CZ22: 0 | DA22: 1 | DB22: 2 | DG22: 3 | DN22: 0 | DU22: 0 | EB22: 0 | EC22: 1 | ED22: 2 | EE22: 0 | EF22: 0 | EG22: 0 | EH22: 0 | EI22: 3 | EJ22: NO | EK22: NO | EL22: NO | EM22: NO | EN22: NO | EO22: NO | EP22: NO | EQ22: NO | ER22: NO | ES22: NO | ET22: NO | EU22: NO | EV22: YES | EW22: YES | EX22: NO | EY22: NO | EZ22: NO | FA22: NO | FB22: NO | FC22: NO | FD22: NO | FE22: NO | FF22: NO | FG22: NO | FH22: NO | FI22: NO | FJ22: NO | FK22: NO | FL22: NO | FM22: NO | FN22: NO | FO22: NO | FP22: NO | FQ22: NO | FR22: NO | FS22: NO | FT22: 191 | FZ22: 191 | GG22: 0 | GN22: 0 | GU22: 0 | GV22: 26 | HB22: 26 | HD22: 473 | HI22: 473 | HJ22: 20 | HP22: 20 | HX22: 0 | HY22: 237 | HZ22: 473 | IA22: 0 | IB22: 0 | IC22: 0 | ID22: 0 | IE22: 710 | IL22: 0 | IS22: 0 | IT22: 237 | IU22: 473 | IZ22: 710 | JG22: 0 | JN22: 0 | JO22: 237 | JP22: 473 | JQ22: 0 | JR22: 0 | JS22: 0 | JT22: 0 | JU22: 710 | JV22: 0 | JX22: 100 | KA22: 2 | KB22: 3 | KC22: 2 | KD22: START Asia Pacific: | OG22: START Europe: | SJ22: START North America: | WM22: START Global: | AAP22: START SOUTH America: | AES22: START Africa:
A23: C9CZY636N | B23: NCREIF | C23: Farmland Opportunity | LLC | P23: FALSE | Q23: FALSE | R23: FALSE | S23: FALSE | T23: FALSE | U23: FALSE | V23: 609 | W23: 43482.051 | X23: 174.216.26.60 | Y23: 2019 | Z23: Jay Girotto | AA23: Farmland Opportunity, LLC | AB23: =VLOOKUP(MID(AD23,SEARCH("@",AD23,1),LEN(AD23)-SEARCH("@",AD23,1)+1),[2]Sheet1!$D:$F,3,FALSE) -> NC001 | AC23: President | AD23: jgirotto@farmopp.com | AE23: 4253010728 | AF23: United States | AG23: USD | AI23: 2 | AJ23: 6 | AK23: High net worth, single family offices only | AV23: 0 | BC23: 0 | BJ23: 0 | BQ23: 0 | BX23: 0 | CE23: 0 | CF23: 0 | CG23: 0 | CH23: 0 | CI23: 0 | CJ23: 0 | CK23: 0 | CL23: 0 | CS23: 0 | CZ23: 0 | DG23: 0 | DN23: 0 | DU23: 0 | EB23: 0 | EC23: 0 | ED23: 0 | EE23: 0 | EF23: 0 | EG23: 0 | EH23: 0 | EI23: 0 | EJ23: NO | EK23: NO | EL23: NO | EM23: NO | EN23: NO | EO23: NO | EP23: NO | EQ23: NO | ER23: NO | ES23: NO | ET23: NO | EU23: NO | EV23: NO | EW23: NO | EX23: NO | EY23: NO | EZ23: NO | FA23: NO | FB23: NO | FC23: NO | FD23: NO | FE23: NO | FF23: NO | FG23: NO | FH23: NO | FI23: NO | FJ23: NO | FK23: NO | FL23: NO | FM23: NO | FN23: NO | FO23: NO | FP23: NO | FQ23: NO | FR23: NO | FS23: NO | FZ23: 0 | GG23: 0 | GN23: 0 | GU23: 0 | HB23: 0 | HI23: 0 | HP23: 0 | HX23: 0 | HY23: 0 | HZ23: 0 | IA23: 0 | IB23: 0 | IC23: 0 | ID23: 0 | IE23: 0 | IL23: 0 | IS23: 0 | IZ23: 0 | JG23: 0 | JN23: 0 | JO23: 0 | JP23: 0 | JQ23: 0 | JR23: 0 | JS23: 0 | JT23: 0 | JU23: 0 | KA23: 1 | KB23: 3 | KC23: 1 | KD23: START Asia Pacific: | OG23: START Europe: | SJ23: START North America: | WM23: START Global: | AAP23: START SOUTH America: | AES23: START Africa:
A24: C9DEV464E | B24: INREV | C24: Kristensen Properties | P24: FALSE | Q24: FALSE | R24: FALSE | S24: FALSE | T24: FALSE | U24: FALSE | V24: 591 | W24: 43481.479 | X24: 87.51.5.162 | Y24: 2019 | Z24: Anders Holm Pedersen | AA24: Kristensen Properties | AB24: =VLOOKUP(MID(AD24,SEARCH("@",AD24,1),LEN(AD24)-SEARCH("@",AD24,1)+1),[2]Sheet1!$D:$F,3,FALSE) -> M160 | AC24: CIO | AD24: ahp@kristensenproperties.com | AE24: 4520606020 | AF24: Denmark | AG24: EUR | AI24: 2 | AJ24: 2 | AV24: 0 | BC24: 0 | BJ24: 0 | BQ24: 0 | BX24: 0 | CE24: 0 | CF24: 0 | CG24: 0 | CH24: 0 | CI24: 0 | CJ24: 0 | CK24: 0 | CL24: 0 | CS24: 0 | CZ24: 0 | DG24: 0 | DN24: 0 | DU24: 0 | EB24: 0 | EC24: 0 | ED24: 0 | EE24: 0 | EF24: 0 | EG24: 0 | EH24: 0 | EI24: 0 | EJ24: NO | EK24: NO | EL24: NO | EM24: NO | EN24: NO | EO24: NO | EP24: NO | EQ24: NO | ER24: NO | ES24: NO | ET24: NO | EU24: NO | EV24: NO | EW24: NO | EX24: NO | EY24: NO | EZ24: NO | FA24: NO | FB24: NO | FC24: NO | FD24: NO | FE24: NO | FF24: NO | FG24: NO | FH24: NO | FI24: NO | FJ24: NO | FK24: NO | FL24: NO | FM24: NO | FN24: NO | FO24: NO | FP24: NO | FQ24: NO | FR24: NO | FS24: NO | FZ24: 0 | GG24: 0 | GN24: 0 | GU24: 0 | HB24: 0 | HI24: 0 | HP24: 0 | HX24: 0 | HY24: 0 | HZ24: 0 | IA24: 0 | IB24: 0 | IC24: 0 | ID24: 0 | IE24: 0 | IL24: 0 | IS24: 0 | IZ24: 0 | JG24: 0 | JN24: 0 | JO24: 0 | JP24: 0 | JQ24: 0 | JR24: 0 | JS24: 0 | JT24: 0 | JU24: 0 | KA24: 1 | KB24: 2 | KC24: 1 | KD24: START Asia Pacific: | OG24: START Europe: | SJ24: START North America: | WM24: START Global: | AAP24: START SOUTH America: | AES24: START Africa:
A25: C9DFE466Y | B25: INREV | C25: La Française | P25: TRUE | Q25: FALSE | R25: FALSE | S25: FALSE | T25: FALSE | U25: FALSE | V25: 549 | W25: 43518.68 | X25: 83.167.51.62 | Y25: 2019 | Z25: Donovan McGill | AA25: La Francaise | AB25: =VLOOKUP(MID(AD25,SEARCH("@",AD25,1),LEN(AD25)-SEARCH("@",AD25,1)+1),[2]Sheet1!$D:$F,3,FALSE) -> M379 | AC25: International Marketing Manager | AD25: dmcgill@la-francaise.com | AF25: France | AG25: EUR | AI25: 1 | AL25: 3127 | AM25: 3127 | AN25: 3127 | AO25: 3127 | AV25: 0 | AW25: 1686.5 | AX25: 1440.7 | BC25: 3127.2 | BJ25: 0 | BQ25: 0 | BX25: 0 | CE25: 0 | CF25: 1686.5 | CG25: 1440.7 | CH25: 0 | CI25: 0 | CJ25: 0 | CK25: 0 | CL25: 3127.2 | CS25: 0 | DG25: 0 | DN25: 0 | DU25: 0 | EB25: 0 | EE25: 0 | EF25: 0 | EG25: 0 | EH25: 0 | EJ25: NO | EK25: NO | EL25: NO | EM25: NO | EN25: NO | EO25: NO | EP25: YES | EQ25: YES | ER25: NO | ES25: NO | ET25: NO | EU25: NO | EV25: NO | EW25: NO | EX25: NO | EY25: NO | EZ25: NO | FA25: NO | FB25: NO | FC25: NO | FD25: NO | FE25: NO | FF25: NO | FG25: NO | FH25: NO | FI25: NO | FJ25: NO | FK25: NO | FL25: NO | FM25: NO | FN25: NO | FO25: NO | FP25: NO | FQ25: NO | FR25: NO | FS25: NO | FT25: 289.4 | FU25: 565.8 | FZ25: 855.2 | GA25: 478.3 | GB25: 874.9 | GG25: 1353.2 | GN25: 0 | GU25: 0 | GV25: 30 | HB25: 30 | HI25: 0 | HJ25: 506.3 | HP25: 506.3 | HQ25: Non-financial corporates | HR25: 382.5 | HX25: 382.5 | HY25: 1686.5 | HZ25: 1440.7 | IA25: 0 | IB25: 0 | IC25: 0 | ID25: 0 | IE25: 3127.2 | IG25: 217 | IL25: 217 | IM25: 1685.5 | IN25: 1223.7 | IS25: 2909.2 | IZ25: 0 | JG25: 0 | JH25: 1 | JN25: 1 | JO25: 1686.5 | JP25: 1440.7 | JQ25: 0 | JR25: 0 | JS25: 0 | JT25: 0 | JU25: 3127.2 | JX25: 100 | KA25: 1 | KB25: 3 | KC25: 1 | KD25: START Asia Pacific: | OG25: START Europe: | SJ25: START North America: | WM25: START Global: | AAP25: START SOUTH America: | AES25: START Africa:
A26: C9DGF873T | B26: ANREV | C26: Propertylink Group | P26: FALSE | Q26: FALSE | R26: FALSE | S26: FALSE | T26: FALSE | U26: FALSE | V26: 694 | W26: 43501.132 | X26: 103.252.58.14 | Y26: 2019 | Z26: Tim Simpson | AA26: Propertylink | AB26: =VLOOKUP(MID(AD26,SEARCH("@",AD26,1),LEN(AD26)-SEARCH("@",AD26,1)+1),[2]Sheet1!$D:$F,3,FALSE) -> M0220 | AC26: General Manager | AD26: tsimpson@propertylink.com.au | AE26: +612 9186 4700 | AF26: Australia | AG26: AUD | AI26: 2 | AJ26: 6 | AK26: ongoing corporate restructure | AV26: 0 | BC26: 0 | BJ26: 0 | BQ26: 0 | BX26: 0 | CE26: 0 | CF26: 0 | CG26: 0 | CH26: 0 | CI26: 0 | CJ26: 0 | CK26: 0 | CL26: 0 | CS26: 0 | CZ26: 0 | DG26: 0 | DN26: 0 | DU26: 0 | EB26: 0 | EC26: 0 | ED26: 0 | EE26: 0 | EF26: 0 | EG26: 0 | EH26: 0 | EI26: 0 | EJ26: NO | EK26: NO | EL26: NO | EM26: NO | EN26: NO | EO26: NO | EP26: NO | EQ26: NO | ER26: NO | ES26: NO | ET26: NO | EU26: NO | EV26: NO | EW26: NO | EX26: NO | EY26: NO | EZ26: NO | FA26: NO | FB26: NO | FC26: NO | FD26: NO | FE26: NO | FF26: NO | FG26: NO | FH26: NO | FI26: NO | FJ26: NO | FK26: NO | FL26: NO | FM26: NO | FN26: NO | FO26: NO | FP26: NO | FQ26: NO | FR26: NO | FS26: NO | FZ26: 0 | GG26: 0 | GN26: 0 | GU26: 0 | HB26: 0 | HI26: 0 | HP26: 0 | HX26: 0 | HY26: 0 | HZ26: 0 | IA26: 0 | IB26: 0 | IC26: 0 | ID26: 0 | IE26: 0 | IL26: 0 | IS26: 0 | IZ26: 0 | JG26: 0 | JN26: 0 | JO26: 0 | JP26: 0 | JQ26: 0 | JR26: 0 | JS26: 0 | JT26: 0 | JU26: 0 | KA26: 1 | KB26: 3 | KC26: 1 | KD26: START Asia Pacific: | OG26: START Europe: | SJ26: START North America: | WM26: START Global: | AAP26: START SOUTH America: | AES26: START Africa:
A27: C9DJC456T | B27: INREV | C27: Kames Capital | P27: FALSE | Q27: FALSE | R27: FALSE | S27: FALSE | T27: FALSE | U27: FALSE | V27: 556 | W27: 43475.388 | X27: 198.39.100.21 | Y27: 2019 | Z27: Philip Clark | AA27: AEGON Asset Management | AB27: =VLOOKUP(MID(AD27,SEARCH("@",AD27,1),LEN(AD27)-SEARCH("@",AD27,1)+1),[2]Sheet1!$D:$F,3,FALSE) -> M291 | AC27: European Head of Real Estate | AD27: phil.clark@kamescapital.com | AE27: 0044 7740 897989 | AF27: Netherlands | AG27: EUR | AI27: 2 | AJ27: 6 | AK27: No funds launched. | AV27: 0 | BC27: 0 | BJ27: 0 | BQ27: 0 | BX27: 0 | CE27: 0 | CF27: 0 | CG27: 0 | CH27: 0 | CI27: 0 | CJ27: 0 | CK27: 0 | CL27: 0 | CS27: 0 | CZ27: 0 | DG27: 0 | DN27: 0 | DU27: 0 | EB27: 0 | EC27: 0 | ED27: 0 | EE27: 0 | EF27: 0 | EG27: 0 | EH27: 0 | EI27: 0 | EJ27: NO | EK27: NO | EL27: NO | EM27: NO | EN27: NO | EO27: NO | EP27: NO | EQ27: NO | ER27: NO | ES27: NO | ET27: NO | EU27: NO | EV27: NO | EW27: NO | EX27: NO | EY27: NO | EZ27: NO | FA27: NO | FB27: NO | FC27: NO | FD27: NO | FE27: NO | FF27: NO | FG27: NO | FH27: NO | FI27: NO | FJ27: NO | FK27: NO | FL27: NO | FM27: NO | FN27: NO | FO27: NO | FP27: NO | FQ27: NO | FR27: NO | FS27: NO | FZ27: 0 | GG27: 0 | GN27: 0 | GU27: 0 | HB27: 0 | HI27: 0 | HP27: 0 | HX27: 0 | HY27: 0 | HZ27: 0 | IA27: 0 | IB27: 0 | IC27: 0 | ID27: 0 | IE27: 0 | IL27: 0 | IS27: 0 | IZ27: 0 | JG27: 0 | JN27: 0 | JO27: 0 | JP27: 0 | JQ27: 0 | JR27: 0 | JS27: 0 | JT27: 0 | JU27: 0 | KA27: 2 | KB27: 2 | KC27: 2 | KD27: START Asia Pacific: | OG27: START Europe: | SJ27: START North America: | WM27: START Global: | AAP27: START SOUTH America: | AES27: START Africa:
A28: C9DJE896V | B28: ANREV | C28: White Peak | P28: FALSE | Q28: TRUE | R28: FALSE | S28: FALSE | T28: FALSE | U28: FALSE | V28: 727 | W28: 43524.32 | X28: 157.55.39.96 | Y28: 2019 | Z28: Karen Xu | AA28: White Peak Real Estate Investment | AB28: =VLOOKUP(MID(AD28,SEARCH("@",AD28,1),LEN(AD28)-SEARCH("@",AD28,1)+1),[2]Sheet1!$D:$F,3,FALSE) -> M0128 | AC28: Head of Investor Relations | AD28: karen.xu@wprei.com | AE28: 8615821564358 | AF28: China | AG28: CNY | AI28: 1 | AL28: 1074 | AM28: 1074 | AN28: 1074 | AO28: 1074 | AP28: 1074 | AV28: 1074 | BC28: 0 | BJ28: 0 | BQ28: 0 | BX28: 0 | CE28: 0 | CF28: 1074 | CG28: 0 | CH28: 0 | CI28: 0 | CJ28: 0 | CK28: 0 | CL28: 1074 | CM28: 1 | CS28: 1 | CZ28: 0 | DG28: 0 | DN28: 0 | DU28: 0 | EB28: 0 | EC28: 1 | ED28: 0 | EE28: 0 | EF28: 0 | EG28: 0 | EH28: 0 | EI28: 1 | EJ28: YES | EK28: NO | EL28: NO | EM28: NO | EN28: NO | EO28: NO | EP28: NO | EQ28: NO | ER28: NO | ES28: NO | ET28: NO | EU28: NO | EV28: NO | EW28: NO | EX28: NO | EY28: NO | EZ28: NO | FA28: NO | FB28: NO | FC28: NO | FD28: NO | FE28: NO | FF28: NO | FG28: NO | FH28: NO | FI28: NO | FJ28: NO | FK28: NO | FL28: NO | FM28: NO | FN28: NO | FO28: NO | FP28: NO | FQ28: NO | FR28: NO | FS28: NO | FT28: 1074 | FZ28: 1074 | GG28: 0 | GN28: 0 | GU28: 0 | HB28: 0 | HI28: 0 | HP28: 0 | HX28: 0 | HY28: 1074 | HZ28: 0 | IA28: 0 | IB28: 0 | IC28: 0 | ID28: 0 | IE28: 1074 | IL28: 0 | IM28: 1074 | IS28: 1074 | IZ28: 0 | JG28: 0 | JN28: 0 | JO28: 1074 | JP28: 0 | JQ28: 0 | JR28: 0 | JS28: 0 | JT28: 0 | JU28: 1074 | JX28: 100 | KA28: 1 | KB28: 3 | KC28: 1 | KD28: START Asia Pacific: | OG28: START Europe: | SJ28: START North America: | WM28: START Global: | AAP28: START SOUTH America: | AES28: START Africa:
A29: C9DLZ342V | B29: INREV | C29: Azora Capital S.L. | P29: TRUE | Q29: FALSE | R29: FALSE | S29: FALSE | T29: FALSE | U29: FALSE | V29: 571 | W29: 43510.706 | X29: 80.28.105.241 | Y29: 2019 | Z29: Isabel Troya | AA29: Azora Capital | AB29: =VLOOKUP(MID(AD29,SEARCH("@",AD29,1),LEN(AD29)-SEARCH("@",AD29,1)+1),[2]Sheet1!$D:$F,3,FALSE) -> M03115 | AC29: Head of IR & Communication | AD29: isabeltroya@azora.es | AE29: 34917817302 | AF29: Spain | AG29: EUR | AI29: 1 | AL29: 766 | AM29: 766 | AN29: 716 | AO29: 716 | AV29: 0 | AZ29: 766 | BC29: 766 | BJ29: 0 | BQ29: 0 | BX29: 0 | CE29: 0 | CG29: 0 | CH29: 0 | CI29: 766 | CJ29: 0 | CK29: 0 | CL29: 766 | CS29: 0 | CW29: 1 | CZ29: 1 | DG29: 0 | DN29: 0 | DU29: 0 | EB29: 0 | EC29: 0 | ED29: 0 | EE29: 0 | EF29: 1 | EG29: 0 | EH29: 0 | EI29: 1 | EJ29: NO | EK29: NO | EL29: NO | EM29: NO | EN29: NO | EO29: NO | EP29: NO | EQ29: NO | ER29: NO | ES29: YES | ET29: NO | EU29: NO | EV29: NO | EW29: NO | EX29: NO | EY29: NO | EZ29: NO | FA29: NO | FB29: NO | FC29: NO | FD29: NO | FE29: NO | FF29: NO | FG29: NO | FH29: NO | FI29: NO | FJ29: NO | FK29: NO | FL29: NO | FM29: NO | FN29: NO | FO29: NO | FP29: NO | FQ29: NO | FR29: NO | FS29: NO | FZ29: 0 | GD29: 169 | GG29: 169 | GN29: 0 | GU29: 0 | HB29: 0 | HI29: 0 | HP29: 0 | HQ29: Real Estate institutional investor | HU29: 597 | HX29: 597 | HY29: 0 | HZ29: 0 | IA29: 0 | IB29: 766 | IC29: 0 | ID29: 0 | IE29: 766 | IL29: 0 | IP29: 550 | IS29: 550 | IW29: 216 | IZ29: 216 | JG29: 0 | JN29: 0 | JO29: 0 | JP29: 0 | JQ29: 0 | JR29: 766 | JS29: 0 | JT29: 0 | JU29: 766 | JV29: 100 | KA29: 1 | KB29: 3 | KC29: 2 | KD29: START Asia Pacific: | OG29: START Europe: | SJ29: START North America: | WM29: START Global: | AAP29: START SOUTH America: | AES29: START Africa:
A30: C9DNL392U | B30: INREV | C30: Elysian Residences | P30: FALSE | Q30: FALSE | R30: FALSE | S30: FALSE | T30: FALSE | U30: FALSE | V30: 679 | W30: 43523.594 | X30: 188.214.9.65 | Y30: 2019 | Z30: Jonas Frantz | AA30: Elysian Residences | AB30: =VLOOKUP(MID(AD30,SEARCH("@",AD30,1),LEN(AD30)-SEARCH("@",AD30,1)+1),[2]Sheet1!$D:$F,3,FALSE) -> M03091 | AC30: Partner | AD30: frantz@elysianresidences.com | AE30: +44 207 015 2246 | AF30: United Kingdom | AG30: GBP | AI30: 2 | AJ30: 6 | AK30: First Time Fund | AV30: 0 | BC30: 0 | BJ30: 0 | BQ30: 0 | BX30: 0 | CE30: 0 | CF30: 0 | CG30: 0 | CH30: 0 | CI30: 0 | CJ30: 0 | CK30: 0 | CL30: 0 | CS30: 0 | CZ30: 0 | DG30: 0 | DN30: 0 | DU30: 0 | EB30: 0 | EC30: 0 | ED30: 0 | EE30: 0 | EF30: 0 | EG30: 0 | EH30: 0 | EI30: 0 | EJ30: NO | EK30: NO | EL30: NO | EM30: NO | EN30: NO | EO30: NO | EP30: NO | EQ30: NO | ER30: NO | ES30: NO | ET30: NO | EU30: NO | EV30: NO | EW30: NO | EX30: NO | EY30: NO | EZ30: NO | FA30: NO | FB30: NO | FC30: NO | FD30: NO | FE30: NO | FF30: NO | FG30: NO | FH30: NO | FI30: NO | FJ30: NO | FK30: NO | FL30: NO | FM30: NO | FN30: NO | FO30: NO | FP30: NO | FQ30: NO | FR30: NO | FS30: NO | FZ30: 0 | GG30: 0 | GN30: 0 | GU30: 0 | HB30: 0 | HI30: 0 | HP30: 0 | HX30: 0 | HY30: 0 | HZ30: 0 | IA30: 0 | IB30: 0 | IC30: 0 | ID30: 0 | IE30: 0 | IL30: 0 | IS30: 0 | IZ30: 0 | JG30: 0 | JN30: 0 | JO30: 0 | JP30: 0 | JQ30: 0 | JR30: 0 | JS30: 0 | JT30: 0 | JU30: 0 | KA30: 1 | KB30: 2 | KC30: 2 | KD30: START Asia Pacific: | OG30: START Europe: | SJ30: START North America: | WM30: START Global: | AAP30: START SOUTH America: | AES30: START Africa:
A31: C9DRK656R | B31: NCREIF | C31: Intercontinental Real Estate Corp. | P31: FALSE | Q31: FALSE | R31: TRUE | S31: FALSE | T31: FALSE | U31: FALSE | V31: 722 | W31: 43516.324 | X31: 65.215.112.242 | Y31: 2019 | Z31: Brandon Millen | AA31: Intercontinental Real Estate Corp | AB31: =VLOOKUP(MID(AD31,SEARCH("@",AD31,1),LEN(AD31)-SEARCH("@",AD31,1)+1),[2]Sheet1!$D:$F,3,FALSE) -> NC007 | AC31: Associate Director, Performance | AD31: brandonm@intercontinental.net | AE31: 6177790490 | AF31: United States | AG31: USD | AI31: 1 | AL31: 568.91637 | AM31: 0 | AN31: 567.91637 | AO31: 0 | AV31: 0 | BC31: 0 | BD31: 568.91637 | BJ31: 568.92 | BQ31: 0 | BX31: 0 | CE31: 0 | CF31: 568.92 | CG31: 0 | CH31: 0 | CI31: 0 | CJ31: 0 | CK31: 0 | CL31: 568.92 | CS31: 0 | CZ31: 0 | DA31: 1 | DG31: 1 | DN31: 0 | DU31: 0 | EB31: 0 | EC31: 1 | ED31: 0 | EE31: 0 | EF31: 0 | EG31: 0 | EH31: 0 | EI31: 1 | EJ31: NO | EK31: NO | EL31: NO | EM31: NO | EN31: NO | EO31: NO | EP31: NO | EQ31: NO | ER31: NO | ES31: NO | ET31: NO | EU31: NO | EV31: YES | EW31: NO | EX31: NO | EY31: NO | EZ31: NO | FA31: NO | FB31: NO | FC31: NO | FD31: NO | FE31: NO | FF31: NO | FG31: NO | FH31: NO | FI31: NO | FJ31: NO | FK31: NO | FL31: NO | FM31: NO | FN31: NO | FO31: NO | FP31: NO | FQ31: NO | FR31: NO | FS31: NO | FT31: 537.323 | FZ31: 537.32 | GG31: 0 | GN31: 0 | GU31: 0 | GV31: 11.65056 | HB31: 11.65 | HI31: 0 | HJ31: 1.304957 | HP31: 1.3 | HQ31: Corporate | HR31: 18.637845 | HX31: 18.64 | HY31: 568.92 | HZ31: 0 | IA31: 0 | IB31: 0 | IC31: 0 | ID31: 0 | IE31: 568.92 | IL31: 0 | IS31: 0 | IT31: 568.91637 | IZ31: 568.92 | JG31: 0 | JN31: 0 | JO31: 568.92 | JP31: 0 | JQ31: 0 | JR31: 0 | JS31: 0 | JT31: 0 | JU31: 568.92 | JX31: 100 | KA31: 3 | KB31: 3 | KC31: 1 | KD31: START Asia Pacific: | OG31: START Europe: | SJ31: START North America: | WM31: START Global: | AAP31: START SOUTH America: | AES31: START Africa:
A32: C9DTL363X | B32: INREV | C32: Catalyst Capital LLP | P32: TRUE | Q32: FALSE | R32: FALSE | S32: FALSE | T32: FALSE | U32: FALSE | V32: 766 | W32: 43516.419 | X32: 83.206.159.77 | Y32: 2019 | Z32: Fabrice de Clermont-Tonnerre | AA32: Catalyst Capital LLP | AB32: =VLOOKUP(MID(AD32,SEARCH("@",AD32,1),LEN(AD32)-SEARCH("@",AD32,1)+1),[2]Sheet1!$D:$F,3,FALSE) -> M310 | AC32: Partner | AD32: fdect@catalystcapital.com | AF32: United Kingdom | AG32: EUR | AI32: 1 | AL32: 350 | AM32: 350 | AN32: 180 | AO32: 180 | AV32: 0 | AW32: 350 | BC32: 350 | BJ32: 0 | BQ32: 0 | BX32: 0 | CE32: 0 | CF32: 350 | CG32: 0 | CH32: 0 | CI32: 0 | CJ32: 0 | CK32: 0 | CL32: 350 | CS32: 0 | CT32: 2 | CZ32: 2 | DG32: 0 | DN32: 0 | DU32: 0 | EB32: 0 | EC32: 2 | ED32: 0 | EE32: 0 | EF32: 0 | EG32: 0 | EH32: 0 | EI32: 2 | EJ32: NO | EK32: NO | EL32: NO | EM32: NO | EN32: NO | EO32: NO | EP32: YES | EQ32: NO | ER32: NO | ES32: NO | ET32: NO | EU32: NO | EV32: NO | EW32: NO | EX32: NO | EY32: NO | EZ32: NO | FA32: NO | FB32: NO | FC32: NO | FD32: NO | FE32: NO | FF32: NO | FG32: NO | FH32: NO | FI32: NO | FJ32: NO | FK32: NO | FL32: NO | FM32: NO | FN32: NO | FO32: NO | FP32: NO | FQ32: NO | FR32: NO | FS32: NO | FT32: 300 | FZ32: 300 | GG32: 0 | GN32: 0 | GU32: 0 | HB32: 0 | HI32: 0 | HJ32: 50 | HP32: 50 | HX32: 0 | HY32: 350 | HZ32: 0 | IA32: 0 | IB32: 0 | IC32: 0 | ID32: 0 | IE32: 350 | IF32: 50 | IL32: 50 | IS32: 0 | IZ32: 0 | JG32: 0 | JH32: 300 | JN32: 300 | JO32: 350 | JP32: 0 | JQ32: 0 | JR32: 0 | JS32: 0 | JT32: 0 | JU32: 350 | JV32: 85 | JX32: 15 | KA32: 1 | KB32: 3 | KC32: 1 | KD32: START Asia Pacific: | OG32: START Europe: | SJ32: START North America: | WM32: START Global: | AAP32: START SOUTH America: | AES32: START Africa:
A33: C9DTT329Y | B33: INREV | C33: Aquila Capital | P33: TRUE | Q33: FALSE | R33: FALSE | S33: FALSE | T33: FALSE | U33: FALSE | V33: 704 | W33: 43504.591 | X33: 217.110.136.82 | Y33: 2019 | Z33: Michael Husung | AA33: Aquila Capital | AB33: =VLOOKUP(MID(AD33,SEARCH("@",AD33,1),LEN(AD33)-SEARCH("@",AD33,1)+1),[2]Sheet1!$D:$F,3,FALSE) -> M2842 | AC33: Head Sales Real Estate | AD33: michaell.husung@aquila-capital.com | AE33: +49 172 89 82 498 | AF33: Germany | AG33: EUR | AI33: 1 | AL33: 245 | AM33: 245 | AN33: 245 | AO33: 245 | AV33: 0 | AW33: 5 | AY33: 240 | BC33: 245 | BJ33: 0 | BQ33: 0 | BX33: 0 | CE33: 0 | CF33: 5 | CG33: 0 | CH33: 240 | CI33: 0 | CJ33: 0 | CK33: 0 | CL33: 245 | CS33: 0 | CT33: 1 | CV33: 1 | CZ33: 2 | DG33: 0 | DN33: 0 | DU33: 0 | EB33: 0 | EC33: 1 | ED33: 0 | EE33: 1 | EF33: 0 | EG33: 0 | EH33: 0 | EI33: 2 | EJ33: NO | EK33: NO | EL33: NO | EM33: NO | EN33: NO | EO33: NO | EP33: YES | EQ33: NO | ER33: YES | ES33: NO | ET33: NO | EU33: NO | EV33: NO | EW33: NO | EX33: NO | EY33: NO | EZ33: NO | FA33: NO | FB33: NO | FC33: NO | FD33: NO | FE33: NO | FF33: NO | FG33: NO | FH33: NO | FI33: NO | FJ33: NO | FK33: NO | FL33: NO | FM33: NO | FN33: NO | FO33: NO | FP33: NO | FQ33: NO | FR33: NO | FS33: NO | FV33: 240 | FZ33: 240 | GG33: 0 | GN33: 0 | GU33: 0 | HB33: 0 | HI33: 0 | HJ33: 5 | HP33: 5 | HX33: 0 | HY33: 5 | HZ33: 0 | IA33: 240 | IB33: 0 | IC33: 0 | ID33: 0 | IE33: 245 | IL33: 0 | IM33: 5 | IO33: 240 | IS33: 245 | IZ33: 0 | JG33: 0 | JN33: 0 | JO33: 5 | JP33: 0 | JQ33: 240 | JR33: 0 | JS33: 0 | JT33: 0 | JU33: 245 | JV33: 0 | JW33: 90 | JX33: 10 | KA33: 1 | KB33: 3 | KC33: 1 | KD33: START Asia Pacific: | OG33: START Europe: | SJ33: START North America: | WM33: START Global: | AAP33: START SOUTH America: | AES33: START Africa:
A34: C9DUU704H | B34: ANREV | C34: Lendlease Investment Management | P34: TRUE | Q34: TRUE | R34: TRUE | S34: FALSE | T34: FALSE | U34: FALSE | V34: 698 | W34: 43508.227 | X34: 108.171.134.165 | Y34: 2019 | Z34: Peter Wylie | AA34: Lendlease | AB34: =VLOOKUP(MID(AD34,SEARCH("@",AD34,1),LEN(AD34)-SEARCH("@",AD34,1)+1),[2]Sheet1!$D:$F,3,FALSE) -> M243 | AC34: Group Director, Investment & Capital Markets | AD34: peter.wylie@lendlease.com | AE34: 61477309659 | AF34: Australia | AG34: AUD | AI34: 1 | AL34: 2389 | AM34: 2389 | AN34: 2075 | AO34: 2075 | AP34: 513 | AQ34: 747 | AS34: 37.7 | AV34: 1297.7 | AZ34: 618 | BC34: 618 | BG34: 474 | BJ34: 474 | BQ34: 0 | BX34: 0 | CE34: 0 | CF34: 513 | CG34: 747 | CH34: 0 | CI34: 1129.7 | CJ34: 0 | CK34: 0 | CL34: 2389.7 | CM34: 2 | CN34: 5 | CP34: 1 | CS34: 8 | CW34: 1 | CZ34: 1 | DD34: 2 | DG34: 2 | DN34: 0 | DU34: 0 | EB34: 0 | EC34: 2 | ED34: 5 | EE34: 0 | EF34: 4 | EG34: 0 | EH34: 0 | EI34: 11 | EJ34: YES | EK34: YES | EL34: NO | EM34: YES | EN34: NO | EO34: NO | EP34: NO | EQ34: NO | ER34: NO | ES34: YES | ET34: NO | EU34: NO | EV34: NO | EW34: NO | EX34: NO | EY34: YES | EZ34: NO | FA34: NO | FB34: NO | FC34: NO | FD34: NO | FE34: NO | FF34: NO | FG34: NO | FH34: NO | FI34: NO | FJ34: NO | FK34: NO | FL34: NO | FM34: NO | FN34: NO | FO34: NO | FP34: NO | FQ34: NO | FR34: NO | FS34: NO | FT34: 203 | FU34: 332 | FW34: 832 | FZ34: 1367 | GG34: 0 | GH34: 210 | GI34: 415 | GK34: 37.7 | GN34: 662.7 | GO34: 100 | GU34: 100 | HB34: 0 | HI34: 0 | HP34: 0 | HQ34: Corporate partner | HU34: 260 | HX34: 260 | HY34: 513 | HZ34: 747 | IA34: 0 | IB34: 1129.7 | IC34: 0 | ID34: 0 | IE34: 2389.7 | IF34: 513 | IG34: 747 | II34: 511.7 | IL34: 1771.7 | IS34: 0 | IW34: 618 | IZ34: 618 | JG34: 0 | JN34: 0 | JO34: 513 | JP34: 747 | JQ34: 0 | JR34: 1129.7 | JS34: 0 | JT34: 0 | JU34: 2389.7 | JV34: 0 | JX34: 100 | KA34: 1 | KB34: 3 | KC34: 1 | KD34: START Asia Pacific: | OG34: START Europe: | SJ34: START North America: | WM34: START Global: | AAP34: START SOUTH America: | AES34: START Africa:
A35: C9DWH305A | B35: ANREV | C35: Baring Private Equity Asia Pte Ltd | P35: FALSE | Q35: TRUE | R35: FALSE | S35: FALSE | T35: FALSE | U35: FALSE | V35: 714 | W35: 43511.281 | X35: 101.78.178.130 | Y35: 2019 | Z35: Tiffany Wang | AA35: BPEA Real Estate | AB35: =VLOOKUP(MID(AD35,SEARCH("@",AD35,1),LEN(AD35)-SEARCH("@",AD35,1)+1),[2]Sheet1!$D:$F,3,FALSE) -> M0149 | AC35: Corporate Communication Officer | AD35: TiffanyWang@bpeasia.com | AE35: +852 2843 9362 | AF35: Hong Kong | AG35: USD | AI35: 1 | AM35: 1000 | AO35: 160 | AP35: 1000 | AV35: 1000 | BC35: 0 | BJ35: 0 | BQ35: 0 | BX35: 0 | CE35: 0 | CF35: 1000 | CG35: 0 | CH35: 0 | CI35: 0 | CJ35: 0 | CK35: 0 | CL35: 1000 | CM35: 1 | CS35: 1 | CZ35: 0 | DG35: 0 | DN35: 0 | DU35: 0 | EB35: 0 | EC35: 1 | ED35: 0 | EE35: 0 | EF35: 0 | EG35: 0 | EH35: 0 | EI35: 1 | EJ35: YES | EK35: NO | EL35: NO | EM35: NO | EN35: NO | EO35: NO | EP35: NO | EQ35: NO | ER35: NO | ES35: NO | ET35: NO | EU35: NO | EV35: NO | EW35: NO | EX35: NO | EY35: NO | EZ35: NO | FA35: NO | FB35: NO | FC35: NO | FD35: NO | FE35: NO | FF35: NO | FG35: NO | FH35: NO | FI35: NO | FJ35: NO | FK35: NO | FL35: NO | FM35: NO | FN35: NO | FO35: NO | FP35: NO | FQ35: NO | FR35: NO | FS35: NO | FZ35: 0 | GG35: 0 | GN35: 0 | GU35: 0 | HB35: 0 | HI35: 0 | HP35: 0 | HX35: 0 | HY35: 0 | HZ35: 0 | IA35: 0 | IB35: 0 | IC35: 0 | ID35: 0 | IE35: 0 | IL35: 0 | IS35: 0 | IZ35: 0 | JG35: 0 | JN35: 0 | JO35: 0 | JP35: 0 | JQ35: 0 | JR35: 0 | JS35: 0 | JT35: 0 | JU35: 0 | KA35: 1 | KB35: 2 | KC35: 1 | KD35: START Asia Pacific: | OG35: START Europe: | SJ35: START North America: | WM35: START Global: | AAP35: START SOUTH America: | AES35: START Africa:
A36: C9DWW298G | B36: INREV | C36: PATRIZIA Immobilien AG | P36: TRUE | Q36: FALSE | R36: FALSE | S36: FALSE | T36: FALSE | U36: FALSE | V36: 782 | W36: 43528.576 | X36: 212.114.207.108 | Y36: 2019 | Z36: Sebastian | AA36: Gey | AB36: =VLOOKUP(MID(AD36,SEARCH("@",AD36,1),LEN(AD36)-SEARCH("@",AD36,1)+1),[2]Sheet1!$D:$F,3,FALSE) -> M180 | AC36: Head of Product Development | AD36: sebastian.gey@patrizia.ag | AE36: +49 171 1904152 | AF36: Germany | AG36: EUR | AI36: 1 | AL36: 2283 | AM36: 2283 | AN36: 1619.2 | AO36: 1619.2 | AV36: 0 | AW36: 777 | AX36: 1463 | AZ36: 43 | BC36: 2283 | BJ36: 0 | BQ36: 0 | BX36: 0 | CE36: 0 | CF36: 777 | CG36: 1463 | CH36: 0 | CI36: 43 | CJ36: 0 | CK36: 0 | CL36: 2283 | CS36: 0 | CT36: 11 | CU36: 15 | CW36: 2 | CZ36: 28 | DG36: 0 | DN36: 0 | DU36: 0 | EB36: 0 | EC36: 11 | ED36: 15 | EE36: 0 | EF36: 2 | EG36: 0 | EH36: 0 | EI36: 28 | EJ36: NO | EK36: NO | EL36: NO | EM36: NO | EN36: NO | EO36: NO | EP36: YES | EQ36: YES | ER36: NO | ES36: YES | ET36: NO | EU36: NO | EV36: NO | EW36: NO | EX36: NO | EY36: NO | EZ36: NO | FA36: NO | FB36: NO | FC36: NO | FD36: NO | FE36: NO | FF36: NO | FG36: NO | FH36: NO | FI36: NO | FJ36: NO | FK36: NO | FL36: NO | FM36: NO | FN36: NO | FO36: NO | FP36: NO | FQ36: NO | FR36: NO | FS36: NO | FT36: 168 | FU36: 346 | FZ36: 514 | GA36: 45 | GB36: 530 | GD36: 43 | GG36: 618 | GH36: 75 | GI36: 200 | GN36: 275 | GU36: 0 | GV36: 1 | GW36: 57 | HB36: 58 | HI36: 0 | HP36: 0 | HQ36: Saving banks, banks etc. | HR36: 488 | HS36: 330 | HX36: 818 | HY36: 777 | HZ36: 1463 | IA36: 0 | IB36: 43 | IC36: 0 | ID36: 0 | IE36: 2283 | IF36: 75 | IG36: 890 | IL36: 965 | IM36: 700 | IN36: 573 | IP36: 43 | IS36: 1316 | IZ36: 0 | JA36: 2 | JG36: 2 | JN36: 0 | JO36: 777 | JP36: 1463 | JQ36: 0 | JR36: 43 | JS36: 0 | JT36: 0 | JU36: 2283 | JX36: 100 | KA36: 1 | KB36: 3 | KC36: 1 | KD36: START Asia Pacific: | OG36: START Europe: | SJ36: START North America: | WM36: START Global: | AAP36: START SOUTH America: | AES36: START Africa:
A37: C9DYF617U | B37: NCREIF | C37: Buzz Oates | P37: FALSE | Q37: FALSE | R37: FALSE | S37: FALSE | T37: FALSE | U37: FALSE | V37: 598 | W37: 43511.941 | X37: 209.222.83.71 | Y37: 2019 | Z37: Larry Allbaugh | AA37: Buzz Oates | AB37: =VLOOKUP(MID(AD37,SEARCH("@",AD37,1),LEN(AD37)-SEARCH("@",AD37,1)+1),[2]Sheet1!$D:$F,3,FALSE) -> NC016 | AC37: CEO | AD37: larryallbaugh@buzzoates.com | AE37: 9163793800 | AF37: United States | AG37: USD | AI37: 2 | AJ37: 6 | AK37: sufficient capital raised previously | AV37: 0 | BC37: 0 | BJ37: 0 | BQ37: 0 | BX37: 0 | CE37: 0 | CF37: 0 | CG37: 0 | CH37: 0 | CI37: 0 | CJ37: 0 | CK37: 0 | CL37: 0 | CS37: 0 | CZ37: 0 | DG37: 0 | DN37: 0 | DU37: 0 | EB37: 0 | EC37: 0 | ED37: 0 | EE37: 0 | EF37: 0 | EG37: 0 | EH37: 0 | EI37: 0 | EJ37: NO | EK37: NO | EL37: NO | EM37: NO | EN37: NO | EO37: NO | EP37: NO | EQ37: NO | ER37: NO | ES37: NO | ET37: NO | EU37: NO | EV37: NO | EW37: NO | EX37: NO | EY37: NO | EZ37: NO | FA37: NO | FB37: NO | FC37: NO | FD37: NO | FE37: NO | FF37: NO | FG37: NO | FH37: NO | FI37: NO | FJ37: NO | FK37: NO | FL37: NO | FM37: NO | FN37: NO | FO37: NO | FP37: NO | FQ37: NO | FR37: NO | FS37: NO | FZ37: 0 | GG37: 0 | GN37: 0 | GU37: 0 | HB37: 0 | HI37: 0 | HP37: 0 | HX37: 0 | HY37: 0 | HZ37: 0 | IA37: 0 | IB37: 0 | IC37: 0 | ID37: 0 | IE37: 0 | IL37: 0 | IS37: 0 | IZ37: 0 | JG37: 0 | JN37: 0 | JO37: 0 | JP37: 0 | JQ37: 0 | JR37: 0 | JS37: 0 | JT37: 0 | JU37: 0 | KA37: 1 | KB37: 3 | KC37: 1 | KD37: START Asia Pacific: | OG37: START Europe: | SJ37: START North America: | WM37: START Global: | AAP37: START SOUTH America: | AES37: START Africa:
A38: C9ECX442Q | B38: INREV | C38: Intermediate Capital Group (ICG) | P38: TRUE | Q38: FALSE | R38: FALSE | S38: FALSE | T38: FALSE | U38: FALSE | V38: 566 | W38: 43483.444 | X38: 154.47.76.94 | Y38: 2019 | Z38: Cilla Yngvesson | AA38: ICG-Longbow | AB38: =VLOOKUP(MID(AD38,SEARCH("@",AD38,1),LEN(AD38)-SEARCH("@",AD38,1)+1),[2]Sheet1!$D:$F,3,FALSE) -> M674 | AC38: Manager | AD38: cilla.yngvesson@icgam.com | AE38: 2032017772 | AF38: United Kingdom | AG38: GBP | AI38: 1 | AL38: 725.5 | AM38: 725.5 | AN38: 336 | AO38: 336 | AV38: 0 | BB38: 725.5 | BC38: 725.5 | BJ38: 0 | BQ38: 0 | BX38: 0 | CE38: 0 | CF38: 0 | CG38: 0 | CH38: 0 | CI38: 0 | CJ38: 0 | CK38: 725.5 | CL38: 725.5 | CS38: 0 | CY38: 2 | CZ38: 2 | DG38: 0 | DN38: 0 | DU38: 0 | EB38: 0 | EC38: 0 | ED38: 0 | EE38: 0 | EF38: 0 | EG38: 0 | EH38: 2 | EI38: 2 | EJ38: NO | EK38: NO | EL38: NO | EM38: NO | EN38: NO | EO38: NO | EP38: NO | EQ38: NO | ER38: NO | ES38: NO | ET38: NO | EU38: YES | EV38: NO | EW38: NO | EX38: NO | EY38: NO | EZ38: NO | FA38: NO | FB38: NO | FC38: NO | FD38: NO | FE38: NO | FF38: NO | FG38: NO | FH38: NO | FI38: NO | FJ38: NO | FK38: NO | FL38: NO | FM38: NO | FN38: NO | FO38: NO | FP38: NO | FQ38: NO | FR38: NO | FS38: NO | FY38: 396.5 | FZ38: 396.5 | GF38: 143.5 | GG38: 143.5 | GM38: 100 | GN38: 100 | GU38: 0 | HB38: 0 | HH38: 78 | HI38: 78 | HP38: 0 | HW38: 7.5 | HX38: 7.5 | HY38: 0 | HZ38: 0 | IA38: 0 | IB38: 0 | IC38: 0 | ID38: 725.5 | IE38: 725.5 | IK38: 7.5 | IL38: 7.5 | IR38: 718 | IS38: 718 | IZ38: 0 | JG38: 0 | JN38: 0 | JO38: 0 | JP38: 0 | JQ38: 0 | JR38: 0 | JS38: 0 | JT38: 725.5 | JU38: 725.5 | JX38: 100 | KA38: 3 | KB38: 3 | KC38: 1 | KD38: START Asia Pacific: | OG38: START Europe: | SJ38: START North America: | WM38: START Global: | AAP38: START SOUTH America: | AES38: START Africa:
A39: C9EGN815A | B39: ANREV | C39: Mitsui Fudosan Investment Advisors, Inc. | D39: asia | E39: 43524.233 | H39: northamerica | I39: 43524.233 | P39: FALSE | Q39: TRUE | R39: TRUE | S39: FALSE | T39: FALSE | U39: FALSE | V39: 818 | W39: 43524.231 | X39: 211.19.34.54 | Y39: 2019 | Z39: NAKAO IIJIMA | AA39: Mitsui Fudosan Investment Advisors Inc. | AB39: =VLOOKUP(MID(AD39,SEARCH("@",AD39,1),LEN(AD39)-SEARCH("@",AD39,1)+1),[2]Sheet1!$D:$F,3,FALSE) -> M0177 | AC39: General Manager Research Dept. | AD39: n-iijima@mfia.co.jp | AE39: =81-3-3246-3332 -> -6500 | AF39: Japan | AG39: JPY | AI39: 1 | AL39: 23302 | AM39: 23302 | AN39: 23302 | AO39: 23302 | AP39: 0 | AQ39: 14400 | AR39: 0 | AS39: 0 | AT39: 0 | AU39: 0 | AV39: 14400 | AW39: 0 | AX39: 0 | AY39: 0 | AZ39: 0 | BA39: 0 | BB39: 0 | BC39: 0 | BD39: 0 | BE39: 0 | BF39: 0 | BG39: 8902 | BH39: 0 | BI39: 0 | BJ39: 8902 | BK39: 0 | BL39: 0 | BM39: 0 | BN39: 0 | BO39: 0 | BP39: 0 | BQ39: 0 | BR39: 0 | BS39: 0 | BT39: 0 | BU39: 0 | BV39: 0 | BW39: 0 | BX39: 0 | BY39: 0 | BZ39: 0 | CA39: 0 | CB39: 0 | CC39: 0 | CD39: 0 | CE39: 0 | CF39: 0 | CG39: 14400 | CH39: 0 | CI39: 8902 | CJ39: 0 | CK39: 0 | CL39: 23302 | CN39: 1 | CS39: 1 | CZ39: 0 | DD39: 1 | DG39: 1 | DN39: 0 | DU39: 0 | EB39: 0 | EC39: 0 | ED39: 1 | EE39: 0 | EF39: 1 | EG39: 0 | EH39: 0 | EI39: 2 | EJ39: NO | EK39: YES | EL39: NO | EM39: NO | EN39: NO | EO39: NO | EP39: NO | EQ39: NO | ER39: NO | ES39: NO | ET39: NO | EU39: NO | EV39: NO | EW39: NO | EX39: NO | EY39: YES | EZ39: NO | FA39: NO | FB39: NO | FC39: NO | FD39: NO | FE39: NO | FF39: NO | FG39: NO | FH39: NO | FI39: NO | FJ39: NO | FK39: NO | FL39: NO | FM39: NO | FN39: NO | FO39: NO | FP39: NO | FQ39: NO | FR39: NO | FS39: NO | FZ39: 0 | GG39: 0 | GN39: 0 | GU39: 0 | HB39: 0 | HI39: 0 | HP39: 0 | HQ39: Banks & other types of companies | HS39: 14400 | HU39: 8902 | HX39: 23302 | HY39: 0 | HZ39: 14400 | IA39: 0 | IB39: 8902 | IC39: 0 | ID39: 0 | IE39: 23302 | IG39: 14400 | II39: 8902 | IL39: 23302 | IS39: 0 | IZ39: 0 | JG39: 0 | JN39: 0 | JO39: 0 | JP39: 14400 | JQ39: 0 | JR39: 8902 | JS39: 0 | JT39: 0 | JU39: 23302 | JX39: 100 | KA39: 3 | KB39: 3 | KC39: 2 | KD39: START Asia Pacific: | KK39: 0 | KR39: 0 | KY39: 0 | LF39: 0 | LM39: 0 | LT39: 0 | MA39: 0 | MB39: other type of company | MD39: 14400 | MI39: 14400 | MJ39: 0 | MK39: 14400 | ML39: 0 | MM39: 0 | MN39: 0 | MO39: 0 | MP39: 14400 | MW39: 0 | MY39: 14400 | ND39: 14400 | NK39: 0 | NR39: 0 | NY39: 0 | NZ39: 0 | OA39: 14400 | OB39: 0 | OC39: 0 | OD39: 0 | OE39: 0 | OF39: 14400 | OG39: START Europe: | SJ39: START North America: | SQ39: 0 | SX39: 0 | TE39: 0 | TL39: 0 | TS39: 0 | TZ39: 0 | UG39: 0 | UH39: Banks & other types of companies | UL39: 8902 | UO39: 8902 | UP39: 0 | UQ39: 0 | UR39: 0 | US39: 8902 | UT39: 0 | UU39: 0 | UV39: 8902 | VC39: 0 | VG39: 8902 | VJ39: 8902 | VQ39: 0 | VX39: 0 | WE39: 0 | WF39: 0 | WG39: 0 | WH39: 0 | WI39: 8902 | WJ39: 0 | WK39: 0 | WL39: 8902 | WM39: START Global: | AAP39: START SOUTH America: | AES39: START Africa:
A40: C9EML411W | B40: INREV | C40: Franklin Templeton Real Asset Advisors | F40: europe | G40: 43517.092 | J40: global | K40: 43517.092 | P40: TRUE | Q40: FALSE | R40: FALSE | S40: TRUE | T40: FALSE | U40: FALSE | V40: 751 | W40: 43517.093 | X40: 119.17.137.127 | Y40: 2019 | Z40: Greg Wilkinson | AA40: Franklin Templeton Investments | AB40: =VLOOKUP(MID(AD40,SEARCH("@",AD40,1),LEN(AD40)-SEARCH("@",AD40,1)+1),[2]Sheet1!$D:$F,3,FALSE) -> M106 | AC40: Director | AD40: greg.wilkinson@franklintempleton.com | AE40: 61396529415 | AF40: United States | AG40: USD | AI40: 1 | AL40: 400 | AM40: 400 | AN40: 212 | AO40: 212 | AV40: 0 | AW40: 180 | BC40: 180 | BJ40: 0 | BK40: 67 | BO40: 153 | BQ40: 220 | BX40: 0 | CE40: 0 | CF40: 247 | CG40: 0 | CH40: 0 | CI40: 0 | CJ40: 153 | CK40: 0 | CL40: 400 | CS40: 0 | CT40: 1 | CZ40: 1 | DG40: 0 | DH40: 1 | DL40: 1 | DN40: 2 | DU40: 0 | EB40: 0 | EC40: 2 | ED40: 0 | EE40: 0 | EF40: 0 | EG40: 1 | EH40: 0 | EI40: 3 | EJ40: NO | EK40: NO | EL40: NO | EM40: NO | EN40: NO | EO40: NO | EP40: YES | EQ40: NO | ER40: NO | ES40: NO | ET40: NO | EU40: NO | EV40: NO | EW40: NO | EX40: NO | EY40: NO | EZ40: NO | FA40: NO | FB40: YES | FC40: NO | FD40: NO | FE40: NO | FF40: YES | FG40: NO | FH40: NO | FI40: NO | FJ40: NO | FK40: NO | FL40: NO | FM40: NO | FN40: NO | FO40: NO | FP40: NO | FQ40: NO | FR40: NO | FS40: NO | FT40: 216 | FX40: 102 | FZ40: 318 | GG40: 0 | GN40: 0 | GU40: 0 | HB40: 0 | HI40: 0 | HJ40: 31 | HN40: 51 | HP40: 82 | HX40: 0 | HY40: 247 | HZ40: 0 | IA40: 0 | IB40: 0 | IC40: 153 | ID40: 0 | IE40: 400 | IL40: 0 | IM40: 178 | IS40: 178 | IT40: 70 | IX40: 152 | IZ40: 222 | JG40: 0 | JN40: 0 | JO40: 248 | JP40: 0 | JQ40: 0 | JR40: 0 | JS40: 152 | JT40: 0 | JU40: 400 | JX40: 100 | KA40: 1 | KB40: 3 | KC40: 1 | KD40: START Asia Pacific: | OG40: START Europe: | OH40: 180 | ON40: 180 | OU40: 0 | PB40: 0 | PI40: 0 | PP40: 0 | PW40: 0 | QD40: 0 | QL40: 0 | QM40: 180 | QN40: 0 | QO40: 0 | QP40: 0 | QQ40: 0 | QR40: 0 | QS40: 180 | QT40: 167 | QZ40: 167 | RG40: 0 | RH40: 13 | RN40: 13 | RU40: 0 | SB40: 0 | SC40: 180 | SD40: 0 | SE40: 0 | SF40: 0 | SG40: 0 | SH40: 0 | SI40: 180 | SJ40: START North America: | WM40: START Global: | WN40: 137 | WT40: 137 | XA40: 0 | XH40: 0 | XO40: 0 | XV40: 0 | YC40: 0 | YD40: 83 | YJ40: 83 | YR40: 0 | YS40: 220 | YT40: 0 | YU40: 0 | YV40: 0 | YW40: 0 | YX40: 0 | YY40: 220 | ZF40: 0 | ZM40: 0 | ZN40: 220 | ZT40: 220 | AAA40: 0 | AAH40: 0 | AAI40: 220 | AAJ40: 0 | AAK40: 0 | AAL40: 0 | AAM40: 0 | AAN40: 0 | AAO40: 220 | AAP40: START SOUTH America: | AES40: START Africa:
A41: C9ENH304P | B41: INREV | C41: Aberdeen Asset Management (FOF) | P41: TRUE | Q41: FALSE | R41: FALSE | S41: TRUE | T41: FALSE | U41: FALSE | V41: 822 | W41: 43532.623 | X41: 80.254.154.43 | Y41: 2019 | Z41: Magdalena Svensson | AA41: Aberdeen Standard Investments | AB41: =VLOOKUP(MID(AD41,SEARCH("@",AD41,1),LEN(AD41)-SEARCH("@",AD41,1)+1),[2]Sheet1!$D:$F,3,FALSE) -> M675 | AC41: Operations Manager | AD41: magdalena.svensson@aberdeen-asset.com | AF41: United Kingdom | AG41: EUR | AI41: 1 | AL41: 1022.4762 | AM41: 1022.4762 | AN41: 17.102387 | AO41: 17.102387 | AV41: 0 | BA41: 135.36313 | BC41: 135.36313 | BJ41: 0 | BO41: 887.11308 | BQ41: 887.11308 | BX41: 0 | CE41: 0 | CF41: 0 | CG41: 0 | CH41: 0 | CI41: 0 | CJ41: 1022.4762 | CK41: 0 | CL41: 1022.4762 | CS41: 0 | CX41: 2 | CZ41: 2 | DG41: 0 | DL41: 1 | DN41: 1 | DU41: 0 | EB41: 0 | EC41: 0 | ED41: 0 | EE41: 0 | EF41: 0 | EG41: 3 | EH41: 0 | EI41: 3 | EJ41: NO | EK41: NO | EL41: NO | EM41: NO | EN41: NO | EO41: NO | EP41: NO | EQ41: NO | ER41: NO | ES41: NO | ET41: YES | EU41: NO | EV41: NO | EW41: NO | EX41: NO | EY41: NO | EZ41: NO | FA41: NO | FB41: NO | FC41: NO | FD41: NO | FE41: NO | FF41: YES | FG41: NO | FH41: NO | FI41: NO | FJ41: NO | FK41: NO | FL41: NO | FM41: NO | FN41: NO | FO41: NO | FP41: NO | FQ41: NO | FR41: NO | FS41: NO | FZ41: 0 | GG41: 0 | GN41: 0 | GU41: 0 | HB41: 0 | HG41: 1022.4762 | HI41: 1022.4762 | HP41: 0 | HX41: 0 | HY41: 0 | HZ41: 0 | IA41: 0 | IB41: 0 | IC41: 1022.4762 | ID41: 0 | IE41: 1022.4762 | IJ41: 887.11308 | IL41: 887.11308 | IQ41: 135.36313 | IS41: 135.36313 | IZ41: 0 | JG41: 0 | JN41: 0 | JO41: 0 | JP41: 0 | JQ41: 0 | JR41: 0 | JS41: 1022.4762 | JT41: 0 | JU41: 1022.4762 | JX41: 100 | KA41: 2 | KB41: 2 | KC41: 2 | KD41: START Asia Pacific: | OG41: START Europe: | SJ41: START North America: | WM41: START Global: | AAP41: START SOUTH America: | AES41: START Africa:
A42: C9EUE452P | B42: INREV | C42: IPUT plc | P42: TRUE | Q42: FALSE | R42: FALSE | S42: FALSE | T42: FALSE | U42: FALSE | V42: 569 | W42: 43475.543 | X42: 5.149.174.42 | Y42: 2019 | Z42: Patrick McGinley | AA42: IPUT plc | AB42: =VLOOKUP(MID(AD42,SEARCH("@",AD42,1),LEN(AD42)-SEARCH("@",AD42,1)+1),[2]Sheet1!$D:$F,3,FALSE) -> M628 | AC42: Head of Finance | AD42: pmcginley@iput.com | AF42: Ireland | AG42: EUR | AI42: 1 | AL42: 350 | AM42: 350 | AN42: 180 | AO42: 180 | AV42: 0 | AW42: 350 | BC42: 350 | BJ42: 0 | BQ42: 0 | BX42: 0 | CE42: 0 | CF42: 350 | CG42: 0 | CH42: 0 | CI42: 0 | CJ42: 0 | CK42: 0 | CL42: 350 | CS42: 0 | CT42: 1 | CZ42: 1 | DG42: 0 | DN42: 0 | DU42: 0 | EB42: 0 | EC42: 1 | ED42: 0 | EE42: 0 | EF42: 0 | EG42: 0 | EH42: 0 | EI42: 1 | EJ42: NO | EK42: NO | EL42: NO | EM42: NO | EN42: NO | EO42: NO | EP42: YES | EQ42: NO | ER42: NO | ES42: NO | ET42: NO | EU42: NO | EV42: NO | EW42: NO | EX42: NO | EY42: NO | EZ42: NO | FA42: NO | FB42: NO | FC42: NO | FD42: NO | FE42: NO | FF42: NO | FG42: NO | FH42: NO | FI42: NO | FJ42: NO | FK42: NO | FL42: NO | FM42: NO | FN42: NO | FO42: NO | FP42: NO | FQ42: NO | FR42: NO | FS42: NO | FT42: 50 | FZ42: 50 | GA42: 300 | GG42: 300 | GN42: 0 | GU42: 0 | HB42: 0 | HI42: 0 | HP42: 0 | HX42: 0 | HY42: 350 | HZ42: 0 | IA42: 0 | IB42: 0 | IC42: 0 | ID42: 0 | IE42: 350 | IF42: 30 | IL42: 30 | IM42: 320 | IS42: 320 | IZ42: 0 | JG42: 0 | JN42: 0 | JO42: 350 | JP42: 0 | JQ42: 0 | JR42: 0 | JS42: 0 | JT42: 0 | JU42: 350 | JX42: 100 | KA42: 2 | KB42: 3 | KC42: 1 | KD42: START Asia Pacific: | OG42: START Europe: | SJ42: START North America: | WM42: START Global: | AAP42: START SOUTH America: | AES42: START Africa:
A43: C9EXY387X | B43: INREV | C43: DRC Capital LLP | P43: TRUE | Q43: FALSE | R43: FALSE | S43: FALSE | T43: FALSE | U43: FALSE | V43: 737 | W43: 43514.417 | X43: 217.10.134.222 | Y43: 2019 | Z43: Steve Emsley | AA43: DRC Capital | AB43: =VLOOKUP(MID(AD43,SEARCH("@",AD43,1),LEN(AD43)-SEARCH("@",AD43,1)+1),[2]Sheet1!$D:$F,3,FALSE) -> M666 | AC43: CFO | AD43: se@drccap.com | AE43: 442070420617 | AF43: United Kingdom | AG43: GBP | AI43: 1 | AL43: 488 | AM43: 488 | AN43: 135 | AO43: 135 | AV43: 0 | BB43: 488 | BC43: 488 | BJ43: 0 | BQ43: 0 | BX43: 0 | CE43: 0 | CF43: 0 | CG43: 0 | CH43: 0 | CI43: 0 | CJ43: 0 | CK43: 488 | CL43: 488 | CS43: 0 | CY43: 1 | CZ43: 1 | DG43: 0 | DN43: 0 | DU43: 0 | EB43: 0 | EC43: 0 | ED43: 0 | EE43: 0 | EF43: 0 | EG43: 0 | EH43: 1 | EI43: 1 | EJ43: NO | EK43: NO | EL43: NO | EM43: NO | EN43: NO | EO43: NO | EP43: NO | EQ43: NO | ER43: NO | ES43: NO | ET43: NO | EU43: YES | EV43: NO | EW43: NO | EX43: NO | EY43: NO | EZ43: NO | FA43: NO | FB43: NO | FC43: NO | FD43: NO | FE43: NO | FF43: NO | FG43: NO | FH43: NO | FI43: NO | FJ43: NO | FK43: NO | FL43: NO | FM43: NO | FN43: NO | FO43: NO | FP43: NO | FQ43: NO | FR43: NO | FS43: NO | FY43: 488 | FZ43: 488 | GG43: 0 | GN43: 0 | GU43: 0 | HB43: 0 | HI43: 0 | HP43: 0 | HX43: 0 | HY43: 0 | HZ43: 0 | IA43: 0 | IB43: 0 | IC43: 0 | ID43: 488 | IE43: 488 | IL43: 0 | IR43: 488 | IS43: 488 | IZ43: 0 | JG43: 0 | JN43: 0 | JO43: 0 | JP43: 0 | JQ43: 0 | JR43: 0 | JS43: 0 | JT43: 488 | JU43: 488 | JX43: 100 | KA43: 1 | KB43: 3 | KC43: 1 | KD43: START Asia Pacific: | OG43: START Europe: | SJ43: START North America: | WM43: START Global: | AAP43: START SOUTH America: | AES43: START Africa:
A44: C9EYM602B | B44: NCREIF | C44: Ascentris | P44: FALSE | Q44: FALSE | R44: TRUE | S44: FALSE | T44: FALSE | U44: FALSE | V44: 596 | W44: 43516.104 | X44: 38.140.184.26 | Y44: 2019 | Z44: Katie Milleville | AA44: Ascentris | AB44: =VLOOKUP(MID(AD44,SEARCH("@",AD44,1),LEN(AD44)-SEARCH("@",AD44,1)+1),[2]Sheet1!$D:$F,3,FALSE) -> NC018 | AC44: Associate, Investor Relations | AD44: katie.milleville@ascentris.com | AE44: 3033176464 | AF44: United States | AG44: USD | AI44: 1 | AL44: 221.4 | AM44: 221.4 | AN44: 171.4 | AO44: 171.4 | AV44: 0 | BC44: 0 | BD44: 50 | BE44: 171.4 | BJ44: 221.4 | BQ44: 0 | BX44: 0 | CE44: 0 | CF44: 50 | CG44: 171.4 | CH44: 0 | CI44: 0 | CJ44: 0 | CK44: 0 | CL44: 221.4 | CS44: 0 | CZ44: 0 | DA44: 1 | DB44: 2 | DG44: 3 | DN44: 0 | DU44: 0 | EB44: 0 | EC44: 1 | ED44: 2 | EE44: 0 | EF44: 0 | EG44: 0 | EH44: 0 | EI44: 3 | EJ44: NO | EK44: NO | EL44: NO | EM44: NO | EN44: NO | EO44: NO | EP44: NO | EQ44: NO | ER44: NO | ES44: NO | ET44: NO | EU44: NO | EV44: YES | EW44: YES | EX44: NO | EY44: NO | EZ44: NO | FA44: NO | FB44: NO | FC44: NO | FD44: NO | FE44: NO | FF44: NO | FG44: NO | FH44: NO | FI44: NO | FJ44: NO | FK44: NO | FL44: NO | FM44: NO | FN44: NO | FO44: NO | FP44: NO | FQ44: NO | FR44: NO | FS44: NO | FT44: 50 | FU44: 171.4 | FZ44: 221.4 | GG44: 0 | GN44: 0 | GU44: 0 | HB44: 0 | HI44: 0 | HP44: 0 | HX44: 0 | HY44: 50 | HZ44: 171.4 | IA44: 0 | IB44: 0 | IC44: 0 | ID44: 0 | IE44: 221.4 | IL44: 0 | IS44: 0 | IT44: 50 | IU44: 171.4 | IZ44: 221.4 | JG44: 0 | JN44: 0 | JO44: 50 | JP44: 171.4 | JQ44: 0 | JR44: 0 | JS44: 0 | JT44: 0 | JU44: 221.4 | JX44: 100 | KA44: 1 | KB44: 3 | KC44: 1 | KD44: START Asia Pacific: | OG44: START Europe: | SJ44: START North America: | WM44: START Global: | AAP44: START SOUTH America: | AES44: START Africa:
A45: C9EYY906C | B45: INREV | C45: Seaforth Land | P45: TRUE | Q45: FALSE | R45: FALSE | S45: FALSE | T45: FALSE | U45: FALSE | V45: 621 | W45: 43514.933 | X45: 62.6.56.35 | Y45: 2019 | Z45: Tyler E. Goodwin | AA45: Seaforth Land | AB45: =VLOOKUP(MID(AD45,SEARCH("@",AD45,1),LEN(AD45)-SEARCH("@",AD45,1)+1),[2]Sheet1!$D:$F,3,FALSE) -> M03109 | AC45: CEO | AD45: Tyler.Goodwin@Seaforthland.com | AE45: 7745045077 | AF45: United Kingdom | AG45: GBP | AI45: 1 | AL45: 242 | AM45: 242 | AN45: 100 | AO45: 100 | AV45: 0 | AX45: 242 | BC45: 242 | BJ45: 0 | BQ45: 0 | BX45: 0 | CE45: 0 | CF45: 0 | CG45: 242 | CH45: 0 | CI45: 0 | CJ45: 0 | CK45: 0 | CL45: 242 | CS45: 0 | CU45: 2 | CZ45: 2 | DG45: 0 | DN45: 0 | DU45: 0 | EB45: 0 | EC45: 0 | ED45: 2 | EE45: 0 | EF45: 0 | EG45: 0 | EH45: 0 | EI45: 2 | EJ45: NO | EK45: NO | EL45: NO | EM45: NO | EN45: NO | EO45: NO | EP45: NO | EQ45: YES | ER45: NO | ES45: NO | ET45: NO | EU45: NO | EV45: NO | EW45: NO | EX45: NO | EY45: NO | EZ45: NO | FA45: NO | FB45: NO | FC45: NO | FD45: NO | FE45: NO | FF45: NO | FG45: NO | FH45: NO | FI45: NO | FJ45: NO | FK45: NO | FL45: NO | FM45: NO | FN45: NO | FO45: NO | FP45: NO | FQ45: NO | FR45: NO | FS45: NO | FU45: 220 | FZ45: 220 | GG45: 0 | GN45: 0 | GU45: 0 | HB45: 0 | HI45: 0 | HK45: 22 | HP45: 22 | HX45: 0 | HY45: 0 | HZ45: 242 | IA45: 0 | IB45: 0 | IC45: 0 | ID45: 0 | IE45: 242 | IG45: 22 | IL45: 22 | IS45: 0 | IU45: 220 | IZ45: 220 | JG45: 0 | JN45: 0 | JO45: 0 | JP45: 242 | JQ45: 0 | JR45: 0 | JS45: 0 | JT45: 0 | JU45: 242 | JX45: 100 | KA45: 1 | KB45: 3 | KC45: 1 | KD45: START Asia Pacific: | OG45: START Europe: | SJ45: START North America: | WM45: START Global: | AAP45: START SOUTH America: | AES45: START Africa:
A46: C9EZU414M | B46: INREV | C46: Garbe Industrial Real Estate GmbH | P46: TRUE | Q46: FALSE | R46: FALSE | S46: FALSE | T46: FALSE | U46: FALSE | V46: 805 | W46: 43531.674 | X46: 109.41.67.136 | Y46: 2019 | Z46: Jan Philipp Daun | AA46: GARBE Industrial Real Estate GmbH | AB46: =VLOOKUP(MID(AD46,SEARCH("@",AD46,1),LEN(AD46)-SEARCH("@",AD46,1)+1),[2]Sheet1!$D:$F,3,FALSE) -> M300 | AC46: Head of portfoliomanagement | AD46: jp.daun@garbe.de | AF46: Germany | AG46: EUR | AI46: 1 | AL46: 120 | AM46: 120 | AN46: 100 | AO46: 100 | AV46: 0 | AW46: 30 | AZ46: 90 | BC46: 120 | BJ46: 0 | BQ46: 0 | BX46: 0 | CE46: 0 | CF46: 30 | CG46: 0 | CH46: 0 | CI46: 90 | CJ46: 0 | CK46: 0 | CL46: 120 | CS46: 0 | CT46: 1 | CW46: 1 | CZ46: 2 | DG46: 0 | DN46: 0 | DU46: 0 | EB46: 0 | EC46: 1 | ED46: 0 | EE46: 0 | EF46: 1 | EG46: 0 | EH46: 0 | EI46: 2 | EJ46: NO | EK46: NO | EL46: NO | EM46: NO | EN46: NO | EO46: NO | EP46: YES | EQ46: NO | ER46: NO | ES46: YES | ET46: NO | EU46: NO | EV46: NO | EW46: NO | EX46: NO | EY46: NO | EZ46: NO | FA46: NO | FB46: NO | FC46: NO | FD46: NO | FE46: NO | FF46: NO | FG46: NO | FH46: NO | FI46: NO | FJ46: NO | FK46: NO | FL46: NO | FM46: NO | FN46: NO | FO46: NO | FP46: NO | FQ46: NO | FR46: NO | FS46: NO | FT46: 30 | FZ46: 30 | GG46: 0 | GN46: 0 | GU46: 0 | HB46: 0 | HI46: 0 | HP46: 0 | HQ46: PE | HU46: 90 | HX46: 90 | HY46: 30 | HZ46: 0 | IA46: 0 | IB46: 90 | IC46: 0 | ID46: 0 | IE46: 120 | IL46: 0 | IM46: 30 | IP46: 90 | IS46: 120 | IZ46: 0 | JG46: 0 | JN46: 0 | JO46: 30 | JP46: 0 | JQ46: 0 | JR46: 90 | JS46: 0 | JT46: 0 | JU46: 120 | JV46: 10 | JX46: 90 | KA46: 1 | KB46: 2 | KC46: 1 | KD46: START Asia Pacific: | OG46: START Europe: | SJ46: START North America: | WM46: START Global: | AAP46: START SOUTH America: | AES46: START Africa:
A47: C9FAT672M | B47: NCREIF | C47: MetLife | P47: TRUE | Q47: TRUE | R47: TRUE | S47: FALSE | T47: TRUE | U47: FALSE | V47: 612 | W47: 43525.885 | X47: 216.163.247.1 | Y47: 2019 | Z47: Brittany Seichal | AA47: MetLife Investment Management | AB47: =VLOOKUP(MID(AD47,SEARCH("@",AD47,1),LEN(AD47)-SEARCH("@",AD47,1)+1),[2]Sheet1!$D:$F,3,FALSE) -> M03148 | AD47: brittany.seichal@metlife.com | AE47: 9733554979 | AF47: United States | AG47: USD | AI47: 1 | AL47: 12125 | AN47: 12125 | AQ47: 500 | AU47: 811.7 | AV47: 1311.7 | BB47: 32.4 | BC47: 32.4 | BD47: 694.8 | BE47: 493.2 | BG47: 562.1 | BI47: 8700 | BJ47: 10450.1 | BQ47: 0 | BW47: 330.4 | BX47: 330.4 | CE47: 0 | CF47: 694.8 | CG47: 993.2 | CH47: 0 | CI47: 562.1 | CJ47: 0 | CK47: 9874.5 | CL47: 12124.6 | CN47: 1 | CR47: 1 | CS47: 2 | CY47: 1 | CZ47: 1 | DA47: 2 | DB47: 2 | DD47: 7 | DF47: 3 | DG47: 14 | DN47: 0 | DT47: 1 | DU47: 1 | EB47: 0 | EC47: 2 | ED47: 3 | EE47: 0 | EF47: 7 | EG47: 0 | EH47: 6 | EI47: 18 | EJ47: NO | EK47: YES | EL47: NO | EM47: NO | EN47: NO | EO47: YES | EP47: NO | EQ47: NO | ER47: NO | ES47: NO | ET47: NO | EU47: YES | EV47: YES | EW47: YES | EX47: NO | EY47: YES | EZ47: NO | FA47: YES | FB47: NO | FC47: NO | FD47: NO | FE47: NO | FF47: NO | FG47: NO | FH47: NO | FI47: NO | FJ47: NO | FK47: NO | FL47: NO | FM47: YES | FN47: NO | FO47: NO | FP47: NO | FQ47: NO | FR47: NO | FS47: NO | FT47: 25.1 | FZ47: 25.1 | GA47: 550.5 | GB47: 960 | GD47: 43.9 | GF47: 9874.5 | GG47: 11428.9 | GK47: 314.4 | GN47: 314.4 | GO47: 90.9 | GP47: 33.1 | GR47: 203.9 | GU47: 327.9 | HB47: 0 | HC47: 5.2 | HI47: 5.2 | HP47: 0 | HQ47: trust | HR47: 23.1 | HX47: 23.1 | HY47: 694.8 | HZ47: 993.1 | IA47: 0 | IB47: 562.2 | IC47: 0 | ID47: 9874.5 | IE47: 12124.6 | IF47: 185.13 | IL47: 185.13 | IM47: 15.1 | IP47: 60.89 | IS47: 75.99 | IT47: 494.6 | IU47: 993.2 | IW47: 247.77 | IY47: 9874.5 | IZ47: 11610.07 | JG47: 0 | JK47: 253.41 | JN47: 253.41 | JO47: 694.83 | JP47: 993.2 | JQ47: 0 | JR47: 562.07 | JS47: 0 | JT47: 9874.5 | JU47: 12124.6 | JX47: 100 | KA47: 1 | KB47: 1 | KC47: 1 | KD47: START Asia Pacific: | OG47: START Europe: | SJ47: START North America: | WM47: START Global: | AAP47: START SOUTH America: | AES47: START Africa:
A48: C9FAW364R | B48: INREV | C48: Catella AB | P48: TRUE | Q48: FALSE | R48: FALSE | S48: FALSE | T48: FALSE | U48: FALSE | V48: 628 | W48: 43522.582 | X48: 37.24.36.2 | Y48: 2019 | Z48: Thomas Beyerle | AA48: Catella | AB48: =VLOOKUP(MID(AD48,SEARCH("@",AD48,1),LEN(AD48)-SEARCH("@",AD48,1)+1),[2]Sheet1!$D:$F,3,FALSE) -> M063 | AC48: Head of Group Research | AD48: thomas.beyerle@catella.de | AE48: 1725255909 | AF48: Germany | AG48: EUR | AI48: 1 | AL48: 350 | AM48: 350 | AN48: 210 | AO48: 210 | AV48: 0 | AW48: 350 | BC48: 350 | BJ48: 0 | BQ48: 0 | BX48: 0 | CE48: 0 | CF48: 350 | CG48: 0 | CH48: 0 | CI48: 0 | CJ48: 0 | CK48: 0 | CL48: 350 | CS48: 0 | CT48: 4 | CZ48: 4 | DG48: 0 | DN48: 0 | DU48: 0 | EB48: 0 | EC48: 4 | ED48: 0 | EE48: 0 | EF48: 0 | EG48: 0 | EH48: 0 | EI48: 4 | EJ48: NO | EK48: NO | EL48: NO | EM48: NO | EN48: NO | EO48: NO | EP48: YES | EQ48: NO | ER48: NO | ES48: NO | ET48: NO | EU48: NO | EV48: NO | EW48: NO | EX48: NO | EY48: NO | EZ48: NO | FA48: NO | FB48: NO | FC48: NO | FD48: NO | FE48: NO | FF48: NO | FG48: NO | FH48: NO | FI48: NO | FJ48: NO | FK48: NO | FL48: NO | FM48: NO | FN48: NO | FO48: NO | FP48: NO | FQ48: NO | FR48: NO | FS48: NO | FT48: 140 | FZ48: 140 | GA48: 105 | GG48: 105 | GN48: 0 | GU48: 0 | GV48: 105 | HB48: 105 | HI48: 0 | HP48: 0 | HX48: 0 | HY48: 350 | HZ48: 0 | IA48: 0 | IB48: 0 | IC48: 0 | ID48: 0 | IE48: 350 | IL48: 0 | IM48: 350 | IS48: 350 | IZ48: 0 | JG48: 0 | JN48: 0 | JO48: 350 | JP48: 0 | JQ48: 0 | JR48: 0 | JS48: 0 | JT48: 0 | JU48: 350 | JV48: 10 | JW48: 10 | JX48: 80 | KA48: 1 | KB48: 2 | KC48: 1 | KD48: START Asia Pacific: | OG48: START Europe: | SJ48: START North America: | WM48: START Global: | AAP48: START SOUTH America: | AES48: START Africa:
A49: C9FBF528Y | B49: INREV | C49: Quantum Immobilien AG | P49: TRUE | Q49: FALSE | R49: FALSE | S49: FALSE | T49: FALSE | U49: FALSE | V49: 630 | W49: 43488.648 | X49: 212.202.231.18 | Y49: 2019 | Z49: Maximilian Schneidler | AA49: Herr | AB49: =VLOOKUP(MID(AD49,SEARCH("@",AD49,1),LEN(AD49)-SEARCH("@",AD49,1)+1),[2]Sheet1!$D:$F,3,FALSE) -> M346 | AC49: Investor Relations | AD49: mas@quantum.ag | AE49: 491721085920 | AF49: Germany | AG49: EUR | AI49: 1 | AL49: 574 | AM49: 574 | AO49: 440 | AV49: 0 | AW49: 391 | AX49: 93 | AZ49: 90 | BC49: 574 | BJ49: 0 | BQ49: 0 | BX49: 0 | CE49: 0 | CF49: 391 | CG49: 93 | CH49: 0 | CI49: 90 | CJ49: 0 | CK49: 0 | CL49: 574 | CS49: 0 | CT49: 3 | CU49: 1 | CW49: 3 | CZ49: 7 | DG49: 0 | DN49: 0 | DU49: 0 | EB49: 0 | EC49: 3 | ED49: 1 | EE49: 0 | EF49: 3 | EG49: 0 | EH49: 0 | EI49: 7 | EJ49: NO | EK49: NO | EL49: NO | EM49: NO | EN49: NO | EO49: NO | EP49: YES | EQ49: YES | ER49: NO | ES49: YES | ET49: NO | EU49: NO | EV49: NO | EW49: NO | EX49: NO | EY49: NO | EZ49: NO | FA49: NO | FB49: NO | FC49: NO | FD49: NO | FE49: NO | FF49: NO | FG49: NO | FH49: NO | FI49: NO | FJ49: NO | FK49: NO | FL49: NO | FM49: NO | FN49: NO | FO49: NO | FP49: NO | FQ49: NO | FR49: NO | FS49: NO | FT49: 232 | FU49: 93 | FW49: 90 | FZ49: 415 | GA49: 159 | GG49: 159 | GN49: 0 | GU49: 0 | HB49: 0 | HI49: 0 | HP49: 0 | HX49: 0 | HY49: 391 | HZ49: 93 | IA49: 0 | IB49: 90 | IC49: 0 | ID49: 0 | IE49: 574 | IL49: 0 | IM49: 391 | IN49: 93 | IP49: 90 | IS49: 574 | IZ49: 0 | JG49: 0 | JN49: 0 | JO49: 391 | JP49: 93 | JQ49: 0 | JR49: 90 | JS49: 0 | JT49: 0 | JU49: 574 | JX49: 100 | KA49: 3 | KB49: 3 | KC49: 1 | KD49: START Asia Pacific: | OG49: START Europe: | SJ49: START North America: | WM49: START Global: | AAP49: START SOUTH America: | AES49: START Africa:
A50: C9FDR539N | B50: INREV | C50: Round Hill Capital | P50: TRUE | Q50: FALSE | R50: TRUE | S50: FALSE | T50: FALSE | U50: FALSE | V50: 757 | W50: 43525.472 | X50: 154.47.76.253 | Y50: 2019 | Z50: Camilla Bergesen | AA50: Round Hill Capital | AB50: =VLOOKUP(MID(AD50,SEARCH("@",AD50,1),LEN(AD50)-SEARCH("@",AD50,1)+1),[2]Sheet1!$D:$F,3,FALSE) -> M2856 | AC50: Investor Relations | AD50: cbergesen@roundhillcapital.com | AE50: 2039280785 | AF50: United Kingdom | AG50: USD | AI50: 1 | AL50: 1329 | AM50: 1329 | AN50: 340 | AO50: 340 | AV50: 0 | AX50: 1115 | AZ50: 150 | BC50: 1265 | BD50: 64 | BJ50: 64 | BQ50: 0 | BX50: 0 | CE50: 0 | CF50: 64 | CG50: 1115 | CH50: 0 | CI50: 150 | CJ50: 0 | CK50: 0 | CL50: 1329 | CS50: 0 | CU50: 8 | CW50: 1 | CZ50: 9 | DA50: 1 | DG50: 1 | DN50: 0 | DU50: 0 | EB50: 0 | EC50: 1 | ED50: 8 | EE50: 0 | EF50: 1 | EG50: 0 | EH50: 0 | EI50: 10 | EJ50: NO | EK50: NO | EL50: NO | EM50: NO | EN50: NO | EO50: NO | EP50: NO | EQ50: YES | ER50: NO | ES50: YES | ET50: NO | EU50: NO | EV50: YES | EW50: NO | EX50: NO | EY50: NO | EZ50: NO | FA50: NO | FB50: NO | FC50: NO | FD50: NO | FE50: NO | FF50: NO | FG50: NO | FH50: NO | FI50: NO | FJ50: NO | FK50: NO | FL50: NO | FM50: NO | FN50: NO | FO50: NO | FP50: NO | FQ50: NO | FR50: NO | FS50: NO | FT50: 34 | FZ50: 34 | GG50: 0 | GN50: 0 | GU50: 0 | HB50: 0 | HI50: 0 | HJ50: 30 | HP50: 30 | HQ50: Private Investment Companies | HS50: 1115 | HU50: 150 | HX50: 1265 | HY50: 64 | HZ50: 1115 | IA50: 0 | IB50: 150 | IC50: 0 | ID50: 0 | IE50: 1329 | IL50: 0 | IM50: 34 | IS50: 34 | IT50: 30 | IU50: 1115 | IW50: 150 | IZ50: 1295 | JG50: 0 | JN50: 0 | JO50: 64 | JP50: 1115 | JQ50: 0 | JR50: 150 | JS50: 0 | JT50: 0 | JU50: 1329 | KA50: 1 | KB50: 3 | KC50: 2 | KD50: START Asia Pacific: | OG50: START Europe: | SJ50: START North America: | WM50: START Global: | AAP50: START SOUTH America: | AES50: START Africa:
A51: C9FFE356E | B51: INREV | C51: Caisson Investment Management | P51: TRUE | Q51: FALSE | R51: FALSE | S51: FALSE | T51: FALSE | U51: FALSE | V51: 767 | W51: 43516.486 | X51: 167.98.113.4 | Y51: 2019 | Z51: Michael Newman | AA51: Caisson Investment Management | AB51: =VLOOKUP(MID(AD51,SEARCH("@",AD51,1),LEN(AD51)-SEARCH("@",AD51,1)+1),[2]Sheet1!$D:$F,3,FALSE) -> M2757 | AC51: Finance Partner | AD51: michaelnewman1974@msn.com | AE51: 7976103926 | AF51: United Kingdom | AG51: GBP | AI51: 1 | AL51: 21 | AM51: 21 | AN51: 7 | AO51: 7 | AV51: 0 | AX51: 1 | AY51: 20 | BC51: 21 | BJ51: 0 | BQ51: 0 | BX51: 0 | CE51: 0 | CF51: 0 | CG51: 1 | CH51: 20 | CI51: 0 | CJ51: 0 | CK51: 0 | CL51: 21 | CS51: 0 | CU51: 1 | CV51: 1 | CZ51: 2 | DG51: 0 | DN51: 0 | DU51: 0 | EB51: 0 | EC51: 0 | ED51: 1 | EE51: 1 | EF51: 0 | EG51: 0 | EH51: 0 | EI51: 2 | EJ51: NO | EK51: NO | EL51: NO | EM51: NO | EN51: NO | EO51: NO | EP51: NO | EQ51: YES | ER51: YES | ES51: NO | ET51: NO | EU51: NO | EV51: NO | EW51: NO | EX51: NO | EY51: NO | EZ51: NO | FA51: NO | FB51: NO | FC51: NO | FD51: NO | FE51: NO | FF51: NO | FG51: NO | FH51: NO | FI51: NO | FJ51: NO | FK51: NO | FL51: NO | FM51: NO | FN51: NO | FO51: NO | FP51: NO | FQ51: NO | FR51: NO | FS51: NO | FV51: 20 | FZ51: 20 | GG51: 0 | GN51: 0 | GU51: 0 | HB51: 0 | HI51: 0 | HK51: 1 | HP51: 1 | HX51: 0 | HY51: 0 | HZ51: 1 | IA51: 20 | IB51: 0 | IC51: 0 | ID51: 0 | IE51: 21 | IL51: 0 | IN51: 1 | IO51: 20 | IS51: 21 | IZ51: 0 | JG51: 0 | JN51: 0 | JO51: 0 | JP51: 1 | JQ51: 20 | JR51: 0 | JS51: 0 | JT51: 0 | JU51: 21 | JV51: 0 | JX51: 100 | KA51: 1 | KB51: 3 | KC51: 1 | KD51: START Asia Pacific: | OG51: START Europe: | SJ51: START North America: | WM51: START Global: | AAP51: START SOUTH America: | AES51: START Africa:
A52: C9FJC902J | B52: INREV | C52: Long Harbour | P52: FALSE | Q52: FALSE | R52: FALSE | S52: FALSE | T52: FALSE | U52: FALSE | V52: 807 | W52: 43524.502 | X52: 154.47.76.70 | Y52: 2019 | Z52: Tabitha Perry | AA52: Long Harbour | AB52: =VLOOKUP(MID(AD52,SEARCH("@",AD52,1),LEN(AD52)-SEARCH("@",AD52,1)+1),[2]Sheet1!$D:$F,3,FALSE) -> M03137 | AD52: tjp@longharbour.co.uk | AF52: United Kingdom | AG52: GBP | AI52: 2 | AV52: 0 | BC52: 0 | BJ52: 0 | BQ52: 0 | BX52: 0 | CE52: 0 | CF52: 0 | CG52: 0 | CH52: 0 | CI52: 0 | CJ52: 0 | CK52: 0 | CL52: 0 | CS52: 0 | CZ52: 0 | DG52: 0 | DN52: 0 | DU52: 0 | EB52: 0 | EC52: 0 | ED52: 0 | EE52: 0 | EF52: 0 | EG52: 0 | EH52: 0 | EI52: 0 | EJ52: NO | EK52: NO | EL52: NO | EM52: NO | EN52: NO | EO52: NO | EP52: NO | EQ52: NO | ER52: NO | ES52: NO | ET52: NO | EU52: NO | EV52: NO | EW52: NO | EX52: NO | EY52: NO | EZ52: NO | FA52: NO | FB52: NO | FC52: NO | FD52: NO | FE52: NO | FF52: NO | FG52: NO | FH52: NO | FI52: NO | FJ52: NO | FK52: NO | FL52: NO | FM52: NO | FN52: NO | FO52: NO | FP52: NO | FQ52: NO | FR52: NO | FS52: NO | FZ52: 0 | GG52: 0 | GN52: 0 | GU52: 0 | HB52: 0 | HI52: 0 | HP52: 0 | HX52: 0 | HY52: 0 | HZ52: 0 | IA52: 0 | IB52: 0 | IC52: 0 | ID52: 0 | IE52: 0 | IL52: 0 | IS52: 0 | IZ52: 0 | JG52: 0 | JN52: 0 | JO52: 0 | JP52: 0 | JQ52: 0 | JR52: 0 | JS52: 0 | JT52: 0 | JU52: 0 | KC52: 2 | KD52: START Asia Pacific: | OG52: START Europe: | SJ52: START North America: | WM52: START Global: | AAP52: START SOUTH America: | AES52: START Africa:
A53: C9FNB361D | B53: INREV | C53: The Carlyle Group (FM) | P53: TRUE | Q53: FALSE | R53: FALSE | S53: FALSE | T53: FALSE | U53: FALSE | V53: 804 | W53: 43522.436 | X53: 85.115.53.201 | Y53: 2019 | Z53: Peter Stoll | AA53: The Carlyle Group | AB53: =VLOOKUP(MID(AD53,SEARCH("@",AD53,1),LEN(AD53)-SEARCH("@",AD53,1)+1),[2]Sheet1!$D:$F,3,FALSE) -> M769 | AD53: peter.stoll@carlyle.com | AE53: 2078943482 | AF53: United Kingdom | AG53: EUR | AI53: 1 | AL53: 568 | AN53: 130 | AV53: 0 | AW53: 550 | AZ53: 18 | BC53: 568 | BJ53: 0 | BQ53: 0 | BX53: 0 | CE53: 0 | CF53: 550 | CG53: 0 | CH53: 0 | CI53: 18 | CJ53: 0 | CK53: 0 | CL53: 568 | CS53: 0 | CT53: 1 | CW53: 1 | CZ53: 2 | DG53: 0 | DN53: 0 | DU53: 0 | EB53: 0 | EC53: 1 | ED53: 0 | EE53: 0 | EF53: 1 | EG53: 0 | EH53: 0 | EI53: 2 | EJ53: NO | EK53: NO | EL53: NO | EM53: NO | EN53: NO | EO53: NO | EP53: YES | EQ53: NO | ER53: NO | ES53: YES | ET53: NO | EU53: NO | EV53: NO | EW53: NO | EX53: NO | EY53: NO | EZ53: NO | FA53: NO | FB53: NO | FC53: NO | FD53: NO | FE53: NO | FF53: NO | FG53: NO | FH53: NO | FI53: NO | FJ53: NO | FK53: NO | FL53: NO | FM53: NO | FN53: NO | FO53: NO | FP53: NO | FQ53: NO | FR53: NO | FS53: NO | FT53: 350 | FW53: 18 | FZ53: 368 | GA53: 50 | GG53: 50 | GN53: 0 | GO53: 20 | GU53: 20 | GV53: 20 | HB53: 20 | HC53: 25 | HI53: 25 | HJ53: 35 | HP53: 35 | HQ53: Employees | HR53: 50 | HX53: 50 | HY53: 550 | HZ53: 0 | IA53: 0 | IB53: 18 | IC53: 0 | ID53: 0 | IE53: 568 | IL53: 0 | IM53: 390 | IP53: 18 | IS53: 408 | IT53: 135 | IZ53: 135 | JA53: 25 | JG53: 25 | JN53: 0 | JO53: 550 | JP53: 0 | JQ53: 0 | JR53: 18 | JS53: 0 | JT53: 0 | JU53: 568 | JV53: 0 | JX53: 100 | KA53: 3 | KB53: 3 | KC53: 2 | KD53: START Asia Pacific: | OG53: START Europe: | SJ53: START North America: | WM53: START Global: | AAP53: START SOUTH America: | AES53: START Africa:
A54: C9FND894E | B54: ANREV | C54: Vicinity Centres | P54: FALSE | Q54: FALSE | R54: FALSE | S54: FALSE | T54: FALSE | U54: FALSE | V54: 715 | W54: 43515.269 | X54: 220.101.40.240 | Y54: 2019 | Z54: Andrew Turnham | AA54: Vicinity Centres | AB54: =VLOOKUP(MID(AD54,SEARCH("@",AD54,1),LEN(AD54)-SEARCH("@",AD54,1)+1),[2]Sheet1!$D:$F,3,FALSE) -> N0298 | AC54: Senior Investment Analyst | AD54: andrew.turnham@vicinity.com.au | AE54: 408638841 | AF54: Australia | AG54: AUD | AI54: 2 | AJ54: 6 | AK54: Market Conditions | AV54: 0 | BC54: 0 | BJ54: 0 | BQ54: 0 | BX54: 0 | CE54: 0 | CF54: 0 | CG54: 0 | CH54: 0 | CI54: 0 | CJ54: 0 | CK54: 0 | CL54: 0 | CS54: 0 | CZ54: 0 | DG54: 0 | DN54: 0 | DU54: 0 | EB54: 0 | EC54: 0 | ED54: 0 | EE54: 0 | EF54: 0 | EG54: 0 | EH54: 0 | EI54: 0 | EJ54: NO | EK54: NO | EL54: NO | EM54: NO | EN54: NO | EO54: NO | EP54: NO | EQ54: NO | ER54: NO | ES54: NO | ET54: NO | EU54: NO | EV54: NO | EW54: NO | EX54: NO | EY54: NO | EZ54: NO | FA54: NO | FB54: NO | FC54: NO | FD54: NO | FE54: NO | FF54: NO | FG54: NO | FH54: NO | FI54: NO | FJ54: NO | FK54: NO | FL54: NO | FM54: NO | FN54: NO | FO54: NO | FP54: NO | FQ54: NO | FR54: NO | FS54: NO | FZ54: 0 | GG54: 0 | GN54: 0 | GU54: 0 | HB54: 0 | HI54: 0 | HP54: 0 | HX54: 0 | HY54: 0 | HZ54: 0 | IA54: 0 | IB54: 0 | IC54: 0 | ID54: 0 | IE54: 0 | IL54: 0 | IS54: 0 | IZ54: 0 | JG54: 0 | JN54: 0 | JO54: 0 | JP54: 0 | JQ54: 0 | JR54: 0 | JS54: 0 | JT54: 0 | JU54: 0 | KA54: 1 | KB54: 3 | KC54: 1 | KD54: START Asia Pacific: | OG54: START Europe: | SJ54: START North America: | WM54: START Global: | AAP54: START SOUTH America: | AES54: START Africa:
A55: C9FNK492M | B55: INREV | C55: Moorfield Group | P55: TRUE | Q55: FALSE | R55: FALSE | S55: FALSE | T55: FALSE | U55: FALSE | V55: 775 | W55: 43516.661 | X55: 154.47.76.247 | Y55: 2019 | Z55: Robbert Zoet | AA55: Moorfield | AB55: =VLOOKUP(MID(AD55,SEARCH("@",AD55,1),LEN(AD55)-SEARCH("@",AD55,1)+1),[2]Sheet1!$D:$F,3,FALSE) -> M655 | AC55: Head of Capital Markets | AD55: robbert.zoet@moorfield.com | AE55: 2073991936 | AF55: United Kingdom | AG55: GBP | AI55: 1 | AL55: 220 | AM55: 220 | AN55: 50 | AO55: 50 | AV55: 0 | AW55: 220 | BC55: 220 | BJ55: 0 | BQ55: 0 | BX55: 0 | CE55: 0 | CF55: 220 | CG55: 0 | CH55: 0 | CI55: 0 | CJ55: 0 | CK55: 0 | CL55: 220 | CS55: 0 | CT55: 1 | CZ55: 1 | DG55: 0 | DN55: 0 | DU55: 0 | EB55: 0 | EC55: 1 | ED55: 0 | EE55: 0 | EF55: 0 | EG55: 0 | EH55: 0 | EI55: 1 | EJ55: NO | EK55: NO | EL55: NO | EM55: NO | EN55: NO | EO55: NO | EP55: YES | EQ55: NO | ER55: NO | ES55: NO | ET55: NO | EU55: NO | EV55: NO | EW55: NO | EX55: NO | EY55: NO | EZ55: NO | FA55: NO | FB55: NO | FC55: NO | FD55: NO | FE55: NO | FF55: NO | FG55: NO | FH55: NO | FI55: NO | FJ55: NO | FK55: NO | FL55: NO | FM55: NO | FN55: NO | FO55: NO | FP55: NO | FQ55: NO | FR55: NO | FS55: NO | FT55: 95 | FZ55: 95 | GG55: 0 | GH55: 38 | GN55: 38 | GU55: 0 | GV55: 87 | HB55: 87 | HI55: 0 | HP55: 0 | HX55: 0 | HY55: 220 | HZ55: 0 | IA55: 0 | IB55: 0 | IC55: 0 | ID55: 0 | IE55: 220 | IF55: 44 | IL55: 44 | IM55: 102 | IS55: 102 | IT55: 74 | IZ55: 74 | JG55: 0 | JN55: 0 | JO55: 220 | JP55: 0 | JQ55: 0 | JR55: 0 | JS55: 0 | JT55: 0 | JU55: 220 | JV55: 42 | JX55: 58 | KA55: 1 | KB55: 2 | KC55: 1 | KD55: START Asia Pacific: | OG55: START Europe: | SJ55: START North America: | WM55: START Global: | AAP55: START SOUTH America: | AES55: START Africa:
A56: C9FNR589R | B56: NCREIF | C56: Heitman | D56: Asia | E56: 43518.923 | H56: northamerica | I56: 43518.926 | P56: FALSE | Q56: TRUE | R56: TRUE | S56: FALSE | T56: FALSE | U56: FALSE | V56: 703 | W56: 43518.919 | X56: 145.131.178.65 | Y56: 2019 | Z56: Nicole Luna | AA56: Heitman | AB56: =VLOOKUP(MID(AD56,SEARCH("@",AD56,1),LEN(AD56)-SEARCH("@",AD56,1)+1),[2]Sheet1!$D:$F,3,FALSE) -> M107 | AC56: Assistant Vice President | AD56: consultant.services@heitman.com | AE56: 312-425-0492 | AF56: United States | AG56: USD | AI56: 1 | AL56: 5202 | AM56: 3514 | AN56: 3471 | AO56: 1782 | AP56: 155 | AQ56: 28 | AV56: 183 | BC56: 0 | BD56: 1805 | BE56: 550 | BI56: 976 | BJ56: 3331 | BQ56: 0 | BX56: 0 | CE56: 0 | CF56: 1960 | CG56: 578 | CH56: 0 | CI56: 0 | CJ56: 0 | CK56: 976 | CL56: 3514 | CM56: 1 | CN56: 1 | CS56: 2 | CZ56: 0 | DA56: 2 | DB56: 1 | DF56: 4 | DG56: 7 | DN56: 0 | DU56: 0 | EB56: 0 | EC56: 3 | ED56: 2 | EE56: 0 | EF56: 0 | EG56: 0 | EH56: 4 | EI56: 9 | EJ56: YES | EK56: YES | EL56: NO | EM56: NO | EN56: NO | EO56: NO | EP56: NO | EQ56: NO | ER56: NO | ES56: NO | ET56: NO | EU56: NO | EV56: YES | EW56: YES | EX56: NO | EY56: NO | EZ56: NO | FA56: YES | FB56: NO | FC56: NO | FD56: NO | FE56: NO | FF56: NO | FG56: NO | FH56: NO | FI56: NO | FJ56: NO | FK56: NO | FL56: NO | FM56: NO | FN56: NO | FO56: NO | FP56: NO | FQ56: NO | FR56: NO | FS56: NO | FT56: 117 | FU56: 0 | FY56: 0 | FZ56: 117 | GA56: 0 | GB56: 0 | GF56: 0 | GG56: 0 | GH56: 0 | GI56: 28 | GM56: 0 | GN56: 28 | GO56: 1333 | GP56: 550 | GT56: 916 | GU56: 2799 | GV56: 21 | GW56: 0 | HA56: 0 | HB56: 21 | HC56: 77 | HD56: 0 | HH56: 0 | HI56: 77 | HJ56: 0 | HK56: 0 | HO56: 0 | HP56: 0 | HQ56: corporate, taft-hartley | HR56: 411 | HS56: 0 | HW56: 61 | HX56: 472 | HY56: 1959 | HZ56: 578 | IA56: 0 | IB56: 0 | IC56: 0 | ID56: 977 | IE56: 3514 | IF56: 180 | IG56: 28 | IK56: 428 | IL56: 636 | IM56: 94 | IS56: 94 | IT56: 1686 | IU56: 550 | IY56: 548 | IZ56: 2784 | JG56: 0 | JN56: 0 | JO56: 1960 | JP56: 578 | JQ56: 0 | JR56: 0 | JS56: 0 | JT56: 976 | JU56: 3514 | JW56: 5 | JX56: 50 | JY56: new clients from prospecting | JZ56: 45 | KA56: 3 | KB56: 1 | KC56: 1 | KD56: START Asia Pacific: | KE56: 18 | KK56: 18 | KR56: 0 | KT56: 28 | KY56: 28 | KZ56: 132 | LF56: 132 | LM56: 0 | LT56: 0 | MA56: 0 | MB56: corporate | MC56: 5 | MI56: 5 | MJ56: 155 | MK56: 28 | ML56: 0 | MM56: 0 | MN56: 0 | MO56: 0 | MP56: 183 | MQ56: 17 | MW56: 17 | MY56: 28 | ND56: 28 | NE56: 138 | NK56: 138 | NR56: 0 | NY56: 0 | NZ56: 155 | OA56: 28 | OB56: 0 | OC56: 0 | OD56: 0 | OE56: 0 | OF56: 183 | OG56: START Europe: | SJ56: START North America: | SK56: 99 | SQ56: 99 | SX56: 0 | TE56: 0 | TF56: 1202 | TG56: 550 | TK56: 915 | TL56: 2667 | TM56: 21 | TS56: 21 | TT56: 77 | TZ56: 77 | UG56: 0 | UH56: corporate, taft-hartley | UI56: 406 | UN56: 61 | UO56: 467 | UP56: 1805 | UQ56: 550 | UR56: 0 | US56: 0 | UT56: 0 | UU56: 976 | UV56: 3331 | UW56: 77 | VC56: 77 | VD56: 180 | VI56: 428 | VJ56: 608 | VK56: 1548 | VL56: 550 | VP56: 548 | VQ56: 2646 | VX56: 0 | WE56: 0 | WF56: 1805 | WG56: 550 | WH56: 0 | WI56: 0 | WJ56: 0 | WK56: 976 | WL56: 3331 | WM56: START Global: | AAP56: START SOUTH America: | AES56: START Africa:
A57: C9FNV676B | B57: NCREIF | C57: Northwestern Mutual Life Insurance | P57: FALSE | Q57: FALSE | R57: TRUE | S57: FALSE | T57: FALSE | U57: FALSE | V57: 721 | W57: 43514.572 | X57: 216.20.176.6 | Y57: 2019 | Z57: Daniel Flesch | AA57: Northwestern Mutual | AB57: =VLOOKUP(MID(AD57,SEARCH("@",AD57,1),LEN(AD57)-SEARCH("@",AD57,1)+1),[2]Sheet1!$D:$F,3,FALSE) -> NC019 | AC57: Director | AD57: dannyflesch@northwesternmutual.com | AE57: 414-665-2433 | AF57: United States | AG57: USD | AI57: 1 | AL57: 7400 | AM57: 7400 | AN57: 7400 | AO57: 7400 | AV57: 0 | BC57: 0 | BE57: 1700 | BI57: 5700 | BJ57: 7400 | BQ57: 0 | BX57: 0 | CE57: 0 | CF57: 0 | CG57: 1700 | CH57: 0 | CI57: 0 | CJ57: 0 | CK57: 5700 | CL57: 7400 | CS57: 0 | CZ57: 0 | DB57: 1 | DF57: 1 | DG57: 2 | DN57: 0 | DU57: 0 | EB57: 0 | EC57: 0 | ED57: 1 | EE57: 0 | EF57: 0 | EG57: 0 | EH57: 1 | EI57: 2 | EJ57: NO | EK57: NO | EL57: NO | EM57: NO | EN57: NO | EO57: NO | EP57: NO | EQ57: NO | ER57: NO | ES57: NO | ET57: NO | EU57: NO | EV57: NO | EW57: YES | EX57: NO | EY57: NO | EZ57: NO | FA57: YES | FB57: NO | FC57: NO | FD57: NO | FE57: NO | FF57: NO | FG57: NO | FH57: NO | FI57: NO | FJ57: NO | FK57: NO | FL57: NO | FM57: NO | FN57: NO | FO57: NO | FP57: NO | FQ57: NO | FR57: NO | FS57: NO | FZ57: 0 | GB57: 1700 | GF57: 5700 | GG57: 7400 | GN57: 0 | GU57: 0 | HB57: 0 | HI57: 0 | HP57: 0 | HX57: 0 | HY57: 0 | HZ57: 1700 | IA57: 0 | IB57: 0 | IC57: 0 | ID57: 5700 | IE57: 7400 | IL57: 0 | IS57: 0 | IU57: 1700 | IY57: 5700 | IZ57: 7400 | JG57: 0 | JN57: 0 | JO57: 0 | JP57: 1700 | JQ57: 0 | JR57: 0 | JS57: 0 | JT57: 5700 | JU57: 7400 | JY57: We only manage assets for the insurance company. | JZ57: 100 | KA57: 2 | KB57: 3 | KC57: 2 | KD57: START Asia Pacific: | OG57: START Europe: | SJ57: START North America: | WM57: START Global: | AAP57: START SOUTH America: | AES57: START Africa:
A58: C9FVR345Z | B58: INREV | C58: BEOS AG | P58: TRUE | Q58: FALSE | R58: FALSE | S58: FALSE | T58: FALSE | U58: FALSE | V58: 576 | W58: 43486.444 | X58: 195.227.81.241 | Y58: 2019 | Z58: Maximilian Brüne | AA58: BEOS AG | AB58: =VLOOKUP(MID(AD58,SEARCH("@",AD58,1),LEN(AD58)-SEARCH("@",AD58,1)+1),[2]Sheet1!$D:$F,3,FALSE) -> M617 | AC58: Portfolio manager | AD58: maximilian.bruene@beos.net | AF58: Germany | AG58: EUR | AI58: 1 | AL58: 182 | AM58: 182 | AN58: 182 | AO58: 182 | AV58: 0 | AW58: 182 | BC58: 182 | BJ58: 0 | BQ58: 0 | BX58: 0 | CE58: 0 | CF58: 182 | CG58: 0 | CH58: 0 | CI58: 0 | CJ58: 0 | CK58: 0 | CL58: 182 | CS58: 0 | CT58: 2 | CZ58: 2 | DG58: 0 | DN58: 0 | DU58: 0 | EB58: 0 | EC58: 2 | ED58: 0 | EE58: 0 | EF58: 0 | EG58: 0 | EH58: 0 | EI58: 2 | EJ58: NO | EK58: NO | EL58: NO | EM58: NO | EN58: NO | EO58: NO | EP58: YES | EQ58: NO | ER58: NO | ES58: NO | ET58: NO | EU58: NO | EV58: NO | EW58: NO | EX58: NO | EY58: NO | EZ58: NO | FA58: NO | FB58: NO | FC58: NO | FD58: NO | FE58: NO | FF58: NO | FG58: NO | FH58: NO | FI58: NO | FJ58: NO | FK58: NO | FL58: NO | FM58: NO | FN58: NO | FO58: NO | FP58: NO | FQ58: NO | FR58: NO | FS58: NO | FT58: 35.3 | FZ58: 35.3 | GA58: 11.3 | GG58: 11.3 | GN58: 0 | GU58: 0 | GV58: 1.3 | HB58: 1.3 | HC58: 118.7 | HI58: 118.7 | HP58: 0 | HQ58: Church-institutions / church-related-institutions | HR58: 15.4 | HX58: 15.4 | HY58: 182 | HZ58: 0 | IA58: 0 | IB58: 0 | IC58: 0 | ID58: 0 | IE58: 182 | IL58: 0 | IM58: 182 | IS58: 182 | IZ58: 0 | JG58: 0 | JN58: 0 | JO58: 182 | JP58: 0 | JQ58: 0 | JR58: 0 | JS58: 0 | JT58: 0 | JU58: 182 | JX58: 100 | KA58: 1 | KB58: 3 | KC58: 1 | KD58: START Asia Pacific: | OG58: START Europe: | SJ58: START North America: | WM58: START Global: | AAP58: START SOUTH America: | AES58: START Africa:
A59: C9GAE462U | B59: INREV | C59: KGAL GmbH & Co. KG | P59: TRUE | Q59: FALSE | R59: FALSE | S59: FALSE | T59: FALSE | U59: FALSE | V59: 620 | W59: 43490.442 | X59: 194.8.124.5 | Y59: 2019 | Z59: Roland Gill | AA59: KGAL Capital GmbH & Co KG | AB59: =VLOOKUP(MID(AD59,SEARCH("@",AD59,1),LEN(AD59)-SEARCH("@",AD59,1)+1),[2]Sheet1!$D:$F,3,FALSE) -> M637 | AC59: Manager Consultant Relations | AD59: roland.gill@kgal.de | AE59: +49 89 64143-143 | AF59: Germany | AG59: EUR | AI59: 1 | AM59: 100 | AO59: 92.3 | AV59: 0 | AW59: 100 | BC59: 100 | BJ59: 0 | BQ59: 0 | BX59: 0 | CE59: 0 | CF59: 100 | CG59: 0 | CH59: 0 | CI59: 0 | CJ59: 0 | CK59: 0 | CL59: 100 | CS59: 0 | CT59: 1 | CZ59: 1 | DG59: 0 | DN59: 0 | DU59: 0 | EB59: 0 | EC59: 1 | ED59: 0 | EE59: 0 | EF59: 0 | EG59: 0 | EH59: 0 | EI59: 1 | EJ59: NO | EK59: NO | EL59: NO | EM59: NO | EN59: NO | EO59: NO | EP59: YES | EQ59: NO | ER59: NO | ES59: NO | ET59: NO | EU59: NO | EV59: NO | EW59: NO | EX59: NO | EY59: NO | EZ59: NO | FA59: NO | FB59: NO | FC59: NO | FD59: NO | FE59: NO | FF59: NO | FG59: NO | FH59: NO | FI59: NO | FJ59: NO | FK59: NO | FL59: NO | FM59: NO | FN59: NO | FO59: NO | FP59: NO | FQ59: NO | FR59: NO | FS59: NO | FZ59: 0 | GG59: 0 | GN59: 0 | GU59: 0 | HB59: 0 | HI59: 0 | HP59: 0 | HQ59: Church Institution | HR59: 100 | HX59: 100 | HY59: 100 | HZ59: 0 | IA59: 0 | IB59: 0 | IC59: 0 | ID59: 0 | IE59: 100 | IL59: 0 | IM59: 100 | IS59: 100 | IZ59: 0 | JG59: 0 | JN59: 0 | JO59: 100 | JP59: 0 | JQ59: 0 | JR59: 0 | JS59: 0 | JT59: 0 | JU59: 100 | JX59: 100 | KA59: 1 | KB59: 3 | KC59: 1 | KD59: START Asia Pacific: | OG59: START Europe: | SJ59: START North America: | WM59: START Global: | AAP59: START SOUTH America: | AES59: START Africa:
A60: C9GBR502X | B60: INREV | C60: NREP | P60: TRUE | Q60: FALSE | R60: FALSE | S60: FALSE | T60: FALSE | U60: FALSE | V60: 640 | W60: 43509.539 | X60: 31.31.84.65 | Y60: 2019 | Z60: Anne Schachner | AA60: NREP | AB60: =VLOOKUP(MID(AD60,SEARCH("@",AD60,1),LEN(AD60)-SEARCH("@",AD60,1)+1),[2]Sheet1!$D:$F,3,FALSE) -> M305 | AC60: Associate | AD60: ansc@nrep.com | AE60: +45 30520201 | AF60: Denmark | AG60: EUR | AI60: 1 | AL60: 675 | AM60: 675 | AN60: 307 | AO60: 307 | AV60: 0 | AW60: 675 | BC60: 675 | BJ60: 0 | BQ60: 0 | BX60: 0 | CE60: 0 | CF60: 675 | CG60: 0 | CH60: 0 | CI60: 0 | CJ60: 0 | CK60: 0 | CL60: 675 | CS60: 0 | CT60: 1 | CZ60: 1 | DG60: 0 | DN60: 0 | DU60: 0 | EB60: 0 | EC60: 1 | ED60: 0 | EE60: 0 | EF60: 0 | EG60: 0 | EH60: 0 | EI60: 1 | EJ60: NO | EK60: NO | EL60: NO | EM60: NO | EN60: NO | EO60: NO | EP60: YES | EQ60: NO | ER60: NO | ES60: NO | ET60: NO | EU60: NO | EV60: NO | EW60: NO | EX60: NO | EY60: NO | EZ60: NO | FA60: NO | FB60: NO | FC60: NO | FD60: NO | FE60: NO | FF60: NO | FG60: NO | FH60: NO | FI60: NO | FJ60: NO | FK60: NO | FL60: NO | FM60: NO | FN60: NO | FO60: NO | FP60: NO | FQ60: NO | FR60: NO | FS60: NO | FT60: 212 | FZ60: 212 | GA60: 153 | GG60: 153 | GH60: 0 | GN60: 0 | GO60: 0 | GU60: 0 | GV60: 90 | HB60: 90 | HC60: 0 | HI60: 0 | HJ60: 14 | HP60: 14 | HQ60: Investment firms, Wealth managers, Endowments, Private banks | HR60: 206 | HX60: 206 | HY60: 675 | HZ60: 0 | IA60: 0 | IB60: 0 | IC60: 0 | ID60: 0 | IE60: 675 | IF60: 120 | IL60: 120 | IM60: 390 | IS60: 390 | IT60: 165 | IZ60: 165 | JG60: 0 | JN60: 0 | JO60: 675 | JP60: 0 | JQ60: 0 | JR60: 0 | JS60: 0 | JT60: 0 | JU60: 675 | JV60: 0 | JW60: 25 | JX60: 75 | KA60: 1 | KB60: 3 | KC60: 2 | KD60: START Asia Pacific: | OG60: START Europe: | SJ60: START North America: | WM60: START Global: | AAP60: START SOUTH America: | AES60: START Africa:
A61: C9GBT640V | B61: NCREIF | C61: Forest Investment Associates | P61: FALSE | Q61: FALSE | R61: TRUE | S61: FALSE | T61: FALSE | U61: FALSE | V61: 693 | W61: 43500.869 | X61: 12.227.210.66 | Y61: 2019 | Z61: Ryan Reddish | AA61: Forest Investment Associates | AB61: =VLOOKUP(MID(AD61,SEARCH("@",AD61,1),LEN(AD61)-SEARCH("@",AD61,1)+1),[2]Sheet1!$D:$F,3,FALSE) -> NC008 | AC61: Acquisitions Manager | AD61: rreddish@forestinvest.com | AF61: United States | AG61: USD | AI61: 1 | AL61: 220 | AM61: 220 | AN61: 175 | AO61: 175 | AV61: 0 | BC61: 0 | BE61: 220 | BJ61: 220 | BQ61: 0 | BX61: 0 | CE61: 0 | CF61: 0 | CG61: 220 | CH61: 0 | CI61: 0 | CJ61: 0 | CK61: 0 | CL61: 220 | CS61: 0 | CZ61: 0 | DB61: 2 | DG61: 2 | DN61: 0 | DU61: 0 | EB61: 0 | EC61: 0 | ED61: 2 | EE61: 0 | EF61: 0 | EG61: 0 | EH61: 0 | EI61: 2 | EJ61: NO | EK61: NO | EL61: NO | EM61: NO | EN61: NO | EO61: NO | EP61: NO | EQ61: NO | ER61: NO | ES61: NO | ET61: NO | EU61: NO | EV61: NO | EW61: YES | EX61: NO | EY61: NO | EZ61: NO | FA61: NO | FB61: NO | FC61: NO | FD61: NO | FE61: NO | FF61: NO | FG61: NO | FH61: NO | FI61: NO | FJ61: NO | FK61: NO | FL61: NO | FM61: NO | FN61: NO | FO61: NO | FP61: NO | FQ61: NO | FR61: NO | FS61: NO | FU61: 220 | FZ61: 220 | GG61: 0 | GN61: 0 | GU61: 0 | HB61: 0 | HI61: 0 | HP61: 0 | HX61: 0 | HY61: 0 | HZ61: 220 | IA61: 0 | IB61: 0 | IC61: 0 | ID61: 0 | IE61: 220 | IL61: 0 | IS61: 0 | IU61: 220 | IZ61: 220 | JG61: 0 | JN61: 0 | JO61: 0 | JP61: 220 | JQ61: 0 | JR61: 0 | JS61: 0 | JT61: 0 | JU61: 220 | JX61: 100 | KA61: 1 | KB61: 3 | KC61: 2 | KD61: START Asia Pacific: | OG61: START Europe: | SJ61: START North America: | WM61: START Global: | AAP61: START SOUTH America: | AES61: START Africa:
A62: C9GCU682K | B62: ANREV | C62: Kenedix, Inc. | P62: FALSE | Q62: TRUE | R62: FALSE | S62: FALSE | T62: FALSE | U62: FALSE | V62: 541 | W62: 43517.326 | X62: 220.216.110.130 | Y62: 2019 | Z62: Shunsuke Saki | AA62: Kenedix | AB62: =VLOOKUP(MID(AD62,SEARCH("@",AD62,1),LEN(AD62)-SEARCH("@",AD62,1)+1),[2]Sheet1!$D:$F,3,FALSE) -> M0230 | AC62: manager | AD62: shunsuke_saeki@kenedix.com | AE62: 03-6889-6066 | AF62: Japan | AG62: JPY | AI62: 1 | AL62: 100000 | AM62: 50000 | AN62: 40000 | AO62: 40000 | AQ62: 50000 | AV62: 50000 | BC62: 0 | BJ62: 0 | BQ62: 0 | BX62: 0 | CE62: 0 | CF62: 0 | CG62: 50000 | CH62: 0 | CI62: 0 | CJ62: 0 | CK62: 0 | CL62: 50000 | CN62: 60 | CS62: 60 | CZ62: 0 | DG62: 0 | DN62: 0 | DU62: 0 | EB62: 0 | EC62: 0 | ED62: 60 | EE62: 0 | EF62: 0 | EG62: 0 | EH62: 0 | EI62: 60 | EJ62: NO | EK62: YES | EL62: NO | EM62: NO | EN62: NO | EO62: NO | EP62: NO | EQ62: NO | ER62: NO | ES62: NO | ET62: NO | EU62: NO | EV62: NO | EW62: NO | EX62: NO | EY62: NO | EZ62: NO | FA62: NO | FB62: NO | FC62: NO | FD62: NO | FE62: NO | FF62: NO | FG62: NO | FH62: NO | FI62: NO | FJ62: NO | FK62: NO | FL62: NO | FM62: NO | FN62: NO | FO62: NO | FP62: NO | FQ62: NO | FR62: NO | FS62: NO | FU62: 25000 | FZ62: 25000 | GB62: 25000 | GG62: 25000 | GN62: 0 | GU62: 0 | HB62: 0 | HI62: 0 | HP62: 0 | HX62: 0 | HY62: 0 | HZ62: 50000 | IA62: 0 | IB62: 0 | IC62: 0 | ID62: 0 | IE62: 50000 | IG62: 50000 | IL62: 50000 | IS62: 0 | IZ62: 0 | JG62: 0 | JN62: 0 | JO62: 0 | JP62: 50000 | JQ62: 0 | JR62: 0 | JS62: 0 | JT62: 0 | JU62: 50000 | JW62: 100 | KA62: 3 | KB62: 3 | KC62: 2 | KD62: START Asia Pacific: | OG62: START Europe: | SJ62: START North America: | WM62: START Global: | AAP62: START SOUTH America: | AES62: START Africa:
A63: C9GDC679D | B63: NCREIF | C63: PCCP | LLC | P63: FALSE | Q63: FALSE | R63: TRUE | S63: FALSE | T63: FALSE | U63: FALSE | V63: 604 | W63: 43518.063 | X63: 38.88.160.234 | Y63: 2019 | Z63: Investor Reporting, Kathryn Gorsch | AA63: PCCP, LLC | AB63: =VLOOKUP(MID(AD63,SEARCH("@",AD63,1),LEN(AD63)-SEARCH("@",AD63,1)+1),[2]Sheet1!$D:$F,3,FALSE) -> M05120 | AC63: Investor Relations | AD63: investorreporting@pccpllc.com | AE63: 310-414-7870 | AF63: United States | AG63: USD | AI63: 1 | AL63: 2594 | AM63: 2594 | AN63: 1053 | AO63: 1053 | AV63: 0 | BC63: 0 | BD63: 627 | BE63: 115 | BF63: 0 | BG63: 850 | BH63: 0 | BI63: 1002 | BJ63: 2594 | BQ63: 0 | BX63: 0 | CE63: 0 | CF63: 627 | CG63: 115 | CH63: 0 | CI63: 850 | CJ63: 0 | CK63: 1002 | CL63: 2594 | CS63: 0 | CZ63: 0 | DA63: 2 | DB63: 1 | DD63: 3 | DF63: 1 | DG63: 7 | DN63: 0 | DU63: 0 | EB63: 0 | EC63: 2 | ED63: 1 | EE63: 0 | EF63: 3 | EG63: 0 | EH63: 1 | EI63: 7 | EJ63: NO | EK63: NO | EL63: NO | EM63: NO | EN63: NO | EO63: NO | EP63: NO | EQ63: NO | ER63: NO | ES63: NO | ET63: NO | EU63: NO | EV63: YES | EW63: YES | EX63: NO | EY63: YES | EZ63: NO | FA63: YES | FB63: NO | FC63: NO | FD63: NO | FE63: NO | FF63: NO | FG63: NO | FH63: NO | FI63: NO | FJ63: NO | FK63: NO | FL63: NO | FM63: NO | FN63: NO | FO63: NO | FP63: NO | FQ63: NO | FR63: NO | FS63: NO | FT63: 365 | FU63: 115 | FW63: 840 | FY63: 364 | FZ63: 1684 | GA63: 110 | GF63: 275 | GG63: 385 | GM63: 100 | GN63: 100 | GT63: 4 | GU63: 4 | GV63: 10 | HB63: 10 | HH63: 20 | HI63: 20 | HO63: 10 | HP63: 10 | HQ63: PCCP, Asset Manager, Private Pension | HR63: 142 | HU63: 10 | HW63: 229 | HX63: 381 | HY63: 627 | HZ63: 115 | IA63: 0 | IB63: 850 | IC63: 0 | ID63: 1002 | IE63: 2594 | IL63: 0 | IS63: 0 | IT63: 627 | IU63: 115 | IW63: 850 | IY63: =1002 -> 1002 | IZ63: =2594 -> 2594 | JG63: 0 | JN63: 0 | JO63: 627 | JP63: 115 | JQ63: 0 | JR63: 850 | JS63: 0 | JT63: 1002 | JU63: 2594 | KA63: 1 | KB63: 3 | KC63: 2 | KD63: START Asia Pacific: | OG63: START Europe: | SJ63: START North America: | WM63: START Global: | AAP63: START SOUTH America: | AES63: START Africa:
A64: C9GDF293E | B64: ANREV | C64: AEP Investment Management | D64: Asia | E64: 43521.151 | F64: europe | G64: 43521.152 | P64: TRUE | Q64: TRUE | R64: FALSE | S64: FALSE | T64: FALSE | U64: FALSE | V64: 534 | W64: 43521.151 | X64: 101.78.249.218 | Y64: 2019 | Z64: Johan Shah | AA64: AEP Investment Management Pte Ltd | AB64: =VLOOKUP(MID(AD64,SEARCH("@",AD64,1),LEN(AD64)-SEARCH("@",AD64,1)+1),[2]Sheet1!$D:$F,3,FALSE) -> M0291 | AC64: Director, Head of Asset Management and Investor Relations | AD64: johan.shah@aep-im.com | AE64: 65572220 | AF64: Singapore | AG64: USD | AI64: 1 | AL64: 57 | AP64: 28.5 | AV64: 28.5 | AW64: 28.5 | BC64: 28.5 | BJ64: 0 | BQ64: 0 | BX64: 0 | CE64: 0 | CF64: 57 | CG64: 0 | CH64: 0 | CI64: 0 | CJ64: 0 | CK64: 0 | CL64: 57 | CM64: 1 | CS64: 1 | CT64: 1 | CZ64: 1 | DG64: 0 | DN64: 0 | DU64: 0 | EB64: 0 | EC64: 2 | ED64: 0 | EE64: 0 | EF64: 0 | EG64: 0 | EH64: 0 | EI64: 2 | EJ64: YES | EK64: NO | EL64: NO | EM64: NO | EN64: NO | EO64: NO | EP64: YES | EQ64: NO | ER64: NO | ES64: NO | ET64: NO | EU64: NO | EV64: NO | EW64: NO | EX64: NO | EY64: NO | EZ64: NO | FA64: NO | FB64: NO | FC64: NO | FD64: NO | FE64: NO | FF64: NO | FG64: NO | FH64: NO | FI64: NO | FJ64: NO | FK64: NO | FL64: NO | FM64: NO | FN64: NO | FO64: NO | FP64: NO | FQ64: NO | FR64: NO | FS64: NO | FZ64: 0 | GA64: 4 | GG64: 4 | GN64: 0 | GO64: 24.5 | GU64: 24.5 | HB64: 0 | HI64: 0 | HJ64: 28.5 | HP64: 28.5 | HX64: 0 | HY64: 57 | HZ64: 0 | IA64: 0 | IB64: 0 | IC64: 0 | ID64: 0 | IE64: 57 | IF64: 28.5 | IL64: 28.5 | IS64: 0 | IZ64: 0 | JG64: 0 | JH64: 28.5 | JN64: 28.5 | JO64: 57 | JP64: 0 | JQ64: 0 | JR64: 0 | JS64: 0 | JT64: 0 | JU64: 57 | JX64: 100 | KA64: 1 | KB64: 3 | KC64: 1 | KD64: START Asia Pacific: | KK64: 0 | KL64: 2 | KR64: 2 | KY64: 0 | KZ64: 12.25 | LF64: 12.25 | LM64: 0 | LT64: 0 | LU64: 14.25 | MA64: 14.25 | MI64: 0 | MJ64: 28.5 | MK64: 0 | ML64: 0 | MM64: 0 | MN64: 0 | MO64: 0 | MP64: 28.5 | MW64: 0 | MX64: 14.25 | ND64: 14.25 | NK64: 0 | NR64: 0 | NS64: 14.25 | NY64: 14.25 | NZ64: 28.5 | OA64: 0 | OB64: 0 | OC64: 0 | OD64: 0 | OE64: 0 | OF64: 28.5 | OG64: START Europe: | ON64: 0 | OO64: 2 | OU64: 2 | PB64: 0 | PC64: 12.25 | PI64: 12.25 | PP64: 0 | PW64: 0 | PX64: 14.25 | QD64: 14.25 | QL64: 0 | QM64: 28.5 | QN64: 0 | QO64: 0 | QP64: 0 | QQ64: 0 | QR64: 0 | QS64: 28.5 | QZ64: 0 | RA64: 14.25 | RG64: 14.25 | RN64: 0 | RU64: 0 | RV64: 14.25 | SB64: 14.25 | SC64: 28.5 | SD64: 0 | SE64: 0 | SF64: 0 | SG64: 0 | SH64: 0 | SI64: 28.5 | SJ64: START North America: | WM64: START Global: | AAP64: START SOUTH America: | AES64: START Africa:
A65: C9GEM564E | B65: INREV | C65: Tishman Speyer | P65: FALSE | Q65: FALSE | R65: FALSE | S65: FALSE | T65: FALSE | U65: FALSE | V65: 574 | W65: 43529.662 | X65: 196.17.100.228 | Y65: 2019 | Z65: INREV | AA65: Tishman Speyer | AB65: =VLOOKUP(MID(AD65,SEARCH("@",AD65,1),LEN(AD65)-SEARCH("@",AD65,1)+1),[2]Sheet1!$D:$F,3,FALSE) -> M636 | AD65: research@inrev.org | AF65: United States | AG65: USD | AI65: 1 | AL65: 2283 | AV65: 0 | BC65: 0 | BJ65: 0 | BQ65: 0 | BX65: 0 | CE65: 0 | CF65: 0 | CG65: 0 | CH65: 0 | CI65: 0 | CJ65: 0 | CK65: 0 | CL65: 0 | CS65: 0 | CZ65: 0 | DG65: 0 | DN65: 0 | DU65: 0 | EB65: 0 | EC65: 0 | ED65: 0 | EE65: 0 | EF65: 0 | EG65: 0 | EH65: 0 | EI65: 0 | EJ65: NO | EK65: NO | EL65: NO | EM65: NO | EN65: NO | EO65: NO | EP65: NO | EQ65: NO | ER65: NO | ES65: NO | ET65: NO | EU65: NO | EV65: NO | EW65: NO | EX65: NO | EY65: NO | EZ65: NO | FA65: NO | FB65: NO | FC65: NO | FD65: NO | FE65: NO | FF65: NO | FG65: NO | FH65: NO | FI65: NO | FJ65: NO | FK65: NO | FL65: NO | FM65: NO | FN65: NO | FO65: NO | FP65: NO | FQ65: NO | FR65: NO | FS65: NO | FZ65: 0 | GG65: 0 | GN65: 0 | GU65: 0 | HB65: 0 | HI65: 0 | HP65: 0 | HX65: 0 | HY65: 0 | HZ65: 0 | IA65: 0 | IB65: 0 | IC65: 0 | ID65: 0 | IE65: 0 | IL65: 0 | IS65: 0 | IZ65: 0 | JG65: 0 | JN65: 0 | JO65: 0 | JP65: 0 | JQ65: 0 | JR65: 0 | JS65: 0 | JT65: 0 | JU65: 0 | KC65: 1 | KD65: START Asia Pacific: | OG65: START Europe: | SJ65: START North America: | WM65: START Global: | AAP65: START SOUTH America: | AES65: START Africa:
A66: C9GJE907Z | B66: INREV | C66: Syntrus Achmea Real Estate & Finance (FM) | D66: asia | E66: 43529.642 | F66: europe | G66: 43529.648 | H66: northamerica | I66: 43529.642 | P66: TRUE | Q66: TRUE | R66: TRUE | S66: FALSE | T66: FALSE | U66: FALSE | V66: 585 | W66: 43531.674 | X66: 62.58.82.179 | Y66: 2019 | Z66: Syvia van der Schaaff | AA66: Syntrus Achmea Real Estate & Finance | AB66: =VLOOKUP(MID(AD66,SEARCH("@",AD66,1),LEN(AD66)-SEARCH("@",AD66,1)+1),[2]Sheet1!$D:$F,3,FALSE) -> M710 | AC66: Propositionmanager | AD66: sylvia.van.der.schaaff@achmeavastgoed.nl | AE66: + 31 630227164 | AF66: Netherlands | AG66: EUR | AI66: 1 | AL66: 1952 | AM66: 272 | AP66: 0 | AQ66: 0 | AR66: 16 | AT66: 0 | AU66: 0 | AV66: 16 | AW66: 272.1 | AX66: 816 | AY66: 24 | BA66: 0 | BB66: 799.9 | BC66: 1912 | BD66: 0 | BE66: 0 | BF66: 24 | BH66: 0 | BI66: 0 | BJ66: 24 | BQ66: 0 | BX66: 0 | CE66: 0 | CF66: 272.1 | CG66: 816 | CH66: 64 | CI66: 0 | CJ66: 0 | CK66: 799.9 | CL66: 1952 | CO66: 1 | CS66: 1 | CT66: 6 | CU66: 5 | CV66: 0 | CY66: 3 | CZ66: 14 | DC66: 1 | DG66: 1 | DN66: 0 | DU66: 0 | EB66: 0 | EC66: 6 | ED66: 5 | EE66: 2 | EF66: 0 | EG66: 0 | EH66: 3 | EI66: 16 | EJ66: NO | EK66: NO | EL66: YES | EM66: NO | EN66: NO | EO66: NO | EP66: YES | EQ66: YES | ER66: YES | ES66: NO | ET66: NO | EU66: YES | EV66: NO | EW66: NO | EX66: YES | EY66: NO | EZ66: NO | FA66: NO | FB66: NO | FC66: NO | FD66: NO | FE66: NO | FF66: NO | FG66: NO | FH66: NO | FI66: NO | FJ66: NO | FK66: NO | FL66: NO | FM66: NO | FN66: NO | FO66: NO | FP66: NO | FQ66: NO | FR66: NO | FS66: NO | FT66: 110.6 | FU66: 816 | FV66: 64 | FY66: 713.8 | FZ66: 1704.4 | GA66: 136.5 | GB66: 0 | GC66: 0 | GF66: 86.1 | GG66: 222.6 | GN66: 0 | GU66: 0 | HB66: 0 | HI66: 0 | HP66: 0 | HQ66: Other segment | HR66: 25 | HX66: 25 | HY66: 272.1 | HZ66: 816 | IA66: 64 | IB66: 0 | IC66: 0 | ID66: 799.9 | IE66: 1952 | IF66: 0 | IG66: 0 | IH66: 0 | IK66: 0 | IL66: 0 | IM66: 272.1 | IN66: 816 | IO66: 64 | IR66: 799.9 | IS66: 1952 | IT66: 0 | IU66: 0 | IV66: 0 | IY66: 0 | IZ66: 0 | JA66: 0 | JB66: 0 | JC66: 0 | JF66: 0 | JG66: 0 | JH66: 0 | JI66: 0 | JJ66: 0 | JM66: 0 | JN66: 0 | JO66: 272.1 | JP66: 816 | JQ66: 64 | JR66: 0 | JS66: 0 | JT66: 799.9 | JU66: 1952 | JV66: 0 | JW66: 0 | JX66: 100 | JZ66: 0 | KA66: 1 | KB66: 3 | KC66: 1 | KD66: START Asia Pacific: | KE66: 0 | KF66: 0 | KG66: 0 | KJ66: 0 | KK66: 0 | KL66: 0 | KM66: 0 | KN66: 0 | KQ66: 0 | KR66: 0 | KS66: 0 | KT66: 0 | KU66: 0 | KX66: 0 | KY66: 0 | KZ66: 0 | LA66: 0 | LB66: 0 | LE66: 0 | LF66: 0 | LG66: 0 | LH66: 0 | LI66: 0 | LL66: 0 | LM66: 0 | LN66: 0 | LO66: 0 | LS66: 0 | LT66: 0 | LU66: 0 | LV66: 0 | LW66: 0 | LZ66: 0 | MA66: 0 | MI66: 0 | MJ66: 0 | MK66: 0 | ML66: 0 | MM66: 0 | MN66: 0 | MO66: 0 | MP66: 0 | MQ66: 0 | MR66: 0 | MS66: 0 | MV66: 0 | MW66: 0 | MX66: 0 | MY66: 0 | MZ66: 16 | NC66: 0 | ND66: 16 | NE66: 0 | NF66: 0 | NG66: 0 | NJ66: 0 | NK66: 0 | NL66: 0 | NM66: 0 | NN66: 0 | NQ66: 0 | NR66: 0 | NS66: 0 | NT66: 0 | NU66: 0 | NX66: 0 | NY66: 0 | NZ66: 0 | OA66: 0 | OB66: 16 | OC66: 0 | OD66: 0 | OE66: 0 | OF66: 16 | OG66: START Europe: | ON66: 0 | OU66: 0 | PB66: 0 | PI66: 0 | PP66: 0 | PW66: 0 | QD66: 0 | QL66: 0 | QM66: 0 | QN66: 0 | QO66: 0 | QP66: 0 | QQ66: 0 | QR66: 0 | QS66: 0 | QV66: 24 | QZ66: 24 | RG66: 0 | RN66: 0 | RU66: 0 | SB66: 0 | SC66: 0 | SD66: 0 | SE66: 24 | SF66: 0 | SG66: 0 | SH66: 0 | SI66: 24 | SJ66: START North America: | SQ66: 0 | SX66: 0 | TE66: 0 | TL66: 0 | TS66: 0 | TZ66: 0 | UG66: 0 | UO66: 0 | UP66: 0 | UQ66: 0 | UR66: 0 | US66: 0 | UT66: 0 | UU66: 0 | UV66: 0 | VC66: 0 | VJ66: 0 | VM66: 24 | VQ66: 24 | VX66: 0 | WE66: 0 | WF66: 0 | WG66: 0 | WH66: 24 | WI66: 0 | WJ66: 0 | WK66: 0 | WL66: 24 | WM66: START Global: | AAP66: START SOUTH America: | AES66: START Africa:
A67: C9GMK908Q | B67: INREV | C67: Syntrus Achmea Real Estate & Finance (FoF) | P67: TRUE | Q67: TRUE | R67: TRUE | S67: FALSE | T67: FALSE | U67: FALSE | V67: 639 | W67: 43528.554 | X67: 62.58.82.179 | Y67: 2019 | Z67: Sylvia van der Schaaff | AA67: Syntrus Achmea Real Estate & Finance | AB67: M710 | AC67: Propositionmanager | AD67: sylvia.van.der.schaaff | AE67: 00 31+630227164 | AF67: Netherlands | AG67: EUR | AI67: 1 | AL67: 179 | AT67: 26 | AV67: 26 | BA67: 110 | BC67: 110 | BH67: 43 | BJ67: 43 | BQ67: 0 | BX67: 0 | CE67: 0 | CF67: 0 | CG67: 0 | CH67: 0 | CI67: 0 | CJ67: 179 | CK67: 0 | CL67: 179 | CQ67: 1 | CS67: 1 | CX67: 1 | CZ67: 1 | DE67: 1 | DG67: 1 | DN67: 0 | DU67: 0 | EB67: 0 | EC67: 0 | ED67: 0 | EE67: 0 | EF67: 0 | EG67: 3 | EH67: 0 | EI67: 3 | EJ67: NO | EK67: NO | EL67: NO | EM67: NO | EN67: YES | EO67: NO | EP67: NO | EQ67: NO | ER67: NO | ES67: NO | ET67: YES | EU67: NO | EV67: NO | EW67: NO | EX67: NO | EY67: NO | EZ67: YES | FA67: NO | FB67: NO | FC67: NO | FD67: NO | FE67: NO | FF67: NO | FG67: NO | FH67: NO | FI67: NO | FJ67: NO | FK67: NO | FL67: NO | FM67: NO | FN67: NO | FO67: NO | FP67: NO | FQ67: NO | FR67: NO | FS67: NO | FZ67: 0 | GG67: 0 | GN67: 0 | GU67: 0 | HB67: 0 | HI67: 0 | HP67: 0 | HX67: 0 | HY67: 0 | HZ67: 0 | IA67: 0 | IB67: 0 | IC67: 0 | ID67: 0 | IE67: 0 | IL67: 0 | IS67: 0 | IZ67: 0 | JG67: 0 | JN67: 0 | JO67: 0 | JP67: 0 | JQ67: 0 | JR67: 0 | JS67: 0 | JT67: 0 | JU67: 0 | JX67: 100 | KA67: 1 | KB67: 3 | KC67: 1 | KD67: START Asia Pacific: | OG67: START Europe: | SJ67: START North America: | WM67: START Global: | AAP67: START SOUTH America: | AES67: START Africa:
A68: C9GMZ690D | B68: NCREIF | C68: Sarofim Realty Advisors | P68: FALSE | Q68: FALSE | R68: TRUE | S68: FALSE | T68: FALSE | U68: FALSE | V68: 777 | W68: 43516.83 | X68: 216.74.249.19 | Y68: 2019 | Z68: Lisa Wallis | AA68: Sarofim Realty Advisors Co. | AB68: =VLOOKUP(MID(AD68,SEARCH("@",AD68,1),LEN(AD68)-SEARCH("@",AD68,1)+1),[2]Sheet1!$D:$F,3,FALSE) -> NC003 | AC68: Portfolio Controller | AD68: lwallis@sraco.com | AE68: 214-692-4266 | AF68: United States | AG68: USD | AI68: 1 | AL68: 350 | AM68: 350 | AN68: 10.6 | AO68: 10.6 | AV68: 0 | BC68: 0 | BE68: 350 | BJ68: 350 | BQ68: 0 | BX68: 0 | CE68: 0 | CF68: 0 | CG68: 350 | CH68: 0 | CI68: 0 | CJ68: 0 | CK68: 0 | CL68: 350 | CS68: 0 | CZ68: 0 | DB68: 2 | DG68: 2 | DN68: 0 | DU68: 0 | EB68: 0 | EC68: 0 | ED68: 2 | EE68: 0 | EF68: 0 | EG68: 0 | EH68: 0 | EI68: 2 | EJ68: NO | EK68: NO | EL68: NO | EM68: NO | EN68: NO | EO68: NO | EP68: NO | EQ68: NO | ER68: NO | ES68: NO | ET68: NO | EU68: NO | EV68: NO | EW68: YES | EX68: NO | EY68: NO | EZ68: NO | FA68: NO | FB68: NO | FC68: NO | FD68: NO | FE68: NO | FF68: NO | FG68: NO | FH68: NO | FI68: NO | FJ68: NO | FK68: NO | FL68: NO | FM68: NO | FN68: NO | FO68: NO | FP68: NO | FQ68: NO | FR68: NO | FS68: NO | FU68: 100 | FZ68: 100 | GG68: 0 | GN68: 0 | GP68: 250 | GU68: 250 | HB68: 0 | HI68: 0 | HP68: 0 | HX68: 0 | HY68: 0 | HZ68: 350 | IA68: 0 | IB68: 0 | IC68: 0 | ID68: 0 | IE68: 350 | IL68: 0 | IS68: 0 | IU68: 350 | IZ68: 350 | JG68: 0 | JN68: 0 | JO68: 0 | JP68: 350 | JQ68: 0 | JR68: 0 | JS68: 0 | JT68: 0 | JU68: 350 | JX68: 100 | KA68: 1 | KB68: 3 | KC68: 1 | KD68: START Asia Pacific: | OG68: START Europe: | SJ68: START North America: | WM68: START Global: | AAP68: START SOUTH America: | AES68: START Africa:
A69: C9GQG881Q | B69: ANREV | C69: Seven Seas Advisors Co. LTD. | P69: FALSE | Q69: TRUE | R69: FALSE | S69: FALSE | T69: FALSE | U69: FALSE | V69: 646 | W69: 43489.978 | X69: 210.138.169.29 | Y69: 2019 | Z69: Minoru Yonekura | AA69: Seven Seas Advisors Co., LTD. | AB69: =VLOOKUP(MID(AD69,SEARCH("@",AD69,1),LEN(AD69)-SEARCH("@",AD69,1)+1),[2]Sheet1!$D:$F,3,FALSE) -> M0235 | AD69: minoru.yonekura@sevenseas-adv.com | AE69: +813 3539 1491 | AF69: Japan | AG69: JPY | AI69: 1 | AL69: 10000 | AM69: 10000 | AN69: 10000 | AO69: 10000 | AQ69: 10000 | AV69: 10000 | BC69: 0 | BJ69: 0 | BQ69: 0 | BX69: 0 | CE69: 0 | CF69: 0 | CG69: 10000 | CH69: 0 | CI69: 0 | CJ69: 0 | CK69: 0 | CL69: 10000 | CN69: 3 | CS69: 3 | CZ69: 0 | DG69: 0 | DN69: 0 | DU69: 0 | EB69: 0 | EC69: 0 | ED69: 3 | EE69: 0 | EF69: 0 | EG69: 0 | EH69: 0 | EI69: 3 | EJ69: NO | EK69: YES | EL69: NO | EM69: NO | EN69: NO | EO69: NO | EP69: NO | EQ69: NO | ER69: NO | ES69: NO | ET69: NO | EU69: NO | EV69: NO | EW69: NO | EX69: NO | EY69: NO | EZ69: NO | FA69: NO | FB69: NO | FC69: NO | FD69: NO | FE69: NO | FF69: NO | FG69: NO | FH69: NO | FI69: NO | FJ69: NO | FK69: NO | FL69: NO | FM69: NO | FN69: NO | FO69: NO | FP69: NO | FQ69: NO | FR69: NO | FS69: NO | FZ69: 0 | GG69: 0 | GN69: 0 | GU69: 0 | HB69: 0 | HD69: 10000 | HI69: 10000 | HP69: 0 | HX69: 0 | HY69: 0 | HZ69: 10000 | IA69: 0 | IB69: 0 | IC69: 0 | ID69: 0 | IE69: 10000 | IG69: 10000 | IL69: 10000 | IS69: 0 | IZ69: 0 | JG69: 0 | JN69: 0 | JO69: 0 | JP69: 10000 | JQ69: 0 | JR69: 0 | JS69: 0 | JT69: 0 | JU69: 10000 | JX69: 100 | KA69: 1 | KB69: 3 | KC69: 2 | KD69: START Asia Pacific: | OG69: START Europe: | SJ69: START North America: | WM69: START Global: | AAP69: START SOUTH America: | AES69: START Africa:
A70: C9GUT351T | B70: INREV | C70: Bouwinvest Real Estate Investors | P70: FALSE | Q70: FALSE | R70: FALSE | S70: TRUE | T70: FALSE | U70: FALSE | V70: 589 | W70: 43517.594 | X70: 185.48.69.2 | Y70: 2019 | Z70: Renata Renckens-Joor | AA70: Bouwinvest Real Estate Investors | AB70: =VLOOKUP(MID(AD70,SEARCH("@",AD70,1),LEN(AD70)-SEARCH("@",AD70,1)+1),[2]Sheet1!$D:$F,3,FALSE) -> M660 | AC70: Corporate Marketing & Communications Associate | AD70: r.joor@bouwinvest.nl | AE70: 06-10385347 | AF70: Netherlands | AG70: EUR | AI70: 1 | AL70: 759 | AM70: 759 | AN70: 469 | AO70: 469 | AV70: 0 | BC70: 0 | BJ70: 0 | BK70: 561 | BL70: 198 | BQ70: 759 | BX70: 0 | CE70: 0 | CF70: 561 | CG70: 198 | CH70: 0 | CI70: 0 | CJ70: 0 | CK70: 0 | CL70: 759 | CS70: 0 | CZ70: 0 | DG70: 0 | DH70: 3 | DI70: 1 | DN70: 4 | DU70: 0 | EB70: 0 | EC70: 3 | ED70: 1 | EE70: 0 | EF70: 0 | EG70: 0 | EH70: 0 | EI70: 4 | EJ70: NO | EK70: NO | EL70: NO | EM70: NO | EN70: NO | EO70: NO | EP70: NO | EQ70: NO | ER70: NO | ES70: NO | ET70: NO | EU70: NO | EV70: NO | EW70: NO | EX70: NO | EY70: NO | EZ70: NO | FA70: NO | FB70: YES | FC70: YES | FD70: NO | FE70: NO | FF70: NO | FG70: NO | FH70: NO | FI70: NO | FJ70: NO | FK70: NO | FL70: NO | FM70: NO | FN70: NO | FO70: NO | FP70: NO | FQ70: NO | FR70: NO | FS70: NO | FT70: 536 | FU70: 198 | FZ70: 734 | GA70: 25 | GG70: 25 | GN70: 0 | GU70: 0 | HB70: 0 | HI70: 0 | HP70: 0 | HX70: 0 | HY70: 561 | HZ70: 198 | IA70: 0 | IB70: 0 | IC70: 0 | ID70: 0 | IE70: 759 | IL70: 0 | IM70: 561 | IN70: 198 | IS70: 759 | IZ70: 0 | JG70: 0 | JN70: 0 | JO70: 561 | JP70: 198 | JQ70: 0 | JR70: 0 | JS70: 0 | JT70: 0 | JU70: 759 | JX70: 100 | KA70: 2 | KB70: 3 | KC70: 1 | KD70: START Asia Pacific: | OG70: START Europe: | SJ70: START North America: | WM70: START Global: | AAP70: START SOUTH America: | AES70: START Africa:
A71: C9GWV435M | B71: INREV | C71: Hermes Real Estate Investment Management Limited | P71: TRUE | Q71: FALSE | R71: FALSE | S71: FALSE | T71: FALSE | U71: FALSE | V71: 821 | W71: 43531.403 | X71: 154.47.76.148 | Y71: 2019 | Z71: Ricky Prior | AA71: Hermes Investment Management | AB71: =VLOOKUP(MID(AD71,SEARCH("@",AD71,1),LEN(AD71)-SEARCH("@",AD71,1)+1),[2]Sheet1!$D:$F,3,FALSE) -> M136 | AC71: Consultant Database Manager | AD71: Ricky.Prior@hermes-investment.com | AF71: United Kingdom | AG71: GBP | AI71: 1 | AL71: 7.6 | AM71: 7.6 | AN71: 7.6 | AO71: 7.6 | AV71: 0 | AW71: 7.6 | BC71: 7.6 | BJ71: 0 | BQ71: 0 | BX71: 0 | CE71: 0 | CF71: 7.6 | CG71: 0 | CH71: 0 | CI71: 0 | CJ71: 0 | CK71: 0 | CL71: 7.6 | CS71: 0 | CT71: 1 | CZ71: 1 | DG71: 0 | DN71: 0 | DU71: 0 | EB71: 0 | EC71: 1 | ED71: 0 | EE71: 0 | EF71: 0 | EG71: 0 | EH71: 0 | EI71: 1 | EJ71: NO | EK71: NO | EL71: NO | EM71: NO | EN71: NO | EO71: NO | EP71: YES | EQ71: NO | ER71: NO | ES71: NO | ET71: NO | EU71: NO | EV71: NO | EW71: NO | EX71: NO | EY71: NO | EZ71: NO | FA71: NO | FB71: NO | FC71: NO | FD71: NO | FE71: NO | FF71: NO | FG71: NO | FH71: NO | FI71: NO | FJ71: NO | FK71: NO | FL71: NO | FM71: NO | FN71: NO | FO71: NO | FP71: NO | FQ71: NO | FR71: NO | FS71: NO | FT71: 7.6 | FZ71: 7.6 | GG71: 0 | GN71: 0 | GU71: 0 | HB71: 0 | HI71: 0 | HP71: 0 | HX71: 0 | HY71: 7.6 | HZ71: 0 | IA71: 0 | IB71: 0 | IC71: 0 | ID71: 0 | IE71: 7.6 | IL71: 0 | IM71: 7.6 | IS71: 7.6 | IZ71: 0 | JG71: 0 | JN71: 0 | JO71: 7.6 | JP71: 0 | JQ71: 0 | JR71: 0 | JS71: 0 | JT71: 0 | JU71: 7.6 | JX71: 60 | JY71: Investment Manager | JZ71: 40 | KA71: 3 | KB71: 3 | KC71: 2 | KD71: START Asia Pacific: | OG71: START Europe: | SJ71: START North America: | WM71: START Global: | AAP71: START SOUTH America: | AES71: START Africa:
A72: C9GZV892T | B72: ANREV | C72: Tokyo Tatemono Investment Advisors Co., Ltd. | P72: FALSE | Q72: TRUE | R72: FALSE | S72: FALSE | T72: FALSE | U72: FALSE | V72: 536 | W72: 43510.069 | X72: 221.186.68.97 | Y72: 2019 | Z72: Yasuhide Nakai | AA72: Tokyo Tatemono Investment Advisor Co.,Ltd. | AB72: =VLOOKUP(MID(AD72,SEARCH("@",AD72,1),LEN(AD72)-SEARCH("@",AD72,1)+1),[2]Sheet1!$D:$F,3,FALSE) -> M0239 | AC72: Senior Manager | AD72: nakaiys@tt-ia.com | AE72: =81-3-3548-3351 -> -6821 | AF72: Japan | AG72: JPY | AI72: 1 | AM72: 3413 | AO72: 3413 | AP72: 3413 | AV72: 3413 | BC72: 0 | BJ72: 0 | BQ72: 0 | BX72: 0 | CE72: 0 | CF72: 3413 | CG72: 0 | CH72: 0 | CI72: 0 | CJ72: 0 | CK72: 0 | CL72: 3413 | CM72: 1 | CS72: 1 | CZ72: 0 | DG72: 0 | DN72: 0 | DU72: 0 | EB72: 0 | EC72: 1 | ED72: 0 | EE72: 0 | EF72: 0 | EG72: 0 | EH72: 0 | EI72: 1 | EJ72: YES | EK72: NO | EL72: NO | EM72: NO | EN72: NO | EO72: NO | EP72: NO | EQ72: NO | ER72: NO | ES72: NO | ET72: NO | EU72: NO | EV72: NO | EW72: NO | EX72: NO | EY72: NO | EZ72: NO | FA72: NO | FB72: NO | FC72: NO | FD72: NO | FE72: NO | FF72: NO | FG72: NO | FH72: NO | FI72: NO | FJ72: NO | FK72: NO | FL72: NO | FM72: NO | FN72: NO | FO72: NO | FP72: NO | FQ72: NO | FR72: NO | FS72: NO | FT72: 519 | FZ72: 519 | GG72: 0 | GN72: 0 | GU72: 0 | HB72: 0 | HI72: 0 | HP72: 0 | HQ72: Corporations/Banks | HR72: 2894 | HX72: 2894 | HY72: 3413 | HZ72: 0 | IA72: 0 | IB72: 0 | IC72: 0 | ID72: 0 | IE72: 3413 | IF72: 3413 | IL72: 3413 | IS72: 0 | IZ72: 0 | JG72: 0 | JN72: 0 | JO72: 3413 | JP72: 0 | JQ72: 0 | JR72: 0 | JS72: 0 | JT72: 0 | JU72: 3413 | JV72: 100 | KA72: 1 | KB72: 1 | KC72: 2 | KD72: START Asia Pacific: | OG72: START Europe: | SJ72: START North America: | WM72: START Global: | AAP72: START SOUTH America: | AES72: START Africa:
A73: C9HHA359Q | B73: INREV | C73: Capman Real Estate | P73: TRUE | Q73: FALSE | R73: FALSE | S73: FALSE | T73: FALSE | U73: FALSE | V73: 824 | W73: 43529.736 | X73: 212.161.80.4 | Y73: 2019 | Z73: Nigel Pedroz | AA73: CapMan Real Estate | AB73: =VLOOKUP(MID(AD73,SEARCH("@",AD73,1),LEN(AD73)-SEARCH("@",AD73,1)+1),[2]Sheet1!$D:$F,3,FALSE) -> M168 | AC73: Partner | AD73: nigel.pedroz@capman.com | AE73: 7796853569 | AF73: Finland | AG73: EUR | AI73: 1 | AL73: 260 | AM73: 260 | AN73: 240 | AO73: 240 | AV73: 0 | AW73: 50 | AX73: 210 | BC73: 260 | BJ73: 0 | BQ73: 0 | BX73: 0 | CE73: 0 | CF73: 50 | CG73: 210 | CH73: 0 | CI73: 0 | CJ73: 0 | CK73: 0 | CL73: 260 | CS73: 0 | CT73: 1 | CU73: 1 | CZ73: 2 | DG73: 0 | DN73: 0 | DU73: 0 | EB73: 0 | EC73: 1 | ED73: 1 | EE73: 0 | EF73: 0 | EG73: 0 | EH73: 0 | EI73: 2 | EJ73: NO | EK73: NO | EL73: NO | EM73: NO | EN73: NO | EO73: NO | EP73: YES | EQ73: YES | ER73: NO | ES73: NO | ET73: NO | EU73: NO | EV73: NO | EW73: NO | EX73: NO | EY73: NO | EZ73: NO | FA73: NO | FB73: NO | FC73: NO | FD73: NO | FE73: NO | FF73: NO | FG73: NO | FH73: NO | FI73: NO | FJ73: NO | FK73: NO | FL73: NO | FM73: NO | FN73: NO | FO73: NO | FP73: NO | FQ73: NO | FR73: NO | FS73: NO | FU73: 210 | FZ73: 210 | GG73: 0 | GN73: 0 | GU73: 0 | GV73: 50 | HB73: 50 | HI73: 0 | HP73: 0 | HX73: 0 | HY73: 50 | HZ73: 210 | IA73: 0 | IB73: 0 | IC73: 0 | ID73: 0 | IE73: 260 | IL73: 0 | IM73: 50 | IN73: 210 | IS73: 260 | IZ73: 0 | JG73: 0 | JN73: 0 | JO73: 50 | JP73: 210 | JQ73: 0 | JR73: 0 | JS73: 0 | JT73: 0 | JU73: 260 | JV73: 0 | JW73: 0 | JX73: 100 | KA73: 1 | KB73: 2 | KC73: 1 | KD73: START Asia Pacific: | OG73: START Europe: | SJ73: START North America: | WM73: START Global: | AAP73: START SOUTH America: | AES73: START Africa:
A74: C9HHX335W | B74: INREV | C74: Arminius Funds Management Limited | P74: TRUE | Q74: FALSE | R74: FALSE | S74: FALSE | T74: FALSE | U74: FALSE | V74: 800 | W74: 43523.367 | X74: 217.250.141.249 | Y74: 2019 | Z74: Ilka Völker | AA74: Arminius Kapitalgesellschaft mbH / Arminius Group | AB74: =VLOOKUP(MID(AD74,SEARCH("@",AD74,1),LEN(AD74)-SEARCH("@",AD74,1)+1),[2]Sheet1!$D:$F,3,FALSE) -> M451 | AC74: Senior Finance Manager | AD74: ivoelker@arminiuskapital.de | AE74: 69247515150 | AF74: Germany | AG74: EUR | AI74: 1 | AL74: 217.5 | AM74: 217.5 | AN74: 203.9 | AO74: 203.9 | AV74: 0 | AW74: 57 | AX74: 160.5 | BC74: 217.5 | BJ74: 0 | BQ74: 0 | BX74: 0 | CE74: 0 | CF74: 57 | CG74: 160.5 | CH74: 0 | CI74: 0 | CJ74: 0 | CK74: 0 | CL74: 217.5 | CS74: 0 | CT74: 1 | CU74: 1 | CZ74: 2 | DG74: 0 | DN74: 0 | DU74: 0 | EB74: 0 | EC74: 1 | ED74: 1 | EE74: 0 | EF74: 0 | EG74: 0 | EH74: 0 | EI74: 2 | EJ74: NO | EK74: NO | EL74: NO | EM74: NO | EN74: NO | EO74: NO | EP74: YES | EQ74: YES | ER74: NO | ES74: NO | ET74: NO | EU74: NO | EV74: NO | EW74: NO | EX74: NO | EY74: NO | EZ74: NO | FA74: NO | FB74: NO | FC74: NO | FD74: NO | FE74: NO | FF74: NO | FG74: NO | FH74: NO | FI74: NO | FJ74: NO | FK74: NO | FL74: NO | FM74: NO | FN74: NO | FO74: NO | FP74: NO | FQ74: NO | FR74: NO | FS74: NO | FU74: 160.5 | FZ74: 160.5 | GA74: 57 | GG74: 57 | GN74: 0 | GU74: 0 | HB74: 0 | HI74: 0 | HP74: 0 | HX74: 0 | HY74: 57 | HZ74: 160.5 | IA74: 0 | IB74: 0 | IC74: 0 | ID74: 0 | IE74: 217.5 | IL74: 0 | IM74: 57 | IN74: 160.5 | IS74: 217.5 | IZ74: 0 | JG74: 0 | JN74: 0 | JO74: 57 | JP74: 160.5 | JQ74: 0 | JR74: 0 | JS74: 0 | JT74: 0 | JU74: 217.5 | JX74: 100 | KA74: 1 | KB74: 1 | KC74: 1 | KD74: START Asia Pacific: | OG74: START Europe: | SJ74: START North America: | WM74: START Global: | AAP74: START SOUTH America: | AES74: START Africa:
A75: C9HRN771D | B75: ANREV | C75: MaxCap Group | P75: FALSE | Q75: FALSE | R75: FALSE | S75: FALSE | T75: FALSE | U75: FALSE | V75: 645 | W75: 43516.469 | X75: 61.69.86.22 | Y75: 2019 | Z75: Chris van Beek | AA75: MaxCap Group Pty. Ltd. | AB75: =VLOOKUP(MID(AD75,SEARCH("@",AD75,1),LEN(AD75)-SEARCH("@",AD75,1)+1),[2]Sheet1!$D:$F,3,FALSE) -> M0263 | AC75: Distribution Director | AD75: chris.vanbeek@maxcapgroup.com.au | AE75: +61 2 8397 7200 | AF75: Australia | AG75: AUD | AI75: 1 | AV75: 0 | BC75: 0 | BJ75: 0 | BQ75: 0 | BX75: 0 | CE75: 0 | CF75: 0 | CG75: 0 | CH75: 0 | CI75: 0 | CJ75: 0 | CK75: 0 | CL75: 0 | CS75: 0 | CZ75: 0 | DG75: 0 | DN75: 0 | DU75: 0 | EB75: 0 | EC75: 0 | ED75: 0 | EE75: 0 | EF75: 0 | EG75: 0 | EH75: 0 | EI75: 0 | EJ75: NO | EK75: NO | EL75: NO | EM75: NO | EN75: NO | EO75: NO | EP75: NO | EQ75: NO | ER75: NO | ES75: NO | ET75: NO | EU75: NO | EV75: NO | EW75: NO | EX75: NO | EY75: NO | EZ75: NO | FA75: NO | FB75: NO | FC75: NO | FD75: NO | FE75: NO | FF75: NO | FG75: NO | FH75: NO | FI75: NO | FJ75: NO | FK75: NO | FL75: NO | FM75: NO | FN75: NO | FO75: NO | FP75: NO | FQ75: NO | FR75: NO | FS75: NO | FZ75: 0 | GG75: 0 | GN75: 0 | GU75: 0 | HB75: 0 | HI75: 0 | HP75: 0 | HX75: 0 | HY75: 0 | HZ75: 0 | IA75: 0 | IB75: 0 | IC75: 0 | ID75: 0 | IE75: 0 | IL75: 0 | IS75: 0 | IZ75: 0 | JG75: 0 | JN75: 0 | JO75: 0 | JP75: 0 | JQ75: 0 | JR75: 0 | JS75: 0 | JT75: 0 | JU75: 0 | JV75: 0 | JW75: 50 | JX75: 50 | KA75: 1 | KB75: 1 | KC75: 1 | KD75: START Asia Pacific: | OG75: START Europe: | SJ75: START North America: | WM75: START Global: | AAP75: START SOUTH America: | AES75: START Africa:
A76: C9HTB891X | B76: ANREV | C76: Mitsubishi UFJ Trust and Banking Corporation | P76: FALSE | Q76: TRUE | R76: FALSE | S76: FALSE | T76: FALSE | U76: FALSE | V76: 586 | W76: 43515.341 | X76: 103.9.96.227 | Y76: 2019 | Z76: Hiroshi Ushio | AA76: Mitsubishi UFJ Trust and Banking Corporation | AB76: =VLOOKUP(MID(AD76,SEARCH("@",AD76,1),LEN(AD76)-SEARCH("@",AD76,1)+1),[2]Sheet1!$D:$F,3,FALSE) -> M0232 | AC76: Assistant Manager | AD76: hiroshi_ushio@tr.mufg.jp | AE76: =81-3-6250-4616 -> -10788 | AF76: Japan | AG76: JPY | AI76: 1 | AL76: 107913 | AM76: 107913 | AN76: 107913 | AO76: 107913 | AQ76: 107913 | AV76: 107913 | BC76: 0 | BJ76: 0 | BQ76: 0 | BX76: 0 | CE76: 0 | CF76: 0 | CG76: 107913 | CH76: 0 | CI76: 0 | CJ76: 0 | CK76: 0 | CL76: 107913 | CN76: 6 | CS76: 6 | CZ76: 0 | DG76: 0 | DN76: 0 | DU76: 0 | EB76: 0 | EC76: 0 | ED76: 6 | EE76: 0 | EF76: 0 | EG76: 0 | EH76: 0 | EI76: 6 | EJ76: NO | EK76: YES | EL76: NO | EM76: NO | EN76: NO | EO76: NO | EP76: NO | EQ76: NO | ER76: NO | ES76: NO | ET76: NO | EU76: NO | EV76: NO | EW76: NO | EX76: NO | EY76: NO | EZ76: NO | FA76: NO | FB76: NO | FC76: NO | FD76: NO | FE76: NO | FF76: NO | FG76: NO | FH76: NO | FI76: NO | FJ76: NO | FK76: NO | FL76: NO | FM76: NO | FN76: NO | FO76: NO | FP76: NO | FQ76: NO | FR76: NO | FS76: NO | FU76: 6380 | FZ76: 6380 | GB76: 86148 | GG76: 86148 | GN76: 0 | GU76: 0 | HB76: 0 | HI76: 0 | HP76: 0 | HQ76: Financial Institutions | HS76: 15385 | HX76: 15385 | HY76: 0 | HZ76: 107913 | IA76: 0 | IB76: 0 | IC76: 0 | ID76: 0 | IE76: 107913 | IG76: 107913 | IL76: 107913 | IS76: 0 | IZ76: 0 | JG76: 0 | JN76: 0 | JO76: 0 | JP76: 107913 | JQ76: 0 | JR76: 0 | JS76: 0 | JT76: 0 | JU76: 107913 | JX76: 100 | KA76: 2 | KB76: 3 | KC76: 1 | KD76: START Asia Pacific: | OG76: START Europe: | SJ76: START North America: | WM76: START Global: | AAP76: START SOUTH America: | AES76: START Africa:
A77: C9HVL454K | B77: INREV | C77: Jamestown US - Immobilien GmbH | P77: FALSE | Q77: FALSE | R77: TRUE | S77: FALSE | T77: FALSE | U77: FALSE | V77: 781 | W77: 43517.41 | X77: 89.1.66.245 | Y77: 2019 | Z77: klaus-dieter schmidt | AA77: jamestown | AB77: =VLOOKUP(MID(AD77,SEARCH("@",AD77,1),LEN(AD77)-SEARCH("@",AD77,1)+1),[2]Sheet1!$D:$F,3,FALSE) -> M551 | AC77: managing director | AD77: schmidtkd@jamestown.de | AE77: 1622040521 | AF77: United States | AG77: USD | AI77: 1 | AL77: 250 | AM77: 250 | AN77: 0 | AO77: 0 | AV77: 0 | BC77: 0 | BD77: 100 | BE77: 150 | BJ77: 250 | BQ77: 0 | BX77: 0 | CE77: 0 | CF77: 100 | CG77: 150 | CH77: 0 | CI77: 0 | CJ77: 0 | CK77: 0 | CL77: 250 | CS77: 0 | CZ77: 0 | DA77: 1 | DB77: 1 | DG77: 2 | DN77: 0 | DU77: 0 | EB77: 0 | EC77: 1 | ED77: 1 | EE77: 0 | EF77: 0 | EG77: 0 | EH77: 0 | EI77: 2 | EJ77: NO | EK77: NO | EL77: NO | EM77: NO | EN77: NO | EO77: NO | EP77: NO | EQ77: NO | ER77: NO | ES77: NO | ET77: NO | EU77: NO | EV77: YES | EW77: YES | EX77: NO | EY77: NO | EZ77: NO | FA77: NO | FB77: NO | FC77: NO | FD77: NO | FE77: NO | FF77: NO | FG77: NO | FH77: NO | FI77: NO | FJ77: NO | FK77: NO | FL77: NO | FM77: NO | FN77: NO | FO77: NO | FP77: NO | FQ77: NO | FR77: NO | FS77: NO | FT77: 100 | FU77: 150 | FZ77: 250 | GG77: 0 | GN77: 0 | GU77: 0 | HB77: 0 | HI77: 0 | HP77: 0 | HX77: 0 | HY77: 100 | HZ77: 150 | IA77: 0 | IB77: 0 | IC77: 0 | ID77: 0 | IE77: 250 | IL77: 0 | IN77: 150 | IS77: 150 | IT77: 100 | IZ77: 100 | JG77: 0 | JN77: 0 | JO77: 100 | JP77: 150 | JQ77: 0 | JR77: 0 | JS77: 0 | JT77: 0 | JU77: 250 | JW77: 100 | KA77: 1 | KB77: 3 | KC77: 1 | KD77: START Asia Pacific: | OG77: START Europe: | SJ77: START North America: | WM77: START Global: | AAP77: START SOUTH America: | AES77: START Africa:
A78: C9HVL889W | B78: ANREV | C78: ARCH Capital Management Co Ltd | P78: FALSE | Q78: TRUE | R78: FALSE | S78: FALSE | T78: FALSE | U78: FALSE | V78: 658 | W78: 43529.129 | X78: 101.78.165.217 | Y78: 2019 | Z78: Loretta Li | AA78: ARCH Capital Management Co Ltd | AB78: =VLOOKUP(MID(AD78,SEARCH("@",AD78,1),LEN(AD78)-SEARCH("@",AD78,1)+1),[2]Sheet1!$D:$F,3,FALSE) -> M421 | AC78: Finance Director | AD78: lli@archcapital.net | AF78: Hong Kong | AG78: USD | AI78: 1 | AL78: 170 | AM78: 170 | AN78: 110 | AO78: 110 | AP78: 170 | AV78: 170 | BC78: 0 | BJ78: 0 | BQ78: 0 | BX78: 0 | CE78: 0 | CF78: 170 | CG78: 0 | CH78: 0 | CI78: 0 | CJ78: 0 | CK78: 0 | CL78: 170 | CM78: 1 | CS78: 1 | CZ78: 0 | DG78: 0 | DN78: 0 | DU78: 0 | EB78: 0 | EC78: 1 | ED78: 0 | EE78: 0 | EF78: 0 | EG78: 0 | EH78: 0 | EI78: 1 | EJ78: YES | EK78: NO | EL78: NO | EM78: NO | EN78: NO | EO78: NO | EP78: NO | EQ78: NO | ER78: NO | ES78: NO | ET78: NO | EU78: NO | EV78: NO | EW78: NO | EX78: NO | EY78: NO | EZ78: NO | FA78: NO | FB78: NO | FC78: NO | FD78: NO | FE78: NO | FF78: NO | FG78: NO | FH78: NO | FI78: NO | FJ78: NO | FK78: NO | FL78: NO | FM78: NO | FN78: NO | FO78: NO | FP78: NO | FQ78: NO | FR78: NO | FS78: NO | FT78: 51 | FZ78: 51 | GG78: 0 | GN78: 0 | GU78: 0 | HB78: 0 | HI78: 0 | HJ78: 15 | HP78: 15 | HQ78: Financial institution and Corporate | HR78: 104 | HX78: 104 | HY78: 170 | HZ78: 0 | IA78: 0 | IB78: 0 | IC78: 0 | ID78: 0 | IE78: 170 | IF78: 119 | IL78: 119 | IS78: 0 | IT78: 51 | IZ78: 51 | JG78: 0 | JN78: 0 | JO78: 170 | JP78: 0 | JQ78: 0 | JR78: 0 | JS78: 0 | JT78: 0 | JU78: 170 | JX78: 100 | KA78: 3 | KB78: 3 | KC78: 2 | KD78: START Asia Pacific: | OG78: START Europe: | SJ78: START North America: | WM78: START Global: | AAP78: START SOUTH America: | AES78: START Africa:
A79: C9HVP546A | B79: INREV | C79: Swiss Finance & Property | P79: TRUE | Q79: TRUE | R79: TRUE | S79: FALSE | T79: FALSE | U79: FALSE | V79: 795 | W79: 43521.459 | X79: 212.25.22.162 | Y79: 2019 | Z79: Frederik De Block | AA79: Swiss Finance & Property | AB79: =VLOOKUP(MID(AD79,SEARCH("@",AD79,1),LEN(AD79)-SEARCH("@",AD79,1)+1),[2]Sheet1!$D:$F,3,FALSE) -> M03114 | AC79: Senior Portfolio Manager | AD79: deblock@sfp.ch | AE79: +41 433441283 | AF79: Switzerland | AG79: CHF | AI79: 1 | AL79: 1011.1 | AM79: 55.5 | AN79: 900 | AO79: 40 | AP79: 10 | AV79: 10 | AW79: 20 | AX79: 1011 | BC79: 1031 | BD79: 20 | BJ79: 20 | BQ79: 0 | BX79: 0 | CE79: 0 | CF79: 50 | CG79: 1011 | CH79: 0 | CI79: 0 | CJ79: 0 | CK79: 0 | CL79: 1061 | CM79: 3 | CS79: 3 | CT79: 5 | CU79: 6 | CZ79: 11 | DA79: 4 | DG79: 4 | DN79: 0 | DU79: 0 | EB79: 0 | EC79: 12 | ED79: 6 | EE79: 0 | EF79: 0 | EG79: 0 | EH79: 0 | EI79: 18 | EJ79: YES | EK79: NO | EL79: NO | EM79: NO | EN79: NO | EO79: NO | EP79: YES | EQ79: YES | ER79: NO | ES79: NO | ET79: NO | EU79: NO | EV79: YES | EW79: NO | EX79: NO | EY79: NO | EZ79: NO | FA79: NO | FB79: NO | FC79: NO | FD79: NO | FE79: NO | FF79: NO | FG79: NO | FH79: NO | FI79: NO | FJ79: NO | FK79: NO | FL79: NO | FM79: NO | FN79: NO | FO79: NO | FP79: NO | FQ79: NO | FR79: NO | FS79: NO | FT79: 50 | FU79: 700 | FZ79: 750 | GB79: 300 | GG79: 300 | GN79: 0 | GU79: 0 | HB79: 0 | HD79: 11 | HI79: 11 | HP79: 0 | HX79: 0 | HY79: 50 | HZ79: 1011 | IA79: 0 | IB79: 0 | IC79: 0 | ID79: 0 | IE79: 1061 | IL79: 0 | IM79: 50 | IN79: 1011 | IS79: 1061 | IZ79: 0 | JG79: 0 | JN79: 0 | JO79: 50 | JP79: 1011 | JQ79: 0 | JR79: 0 | JS79: 0 | JT79: 0 | JU79: 1061 | JV79: 0 | JW79: 0 | JX79: 100 | KA79: 1 | KB79: 3 | KC79: 2 | KD79: START Asia Pacific: | OG79: START Europe: | SJ79: START North America: | WM79: START Global: | AAP79: START SOUTH America: | AES79: START Africa:
A80: C9HVR328R | B80: INREV | C80: Antirion SGR | P80: TRUE | Q80: FALSE | R80: FALSE | S80: FALSE | T80: FALSE | U80: FALSE | V80: 731 | W80: 43517.639 | X80: 205.201.132.14 | Y80: 2019 | Z80: Simone Roberti | AA80: Antirion Sgr | AB80: =VLOOKUP(MID(AD80,SEARCH("@",AD80,1),LEN(AD80)-SEARCH("@",AD80,1)+1),[2]Sheet1!$D:$F,3,FALSE) -> M776 | AC80: Head of Research | AD80: simone.roberti@colliers.it | AE80: 393483806762 | AF80: Italy | AG80: EUR | AI80: 1 | AL80: 400 | AM80: 400 | AN80: 400 | AO80: 400 | AV80: 0 | AW80: 400 | BC80: 400 | BJ80: 0 | BQ80: 0 | BX80: 0 | CE80: 0 | CF80: 400 | CG80: 0 | CH80: 0 | CI80: 0 | CJ80: 0 | CK80: 0 | CL80: 400 | CS80: 0 | CT80: 2 | CZ80: 2 | DG80: 0 | DN80: 0 | DU80: 0 | EB80: 0 | EC80: 2 | ED80: 0 | EE80: 0 | EF80: 0 | EG80: 0 | EH80: 0 | EI80: 2 | EJ80: NO | EK80: NO | EL80: NO | EM80: NO | EN80: NO | EO80: NO | EP80: YES | EQ80: NO | ER80: NO | ES80: NO | ET80: NO | EU80: NO | EV80: NO | EW80: NO | EX80: NO | EY80: NO | EZ80: NO | FA80: NO | FB80: NO | FC80: NO | FD80: NO | FE80: NO | FF80: NO | FG80: NO | FH80: NO | FI80: NO | FJ80: NO | FK80: NO | FL80: NO | FM80: NO | FN80: NO | FO80: NO | FP80: NO | FQ80: NO | FR80: NO | FS80: NO | FT80: 300 | FZ80: 300 | GG80: 0 | GN80: 0 | GU80: 0 | HB80: 0 | HC80: 100 | HI80: 100 | HP80: 0 | HX80: 0 | HY80: 400 | HZ80: 0 | IA80: 0 | IB80: 0 | IC80: 0 | ID80: 0 | IE80: 400 | IL80: 0 | IM80: 400 | IS80: 400 | IZ80: 0 | JG80: 0 | JN80: 0 | JO80: 400 | JP80: 0 | JQ80: 0 | JR80: 0 | JS80: 0 | JT80: 0 | JU80: 400 | JX80: 100 | KA80: 1 | KB80: 3 | KC80: 1 | KD80: START Asia Pacific: | OG80: START Europe: | SJ80: START North America: | WM80: START Global: | AAP80: START SOUTH America: | AES80: START Africa:
A81: C9HXK600C | B81: NCREIF | C81: American Realty Advisors | P81: FALSE | Q81: FALSE | R81: TRUE | S81: FALSE | T81: FALSE | U81: FALSE | V81: 595 | W81: 43517.772 | X81: 216.5.175.66 | Y81: 2019 | Z81: Jay Butterfield | AA81: American Realty Advisors | AB81: =VLOOKUP(MID(AD81,SEARCH("@",AD81,1),LEN(AD81)-SEARCH("@",AD81,1)+1),[2]Sheet1!$D:$F,3,FALSE) -> NC011 | AC81: Executive Managing Director | AD81: jbutterfield@aracapital.com | AE81: 2132335743 | AF81: United States | AG81: USD | AI81: 1 | AL81: 350 | AM81: 350 | AN81: 200 | AO81: 200 | AV81: 0 | BC81: 0 | BD81: 350 | BJ81: 350 | BQ81: 0 | BX81: 0 | CE81: 0 | CF81: 350 | CG81: 0 | CH81: 0 | CI81: 0 | CJ81: 0 | CK81: 0 | CL81: 350 | CS81: 0 | CZ81: 0 | DA81: 2 | DG81: 2 | DN81: 0 | DU81: 0 | EB81: 0 | EC81: 2 | ED81: 0 | EE81: 0 | EF81: 0 | EG81: 0 | EH81: 0 | EI81: 2 | EJ81: NO | EK81: NO | EL81: NO | EM81: NO | EN81: NO | EO81: NO | EP81: NO | EQ81: NO | ER81: NO | ES81: NO | ET81: NO | EU81: NO | EV81: YES | EW81: NO | EX81: NO | EY81: NO | EZ81: NO | FA81: NO | FB81: NO | FC81: NO | FD81: NO | FE81: NO | FF81: NO | FG81: NO | FH81: NO | FI81: NO | FJ81: NO | FK81: NO | FL81: NO | FM81: NO | FN81: NO | FO81: NO | FP81: NO | FQ81: NO | FR81: NO | FS81: NO | FT81: 125 | FZ81: 125 | GG81: 0 | GN81: 0 | GO81: 125 | GU81: 125 | GV81: 66 | HB81: 66 | HI81: 0 | HJ81: 1 | HP81: 1 | HQ81: Interval Funds | HR81: 33 | HX81: 33 | HY81: 350 | HZ81: 0 | IA81: 0 | IB81: 0 | IC81: 0 | ID81: 0 | IE81: 350 | IL81: 0 | IS81: 0 | IT81: 350 | IZ81: 350 | JG81: 0 | JN81: 0 | JO81: 350 | JP81: 0 | JQ81: 0 | JR81: 0 | JS81: 0 | JT81: 0 | JU81: 350 | JV81: 0 | JW81: 0 | JX81: 47 | JY81: Consultants | JZ81: 53 | KA81: 1 | KB81: 3 | KC81: 1 | KD81: START Asia Pacific: | OG81: START Europe: | SJ81: START North America: | WM81: START Global: | AAP81: START SOUTH America: | AES81: START Africa:
A82: C9HXT423V | B82: INREV | C82: GTIS Partners | P82: FALSE | Q82: FALSE | R82: TRUE | S82: FALSE | T82: TRUE | U82: FALSE | V82: 798 | W82: 43524.98 | X82: 196.17.100.70 | Y82: 2019 | Z82: Dietrich Heidtmann | AA82: GTIS Partners | AB82: =VLOOKUP(MID(AD82,SEARCH("@",AD82,1),LEN(AD82)-SEARCH("@",AD82,1)+1),[2]Sheet1!$D:$F,3,FALSE) -> M401 | AC82: MD | AD82: dheidtmann@gtispartners.com | AE82: + 331 7037 5880 | AF82: United States | AG82: USD | AI82: 1 | AL82: 80.1 | AM82: 80.1 | AN82: 69.4 | AO82: 69.4 | AV82: 0 | BC82: 0 | BD82: 20 | BI82: 46 | BJ82: 66 | BQ82: 0 | BR82: 14.1 | BX82: 14.1 | CE82: 0 | CF82: 34.1 | CG82: 0 | CH82: 0 | CI82: 0 | CJ82: 0 | CK82: 46 | CL82: 80.1 | CS82: 0 | CZ82: 0 | DA82: 1 | DF82: 1 | DG82: 2 | DN82: 0 | DO82: 1 | DU82: 1 | EB82: 0 | EC82: 2 | ED82: 0 | EE82: 0 | EF82: 0 | EG82: 0 | EH82: 1 | EI82: 3 | EJ82: NO | EK82: NO | EL82: NO | EM82: NO | EN82: NO | EO82: NO | EP82: NO | EQ82: NO | ER82: NO | ES82: NO | ET82: NO | EU82: NO | EV82: YES | EW82: NO | EX82: NO | EY82: NO | EZ82: NO | FA82: YES | FB82: NO | FC82: NO | FD82: NO | FE82: NO | FF82: NO | FG82: NO | FH82: YES | FI82: NO | FJ82: NO | FK82: NO | FL82: NO | FM82: NO | FN82: NO | FO82: NO | FP82: NO | FQ82: NO | FR82: NO | FS82: NO | FZ82: 0 | GA82: 20 | GG82: 20 | GN82: 0 | GU82: 0 | HB82: 0 | HC82: 13.4 | HH82: 46 | HI82: 59.4 | HJ82: 0.7 | HP82: 0.7 | HX82: 0 | HY82: 34.1 | HZ82: 0 | IA82: 0 | IB82: 0 | IC82: 0 | ID82: 46 | IE82: 80.1 | IL82: 0 | IM82: 20 | IS82: 20 | IT82: 14.1 | IY82: 46 | IZ82: 60.1 | JG82: 0 | JN82: 0 | JO82: 34.1 | JP82: 0 | JQ82: 0 | JR82: 0 | JS82: 0 | JT82: 46 | JU82: 80.1 | JX82: 100 | KA82: 1 | KB82: 1 | KC82: 1 | KD82: START Asia Pacific: | OG82: START Europe: | SJ82: START North America: | WM82: START Global: | AAP82: START SOUTH America: | AES82: START Africa:
A83: C9HYN324C | B83: INREV | C83: Amundi Asset Management | P83: TRUE | Q83: FALSE | R83: FALSE | S83: FALSE | T83: FALSE | U83: FALSE | V83: 547 | W83: 43514.552 | X83: 52.41.60.67 | Y83: 2019 | Z83: Stanislas HENRY | AA83: AMUNDI REAL ESTATE | AB83: =VLOOKUP(MID(AD83,SEARCH("@",AD83,1),LEN(AD83)-SEARCH("@",AD83,1)+1),[2]Sheet1!$D:$F,3,FALSE) -> M365 | AC83: Head of Institutional Funds & Solutions | AD83: stanislas.henry@amundi.com | AE83: 33176321505 | AF83: France | AG83: EUR | AI83: 1 | AL83: 2086.41 | AM83: 0 | AN83: 2086.41 | AV83: 0 | AX83: 1008.92 | AY83: 25.24 | AZ83: 1052.25 | BC83: 2086.41 | BJ83: 0 | BQ83: 0 | BX83: 0 | CE83: 0 | CF83: 0 | CG83: 1008.92 | CH83: 25.24 | CI83: 1052.25 | CJ83: 0 | CK83: 0 | CL83: 2086.41 | CS83: 0 | CU83: 8 | CV83: 2 | CW83: 8 | CZ83: 18 | DG83: 0 | DN83: 0 | DU83: 0 | EB83: 0 | EC83: 0 | ED83: 8 | EE83: 2 | EF83: 8 | EG83: 0 | EH83: 0 | EI83: 18 | EJ83: NO | EK83: NO | EL83: NO | EM83: NO | EN83: NO | EO83: NO | EP83: NO | EQ83: YES | ER83: YES | ES83: YES | ET83: NO | EU83: NO | EV83: NO | EW83: NO | EX83: NO | EY83: NO | EZ83: NO | FA83: NO | FB83: NO | FC83: NO | FD83: NO | FE83: NO | FF83: NO | FG83: NO | FH83: NO | FI83: NO | FJ83: NO | FK83: NO | FL83: NO | FM83: NO | FN83: NO | FO83: NO | FP83: NO | FQ83: NO | FR83: NO | FS83: NO | FU83: 90 | FZ83: 90 | GB83: 522.26 | GC83: 25.24 | GD83: 38.08 | GG83: 585.58 | GN83: 0 | GR83: 166.21 | GU83: 166.21 | HB83: 0 | HI83: 0 | HK83: 3 | HM83: 29.98 | HP83: 32.98 | HQ83: Retail funds | HS83: 393.66 | HU83: 817.98 | HX83: 1211.64 | HY83: 0 | HZ83: 1008.92 | IA83: 25.24 | IB83: 1052.25 | IC83: 0 | ID83: 0 | IE83: 2086.41 | IL83: 0 | IN83: 1008.92 | IO83: 25.24 | IP83: 1052.25 | IS83: 2086.41 | IZ83: 0 | JG83: 0 | JN83: 0 | JO83: 0 | JP83: 1008.92 | JQ83: 25.24 | JR83: 1052.25 | JS83: 0 | JT83: 0 | JU83: 2086.41 | JW83: 59 | JX83: 41 | KA83: 1 | KB83: 3 | KC83: 1 | KD83: START Asia Pacific: | OG83: START Europe: | SJ83: START North America: | WM83: START Global: | AAP83: START SOUTH America: | AES83: START Africa:
A84: C9HYN749K | B84: ANREV | C84: Madigan | P84: FALSE | Q84: TRUE | R84: FALSE | S84: FALSE | T84: FALSE | U84: FALSE | V84: 647 | W84: 43500.109 | X84: 203.174.136.238 | Y84: 2019 | Z84: Richa | AA84: Madigan capital | AB84: =VLOOKUP(MID(AD84,SEARCH("@",AD84,1),LEN(AD84)-SEARCH("@",AD84,1)+1),[2]Sheet1!$D:$F,3,FALSE) -> M0325 | AC84: Analyst | AD84: rkothari@madigancapital.com | AE84: 450976797 | AF84: Australia | AG84: AUD | AI84: 1 | AL84: 200 | AM84: 200 | AN84: 200 | AO84: 200 | AU84: 200 | AV84: 200 | BC84: 0 | BJ84: 0 | BQ84: 0 | BX84: 0 | CE84: 0 | CF84: 0 | CG84: 0 | CH84: 0 | CI84: 0 | CJ84: 0 | CK84: 200 | CL84: 200 | CR84: 1 | CS84: 1 | CZ84: 0 | DG84: 0 | DN84: 0 | DU84: 0 | EB84: 0 | EC84: 0 | ED84: 0 | EE84: 0 | EF84: 0 | EG84: 0 | EH84: 1 | EI84: 1 | EJ84: NO | EK84: NO | EL84: NO | EM84: NO | EN84: NO | EO84: YES | EP84: NO | EQ84: NO | ER84: NO | ES84: NO | ET84: NO | EU84: NO | EV84: NO | EW84: NO | EX84: NO | EY84: NO | EZ84: NO | FA84: NO | FB84: NO | FC84: NO | FD84: NO | FE84: NO | FF84: NO | FG84: NO | FH84: NO | FI84: NO | FJ84: NO | FK84: NO | FL84: NO | FM84: NO | FN84: NO | FO84: NO | FP84: NO | FQ84: NO | FR84: NO | FS84: NO | FY84: 200 | FZ84: 200 | GG84: 0 | GN84: 0 | GU84: 0 | HB84: 0 | HI84: 0 | HP84: 0 | HX84: 0 | HY84: 0 | HZ84: 0 | IA84: 0 | IB84: 0 | IC84: 0 | ID84: 200 | IE84: 200 | IK84: 200 | IL84: 200 | IS84: 0 | IZ84: 0 | JG84: 0 | JN84: 0 | JO84: 0 | JP84: 0 | JQ84: 0 | JR84: 0 | JS84: 0 | JT84: 200 | JU84: 200 | JX84: 100 | KA84: 1 | KB84: 3 | KC84: 1 | KD84: START Asia Pacific: | OG84: START Europe: | SJ84: START North America: | WM84: START Global: | AAP84: START SOUTH America: | AES84: START Africa:
A85: C9JAK424A | B85: INREV | C85: HAHN Fonds Management GmbH | P85: TRUE | Q85: FALSE | R85: FALSE | S85: FALSE | T85: FALSE | U85: FALSE | V85: 578 | W85: 43475.754 | X85: 130.180.126.154 | Y85: 2019 | Z85: Oliver Luckey | AA85: Hahn Group | AB85: =VLOOKUP(MID(AD85,SEARCH("@",AD85,1),LEN(AD85)-SEARCH("@",AD85,1)+1),[2]Sheet1!$D:$F,3,FALSE) -> M369 | AC85: Head of Fund Management | AD85: oluckey@hahnag.de | AE85: =4922049490-135 -> 4922049355 | AF85: Germany | AG85: EUR | AI85: 1 | AL85: 50 | AM85: 50 | AN85: 50 | AO85: 50 | AV85: 0 | AW85: 50 | BC85: 50 | BJ85: 0 | BQ85: 0 | BX85: 0 | CE85: 0 | CF85: 50 | CG85: 0 | CH85: 0 | CI85: 0 | CJ85: 0 | CK85: 0 | CL85: 50 | CS85: 0 | CT85: 1 | CZ85: 1 | DG85: 0 | DN85: 0 | DU85: 0 | EB85: 0 | EC85: 1 | ED85: 0 | EE85: 0 | EF85: 0 | EG85: 0 | EH85: 0 | EI85: 1 | EJ85: NO | EK85: NO | EL85: NO | EM85: NO | EN85: NO | EO85: NO | EP85: YES | EQ85: NO | ER85: NO | ES85: NO | ET85: NO | EU85: NO | EV85: NO | EW85: NO | EX85: NO | EY85: NO | EZ85: NO | FA85: NO | FB85: NO | FC85: NO | FD85: NO | FE85: NO | FF85: NO | FG85: NO | FH85: NO | FI85: NO | FJ85: NO | FK85: NO | FL85: NO | FM85: NO | FN85: NO | FO85: NO | FP85: NO | FQ85: NO | FR85: NO | FS85: NO | FT85: 25 | FZ85: 25 | GG85: 0 | GN85: 0 | GU85: 0 | GV85: 25 | HB85: 25 | HI85: 0 | HP85: 0 | HX85: 0 | HY85: 50 | HZ85: 0 | IA85: 0 | IB85: 0 | IC85: 0 | ID85: 0 | IE85: 50 | IL85: 0 | IM85: 50 | IS85: 50 | IZ85: 0 | JG85: 0 | JN85: 0 | JO85: 50 | JP85: 0 | JQ85: 0 | JR85: 0 | JS85: 0 | JT85: 0 | JU85: 50 | JV85: 50 | JX85: 50 | KA85: 2 | KB85: 3 | KC85: 1 | KD85: START Asia Pacific: | OG85: START Europe: | SJ85: START North America: | WM85: START Global: | AAP85: START SOUTH America: | AES85: START Africa:
A86: C9JEY441J | B86: INREV | C86: ICECAPITAL REAM Oy | P86: FALSE | Q86: FALSE | R86: FALSE | S86: FALSE | T86: FALSE | U86: FALSE | V86: 670 | W86: 43495.442 | X86: 205.201.132.14 | Y86: 2019 | Z86: Thomas Hägglund | AA86: ICECAPITAL REAM Ltd | AB86: =VLOOKUP(MID(AD86,SEARCH("@",AD86,1),LEN(AD86)-SEARCH("@",AD86,1)+1),[2]Sheet1!$D:$F,3,FALSE) -> M2656 | AD86: thomas.hagglund@icecapital.fi | AF86: Finland | AG86: EUR | AI86: 2 | AJ86: 6 | AK86: Timeline not optimal | AV86: 0 | BC86: 0 | BJ86: 0 | BQ86: 0 | BX86: 0 | CE86: 0 | CF86: 0 | CG86: 0 | CH86: 0 | CI86: 0 | CJ86: 0 | CK86: 0 | CL86: 0 | CS86: 0 | CZ86: 0 | DG86: 0 | DN86: 0 | DU86: 0 | EB86: 0 | EC86: 0 | ED86: 0 | EE86: 0 | EF86: 0 | EG86: 0 | EH86: 0 | EI86: 0 | EJ86: NO | EK86: NO | EL86: NO | EM86: NO | EN86: NO | EO86: NO | EP86: NO | EQ86: NO | ER86: NO | ES86: NO | ET86: NO | EU86: NO | EV86: NO | EW86: NO | EX86: NO | EY86: NO | EZ86: NO | FA86: NO | FB86: NO | FC86: NO | FD86: NO | FE86: NO | FF86: NO | FG86: NO | FH86: NO | FI86: NO | FJ86: NO | FK86: NO | FL86: NO | FM86: NO | FN86: NO | FO86: NO | FP86: NO | FQ86: NO | FR86: NO | FS86: NO | FZ86: 0 | GG86: 0 | GN86: 0 | GU86: 0 | HB86: 0 | HI86: 0 | HP86: 0 | HX86: 0 | HY86: 0 | HZ86: 0 | IA86: 0 | IB86: 0 | IC86: 0 | ID86: 0 | IE86: 0 | IL86: 0 | IS86: 0 | IZ86: 0 | JG86: 0 | JN86: 0 | JO86: 0 | JP86: 0 | JQ86: 0 | JR86: 0 | JS86: 0 | JT86: 0 | JU86: 0 | KA86: 3 | KB86: 2 | KC86: 2 | KD86: START Asia Pacific: | OG86: START Europe: | SJ86: START North America: | WM86: START Global: | AAP86: START SOUTH America: | AES86: START Africa:
A87: C9JFC652Z | B87: NCREIF | C87: Hines | D87: Asia | E87: 43528.85 | F87: europe | G87: 43528.852 | H87: northamerica | I87: 43528.854 | P87: TRUE | Q87: TRUE | R87: TRUE | S87: FALSE | T87: FALSE | U87: FALSE | V87: 705 | W87: 43528.849 | X87: 158.106.223.226 | Y87: 2019 | Z87: Erica Garren | AA87: Hines | AB87: =VLOOKUP(MID(AD87,SEARCH("@",AD87,1),LEN(AD87)-SEARCH("@",AD87,1)+1),[2]Sheet1!$D:$F,3,FALSE) -> M073 | AC87: Sr. Internal Data Analyst | AD87: erica.garren@hines.com | AE87: 7139665373 | AF87: United States | AG87: USD | AI87: 1 | AL87: 3373.6743 | AM87: 3373.6743 | AS87: 81.04 | AV87: 81.04 | AW87: 412.44 | AZ87: 1344.13 | BC87: 1756.57 | BE87: 23.08 | BG87: 1512.98 | BJ87: 1536.06 | BQ87: 0 | BX87: 0 | CE87: 0 | CF87: 412.44 | CG87: 23.08 | CH87: 0 | CI87: 2938.15 | CJ87: 0 | CK87: 0 | CL87: 3373.67 | CP87: 1 | CS87: 1 | CT87: 2 | CW87: 12 | CZ87: 14 | DB87: 1 | DD87: 27 | DG87: 28 | DN87: 0 | DU87: 0 | EB87: 0 | EC87: 2 | ED87: 1 | EE87: 0 | EF87: 40 | EG87: 0 | EH87: 0 | EI87: 43 | EJ87: NO | EK87: NO | EL87: NO | EM87: YES | EN87: NO | EO87: NO | EP87: YES | EQ87: NO | ER87: NO | ES87: YES | ET87: NO | EU87: NO | EV87: NO | EW87: YES | EX87: NO | EY87: YES | EZ87: NO | FA87: NO | FB87: NO | FC87: NO | FD87: NO | FE87: NO | FF87: NO | FG87: NO | FH87: NO | FI87: NO | FJ87: NO | FK87: NO | FL87: NO | FM87: NO | FN87: NO | FO87: NO | FP87: NO | FQ87: NO | FR87: NO | FS87: NO | FT87: 346.168 | FW87: 1084.4276 | FZ87: 1430.6 | GA87: 24.8282 | GD87: 140.94265 | GG87: 165.77 | GH87: 17.149 | GK87: 25.3485 | GN87: 42.5 | GU87: 0 | HB87: 0 | HC87: 24.2995 | HF87: 569.07667 | HI87: 593.38 | HM87: 159.0253 | HP87: 159.03 | HQ87: Asset Manager, Bank, Corporate or Other Institutional | HS87: 23.0832 | HU87: 959.32563 | HX87: 982.41 | HY87: 412.44 | HZ87: 23.08 | IA87: 0 | IB87: 2938.15 | IC87: 0 | ID87: 0 | IE87: 3373.67 | IF87: 171.0678 | II87: 412.99425 | IL87: 584.06 | IM87: 241.3769 | IP87: 1116.0858 | IS87: 1357.46 | IU87: 23.08 | IW87: 1267.5429 | IZ87: 1290.62 | JD87: 116.1748 | JG87: 116.17 | JK87: 25.3485 | JN87: 25.35 | JO87: 412.44 | JP87: 23.08 | JQ87: 0 | JR87: 2938.15 | JS87: 0 | JT87: 0 | JU87: 3373.67 | JX87: 100 | KA87: 3 | KB87: 2 | KC87: 1 | KD87: START Asia Pacific: | KK87: 0 | KR87: 0 | KY87: 0 | LF87: 0 | LM87: 0 | LT87: 0 | MA87: 0 | MB87: Asset Manager, Bank, Corporate or Other Institutional | MF87: 81.0391 | MI87: 81.04 | MJ87: 0 | MK87: 0 | ML87: 0 | MM87: 81.04 | MN87: 0 | MO87: 0 | MP87: 81.04 | MW87: 0 | ND87: 0 | NH87: 81.04 | NK87: 81.04 | NR87: 0 | NY87: 0 | NZ87: 0 | OA87: 0 | OB87: 0 | OC87: 81.04 | OD87: 0 | OE87: 0 | OF87: 81.04 | OG87: START Europe: | OH87: 346.168 | OK87: 924.7275 | ON87: 1270.9 | OO87: 24.8282 | OR87: 49.063 | OU87: 73.89 | OV87: 17.149 | PB87: 17.15 | PI87: 0 | PP87: 0 | PQ87: 24.2995 | PT87: 27.4384 | PW87: 51.74 | QA87: 39.4257 | QD87: 39.43 | QE87: Asset Manager, Bank, Corporate or Other Institutional | QI87: 303.47129 | QL87: 303.47 | QM87: 412.44 | QN87: 0 | QO87: 0 | QP87: 1344.13 | QQ87: 0 | QR87: 0 | QS87: 1756.57 | QT87: 241.3769 | QW87: 1116.0858 | QZ87: 1357.46 | RA87: 171.0678 | RD87: 182.27165 | RG87: 353.34 | RK87: 45.7684 | RN87: 45.77 | RU87: 0 | SB87: 0 | SC87: 412.44 | SD87: 0 | SE87: 0 | SF87: 1344.13 | SG87: 0 | SH87: 0 | SI87: 1756.57 | SJ87: START North America: | SN87: 159.7001 | SQ87: 159.7 | SU87: 91.87965 | SX87: 91.88 | TB87: 25.3485 | TE87: 25.35 | TL87: 0 | TS87: 0 | TW87: 541.63827 | TZ87: 541.64 | UD87: 119.5996 | UG87: 119.6 | UH87: Asset Manager, Bank, Corporate or Other Institutional | UJ87: 23.0832 | UL87: 574.81524 | UO87: 597.9 | UP87: 0 | UQ87: 23.08 | UR87: 0 | US87: 1512.98 | UT87: 0 | UU87: 0 | UV87: 1536.06 | VC87: 0 | VG87: 230.7226 | VJ87: 230.72 | VL87: 23.0832 | VN87: 1140.7354 | VQ87: 1163.82 | VU87: 116.1748 | VX87: 116.17 | WB87: 25.3485 | WE87: 25.35 | WF87: 0 | WG87: 23.08 | WH87: 0 | WI87: 1512.98 | WJ87: 0 | WK87: 0 | WL87: 1536.06 | WM87: START Global: | AAP87: START SOUTH America: | AES87: START Africa:
A88: C9JHZ646R | B88: NCREIF | C88: Greystar Real Estate Partners | F88: europe | G88: 43519.154 | H88: northamerica | I88: 43519.171 | L88: southamerica | M88: 43519.176 | P88: TRUE | Q88: FALSE | R88: TRUE | S88: FALSE | T88: TRUE | U88: FALSE | V88: 608 | W88: 43519.135 | X88: 50.201.95.250 | Y88: 2019 | Z88: Rosanna Singh | AA88: Greystar | AB88: =VLOOKUP(MID(AD88,SEARCH("@",AD88,1),LEN(AD88)-SEARCH("@",AD88,1)+1),[2]Sheet1!$D:$F,3,FALSE) -> M718 | AC88: Senior Director | AD88: rosanna.singh@greystar.com | AE88: 8437142306 | AF88: United States | AG88: USD | AI88: 1 | AL88: 4190.9 | AM88: 4190.9 | AN88: 2964 | AO88: 2964 | AP88: 0 | AQ88: 0 | AR88: 0 | AS88: 0 | AT88: 0 | AU88: 0 | AV88: 0 | AW88: 0 | AX88: 572 | AY88: 0 | AZ88: 233.7 | BA88: 0 | BB88: 0 | BC88: 805.7 | BD88: 2436.3 | BE88: 131.6 | BF88: 0 | BG88: 221.4 | BH88: 0 | BI88: 505 | BJ88: 3294.3 | BK88: 0 | BL88: 0 | BM88: 0 | BN88: 0 | BO88: 0 | BP88: 0 | BQ88: 0 | BR88: 0 | BS88: 91 | BT88: 0 | BU88: 0 | BV88: 0 | BW88: 0 | BX88: 91 | BY88: 0 | BZ88: 0 | CA88: 0 | CB88: 0 | CC88: 0 | CD88: 0 | CE88: 0 | CF88: 2436.3 | CG88: 794.6 | CH88: 0 | CI88: 455.1 | CJ88: 0 | CK88: 505 | CL88: 4191 | CS88: 0 | CU88: 4 | CW88: 4 | CZ88: 8 | DA88: 5 | DB88: 11 | DD88: 12 | DF88: 1 | DG88: 29 | DN88: 0 | DP88: 3 | DU88: 3 | EB88: 0 | EC88: 5 | ED88: 18 | EE88: 0 | EF88: 16 | EG88: 0 | EH88: 1 | EI88: 40 | EJ88: NO | EK88: NO | EL88: NO | EM88: NO | EN88: NO | EO88: NO | EP88: NO | EQ88: YES | ER88: NO | ES88: YES | ET88: NO | EU88: NO | EV88: YES | EW88: YES | EX88: NO | EY88: YES | EZ88: NO | FA88: YES | FB88: NO | FC88: NO | FD88: NO | FE88: NO | FF88: NO | FG88: NO | FH88: NO | FI88: YES | FJ88: NO | FK88: NO | FL88: NO | FM88: NO | FN88: NO | FO88: NO | FP88: NO | FQ88: NO | FR88: NO | FS88: NO | FT88: 1013 | FU88: 522.3 | FW88: 234.1 | FY88: 0 | FZ88: 1769.4 | GA88: 45.6 | GB88: 30.3 | GD88: 125.7 | GF88: 0 | GG88: 201.6 | GH88: 131.5 | GI88: 164.8 | GK88: 25.6 | GM88: 119.7 | GN88: 441.6 | GO88: 0 | GP88: 0 | GR88: 0 | GT88: 0 | GU88: 0 | GV88: 14.4 | GW88: 0 | GY88: 0 | HA88: 0 | HB88: 14.4 | HC88: 0 | HD88: 0 | HF88: 0 | HH88: 0 | HI88: 0 | HJ88: 2.4 | HK88: 0 | HM88: 0 | HO88: 0 | HP88: 2.4 | HQ88: Sponsor, Corporate Non-Pension, PE | HR88: 453 | HS88: 537.5 | HU88: 769.9 | HW88: 1.2 | HX88: 1761.6 | HY88: 1659.9 | HZ88: 1254.9 | IA88: 0 | IB88: 1155.3 | IC88: 0 | ID88: 120.9 | IE88: 4191 | IF88: 0 | IG88: 0 | II88: 0 | IK88: 0 | IL88: 0 | IM88: 0 | IN88: 572 | IP88: 233.7 | IR88: 0 | IS88: 805.7 | IT88: 2436.3 | IU88: 131.6 | IW88: 221.4 | IY88: 505 | IZ88: 3294.3 | JA88: 0 | JB88: 91 | JD88: 0 | JF88: 0 | JG88: 91 | JH88: 0 | JI88: 0 | JK88: 0 | JM88: 0 | JN88: 0 | JO88: 2436.3 | JP88: 794.6 | JQ88: 0 | JR88: 455.1 | JS88: 0 | JT88: 505 | JU88: 4191 | JV88: 0 | JW88: 10 | JX88: 90 | KA88: 1 | KB88: 3 | KC88: 1 | KD88: START Asia Pacific: | OG88: START Europe: | OH88: 0 | OI88: 112 | OK88: 135 | OM88: 0 | ON88: 247 | OO88: 0 | OP88: 0 | OR88: 50 | OT88: 0 | OU88: 50 | OV88: 0 | OW88: 113 | OY88: 21 | PA88: 0 | PB88: 134 | PC88: 0 | PD88: 0 | PF88: 0 | PH88: 0 | PI88: 0 | PJ88: 0 | PK88: 0 | PM88: 0 | PO88: 0 | PP88: 0 | PQ88: 0 | PR88: 0 | PT88: 0 | PV88: 0 | PW88: 0 | PX88: 0 | PY88: 0 | QA88: 0 | QC88: 0 | QD88: 0 | QE88: Sponsor, Corporate Non-Pension, PE | QF88: 0 | QG88: 324 | QI88: 51 | QK88: 0 | QL88: 375 | QM88: 0 | QN88: 549 | QO88: 0 | QP88: 257 | QQ88: 0 | QR88: 0 | QS88: 806 | QT88: 0 | QU88: 224.2 | QW88: 168.8 | QY88: 0 | QZ88: 393 | RA88: 0 | RB88: 0 | RD88: 0 | RF88: 0 | RG88: 0 | RH88: 0 | RI88: 324.4 | RK88: 88.4 | RM88: 0 | RN88: 412.8 | RO88: 0 | RP88: 0 | RR88: 0 | RT88: 0 | RU88: 0 | RV88: 0 | RW88: 0 | RY88: 0 | SA88: 0 | SB88: 0 | SC88: 0 | SD88: 548.6 | SE88: 0 | SF88: 257.2 | SG88: 0 | SH88: 0 | SI88: 805.8 | SJ88: START North America: | SK88: 1045.9 | SL88: 400.8 | SN88: 74.7 | SQ88: 1521.4 | SR88: 47.1 | SU88: 67.9 | SX88: 115 | SY88: 135.7 | SZ88: 30.2 | TD88: 123.5 | TE88: 289.4 | TL88: 0 | TM88: 14.8 | TS88: 14.8 | TZ88: 0 | UA88: 2.5 | UG88: 2.5 | UH88: Sponsor, Corporate Non-Pension, PE | UI88: 467.7 | UJ88: 151.1 | UL88: 731.1 | UN88: 1.2 | UO88: 1351.1 | UP88: 1713.7 | UQ88: 582.1 | UR88: 0 | US88: 873.7 | UT88: 0 | UU88: 124.7 | UV88: 3294.2 | UW88: 460 | UX88: 69 | VC88: 529 | VD88: 251 | VE88: 180 | VI88: 108 | VJ88: 539 | VK88: 790 | VL88: 618 | VN88: 817 | VP88: 1 | VQ88: 2226 | VX88: 0 | WE88: 0 | WF88: 1501 | WG88: 867 | WH88: 0 | WI88: 817 | WJ88: 0 | WK88: 109 | WL88: 3294 | WM88: START Global: | AAP88: START SOUTH America: | AAW88: 0 | AAY88: 87.8 | ABD88: 87.8 | ABK88: 0 | ABR88: 0 | ABY88: 0 | ACF88: 0 | ACM88: 0 | ACN88: Sponsor | ACP88: 3.2 | ACU88: 3.2 | ACV88: 0 | ACW88: 91 | ACX88: 0 | ACY88: 0 | ACZ88: 0 | ADA88: 0 | ADB88: 91 | ADI88: 0 | ADP88: 0 | ADR88: 91 | ADW88: 91 | AED88: 0 | AEK88: 0 | AEL88: 0 | AEM88: 91 | AEN88: 0 | AEO88: 0 | AEP88: 0 | AEQ88: 0 | AER88: 91 | AES88: START Africa:
A89: C9JJM390C | B89: INREV | C89: DWS Alternatives GmbH | D89: Asia | E89: 43524.672 | F89: europe | G89: 43524.674 | H89: northamerica | I89: 43524.676 | P89: TRUE | Q89: TRUE | R89: TRUE | S89: FALSE | T89: FALSE | U89: FALSE | V89: 659 | W89: 43524.667 | X89: 80.187.103.122 | Y89: 2019 | Z89: Georg Allendorf | AA89: DWS Alternatives | AB89: =VLOOKUP(MID(AD89,SEARCH("@",AD89,1),LEN(AD89)-SEARCH("@",AD89,1)+1),[2]Sheet1!$D:$F,3,FALSE) -> M085 | AC89: Head of Real Estate Europe | AD89: Georg.allendorf@dws.com | AE89: 496991016655 | AF89: Germany | AG89: EUR | AI89: 1 | AL89: 2300 | AM89: 34 | AN89: 1442 | AO89: 30 | AP89: 130 | AQ89: 154 | AV89: 284 | AW89: 615 | BC89: 615 | BD89: 1402 | BJ89: 1402 | BQ89: 0 | BX89: 0 | CE89: 0 | CF89: 2147 | CG89: 154 | CH89: 0 | CI89: 0 | CJ89: 0 | CK89: 0 | CL89: 2301 | CM89: 1 | CN89: 1 | CS89: 2 | CT89: 7 | CZ89: 7 | DA89: 2 | DG89: 2 | DN89: 0 | DU89: 0 | EB89: 0 | EC89: 10 | ED89: 1 | EE89: 0 | EF89: 0 | EG89: 0 | EH89: 0 | EI89: 11 | EJ89: YES | EK89: YES | EL89: NO | EM89: NO | EN89: NO | EO89: NO | EP89: YES | EQ89: NO | ER89: NO | ES89: NO | ET89: NO | EU89: NO | EV89: YES | EW89: NO | EX89: NO | EY89: NO | EZ89: NO | FA89: NO | FB89: NO | FC89: NO | FD89: NO | FE89: NO | FF89: NO | FG89: NO | FH89: NO | FI89: NO | FJ89: NO | FK89: NO | FL89: NO | FM89: NO | FN89: NO | FO89: NO | FP89: NO | FQ89: NO | FR89: NO | FS89: NO | FT89: 409 | FZ89: 409 | GA89: 129 | GG89: 129 | GH89: 113 | GN89: 113 | GO89: 108 | GU89: 108 | GV89: 34 | HB89: 34 | HC89: 413 | HI89: 413 | HP89: 0 | HR89: 941 | HS89: 154 | HX89: 1095 | HY89: 2147 | HZ89: 154 | IA89: 0 | IB89: 0 | IC89: 0 | ID89: 0 | IE89: 2301 | IG89: 154 | IL89: 154 | IM89: 345 | IS89: 345 | IT89: 1802 | IZ89: 1802 | JG89: 0 | JN89: 0 | JO89: 2147 | JP89: 154 | JQ89: 0 | JR89: 0 | JS89: 0 | JT89: 0 | JU89: 2301 | JW89: 30 | JX89: 70 | KA89: 1 | KB89: 3 | KC89: 2 | KD89: START Asia Pacific: | KK89: 0 | KR89: 0 | KS89: 100 | KY89: 100 | LF89: 0 | LM89: 0 | LN89: 30 | LT89: 30 | MA89: 0 | MD89: 154 | MI89: 154 | MJ89: 130 | MK89: 154 | ML89: 0 | MM89: 0 | MN89: 0 | MO89: 0 | MP89: 284 | MQ89: 30 | MW89: 30 | MY89: 154 | ND89: 154 | NE89: 100 | NK89: 100 | NR89: 0 | NY89: 0 | NZ89: 130 | OA89: 154 | OB89: 0 | OC89: 0 | OD89: 0 | OE89: 0 | OF89: 284 | OG89: START Europe: | OH89: 20 | ON89: 20 | OU89: 0 | PB89: 0 | PI89: 0 | PP89: 0 | PW89: 0 | QD89: 0 | QF89: 595 | QL89: 595 | QM89: 615 | QN89: 0 | QO89: 0 | QP89: 0 | QQ89: 0 | QR89: 0 | QS89: 615 | QT89: 315 | QZ89: 315 | RG89: 0 | RH89: 300 | RN89: 300 | RU89: 0 | SB89: 0 | SC89: 615 | SD89: 0 | SE89: 0 | SF89: 0 | SG89: 0 | SH89: 0 | SI89: 615 | SJ89: START North America: | SK89: 389 | SQ89: 389 | SR89: 129 | SX89: 129 | SY89: 13 | TE89: 13 | TF89: 107 | TL89: 107 | TM89: 34 | TS89: 34 | TT89: 383 | TZ89: 383 | UG89: 0 | UI89: 347 | UO89: 347 | UP89: 1402 | UQ89: 0 | UR89: 0 | US89: 0 | UT89: 0 | UU89: 0 | UV89: 1402 | VC89: 0 | VJ89: 0 | VK89: 1402 | VQ89: 1402 | VX89: 0 | WE89: 0 | WF89: 1402 | WG89: 0 | WH89: 0 | WI89: 0 | WJ89: 0 | WK89: 0 | WL89: 1402 | WM89: START Global: | AAP89: START SOUTH America: | AES89: START Africa:
A90: C9JLT563Y | B90: INREV | C90: Threestones Capital Management | P90: TRUE | Q90: FALSE | R90: FALSE | S90: FALSE | T90: FALSE | U90: FALSE | V90: 564 | W90: 43502.676 | X90: 146.0.190.192 | Y90: 2019 | Z90: Shanu Sherwani | AA90: Threestones Capital | AB90: =VLOOKUP(MID(AD90,SEARCH("@",AD90,1),LEN(AD90)-SEARCH("@",AD90,1)+1),[2]Sheet1!$D:$F,3,FALSE) -> M751 | AC90: Head of Business Development | AD90: s.sherwani@threestonescapital.com | AE90: 3522484711 | AF90: Luxembourg | AG90: EUR | AI90: 1 | AL90: 214 | AN90: 96 | AV90: 0 | AW90: 214 | BC90: 214 | BJ90: 0 | BQ90: 0 | BX90: 0 | CE90: 0 | CF90: 214 | CG90: 0 | CH90: 0 | CI90: 0 | CJ90: 0 | CK90: 0 | CL90: 214 | CS90: 0 | CT90: 2 | CZ90: 2 | DG90: 0 | DN90: 0 | DU90: 0 | EB90: 0 | EC90: 2 | ED90: 0 | EE90: 0 | EF90: 0 | EG90: 0 | EH90: 0 | EI90: 2 | EJ90: NO | EK90: NO | EL90: NO | EM90: NO | EN90: NO | EO90: NO | EP90: YES | EQ90: NO | ER90: NO | ES90: NO | ET90: NO | EU90: NO | EV90: NO | EW90: NO | EX90: NO | EY90: NO | EZ90: NO | FA90: NO | FB90: NO | FC90: NO | FD90: NO | FE90: NO | FF90: NO | FG90: NO | FH90: NO | FI90: NO | FJ90: NO | FK90: NO | FL90: NO | FM90: NO | FN90: NO | FO90: NO | FP90: NO | FQ90: NO | FR90: NO | FS90: NO | FT90: 43 | FZ90: 43 | GA90: 22 | GG90: 22 | GN90: 0 | GU90: 0 | HB90: 0 | HC90: 1 | HI90: 1 | HJ90: 127 | HP90: 127 | HQ90: Bank | HR90: 21 | HX90: 21 | HY90: 214 | HZ90: 0 | IA90: 0 | IB90: 0 | IC90: 0 | ID90: 0 | IE90: 214 | IL90: 0 | IM90: 214 | IS90: 214 | IZ90: 0 | JG90: 0 | JN90: 0 | JO90: 214 | JP90: 0 | JQ90: 0 | JR90: 0 | JS90: 0 | JT90: 0 | JU90: 214 | JX90: 10 | JY90: Introducers/Distributors | JZ90: 90 | KA90: 1 | KB90: 1 | KC90: 1 | KD90: START Asia Pacific: | OG90: START Europe: | SJ90: START North America: | WM90: START Global: | AAP90: START SOUTH America: | AES90: START Africa:
A91: C9JLW327H | B91: ANREV | C91: Challenger Ltd | P91: FALSE | Q91: TRUE | R91: FALSE | S91: FALSE | T91: FALSE | U91: FALSE | V91: 697 | W91: 43501.992 | X91: 203.27.87.126 | Y91: 2019 | Z91: Trent | AA91: Challenger | AB91: =VLOOKUP(MID(AD91,SEARCH("@",AD91,1),LEN(AD91)-SEARCH("@",AD91,1)+1),[2]Sheet1!$D:$F,3,FALSE) -> M0224 | AC91: Head of Real Estate | AD91: talston@challenger.com.au | AE91: 61299947851 | AF91: Australia | AG91: AUD | AI91: 1 | AL91: 100 | AM91: 100 | AN91: 100 | AO91: 100 | AQ91: 100 | AV91: 100 | BC91: 0 | BJ91: 0 | BQ91: 0 | BX91: 0 | CE91: 0 | CF91: 0 | CG91: 100 | CH91: 0 | CI91: 0 | CJ91: 0 | CK91: 0 | CL91: 100 | CN91: 1 | CS91: 1 | CZ91: 0 | DG91: 0 | DN91: 0 | DU91: 0 | EB91: 0 | EC91: 0 | ED91: 1 | EE91: 0 | EF91: 0 | EG91: 0 | EH91: 0 | EI91: 1 | EJ91: NO | EK91: YES | EL91: NO | EM91: NO | EN91: NO | EO91: NO | EP91: NO | EQ91: NO | ER91: NO | ES91: NO | ET91: NO | EU91: NO | EV91: NO | EW91: NO | EX91: NO | EY91: NO | EZ91: NO | FA91: NO | FB91: NO | FC91: NO | FD91: NO | FE91: NO | FF91: NO | FG91: NO | FH91: NO | FI91: NO | FJ91: NO | FK91: NO | FL91: NO | FM91: NO | FN91: NO | FO91: NO | FP91: NO | FQ91: NO | FR91: NO | FS91: NO | FZ91: 0 | GB91: 100 | GG91: 100 | GN91: 0 | GU91: 0 | HB91: 0 | HI91: 0 | HP91: 0 | HX91: 0 | HY91: 0 | HZ91: 100 | IA91: 0 | IB91: 0 | IC91: 0 | ID91: 0 | IE91: 100 | IG91: 100 | IL91: 100 | IS91: 0 | IZ91: 0 | JG91: 0 | JN91: 0 | JO91: 0 | JP91: 100 | JQ91: 0 | JR91: 0 | JS91: 0 | JT91: 0 | JU91: 100 | JX91: 100 | KA91: 1 | KB91: 3 | KC91: 1 | KD91: START Asia Pacific: | OG91: START Europe: | SJ91: START North America: | WM91: START Global: | AAP91: START SOUTH America: | AES91: START Africa:
A92: C9JNT849H | B92: ANREV | C92: Orion Partners Real Estate Group | P92: FALSE | Q92: FALSE | R92: FALSE | S92: FALSE | T92: FALSE | U92: FALSE | V92: 709 | W92: 43508.343 | X92: 202.77.62.76 | Y92: 2019 | Z92: John LEE | AA92: Orion Partners Real Estate Group | AB92: =VLOOKUP(MID(AD92,SEARCH("@",AD92,1),LEN(AD92)-SEARCH("@",AD92,1)+1),[2]Sheet1!$D:$F,3,FALSE) -> M0035 | AC92: Partner and Head of Real Estate Group | AD92: jlee@orionpartners.com | AE92: +852 2218 2168 | AF92: Hong Kong | AG92: USD | AI92: 2 | AJ92: 6 | AK92: Held off in 2018 pending completion of current Fund. Recommence in 2019. | AV92: 0 | BC92: 0 | BJ92: 0 | BQ92: 0 | BX92: 0 | CE92: 0 | CF92: 0 | CG92: 0 | CH92: 0 | CI92: 0 | CJ92: 0 | CK92: 0 | CL92: 0 | CS92: 0 | CZ92: 0 | DG92: 0 | DN92: 0 | DU92: 0 | EB92: 0 | EC92: 0 | ED92: 0 | EE92: 0 | EF92: 0 | EG92: 0 | EH92: 0 | EI92: 0 | EJ92: NO | EK92: NO | EL92: NO | EM92: NO | EN92: NO | EO92: NO | EP92: NO | EQ92: NO | ER92: NO | ES92: NO | ET92: NO | EU92: NO | EV92: NO | EW92: NO | EX92: NO | EY92: NO | EZ92: NO | FA92: NO | FB92: NO | FC92: NO | FD92: NO | FE92: NO | FF92: NO | FG92: NO | FH92: NO | FI92: NO | FJ92: NO | FK92: NO | FL92: NO | FM92: NO | FN92: NO | FO92: NO | FP92: NO | FQ92: NO | FR92: NO | FS92: NO | FZ92: 0 | GG92: 0 | GN92: 0 | GU92: 0 | HB92: 0 | HI92: 0 | HP92: 0 | HX92: 0 | HY92: 0 | HZ92: 0 | IA92: 0 | IB92: 0 | IC92: 0 | ID92: 0 | IE92: 0 | IL92: 0 | IS92: 0 | IZ92: 0 | JG92: 0 | JN92: 0 | JO92: 0 | JP92: 0 | JQ92: 0 | JR92: 0 | JS92: 0 | JT92: 0 | JU92: 0 | KA92: 1 | KB92: 3 | KC92: 1 | KD92: START Asia Pacific: | OG92: START Europe: | SJ92: START North America: | WM92: START Global: | AAP92: START SOUTH America: | AES92: START Africa:
A93: C9JRA571A | B93: ANREV | C93: The GPT Group | P93: FALSE | Q93: TRUE | R93: FALSE | S93: FALSE | T93: FALSE | U93: FALSE | V93: 690 | W93: 43515.972 | X93: 101.78.165.217 | Y93: 2019 | Z93: Paul Caddy | AA93: The GPT Group | AB93: =VLOOKUP(MID(AD93,SEARCH("@",AD93,1),LEN(AD93)-SEARCH("@",AD93,1)+1),[2]Sheet1!$D:$F,3,FALSE) -> M0075 | AC93: Senior Fund Analyst | AD93: paul.caddy@gpt.com.au | AE93: +61 2 8239 3858 | AF93: Australia | AG93: AUD | AI93: 1 | AL93: 327.1 | AM93: 327.1 | AN93: 327.1 | AO93: 327.1 | AP93: 327.1 | AV93: 327.1 | BC93: 0 | BJ93: 0 | BQ93: 0 | BX93: 0 | CE93: 0 | CF93: 327.1 | CG93: 0 | CH93: 0 | CI93: 0 | CJ93: 0 | CK93: 0 | CL93: 327.1 | CM93: 2 | CS93: 2 | CZ93: 0 | DG93: 0 | DN93: 0 | DU93: 0 | EB93: 0 | EC93: 2 | ED93: 0 | EE93: 0 | EF93: 0 | EG93: 0 | EH93: 0 | EI93: 2 | EJ93: YES | EK93: NO | EL93: NO | EM93: NO | EN93: NO | EO93: NO | EP93: NO | EQ93: NO | ER93: NO | ES93: NO | ET93: NO | EU93: NO | EV93: NO | EW93: NO | EX93: NO | EY93: NO | EZ93: NO | FA93: NO | FB93: NO | FC93: NO | FD93: NO | FE93: NO | FF93: NO | FG93: NO | FH93: NO | FI93: NO | FJ93: NO | FK93: NO | FL93: NO | FM93: NO | FN93: NO | FO93: NO | FP93: NO | FQ93: NO | FR93: NO | FS93: NO | FT93: 243.1 | FZ93: 243.1 | GG93: 0 | GN93: 0 | GO93: 40 | GU93: 40 | GV93: 12.9 | HB93: 12.9 | HC93: 31.1 | HI93: 31.1 | HP93: 0 | HX93: 0 | HY93: 327.1 | HZ93: 0 | IA93: 0 | IB93: 0 | IC93: 0 | ID93: 0 | IE93: 327.1 | IF93: 280.8 | IL93: 280.8 | IM93: 46.3 | IS93: 46.3 | IZ93: 0 | JG93: 0 | JN93: 0 | JO93: 327.1 | JP93: 0 | JQ93: 0 | JR93: 0 | JS93: 0 | JT93: 0 | JU93: 327.1 | JX93: 100 | KA93: 2 | KB93: 3 | KC93: 1 | KD93: START Asia Pacific: | OG93: START Europe: | SJ93: START North America: | WM93: START Global: | AAP93: START SOUTH America: | AES93: START Africa:
A94: C9JVW472X | B94: INREV | C94: LGT Capital Partners | P94: FALSE | Q94: FALSE | R94: FALSE | S94: FALSE | T94: FALSE | U94: FALSE | V94: 575 | W94: 43523.622 | X94: 77.59.199.231 | Y94: 2019 | Z94: Thomas B. Brown | AA94: LGT Capital Partners | AB94: =VLOOKUP(MID(AD94,SEARCH("@",AD94,1),LEN(AD94)-SEARCH("@",AD94,1)+1),[2]Sheet1!$D:$F,3,FALSE) -> M411 | AC94: Partner | AD94: thomas.brown@lgt.com | AE94: =_FV(_FV(1.212,"336"),"0681") -> #VALUE! | AF94: Switzerland | AG94: USD | AI94: 2 | AJ94: 6 | AK94: Investing other vehicles | AV94: 0 | BC94: 0 | BJ94: 0 | BQ94: 0 | BX94: 0 | CE94: 0 | CF94: 0 | CG94: 0 | CH94: 0 | CI94: 0 | CJ94: 0 | CK94: 0 | CL94: 0 | CS94: 0 | CZ94: 0 | DG94: 0 | DN94: 0 | DU94: 0 | EB94: 0 | EC94: 0 | ED94: 0 | EE94: 0 | EF94: 0 | EG94: 0 | EH94: 0 | EI94: 0 | EJ94: NO | EK94: NO | EL94: NO | EM94: NO | EN94: NO | EO94: NO | EP94: NO | EQ94: NO | ER94: NO | ES94: NO | ET94: NO | EU94: NO | EV94: NO | EW94: NO | EX94: NO | EY94: NO | EZ94: NO | FA94: NO | FB94: NO | FC94: NO | FD94: NO | FE94: NO | FF94: NO | FG94: NO | FH94: NO | FI94: NO | FJ94: NO | FK94: NO | FL94: NO | FM94: NO | FN94: NO | FO94: NO | FP94: NO | FQ94: NO | FR94: NO | FS94: NO | FZ94: 0 | GG94: 0 | GN94: 0 | GU94: 0 | HB94: 0 | HI94: 0 | HP94: 0 | HX94: 0 | HY94: 0 | HZ94: 0 | IA94: 0 | IB94: 0 | IC94: 0 | ID94: 0 | IE94: 0 | IL94: 0 | IS94: 0 | IZ94: 0 | JG94: 0 | JN94: 0 | JO94: 0 | JP94: 0 | JQ94: 0 | JR94: 0 | JS94: 0 | JT94: 0 | JU94: 0 | KA94: 1 | KB94: 2 | KC94: 2 | KD94: START Asia Pacific: | OG94: START Europe: | SJ94: START North America: | WM94: START Global: | AAP94: START SOUTH America: | AES94: START Africa:
