Workbook
Name RMITeam: [1]ContactDetails!$B$9:$B$13

Sheet DataCompleted
A1: Surveycode | B1: Association | C1: Company | D1: FullName | E1: EmailAddress | F1: SampleNote | G1: SurveyURL | H1: REGION1 | I1: DateCompleted1 | J1: REGION2 | K1: DateCompleted2 | L1: REGION3 | M1: DateCompleted3 | N1: REGION4 | O1: DateCompleted4 | P1: REGION5 | Q1: DateCompleted5 | R1: REGION6 | S1: DateCompleted6 | T1: ShowEurope | U1: ShowAsia | V1: ShowNA | W1: ShowGlobal | X1: ShowSA | Y1: ShowAfrica | Z1: RecordNo | AA1: DateCompleted | AB1: IPaddress | AC1: Version | AD1: qName | AE1: qCompany | AF1: mnumber | AG1: qJobtitle | AH1: qEmail | AI1: qTelephone | AJ1: qCountry | AK1: qCurrency | AL1: qCurrencyOther | AM1: q1 | AN1: q2 | AO1: q2other | AP1: q31_1 | AQ1: q31_2 | AR1: q31_3 | AS1: q31_4 | AT1: q31_5 | AU1: q31_6 | AV1: q3ROW1_hidden | AW1: q32_1 | AX1: q32_2 | AY1: q32_3 | AZ1: q32_4 | BA1: q32_5 | BB1: q32_6 | BC1: q3ROW2_hidden | BD1: q33_1 | BE1: q33_2 | BF1: q33_3 | BG1: q33_4 | BH1: q33_5 | BI1: q33_6 | BJ1: q3ROW3_hidden | BK1: q34_1 | BL1: q34_2 | BM1: q34_3 | BN1: q34_4 | BO1: q34_5 | BP1: q34_6 | BQ1: q3ROW4_hidden | BR1: q35_1 | BS1: q35_2 | BT1: q35_3 | BU1: q35_4 | BV1: q35_5 | BW1: q35_6 | BX1: q3ROW5_hidden | BY1: q36_1 | BZ1: q36_2 | CA1: q36_3 | CB1: q36_4 | CC1: q36_5 | CD1: q36_6 | CE1: q3ROW6_hidden | CF1: q3COL1_hidden | CG1: q3COL2_hidden | CH1: q3COL3_hidden | CI1: q3COL4_hidden | CJ1: q3COL5_hidden | CK1: q3COL6_hidden | CL1: q3GRANDTotal_hidden | CM1: q41_1 | CN1: q41_2 | CO1: q41_3 | CP1: q41_4 | CQ1: q41_5 | CR1: q41_6 | CS1: q4ROW1_hidden | CT1: q42_1 | CU1: q42_2 | CV1: q42_3 | CW1: q42_4 | CX1: q42_5 | CY1: q42_6 | CZ1: q4ROW2_hidden | DA1: q43_1 | DB1: q43_2 | DC1: q43_3 | DD1: q43_4 | DE1: q43_5 | DF1: q43_6 | DG1: q4ROW3_hidden | DH1: q44_1 | DI1: q44_2 | DJ1: q44_3 | DK1: q44_4 | DL1: q44_5 | DM1: q44_6 | DN1: q4ROW4_hidden | DO1: q45_1 | DP1: q45_2 | DQ1: q45_3 | DR1: q45_4 | DS1: q45_5 | DT1: q45_6 | DU1: q4ROW5_hidden | DV1: q46_1 | DW1: q46_2 | DX1: q46_3 | DY1: q46_4 | DZ1: q46_5 | EA1: q46_6 | EB1: q4ROW6_hidden | EC1: q4COL1_hidden | ED1: q4COL2_hidden | EE1: q4COL3_hidden | EF1: q4COL4_hidden | EG1: q4COL5_hidden | EH1: q4COL6_hidden | EI1: q4GRANDTotal_hidden | EJ1: Alert41_1 | EK1: Alert41_2 | EL1: Alert41_3 | EM1: Alert41_4 | EN1: Alert41_5 | EO1: Alert41_6 | EP1: Alert42_1 | EQ1: Alert42_2 | ER1: Alert42_3 | ES1: Alert42_4 | ET1: Alert42_5 | EU1: Alert42_6 | EV1: Alert43_1 | EW1: Alert43_2 | EX1: Alert43_3 | EY1: Alert43_4 | EZ1: Alert43_5 | FA1: Alert43_6 | FB1: Alert44_1 | FC1: Alert44_2 | FD1: Alert44_3 | FE1: Alert44_4 | FF1: Alert44_5 | FG1: Alert44_6 | FH1: Alert45_1 | FI1: Alert45_2 | FJ1: Alert45_3 | FK1: Alert45_4 | FL1: Alert45_5 | FM1: Alert45_6 | FN1: Alert46_1 | FO1: Alert46_2 | FP1: Alert46_3 | FQ1: Alert46_4 | FR1: Alert46_5 | FS1: Alert46_6 | FT1: q51_1 | FU1: q51_2 | FV1: q51_3 | FW1: q51_4 | FX1: q51_5 | FY1: q51_6 | FZ1: q5ROW1_hidden | GA1: q52_1 | GB1: q52_2 | GC1: q52_3 | GD1: q52_4 | GE1: q52_5 | GF1: q52_6 | GG1: q5ROW2_hidden | GH1: q53_1 | GI1: q53_2 | GJ1: q53_3 | GK1: q53_4 | GL1: q53_5 | GM1: q53_6 | GN1: q5ROW3_hidden | GO1: q54_1 | GP1: q54_2 | GQ1: q54_3 | GR1: q54_4 | GS1: q54_5 | GT1: q54_6 | GU1: q5ROW4_hidden | GV1: q55_1 | GW1: q55_2 | GX1: q55_3 | GY1: q55_4 | GZ1: q55_5 | HA1: q55_6 | HB1: q5ROW5_hidden | HC1: q56_1 | HD1: q56_2 | HE1: q56_3 | HF1: q56_4 | HG1: q56_5 | HH1: q56_6 | HI1: q5ROW6_hidden | HJ1: q57_1 | HK1: q57_2 | HL1: q57_3 | HM1: q57_4 | HN1: q57_5 | HO1: q57_6 | HP1: q5ROW7_hidden | HQ1: q5other | HR1: q58_1 | HS1: q58_2 | HT1: q58_3 | HU1: q58_4 | HV1: q58_5 | HW1: q58_6 | HX1: q5ROW8_hidden | HY1: q5COL1_hidden | HZ1: q5COL2_hidden | IA1: q5COL3_hidden | IB1: q5COL4_hidden | IC1: q5COL5_hidden | ID1: q5COL6_hidden | IE1: q5GRANDTotal_hidden | IF1: q61_1 | IG1: q61_2 | IH1: q61_3 | II1: q61_4 | IJ1: q61_5 | IK1: q61_6 | IL1: q6ROW1_hidden | IM1: q62_1 | IN1: q62_2 | IO1: q62_3 | IP1: q62_4 | IQ1: q62_5 | IR1: q62_6 | IS1: q6ROW2_hidden | IT1: q63_1 | IU1: q63_2 | IV1: q63_3 | IW1: q63_4 | IX1: q63_5 | IY1: q63_6 | IZ1: q6ROW3_hidden | JA1: q64_1 | JB1: q64_2 | JC1: q64_3 | JD1: q64_4 | JE1: q64_5 | JF1: q64_6 | JG1: q6ROW4_hidden | JH1: q65_1 | JI1: q65_2 | JJ1: q65_3 | JK1: q65_4 | JL1: q65_5 | JM1: q65_6 | JN1: q6ROW5_hidden | JO1: q6COL1_hidden | JP1: q6COL2_hidden | JQ1: q6COL3_hidden | JR1: q6COL4_hidden | JS1: q6COL5_hidden | JT1: q6COL6_hidden | JU1: q6GRANDTotal_hidden | JV1: q7_1 | JW1: q7_2 | JX1: q7_3 | JY1: q7other | JZ1: q7_4 | KA1: q8 | KB1: q9 | KC1: q91 | KD1: ASIA PACIFIC_apac | KE1: q101_1_apac | KF1: q101_2_apac | KG1: q101_3_apac | KH1: q101_4_apac | KI1: q101_5_apac | KJ1: q101_6_apac | KK1: q10ROW1_hidden_apac | KL1: q102_1_apac | KM1: q102_2_apac | KN1: q102_3_apac | KO1: q102_4_apac | KP1: q102_5_apac | KQ1: q102_6_apac | KR1: q10ROW2_hidden_apac | KS1: q103_1_apac | KT1: q103_2_apac | KU1: q103_3_apac | KV1: q103_4_apac | KW1: q103_5_apac | KX1: q103_6_apac | KY1: q10ROW3_hidden_apac | KZ1: q104_1_apac | LA1: q104_2_apac | LB1: q104_3_apac | LC1: q104_4_apac | LD1: q104_5_apac | LE1: q104_6_apac | LF1: q10ROW4_hidden_apac | LG1: q105_1_apac | LH1: q105_2_apac | LI1: q105_3_apac | LJ1: q105_4_apac | LK1: q105_5_apac | LL1: q105_6_apac | LM1: q10ROW5_hidden_apac | LN1: q106_1_apac | LO1: q106_2_apac | LP1: q106_3_apac | LQ1: q106_4_apac | LR1: q106_5_apac | LS1: q106_6_apac | LT1: q10ROW6_hidden_apac | LU1: q107_1_apac | LV1: q107_2_apac | LW1: q107_3_apac | LX1: q107_4_apac | LY1: q107_5_apac | LZ1: q107_6_apac | MA1: q10ROW7_hidden_apac | MB1: q10other_apac | MC1: q108_1_apac | MD1: q108_2_apac | ME1: q108_3_apac | MF1: q108_4_apac | MG1: q108_5_apac | MH1: q108_6_apac | MI1: q10ROW8_hidden_apac | MJ1: q10COL1_hidden_apac | MK1: q10COL2_hidden_apac | ML1: q10COL3_hidden_apac | MM1: q10COL4_hidden_apac | MN1: q10COL5_hidden_apac | MO1: q10COL6_hidden_apac | MP1: q10GRANDTotal_hidden_apac | MQ1: q111_1_apac | MR1: q111_2_apac | MS1: q111_3_apac | MT1: q111_4_apac | MU1: q111_5_apac | MV1: q111_6_apac | MW1: q11ROW1_hidden_apac | MX1: q112_1_apac | MY1: q112_2_apac | MZ1: q112_3_apac | NA1: q112_4_apac | NB1: q112_5_apac | NC1: q112_6_apac | ND1: q11ROW2_hidden_apac | NE1: q113_1_apac | NF1: q113_2_apac | NG1: q113_3_apac | NH1: q113_4_apac | NI1: q113_5_apac | NJ1: q113_6_apac | NK1: q11ROW3_hidden_apac | NL1: q114_1_apac | NM1: q114_2_apac | NN1: q114_3_apac | NO1: q114_4_apac | NP1: q114_5_apac | NQ1: q114_6_apac | NR1: q11ROW4_hidden_apac | NS1: q115_1_apac | NT1: q115_2_apac | NU1: q115_3_apac | NV1: q115_4_apac | NW1: q115_5_apac | NX1: q115_6_apac | NY1: q11ROW5_hidden_apac | NZ1: q11COL1_hidden_apac | OA1: q11COL2_hidden_apac | OB1: q11COL3_hidden_apac | OC1: q11COL4_hidden_apac | OD1: q11COL5_hidden_apac | OE1: q11COL6_hidden_apac | OF1: q11GRANDTotal_hidden_apac | OG1: EUROPE_europe | OH1: q101_1_europe | OI1: q101_2_europe | OJ1: q101_3_europe | OK1: q101_4_europe | OL1: q101_5_europe | OM1: q101_6_europe | ON1: q10ROW1_hidden_europe | OO1: q102_1_europe | OP1: q102_2_europe | OQ1: q102_3_europe | OR1: q102_4_europe | OS1: q102_5_europe | OT1: q102_6_europe | OU1: q10ROW2_hidden_europe | OV1: q103_1_europe | OW1: q103_2_europe | OX1: q103_3_europe | OY1: q103_4_europe | OZ1: q103_5_europe | PA1: q103_6_europe | PB1: q10ROW3_hidden_europe | PC1: q104_1_europe | PD1: q104_2_europe | PE1: q104_3_europe | PF1: q104_4_europe | PG1: q104_5_europe | PH1: q104_6_europe | PI1: q10ROW4_hidden_europe | PJ1: q105_1_europe | PK1: q105_2_europe | PL1: q105_3_europe | PM1: q105_4_europe | PN1: q105_5_europe | PO1: q105_6_europe | PP1: q10ROW5_hidden_europe | PQ1: q106_1_europe | PR1: q106_2_europe | PS1: q106_3_europe | PT1: q106_4_europe | PU1: q106_5_europe | PV1: q106_6_europe | PW1: q10ROW6_hidden_europe | PX1: q107_1_europe | PY1: q107_2_europe | PZ1: q107_3_europe | QA1: q107_4_europe | QB1: q107_5_europe | QC1: q107_6_europe | QD1: q10ROW7_hidden_europe | QE1: q10other_europe | QF1: q108_1_europe | QG1: q108_2_europe | QH1: q108_3_europe | QI1: q108_4_europe | QJ1: q108_5_europe | QK1: q108_6_europe | QL1: q10ROW8_hidden_europe | QM1: q10COL1_hidden_europe | QN1: q10COL2_hidden_europe | QO1: q10COL3_hidden_europe | QP1: q10COL4_hidden_europe | QQ1: q10COL5_hidden_europe | QR1: q10COL6_hidden_europe | QS1: q10GRANDTotal_hidden_europe | QT1: q111_1_europe | QU1: q111_2_europe | QV1: q111_3_europe | QW1: q111_4_europe | QX1: q111_5_europe | QY1: q111_6_europe | QZ1: q11ROW1_hidden_europe | RA1: q112_1_europe | RB1: q112_2_europe | RC1: q112_3_europe | RD1: q112_4_europe | RE1: q112_5_europe | RF1: q112_6_europe | RG1: q11ROW2_hidden_europe | RH1: q113_1_europe | RI1: q113_2_europe | RJ1: q113_3_europe | RK1: q113_4_europe | RL1: q113_5_europe | RM1: q113_6_europe | RN1: q11ROW3_hidden_europe | RO1: q114_1_europe | RP1: q114_2_europe | RQ1: q114_3_europe | RR1: q114_4_europe | RS1: q114_5_europe | RT1: q114_6_europe | RU1: q11ROW4_hidden_europe | RV1: q115_1_europe | RW1: q115_2_europe | RX1: q115_3_europe | RY1: q115_4_europe | RZ1: q115_5_europe | SA1: q115_6_europe | SB1: q11ROW5_hidden_europe | SC1: q11COL1_hidden_europe | SD1: q11COL2_hidden_europe | SE1: q11COL3_hidden_europe | SF1: q11COL4_hidden_europe | SG1: q11COL5_hidden_europe | SH1: q11COL6_hidden_europe | SI1: q11GRANDTotal_hidden_europe | SJ1: NORTH AMERICA_northamerica | SK1: q101_1_northamerica | SL1: q101_2_northamerica | SM1: q101_3_northamerica | SN1: q101_4_northamerica | SO1: q101_5_northamerica | SP1: q101_6_northamerica | SQ1: q10ROW1_hidden_northamerica | SR1: q102_1_northamerica | SS1: q102_2_northamerica | ST1: q102_3_northamerica | SU1: q102_4_northamerica | SV1: q102_5_northamerica | SW1: q102_6_northamerica | SX1: q10ROW2_hidden_northamerica | SY1: q103_1_northamerica | SZ1: q103_2_northamerica | TA1: q103_3_northamerica | TB1: q103_4_northamerica | TC1: q103_5_northamerica | TD1: q103_6_northamerica | TE1: q10ROW3_hidden_northamerica | TF1: q104_1_northamerica | TG1: q104_2_northamerica | TH1: q104_3_northamerica | TI1: q104_4_northamerica | TJ1: q104_5_northamerica | TK1: q104_6_northamerica | TL1: q10ROW4_hidden_northamerica | TM1: q105_1_northamerica | TN1: q105_2_northamerica | TO1: q105_3_northamerica | TP1: q105_4_northamerica | TQ1: q105_5_northamerica | TR1: q105_6_northamerica | TS1: q10ROW5_hidden_northamerica | TT1: q106_1_northamerica | TU1: q106_2_northamerica | TV1: q106_3_northamerica | TW1: q106_4_northamerica | TX1: q106_5_northamerica | TY1: q106_6_northamerica | TZ1: q10ROW6_hidden_northamerica | UA1: q107_1_northamerica | UB1: q107_2_northamerica | UC1: q107_3_northamerica | UD1: q107_4_northamerica | UE1: q107_5_northamerica | UF1: q107_6_northamerica | UG1: q10ROW7_hidden_northamerica | UH1: q10other_northamerica | UI1: q108_1_northamerica | UJ1: q108_2_northamerica | UK1: q108_3_northamerica | UL1: q108_4_northamerica | UM1: q108_5_northamerica | UN1: q108_6_northamerica | UO1: q10ROW8_hidden_northamerica | UP1: q10COL1_hidden_northamerica | UQ1: q10COL2_hidden_northamerica | UR1: q10COL3_hidden_northamerica | US1: q10COL4_hidden_northamerica | UT1: q10COL5_hidden_northamerica | UU1: q10COL6_hidden_northamerica | UV1: q10GRANDTotal_hidden_northamerica | UW1: q111_1_northamerica | UX1: q111_2_northamerica | UY1: q111_3_northamerica | UZ1: q111_4_northamerica | VA1: q111_5_northamerica | VB1: q111_6_northamerica | VC1: q11ROW1_hidden_northamerica | VD1: q112_1_northamerica | VE1: q112_2_northamerica | VF1: q112_3_northamerica | VG1: q112_4_northamerica | VH1: q112_5_northamerica | VI1: q112_6_northamerica | VJ1: q11ROW2_hidden_northamerica | VK1: q113_1_northamerica | VL1: q113_2_northamerica | VM1: q113_3_northamerica | VN1: q113_4_northamerica | VO1: q113_5_northamerica | VP1: q113_6_northamerica | VQ1: q11ROW3_hidden_northamerica | VR1: q114_1_northamerica | VS1: q114_2_northamerica | VT1: q114_3_northamerica | VU1: q114_4_northamerica | VV1: q114_5_northamerica | VW1: q114_6_northamerica | VX1: q11ROW4_hidden_northamerica | VY1: q115_1_northamerica | VZ1: q115_2_northamerica | WA1: q115_3_northamerica | WB1: q115_4_northamerica | WC1: q115_5_northamerica | WD1: q115_6_northamerica | WE1: q11ROW5_hidden_northamerica | WF1: q11COL1_hidden_northamerica | WG1: q11COL2_hidden_northamerica | WH1: q11COL3_hidden_northamerica | WI1: q11COL4_hidden_northamerica | WJ1: q11COL5_hidden_northamerica | WK1: q11COL6_hidden_northamerica | WL1: q11GRANDTotal_hidden_northamerica | WM1: Global_global | WN1: q101_1_global | WO1: q101_2_global | WP1: q101_3_global | WQ1: q101_4_global | WR1: q101_5_global | WS1: q101_6_global | WT1: q10ROW1_hidden_global | WU1: q102_1_global | WV1: q102_2_global | WW1: q102_3_global | WX1: q102_4_global | WY1: q102_5_global | WZ1: q102_6_global | XA1: q10ROW2_hidden_global | XB1: q103_1_global | XC1: q103_2_global | XD1: q103_3_global | XE1: q103_4_global | XF1: q103_5_global | XG1: q103_6_global | XH1: q10ROW3_hidden_global | XI1: q104_1_global | XJ1: q104_2_global | XK1: q104_3_global | XL1: q104_4_global | XM1: q104_5_global | XN1: q104_6_global | XO1: q10ROW4_hidden_global | XP1: q105_1_global | XQ1: q105_2_global | XR1: q105_3_global | XS1: q105_4_global | XT1: q105_5_global | XU1: q105_6_global | XV1: q10ROW5_hidden_global | XW1: q106_1_global | XX1: q106_2_global | XY1: q106_3_global | XZ1: q106_4_global | YA1: q106_5_global | YB1: q106_6_global | YC1: q10ROW6_hidden_global | YD1: q107_1_global | YE1: q107_2_global | YF1: q107_3_global | YG1: q107_4_global | YH1: q107_5_global | YI1: q107_6_global | YJ1: q10ROW7_hidden_global | YK1: q10other_global | YL1: q108_1_global | YM1: q108_2_global | YN1: q108_3_global | YO1: q108_4_global | YP1: q108_5_global | YQ1: q108_6_global | YR1: q10ROW8_hidden_global | YS1: q10COL1_hidden_global | YT1: q10COL2_hidden_global | YU1: q10COL3_hidden_global | YV1: q10COL4_hidden_global | YW1: q10COL5_hidden_global | YX1: q10COL6_hidden_global | YY1: q10GRANDTotal_hidden_global | YZ1: q111_1_global | ZA1: q111_2_global | ZB1: q111_3_global | ZC1: q111_4_global | ZD1: q111_5_global | ZE1: q111_6_global | ZF1: q11ROW1_hidden_global | ZG1: q112_1_global | ZH1: q112_2_global | ZI1: q112_3_global | ZJ1: q112_4_global | ZK1: q112_5_global | ZL1: q112_6_global | ZM1: q11ROW2_hidden_global | ZN1: q113_1_global | ZO1: q113_2_global | ZP1: q113_3_global | ZQ1: q113_4_global | ZR1: q113_5_global | ZS1: q113_6_global | ZT1: q11ROW3_hidden_global | ZU1: q114_1_global | ZV1: q114_2_global | ZW1: q114_3_global | ZX1: q114_4_global | ZY1: q114_5_global | ZZ1: q114_6_global | AAA1: q11ROW4_hidden_global | AAB1: q115_1_global | AAC1: q115_2_global | AAD1: q115_3_global | AAE1: q115_4_global | AAF1: q115_5_global | AAG1: q115_6_global | AAH1: q11ROW5_hidden_global | AAI1: q11COL1_hidden_global | AAJ1: q11COL2_hidden_global | AAK1: q11COL3_hidden_global | AAL1: q11COL4_hidden_global | AAM1: q11COL5_hidden_global | AAN1: q11COL6_hidden_global | AAO1: q11GRANDTotal_hidden_global | AAP1: SOUTH AMERICA_southamerica | AAQ1: q101_1_southamerica | AAR1: q101_2_southamerica | AAS1: q101_3_southamerica | AAT1: q101_4_southamerica | AAU1: q101_5_southamerica | AAV1: q101_6_southamerica | AAW1: q10ROW1_hidden_southamerica | AAX1: q102_1_southamerica | AAY1: q102_2_southamerica | AAZ1: q102_3_southamerica | ABA1: q102_4_southamerica | ABB1: q102_5_southamerica | ABC1: q102_6_southamerica | ABD1: q10ROW2_hidden_southamerica | ABE1: q103_1_southamerica | ABF1: q103_2_southamerica | ABG1: q103_3_southamerica | ABH1: q103_4_southamerica | ABI1: q103_5_southamerica | ABJ1: q103_6_southamerica | ABK1: q10ROW3_hidden_southamerica | ABL1: q104_1_southamerica | ABM1: q104_2_southamerica | ABN1: q104_3_southamerica | ABO1: q104_4_southamerica | ABP1: q104_5_southamerica | ABQ1: q104_6_southamerica | ABR1: q10ROW4_hidden_southamerica | ABS1: q105_1_southamerica | ABT1: q105_2_southamerica | ABU1: q105_3_southamerica | ABV1: q105_4_southamerica | ABW1: q105_5_southamerica | ABX1: q105_6_southamerica | ABY1: q10ROW5_hidden_southamerica | ABZ1: q106_1_southamerica | ACA1: q106_2_southamerica | ACB1: q106_3_southamerica | ACC1: q106_4_southamerica | ACD1: q106_5_southamerica | ACE1: q106_6_southamerica | ACF1: q10ROW6_hidden_southamerica | ACG1: q107_1_southamerica | ACH1: q107_2_southamerica | ACI1: q107_3_southamerica | ACJ1: q107_4_southamerica | ACK1: q107_5_southamerica | ACL1: q107_6_southamerica | ACM1: q10ROW7_hidden_southamerica | ACN1: q10other_southamerica | ACO1: q108_1_southamerica | ACP1: q108_2_southamerica | ACQ1: q108_3_southamerica | ACR1: q108_4_southamerica | ACS1: q108_5_southamerica | ACT1: q108_6_southamerica | ACU1: q10ROW8_hidden_southamerica | ACV1: q10COL1_hidden_southamerica | ACW1: q10COL2_hidden_southamerica | ACX1: q10COL3_hidden_southamerica | ACY1: q10COL4_hidden_southamerica | ACZ1: q10COL5_hidden_southamerica | ADA1: q10COL6_hidden_southamerica | ADB1: q10GRANDTotal_hidden_southamerica | ADC1: q111_1_southamerica | ADD1: q111_2_southamerica | ADE1: q111_3_southamerica | ADF1: q111_4_southamerica | ADG1: q111_5_southamerica | ADH1: q111_6_southamerica | ADI1: q11ROW1_hidden_southamerica | ADJ1: q112_1_southamerica | ADK1: q112_2_southamerica | ADL1: q112_3_southamerica | ADM1: q112_4_southamerica | ADN1: q112_5_southamerica | ADO1: q112_6_southamerica | ADP1: q11ROW2_hidden_southamerica | ADQ1: q113_1_southamerica | ADR1: q113_2_southamerica | ADS1: q113_3_southamerica | ADT1: q113_4_southamerica | ADU1: q113_5_southamerica | ADV1: q113_6_southamerica | ADW1: q11ROW3_hidden_southamerica | ADX1: q114_1_southamerica | ADY1: q114_2_southamerica | ADZ1: q114_3_southamerica | AEA1: q114_4_southamerica | AEB1: q114_5_southamerica | AEC1: q114_6_southamerica | AED1: q11ROW4_hidden_southamerica | AEE1: q115_1_southamerica | AEF1: q115_2_southamerica | AEG1: q115_3_southamerica | AEH1: q115_4_southamerica | AEI1: q115_5_southamerica | AEJ1: q115_6_southamerica | AEK1: q11ROW5_hidden_southamerica | AEL1: q11COL1_hidden_southamerica | AEM1: q11COL2_hidden_southamerica | AEN1: q11COL3_hidden_southamerica | AEO1: q11COL4_hidden_southamerica | AEP1: q11COL5_hidden_southamerica | AEQ1: q11COL6_hidden_southamerica | AER1: q11GRANDTotal_hidden_southamerica | AES1: AFRICA_africa | AET1: q101_1_africa | AEU1: q101_2_africa | AEV1: q101_3_africa | AEW1: q101_4_africa | AEX1: q101_5_africa | AEY1: q101_6_africa | AEZ1: q10ROW1_hidden_africa | AFA1: q102_1_africa | AFB1: q102_2_africa | AFC1: q102_3_africa | AFD1: q102_4_africa | AFE1: q102_5_africa | AFF1: q102_6_africa | AFG1: q10ROW2_hidden_africa | AFH1: q103_1_africa | AFI1: q103_2_africa | AFJ1: q103_3_africa | AFK1: q103_4_africa | AFL1: q103_5_africa | AFM1: q103_6_africa | AFN1: q10ROW3_hidden_africa | AFO1: q104_1_africa | AFP1: q104_2_africa | AFQ1: q104_3_africa | AFR1: q104_4_africa | AFS1: q104_5_africa | AFT1: q104_6_africa | AFU1: q10ROW4_hidden_africa | AFV1: q105_1_africa | AFW1: q105_2_africa | AFX1: q105_3_africa | AFY1: q105_4_africa | AFZ1: q105_5_africa | AGA1: q105_6_africa | AGB1: q10ROW5_hidden_africa | AGC1: q106_1_africa | AGD1: q106_2_africa | AGE1: q106_3_africa | AGF1: q106_4_africa | AGG1: q106_5_africa | AGH1: q106_6_africa | AGI1: q10ROW6_hidden_africa | AGJ1: q107_1_africa | AGK1: q107_2_africa | AGL1: q107_3_africa | AGM1: q107_4_africa | AGN1: q107_5_africa | AGO1: q107_6_africa | AGP1: q10ROW7_hidden_africa | AGQ1: q10other_africa | AGR1: q108_1_africa | AGS1: q108_2_africa | AGT1: q108_3_africa | AGU1: q108_4_africa | AGV1: q108_5_africa | AGW1: q108_6_africa | AGX1: q10ROW8_hidden_africa | AGY1: q10COL1_hidden_africa | AGZ1: q10COL2_hidden_africa | AHA1: q10COL3_hidden_africa | AHB1: q10COL4_hidden_africa | AHC1: q10COL5_hidden_africa | AHD1: q10COL6_hidden_africa | AHE1: q10GRANDTotal_hidden_africa | AHF1: q111_1_africa | AHG1: q111_2_africa | AHH1: q111_3_africa | AHI1: q111_4_africa | AHJ1: q111_5_africa | AHK1: q111_6_africa | AHL1: q11ROW1_hidden_africa | AHM1: q112_1_africa | AHN1: q112_2_africa | AHO1: q112_3_africa | AHP1: q112_4_africa | AHQ1: q112_5_africa | AHR1: q112_6_africa | AHS1: q11ROW2_hidden_africa | AHT1: q113_1_africa | AHU1: q113_2_africa | AHV1: q113_3_africa | AHW1: q113_4_africa | AHX1: q113_5_africa | AHY1: q113_6_africa | AHZ1: q11ROW3_hidden_africa | AIA1: q114_1_africa | AIB1: q114_2_africa | AIC1: q114_3_africa | AID1: q114_4_africa | AIE1: q114_5_africa | AIF1: q114_6_africa | AIG1: q11ROW4_hidden_africa | AIH1: q115_1_africa | AII1: q115_2_africa | AIJ1: q115_3_africa | AIK1: q115_4_africa | AIL1: q115_5_africa | AIM1: q115_6_africa | AIN1: q11ROW5_hidden_africa | AIO1: q11COL1_hidden_africa | AIP1: q11COL2_hidden_africa | AIQ1: q11COL3_hidden_africa | AIR1: q11COL4_hidden_africa | AIS1: q11COL5_hidden_africa | AIT1: q11COL6_hidden_africa | AIU1: q11GRANDTotal_hidden_africa | AIV1: Domain
A2: A0BHE1R | B2: ANREV | C2: Proprium Capital Partners, L.P. | E2: rajul.patel@proprium.com | G2: https://secure.surveylab.co.uk/anrev-inrev-ncreif-capital-raising-2018/default.asp?survey=A0BHE1R | T2: FALSE | U2: FALSE | V2: FALSE | W2: FALSE | X2: FALSE | Y2: FALSE | Z2: 447 | AA2: 43153.792 | AB2: 38.88.11.74 | AC2: 2018 | AD2: Rajul Patel | AE2: Proprium Capital Partners, L.P. | AF2: =VLOOKUP(MID(E2,SEARCH("@",E2,1),LEN(E2)-SEARCH("@",E2,1)+1),[2]Sheet1!$D:$F,3,FALSE) -> M0201 | AG2: Principal | AH2: rajul.patel@proprium.com | AI2: 404-334-3312 | AJ2: United States | AK2: USD | AM2: 2 | AN2: 6 | AO2: Started Marketing Process during the year | AV2: 0 | BC2: 0 | BJ2: 0 | BQ2: 0 | BX2: 0 | CE2: 0 | CF2: 0 | CG2: 0 | CH2: 0 | CI2: 0 | CJ2: 0 | CK2: 0 | CL2: 0 | CS2: 0 | CZ2: 0 | DG2: 0 | DN2: 0 | DU2: 0 | EB2: 0 | EC2: 0 | ED2: 0 | EE2: 0 | EF2: 0 | EG2: 0 | EH2: 0 | EI2: 0 | EJ2: NO | EK2: NO | EL2: NO | EM2: NO | EN2: NO | EO2: NO | EP2: NO | EQ2: NO | ER2: NO | ES2: NO | ET2: NO | EU2: NO | EV2: NO | EW2: NO | EX2: NO | EY2: NO | EZ2: NO | FA2: NO | FB2: NO | FC2: NO | FD2: NO | FE2: NO | FF2: NO | FG2: NO | FH2: NO | FI2: NO | FJ2: NO | FK2: NO | FL2: NO | FM2: NO | FN2: NO | FO2: NO | FP2: NO | FQ2: NO | FR2: NO | FS2: NO | FZ2: 0 | GG2: 0 | GN2: 0 | GU2: 0 | HB2: 0 | HI2: 0 | HP2: 0 | HX2: 0 | HY2: 0 | HZ2: 0 | IA2: 0 | IB2: 0 | IC2: 0 | ID2: 0 | IE2: 0 | IL2: 0 | IS2: 0 | IZ2: 0 | JG2: 0 | JN2: 0 | JO2: 0 | JP2: 0 | JQ2: 0 | JR2: 0 | JS2: 0 | JT2: 0 | JU2: 0 | KA2: 1 | KB2: 3 | KC2: 1 | KD2: START Asia Pacific: | OG2: START Europe: | SJ2: START North America: | WM2: START Global: | AAP2: START SOUTH America: | AES2: START Africa: | AIV2: =IFERROR(RIGHT(AH2,LEN(AH2)-SEARCH("@",AH2,1)),"") -> proprium.com
A3: A0JVE5M | B3: ANREV | C3: Tokyu Land Capital Management | E3: Yumiko_Nakamoto@tokyu-tlcm.co.jp | G3: https://secure.surveylab.co.uk/anrev-inrev-ncreif-capital-raising-2018/default.asp?survey=A0JVE5M | T3: FALSE | U3: TRUE | V3: FALSE | W3: FALSE | X3: FALSE | Y3: FALSE | Z3: 472 | AA3: 43165.403 | AB3: 118.103.94.201 | AC3: 2018 | AD3: Yumiko Nakamoto | AE3: Tokyu Land Capital Management Inc. | AF3: =VLOOKUP(MID(E3,SEARCH("@",E3,1),LEN(E3)-SEARCH("@",E3,1)+1),[2]Sheet1!$D:$F,3,FALSE) -> M0298 | AG3: Manager | AH3: Yumiko_Nakamoto@tokyu-tlcm.co.jp | AI3: -16835 | AJ3: Japan | AK3: JPY | AM3: 1 | AR3: 127.1 | AV3: 127.1 | BC3: 0 | BJ3: 0 | BQ3: 0 | BX3: 0 | CE3: 0 | CF3: 0 | CG3: 0 | CH3: 127.1 | CI3: 0 | CJ3: 0 | CK3: 0 | CL3: 127.1 | CO3: 7 | CS3: 7 | CZ3: 0 | DG3: 0 | DN3: 0 | DU3: 0 | EB3: 0 | EC3: 0 | ED3: 0 | EE3: 7 | EF3: 0 | EG3: 0 | EH3: 0 | EI3: 7 | EJ3: NO | EK3: NO | EL3: YES | EM3: NO | EN3: NO | EO3: NO | EP3: NO | EQ3: NO | ER3: NO | ES3: NO | ET3: NO | EU3: NO | EV3: NO | EW3: NO | EX3: NO | EY3: NO | EZ3: NO | FA3: NO | FB3: NO | FC3: NO | FD3: NO | FE3: NO | FF3: NO | FG3: NO | FH3: NO | FI3: NO | FJ3: NO | FK3: NO | FL3: NO | FM3: NO | FN3: NO | FO3: NO | FP3: NO | FQ3: NO | FR3: NO | FS3: NO | FZ3: 0 | GG3: 0 | GN3: 0 | GU3: 0 | HB3: 0 | HI3: 0 | HP3: 0 | HT3: 127.1 | HX3: 127.1 | HY3: 0 | HZ3: 0 | IA3: 127.1 | IB3: 0 | IC3: 0 | ID3: 0 | IE3: 127.1 | IH3: 127.1 | IL3: 127.1 | IS3: 0 | IZ3: 0 | JG3: 0 | JN3: 0 | JO3: 0 | JP3: 0 | JQ3: 127.1 | JR3: 0 | JS3: 0 | JT3: 0 | JU3: 127.1 | JX3: 100 | KA3: 3 | KB3: 3 | KC3: 1 | KD3: START Asia Pacific: | OG3: START Europe: | SJ3: START North America: | WM3: START Global: | AAP3: START SOUTH America: | AES3: START Africa: | AIV3: =IFERROR(RIGHT(AH3,LEN(AH3)-SEARCH("@",AH3,1)),"") -> tokyu-tlcm.co.jp
A4: A0QKG9H | B4: ANREV | C4: KaiLong Investments | E4: don.tan@kailongrei.com | G4: https://secure.surveylab.co.uk/anrev-inrev-ncreif-capital-raising-2018/default.asp?survey=A0QKG9H | H4: asia | I4: 43138.342 | T4: FALSE | U4: TRUE | V4: FALSE | W4: FALSE | X4: FALSE | Y4: FALSE | Z4: 417 | AA4: 43138.34 | AB4: 180.87.13.170 | AC4: 2018 | AD4: Don Tan | AE4: KaiLong Investments | AF4: =VLOOKUP(MID(E4,SEARCH("@",E4,1),LEN(E4)-SEARCH("@",E4,1)+1),[2]Sheet1!$D:$F,3,FALSE) -> M0226 | AG4: SVP, Fund Management | AH4: don.tan@kailongrei.com | AI4: 85237982627 | AJ4: China | AK4: USD | AM4: 1 | AQ4: 176 | AV4: 176 | BC4: 0 | BJ4: 0 | BQ4: 0 | BX4: 0 | CE4: 0 | CF4: 0 | CG4: 176 | CH4: 0 | CI4: 0 | CJ4: 0 | CK4: 0 | CL4: 176 | CN4: 2 | CS4: 2 | CZ4: 0 | DG4: 0 | DN4: 0 | DU4: 0 | EB4: 0 | EC4: 0 | ED4: 2 | EE4: 0 | EF4: 0 | EG4: 0 | EH4: 0 | EI4: 2 | EJ4: NO | EK4: YES | EL4: NO | EM4: NO | EN4: NO | EO4: NO | EP4: NO | EQ4: NO | ER4: NO | ES4: NO | ET4: NO | EU4: NO | EV4: NO | EW4: NO | EX4: NO | EY4: NO | EZ4: NO | FA4: NO | FB4: NO | FC4: NO | FD4: NO | FE4: NO | FF4: NO | FG4: NO | FH4: NO | FI4: NO | FJ4: NO | FK4: NO | FL4: NO | FM4: NO | FN4: NO | FO4: NO | FP4: NO | FQ4: NO | FR4: NO | FS4: NO | FZ4: 0 | GG4: 0 | GN4: 0 | GP4: 5 | GU4: 5 | HB4: 0 | HI4: 0 | HK4: 132 | HP4: 132 | HQ4: Banks | HS4: 39 | HX4: 39 | HY4: 0 | HZ4: 176 | IA4: 0 | IB4: 0 | IC4: 0 | ID4: 0 | IE4: 176 | IG4: 156 | IL4: 156 | IN4: 20 | IS4: 20 | IZ4: 0 | JG4: 0 | JN4: 0 | JO4: 0 | JP4: 176 | JQ4: 0 | JR4: 0 | JS4: 0 | JT4: 0 | JU4: 176 | JX4: 100 | KA4: 1 | KB4: 1 | KC4: 1 | KD4: START Asia Pacific: | KK4: 0 | KR4: 0 | KY4: 0 | LA4: 20 | LF4: 20 | LM4: 0 | LT4: 0 | LV4: 116 | MA4: 116 | MB4: Banks | MD4: 40 | MI4: 40 | MJ4: 0 | MK4: 176 | ML4: 0 | MM4: 0 | MN4: 0 | MO4: 0 | MP4: 176 | MR4: 20 | MW4: 20 | MY4: 156 | ND4: 156 | NK4: 0 | NR4: 0 | NY4: 0 | NZ4: 0 | OA4: 176 | OB4: 0 | OC4: 0 | OD4: 0 | OE4: 0 | OF4: 176 | OG4: START Europe: | SJ4: START North America: | WM4: START Global: | AAP4: START SOUTH America: | AES4: START Africa: | AIV4: =IFERROR(RIGHT(AH4,LEN(AH4)-SEARCH("@",AH4,1)),"") -> kailongrei.com
A5: A0QVB6X | B5: ANREV | C5: EG Fund Management | E5: rparker@eg.com.au | G5: https://secure.surveylab.co.uk/anrev-inrev-ncreif-capital-raising-2018/default.asp?survey=A0QVB6X | H5: asia | I5: 43123.292 | T5: FALSE | U5: TRUE | V5: FALSE | W5: FALSE | X5: FALSE | Y5: FALSE | Z5: 369 | AA5: 43123.29 | AB5: 59.100.170.162 | AC5: 2018 | AD5: Linh Pham | AE5: EG Funds Management | AF5: =VLOOKUP(MID(E5,SEARCH("@",E5,1),LEN(E5)-SEARCH("@",E5,1)+1),[2]Sheet1!$D:$F,3,FALSE) -> M0249 | AG5: Analyst | AH5: lpham@eg.com.au | AJ5: Australia | AK5: AUD | AM5: 1 | AP5: 67.5 | AV5: 67.5 | BC5: 0 | BJ5: 0 | BQ5: 0 | BX5: 0 | CE5: 0 | CF5: 67.5 | CG5: 0 | CH5: 0 | CI5: 0 | CJ5: 0 | CK5: 0 | CL5: 67.5 | CM5: 2 | CS5: 2 | CZ5: 0 | DG5: 0 | DN5: 0 | DU5: 0 | EB5: 0 | EC5: 2 | ED5: 0 | EE5: 0 | EF5: 0 | EG5: 0 | EH5: 0 | EI5: 2 | EJ5: YES | EK5: NO | EL5: NO | EM5: NO | EN5: NO | EO5: NO | EP5: NO | EQ5: NO | ER5: NO | ES5: NO | ET5: NO | EU5: NO | EV5: NO | EW5: NO | EX5: NO | EY5: NO | EZ5: NO | FA5: NO | FB5: NO | FC5: NO | FD5: NO | FE5: NO | FF5: NO | FG5: NO | FH5: NO | FI5: NO | FJ5: NO | FK5: NO | FL5: NO | FM5: NO | FN5: NO | FO5: NO | FP5: NO | FQ5: NO | FR5: NO | FS5: NO | FT5: 60 | FZ5: 60 | GG5: 0 | GN5: 0 | GU5: 0 | HB5: 0 | HI5: 0 | HP5: 0 | HQ5: Endowment Fund | HR5: 7.5 | HX5: 7.5 | HY5: 67.5 | HZ5: 0 | IA5: 0 | IB5: 0 | IC5: 0 | ID5: 0 | IE5: 67.5 | IF5: 67.5 | IL5: 67.5 | IS5: 0 | IZ5: 0 | JG5: 0 | JN5: 0 | JO5: 67.5 | JP5: 0 | JQ5: 0 | JR5: 0 | JS5: 0 | JT5: 0 | JU5: 67.5 | JX5: 100 | KA5: 1 | KB5: 2 | KC5: 1 | KD5: START Asia Pacific: | KE5: 67.5 | KK5: 67.5 | KR5: 0 | KY5: 0 | LF5: 0 | LM5: 0 | LT5: 0 | MA5: 0 | MI5: 0 | MJ5: 67.5 | MK5: 0 | ML5: 0 | MM5: 0 | MN5: 0 | MO5: 0 | MP5: 67.5 | MW5: 0 | MX5: 67.5 | ND5: 67.5 | NK5: 0 | NR5: 0 | NY5: 0 | NZ5: 67.5 | OA5: 0 | OB5: 0 | OC5: 0 | OD5: 0 | OE5: 0 | OF5: 67.5 | OG5: START Europe: | SJ5: START North America: | WM5: START Global: | AAP5: START SOUTH America: | AES5: START Africa: | AIV5: =IFERROR(RIGHT(AH5,LEN(AH5)-SEARCH("@",AH5,1)),"") -> eg.com.au
A6: A0WWG6Z | B6: ANREV | C6: Mitsubishi UFJ Trust and Banking Corporation | E6: soichiro_tabu@tr.mufg.jp | G6: https://secure.surveylab.co.uk/anrev-inrev-ncreif-capital-raising-2018/default.asp?survey=A0WWG6Z | H6: asia | I6: 43138.039 | T6: FALSE | U6: TRUE | V6: FALSE | W6: FALSE | X6: FALSE | Y6: FALSE | Z6: 412 | AA6: 43138.038 | AB6: 103.9.97.232 | AC6: 2018 | AD6: Soichiro Tabu | AE6: Mitsubishi UFJ Trust and Banking Corporation | AF6: =VLOOKUP(MID(E6,SEARCH("@",E6,1),LEN(E6)-SEARCH("@",E6,1)+1),[2]Sheet1!$D:$F,3,FALSE) -> M0232 | AG6: Senior Manager | AH6: soichiro.tabu@tr.mufg.jp | AI6: 8162146580 | AJ6: Japan | AK6: JPY | AM6: 1 | AQ6: 1000 | AV6: 1000 | BC6: 0 | BJ6: 0 | BQ6: 0 | BX6: 0 | CE6: 0 | CF6: 0 | CG6: 1000 | CH6: 0 | CI6: 0 | CJ6: 0 | CK6: 0 | CL6: 1000 | CN6: 1 | CS6: 1 | CZ6: 0 | DG6: 0 | DN6: 0 | DU6: 0 | EB6: 0 | EC6: 0 | ED6: 1 | EE6: 0 | EF6: 0 | EG6: 0 | EH6: 0 | EI6: 1 | EJ6: NO | EK6: YES | EL6: NO | EM6: NO | EN6: NO | EO6: NO | EP6: NO | EQ6: NO | ER6: NO | ES6: NO | ET6: NO | EU6: NO | EV6: NO | EW6: NO | EX6: NO | EY6: NO | EZ6: NO | FA6: NO | FB6: NO | FC6: NO | FD6: NO | FE6: NO | FF6: NO | FG6: NO | FH6: NO | FI6: NO | FJ6: NO | FK6: NO | FL6: NO | FM6: NO | FN6: NO | FO6: NO | FP6: NO | FQ6: NO | FR6: NO | FS6: NO | FZ6: 0 | GG6: 0 | GN6: 0 | GU6: 0 | HB6: 0 | HD6: 1000 | HI6: 1000 | HP6: 0 | HX6: 0 | HY6: 0 | HZ6: 1000 | IA6: 0 | IB6: 0 | IC6: 0 | ID6: 0 | IE6: 1000 | IG6: 1000 | IL6: 1000 | IS6: 0 | IZ6: 0 | JG6: 0 | JN6: 0 | JO6: 0 | JP6: 1000 | JQ6: 0 | JR6: 0 | JS6: 0 | JT6: 0 | JU6: 1000 | JX6: 100 | KA6: 1 | KB6: 1 | KC6: 1 | KD6: START Asia Pacific: | KK6: 0 | KR6: 0 | KY6: 0 | LF6: 0 | LM6: 0 | LO6: 1000 | LT6: 1000 | MA6: 0 | MI6: 0 | MJ6: 0 | MK6: 1000 | ML6: 0 | MM6: 0 | MN6: 0 | MO6: 0 | MP6: 1000 | MW6: 0 | MY6: 1000 | ND6: 1000 | NK6: 0 | NR6: 0 | NY6: 0 | NZ6: 0 | OA6: 1000 | OB6: 0 | OC6: 0 | OD6: 0 | OE6: 0 | OF6: 1000 | OG6: START Europe: | SJ6: START North America: | WM6: START Global: | AAP6: START SOUTH America: | AES6: START Africa: | AIV6: =IFERROR(RIGHT(AH6,LEN(AH6)-SEARCH("@",AH6,1)),"") -> tr.mufg.jp
A7: A1EZQ9H | B7: ANREV | C7: Creditease | E7: pengzhang@creditease.hk | G7: https://secure.surveylab.co.uk/anrev-inrev-ncreif-capital-raising-2018/default.asp?survey=A1EZQ9H | T7: FALSE | U7: FALSE | V7: FALSE | W7: FALSE | X7: FALSE | Y7: FALSE | Z7: 409 | AA7: 43136.38 | AB7: 42.61.55.10 | AC7: 2018 | AD7: Evangeline Ho | AE7: CreditEase Asset Management (Singapore) Pte Ltd | AF7: =VLOOKUP(MID(E7,SEARCH("@",E7,1),LEN(E7)-SEARCH("@",E7,1)+1),[2]Sheet1!$D:$F,3,FALSE) -> N0278 | AH7: evangeline.ho@creditease.com.sg | AJ7: China | AK7: USD | AM7: 2 | AN7: 6 | AO7: Focus is on HNWI | AV7: 0 | BC7: 0 | BJ7: 0 | BQ7: 0 | BX7: 0 | CE7: 0 | CF7: 0 | CG7: 0 | CH7: 0 | CI7: 0 | CJ7: 0 | CK7: 0 | CL7: 0 | CS7: 0 | CZ7: 0 | DG7: 0 | DN7: 0 | DU7: 0 | EB7: 0 | EC7: 0 | ED7: 0 | EE7: 0 | EF7: 0 | EG7: 0 | EH7: 0 | EI7: 0 | EJ7: NO | EK7: NO | EL7: NO | EM7: NO | EN7: NO | EO7: NO | EP7: NO | EQ7: NO | ER7: NO | ES7: NO | ET7: NO | EU7: NO | EV7: NO | EW7: NO | EX7: NO | EY7: NO | EZ7: NO | FA7: NO | FB7: NO | FC7: NO | FD7: NO | FE7: NO | FF7: NO | FG7: NO | FH7: NO | FI7: NO | FJ7: NO | FK7: NO | FL7: NO | FM7: NO | FN7: NO | FO7: NO | FP7: NO | FQ7: NO | FR7: NO | FS7: NO | FZ7: 0 | GG7: 0 | GN7: 0 | GU7: 0 | HB7: 0 | HI7: 0 | HP7: 0 | HX7: 0 | HY7: 0 | HZ7: 0 | IA7: 0 | IB7: 0 | IC7: 0 | ID7: 0 | IE7: 0 | IL7: 0 | IS7: 0 | IZ7: 0 | JG7: 0 | JN7: 0 | JO7: 0 | JP7: 0 | JQ7: 0 | JR7: 0 | JS7: 0 | JT7: 0 | JU7: 0 | KA7: 2 | KB7: 2 | KC7: 2 | KD7: START Asia Pacific: | OG7: START Europe: | SJ7: START North America: | WM7: START Global: | AAP7: START SOUTH America: | AES7: START Africa: | AIV7: =IFERROR(RIGHT(AH7,LEN(AH7)-SEARCH("@",AH7,1)),"") -> creditease.com.sg
A8: A1MCM9B | B8: ANREV | C8: Kenedix, Inc. | E8: masahiko_tajima@kenedix.com | G8: https://secure.surveylab.co.uk/anrev-inrev-ncreif-capital-raising-2018/default.asp?survey=A1MCM9B | T8: FALSE | U8: FALSE | V8: FALSE | W8: FALSE | X8: FALSE | Y8: FALSE | Z8: 384 | AA8: 43146.075 | AB8: 119.245.128.17 | AC8: 2018 | AD8: Motohiro Horiuchi | AE8: Kenedix, Inc. | AF8: =VLOOKUP(MID(E8,SEARCH("@",E8,1),LEN(E8)-SEARCH("@",E8,1)+1),[2]Sheet1!$D:$F,3,FALSE) -> M0230 | AH8: motohiro_horiuchi@kenedix.com | AJ8: Japan | AK8: JPY | AM8: 1 | AV8: 0 | BC8: 0 | BJ8: 0 | BQ8: 0 | BX8: 0 | CE8: 0 | CF8: 0 | CG8: 0 | CH8: 0 | CI8: 0 | CJ8: 0 | CK8: 0 | CL8: 0 | CS8: 0 | CZ8: 0 | DG8: 0 | DN8: 0 | DU8: 0 | EB8: 0 | EC8: 0 | ED8: 0 | EE8: 0 | EF8: 0 | EG8: 0 | EH8: 0 | EI8: 0 | EJ8: NO | EK8: NO | EL8: NO | EM8: NO | EN8: NO | EO8: NO | EP8: NO | EQ8: NO | ER8: NO | ES8: NO | ET8: NO | EU8: NO | EV8: NO | EW8: NO | EX8: NO | EY8: NO | EZ8: NO | FA8: NO | FB8: NO | FC8: NO | FD8: NO | FE8: NO | FF8: NO | FG8: NO | FH8: NO | FI8: NO | FJ8: NO | FK8: NO | FL8: NO | FM8: NO | FN8: NO | FO8: NO | FP8: NO | FQ8: NO | FR8: NO | FS8: NO | FZ8: 0 | GG8: 0 | GN8: 0 | GU8: 0 | HB8: 0 | HI8: 0 | HP8: 0 | HX8: 0 | HY8: 0 | HZ8: 0 | IA8: 0 | IB8: 0 | IC8: 0 | ID8: 0 | IE8: 0 | IL8: 0 | IS8: 0 | IZ8: 0 | JG8: 0 | JN8: 0 | JO8: 0 | JP8: 0 | JQ8: 0 | JR8: 0 | JS8: 0 | JT8: 0 | JU8: 0 | KA8: 1 | KB8: 3 | KC8: 2 | KD8: START Asia Pacific: | OG8: START Europe: | SJ8: START North America: | WM8: START Global: | AAP8: START SOUTH America: | AES8: START Africa: | AIV8: =IFERROR(RIGHT(AH8,LEN(AH8)-SEARCH("@",AH8,1)),"") -> kenedix.com
A9: A1NJV4Y | B9: ANREV | C9: Pamfleet | E9: singuz.lo@pamfleet.com | G9: https://secure.surveylab.co.uk/anrev-inrev-ncreif-capital-raising-2018/default.asp?survey=A1NJV4Y | T9: FALSE | U9: FALSE | V9: FALSE | W9: FALSE | X9: FALSE | Y9: FALSE | Z9: 483 | AA9: 43160.272 | AB9: 118.200.5.237 | AC9: 2018 | AD9: YC TANG | AE9: PAMFLEET | AF9: =VLOOKUP(MID(E9,SEARCH("@",E9,1),LEN(E9)-SEARCH("@",E9,1)+1),[2]Sheet1!$D:$F,3,FALSE) -> M0125 | AG9: Director | AH9: yc.tang@pamfleet.com | AI9: +65 6325 0160 | AJ9: Hong Kong | AK9: USD | AM9: 2 | AN9: 6 | AO9: no product | AV9: 0 | BC9: 0 | BJ9: 0 | BQ9: 0 | BX9: 0 | CE9: 0 | CF9: 0 | CG9: 0 | CH9: 0 | CI9: 0 | CJ9: 0 | CK9: 0 | CL9: 0 | CS9: 0 | CZ9: 0 | DG9: 0 | DN9: 0 | DU9: 0 | EB9: 0 | EC9: 0 | ED9: 0 | EE9: 0 | EF9: 0 | EG9: 0 | EH9: 0 | EI9: 0 | EJ9: NO | EK9: NO | EL9: NO | EM9: NO | EN9: NO | EO9: NO | EP9: NO | EQ9: NO | ER9: NO | ES9: NO | ET9: NO | EU9: NO | EV9: NO | EW9: NO | EX9: NO | EY9: NO | EZ9: NO | FA9: NO | FB9: NO | FC9: NO | FD9: NO | FE9: NO | FF9: NO | FG9: NO | FH9: NO | FI9: NO | FJ9: NO | FK9: NO | FL9: NO | FM9: NO | FN9: NO | FO9: NO | FP9: NO | FQ9: NO | FR9: NO | FS9: NO | FZ9: 0 | GG9: 0 | GN9: 0 | GU9: 0 | HB9: 0 | HI9: 0 | HP9: 0 | HX9: 0 | HY9: 0 | HZ9: 0 | IA9: 0 | IB9: 0 | IC9: 0 | ID9: 0 | IE9: 0 | IL9: 0 | IS9: 0 | IZ9: 0 | JG9: 0 | JN9: 0 | JO9: 0 | JP9: 0 | JQ9: 0 | JR9: 0 | JS9: 0 | JT9: 0 | JU9: 0 | KA9: 1 | KB9: 2 | KC9: 1 | KD9: START Asia Pacific: | OG9: START Europe: | SJ9: START North America: | WM9: START Global: | AAP9: START SOUTH America: | AES9: START Africa: | AIV9: =IFERROR(RIGHT(AH9,LEN(AH9)-SEARCH("@",AH9,1)),"") -> pamfleet.com
A10: A1PBK7A | B10: ANREV | C10: Additional Record | E10: Arvydas.Jadevicius@inrev.org | G10: https://secure.surveylab.co.uk/anrev-inrev-ncreif-capital-raising-2018/default.asp?survey=A1PBK7A | H10: asia | I10: 43161.158 | L10: northamerica | M10: 43161.159 | N10: global | O10: 43161.16 | T10: FALSE | U10: TRUE | V10: TRUE | W10: TRUE | X10: FALSE | Y10: FALSE | Z10: 366 | AA10: 43161.157 | AB10: 101.78.165.56 | AC10: 2018 | AD10: Paul Keogh | AE10: Morgan Stanley Real Estate Investing | AF10: =VLOOKUP(MID(E10,SEARCH("@",E10,1),LEN(E10)-SEARCH("@",E10,1)+1),[2]Sheet1!$D:$F,3,FALSE) -> M636 | AG10: Managing Director | AH10: paul.keogh@morganstanley.com | AI10: +65 6834-8388 | AJ10: United States | AK10: USD | AM10: 1 | AP10: 471 | AV10: 471 | BC10: 0 | BD10: 1960.78 | BJ10: 1960.78 | BK10: 2577.36 | BQ10: 2577.36 | BX10: 0 | CE10: 0 | CF10: 5009.14 | CG10: 0 | CH10: 0 | CI10: 0 | CJ10: 0 | CK10: 0 | CL10: 5009.14 | CM10: 1 | CS10: 1 | CZ10: 0 | DA10: 1 | DG10: 1 | DH10: 1 | DN10: 1 | DU10: 0 | EB10: 0 | EC10: 3 | ED10: 0 | EE10: 0 | EF10: 0 | EG10: 0 | EH10: 0 | EI10: 3 | EJ10: YES | EK10: NO | EL10: NO | EM10: NO | EN10: NO | EO10: NO | EP10: NO | EQ10: NO | ER10: NO | ES10: NO | ET10: NO | EU10: NO | EV10: YES | EW10: NO | EX10: NO | EY10: NO | EZ10: NO | FA10: NO | FB10: YES | FC10: NO | FD10: NO | FE10: NO | FF10: NO | FG10: NO | FH10: NO | FI10: NO | FJ10: NO | FK10: NO | FL10: NO | FM10: NO | FN10: NO | FO10: NO | FP10: NO | FQ10: NO | FR10: NO | FS10: NO | FT10: 2108.55 | FZ10: 2108.55 | GA10: 466 | GG10: 466 | GH10: 825 | GN10: 825 | GO10: 519 | GU10: 519 | GV10: 214.11 | HB10: 214.11 | HC10: 522.67 | HI10: 522.67 | HJ10: 88.2 | HP10: 88.2 | HQ10: Corporations, Unions, Taft-Hartley, Trusts | HR10: 265.62 | HX10: 265.62 | HY10: 5009.15 | HZ10: 0 | IA10: 0 | IB10: 0 | IC10: 0 | ID10: 0 | IE10: 5009.15 | IF10: 1251.57 | IL10: 1251.57 | IM10: 2076.8 | IS10: 2076.8 | IT10: 1680.77 | IZ10: 1680.77 | JG10: 0 | JN10: 0 | JO10: 5009.14 | JP10: 0 | JQ10: 0 | JR10: 0 | JS10: 0 | JT10: 0 | JU10: 5009.14 | JX10: 100 | KA10: 3 | KB10: 3 | KC10: 1 | KD10: START Asia Pacific: | KE10: 205.83 | KK10: 205.83 | KL10: 25 | KR10: 25 | KY10: 0 | LF10: 0 | LM10: 0 | LN10: 230.17 | LT10: 230.17 | MA10: 0 | MC10: 10 | MI10: 10 | MJ10: 471 | MK10: 0 | ML10: 0 | MM10: 0 | MN10: 0 | MO10: 0 | MP10: 471 | MQ10: 461 | MW10: 461 | MX10: 10 | ND10: 10 | NK10: 0 | NR10: 0 | NY10: 0 | NZ10: 471 | OA10: 0 | OB10: 0 | OC10: 0 | OD10: 0 | OE10: 0 | OF10: 471 | OG10: START Europe: | SJ10: START North America: | SK10: 1264.41 | SQ10: 1264.41 | SR10: 44 | SX10: 44 | TE10: 0 | TF10: 119 | TL10: 119 | TM10: 214.11 | TS10: 214.11 | TT10: 232.5 | TZ10: 232.5 | UA10: 7.2 | UG10: 7.2 | UI10: 79.56 | UO10: 79.56 | UP10: 1960.78 | UQ10: 0 | UR10: 0 | US10: 0 | UT10: 0 | UU10: 0 | UV10: 1960.78 | UW10: 220 | VC10: 220 | VD10: 256.32 | VJ10: 256.32 | VK10: 1484.46 | VQ10: 1484.46 | VX10: 0 | WE10: 0 | WF10: 1960.78 | WG10: 0 | WH10: 0 | WI10: 0 | WJ10: 0 | WK10: 0 | WL10: 1960.78 | WM10: START Global: | WN10: 638.3 | WT10: 638.3 | WU10: 397 | XA10: 397 | XB10: 825 | XH10: 825 | XI10: 400 | XO10: 400 | XV10: 0 | XW10: 60 | YC10: 60 | YD10: 81 | YJ10: 81 | YL10: 176.06 | YR10: 176.06 | YS10: 2577.36 | YT10: 0 | YU10: 0 | YV10: 0 | YW10: 0 | YX10: 0 | YY10: 2577.36 | YZ10: 1395.8 | ZF10: 1395.8 | ZG10: 985.25 | ZM10: 985.25 | ZN10: 196.31 | ZT10: 196.31 | AAA10: 0 | AAH10: 0 | AAI10: 2577.36 | AAJ10: 0 | AAK10: 0 | AAL10: 0 | AAM10: 0 | AAN10: 0 | AAO10: 2577.36 | AAP10: START SOUTH America: | AES10: START Africa: | AIV10: =IFERROR(RIGHT(AH10,LEN(AH10)-SEARCH("@",AH10,1)),"") -> morganstanley.com
A11: A1PXF1R | B11: ANREV | C11: Chelsfield | E11: wlo@chelsfield.com | G11: https://secure.surveylab.co.uk/anrev-inrev-ncreif-capital-raising-2018/default.asp?survey=A1PXF1R | T11: FALSE | U11: FALSE | V11: FALSE | W11: FALSE | X11: FALSE | Y11: FALSE | Z11: 456 | AA11: 43171.522 | AB11: 218.255.227.142 | AC11: 2018 | AD11: William Lo | AE11: Chelsfield Asia (Hong Kong) Limited | AF11: =VLOOKUP(MID(E11,SEARCH("@",E11,1),LEN(E11)-SEARCH("@",E11,1)+1),[2]Sheet1!$D:$F,3,FALSE) -> M03089 | AG11: Chief Operating Officer | AH11: wlo@chelsfield.com | AI11: +852 3589 5562 | AJ11: United Kingdom | AK11: USD | AM11: 1 | AV11: 0 | BC11: 0 | BJ11: 0 | BQ11: 0 | BX11: 0 | CE11: 0 | CF11: 0 | CG11: 0 | CH11: 0 | CI11: 0 | CJ11: 0 | CK11: 0 | CL11: 0 | CS11: 0 | CZ11: 0 | DG11: 0 | DN11: 0 | DU11: 0 | EB11: 0 | EC11: 0 | ED11: 0 | EE11: 0 | EF11: 0 | EG11: 0 | EH11: 0 | EI11: 0 | EJ11: NO | EK11: NO | EL11: NO | EM11: NO | EN11: NO | EO11: NO | EP11: NO | EQ11: NO | ER11: NO | ES11: NO | ET11: NO | EU11: NO | EV11: NO | EW11: NO | EX11: NO | EY11: NO | EZ11: NO | FA11: NO | FB11: NO | FC11: NO | FD11: NO | FE11: NO | FF11: NO | FG11: NO | FH11: NO | FI11: NO | FJ11: NO | FK11: NO | FL11: NO | FM11: NO | FN11: NO | FO11: NO | FP11: NO | FQ11: NO | FR11: NO | FS11: NO | FZ11: 0 | GG11: 0 | GN11: 0 | GU11: 0 | HB11: 0 | HI11: 0 | HP11: 0 | HX11: 0 | HY11: 0 | HZ11: 0 | IA11: 0 | IB11: 0 | IC11: 0 | ID11: 0 | IE11: 0 | IL11: 0 | IS11: 0 | IZ11: 0 | JG11: 0 | JN11: 0 | JO11: 0 | JP11: 0 | JQ11: 0 | JR11: 0 | JS11: 0 | JT11: 0 | JU11: 0 | KC11: 1 | KD11: START Asia Pacific: | OG11: START Europe: | SJ11: START North America: | WM11: START Global: | AAP11: START SOUTH America: | AES11: START Africa: | AIV11: =IFERROR(RIGHT(AH11,LEN(AH11)-SEARCH("@",AH11,1)),"") -> chelsfield.com
A12: A1QPU4E | B12: ANREV | C12: Mitsui Fudosan Investment Advisors, Inc. | E12: k-hiratani@mfia.co.jp | G12: https://secure.surveylab.co.uk/anrev-inrev-ncreif-capital-raising-2018/default.asp?survey=A1QPU4E | H12: asia | I12: 43152.285 | T12: FALSE | U12: TRUE | V12: FALSE | W12: FALSE | X12: FALSE | Y12: FALSE | Z12: 346 | AA12: 43152.283 | AB12: 101.78.165.56 | AC12: 2018 | AD12: NAKAO IIJIMA | AE12: Mitsui Fudosan Investment Advisors, Inc. | AF12: =VLOOKUP(MID(E12,SEARCH("@",E12,1),LEN(E12)-SEARCH("@",E12,1)+1),[2]Sheet1!$D:$F,3,FALSE) -> M0177 | AG12: General Manager, Research Department | AH12: n-iijima@mfia.co.jp | AI12: 81-3-3246-3332 | AJ12: Japan | AK12: JPY | AM12: 1 | AP12: 2930 | AQ12: 3182 | AR12: 0 | AS12: 0 | AT12: 0 | AU12: 0 | AV12: 6112 | AW12: 0 | AX12: 0 | AY12: 0 | AZ12: 0 | BA12: 0 | BB12: 0 | BC12: 0 | BD12: 0 | BE12: 0 | BF12: 0 | BG12: 0 | BH12: 0 | BI12: 0 | BJ12: 0 | BK12: 0 | BL12: 0 | BM12: 0 | BN12: 0 | BO12: 0 | BP12: 0 | BQ12: 0 | BR12: 0 | BS12: 0 | BT12: 0 | BU12: 0 | BV12: 0 | BW12: 0 | BX12: 0 | BY12: 0 | BZ12: 0 | CA12: 0 | CB12: 0 | CC12: 0 | CD12: 0 | CE12: 0 | CF12: 2930 | CG12: 3182 | CH12: 0 | CI12: 0 | CJ12: 0 | CK12: 0 | CL12: 6112 | CM12: 1 | CN12: 1 | CS12: 2 | CZ12: 0 | DG12: 0 | DN12: 0 | DU12: 0 | EB12: 0 | EC12: 1 | ED12: 1 | EE12: 0 | EF12: 0 | EG12: 0 | EH12: 0 | EI12: 2 | EJ12: YES | EK12: YES | EL12: NO | EM12: NO | EN12: NO | EO12: NO | EP12: NO | EQ12: NO | ER12: NO | ES12: NO | ET12: NO | EU12: NO | EV12: NO | EW12: NO | EX12: NO | EY12: NO | EZ12: NO | FA12: NO | FB12: NO | FC12: NO | FD12: NO | FE12: NO | FF12: NO | FG12: NO | FH12: NO | FI12: NO | FJ12: NO | FK12: NO | FL12: NO | FM12: NO | FN12: NO | FO12: NO | FP12: NO | FQ12: NO | FR12: NO | FS12: NO | FT12: 2930 | FZ12: 2930 | GG12: 0 | GN12: 0 | GU12: 0 | HB12: 0 | HI12: 0 | HP12: 0 | HQ12: Parent company | HS12: 3182 | HX12: 3182 | HY12: 2930 | HZ12: 3182 | IA12: 0 | IB12: 0 | IC12: 0 | ID12: 0 | IE12: 6112 | IF12: 2930 | IG12: 3182 | IL12: 6112 | IS12: 0 | IZ12: 0 | JG12: 0 | JN12: 0 | JO12: 2930 | JP12: 3182 | JQ12: 0 | JR12: 0 | JS12: 0 | JT12: 0 | JU12: 6112 | JX12: 100 | KA12: 1 | KB12: 2 | KC12: 1 | KD12: START Asia Pacific: | KE12: 2930 | KK12: 2930 | KR12: 0 | KY12: 0 | LF12: 0 | LM12: 0 | LT12: 0 | MA12: 0 | MB12: Parent company | MD12: 3182 | MI12: 3182 | MJ12: 2930 | MK12: 3182 | ML12: 0 | MM12: 0 | MN12: 0 | MO12: 0 | MP12: 6112 | MW12: 0 | MX12: 2930 | MY12: 3182 | ND12: 6112 | NK12: 0 | NR12: 0 | NY12: 0 | NZ12: 2930 | OA12: 3182 | OB12: 0 | OC12: 0 | OD12: 0 | OE12: 0 | OF12: 6112 | OG12: START Europe: | SJ12: START North America: | WM12: START Global: | AAP12: START SOUTH America: | AES12: START Africa: | AIV12: =IFERROR(RIGHT(AH12,LEN(AH12)-SEARCH("@",AH12,1)),"") -> mfia.co.jp
A13: A1ZJM9T | B13: ANREV | C13: Aventus | E13: lawrence@aventusproperty.com.au | G13: https://secure.surveylab.co.uk/anrev-inrev-ncreif-capital-raising-2018/default.asp?survey=A1ZJM9T | T13: FALSE | U13: FALSE | V13: FALSE | W13: FALSE | X13: FALSE | Y13: FALSE | Z13: 453 | AA13: 43151.921 | AB13: 61.68.16.22 | AC13: 2018 | AD13: Lawrence Wong | AE13: Aventus | AF13: =VLOOKUP(MID(E13,SEARCH("@",E13,1),LEN(E13)-SEARCH("@",E13,1)+1),[2]Sheet1!$D:$F,3,FALSE) -> N0302 | AG13: CFO | AH13: lawrence@aventusproperty.com.au | AI13: 02 9285 6703 | AJ13: Australia | AK13: AUD | AM13: 2 | AN13: 5 | AV13: 0 | BC13: 0 | BJ13: 0 | BQ13: 0 | BX13: 0 | CE13: 0 | CF13: 0 | CG13: 0 | CH13: 0 | CI13: 0 | CJ13: 0 | CK13: 0 | CL13: 0 | CS13: 0 | CZ13: 0 | DG13: 0 | DN13: 0 | DU13: 0 | EB13: 0 | EC13: 0 | ED13: 0 | EE13: 0 | EF13: 0 | EG13: 0 | EH13: 0 | EI13: 0 | EJ13: NO | EK13: NO | EL13: NO | EM13: NO | EN13: NO | EO13: NO | EP13: NO | EQ13: NO | ER13: NO | ES13: NO | ET13: NO | EU13: NO | EV13: NO | EW13: NO | EX13: NO | EY13: NO | EZ13: NO | FA13: NO | FB13: NO | FC13: NO | FD13: NO | FE13: NO | FF13: NO | FG13: NO | FH13: NO | FI13: NO | FJ13: NO | FK13: NO | FL13: NO | FM13: NO | FN13: NO | FO13: NO | FP13: NO | FQ13: NO | FR13: NO | FS13: NO | FZ13: 0 | GG13: 0 | GN13: 0 | GU13: 0 | HB13: 0 | HI13: 0 | HP13: 0 | HX13: 0 | HY13: 0 | HZ13: 0 | IA13: 0 | IB13: 0 | IC13: 0 | ID13: 0 | IE13: 0 | IL13: 0 | IS13: 0 | IZ13: 0 | JG13: 0 | JN13: 0 | JO13: 0 | JP13: 0 | JQ13: 0 | JR13: 0 | JS13: 0 | JT13: 0 | JU13: 0 | KA13: 2 | KB13: 3 | KC13: 1 | KD13: START Asia Pacific: | OG13: START Europe: | SJ13: START North America: | WM13: START Global: | AAP13: START SOUTH America: | AES13: START Africa: | AIV13: =IFERROR(RIGHT(AH13,LEN(AH13)-SEARCH("@",AH13,1)),"") -> aventusproperty.com.au
A14: A2FUA9N | B14: ANREV | C14: AEP Investment Management | E14: yusof.wahid@aep-im.com | G14: https://secure.surveylab.co.uk/anrev-inrev-ncreif-capital-raising-2018/default.asp?survey=A2FUA9N | H14: asia | I14: 43137.627 | T14: FALSE | U14: TRUE | V14: FALSE | W14: FALSE | X14: FALSE | Y14: FALSE | Z14: 413 | AA14: 43137.361 | AB14: 122.11.137.216 | AC14: 2018 | AD14: Roland Kyle | AE14: AEP Investment Management | AF14: =VLOOKUP(MID(E14,SEARCH("@",E14,1),LEN(E14)-SEARCH("@",E14,1)+1),[2]Sheet1!$D:$F,3,FALSE) -> M0291 | AG14: Senior Principal | AH14: roland.kyle@aep-im.com | AI14: 62260212 | AJ14: Singapore | AK14: USD | AM14: 1 | AP14: 50 | AV14: 50 | BC14: 0 | BJ14: 0 | BQ14: 0 | BX14: 0 | CE14: 0 | CF14: 50 | CG14: 0 | CH14: 0 | CI14: 0 | CJ14: 0 | CK14: 0 | CL14: 50 | CM14: 1 | CS14: 1 | CZ14: 0 | DG14: 0 | DN14: 0 | DU14: 0 | EB14: 0 | EC14: 1 | ED14: 0 | EE14: 0 | EF14: 0 | EG14: 0 | EH14: 0 | EI14: 1 | EJ14: YES | EK14: NO | EL14: NO | EM14: NO | EN14: NO | EO14: NO | EP14: NO | EQ14: NO | ER14: NO | ES14: NO | ET14: NO | EU14: NO | EV14: NO | EW14: NO | EX14: NO | EY14: NO | EZ14: NO | FA14: NO | FB14: NO | FC14: NO | FD14: NO | FE14: NO | FF14: NO | FG14: NO | FH14: NO | FI14: NO | FJ14: NO | FK14: NO | FL14: NO | FM14: NO | FN14: NO | FO14: NO | FP14: NO | FQ14: NO | FR14: NO | FS14: NO | FZ14: 0 | GG14: 0 | GH14: 25 | GN14: 25 | GU14: 0 | HB14: 0 | HI14: 0 | HJ14: 25 | HP14: 25 | HX14: 0 | HY14: 50 | HZ14: 0 | IA14: 0 | IB14: 0 | IC14: 0 | ID14: 0 | IE14: 50 | IF14: 50 | IL14: 50 | IS14: 0 | IZ14: 0 | JG14: 0 | JN14: 0 | JO14: 50 | JP14: 0 | JQ14: 0 | JR14: 0 | JS14: 0 | JT14: 0 | JU14: 50 | JX14: 100 | KA14: 1 | KB14: 3 | KC14: 1 | KD14: START Asia Pacific: | KK14: 0 | KR14: 0 | KS14: 25 | KY14: 25 | LF14: 0 | LM14: 0 | LT14: 0 | LU14: 25 | MA14: 25 | MI14: 0 | MJ14: 50 | MK14: 0 | ML14: 0 | MM14: 0 | MN14: 0 | MO14: 0 | MP14: 50 | MW14: 0 | MX14: 50 | ND14: 50 | NK14: 0 | NR14: 0 | NY14: 0 | NZ14: 50 | OA14: 0 | OB14: 0 | OC14: 0 | OD14: 0 | OE14: 0 | OF14: 50 | OG14: START Europe: | SJ14: START North America: | WM14: START Global: | AAP14: START SOUTH America: | AES14: START Africa: | AIV14: =IFERROR(RIGHT(AH14,LEN(AH14)-SEARCH("@",AH14,1)),"") -> aep-im.com
A15: A2WHW5Y | B15: ANREV | C15: Baring Private Equity Asia Pte Ltd | E15: karenko@bpeasia.com | G15: https://secure.surveylab.co.uk/anrev-inrev-ncreif-capital-raising-2018/default.asp?survey=A2WHW5Y | H15: asia | I15: 43151.354 | T15: FALSE | U15: TRUE | V15: FALSE | W15: FALSE | X15: FALSE | Y15: FALSE | Z15: 411 | AA15: 43151.353 | AB15: 101.78.178.130 | AC15: 2018 | AD15: Tiffany Wang | AE15: Baring Private Equity Asia | AF15: =VLOOKUP(MID(E15,SEARCH("@",E15,1),LEN(E15)-SEARCH("@",E15,1)+1),[2]Sheet1!$D:$F,3,FALSE) -> M0149 | AG15: Corporate Communication Officer | AH15: TiffanyWang@bpeasia.com | AI15: +852 2843 9362 | AJ15: Hong Kong | AK15: USD | AM15: 1 | AP15: 488 | AV15: 488 | BC15: 0 | BJ15: 0 | BQ15: 0 | BX15: 0 | CE15: 0 | CF15: 488 | CG15: 0 | CH15: 0 | CI15: 0 | CJ15: 0 | CK15: 0 | CL15: 488 | CM15: 1 | CS15: 1 | CZ15: 0 | DG15: 0 | DN15: 0 | DU15: 0 | EB15: 0 | EC15: 1 | ED15: 0 | EE15: 0 | EF15: 0 | EG15: 0 | EH15: 0 | EI15: 1 | EJ15: YES | EK15: NO | EL15: NO | EM15: NO | EN15: NO | EO15: NO | EP15: NO | EQ15: NO | ER15: NO | ES15: NO | ET15: NO | EU15: NO | EV15: NO | EW15: NO | EX15: NO | EY15: NO | EZ15: NO | FA15: NO | FB15: NO | FC15: NO | FD15: NO | FE15: NO | FF15: NO | FG15: NO | FH15: NO | FI15: NO | FJ15: NO | FK15: NO | FL15: NO | FM15: NO | FN15: NO | FO15: NO | FP15: NO | FQ15: NO | FR15: NO | FS15: NO | FZ15: 0 | GG15: 0 | GN15: 0 | GU15: 0 | HB15: 0 | HI15: 0 | HP15: 0 | HX15: 0 | HY15: 0 | HZ15: 0 | IA15: 0 | IB15: 0 | IC15: 0 | ID15: 0 | IE15: 0 | IL15: 0 | IS15: 0 | IZ15: 0 | JG15: 0 | JN15: 0 | JO15: 0 | JP15: 0 | JQ15: 0 | JR15: 0 | JS15: 0 | JT15: 0 | JU15: 0 | KA15: 3 | KB15: 3 | KC15: 2 | KD15: START Asia Pacific: | KK15: 0 | KR15: 0 | KY15: 0 | LF15: 0 | LM15: 0 | LT15: 0 | MA15: 0 | MI15: 0 | MJ15: 0 | MK15: 0 | ML15: 0 | MM15: 0 | MN15: 0 | MO15: 0 | MP15: 0 | MW15: 0 | ND15: 0 | NK15: 0 | NR15: 0 | NY15: 0 | NZ15: 0 | OA15: 0 | OB15: 0 | OC15: 0 | OD15: 0 | OE15: 0 | OF15: 0 | OG15: START Europe: | SJ15: START North America: | WM15: START Global: | AAP15: START SOUTH America: | AES15: START Africa: | AIV15: =IFERROR(RIGHT(AH15,LEN(AH15)-SEARCH("@",AH15,1)),"") -> bpeasia.com
A16: A3AAT7R | B16: ANREV | C16: BlackRock | E16: nicholas.dempsey@blackrock.com | G16: https://secure.surveylab.co.uk/anrev-inrev-ncreif-capital-raising-2018/default.asp?survey=A3AAT7R | H16: asia | I16: 43153.722 | J16: europe | K16: 43153.722 | L16: northamerica | M16: 43153.722 | T16: TRUE | U16: TRUE | V16: TRUE | W16: FALSE | X16: FALSE | Y16: FALSE | Z16: 328 | AA16: 43153.722 | AB16: 69.52.69.38 | AC16: 2018 | AD16: Lauren Anderson | AE16: BlackRock | AF16: =VLOOKUP(MID(E16,SEARCH("@",E16,1),LEN(E16)-SEARCH("@",E16,1)+1),[2]Sheet1!$D:$F,3,FALSE) -> M181 | AG16: Analyst | AH16: lauren.anderson@blackrock.com | AI16: 2077431621 | AJ16: United States | AK16: USD | AM16: 1 | AP16: 251 | AQ16: 62 | AV16: 313 | AW16: 954 | BB16: 100 | BC16: 1054 | BD16: 224 | BE16: 650 | BI16: 753 | BJ16: 1627 | BQ16: 0 | BX16: 0 | CE16: 0 | CF16: 1429 | CG16: 712 | CH16: 0 | CI16: 0 | CJ16: 0 | CK16: 853 | CL16: 2994 | CM16: 1 | CN16: 1 | CS16: 2 | CT16: 2 | CY16: 1 | CZ16: 3 | DA16: 1 | DB16: 7 | DF16: 2 | DG16: 10 | DN16: 0 | DU16: 0 | EB16: 0 | EC16: 4 | ED16: 8 | EE16: 0 | EF16: 0 | EG16: 0 | EH16: 3 | EI16: 15 | EJ16: YES | EK16: YES | EL16: NO | EM16: NO | EN16: NO | EO16: NO | EP16: YES | EQ16: NO | ER16: NO | ES16: NO | ET16: NO | EU16: YES | EV16: YES | EW16: YES | EX16: NO | EY16: NO | EZ16: NO | FA16: YES | FB16: NO | FC16: NO | FD16: NO | FE16: NO | FF16: NO | FG16: NO | FH16: NO | FI16: NO | FJ16: NO | FK16: NO | FL16: NO | FM16: NO | FN16: NO | FO16: NO | FP16: NO | FQ16: NO | FR16: NO | FS16: NO | FT16: 629 | FU16: 712 | FY16: 391 | FZ16: 1732 | GA16: 180 | GF16: 104 | GG16: 284 | GH16: 114 | GM16: 200 | GN16: 314 | GU16: 0 | HA16: 1 | HB16: 1 | HC16: 4 | HI16: 4 | HJ16: 63 | HO16: 57 | HP16: 120 | HQ16: Institutional | HR16: 439 | HW16: 100 | HX16: 539 | HY16: 1429 | HZ16: 712 | IA16: 0 | IB16: 0 | IC16: 0 | ID16: 853 | IE16: 2994 | IF16: 206 | IG16: 62 | IK16: 375 | IL16: 643 | IM16: 876 | IR16: 160 | IS16: 1036 | IT16: 347 | IU16: 650 | IY16: 318 | IZ16: 1315 | JG16: 0 | JN16: 0 | JO16: 1429 | JP16: 712 | JQ16: 0 | JR16: 0 | JS16: 0 | JT16: 853 | JU16: 2994 | JX16: 100 | KA16: 1 | KB16: 3 | KC16: 1 | KD16: START Asia Pacific: | KE16: 83 | KF16: 62 | KK16: 145 | KL16: 159 | KR16: 159 | KY16: 0 | LF16: 0 | LM16: 0 | LT16: 0 | MA16: 0 | MB16: Institutional | MC16: 9 | MI16: 9 | MJ16: 251 | MK16: 62 | ML16: 0 | MM16: 0 | MN16: 0 | MO16: 0 | MP16: 313 | MQ16: 120 | MR16: 62 | MW16: 182 | MX16: 69 | ND16: 69 | NE16: 62 | NK16: 62 | NR16: 0 | NY16: 0 | NZ16: 251 | OA16: 62 | OB16: 0 | OC16: 0 | OD16: 0 | OE16: 0 | OF16: 313 | OG16: START Europe: | OH16: 529 | ON16: 529 | OO16: 21 | OU16: 21 | OV16: 114 | PB16: 114 | PI16: 0 | PP16: 0 | PW16: 0 | PX16: 60 | QD16: 60 | QE16: Institutional | QF16: 230 | QK16: 100 | QL16: 330 | QM16: 954 | QN16: 0 | QO16: 0 | QP16: 0 | QQ16: 0 | QR16: 100 | QS16: 1054 | QT16: 756 | QY16: 100 | QZ16: 856 | RA16: 137 | RG16: 137 | RH16: 61 | RN16: 61 | RU16: 0 | SB16: 0 | SC16: 954 | SD16: 0 | SE16: 0 | SF16: 0 | SG16: 0 | SH16: 100 | SI16: 1054 | SJ16: START North America: | SK16: 17 | SL16: 650 | SP16: 391 | SQ16: 1058 | SW16: 104 | SX16: 104 | TD16: 200 | TE16: 200 | TL16: 0 | TR16: 1 | TS16: 1 | TT16: 4 | TZ16: 4 | UA16: 3 | UF16: 57 | UG16: 60 | UH16: Institutional | UI16: 200 | UO16: 200 | UP16: 224 | UQ16: 650 | UR16: 0 | US16: 0 | UT16: 0 | UU16: 753 | UV16: 1627 | VB16: 60 | VC16: 60 | VI16: 375 | VJ16: 375 | VK16: 224 | VL16: 650 | VP16: 318 | VQ16: 1192 | VX16: 0 | WE16: 0 | WF16: 224 | WG16: 650 | WH16: 0 | WI16: 0 | WJ16: 0 | WK16: 753 | WL16: 1627 | WM16: START Global: | AAP16: START SOUTH America: | AES16: START Africa: | AIV16: =IFERROR(RIGHT(AH16,LEN(AH16)-SEARCH("@",AH16,1)),"") -> blackrock.com
A17: A3DNZ5Q | B17: ANREV | C17: ESR Singapore Pte. Ltd. | E17: wlim@sg.esr.com | G17: https://secure.surveylab.co.uk/anrev-inrev-ncreif-capital-raising-2018/default.asp?survey=A3DNZ5Q | H17: asia | I17: 43136.33 | T17: FALSE | U17: TRUE | V17: FALSE | W17: FALSE | X17: FALSE | Y17: FALSE | Z17: 388 | AA17: 43136.329 | AB17: 58.185.53.226 | AC17: 2018 | AD17: LIM WEI HUANG | AE17: ESR Singapore Pte Ltd | AF17: =VLOOKUP(MID(E17,SEARCH("@",E17,1),LEN(E17)-SEARCH("@",E17,1)+1),[2]Sheet1!$D:$F,3,FALSE) -> M0231 | AG17: Senior Corporate Controller | AH17: wlim@sg.esr.com | AI17: 65-6850 0449 | AJ17: Singapore | AK17: USD | AM17: 1 | AP17: 110 | AV17: 110 | BC17: 0 | BJ17: 0 | BQ17: 0 | BX17: 0 | CE17: 0 | CF17: 110 | CG17: 0 | CH17: 0 | CI17: 0 | CJ17: 0 | CK17: 0 | CL17: 110 | CM17: 1 | CS17: 1 | CZ17: 0 | DG17: 0 | DN17: 0 | DU17: 0 | EB17: 0 | EC17: 1 | ED17: 0 | EE17: 0 | EF17: 0 | EG17: 0 | EH17: 0 | EI17: 1 | EJ17: YES | EK17: NO | EL17: NO | EM17: NO | EN17: NO | EO17: NO | EP17: NO | EQ17: NO | ER17: NO | ES17: NO | ET17: NO | EU17: NO | EV17: NO | EW17: NO | EX17: NO | EY17: NO | EZ17: NO | FA17: NO | FB17: NO | FC17: NO | FD17: NO | FE17: NO | FF17: NO | FG17: NO | FH17: NO | FI17: NO | FJ17: NO | FK17: NO | FL17: NO | FM17: NO | FN17: NO | FO17: NO | FP17: NO | FQ17: NO | FR17: NO | FS17: NO | FZ17: 0 | GG17: 0 | GN17: 0 | GU17: 0 | HB17: 0 | HC17: 110 | HI17: 110 | HP17: 0 | HX17: 0 | HY17: 110 | HZ17: 0 | IA17: 0 | IB17: 0 | IC17: 0 | ID17: 0 | IE17: 110 | IL17: 0 | IM17: 100 | IS17: 100 | IT17: 10 | IZ17: 10 | JG17: 0 | JN17: 0 | JO17: 110 | JP17: 0 | JQ17: 0 | JR17: 0 | JS17: 0 | JT17: 0 | JU17: 110 | JX17: 100 | KA17: 1 | KB17: 3 | KC17: 2 | KD17: START Asia Pacific: | KK17: 0 | KR17: 0 | KY17: 0 | LF17: 0 | LM17: 0 | LN17: 110 | LT17: 110 | MA17: 0 | MI17: 0 | MJ17: 110 | MK17: 0 | ML17: 0 | MM17: 0 | MN17: 0 | MO17: 0 | MP17: 110 | MQ17: 100 | MW17: 100 | ND17: 0 | NE17: 10 | NK17: 10 | NR17: 0 | NY17: 0 | NZ17: 110 | OA17: 0 | OB17: 0 | OC17: 0 | OD17: 0 | OE17: 0 | OF17: 110 | OG17: START Europe: | SJ17: START North America: | WM17: START Global: | AAP17: START SOUTH America: | AES17: START Africa: | AIV17: =IFERROR(RIGHT(AH17,LEN(AH17)-SEARCH("@",AH17,1)),"") -> sg.esr.com
A18: A3WFZ9X | B18: ANREV | C18: The Blackstone Group L.P. | E18: Jenner.Currier@blackstone.com | G18: https://secure.surveylab.co.uk/anrev-inrev-ncreif-capital-raising-2018/default.asp?survey=A3WFZ9X | T18: TRUE | U18: TRUE | V18: TRUE | W18: TRUE | X18: FALSE | Y18: FALSE | Z18: 308 | AA18: 43166.363 | AB18: 67.202.213.1 | AC18: 2018 | AD18: Jenner Currier | AE18: The Blackstone Group L.P. | AF18: =VLOOKUP(MID(E18,SEARCH("@",E18,1),LEN(E18)-SEARCH("@",E18,1)+1),[2]Sheet1!$D:$F,3,FALSE) -> M178 | AG18: Analyst | AH18: jenner.currier@blackstone.com | AI18: +1 (212) 390-2691 | AJ18: United States | AK18: USD | AM18: 1 | AP18: 5873 | AQ18: 0 | AR18: 0 | AS18: 0 | AT18: 0 | AU18: 0 | AV18: 5873 | AW18: 2293 | AX18: 5961 | AY18: 0 | AZ18: 0 | BA18: 0 | BB18: 0 | BC18: 8254 | BD18: 3409 | BE18: 51 | BF18: 0 | BG18: 0 | BH18: 0 | BI18: 0 | BJ18: 3460 | BK18: 197 | BL18: 559 | BM18: 0 | BN18: 0 | BO18: 0 | BP18: 1929 | BQ18: 2685 | BX18: 0 | CE18: 0 | CF18: 11772 | CG18: 6571 | CH18: 0 | CI18: 0 | CJ18: 0 | CK18: 1929 | CL18: 20272 | CM18: 1 | CS18: 1 | CT18: 2 | CU18: 1 | CZ18: 3 | DA18: 2 | DB18: 1 | DG18: 3 | DH18: 1 | DI18: 2 | DM18: 9 | DN18: 12 | DU18: 0 | EB18: 0 | EC18: 6 | ED18: 4 | EE18: 0 | EF18: 0 | EG18: 0 | EH18: 9 | EI18: 19 | EJ18: YES | EK18: NO | EL18: NO | EM18: NO | EN18: NO | EO18: NO | EP18: YES | EQ18: YES | ER18: NO | ES18: NO | ET18: NO | EU18: NO | EV18: YES | EW18: YES | EX18: NO | EY18: NO | EZ18: NO | FA18: NO | FB18: YES | FC18: YES | FD18: NO | FE18: NO | FF18: NO | FG18: YES | FH18: NO | FI18: NO | FJ18: NO | FK18: NO | FL18: NO | FM18: NO | FN18: NO | FO18: NO | FP18: NO | FQ18: NO | FR18: NO | FS18: NO | FZ18: 0 | GG18: 0 | GN18: 0 | GU18: 0 | HB18: 0 | HI18: 0 | HP18: 0 | HX18: 0 | HY18: 0 | HZ18: 0 | IA18: 0 | IB18: 0 | IC18: 0 | ID18: 0 | IE18: 0 | IL18: 0 | IS18: 0 | IZ18: 0 | JG18: 0 | JN18: 0 | JO18: 0 | JP18: 0 | JQ18: 0 | JR18: 0 | JS18: 0 | JT18: 0 | JU18: 0 | KC18: 1 | KD18: START Asia Pacific: | OG18: START Europe: | SJ18: START North America: | WM18: START Global: | AAP18: START SOUTH America: | AES18: START Africa: | AIV18: =IFERROR(RIGHT(AH18,LEN(AH18)-SEARCH("@",AH18,1)),"") -> blackstone.com
A19: A3WYR9R | B19: ANREV | C19: IGIS Asset Management | E19: joseph.lee@igisam.com | G19: https://secure.surveylab.co.uk/anrev-inrev-ncreif-capital-raising-2018/default.asp?survey=A3WYR9R | H19: Asia | I19: 43138.258 | J19: Europe | K19: 43138.292 | L19: NorthAmerica | M19: 43138.293 | N19: Global | O19: 43138.294 | T19: TRUE | U19: TRUE | V19: TRUE | W19: TRUE | X19: FALSE | Y19: FALSE | Z19: 305 | AA19: 43138.244 | AB19: 112.218.108.195 | AC19: 2018 | AD19: Lee, Joseph(Lee, Gyusung) | AE19: IGIS Assest Management | AF19: =VLOOKUP(MID(E19,SEARCH("@",E19,1),LEN(E19)-SEARCH("@",E19,1)+1),[2]Sheet1!$D:$F,3,FALSE) -> M0333 | AG19: Senior Manager | AH19: joseph.lee@igisam.com | AI19: -9981 | AJ19: Korea, Republic Of | AK19: KRW | AM19: 1 | AP19: 1416611 | AQ19: 0 | AR19: 0 | AS19: 2519988 | AT19: 109554 | AU19: 419840 | AV19: 4465993 | AW19: 346993 | AX19: 0 | AY19: 0 | AZ19: 0 | BA19: 132401 | BB19: 56898 | BC19: 536292 | BD19: 0 | BE19: 0 | BF19: 0 | BG19: 0 | BH19: 84251 | BI19: 487674 | BJ19: 571925 | BK19: 0 | BL19: 0 | BM19: 0 | BN19: 0 | BO19: 50219 | BP19: 0 | BQ19: 50219 | BR19: 0 | BS19: 0 | BT19: 0 | BU19: 0 | BV19: 0 | BW19: 0 | BX19: 0 | BY19: 0 | BZ19: 0 | CA19: 0 | CB19: 0 | CC19: 0 | CD19: 0 | CE19: 0 | CF19: 1763604 | CG19: 0 | CH19: 0 | CI19: 2519988 | CJ19: 376425 | CK19: 964412 | CL19: 5624429 | CM19: 3 | CP19: 10 | CQ19: 5 | CR19: 9 | CS19: 27 | CT19: 1 | CX19: 2 | CY19: 1 | CZ19: 4 | DE19: 4 | DF19: 5 | DG19: 9 | DL19: 2 | DN19: 2 | DU19: 0 | EB19: 0 | EC19: 4 | ED19: 0 | EE19: 0 | EF19: 10 | EG19: 13 | EH19: 15 | EI19: 42 | EJ19: YES | EK19: NO | EL19: NO | EM19: YES | EN19: YES | EO19: YES | EP19: YES | EQ19: NO | ER19: NO | ES19: NO | ET19: YES | EU19: YES | EV19: NO | EW19: NO | EX19: NO | EY19: NO | EZ19: YES | FA19: YES | FB19: NO | FC19: NO | FD19: NO | FE19: NO | FF19: YES | FG19: NO | FH19: NO | FI19: NO | FJ19: NO | FK19: NO | FL19: NO | FM19: NO | FN19: NO | FO19: NO | FP19: NO | FQ19: NO | FR19: NO | FS19: NO | FT19: 1229428 | FW19: 0 | FX19: 191840 | FY19: 100400 | FZ19: 1521668 | GA19: 21646 | GD19: 0 | GE19: 24492 | GF19: 443797 | GG19: 489935 | GH19: 0 | GK19: 0 | GL19: 0 | GM19: 0 | GN19: 0 | GO19: 0 | GR19: 435455 | GS19: 0 | GT19: 0 | GU19: 435455 | GV19: 0 | GY19: 0 | GZ19: 0 | HA19: 0 | HB19: 0 | HC19: 0 | HF19: 453163 | HG19: 0 | HH19: 20000 | HI19: 473163 | HJ19: 0 | HM19: 0 | HN19: 0 | HO19: 0 | HP19: 0 | HQ19: Mutual Aid, Invest Bank, Corporation, Individuals. | HR19: 512530 | HU19: 1631370 | HV19: 160093 | HW19: 400215 | HX19: 2704208 | HY19: 1763604 | HZ19: 0 | IA19: 0 | IB19: 2519988 | IC19: 376425 | ID19: 964412 | IE19: 5624429 | IF19: 1763604 | II19: 2248283 | IJ19: 376425 | IK19: 964412 | IL19: 5352724 | IM19: 0 | IP19: 271705 | IQ19: 0 | IR19: 0 | IS19: 271705 | IT19: 0 | IW19: 0 | IX19: 0 | IY19: 0 | IZ19: 0 | JA19: 0 | JD19: 0 | JE19: 0 | JF19: 0 | JG19: 0 | JH19: 0 | JK19: 0 | JL19: 0 | JM19: 0 | JN19: 0 | JO19: 1763604 | JP19: 0 | JQ19: 0 | JR19: 2519988 | JS19: 376425 | JT19: 964412 | JU19: 5624429 | JV19: 0 | JW19: 0 | JX19: 100 | JZ19: 0 | KA19: 1 | KB19: 1 | KC19: 1 | KD19: START Asia Pacific: | KE19: 1229428 | KH19: 0 | KI19: 20000 | KJ19: 100400 | KK19: 1349828 | KL19: 21646 | KO19: 0 | KP19: 5000 | KQ19: 119522 | KR19: 146168 | KS19: 0 | KV19: 0 | KW19: 0 | KX19: 0 | KY19: 0 | KZ19: 0 | LC19: 435455 | LD19: 0 | LE19: 0 | LF19: 435455 | LG19: 0 | LJ19: 0 | LK19: 0 | LL19: 0 | LM19: 0 | LN19: 0 | LQ19: 453163 | LR19: 0 | LS19: 20000 | LT19: 473163 | MA19: 0 | MB19: Mutual Aid, Invest Bank, Corporation, Individuals. | MC19: 165537 | MF19: 1631370 | MG19: 84554 | MH19: 179918 | MI19: 2061379 | MJ19: 1416611 | MK19: 0 | ML19: 0 | MM19: 2519988 | MN19: 109554 | MO19: 419840 | MP19: 4465993 | MQ19: 0 | MT19: 271705 | MU19: 0 | MV19: 0 | MW19: 271705 | MX19: 1416611 | NA19: 2248283 | NB19: 109554 | NC19: 419840 | ND19: 4194288 | NE19: 0 | NH19: 0 | NI19: 0 | NJ19: 0 | NK19: 0 | NL19: 0 | NO19: 0 | NP19: 0 | NQ19: 0 | NR19: 0 | NS19: 0 | NV19: 0 | NW19: 0 | NX19: 0 | NY19: 0 | NZ19: 1416611 | OA19: 0 | OB19: 0 | OC19: 2519988 | OD19: 109554 | OE19: 419840 | OF19: 4465993 | OG19: START Europe: | OH19: 0 | OK19: 0 | OL19: 132400 | OM19: 0 | ON19: 132400 | OO19: 0 | OR19: 0 | OS19: 0 | OT19: 0 | OU19: 0 | OV19: 0 | OY19: 0 | OZ19: 0 | PA19: 0 | PB19: 0 | PC19: 0 | PF19: 0 | PG19: 0 | PH19: 0 | PI19: 0 | PJ19: 0 | PM19: 0 | PN19: 0 | PO19: 0 | PP19: 0 | PQ19: 0 | PT19: 0 | PU19: 0 | PV19: 0 | PW19: 0 | PX19: 0 | QA19: 0 | QB19: 0 | QC19: 0 | QD19: 0 | QE19: Mutual Aid, Corporation. | QF19: 346993 | QI19: 0 | QJ19: 1 | QK19: 56898 | QL19: 403892 | QM19: 346993 | QN19: 0 | QO19: 0 | QP19: 0 | QQ19: 132401 | QR19: 56898 | QS19: 536292 | QT19: 0 | QW19: 0 | QX19: 0 | QY19: 0 | QZ19: 0 | RA19: 346993 | RD19: 0 | RE19: 132401 | RF19: 56898 | RG19: 536292 | RH19: 0 | RK19: 0 | RL19: 0 | RM19: 0 | RN19: 0 | RO19: 0 | RR19: 0 | RS19: 0 | RT19: 0 | RU19: 0 | RV19: 0 | RY19: 0 | RZ19: 0 | SA19: 0 | SB19: 0 | SC19: 346993 | SD19: 0 | SE19: 0 | SF19: 0 | SG19: 132401 | SH19: 56898 | SI19: 536292 | SJ19: START North America: | SK19: 0 | SN19: 0 | SO19: 39440 | SP19: 0 | SQ19: 39440 | SR19: 0 | SU19: 0 | SV19: 8184 | SW19: 324275 | SX19: 332459 | SY19: 0 | TB19: 0 | TC19: 0 | TD19: 0 | TE19: 0 | TF19: 0 | TI19: 0 | TJ19: 0 | TK19: 0 | TL19: 0 | TM19: 0 | TP19: 0 | TQ19: 0 | TR19: 0 | TS19: 0 | TT19: 0 | TW19: 0 | TX19: 0 | TY19: 0 | TZ19: 0 | UA19: 0 | UD19: 0 | UE19: 0 | UF19: 0 | UG19: 0 | UH19: Mutual Aid, Invest Bank, Corporation. | UI19: 0 | UL19: 0 | UM19: 36627 | UN19: 163399 | UO19: 200026 | UP19: 0 | UQ19: 0 | UR19: 0 | US19: 0 | UT19: 84251 | UU19: 487674 | UV19: 571925 | UW19: 0 | UZ19: 0 | VA19: 0 | VB19: 0 | VC19: 0 | VD19: 0 | VG19: 0 | VH19: 84251 | VI19: 487674 | VJ19: 571925 | VK19: 0 | VN19: 0 | VO19: 0 | VP19: 0 | VQ19: 0 | VR19: 0 | VU19: 0 | VV19: 0 | VW19: 0 | VX19: 0 | VY19: 0 | WB19: 0 | WC19: 0 | WD19: 0 | WE19: 0 | WF19: 0 | WG19: 0 | WH19: 0 | WI19: 0 | WJ19: 84251 | WK19: 487674 | WL19: 571925 | WM19: START Global: | WN19: 0 | WQ19: 0 | WR19: 0 | WS19: 0 | WT19: 0 | WU19: 0 | WX19: 0 | WY19: 11308 | WZ19: 0 | XA19: 11308 | XB19: 0 | XE19: 0 | XF19: 0 | XG19: 0 | XH19: 0 | XI19: 0 | XL19: 0 | XM19: 0 | XN19: 0 | XO19: 0 | XP19: 0 | XS19: 0 | XT19: 0 | XU19: 0 | XV19: 0 | XW19: 0 | XZ19: 0 | YA19: 0 | YB19: 0 | YC19: 0 | YD19: 0 | YG19: 0 | YH19: 0 | YI19: 0 | YJ19: 0 | YK19: Mutual Aid, Invest Bank | YL19: 0 | YO19: 0 | YP19: 38911 | YQ19: 0 | YR19: 38911 | YS19: 0 | YT19: 0 | YU19: 0 | YV19: 0 | YW19: 50219 | YX19: 0 | YY19: 50219 | YZ19: 0 | ZC19: 0 | ZD19: 0 | ZE19: 0 | ZF19: 0 | ZG19: 0 | ZJ19: 0 | ZK19: 50219 | ZL19: 0 | ZM19: 50219 | ZN19: 0 | ZQ19: 0 | ZR19: 0 | ZS19: 0 | ZT19: 0 | ZU19: 0 | ZX19: 0 | ZY19: 0 | ZZ19: 0 | AAA19: 0 | AAB19: 0 | AAE19: 0 | AAF19: 0 | AAG19: 0 | AAH19: 0 | AAI19: 0 | AAJ19: 0 | AAK19: 0 | AAL19: 0 | AAM19: 50219 | AAN19: 0 | AAO19: 50219 | AAP19: START SOUTH America: | AES19: START Africa: | AIV19: =IFERROR(RIGHT(AH19,LEN(AH19)-SEARCH("@",AH19,1)),"") -> igisam.com
A20: A3YXX2L | B20: ANREV | C20: Cromwell Corporation Limited | E20: Bevan.Towning@cromwell.com.au | G20: https://secure.surveylab.co.uk/anrev-inrev-ncreif-capital-raising-2018/default.asp?survey=A3YXX2L | T20: FALSE | U20: FALSE | V20: FALSE | W20: FALSE | X20: FALSE | Y20: FALSE | Z20: 492 | AA20: 43163.991 | AB20: 115.124.35.104 | AC20: 2018 | AD20: Darren Connolly | AE20: Cromwell Property Group | AF20: =VLOOKUP(MID(E20,SEARCH("@",E20,1),LEN(E20)-SEARCH("@",E20,1)+1),[2]Sheet1!$D:$F,3,FALSE) -> M126 | AG20: Head of Marketing | AH20: darren.connolly@cromwell.com.au | AI20: 459492621 | AJ20: Australia | AK20: AUD | AM20: 2 | AN20: 6 | AO20: Listed focus / vehicles in 2017 | AV20: 0 | BC20: 0 | BJ20: 0 | BQ20: 0 | BX20: 0 | CE20: 0 | CF20: 0 | CG20: 0 | CH20: 0 | CI20: 0 | CJ20: 0 | CK20: 0 | CL20: 0 | CS20: 0 | CZ20: 0 | DG20: 0 | DN20: 0 | DU20: 0 | EB20: 0 | EC20: 0 | ED20: 0 | EE20: 0 | EF20: 0 | EG20: 0 | EH20: 0 | EI20: 0 | EJ20: NO | EK20: NO | EL20: NO | EM20: NO | EN20: NO | EO20: NO | EP20: NO | EQ20: NO | ER20: NO | ES20: NO | ET20: NO | EU20: NO | EV20: NO | EW20: NO | EX20: NO | EY20: NO | EZ20: NO | FA20: NO | FB20: NO | FC20: NO | FD20: NO | FE20: NO | FF20: NO | FG20: NO | FH20: NO | FI20: NO | FJ20: NO | FK20: NO | FL20: NO | FM20: NO | FN20: NO | FO20: NO | FP20: NO | FQ20: NO | FR20: NO | FS20: NO | FZ20: 0 | GG20: 0 | GN20: 0 | GU20: 0 | HB20: 0 | HI20: 0 | HP20: 0 | HX20: 0 | HY20: 0 | HZ20: 0 | IA20: 0 | IB20: 0 | IC20: 0 | ID20: 0 | IE20: 0 | IL20: 0 | IS20: 0 | IZ20: 0 | JG20: 0 | JN20: 0 | JO20: 0 | JP20: 0 | JQ20: 0 | JR20: 0 | JS20: 0 | JT20: 0 | JU20: 0 | KA20: 1 | KB20: 3 | KC20: 2 | KD20: START Asia Pacific: | OG20: START Europe: | SJ20: START North America: | WM20: START Global: | AAP20: START SOUTH America: | AES20: START Africa: | AIV20: =IFERROR(RIGHT(AH20,LEN(AH20)-SEARCH("@",AH20,1)),"") -> cromwell.com.au
A21: A4LKN2E | B21: ANREV | C21: Global Logistic Properties Limited | E21: yfujioka@glprop.com | G21: https://secure.surveylab.co.uk/anrev-inrev-ncreif-capital-raising-2018/default.asp?survey=A4LKN2E | J21: europe | K21: 43123.322 | L21: northamerica | M21: 43123.322 | T21: TRUE | U21: FALSE | V21: TRUE | W21: FALSE | X21: FALSE | Y21: FALSE | Z21: 371 | AA21: 43123.321 | AB21: 42.61.82.81 | AC21: 2018 | AD21: Yosuke Fujioka | AE21: GLP | AF21: =VLOOKUP(MID(E21,SEARCH("@",E21,1),LEN(E21)-SEARCH("@",E21,1)+1),[2]Sheet1!$D:$F,3,FALSE) -> M0144 | AG21: SVP - Fund Management | AH21: yfujioka@glprop.com | AI21: +65 6672 5472 | AJ21: Singapore | AK21: USD | AM21: 1 | AV21: 0 | AW21: 527 | BC21: 527 | BD21: 47 | BJ21: 47 | BQ21: 0 | BX21: 0 | CE21: 0 | CF21: 574 | CG21: 0 | CH21: 0 | CI21: 0 | CJ21: 0 | CK21: 0 | CL21: 574 | CS21: 0 | CT21: 2 | CZ21: 2 | DA21: 1 | DG21: 1 | DN21: 0 | DU21: 0 | EB21: 0 | EC21: 3 | ED21: 0 | EE21: 0 | EF21: 0 | EG21: 0 | EH21: 0 | EI21: 3 | EJ21: NO | EK21: NO | EL21: NO | EM21: NO | EN21: NO | EO21: NO | EP21: YES | EQ21: NO | ER21: NO | ES21: NO | ET21: NO | EU21: NO | EV21: YES | EW21: NO | EX21: NO | EY21: NO | EZ21: NO | FA21: NO | FB21: NO | FC21: NO | FD21: NO | FE21: NO | FF21: NO | FG21: NO | FH21: NO | FI21: NO | FJ21: NO | FK21: NO | FL21: NO | FM21: NO | FN21: NO | FO21: NO | FP21: NO | FQ21: NO | FR21: NO | FS21: NO | FT21: 172 | FZ21: 172 | GG21: 0 | GH21: 402 | GN21: 402 | GU21: 0 | HB21: 0 | HI21: 0 | HP21: 0 | HX21: 0 | HY21: 574 | HZ21: 0 | IA21: 0 | IB21: 0 | IC21: 0 | ID21: 0 | IE21: 574 | IF21: 574 | IL21: 574 | IS21: 0 | IZ21: 0 | JG21: 0 | JN21: 0 | JO21: 574 | JP21: 0 | JQ21: 0 | JR21: 0 | JS21: 0 | JT21: 0 | JU21: 574 | JV21: 100 | KA21: 1 | KB21: 3 | KC21: 2 | KD21: START Asia Pacific: | OG21: START Europe: | OH21: 125 | ON21: 125 | OU21: 0 | OV21: 402 | PB21: 402 | PI21: 0 | PP21: 0 | PW21: 0 | QD21: 0 | QL21: 0 | QM21: 527 | QN21: 0 | QO21: 0 | QP21: 0 | QQ21: 0 | QR21: 0 | QS21: 527 | QZ21: 0 | RA21: 527 | RG21: 527 | RN21: 0 | RU21: 0 | SB21: 0 | SC21: 527 | SD21: 0 | SE21: 0 | SF21: 0 | SG21: 0 | SH21: 0 | SI21: 527 | SJ21: START North America: | SK21: 47 | SQ21: 47 | SX21: 0 | TE21: 0 | TL21: 0 | TS21: 0 | TZ21: 0 | UG21: 0 | UO21: 0 | UP21: 47 | UQ21: 0 | UR21: 0 | US21: 0 | UT21: 0 | UU21: 0 | UV21: 47 | VC21: 0 | VD21: 47 | VJ21: 47 | VQ21: 0 | VX21: 0 | WE21: 0 | WF21: 47 | WG21: 0 | WH21: 0 | WI21: 0 | WJ21: 0 | WK21: 0 | WL21: 47 | WM21: START Global: | AAP21: START SOUTH America: | AES21: START Africa: | AIV21: =IFERROR(RIGHT(AH21,LEN(AH21)-SEARCH("@",AH21,1)),"") -> glprop.com
A22: A4MAK3W | B22: ANREV | C22: PGIM Real Estate | E22: jennifer.mcdermott@pgim.com | G22: https://secure.surveylab.co.uk/anrev-inrev-ncreif-capital-raising-2018/default.asp?survey=A4MAK3W | H22: asia | I22: 43154.688 | J22: europe | K22: 43154.684 | L22: northamerica | M22: 43154.694 | P22: southamerica | Q22: 43154.697 | T22: TRUE | U22: TRUE | V22: TRUE | W22: FALSE | X22: TRUE | Y22: FALSE | Z22: 342 | AA22: 43154.675 | AB22: 12.42.51.27 | AC22: 2018 | AD22: Meghan Lakeland | AE22: PGIM Real Estate | AF22: =VLOOKUP(MID(E22,SEARCH("@",E22,1),LEN(E22)-SEARCH("@",E22,1)+1),[2]Sheet1!$D:$F,3,FALSE) -> M042 | AG22: Vice President, Business Development | AH22: meghan.lakeland@pgim.com | AI22: 973-734-1461 | AJ22: United States | AK22: USD | AM22: 1 | AP22: 200 | AQ22: 127.4 | AV22: 327.4 | AW22: 217.9 | AX22: 749.5 | BB22: 560.3 | BC22: 1527.7 | BD22: 2127.2 | BE22: 127.5 | BI22: 390 | BJ22: 2644.7 | BQ22: 0 | BR22: 235 | BX22: 235 | CE22: 0 | CF22: 2780.1 | CG22: 1004.4 | CH22: 0 | CI22: 0 | CJ22: 0 | CK22: 950.3 | CL22: 4734.8 | CM22: 1 | CN22: 2 | CS22: 3 | CT22: 2 | CU22: 4 | CY22: 1 | CZ22: 7 | DA22: 5 | DB22: 3 | DF22: 1 | DG22: 9 | DN22: 0 | DO22: 1 | DU22: 1 | EB22: 0 | EC22: 9 | ED22: 9 | EE22: 0 | EF22: 0 | EG22: 0 | EH22: 2 | EI22: 20 | EJ22: YES | EK22: YES | EL22: NO | EM22: NO | EN22: NO | EO22: NO | EP22: YES | EQ22: YES | ER22: NO | ES22: NO | ET22: NO | EU22: YES | EV22: YES | EW22: YES | EX22: NO | EY22: NO | EZ22: NO | FA22: YES | FB22: NO | FC22: NO | FD22: NO | FE22: NO | FF22: NO | FG22: NO | FH22: YES | FI22: NO | FJ22: NO | FK22: NO | FL22: NO | FM22: NO | FN22: NO | FO22: NO | FP22: NO | FQ22: NO | FR22: NO | FS22: NO | FT22: 1483.6 | FU22: 914.7 | FY22: 708.4 | FZ22: 3106.7 | GA22: 277.5 | GB22: 78.5 | GF22: 50 | GG22: 406 | GI22: 11.2 | GM22: 70.2 | GN22: 81.4 | GU22: 0 | GV22: 60.8 | HA22: 25 | HB22: 85.8 | HC22: 133.5 | HI22: 133.5 | HJ22: 77.8 | HO22: 75 | HP22: 152.8 | HQ22: Trusts, Defined Contribution (Corporate) | HR22: 747 | HW22: 21.6 | HX22: 768.6 | HY22: 2780.2 | HZ22: 1004.4 | IA22: 0 | IB22: 0 | IC22: 0 | ID22: 950.2 | IE22: 4734.8 | IF22: 381 | IG22: 116.2 | IK22: 50 | IL22: 547.2 | IM22: 652.9 | IN22: 760.7 | IR22: 143.1 | IS22: 1556.7 | IT22: 1484.2 | IU22: 127.5 | IY22: 757.2 | IZ22: 2368.9 | JA22: 262 | JG22: 262 | JN22: 0 | JO22: 2780.1 | JP22: 1004.4 | JQ22: 0 | JR22: 0 | JS22: 0 | JT22: 950.3 | JU22: 4734.8 | JV22: 0 | JW22: 0 | JX22: 100 | KA22: 3 | KB22: 3 | KC22: 1 | KD22: START Asia Pacific: | KF22: 116.2 | KK22: 116.2 | KL22: 200 | KR22: 200 | KT22: 11.2 | KY22: 11.2 | LF22: 0 | LM22: 0 | LT22: 0 | MA22: 0 | MI22: 0 | MJ22: 200 | MK22: 127.4 | ML22: 0 | MM22: 0 | MN22: 0 | MO22: 0 | MP22: 327.4 | MR22: 11.2 | MW22: 11.2 | MX22: 100 | MY22: 116.2 | ND22: 216.2 | NE22: 100 | NK22: 100 | NR22: 0 | NY22: 0 | NZ22: 200 | OA22: 127.4 | OB22: 0 | OC22: 0 | OD22: 0 | OE22: 0 | OF22: 327.4 | OG22: START Europe: | OH22: 217.9 | OI22: 749.5 | OM22: 421.2 | ON22: 1388.6 | OT22: 13.5 | OU22: 13.5 | PA22: 70.2 | PB22: 70.2 | PI22: 0 | PP22: 0 | PV22: 33.8 | PW22: 33.8 | QD22: 0 | QK22: 21.6 | QL22: 21.6 | QM22: 217.9 | QN22: 749.5 | QO22: 0 | QP22: 0 | QQ22: 0 | QR22: 560.3 | QS22: 1527.7 | QT22: 217.9 | QU22: 749.5 | QY22: 143.1 | QZ22: 1110.5 | RF22: 50 | RG22: 50 | RM22: 367.2 | RN22: 367.2 | RU22: 0 | SB22: 0 | SC22: 217.9 | SD22: 749.5 | SE22: 0 | SF22: 0 | SG22: 0 | SH22: 560.3 | SI22: 1527.7 | SJ22: START North America: | SK22: 1589.8 | SL22: 49 | SP22: 240 | SQ22: 1878.8 | SR22: 30 | SS22: 78.5 | SW22: 50 | SX22: 158.5 | TE22: 0 | TL22: 0 | TM22: 60.8 | TR22: 25 | TS22: 85.8 | TT22: 81 | TY22: 75 | TZ22: 156 | UG22: 0 | UI22: 365.6 | UO22: 365.6 | UP22: 2127.2 | UQ22: 127.5 | UR22: 0 | US22: 0 | UT22: 0 | UU22: 390 | UV22: 2644.7 | UW22: 435 | VC22: 435 | VD22: 281 | VJ22: 281 | VK22: 1384.2 | VL22: 127.5 | VP22: 390 | VQ22: 1901.7 | VR22: 27 | VX22: 27 | WE22: 0 | WF22: 2127.2 | WG22: 127.5 | WH22: 0 | WI22: 0 | WJ22: 0 | WK22: 390 | WL22: 2644.7 | WM22: START Global: | AAP22: START SOUTH America: | AAQ22: 149 | AAW22: 149 | AAX22: 36.7 | ABD22: 36.7 | ABK22: 0 | ABR22: 0 | ABY22: 0 | ABZ22: 7.9 | ACF22: 7.9 | ACM22: 0 | ACO22: 41.4 | ACU22: 41.4 | ACV22: 235 | ACW22: 0 | ACX22: 0 | ACY22: 0 | ACZ22: 0 | ADA22: 0 | ADB22: 235 | ADI22: 0 | ADP22: 0 | ADW22: 0 | ADX22: 235 | AED22: 235 | AEK22: 0 | AEL22: 235 | AEM22: 0 | AEN22: 0 | AEO22: 0 | AEP22: 0 | AEQ22: 0 | AER22: 235 | AES22: START Africa: | AIV22: =IFERROR(RIGHT(AH22,LEN(AH22)-SEARCH("@",AH22,1)),"") -> pgim.com
A23: A4VWH6N | B23: ANREV | C23: Nippon ResCap Investors KK | E23: kfridley@nipponrescap.com | G23: https://secure.surveylab.co.uk/anrev-inrev-ncreif-capital-raising-2018/default.asp?survey=A4VWH6N | H23: asia | I23: 43152.288 | T23: FALSE | U23: TRUE | V23: FALSE | W23: FALSE | X23: FALSE | Y23: FALSE | Z23: 454 | AA23: 43152.287 | AB23: 54.65.203.235 | AC23: 2018 | AD23: Kenneth Fridley | AE23: Capbridge Investors K.K. | AF23: =VLOOKUP(MID(E23,SEARCH("@",E23,1),LEN(E23)-SEARCH("@",E23,1)+1),[2]Sheet1!$D:$F,3,FALSE) -> N0304 | AG23: President | AH23: k.fridley@capbridge-group.com | AI23: +813 5468-2820 | AJ23: Japan | AK23: JPY | AM23: 1 | AQ23: 10000 | AV23: 10000 | BC23: 0 | BJ23: 0 | BQ23: 0 | BX23: 0 | CE23: 0 | CF23: 0 | CG23: 10000 | CH23: 0 | CI23: 0 | CJ23: 0 | CK23: 0 | CL23: 10000 | CN23: 2 | CS23: 2 | CZ23: 0 | DG23: 0 | DN23: 0 | DU23: 0 | EB23: 0 | EC23: 0 | ED23: 2 | EE23: 0 | EF23: 0 | EG23: 0 | EH23: 0 | EI23: 2 | EJ23: NO | EK23: YES | EL23: NO | EM23: NO | EN23: NO | EO23: NO | EP23: NO | EQ23: NO | ER23: NO | ES23: NO | ET23: NO | EU23: NO | EV23: NO | EW23: NO | EX23: NO | EY23: NO | EZ23: NO | FA23: NO | FB23: NO | FC23: NO | FD23: NO | FE23: NO | FF23: NO | FG23: NO | FH23: NO | FI23: NO | FJ23: NO | FK23: NO | FL23: NO | FM23: NO | FN23: NO | FO23: NO | FP23: NO | FQ23: NO | FR23: NO | FS23: NO | FZ23: 0 | GG23: 0 | GN23: 0 | GU23: 0 | HB23: 0 | HD23: 5000 | HI23: 5000 | HK23: 5000 | HP23: 5000 | HX23: 0 | HY23: 0 | HZ23: 10000 | IA23: 0 | IB23: 0 | IC23: 0 | ID23: 0 | IE23: 10000 | IG23: 10000 | IL23: 10000 | IS23: 0 | IZ23: 0 | JG23: 0 | JN23: 0 | JO23: 0 | JP23: 10000 | JQ23: 0 | JR23: 0 | JS23: 0 | JT23: 0 | JU23: 10000 | JV23: 50 | JX23: 50 | KA23: 1 | KB23: 3 | KC23: 1 | KD23: START Asia Pacific: | KK23: 0 | KM23: 5000 | KR23: 5000 | KY23: 0 | LF23: 0 | LM23: 0 | LT23: 0 | LV23: 5000 | MA23: 5000 | MI23: 0 | MJ23: 0 | MK23: 10000 | ML23: 0 | MM23: 0 | MN23: 0 | MO23: 0 | MP23: 10000 | MW23: 0 | MY23: 10000 | ND23: 10000 | NK23: 0 | NR23: 0 | NY23: 0 | NZ23: 0 | OA23: 10000 | OB23: 0 | OC23: 0 | OD23: 0 | OE23: 0 | OF23: 10000 | OG23: START Europe: | SJ23: START North America: | WM23: START Global: | AAP23: START SOUTH America: | AES23: START Africa: | AIV23: =IFERROR(RIGHT(AH23,LEN(AH23)-SEARCH("@",AH23,1)),"") -> capbridge-group.com
A24: A4WCE7F | B24: ANREV | C24: Vicinity Centres | E24: andrew.turnham@vicinity.com.au | G24: https://secure.surveylab.co.uk/anrev-inrev-ncreif-capital-raising-2018/default.asp?survey=A4WCE7F | T24: FALSE | U24: FALSE | V24: FALSE | W24: FALSE | X24: FALSE | Y24: FALSE | Z24: 321 | AA24: 43138.194 | AB24: 101.78.165.56 | AC24: 2018 | AD24: Andrew Turnham | AE24: Vicinity Centres | AF24: =VLOOKUP(MID(E24,SEARCH("@",E24,1),LEN(E24)-SEARCH("@",E24,1)+1),[2]Sheet1!$D:$F,3,FALSE) -> N0298 | AG24: Senior Analyst | AH24: andrew.turnham@vicinity.com.au | AI24: +61 2 82297752 | AJ24: Australia | AK24: AUD | AM24: 2 | AN24: 6 | AO24: Market Conditions | AV24: 0 | BC24: 0 | BJ24: 0 | BQ24: 0 | BX24: 0 | CE24: 0 | CF24: 0 | CG24: 0 | CH24: 0 | CI24: 0 | CJ24: 0 | CK24: 0 | CL24: 0 | CS24: 0 | CZ24: 0 | DG24: 0 | DN24: 0 | DU24: 0 | EB24: 0 | EC24: 0 | ED24: 0 | EE24: 0 | EF24: 0 | EG24: 0 | EH24: 0 | EI24: 0 | EJ24: NO | EK24: NO | EL24: NO | EM24: NO | EN24: NO | EO24: NO | EP24: NO | EQ24: NO | ER24: NO | ES24: NO | ET24: NO | EU24: NO | EV24: NO | EW24: NO | EX24: NO | EY24: NO | EZ24: NO | FA24: NO | FB24: NO | FC24: NO | FD24: NO | FE24: NO | FF24: NO | FG24: NO | FH24: NO | FI24: NO | FJ24: NO | FK24: NO | FL24: NO | FM24: NO | FN24: NO | FO24: NO | FP24: NO | FQ24: NO | FR24: NO | FS24: NO | FZ24: 0 | GG24: 0 | GN24: 0 | GU24: 0 | HB24: 0 | HI24: 0 | HP24: 0 | HX24: 0 | HY24: 0 | HZ24: 0 | IA24: 0 | IB24: 0 | IC24: 0 | ID24: 0 | IE24: 0 | IL24: 0 | IS24: 0 | IZ24: 0 | JG24: 0 | JN24: 0 | JO24: 0 | JP24: 0 | JQ24: 0 | JR24: 0 | JS24: 0 | JT24: 0 | JU24: 0 | KA24: 1 | KB24: 3 | KC24: 2 | KD24: START Asia Pacific: | OG24: START Europe: | SJ24: START North America: | WM24: START Global: | AAP24: START SOUTH America: | AES24: START Africa: | AIV24: =IFERROR(RIGHT(AH24,LEN(AH24)-SEARCH("@",AH24,1)),"") -> vicinity.com.au
A25: A5DBE2T | B25: ANREV | C25: Alpha Investment Partners Limited | E25: Adrian Low' <adrian.low@alphaipartners.com> | G25: https://secure.surveylab.co.uk/anrev-inrev-ncreif-capital-raising-2018/default.asp?survey=A5DBE2T | T25: FALSE | U25: FALSE | V25: FALSE | W25: FALSE | X25: FALSE | Y25: FALSE | Z25: 441 | AA25: 43152.294 | AB25: 118.189.41.121 | AC25: 2018 | AD25: Marie Yan | AE25: Alpha Investment Partners | AF25: =VLOOKUP(MID(E25,SEARCH("@",E25,1),LEN(E25)-SEARCH("@",E25,1)+1),[2]Sheet1!$D:$F,3,FALSE) -> M0106 | AH25: marie.yan@kepcapital.com | AI25: 6803 1747 | AJ25: Singapore | AK25: USD | AM25: 1 | AV25: 0 | BC25: 0 | BJ25: 0 | BQ25: 0 | BX25: 0 | CE25: 0 | CF25: 0 | CG25: 0 | CH25: 0 | CI25: 0 | CJ25: 0 | CK25: 0 | CL25: 0 | CS25: 0 | CZ25: 0 | DG25: 0 | DN25: 0 | DU25: 0 | EB25: 0 | EC25: 0 | ED25: 0 | EE25: 0 | EF25: 0 | EG25: 0 | EH25: 0 | EI25: 0 | EJ25: NO | EK25: NO | EL25: NO | EM25: NO | EN25: NO | EO25: NO | EP25: NO | EQ25: NO | ER25: NO | ES25: NO | ET25: NO | EU25: NO | EV25: NO | EW25: NO | EX25: NO | EY25: NO | EZ25: NO | FA25: NO | FB25: NO | FC25: NO | FD25: NO | FE25: NO | FF25: NO | FG25: NO | FH25: NO | FI25: NO | FJ25: NO | FK25: NO | FL25: NO | FM25: NO | FN25: NO | FO25: NO | FP25: NO | FQ25: NO | FR25: NO | FS25: NO | FZ25: 0 | GG25: 0 | GN25: 0 | GU25: 0 | HB25: 0 | HI25: 0 | HP25: 0 | HX25: 0 | HY25: 0 | HZ25: 0 | IA25: 0 | IB25: 0 | IC25: 0 | ID25: 0 | IE25: 0 | IL25: 0 | IS25: 0 | IZ25: 0 | JG25: 0 | JN25: 0 | JO25: 0 | JP25: 0 | JQ25: 0 | JR25: 0 | JS25: 0 | JT25: 0 | JU25: 0 | JV25: 1 | JX25: 99 | KA25: 1 | KB25: 2 | KC25: 2 | KD25: START Asia Pacific: | OG25: START Europe: | SJ25: START North America: | WM25: START Global: | AAP25: START SOUTH America: | AES25: START Africa: | AIV25: =IFERROR(RIGHT(AH25,LEN(AH25)-SEARCH("@",AH25,1)),"") -> kepcapital.com
A26: A5GLL7V | B26: ANREV | C26: The GPT Group | E26: paul.caddy@gpt.com.au | G26: https://secure.surveylab.co.uk/anrev-inrev-ncreif-capital-raising-2018/default.asp?survey=A5GLL7V | T26: FALSE | U26: FALSE | V26: FALSE | W26: FALSE | X26: FALSE | Y26: FALSE | Z26: 323 | AA26: 43136.149 | AB26: 101.78.165.56 | AC26: 2018 | AD26: Paul Caddy | AE26: The GPT Group | AF26: =VLOOKUP(MID(E26,SEARCH("@",E26,1),LEN(E26)-SEARCH("@",E26,1)+1),[2]Sheet1!$D:$F,3,FALSE) -> M0075 | AG26: Senior Fund Analyst | AH26: paul.caddy@gpt.com.au | AI26: +61 2 8239 3858 | AJ26: Australia | AK26: AUD | AM26: 2 | AN26: 6 | AO26: No requirement for new capital | AV26: 0 | BC26: 0 | BJ26: 0 | BQ26: 0 | BX26: 0 | CE26: 0 | CF26: 0 | CG26: 0 | CH26: 0 | CI26: 0 | CJ26: 0 | CK26: 0 | CL26: 0 | CS26: 0 | CZ26: 0 | DG26: 0 | DN26: 0 | DU26: 0 | EB26: 0 | EC26: 0 | ED26: 0 | EE26: 0 | EF26: 0 | EG26: 0 | EH26: 0 | EI26: 0 | EJ26: NO | EK26: NO | EL26: NO | EM26: NO | EN26: NO | EO26: NO | EP26: NO | EQ26: NO | ER26: NO | ES26: NO | ET26: NO | EU26: NO | EV26: NO | EW26: NO | EX26: NO | EY26: NO | EZ26: NO | FA26: NO | FB26: NO | FC26: NO | FD26: NO | FE26: NO | FF26: NO | FG26: NO | FH26: NO | FI26: NO | FJ26: NO | FK26: NO | FL26: NO | FM26: NO | FN26: NO | FO26: NO | FP26: NO | FQ26: NO | FR26: NO | FS26: NO | FZ26: 0 | GG26: 0 | GN26: 0 | GU26: 0 | HB26: 0 | HI26: 0 | HP26: 0 | HX26: 0 | HY26: 0 | HZ26: 0 | IA26: 0 | IB26: 0 | IC26: 0 | ID26: 0 | IE26: 0 | IL26: 0 | IS26: 0 | IZ26: 0 | JG26: 0 | JN26: 0 | JO26: 0 | JP26: 0 | JQ26: 0 | JR26: 0 | JS26: 0 | JT26: 0 | JU26: 0 | KA26: 1 | KB26: 3 | KC26: 1 | KD26: START Asia Pacific: | OG26: START Europe: | SJ26: START North America: | WM26: START Global: | AAP26: START SOUTH America: | AES26: START Africa: | AIV26: =IFERROR(RIGHT(AH26,LEN(AH26)-SEARCH("@",AH26,1)),"") -> gpt.com.au
A27: A5PMT4G | B27: ANREV | C27: CapitaLand | E27: chew.weiting@capitaland.com | G27: https://secure.surveylab.co.uk/anrev-inrev-ncreif-capital-raising-2018/default.asp?survey=A5PMT4G | H27: asia | I27: 43137.183 | T27: FALSE | U27: TRUE | V27: FALSE | W27: FALSE | X27: FALSE | Y27: FALSE | Z27: 375 | AA27: 43137.183 | AB27: 175.156.61.80 | AC27: 2018 | AD27: Chew Weiting | AE27: CapitaLand | AF27: =VLOOKUP(MID(E27,SEARCH("@",E27,1),LEN(E27)-SEARCH("@",E27,1)+1),[2]Sheet1!$D:$F,3,FALSE) -> M0091 | AG27: Manager | AH27: chew.weiting@capitaland.com | AI27: +65 6713 3108 | AJ27: Singapore | AK27: USD | AM27: 1 | AP27: 300 | AV27: 300 | BC27: 0 | BJ27: 0 | BQ27: 0 | BX27: 0 | CE27: 0 | CF27: 300 | CG27: 0 | CH27: 0 | CI27: 0 | CJ27: 0 | CK27: 0 | CL27: 300 | CM27: 1 | CS27: 1 | CZ27: 0 | DG27: 0 | DN27: 0 | DU27: 0 | EB27: 0 | EC27: 1 | ED27: 0 | EE27: 0 | EF27: 0 | EG27: 0 | EH27: 0 | EI27: 1 | EJ27: YES | EK27: NO | EL27: NO | EM27: NO | EN27: NO | EO27: NO | EP27: NO | EQ27: NO | ER27: NO | ES27: NO | ET27: NO | EU27: NO | EV27: NO | EW27: NO | EX27: NO | EY27: NO | EZ27: NO | FA27: NO | FB27: NO | FC27: NO | FD27: NO | FE27: NO | FF27: NO | FG27: NO | FH27: NO | FI27: NO | FJ27: NO | FK27: NO | FL27: NO | FM27: NO | FN27: NO | FO27: NO | FP27: NO | FQ27: NO | FR27: NO | FS27: NO | FZ27: 0 | GG27: 0 | GH27: 90 | GN27: 90 | GU27: 0 | HB27: 0 | HI27: 0 | HP27: 0 | HQ27: Corporation | HR27: 210 | HX27: 210 | HY27: 300 | HZ27: 0 | IA27: 0 | IB27: 0 | IC27: 0 | ID27: 0 | IE27: 300 | IF27: 300 | IL27: 300 | IS27: 0 | IZ27: 0 | JG27: 0 | JN27: 0 | JO27: 300 | JP27: 0 | JQ27: 0 | JR27: 0 | JS27: 0 | JT27: 0 | JU27: 300 | JX27: 100 | KA27: 2 | KB27: 2 | KC27: 1 | KD27: START Asia Pacific: | KK27: 0 | KR27: 0 | KS27: 90 | KY27: 90 | LF27: 0 | LM27: 0 | LT27: 0 | MA27: 0 | MB27: Corporation | MC27: 210 | MI27: 210 | MJ27: 300 | MK27: 0 | ML27: 0 | MM27: 0 | MN27: 0 | MO27: 0 | MP27: 300 | MW27: 0 | MX27: 300 | ND27: 300 | NK27: 0 | NR27: 0 | NY27: 0 | NZ27: 300 | OA27: 0 | OB27: 0 | OC27: 0 | OD27: 0 | OE27: 0 | OF27: 300 | OG27: START Europe: | SJ27: START North America: | WM27: START Global: | AAP27: START SOUTH America: | AES27: START Africa: | AIV27: =IFERROR(RIGHT(AH27,LEN(AH27)-SEARCH("@",AH27,1)),"") -> capitaland.com
A28: A5UNR6M | B28: ANREV | C28: DEXUS Property Group | E28: jonathan.davies@dexus.com | G28: https://secure.surveylab.co.uk/anrev-inrev-ncreif-capital-raising-2018/default.asp?survey=A5UNR6M | H28: asia | I28: 43154.419 | T28: FALSE | U28: TRUE | V28: FALSE | W28: FALSE | X28: FALSE | Y28: FALSE | Z28: 357 | AA28: 43154.21 | AB28: 210.87.32.165 | AC28: 2018 | AD28: Sophia Rao | AE28: Dexus | AF28: =VLOOKUP(MID(E28,SEARCH("@",E28,1),LEN(E28)-SEARCH("@",E28,1)+1),[2]Sheet1!$D:$F,3,FALSE) -> M0090 | AG28: Investor Relations and Operations Manager | AH28: sophia.rao@dexus.com | AI28: +61 2 9017 1193 | AJ28: Australia | AK28: AUD | AM28: 1 | AP28: 712.5 | AV28: 712.5 | BC28: 0 | BJ28: 0 | BQ28: 0 | BX28: 0 | CE28: 0 | CF28: 712.5 | CG28: 0 | CH28: 0 | CI28: 0 | CJ28: 0 | CK28: 0 | CL28: 712.5 | CM28: 4 | CS28: 4 | CZ28: 0 | DG28: 0 | DN28: 0 | DU28: 0 | EB28: 0 | EC28: 4 | ED28: 0 | EE28: 0 | EF28: 0 | EG28: 0 | EH28: 0 | EI28: 4 | EJ28: YES | EK28: NO | EL28: NO | EM28: NO | EN28: NO | EO28: NO | EP28: NO | EQ28: NO | ER28: NO | ES28: NO | ET28: NO | EU28: NO | EV28: NO | EW28: NO | EX28: NO | EY28: NO | EZ28: NO | FA28: NO | FB28: NO | FC28: NO | FD28: NO | FE28: NO | FF28: NO | FG28: NO | FH28: NO | FI28: NO | FJ28: NO | FK28: NO | FL28: NO | FM28: NO | FN28: NO | FO28: NO | FP28: NO | FQ28: NO | FR28: NO | FS28: NO | FT28: 459.88 | FZ28: 459.88 | GA28: 8.2 | GG28: 8.2 | GH28: 0 | GN28: 0 | GO28: 87.5 | GU28: 87.5 | GV28: 0 | HB28: 0 | HC28: 0 | HI28: 0 | HJ28: 0 | HP28: 0 | HQ28: Healthcare operator | HR28: 156.92 | HX28: 156.92 | HY28: 712.5 | HZ28: 0 | IA28: 0 | IB28: 0 | IC28: 0 | ID28: 0 | IE28: 712.5 | IF28: 712.5 | IL28: 712.5 | IS28: 0 | IZ28: 0 | JG28: 0 | JN28: 0 | JO28: 712.5 | JP28: 0 | JQ28: 0 | JR28: 0 | JS28: 0 | JT28: 0 | JU28: 712.5 | JV28: 0 | JW28: 0 | JX28: 100 | JZ28: 0 | KA28: 1 | KB28: 3 | KC28: 1 | KD28: START Asia Pacific: | KE28: 459.88 | KK28: 459.88 | KL28: 8.2 | KR28: 8.2 | KY28: 0 | KZ28: 87.5 | LF28: 87.5 | LM28: 0 | LT28: 0 | MA28: 0 | MB28: Healthcare operator | MC28: 156.92 | MI28: 156.92 | MJ28: 712.5 | MK28: 0 | ML28: 0 | MM28: 0 | MN28: 0 | MO28: 0 | MP28: 712.5 | MW28: 0 | MX28: 712.5 | ND28: 712.5 | NK28: 0 | NR28: 0 | NY28: 0 | NZ28: 712.5 | OA28: 0 | OB28: 0 | OC28: 0 | OD28: 0 | OE28: 0 | OF28: 712.5 | OG28: START Europe: | SJ28: START North America: | WM28: START Global: | AAP28: START SOUTH America: | AES28: START Africa: | AIV28: =IFERROR(RIGHT(AH28,LEN(AH28)-SEARCH("@",AH28,1)),"") -> dexus.com
A29: A6AYK4K | B29: ANREV | C29: CITIC Capital Holdings Limited | E29: jfung@citiccapital.com | G29: https://secure.surveylab.co.uk/anrev-inrev-ncreif-capital-raising-2018/default.asp?survey=A6AYK4K | H29: asia | I29: 43161.421 | N29: global | O29: 43165.263 | T29: FALSE | U29: TRUE | V29: FALSE | W29: TRUE | X29: FALSE | Y29: FALSE | Z29: 457 | AA29: 43161.421 | AB29: 61.244.118.81 | AC29: 2018 | AD29: Vivian Wong | AE29: CITIC Capital Holdings Limited | AF29: =VLOOKUP(MID(E29,SEARCH("@",E29,1),LEN(E29)-SEARCH("@",E29,1)+1),[2]Sheet1!$D:$F,3,FALSE) -> M0107 | AG29: Executive Director | AH29: vivianwong@citiccapital.com | AJ29: Hong Kong | AK29: USD | AM29: 1 | AP29: 510 | AV29: 510 | BC29: 0 | BJ29: 0 | BK29: 30 | BQ29: 30 | BX29: 0 | CE29: 0 | CF29: 540 | CG29: 0 | CH29: 0 | CI29: 0 | CJ29: 0 | CK29: 0 | CL29: 540 | CM29: 2 | CS29: 2 | CZ29: 0 | DG29: 0 | DH29: 1 | DN29: 1 | DU29: 0 | EB29: 0 | EC29: 3 | ED29: 0 | EE29: 0 | EF29: 0 | EG29: 0 | EH29: 0 | EI29: 3 | EJ29: YES | EK29: NO | EL29: NO | EM29: NO | EN29: NO | EO29: NO | EP29: NO | EQ29: NO | ER29: NO | ES29: NO | ET29: NO | EU29: NO | EV29: NO | EW29: NO | EX29: NO | EY29: NO | EZ29: NO | FA29: NO | FB29: YES | FC29: NO | FD29: NO | FE29: NO | FF29: NO | FG29: NO | FH29: NO | FI29: NO | FJ29: NO | FK29: NO | FL29: NO | FM29: NO | FN29: NO | FO29: NO | FP29: NO | FQ29: NO | FR29: NO | FS29: NO | FZ29: 0 | GG29: 0 | GN29: 0 | GU29: 0 | HB29: 0 | HI29: 0 | HP29: 0 | HR29: 540 | HX29: 540 | HY29: 540 | HZ29: 0 | IA29: 0 | IB29: 0 | IC29: 0 | ID29: 0 | IE29: 540 | IF29: 540 | IL29: 540 | IS29: 0 | IZ29: 0 | JG29: 0 | JN29: 0 | JO29: 540 | JP29: 0 | JQ29: 0 | JR29: 0 | JS29: 0 | JT29: 0 | JU29: 540 | JW29: 50 | JX29: 50 | KA29: 1 | KB29: 3 | KC29: 1 | KD29: START Asia Pacific: | KK29: 0 | KR29: 0 | KY29: 0 | LF29: 0 | LM29: 0 | LT29: 0 | MA29: 0 | MC29: 510 | MI29: 510 | MJ29: 510 | MK29: 0 | ML29: 0 | MM29: 0 | MN29: 0 | MO29: 0 | MP29: 510 | MW29: 0 | MX29: 510 | ND29: 510 | NK29: 0 | NR29: 0 | NY29: 0 | NZ29: 510 | OA29: 0 | OB29: 0 | OC29: 0 | OD29: 0 | OE29: 0 | OF29: 510 | OG29: START Europe: | SJ29: START North America: | WM29: START Global: | WT29: 0 | XA29: 0 | XH29: 0 | XO29: 0 | XV29: 0 | YC29: 0 | YJ29: 0 | YL29: 30 | YR29: 30 | YS29: 30 | YT29: 0 | YU29: 0 | YV29: 0 | YW29: 0 | YX29: 0 | YY29: 30 | ZF29: 0 | ZG29: 30 | ZM29: 30 | ZT29: 0 | AAA29: 0 | AAH29: 0 | AAI29: 30 | AAJ29: 0 | AAK29: 0 | AAL29: 0 | AAM29: 0 | AAN29: 0 | AAO29: 30 | AAP29: START SOUTH America: | AES29: START Africa: | AIV29: =IFERROR(RIGHT(AH29,LEN(AH29)-SEARCH("@",AH29,1)),"") -> citiccapital.com
A30: A6DGG5R | B30: ANREV | C30: EZLand | E30: olivier.dongoc@ezland.vn | G30: https://secure.surveylab.co.uk/anrev-inrev-ncreif-capital-raising-2018/default.asp?survey=A6DGG5R | T30: FALSE | U30: TRUE | V30: FALSE | W30: FALSE | X30: FALSE | Y30: FALSE | Z30: 331 | AA30: 43115.761 | AB30: 14.161.9.128 | AC30: 2018 | AD30: Olivier Dung Do Ngoc | AE30: AHF GP Hong Kong | AF30: =VLOOKUP(MID(E30,SEARCH("@",E30,1),LEN(E30)-SEARCH("@",E30,1)+1),[2]Sheet1!$D:$F,3,FALSE) -> M0278 | AG30: Managing Partner | AH30: olivier.dongoc@ezland.vn | AI30: 84933333960 | AJ30: Luxembourg | AK30: USD | AM30: 1 | AS30: 15 | AV30: 15 | BC30: 0 | BJ30: 0 | BQ30: 0 | BX30: 0 | CE30: 0 | CF30: 0 | CG30: 0 | CH30: 0 | CI30: 15 | CJ30: 0 | CK30: 0 | CL30: 15 | CP30: 1 | CS30: 1 | CZ30: 0 | DG30: 0 | DN30: 0 | DU30: 0 | EB30: 0 | EC30: 0 | ED30: 0 | EE30: 0 | EF30: 1 | EG30: 0 | EH30: 0 | EI30: 1 | EJ30: NO | EK30: NO | EL30: NO | EM30: YES | EN30: NO | EO30: NO | EP30: NO | EQ30: NO | ER30: NO | ES30: NO | ET30: NO | EU30: NO | EV30: NO | EW30: NO | EX30: NO | EY30: NO | EZ30: NO | FA30: NO | FB30: NO | FC30: NO | FD30: NO | FE30: NO | FF30: NO | FG30: NO | FH30: NO | FI30: NO | FJ30: NO | FK30: NO | FL30: NO | FM30: NO | FN30: NO | FO30: NO | FP30: NO | FQ30: NO | FR30: NO | FS30: NO | FZ30: 0 | GG30: 0 | GN30: 0 | GU30: 0 | HB30: 0 | HF30: 15 | HI30: 15 | HP30: 0 | HX30: 0 | HY30: 0 | HZ30: 0 | IA30: 0 | IB30: 15 | IC30: 0 | ID30: 0 | IE30: 15 | II30: 15 | IL30: 15 | IS30: 0 | IZ30: 0 | JG30: 0 | JN30: 0 | JO30: 0 | JP30: 0 | JQ30: 0 | JR30: 15 | JS30: 0 | JT30: 0 | JU30: 15 | JX30: 100 | KA30: 1 | KB30: 3 | KC30: 1 | KD30: START Asia Pacific: | OG30: START Europe: | SJ30: START North America: | WM30: START Global: | AAP30: START SOUTH America: | AES30: START Africa: | AIV30: =IFERROR(RIGHT(AH30,LEN(AH30)-SEARCH("@",AH30,1)),"") -> ezland.vn
A31: A6HUN6R | B31: ANREV | C31: Macquarie | E31: ingrid.nell@macquarie.com | G31: https://secure.surveylab.co.uk/anrev-inrev-ncreif-capital-raising-2018/default.asp?survey=A6HUN6R | T31: FALSE | U31: FALSE | V31: FALSE | W31: FALSE | X31: FALSE | Y31: FALSE | Z31: 385 | AA31: 43124.24 | AB31: 203.210.79.192 | AC31: 2018 | AD31: Ingrid Nell | AE31: Macquarie Infrastructure & Real Assets | AF31: =VLOOKUP(MID(E31,SEARCH("@",E31,1),LEN(E31)-SEARCH("@",E31,1)+1),[2]Sheet1!$D:$F,3,FALSE) -> M766 | AG31: Senior Vice President | AH31: ingrid.nell@macquarie.com | AJ31: Australia | AK31: USD | AM31: 2 | AN31: 6 | AO31: Couldnt find suitable assets | AV31: 0 | BC31: 0 | BJ31: 0 | BQ31: 0 | BX31: 0 | CE31: 0 | CF31: 0 | CG31: 0 | CH31: 0 | CI31: 0 | CJ31: 0 | CK31: 0 | CL31: 0 | CS31: 0 | CZ31: 0 | DG31: 0 | DN31: 0 | DU31: 0 | EB31: 0 | EC31: 0 | ED31: 0 | EE31: 0 | EF31: 0 | EG31: 0 | EH31: 0 | EI31: 0 | EJ31: NO | EK31: NO | EL31: NO | EM31: NO | EN31: NO | EO31: NO | EP31: NO | EQ31: NO | ER31: NO | ES31: NO | ET31: NO | EU31: NO | EV31: NO | EW31: NO | EX31: NO | EY31: NO | EZ31: NO | FA31: NO | FB31: NO | FC31: NO | FD31: NO | FE31: NO | FF31: NO | FG31: NO | FH31: NO | FI31: NO | FJ31: NO | FK31: NO | FL31: NO | FM31: NO | FN31: NO | FO31: NO | FP31: NO | FQ31: NO | FR31: NO | FS31: NO | FZ31: 0 | GG31: 0 | GN31: 0 | GU31: 0 | HB31: 0 | HI31: 0 | HP31: 0 | HX31: 0 | HY31: 0 | HZ31: 0 | IA31: 0 | IB31: 0 | IC31: 0 | ID31: 0 | IE31: 0 | IL31: 0 | IS31: 0 | IZ31: 0 | JG31: 0 | JN31: 0 | JO31: 0 | JP31: 0 | JQ31: 0 | JR31: 0 | JS31: 0 | JT31: 0 | JU31: 0 | KA31: 1 | KB31: 3 | KC31: 2 | KD31: START Asia Pacific: | OG31: START Europe: | SJ31: START North America: | WM31: START Global: | AAP31: START SOUTH America: | AES31: START Africa: | AIV31: =IFERROR(RIGHT(AH31,LEN(AH31)-SEARCH("@",AH31,1)),"") -> macquarie.com
A32: A6KPD5U | B32: ANREV | C32: Orion Partners Real Estate Group | E32: klee@orionpartners.com | G32: https://secure.surveylab.co.uk/anrev-inrev-ncreif-capital-raising-2018/default.asp?survey=A6KPD5U | H32: asia | I32: 43139.148 | T32: FALSE | U32: TRUE | V32: FALSE | W32: FALSE | X32: FALSE | Y32: FALSE | Z32: 365 | AA32: 43139.145 | AB32: 202.77.62.76 | AC32: 2018 | AD32: John LEE | AE32: Orion Partners Real Estate Group | AF32: =VLOOKUP(MID(E32,SEARCH("@",E32,1),LEN(E32)-SEARCH("@",E32,1)+1),[2]Sheet1!$D:$F,3,FALSE) -> M0035 | AG32: Partner and Head of Real Estate Group | AH32: jlee@orionpartners.com | AI32: +852 2218-2168 | AJ32: Hong Kong | AK32: EUR | AM32: 1 | AQ32: 101 | AV32: 101 | BC32: 0 | BJ32: 0 | BQ32: 0 | BX32: 0 | CE32: 0 | CF32: 0 | CG32: 101 | CH32: 0 | CI32: 0 | CJ32: 0 | CK32: 0 | CL32: 101 | CN32: 1 | CS32: 1 | CZ32: 0 | DG32: 0 | DN32: 0 | DU32: 0 | EB32: 0 | EC32: 0 | ED32: 1 | EE32: 0 | EF32: 0 | EG32: 0 | EH32: 0 | EI32: 1 | EJ32: NO | EK32: YES | EL32: NO | EM32: NO | EN32: NO | EO32: NO | EP32: NO | EQ32: NO | ER32: NO | ES32: NO | ET32: NO | EU32: NO | EV32: NO | EW32: NO | EX32: NO | EY32: NO | EZ32: NO | FA32: NO | FB32: NO | FC32: NO | FD32: NO | FE32: NO | FF32: NO | FG32: NO | FH32: NO | FI32: NO | FJ32: NO | FK32: NO | FL32: NO | FM32: NO | FN32: NO | FO32: NO | FP32: NO | FQ32: NO | FR32: NO | FS32: NO | FU32: 100 | FZ32: 100 | GG32: 0 | GN32: 0 | GU32: 0 | HB32: 0 | HI32: 0 | HP32: 0 | HQ32: Corporations | HS32: 1 | HX32: 1 | HY32: 0 | HZ32: 101 | IA32: 0 | IB32: 0 | IC32: 0 | ID32: 0 | IE32: 101 | IL32: 0 | IN32: 101 | IS32: 101 | IZ32: 0 | JG32: 0 | JN32: 0 | JO32: 0 | JP32: 101 | JQ32: 0 | JR32: 0 | JS32: 0 | JT32: 0 | JU32: 101 | JX32: 100 | JY32: Being top-up Commitment in existing fund raised in FY2015 | KA32: 1 | KB32: 3 | KC32: 1 | KD32: START Asia Pacific: | KF32: 100 | KK32: 100 | KR32: 0 | KY32: 0 | LF32: 0 | LM32: 0 | LT32: 0 | MA32: 0 | MB32: Corporations | MD32: 1 | MI32: 1 | MJ32: 0 | MK32: 101 | ML32: 0 | MM32: 0 | MN32: 0 | MO32: 0 | MP32: 101 | MR32: 101 | MW32: 101 | ND32: 0 | NK32: 0 | NR32: 0 | NY32: 0 | NZ32: 0 | OA32: 101 | OB32: 0 | OC32: 0 | OD32: 0 | OE32: 0 | OF32: 101 | OG32: START Europe: | SJ32: START North America: | WM32: START Global: | AAP32: START SOUTH America: | AES32: START Africa: | AIV32: =IFERROR(RIGHT(AH32,LEN(AH32)-SEARCH("@",AH32,1)),"") -> orionpartners.com
A33: A6KXR5U | B33: ANREV | C33: Piramal Fund Management - INDIAREIT Fund Advisors | E33: mukul.singh@piramal.com | G33: https://secure.surveylab.co.uk/anrev-inrev-ncreif-capital-raising-2018/default.asp?survey=A6KXR5U | H33: asia | I33: 43136.371 | T33: FALSE | U33: TRUE | V33: FALSE | W33: FALSE | X33: FALSE | Y33: FALSE | Z33: 306 | AA33: 43136.37 | AB33: 110.173.185.219 | AC33: 2018 | AD33: Piramal Fund Management Pvt. Ltd | AE33: Piramal Fund | AF33: =VLOOKUP(MID(E33,SEARCH("@",E33,1),LEN(E33)-SEARCH("@",E33,1)+1),[2]Sheet1!$D:$F,3,FALSE) -> N0292 | AG33: Investor Relations | AH33: investors@piramal.com | AJ33: India | AK33: INR | AM33: 1 | AP33: 330 | AV33: 330 | BC33: 0 | BJ33: 0 | BQ33: 0 | BX33: 0 | CE33: 0 | CF33: 330 | CG33: 0 | CH33: 0 | CI33: 0 | CJ33: 0 | CK33: 0 | CL33: 330 | CM33: 1 | CS33: 1 | CZ33: 0 | DG33: 0 | DN33: 0 | DU33: 0 | EB33: 0 | EC33: 1 | ED33: 0 | EE33: 0 | EF33: 0 | EG33: 0 | EH33: 0 | EI33: 1 | EJ33: YES | EK33: NO | EL33: NO | EM33: NO | EN33: NO | EO33: NO | EP33: NO | EQ33: NO | ER33: NO | ES33: NO | ET33: NO | EU33: NO | EV33: NO | EW33: NO | EX33: NO | EY33: NO | EZ33: NO | FA33: NO | FB33: NO | FC33: NO | FD33: NO | FE33: NO | FF33: NO | FG33: NO | FH33: NO | FI33: NO | FJ33: NO | FK33: NO | FL33: NO | FM33: NO | FN33: NO | FO33: NO | FP33: NO | FQ33: NO | FR33: NO | FS33: NO | FZ33: 0 | GG33: 0 | GN33: 0 | GU33: 0 | HB33: 0 | HI33: 0 | HJ33: 330 | HP33: 330 | HX33: 0 | HY33: 330 | HZ33: 0 | IA33: 0 | IB33: 0 | IC33: 0 | ID33: 0 | IE33: 330 | IF33: 330 | IL33: 330 | IS33: 0 | IZ33: 0 | JG33: 0 | JN33: 0 | JO33: 330 | JP33: 0 | JQ33: 0 | JR33: 0 | JS33: 0 | JT33: 0 | JU33: 330 | JV33: 60 | JW33: 20 | JX33: 20 | KA33: 1 | KB33: 1 | KC33: 2 | KD33: START Asia Pacific: | KK33: 0 | KR33: 0 | KY33: 0 | LF33: 0 | LM33: 0 | LT33: 0 | LU33: 330 | MA33: 330 | MI33: 0 | MJ33: 330 | MK33: 0 | ML33: 0 | MM33: 0 | MN33: 0 | MO33: 0 | MP33: 330 | MW33: 0 | MX33: 330 | ND33: 330 | NK33: 0 | NR33: 0 | NY33: 0 | NZ33: 330 | OA33: 0 | OB33: 0 | OC33: 0 | OD33: 0 | OE33: 0 | OF33: 330 | OG33: START Europe: | SJ33: START North America: | WM33: START Global: | AAP33: START SOUTH America: | AES33: START Africa: | AIV33: =IFERROR(RIGHT(AH33,LEN(AH33)-SEARCH("@",AH33,1)),"") -> piramal.com
A34: A6NCX6A | B34: ANREV | C34: White Peak | E34: markus.puusepp@wprei.com | G34: https://secure.surveylab.co.uk/anrev-inrev-ncreif-capital-raising-2018/default.asp?survey=A6NCX6A | T34: FALSE | U34: FALSE | V34: FALSE | W34: FALSE | X34: FALSE | Y34: FALSE | Z34: 477 | AA34: 43158.355 | AB34: 47.52.39.31 | AC34: 2018 | AD34: Karen Xu | AE34: White Peak Real Estate Investment | AF34: =VLOOKUP(MID(E34,SEARCH("@",E34,1),LEN(E34)-SEARCH("@",E34,1)+1),[2]Sheet1!$D:$F,3,FALSE) -> M0128 | AG34: Head of Investor Relations | AH34: karen.xu@wprei.com | AJ34: China | AK34: CNY | AM34: 2 | AN34: 5 | AV34: 0 | BC34: 0 | BJ34: 0 | BQ34: 0 | BX34: 0 | CE34: 0 | CF34: 0 | CG34: 0 | CH34: 0 | CI34: 0 | CJ34: 0 | CK34: 0 | CL34: 0 | CS34: 0 | CZ34: 0 | DG34: 0 | DN34: 0 | DU34: 0 | EB34: 0 | EC34: 0 | ED34: 0 | EE34: 0 | EF34: 0 | EG34: 0 | EH34: 0 | EI34: 0 | EJ34: NO | EK34: NO | EL34: NO | EM34: NO | EN34: NO | EO34: NO | EP34: NO | EQ34: NO | ER34: NO | ES34: NO | ET34: NO | EU34: NO | EV34: NO | EW34: NO | EX34: NO | EY34: NO | EZ34: NO | FA34: NO | FB34: NO | FC34: NO | FD34: NO | FE34: NO | FF34: NO | FG34: NO | FH34: NO | FI34: NO | FJ34: NO | FK34: NO | FL34: NO | FM34: NO | FN34: NO | FO34: NO | FP34: NO | FQ34: NO | FR34: NO | FS34: NO | FZ34: 0 | GG34: 0 | GN34: 0 | GU34: 0 | HB34: 0 | HI34: 0 | HP34: 0 | HX34: 0 | HY34: 0 | HZ34: 0 | IA34: 0 | IB34: 0 | IC34: 0 | ID34: 0 | IE34: 0 | IL34: 0 | IS34: 0 | IZ34: 0 | JG34: 0 | JN34: 0 | JO34: 0 | JP34: 0 | JQ34: 0 | JR34: 0 | JS34: 0 | JT34: 0 | JU34: 0 | KA34: 2 | KB34: 2 | KC34: 1 | KD34: START Asia Pacific: | OG34: START Europe: | SJ34: START North America: | WM34: START Global: | AAP34: START SOUTH America: | AES34: START Africa: | AIV34: =IFERROR(RIGHT(AH34,LEN(AH34)-SEARCH("@",AH34,1)),"") -> wprei.com
A35: A6PBW7W | B35: ANREV | C35: ARCH Capital Management Co Ltd | E35: lli@archcapital.net | G35: https://secure.surveylab.co.uk/anrev-inrev-ncreif-capital-raising-2018/default.asp?survey=A6PBW7W | T35: FALSE | U35: FALSE | V35: FALSE | W35: FALSE | X35: FALSE | Y35: FALSE | Z35: 440 | AA35: 43151.531 | AB35: 125.215.194.145 | AC35: 2018 | AD35: Loretta Li | AE35: ARCH Capital Management Co Ltd | AF35: =VLOOKUP(MID(E35,SEARCH("@",E35,1),LEN(E35)-SEARCH("@",E35,1)+1),[2]Sheet1!$D:$F,3,FALSE) -> M421 | AH35: lli@archcapital.net | AJ35: Hong Kong | AK35: USD | AM35: 2 | AN35: 6 | AO35: we are not having fund raise in every year | AV35: 0 | BC35: 0 | BJ35: 0 | BQ35: 0 | BX35: 0 | CE35: 0 | CF35: 0 | CG35: 0 | CH35: 0 | CI35: 0 | CJ35: 0 | CK35: 0 | CL35: 0 | CS35: 0 | CZ35: 0 | DG35: 0 | DN35: 0 | DU35: 0 | EB35: 0 | EC35: 0 | ED35: 0 | EE35: 0 | EF35: 0 | EG35: 0 | EH35: 0 | EI35: 0 | EJ35: NO | EK35: NO | EL35: NO | EM35: NO | EN35: NO | EO35: NO | EP35: NO | EQ35: NO | ER35: NO | ES35: NO | ET35: NO | EU35: NO | EV35: NO | EW35: NO | EX35: NO | EY35: NO | EZ35: NO | FA35: NO | FB35: NO | FC35: NO | FD35: NO | FE35: NO | FF35: NO | FG35: NO | FH35: NO | FI35: NO | FJ35: NO | FK35: NO | FL35: NO | FM35: NO | FN35: NO | FO35: NO | FP35: NO | FQ35: NO | FR35: NO | FS35: NO | FZ35: 0 | GG35: 0 | GN35: 0 | GU35: 0 | HB35: 0 | HI35: 0 | HP35: 0 | HX35: 0 | HY35: 0 | HZ35: 0 | IA35: 0 | IB35: 0 | IC35: 0 | ID35: 0 | IE35: 0 | IL35: 0 | IS35: 0 | IZ35: 0 | JG35: 0 | JN35: 0 | JO35: 0 | JP35: 0 | JQ35: 0 | JR35: 0 | JS35: 0 | JT35: 0 | JU35: 0 | KA35: 3 | KB35: 3 | KC35: 2 | KD35: START Asia Pacific: | OG35: START Europe: | SJ35: START North America: | WM35: START Global: | AAP35: START SOUTH America: | AES35: START Africa: | AIV35: =IFERROR(RIGHT(AH35,LEN(AH35)-SEARCH("@",AH35,1)),"") -> archcapital.net
A36: A6TYT2V | B36: ANREV | C36: Investa Property Group | E36: nchui@investa.com.au | G36: https://secure.surveylab.co.uk/anrev-inrev-ncreif-capital-raising-2018/default.asp?survey=A6TYT2V | T36: FALSE | U36: FALSE | V36: FALSE | W36: FALSE | X36: FALSE | Y36: FALSE | Z36: 407 | AA36: 43143.033 | AB36: 115.124.35.138 | AC36: 2018 | AD36: Anna Changizi | AE36: Investa Property Group | AF36: =VLOOKUP(MID(E36,SEARCH("@",E36,1),LEN(E36)-SEARCH("@",E36,1)+1),[2]Sheet1!$D:$F,3,FALSE) -> M0077 | AG36: Client Support Associate | AH36: achangizi@investa.com.au | AJ36: Australia | AK36: AUD | AM36: 2 | AN36: 1 | AV36: 0 | BC36: 0 | BJ36: 0 | BQ36: 0 | BX36: 0 | CE36: 0 | CF36: 0 | CG36: 0 | CH36: 0 | CI36: 0 | CJ36: 0 | CK36: 0 | CL36: 0 | CS36: 0 | CZ36: 0 | DG36: 0 | DN36: 0 | DU36: 0 | EB36: 0 | EC36: 0 | ED36: 0 | EE36: 0 | EF36: 0 | EG36: 0 | EH36: 0 | EI36: 0 | EJ36: NO | EK36: NO | EL36: NO | EM36: NO | EN36: NO | EO36: NO | EP36: NO | EQ36: NO | ER36: NO | ES36: NO | ET36: NO | EU36: NO | EV36: NO | EW36: NO | EX36: NO | EY36: NO | EZ36: NO | FA36: NO | FB36: NO | FC36: NO | FD36: NO | FE36: NO | FF36: NO | FG36: NO | FH36: NO | FI36: NO | FJ36: NO | FK36: NO | FL36: NO | FM36: NO | FN36: NO | FO36: NO | FP36: NO | FQ36: NO | FR36: NO | FS36: NO | FZ36: 0 | GG36: 0 | GN36: 0 | GU36: 0 | HB36: 0 | HI36: 0 | HP36: 0 | HX36: 0 | HY36: 0 | HZ36: 0 | IA36: 0 | IB36: 0 | IC36: 0 | ID36: 0 | IE36: 0 | IL36: 0 | IS36: 0 | IZ36: 0 | JG36: 0 | JN36: 0 | JO36: 0 | JP36: 0 | JQ36: 0 | JR36: 0 | JS36: 0 | JT36: 0 | JU36: 0 | KA36: 1 | KB36: 3 | KD36: START Asia Pacific: | OG36: START Europe: | SJ36: START North America: | WM36: START Global: | AAP36: START SOUTH America: | AES36: START Africa: | AIV36: =IFERROR(RIGHT(AH36,LEN(AH36)-SEARCH("@",AH36,1)),"") -> investa.com.au
A37: A6VGA2X | B37: ANREV | C37: Seven Seas Advisors Co. LTD. | E37: minoru.yonekura@sevenseas-adv.com | G37: https://secure.surveylab.co.uk/anrev-inrev-ncreif-capital-raising-2018/default.asp?survey=A6VGA2X | H37: asia | I37: 43151.388 | T37: FALSE | U37: TRUE | V37: FALSE | W37: FALSE | X37: FALSE | Y37: FALSE | Z37: 451 | AA37: 43151.387 | AB37: 210.138.169.29 | AC37: 2018 | AD37: Minoru Yonekura | AE37: Seven Seas Advisors Co., LTD. | AF37: =VLOOKUP(MID(E37,SEARCH("@",E37,1),LEN(E37)-SEARCH("@",E37,1)+1),[2]Sheet1!$D:$F,3,FALSE) -> M0235 | AG37: CEO | AH37: minoru.yonekura@sevenseas-adv.com | AI37: +813 3539 1491 | AJ37: Japan | AK37: JPY | AM37: 1 | AQ37: 2000 | AV37: 2000 | BC37: 0 | BJ37: 0 | BQ37: 0 | BX37: 0 | CE37: 0 | CF37: 0 | CG37: 2000 | CH37: 0 | CI37: 0 | CJ37: 0 | CK37: 0 | CL37: 2000 | CN37: 2 | CS37: 2 | CZ37: 0 | DG37: 0 | DN37: 0 | DU37: 0 | EB37: 0 | EC37: 0 | ED37: 2 | EE37: 0 | EF37: 0 | EG37: 0 | EH37: 0 | EI37: 2 | EJ37: NO | EK37: YES | EL37: NO | EM37: NO | EN37: NO | EO37: NO | EP37: NO | EQ37: NO | ER37: NO | ES37: NO | ET37: NO | EU37: NO | EV37: NO | EW37: NO | EX37: NO | EY37: NO | EZ37: NO | FA37: NO | FB37: NO | FC37: NO | FD37: NO | FE37: NO | FF37: NO | FG37: NO | FH37: NO | FI37: NO | FJ37: NO | FK37: NO | FL37: NO | FM37: NO | FN37: NO | FO37: NO | FP37: NO | FQ37: NO | FR37: NO | FS37: NO | FZ37: 0 | GG37: 0 | GN37: 0 | GU37: 0 | HB37: 0 | HD37: 2000 | HI37: 2000 | HP37: 0 | HX37: 0 | HY37: 0 | HZ37: 2000 | IA37: 0 | IB37: 0 | IC37: 0 | ID37: 0 | IE37: 2000 | IG37: 2000 | IL37: 2000 | IS37: 0 | IZ37: 0 | JG37: 0 | JN37: 0 | JO37: 0 | JP37: 2000 | JQ37: 0 | JR37: 0 | JS37: 0 | JT37: 0 | JU37: 2000 | JX37: 100 | KA37: 2 | KB37: 2 | KC37: 1 | KD37: START Asia Pacific: | KK37: 0 | KR37: 0 | KY37: 0 | LF37: 0 | LM37: 0 | LO37: 2000 | LT37: 2000 | MA37: 0 | MI37: 0 | MJ37: 0 | MK37: 2000 | ML37: 0 | MM37: 0 | MN37: 0 | MO37: 0 | MP37: 2000 | MW37: 0 | MY37: 2000 | ND37: 2000 | NK37: 0 | NR37: 0 | NY37: 0 | NZ37: 0 | OA37: 2000 | OB37: 0 | OC37: 0 | OD37: 0 | OE37: 0 | OF37: 2000 | OG37: START Europe: | SJ37: START North America: | WM37: START Global: | AAP37: START SOUTH America: | AES37: START Africa: | AIV37: =IFERROR(RIGHT(AH37,LEN(AH37)-SEARCH("@",AH37,1)),"") -> sevenseas-adv.com
A38: A7DVH2J | B38: ANREV | C38: ISPT Pty. Ltd | E38: susannahb@ispt.net.au | G38: https://secure.surveylab.co.uk/anrev-inrev-ncreif-capital-raising-2018/default.asp?survey=A7DVH2J | T38: FALSE | U38: FALSE | V38: FALSE | W38: FALSE | X38: FALSE | Y38: FALSE | Z38: 476 | AA38: 43157.926 | AB38: 139.130.60.130 | AC38: 2018 | AD38: susannah bourke | AE38: ispt | AF38: =VLOOKUP(MID(E38,SEARCH("@",E38,1),LEN(E38)-SEARCH("@",E38,1)+1),[2]Sheet1!$D:$F,3,FALSE) -> M0269 | AG38: investor relatoins | AH38: susannahb@ispt.net.au | AJ38: Australia | AK38: AUD | AM38: 2 | AN38: 1 | AV38: 0 | BC38: 0 | BJ38: 0 | BQ38: 0 | BX38: 0 | CE38: 0 | CF38: 0 | CG38: 0 | CH38: 0 | CI38: 0 | CJ38: 0 | CK38: 0 | CL38: 0 | CS38: 0 | CZ38: 0 | DG38: 0 | DN38: 0 | DU38: 0 | EB38: 0 | EC38: 0 | ED38: 0 | EE38: 0 | EF38: 0 | EG38: 0 | EH38: 0 | EI38: 0 | EJ38: NO | EK38: NO | EL38: NO | EM38: NO | EN38: NO | EO38: NO | EP38: NO | EQ38: NO | ER38: NO | ES38: NO | ET38: NO | EU38: NO | EV38: NO | EW38: NO | EX38: NO | EY38: NO | EZ38: NO | FA38: NO | FB38: NO | FC38: NO | FD38: NO | FE38: NO | FF38: NO | FG38: NO | FH38: NO | FI38: NO | FJ38: NO | FK38: NO | FL38: NO | FM38: NO | FN38: NO | FO38: NO | FP38: NO | FQ38: NO | FR38: NO | FS38: NO | FZ38: 0 | GG38: 0 | GN38: 0 | GU38: 0 | HB38: 0 | HI38: 0 | HP38: 0 | HX38: 0 | HY38: 0 | HZ38: 0 | IA38: 0 | IB38: 0 | IC38: 0 | ID38: 0 | IE38: 0 | IL38: 0 | IS38: 0 | IZ38: 0 | JG38: 0 | JN38: 0 | JO38: 0 | JP38: 0 | JQ38: 0 | JR38: 0 | JS38: 0 | JT38: 0 | JU38: 0 | KA38: 1 | KB38: 2 | KC38: 1 | KD38: START Asia Pacific: | OG38: START Europe: | SJ38: START North America: | WM38: START Global: | AAP38: START SOUTH America: | AES38: START Africa: | AIV38: =IFERROR(RIGHT(AH38,LEN(AH38)-SEARCH("@",AH38,1)),"") -> ispt.net.au
A39: A7EZP4L | B39: ANREV | C39: Ascendas Pte Ltd | E39: alan.ooi@ascendas.com | G39: https://secure.surveylab.co.uk/anrev-inrev-ncreif-capital-raising-2018/default.asp?survey=A7EZP4L | T39: FALSE | U39: FALSE | V39: FALSE | W39: FALSE | X39: FALSE | Y39: FALSE | Z39: 372 | AA39: 43123.332 | AB39: 118.189.68.71 | AC39: 2018 | AD39: Adrian Low | AE39: Ascendas | AF39: =VLOOKUP(MID(E39,SEARCH("@",E39,1),LEN(E39)-SEARCH("@",E39,1)+1),[2]Sheet1!$D:$F,3,FALSE) -> M0189 | AG39: Head, Fundraising | AH39: adrian.low@ascendas-singbridge.com | AJ39: Singapore | AK39: USD | AM39: 2 | AN39: 6 | AO39: Under negotiation / on track | AV39: 0 | BC39: 0 | BJ39: 0 | BQ39: 0 | BX39: 0 | CE39: 0 | CF39: 0 | CG39: 0 | CH39: 0 | CI39: 0 | CJ39: 0 | CK39: 0 | CL39: 0 | CS39: 0 | CZ39: 0 | DG39: 0 | DN39: 0 | DU39: 0 | EB39: 0 | EC39: 0 | ED39: 0 | EE39: 0 | EF39: 0 | EG39: 0 | EH39: 0 | EI39: 0 | EJ39: NO | EK39: NO | EL39: NO | EM39: NO | EN39: NO | EO39: NO | EP39: NO | EQ39: NO | ER39: NO | ES39: NO | ET39: NO | EU39: NO | EV39: NO | EW39: NO | EX39: NO | EY39: NO | EZ39: NO | FA39: NO | FB39: NO | FC39: NO | FD39: NO | FE39: NO | FF39: NO | FG39: NO | FH39: NO | FI39: NO | FJ39: NO | FK39: NO | FL39: NO | FM39: NO | FN39: NO | FO39: NO | FP39: NO | FQ39: NO | FR39: NO | FS39: NO | FZ39: 0 | GG39: 0 | GN39: 0 | GU39: 0 | HB39: 0 | HI39: 0 | HP39: 0 | HX39: 0 | HY39: 0 | HZ39: 0 | IA39: 0 | IB39: 0 | IC39: 0 | ID39: 0 | IE39: 0 | IL39: 0 | IS39: 0 | IZ39: 0 | JG39: 0 | JN39: 0 | JO39: 0 | JP39: 0 | JQ39: 0 | JR39: 0 | JS39: 0 | JT39: 0 | JU39: 0 | KA39: 1 | KB39: 3 | KC39: 1 | KD39: START Asia Pacific: | OG39: START Europe: | SJ39: START North America: | WM39: START Global: | AAP39: START SOUTH America: | AES39: START Africa: | AIV39: =IFERROR(RIGHT(AH39,LEN(AH39)-SEARCH("@",AH39,1)),"") -> ascendas-singbridge.com
A40: A7TLM5G | B40: ANREV | C40: Tokyo Tatemono Investment Advisors Co., Ltd. | E40: kondokn@tt-ia.com | G40: https://secure.surveylab.co.uk/anrev-inrev-ncreif-capital-raising-2018/default.asp?survey=A7TLM5G | H40: asia | I40: 43150.374 | T40: FALSE | U40: TRUE | V40: FALSE | W40: FALSE | X40: FALSE | Y40: FALSE | Z40: 414 | AA40: 43150.369 | AB40: 221.186.68.97 | AC40: 2018 | AD40: Yasuhide Nakai | AE40: Tokyo Tatemono Investment Advisors Co., Ltd. | AF40: =VLOOKUP(MID(E40,SEARCH("@",E40,1),LEN(E40)-SEARCH("@",E40,1)+1),[2]Sheet1!$D:$F,3,FALSE) -> M0239 | AG40: Senior Manager | AH40: nakaiys@tt-ia.com | AI40: -6821 | AJ40: Japan | AK40: JPY | AM40: 1 | AP40: 5337 | AQ40: 4583 | AT40: 95 | AV40: 10015 | BC40: 0 | BJ40: 0 | BQ40: 0 | BX40: 0 | CE40: 0 | CF40: 5337 | CG40: 4583 | CH40: 0 | CI40: 0 | CJ40: 95 | CK40: 0 | CL40: 10015 | CM40: 1 | CN40: 1 | CQ40: 1 | CS40: 3 | CZ40: 0 | DG40: 0 | DN40: 0 | DU40: 0 | EB40: 0 | EC40: 1 | ED40: 1 | EE40: 0 | EF40: 0 | EG40: 1 | EH40: 0 | EI40: 3 | EJ40: YES | EK40: YES | EL40: NO | EM40: NO | EN40: YES | EO40: NO | EP40: NO | EQ40: NO | ER40: NO | ES40: NO | ET40: NO | EU40: NO | EV40: NO | EW40: NO | EX40: NO | EY40: NO | EZ40: NO | FA40: NO | FB40: NO | FC40: NO | FD40: NO | FE40: NO | FF40: NO | FG40: NO | FH40: NO | FI40: NO | FJ40: NO | FK40: NO | FL40: NO | FM40: NO | FN40: NO | FO40: NO | FP40: NO | FQ40: NO | FR40: NO | FS40: NO | FT40: 736 | FZ40: 736 | GA40: 641 | GG40: 641 | GN40: 0 | GU40: 0 | HB40: 0 | HI40: 0 | HP40: 0 | HQ40: Corporations/Banks | HR40: 3960 | HS40: 4583 | HV40: 95 | HX40: 8638 | HY40: 5337 | HZ40: 4583 | IA40: 0 | IB40: 0 | IC40: 95 | ID40: 0 | IE40: 10015 | IF40: 5337 | IG40: 4583 | IJ40: 95 | IL40: 10015 | IS40: 0 | IZ40: 0 | JG40: 0 | JN40: 0 | JO40: 5337 | JP40: 4583 | JQ40: 0 | JR40: 0 | JS40: 95 | JT40: 0 | JU40: 10015 | JV40: 99 | JX40: 1 | KA40: 3 | KB40: 3 | KC40: 1 | KD40: START Asia Pacific: | KE40: 736 | KK40: 736 | KL40: 641 | KR40: 641 | KY40: 0 | LF40: 0 | LM40: 0 | LT40: 0 | MA40: 0 | MB40: Corporations/Banks | MC40: 3960 | MD40: 4583 | MG40: 95 | MI40: 8638 | MJ40: 5337 | MK40: 4583 | ML40: 0 | MM40: 0 | MN40: 95 | MO40: 0 | MP40: 10015 | MW40: 0 | MX40: 5337 | MY40: 4583 | NB40: 95 | ND40: 10015 | NK40: 0 | NR40: 0 | NY40: 0 | NZ40: 5337 | OA40: 4583 | OB40: 0 | OC40: 0 | OD40: 95 | OE40: 0 | OF40: 10015 | OG40: START Europe: | SJ40: START North America: | WM40: START Global: | AAP40: START SOUTH America: | AES40: START Africa: | AIV40: =IFERROR(RIGHT(AH40,LEN(AH40)-SEARCH("@",AH40,1)),"") -> tt-ia.com
A41: A7TQC2M | B41: ANREV | C41: SilkRoad Property Partners | E41: viola.chee@silkroadpp.com | G41: https://secure.surveylab.co.uk/anrev-inrev-ncreif-capital-raising-2018/default.asp?survey=A7TQC2M | T41: FALSE | U41: FALSE | V41: FALSE | W41: FALSE | X41: FALSE | Y41: FALSE | Z41: 408 | AA41: 43151.385 | AB41: 203.125.141.130 | AC41: 2018 | AD41: Viola Chee | AE41: Silkroad Property Partners | AF41: =VLOOKUP(MID(E41,SEARCH("@",E41,1),LEN(E41)-SEARCH("@",E41,1)+1),[2]Sheet1!$D:$F,3,FALSE) -> M0182 | AG41: Financial Controller | AH41: viola.chee@silkroadpp.com | AI41: 69225560 | AJ41: Singapore | AK41: USD | AM41: 2 | AN41: 6 | AO41: Fund closed in 2016 | AV41: 0 | BC41: 0 | BJ41: 0 | BQ41: 0 | BX41: 0 | CE41: 0 | CF41: 0 | CG41: 0 | CH41: 0 | CI41: 0 | CJ41: 0 | CK41: 0 | CL41: 0 | CS41: 0 | CZ41: 0 | DG41: 0 | DN41: 0 | DU41: 0 | EB41: 0 | EC41: 0 | ED41: 0 | EE41: 0 | EF41: 0 | EG41: 0 | EH41: 0 | EI41: 0 | EJ41: NO | EK41: NO | EL41: NO | EM41: NO | EN41: NO | EO41: NO | EP41: NO | EQ41: NO | ER41: NO | ES41: NO | ET41: NO | EU41: NO | EV41: NO | EW41: NO | EX41: NO | EY41: NO | EZ41: NO | FA41: NO | FB41: NO | FC41: NO | FD41: NO | FE41: NO | FF41: NO | FG41: NO | FH41: NO | FI41: NO | FJ41: NO | FK41: NO | FL41: NO | FM41: NO | FN41: NO | FO41: NO | FP41: NO | FQ41: NO | FR41: NO | FS41: NO | FZ41: 0 | GG41: 0 | GN41: 0 | GU41: 0 | HB41: 0 | HI41: 0 | HP41: 0 | HX41: 0 | HY41: 0 | HZ41: 0 | IA41: 0 | IB41: 0 | IC41: 0 | ID41: 0 | IE41: 0 | IL41: 0 | IS41: 0 | IZ41: 0 | JG41: 0 | JN41: 0 | JO41: 0 | JP41: 0 | JQ41: 0 | JR41: 0 | JS41: 0 | JT41: 0 | JU41: 0 | KA41: 1 | KB41: 3 | KC41: 2 | KD41: START Asia Pacific: | OG41: START Europe: | SJ41: START North America: | WM41: START Global: | AAP41: START SOUTH America: | AES41: START Africa: | AIV41: =IFERROR(RIGHT(AH41,LEN(AH41)-SEARCH("@",AH41,1)),"") -> silkroadpp.com
A42: A7XUQ6J | B42: ANREV | C42: Mapletree Investments Pte Ltd | E42: christine.ong@mapletree.com.sg | G42: https://secure.surveylab.co.uk/anrev-inrev-ncreif-capital-raising-2018/default.asp?survey=A7XUQ6J | N42: global | O42: 43144.521 | T42: FALSE | U42: FALSE | V42: FALSE | W42: TRUE | X42: FALSE | Y42: FALSE | Z42: 387 | AA42: 43144.138 | AB42: 118.201.52.2 | AC42: 2018 | AD42: Snow Xiao | AE42: Mapletree Investments | AF42: =VLOOKUP(MID(E42,SEARCH("@",E42,1),LEN(E42)-SEARCH("@",E42,1)+1),[2]Sheet1!$D:$F,3,FALSE) -> M0180 | AG42: Executive, Private Fund Management | AH42: snow.xiao@mapletree.com.sg | AI42: 0065-63776896 | AJ42: Singapore | AK42: SGD | AM42: 1 | AV42: 0 | BC42: 0 | BJ42: 0 | BK42: 740 | BQ42: 740 | BX42: 0 | CE42: 0 | CF42: 740 | CG42: 0 | CH42: 0 | CI42: 0 | CJ42: 0 | CK42: 0 | CL42: 740 | CS42: 0 | CZ42: 0 | DG42: 0 | DH42: 1 | DN42: 1 | DU42: 0 | EB42: 0 | EC42: 1 | ED42: 0 | EE42: 0 | EF42: 0 | EG42: 0 | EH42: 0 | EI42: 1 | EJ42: NO | EK42: NO | EL42: NO | EM42: NO | EN42: NO | EO42: NO | EP42: NO | EQ42: NO | ER42: NO | ES42: NO | ET42: NO | EU42: NO | EV42: NO | EW42: NO | EX42: NO | EY42: NO | EZ42: NO | FA42: NO | FB42: YES | FC42: NO | FD42: NO | FE42: NO | FF42: NO | FG42: NO | FH42: NO | FI42: NO | FJ42: NO | FK42: NO | FL42: NO | FM42: NO | FN42: NO | FO42: NO | FP42: NO | FQ42: NO | FR42: NO | FS42: NO | FZ42: 0 | GA42: 110 | GG42: 110 | GN42: 0 | GU42: 0 | HB42: 0 | HI42: 0 | HJ42: 333 | HP42: 333 | HQ42: corporate/sponsor | HR42: 297 | HX42: 297 | HY42: 740 | HZ42: 0 | IA42: 0 | IB42: 0 | IC42: 0 | ID42: 0 | IE42: 740 | IF42: 580 | IL42: 580 | IM42: 160 | IS42: 160 | IZ42: 0 | JG42: 0 | JN42: 0 | JO42: 740 | JP42: 0 | JQ42: 0 | JR42: 0 | JS42: 0 | JT42: 0 | JU42: 740 | JX42: 100 | KA42: 1 | KB42: 2 | KC42: 2 | KD42: START Asia Pacific: | OG42: START Europe: | SJ42: START North America: | WM42: START Global: | WT42: 0 | WU42: 110 | XA42: 110 | XH42: 0 | XO42: 0 | XV42: 0 | YC42: 0 | YD42: 333 | YJ42: 333 | YK42: corporate/sponsor | YL42: 297 | YR42: 297 | YS42: 740 | YT42: 0 | YU42: 0 | YV42: 0 | YW42: 0 | YX42: 0 | YY42: 740 | YZ42: 160 | ZF42: 160 | ZG42: 580 | ZM42: 580 | ZT42: 0 | AAA42: 0 | AAH42: 0 | AAI42: 740 | AAJ42: 0 | AAK42: 0 | AAL42: 0 | AAM42: 0 | AAN42: 0 | AAO42: 740 | AAP42: START SOUTH America: | AES42: START Africa: | AIV42: =IFERROR(RIGHT(AH42,LEN(AH42)-SEARCH("@",AH42,1)),"") -> mapletree.com.sg
A43: A8EYV1H | B43: ANREV | C43: PAG | E43: nnakata@pagasia.com | G43: https://secure.surveylab.co.uk/anrev-inrev-ncreif-capital-raising-2018/default.asp?survey=A8EYV1H | H43: asia | I43: 43155.267 | T43: FALSE | U43: TRUE | V43: FALSE | W43: FALSE | X43: FALSE | Y43: FALSE | Z43: 473 | AA43: 43155.265 | AB43: 113.28.102.61 | AC43: 2018 | AD43: Vivian Deng | AE43: PAG | AF43: =VLOOKUP(MID(E43,SEARCH("@",E43,1),LEN(E43)-SEARCH("@",E43,1)+1),[2]Sheet1!$D:$F,3,FALSE) -> M0137 | AG43: Associate | AH43: vdeng@pag.com | AJ43: Hong Kong | AK43: USD | AM43: 1 | AP43: 1900 | AQ43: 550 | AV43: 2450 | BC43: 0 | BJ43: 0 | BQ43: 0 | BX43: 0 | CE43: 0 | CF43: 1900 | CG43: 550 | CH43: 0 | CI43: 0 | CJ43: 0 | CK43: 0 | CL43: 2450 | CM43: 1 | CN43: 1 | CS43: 2 | CZ43: 0 | DG43: 0 | DN43: 0 | DU43: 0 | EB43: 0 | EC43: 1 | ED43: 1 | EE43: 0 | EF43: 0 | EG43: 0 | EH43: 0 | EI43: 2 | EJ43: YES | EK43: YES | EL43: NO | EM43: NO | EN43: NO | EO43: NO | EP43: NO | EQ43: NO | ER43: NO | ES43: NO | ET43: NO | EU43: NO | EV43: NO | EW43: NO | EX43: NO | EY43: NO | EZ43: NO | FA43: NO | FB43: NO | FC43: NO | FD43: NO | FE43: NO | FF43: NO | FG43: NO | FH43: NO | FI43: NO | FJ43: NO | FK43: NO | FL43: NO | FM43: NO | FN43: NO | FO43: NO | FP43: NO | FQ43: NO | FR43: NO | FS43: NO | FT43: 905 | FZ43: 905 | GA43: 80 | GB43: 550 | GG43: 630 | GH43: 550 | GN43: 550 | GU43: 0 | GV43: 149 | HB43: 149 | HC43: 161 | HI43: 161 | HJ43: 30 | HP43: 30 | HQ43: GP Commit | HR43: 25 | HX43: 25 | HY43: 1900 | HZ43: 550 | IA43: 0 | IB43: 0 | IC43: 0 | ID43: 0 | IE43: 2450 | IF43: 590 | IL43: 590 | IM43: 330 | IN43: 550 | IS43: 880 | IT43: 980 | IZ43: 980 | JG43: 0 | JN43: 0 | JO43: 1900 | JP43: 550 | JQ43: 0 | JR43: 0 | JS43: 0 | JT43: 0 | JU43: 2450 | JV43: 78 | JX43: 22 | KA43: 1 | KB43: 3 | KC43: 2 | KD43: START Asia Pacific: | KE43: 905 | KK43: 905 | KL43: 80 | KM43: 550 | KR43: 630 | KS43: 550 | KY43: 550 | LF43: 0 | LG43: 149 | LM43: 149 | LN43: 161 | LT43: 161 | LU43: 30 | MA43: 30 | MB43: GP Commit | MC43: 25 | MI43: 25 | MJ43: 1900 | MK43: 550 | ML43: 0 | MM43: 0 | MN43: 0 | MO43: 0 | MP43: 2450 | MQ43: 330 | MR43: 550 | MW43: 880 | MX43: 590 | ND43: 590 | NE43: 980 | NK43: 980 | NR43: 0 | NY43: 0 | NZ43: 1900 | OA43: 550 | OB43: 0 | OC43: 0 | OD43: 0 | OE43: 0 | OF43: 2450 | OG43: START Europe: | SJ43: START North America: | WM43: START Global: | AAP43: START SOUTH America: | AES43: START Africa: | AIV43: =IFERROR(RIGHT(AH43,LEN(AH43)-SEARCH("@",AH43,1)),"") -> pag.com
A44: A8FUW3D | B44: ANREV | C44: Charter Hall Group | E44: richard.stacker@charterhall.com.au | G44: https://secure.surveylab.co.uk/anrev-inrev-ncreif-capital-raising-2018/default.asp?survey=A8FUW3D | H44: asia | I44: 43144.054 | T44: FALSE | U44: TRUE | V44: FALSE | W44: FALSE | X44: FALSE | Y44: FALSE | Z44: 303 | AA44: 43144.055 | AB44: 116.50.58.180 | AC44: 2018 | AD44: Kivanch Mehmet | AE44: Charter Hall | AF44: =VLOOKUP(MID(E44,SEARCH("@",E44,1),LEN(E44)-SEARCH("@",E44,1)+1),[2]Sheet1!$D:$F,3,FALSE) -> M03232 | AG44: Head of Wholesale Investor Relations | AH44: kivanch.mehmet@charterhall.com.au | AI44: +61 429 362 079 | AJ44: Australia | AK44: AUD | AM44: 1 | AP44: 1215 | AV44: 1215 | BC44: 0 | BJ44: 0 | BQ44: 0 | BX44: 0 | CE44: 0 | CF44: 1215 | CG44: 0 | CH44: 0 | CI44: 0 | CJ44: 0 | CK44: 0 | CL44: 1215 | CM44: 8 | CS44: 8 | CZ44: 0 | DG44: 0 | DN44: 0 | DU44: 0 | EB44: 0 | EC44: 8 | ED44: 0 | EE44: 0 | EF44: 0 | EG44: 0 | EH44: 0 | EI44: 8 | EJ44: YES | EK44: NO | EL44: NO | EM44: NO | EN44: NO | EO44: NO | EP44: NO | EQ44: NO | ER44: NO | ES44: NO | ET44: NO | EU44: NO | EV44: NO | EW44: NO | EX44: NO | EY44: NO | EZ44: NO | FA44: NO | FB44: NO | FC44: NO | FD44: NO | FE44: NO | FF44: NO | FG44: NO | FH44: NO | FI44: NO | FJ44: NO | FK44: NO | FL44: NO | FM44: NO | FN44: NO | FO44: NO | FP44: NO | FQ44: NO | FR44: NO | FS44: NO | FT44: 551 | FZ44: 551 | GA44: 15 | GG44: 15 | GH44: 198 | GN44: 198 | GO44: 65 | GU44: 65 | HB44: 0 | HC44: 76 | HI44: 76 | HJ44: 20 | HP44: 20 | HQ44: Wholesale Investors | HR44: 290 | HX44: 290 | HY44: 1215 | HZ44: 0 | IA44: 0 | IB44: 0 | IC44: 0 | ID44: 0 | IE44: 1215 | IF44: 1048 | IL44: 1048 | IM44: 114 | IS44: 114 | IT44: 53 | IZ44: 53 | JG44: 0 | JN44: 0 | JO44: 1215 | JP44: 0 | JQ44: 0 | JR44: 0 | JS44: 0 | JT44: 0 | JU44: 1215 | JX44: 100 | KA44: 1 | KB44: 1 | KC44: 1 | KD44: START Asia Pacific: | KE44: 551 | KK44: 551 | KL44: 15 | KR44: 15 | KS44: 198 | KY44: 198 | KZ44: 65 | LF44: 65 | LM44: 0 | LN44: 76 | LT44: 76 | LU44: 20 | MA44: 20 | MB44: Wholesale Investors | MC44: 290 | MI44: 290 | MJ44: 1215 | MK44: 0 | ML44: 0 | MM44: 0 | MN44: 0 | MO44: 0 | MP44: 1215 | MQ44: 114 | MW44: 114 | MX44: 1048 | ND44: 1048 | NE44: 53 | NK44: 53 | NR44: 0 | NY44: 0 | NZ44: 1215 | OA44: 0 | OB44: 0 | OC44: 0 | OD44: 0 | OE44: 0 | OF44: 1215 | OG44: START Europe: | SJ44: START North America: | WM44: START Global: | AAP44: START SOUTH America: | AES44: START Africa: | AIV44: =IFERROR(RIGHT(AH44,LEN(AH44)-SEARCH("@",AH44,1)),"") -> charterhall.com.au
A45: A8NLG7X | B45: ANREV | C45: City Square REI | E45: robert.lie@citysquarerei.com | G45: https://secure.surveylab.co.uk/anrev-inrev-ncreif-capital-raising-2018/default.asp?survey=A8NLG7X | T45: FALSE | U45: FALSE | V45: FALSE | W45: FALSE | X45: FALSE | Y45: FALSE | Z45: 423 | AA45: 43140.253 | AB45: 118.140.84.186 | AC45: 2018 | AD45: Robert Lie | AE45: City Square REI | AF45: =VLOOKUP(MID(E45,SEARCH("@",E45,1),LEN(E45)-SEARCH("@",E45,1)+1),[2]Sheet1!$D:$F,3,FALSE) -> M0279 | AG45: CEO | AH45: robert.lie@citysquarerei.com | AJ45: Hong Kong | AK45: USD | AM45: 2 | AN45: 6 | AO45: private capital sources | AV45: 0 | BC45: 0 | BJ45: 0 | BQ45: 0 | BX45: 0 | CE45: 0 | CF45: 0 | CG45: 0 | CH45: 0 | CI45: 0 | CJ45: 0 | CK45: 0 | CL45: 0 | CS45: 0 | CZ45: 0 | DG45: 0 | DN45: 0 | DU45: 0 | EB45: 0 | EC45: 0 | ED45: 0 | EE45: 0 | EF45: 0 | EG45: 0 | EH45: 0 | EI45: 0 | EJ45: NO | EK45: NO | EL45: NO | EM45: NO | EN45: NO | EO45: NO | EP45: NO | EQ45: NO | ER45: NO | ES45: NO | ET45: NO | EU45: NO | EV45: NO | EW45: NO | EX45: NO | EY45: NO | EZ45: NO | FA45: NO | FB45: NO | FC45: NO | FD45: NO | FE45: NO | FF45: NO | FG45: NO | FH45: NO | FI45: NO | FJ45: NO | FK45: NO | FL45: NO | FM45: NO | FN45: NO | FO45: NO | FP45: NO | FQ45: NO | FR45: NO | FS45: NO | FZ45: 0 | GG45: 0 | GN45: 0 | GU45: 0 | HB45: 0 | HI45: 0 | HP45: 0 | HX45: 0 | HY45: 0 | HZ45: 0 | IA45: 0 | IB45: 0 | IC45: 0 | ID45: 0 | IE45: 0 | IL45: 0 | IS45: 0 | IZ45: 0 | JG45: 0 | JN45: 0 | JO45: 0 | JP45: 0 | JQ45: 0 | JR45: 0 | JS45: 0 | JT45: 0 | JU45: 0 | KA45: 1 | KB45: 3 | KC45: 2 | KD45: START Asia Pacific: | OG45: START Europe: | SJ45: START North America: | WM45: START Global: | AAP45: START SOUTH America: | AES45: START Africa: | AIV45: =IFERROR(RIGHT(AH45,LEN(AH45)-SEARCH("@",AH45,1)),"") -> citysquarerei.com
A46: A8QGT6R | B46: ANREV | C46: Propertylink Group | E46: eshen@propertylink.com.au' | G46: https://secure.surveylab.co.uk/anrev-inrev-ncreif-capital-raising-2018/default.asp?survey=A8QGT6R | H46: asia | I46: 43131.218 | T46: FALSE | U46: TRUE | V46: FALSE | W46: FALSE | X46: FALSE | Y46: FALSE | Z46: 404 | AA46: 43131.051 | AB46: 103.252.58.14 | AC46: 2018 | AD46: Tim Simpson | AE46: Propertylink Group | AF46: =VLOOKUP(MID(E46,SEARCH("@",E46,1),LEN(E46)-SEARCH("@",E46,1)+1),[2]Sheet1!$D:$F,3,FALSE) -> M0220 | AG46: General Manager | AH46: tsimpson@propertylink.com.au | AI46: +61 2 9186 4715 | AJ46: Australia | AK46: AUD | AM46: 1 | AP46: 20 | AS46: 166 | AV46: 186 | BC46: 0 | BJ46: 0 | BQ46: 0 | BX46: 0 | CE46: 0 | CF46: 20 | CG46: 0 | CH46: 0 | CI46: 166 | CJ46: 0 | CK46: 0 | CL46: 186 | CM46: 1 | CP46: 2 | CS46: 3 | CZ46: 0 | DG46: 0 | DN46: 0 | DU46: 0 | EB46: 0 | EC46: 1 | ED46: 0 | EE46: 0 | EF46: 2 | EG46: 0 | EH46: 0 | EI46: 3 | EJ46: YES | EK46: NO | EL46: NO | EM46: YES | EN46: NO | EO46: NO | EP46: NO | EQ46: NO | ER46: NO | ES46: NO | ET46: NO | EU46: NO | EV46: NO | EW46: NO | EX46: NO | EY46: NO | EZ46: NO | FA46: NO | FB46: NO | FC46: NO | FD46: NO | FE46: NO | FF46: NO | FG46: NO | FH46: NO | FI46: NO | FJ46: NO | FK46: NO | FL46: NO | FM46: NO | FN46: NO | FO46: NO | FP46: NO | FQ46: NO | FR46: NO | FS46: NO | FZ46: 0 | GG46: 0 | GN46: 0 | GU46: 0 | HB46: 0 | HI46: 0 | HP46: 0 | HQ46: Institutional | HR46: 20 | HU46: 166 | HX46: 186 | HY46: 20 | HZ46: 0 | IA46: 0 | IB46: 166 | IC46: 0 | ID46: 0 | IE46: 186 | IF46: 20 | II46: 35 | IL46: 55 | IP46: 65 | IS46: 65 | IW46: 66 | IZ46: 66 | JG46: 0 | JN46: 0 | JO46: 20 | JP46: 0 | JQ46: 0 | JR46: 166 | JS46: 0 | JT46: 0 | JU46: 186 | JX46: 100 | KA46: 1 | KB46: 3 | KC46: 1 | KD46: START Asia Pacific: | KK46: 0 | KR46: 0 | KY46: 0 | LF46: 0 | LM46: 0 | LT46: 0 | MA46: 0 | MB46: Institutional | MC46: 20 | MF46: 166 | MI46: 186 | MJ46: 20 | MK46: 0 | ML46: 0 | MM46: 166 | MN46: 0 | MO46: 0 | MP46: 186 | MT46: 65 | MW46: 65 | MX46: 20 | NA46: 35 | ND46: 55 | NH46: 66 | NK46: 66 | NR46: 0 | NY46: 0 | NZ46: 20 | OA46: 0 | OB46: 0 | OC46: 166 | OD46: 0 | OE46: 0 | OF46: 186 | OG46: START Europe: | SJ46: START North America: | WM46: START Global: | AAP46: START SOUTH America: | AES46: START Africa: | AIV46: =IFERROR(RIGHT(AH46,LEN(AH46)-SEARCH("@",AH46,1)),"") -> propertylink.com.au
A47: A8RKR7J | B47: ANREV | C47: Diamond Real estate | E47: takashi.tsuji@mc-dream.com | G47: https://secure.surveylab.co.uk/anrev-inrev-ncreif-capital-raising-2018/default.asp?survey=A8RKR7J | H47: asia | I47: 43154.294 | L47: northamerica | M47: 43154.295 | T47: FALSE | U47: TRUE | V47: TRUE | W47: FALSE | X47: FALSE | Y47: FALSE | Z47: 394 | AA47: 43154.294 | AB47: 202.222.71.17 | AC47: 2018 | AD47: Hiromutsu Kano | AE47: Diamond Realty Management inc. | AF47: =VLOOKUP(MID(E47,SEARCH("@",E47,1),LEN(E47)-SEARCH("@",E47,1)+1),[2]Sheet1!$D:$F,3,FALSE) -> M0007 | AG47: Managing Director,Administration Division | AH47: hiromutsu.kano@mc-dream.com | AI47: 81-3-5212-4835 | AJ47: Japan | AK47: JPY | AM47: 1 | AP47: 23453 | AQ47: 13100 | AR47: 11170 | AS47: 1420 | AU47: 13451 | AV47: 62594 | BC47: 0 | BD47: 5566 | BI47: 4950 | BJ47: 10516 | BQ47: 0 | BX47: 0 | CE47: 0 | CF47: 29019 | CG47: 13100 | CH47: 11170 | CI47: 1420 | CJ47: 0 | CK47: 18401 | CL47: 73110 | CM47: 2 | CN47: 1 | CO47: 3 | CP47: 1 | CR47: 4 | CS47: 11 | CZ47: 0 | DA47: 1 | DF47: 1 | DG47: 2 | DN47: 0 | DU47: 0 | EB47: 0 | EC47: 3 | ED47: 1 | EE47: 3 | EF47: 1 | EG47: 0 | EH47: 5 | EI47: 13 | EJ47: YES | EK47: YES | EL47: YES | EM47: YES | EN47: NO | EO47: YES | EP47: NO | EQ47: NO | ER47: NO | ES47: NO | ET47: NO | EU47: NO | EV47: YES | EW47: NO | EX47: NO | EY47: NO | EZ47: NO | FA47: YES | FB47: NO | FC47: NO | FD47: NO | FE47: NO | FF47: NO | FG47: NO | FH47: NO | FI47: NO | FJ47: NO | FK47: NO | FL47: NO | FM47: NO | FN47: NO | FO47: NO | FP47: NO | FQ47: NO | FR47: NO | FS47: NO | FT47: 2680 | FV47: 5520 | FY47: 560 | FZ47: 8760 | GA47: 6443 | GF47: 124 | GG47: 6567 | GN47: 0 | GU47: 0 | HB47: 0 | HI47: 0 | HP47: 0 | HQ47: Finacial Institusion, | HR47: 19896 | HS47: 13100 | HT47: 5650 | HU47: 1420 | HW47: 17717 | HX47: 57783 | HY47: 29019 | HZ47: 13100 | IA47: 11170 | IB47: 1420 | IC47: 0 | ID47: 18401 | IE47: 73110 | IF47: 23453 | IG47: 13100 | IH47: 11170 | II47: 1420 | IK47: 13451 | IL47: 62594 | IS47: 0 | IT47: 5566 | IY47: 4950 | IZ47: 10516 | JG47: 0 | JN47: 0 | JO47: 29019 | JP47: 13100 | JQ47: 11170 | JR47: 1420 | JS47: 0 | JT47: 18401 | JU47: 73110 | JV47: 30.1 | JX47: 69.9 | KA47: 1 | KB47: 3 | KC47: 2 | KD47: START Asia Pacific: | KE47: 2680 | KG47: 5520 | KJ47: 560 | KK47: 8760 | KL47: 6443 | KQ47: 124 | KR47: 6567 | KY47: 0 | LF47: 0 | LM47: 0 | LT47: 0 | MA47: 0 | MC47: 14330 | MD47: 13100 | ME47: 5650 | MF47: 1420 | MH47: 12767 | MI47: 47267 | MJ47: 23453 | MK47: 13100 | ML47: 11170 | MM47: 1420 | MN47: 0 | MO47: 13451 | MP47: 62594 | MW47: 0 | MX47: 23453 | MY47: 13100 | MZ47: 11170 | NA47: 1420 | NC47: 13451 | ND47: 62594 | NK47: 0 | NR47: 0 | NY47: 0 | NZ47: 23453 | OA47: 13100 | OB47: 11170 | OC47: 1420 | OD47: 0 | OE47: 13451 | OF47: 62594 | OG47: START Europe: | SJ47: START North America: | SQ47: 0 | SX47: 0 | TE47: 0 | TL47: 0 | TS47: 0 | TZ47: 0 | UG47: 0 | UI47: 5566 | UN47: 4950 | UO47: 10516 | UP47: 5566 | UQ47: 0 | UR47: 0 | US47: 0 | UT47: 0 | UU47: 4950 | UV47: 10516 | VC47: 0 | VD47: 5566 | VI47: 4950 | VJ47: 10516 | VQ47: 0 | VX47: 0 | WE47: 0 | WF47: 5566 | WG47: 0 | WH47: 0 | WI47: 0 | WJ47: 0 | WK47: 4950 | WL47: 10516 | WM47: START Global: | AAP47: START SOUTH America: | AES47: START Africa: | AIV47: =IFERROR(RIGHT(AH47,LEN(AH47)-SEARCH("@",AH47,1)),"") -> mc-dream.com
A48: A9LVA3W | B48: ANREV | C48: Dynasty Investments | E48: olivier.dongoc@dynasty-investments.com | G48: https://secure.surveylab.co.uk/anrev-inrev-ncreif-capital-raising-2018/default.asp?survey=A9LVA3W | H48: asia | I48: 43136.497 | T48: FALSE | U48: TRUE | V48: FALSE | W48: FALSE | X48: FALSE | Y48: FALSE | Z48: 410 | AA48: 43136.382 | AB48: 90.41.150.240 | AC48: 2018 | AD48: Olivier Dung Do Ngoc | AE48: AHF GP Hong Kong | AF48: =VLOOKUP(MID(E48,SEARCH("@",E48,1),LEN(E48)-SEARCH("@",E48,1)+1),[2]Sheet1!$D:$F,3,FALSE) -> M0278 | AG48: Managing Partner | AH48: olivier.dongoc@ezland.vn | AI48: 84838275000 | AJ48: Luxembourg | AK48: USD | AM48: 1 | AS48: 15 | AV48: 15 | BC48: 0 | BJ48: 0 | BQ48: 0 | BX48: 0 | CE48: 0 | CF48: 0 | CG48: 0 | CH48: 0 | CI48: 15 | CJ48: 0 | CK48: 0 | CL48: 15 | CP48: 1 | CS48: 1 | CZ48: 0 | DG48: 0 | DN48: 0 | DU48: 0 | EB48: 0 | EC48: 0 | ED48: 0 | EE48: 0 | EF48: 1 | EG48: 0 | EH48: 0 | EI48: 1 | EJ48: NO | EK48: NO | EL48: NO | EM48: YES | EN48: NO | EO48: NO | EP48: NO | EQ48: NO | ER48: NO | ES48: NO | ET48: NO | EU48: NO | EV48: NO | EW48: NO | EX48: NO | EY48: NO | EZ48: NO | FA48: NO | FB48: NO | FC48: NO | FD48: NO | FE48: NO | FF48: NO | FG48: NO | FH48: NO | FI48: NO | FJ48: NO | FK48: NO | FL48: NO | FM48: NO | FN48: NO | FO48: NO | FP48: NO | FQ48: NO | FR48: NO | FS48: NO | FZ48: 0 | GG48: 0 | GN48: 0 | GU48: 0 | HB48: 0 | HF48: 15 | HI48: 15 | HP48: 0 | HX48: 0 | HY48: 0 | HZ48: 0 | IA48: 0 | IB48: 15 | IC48: 0 | ID48: 0 | IE48: 15 | II48: 15 | IL48: 15 | IS48: 0 | IZ48: 0 | JG48: 0 | JN48: 0 | JO48: 0 | JP48: 0 | JQ48: 0 | JR48: 15 | JS48: 0 | JT48: 0 | JU48: 15 | JX48: 100 | KA48: 1 | KB48: 3 | KC48: 1 | KD48: START Asia Pacific: | KK48: 0 | KR48: 0 | KY48: 0 | LF48: 0 | LM48: 0 | LQ48: 15 | LT48: 15 | MA48: 0 | MI48: 0 | MJ48: 0 | MK48: 0 | ML48: 0 | MM48: 15 | MN48: 0 | MO48: 0 | MP48: 15 | MW48: 0 | NA48: 15 | ND48: 15 | NK48: 0 | NR48: 0 | NY48: 0 | NZ48: 0 | OA48: 0 | OB48: 0 | OC48: 15 | OD48: 0 | OE48: 0 | OF48: 15 | OG48: START Europe: | SJ48: START North America: | WM48: START Global: | AAP48: START SOUTH America: | AES48: START Africa: | AIV48: =IFERROR(RIGHT(AH48,LEN(AH48)-SEARCH("@",AH48,1)),"") -> ezland.vn
A49: A9WTQ2A | B49: ANREV | C49: AMP Capital | E49: peta.carruthers@ampcapital.com | G49: https://secure.surveylab.co.uk/anrev-inrev-ncreif-capital-raising-2018/default.asp?survey=A9WTQ2A | H49: asia | I49: 43146.358 | T49: FALSE | U49: TRUE | V49: FALSE | W49: FALSE | X49: FALSE | Y49: FALSE | Z49: 383 | AA49: 43145.994 | AB49: 103.30.185.167 | AC49: 2018 | AD49: Greg Edelmuth | AE49: AMP Capital | AF49: =VLOOKUP(MID(E49,SEARCH("@",E49,1),LEN(E49)-SEARCH("@",E49,1)+1),[2]Sheet1!$D:$F,3,FALSE) -> M0082 | AG49: Manager, Real Estate Equity | AH49: greg.edelmuth@ampcapital.com | AI49: 92579032 | AJ49: Australia | AK49: AUD | AM49: 1 | AP49: 1894 | AQ49: 453 | AV49: 2347 | BC49: 0 | BJ49: 0 | BQ49: 0 | BX49: 0 | CE49: 0 | CF49: 1894 | CG49: 453 | CH49: 0 | CI49: 0 | CJ49: 0 | CK49: 0 | CL49: 2347 | CM49: 4 | CN49: 2 | CS49: 6 | CZ49: 0 | DG49: 0 | DN49: 0 | DU49: 0 | EB49: 0 | EC49: 4 | ED49: 2 | EE49: 0 | EF49: 0 | EG49: 0 | EH49: 0 | EI49: 6 | EJ49: YES | EK49: YES | EL49: NO | EM49: NO | EN49: NO | EO49: NO | EP49: NO | EQ49: NO | ER49: NO | ES49: NO | ET49: NO | EU49: NO | EV49: NO | EW49: NO | EX49: NO | EY49: NO | EZ49: NO | FA49: NO | FB49: NO | FC49: NO | FD49: NO | FE49: NO | FF49: NO | FG49: NO | FH49: NO | FI49: NO | FJ49: NO | FK49: NO | FL49: NO | FM49: NO | FN49: NO | FO49: NO | FP49: NO | FQ49: NO | FR49: NO | FS49: NO | FT49: 1893 | FU49: 142 | FZ49: 2035 | GB49: 312 | GG49: 312 | GN49: 0 | GU49: 0 | HB49: 0 | HI49: 0 | HP49: 0 | HX49: 0 | HY49: 1893 | HZ49: 454 | IA49: 0 | IB49: 0 | IC49: 0 | ID49: 0 | IE49: 2347 | IF49: 1893 | IG49: 142 | IL49: 2035 | IN49: 312 | IS49: 312 | IZ49: 0 | JG49: 0 | JN49: 0 | JO49: 1893 | JP49: 454 | JQ49: 0 | JR49: 0 | JS49: 0 | JT49: 0 | JU49: 2347 | JV49: 0 | JW49: 13 | JX49: 87 | KA49: 2 | KB49: 3 | KC49: 2 | KD49: START Asia Pacific: | KE49: 1893 | KF49: 142 | KK49: 2035 | KM49: 312 | KR49: 312 | KY49: 0 | LF49: 0 | LM49: 0 | LT49: 0 | MA49: 0 | MI49: 0 | MJ49: 1893 | MK49: 454 | ML49: 0 | MM49: 0 | MN49: 0 | MO49: 0 | MP49: 2347 | MR49: 312 | MW49: 312 | MX49: 1893 | MY49: 142 | ND49: 2035 | NK49: 0 | NR49: 0 | NY49: 0 | NZ49: 1893 | OA49: 454 | OB49: 0 | OC49: 0 | OD49: 0 | OE49: 0 | OF49: 2347 | OG49: START Europe: | SJ49: START North America: | WM49: START Global: | AAP49: START SOUTH America: | AES49: START Africa: | AIV49: =IFERROR(RIGHT(AH49,LEN(AH49)-SEARCH("@",AH49,1)),"") -> ampcapital.com
A50: A9ZYQ9Z | B50: ANREV | C50: CLSA | E50: angel.li@clsa.com | G50: https://secure.surveylab.co.uk/anrev-inrev-ncreif-capital-raising-2018/default.asp?survey=A9ZYQ9Z | H50: asia | I50: 43129.396 | T50: FALSE | U50: TRUE | V50: FALSE | W50: FALSE | X50: FALSE | Y50: FALSE | Z50: 302 | AA50: 43129.282 | AB50: 101.78.165.56 | AC50: 2018 | AD50: Danny Cheung | AE50: CLSA Real Estate | AF50: =VLOOKUP(MID(E50,SEARCH("@",E50,1),LEN(E50)-SEARCH("@",E50,1)+1),[2]Sheet1!$D:$F,3,FALSE) -> M0309 | AG50: Vice President | AH50: danny.cheung@clsa.com | AJ50: Hong Kong | AK50: USD | AM50: 1 | AQ50: 300 | AV50: 300 | BC50: 0 | BJ50: 0 | BQ50: 0 | BX50: 0 | CE50: 0 | CF50: 0 | CG50: 300 | CH50: 0 | CI50: 0 | CJ50: 0 | CK50: 0 | CL50: 300 | CN50: 1 | CS50: 1 | CZ50: 0 | DG50: 0 | DN50: 0 | DU50: 0 | EB50: 0 | EC50: 0 | ED50: 1 | EE50: 0 | EF50: 0 | EG50: 0 | EH50: 0 | EI50: 1 | EJ50: NO | EK50: YES | EL50: NO | EM50: NO | EN50: NO | EO50: NO | EP50: NO | EQ50: NO | ER50: NO | ES50: NO | ET50: NO | EU50: NO | EV50: NO | EW50: NO | EX50: NO | EY50: NO | EZ50: NO | FA50: NO | FB50: NO | FC50: NO | FD50: NO | FE50: NO | FF50: NO | FG50: NO | FH50: NO | FI50: NO | FJ50: NO | FK50: NO | FL50: NO | FM50: NO | FN50: NO | FO50: NO | FP50: NO | FQ50: NO | FR50: NO | FS50: NO | FZ50: 0 | GG50: 0 | GN50: 0 | GU50: 0 | HB50: 0 | HI50: 0 | HP50: 0 | HQ50: Corporate | HS50: 300 | HX50: 300 | HY50: 0 | HZ50: 300 | IA50: 0 | IB50: 0 | IC50: 0 | ID50: 0 | IE50: 300 | IG50: 300 | IL50: 300 | IS50: 0 | IZ50: 0 | JG50: 0 | JN50: 0 | JO50: 0 | JP50: 300 | JQ50: 0 | JR50: 0 | JS50: 0 | JT50: 0 | JU50: 300 | JW50: 100 | KA50: 1 | KB50: 1 | KC50: 2 | KD50: START Asia Pacific: | KK50: 0 | KR50: 0 | KY50: 0 | LF50: 0 | LM50: 0 | LT50: 0 | MA50: 0 | MB50: Corporate | MD50: 300 | MI50: 300 | MJ50: 0 | MK50: 300 | ML50: 0 | MM50: 0 | MN50: 0 | MO50: 0 | MP50: 300 | MW50: 0 | MY50: 300 | ND50: 300 | NK50: 0 | NR50: 0 | NY50: 0 | NZ50: 0 | OA50: 300 | OB50: 0 | OC50: 0 | OD50: 0 | OE50: 0 | OF50: 300 | OG50: START Europe: | SJ50: START North America: | WM50: START Global: | AAP50: START SOUTH America: | AES50: START Africa: | AIV50: =IFERROR(RIGHT(AH50,LEN(AH50)-SEARCH("@",AH50,1)),"") -> clsa.com
A51: C0FZJ6T | B51: NCREIF | C51: Barings Real Estate Advisers | D51: Alden Johnson | E51: alden.johnson@barings.com | G51: https://secure.surveylab.co.uk/anrev-inrev-ncreif-capital-raising-2018/default.asp?survey=C0FZJ6T | J51: europe | K51: 43152.712 | L51: northamerica | M51: 43152.715 | T51: TRUE | U51: FALSE | V51: TRUE | W51: FALSE | X51: FALSE | Y51: FALSE | Z51: 313 | AA51: 43152.708 | AB51: 63.66.112.5 | AC51: 2018 | AD51: Barbara Epler | AE51: Barings LLC | AF51: =VLOOKUP(MID(E51,SEARCH("@",E51,1),LEN(E51)-SEARCH("@",E51,1)+1),[2]Sheet1!$D:$F,3,FALSE) -> M215 | AG51: Associate Director | AH51: barbara.epler@barings.com | AI51: 806 509 2317 | AJ51: United States | AK51: USD | AM51: 1 | AV51: 0 | AW51: 607.1 | AX51: 196.8 | BC51: 803.9 | BD51: 81.8 | BE51: 671.1 | BI51: 443.5 | BJ51: 1196.4 | BQ51: 0 | BX51: 0 | CE51: 0 | CF51: 688.9 | CG51: 867.9 | CH51: 0 | CI51: 0 | CJ51: 0 | CK51: 443.5 | CL51: 2000.3 | CS51: 0 | CT51: 2 | CU51: 2 | CZ51: 4 | DA51: 1 | DB51: 1 | DF51: 2 | DG51: 4 | DN51: 0 | DU51: 0 | EB51: 0 | EC51: 3 | ED51: 3 | EE51: 0 | EF51: 0 | EG51: 0 | EH51: 2 | EI51: 8 | EJ51: NO | EK51: NO | EL51: NO | EM51: NO | EN51: NO | EO51: NO | EP51: YES | EQ51: YES | ER51: NO | ES51: NO | ET51: NO | EU51: NO | EV51: YES | EW51: YES | EX51: NO | EY51: NO | EZ51: NO | FA51: YES | FB51: NO | FC51: NO | FD51: NO | FE51: NO | FF51: NO | FG51: NO | FH51: NO | FI51: NO | FJ51: NO | FK51: NO | FL51: NO | FM51: NO | FN51: NO | FO51: NO | FP51: NO | FQ51: NO | FR51: NO | FS51: NO | FT51: 381.5 | FU51: 671.1 | FY51: 313 | FZ51: 1365.6 | GF51: 12 | GG51: 12 | GN51: 0 | GU51: 0 | GV51: 109.9 | HB51: 109.9 | HC51: 133.5 | HI51: 133.5 | HP51: 0 | HR51: 64 | HS51: 196.8 | HW51: 118.5 | HX51: 379.3 | HY51: 688.9 | HZ51: 867.9 | IA51: 0 | IB51: 0 | IC51: 0 | ID51: 443.5 | IE51: 2000.3 | IK51: 42 | IL51: 42 | IM51: 517.7 | IN51: 196.8 | IS51: 714.5 | IT51: 171.2 | IU51: 671.1 | IY51: 401.5 | IZ51: 1243.8 | JG51: 0 | JN51: 0 | JO51: 688.9 | JP51: 867.9 | JQ51: 0 | JR51: 0 | JS51: 0 | JT51: 443.5 | JU51: 2000.3 | JX51: 100 | KA51: 1 | KB51: 3 | KC51: 1 | KD51: START Asia Pacific: | OG51: START Europe: | OH51: 354.5 | ON51: 354.5 | OU51: 0 | PB51: 0 | PI51: 0 | PJ51: 98.7 | PP51: 98.7 | PQ51: 101.3 | PW51: 101.3 | QD51: 0 | QE51: other corporates & privates | QF51: 52.6 | QG51: 196.8 | QL51: 249.4 | QM51: 607.1 | QN51: 196.8 | QO51: 0 | QP51: 0 | QQ51: 0 | QR51: 0 | QS51: 803.9 | QT51: 517.7 | QU51: 196.8 | QZ51: 714.5 | RG51: 0 | RH51: 89.4 | RN51: 89.4 | RU51: 0 | SB51: 0 | SC51: 607.1 | SD51: 196.8 | SE51: 0 | SF51: 0 | SG51: 0 | SH51: 0 | SI51: 803.9 | SJ51: START North America: | SK51: 26.9 | SL51: 671.1 | SP51: 313 | SQ51: 1011 | SW51: 12 | SX51: 12 | TE51: 0 | TL51: 0 | TM51: 11.2 | TS51: 11.2 | TT51: 32.2 | TZ51: 32.2 | UG51: 0 | UH51: other corporates & privates | UI51: 11.5 | UN51: 118.5 | UO51: 130 | UP51: 81.8 | UQ51: 671.1 | UR51: 0 | US51: 0 | UT51: 0 | UU51: 443.5 | UV51: 1196.4 | VC51: 0 | VI51: 42 | VJ51: 42 | VK51: 81.8 | VL51: 671.1 | VP51: 401.5 | VQ51: 1154.4 | VX51: 0 | WE51: 0 | WF51: 81.8 | WG51: 671.1 | WH51: 0 | WI51: 0 | WJ51: 0 | WK51: 443.5 | WL51: 1196.4 | WM51: START Global: | AAP51: START SOUTH America: | AES51: START Africa: | AIV51: =IFERROR(RIGHT(AH51,LEN(AH51)-SEARCH("@",AH51,1)),"") -> barings.com
A52: C0TAF9A | B52: NCREIF | C52: Waterton Associates | D52: Philip Lukowski | E52: plukowski@wallc.com | G52: https://secure.surveylab.co.uk/anrev-inrev-ncreif-capital-raising-2018/default.asp?survey=C0TAF9A | L52: northamerica | M52: 43166.364 | T52: FALSE | U52: FALSE | V52: TRUE | W52: FALSE | X52: FALSE | Y52: FALSE | Z52: 319 | AA52: 43165.851 | AB52: 107.77.207.18 | AC52: 2018 | AD52: Laura Bakrins | AE52: Waterton | AF52: =VLOOKUP(MID(E52,SEARCH("@",E52,1),LEN(E52)-SEARCH("@",E52,1)+1),[2]Sheet1!$D:$F,3,FALSE) -> NC024 | AG52: Vice President | AH52: laura.bakrins@waterton.com | AI52: 312-948-4554 | AJ52: United States | AK52: USD | AM52: 1 | AV52: 0 | BC52: 0 | BD52: 647 | BE52: 50 | BI52: 33 | BJ52: 730 | BQ52: 0 | BX52: 0 | CE52: 0 | CF52: 647 | CG52: 50 | CH52: 0 | CI52: 0 | CJ52: 0 | CK52: 33 | CL52: 730 | CS52: 0 | CZ52: 0 | DA52: 1 | DB52: 1 | DF52: 1 | DG52: 3 | DN52: 0 | DU52: 0 | EB52: 0 | EC52: 1 | ED52: 1 | EE52: 0 | EF52: 0 | EG52: 0 | EH52: 1 | EI52: 3 | EJ52: NO | EK52: NO | EL52: NO | EM52: NO | EN52: NO | EO52: NO | EP52: NO | EQ52: NO | ER52: NO | ES52: NO | ET52: NO | EU52: NO | EV52: YES | EW52: YES | EX52: NO | EY52: NO | EZ52: NO | FA52: YES | FB52: NO | FC52: NO | FD52: NO | FE52: NO | FF52: NO | FG52: NO | FH52: NO | FI52: NO | FJ52: NO | FK52: NO | FL52: NO | FM52: NO | FN52: NO | FO52: NO | FP52: NO | FQ52: NO | FR52: NO | FS52: NO | FT52: 265 | FU52: 50 | FY52: 16.5 | FZ52: 331.5 | GA52: 174 | GG52: 174 | GH52: 175 | GM52: 16.5 | GN52: 191.5 | GU52: 0 | HB52: 0 | HI52: 0 | HJ52: 25 | HP52: 25 | HQ52: GP | HR52: 8 | HX52: 8 | HY52: 647 | HZ52: 50 | IA52: 0 | IB52: 0 | IC52: 0 | ID52: 33 | IE52: 730 | IF52: 175 | IK52: 16.5 | IL52: 191.5 | IS52: 0 | IT52: 408 | IU52: 50 | IY52: 16.5 | IZ52: 474.5 | JG52: 0 | JH52: 64 | JN52: 64 | JO52: 647 | JP52: 50 | JQ52: 0 | JR52: 0 | JS52: 0 | JT52: 33 | JU52: 730 | JV52: 2 | JW52: 2 | JX52: 96 | KA52: 2 | KB52: 2 | KC52: 1 | KD52: START Asia Pacific: | OG52: START Europe: | SJ52: START North America: | SK52: 265 | SL52: 50 | SP52: 16.5 | SQ52: 331.5 | SR52: 174 | SX52: 174 | SY52: 175 | TD52: 16.5 | TE52: 191.5 | TL52: 0 | TS52: 0 | TZ52: 0 | UA52: 25 | UG52: 25 | UH52: GP | UI52: 8 | UO52: 8 | UP52: 647 | UQ52: 50 | UR52: 0 | US52: 0 | UT52: 0 | UU52: 33 | UV52: 730 | VC52: 0 | VD52: 175 | VI52: 16.5 | VJ52: 191.5 | VK52: 408 | VL52: 50 | VP52: 16.5 | VQ52: 474.5 | VX52: 0 | VY52: 64 | WE52: 64 | WF52: 647 | WG52: 50 | WH52: 0 | WI52: 0 | WJ52: 0 | WK52: 33 | WL52: 730 | WM52: START Global: | AAP52: START SOUTH America: | AES52: START Africa: | AIV52: =IFERROR(RIGHT(AH52,LEN(AH52)-SEARCH("@",AH52,1)),"") -> waterton.com
A53: C0XGG3Z | B53: NCREIF | C53: Sarofim Realty Advisors | D53: Ann Melasky | E53: amelasky@sraco.com | G53: https://secure.surveylab.co.uk/anrev-inrev-ncreif-capital-raising-2018/default.asp?survey=C0XGG3Z | L53: northamerica | M53: 43154.86 | T53: FALSE | U53: FALSE | V53: TRUE | W53: FALSE | X53: FALSE | Y53: FALSE | Z53: 312 | AA53: 43154.86 | AB53: 216.74.249.19 | AC53: 2018 | AD53: Lisa Wallis | AE53: Sarofim Realty Advisors Co. | AF53: =VLOOKUP(MID(E53,SEARCH("@",E53,1),LEN(E53)-SEARCH("@",E53,1)+1),[2]Sheet1!$D:$F,3,FALSE) -> NC003 | AG53: Portfolio Controller | AH53: lwallis@sraco.com | AI53: 214-692-4266 | AJ53: United States | AK53: USD | AM53: 1 | AV53: 0 | BC53: 0 | BE53: 280 | BJ53: 280 | BQ53: 0 | BX53: 0 | CE53: 0 | CF53: 0 | CG53: 280 | CH53: 0 | CI53: 0 | CJ53: 0 | CK53: 0 | CL53: 280 | CS53: 0 | CZ53: 0 | DB53: 2 | DG53: 2 | DN53: 0 | DU53: 0 | EB53: 0 | EC53: 0 | ED53: 2 | EE53: 0 | EF53: 0 | EG53: 0 | EH53: 0 | EI53: 2 | EJ53: NO | EK53: NO | EL53: NO | EM53: NO | EN53: NO | EO53: NO | EP53: NO | EQ53: NO | ER53: NO | ES53: NO | ET53: NO | EU53: NO | EV53: NO | EW53: YES | EX53: NO | EY53: NO | EZ53: NO | FA53: NO | FB53: NO | FC53: NO | FD53: NO | FE53: NO | FF53: NO | FG53: NO | FH53: NO | FI53: NO | FJ53: NO | FK53: NO | FL53: NO | FM53: NO | FN53: NO | FO53: NO | FP53: NO | FQ53: NO | FR53: NO | FS53: NO | FZ53: 0 | GG53: 0 | GN53: 0 | GP53: 280 | GU53: 280 | HB53: 0 | HI53: 0 | HP53: 0 | HX53: 0 | HY53: 0 | HZ53: 280 | IA53: 0 | IB53: 0 | IC53: 0 | ID53: 0 | IE53: 280 | IL53: 0 | IS53: 0 | IU53: 280 | IZ53: 280 | JG53: 0 | JN53: 0 | JO53: 0 | JP53: 280 | JQ53: 0 | JR53: 0 | JS53: 0 | JT53: 0 | JU53: 280 | JV53: 54 | JX53: 46 | KA53: 1 | KB53: 3 | KC53: 1 | KD53: START Asia Pacific: | OG53: START Europe: | SJ53: START North America: | SQ53: 0 | SX53: 0 | TE53: 0 | TG53: 280 | TL53: 280 | TS53: 0 | TZ53: 0 | UG53: 0 | UO53: 0 | UP53: 0 | UQ53: 280 | UR53: 0 | US53: 0 | UT53: 0 | UU53: 0 | UV53: 280 | VC53: 0 | VJ53: 0 | VL53: 280 | VQ53: 280 | VX53: 0 | WE53: 0 | WF53: 0 | WG53: 280 | WH53: 0 | WI53: 0 | WJ53: 0 | WK53: 0 | WL53: 280 | WM53: START Global: | AAP53: START SOUTH America: | AES53: START Africa: | AIV53: =IFERROR(RIGHT(AH53,LEN(AH53)-SEARCH("@",AH53,1)),"") -> sraco.com
A54: C1KBH6T | B54: NCREIF | C54: Sentinel | D54: Paul D'Elisa | E54: DElisa@sentinelcorp.com | G54: https://secure.surveylab.co.uk/anrev-inrev-ncreif-capital-raising-2018/default.asp?survey=C1KBH6T | L54: northamerica | M54: 43147.903 | T54: FALSE | U54: FALSE | V54: TRUE | W54: FALSE | X54: FALSE | Y54: FALSE | Z54: 448 | AA54: 43147.902 | AB54: 173.251.20.37 | AC54: 2018 | AD54: Paul D`Elisa | AE54: Sentinel Real Estate Corporation | AF54: =VLOOKUP(MID(E54,SEARCH("@",E54,1),LEN(E54)-SEARCH("@",E54,1)+1),[2]Sheet1!$D:$F,3,FALSE) -> M473 | AG54: Senior Vice President | AH54: delisa@sentinelcorp.com | AI54: 212-408-2952 | AJ54: United States | AK54: USD | AM54: 1 | AV54: 0 | BC54: 0 | BD54: 79 | BE54: 1005 | BJ54: 1084 | BQ54: 0 | BX54: 0 | CE54: 0 | CF54: 79 | CG54: 1005 | CH54: 0 | CI54: 0 | CJ54: 0 | CK54: 0 | CL54: 1084 | CS54: 0 | CZ54: 0 | DA54: 1 | DB54: 3 | DG54: 4 | DN54: 0 | DU54: 0 | EB54: 0 | EC54: 1 | ED54: 3 | EE54: 0 | EF54: 0 | EG54: 0 | EH54: 0 | EI54: 4 | EJ54: NO | EK54: NO | EL54: NO | EM54: NO | EN54: NO | EO54: NO | EP54: NO | EQ54: NO | ER54: NO | ES54: NO | ET54: NO | EU54: NO | EV54: YES | EW54: YES | EX54: NO | EY54: NO | EZ54: NO | FA54: NO | FB54: NO | FC54: NO | FD54: NO | FE54: NO | FF54: NO | FG54: NO | FH54: NO | FI54: NO | FJ54: NO | FK54: NO | FL54: NO | FM54: NO | FN54: NO | FO54: NO | FP54: NO | FQ54: NO | FR54: NO | FS54: NO | FT54: 51 | FU54: 950 | FZ54: 1001 | GG54: 0 | GI54: 50 | GN54: 50 | GU54: 0 | HB54: 0 | HC54: 23 | HI54: 23 | HJ54: 5 | HK54: 5 | HP54: 10 | HX54: 0 | HY54: 79 | HZ54: 1005 | IA54: 0 | IB54: 0 | IC54: 0 | ID54: 0 | IE54: 1084 | IG54: 72 | IL54: 72 | IM54: 35 | IS54: 35 | IT54: 44 | IU54: 933 | IZ54: 977 | JG54: 0 | JN54: 0 | JO54: 79 | JP54: 1005 | JQ54: 0 | JR54: 0 | JS54: 0 | JT54: 0 | JU54: 1084 | JX54: 100 | KC54: 1 | KD54: START Asia Pacific: | OG54: START Europe: | SJ54: START North America: | SK54: 51 | SL54: 950 | SQ54: 1001 | SX54: 0 | SZ54: 50 | TE54: 50 | TL54: 0 | TS54: 0 | TT54: 23 | TZ54: 23 | UA54: 5 | UB54: 5 | UG54: 10 | UO54: 0 | UP54: 79 | UQ54: 1005 | UR54: 0 | US54: 0 | UT54: 0 | UU54: 0 | UV54: 1084 | UW54: 35 | VC54: 35 | VE54: 72 | VJ54: 72 | VK54: 44 | VL54: 933 | VQ54: 977 | VX54: 0 | WE54: 0 | WF54: 79 | WG54: 1005 | WH54: 0 | WI54: 0 | WJ54: 0 | WK54: 0 | WL54: 1084 | WM54: START Global: | AAP54: START SOUTH America: | AES54: START Africa: | AIV54: =IFERROR(RIGHT(AH54,LEN(AH54)-SEARCH("@",AH54,1)),"") -> sentinelcorp.com
A55: C1ZDT8K | B55: NCREIF | C55: Cottonwood Partners Management | D55: John West | E55: jfwest@cottonwoodpartners.com | G55: https://secure.surveylab.co.uk/anrev-inrev-ncreif-capital-raising-2018/default.asp?survey=C1ZDT8K | T55: FALSE | U55: FALSE | V55: FALSE | W55: FALSE | X55: FALSE | Y55: FALSE | Z55: 467 | AA55: 43152.808 | AB55: 67.135.181.210 | AC55: 2018 | AD55: John F. West | AE55: Cottonwood Partners | AF55: =VLOOKUP(MID(E55,SEARCH("@",E55,1),LEN(E55)-SEARCH("@",E55,1)+1),[2]Sheet1!$D:$F,3,FALSE) -> NC025 | AG55: CFO | AH55: jfwest@cottonwoodpartners.com | AI55: 801-365-6227 | AJ55: United States | AK55: USD | AM55: 2 | AN55: 5 | AV55: 0 | BC55: 0 | BJ55: 0 | BQ55: 0 | BX55: 0 | CE55: 0 | CF55: 0 | CG55: 0 | CH55: 0 | CI55: 0 | CJ55: 0 | CK55: 0 | CL55: 0 | CS55: 0 | CZ55: 0 | DG55: 0 | DN55: 0 | DU55: 0 | EB55: 0 | EC55: 0 | ED55: 0 | EE55: 0 | EF55: 0 | EG55: 0 | EH55: 0 | EI55: 0 | EJ55: NO | EK55: NO | EL55: NO | EM55: NO | EN55: NO | EO55: NO | EP55: NO | EQ55: NO | ER55: NO | ES55: NO | ET55: NO | EU55: NO | EV55: NO | EW55: NO | EX55: NO | EY55: NO | EZ55: NO | FA55: NO | FB55: NO | FC55: NO | FD55: NO | FE55: NO | FF55: NO | FG55: NO | FH55: NO | FI55: NO | FJ55: NO | FK55: NO | FL55: NO | FM55: NO | FN55: NO | FO55: NO | FP55: NO | FQ55: NO | FR55: NO | FS55: NO | FZ55: 0 | GG55: 0 | GN55: 0 | GU55: 0 | HB55: 0 | HI55: 0 | HP55: 0 | HX55: 0 | HY55: 0 | HZ55: 0 | IA55: 0 | IB55: 0 | IC55: 0 | ID55: 0 | IE55: 0 | IL55: 0 | IS55: 0 | IZ55: 0 | JG55: 0 | JN55: 0 | JO55: 0 | JP55: 0 | JQ55: 0 | JR55: 0 | JS55: 0 | JT55: 0 | JU55: 0 | KA55: 1 | KB55: 1 | KC55: 1 | KD55: START Asia Pacific: | OG55: START Europe: | SJ55: START North America: | WM55: START Global: | AAP55: START SOUTH America: | AES55: START Africa: | AIV55: =IFERROR(RIGHT(AH55,LEN(AH55)-SEARCH("@",AH55,1)),"") -> cottonwoodpartners.com
A56: C2EDQ7W | B56: NCREIF | C56: Northwestern Mutual Life Insurance | D56: Daniel Flesch | E56: dannyflesch@northwesternmutual.com | G56: https://secure.surveylab.co.uk/anrev-inrev-ncreif-capital-raising-2018/default.asp?survey=C2EDQ7W | T56: FALSE | U56: FALSE | V56: FALSE | W56: FALSE | X56: FALSE | Y56: FALSE | Z56: 471 | AA56: 43153.787 | AB56: 216.20.176.5 | AC56: 2018 | AD56: Northwestern Mutual Life Insurance Company | AE56: Northwestern Mutual | AF56: =VLOOKUP(MID(E56,SEARCH("@",E56,1),LEN(E56)-SEARCH("@",E56,1)+1),[2]Sheet1!$D:$F,3,FALSE) -> NC019 | AH56: dannyflesch@northwesternmutual.com | AJ56: United States | AK56: USD | AM56: 2 | AN56: 6 | AV56: 0 | BC56: 0 | BJ56: 0 | BQ56: 0 | BX56: 0 | CE56: 0 | CF56: 0 | CG56: 0 | CH56: 0 | CI56: 0 | CJ56: 0 | CK56: 0 | CL56: 0 | CS56: 0 | CZ56: 0 | DG56: 0 | DN56: 0 | DU56: 0 | EB56: 0 | EC56: 0 | ED56: 0 | EE56: 0 | EF56: 0 | EG56: 0 | EH56: 0 | EI56: 0 | EJ56: NO | EK56: NO | EL56: NO | EM56: NO | EN56: NO | EO56: NO | EP56: NO | EQ56: NO | ER56: NO | ES56: NO | ET56: NO | EU56: NO | EV56: NO | EW56: NO | EX56: NO | EY56: NO | EZ56: NO | FA56: NO | FB56: NO | FC56: NO | FD56: NO | FE56: NO | FF56: NO | FG56: NO | FH56: NO | FI56: NO | FJ56: NO | FK56: NO | FL56: NO | FM56: NO | FN56: NO | FO56: NO | FP56: NO | FQ56: NO | FR56: NO | FS56: NO | FZ56: 0 | GG56: 0 | GN56: 0 | GU56: 0 | HB56: 0 | HI56: 0 | HP56: 0 | HX56: 0 | HY56: 0 | HZ56: 0 | IA56: 0 | IB56: 0 | IC56: 0 | ID56: 0 | IE56: 0 | IL56: 0 | IS56: 0 | IZ56: 0 | JG56: 0 | JN56: 0 | JO56: 0 | JP56: 0 | JQ56: 0 | JR56: 0 | JS56: 0 | JT56: 0 | JU56: 0 | KC56: 2 | KD56: START Asia Pacific: | OG56: START Europe: | SJ56: START North America: | WM56: START Global: | AAP56: START SOUTH America: | AES56: START Africa: | AIV56: =IFERROR(RIGHT(AH56,LEN(AH56)-SEARCH("@",AH56,1)),"") -> northwesternmutual.com
A57: C4BHF3T | B57: NCREIF | C57: LaSalle Investment Management | Inc. | D57: Richard Kleinman | E57: Richard.Kleinman@lasalle.com | G57: https://secure.surveylab.co.uk/anrev-inrev-ncreif-capital-raising-2018/default.asp?survey=C4BHF3T | H57: asia | I57: 43144.456 | J57: europe | K57: 43144.458 | L57: northamerica | M57: 43144.474 | T57: TRUE | U57: TRUE | V57: TRUE | W57: FALSE | X57: FALSE | Y57: FALSE | Z57: 317 | AA57: 43145.548 | AB57: 108.171.131.166 | AC57: 2018 | AD57: Thomas Heather | AE57: LaSalle Investment Management | AF57: =VLOOKUP(MID(E57,SEARCH("@",E57,1),LEN(E57)-SEARCH("@",E57,1)+1),[2]Sheet1!$D:$F,3,FALSE) -> M020 | AG57: Associate, Client Capital Group | AH57: tom.heather@lasalle.com | AI57: +44 203 147 1318 | AJ57: United States | AK57: USD | AM57: 1 | AP57: 588 | AQ57: 360 | AS57: 259 | AV57: 1207 | AW57: 397 | AX57: 217 | BB57: 1276 | BC57: 1890 | BD57: 1187 | BE57: 491 | BJ57: 1678 | BQ57: 0 | BX57: 0 | CE57: 0 | CF57: 2172 | CG57: 1068 | CH57: 0 | CI57: 259 | CJ57: 0 | CK57: 1276 | CL57: 4775 | CM57: 1 | CN57: 1 | CP57: 4 | CS57: 6 | CT57: 2 | CU57: 3 | CY57: 2 | CZ57: 7 | DA57: 4 | DB57: 4 | DG57: 8 | DN57: 0 | DU57: 0 | EB57: 0 | EC57: 7 | ED57: 8 | EE57: 0 | EF57: 4 | EG57: 0 | EH57: 2 | EI57: 21 | EJ57: YES | EK57: YES | EL57: NO | EM57: YES | EN57: NO | EO57: NO | EP57: YES | EQ57: YES | ER57: NO | ES57: NO | ET57: NO | EU57: YES | EV57: YES | EW57: YES | EX57: NO | EY57: NO | EZ57: NO | FA57: NO | FB57: NO | FC57: NO | FD57: NO | FE57: NO | FF57: NO | FG57: NO | FH57: NO | FI57: NO | FJ57: NO | FK57: NO | FL57: NO | FM57: NO | FN57: NO | FO57: NO | FP57: NO | FQ57: NO | FR57: NO | FS57: NO | FT57: 993 | FU57: 1068 | FY57: 749 | FZ57: 2810 | GA57: 72 | GF57: 219 | GG57: 291 | GH57: 100 | GN57: 100 | GO57: 200 | GT57: 203 | GU57: 403 | HB57: 0 | HC57: 208 | HI57: 208 | HJ57: 94 | HM57: 95 | HP57: 189 | HR57: 505 | HU57: 164 | HW57: 105 | HX57: 774 | HY57: 2172 | HZ57: 1068 | IA57: 0 | IB57: 259 | IC57: 0 | ID57: 1276 | IE57: 4775 | IF57: 203 | IG57: 191 | II57: 259 | IK57: 145 | IL57: 798 | IM57: 856 | IN57: 577 | IR57: 1131 | IS57: 2564 | IT57: 1113 | IU57: 300 | IZ57: 1413 | JG57: 0 | JN57: 0 | JO57: 2172 | JP57: 1068 | JQ57: 0 | JR57: 259 | JS57: 0 | JT57: 1276 | JU57: 4775 | JV57: 0 | JW57: 0 | JX57: 100 | KA57: 3 | KB57: 3 | KC57: 1 | KD57: START Asia Pacific: | KE57: 185 | KF57: 360 | KK57: 545 | KR57: 0 | KS57: 100 | KY57: 100 | KZ57: 200 | LF57: 200 | LM57: 0 | LN57: 78 | LT57: 78 | LX57: 95 | MA57: 95 | MB57: Corporate | MC57: 25 | MF57: 164 | MI57: 189 | MJ57: 588 | MK57: 360 | ML57: 0 | MM57: 259 | MN57: 0 | MO57: 0 | MP57: 1207 | MQ57: 325 | MR57: 360 | MW57: 685 | MX57: 58 | NA57: 259 | ND57: 317 | NE57: 205 | NK57: 205 | NR57: 0 | NY57: 0 | NZ57: 588 | OA57: 360 | OB57: 0 | OC57: 259 | OD57: 0 | OE57: 0 | OF57: 1207 | OG57: START Europe: | OH57: 128 | OI57: 217 | OM57: 749 | ON57: 1094 | OO57: 67 | OT57: 219 | OU57: 286 | PB57: 0 | PH57: 203 | PI57: 203 | PP57: 0 | PQ57: 116 | PW57: 116 | QD57: 0 | QE57: Corporate | QF57: 86 | QK57: 105 | QL57: 191 | QM57: 397 | QN57: 217 | QO57: 0 | QP57: 0 | QQ57: 0 | QR57: 1276 | QS57: 1890 | QT57: 362 | QU57: 217 | QY57: 1131 | QZ57: 1710 | RA57: 25 | RF57: 145 | RG57: 170 | RH57: 10 | RN57: 10 | RU57: 0 | SB57: 0 | SC57: 397 | SD57: 217 | SE57: 0 | SF57: 0 | SG57: 0 | SH57: 1276 | SI57: 1890 | SJ57: START North America: | SK57: 680 | SL57: 491 | SQ57: 1171 | SR57: 5 | SX57: 5 | TE57: 0 | TL57: 0 | TS57: 0 | TT57: 14 | TZ57: 14 | UA57: 94 | UG57: 94 | UH57: Corporate | UI57: 394 | UO57: 394 | UP57: 1187 | UQ57: 491 | UR57: 0 | US57: 0 | UT57: 0 | UU57: 0 | UV57: 1678 | UW57: 169 | VC57: 169 | VD57: 120 | VE57: 191 | VJ57: 311 | VK57: 898 | VL57: 300 | VQ57: 1198 | VX57: 0 | WE57: 0 | WF57: 1187 | WG57: 491 | WH57: 0 | WI57: 0 | WJ57: 0 | WK57: 0 | WL57: 1678 | WM57: START Global: | AAP57: START SOUTH America: | AES57: START Africa: | AIV57: =IFERROR(RIGHT(AH57,LEN(AH57)-SEARCH("@",AH57,1)),"") -> lasalle.com
A58: C4RQE8A | B58: NCREIF | C58: TH Real Estate | D58: John Caruso | E58: jcaruso@tiaa-cref.org | G58: https://secure.surveylab.co.uk/anrev-inrev-ncreif-capital-raising-2018/default.asp?survey=C4RQE8A | H58: asia | I58: 43154.924 | J58: europe | K58: 43164.679 | L58: northamerica | M58: 43154.926 | T58: TRUE | U58: TRUE | V58: TRUE | W58: FALSE | X58: FALSE | Y58: FALSE | Z58: 324 | AA58: 43164.692 | AB58: 143.165.48.50 | AC58: 2018 | AD58: Laurence Price | AE58: Nuveen / TH Real Estate | AF58: =VLOOKUP(MID(E58,SEARCH("@",E58,1),LEN(E58)-SEARCH("@",E58,1)+1),[2]Sheet1!$D:$F,3,FALSE) -> M038 | AG58: Senior Analyst | AH58: laurence.price@nuveen.com | AI58: 212-916-6477 | AJ58: United States | AK58: USD | AM58: 1 | AP58: 549.6 | AU58: 700 | AV58: 1249.6 | AW58: 798.6691 | AX58: 299.50714 | BC58: 1098.18 | BD58: 453.94 | BG58: 347.0635 | BI58: 745.41 | BJ58: 1546.41 | BQ58: 0 | BX58: 0 | CE58: 0 | CF58: 1802.21 | CG58: 299.51 | CH58: 0 | CI58: 347.06 | CJ58: 0 | CK58: 1445.41 | CL58: 3894.19 | CM58: 1 | CR58: 2 | CS58: 3 | CT58: 6 | CU58: 1 | CZ58: 7 | DA58: 3 | DD58: 2 | DF58: 1 | DG58: 6 | DN58: 0 | DU58: 0 | EB58: 0 | EC58: 10 | ED58: 1 | EE58: 0 | EF58: 2 | EG58: 0 | EH58: 3 | EI58: 16 | EJ58: YES | EK58: NO | EL58: NO | EM58: NO | EN58: NO | EO58: YES | EP58: YES | EQ58: YES | ER58: NO | ES58: NO | ET58: NO | EU58: NO | EV58: YES | EW58: NO | EX58: NO | EY58: YES | EZ58: NO | FA58: YES | FB58: NO | FC58: NO | FD58: NO | FE58: NO | FF58: NO | FG58: NO | FH58: NO | FI58: NO | FJ58: NO | FK58: NO | FL58: NO | FM58: NO | FN58: NO | FO58: NO | FP58: NO | FQ58: NO | FR58: NO | FS58: NO | FT58: 574.92 | FW58: 216.17 | FY58: 550 | FZ58: 1341.09 | GA58: 818.99 | GB58: 299.51 | GD58: 46 | GF58: 745.41 | GG58: 1909.91 | GK58: 54.89 | GN58: 54.89 | GT58: 150 | GU58: 150 | GV58: 21.56 | GY58: 30 | HB58: 51.56 | HI58: 0 | HP58: 0 | HQ58: Private Company | HR58: 386.73 | HX58: 386.73 | HY58: 1802.2 | HZ58: 299.51 | IA58: 0 | IB58: 347.06 | IC58: 0 | ID58: 1445.41 | IE58: 3894.18 | IF58: 469.2 | IK58: 700 | IL58: 1169.2 | IM58: 806.39 | IN58: 299.51 | IP58: 84.89 | IS58: 1190.79 | IT58: 526.62 | IW58: 262.17 | IY58: 745.41 | IZ58: 1534.2 | JG58: 0 | JN58: 0 | JO58: 1802.21 | JP58: 299.51 | JQ58: 0 | JR58: 347.06 | JS58: 0 | JT58: 1445.41 | JU58: 3894.19 | JX58: 100 | KA58: 1 | KB58: 3 | KC58: 1 | KD58: START Asia Pacific: | KE58: 346.6 | KJ58: 550 | KK58: 896.6 | KL58: 50 | KR58: 50 | KY58: 0 | LE58: 150 | LF58: 150 | LM58: 0 | LT58: 0 | MA58: 0 | MB58: Private Company | MC58: 153 | MI58: 153 | MJ58: 549.6 | MK58: 0 | ML58: 0 | MM58: 0 | MN58: 0 | MO58: 700 | MP58: 1249.6 | MQ58: 469.2 | MV58: 700 | MW58: 1169.2 | MX58: 7.72 | ND58: 7.72 | NE58: 72.68 | NK58: 72.68 | NR58: 0 | NY58: 0 | NZ58: 549.6 | OA58: 0 | OB58: 0 | OC58: 0 | OD58: 0 | OE58: 700 | OF58: 1249.6 | OG58: START Europe: | OH58: 227.65 | ON58: 227.65 | OO58: 718.5 | OU58: 718.5 | PB58: 0 | PI58: 0 | PJ58: 21.56 | PM58: 30 | PP58: 51.56 | PW58: 0 | QD58: 0 | QE58: Private Company | QF58: 130.47 | QL58: 130.47 | QM58: 1098.18 | QN58: 0 | QO58: 0 | QP58: 30 | QQ58: 0 | QR58: 0 | QS58: 1128.18 | QT58: 1098.18 | QW58: 30 | QZ58: 1128.18 | RG58: 0 | RN58: 0 | RU58: 0 | SB58: 0 | SC58: 1098.18 | SD58: 0 | SE58: 0 | SF58: 30 | SG58: 0 | SH58: 0 | SI58: 1128.18 | SJ58: START North America: | SK58: 0.68 | SN58: 216.17 | SQ58: 216.85 | SR58: 350 | SU58: 46 | SW58: 745.41 | SX58: 1141.41 | TB58: 54.89 | TE58: 54.89 | TL58: 0 | TS58: 0 | TZ58: 0 | UG58: 0 | UH58: Private Company | UI58: 103.26 | UO58: 103.26 | UP58: 453.94 | UQ58: 0 | UR58: 0 | US58: 317.06 | UT58: 0 | UU58: 745.41 | UV58: 1516.41 | UZ58: 54.89 | VC58: 54.89 | VJ58: 0 | VK58: 453.94 | VN58: 262.17 | VP58: 745.41 | VQ58: 1461.52 | VX58: 0 | WE58: 0 | WF58: 453.94 | WG58: 0 | WH58: 0 | WI58: 317.06 | WJ58: 0 | WK58: 745.41 | WL58: 1516.41 | WM58: START Global: | AAP58: START SOUTH America: | AES58: START Africa: | AIV58: =IFERROR(RIGHT(AH58,LEN(AH58)-SEARCH("@",AH58,1)),"") -> nuveen.com
A59: C4YZK3E | B59: NCREIF | C59: Blue Vista | D59: James Strezewski | E59: jstrezewski@bluevistallc.com | G59: https://secure.surveylab.co.uk/anrev-inrev-ncreif-capital-raising-2018/default.asp?survey=C4YZK3E | L59: northamerica | M59: 43138.943 | T59: FALSE | U59: FALSE | V59: TRUE | W59: FALSE | X59: FALSE | Y59: FALSE | Z59: 345 | AA59: 43138.943 | AB59: 38.88.203.14 | AC59: 2018 | AD59: Rachel Woolf | AE59: Blue Vista Capital Management | AF59: =VLOOKUP(MID(E59,SEARCH("@",E59,1),LEN(E59)-SEARCH("@",E59,1)+1),[2]Sheet1!$D:$F,3,FALSE) -> NC013 | AG59: Investor Relations | AH59: rwoolf@bluevistallc.com | AI59: 3124772497 | AJ59: United States | AK59: USD | AM59: 1 | AV59: 0 | BC59: 0 | BG59: 82 | BI59: 70 | BJ59: 152 | BQ59: 0 | BX59: 0 | CE59: 0 | CF59: 0 | CG59: 0 | CH59: 0 | CI59: 82 | CJ59: 0 | CK59: 70 | CL59: 152 | CS59: 0 | CZ59: 0 | DD59: 1 | DF59: 2 | DG59: 3 | DN59: 0 | DU59: 0 | EB59: 0 | EC59: 0 | ED59: 0 | EE59: 0 | EF59: 1 | EG59: 0 | EH59: 2 | EI59: 3 | EJ59: NO | EK59: NO | EL59: NO | EM59: NO | EN59: NO | EO59: NO | EP59: NO | EQ59: NO | ER59: NO | ES59: NO | ET59: NO | EU59: NO | EV59: NO | EW59: NO | EX59: NO | EY59: YES | EZ59: NO | FA59: YES | FB59: NO | FC59: NO | FD59: NO | FE59: NO | FF59: NO | FG59: NO | FH59: NO | FI59: NO | FJ59: NO | FK59: NO | FL59: NO | FM59: NO | FN59: NO | FO59: NO | FP59: NO | FQ59: NO | FR59: NO | FS59: NO | FZ59: 0 | GD59: 82 | GF59: 70 | GG59: 152 | GN59: 0 | GU59: 0 | HB59: 0 | HI59: 0 | HP59: 0 | HX59: 0 | HY59: 0 | HZ59: 0 | IA59: 0 | IB59: 82 | IC59: 0 | ID59: 70 | IE59: 152 | IL59: 0 | IS59: 0 | IW59: 82 | IY59: 70 | IZ59: 152 | JG59: 0 | JN59: 0 | JO59: 0 | JP59: 0 | JQ59: 0 | JR59: 82 | JS59: 0 | JT59: 70 | JU59: 152 | JX59: 100 | KA59: 1 | KB59: 3 | KC59: 1 | KD59: START Asia Pacific: | OG59: START Europe: | SJ59: START North America: | SQ59: 0 | SU59: 82 | SW59: 70 | SX59: 152 | TE59: 0 | TL59: 0 | TS59: 0 | TZ59: 0 | UG59: 0 | UO59: 0 | UP59: 0 | UQ59: 0 | UR59: 0 | US59: 82 | UT59: 0 | UU59: 70 | UV59: 152 | VC59: 0 | VJ59: 0 | VN59: 82 | VP59: 70 | VQ59: 152 | VX59: 0 | WE59: 0 | WF59: 0 | WG59: 0 | WH59: 0 | WI59: 82 | WJ59: 0 | WK59: 70 | WL59: 152 | WM59: START Global: | AAP59: START SOUTH America: | AES59: START Africa: | AIV59: =IFERROR(RIGHT(AH59,LEN(AH59)-SEARCH("@",AH59,1)),"") -> bluevistallc.com
A60: C5EMC3B | B60: NCREIF | C60: Lincoln Advisors | D60: Gary Kobus | E60: gkobus@lpc.com | G60: https://secure.surveylab.co.uk/anrev-inrev-ncreif-capital-raising-2018/default.asp?survey=C5EMC3B | T60: FALSE | U60: FALSE | V60: FALSE | W60: FALSE | X60: FALSE | Y60: FALSE | Z60: 332 | AA60: 43115.83 | AB60: 196.17.100.253 | AC60: 2018 | AD60: Gary Kobus | AE60: Lincoln Advisors | AF60: =VLOOKUP(MID(E60,SEARCH("@",E60,1),LEN(E60)-SEARCH("@",E60,1)+1),[2]Sheet1!$D:$F,3,FALSE) -> NC026 | AG60: Executive Vice President | AH60: gkobus@lpc.com | AI60: 3123458776 | AJ60: United States | AK60: USD | AM60: 2 | AN60: 6 | AV60: 0 | BC60: 0 | BJ60: 0 | BQ60: 0 | BX60: 0 | CE60: 0 | CF60: 0 | CG60: 0 | CH60: 0 | CI60: 0 | CJ60: 0 | CK60: 0 | CL60: 0 | CS60: 0 | CZ60: 0 | DG60: 0 | DN60: 0 | DU60: 0 | EB60: 0 | EC60: 0 | ED60: 0 | EE60: 0 | EF60: 0 | EG60: 0 | EH60: 0 | EI60: 0 | EJ60: NO | EK60: NO | EL60: NO | EM60: NO | EN60: NO | EO60: NO | EP60: NO | EQ60: NO | ER60: NO | ES60: NO | ET60: NO | EU60: NO | EV60: NO | EW60: NO | EX60: NO | EY60: NO | EZ60: NO | FA60: NO | FB60: NO | FC60: NO | FD60: NO | FE60: NO | FF60: NO | FG60: NO | FH60: NO | FI60: NO | FJ60: NO | FK60: NO | FL60: NO | FM60: NO | FN60: NO | FO60: NO | FP60: NO | FQ60: NO | FR60: NO | FS60: NO | FZ60: 0 | GG60: 0 | GN60: 0 | GU60: 0 | HB60: 0 | HI60: 0 | HP60: 0 | HX60: 0 | HY60: 0 | HZ60: 0 | IA60: 0 | IB60: 0 | IC60: 0 | ID60: 0 | IE60: 0 | IL60: 0 | IS60: 0 | IZ60: 0 | JG60: 0 | JN60: 0 | JO60: 0 | JP60: 0 | JQ60: 0 | JR60: 0 | JS60: 0 | JT60: 0 | JU60: 0 | KA60: 1 | KB60: 3 | KC60: 1 | KD60: START Asia Pacific: | OG60: START Europe: | SJ60: START North America: | WM60: START Global: | AAP60: START SOUTH America: | AES60: START Africa: | AIV60: =IFERROR(RIGHT(AH60,LEN(AH60)-SEARCH("@",AH60,1)),"") -> lpc.com
A61: C5MFP8Q | B61: NCREIF | C61: PNC | D61: Cynthia Helms | E61: cynthia.helms@pnc.com | G61: https://secure.surveylab.co.uk/anrev-inrev-ncreif-capital-raising-2018/default.asp?survey=C5MFP8Q | L61: northamerica | M61: 43138.548 | T61: FALSE | U61: FALSE | V61: TRUE | W61: FALSE | X61: FALSE | Y61: FALSE | Z61: 416 | AA61: 43138.547 | AB61: 161.150.176.4 | AC61: 2018 | AD61: David Schenning | AE61: PNC | AF61: =VLOOKUP(MID(E61,SEARCH("@",E61,1),LEN(E61)-SEARCH("@",E61,1)+1),[2]Sheet1!$D:$F,3,FALSE) -> NC020 | AG61: SVP | AH61: david.schenning@pnc.com | AI61: 410-237-4512 | AJ61: United States | AK61: USD | AM61: 1 | AV61: 0 | BC61: 0 | BD61: 199 | BJ61: 199 | BQ61: 0 | BX61: 0 | CE61: 0 | CF61: 199 | CG61: 0 | CH61: 0 | CI61: 0 | CJ61: 0 | CK61: 0 | CL61: 199 | CS61: 0 | CZ61: 0 | DA61: 1 | DG61: 1 | DN61: 0 | DU61: 0 | EB61: 0 | EC61: 1 | ED61: 0 | EE61: 0 | EF61: 0 | EG61: 0 | EH61: 0 | EI61: 1 | EJ61: NO | EK61: NO | EL61: NO | EM61: NO | EN61: NO | EO61: NO | EP61: NO | EQ61: NO | ER61: NO | ES61: NO | ET61: NO | EU61: NO | EV61: YES | EW61: NO | EX61: NO | EY61: NO | EZ61: NO | FA61: NO | FB61: NO | FC61: NO | FD61: NO | FE61: NO | FF61: NO | FG61: NO | FH61: NO | FI61: NO | FJ61: NO | FK61: NO | FL61: NO | FM61: NO | FN61: NO | FO61: NO | FP61: NO | FQ61: NO | FR61: NO | FS61: NO | FT61: 199 | FZ61: 199 | GG61: 0 | GN61: 0 | GU61: 0 | HB61: 0 | HI61: 0 | HP61: 0 | HX61: 0 | HY61: 199 | HZ61: 0 | IA61: 0 | IB61: 0 | IC61: 0 | ID61: 0 | IE61: 199 | IL61: 0 | IS61: 0 | IT61: 199 | IZ61: 199 | JG61: 0 | JN61: 0 | JO61: 199 | JP61: 0 | JQ61: 0 | JR61: 0 | JS61: 0 | JT61: 0 | JU61: 199 | JV61: 100 | KA61: 2 | KB61: 3 | KC61: 1 | KD61: START Asia Pacific: | OG61: START Europe: | SJ61: START North America: | SK61: 199 | SQ61: 199 | SX61: 0 | TE61: 0 | TL61: 0 | TS61: 0 | TZ61: 0 | UG61: 0 | UO61: 0 | UP61: 199 | UQ61: 0 | UR61: 0 | US61: 0 | UT61: 0 | UU61: 0 | UV61: 199 | VC61: 0 | VJ61: 0 | VK61: 199 | VQ61: 199 | VX61: 0 | WE61: 0 | WF61: 199 | WG61: 0 | WH61: 0 | WI61: 0 | WJ61: 0 | WK61: 0 | WL61: 199 | WM61: START Global: | AAP61: START SOUTH America: | AES61: START Africa: | AIV61: =IFERROR(RIGHT(AH61,LEN(AH61)-SEARCH("@",AH61,1)),"") -> pnc.com
A62: C5MPT5L | B62: NCREIF | C62: The General Investment & Development Companies | D62: Joanna Stimpson | E62: jstimpson@gid.com | G62: https://secure.surveylab.co.uk/anrev-inrev-ncreif-capital-raising-2018/default.asp?survey=C5MPT5L | T62: FALSE | U62: FALSE | V62: FALSE | W62: FALSE | X62: FALSE | Y62: FALSE | Z62: 464 | AA62: 43162.897 | AB62: 38.97.101.249 | AC62: 2018 | AD62: Mark Conopka | AE62: GID Investment Advisors | AF62: =VLOOKUP(MID(E62,SEARCH("@",E62,1),LEN(E62)-SEARCH("@",E62,1)+1),[2]Sheet1!$D:$F,3,FALSE) -> NC027 | AG62: VP, Portfolio Management | AH62: mconopka@gid.com | AJ62: United States | AK62: USD | AM62: 2 | AN62: 1 | AV62: 0 | BC62: 0 | BJ62: 0 | BQ62: 0 | BX62: 0 | CE62: 0 | CF62: 0 | CG62: 0 | CH62: 0 | CI62: 0 | CJ62: 0 | CK62: 0 | CL62: 0 | CS62: 0 | CZ62: 0 | DG62: 0 | DN62: 0 | DU62: 0 | EB62: 0 | EC62: 0 | ED62: 0 | EE62: 0 | EF62: 0 | EG62: 0 | EH62: 0 | EI62: 0 | EJ62: NO | EK62: NO | EL62: NO | EM62: NO | EN62: NO | EO62: NO | EP62: NO | EQ62: NO | ER62: NO | ES62: NO | ET62: NO | EU62: NO | EV62: NO | EW62: NO | EX62: NO | EY62: NO | EZ62: NO | FA62: NO | FB62: NO | FC62: NO | FD62: NO | FE62: NO | FF62: NO | FG62: NO | FH62: NO | FI62: NO | FJ62: NO | FK62: NO | FL62: NO | FM62: NO | FN62: NO | FO62: NO | FP62: NO | FQ62: NO | FR62: NO | FS62: NO | FZ62: 0 | GG62: 0 | GN62: 0 | GU62: 0 | HB62: 0 | HI62: 0 | HP62: 0 | HX62: 0 | HY62: 0 | HZ62: 0 | IA62: 0 | IB62: 0 | IC62: 0 | ID62: 0 | IE62: 0 | IL62: 0 | IS62: 0 | IZ62: 0 | JG62: 0 | JN62: 0 | JO62: 0 | JP62: 0 | JQ62: 0 | JR62: 0 | JS62: 0 | JT62: 0 | JU62: 0 | KA62: 1 | KB62: 3 | KC62: 1 | KD62: START Asia Pacific: | OG62: START Europe: | SJ62: START North America: | WM62: START Global: | AAP62: START SOUTH America: | AES62: START Africa: | AIV62: =IFERROR(RIGHT(AH62,LEN(AH62)-SEARCH("@",AH62,1)),"") -> gid.com
A63: C5RKX5H | B63: NCREIF | C63: Hart Realty Advisers | Inc. | D63: Daryl Krivanec | E63: drk@hartadvisers.com | G63: https://secure.surveylab.co.uk/anrev-inrev-ncreif-capital-raising-2018/default.asp?survey=C5RKX5H | T63: FALSE | U63: FALSE | V63: FALSE | W63: FALSE | X63: FALSE | Y63: FALSE | Z63: 343 | AA63: 43116.699 | AB63: 50.201.70.118 | AC63: 2018 | AD63: David Huntley | AE63: Hart Realty Advisers, LLC | AF63: =VLOOKUP(MID(E63,SEARCH("@",E63,1),LEN(E63)-SEARCH("@",E63,1)+1),[2]Sheet1!$D:$F,3,FALSE) -> NC006 | AG63: CFO | AH63: dbh@hartadvisers.com | AI63: 860-651-2017 | AJ63: United States | AK63: USD | AM63: 2 | AN63: 6 | AO63: too small | AV63: 0 | BC63: 0 | BJ63: 0 | BQ63: 0 | BX63: 0 | CE63: 0 | CF63: 0 | CG63: 0 | CH63: 0 | CI63: 0 | CJ63: 0 | CK63: 0 | CL63: 0 | CS63: 0 | CZ63: 0 | DG63: 0 | DN63: 0 | DU63: 0 | EB63: 0 | EC63: 0 | ED63: 0 | EE63: 0 | EF63: 0 | EG63: 0 | EH63: 0 | EI63: 0 | EJ63: NO | EK63: NO | EL63: NO | EM63: NO | EN63: NO | EO63: NO | EP63: NO | EQ63: NO | ER63: NO | ES63: NO | ET63: NO | EU63: NO | EV63: NO | EW63: NO | EX63: NO | EY63: NO | EZ63: NO | FA63: NO | FB63: NO | FC63: NO | FD63: NO | FE63: NO | FF63: NO | FG63: NO | FH63: NO | FI63: NO | FJ63: NO | FK63: NO | FL63: NO | FM63: NO | FN63: NO | FO63: NO | FP63: NO | FQ63: NO | FR63: NO | FS63: NO | FZ63: 0 | GG63: 0 | GN63: 0 | GU63: 0 | HB63: 0 | HI63: 0 | HP63: 0 | HX63: 0 | HY63: 0 | HZ63: 0 | IA63: 0 | IB63: 0 | IC63: 0 | ID63: 0 | IE63: 0 | IL63: 0 | IS63: 0 | IZ63: 0 | JG63: 0 | JN63: 0 | JO63: 0 | JP63: 0 | JQ63: 0 | JR63: 0 | JS63: 0 | JT63: 0 | JU63: 0 | KA63: 1 | KB63: 2 | KC63: 1 | KD63: START Asia Pacific: | OG63: START Europe: | SJ63: START North America: | WM63: START Global: | AAP63: START SOUTH America: | AES63: START Africa: | AIV63: =IFERROR(RIGHT(AH63,LEN(AH63)-SEARCH("@",AH63,1)),"") -> hartadvisers.com
A64: C6LFQ7Y | B64: NCREIF | C64: Equus | D64: Joe Nahas | E64: jnahas@equuspartners.com | G64: https://secure.surveylab.co.uk/anrev-inrev-ncreif-capital-raising-2018/default.asp?survey=C6LFQ7Y | T64: FALSE | U64: FALSE | V64: FALSE | W64: FALSE | X64: FALSE | Y64: FALSE | Z64: 311 | AA64: 43143.921 | AB64: 38.98.251.2 | AC64: 2018 | AD64: Joseph G. Nahas, Jr. CRE | AE64: Equus Capital Partners, Ltd. | AF64: =VLOOKUP(MID(E64,SEARCH("@",E64,1),LEN(E64)-SEARCH("@",E64,1)+1),[2]Sheet1!$D:$F,3,FALSE) -> NC017 | AG64: Sr. Vice President | AH64: jnahas@equuspartners.com | AI64: 215-575-2363 | AJ64: United States | AK64: USD | AM64: 2 | AN64: 6 | AO64: Finish investing current vehicle | AV64: 0 | BC64: 0 | BJ64: 0 | BQ64: 0 | BX64: 0 | CE64: 0 | CF64: 0 | CG64: 0 | CH64: 0 | CI64: 0 | CJ64: 0 | CK64: 0 | CL64: 0 | CS64: 0 | CZ64: 0 | DG64: 0 | DN64: 0 | DU64: 0 | EB64: 0 | EC64: 0 | ED64: 0 | EE64: 0 | EF64: 0 | EG64: 0 | EH64: 0 | EI64: 0 | EJ64: NO | EK64: NO | EL64: NO | EM64: NO | EN64: NO | EO64: NO | EP64: NO | EQ64: NO | ER64: NO | ES64: NO | ET64: NO | EU64: NO | EV64: NO | EW64: NO | EX64: NO | EY64: NO | EZ64: NO | FA64: NO | FB64: NO | FC64: NO | FD64: NO | FE64: NO | FF64: NO | FG64: NO | FH64: NO | FI64: NO | FJ64: NO | FK64: NO | FL64: NO | FM64: NO | FN64: NO | FO64: NO | FP64: NO | FQ64: NO | FR64: NO | FS64: NO | FZ64: 0 | GG64: 0 | GN64: 0 | GU64: 0 | HB64: 0 | HI64: 0 | HP64: 0 | HX64: 0 | HY64: 0 | HZ64: 0 | IA64: 0 | IB64: 0 | IC64: 0 | ID64: 0 | IE64: 0 | IL64: 0 | IS64: 0 | IZ64: 0 | JG64: 0 | JN64: 0 | JO64: 0 | JP64: 0 | JQ64: 0 | JR64: 0 | JS64: 0 | JT64: 0 | JU64: 0 | KA64: 3 | KB64: 3 | KC64: 2 | KD64: START Asia Pacific: | OG64: START Europe: | SJ64: START North America: | WM64: START Global: | AAP64: START SOUTH America: | AES64: START Africa: | AIV64: =IFERROR(RIGHT(AH64,LEN(AH64)-SEARCH("@",AH64,1)),"") -> equuspartners.com
A65: C6LRE8A | B65: NCREIF | C65: Heitman | D65: Mary Ludgin | E65: mary.ludgin@heitman.com | G65: https://secure.surveylab.co.uk/anrev-inrev-ncreif-capital-raising-2018/default.asp?survey=C6LRE8A | T65: TRUE | U65: TRUE | V65: TRUE | W65: FALSE | X65: FALSE | Y65: FALSE | Z65: 463 | AA65: 43153.83 | AB65: 196.17.100.162 | AC65: 2018 | AD65: Sarah Berg | AE65: Heitman | AF65: =VLOOKUP(MID(E65,SEARCH("@",E65,1),LEN(E65)-SEARCH("@",E65,1)+1),[2]Sheet1!$D:$F,3,FALSE) -> M107 | AG65: Vice President | AH65: consultant.services@heitman.com | AI65: 312-425-0432 | AJ65: United States | AK65: USD | AM65: 1 | AP65: 182 | AV65: 182 | AW65: 28 | AX65: 466 | BC65: 494 | BD65: 1422 | BE65: 615 | BI65: 1121 | BJ65: 3158 | BQ65: 0 | BX65: 0 | CE65: 0 | CF65: 1632 | CG65: 1081 | CH65: 0 | CI65: 0 | CJ65: 0 | CK65: 1121 | CL65: 3834 | CM65: 1 | CS65: 1 | CT65: 1 | CU65: 1 | CZ65: 2 | DA65: 2 | DB65: 4 | DF65: 3 | DG65: 9 | DN65: 0 | DU65: 0 | EB65: 0 | EC65: 4 | ED65: 5 | EE65: 0 | EF65: 0 | EG65: 0 | EH65: 3 | EI65: 12 | EJ65: YES | EK65: NO | EL65: NO | EM65: NO | EN65: NO | EO65: NO | EP65: YES | EQ65: YES | ER65: NO | ES65: NO | ET65: NO | EU65: NO | EV65: YES | EW65: YES | EX65: NO | EY65: NO | EZ65: NO | FA65: YES | FB65: NO | FC65: NO | FD65: NO | FE65: NO | FF65: NO | FG65: NO | FH65: NO | FI65: NO | FJ65: NO | FK65: NO | FL65: NO | FM65: NO | FN65: NO | FO65: NO | FP65: NO | FQ65: NO | FR65: NO | FS65: NO | FT65: 97 | FU65: 0 | FY65: 0 | FZ65: 97 | GA65: 0 | GB65: 0 | GF65: 200 | GG65: 200 | GH65: 0 | GI65: 0 | GM65: 0 | GN65: 0 | GO65: 1411 | GP65: 1081 | GT65: 624 | GU65: 3116 | GV65: 6 | GW65: 0 | HA65: 0 | HB65: 6 | HC65: 63 | HD65: 0 | HH65: 270 | HI65: 333 | HJ65: 0 | HK65: 0 | HO65: 0 | HP65: 0 | HQ65: Individuals (not HNW) and Taxable Corporate | HR65: 55 | HW65: 27 | HX65: 82 | HY65: 1632 | HZ65: 1081 | IA65: 0 | IB65: 0 | IC65: 0 | ID65: 1121 | IE65: 3834 | IF65: 595 | IG65: 466 | IK65: 27 | IL65: 1088 | IM65: 112 | IN65: 0 | IR65: 0 | IS65: 112 | IT65: 925 | IU65: 615 | IY65: 1094 | IZ65: 2634 | JA65: 0 | JB65: 0 | JF65: 0 | JG65: 0 | JH65: 0 | JI65: 0 | JM65: 0 | JN65: 0 | JO65: 1632 | JP65: 1081 | JQ65: 0 | JR65: 0 | JS65: 0 | JT65: 1121 | JU65: 3834 | JW65: 5 | JX65: 50 | JY65: new clients from prospecting | JZ65: 45 | KA65: 3 | KB65: 1 | KC65: 1 | KD65: START Asia Pacific: | OG65: START Europe: | SJ65: START North America: | WM65: START Global: | AAP65: START SOUTH America: | AES65: START Africa: | AIV65: =IFERROR(RIGHT(AH65,LEN(AH65)-SEARCH("@",AH65,1)),"") -> heitman.com
A66: C6ZGQ8R | B66: NCREIF | C66: AmCap Inc. | D66: Matthew Allen | E66: mallen@amcap.com | G66: https://secure.surveylab.co.uk/anrev-inrev-ncreif-capital-raising-2018/default.asp?survey=C6ZGQ8R | L66: northamerica | M66: 43139.872 | T66: FALSE | U66: FALSE | V66: TRUE | W66: FALSE | X66: FALSE | Y66: FALSE | Z66: 422 | AA66: 43139.872 | AB66: 96.56.90.26 | AC66: 2018 | AD66: Jason Liu | AE66: AmCap Incorporated | AF66: =VLOOKUP(MID(E66,SEARCH("@",E66,1),LEN(E66)-SEARCH("@",E66,1)+1),[2]Sheet1!$D:$F,3,FALSE) -> NC028 | AH66: jliu@amcap.com | AI66: 2033272001 | AJ66: United States | AK66: USD | AM66: 1 | AV66: 0 | BC66: 0 | BD66: 100 | BJ66: 100 | BQ66: 0 | BX66: 0 | CE66: 0 | CF66: 100 | CG66: 0 | CH66: 0 | CI66: 0 | CJ66: 0 | CK66: 0 | CL66: 100 | CS66: 0 | CZ66: 0 | DA66: 1 | DG66: 1 | DN66: 0 | DU66: 0 | EB66: 0 | EC66: 1 | ED66: 0 | EE66: 0 | EF66: 0 | EG66: 0 | EH66: 0 | EI66: 1 | EJ66: NO | EK66: NO | EL66: NO | EM66: NO | EN66: NO | EO66: NO | EP66: NO | EQ66: NO | ER66: NO | ES66: NO | ET66: NO | EU66: NO | EV66: YES | EW66: NO | EX66: NO | EY66: NO | EZ66: NO | FA66: NO | FB66: NO | FC66: NO | FD66: NO | FE66: NO | FF66: NO | FG66: NO | FH66: NO | FI66: NO | FJ66: NO | FK66: NO | FL66: NO | FM66: NO | FN66: NO | FO66: NO | FP66: NO | FQ66: NO | FR66: NO | FS66: NO | FZ66: 0 | GG66: 0 | GN66: 0 | GU66: 0 | HB66: 0 | HI66: 0 | HP66: 0 | HQ66: Bank | HR66: 100 | HX66: 100 | HY66: 100 | HZ66: 0 | IA66: 0 | IB66: 0 | IC66: 0 | ID66: 0 | IE66: 100 | IF66: 100 | IL66: 100 | IS66: 0 | IZ66: 0 | JG66: 0 | JN66: 0 | JO66: 100 | JP66: 0 | JQ66: 0 | JR66: 0 | JS66: 0 | JT66: 0 | JU66: 100 | JV66: 50 | JX66: 50 | KA66: 1 | KB66: 1 | KC66: 1 | KD66: START Asia Pacific: | OG66: START Europe: | SJ66: START North America: | SQ66: 0 | SX66: 0 | TE66: 0 | TL66: 0 | TS66: 0 | TZ66: 0 | UG66: 0 | UH66: Bank | UI66: 100 | UO66: 100 | UP66: 100 | UQ66: 0 | UR66: 0 | US66: 0 | UT66: 0 | UU66: 0 | UV66: 100 | VC66: 0 | VD66: 100 | VJ66: 100 | VQ66: 0 | VX66: 0 | WE66: 0 | WF66: 100 | WG66: 0 | WH66: 0 | WI66: 0 | WJ66: 0 | WK66: 0 | WL66: 100 | WM66: START Global: | AAP66: START SOUTH America: | AES66: START Africa: | AIV66: =IFERROR(RIGHT(AH66,LEN(AH66)-SEARCH("@",AH66,1)),"") -> amcap.com
A67: C7JHG3R | B67: NCREIF | C67: American Realty Advisors | D67: Glenn Anderson | E67: ganderson@americanreal.com | G67: https://secure.surveylab.co.uk/anrev-inrev-ncreif-capital-raising-2018/default.asp?survey=C7JHG3R | L67: northamerica | M67: 43153.815 | T67: FALSE | U67: FALSE | V67: TRUE | W67: FALSE | X67: FALSE | Y67: FALSE | Z67: 439 | AA67: 43153.812 | AB67: 216.5.175.66 | AC67: 2018 | AD67: Jay Butterfield | AE67: American Realty Advisors | AF67: =VLOOKUP(MID(E67,SEARCH("@",E67,1),LEN(E67)-SEARCH("@",E67,1)+1),[2]Sheet1!$D:$F,3,FALSE) -> NC029 | AG67: Executive Managing Director | AH67: butterfield@aracapital.com | AI67: (213) 233 - 5743 | AJ67: United States | AK67: USD | AM67: 1 | AV67: 0 | BC67: 0 | BD67: 345.6 | BJ67: 345.6 | BQ67: 0 | BX67: 0 | CE67: 0 | CF67: 345.6 | CG67: 0 | CH67: 0 | CI67: 0 | CJ67: 0 | CK67: 0 | CL67: 345.6 | CS67: 0 | CZ67: 0 | DA67: 2 | DG67: 2 | DN67: 0 | DU67: 0 | EB67: 0 | EC67: 2 | ED67: 0 | EE67: 0 | EF67: 0 | EG67: 0 | EH67: 0 | EI67: 2 | EJ67: NO | EK67: NO | EL67: NO | EM67: NO | EN67: NO | EO67: NO | EP67: NO | EQ67: NO | ER67: NO | ES67: NO | ET67: NO | EU67: NO | EV67: YES | EW67: NO | EX67: NO | EY67: NO | EZ67: NO | FA67: NO | FB67: NO | FC67: NO | FD67: NO | FE67: NO | FF67: NO | FG67: NO | FH67: NO | FI67: NO | FJ67: NO | FK67: NO | FL67: NO | FM67: NO | FN67: NO | FO67: NO | FP67: NO | FQ67: NO | FR67: NO | FS67: NO | FT67: 149.3 | FZ67: 149.3 | GA67: 0 | GG67: 0 | GH67: 0 | GN67: 0 | GO67: 164.1 | GU67: 164.1 | GV67: 7.2 | HB67: 7.2 | HC67: 2.1 | HI67: 2.1 | HP67: 0 | HQ67: Eleemosynary | HR67: 22.9 | HX67: 22.9 | HY67: 345.6 | HZ67: 0 | IA67: 0 | IB67: 0 | IC67: 0 | ID67: 0 | IE67: 345.6 | IL67: 0 | IS67: 0 | IT67: 345.6 | IZ67: 345.6 | JG67: 0 | JN67: 0 | JO67: 345.6 | JP67: 0 | JQ67: 0 | JR67: 0 | JS67: 0 | JT67: 0 | JU67: 345.6 | JX67: 100 | KA67: 1 | KB67: 3 | KC67: 1 | KD67: START Asia Pacific: | OG67: START Europe: | SJ67: START North America: | SK67: 149.3 | SQ67: 149.3 | SR67: 0 | SX67: 0 | SY67: 0 | TE67: 0 | TF67: 164.1 | TL67: 164.1 | TM67: 7.2 | TS67: 7.2 | TT67: 2.1 | TZ67: 2.1 | UA67: 0 | UG67: 0 | UH67: Eleemosynary | UI67: 22.9 | UO67: 22.9 | UP67: 345.6 | UQ67: 0 | UR67: 0 | US67: 0 | UT67: 0 | UU67: 0 | UV67: 345.6 | VC67: 0 | VJ67: 0 | VK67: 345.6 | VQ67: 345.6 | VX67: 0 | WE67: 0 | WF67: 345.6 | WG67: 0 | WH67: 0 | WI67: 0 | WJ67: 0 | WK67: 0 | WL67: 345.6 | WM67: START Global: | AAP67: START SOUTH America: | AES67: START Africa: | AIV67: =IFERROR(RIGHT(AH67,LEN(AH67)-SEARCH("@",AH67,1)),"") -> aracapital.com
A68: C7QAP9H | B68: NCREIF | C68: Prologis US Logistics Fund | D68: Jon Starek | E68: jstarek@prologis.com | G68: https://secure.surveylab.co.uk/anrev-inrev-ncreif-capital-raising-2018/default.asp?survey=C7QAP9H | J68: europe | K68: 43161.805 | L68: northamerica | M68: 43161.805 | T68: TRUE | U68: FALSE | V68: TRUE | W68: FALSE | X68: FALSE | Y68: FALSE | Z68: 344 | AA68: 43161.81 | AB68: 209.49.4.206 | AC68: 2018 | AD68: Meredith McCreary | AE68: Prologis | AF68: =VLOOKUP(MID(E68,SEARCH("@",E68,1),LEN(E68)-SEARCH("@",E68,1)+1),[2]Sheet1!$D:$F,3,FALSE) -> M024 | AG68: DDQ/RFP Associate | AH68: mmccreary@prologis.com | AI68: 415-733-9465 | AJ68: United States | AK68: USD | AM68: 1 | AV68: 0 | AW68: 1035.17 | AZ68: 403.63 | BC68: 1438.8 | BD68: 1227.85 | BJ68: 1227.85 | BQ68: 0 | BX68: 0 | CE68: 0 | CF68: 2263.02 | CG68: 0 | CH68: 0 | CI68: 403.63 | CJ68: 0 | CK68: 0 | CL68: 2666.65 | CS68: 0 | CT68: 1 | CW68: 1 | CZ68: 2 | DA68: 1 | DG68: 1 | DN68: 0 | DU68: 0 | EB68: 0 | EC68: 2 | ED68: 0 | EE68: 0 | EF68: 1 | EG68: 0 | EH68: 0 | EI68: 3 | EJ68: NO | EK68: NO | EL68: NO | EM68: NO | EN68: NO | EO68: NO | EP68: YES | EQ68: NO | ER68: NO | ES68: YES | ET68: NO | EU68: NO | EV68: YES | EW68: NO | EX68: NO | EY68: NO | EZ68: NO | FA68: NO | FB68: NO | FC68: NO | FD68: NO | FE68: NO | FF68: NO | FG68: NO | FH68: NO | FI68: NO | FJ68: NO | FK68: NO | FL68: NO | FM68: NO | FN68: NO | FO68: NO | FP68: NO | FQ68: NO | FR68: NO | FS68: NO | FT68: 369.76 | FZ68: 369.76 | GA68: 315.45 | GG68: 315.45 | GN68: 0 | GO68: 855.79 | GU68: 855.79 | GV68: 15 | HB68: 15 | HC68: 270.05 | HF68: 403.63 | HI68: 673.68 | HP68: 0 | HQ68: Corporation, RIC, & Trust | HR68: 436.97 | HX68: 436.97 | HY68: 2263.02 | HZ68: 0 | IA68: 0 | IB68: 403.63 | IC68: 0 | ID68: 0 | IE68: 2666.65 | IF68: 556.73 | IL68: 556.73 | IM68: 965.69 | IP68: 403.63 | IS68: 1369.32 | IT68: 740.6 | IZ68: 740.6 | JG68: 0 | JN68: 0 | JO68: 2263.02 | JP68: 0 | JQ68: 0 | JR68: 403.63 | JS68: 0 | JT68: 0 | JU68: 2666.65 | KA68: 2 | KB68: 3 | KC68: 1 | KD68: START Asia Pacific: | OG68: START Europe: | OH68: 29.76 | ON68: 29.76 | OO68: 315.45 | OU68: 315.45 | PB68: 0 | PC68: 359.79 | PI68: 359.79 | PP68: 0 | PQ68: 107 | PT68: 403.63 | PW68: 510.63 | QD68: 0 | QE68: Corporation and Trust | QF68: 223.17 | QL68: 223.17 | QM68: 1035.17 | QN68: 0 | QO68: 0 | QP68: 403.63 | QQ68: 0 | QR68: 0 | QS68: 1438.8 | QT68: 578.44 | QW68: 403.63 | QZ68: 982.07 | RA68: 456.73 | RG68: 456.73 | RN68: 0 | RU68: 0 | SB68: 0 | SC68: 1035.17 | SD68: 0 | SE68: 0 | SF68: 403.63 | SG68: 0 | SH68: 0 | SI68: 1438.8 | SJ68: START North America: | SK68: 340 | SQ68: 340 | SX68: 0 | TE68: 0 | TF68: 496 | TL68: 496 | TM68: 15 | TS68: 15 | TT68: 163.05 | TZ68: 163.05 | UG68: 0 | UH68: Corporation and RIC | UI68: 213.8 | UO68: 213.8 | UP68: 1227.85 | UQ68: 0 | UR68: 0 | US68: 0 | UT68: 0 | UU68: 0 | UV68: 1227.85 | UW68: 387.25 | VC68: 387.25 | VD68: 100 | VJ68: 100 | VK68: 740.6 | VQ68: 740.6 | VX68: 0 | WE68: 0 | WF68: 1227.85 | WG68: 0 | WH68: 0 | WI68: 0 | WJ68: 0 | WK68: 0 | WL68: 1227.85 | WM68: START Global: | AAP68: START SOUTH America: | AES68: START Africa: | AIV68: =IFERROR(RIGHT(AH68,LEN(AH68)-SEARCH("@",AH68,1)),"") -> prologis.com
A69: C8CWG8L | B69: NCREIF | C69: ASB Capital Management | LLC | D69: Hanneke Talbot | E69: htalbot@asbrealestate.com | G69: https://secure.surveylab.co.uk/anrev-inrev-ncreif-capital-raising-2018/default.asp?survey=C8CWG8L | T69: FALSE | U69: FALSE | V69: FALSE | W69: FALSE | X69: FALSE | Y69: FALSE | Z69: 446 | AA69: 43146.797 | AB69: 38.100.6.131 | AC69: 2018 | AD69: David Kim | AE69: ASB Real Estate Investments | AF69: =VLOOKUP(MID(E69,SEARCH("@",E69,1),LEN(E69)-SEARCH("@",E69,1)+1),[2]Sheet1!$D:$F,3,FALSE) -> NC030 | AG69: Senior Portfolio Management Analyst | AH69: dkim@asbrealestate.com | AI69: 240-482-2923 | AJ69: United States | AK69: USD | AM69: 2 | AN69: 1 | AV69: 0 | BC69: 0 | BJ69: 0 | BQ69: 0 | BX69: 0 | CE69: 0 | CF69: 0 | CG69: 0 | CH69: 0 | CI69: 0 | CJ69: 0 | CK69: 0 | CL69: 0 | CS69: 0 | CZ69: 0 | DG69: 0 | DN69: 0 | DU69: 0 | EB69: 0 | EC69: 0 | ED69: 0 | EE69: 0 | EF69: 0 | EG69: 0 | EH69: 0 | EI69: 0 | EJ69: NO | EK69: NO | EL69: NO | EM69: NO | EN69: NO | EO69: NO | EP69: NO | EQ69: NO | ER69: NO | ES69: NO | ET69: NO | EU69: NO | EV69: NO | EW69: NO | EX69: NO | EY69: NO | EZ69: NO | FA69: NO | FB69: NO | FC69: NO | FD69: NO | FE69: NO | FF69: NO | FG69: NO | FH69: NO | FI69: NO | FJ69: NO | FK69: NO | FL69: NO | FM69: NO | FN69: NO | FO69: NO | FP69: NO | FQ69: NO | FR69: NO | FS69: NO | FZ69: 0 | GG69: 0 | GN69: 0 | GU69: 0 | HB69: 0 | HI69: 0 | HP69: 0 | HX69: 0 | HY69: 0 | HZ69: 0 | IA69: 0 | IB69: 0 | IC69: 0 | ID69: 0 | IE69: 0 | IL69: 0 | IS69: 0 | IZ69: 0 | JG69: 0 | JN69: 0 | JO69: 0 | JP69: 0 | JQ69: 0 | JR69: 0 | JS69: 0 | JT69: 0 | JU69: 0 | KA69: 1 | KB69: 1 | KC69: 1 | KD69: START Asia Pacific: | OG69: START Europe: | SJ69: START North America: | WM69: START Global: | AAP69: START SOUTH America: | AES69: START Africa: | AIV69: =IFERROR(RIGHT(AH69,LEN(AH69)-SEARCH("@",AH69,1)),"") -> asbrealestate.com
A70: C8VRC4D | B70: NCREIF | C70: Clarion Partners | D70: Patrick Tully | E70: patrick.tully@clarionpartners.com | G70: https://secure.surveylab.co.uk/anrev-inrev-ncreif-capital-raising-2018/default.asp?survey=C8VRC4D | L70: northamerica | M70: 43158.92 | T70: FALSE | U70: FALSE | V70: TRUE | W70: FALSE | X70: FALSE | Y70: FALSE | Z70: 465 | AA70: 43158.919 | AB70: 196.17.100.200 | AC70: 2018 | AD70: Karen Schumacher | AE70: Clarion Partners | AF70: =VLOOKUP(MID(E70,SEARCH("@",E70,1),LEN(E70)-SEARCH("@",E70,1)+1),[2]Sheet1!$D:$F,3,FALSE) -> M677 | AG70: Vice President | AH70: karen.schumacher@clarionpartners.com | AI70: 2128832740 | AJ70: United States | AK70: USD | AM70: 1 | AV70: 0 | BC70: 0 | BD70: 2057 | BE70: 425 | BJ70: 2482 | BQ70: 0 | BX70: 0 | CE70: 0 | CF70: 2057 | CG70: 425 | CH70: 0 | CI70: 0 | CJ70: 0 | CK70: 0 | CL70: 2482 | CS70: 0 | CZ70: 0 | DA70: 5 | DB70: 4 | DG70: 9 | DN70: 0 | DU70: 0 | EB70: 0 | EC70: 5 | ED70: 4 | EE70: 0 | EF70: 0 | EG70: 0 | EH70: 0 | EI70: 9 | EJ70: NO | EK70: NO | EL70: NO | EM70: NO | EN70: NO | EO70: NO | EP70: NO | EQ70: NO | ER70: NO | ES70: NO | ET70: NO | EU70: NO | EV70: YES | EW70: YES | EX70: NO | EY70: NO | EZ70: NO | FA70: NO | FB70: NO | FC70: NO | FD70: NO | FE70: NO | FF70: NO | FG70: NO | FH70: NO | FI70: NO | FJ70: NO | FK70: NO | FL70: NO | FM70: NO | FN70: NO | FO70: NO | FP70: NO | FQ70: NO | FR70: NO | FS70: NO | FT70: 636 | FU70: 125 | FZ70: 761 | GA70: 440 | GB70: 100 | GG70: 540 | GN70: 0 | GU70: 0 | GV70: 62 | HB70: 62 | HC70: 598 | HI70: 598 | HJ70: 58 | HK70: 200 | HP70: 258 | HQ70: Mixed entities, Asset mgrs, etc. | HR70: 263 | HX70: 263 | HY70: 2057 | HZ70: 425 | IA70: 0 | IB70: 0 | IC70: 0 | ID70: 0 | IE70: 2482 | IF70: 430 | IL70: 430 | IM70: 504 | IS70: 504 | IT70: 1118 | IU70: 225 | IZ70: 1343 | JA70: 5 | JB70: 200 | JG70: 205 | JN70: 0 | JO70: 2057 | JP70: 425 | JQ70: 0 | JR70: 0 | JS70: 0 | JT70: 0 | JU70: 2482 | JX70: 100 | KA70: 1 | KB70: 3 | KC70: 1 | KD70: START Asia Pacific: | OG70: START Europe: | SJ70: START North America: | SK70: 636 | SL70: 125 | SQ70: 761 | SR70: 440 | SS70: 100 | SX70: 540 | TE70: 0 | TL70: 0 | TM70: 62 | TS70: 62 | TT70: 598 | TZ70: 598 | UA70: 58 | UB70: 200 | UG70: 258 | UH70: mixed entities, asset mgrs, etc. | UI70: 263 | UO70: 263 | UP70: 2057 | UQ70: 425 | UR70: 0 | US70: 0 | UT70: 0 | UU70: 0 | UV70: 2482 | UW70: 430 | VC70: 430 | VD70: 504 | VJ70: 504 | VK70: 1118 | VL70: 225 | VQ70: 1343 | VR70: 5 | VS70: 200 | VX70: 205 | WE70: 0 | WF70: 2057 | WG70: 425 | WH70: 0 | WI70: 0 | WJ70: 0 | WK70: 0 | WL70: 2482 | WM70: START Global: | AAP70: START SOUTH America: | AES70: START Africa: | AIV70: =IFERROR(RIGHT(AH70,LEN(AH70)-SEARCH("@",AH70,1)),"") -> clarionpartners.com
A71: C8ZWE6V | B71: NCREIF | C71: Intercontinental Real Estate Corp. | D71: David Carella | E71: davec@intercontinental.net | G71: https://secure.surveylab.co.uk/anrev-inrev-ncreif-capital-raising-2018/default.asp?survey=C8ZWE6V | L71: northamerica | M71: 43140.614 | T71: FALSE | U71: FALSE | V71: TRUE | W71: FALSE | X71: FALSE | Y71: FALSE | Z71: 421 | AA71: 43140.613 | AB71: 65.215.112.242 | AC71: 2018 | AD71: Brandon Millen | AE71: Intercontinental Real Estate Corp. | AF71: =VLOOKUP(MID(E71,SEARCH("@",E71,1),LEN(E71)-SEARCH("@",E71,1)+1),[2]Sheet1!$D:$F,3,FALSE) -> NC007 | AG71: Associate Direction, Performance | AH71: Brandonm@intercontinental.net | AI71: 6177790490 | AJ71: United States | AK71: USD | AM71: 1 | AV71: 0 | BC71: 0 | BD71: 662 | BJ71: 662 | BQ71: 0 | BX71: 0 | CE71: 0 | CF71: 662 | CG71: 0 | CH71: 0 | CI71: 0 | CJ71: 0 | CK71: 0 | CL71: 662 | CS71: 0 | CZ71: 0 | DA71: 1 | DG71: 1 | DN71: 0 | DU71: 0 | EB71: 0 | EC71: 1 | ED71: 0 | EE71: 0 | EF71: 0 | EG71: 0 | EH71: 0 | EI71: 1 | EJ71: NO | EK71: NO | EL71: NO | EM71: NO | EN71: NO | EO71: NO | EP71: NO | EQ71: NO | ER71: NO | ES71: NO | ET71: NO | EU71: NO | EV71: YES | EW71: NO | EX71: NO | EY71: NO | EZ71: NO | FA71: NO | FB71: NO | FC71: NO | FD71: NO | FE71: NO | FF71: NO | FG71: NO | FH71: NO | FI71: NO | FJ71: NO | FK71: NO | FL71: NO | FM71: NO | FN71: NO | FO71: NO | FP71: NO | FQ71: NO | FR71: NO | FS71: NO | FT71: 652 | FZ71: 652 | GG71: 0 | GN71: 0 | GU71: 0 | GV71: 4.6 | HB71: 4.6 | HI71: 0 | HJ71: 5.4 | HP71: 5.4 | HX71: 0 | HY71: 662 | HZ71: 0 | IA71: 0 | IB71: 0 | IC71: 0 | ID71: 0 | IE71: 662 | IL71: 0 | IS71: 0 | IT71: 662 | IZ71: 662 | JG71: 0 | JN71: 0 | JO71: 662 | JP71: 0 | JQ71: 0 | JR71: 0 | JS71: 0 | JT71: 0 | JU71: 662 | JX71: 100 | KA71: 3 | KB71: 3 | KC71: 1 | KD71: START Asia Pacific: | OG71: START Europe: | SJ71: START North America: | SK71: 652 | SQ71: 652 | SX71: 0 | TE71: 0 | TL71: 0 | TM71: 4.6 | TS71: 4.6 | TZ71: 0 | UA71: 5.4 | UG71: 5.4 | UO71: 0 | UP71: 662 | UQ71: 0 | UR71: 0 | US71: 0 | UT71: 0 | UU71: 0 | UV71: 662 | VC71: 0 | VJ71: 0 | VK71: 662 | VQ71: 662 | VX71: 0 | WE71: 0 | WF71: 662 | WG71: 0 | WH71: 0 | WI71: 0 | WJ71: 0 | WK71: 0 | WL71: 662 | WM71: START Global: | AAP71: START SOUTH America: | AES71: START Africa: | AIV71: =IFERROR(RIGHT(AH71,LEN(AH71)-SEARCH("@",AH71,1)),"") -> intercontinental.net
A72: C9VPM5J | B72: NCREIF | C72: Invesco | D72: Mike Sobolik | E72: mike.sobolik@invesco.com | G72: https://secure.surveylab.co.uk/anrev-inrev-ncreif-capital-raising-2018/default.asp?survey=C9VPM5J | H72: asia | I72: 43164.82 | J72: europe | K72: 43164.831 | L72: northamerica | M72: 43164.842 | N72: Global | O72: 43164.844 | T72: TRUE | U72: TRUE | V72: TRUE | W72: TRUE | X72: FALSE | Y72: FALSE | Z72: 334 | AA72: 43164.818 | AB72: 193.23.124.65 | AC72: 2018 | AD72: Lisa Nell | AE72: Invesco Real Estate | AF72: =VLOOKUP(MID(E72,SEARCH("@",E72,1),LEN(E72)-SEARCH("@",E72,1)+1),[2]Sheet1!$D:$F,3,FALSE) -> M114 | AG72: Director - Head of Marketing | AH72: lisa.nell@invesco.com | AI72: 2075433535 | AJ72: United States | AK72: USD | AM72: 1 | AP72: 609.16 | AQ72: 20.39 | AV72: 629.55 | AW72: 947.68 | AX72: 491.54 | BC72: 1439.22 | BD72: 2572.35 | BE72: 776.97 | BJ72: 3349.32 | BK72: 143.93 | BL72: 61.15 | BQ72: 205.08 | BX72: 0 | CE72: 0 | CF72: 4273.12 | CG72: 1350.05 | CH72: 0 | CI72: 0 | CJ72: 0 | CK72: 0 | CL72: 5623.17 | CM72: 2 | CN72: 1 | CS72: 3 | CT72: 4 | CU72: 6 | CZ72: 10 | DA72: 4 | DB72: 5 | DG72: 9 | DH72: 2 | DI72: 1 | DN72: 3 | DU72: 0 | EB72: 0 | EC72: 12 | ED72: 13 | EE72: 0 | EF72: 0 | EG72: 0 | EH72: 0 | EI72: 25 | EJ72: YES | EK72: YES | EL72: NO | EM72: NO | EN72: NO | EO72: NO | EP72: YES | EQ72: YES | ER72: NO | ES72: NO | ET72: NO | EU72: NO | EV72: YES | EW72: YES | EX72: NO | EY72: NO | EZ72: NO | FA72: NO | FB72: YES | FC72: YES | FD72: NO | FE72: NO | FF72: NO | FG72: NO | FH72: NO | FI72: NO | FJ72: NO | FK72: NO | FL72: NO | FM72: NO | FN72: NO | FO72: NO | FP72: NO | FQ72: NO | FR72: NO | FS72: NO | FT72: 3041.0946 | FU72: 1350.0409 | FZ72: 4391.14 | GA72: 367.2 | GG72: 367.2 | GH72: 85.988614 | GN72: 85.99 | GO72: 25 | GU72: 25 | GV72: 91.062 | HB72: 91.06 | HC72: 526.60811 | HD72: 20.389966 | HI72: 547 | HJ72: 25.13 | HP72: 25.13 | HQ72: Corporates, Banks, Endownments | HR72: 56.39 | HS72: 34.27059 | HX72: 90.66 | HY72: 4218.47 | HZ72: 1404.7 | IA72: 0 | IB72: 0 | IC72: 0 | ID72: 0 | IE72: 5623.17 | IF72: 1523.24 | IG72: 20.389966 | IL72: 1543.63 | IM72: 1270.994 | IN72: 552.68714 | IS72: 1823.68 | IT72: 1478.895 | IU72: 776.96387 | IZ72: 2255.86 | JG72: 0 | JN72: 0 | JO72: 4273.13 | JP72: 1350.04 | JQ72: 0 | JR72: 0 | JS72: 0 | JT72: 0 | JU72: 5623.17 | JW72: 40 | JX72: 60 | KA72: 1 | KB72: 3 | KC72: 1 | KD72: START Asia Pacific: | KE72: 404 | KK72: 404 | KR72: 0 | KY72: 0 | KZ72: 25 | LF72: 25 | LM72: 0 | LN72: 180.16 | LO72: 20.389966 | LT72: 200.55 | MA72: 0 | MI72: 0 | MJ72: 609.16 | MK72: 20.39 | ML72: 0 | MM72: 0 | MN72: 0 | MO72: 0 | MP72: 629.55 | MQ72: 340.72 | MW72: 340.72 | MX72: 58.44 | MY72: 20.389966 | ND72: 78.83 | NE72: 210 | NK72: 210 | NR72: 0 | NY72: 0 | NZ72: 609.16 | OA72: 20.39 | OB72: 0 | OC72: 0 | OD72: 0 | OE72: 0 | OF72: 629.55 | OG72: START Europe: | OH72: 725.48 | OI72: 457.27 | ON72: 1182.75 | OO72: 43.30075 | OU72: 43.3 | OV72: 10.988614 | PB72: 10.99 | PI72: 0 | PJ72: 21.562 | PP72: 21.56 | PQ72: 94.936 | PW72: 94.94 | QD72: 0 | QE72: Bank | QF72: 51.4125 | QG72: 34.27059 | QL72: 85.68 | QM72: 947.68 | QN72: 491.54 | QO72: 0 | QP72: 0 | QQ72: 0 | QR72: 0 | QS72: 1439.22 | QT72: 807.78132 | QU72: 491.538 | QZ72: 1299.32 | RA72: 82.774125 | RG72: 82.77 | RH72: 57.125 | RN72: 57.13 | RU72: 0 | SB72: 0 | SC72: 947.68 | SD72: 491.54 | SE72: 0 | SF72: 0 | SG72: 0 | SH72: 0 | SI72: 1439.22 | SJ72: START North America: | SK72: 1787.75 | SL72: 776.96387 | SQ72: 2564.71 | SR72: 318.9 | SX72: 318.9 | SY72: 75 | TE72: 75 | TL72: 0 | TM72: 69.5 | TS72: 69.5 | TT72: 251.52 | TZ72: 251.52 | UA72: 25.14 | UG72: 25.14 | UH72: Endowment, Corporation | UI72: 44.55 | UO72: 44.55 | UP72: 2572.36 | UQ72: 776.96 | UR72: 0 | US72: 0 | UT72: 0 | UU72: 0 | UV72: 3349.32 | UW72: 46 | VC72: 46 | VD72: 1382.06 | VJ72: 1382.06 | VK72: 1144.34 | VL72: 776.92 | VQ72: 1921.26 | VX72: 0 | WE72: 0 | WF72: 2572.4 | WG72: 776.92 | WH72: 0 | WI72: 0 | WJ72: 0 | WK72: 0 | WL72: 3349.32 | WM72: START Global: | WN72: 112.44 | WO72: 61.148 | WT72: 173.59 | WU72: 5 | XA72: 5 | XH72: 0 | XO72: 0 | XV72: 0 | YC72: 0 | YJ72: 0 | YL72: 26.493 | YR72: 26.49 | YS72: 143.93 | YT72: 61.15 | YU72: 0 | YV72: 0 | YW72: 0 | YX72: 0 | YY72: 205.08 | YZ72: 51.493 | ZA72: 61.148 | ZF72: 112.64 | ZM72: 0 | ZN72: 92.44 | ZT72: 92.44 | AAA72: 0 | AAH72: 0 | AAI72: 143.93 | AAJ72: 61.15 | AAK72: 0 | AAL72: 0 | AAM72: 0 | AAN72: 0 | AAO72: 205.08 | AAP72: START SOUTH America: | AES72: START Africa: | AIV72: =IFERROR(RIGHT(AH72,LEN(AH72)-SEARCH("@",AH72,1)),"") -> invesco.com
A73: N0AGQ3C | B73: INREV | C73: ECE Real Estate Partners | D73: Jose María Ortiz | E73: JoseMaria.Ortiz@ece.com | G73: https://secure.surveylab.co.uk/anrev-inrev-ncreif-capital-raising-2018/default.asp?survey=N0AGQ3C | T73: FALSE | U73: FALSE | V73: FALSE | W73: FALSE | X73: FALSE | Y73: FALSE | Z73: 491 | AA73: 43161.689 | AB73: 83.236.160.70 | AC73: 2018 | AD73: José María Ortiz | AE73: ECE Real Estate Partners S.à r.l. | AF73: =VLOOKUP(MID(E73,SEARCH("@",E73,1),LEN(E73)-SEARCH("@",E73,1)+1),[2]Sheet1!$D:$F,3,FALSE) -> M657 | AG73: Managing Director | AH73: josemaria.ortiz@ece.com | AI73: 2678592920 | AJ73: Germany | AK73: EUR | AM73: 2 | AN73: 6 | AO73: Investment period for current funds is not ended | AV73: 0 | BC73: 0 | BJ73: 0 | BQ73: 0 | BX73: 0 | CE73: 0 | CF73: 0 | CG73: 0 | CH73: 0 | CI73: 0 | CJ73: 0 | CK73: 0 | CL73: 0 | CS73: 0 | CZ73: 0 | DG73: 0 | DN73: 0 | DU73: 0 | EB73: 0 | EC73: 0 | ED73: 0 | EE73: 0 | EF73: 0 | EG73: 0 | EH73: 0 | EI73: 0 | EJ73: NO | EK73: NO | EL73: NO | EM73: NO | EN73: NO | EO73: NO | EP73: NO | EQ73: NO | ER73: NO | ES73: NO | ET73: NO | EU73: NO | EV73: NO | EW73: NO | EX73: NO | EY73: NO | EZ73: NO | FA73: NO | FB73: NO | FC73: NO | FD73: NO | FE73: NO | FF73: NO | FG73: NO | FH73: NO | FI73: NO | FJ73: NO | FK73: NO | FL73: NO | FM73: NO | FN73: NO | FO73: NO | FP73: NO | FQ73: NO | FR73: NO | FS73: NO | FZ73: 0 | GG73: 0 | GN73: 0 | GU73: 0 | HB73: 0 | HI73: 0 | HP73: 0 | HX73: 0 | HY73: 0 | HZ73: 0 | IA73: 0 | IB73: 0 | IC73: 0 | ID73: 0 | IE73: 0 | IL73: 0 | IS73: 0 | IZ73: 0 | JG73: 0 | JN73: 0 | JO73: 0 | JP73: 0 | JQ73: 0 | JR73: 0 | JS73: 0 | JT73: 0 | JU73: 0 | KA73: 1 | KB73: 3 | KC73: 1 | KD73: START Asia Pacific: | OG73: START Europe: | SJ73: START North America: | WM73: START Global: | AAP73: START SOUTH America: | AES73: START Africa: | AIV73: =IFERROR(RIGHT(AH73,LEN(AH73)-SEARCH("@",AH73,1)),"") -> ece.com
A74: N0ERX4C | B74: INREV | C74: DeWert Deutsche Wertinvestment GmbH | D74: Jorg Thomsen | E74: jthomsen@de-wert.de | G74: https://secure.surveylab.co.uk/anrev-inrev-ncreif-capital-raising-2018/default.asp?survey=N0ERX4C | J74: europe | K74: 43159.708 | T74: TRUE | U74: FALSE | V74: FALSE | W74: FALSE | X74: FALSE | Y74: FALSE | Z74: 461 | AA74: 43159.707 | AB74: 130.180.126.154 | AC74: 2018 | AD74: Marc Weisener | AE74: Hahn Group | AF74: =VLOOKUP(MID(E74,SEARCH("@",E74,1),LEN(E74)-SEARCH("@",E74,1)+1),[2]Sheet1!$D:$F,3,FALSE) -> M369 | AG74: Investor Relations | AH74: mweisener@hahnag.de | AJ74: Germany | AK74: EUR | AM74: 1 | AV74: 0 | AW74: 62 | AY74: 4 | BC74: 66 | BJ74: 0 | BQ74: 0 | BX74: 0 | CE74: 0 | CF74: 62 | CG74: 0 | CH74: 4 | CI74: 0 | CJ74: 0 | CK74: 0 | CL74: 66 | CS74: 0 | CT74: 1 | CV74: 1 | CZ74: 2 | DG74: 0 | DN74: 0 | DU74: 0 | EB74: 0 | EC74: 1 | ED74: 0 | EE74: 1 | EF74: 0 | EG74: 0 | EH74: 0 | EI74: 2 | EJ74: NO | EK74: NO | EL74: NO | EM74: NO | EN74: NO | EO74: NO | EP74: YES | EQ74: NO | ER74: YES | ES74: NO | ET74: NO | EU74: NO | EV74: NO | EW74: NO | EX74: NO | EY74: NO | EZ74: NO | FA74: NO | FB74: NO | FC74: NO | FD74: NO | FE74: NO | FF74: NO | FG74: NO | FH74: NO | FI74: NO | FJ74: NO | FK74: NO | FL74: NO | FM74: NO | FN74: NO | FO74: NO | FP74: NO | FQ74: NO | FR74: NO | FS74: NO | FZ74: 0 | GG74: 0 | GN74: 0 | GU74: 0 | GV74: 62 | HB74: 62 | HI74: 0 | HP74: 0 | HT74: 4 | HX74: 4 | HY74: 62 | HZ74: 0 | IA74: 4 | IB74: 0 | IC74: 0 | ID74: 0 | IE74: 66 | IL74: 0 | IM74: 62 | IO74: 4 | IS74: 66 | IZ74: 0 | JG74: 0 | JN74: 0 | JO74: 62 | JP74: 0 | JQ74: 4 | JR74: 0 | JS74: 0 | JT74: 0 | JU74: 66 | JX74: 100 | KA74: 1 | KB74: 3 | KC74: 1 | KD74: START Asia Pacific: | OG74: START Europe: | ON74: 0 | OU74: 0 | PB74: 0 | PI74: 0 | PJ74: 62 | PL74: 4 | PP74: 66 | PW74: 0 | QD74: 0 | QL74: 0 | QM74: 62 | QN74: 0 | QO74: 4 | QP74: 0 | QQ74: 0 | QR74: 0 | QS74: 66 | QT74: 62 | QV74: 4 | QZ74: 66 | RG74: 0 | RN74: 0 | RU74: 0 | SB74: 0 | SC74: 62 | SD74: 0 | SE74: 4 | SF74: 0 | SG74: 0 | SH74: 0 | SI74: 66 | SJ74: START North America: | WM74: START Global: | AAP74: START SOUTH America: | AES74: START Africa: | AIV74: =IFERROR(RIGHT(AH74,LEN(AH74)-SEARCH("@",AH74,1)),"") -> hahnag.de
A75: N0HUC2F | B75: INREV | C75: Tristan Capital Partners | D75: Adam Smith | E75: asmith@tristancap.com | G75: https://secure.surveylab.co.uk/anrev-inrev-ncreif-capital-raising-2018/default.asp?survey=N0HUC2F | J75: europe | K75: 43117.512 | T75: TRUE | U75: FALSE | V75: FALSE | W75: FALSE | X75: FALSE | Y75: FALSE | Z75: 352 | AA75: 43117.471 | AB75: 92.207.173.34 | AC75: 2018 | AD75: Adam Smith | AE75: Tristan Capital Partners | AF75: =VLOOKUP(MID(E75,SEARCH("@",E75,1),LEN(E75)-SEARCH("@",E75,1)+1),[2]Sheet1!$D:$F,3,FALSE) -> M486 | AG75: Executive Director | AH75: asmith@tristancap.com | AI75: 442034638867 | AJ75: United Kingdom | AK75: EUR | AM75: 1 | AV75: 0 | AW75: 622.63 | BC75: 622.63 | BJ75: 0 | BQ75: 0 | BX75: 0 | CE75: 0 | CF75: 622.63 | CG75: 0 | CH75: 0 | CI75: 0 | CJ75: 0 | CK75: 0 | CL75: 622.63 | CS75: 0 | CT75: 1 | CZ75: 1 | DG75: 0 | DN75: 0 | DU75: 0 | EB75: 0 | EC75: 1 | ED75: 0 | EE75: 0 | EF75: 0 | EG75: 0 | EH75: 0 | EI75: 1 | EJ75: NO | EK75: NO | EL75: NO | EM75: NO | EN75: NO | EO75: NO | EP75: YES | EQ75: NO | ER75: NO | ES75: NO | ET75: NO | EU75: NO | EV75: NO | EW75: NO | EX75: NO | EY75: NO | EZ75: NO | FA75: NO | FB75: NO | FC75: NO | FD75: NO | FE75: NO | FF75: NO | FG75: NO | FH75: NO | FI75: NO | FJ75: NO | FK75: NO | FL75: NO | FM75: NO | FN75: NO | FO75: NO | FP75: NO | FQ75: NO | FR75: NO | FS75: NO | FT75: 240 | FZ75: 240 | GA75: 203 | GG75: 203 | GN75: 0 | GO75: 30 | GU75: 30 | GV75: 104.1 | HB75: 104.1 | HI75: 0 | HJ75: 39.3 | HP75: 39.3 | HQ75: GP Co-Investment | HR75: 6.23 | HX75: 6.23 | HY75: 622.63 | HZ75: 0 | IA75: 0 | IB75: 0 | IC75: 0 | ID75: 0 | IE75: 622.63 | IF75: 33 | IL75: 33 | IM75: 414.63 | IS75: 414.63 | IT75: 160 | IZ75: 160 | JG75: 0 | JH75: 15 | JN75: 15 | JO75: 622.63 | JP75: 0 | JQ75: 0 | JR75: 0 | JS75: 0 | JT75: 0 | JU75: 622.63 | KA75: 1 | KB75: 3 | KC75: 1 | KD75: START Asia Pacific: | OG75: START Europe: | OH75: 240 | ON75: 240 | OO75: 203 | OU75: 203 | PB75: 0 | PC75: 30 | PI75: 30 | PJ75: 104.1 | PP75: 104.1 | PW75: 0 | PX75: 39.3 | QD75: 39.3 | QE75: GP Co-Investment | QF75: 6.23 | QL75: 6.23 | QM75: 622.63 | QN75: 0 | QO75: 0 | QP75: 0 | QQ75: 0 | QR75: 0 | QS75: 622.63 | QT75: 414.63 | QZ75: 414.63 | RA75: 33 | RG75: 33 | RH75: 160 | RN75: 160 | RU75: 0 | RV75: 15 | SB75: 15 | SC75: 622.63 | SD75: 0 | SE75: 0 | SF75: 0 | SG75: 0 | SH75: 0 | SI75: 622.63 | SJ75: START North America: | WM75: START Global: | AAP75: START SOUTH America: | AES75: START Africa: | AIV75: =IFERROR(RIGHT(AH75,LEN(AH75)-SEARCH("@",AH75,1)),"") -> tristancap.com
A76: N0HXE1P | B76: INREV | C76: Alma Property Partners | D76: Sloan Wobbeking | E76: sloan.wobbeking@almaproperty.se | G76: https://secure.surveylab.co.uk/anrev-inrev-ncreif-capital-raising-2018/default.asp?survey=N0HXE1P | J76: europe | K76: 43123.634 | T76: TRUE | U76: FALSE | V76: FALSE | W76: FALSE | X76: FALSE | Y76: FALSE | Z76: 376 | AA76: 43123.632 | AB76: 185.40.184.11 | AC76: 2018 | AD76: Sloan Wobbeking | AE76: Alma Property Partners | AF76: =VLOOKUP(MID(E76,SEARCH("@",E76,1),LEN(E76)-SEARCH("@",E76,1)+1),[2]Sheet1!$D:$F,3,FALSE) -> M736 | AG76: Partner & CEO | AH76: sloan.wobbeking@almaproperty.se | AI76: +46 70 227 7400 | AJ76: Sweden | AK76: EUR | AM76: 1 | AV76: 0 | AW76: 140 | BC76: 140 | BJ76: 0 | BQ76: 0 | BX76: 0 | CE76: 0 | CF76: 140 | CG76: 0 | CH76: 0 | CI76: 0 | CJ76: 0 | CK76: 0 | CL76: 140 | CS76: 0 | CT76: 1 | CZ76: 1 | DG76: 0 | DN76: 0 | DU76: 0 | EB76: 0 | EC76: 1 | ED76: 0 | EE76: 0 | EF76: 0 | EG76: 0 | EH76: 0 | EI76: 1 | EJ76: NO | EK76: NO | EL76: NO | EM76: NO | EN76: NO | EO76: NO | EP76: YES | EQ76: NO | ER76: NO | ES76: NO | ET76: NO | EU76: NO | EV76: NO | EW76: NO | EX76: NO | EY76: NO | EZ76: NO | FA76: NO | FB76: NO | FC76: NO | FD76: NO | FE76: NO | FF76: NO | FG76: NO | FH76: NO | FI76: NO | FJ76: NO | FK76: NO | FL76: NO | FM76: NO | FN76: NO | FO76: NO | FP76: NO | FQ76: NO | FR76: NO | FS76: NO | FT76: 73 | FZ76: 73 | GA76: 7 | GG76: 7 | GN76: 0 | GU76: 0 | GV76: 18 | HB76: 18 | HC76: 5 | HI76: 5 | HJ76: 34 | HP76: 34 | HQ76: Employees | HR76: 3 | HX76: 3 | HY76: 140 | HZ76: 0 | IA76: 0 | IB76: 0 | IC76: 0 | ID76: 0 | IE76: 140 | IL76: 0 | IM76: 140 | IS76: 140 | IZ76: 0 | JG76: 0 | JN76: 0 | JO76: 140 | JP76: 0 | JQ76: 0 | JR76: 0 | JS76: 0 | JT76: 0 | JU76: 140 | JV76: 17 | JX76: 83 | KA76: 3 | KB76: 2 | KC76: 1 | KD76: START Asia Pacific: | OG76: START Europe: | OH76: 73 | ON76: 73 | OO76: 7 | OU76: 7 | PB76: 0 | PI76: 0 | PJ76: 18 | PP76: 18 | PQ76: 5 | PW76: 5 | PX76: 34 | QD76: 34 | QE76: Employees | QF76: 3 | QL76: 3 | QM76: 140 | QN76: 0 | QO76: 0 | QP76: 0 | QQ76: 0 | QR76: 0 | QS76: 140 | QT76: 140 | QZ76: 140 | RG76: 0 | RN76: 0 | RU76: 0 | SB76: 0 | SC76: 140 | SD76: 0 | SE76: 0 | SF76: 0 | SG76: 0 | SH76: 0 | SI76: 140 | SJ76: START North America: | WM76: START Global: | AAP76: START SOUTH America: | AES76: START Africa: | AIV76: =IFERROR(RIGHT(AH76,LEN(AH76)-SEARCH("@",AH76,1)),"") -> almaproperty.se
