Workbook

Sheet DataCompleted_final_analysis_AV
A1: RecordNo | B1: Surveycode | C1: URIstring | D1: DateUpdated | E1: DateCompleted | F1: PageNo | G1: PathInfo | H1: Referrer | I1: IPaddress | J1: Version | K1: qName | L1: qCompany | M1: mnumber | N1: qJobtitle | O1: qEmail | P1: qTelephone | Q1: qCountry | R1: qCurrency | S1: qCurrencyOther | T1: q1 | U1: q2 | V1: q2other | W1: q31_1 | X1: q31_2 | Y1: q31_3 | Z1: q31_4 | AA1: q31_5 | AB1: q31_6 | AC1: q3ROW1_hidden | AD1: q32_1 | AE1: q32_2 | AF1: q32_3 | AG1: q32_4 | AH1: q32_5 | AI1: q32_6 | AJ1: q3ROW2_hidden | AK1: q33_1 | AL1: q33_2 | AM1: q33_3 | AN1: q33_4 | AO1: q33_5 | AP1: q33_6 | AQ1: q3ROW3_hidden | AR1: q34_1 | AS1: q34_2 | AT1: q34_3 | AU1: q34_4 | AV1: q34_5 | AW1: q34_6 | AX1: q3ROW4_hidden | AY1: q35_1 | AZ1: q35_2 | BA1: q35_3 | BB1: q35_4 | BC1: q35_5 | BD1: q35_6 | BE1: q3ROW5_hidden | BF1: q36_1 | BG1: q36_2 | BH1: q36_3 | BI1: q36_4 | BJ1: q36_5 | BK1: q36_6 | BL1: q3ROW6_hidden | BM1: q3COL1_hidden | BN1: q3COL2_hidden | BO1: q3COL3_hidden | BP1: q3COL4_hidden | BQ1: q3COL5_hidden | BR1: q3COL6_hidden | BS1: q3GRANDTotal_hidden | BT1: ShowEurope | BU1: ShowAsia | BV1: ShowNA | BW1: ShowGlobal | BX1: ShowSA | BY1: ShowAfrica | BZ1: q41_1 | CA1: q41_2 | CB1: q41_3 | CC1: q41_4 | CD1: q41_5 | CE1: q41_6 | CF1: q4ROW1_hidden | CG1: q42_1 | CH1: q42_2 | CI1: q42_3 | CJ1: q42_4 | CK1: q42_5 | CL1: q42_6 | CM1: q4ROW2_hidden | CN1: q43_1 | CO1: q43_2 | CP1: q43_3 | CQ1: q43_4 | CR1: q43_5 | CS1: q43_6 | CT1: q4ROW3_hidden | CU1: q44_1 | CV1: q44_2 | CW1: q44_3 | CX1: q44_4 | CY1: q44_5 | CZ1: q44_6 | DA1: q4ROW4_hidden | DB1: q45_1 | DC1: q45_2 | DD1: q45_3 | DE1: q45_4 | DF1: q45_5 | DG1: q45_6 | DH1: q4ROW5_hidden | DI1: q46_1 | DJ1: q46_2 | DK1: q46_3 | DL1: q46_4 | DM1: q46_5 | DN1: q46_6 | DO1: q4ROW6_hidden | DP1: q4COL1_hidden | DQ1: q4COL2_hidden | DR1: q4COL3_hidden | DS1: q4COL4_hidden | DT1: q4COL5_hidden | DU1: q4COL6_hidden | DV1: q4GRANDTotal_hidden | DW1: Alert41_1 | DX1: Alert41_2 | DY1: Alert41_3 | DZ1: Alert41_4 | EA1: Alert41_5 | EB1: Alert41_6 | EC1: Alert42_1 | ED1: Alert42_2 | EE1: Alert42_3 | EF1: Alert42_4 | EG1: Alert42_5 | EH1: Alert42_6 | EI1: Alert43_1 | EJ1: Alert43_2 | EK1: Alert43_3 | EL1: Alert43_4 | EM1: Alert43_5 | EN1: Alert43_6 | EO1: Alert44_1 | EP1: Alert44_2 | EQ1: Alert44_3 | ER1: Alert44_4 | ES1: Alert44_5 | ET1: Alert44_6 | EU1: Alert45_1 | EV1: Alert45_2 | EW1: Alert45_3 | EX1: Alert45_4 | EY1: Alert45_5 | EZ1: Alert45_6 | FA1: Alert46_1 | FB1: Alert46_2 | FC1: Alert46_3 | FD1: Alert46_4 | FE1: Alert46_5 | FF1: Alert46_6 | FG1: q51_1 | FH1: q51_2 | FI1: q51_3 | FJ1: q51_4 | FK1: q51_5 | FL1: q51_6 | FM1: q5ROW1_hidden | FN1: q52_1 | FO1: q52_2 | FP1: q52_3 | FQ1: q52_4 | FR1: q52_5 | FS1: q52_6 | FT1: q5ROW2_hidden | FU1: q53_1 | FV1: q53_2 | FW1: q53_3 | FX1: q53_4 | FY1: q53_5 | FZ1: q53_6 | GA1: q5ROW3_hidden | GB1: q54_1 | GC1: q54_2 | GD1: q54_3 | GE1: q54_4 | GF1: q54_5 | GG1: q54_6 | GH1: q5ROW4_hidden | GI1: q55_1 | GJ1: q55_2 | GK1: q55_3 | GL1: q55_4 | GM1: q55_5 | GN1: q55_6 | GO1: q5ROW5_hidden | GP1: q56_1 | GQ1: q56_2 | GR1: q56_3 | GS1: q56_4 | GT1: q56_5 | GU1: q56_6 | GV1: q5ROW6_hidden | GW1: q57_1 | GX1: q57_2 | GY1: q57_3 | GZ1: q57_4 | HA1: q57_5 | HB1: q57_6 | HC1: q5ROW7_hidden | HD1: q5other | HE1: q58_1 | HF1: q58_2 | HG1: q58_3 | HH1: q58_4 | HI1: q58_5 | HJ1: q58_6 | HK1: q5ROW8_hidden | HL1: q5COL1_hidden | HM1: q5COL2_hidden | HN1: q5COL3_hidden | HO1: q5COL4_hidden | HP1: q5COL5_hidden | HQ1: q5COL6_hidden | HR1: q5GRANDTotal_hidden | HS1: q61_1 | HT1: q61_2 | HU1: q61_3 | HV1: q61_4 | HW1: q61_5 | HX1: q61_6 | HY1: q6ROW1_hidden | HZ1: q62_1 | IA1: q62_2 | IB1: q62_3 | IC1: q62_4 | ID1: q62_5 | IE1: q62_6 | IF1: q6ROW2_hidden | IG1: q63_1 | IH1: q63_2 | II1: q63_3 | IJ1: q63_4 | IK1: q63_5 | IL1: q63_6 | IM1: q6ROW3_hidden | IN1: q64_1 | IO1: q64_2 | IP1: q64_3 | IQ1: q64_4 | IR1: q64_5 | IS1: q64_6 | IT1: q6ROW4_hidden | IU1: q65_1 | IV1: q65_2 | IW1: q65_3 | IX1: q65_4 | IY1: q65_5 | IZ1: q65_6 | JA1: q6ROW5_hidden | JB1: q6COL1_hidden | JC1: q6COL2_hidden | JD1: q6COL3_hidden | JE1: q6COL4_hidden | JF1: q6COL5_hidden | JG1: q6COL6_hidden | JH1: q6GRANDTotal_hidden | JI1: q7_1 | JJ1: q7_2 | JK1: q7_3 | JL1: q7other | JM1: q7_4 | JN1: q81_1 | JO1: q81_2 | JP1: q81_3 | JQ1: q81_4 | JR1: q81_5 | JS1: q81_6 | JT1: q8ROW1_hidden | JU1: q82_1 | JV1: q82_2 | JW1: q82_3 | JX1: q82_4 | JY1: q82_5 | JZ1: q82_6 | KA1: q8ROW2_hidden | KB1: q83_1 | KC1: q83_2 | KD1: q83_3 | KE1: q83_4 | KF1: q83_5 | KG1: q83_6 | KH1: q8ROW3_hidden | KI1: q84_1 | KJ1: q84_2 | KK1: q84_3 | KL1: q84_4 | KM1: q84_5 | KN1: q84_6 | KO1: q8ROW4_hidden | KP1: q85_1 | KQ1: q85_2 | KR1: q85_3 | KS1: q85_4 | KT1: q85_5 | KU1: q85_6 | KV1: q8ROW5_hidden | KW1: q86_1 | KX1: q86_2 | KY1: q86_3 | KZ1: q86_4 | LA1: q86_5 | LB1: q86_6 | LC1: q8ROW6_hidden | LD1: q87_1 | LE1: q87_2 | LF1: q87_3 | LG1: q87_4 | LH1: q87_5 | LI1: q87_6 | LJ1: q8ROW7_hidden | LK1: q8other | LL1: q88_1 | LM1: q88_2 | LN1: q88_3 | LO1: q88_4 | LP1: q88_5 | LQ1: q88_6 | LR1: q8ROW8_hidden | LS1: q8COL1_hidden | LT1: q8COL2_hidden | LU1: q8COL3_hidden | LV1: q8COL4_hidden | LW1: q8COL5_hidden | LX1: q8COL6_hidden | LY1: q8GRANDTotal_hidden | LZ1: q91_1 | MA1: q91_2 | MB1: q91_3 | MC1: q91_4 | MD1: q91_5 | ME1: q91_6 | MF1: q9ROW1_hidden | MG1: q92_1 | MH1: q92_2 | MI1: q92_3 | MJ1: q92_4 | MK1: q92_5 | ML1: q92_6 | MM1: q9ROW2_hidden | MN1: q93_1 | MO1: q93_2 | MP1: q93_3 | MQ1: q93_4 | MR1: q93_5 | MS1: q93_6 | MT1: q9ROW3_hidden | MU1: q94_1 | MV1: q94_2 | MW1: q94_3 | MX1: q94_4 | MY1: q94_5 | MZ1: q94_6 | NA1: q9ROW4_hidden | NB1: q95_1 | NC1: q95_2 | ND1: q95_3 | NE1: q95_4 | NF1: q95_5 | NG1: q95_6 | NH1: q9ROW5_hidden | NI1: q96_1 | NJ1: q96_2 | NK1: q96_3 | NL1: q96_4 | NM1: q96_5 | NN1: q96_6 | NO1: q9ROW6_hidden | NP1: q97_1 | NQ1: q97_2 | NR1: q97_3 | NS1: q97_4 | NT1: q97_5 | NU1: q97_6 | NV1: q9ROW7_hidden | NW1: q9other | NX1: q98_1 | NY1: q98_2 | NZ1: q98_3 | OA1: q98_4 | OB1: q98_5 | OC1: q98_6 | OD1: q9ROW8_hidden | OE1: q9COL1_hidden | OF1: q9COL2_hidden | OG1: q9COL3_hidden | OH1: q9COL4_hidden | OI1: q9COL5_hidden | OJ1: q9COL6_hidden | OK1: q9GRANDTotal_hidden | OL1: q101_1 | OM1: q101_2 | ON1: q101_3 | OO1: q101_4 | OP1: q101_5 | OQ1: q101_6 | OR1: q10ROW1_hidden | OS1: q102_1 | OT1: q102_2 | OU1: q102_3 | OV1: q102_4 | OW1: q102_5 | OX1: q102_6 | OY1: q10ROW2_hidden | OZ1: q103_1 | PA1: q103_2 | PB1: q103_3 | PC1: q103_4 | PD1: q103_5 | PE1: q103_6 | PF1: q10ROW3_hidden | PG1: q104_1 | PH1: q104_2 | PI1: q104_3 | PJ1: q104_4 | PK1: q104_5 | PL1: q104_6 | PM1: q10ROW4_hidden | PN1: q105_1 | PO1: q105_2 | PP1: q105_3 | PQ1: q105_4 | PR1: q105_5 | PS1: q105_6 | PT1: q10ROW5_hidden | PU1: q106_1 | PV1: q106_2 | PW1: q106_3 | PX1: q106_4 | PY1: q106_5 | PZ1: q106_6 | QA1: q10ROW6_hidden | QB1: q107_1 | QC1: q107_2 | QD1: q107_3 | QE1: q107_4 | QF1: q107_5 | QG1: q107_6 | QH1: q10ROW7_hidden | QI1: q10other | QJ1: q108_1 | QK1: q108_2 | QL1: q108_3 | QM1: q108_4 | QN1: q108_5 | QO1: q108_6 | QP1: q10ROW8_hidden | QQ1: q10COL1_hidden | QR1: q10COL2_hidden | QS1: q10COL3_hidden | QT1: q10COL4_hidden | QU1: q10COL5_hidden | QV1: q10COL6_hidden | QW1: q10GRANDTotal_hidden | QX1: q111_1 | QY1: q111_2 | QZ1: q111_3 | RA1: q111_4 | RB1: q111_5 | RC1: q111_6 | RD1: q11ROW1_hidden | RE1: q112_1 | RF1: q112_2 | RG1: q112_3 | RH1: q112_4 | RI1: q112_5 | RJ1: q112_6 | RK1: q11ROW2_hidden | RL1: q113_1 | RM1: q113_2 | RN1: q113_3 | RO1: q113_4 | RP1: q113_5 | RQ1: q113_6 | RR1: q11ROW3_hidden | RS1: q114_1 | RT1: q114_2 | RU1: q114_3 | RV1: q114_4 | RW1: q114_5 | RX1: q114_6 | RY1: q11ROW4_hidden | RZ1: q115_1 | SA1: q115_2 | SB1: q115_3 | SC1: q115_4 | SD1: q115_5 | SE1: q115_6 | SF1: q11ROW5_hidden | SG1: q116_1 | SH1: q116_2 | SI1: q116_3 | SJ1: q116_4 | SK1: q116_5 | SL1: q116_6 | SM1: q11ROW6_hidden | SN1: q117_1 | SO1: q117_2 | SP1: q117_3 | SQ1: q117_4 | SR1: q117_5 | SS1: q117_6 | ST1: q11ROW7_hidden | SU1: q11other | SV1: q118_1 | SW1: q118_2 | SX1: q118_3 | SY1: q118_4 | SZ1: q118_5 | TA1: q118_6 | TB1: q11ROW8_hidden | TC1: q11COL1_hidden | TD1: q11COL2_hidden | TE1: q11COL3_hidden | TF1: q11COL4_hidden | TG1: q11COL5_hidden | TH1: q11COL6_hidden | TI1: q11GRANDTotal_hidden | TJ1: q121_1 | TK1: q121_2 | TL1: q121_3 | TM1: q121_4 | TN1: q121_5 | TO1: q121_6 | TP1: q12ROW1_hidden | TQ1: q122_1 | TR1: q122_2 | TS1: q122_3 | TT1: q122_4 | TU1: q122_5 | TV1: q122_6 | TW1: q12ROW2_hidden | TX1: q123_1 | TY1: q123_2 | TZ1: q123_3 | UA1: q123_4 | UB1: q123_5 | UC1: q123_6 | UD1: q12ROW3_hidden | UE1: q124_1 | UF1: q124_2 | UG1: q124_3 | UH1: q124_4 | UI1: q124_5 | UJ1: q124_6 | UK1: q12ROW4_hidden | UL1: q125_1 | UM1: q125_2 | UN1: q125_3 | UO1: q125_4 | UP1: q125_5 | UQ1: q125_6 | UR1: q12ROW5_hidden | US1: q126_1 | UT1: q126_2 | UU1: q126_3 | UV1: q126_4 | UW1: q126_5 | UX1: q126_6 | UY1: q12ROW6_hidden | UZ1: q127_1 | VA1: q127_2 | VB1: q127_3 | VC1: q127_4 | VD1: q127_5 | VE1: q127_6 | VF1: q12ROW7_hidden | VG1: q12other | VH1: q128_1 | VI1: q128_2 | VJ1: q128_3 | VK1: q128_4 | VL1: q128_5 | VM1: q128_6 | VN1: q12ROW8_hidden | VO1: q12COL1_hidden | VP1: q12COL2_hidden | VQ1: q12COL3_hidden | VR1: q12COL4_hidden | VS1: q12COL5_hidden | VT1: q12COL6_hidden | VU1: q12GRANDTotal_hidden | VV1: q131_1 | VW1: q131_2 | VX1: q131_3 | VY1: q131_4 | VZ1: q131_5 | WA1: q131_6 | WB1: q13ROW1_hidden | WC1: q132_1 | WD1: q132_2 | WE1: q132_3 | WF1: q132_4 | WG1: q132_5 | WH1: q132_6 | WI1: q13ROW2_hidden | WJ1: q133_1 | WK1: q133_2 | WL1: q133_3 | WM1: q133_4 | WN1: q133_5 | WO1: q133_6 | WP1: q13ROW3_hidden | WQ1: q134_1 | WR1: q134_2 | WS1: q134_3 | WT1: q134_4 | WU1: q134_5 | WV1: q134_6 | WW1: q13ROW4_hidden | WX1: q135_1 | WY1: q135_2 | WZ1: q135_3 | XA1: q135_4 | XB1: q135_5 | XC1: q135_6 | XD1: q13ROW5_hidden | XE1: q136_1 | XF1: q136_2 | XG1: q136_3 | XH1: q136_4 | XI1: q136_5 | XJ1: q136_6 | XK1: q13ROW6_hidden | XL1: q137_1 | XM1: q137_2 | XN1: q137_3 | XO1: q137_4 | XP1: q137_5 | XQ1: q137_6 | XR1: q13ROW7_hidden | XS1: q13other | XT1: q138_1 | XU1: q138_2 | XV1: q138_3 | XW1: q138_4 | XX1: q138_5 | XY1: q138_6 | XZ1: q13ROW8_hidden | YA1: q13COL1_hidden | YB1: q13COL2_hidden | YC1: q13COL3_hidden | YD1: q13COL4_hidden | YE1: q13COL5_hidden | YF1: q13COL6_hidden | YG1: q13GRANDTotal_hidden | YH1: q14 | YI1: q15 | YJ1: q16 | YK1: UserAgent | YL1: RecordNo1 | YM1: Surveycode1 | YN1: Association | YO1: Company | YP1: FullName | YQ1: EmailAddress | YR1: SampleNote | YS1: SurveyURL
A2: 23 | B2: NVWCK043 | C2: survey=NVWCK043 | D2: 42411.442 | E2: 42411.446 | F2: 14 | G2: 1|2|3|4|5|6|7|8|9|15| | I2: 205.201.132.14 | J2: INREV | K2: Harry Humble | L2: Hunter REIM | M2: =VLOOKUP(MID(O2,SEARCH("@",O2,1),LEN(O2)-SEARCH("@",O2,1)+1),[1]Sheet1!$D:$F,3,FALSE) -> M588 | N2: Director | O2: hhumble@hunterreim.com | P2: 7791109339 | Q2: United Kingdom | R2: GBP | T2: 1 | W2: 66 | X2: 40 | AC2: 106 | AJ2: 0 | AQ2: 0 | AX2: 0 | BE2: 0 | BL2: 0 | BM2: 66 | BN2: 40 | BO2: 0 | BP2: 0 | BQ2: 0 | BR2: 0 | BS2: 106 | BT2: TRUE | BU2: FALSE | BV2: FALSE | BW2: FALSE | BX2: FALSE | BY2: FALSE | BZ2: 1 | CA2: 1 | CF2: 2 | CM2: 0 | CT2: 0 | DA2: 0 | DH2: 0 | DO2: 0 | DP2: 1 | DQ2: 1 | DR2: 0 | DS2: 0 | DT2: 0 | DU2: 0 | DV2: 2 | DW2: YES | DX2: YES | DY2: NO | DZ2: NO | EA2: NO | EB2: NO | EC2: NO | ED2: NO | EE2: NO | EF2: NO | EG2: NO | EH2: NO | EI2: NO | EJ2: NO | EK2: NO | EL2: NO | EM2: NO | EN2: NO | EO2: NO | EP2: NO | EQ2: NO | ER2: NO | ES2: NO | ET2: NO | EU2: NO | EV2: NO | EW2: NO | EX2: NO | EY2: NO | EZ2: NO | FA2: NO | FB2: NO | FC2: NO | FD2: NO | FE2: NO | FF2: NO | FG2: 66 | FM2: 66 | FT2: 0 | FV2: 40 | GA2: 40 | GH2: 0 | GO2: 0 | GV2: 0 | HC2: 0 | HK2: 0 | HL2: 66 | HM2: 40 | HN2: 0 | HO2: 0 | HP2: 0 | HQ2: 0 | HR2: 106 | HS2: 66 | HY2: 66 | IF2: 0 | IH2: 40 | IM2: 40 | IT2: 0 | JA2: 0 | JB2: 66 | JC2: 40 | JD2: 0 | JE2: 0 | JF2: 0 | JG2: 0 | JH2: 106 | JK2: 100 | JN2: 66 | JT2: 66 | KA2: 0 | KC2: 40 | KH2: 40 | KO2: 0 | KV2: 0 | LC2: 0 | LJ2: 0 | LR2: 0 | LS2: 66 | LT2: 40 | LU2: 0 | LV2: 0 | LW2: 0 | LX2: 0 | LY2: 106 | OK2: 0 | QW2: 0 | TI2: 0 | VU2: 0 | YG2: 0 | YH2: 1 | YI2: 3 | YJ2: 1 | YL2: 175 | YM2: NVWCK043 | YN2: INREV | YO2: Hunter Peoperty Fund Management | YP2: Harry Humble | YQ2: hhumble@hpfm.co.uk | YS2: http://click.surveylab.co.uk/anrev-inrev-ncreif-capital-raising-2016/?survey=NVWCK043
A3: 24 | B3: NVCRW472 | C3: survey=NVCRW472 | D3: 42415.641 | E3: 42415.641 | F3: 14 | G3: 1|2|3|2|3|2|3|2|2|3|15| | I3: 89.191.216.221 | J3: INREV | K3: Robin Hubbard | L3: InfraRed Capital Partners | M3: M665 | N3: Director, Business Development | O3: robin.hubbard@ircp.com | P3: 2074841855 | Q3: United Kingdom | R3: GBP | T3: 2 | AC3: 0 | AJ3: 0 | AQ3: 0 | AX3: 0 | BE3: 0 | BL3: 0 | BM3: 0 | BN3: 0 | BO3: 0 | BP3: 0 | BQ3: 0 | BR3: 0 | BS3: 0 | BT3: FALSE | BU3: FALSE | BV3: FALSE | BW3: FALSE | BX3: FALSE | BY3: FALSE | CF3: 0 | CM3: 0 | CT3: 0 | DA3: 0 | DH3: 0 | DO3: 0 | DP3: 0 | DQ3: 0 | DR3: 0 | DS3: 0 | DT3: 0 | DU3: 0 | DV3: 0 | DW3: NO | DX3: NO | DY3: NO | DZ3: NO | EA3: NO | EB3: NO | EC3: NO | ED3: NO | EE3: NO | EF3: NO | EG3: NO | EH3: NO | EI3: NO | EJ3: NO | EK3: NO | EL3: NO | EM3: NO | EN3: NO | EO3: NO | EP3: NO | EQ3: NO | ER3: NO | ES3: NO | ET3: NO | EU3: NO | EV3: NO | EW3: NO | EX3: NO | EY3: NO | EZ3: NO | FA3: NO | FB3: NO | FC3: NO | FD3: NO | FE3: NO | FF3: NO | FM3: 0 | FT3: 0 | GA3: 0 | GH3: 0 | GO3: 0 | GV3: 0 | HC3: 0 | HK3: 0 | HL3: 0 | HM3: 0 | HN3: 0 | HO3: 0 | HP3: 0 | HQ3: 0 | HR3: 0 | HY3: 0 | IF3: 0 | IM3: 0 | IT3: 0 | JA3: 0 | JB3: 0 | JC3: 0 | JD3: 0 | JE3: 0 | JF3: 0 | JG3: 0 | JH3: 0 | JT3: 0 | KA3: 0 | KH3: 0 | KO3: 0 | KV3: 0 | LC3: 0 | LJ3: 0 | LR3: 0 | LS3: 0 | LT3: 0 | LU3: 0 | LV3: 0 | LW3: 0 | LX3: 0 | LY3: 0 | OK3: 0 | QW3: 0 | TI3: 0 | VU3: 0 | YG3: 0 | YH3: 1 | YI3: 2 | YJ3: 1 | YK3: Mozilla/5.0 (Windows NT 6.1; WOW64; Trident/7.0; rv:11.0) like Gecko | YL3: 186 | YM3: NVCRW472 | YN3: INREV | YO3: InfraRed Capital Partners Limited | YP3: Kasia Makarewicz | YQ3: kasia.makarewicz@ircp.com | YS3: http://click.surveylab.co.uk/anrev-inrev-ncreif-capital-raising-2016/?survey=NVCRW472
A4: 25 | B4: NVBVX437 | C4: survey=NVBVX437 | D4: 42416.428 | E4: 42416.427 | F4: 8 | G4: 1|2|2|2|2|2|2|2|3|4|5|6|7|8|6|7|8|3|2|3|4|2|3|4|5|3|4|5|4|5|6|7|8|2|3|4|5|6|7|8|9|6|7|8|9|6|7|8|9|2|3|4|5|6|7|8|9|15|2|3|4|5|6|7|8|9| | I4: 108.171.128.174 | J4: INREV | K4: Christopher Woodley | L4: Aberdeen Asset Management | M4: =VLOOKUP(MID(O4,SEARCH("@",O4,1),LEN(O4)-SEARCH("@",O4,1)+1),[1]Sheet1!$D:$F,3,FALSE) -> M675 | N4: Business Information Manager | O4: christopher.woodley@aberdeen-asset.com | P4: +44 20 7463 6739 | Q4: United Kingdom | R4: GBP | T4: 1 | W4: 90 | X4: 1733 | Y4: 0 | Z4: 0 | AA4: 0 | AB4: 0 | AC4: 1823 | AD4: 0 | AE4: 0 | AF4: 0 | AG4: 0 | AH4: 0 | AI4: 0 | AJ4: 0 | AK4: 0 | AL4: 0 | AM4: 0 | AN4: 0 | AO4: 0 | AP4: 0 | AQ4: 0 | AR4: 0 | AS4: 0 | AT4: 0 | AU4: 0 | AV4: 0 | AW4: 0 | AX4: 0 | AY4: 0 | AZ4: 0 | BA4: 0 | BB4: 0 | BC4: 0 | BD4: 0 | BE4: 0 | BF4: 0 | BG4: 0 | BH4: 0 | BI4: 0 | BJ4: 0 | BK4: 0 | BL4: 0 | BM4: 90 | BN4: 1733 | BO4: 0 | BP4: 0 | BQ4: 0 | BR4: 0 | BS4: 1823 | BT4: TRUE | BU4: FALSE | BV4: FALSE | BW4: FALSE | BX4: FALSE | BY4: FALSE | BZ4: 4 | CA4: 6 | CF4: 10 | CM4: 0 | CT4: 0 | DA4: 0 | DH4: 0 | DO4: 0 | DP4: 4 | DQ4: 6 | DR4: 0 | DS4: 0 | DT4: 0 | DU4: 0 | DV4: 10 | DW4: YES | DX4: YES | DY4: NO | DZ4: NO | EA4: NO | EB4: NO | EC4: NO | ED4: NO | EE4: NO | EF4: NO | EG4: NO | EH4: NO | EI4: NO | EJ4: NO | EK4: NO | EL4: NO | EM4: NO | EN4: NO | EO4: NO | EP4: NO | EQ4: NO | ER4: NO | ES4: NO | ET4: NO | EU4: NO | EV4: NO | EW4: NO | EX4: NO | EY4: NO | EZ4: NO | FA4: NO | FB4: NO | FC4: NO | FD4: NO | FE4: NO | FF4: NO | FG4: 45 | FH4: 1530 | FM4: 1575 | FN4: 6 | FO4: 0 | FT4: 6 | FU4: 0 | FV4: 0 | GA4: 0 | GB4: 2 | GC4: 203 | GH4: 205 | GI4: 0 | GJ4: 0 | GO4: 0 | GP4: 0 | GQ4: 0 | GV4: 0 | GW4: 0 | GX4: 0 | HC4: 0 | HD4: Other Corporate/Unknown | HE4: 37 | HF4: 0 | HK4: 37 | HL4: 90 | HM4: 1733 | HN4: 0 | HO4: 0 | HP4: 0 | HQ4: 0 | HR4: 1823 | HS4: 90 | HT4: 1660 | HY4: 1750 | HZ4: 0 | IA4: 0 | IF4: 0 | IG4: 0 | IH4: 73 | IM4: 73 | IN4: 0 | IO4: 0 | IT4: 0 | IU4: 0 | IV4: 0 | JA4: 0 | JB4: 90 | JC4: 1733 | JD4: 0 | JE4: 0 | JF4: 0 | JG4: 0 | JH4: 1823 | JI4: 0 | JJ4: 0 | JK4: 0 | JL4: Not available | JM4: 100 | JN4: 45 | JO4: 1530 | JT4: 1575 | JU4: 6 | JV4: 0 | KA4: 6 | KB4: 0 | KC4: 0 | KH4: 0 | KI4: 2 | KJ4: 203 | KO4: 205 | KP4: 0 | KQ4: 0 | KV4: 0 | KW4: 0 | KX4: 0 | LC4: 0 | LD4: 0 | LE4: 0 | LJ4: 0 | LK4: Other Corporate/Unknown | LL4: 37 | LM4: 0 | LR4: 37 | LS4: 90 | LT4: 1733 | LU4: 0 | LV4: 0 | LW4: 0 | LX4: 0 | LY4: 1823 | OK4: 0 | QW4: 0 | TI4: 0 | VU4: 0 | YG4: 0 | YH4: 1 | YI4: 2 | YJ4: 1 | YK4: Mozilla/5.0 (compatible; MSIE 9.0; Windows NT 6.0; WOW64; Trident/5.0; ) | YL4: 14 | YM4: NVBVX437 | YN4: INREV | YO4: Aberdeen Asset Management | YP4: Christopher Woodley | YQ4: christopher.woodley@aberdeen-asset.com | YS4: http://click.surveylab.co.uk/anrev-inrev-ncreif-capital-raising-2016/?survey=NVBVX437
A5: 26 | B5: NVXTH459 | C5: survey=NVXTH459 | D5: 42404.569 | E5: 42404.637 | F5: 14 | G5: 1|2|2|3|4|5|6|7|8|9|10|11|15| | I5: 85.115.52.201 | J5: INREV | K5: Charlie Manhoff | L5: Tishman Speyer | M5: =VLOOKUP(MID(O5,SEARCH("@",O5,1),LEN(O5)-SEARCH("@",O5,1)+1),[1]Sheet1!$D:$F,3,FALSE) -> M054 | N5: Associate, Equity Capital Markets | O5: cmanhoff@tishmanspeyer.com | P5: 212-588-8527 | Q5: United States | R5: USD | T5: 1 | W5: 196.96 | Z5: 273.42 | AC5: 470.38 | AG5: 9.15 | AJ5: 9.15 | AN5: 1301.72 | AQ5: 1301.72 | AX5: 0 | BE5: 0 | BL5: 0 | BM5: 196.96 | BN5: 0 | BO5: 0 | BP5: 1584.29 | BQ5: 0 | BR5: 0 | BS5: 1781.25 | BT5: TRUE | BU5: TRUE | BV5: TRUE | BW5: FALSE | BX5: FALSE | BY5: FALSE | BZ5: 2 | CC5: 2 | CF5: 4 | CJ5: 1 | CM5: 1 | CQ5: 8 | CT5: 8 | DA5: 0 | DH5: 0 | DO5: 0 | DP5: 2 | DQ5: 0 | DR5: 0 | DS5: 11 | DT5: 0 | DU5: 0 | DV5: 13 | DW5: YES | DX5: NO | DY5: NO | DZ5: YES | EA5: NO | EB5: NO | EC5: NO | ED5: NO | EE5: NO | EF5: YES | EG5: NO | EH5: NO | EI5: NO | EJ5: NO | EK5: NO | EL5: YES | EM5: NO | EN5: NO | EO5: NO | EP5: NO | EQ5: NO | ER5: NO | ES5: NO | ET5: NO | EU5: NO | EV5: NO | EW5: NO | EX5: NO | EY5: NO | EZ5: NO | FA5: NO | FB5: NO | FC5: NO | FD5: NO | FE5: NO | FF5: NO | FG5: 80.91 | FJ5: 730.22 | FM5: 811.13 | FQ5: 237.47 | FT5: 237.47 | FU5: 37.33 | FX5: 180.18 | GA5: 217.51 | GH5: 0 | GO5: 0 | GV5: 0 | GW5: 22.9 | HC5: 22.9 | HD5: Bank/Investment Manager/Corporate Investor | HE5: 55.81 | HH5: 436.43 | HK5: 492.24 | HL5: 196.95 | HM5: 0 | HN5: 0 | HO5: 1584.3 | HP5: 0 | HQ5: 0 | HR5: 1781.25 | HS5: 25.98 | HV5: 415.1 | HY5: 441.08 | HZ5: 84.55 | IC5: 1145.4 | IF5: 1229.95 | IG5: 68.88 | IJ5: 23.8 | IM5: 92.68 | IN5: 17.54 | IT5: 17.54 | JA5: 0 | JB5: 196.95 | JC5: 0 | JD5: 0 | JE5: 1584.3 | JF5: 0 | JG5: 0 | JH5: 1781.25 | JI5: 0 | JJ5: 0 | JK5: 100 | JN5: 80.91 | JQ5: 82.74 | JT5: 163.65 | JX5: 64.67 | KA5: 64.67 | KB5: 37.33 | KE5: 126.02 | KH5: 163.35 | KO5: 0 | KV5: 0 | LC5: 0 | LD5: 22.9 | LJ5: 22.9 | LK5: Bank/Investment Manager | LL5: 55.81 | LR5: 55.81 | LS5: 196.95 | LT5: 0 | LU5: 0 | LV5: 273.43 | LW5: 0 | LX5: 0 | LY5: 470.38 | MQ5: 9.15 | MT5: 9.15 | OH5: 9.15 | OK5: 9.15 | OO5: 647.49 | OR5: 647.49 | OV5: 172.8 | OY5: 172.8 | PC5: 45 | PF5: 45 | QI5: Corporate Investor/Local Developer | QM5: 436.43 | QP5: 436.43 | QT5: 1301.72 | QW5: 1301.72 | TI5: 0 | VU5: 0 | YG5: 0 | YH5: 1 | YI5: 1 | YJ5: 1 | YK5: Mozilla/5.0 (Windows NT 6.1; WOW64; Trident/7.0; rv:11.0) like Gecko | YL5: 338 | YM5: NVXTH459 | YN5: INREV | YO5: Tishman Speyer | YP5: Michael Spies | YQ5: mspies@tishmanspeyer.com | YS5: http://click.surveylab.co.uk/anrev-inrev-ncreif-capital-raising-2016/?survey=NVXTH459
A6: 27 | B6: NVVJT621 | C6: survey=NVVJT621 | D6: 42416.415 | E6: 42416.418 | F6: 14 | G6: 1|2|2|3|4|5|6|7|8|9|15| | I6: 38.105.189.5 | J6: INREV | K6: Danielle Apstolatos | L6: Bluehouse Capital | M6: =VLOOKUP(MID(O6,SEARCH("@",O6,1),LEN(O6)-SEARCH("@",O6,1)+1),[1]Sheet1!$D:$F,3,FALSE) -> M158 | N6: Director Investor Relations | O6: dapostolatos@bluehousecapital.com | P6: 302103628900 | Q6: Greece | R6: EUR | T6: 1 | W6: 50 | AC6: 50 | AJ6: 0 | AQ6: 0 | AX6: 0 | BE6: 0 | BL6: 0 | BM6: 50 | BN6: 0 | BO6: 0 | BP6: 0 | BQ6: 0 | BR6: 0 | BS6: 50 | BT6: TRUE | BU6: FALSE | BV6: FALSE | BW6: FALSE | BX6: FALSE | BY6: FALSE | BZ6: 1 | CF6: 1 | CM6: 0 | CT6: 0 | DA6: 0 | DH6: 0 | DO6: 0 | DP6: 1 | DQ6: 0 | DR6: 0 | DS6: 0 | DT6: 0 | DU6: 0 | DV6: 1 | DW6: YES | DX6: NO | DY6: NO | DZ6: NO | EA6: NO | EB6: NO | EC6: NO | ED6: NO | EE6: NO | EF6: NO | EG6: NO | EH6: NO | EI6: NO | EJ6: NO | EK6: NO | EL6: NO | EM6: NO | EN6: NO | EO6: NO | EP6: NO | EQ6: NO | ER6: NO | ES6: NO | ET6: NO | EU6: NO | EV6: NO | EW6: NO | EX6: NO | EY6: NO | EZ6: NO | FA6: NO | FB6: NO | FC6: NO | FD6: NO | FE6: NO | FF6: NO | FG6: 30 | FM6: 30 | FT6: 0 | GA6: 0 | GH6: 0 | GI6: 10 | GO6: 10 | GV6: 0 | GW6: 10 | HC6: 10 | HK6: 0 | HL6: 50 | HM6: 0 | HN6: 0 | HO6: 0 | HP6: 0 | HQ6: 0 | HR6: 50 | HS6: 10 | HY6: 10 | IF6: 0 | IG6: 40 | IM6: 40 | IT6: 0 | JA6: 0 | JB6: 50 | JC6: 0 | JD6: 0 | JE6: 0 | JF6: 0 | JG6: 0 | JH6: 50 | JI6: 0 | JK6: 100 | JN6: 30 | JT6: 30 | KA6: 0 | KH6: 0 | KO6: 0 | KP6: 10 | KV6: 10 | LC6: 0 | LD6: 10 | LJ6: 10 | LR6: 0 | LS6: 50 | LT6: 0 | LU6: 0 | LV6: 0 | LW6: 0 | LX6: 0 | LY6: 50 | OK6: 0 | QW6: 0 | TI6: 0 | VU6: 0 | YG6: 0 | YH6: 1 | YI6: 1 | YJ6: 1 | YK6: Mozilla/5.0 (Windows NT 6.1; WOW64) AppleWebKit/537.36 (KHTML, like Gecko) Chrome/47.0.2526.111 Safari/537.36 | YL6: 57 | YM6: NVVJT621 | YN6: INREV | YO6: Bluehouse Capital Advisors | YP6: Victor Pisante | YQ6: vpisante@bluehousecapital.com | YS6: http://click.surveylab.co.uk/anrev-inrev-ncreif-capital-raising-2016/?survey=NVVJT621
A7: 28 | B7: NVZLN199 | C7: survey=NVZLN199 | D7: 42398.409 | E7: 42398.435 | F7: 14 | G7: 1|2|2|3|4|5|6|7|8|9|15| | I7: 212.114.207.108 | J7: INREV | K7: Joni Sekula | L7: PATRIZIA Immobilien AG | M7: =VLOOKUP(MID(O7,SEARCH("@",O7,1),LEN(O7)-SEARCH("@",O7,1)+1),[1]Sheet1!$D:$F,3,FALSE) -> M180 | N7: Manager | O7: joni.sekula@patrizia.ag | P7: +49 821 50910731 | Q7: Germany | R7: EUR | T7: 1 | W7: 604.7 | X7: 790 | Z7: 62.45 | AC7: 1457.15 | AJ7: 0 | AQ7: 0 | AX7: 0 | BE7: 0 | BL7: 0 | BM7: 604.7 | BN7: 790 | BO7: 0 | BP7: 62.45 | BQ7: 0 | BR7: 0 | BS7: 1457.15 | BT7: TRUE | BU7: FALSE | BV7: FALSE | BW7: FALSE | BX7: FALSE | BY7: FALSE | BZ7: 10 | CA7: 5 | CC7: 2 | CF7: 17 | CM7: 0 | CT7: 0 | DA7: 0 | DH7: 0 | DO7: 0 | DP7: 10 | DQ7: 5 | DR7: 0 | DS7: 2 | DT7: 0 | DU7: 0 | DV7: 17 | DW7: YES | DX7: YES | DY7: NO | DZ7: YES | EA7: NO | EB7: NO | EC7: NO | ED7: NO | EE7: NO | EF7: NO | EG7: NO | EH7: NO | EI7: NO | EJ7: NO | EK7: NO | EL7: NO | EM7: NO | EN7: NO | EO7: NO | EP7: NO | EQ7: NO | ER7: NO | ES7: NO | ET7: NO | EU7: NO | EV7: NO | EW7: NO | EX7: NO | EY7: NO | EZ7: NO | FA7: NO | FB7: NO | FC7: NO | FD7: NO | FE7: NO | FF7: NO | FG7: 132 | FH7: 174 | FJ7: 44.95 | FM7: 350.95 | FN7: 15 | FO7: 466 | FT7: 481 | GA7: 0 | GH7: 0 | GO7: 0 | GV7: 0 | HC7: 0 | HD7: Mainly Sparkassen (savings banks) | HE7: 457.7 | HF7: 150 | HH7: 17.5 | HK7: 625.2 | HL7: 604.7 | HM7: 790 | HN7: 0 | HO7: 62.45 | HP7: 0 | HQ7: 0 | HR7: 1457.15 | HS7: 604.7 | HT7: 324 | HV7: 62.45 | HY7: 991.15 | IA7: 466 | IF7: 466 | IM7: 0 | IT7: 0 | JA7: 0 | JB7: 604.7 | JC7: 790 | JD7: 0 | JE7: 62.45 | JF7: 0 | JG7: 0 | JH7: 1457.15 | JI7: 0 | JJ7: 20 | JK7: 80 | JN7: 132 | JO7: 174 | JQ7: 44.95 | JT7: 350.95 | JU7: 15 | JV7: 466 | KA7: 481 | KH7: 0 | KO7: 0 | KV7: 0 | LC7: 0 | LG7: 17.5 | LJ7: 17.5 | LK7: Mainly Sparkassen (savings banks) | LL7: 457.7 | LM7: 150 | LR7: 607.7 | LS7: 604.7 | LT7: 790 | LU7: 0 | LV7: 62.45 | LW7: 0 | LX7: 0 | LY7: 1457.15 | OK7: 0 | QW7: 0 | TI7: 0 | VU7: 0 | YG7: 0 | YH7: 1 | YI7: 3 | YJ7: 1 | YK7: Mozilla/5.0 (Windows NT 6.1; WOW64; Trident/7.0; rv:11.0) like Gecko | YL7: 273 | YM7: NVZLN199 | YN7: INREV | YO7: PATRIZIA Immobilien AG | YP7: Joni Sekula | YQ7: joni.sekula@patrizia.ag | YS7: http://click.surveylab.co.uk/anrev-inrev-ncreif-capital-raising-2016/?survey=NVZLN199
A8: 29 | B8: NVAMM517 | C8: survey=NVAMM517 | D8: 42403.611 | F8: 1 | G8: 1|2|2| | I8: 205.201.132.14 | J8: INREV | M8: =VLOOKUP(MID(O8,SEARCH("@",O8,1),LEN(O8)-SEARCH("@",O8,1)+1),[1]Sheet1!$D:$F,3,FALSE) -> #VALUE! | YL8: 230 | YM8: NVAMM517 | YN8: INREV | YO8: Mayfair Capital | YP8: Simon Martindale | YQ8: smartindale@mayfaircapital.co.uk | YS8: http://click.surveylab.co.uk/anrev-inrev-ncreif-capital-raising-2016/?survey=NVAMM517
A9: 30 | B9: NVHTC024 | C9: survey=NVHTC024 | D9: 42409.31 | E9: 42409.356 | F9: 14 | G9: 1|2|3|4|3|4|5|6|7|8|9|15| | I9: 194.136.168.146 | J9: INREV | K9: Nerijus Zebrauskas | L9: Northern Horizon Capital | M9: =VLOOKUP(MID(O9,SEARCH("@",O9,1),LEN(O9)-SEARCH("@",O9,1)+1),[1]Sheet1!$D:$F,3,FALSE) -> M174 | N9: Head of Fund Controlling | O9: Nerijus.Zebrauskas@nh-cap.com | P9: 37052047122 | Q9: Denmark | R9: EUR | T9: 1 | W9: 9.6 | X9: 60.2 | AC9: 69.8 | AJ9: 0 | AQ9: 0 | AX9: 0 | BE9: 0 | BL9: 0 | BM9: 9.6 | BN9: 60.2 | BO9: 0 | BP9: 0 | BQ9: 0 | BR9: 0 | BS9: 69.8 | BT9: TRUE | BU9: FALSE | BV9: FALSE | BW9: FALSE | BX9: FALSE | BY9: FALSE | BZ9: 2 | CA9: 2 | CF9: 4 | CM9: 0 | CT9: 0 | DA9: 0 | DH9: 0 | DO9: 0 | DP9: 2 | DQ9: 2 | DR9: 0 | DS9: 0 | DT9: 0 | DU9: 0 | DV9: 4 | DW9: YES | DX9: YES | DY9: NO | DZ9: NO | EA9: NO | EB9: NO | EC9: NO | ED9: NO | EE9: NO | EF9: NO | EG9: NO | EH9: NO | EI9: NO | EJ9: NO | EK9: NO | EL9: NO | EM9: NO | EN9: NO | EO9: NO | EP9: NO | EQ9: NO | ER9: NO | ES9: NO | ET9: NO | EU9: NO | EV9: NO | EW9: NO | EX9: NO | EY9: NO | EZ9: NO | FA9: NO | FB9: NO | FC9: NO | FD9: NO | FE9: NO | FF9: NO | FG9: 3 | FH9: 0.8 | FM9: 3.8 | FT9: 0 | GA9: 0 | GH9: 0 | GI9: 0.4 | GO9: 0.4 | GP9: 0.2 | GV9: 0.2 | GW9: 0.8 | HC9: 0.8 | HD9: Private companies / investment banks | HE9: 5.2 | HF9: 59.4 | HK9: 64.6 | HL9: 9.6 | HM9: 60.2 | HN9: 0 | HO9: 0 | HP9: 0 | HQ9: 0 | HR9: 69.8 | HS9: 9.6 | HT9: 60.2 | HY9: 69.8 | IF9: 0 | IM9: 0 | IT9: 0 | JA9: 0 | JB9: 9.6 | JC9: 60.2 | JD9: 0 | JE9: 0 | JF9: 0 | JG9: 0 | JH9: 69.8 | JK9: 100 | JN9: 3 | JO9: 0.8 | JT9: 3.8 | KA9: 0 | KH9: 0 | KO9: 0 | KP9: 0.4 | KV9: 0.4 | KW9: 0.2 | LC9: 0.2 | LD9: 0.8 | LJ9: 0.8 | LK9: Private companies, investment banks | LL9: 5.2 | LM9: 59.4 | LR9: 64.6 | LS9: 9.6 | LT9: 60.2 | LU9: 0 | LV9: 0 | LW9: 0 | LX9: 0 | LY9: 69.8 | OK9: 0 | QW9: 0 | TI9: 0 | VU9: 0 | YG9: 0 | YH9: 1 | YI9: 3 | YJ9: 1 | YK9: Mozilla/5.0 (Windows NT 6.1; WOW64; Trident/7.0; rv:11.0) like Gecko | YL9: 257 | YM9: NVHTC024 | YN9: INREV | YO9: Northern Horizon Capital | YP9: Nerijus Zebrauskas | YQ9: nerijus.zebrauskas@nh-cap.com | YS9: http://click.surveylab.co.uk/anrev-inrev-ncreif-capital-raising-2016/?survey=NVHTC024
A10: 31 | B10: NVBDJ636 | C10: survey=NVBDJ636 | D10: 42423.635 | E10: 42423.639 | F10: 14 | G10: 1|2|3|4|5|6|7|8|2|3|4|2|3|2|3|4|5|2|3|4|5|6|7|8|9|11|12|6|7|8|9|11|12|8|6|6|7|8|9|11|12|15|2|3|4|5|4|5|6|7|8|9|11|12|4|5|6|4|5|6|7|8|9|11|12|15| | I10: 108.179.24.66 | J10: INREV | K10: Amy Dulski | L10: Starwood Capital Group | M10: =VLOOKUP(MID(O10,SEARCH("@",O10,1),LEN(O10)-SEARCH("@",O10,1)+1),[1]Sheet1!$D:$F,3,FALSE) -> M05105 | N10: Investor Relations Coordinator | O10: adulski@starwood.com | P10: 2034227766 | Q10: United States | R10: USD | T10: 1 | Z10: 116.2 | AC10: 116.2 | AJ10: 0 | AN10: 240 | AQ10: 240 | AR10: 1327.7 | AX10: 1327.7 | BE10: 0 | BL10: 0 | BM10: 1327.7 | BN10: 0 | BO10: 0 | BP10: 356.2 | BQ10: 0 | BR10: 0 | BS10: 1683.9 | BT10: TRUE | BU10: FALSE | BV10: TRUE | BW10: TRUE | BX10: FALSE | BY10: FALSE | CC10: 1 | CF10: 1 | CM10: 0 | CQ10: 1 | CT10: 1 | CU10: 1 | DA10: 1 | DH10: 0 | DO10: 0 | DP10: 1 | DQ10: 0 | DR10: 0 | DS10: 2 | DT10: 0 | DU10: 0 | DV10: 3 | DW10: NO | DX10: NO | DY10: NO | DZ10: YES | EA10: NO | EB10: NO | EC10: NO | ED10: NO | EE10: NO | EF10: NO | EG10: NO | EH10: NO | EI10: NO | EJ10: NO | EK10: NO | EL10: YES | EM10: NO | EN10: NO | EO10: YES | EP10: NO | EQ10: NO | ER10: NO | ES10: NO | ET10: NO | EU10: NO | EV10: NO | EW10: NO | EX10: NO | EY10: NO | EZ10: NO | FA10: NO | FB10: NO | FC10: NO | FD10: NO | FE10: NO | FF10: NO | FG10: 390 | FJ10: 135 | FM10: 525 | FN10: 25 | FQ10: 0 | FT10: 25 | FU10: 545 | FX10: 210 | GA10: 755 | GB10: 0 | GE10: 0 | GH10: 0 | GI10: 226 | GL10: 0 | GO10: 226 | GP10: 28 | GS10: 5 | GV10: 33 | GW10: 109.74 | GZ10: 2.54 | HC10: 112.28 | HD10: General Partner | HE10: 3.955 | HH10: 3.662 | HK10: 7.62 | HL10: 1327.69 | HM10: 0 | HN10: 0 | HO10: 356.2 | HP10: 0 | HQ10: 0 | HR10: 1683.9 | HS10: 12.1 | HY10: 12.1 | HZ10: 950 | IC10: 230 | IF10: 1180 | IG10: 365.605 | IJ10: 126.2 | IM10: 491.81 | IT10: 0 | JA10: 0 | JB10: 1327.7 | JC10: 0 | JD10: 0 | JE10: 356.2 | JF10: 0 | JG10: 0 | JH10: 1683.9 | JI10: 19 | JJ10: 0 | JK10: 81 | JQ10: 35 | JT10: 35 | KA10: 0 | KE10: 80 | KH10: 80 | KO10: 0 | KV10: 0 | LC10: 0 | LJ10: 0 | LK10: General Partner | LO10: 1.16 | LR10: 1.16 | LS10: 0 | LT10: 0 | LU10: 0 | LV10: 116.16 | LW10: 0 | LX10: 0 | LY10: 116.16 | OK10: 0 | OO10: 100 | PC10: 130 | PX10: 5 | QE10: 2.5 | QI10: General Partner | QM10: 2.5 | QW10: 240 | QX10: 390 | RE10: 25 | RL10: 545 | RZ10: 226 | SG10: 28 | SN10: 109.75 | SU10: General Partner | SV10: 3.955 | TI10: 1327.7 | VU10: 0 | YG10: 0 | YH10: 2 | YI10: 3 | YJ10: 1 | YK10: Mozilla/5.0 (Windows NT 6.1; WOW64) AppleWebKit/537.36 (KHTML, like Gecko) Chrome/48.0.2564.82 Safari/537.36 | YL10: 323 | YM10: NVBDJ636 | YN10: INREV | YO10: Starwood Capital Group | YP10: Renee Crabtree | YQ10: rcrabtree@starwood.com | YS10: http://click.surveylab.co.uk/anrev-inrev-ncreif-capital-raising-2016/?survey=NVBDJ636
A11: 32 | B11: NVGTY873 | C11: survey=NVGTY873 | D11: 42422.675 | E11: 42422.702 | F11: 14 | G11: 1|2|2|2|2|3|2|3|4|5|6|7|8|15|2|3|4|5|3|4|5|6|5|5|2|3|4|5|4|5|4|5|6|4|3|4|5|6|6|7|8|6|7|8|6|7|8|9|7|7|8|6|7|8|9|6|7|8|9|3|4|5|6|7|8|9|3|4|2|2|3|4|5|6|7|8|9|2|3|3|4|5|6|7|8|6|7|8|9|3|4|5|6|7|8|9|15| | I11: 194.145.239.250 | J11: INREV | K11: Jan Kuhn | L11: TRIUVA Kapitalverwaltungsgesellschaft mbH | M11: =VLOOKUP(MID(O11,SEARCH("@",O11,1),LEN(O11)-SEARCH("@",O11,1)+1),[1]Sheet1!$D:$F,3,FALSE) -> M180 | N11: Head of Investor Relations | O11: jan.kuhn@triuva.com | P11: +49 69 643505–1291 | Q11: Germany | R11: EUR | T11: 1 | X11: 556 | AC11: 556 | AJ11: 0 | AQ11: 0 | AX11: 0 | BE11: 0 | BL11: 0 | BM11: 0 | BN11: 556 | BO11: 0 | BP11: 0 | BQ11: 0 | BR11: 0 | BS11: 556 | BT11: TRUE | BU11: FALSE | BV11: FALSE | BW11: FALSE | BX11: FALSE | BY11: FALSE | CA11: 7 | CF11: 7 | CM11: 0 | CT11: 0 | DA11: 0 | DH11: 0 | DO11: 0 | DP11: 0 | DQ11: 7 | DR11: 0 | DS11: 0 | DT11: 0 | DU11: 0 | DV11: 7 | DW11: NO | DX11: YES | DY11: NO | DZ11: NO | EA11: NO | EB11: NO | EC11: NO | ED11: NO | EE11: NO | EF11: NO | EG11: NO | EH11: NO | EI11: NO | EJ11: NO | EK11: NO | EL11: NO | EM11: NO | EN11: NO | EO11: NO | EP11: NO | EQ11: NO | ER11: NO | ES11: NO | ET11: NO | EU11: NO | EV11: NO | EW11: NO | EX11: NO | EY11: NO | EZ11: NO | FA11: NO | FB11: NO | FC11: NO | FD11: NO | FE11: NO | FF11: NO | FH11: 320 | FM11: 320 | FO11: 91 | FT11: 91 | GA11: 0 | GH11: 0 | GJ11: 145 | GO11: 145 | GV11: 0 | HC11: 0 | HK11: 0 | HL11: 0 | HM11: 556 | HN11: 0 | HO11: 0 | HP11: 0 | HQ11: 0 | HR11: 556 | HT11: 556 | HY11: 556 | IF11: 0 | IM11: 0 | IT11: 0 | JA11: 0 | JB11: 0 | JC11: 556 | JD11: 0 | JE11: 0 | JF11: 0 | JG11: 0 | JH11: 556 | JK11: 100 | JO11: 320 | JT11: 320 | JV11: 91 | KA11: 91 | KH11: 0 | KO11: 0 | KQ11: 145 | KV11: 145 | LC11: 0 | LJ11: 0 | LR11: 0 | LS11: 0 | LT11: 556 | LU11: 0 | LV11: 0 | LW11: 0 | LX11: 0 | LY11: 556 | OK11: 0 | QW11: 0 | TI11: 0 | VU11: 0 | YG11: 0 | YH11: 1 | YI11: 3 | YJ11: 1 | YK11: Mozilla/5.0 (compatible; MSIE 10.0; Windows NT 6.1; WOW64; Trident/6.0) | YL11: 344 | YM11: NVGTY873 | YN11: INREV | YO11: TRIUVA Kapitalverwaltungsgesellschaft mbH | YP11: Steffen Ricken | YQ11: Steffen.Ricken@triuva.com | YS11: http://click.surveylab.co.uk/anrev-inrev-ncreif-capital-raising-2016/?survey=NVGTY873
A12: 33 | B12: NVPMH038 | C12: survey=NVPMH038 | D12: 42401.69 | F12: 1 | G12: 1|2| | I12: 82.109.51.130 | J12: INREV | M12: =VLOOKUP(MID(O12,SEARCH("@",O12,1),LEN(O12)-SEARCH("@",O12,1)+1),[1]Sheet1!$D:$F,3,FALSE) -> #VALUE! | YK12: Mozilla/5.0 (Windows NT 6.1; WOW64; Trident/7.0; rv:11.0) like Gecko | YL12: 58 | YM12: NVPMH038 | YN12: INREV | YO12: BMO Real Estate Partners | YP12: Sue Bjorkegren | YQ12: sbjorkegren@bmorep.com | YS12: http://click.surveylab.co.uk/anrev-inrev-ncreif-capital-raising-2016/?survey=NVPMH038
A13: 34 | B13: NVRNR667 | C13: survey=NVRNR667 | D13: 42396.626 | F13: 1 | G13: 1|2| | I13: 12.20.3.180 | J13: INREV | M13: =VLOOKUP(MID(O13,SEARCH("@",O13,1),LEN(O13)-SEARCH("@",O13,1)+1),[1]Sheet1!$D:$F,3,FALSE) -> #VALUE! | YK13: Mozilla/5.0 (Windows NT 6.1; WOW64) AppleWebKit/537.36 (KHTML, like Gecko) Chrome/47.0.2526.111 Safari/537.36 | YL13: 365 | YM13: NVRNR667 | YN13: INREV | YO13: zzzAdditional Record | YS13: http://click.surveylab.co.uk/anrev-inrev-ncreif-capital-raising-2016/?survey=NVRNR667
A14: 35 | B14: NVMQE634 | C14: survey=NVMQE634 | D14: 42403.326 | E14: 42403.329 | F14: 14 | G14: 1|2|3|4|5|6|7|8|9|15| | I14: 217.110.92.40 | J14: INREV | K14: Sina Stegmann | L14: Warburg-HIH Invest Real Estate GmbH | M14: =VLOOKUP(MID(O14,SEARCH("@",O14,1),LEN(O14)-SEARCH("@",O14,1)+1),[1]Sheet1!$D:$F,3,FALSE) -> M277 | N14: Senior Marketing Manager | O14: sstegmann@warburg-hih.com | P14: +49 40 3282 3618 | Q14: Germany | R14: EUR | T14: 1 | W14: 268 | X14: 215 | AC14: 483 | AJ14: 0 | AQ14: 0 | AX14: 0 | BE14: 0 | BL14: 0 | BM14: 268 | BN14: 215 | BO14: 0 | BP14: 0 | BQ14: 0 | BR14: 0 | BS14: 483 | BT14: TRUE | BU14: FALSE | BV14: FALSE | BW14: FALSE | BX14: FALSE | BY14: FALSE | BZ14: 4 | CA14: 5 | CF14: 9 | CM14: 0 | CT14: 0 | DA14: 0 | DH14: 0 | DO14: 0 | DP14: 4 | DQ14: 5 | DR14: 0 | DS14: 0 | DT14: 0 | DU14: 0 | DV14: 9 | DW14: YES | DX14: YES | DY14: NO | DZ14: NO | EA14: NO | EB14: NO | EC14: NO | ED14: NO | EE14: NO | EF14: NO | EG14: NO | EH14: NO | EI14: NO | EJ14: NO | EK14: NO | EL14: NO | EM14: NO | EN14: NO | EO14: NO | EP14: NO | EQ14: NO | ER14: NO | ES14: NO | ET14: NO | EU14: NO | EV14: NO | EW14: NO | EX14: NO | EY14: NO | EZ14: NO | FA14: NO | FB14: NO | FC14: NO | FD14: NO | FE14: NO | FF14: NO | FG14: 140 | FH14: 208 | FM14: 348 | FN14: 5 | FO14: 7.5 | FT14: 12.5 | GA14: 0 | GH14: 0 | GI14: 21 | GO14: 21 | GV14: 0 | HC14: 0 | HD14: Financial Institutions | HE14: 101.5 | HK14: 101.5 | HL14: 267.5 | HM14: 215.5 | HN14: 0 | HO14: 0 | HP14: 0 | HQ14: 0 | HR14: 483 | HS14: 268 | HT14: 215 | HY14: 483 | IF14: 0 | IM14: 0 | IT14: 0 | JA14: 0 | JB14: 268 | JC14: 215 | JD14: 0 | JE14: 0 | JF14: 0 | JG14: 0 | JH14: 483 | JK14: 100 | JN14: 140 | JO14: 208 | JT14: 348 | JU14: 5 | JV14: 7.5 | KA14: 12.5 | KH14: 0 | KO14: 0 | KP14: 21 | KV14: 21 | LC14: 0 | LJ14: 0 | LK14: Financial Institutions | LL14: 101.5 | LR14: 101.5 | LS14: 267.5 | LT14: 215.5 | LU14: 0 | LV14: 0 | LW14: 0 | LX14: 0 | LY14: 483 | OK14: 0 | QW14: 0 | TI14: 0 | VU14: 0 | YG14: 0 | YH14: 1 | YI14: 3 | YJ14: 1 | YK14: Mozilla/5.0 (Windows NT 6.1; WOW64; Trident/7.0; rv:11.0) like Gecko | YL14: 357 | YM14: NVMQE634 | YN14: INREV | YO14: Warburg - Henderson KAG | YP14: Sina Stegmann | YQ14: sstegmann@warburg-henderson.com | YS14: http://click.surveylab.co.uk/anrev-inrev-ncreif-capital-raising-2016/?survey=NVMQE634
A15: 36 | B15: NVEQN229 | C15: survey=NVEQN229 | D15: 42417.64 | E15: 42417.647 | F15: 14 | G15: 1|2|3|4|5|6|7|8|9|9|10|15| | I15: 193.104.25.125 | J15: INREV | K15: Naomi Vlakancic | L15: Savills Investment Management | M15: =VLOOKUP(MID(O15,SEARCH("@",O15,1),LEN(O15)-SEARCH("@",O15,1)+1),[1]Sheet1!$D:$F,3,FALSE) -> M079 | N15: Head of Investor Relations | O15: naomi.vlakancic@savillsim.com | P15: 44 20 7409 5927 | Q15: United Kingdom | R15: EUR | T15: 1 | W15: 515 | X15: 1060 | AC15: 1575 | AD15: 75 | AE15: 39 | AJ15: 114 | AQ15: 0 | AX15: 0 | BE15: 0 | BL15: 0 | BM15: 590 | BN15: 1099 | BO15: 0 | BP15: 0 | BQ15: 0 | BR15: 0 | BS15: 1689 | BT15: TRUE | BU15: TRUE | BV15: FALSE | BW15: FALSE | BX15: FALSE | BY15: FALSE | BZ15: 8 | CA15: 5 | CF15: 13 | CG15: 1 | CH15: 2 | CM15: 3 | CT15: 0 | DA15: 0 | DH15: 0 | DO15: 0 | DP15: 9 | DQ15: 7 | DR15: 0 | DS15: 0 | DT15: 0 | DU15: 0 | DV15: 16 | DW15: YES | DX15: YES | DY15: NO | DZ15: NO | EA15: NO | EB15: NO | EC15: YES | ED15: YES | EE15: NO | EF15: NO | EG15: NO | EH15: NO | EI15: NO | EJ15: NO | EK15: NO | EL15: NO | EM15: NO | EN15: NO | EO15: NO | EP15: NO | EQ15: NO | ER15: NO | ES15: NO | ET15: NO | EU15: NO | EV15: NO | EW15: NO | EX15: NO | EY15: NO | EZ15: NO | FA15: NO | FB15: NO | FC15: NO | FD15: NO | FE15: NO | FF15: NO | FG15: 25 | FH15: 728 | FM15: 753 | FN15: 263 | FT15: 263 | GA15: 0 | GH15: 0 | GI15: 173 | GO15: 173 | GV15: 0 | GW15: 42 | HC15: 42 | HD15: Wealth Mgt, Bank, Private Equity, Investment company | HE15: 87 | HF15: 371 | HK15: 458 | HL15: 590 | HM15: 1099 | HN15: 0 | HO15: 0 | HP15: 0 | HQ15: 0 | HR15: 1689 | HS15: 478 | HY15: 478 | HZ15: 113 | IA15: 728 | IF15: 841 | IH15: 371 | IM15: 371 | IT15: 0 | JA15: 0 | JB15: 591 | JC15: 1099 | JD15: 0 | JE15: 0 | JF15: 0 | JG15: 0 | JH15: 1690 | JI15: 1 | JK15: 99 | JN15: 25 | JO15: 728 | JT15: 753 | JU15: 263 | KA15: 263 | KH15: 0 | KO15: 0 | KP15: 173 | KV15: 173 | LC15: 0 | LD15: 2 | LJ15: 2 | LK15: Wealth Management, Bank, Private Equity, Investment Company | LL15: 52 | LM15: 332 | LR15: 384 | LS15: 515 | LT15: 1060 | LU15: 0 | LV15: 0 | LW15: 0 | LX15: 0 | LY15: 1575 | NP15: 75 | NV15: 75 | NW15: Investment Company | NY15: 39 | OD15: 39 | OE15: 75 | OF15: 39 | OK15: 114 | QW15: 0 | TI15: 0 | VU15: 0 | YG15: 0 | YH15: 3 | YI15: 2 | YJ15: 1 | YK15: Mozilla/5.0 (Windows NT 6.1; WOW64; Trident/7.0; rv:11.0) like Gecko | YL15: 93 | YM15: NVEQN229 | YN15: INREV | YO15: Cordea Savills | YP15: Naomi Vlakancic | YQ15: naomi.vlakancic@cordeasavills.com | YS15: http://click.surveylab.co.uk/anrev-inrev-ncreif-capital-raising-2016/?survey=NVEQN229
A16: 37 | B16: NVDYF083 | C16: survey=NVDYF083 | D16: 42402.762 | E16: 42402.767 | F16: 14 | G16: 1|2|2|2|3|4|5|6|7|8|2|3|4|5|6|7|8|2|3|4|5|6|7|8|9|11|11|8|9|11|11|11|2|3|4|5|6|7|8|9|11|2|3|4|5|6|7|8|9|11|15| | I16: 209.236.106.85 | J16: INREV | K16: Adrian Fernandez | L16: Prologis | M16: =VLOOKUP(MID(O16,SEARCH("@",O16,1),LEN(O16)-SEARCH("@",O16,1)+1),[1]Sheet1!$D:$F,3,FALSE) -> M024 | N16: VP, Fund Operations | O16: acfernandez@prologis.com | P16: 415-733-9418 | Q16: United States | R16: USD | T16: 1 | W16: 356.8 | Z16: 242.8 | AC16: 599.6 | AJ16: 0 | AK16: 143 | AN16: 2400.4 | AQ16: 2543.4 | AX16: 0 | BE16: 0 | BL16: 0 | BM16: 499.8 | BN16: 0 | BO16: 0 | BP16: 2643.2 | BQ16: 0 | BR16: 0 | BS16: 3143 | BT16: TRUE | BU16: FALSE | BV16: TRUE | BW16: FALSE | BX16: FALSE | BY16: FALSE | BZ16: 1 | CC16: 1 | CF16: 2 | CM16: 0 | CN16: 1 | CQ16: 1 | CT16: 2 | DA16: 0 | DH16: 0 | DO16: 0 | DP16: 2 | DQ16: 0 | DR16: 0 | DS16: 2 | DT16: 0 | DU16: 0 | DV16: 4 | DW16: YES | DX16: NO | DY16: NO | DZ16: YES | EA16: NO | EB16: NO | EC16: NO | ED16: NO | EE16: NO | EF16: NO | EG16: NO | EH16: NO | EI16: YES | EJ16: NO | EK16: NO | EL16: YES | EM16: NO | EN16: NO | EO16: NO | EP16: NO | EQ16: NO | ER16: NO | ES16: NO | ET16: NO | EU16: NO | EV16: NO | EW16: NO | EX16: NO | EY16: NO | EZ16: NO | FA16: NO | FB16: NO | FC16: NO | FD16: NO | FE16: NO | FF16: NO | FG16: 236.8 | FM16: 236.8 | FN16: 250.8 | FT16: 250.8 | FX16: 2643.2 | GA16: 2643.2 | GH16: 0 | GO16: 0 | GV16: 0 | HC16: 0 | HD16: Trust, Registered Investment Company | HE16: 12.2 | HK16: 12.2 | HL16: 499.8 | HM16: 0 | HN16: 0 | HO16: 2643.2 | HP16: 0 | HQ16: 0 | HR16: 3143 | HS16: 356.8 | HV16: 242.8 | HY16: 599.6 | IF16: 0 | IG16: 143 | IJ16: 2400.4 | IM16: 2543.4 | IT16: 0 | JA16: 0 | JB16: 499.8 | JC16: 0 | JD16: 0 | JE16: 2643.2 | JF16: 0 | JG16: 0 | JH16: 3143 | JJ16: 1.59 | JK16: 98.41 | JN16: 158.9 | JT16: 158.9 | JU16: 195.8 | KA16: 195.8 | KE16: 242.8 | KH16: 242.8 | KO16: 0 | KV16: 0 | LC16: 0 | LJ16: 0 | LK16: Trust | LL16: 2.1 | LR16: 2.1 | LS16: 356.8 | LT16: 0 | LU16: 0 | LV16: 242.8 | LW16: 0 | LX16: 0 | LY16: 599.6 | OK16: 0 | OL16: 78 | OS16: 55 | PC16: 2400.4 | QI16: Registered Investment Company | QJ16: 10 | QW16: 2543.4 | TI16: 0 | VU16: 0 | YG16: 0 | YH16: 2 | YI16: 1 | YJ16: 1 | YK16: Mozilla/5.0 (Windows NT 6.1; Trident/7.0; rv:11.0) like Gecko | YL16: 286 | YM16: NVDYF083 | YN16: INREV | YO16: Prologis | YP16: Adrian Fernandez | YQ16: acfernandez@prologis.com | YS16: http://click.surveylab.co.uk/anrev-inrev-ncreif-capital-raising-2016/?survey=NVDYF083
A17: 38 | B17: NVDXY475 | C17: survey=NVDXY475 | D17: 42396.765 | E17: 42396.767 | F17: 14 | G17: 1|2|3|15| | I17: 213.205.84.209 | J17: INREV | K17: joao lelis | L17: sonae sierra | M17: =VLOOKUP(MID(O17,SEARCH("@",O17,1),LEN(O17)-SEARCH("@",O17,1)+1),[1]Sheet1!$D:$F,3,FALSE) -> M028 | N17: fund manager | O17: jclelis@sonaesierra.com | P17: 351220104549 | Q17: Portugal | R17: EUR | T17: 2 | U17: 6 | V17: strategy | AC17: 0 | AJ17: 0 | AQ17: 0 | AX17: 0 | BE17: 0 | BL17: 0 | BM17: 0 | BN17: 0 | BO17: 0 | BP17: 0 | BQ17: 0 | BR17: 0 | BS17: 0 | BT17: FALSE | BU17: FALSE | BV17: FALSE | BW17: FALSE | BX17: FALSE | BY17: FALSE | CF17: 0 | CM17: 0 | CT17: 0 | DA17: 0 | DH17: 0 | DO17: 0 | DP17: 0 | DQ17: 0 | DR17: 0 | DS17: 0 | DT17: 0 | DU17: 0 | DV17: 0 | DW17: NO | DX17: NO | DY17: NO | DZ17: NO | EA17: NO | EB17: NO | EC17: NO | ED17: NO | EE17: NO | EF17: NO | EG17: NO | EH17: NO | EI17: NO | EJ17: NO | EK17: NO | EL17: NO | EM17: NO | EN17: NO | EO17: NO | EP17: NO | EQ17: NO | ER17: NO | ES17: NO | ET17: NO | EU17: NO | EV17: NO | EW17: NO | EX17: NO | EY17: NO | EZ17: NO | FA17: NO | FB17: NO | FC17: NO | FD17: NO | FE17: NO | FF17: NO | FM17: 0 | FT17: 0 | GA17: 0 | GH17: 0 | GO17: 0 | GV17: 0 | HC17: 0 | HK17: 0 | HL17: 0 | HM17: 0 | HN17: 0 | HO17: 0 | HP17: 0 | HQ17: 0 | HR17: 0 | HY17: 0 | IF17: 0 | IM17: 0 | IT17: 0 | JA17: 0 | JB17: 0 | JC17: 0 | JD17: 0 | JE17: 0 | JF17: 0 | JG17: 0 | JH17: 0 | JT17: 0 | KA17: 0 | KH17: 0 | KO17: 0 | KV17: 0 | LC17: 0 | LJ17: 0 | LR17: 0 | LS17: 0 | LT17: 0 | LU17: 0 | LV17: 0 | LW17: 0 | LX17: 0 | LY17: 0 | OK17: 0 | QW17: 0 | TI17: 0 | VU17: 0 | YG17: 0 | YH17: 1 | YI17: 2 | YJ17: 1 | YK17: Mozilla/5.0 (Windows NT 6.1; WOW64; Trident/7.0; rv:11.0) like Gecko | YL17: 316 | YM17: NVDXY475 | YN17: INREV | YO17: Sonae Sierra SGPS | YP17: Joao Lelis | YQ17: jclelis@sonaesierra.com | YS17: http://click.surveylab.co.uk/anrev-inrev-ncreif-capital-raising-2016/?survey=NVDXY475
A18: 40 | B18: ANDVF042 | C18: survey=ANDVF042 | D18: 42416.33 | E18: 42416.333 | F18: 14 | G18: 1|2|3|4|5|6|7|8|6|7|8|10|15| | I18: 122.216.24.202 | J18: ANREV | K18: Johan Shah | L18: AEP Investment Management | M18: =VLOOKUP(MID(O18,SEARCH("@",O18,1),LEN(O18)-SEARCH("@",O18,1)+1),[1]Sheet1!$D:$F,3,FALSE) -> M0291 | N18: VP | O18: johan.shah@aep-im.com | P18: 82006982 | Q18: Singapore | R18: USD | T18: 1 | AC18: 0 | AD18: 150 | AJ18: 150 | AQ18: 0 | AX18: 0 | BE18: 0 | BL18: 0 | BM18: 150 | BN18: 0 | BO18: 0 | BP18: 0 | BQ18: 0 | BR18: 0 | BS18: 150 | BT18: FALSE | BU18: TRUE | BV18: FALSE | BW18: FALSE | BX18: FALSE | BY18: FALSE | CF18: 0 | CG18: 1 | CM18: 1 | CT18: 0 | DA18: 0 | DH18: 0 | DO18: 0 | DP18: 1 | DQ18: 0 | DR18: 0 | DS18: 0 | DT18: 0 | DU18: 0 | DV18: 1 | DW18: NO | DX18: NO | DY18: NO | DZ18: NO | EA18: NO | EB18: NO | EC18: YES | ED18: NO | EE18: NO | EF18: NO | EG18: NO | EH18: NO | EI18: NO | EJ18: NO | EK18: NO | EL18: NO | EM18: NO | EN18: NO | EO18: NO | EP18: NO | EQ18: NO | ER18: NO | ES18: NO | ET18: NO | EU18: NO | EV18: NO | EW18: NO | EX18: NO | EY18: NO | EZ18: NO | FA18: NO | FB18: NO | FC18: NO | FD18: NO | FE18: NO | FF18: NO | FM18: 0 | FN18: 10 | FT18: 10 | GA18: 0 | GH18: 0 | GI18: 22.5 | GO18: 22.5 | GV18: 0 | GW18: 75 | HC18: 75 | HD18: Banks/Haj Funds | HE18: 42.5 | HK18: 42.5 | HL18: 150 | HM18: 0 | HN18: 0 | HO18: 0 | HP18: 0 | HQ18: 0 | HR18: 150 | HY18: 0 | HZ18: 150 | IF18: 150 | IM18: 0 | IT18: 0 | JA18: 0 | JB18: 150 | JC18: 0 | JD18: 0 | JE18: 0 | JF18: 0 | JG18: 0 | JH18: 150 | JK18: 100 | JT18: 0 | KA18: 0 | KH18: 0 | KO18: 0 | KV18: 0 | LC18: 0 | LJ18: 0 | LR18: 0 | LS18: 0 | LT18: 0 | LU18: 0 | LV18: 0 | LW18: 0 | LX18: 0 | LY18: 0 | MG18: 10 | MM18: 10 | NB18: 22.5 | NH18: 22.5 | NP18: 75 | NV18: 75 | NW18: Banks/Haj Funds | NX18: 42.5 | OD18: 42.5 | OE18: 150 | OF18: 0 | OK18: 150 | QW18: 0 | TI18: 0 | VU18: 0 | YG18: 0 | YH18: 1 | YI18: 1 | YJ18: 1 | YK18: Mozilla/5.0 (Windows NT 6.1; WOW64) AppleWebKit/537.36 (KHTML, like Gecko) Chrome/47.0.2526.111 Safari/537.36 | YL18: 17 | YM18: ANDVF042 | YN18: ANREV | YO18: AEP Investment Management Pte Ltd | YP18: Yusof Wahid | YQ18: yusof.wahid@aep-im.com | YS18: http://click.surveylab.co.uk/anrev-inrev-ncreif-capital-raising-2016/?survey=ANDVF042
A19: 41 | B19: NVAGG295 | C19: survey=NVAGG295 | D19: 42397.497 | E19: 42397.499 | F19: 14 | G19: 1|2|3|15| | I19: 195.144.249.4 | J19: INREV | K19: Steven Wayne | L19: Jensen Group | M19: =VLOOKUP(MID(O19,SEARCH("@",O19,1),LEN(O19)-SEARCH("@",O19,1)+1),[1]Sheet1!$D:$F,3,FALSE) -> M662 | N19: CEO | O19: sww@jensen.ru | P19: 78123251306 | Q19: Russian Federation | R19: USD | T19: 2 | U19: 6 | V19: Russia unpopular | AC19: 0 | AJ19: 0 | AQ19: 0 | AX19: 0 | BE19: 0 | BL19: 0 | BM19: 0 | BN19: 0 | BO19: 0 | BP19: 0 | BQ19: 0 | BR19: 0 | BS19: 0 | BT19: FALSE | BU19: FALSE | BV19: FALSE | BW19: FALSE | BX19: FALSE | BY19: FALSE | CF19: 0 | CM19: 0 | CT19: 0 | DA19: 0 | DH19: 0 | DO19: 0 | DP19: 0 | DQ19: 0 | DR19: 0 | DS19: 0 | DT19: 0 | DU19: 0 | DV19: 0 | DW19: NO | DX19: NO | DY19: NO | DZ19: NO | EA19: NO | EB19: NO | EC19: NO | ED19: NO | EE19: NO | EF19: NO | EG19: NO | EH19: NO | EI19: NO | EJ19: NO | EK19: NO | EL19: NO | EM19: NO | EN19: NO | EO19: NO | EP19: NO | EQ19: NO | ER19: NO | ES19: NO | ET19: NO | EU19: NO | EV19: NO | EW19: NO | EX19: NO | EY19: NO | EZ19: NO | FA19: NO | FB19: NO | FC19: NO | FD19: NO | FE19: NO | FF19: NO | FM19: 0 | FT19: 0 | GA19: 0 | GH19: 0 | GO19: 0 | GV19: 0 | HC19: 0 | HK19: 0 | HL19: 0 | HM19: 0 | HN19: 0 | HO19: 0 | HP19: 0 | HQ19: 0 | HR19: 0 | HY19: 0 | IF19: 0 | IM19: 0 | IT19: 0 | JA19: 0 | JB19: 0 | JC19: 0 | JD19: 0 | JE19: 0 | JF19: 0 | JG19: 0 | JH19: 0 | JT19: 0 | KA19: 0 | KH19: 0 | KO19: 0 | KV19: 0 | LC19: 0 | LJ19: 0 | LR19: 0 | LS19: 0 | LT19: 0 | LU19: 0 | LV19: 0 | LW19: 0 | LX19: 0 | LY19: 0 | OK19: 0 | QW19: 0 | TI19: 0 | VU19: 0 | YG19: 0 | YH19: 1 | YI19: 3 | YJ19: 1 | YK19: Mozilla/5.0 (Windows NT 6.3; WOW64; Trident/7.0; Touch; MASAJS; rv:11.0) like Gecko | YL19: 196 | YM19: NVAGG295 | YN19: INREV | YO19: Jensen Group | YP19: Steven Wayne | YQ19: Steven.W.Wayne@jensen.ru | YS19: http://click.surveylab.co.uk/anrev-inrev-ncreif-capital-raising-2016/?survey=NVAGG295
A20: 42 | B20: ANFCR868 | C20: survey=ANFCR868 | D20: 42415.222 | E20: 42415.224 | F20: 14 | G20: 1|2|3|3|4|5|6|7|8|3|2|2|3|4|5|6|7|8|9|10|11|2|2|3|4|5|6|7|8|2|3|4|5|6|7|8|9|9|9|10|11|15|2|3|4|5|6|7|8|9|9|10|11|15| | I20: 58.228.125.22 | J20: ANREV | K20: Joseph Lee | L20: IGIS Asset Management | M20: =VLOOKUP(MID(O20,SEARCH("@",O20,1),LEN(O20)-SEARCH("@",O20,1)+1),[1]Sheet1!$D:$F,3,FALSE) -> M0333 | N20: Senior Managing Director | O20: joseph.lee@igisam.com | P20: 822-6959-3102 | Q20: Korea, Republic Of | R20: KRW | T20: 1 | Z20: 167050 | AA20: 76800 | AC20: 243850 | AG20: 491900 | AJ20: 491900 | AN20: 165022.18 | AO20: 56795 | AQ20: 221817.18 | AX20: 0 | BE20: 0 | BL20: 0 | BM20: 0 | BN20: 0 | BO20: 0 | BP20: 823972.18 | BQ20: 133595 | BR20: 0 | BS20: 957567.18 | BT20: TRUE | BU20: TRUE | BV20: TRUE | BW20: FALSE | BX20: FALSE | BY20: FALSE | CC20: 2 | CD20: 2 | CF20: 4 | CJ20: 9 | CM20: 9 | CQ20: 1 | CR20: 1 | CT20: 2 | DA20: 0 | DH20: 0 | DO20: 0 | DP20: 0 | DQ20: 0 | DR20: 0 | DS20: 12 | DT20: 3 | DU20: 0 | DV20: 15 | DW20: NO | DX20: NO | DY20: NO | DZ20: YES | EA20: YES | EB20: NO | EC20: NO | ED20: NO | EE20: NO | EF20: YES | EG20: NO | EH20: NO | EI20: NO | EJ20: NO | EK20: NO | EL20: YES | EM20: YES | EN20: NO | EO20: NO | EP20: NO | EQ20: NO | ER20: NO | ES20: NO | ET20: NO | EU20: NO | EV20: NO | EW20: NO | EX20: NO | EY20: NO | EZ20: NO | FA20: NO | FB20: NO | FC20: NO | FD20: NO | FE20: NO | FF20: NO | FJ20: 13300 | FK20: 122235 | FM20: 135535 | FQ20: 194118.14 | FR20: 11360 | FT20: 205478.14 | GA20: 0 | GE20: 157717.24 | GH20: 157717.24 | GL20: 4999.95 | GO20: 4999.95 | GS20: 160700 | GV20: 160700 | HC20: 0 | HD20: Banks, Securities, Corporate, Other financial institutions | HH20: 293136.85 | HK20: 293136.85 | HL20: 0 | HM20: 0 | HN20: 0 | HO20: 823972.18 | HP20: 133595 | HQ20: 0 | HR20: 957567.18 | HV20: 167050 | HW20: 76800 | HY20: 243850 | IC20: 491900 | IF20: 491900 | IJ20: 165022.18 | IK20: 56795 | IM20: 221817.18 | IT20: 0 | JA20: 0 | JB20: 0 | JC20: 0 | JD20: 0 | JE20: 823972.18 | JF20: 133595 | JG20: 0 | JH20: 957567.18 | JJ20: 100 | JQ20: 13300 | JR20: 76800 | JT20: 90100 | KA20: 0 | KH20: 0 | KL20: 99613.2 | KO20: 99613.2 | KS20: 4999.95 | KV20: 4999.95 | LC20: 0 | LJ20: 0 | LK20: Banks, Securities, Corporate, Other financial institutions | LO20: 49136.85 | LR20: 49136.85 | LS20: 0 | LT20: 0 | LU20: 0 | LV20: 167050 | LW20: 76800 | LX20: 0 | LY20: 243850 | MJ20: 87200 | NL20: 160700 | NW20: Banks, Securities, Corporate, Other financial institutions | OA20: 244000 | OK20: 491900 | OP20: 45435 | OV20: 106918.14 | OW20: 11360 | PJ20: 58104.04 | QW20: 221817.18 | TI20: 0 | VU20: 0 | YG20: 0 | YH20: 1 | YI20: 1 | YJ20: 1 | YK20: Mozilla/5.0 (iPhone; CPU iPhone OS 9_2_1 like Mac OS X) AppleWebKit/601.1.46 (KHTML, like Gecko) Version/9.0 Mobile/13D15 Safari/601.1 | YL20: 183 | YM20: ANFCR868 | YN20: ANREV | YO20: IGIS Asset Management | YP20: Joseph | YQ20: joseph.lee@igisam.com | YS20: http://click.surveylab.co.uk/anrev-inrev-ncreif-capital-raising-2016/?survey=ANFCR868
A21: 43 | B21: ANATG834 | C21: survey=ANATG834 | D21: 42404.424 | F21: 11 | G21: 1|2|3|2|3|2|2|3|4|5|6|7|8|12|2|3|4|5|6|3|4|5|6|7|8|12|12|2|3|4|5|6|7|8|12| | I21: 118.201.195.144 | J21: ANREV | K21: Chew Weiting | L21: CapitaLand Fund Management Pte. Ltd. | M21: =VLOOKUP(MID(O21,SEARCH("@",O21,1),LEN(O21)-SEARCH("@",O21,1)+1),[1]Sheet1!$D:$F,3,FALSE) -> M0091 | N21: Senior Analyst | O21: chew.weiting@capitaland.com | P21: 65 6713 3108 | Q21: Singapore | R21: USD | T21: 1 | AC21: 0 | AJ21: 0 | AQ21: 0 | AU21: 600 | AX21: 600 | BE21: 0 | BL21: 0 | BM21: 0 | BN21: 0 | BO21: 0 | BP21: 600 | BQ21: 0 | BR21: 0 | BS21: 600 | BT21: FALSE | BU21: FALSE | BV21: FALSE | BW21: TRUE | BX21: FALSE | BY21: FALSE | CF21: 0 | CM21: 0 | CT21: 0 | CX21: 1 | DA21: 1 | DH21: 0 | DO21: 0 | DP21: 0 | DQ21: 0 | DR21: 0 | DS21: 1 | DT21: 0 | DU21: 0 | DV21: 1 | DW21: NO | DX21: NO | DY21: NO | DZ21: NO | EA21: NO | EB21: NO | EC21: NO | ED21: NO | EE21: NO | EF21: NO | EG21: NO | EH21: NO | EI21: NO | EJ21: NO | EK21: NO | EL21: NO | EM21: NO | EN21: NO | EO21: NO | EP21: NO | EQ21: NO | ER21: YES | ES21: NO | ET21: NO | EU21: NO | EV21: NO | EW21: NO | EX21: NO | EY21: NO | EZ21: NO | FA21: NO | FB21: NO | FC21: NO | FD21: NO | FE21: NO | FF21: NO | FM21: 0 | FT21: 0 | FX21: 300 | GA21: 300 | GH21: 0 | GO21: 0 | GV21: 0 | HC21: 0 | HD21: Corporate | HH21: 300 | HK21: 300 | HL21: 0 | HM21: 0 | HN21: 0 | HO21: 600 | HP21: 0 | HQ21: 0 | HR21: 600 | HY21: 0 | IC21: 600 | IF21: 600 | IM21: 0 | IT21: 0 | JA21: 0 | JB21: 0 | JC21: 0 | JD21: 0 | JE21: 600 | JF21: 0 | JG21: 0 | JH21: 600 | JK21: 100 | JT21: 0 | KA21: 0 | KH21: 0 | KO21: 0 | KV21: 0 | LC21: 0 | LJ21: 0 | LR21: 0 | LS21: 0 | LT21: 0 | LU21: 0 | LV21: 0 | LW21: 0 | LX21: 0 | LY21: 0 | OK21: 0 | QW21: 0 | RO21: 300 | SU21: Corporate | SY21: 300 | TI21: 600 | YK21: Mozilla/5.0 (Windows NT 6.1; Trident/7.0; rv:11.0) like Gecko | YL21: 68 | YM21: ANATG834 | YN21: ANREV | YO21: CapitaLand | YP21: Chew Weiting | YQ21: chew.weiting@capitaland.com | YS21: http://click.surveylab.co.uk/anrev-inrev-ncreif-capital-raising-2016/?survey=ANATG834
A22: 44 | B22: NVYGZ815 | C22: survey=NVYGZ815 | D22: 42417.622 | E22: 42417.659 | F22: 14 | G22: 1|2|3|4|4|5|6|2|3|4|5|6|7|8|8|3|4|5|6|7|8|9|3|4|5|6|7|8|9|11|12|12|2|3|4|5|3|3|4|5|4|3|4|5|6|2|3|3|4|5|6|7|8|9|15| | I22: 193.138.107.81 | J22: INREV | K22: Geoff Cunningham | L22: Standard Life Investments | M22: =VLOOKUP(MID(O22,SEARCH("@",O22,1),LEN(O22)-SEARCH("@",O22,1)+1),[1]Sheet1!$D:$F,3,FALSE) -> M675 | N22: Management Information Analyst | O22: geoff_cunningham@standardlife.com | P22: +44 (0)131 245 6862 | Q22: United Kingdom | R22: GBP | T22: 1 | W22: 294.98 | Z22: 276.61 | AB22: 55 | AC22: 626.59 | AJ22: 0 | AQ22: 0 | AX22: 0 | BE22: 0 | BL22: 0 | BM22: 294.98 | BN22: 0 | BO22: 0 | BP22: 276.61 | BQ22: 0 | BR22: 55 | BS22: 626.59 | BT22: TRUE | BU22: FALSE | BV22: FALSE | BW22: FALSE | BX22: FALSE | BY22: FALSE | BZ22: 4 | CC22: 1 | CE22: 1 | CF22: 6 | CM22: 0 | CT22: 0 | DA22: 0 | DH22: 0 | DO22: 0 | DP22: 4 | DQ22: 0 | DR22: 0 | DS22: 1 | DT22: 0 | DU22: 1 | DV22: 6 | DW22: YES | DX22: NO | DY22: NO | DZ22: YES | EA22: NO | EB22: YES | EC22: NO | ED22: NO | EE22: NO | EF22: NO | EG22: NO | EH22: NO | EI22: NO | EJ22: NO | EK22: NO | EL22: NO | EM22: NO | EN22: NO | EO22: NO | EP22: NO | EQ22: NO | ER22: NO | ES22: NO | ET22: NO | EU22: NO | EV22: NO | EW22: NO | EX22: NO | EY22: NO | EZ22: NO | FA22: NO | FB22: NO | FC22: NO | FD22: NO | FE22: NO | FF22: NO | FG22: 134.47 | FJ22: 230.66 | FL22: 55 | FM22: 420.13 | FN22: 77.88 | FQ22: 21.21 | FT22: 99.09 | FU22: 82.64 | GA22: 82.64 | GH22: 0 | GL22: 24.74 | GO22: 24.74 | GV22: 0 | HC22: 0 | HK22: 0 | HL22: 294.99 | HM22: 0 | HN22: 0 | HO22: 276.61 | HP22: 0 | HQ22: 55 | HR22: 626.6 | HS22: 212.34 | HV22: 60.09 | HX22: 55 | HY22: 327.43 | HZ22: 82.64 | IC22: 17.67 | IF22: 100.31 | IJ22: 198.85 | IM22: 198.85 | IT22: 0 | JA22: 0 | JB22: 294.98 | JC22: 0 | JD22: 0 | JE22: 276.61 | JF22: 0 | JG22: 55 | JH22: 626.59 | JK22: 100 | JN22: 134.47 | JQ22: 230.66 | JS22: 55 | JT22: 420.13 | JU22: 77.88 | JX22: 21.21 | KA22: 99.09 | KB22: 82.64 | KH22: 82.64 | KO22: 0 | KS22: 24.74 | KV22: 24.74 | LC22: 0 | LJ22: 0 | LR22: 0 | LS22: 294.99 | LT22: 0 | LU22: 0 | LV22: 276.61 | LW22: 0 | LX22: 55 | LY22: 626.6 | OK22: 0 | QW22: 0 | TI22: 0 | VU22: 0 | YG22: 0 | YH22: 3 | YI22: 2 | YJ22: 2 | YK22: Mozilla/5.0 (Windows NT 6.1; WOW64; Trident/7.0; rv:11.0) like Gecko | YL22: 321 | YM22: NVYGZ815 | YN22: INREV | YO22: Standard Life Investments | YP22: Geoff Cunningham | YQ22: geoff_cunningham@standardlife.com | YS22: http://click.surveylab.co.uk/anrev-inrev-ncreif-capital-raising-2016/?survey=NVYGZ815
A23: 46 | B23: NVEBT812 | C23: survey=NVEBT812 | D23: 42401.473 | E23: 42401.495 | F23: 14 | G23: 1|2|3|3|4|5|5|4|5|6|7|8|6|7|7|7|8|9|4|5|6|7|8|9|3|4|5|6|7|8|9|2|3|4|5|6|7|8|6|6|7|8|9|4|5|6|7|8|9|15| | I23: 57.66.102.116 | J23: INREV | K23: Martin Wheeler/Cilla Yngvesson | L23: ICG-Longbow | M23: =VLOOKUP(MID(O23,SEARCH("@",O23,1),LEN(O23)-SEARCH("@",O23,1)+1),[1]Sheet1!$D:$F,3,FALSE) -> M674 | N23: Co-head/ClientRelations | O23: Cilla.Yngvesson@icgplc.com | P23: +44 (0)20 3201 7772 | Q23: United Kingdom | R23: GBP | T23: 1 | AB23: 982 | AC23: 982 | AJ23: 0 | AQ23: 0 | AX23: 0 | BE23: 0 | BL23: 0 | BM23: 0 | BN23: 0 | BO23: 0 | BP23: 0 | BQ23: 0 | BR23: 982 | BS23: 982 | BT23: TRUE | BU23: FALSE | BV23: FALSE | BW23: FALSE | BX23: FALSE | BY23: FALSE | CE23: 2 | CF23: 2 | CM23: 0 | CT23: 0 | DA23: 0 | DH23: 0 | DO23: 0 | DP23: 0 | DQ23: 0 | DR23: 0 | DS23: 0 | DT23: 0 | DU23: 2 | DV23: 2 | DW23: NO | DX23: NO | DY23: NO | DZ23: NO | EA23: NO | EB23: YES | EC23: NO | ED23: NO | EE23: NO | EF23: NO | EG23: NO | EH23: NO | EI23: NO | EJ23: NO | EK23: NO | EL23: NO | EM23: NO | EN23: NO | EO23: NO | EP23: NO | EQ23: NO | ER23: NO | ES23: NO | ET23: NO | EU23: NO | EV23: NO | EW23: NO | EX23: NO | EY23: NO | EZ23: NO | FA23: NO | FB23: NO | FC23: NO | FD23: NO | FE23: NO | FF23: NO | FL23: 681 | FM23: 681 | FS23: 156 | FT23: 156 | GA23: 0 | GH23: 0 | GO23: 0 | GU23: 90 | GV23: 90 | HC23: 0 | HD23: Endowment Plan/Industry Body | HJ23: 55 | HK23: 55 | HL23: 0 | HM23: 0 | HN23: 0 | HO23: 0 | HP23: 0 | HQ23: 982 | HR23: 982 | HX23: 872 | HY23: 872 | IE23: 110 | IF23: 110 | IM23: 0 | IT23: 0 | JA23: 0 | JB23: 0 | JC23: 0 | JD23: 0 | JE23: 0 | JF23: 0 | JG23: 982 | JH23: 982 | JK23: 100 | JS23: 681 | JT23: 681 | JZ23: 156 | KA23: 156 | KH23: 0 | KO23: 0 | KV23: 0 | LB23: 90 | LC23: 90 | LJ23: 0 | LK23: Endowment Plan/Industry Body | LQ23: 55 | LR23: 55 | LS23: 0 | LT23: 0 | LU23: 0 | LV23: 0 | LW23: 0 | LX23: 982 | LY23: 982 | OK23: 0 | QW23: 0 | TI23: 0 | VU23: 0 | YG23: 0 | YH23: 1 | YI23: 1 | YJ23: 1 | YK23: Mozilla/5.0 (compatible; MSIE 10.0; Windows NT 6.1; WOW64; Trident/6.0) | YL23: 177 | YM23: NVEBT812 | YN23: INREV | YO23: ICG-Longbow | YP23: Cilla Yngvesson | YQ23: cilla.yngvesson@icgam.com | YS23: http://click.surveylab.co.uk/anrev-inrev-ncreif-capital-raising-2016/?survey=NVEBT812
A24: 47 | B24: NVCBA144 | C24: survey=NVCBA144 | D24: 42417.457 | E24: 42417.49 | F24: 14 | G24: 1|2|2|3|4|5|6|7|8|2|2|3|2|2|3|2|3|4|4|5|6|7|8|3|2|3|4|5|6|7|8|9|9|10|11|11|10|2|3|4|5|6|7|8|6|7|8|6|7|8|9|10|11|9|10|11|7|4|3|2|3|4|5|6|7|7|8|9|10|11|2|3|4|3|4|5|6|7|3|4|5|5|3|4|5|6|7|8|9|10|11|15| | I24: 185.48.69.2 | J24: INREV | K24: Iris Gelten | L24: Bouwinvest Real Estate Investment Management (REIM) | M24: =VLOOKUP(MID(O24,SEARCH("@",O24,1),LEN(O24)-SEARCH("@",O24,1)+1),[1]Sheet1!$D:$F,3,FALSE) -> M660 | N24: Corporate Marketing & Communication Adviser | O24: i.gelten@bouwinvest.nl | P24: +31 (0)6 22227735 | Q24: Netherlands | R24: EUR | T24: 1 | W24: 291.5 | AC24: 291.5 | AD24: 46 | AJ24: 46 | AK24: 12 | AQ24: 12 | AX24: 0 | BE24: 0 | BL24: 0 | BM24: 349.5 | BN24: 0 | BO24: 0 | BP24: 0 | BQ24: 0 | BR24: 0 | BS24: 349.5 | BT24: TRUE | BU24: TRUE | BV24: TRUE | BW24: FALSE | BX24: FALSE | BY24: FALSE | BZ24: 6 | CF24: 6 | CG24: 3 | CM24: 3 | CN24: 1 | CT24: 1 | DA24: 0 | DH24: 0 | DO24: 0 | DP24: 10 | DQ24: 0 | DR24: 0 | DS24: 0 | DT24: 0 | DU24: 0 | DV24: 10 | DW24: YES | DX24: NO | DY24: NO | DZ24: NO | EA24: NO | EB24: NO | EC24: YES | ED24: NO | EE24: NO | EF24: NO | EG24: NO | EH24: NO | EI24: YES | EJ24: NO | EK24: NO | EL24: NO | EM24: NO | EN24: NO | EO24: NO | EP24: NO | EQ24: NO | ER24: NO | ES24: NO | ET24: NO | EU24: NO | EV24: NO | EW24: NO | EX24: NO | EY24: NO | EZ24: NO | FA24: NO | FB24: NO | FC24: NO | FD24: NO | FE24: NO | FF24: NO | FG24: 339.5 | FM24: 339.5 | FN24: 10 | FT24: 10 | GA24: 0 | GH24: 0 | GO24: 0 | GV24: 0 | HC24: 0 | HK24: 0 | HL24: 349.5 | HM24: 0 | HN24: 0 | HO24: 0 | HP24: 0 | HQ24: 0 | HR24: 349.5 | HS24: 349.5 | HY24: 349.5 | IF24: 0 | IM24: 0 | IT24: 0 | JA24: 0 | JB24: 349.5 | JC24: 0 | JD24: 0 | JE24: 0 | JF24: 0 | JG24: 0 | JH24: 349.5 | JI24: 29 | JK24: 71 | JN24: 281.5 | JT24: 281.5 | JU24: 10 | KA24: 10 | KH24: 0 | KO24: 0 | KV24: 0 | LC24: 0 | LJ24: 0 | LR24: 0 | LS24: 291.5 | LT24: 0 | LU24: 0 | LV24: 0 | LW24: 0 | LX24: 0 | LY24: 291.5 | LZ24: 46 | OK24: 46 | OL24: 12 | QW24: 12 | TI24: 0 | VU24: 0 | YG24: 0 | YH24: 1 | YI24: 1 | YJ24: 1 | YK24: Mozilla/5.0 (compatible; MSIE 10.0; Windows NT 6.2; WOW64; Trident/6.0) | YL24: 61 | YM24: NVCBA144 | YN24: INREV | YO24: Bouwinvest REIM B.V. | YP24: Iris Gelten | YQ24: i.gelten@bouwnvest.nl | YS24: http://click.surveylab.co.uk/anrev-inrev-ncreif-capital-raising-2016/?survey=NVCBA144
A25: 48 | B25: NVRBQ222 | C25: survey=NVRBQ222 | D25: 42423.48 | E25: 42423.481 | F25: 14 | G25: 1|2|3|4|5|4|4|5|6|7|2|2|2|3|4|2|2|3|4|4|5|6|7|8|9|15|2|3|3|4|5|6|6|7|7|8|9|2|3|4|5|6|7|8|9|15| | I25: 213.208.204.10 | J25: INREV | K25: Remco Rothkrantz | L25: Kempen & Co | M25: =VLOOKUP(MID(O25,SEARCH("@",O25,1),LEN(O25)-SEARCH("@",O25,1)+1),[1]Sheet1!$D:$F,3,FALSE) -> M03085 | N25: Directeur Non-Listed Real Estate Solutions | O25: rrot@kempen.nl | P25: 203488547 | Q25: Netherlands | R25: EUR | T25: 1 | W25: 600 | AC25: 600 | AJ25: 0 | AQ25: 0 | AX25: 0 | BE25: 0 | BL25: 0 | BM25: 600 | BN25: 0 | BO25: 0 | BP25: 0 | BQ25: 0 | BR25: 0 | BS25: 600 | BT25: TRUE | BU25: FALSE | BV25: FALSE | BW25: FALSE | BX25: FALSE | BY25: FALSE | BZ25: 1 | CF25: 1 | CM25: 0 | CT25: 0 | DA25: 0 | DH25: 0 | DO25: 0 | DP25: 1 | DQ25: 0 | DR25: 0 | DS25: 0 | DT25: 0 | DU25: 0 | DV25: 1 | DW25: YES | DX25: NO | DY25: NO | DZ25: NO | EA25: NO | EB25: NO | EC25: NO | ED25: NO | EE25: NO | EF25: NO | EG25: NO | EH25: NO | EI25: NO | EJ25: NO | EK25: NO | EL25: NO | EM25: NO | EN25: NO | EO25: NO | EP25: NO | EQ25: NO | ER25: NO | ES25: NO | ET25: NO | EU25: NO | EV25: NO | EW25: NO | EX25: NO | EY25: NO | EZ25: NO | FA25: NO | FB25: NO | FC25: NO | FD25: NO | FE25: NO | FF25: NO | FM25: 0 | FN25: 300 | FT25: 300 | GA25: 0 | GH25: 0 | GO25: 0 | GV25: 0 | HC25: 0 | HD25: undisclosed | HE25: 300 | HK25: 300 | HL25: 600 | HM25: 0 | HN25: 0 | HO25: 0 | HP25: 0 | HQ25: 0 | HR25: 600 | HS25: 300 | HY25: 300 | HZ25: 300 | IF25: 300 | IM25: 0 | IT25: 0 | JA25: 0 | JB25: 600 | JC25: 0 | JD25: 0 | JE25: 0 | JF25: 0 | JG25: 0 | JH25: 600 | JL25: undisclosed | JM25: 100 | JT25: 0 | KA25: 0 | KH25: 0 | KO25: 0 | KV25: 0 | LC25: 0 | LJ25: 0 | LK25: Undisclosed | LL25: 600 | LR25: 600 | LS25: 600 | LT25: 0 | LU25: 0 | LV25: 0 | LW25: 0 | LX25: 0 | LY25: 600 | OK25: 0 | QW25: 0 | TI25: 0 | VU25: 0 | YG25: 0 | YH25: 1 | YI25: 3 | YJ25: 2 | YK25: Mozilla/5.0 (Windows NT 6.1; WOW64) AppleWebKit/537.36 (KHTML, like Gecko) Chrome/47.0.2526.106 Safari/537.36 | YL25: 201 | YM25: NVRBQ222 | YN25: INREV | YO25: Kempen & Co | YP25: RPL Rothkrantz | YQ25: rrot@kempen.nl | YS25: http://click.surveylab.co.uk/anrev-inrev-ncreif-capital-raising-2016/?survey=NVRBQ222
A26: 49 | B26: NVGKJ874 | C26: survey=NVGKJ874 | D26: 42422.694 | E26: 42422.695 | F26: 14 | G26: 1|2|2|2|3|4|2|3|4|5|5|2|3|4|4|5|6|7|8|2|3|4|2|3|4|5|5|3|3|4|5|5|6|6|7|7|8|9|11|9|11|15|2|3|4|4|5|6|7|8|9|11|15| | I26: 85.115.52.201 | J26: INREV | K26: Ian Currie | L26: TH Real Estate | M26: =VLOOKUP(MID(O26,SEARCH("@",O26,1),LEN(O26)-SEARCH("@",O26,1)+1),[1]Sheet1!$D:$F,3,FALSE) -> M038 | N26: Associate Director, Client Capital | O26: ian.currie@threalestate.com | P26: 442037278288 | Q26: United Kingdom | R26: GBP | T26: 1 | W26: 489 | X26: 558 | Z26: 1068 | AB26: 344 | AC26: 2459 | AJ26: 0 | AK26: 123 | AL26: 40 | AN26: 459 | AQ26: 622 | AX26: 0 | BE26: 0 | BL26: 0 | BM26: 612 | BN26: 598 | BO26: 0 | BP26: 1527 | BQ26: 0 | BR26: 344 | BS26: 3081 | BT26: TRUE | BU26: FALSE | BV26: TRUE | BW26: FALSE | BX26: FALSE | BY26: FALSE | BZ26: 5 | CA26: 3 | CC26: 1 | CE26: 2 | CF26: 11 | CM26: 0 | CN26: 2 | CO26: 1 | CQ26: 3 | CT26: 6 | DA26: 0 | DH26: 0 | DO26: 0 | DP26: 7 | DQ26: 4 | DR26: 0 | DS26: 4 | DT26: 0 | DU26: 2 | DV26: 17 | DW26: YES | DX26: YES | DY26: NO | DZ26: YES | EA26: NO | EB26: YES | EC26: NO | ED26: NO | EE26: NO | EF26: NO | EG26: NO | EH26: NO | EI26: YES | EJ26: YES | EK26: NO | EL26: YES | EM26: NO | EN26: NO | EO26: NO | EP26: NO | EQ26: NO | ER26: NO | ES26: NO | ET26: NO | EU26: NO | EV26: NO | EW26: NO | EX26: NO | EY26: NO | EZ26: NO | FA26: NO | FB26: NO | FC26: NO | FD26: NO | FE26: NO | FF26: NO | FG26: 366 | FH26: 402 | FJ26: 1527 | FL26: 306 | FM26: 2601 | FN26: 20 | FO26: 184 | FQ26: 0 | FS26: 0 | FT26: 204 | FU26: 158 | FX26: 0 | FZ26: 0 | GA26: 158 | GB26: 0 | GC26: 0 | GE26: 0 | GG26: 0 | GH26: 0 | GI26: 3 | GJ26: 0 | GL26: 0 | GN26: 0 | GO26: 3 | GP26: 48 | GQ26: 11 | GS26: 0 | GU26: 38 | GV26: 97 | HC26: 0 | HD26: Financial Institution, Union | HE26: 18 | HK26: 18 | HL26: 613 | HM26: 597 | HN26: 0 | HO26: 1527 | HP26: 0 | HQ26: 344 | HR26: 3081 | HS26: 241.5 | HT26: 185 | HV26: 1486 | HX26: 38 | HY26: 1950.5 | HZ26: 173 | IA26: 233 | IC26: 40 | IE26: 0 | IF26: 446 | IG26: 198 | IH26: 180 | IJ26: 0.49 | IL26: 306 | IM26: 684.49 | IN26: 0 | IO26: 0 | IQ26: 0 | IS26: 0 | IT26: 0 | IU26: 0 | IV26: 0 | IX26: 0 | IZ26: 0 | JA26: 0 | JB26: 612.5 | JC26: 598 | JD26: 0 | JE26: 1526.49 | JF26: 0 | JG26: 344 | JH26: 3080.99 | JN26: 248 | JO26: 373 | JQ26: 1068 | JS26: 306 | JT26: 1995 | JU26: 20 | JV26: 185 | JX26: 0 | JZ26: 0 | KA26: 205 | KB26: 158 | KC26: 0 | KE26: 0 | KG26: 0 | KH26: 158 | KI26: 0 | KJ26: 0 | KL26: 0 | KN26: 0 | KO26: 0 | KP26: 3 | KQ26: 0 | KS26: 0 | KU26: 0 | KV26: 3 | KW26: 48 | LB26: 38 | LC26: 86 | LD26: 0 | LE26: 0 | LG26: 0 | LI26: 0 | LJ26: 0 | LK26: Financial Institutions | LL26: 15 | LR26: 15 | LS26: 492 | LT26: 558 | LU26: 0 | LV26: 1068 | LW26: 0 | LX26: 344 | LY26: 2462 | OK26: 0 | OL26: 117 | OM26: 29 | OO26: 459 | OQ26: 0 | OS26: 0 | OT26: 0 | OV26: 0 | OX26: 0 | OZ26: 0 | PA26: 0 | PC26: 0 | PE26: 0 | PG26: 0 | PH26: 0 | PJ26: 0 | PL26: 0 | PN26: 3 | PO26: 0 | PQ26: 0 | PS26: 0 | PZ26: 0 | QB26: 0 | QC26: 11 | QE26: 0 | QG26: 0 | QI26: Union | QJ26: 3 | QW26: 622 | TI26: 0 | VU26: 0 | YG26: 0 | YH26: 1 | YI26: 2 | YJ26: 1 | YK26: Mozilla/5.0 (Windows NT 6.1; WOW64; Trident/7.0; rv:11.0) like Gecko | YL26: 331 | YM26: NVGKJ874 | YN26: INREV | YO26: TH Real Estate | YP26: Laura Barstow | YQ26: Laura.Barstow@threalestate.com | YS26: http://click.surveylab.co.uk/anrev-inrev-ncreif-capital-raising-2016/?survey=NVGKJ874
A27: 50 | B27: NVPRR399 | C27: survey=NVPRR399 | D27: 42417.629 | E27: 42417.633 | F27: 14 | G27: 1|2|2|3|4|5|6|7|8|11|12|15| | I27: 66.43.76.51 | J27: INREV | K27: Kathleen Flores | L27: Franklin Templeton | M27: =VLOOKUP(MID(O27,SEARCH("@",O27,1),LEN(O27)-SEARCH("@",O27,1)+1),[1]Sheet1!$D:$F,3,FALSE) -> M106 | N27: Product Manager | O27: kathleen.flores@franklintempleton.com | P27: 212-632-4024 | Q27: United States | R27: USD | T27: 1 | AC27: 0 | AJ27: 0 | AM27: 90 | AQ27: 90 | AT27: 260 | AV27: 100 | AX27: 360 | BE27: 0 | BL27: 0 | BM27: 0 | BN27: 0 | BO27: 350 | BP27: 0 | BQ27: 100 | BR27: 0 | BS27: 450 | BT27: FALSE | BU27: FALSE | BV27: TRUE | BW27: TRUE | BX27: FALSE | BY27: FALSE | CF27: 0 | CM27: 0 | CP27: 1 | CT27: 1 | CW27: 1 | CY27: 1 | DA27: 2 | DH27: 0 | DO27: 0 | DP27: 0 | DQ27: 0 | DR27: 2 | DS27: 0 | DT27: 1 | DU27: 0 | DV27: 3 | DW27: NO | DX27: NO | DY27: NO | DZ27: NO | EA27: NO | EB27: NO | EC27: NO | ED27: NO | EE27: NO | EF27: NO | EG27: NO | EH27: NO | EI27: NO | EJ27: NO | EK27: YES | EL27: NO | EM27: NO | EN27: NO | EO27: NO | EP27: NO | EQ27: YES | ER27: NO | ES27: YES | ET27: NO | EU27: NO | EV27: NO | EW27: NO | EX27: NO | EY27: NO | EZ27: NO | FA27: NO | FB27: NO | FC27: NO | FD27: NO | FE27: NO | FF27: NO | FI27: 90 | FK27: 77 | FM27: 167 | FP27: 260 | FT27: 260 | GA27: 0 | GH27: 0 | GM27: 23 | GO27: 23 | GV27: 0 | HC27: 0 | HK27: 0 | HL27: 0 | HM27: 0 | HN27: 350 | HO27: 0 | HP27: 100 | HQ27: 0 | HR27: 450 | HU27: 260 | HW27: 77 | HY27: 337 | IF27: 0 | II27: 90 | IK27: 23 | IM27: 113 | IT27: 0 | JA27: 0 | JB27: 0 | JC27: 0 | JD27: 350 | JE27: 0 | JF27: 100 | JG27: 0 | JH27: 450 | JK27: 95 | JL27: Consultants | JM27: 5 | JT27: 0 | KA27: 0 | KH27: 0 | KO27: 0 | KV27: 0 | LC27: 0 | LJ27: 0 | LR27: 0 | LS27: 0 | LT27: 0 | LU27: 0 | LV27: 0 | LW27: 0 | LX27: 0 | LY27: 0 | OK27: 0 | ON27: 90 | OR27: 90 | QS27: 90 | QW27: 90 | RB27: 77 | RD27: 77 | RG27: 260 | RK27: 260 | SD27: 23 | SF27: 23 | TE27: 260 | TG27: 100 | TI27: 360 | VU27: 0 | YG27: 0 | YH27: 1 | YI27: 1 | YJ27: 1 | YK27: Mozilla/5.0 (Windows NT 6.1; WOW64; Trident/7.0; rv:11.0) like Gecko | YL27: 137 | YM27: NVPRR399 | YN27: INREV | YO27: Franklin Templeton Real Asset Advisors | YP27: Raymond Jacobs | YQ27: rjacobs@frk.com | YS27: http://click.surveylab.co.uk/anrev-inrev-ncreif-capital-raising-2016/?survey=NVPRR399
A28: 51 | B28: ANCBC511 | C28: survey=ANCBC511 | D28: 42400.94 | E28: 42400.942 | F28: 14 | G28: 1|2|3|4|5|6|7|8|10|15| | I28: 90.27.49.93 | J28: ANREV | K28: Olivier Do Ngoc | L28: Dynasty Investments / EZLand | M28: =VLOOKUP(MID(O28,SEARCH("@",O28,1),LEN(O28)-SEARCH("@",O28,1)+1),[1]Sheet1!$D:$F,3,FALSE) -> M0278 | N28: Managing Partner | O28: olivier.dongoc@dynasty-investments.com | P28: 84838275000 | Q28: Viet Nam | R28: USD | T28: 1 | AC28: 0 | AD28: 13 | AJ28: 13 | AQ28: 0 | AX28: 0 | BE28: 0 | BL28: 0 | BM28: 13 | BN28: 0 | BO28: 0 | BP28: 0 | BQ28: 0 | BR28: 0 | BS28: 13 | BT28: FALSE | BU28: TRUE | BV28: FALSE | BW28: FALSE | BX28: FALSE | BY28: FALSE | CF28: 0 | CG28: 1 | CM28: 1 | CT28: 0 | DA28: 0 | DH28: 0 | DO28: 0 | DP28: 1 | DQ28: 0 | DR28: 0 | DS28: 0 | DT28: 0 | DU28: 0 | DV28: 1 | DW28: NO | DX28: NO | DY28: NO | DZ28: NO | EA28: NO | EB28: NO | EC28: YES | ED28: NO | EE28: NO | EF28: NO | EG28: NO | EH28: NO | EI28: NO | EJ28: NO | EK28: NO | EL28: NO | EM28: NO | EN28: NO | EO28: NO | EP28: NO | EQ28: NO | ER28: NO | ES28: NO | ET28: NO | EU28: NO | EV28: NO | EW28: NO | EX28: NO | EY28: NO | EZ28: NO | FA28: NO | FB28: NO | FC28: NO | FD28: NO | FE28: NO | FF28: NO | FM28: 0 | FT28: 0 | GA28: 0 | GH28: 0 | GO28: 0 | GV28: 0 | GW28: 13 | HC28: 13 | HK28: 0 | HL28: 13 | HM28: 0 | HN28: 0 | HO28: 0 | HP28: 0 | HQ28: 0 | HR28: 13 | HY28: 0 | HZ28: 13 | IF28: 13 | IM28: 0 | IT28: 0 | JA28: 0 | JB28: 13 | JC28: 0 | JD28: 0 | JE28: 0 | JF28: 0 | JG28: 0 | JH28: 13 | JK28: 100 | JT28: 0 | KA28: 0 | KH28: 0 | KO28: 0 | KV28: 0 | LC28: 0 | LJ28: 0 | LR28: 0 | LS28: 0 | LT28: 0 | LU28: 0 | LV28: 0 | LW28: 0 | LX28: 0 | LY28: 0 | NP28: 13 | NV28: 13 | OE28: 13 | OK28: 13 | QW28: 0 | TI28: 0 | VU28: 0 | YG28: 0 | YH28: 1 | YI28: 2 | YJ28: 1 | YK28: Mozilla/5.0 (Macintosh; Intel Mac OS X 10.11; rv:44.0) Gecko/20100101 Firefox/44.0 | YL28: 116 | YM28: ANCBC511 | YN28: ANREV | YO28: Dynasty Investments | YP28: Olivier Do Ngoc | YQ28: olivier.dongoc@dynasty-investments.com | YS28: http://click.surveylab.co.uk/anrev-inrev-ncreif-capital-raising-2016/?survey=ANCBC511
A29: 52 | B29: ANERW581 | C29: survey=ANERW581 | D29: 42416.091 | F29: 1 | G29: 1|2| | I29: 52.62.68.230 | J29: ANREV | M29: =VLOOKUP(MID(O29,SEARCH("@",O29,1),LEN(O29)-SEARCH("@",O29,1)+1),[1]Sheet1!$D:$F,3,FALSE) -> #VALUE! | YK29: Mozilla/5.0 (Windows NT 6.1; WOW64; Trident/7.0; rv:11.0) like Gecko | YL29: 100 | YM29: ANERW581 | YN29: ANREV | YO29: Cromwell Corporation Limited | YP29: Paul Weightman | YQ29: paul.weightman@cromwell.com.au | YS29: http://click.surveylab.co.uk/anrev-inrev-ncreif-capital-raising-2016/?survey=ANERW581
A30: 53 | B30: ANLJF817 | C30: survey=ANLJF817 | D30: 42402.091 | E30: 42402.11 | F30: 14 | G30: 1|2|3|4|4|5|6|7|8|6|7|8|10|15| | I30: 122.209.121.50 | J30: ANREV | K30: Masahiko Tajima | L30: Kenedix, Inc. | M30: =VLOOKUP(MID(O30,SEARCH("@",O30,1),LEN(O30)-SEARCH("@",O30,1)+1),[1]Sheet1!$D:$F,3,FALSE) -> M0230 | N30: Director CFO Head of Corporate Planning | O30: masahiko_tajima@kenedix.com | P30: 81-3-5623-8460 | Q30: Japan | R30: JPY | T30: 1 | AC30: 0 | AD30: 8000 | AE30: 7000 | AJ30: 15000 | AQ30: 0 | AX30: 0 | BE30: 0 | BL30: 0 | BM30: 8000 | BN30: 7000 | BO30: 0 | BP30: 0 | BQ30: 0 | BR30: 0 | BS30: 15000 | BT30: FALSE | BU30: TRUE | BV30: FALSE | BW30: FALSE | BX30: FALSE | BY30: FALSE | CF30: 0 | CG30: 1 | CH30: 2 | CM30: 3 | CT30: 0 | DA30: 0 | DH30: 0 | DO30: 0 | DP30: 1 | DQ30: 2 | DR30: 0 | DS30: 0 | DT30: 0 | DU30: 0 | DV30: 3 | DW30: NO | DX30: NO | DY30: NO | DZ30: NO | EA30: NO | EB30: NO | EC30: YES | ED30: YES | EE30: NO | EF30: NO | EG30: NO | EH30: NO | EI30: NO | EJ30: NO | EK30: NO | EL30: NO | EM30: NO | EN30: NO | EO30: NO | EP30: NO | EQ30: NO | ER30: NO | ES30: NO | ET30: NO | EU30: NO | EV30: NO | EW30: NO | EX30: NO | EY30: NO | EZ30: NO | FA30: NO | FB30: NO | FC30: NO | FD30: NO | FE30: NO | FF30: NO | FG30: 1000 | FM30: 1000 | FT30: 0 | GA30: 0 | GH30: 0 | GO30: 0 | GV30: 0 | GX30: 3000 | HC30: 3000 | HD30: Financial Institutions | HE30: 7000 | HF30: 4000 | HK30: 11000 | HL30: 8000 | HM30: 7000 | HN30: 0 | HO30: 0 | HP30: 0 | HQ30: 0 | HR30: 15000 | HY30: 0 | HZ30: 8000 | IA30: 7000 | IF30: 15000 | IM30: 0 | IT30: 0 | JA30: 0 | JB30: 8000 | JC30: 7000 | JD30: 0 | JE30: 0 | JF30: 0 | JG30: 0 | JH30: 15000 | JI30: 50 | JK30: 20 | JL30: financial institution | JM30: 30 | JT30: 0 | KA30: 0 | KH30: 0 | KO30: 0 | KV30: 0 | LC30: 0 | LJ30: 0 | LR30: 0 | LS30: 0 | LT30: 0 | LU30: 0 | LV30: 0 | LW30: 0 | LX30: 0 | LY30: 0 | LZ30: 1000 | MF30: 1000 | NQ30: 3000 | NV30: 3000 | NW30: Financial Institutions | NX30: 7000 | NY30: 4000 | OD30: 11000 | OE30: 8000 | OF30: 7000 | OK30: 15000 | QW30: 0 | TI30: 0 | VU30: 0 | YG30: 0 | YH30: 3 | YI30: 1 | YJ30: 1 | YK30: Mozilla/5.0 (Windows NT 6.1; Trident/7.0; rv:11.0) like Gecko | YL30: 202 | YM30: ANLJF817 | YN30: ANREV | YO30: Kenedix | YP30: Masahiko Tajima | YQ30: masahiko_tajima@kenedix.com | YS30: http://click.surveylab.co.uk/anrev-inrev-ncreif-capital-raising-2016/?survey=ANLJF817
A31: 54 | B31: ANRTD907 | C31: survey=ANRTD907 | D31: 42417.075 | E31: 42417.116 | F31: 14 | G31: 1|2|2|2|2|2|3|4|5|6|7|8|10|15| | I31: 221.186.68.97 | J31: ANREV | K31: Kenji Kondo | L31: Tokyo Tatemono Investment Advisors Co., Ltd. | M31: =VLOOKUP(MID(O31,SEARCH("@",O31,1),LEN(O31)-SEARCH("@",O31,1)+1),[1]Sheet1!$D:$F,3,FALSE) -> M0239 | N31: Corporate Planning Department Senior Manager | O31: kondokn@tt-ia.com | P31: -6821 | Q31: Japan | R31: JPY | T31: 1 | AC31: 0 | AD31: 15683 | AE31: 50 | AH31: 124 | AJ31: 15857 | AQ31: 0 | AX31: 0 | BE31: 0 | BL31: 0 | BM31: 15683 | BN31: 50 | BO31: 0 | BP31: 0 | BQ31: 124 | BR31: 0 | BS31: 15857 | BT31: FALSE | BU31: TRUE | BV31: FALSE | BW31: FALSE | BX31: FALSE | BY31: FALSE | CF31: 0 | CG31: 1 | CH31: 1 | CK31: 1 | CM31: 3 | CT31: 0 | DA31: 0 | DH31: 0 | DO31: 0 | DP31: 1 | DQ31: 1 | DR31: 0 | DS31: 0 | DT31: 1 | DU31: 0 | DV31: 3 | DW31: NO | DX31: NO | DY31: NO | DZ31: NO | EA31: NO | EB31: NO | EC31: YES | ED31: YES | EE31: NO | EF31: NO | EG31: YES | EH31: NO | EI31: NO | EJ31: NO | EK31: NO | EL31: NO | EM31: NO | EN31: NO | EO31: NO | EP31: NO | EQ31: NO | ER31: NO | ES31: NO | ET31: NO | EU31: NO | EV31: NO | EW31: NO | EX31: NO | EY31: NO | EZ31: NO | FA31: NO | FB31: NO | FC31: NO | FD31: NO | FE31: NO | FF31: NO | FM31: 0 | FT31: 0 | GA31: 0 | GH31: 0 | GO31: 0 | GV31: 0 | HC31: 0 | HD31: corporations/ banks | HE31: 15683 | HF31: 50 | HI31: 124 | HK31: 15857 | HL31: 15683 | HM31: 50 | HN31: 0 | HO31: 0 | HP31: 124 | HQ31: 0 | HR31: 15857 | HY31: 0 | HZ31: 15683 | IA31: 50 | ID31: 124 | IF31: 15857 | IM31: 0 | IT31: 0 | JA31: 0 | JB31: 15683 | JC31: 50 | JD31: 0 | JE31: 0 | JF31: 124 | JG31: 0 | JH31: 15857 | JI31: 99 | JK31: 1 | JT31: 0 | KA31: 0 | KH31: 0 | KO31: 0 | KV31: 0 | LC31: 0 | LJ31: 0 | LR31: 0 | LS31: 0 | LT31: 0 | LU31: 0 | LV31: 0 | LW31: 0 | LX31: 0 | LY31: 0 | NW31: corporations/ banks | NX31: 15683 | NY31: 50 | OB31: 124 | OD31: 15857 | OE31: 15683 | OF31: 50 | OG31: 0 | OH31: 0 | OI31: 124 | OJ31: 0 | OK31: 15857 | QW31: 0 | TI31: 0 | VU31: 0 | YG31: 0 | YH31: 3 | YI31: 3 | YJ31: 1 | YK31: Mozilla/5.0 (Windows NT 6.1; Trident/7.0; rv:11.0) like Gecko | YL31: 340 | YM31: ANRTD907 | YN31: ANREV | YO31: Tokyo Tatemono Investment Advisors | YP31: Sho Hattori | YQ31: hattoriss@tt-ia.com | YS31: http://click.surveylab.co.uk/anrev-inrev-ncreif-capital-raising-2016/?survey=ANRTD907
A32: 55 | B32: ANFRA076 | C32: survey=ANFRA076 | D32: 42401.29 | E32: 42401.293 | F32: 14 | G32: 1|2|3|4|2|3|4|5|6|7|8|10|15| | I32: 175.45.116.65 | J32: ANREV | K32: Brad McCann | L32: DEXUS Property Group | M32: =VLOOKUP(MID(O32,SEARCH("@",O32,1),LEN(O32)-SEARCH("@",O32,1)+1),[1]Sheet1!$D:$F,3,FALSE) -> M0090 | N32: DWPF Fund Analyst | O32: brad.mccann@dexus.com | P32: 61290171435 | Q32: Australia | R32: AUD | T32: 1 | AC32: 0 | AD32: 400 | AE32: 0 | AF32: 0 | AG32: 0 | AH32: 0 | AI32: 0 | AJ32: 400 | AQ32: 0 | AX32: 0 | BE32: 0 | BL32: 0 | BM32: 400 | BN32: 0 | BO32: 0 | BP32: 0 | BQ32: 0 | BR32: 0 | BS32: 400 | BT32: FALSE | BU32: TRUE | BV32: FALSE | BW32: FALSE | BX32: FALSE | BY32: FALSE | CF32: 0 | CG32: 1 | CM32: 1 | CT32: 0 | DA32: 0 | DH32: 0 | DO32: 0 | DP32: 1 | DQ32: 0 | DR32: 0 | DS32: 0 | DT32: 0 | DU32: 0 | DV32: 1 | DW32: NO | DX32: NO | DY32: NO | DZ32: NO | EA32: NO | EB32: NO | EC32: YES | ED32: NO | EE32: NO | EF32: NO | EG32: NO | EH32: NO | EI32: NO | EJ32: NO | EK32: NO | EL32: NO | EM32: NO | EN32: NO | EO32: NO | EP32: NO | EQ32: NO | ER32: NO | ES32: NO | ET32: NO | EU32: NO | EV32: NO | EW32: NO | EX32: NO | EY32: NO | EZ32: NO | FA32: NO | FB32: NO | FC32: NO | FD32: NO | FE32: NO | FF32: NO | FM32: 0 | FT32: 0 | GA32: 0 | GH32: 0 | GO32: 0 | GV32: 0 | HC32: 0 | HK32: 0 | HL32: 0 | HM32: 0 | HN32: 0 | HO32: 0 | HP32: 0 | HQ32: 0 | HR32: 0 | HY32: 0 | HZ32: 400 | IF32: 400 | IM32: 0 | IT32: 0 | JA32: 0 | JB32: 400 | JC32: 0 | JD32: 0 | JE32: 0 | JF32: 0 | JG32: 0 | JH32: 400 | JK32: 100 | JT32: 0 | KA32: 0 | KH32: 0 | KO32: 0 | KV32: 0 | LC32: 0 | LJ32: 0 | LR32: 0 | LS32: 0 | LT32: 0 | LU32: 0 | LV32: 0 | LW32: 0 | LX32: 0 | LY32: 0 | OK32: 0 | QW32: 0 | TI32: 0 | VU32: 0 | YG32: 0 | YH32: 2 | YI32: 3 | YJ32: 1 | YK32: Mozilla/5.0 (Windows NT 6.1; Trident/7.0; rv:11.0) like Gecko | YL32: 107 | YM32: ANFRA076 | YN32: ANREV | YO32: DEXUS | YP32: Jonathan Davies | YQ32: jonathan.davies@dexus.com | YS32: http://click.surveylab.co.uk/anrev-inrev-ncreif-capital-raising-2016/?survey=ANFRA076
A33: 56 | B33: ANUMN874 | C33: survey=ANUMN874 | D33: 42401.24 | F33: 1 | G33: 1|2| | I33: 165.100.128.3 | J33: ANREV | M33: =VLOOKUP(MID(O33,SEARCH("@",O33,1),LEN(O33)-SEARCH("@",O33,1)+1),[1]Sheet1!$D:$F,3,FALSE) -> #VALUE! | YK33: Mozilla/5.0 (Windows NT 6.1; rv:44.0) Gecko/20100101 Firefox/44.0 | YL33: 21 | YM33: ANUMN874 | YN33: ANREV | YO33: AIP Japan | YP33: Takahiro | YQ33: takahiro.ito@aipjapan.com | YS33: http://click.surveylab.co.uk/anrev-inrev-ncreif-capital-raising-2016/?survey=ANUMN874
A34: 58 | B34: NVQGU709 | C34: survey=NVQGU709 | D34: 42401.454 | F34: 2 | G34: 1|2|2|3| | I34: 57.66.102.116 | J34: INREV | M34: =VLOOKUP(MID(O34,SEARCH("@",O34,1),LEN(O34)-SEARCH("@",O34,1)+1),[1]Sheet1!$D:$F,3,FALSE) -> #VALUE! | R34: GBP | T34: 1 | YK34: Mozilla/5.0 (Windows NT 6.1; Win64; x64) AppleWebKit/537.36 (KHTML, like Gecko) Chrome/47.0.2526.106 Safari/537.36 | YL34: 188 | YM34: NVQGU709 | YN34: INREV | YO34: Intermediate Capital Group | YP34: Andreas Mondovits | YQ34: andreas.mondovits@icgplc.com | YS34: http://click.surveylab.co.uk/anrev-inrev-ncreif-capital-raising-2016/?survey=NVQGU709
A35: 59 | B35: NVQMX775 | C35: survey=NVQMX775 | D35: 42401.538 | E35: 42401.553 | F35: 14 | G35: 1|2|3|15| | I35: 130.180.126.154 | J35: INREV | K35: Oliver Luckey | L35: Hahn Group | M35: =VLOOKUP(MID(O35,SEARCH("@",O35,1),LEN(O35)-SEARCH("@",O35,1)+1),[1]Sheet1!$D:$F,3,FALSE) -> M369 | N35: Head of Fund Management | O35: oluckey@hahnag.de | P35: +49 2204 9490-135 | Q35: Germany | R35: EUR | T35: 2 | U35: 6 | V35: still enough money to invest | AC35: 0 | AJ35: 0 | AQ35: 0 | AX35: 0 | BE35: 0 | BL35: 0 | BM35: 0 | BN35: 0 | BO35: 0 | BP35: 0 | BQ35: 0 | BR35: 0 | BS35: 0 | BT35: FALSE | BU35: FALSE | BV35: FALSE | BW35: FALSE | BX35: FALSE | BY35: FALSE | CF35: 0 | CM35: 0 | CT35: 0 | DA35: 0 | DH35: 0 | DO35: 0 | DP35: 0 | DQ35: 0 | DR35: 0 | DS35: 0 | DT35: 0 | DU35: 0 | DV35: 0 | DW35: NO | DX35: NO | DY35: NO | DZ35: NO | EA35: NO | EB35: NO | EC35: NO | ED35: NO | EE35: NO | EF35: NO | EG35: NO | EH35: NO | EI35: NO | EJ35: NO | EK35: NO | EL35: NO | EM35: NO | EN35: NO | EO35: NO | EP35: NO | EQ35: NO | ER35: NO | ES35: NO | ET35: NO | EU35: NO | EV35: NO | EW35: NO | EX35: NO | EY35: NO | EZ35: NO | FA35: NO | FB35: NO | FC35: NO | FD35: NO | FE35: NO | FF35: NO | FM35: 0 | FT35: 0 | GA35: 0 | GH35: 0 | GO35: 0 | GV35: 0 | HC35: 0 | HK35: 0 | HL35: 0 | HM35: 0 | HN35: 0 | HO35: 0 | HP35: 0 | HQ35: 0 | HR35: 0 | HY35: 0 | IF35: 0 | IM35: 0 | IT35: 0 | JA35: 0 | JB35: 0 | JC35: 0 | JD35: 0 | JE35: 0 | JF35: 0 | JG35: 0 | JH35: 0 | JT35: 0 | KA35: 0 | KH35: 0 | KO35: 0 | KV35: 0 | LC35: 0 | LJ35: 0 | LR35: 0 | LS35: 0 | LT35: 0 | LU35: 0 | LV35: 0 | LW35: 0 | LX35: 0 | LY35: 0 | OK35: 0 | QW35: 0 | TI35: 0 | VU35: 0 | YG35: 0 | YH35: 1 | YI35: 3 | YJ35: 1 | YK35: Mozilla/5.0 (Windows NT 6.1; WOW64; Trident/7.0; rv:11.0) like Gecko | YL35: 158 | YM35: NVQMX775 | YN35: INREV | YO35: Hahn Group | YP35: Oliver Luckey | YQ35: oluckey@hahnag.de | YS35: http://click.surveylab.co.uk/anrev-inrev-ncreif-capital-raising-2016/?survey=NVQMX775
A36: 60 | B36: NVBXD267 | C36: survey=NVBXD267 | D36: 42401.549 | E36: 42401.552 | F36: 14 | G36: 1|2|3|4|5|6|7|8|9|15| | I36: 92.68.55.82 | J36: INREV | K36: Cyril van den Hoogen | L36: Altera Vastgoed NV | M36: =VLOOKUP(MID(O36,SEARCH("@",O36,1),LEN(O36)-SEARCH("@",O36,1)+1),[1]Sheet1!$D:$F,3,FALSE) -> M021 | N36: CFO | O36: cyril.vandenhoogen@alteravastgoed.nl | P36: 31205452061 | Q36: Netherlands | R36: EUR | T36: 1 | W36: 97 | AC36: 97 | AJ36: 0 | AQ36: 0 | AX36: 0 | BE36: 0 | BL36: 0 | BM36: 97 | BN36: 0 | BO36: 0 | BP36: 0 | BQ36: 0 | BR36: 0 | BS36: 97 | BT36: TRUE | BU36: FALSE | BV36: FALSE | BW36: FALSE | BX36: FALSE | BY36: FALSE | BZ36: 3 | CF36: 3 | CM36: 0 | CT36: 0 | DA36: 0 | DH36: 0 | DO36: 0 | DP36: 3 | DQ36: 0 | DR36: 0 | DS36: 0 | DT36: 0 | DU36: 0 | DV36: 3 | DW36: YES | DX36: NO | DY36: NO | DZ36: NO | EA36: NO | EB36: NO | EC36: NO | ED36: NO | EE36: NO | EF36: NO | EG36: NO | EH36: NO | EI36: NO | EJ36: NO | EK36: NO | EL36: NO | EM36: NO | EN36: NO | EO36: NO | EP36: NO | EQ36: NO | ER36: NO | ES36: NO | ET36: NO | EU36: NO | EV36: NO | EW36: NO | EX36: NO | EY36: NO | EZ36: NO | FA36: NO | FB36: NO | FC36: NO | FD36: NO | FE36: NO | FF36: NO | FG36: 97 | FM36: 97 | FT36: 0 | GA36: 0 | GH36: 0 | GO36: 0 | GV36: 0 | HC36: 0 | HK36: 0 | HL36: 97 | HM36: 0 | HN36: 0 | HO36: 0 | HP36: 0 | HQ36: 0 | HR36: 97 | HS36: 97 | HY36: 97 | IF36: 0 | IM36: 0 | IT36: 0 | JA36: 0 | JB36: 97 | JC36: 0 | JD36: 0 | JE36: 0 | JF36: 0 | JG36: 0 | JH36: 97 | JK36: 100 | JN36: 97 | JT36: 97 | KA36: 0 | KH36: 0 | KO36: 0 | KV36: 0 | LC36: 0 | LJ36: 0 | LR36: 0 | LS36: 97 | LT36: 0 | LU36: 0 | LV36: 0 | LW36: 0 | LX36: 0 | LY36: 97 | OK36: 0 | QW36: 0 | TI36: 0 | VU36: 0 | YG36: 0 | YH36: 1 | YI36: 1 | YJ36: 1 | YK36: Mozilla/5.0 (Windows NT 6.1; WOW64; Trident/7.0; rv:11.0) like Gecko | YL36: 27 | YM36: NVBXD267 | YN36: INREV | YO36: Altera Vastgoed NV | YP36: Cyril Van den Hoogen | YQ36: cyril.vandenhoogen@alteravastgoed.nl | YS36: http://click.surveylab.co.uk/anrev-inrev-ncreif-capital-raising-2016/?survey=NVBXD267
A37: 62 | B37: NVMAP657 | C37: survey=NVMAP657 | D37: 42416.598 | F37: 1 | G37: 1|2|2| | I37: 173.252.128.1 | J37: INREV | M37: =VLOOKUP(MID(O37,SEARCH("@",O37,1),LEN(O37)-SEARCH("@",O37,1)+1),[1]Sheet1!$D:$F,3,FALSE) -> #VALUE! | YK37: Mozilla/5.0 (Windows NT 6.1; WOW64) AppleWebKit/537.36 (KHTML, like Gecko) Chrome/47.0.2526.111 Safari/537.36 | YL37: 65 | YM37: NVMAP657 | YN37: INREV | YO37: Brookfield Asset Management | YP37: Juan Jimenez | YQ37: juan.jimenez@brookfield.com | YS37: http://click.surveylab.co.uk/anrev-inrev-ncreif-capital-raising-2016/?survey=NVMAP657
A38: 63 | B38: NVYYT553 | C38: survey=NVYYT553 | D38: 42405.578 | E38: 42405.685 | F38: 14 | G38: 1|2|2|3|4|5|6|7|8|9|9|3|4|5|6|7|8|9|15| | I38: 194.8.124.3 | J38: INREV | K38: Michelle Ruehl | L38: KGAL GmbH & Co. KG | M38: =VLOOKUP(MID(O38,SEARCH("@",O38,1),LEN(O38)-SEARCH("@",O38,1)+1),[1]Sheet1!$D:$F,3,FALSE) -> M637 | N38: Institutional Business | O38: michelle.ruehl@kgal.de | P38: 498964143147 | Q38: Germany | R38: EUR | T38: 1 | W38: 20 | X38: 500 | AC38: 520 | AJ38: 0 | AQ38: 0 | AX38: 0 | BE38: 0 | BL38: 0 | BM38: 20 | BN38: 500 | BO38: 0 | BP38: 0 | BQ38: 0 | BR38: 0 | BS38: 520 | BT38: TRUE | BU38: FALSE | BV38: FALSE | BW38: FALSE | BX38: FALSE | BY38: FALSE | BZ38: 1 | CA38: 1 | CF38: 2 | CM38: 0 | CT38: 0 | DA38: 0 | DH38: 0 | DO38: 0 | DP38: 1 | DQ38: 1 | DR38: 0 | DS38: 0 | DT38: 0 | DU38: 0 | DV38: 2 | DW38: YES | DX38: YES | DY38: NO | DZ38: NO | EA38: NO | EB38: NO | EC38: NO | ED38: NO | EE38: NO | EF38: NO | EG38: NO | EH38: NO | EI38: NO | EJ38: NO | EK38: NO | EL38: NO | EM38: NO | EN38: NO | EO38: NO | EP38: NO | EQ38: NO | ER38: NO | ES38: NO | ET38: NO | EU38: NO | EV38: NO | EW38: NO | EX38: NO | EY38: NO | EZ38: NO | FA38: NO | FB38: NO | FC38: NO | FD38: NO | FE38: NO | FF38: NO | FM38: 0 | FN38: 20 | FO38: 500 | FT38: 520 | GA38: 0 | GH38: 0 | GO38: 0 | GV38: 0 | HC38: 0 | HK38: 0 | HL38: 20 | HM38: 500 | HN38: 0 | HO38: 0 | HP38: 0 | HQ38: 0 | HR38: 520 | HS38: 20 | HT38: 500 | HY38: 520 | IF38: 0 | IM38: 0 | IT38: 0 | JA38: 0 | JB38: 20 | JC38: 500 | JD38: 0 | JE38: 0 | JF38: 0 | JG38: 0 | JH38: 520 | JK38: 100 | JT38: 0 | JU38: 20 | JV38: 500 | KA38: 520 | KH38: 0 | KO38: 0 | KV38: 0 | LC38: 0 | LJ38: 0 | LR38: 0 | LS38: 20 | LT38: 500 | LU38: 0 | LV38: 0 | LW38: 0 | LX38: 0 | LY38: 520 | OK38: 0 | QW38: 0 | TI38: 0 | VU38: 0 | YG38: 0 | YH38: 3 | YI38: 3 | YJ38: 1 | YK38: Mozilla/5.0 (Windows NT 6.1; WOW64; Trident/7.0; rv:11.0) like Gecko | YL38: 203 | YM38: NVYYT553 | YN38: INREV | YO38: KGAL GmbH & Co. KG | YP38: Andre Zuecker | YQ38: andre.zuecker@kgal.de | YS38: http://click.surveylab.co.uk/anrev-inrev-ncreif-capital-raising-2016/?survey=NVYYT553
A39: 64 | B39: NVHGJ221 | C39: survey=NVHGJ221 | D39: 42401.631 | E39: 42401.642 | F39: 14 | G39: 1|2|3|4|5|4|5|6|7|8|12|15| | I39: 93.176.84.139 | J39: INREV | K39: Peter Lindeschouw | L39: Sparinvest Property Investors | M39: =VLOOKUP(MID(O39,SEARCH("@",O39,1),LEN(O39)-SEARCH("@",O39,1)+1),[1]Sheet1!$D:$F,3,FALSE) -> M180 | N39: Analyst | O39: plr@sparinvest.dk | P39: 4536347034 | Q39: Denmark | R39: EUR | T39: 1 | AC39: 0 | AJ39: 0 | AQ39: 0 | AR39: 0 | AS39: 0 | AT39: 0 | AU39: 0 | AV39: 495 | AW39: 0 | AX39: 495 | BE39: 0 | BL39: 0 | BM39: 0 | BN39: 0 | BO39: 0 | BP39: 0 | BQ39: 495 | BR39: 0 | BS39: 495 | BT39: FALSE | BU39: FALSE | BV39: FALSE | BW39: TRUE | BX39: FALSE | BY39: FALSE | CF39: 0 | CM39: 0 | CT39: 0 | CY39: 1 | DA39: 1 | DH39: 0 | DO39: 0 | DP39: 0 | DQ39: 0 | DR39: 0 | DS39: 0 | DT39: 1 | DU39: 0 | DV39: 1 | DW39: NO | DX39: NO | DY39: NO | DZ39: NO | EA39: NO | EB39: NO | EC39: NO | ED39: NO | EE39: NO | EF39: NO | EG39: NO | EH39: NO | EI39: NO | EJ39: NO | EK39: NO | EL39: NO | EM39: NO | EN39: NO | EO39: NO | EP39: NO | EQ39: NO | ER39: NO | ES39: YES | ET39: NO | EU39: NO | EV39: NO | EW39: NO | EX39: NO | EY39: NO | EZ39: NO | FA39: NO | FB39: NO | FC39: NO | FD39: NO | FE39: NO | FF39: NO | FK39: 450 | FM39: 450 | FT39: 0 | GA39: 0 | GH39: 0 | GM39: 20 | GO39: 20 | GV39: 0 | HA39: 24 | HC39: 24 | HD39: Team | HI39: 1 | HK39: 1 | HL39: 0 | HM39: 0 | HN39: 0 | HO39: 0 | HP39: 495 | HQ39: 0 | HR39: 495 | HW39: 495 | HY39: 495 | IF39: 0 | IM39: 0 | IT39: 0 | JA39: 0 | JB39: 0 | JC39: 0 | JD39: 0 | JE39: 0 | JF39: 495 | JG39: 0 | JH39: 495 | JK39: 100 | JT39: 0 | KA39: 0 | KH39: 0 | KO39: 0 | KV39: 0 | LC39: 0 | LJ39: 0 | LR39: 0 | LS39: 0 | LT39: 0 | LU39: 0 | LV39: 0 | LW39: 0 | LX39: 0 | LY39: 0 | OK39: 0 | QW39: 0 | SK39: 495 | SM39: 495 | TG39: 495 | TI39: 495 | VU39: 0 | YG39: 0 | YH39: 1 | YI39: 3 | YJ39: 1 | YK39: Mozilla/5.0 (Windows NT 6.1; WOW64) AppleWebKit/537.36 (KHTML, like Gecko) Chrome/48.0.2564.97 Safari/537.36 | YL39: 318 | YM39: NVHGJ221 | YN39: INREV | YO39: Sparinvest Property Investors | YP39: Peter Lindeschouw | YQ39: plr@sparinvest.dk | YS39: http://click.surveylab.co.uk/anrev-inrev-ncreif-capital-raising-2016/?survey=NVHGJ221
A40: 65 | B40: NVXRG949 | C40: survey=NVXRG949 | D40: 42401.667 | E40: 42401.673 | F40: 14 | G40: 1|2|3|4|5|4|5|6|7|8|6|7|8|12|15| | I40: 185.23.36.251 | J40: INREV | K40: Marta Herreo | L40: Altan Capital | M40: =VLOOKUP(MID(O40,SEARCH("@",O40,1),LEN(O40)-SEARCH("@",O40,1)+1),[1]Sheet1!$D:$F,3,FALSE) -> M226 | N40: Director | O40: mherrero@altancapital.com | P40: 34 91 426 24 47 | Q40: Spain | R40: EUR | T40: 1 | AC40: 0 | AJ40: 0 | AQ40: 0 | AV40: 35 | AX40: 35 | BE40: 0 | BL40: 0 | BM40: 0 | BN40: 0 | BO40: 0 | BP40: 0 | BQ40: 35 | BR40: 0 | BS40: 35 | BT40: FALSE | BU40: FALSE | BV40: FALSE | BW40: TRUE | BX40: FALSE | BY40: FALSE | CF40: 0 | CM40: 0 | CT40: 0 | CY40: 1 | DA40: 1 | DH40: 0 | DO40: 0 | DP40: 0 | DQ40: 0 | DR40: 0 | DS40: 0 | DT40: 1 | DU40: 0 | DV40: 1 | DW40: NO | DX40: NO | DY40: NO | DZ40: NO | EA40: NO | EB40: NO | EC40: NO | ED40: NO | EE40: NO | EF40: NO | EG40: NO | EH40: NO | EI40: NO | EJ40: NO | EK40: NO | EL40: NO | EM40: NO | EN40: NO | EO40: NO | EP40: NO | EQ40: NO | ER40: NO | ES40: YES | ET40: NO | EU40: NO | EV40: NO | EW40: NO | EX40: NO | EY40: NO | EZ40: NO | FA40: NO | FB40: NO | FC40: NO | FD40: NO | FE40: NO | FF40: NO | FK40: 8 | FM40: 8 | FR40: 16 | FT40: 16 | GA40: 0 | GH40: 0 | GO40: 0 | GV40: 0 | HA40: 11 | HC40: 11 | HK40: 0 | HL40: 0 | HM40: 0 | HN40: 0 | HO40: 0 | HP40: 35 | HQ40: 0 | HR40: 35 | HW40: 35 | HY40: 35 | IF40: 0 | IM40: 0 | IT40: 0 | JA40: 0 | JB40: 0 | JC40: 0 | JD40: 0 | JE40: 0 | JF40: 35 | JG40: 0 | JH40: 35 | JK40: 100 | JT40: 0 | KA40: 0 | KH40: 0 | KO40: 0 | KV40: 0 | LC40: 0 | LJ40: 0 | LR40: 0 | LS40: 0 | LT40: 0 | LU40: 0 | LV40: 0 | LW40: 0 | LX40: 0 | LY40: 0 | OK40: 0 | QW40: 0 | RB40: 8 | RD40: 8 | RI40: 16 | RK40: 16 | SR40: 11 | ST40: 11 | TG40: 35 | TH40: 0 | TI40: 35 | VU40: 0 | YG40: 0 | YH40: 1 | YI40: 3 | YJ40: 1 | YK40: Mozilla/5.0 (Windows NT 6.3; WOW64) AppleWebKit/537.36 (KHTML, like Gecko) Chrome/48.0.2564.97 Safari/537.36 | YL40: 25 | YM40: NVXRG949 | YN40: INREV | YO40: Altan Capital | YP40: Fernado Olaso | YQ40: folaso@altancapital.com | YS40: http://click.surveylab.co.uk/anrev-inrev-ncreif-capital-raising-2016/?survey=NVXRG949
A41: 66 | B41: NVZTG372 | C41: survey=NVZTG372 | D41: 42412.708 | E41: 42412.722 | F41: 14 | G41: 1|2|2|2|2|3|4|5|6|7|8|9|15| | I41: 155.140.133.211 | J41: INREV | K41: Romain Welsch | L41: BNP Paribas REIM | M41: =VLOOKUP(MID(O41,SEARCH("@",O41,1),LEN(O41)-SEARCH("@",O41,1)+1),[1]Sheet1!$D:$F,3,FALSE) -> M318 | N41: Head of Development & Marketing | O41: romain.welsch@bnpparibas.com | P41: 33155652420 | Q41: France | R41: EUR | T41: 1 | W41: 1001 | X41: 161 | Y41: 51 | AA41: 0 | AB41: 29 | AC41: 1242 | AJ41: 0 | AQ41: 0 | AX41: 0 | BE41: 0 | BL41: 0 | BM41: 1001 | BN41: 161 | BO41: 51 | BP41: 0 | BQ41: 0 | BR41: 29 | BS41: 1242 | BT41: TRUE | BU41: FALSE | BV41: FALSE | BW41: FALSE | BX41: FALSE | BY41: FALSE | BZ41: 14 | CA41: 7 | CB41: 2 | CE41: 2 | CF41: 25 | CM41: 0 | CT41: 0 | DA41: 0 | DH41: 0 | DO41: 0 | DP41: 14 | DQ41: 7 | DR41: 2 | DS41: 0 | DT41: 0 | DU41: 2 | DV41: 25 | DW41: YES | DX41: YES | DY41: YES | DZ41: NO | EA41: NO | EB41: YES | EC41: NO | ED41: NO | EE41: NO | EF41: NO | EG41: NO | EH41: NO | EI41: NO | EJ41: NO | EK41: NO | EL41: NO | EM41: NO | EN41: NO | EO41: NO | EP41: NO | EQ41: NO | ER41: NO | ES41: NO | ET41: NO | EU41: NO | EV41: NO | EW41: NO | EX41: NO | EY41: NO | EZ41: NO | FA41: NO | FB41: NO | FC41: NO | FD41: NO | FE41: NO | FF41: NO | FM41: 0 | FP41: 51 | FT41: 51 | GA41: 0 | GH41: 0 | GO41: 0 | GV41: 0 | HC41: 0 | HD41: Retail client / distribution networks | HE41: 322 | HK41: 322 | HL41: 322 | HM41: 0 | HN41: 51 | HO41: 0 | HP41: 0 | HQ41: 0 | HR41: 373 | HY41: 0 | IF41: 0 | IM41: 0 | IT41: 0 | JA41: 0 | JB41: 0 | JC41: 0 | JD41: 0 | JE41: 0 | JF41: 0 | JG41: 0 | JH41: 0 | JT41: 0 | KA41: 0 | KH41: 0 | KO41: 0 | KV41: 0 | LC41: 0 | LJ41: 0 | LR41: 0 | LS41: 0 | LT41: 0 | LU41: 0 | LV41: 0 | LW41: 0 | LX41: 0 | LY41: 0 | OK41: 0 | QW41: 0 | TI41: 0 | VU41: 0 | YG41: 0 | YH41: 1 | YI41: 3 | YJ41: 1 | YK41: Mozilla/5.0 (Windows NT 6.1; WOW64; Trident/7.0; rv:11.0) like Gecko | YL41: 59 | YM41: NVZTG372 | YN41: INREV | YO41: BNP Paribas REIM | YP41: Simone Roberti | YQ41: simone.roberti@bnpparibas.com | YS41: http://click.surveylab.co.uk/anrev-inrev-ncreif-capital-raising-2016/?survey=NVZTG372
A42: 67 | B42: ANYDY038 | C42: survey=ANYDY038 | D42: 42417.065 | E42: 42417.067 | F42: 14 | G42: 1|2|2|2|3|4|5|6|7|8|10|2|3|4|5|6|7|8|10|15| | I42: 202.174.204.154 | J42: ANREV | K42: Hiromutsu Kano | L42: Diamond Realty Management inc. | M42: =VLOOKUP(MID(O42,SEARCH("@",O42,1),LEN(O42)-SEARCH("@",O42,1)+1),[1]Sheet1!$D:$F,3,FALSE) -> M0007 | N42: Division Head | O42: hiromutsu.kano@mc-dream.com | P42: 03-5212-4835 | Q42: Japan | R42: JPY | T42: 1 | AC42: 0 | AD42: 18257 | AE42: 28700 | AF42: 42750 | AG42: 4640 | AI42: 17952 | AJ42: 112299 | AQ42: 0 | AX42: 0 | BE42: 0 | BL42: 0 | BM42: 18257 | BN42: 28700 | BO42: 42750 | BP42: 4640 | BQ42: 0 | BR42: 17952 | BS42: 112299 | BT42: FALSE | BU42: TRUE | BV42: FALSE | BW42: FALSE | BX42: FALSE | BY42: FALSE | CF42: 0 | CG42: 1 | CH42: 1 | CI42: 7 | CJ42: 1 | CL42: 2 | CM42: 12 | CT42: 0 | DA42: 0 | DH42: 0 | DO42: 0 | DP42: 1 | DQ42: 1 | DR42: 7 | DS42: 1 | DT42: 0 | DU42: 2 | DV42: 12 | DW42: NO | DX42: NO | DY42: NO | DZ42: NO | EA42: NO | EB42: NO | EC42: YES | ED42: YES | EE42: YES | EF42: YES | EG42: NO | EH42: YES | EI42: NO | EJ42: NO | EK42: NO | EL42: NO | EM42: NO | EN42: NO | EO42: NO | EP42: NO | EQ42: NO | ER42: NO | ES42: NO | ET42: NO | EU42: NO | EV42: NO | EW42: NO | EX42: NO | EY42: NO | EZ42: NO | FA42: NO | FB42: NO | FC42: NO | FD42: NO | FE42: NO | FF42: NO | FG42: 4421 | FL42: 4660 | FM42: 9081 | FN42: 1596 | FS42: 1369 | FT42: 2965 | GA42: 0 | GH42: 0 | GO42: 0 | GV42: 0 | HC42: 0 | HE42: 12240 | HF42: 28700 | HG42: 42750 | HH42: 4640 | HJ42: 11923 | HK42: 100253 | HL42: 18257 | HM42: 28700 | HN42: 42750 | HO42: 4640 | HP42: 0 | HQ42: 17952 | HR42: 112299 | HY42: 0 | HZ42: 18257 | IA42: 28700 | IB42: 42750 | IC42: 4640 | IE42: 17952 | IF42: 112299 | IM42: 0 | IT42: 0 | JA42: 0 | JB42: 18257 | JC42: 28700 | JD42: 42750 | JE42: 4640 | JF42: 0 | JG42: 17952 | JH42: 112299 | JI42: 17.1 | JK42: 82.9 | JT42: 0 | KA42: 0 | KH42: 0 | KO42: 0 | KV42: 0 | LC42: 0 | LJ42: 0 | LR42: 0 | LS42: 0 | LT42: 0 | LU42: 0 | LV42: 0 | LW42: 0 | LX42: 0 | LY42: 0 | LZ42: 4421 | ME42: 4660 | MF42: 9081 | MG42: 1596 | ML42: 1369 | NX42: 12240 | NY42: 28700 | NZ42: 42750 | OA42: 4640 | OC42: 11923 | OD42: 100253 | OE42: 18257 | OG42: 42750 | OH42: 4640 | OJ42: 17952 | OK42: 112299 | QW42: 0 | TI42: 0 | VU42: 0 | YG42: 0 | YH42: 1 | YI42: 3 | YJ42: 2 | YK42: Mozilla/5.0 (Windows NT 6.1) AppleWebKit/537.36 (KHTML, like Gecko) Chrome/48.0.2564.97 Safari/537.36 | YL42: 108 | YM42: ANYDY038 | YN42: ANREV | YO42: Diamond Realty Management | YP42: Takashi Tsuji | YQ42: takashi.tsuji@mc-dream.com | YR42: Dupe email | YS42: http://click.surveylab.co.uk/anrev-inrev-ncreif-capital-raising-2016/?survey=ANYDY038
A43: 68 | B43: ANDDP265 | C43: survey=ANDDP265 | D43: 42417.247 | E43: 42417.249 | F43: 14 | G43: 1|2|2|2|3|3|15| | I43: 103.9.97.231 | J43: ANREV | K43: Soichiro Tabu | L43: Mitsubishi UFJ Trust and Banking Corporation | M43: =VLOOKUP(MID(O43,SEARCH("@",O43,1),LEN(O43)-SEARCH("@",O43,1)+1),[1]Sheet1!$D:$F,3,FALSE) -> M0232 | N43: Manager | O43: soichiro_tabu@tr.mufg.jp | P43: -12716 | Q43: Japan | R43: JPY | T43: 2 | U43: 6 | V43: Raised capital for direct investments only | AC43: 0 | AJ43: 0 | AQ43: 0 | AX43: 0 | BE43: 0 | BL43: 0 | BM43: 0 | BN43: 0 | BO43: 0 | BP43: 0 | BQ43: 0 | BR43: 0 | BS43: 0 | BT43: FALSE | BU43: FALSE | BV43: FALSE | BW43: FALSE | BX43: FALSE | BY43: FALSE | CF43: 0 | CM43: 0 | CT43: 0 | DA43: 0 | DH43: 0 | DO43: 0 | DP43: 0 | DQ43: 0 | DR43: 0 | DS43: 0 | DT43: 0 | DU43: 0 | DV43: 0 | DW43: NO | DX43: NO | DY43: NO | DZ43: NO | EA43: NO | EB43: NO | EC43: NO | ED43: NO | EE43: NO | EF43: NO | EG43: NO | EH43: NO | EI43: NO | EJ43: NO | EK43: NO | EL43: NO | EM43: NO | EN43: NO | EO43: NO | EP43: NO | EQ43: NO | ER43: NO | ES43: NO | ET43: NO | EU43: NO | EV43: NO | EW43: NO | EX43: NO | EY43: NO | EZ43: NO | FA43: NO | FB43: NO | FC43: NO | FD43: NO | FE43: NO | FF43: NO | FM43: 0 | FT43: 0 | GA43: 0 | GH43: 0 | GO43: 0 | GV43: 0 | HC43: 0 | HK43: 0 | HL43: 0 | HM43: 0 | HN43: 0 | HO43: 0 | HP43: 0 | HQ43: 0 | HR43: 0 | HY43: 0 | IF43: 0 | IM43: 0 | IT43: 0 | JA43: 0 | JB43: 0 | JC43: 0 | JD43: 0 | JE43: 0 | JF43: 0 | JG43: 0 | JH43: 0 | JT43: 0 | KA43: 0 | KH43: 0 | KO43: 0 | KV43: 0 | LC43: 0 | LJ43: 0 | LR43: 0 | LS43: 0 | LT43: 0 | LU43: 0 | LV43: 0 | LW43: 0 | LX43: 0 | LY43: 0 | OK43: 0 | QW43: 0 | TI43: 0 | VU43: 0 | YG43: 0 | YH43: 3 | YI43: 2 | YJ43: 1 | YK43: Mozilla/5.0 (Windows NT 6.1; Trident/7.0; rv:11.0) like Gecko | YL43: 239 | YM43: ANDDP265 | YN43: ANREV | YO43: Mitsubishi UFJ Trust and Banking Corporation | YP43: Soichiro Tabu | YQ43: soichiro_tabu@tr.mufg.jp | YS43: http://click.surveylab.co.uk/anrev-inrev-ncreif-capital-raising-2016/?survey=ANDDP265
A44: 69 | B44: NVVGK295 | C44: survey=NVVGK295 | D44: 42412.529 | E44: 42412.548 | F44: 14 | G44: 1|2|2|2|2|2|3|4|5|6|7|8|9|10|11|12|15| | I44: 139.149.1.241 | J44: INREV | K44: Thomas Stringer | L44: UBS AG | M44: =VLOOKUP(MID(O44,SEARCH("@",O44,1),LEN(O44)-SEARCH("@",O44,1)+1),[1]Sheet1!$D:$F,3,FALSE) -> M064 | N44: Product Specialist | O44: thomas.stringer@ubs.com | P44: +41-61-288 10 45 | Q44: Switzerland | R44: CHF | T44: 1 | W44: 264.5 | X44: 582.5 | Z44: 52.6 | AC44: 899.6 | AE44: 24.7 | AJ44: 24.7 | AK44: 1323.2 | AL44: 106.7 | AQ44: 1429.9 | AS44: 52.2 | AT44: 239.9 | AV44: 1170.6 | AX44: 1462.7 | BE44: 0 | BL44: 0 | BM44: 1587.7 | BN44: 766.1 | BO44: 239.9 | BP44: 52.6 | BQ44: 1170.6 | BR44: 0 | BS44: 3816.9 | BT44: TRUE | BU44: TRUE | BV44: TRUE | BW44: TRUE | BX44: FALSE | BY44: FALSE | BZ44: 6 | CA44: 3 | CC44: 1 | CF44: 10 | CH44: 1 | CM44: 1 | CN44: 4 | CO44: 8 | CT44: 12 | CV44: 1 | CW44: 3 | CY44: 6 | DA44: 10 | DH44: 0 | DO44: 0 | DP44: 10 | DQ44: 13 | DR44: 3 | DS44: 1 | DT44: 6 | DU44: 0 | DV44: 33 | DW44: YES | DX44: YES | DY44: NO | DZ44: YES | EA44: NO | EB44: NO | EC44: NO | ED44: YES | EE44: NO | EF44: NO | EG44: NO | EH44: NO | EI44: YES | EJ44: YES | EK44: NO | EL44: NO | EM44: NO | EN44: NO | EO44: NO | EP44: YES | EQ44: YES | ER44: NO | ES44: YES | ET44: NO | EU44: NO | EV44: NO | EW44: NO | EX44: NO | EY44: NO | EZ44: NO | FA44: NO | FB44: NO | FC44: NO | FD44: NO | FE44: NO | FF44: NO | FM44: 0 | FT44: 0 | GA44: 0 | GH44: 0 | GO44: 0 | GV44: 0 | HC44: 0 | HK44: 0 | HL44: 0 | HM44: 0 | HN44: 0 | HO44: 0 | HP44: 0 | HQ44: 0 | HR44: 0 | HY44: 0 | IF44: 0 | IM44: 0 | IT44: 0 | JA44: 0 | JB44: 0 | JC44: 0 | JD44: 0 | JE44: 0 | JF44: 0 | JG44: 0 | JH44: 0 | JT44: 0 | KA44: 0 | KH44: 0 | KO44: 0 | KV44: 0 | LC44: 0 | LJ44: 0 | LR44: 0 | LS44: 0 | LT44: 0 | LU44: 0 | LV44: 0 | LW44: 0 | LX44: 0 | LY44: 0 | OK44: 0 | QW44: 0 | TI44: 0 | VU44: 0 | YG44: 0 | YH44: 1 | YI44: 2 | YJ44: 1 | YK44: Mozilla/5.0 (Windows NT 6.1; WOW64; Trident/7.0; rv:11.0) like Gecko | YL44: 346 | YM44: NVVGK295 | YN44: INREV | YO44: UBS Global Asset Management | YP44: Tilman Hickl | YQ44: tilman.hickl@ubs.com | YS44: http://click.surveylab.co.uk/anrev-inrev-ncreif-capital-raising-2016/?survey=NVVGK295
A45: 70 | B45: NVBJC148 | C45: survey=NVBJC148 | D45: 42402.533 | E45: 42402.537 | F45: 14 | G45: 1|2|3|15| | I45: 87.51.5.162 | J45: INREV | K45: Anders Holm Pedersen | L45: Kristensen Properties | M45: =VLOOKUP(MID(O45,SEARCH("@",O45,1),LEN(O45)-SEARCH("@",O45,1)+1),[1]Sheet1!$D:$F,3,FALSE) -> M160 | N45: Director - fund manager | O45: ahp@kristensenproperties.com | P45: 4520606020 | Q45: Denmark | R45: EUR | T45: 2 | U45: 6 | V45: our funds are not fully invested | AC45: 0 | AJ45: 0 | AQ45: 0 | AX45: 0 | BE45: 0 | BL45: 0 | BM45: 0 | BN45: 0 | BO45: 0 | BP45: 0 | BQ45: 0 | BR45: 0 | BS45: 0 | BT45: FALSE | BU45: FALSE | BV45: FALSE | BW45: FALSE | BX45: FALSE | BY45: FALSE | CF45: 0 | CM45: 0 | CT45: 0 | DA45: 0 | DH45: 0 | DO45: 0 | DP45: 0 | DQ45: 0 | DR45: 0 | DS45: 0 | DT45: 0 | DU45: 0 | DV45: 0 | DW45: NO | DX45: NO | DY45: NO | DZ45: NO | EA45: NO | EB45: NO | EC45: NO | ED45: NO | EE45: NO | EF45: NO | EG45: NO | EH45: NO | EI45: NO | EJ45: NO | EK45: NO | EL45: NO | EM45: NO | EN45: NO | EO45: NO | EP45: NO | EQ45: NO | ER45: NO | ES45: NO | ET45: NO | EU45: NO | EV45: NO | EW45: NO | EX45: NO | EY45: NO | EZ45: NO | FA45: NO | FB45: NO | FC45: NO | FD45: NO | FE45: NO | FF45: NO | FM45: 0 | FT45: 0 | GA45: 0 | GH45: 0 | GO45: 0 | GV45: 0 | HC45: 0 | HK45: 0 | HL45: 0 | HM45: 0 | HN45: 0 | HO45: 0 | HP45: 0 | HQ45: 0 | HR45: 0 | HY45: 0 | IF45: 0 | IM45: 0 | IT45: 0 | JA45: 0 | JB45: 0 | JC45: 0 | JD45: 0 | JE45: 0 | JF45: 0 | JG45: 0 | JH45: 0 | JT45: 0 | KA45: 0 | KH45: 0 | KO45: 0 | KV45: 0 | LC45: 0 | LJ45: 0 | LR45: 0 | LS45: 0 | LT45: 0 | LU45: 0 | LV45: 0 | LW45: 0 | LX45: 0 | LY45: 0 | OK45: 0 | QW45: 0 | TI45: 0 | VU45: 0 | YG45: 0 | YH45: 1 | YI45: 3 | YJ45: 1 | YK45: Mozilla/5.0 (Windows NT 6.1; WOW64; Trident/7.0; rv:11.0) like Gecko | YL45: 206 | YM45: NVBJC148 | YN45: INREV | YO45: Kristensen Properties | YP45: Anders Holm-Pedersen | YQ45: ahp@kristensenproperties.com | YS45: http://click.surveylab.co.uk/anrev-inrev-ncreif-capital-raising-2016/?survey=NVBJC148
A46: 71 | B46: NVHYX519 | C46: survey=NVHYX519 | D46: 42402.624 | E46: 42402.627 | F46: 14 | G46: 1|2|3|4|5|6|7|8|9|15| | I46: 188.95.173.155 | J46: INREV | K46: Stefan Gales | L46: IBUS Asset Management BV | M46: =VLOOKUP(MID(O46,SEARCH("@",O46,1),LEN(O46)-SEARCH("@",O46,1)+1),[1]Sheet1!$D:$F,3,FALSE) -> M030 | N46: Director | O46: gales@ibus.nl | P46: 31297559000 | Q46: Netherlands | R46: EUR | T46: 1 | W46: 6 | Z46: 12 | AC46: 18 | AJ46: 0 | AQ46: 0 | AX46: 0 | BE46: 0 | BL46: 0 | BM46: 6 | BN46: 0 | BO46: 0 | BP46: 12 | BQ46: 0 | BR46: 0 | BS46: 18 | BT46: TRUE | BU46: FALSE | BV46: FALSE | BW46: FALSE | BX46: FALSE | BY46: FALSE | BZ46: 1 | CC46: 1 | CF46: 2 | CM46: 0 | CT46: 0 | DA46: 0 | DH46: 0 | DO46: 0 | DP46: 1 | DQ46: 0 | DR46: 0 | DS46: 1 | DT46: 0 | DU46: 0 | DV46: 2 | DW46: YES | DX46: NO | DY46: NO | DZ46: YES | EA46: NO | EB46: NO | EC46: NO | ED46: NO | EE46: NO | EF46: NO | EG46: NO | EH46: NO | EI46: NO | EJ46: NO | EK46: NO | EL46: NO | EM46: NO | EN46: NO | EO46: NO | EP46: NO | EQ46: NO | ER46: NO | ES46: NO | ET46: NO | EU46: NO | EV46: NO | EW46: NO | EX46: NO | EY46: NO | EZ46: NO | FA46: NO | FB46: NO | FC46: NO | FD46: NO | FE46: NO | FF46: NO | FM46: 0 | FT46: 0 | GA46: 0 | GH46: 0 | GO46: 0 | GV46: 0 | GW46: 6 | GZ46: 12 | HC46: 18 | HK46: 0 | HL46: 6 | HM46: 0 | HN46: 0 | HO46: 12 | HP46: 0 | HQ46: 0 | HR46: 18 | HY46: 0 | IF46: 0 | IM46: 0 | IT46: 0 | JA46: 0 | JB46: 0 | JC46: 0 | JD46: 0 | JE46: 0 | JF46: 0 | JG46: 0 | JH46: 0 | JK46: 100 | JT46: 0 | KA46: 0 | KH46: 0 | KO46: 0 | KV46: 0 | LC46: 0 | LD46: 6 | LG46: 12 | LJ46: 18 | LR46: 0 | LS46: 6 | LT46: 0 | LU46: 0 | LV46: 12 | LW46: 0 | LX46: 0 | LY46: 18 | OK46: 0 | QW46: 0 | TI46: 0 | VU46: 0 | YG46: 0 | YH46: 1 | YI46: 3 | YJ46: 1 | YK46: Mozilla/5.0 (Windows NT 6.1; WOW64; Trident/7.0; rv:11.0) like Gecko | YL46: 334 | YM46: NVHYX519 | YN46: INREV | YO46: The IBUS Company | YP46: Stefan Gales | YQ46: gales@ibus.nl | YS46: http://click.surveylab.co.uk/anrev-inrev-ncreif-capital-raising-2016/?survey=NVHYX519
A47: 72 | B47: NVEAX092 | C47: survey=NVEAX092 | D47: 42404.685 | E47: 42404.687 | F47: 14 | G47: 1|2|2|3|4|5|3|15| | I47: 85.115.54.201 | J47: INREV | K47: kevin aitchison | L47: knight frank investment management | M47: =VLOOKUP(MID(O47,SEARCH("@",O47,1),LEN(O47)-SEARCH("@",O47,1)+1),[1]Sheet1!$D:$F,3,FALSE) -> M04070 | N47: CEO | O47: kevin.aitchison@kf-im.com | P47: 0207 861 5103 | Q47: United Kingdom | R47: GBP | T47: 2 | U47: 6 | V47: Busy with new equity from existing clients | AC47: 0 | AJ47: 0 | AQ47: 0 | AX47: 0 | BE47: 0 | BL47: 0 | BM47: 0 | BN47: 0 | BO47: 0 | BP47: 0 | BQ47: 0 | BR47: 0 | BS47: 0 | BT47: FALSE | BU47: FALSE | BV47: FALSE | BW47: FALSE | BX47: FALSE | BY47: FALSE | CF47: 0 | CM47: 0 | CT47: 0 | DA47: 0 | DH47: 0 | DO47: 0 | DP47: 0 | DQ47: 0 | DR47: 0 | DS47: 0 | DT47: 0 | DU47: 0 | DV47: 0 | DW47: NO | DX47: NO | DY47: NO | DZ47: NO | EA47: NO | EB47: NO | EC47: NO | ED47: NO | EE47: NO | EF47: NO | EG47: NO | EH47: NO | EI47: NO | EJ47: NO | EK47: NO | EL47: NO | EM47: NO | EN47: NO | EO47: NO | EP47: NO | EQ47: NO | ER47: NO | ES47: NO | ET47: NO | EU47: NO | EV47: NO | EW47: NO | EX47: NO | EY47: NO | EZ47: NO | FA47: NO | FB47: NO | FC47: NO | FD47: NO | FE47: NO | FF47: NO | FM47: 0 | FT47: 0 | GA47: 0 | GH47: 0 | GO47: 0 | GV47: 0 | HC47: 0 | HK47: 0 | HL47: 0 | HM47: 0 | HN47: 0 | HO47: 0 | HP47: 0 | HQ47: 0 | HR47: 0 | HY47: 0 | IF47: 0 | IM47: 0 | IT47: 0 | JA47: 0 | JB47: 0 | JC47: 0 | JD47: 0 | JE47: 0 | JF47: 0 | JG47: 0 | JH47: 0 | JT47: 0 | KA47: 0 | KH47: 0 | KO47: 0 | KV47: 0 | LC47: 0 | LJ47: 0 | LR47: 0 | LS47: 0 | LT47: 0 | LU47: 0 | LV47: 0 | LW47: 0 | LX47: 0 | LY47: 0 | OK47: 0 | QW47: 0 | TI47: 0 | VU47: 0 | YG47: 0 | YH47: 1 | YI47: 3 | YJ47: 1 | YK47: Mozilla/5.0 (Windows NT 6.3; WOW64; Trident/7.0; Touch; rv:11.0) like Gecko | YL47: 204 | YM47: NVEAX092 | YN47: INREV | YO47: KNIGHT FRANK INVESTMENT MANAGEMENT | YP47: KEVIN AITCHISON | YQ47: kevin.aitchison@kf-im.com | YS47: http://click.surveylab.co.uk/anrev-inrev-ncreif-capital-raising-2016/?survey=NVEAX092
A48: 73 | B48: CFTXQ584 | C48: survey=CFTXQ584 | D48: 42416.381 | E48: 42416.41 | F48: 14 | G48: 1|2|2|2|3|4|4|5|3|4|5|5|4|5|4|5|6|7|2|3|4|5|6|7|8|9|10|11|15| | I48: 199.242.0.29 | J48: NCREIF | K48: Paul Winters | L48: BlackRock | M48: =VLOOKUP(MID(O48,SEARCH("@",O48,1),LEN(O48)-SEARCH("@",O48,1)+1),[1]Sheet1!$D:$F,3,FALSE) -> M181 | N48: Director | O48: paul.witners@blackrock.com | P48: 2077434052 | Q48: United States | R48: USD | T48: 1 | W48: 491 | X48: 80 | AB48: 250 | AC48: 821 | AD48: 240 | AJ48: 240 | AK48: 223 | AL48: 538 | AP48: 174 | AQ48: 935 | AX48: 0 | BE48: 0 | BL48: 0 | BM48: 954 | BN48: 618 | BO48: 0 | BP48: 0 | BQ48: 0 | BR48: 424 | BS48: 1996 | BT48: TRUE | BU48: TRUE | BV48: TRUE | BW48: FALSE | BX48: FALSE | BY48: FALSE | BZ48: 3 | CA48: 1 | CE48: 1 | CF48: 5 | CG48: 2 | CM48: 2 | CN48: 1 | CO48: 2 | CS48: 1 | CT48: 4 | DA48: 0 | DH48: 0 | DO48: 0 | DP48: 6 | DQ48: 3 | DR48: 0 | DS48: 0 | DT48: 0 | DU48: 2 | DV48: 11 | DW48: YES | DX48: YES | DY48: NO | DZ48: NO | EA48: NO | EB48: YES | EC48: YES | ED48: NO | EE48: NO | EF48: NO | EG48: NO | EH48: NO | EI48: YES | EJ48: YES | EK48: NO | EL48: NO | EM48: NO | EN48: YES | EO48: NO | EP48: NO | EQ48: NO | ER48: NO | ES48: NO | ET48: NO | EU48: NO | EV48: NO | EW48: NO | EX48: NO | EY48: NO | EZ48: NO | FA48: NO | FB48: NO | FC48: NO | FD48: NO | FE48: NO | FF48: NO | FG48: 442 | FH48: 80 | FM48: 522 | FT48: 0 | GA48: 0 | GB48: 432 | GC48: 538 | GH48: 970 | GO48: 0 | GV48: 0 | GW48: 51 | HC48: 51 | HD48: not available | HE48: 29 | HJ48: 424 | HK48: 453 | HL48: 954 | HM48: 618 | HN48: 0 | HO48: 0 | HP48: 0 | HQ48: 424 | HR48: 1996 | HS48: 520 | HX48: 286 | HY48: 806 | HZ48: 211 | IF48: 211 | IG48: 223 | IH48: 618 | IL48: 138 | IM48: 979 | IT48: 0 | JA48: 0 | JB48: 954 | JC48: 618 | JD48: 0 | JE48: 0 | JF48: 0 | JG48: 424 | JH48: 1996 | JI48: 0 | JL48: difficult to classify between existing and new | JM48: 100 | JN48: 356 | JT48: 356 | KA48: 0 | KH48: 0 | KI48: 56 | KJ48: 80 | KO48: 136 | KV48: 0 | LC48: 0 | LD48: 52 | LJ48: 52 | LL48: 27 | LQ48: 250 | LR48: 277 | LS48: 491 | LT48: 80 | LU48: 0 | LV48: 0 | LW48: 0 | LX48: 250 | LY48: 821 | LZ48: 70 | MF48: 70 | MU48: 170 | NA48: 170 | OE48: 240 | OK48: 240 | PG48: 297 | PH48: 448 | PM48: 745 | QJ48: 16 | QO48: 174 | QP48: 190 | QQ48: 313 | QR48: 448 | QV48: 174 | QW48: 935 | TI48: 0 | VU48: 0 | YG48: 0 | YH48: 1 | YI48: 3 | YJ48: 1 | YK48: Mozilla/5.0 (Windows NT 6.1; WOW64; Trident/7.0; rv:11.0) like Gecko | YL48: 56 | YM48: CFTXQ584 | YN48: NCREIF | YO48: Blackrock | YS48: http://click.surveylab.co.uk/anrev-inrev-ncreif-capital-raising-2016/?survey=CFTXQ584
A49: 74 | B49: CFDRU625 | C49: survey=CFDRU625 | D49: 42418.749 | E49: 42418.766 | F49: 14 | G49: 1|2|2|2|3|4|5|6|7|8|9|10|11|11|15| | I49: 208.68.247.152 | J49: NCREIF | K49: Tom Pentolino | L49: CBRE Global Investors LLC | M49: =VLOOKUP(MID(O49,SEARCH("@",O49,1),LEN(O49)-SEARCH("@",O49,1)+1),[1]Sheet1!$D:$F,3,FALSE) -> M231 | N49: Accounting Manager | O49: tom.pentolino@cbreglobalinvestors.com | P49: 213-683-4122 | Q49: United States | R49: USD | T49: 1 | W49: 1618 | X49: 3021 | AC49: 4639 | AD49: 368 | AE49: 422 | AJ49: 790 | AK49: 1098 | AL49: 475 | AQ49: 1573 | AX49: 0 | BE49: 0 | BL49: 0 | BM49: 3084 | BN49: 3918 | BO49: 0 | BP49: 0 | BQ49: 0 | BR49: 0 | BS49: 7002 | BT49: TRUE | BU49: TRUE | BV49: TRUE | BW49: FALSE | BX49: FALSE | BY49: FALSE | BZ49: 82 | CA49: 26 | CF49: 108 | CG49: 13 | CH49: 2 | CM49: 15 | CN49: 16 | CO49: 4 | CT49: 20 | DA49: 0 | DH49: 0 | DO49: 0 | DP49: 111 | DQ49: 32 | DR49: 0 | DS49: 0 | DT49: 0 | DU49: 0 | DV49: 143 | DW49: YES | DX49: YES | DY49: NO | DZ49: NO | EA49: NO | EB49: NO | EC49: YES | ED49: YES | EE49: NO | EF49: NO | EG49: NO | EH49: NO | EI49: YES | EJ49: YES | EK49: NO | EL49: NO | EM49: NO | EN49: NO | EO49: NO | EP49: NO | EQ49: NO | ER49: NO | ES49: NO | ET49: NO | EU49: NO | EV49: NO | EW49: NO | EX49: NO | EY49: NO | EZ49: NO | FA49: NO | FB49: NO | FC49: NO | FD49: NO | FE49: NO | FF49: NO | FG49: 1679 | FH49: 1920 | FM49: 3599 | FN49: 360 | FO49: 1075 | FT49: 1435 | FU49: 111 | FV49: 422 | GA49: 533 | GH49: 0 | GO49: 0 | GV49: 0 | GW49: 124 | GX49: 53 | HC49: 177 | HD49: Corporations/Other | HE49: 809 | HF49: 449 | HK49: 1258 | HL49: 3083 | HM49: 3919 | HN49: 0 | HO49: 0 | HP49: 0 | HQ49: 0 | HR49: 7002 | HS49: 1618 | HT49: 3021 | HY49: 4639 | HZ49: 244 | IA49: 422 | IF49: 666 | IG49: 1098 | IH49: 422 | IM49: 1520 | IT49: 0 | JA49: 0 | JB49: 2960 | JC49: 3865 | JD49: 0 | JE49: 0 | JF49: 0 | JG49: 0 | JH49: 6825 | JJ49: 10 | JK49: 90 | JN49: 886 | JO49: 1770 | JT49: 2656 | JU49: 247 | JV49: 1075 | KA49: 1322 | KB49: 55 | KH49: 55 | KO49: 0 | KV49: 0 | LC49: 0 | LJ49: 0 | LK49: Corporations/other | LL49: 430 | LM49: 176 | LR49: 606 | LS49: 1618 | LT49: 3021 | LU49: 0 | LV49: 0 | LW49: 0 | LX49: 0 | LY49: 4639 | LZ49: 61 | MF49: 61 | MG49: 55 | MM49: 55 | MN49: 56 | MO49: 422 | MT49: 478 | NP49: 124 | NV49: 124 | NW49: Corporations/Other | NX49: 72 | OD49: 72 | OE49: 368 | OF49: 422 | OK49: 790 | OL49: 732 | OM49: 150 | OR49: 882 | OS49: 58 | OY49: 58 | QC49: 53 | QH49: 53 | QI49: Corporations/Other | QJ49: 307 | QK49: 273 | QP49: 580 | QQ49: 1097 | QR49: 476 | QW49: 1573 | TI49: 0 | VU49: 0 | YG49: 0 | YH49: 1 | YI49: 2 | YJ49: 1 | YK49: Mozilla/5.0 (Windows NT 6.1; WOW64; Trident/7.0; rv:11.0) like Gecko | YL49: 77 | YM49: CFDRU625 | YN49: NCREIF | YO49: CBRE Global Investors | YS49: http://click.surveylab.co.uk/anrev-inrev-ncreif-capital-raising-2016/?survey=CFDRU625
A50: 75 | B50: CFWQL796 | C50: survey=CFWQL796 | D50: 42417.042 | E50: 42411.646 | F50: 1 | G50: 1|2|2|2|2|3|4|5|6|7|8|9|11|2|3|4|5|6|7|8|9|11|2|3|4|5|6|7|8|9|11|15|2| | I50: 63.66.112.5 | J50: NCREIF | K50: Barbara Epler | L50: Cornerstone Real Estate Advisers LLC | M50: =VLOOKUP(MID(O50,SEARCH("@",O50,1),LEN(O50)-SEARCH("@",O50,1)+1),[1]Sheet1!$D:$F,3,FALSE) -> NC032 | N50: Senior Marketing Specialist | O50: bepler@cornerstoneadvisers.com | P50: 8605092317 | Q50: United States | R50: USD | T50: 1 | X50: 172 | AB50: 200 | AC50: 372 | AJ50: 0 | AK50: 318 | AP50: 800 | AQ50: 1118 | AX50: 0 | BE50: 0 | BL50: 0 | BM50: 318 | BN50: 172 | BO50: 0 | BP50: 0 | BQ50: 0 | BR50: 1000 | BS50: 1490 | BT50: TRUE | BU50: FALSE | BV50: TRUE | BW50: FALSE | BX50: FALSE | BY50: FALSE | CA50: 3 | CE50: 1 | CF50: 4 | CM50: 0 | CN50: 3 | CS50: 3 | CT50: 6 | DA50: 0 | DH50: 0 | DO50: 0 | DP50: 3 | DQ50: 3 | DR50: 0 | DS50: 0 | DT50: 0 | DU50: 4 | DV50: 10 | DW50: NO | DX50: YES | DY50: NO | DZ50: NO | EA50: NO | EB50: YES | EC50: NO | ED50: NO | EE50: NO | EF50: NO | EG50: NO | EH50: NO | EI50: YES | EJ50: NO | EK50: NO | EL50: NO | EM50: NO | EN50: YES | EO50: NO | EP50: NO | EQ50: NO | ER50: NO | ES50: NO | ET50: NO | EU50: NO | EV50: NO | EW50: NO | EX50: NO | EY50: NO | EZ50: NO | FA50: NO | FB50: NO | FC50: NO | FD50: NO | FE50: NO | FF50: NO | FG50: 139 | FL50: 700 | FM50: 839 | FN50: 105 | FS50: 220 | FT50: 325 | GA50: 0 | GB50: 4 | GH50: 4 | GI50: 44 | GO50: 44 | GP50: 22 | GV50: 22 | HC50: 0 | HD50: Financial institutions, employee investors, other corporate/private | HE50: 4 | HF50: 172 | HJ50: 80 | HK50: 256 | HL50: 318 | HM50: 172 | HN50: 0 | HO50: 0 | HP50: 0 | HQ50: 1000 | HR50: 1490 | HT50: 172 | HY50: 172 | IE50: 500 | IF50: 500 | IG50: 318 | IL50: 500 | IM50: 818 | IT50: 0 | JA50: 0 | JB50: 318 | JC50: 172 | JD50: 0 | JE50: 0 | JF50: 0 | JG50: 1000 | JH50: 1490 | JI50: 0 | JJ50: 10 | JK50: 90 | JT50: 0 | JZ50: 200 | KA50: 200 | KH50: 0 | KO50: 0 | KV50: 0 | LC50: 0 | LJ50: 0 | LK50: Other corporate | LM50: 172 | LR50: 172 | LS50: 0 | LT50: 172 | LU50: 0 | LV50: 0 | LW50: 0 | LX50: 200 | LY50: 372 | OK50: 0 | OL50: 139 | OQ50: 700 | OS50: 105 | OX50: 20 | PG50: 4 | PN50: 44 | PU50: 22 | QI50: Financial institutions, employee investors, other private | QJ50: 4 | QO50: 80 | QW50: 1118 | TI50: 0 | VU50: 0 | YG50: 0 | YH50: 2 | YI50: 1 | YJ50: 1 | YK50: Mozilla/5.0 (compatible; MSIE 10.0; Windows NT 6.1; WOW64; Trident/6.0) | YL50: 96 | YM50: CFWQL796 | YN50: NCREIF | YO50: Cornerstone Real Estate Advisers LLC | YS50: http://click.surveylab.co.uk/anrev-inrev-ncreif-capital-raising-2016/?survey=CFWQL796
A51: 78 | B51: CFXLY224 | C51: survey=CFXLY224 | D51: 42418.844 | E51: 42418.847 | F51: 14 | G51: 1|2|3|4|5|6|7|8|11|2|3|4|5|6|7|8|11|15| | I51: 216.74.249.19 | J51: NCREIF | K51: Lisa Wallis | L51: Sarofim Realty Advisors | M51: =VLOOKUP(MID(O51,SEARCH("@",O51,1),LEN(O51)-SEARCH("@",O51,1)+1),[1]Sheet1!$D:$F,3,FALSE) -> NC003 | N51: Portfolio Controller | O51: lwallis@sraco.com | P51: 214-692-4266 | Q51: United States | R51: USD | T51: 1 | AC51: 0 | AJ51: 0 | AL51: 300 | AQ51: 300 | AX51: 0 | BE51: 0 | BL51: 0 | BM51: 0 | BN51: 300 | BO51: 0 | BP51: 0 | BQ51: 0 | BR51: 0 | BS51: 300 | BT51: FALSE | BU51: FALSE | BV51: TRUE | BW51: FALSE | BX51: FALSE | BY51: FALSE | CF51: 0 | CM51: 0 | CO51: 1 | CT51: 1 | DA51: 0 | DH51: 0 | DO51: 0 | DP51: 0 | DQ51: 1 | DR51: 0 | DS51: 0 | DT51: 0 | DU51: 0 | DV51: 1 | DW51: NO | DX51: NO | DY51: NO | DZ51: NO | EA51: NO | EB51: NO | EC51: NO | ED51: NO | EE51: NO | EF51: NO | EG51: NO | EH51: NO | EI51: NO | EJ51: YES | EK51: NO | EL51: NO | EM51: NO | EN51: NO | EO51: NO | EP51: NO | EQ51: NO | ER51: NO | ES51: NO | ET51: NO | EU51: NO | EV51: NO | EW51: NO | EX51: NO | EY51: NO | EZ51: NO | FA51: NO | FB51: NO | FC51: NO | FD51: NO | FE51: NO | FF51: NO | FH51: 300 | FM51: 300 | FT51: 0 | GA51: 0 | GH51: 0 | GO51: 0 | GV51: 0 | HC51: 0 | HK51: 0 | HL51: 0 | HM51: 300 | HN51: 0 | HO51: 0 | HP51: 0 | HQ51: 0 | HR51: 300 | HY51: 0 | IF51: 0 | IH51: 300 | IM51: 300 | IT51: 0 | JA51: 0 | JB51: 0 | JC51: 300 | JD51: 0 | JE51: 0 | JF51: 0 | JG51: 0 | JH51: 300 | JK51: 100 | JT51: 0 | KA51: 0 | KH51: 0 | KO51: 0 | KV51: 0 | LC51: 0 | LJ51: 0 | LR51: 0 | LS51: 0 | LT51: 0 | LU51: 0 | LV51: 0 | LW51: 0 | LX51: 0 | LY51: 0 | OK51: 0 | OM51: 300 | QW51: 300 | TI51: 0 | VU51: 0 | YG51: 0 | YH51: 1 | YI51: 3 | YJ51: 1 | YK51: Mozilla/5.0 (Windows NT 6.1; rv:43.0) Gecko/20100101 Firefox/43.0 | YL51: 308 | YM51: CFXLY224 | YN51: NCREIF | YO51: Sarofim Realty Advisors | YS51: http://click.surveylab.co.uk/anrev-inrev-ncreif-capital-raising-2016/?survey=CFXLY224
A52: 79 | B52: CFZPE965 | C52: survey=CFZPE965 | D52: 42411.846 | E52: 42411.846 | F52: 2 | G52: 1|2|2|2|3|2|2|3|4|5|6|7|8|11|2|3|4|5|6|7|8|11|2|3|4|5|6|7|8|11|15|2|3| | I52: 70.192.23.87 | J52: NCREIF | K52: Brandon Millen | L52: Intercontinental Real Estate Corp. | M52: =VLOOKUP(MID(O52,SEARCH("@",O52,1),LEN(O52)-SEARCH("@",O52,1)+1),[1]Sheet1!$D:$F,3,FALSE) -> NC007 | N52: Associate Director, Investment Reporting and Performance Mea | O52: Brandonm@intercontinental.net | P52: 617-779-0490 | Q52: United States | R52: USD | T52: 1 | AC52: 0 | AJ52: 0 | AK52: 883.236 | AQ52: 883.24 | AX52: 0 | BE52: 0 | BL52: 0 | BM52: 883.24 | BN52: 0 | BO52: 0 | BP52: 0 | BQ52: 0 | BR52: 0 | BS52: 883.24 | BT52: FALSE | BU52: FALSE | BV52: TRUE | BW52: FALSE | BX52: FALSE | BY52: FALSE | CF52: 0 | CM52: 0 | CN52: 1 | CT52: 1 | DA52: 0 | DH52: 0 | DO52: 0 | DP52: 1 | DQ52: 0 | DR52: 0 | DS52: 0 | DT52: 0 | DU52: 0 | DV52: 1 | DW52: NO | DX52: NO | DY52: NO | DZ52: NO | EA52: NO | EB52: NO | EC52: NO | ED52: NO | EE52: NO | EF52: NO | EG52: NO | EH52: NO | EI52: YES | EJ52: NO | EK52: NO | EL52: NO | EM52: NO | EN52: NO | EO52: NO | EP52: NO | EQ52: NO | ER52: NO | ES52: NO | ET52: NO | EU52: NO | EV52: NO | EW52: NO | EX52: NO | EY52: NO | EZ52: NO | FA52: NO | FB52: NO | FC52: NO | FD52: NO | FE52: NO | FF52: NO | FG52: 720.886 | FM52: 720.89 | FT52: 0 | GA52: 0 | GH52: 0 | GI52: 158.4 | GO52: 158.4 | GV52: 0 | GW52: 3.95 | HC52: 3.95 | HK52: 0 | HL52: 883.24 | HM52: 0 | HN52: 0 | HO52: 0 | HP52: 0 | HQ52: 0 | HR52: 883.24 | HY52: 0 | IF52: 0 | IG52: 883.24 | IM52: 883.24 | IT52: 0 | JA52: 0 | JB52: 883.24 | JC52: 0 | JD52: 0 | JE52: 0 | JF52: 0 | JG52: 0 | JH52: 883.24 | JK52: 100 | JT52: 0 | KA52: 0 | KH52: 0 | KO52: 0 | KV52: 0 | LC52: 0 | LJ52: 0 | LR52: 0 | LS52: 0 | LT52: 0 | LU52: 0 | LV52: 0 | LW52: 0 | LX52: 0 | LY52: 0 | OK52: 0 | OL52: 720.886 | PN52: 158.4 | QB52: 3.95 | QW52: 883.24 | TI52: 0 | VU52: 0 | YG52: 0 | YH52: 1 | YI52: 3 | YJ52: 1 | YK52: Mozilla/5.0 (iPhone; CPU iPhone OS 9_2_1 like Mac OS X) AppleWebKit/601.1.46 (KHTML, like Gecko) Version/9.0 Mobile/13D15 Safari/601.1 | YL52: 187 | YM52: CFZPE965 | YN52: NCREIF | YO52: Intercontinental Real Estate Corp. | YS52: http://click.surveylab.co.uk/anrev-inrev-ncreif-capital-raising-2016/?survey=CFZPE965
A53: 80 | B53: CFFNF859 | C53: survey=CFFNF859 | D53: 42422.127 | E53: 42422.132 | F53: 14 | G53: 1|2|2|2|3|4|5|6|7|8|9|10|11|12|15| | I53: 170.74.231.19 | J53: NCREIF | K53: Martijn van Eldik | L53: Morgan Stanley Real Estate Investing | M53: =VLOOKUP(MID(O53,SEARCH("@",O53,1),LEN(O53)-SEARCH("@",O53,1)+1),[1]Sheet1!$D:$F,3,FALSE) -> M0045 | N53: Executive Director | O53: martijn.van.eldik@morganstanley.com | P53: 6568346338 | Q53: United States | R53: USD | T53: 1 | Z53: 229 | AC53: 229 | AD53: 200 | AJ53: 200 | AK53: 1776 | AQ53: 1776 | AR53: 880 | AX53: 880 | BE53: 0 | BL53: 0 | BM53: 2856 | BN53: 0 | BO53: 0 | BP53: 229 | BQ53: 0 | BR53: 0 | BS53: 3085 | BT53: TRUE | BU53: TRUE | BV53: TRUE | BW53: TRUE | BX53: FALSE | BY53: FALSE | CC53: 1 | CF53: 1 | CG53: 1 | CM53: 1 | CN53: 1 | CT53: 1 | CU53: 1 | DA53: 1 | DH53: 0 | DO53: 0 | DP53: 3 | DQ53: 0 | DR53: 0 | DS53: 1 | DT53: 0 | DU53: 0 | DV53: 4 | DW53: NO | DX53: NO | DY53: NO | DZ53: YES | EA53: NO | EB53: NO | EC53: YES | ED53: NO | EE53: NO | EF53: NO | EG53: NO | EH53: NO | EI53: YES | EJ53: NO | EK53: NO | EL53: NO | EM53: NO | EN53: NO | EO53: YES | EP53: NO | EQ53: NO | ER53: NO | ES53: NO | ET53: NO | EU53: NO | EV53: NO | EW53: NO | EX53: NO | EY53: NO | EZ53: NO | FA53: NO | FB53: NO | FC53: NO | FD53: NO | FE53: NO | FF53: NO | FG53: 1715 | FJ53: 115 | FM53: 1830 | FN53: 163 | FT53: 163 | FU53: 282 | FX53: 114 | GA53: 396 | GH53: 0 | GI53: 104 | GO53: 104 | GP53: 450 | GV53: 450 | GW53: 143 | HC53: 143 | HK53: 0 | HL53: 2857 | HM53: 0 | HN53: 0 | HO53: 229 | HP53: 0 | HQ53: 0 | HR53: 3086 | HS53: 1002 | HY53: 1002 | HZ53: 347 | IC53: 229 | IF53: 576 | IG53: 1508 | IM53: 1508 | IT53: 0 | JA53: 0 | JB53: 2857 | JC53: 0 | JD53: 0 | JE53: 229 | JF53: 0 | JG53: 0 | JH53: 3086 | JJ53: 15 | JK53: 85 | JQ53: 115 | JT53: 115 | KA53: 0 | KE53: 114 | KH53: 114 | KO53: 0 | KV53: 0 | LC53: 0 | LJ53: 0 | LR53: 0 | LS53: 0 | LT53: 0 | LU53: 0 | LV53: 229 | LW53: 0 | LX53: 0 | LY53: 229 | LZ53: 200 | MF53: 200 | OE53: 200 | OK53: 200 | OL53: 1090 | OR53: 1090 | OS53: 163 | OY53: 163 | PN53: 104 | PT53: 104 | PU53: 400 | QA53: 400 | QB53: 20 | QH53: 20 | QQ53: 1777 | QW53: 1777 | QX53: 425 | RD53: 425 | RL53: 282 | RR53: 282 | SG53: 50 | SM53: 50 | SN53: 123 | ST53: 123 | TC53: 880 | TI53: 880 | VU53: 0 | YG53: 0 | YH53: 1 | YI53: 3 | YJ53: 1 | YK53: Mozilla/5.0 (Windows NT 6.1; WOW64; Trident/7.0; MSBrowserIE; rv:11.0) like Gecko | YL53: 244 | YM53: CFFNF859 | YN53: NCREIF | YO53: Morgan Stanley | YS53: http://click.surveylab.co.uk/anrev-inrev-ncreif-capital-raising-2016/?survey=CFFNF859
A54: 81 | B54: CFMFA275 | C54: survey=CFMFA275 | D54: 42402.89 | F54: 10 | G54: 1|2|3|4|5|6|7|8|11| | I54: 98.79.94.25 | J54: NCREIF | K54: Jay Butterfield | L54: American Realty Advisors | M54: =VLOOKUP(MID(O54,SEARCH("@",O54,1),LEN(O54)-SEARCH("@",O54,1)+1),[1]Sheet1!$D:$F,3,FALSE) -> NC029 | N54: Managing Director | O54: jbutterfield@americanreal.com | P54: 1-818-409-3243 | Q54: United States | R54: USD | T54: 1 | AC54: 0 | AJ54: 0 | AK54: 400 | AQ54: 400 | AX54: 0 | BE54: 0 | BL54: 0 | BM54: 400 | BN54: 0 | BO54: 0 | BP54: 0 | BQ54: 0 | BR54: 0 | BS54: 400 | BT54: FALSE | BU54: FALSE | BV54: TRUE | BW54: FALSE | BX54: FALSE | BY54: FALSE | CF54: 0 | CM54: 0 | CN54: 2 | CT54: 2 | DA54: 0 | DH54: 0 | DO54: 0 | DP54: 2 | DQ54: 0 | DR54: 0 | DS54: 0 | DT54: 0 | DU54: 0 | DV54: 2 | DW54: NO | DX54: NO | DY54: NO | DZ54: NO | EA54: NO | EB54: NO | EC54: NO | ED54: NO | EE54: NO | EF54: NO | EG54: NO | EH54: NO | EI54: YES | EJ54: NO | EK54: NO | EL54: NO | EM54: NO | EN54: NO | EO54: NO | EP54: NO | EQ54: NO | ER54: NO | ES54: NO | ET54: NO | EU54: NO | EV54: NO | EW54: NO | EX54: NO | EY54: NO | EZ54: NO | FA54: NO | FB54: NO | FC54: NO | FD54: NO | FE54: NO | FF54: NO | FG54: 375 | FM54: 375 | FN54: 25 | FT54: 25 | GA54: 0 | GH54: 0 | GO54: 0 | GV54: 0 | HC54: 0 | HK54: 0 | HL54: 400 | HM54: 0 | HN54: 0 | HO54: 0 | HP54: 0 | HQ54: 0 | HR54: 400 | HS54: 35 | HY54: 35 | IF54: 0 | IG54: 365 | IM54: 365 | IT54: 0 | JA54: 0 | JB54: 400 | JC54: 0 | JD54: 0 | JE54: 0 | JF54: 0 | JG54: 0 | JH54: 400 | JJ54: 60 | JK54: 40 | JT54: 0 | KA54: 0 | KH54: 0 | KO54: 0 | KV54: 0 | LC54: 0 | LJ54: 0 | LR54: 0 | LS54: 0 | LT54: 0 | LU54: 0 | LV54: 0 | LW54: 0 | LX54: 0 | LY54: 0 | OK54: 0 | OL54: 375 | OR54: 375 | OS54: 25 | OY54: 25 | QQ54: 400 | QW54: 400 | YK54: Mozilla/5.0 (compatible; MSIE 10.0; Windows NT 6.1; WOW64; Trident/6.0) | YL54: 29 | YM54: CFMFA275 | YN54: NCREIF | YO54: American Realty Advisors | YS54: http://click.surveylab.co.uk/anrev-inrev-ncreif-capital-raising-2016/?survey=CFMFA275
A55: 82 | B55: ANCAD263 | C55: survey=ANCAD263 | D55: 42417.494 | E55: 42417.501 | F55: 14 | G55: 1|2|3|4|5|2|2|3|4|5|6|7|8|9|10|15|2|2|3|4|5|6|7|8|9|10|2|3|4|5|6|7|8|9|9|10|15| | I55: 80.247.61.10 | J55: ANREV | K55: Christopher Andrews | L55: M&G RealEstate | M55: =VLOOKUP(MID(O55,SEARCH("@",O55,1),LEN(O55)-SEARCH("@",O55,1)+1),[1]Sheet1!$D:$F,3,FALSE) -> M010 | N55: Head of Client Relationships & Marketing | O55: chris.j.andrews@mandg.com | P55: 6564365331 | Q55: United Kingdom | R55: GBP | T55: 1 | W55: 809.58 | AC55: 809.58 | AD55: 363.37 | AJ55: 363.37 | AQ55: 0 | AX55: 0 | BE55: 0 | BL55: 0 | BM55: 1172.95 | BN55: 0 | BO55: 0 | BP55: 0 | BQ55: 0 | BR55: 0 | BS55: 1172.95 | BT55: TRUE | BU55: TRUE | BV55: FALSE | BW55: FALSE | BX55: FALSE | BY55: FALSE | BZ55: 4 | CF55: 4 | CG55: 1 | CM55: 1 | CT55: 0 | DA55: 0 | DH55: 0 | DO55: 0 | DP55: 5 | DQ55: 0 | DR55: 0 | DS55: 0 | DT55: 0 | DU55: 0 | DV55: 5 | DW55: YES | DX55: NO | DY55: NO | DZ55: NO | EA55: NO | EB55: NO | EC55: YES | ED55: NO | EE55: NO | EF55: NO | EG55: NO | EH55: NO | EI55: NO | EJ55: NO | EK55: NO | EL55: NO | EM55: NO | EN55: NO | EO55: NO | EP55: NO | EQ55: NO | ER55: NO | ES55: NO | ET55: NO | EU55: NO | EV55: NO | EW55: NO | EX55: NO | EY55: NO | EZ55: NO | FA55: NO | FB55: NO | FC55: NO | FD55: NO | FE55: NO | FF55: NO | FG55: 445.62 | FM55: 445.62 | FN55: 641.82 | FT55: 641.82 | GA55: 0 | GH55: 0 | GI55: 1.11 | GO55: 1.11 | GP55: 60.64 | GV55: 60.64 | HC55: 0 | HD55: Parent company seed investor | HE55: 23.77 | HK55: 23.77 | HL55: 1172.96 | HM55: 0 | HN55: 0 | HO55: 0 | HP55: 0 | HQ55: 0 | HR55: 1172.96 | HS55: 1099.2 | HY55: 1099.2 | HZ55: 47.94 | IF55: 47.94 | IG55: 25.81 | IM55: 25.81 | IT55: 0 | JA55: 0 | JB55: 1172.95 | JC55: 0 | JD55: 0 | JE55: 0 | JF55: 0 | JG55: 0 | JH55: 1172.95 | JK55: 100 | JN55: 394.78 | JT55: 394.78 | JU55: 346.94 | KA55: 346.94 | KH55: 0 | KO55: 0 | KP55: 1.1 | KV55: 1.1 | KW55: 43 | LC55: 43 | LJ55: 0 | LK55: Parent company seed investor | LL55: 23.77 | LR55: 23.77 | LS55: 809.59 | LT55: 0 | LU55: 0 | LV55: 0 | LW55: 0 | LX55: 0 | LY55: 809.59 | LZ55: 50.84 | MG55: 294.89 | NI55: 17.64 | OK55: 363.37 | QW55: 0 | TI55: 0 | VU55: 0 | YG55: 0 | YH55: 1 | YI55: 3 | YJ55: 1 | YK55: Mozilla/5.0 (Windows NT 6.1; WOW64; Trident/7.0; rv:11.0) like Gecko | YL55: 222 | YM55: ANCAD263 | YN55: ANREV | YO55: M&G | YP55: Christopher Andrews | YQ55: chris.j.andrews@mandg.com | YS55: http://click.surveylab.co.uk/anrev-inrev-ncreif-capital-raising-2016/?survey=ANCAD263
A56: 83 | B56: CFKRK156 | C56: survey=CFKRK156 | D56: 42409.681 | E56: 42409.684 | F56: 14 | G56: 1|2|2|3|4|5|6|7|8|11|15| | I56: 70.210.157.80 | J56: NCREIF | K56: gregory fowler | L56: fpa multifamily | M56: =VLOOKUP(MID(O56,SEARCH("@",O56,1),LEN(O56)-SEARCH("@",O56,1)+1),[1]Sheet1!$D:$F,3,FALSE) -> NC033 | N56: general partner | O56: greg@fpamf.com | P56: 4159253100 | Q56: United States | R56: USD | T56: 1 | AC56: 0 | AJ56: 0 | AK56: 522 | AQ56: 522 | AX56: 0 | BE56: 0 | BL56: 0 | BM56: 522 | BN56: 0 | BO56: 0 | BP56: 0 | BQ56: 0 | BR56: 0 | BS56: 522 | BT56: FALSE | BU56: FALSE | BV56: TRUE | BW56: FALSE | BX56: FALSE | BY56: FALSE | CF56: 0 | CM56: 0 | CN56: 2 | CT56: 2 | DA56: 0 | DH56: 0 | DO56: 0 | DP56: 2 | DQ56: 0 | DR56: 0 | DS56: 0 | DT56: 0 | DU56: 0 | DV56: 2 | DW56: NO | DX56: NO | DY56: NO | DZ56: NO | EA56: NO | EB56: NO | EC56: NO | ED56: NO | EE56: NO | EF56: NO | EG56: NO | EH56: NO | EI56: YES | EJ56: NO | EK56: NO | EL56: NO | EM56: NO | EN56: NO | EO56: NO | EP56: NO | EQ56: NO | ER56: NO | ES56: NO | ET56: NO | EU56: NO | EV56: NO | EW56: NO | EX56: NO | EY56: NO | EZ56: NO | FA56: NO | FB56: NO | FC56: NO | FD56: NO | FE56: NO | FF56: NO | FG56: 60 | FM56: 60 | FT56: 0 | GA56: 0 | GH56: 0 | GI56: 295 | GO56: 295 | GP56: 35 | GV56: 35 | GW56: 132 | HC56: 132 | HK56: 0 | HL56: 522 | HM56: 0 | HN56: 0 | HO56: 0 | HP56: 0 | HQ56: 0 | HR56: 522 | HY56: 0 | IF56: 0 | IG56: 522 | IM56: 522 | IT56: 0 | JA56: 0 | JB56: 522 | JC56: 0 | JD56: 0 | JE56: 0 | JF56: 0 | JG56: 0 | JH56: 522 | JI56: 0 | JJ56: 20 | JK56: 80 | JT56: 0 | KA56: 0 | KH56: 0 | KO56: 0 | KV56: 0 | LC56: 0 | LJ56: 0 | LR56: 0 | LS56: 0 | LT56: 0 | LU56: 0 | LV56: 0 | LW56: 0 | LX56: 0 | LY56: 0 | OK56: 0 | OL56: 60 | OR56: 60 | PN56: 295 | PT56: 295 | PU56: 35 | QA56: 35 | QB56: 132 | QH56: 132 | QQ56: 522 | QW56: 522 | TI56: 0 | VU56: 0 | YG56: 0 | YH56: 3 | YI56: 3 | YJ56: 1 | YK56: Mozilla/5.0 (iPhone; CPU iPhone OS 9_2_1 like Mac OS X) AppleWebKit/601.1.46 (KHTML, like Gecko) Version/9.0 Mobile/13D15 Safari/601.1 | YL56: 136 | YM56: CFKRK156 | YN56: NCREIF | YO56: FPA Multifamily | YP56: Gregory Fowler | YQ56: greg@fpamf.com | YS56: http://click.surveylab.co.uk/anrev-inrev-ncreif-capital-raising-2016/?survey=CFKRK156
A57: 84 | B57: NVWAE407 | C57: survey=NVWAE407 | D57: 42424.437 | E57: 42419.485 | F57: 2 | G57: 1|2|2|3|4|5|6|3|2|2|3|4|5|6|2|3|4|5|6|7|8|9|12|15|2|3|2|3|4|5|4|5|6|6|7|8|9|12|15|2|3| | I57: 194.203.81.11 | J57: INREV | K57: Rebecca Madsen | L57: Grosvenor Fund Management | M57: =VLOOKUP(MID(O57,SEARCH("@",O57,1),LEN(O57)-SEARCH("@",O57,1)+1),[1]Sheet1!$D:$F,3,FALSE) -> M052 | N57: Analyst, Capital Markets | O57: rebecca.madsen@grosvenor.com | P57: +44 20 7312 6345 | Q57: United Kingdom | R57: EUR | T57: 1 | W57: 202.9 | X57: 46.4 | AC57: 249.3 | AJ57: 0 | AQ57: 0 | AR57: 25.8 | AX57: 25.8 | BE57: 0 | BL57: 0 | BM57: 228.7 | BN57: 46.4 | BO57: 0 | BP57: 0 | BQ57: 0 | BR57: 0 | BS57: 275.1 | BT57: TRUE | BU57: FALSE | BV57: FALSE | BW57: TRUE | BX57: FALSE | BY57: FALSE | BZ57: 1 | CA57: 1 | CF57: 2 | CM57: 0 | CT57: 0 | CU57: 1 | DA57: 1 | DH57: 0 | DO57: 0 | DP57: 2 | DQ57: 1 | DR57: 0 | DS57: 0 | DT57: 0 | DU57: 0 | DV57: 3 | DW57: YES | DX57: YES | DY57: NO | DZ57: NO | EA57: NO | EB57: NO | EC57: NO | ED57: NO | EE57: NO | EF57: NO | EG57: NO | EH57: NO | EI57: NO | EJ57: NO | EK57: NO | EL57: NO | EM57: NO | EN57: NO | EO57: YES | EP57: NO | EQ57: NO | ER57: NO | ES57: NO | ET57: NO | EU57: NO | EV57: NO | EW57: NO | EX57: NO | EY57: NO | EZ57: NO | FA57: NO | FB57: NO | FC57: NO | FD57: NO | FE57: NO | FF57: NO | FG57: 61.7 | FM57: 61.7 | FT57: 0 | FU57: 121.7 | FV57: 46.4 | GA57: 168.1 | GH57: 0 | GO57: 0 | GV57: 0 | GW57: 45.3 | HC57: 45.3 | HK57: 0 | HL57: 228.7 | HM57: 46.4 | HN57: 0 | HO57: 0 | HP57: 0 | HQ57: 0 | HR57: 275.1 | HS57: 107 | HY57: 107 | HZ57: 121.7 | IA57: 46.4 | IF57: 168.1 | IM57: 0 | IT57: 0 | JA57: 0 | JB57: 228.7 | JC57: 46.4 | JD57: 0 | JE57: 0 | JF57: 0 | JG57: 0 | JH57: 275.1 | JK57: 100 | JN57: 61.7 | JT57: 61.7 | KA57: 0 | KB57: 121.7 | KC57: 46.4 | KH57: 168.1 | KO57: 0 | KV57: 0 | LC57: 0 | LD57: 19.5 | LJ57: 19.5 | LR57: 0 | LS57: 202.9 | LT57: 46.4 | LU57: 0 | LV57: 0 | LW57: 0 | LX57: 0 | LY57: 249.3 | OK57: 0 | QW57: 0 | SN57: 25.8 | ST57: 25.8 | TC57: 25.8 | TI57: 25.8 | VU57: 0 | YG57: 0 | YH57: 1 | YI57: 3 | YJ57: 1 | YK57: Mozilla/5.0 (Windows NT 6.1; WOW64; Trident/7.0; rv:11.0) like Gecko | YL57: 154 | YM57: NVWAE407 | YN57: INREV | YO57: Grosvenor Fund Management | YP57: Ian Currie | YQ57: ian.currie@grosvenor.com | YS57: http://click.surveylab.co.uk/anrev-inrev-ncreif-capital-raising-2016/?survey=NVWAE407
A58: 85 | B58: ANCHR786 | C58: survey=ANCHR786 | D58: 42416.245 | E58: 42416.424 | F58: 14 | G58: 1|2|2|3|4|5|6|7|8|6|7|8|10|15| | I58: 49.128.62.9 | J58: ANREV | K58: Alan Ooi | L58: Ascendas | M58: =VLOOKUP(MID(O58,SEARCH("@",O58,1),LEN(O58)-SEARCH("@",O58,1)+1),[1]Sheet1!$D:$F,3,FALSE) -> M0189 | N58: Head, Fund Raising, Real Estate Funds | O58: alan.ooi@ascendas.com | P58: 6565088808 | Q58: Singapore | R58: SGD | T58: 1 | AC58: 0 | AD58: 633 | AJ58: 633 | AQ58: 0 | AX58: 0 | BE58: 0 | BL58: 0 | BM58: 633 | BN58: 0 | BO58: 0 | BP58: 0 | BQ58: 0 | BR58: 0 | BS58: 633 | BT58: FALSE | BU58: TRUE | BV58: FALSE | BW58: FALSE | BX58: FALSE | BY58: FALSE | CF58: 0 | CG58: 2 | CM58: 2 | CT58: 0 | DA58: 0 | DH58: 0 | DO58: 0 | DP58: 2 | DQ58: 0 | DR58: 0 | DS58: 0 | DT58: 0 | DU58: 0 | DV58: 2 | DW58: NO | DX58: NO | DY58: NO | DZ58: NO | EA58: NO | EB58: NO | EC58: YES | ED58: NO | EE58: NO | EF58: NO | EG58: NO | EH58: NO | EI58: NO | EJ58: NO | EK58: NO | EL58: NO | EM58: NO | EN58: NO | EO58: NO | EP58: NO | EQ58: NO | ER58: NO | ES58: NO | ET58: NO | EU58: NO | EV58: NO | EW58: NO | EX58: NO | EY58: NO | EZ58: NO | FA58: NO | FB58: NO | FC58: NO | FD58: NO | FE58: NO | FF58: NO | FG58: 133 | FM58: 133 | FT58: 0 | FU58: 380 | GA58: 380 | GB58: 40 | GH58: 40 | GI58: 60 | GO58: 60 | GP58: 20 | GV58: 20 | HC58: 0 | HK58: 0 | HL58: 633 | HM58: 0 | HN58: 0 | HO58: 0 | HP58: 0 | HQ58: 0 | HR58: 633 | HS58: 180 | HY58: 180 | HZ58: 453 | IF58: 453 | IM58: 0 | IT58: 0 | JA58: 0 | JB58: 633 | JC58: 0 | JD58: 0 | JE58: 0 | JF58: 0 | JG58: 0 | JH58: 633 | JI58: 15.8 | JK58: 84.2 | JT58: 0 | KA58: 0 | KH58: 0 | KO58: 0 | KV58: 0 | LC58: 0 | LJ58: 0 | LR58: 0 | LS58: 0 | LT58: 0 | LU58: 0 | LV58: 0 | LW58: 0 | LX58: 0 | LY58: 0 | LZ58: 133 | MF58: 133 | MN58: 380 | MT58: 380 | MU58: 40 | NA58: 40 | NB58: 60 | NH58: 60 | NI58: 20 | NO58: 20 | OE58: 633 | OK58: 633 | QW58: 0 | TI58: 0 | VU58: 0 | YG58: 0 | YH58: 1 | YI58: 2 | YJ58: 1 | YK58: Mozilla/5.0 (Windows NT 6.1; Trident/7.0; rv:11.0) like Gecko | YL58: 47 | YM58: ANCHR786 | YN58: ANREV | YO58: Ascendas Pte Ltd | YP58: Alan Ooi | YQ58: alan.ooi@ascendas.com | YS58: http://click.surveylab.co.uk/anrev-inrev-ncreif-capital-raising-2016/?survey=ANCHR786
A59: 86 | B59: NVZUM346 | C59: survey=NVZUM346 | D59: 42403.415 | E59: 42403.419 | F59: 14 | G59: 1|2|3|4|5|6|7|8|12|15| | I59: 62.133.24.224 | J59: INREV | K59: Elliot Glausiusz | L59: ImmoFinRE Group | M59: =VLOOKUP(MID(O59,SEARCH("@",O59,1),LEN(O59)-SEARCH("@",O59,1)+1),[1]Sheet1!$D:$F,3,FALSE) -> M05136 | N59: Head of Investment | O59: elliot.glausiusz@immofinre.com | P59: 2070429788 | Q59: Luxembourg | R59: USD | T59: 1 | AC59: 0 | AJ59: 0 | AQ59: 0 | AV59: 90 | AX59: 90 | BE59: 0 | BL59: 0 | BM59: 0 | BN59: 0 | BO59: 0 | BP59: 0 | BQ59: 90 | BR59: 0 | BS59: 90 | BT59: FALSE | BU59: FALSE | BV59: FALSE | BW59: TRUE | BX59: FALSE | BY59: FALSE | CF59: 0 | CM59: 0 | CT59: 0 | CY59: 1 | DA59: 1 | DH59: 0 | DO59: 0 | DP59: 0 | DQ59: 0 | DR59: 0 | DS59: 0 | DT59: 1 | DU59: 0 | DV59: 1 | DW59: NO | DX59: NO | DY59: NO | DZ59: NO | EA59: NO | EB59: NO | EC59: NO | ED59: NO | EE59: NO | EF59: NO | EG59: NO | EH59: NO | EI59: NO | EJ59: NO | EK59: NO | EL59: NO | EM59: NO | EN59: NO | EO59: NO | EP59: NO | EQ59: NO | ER59: NO | ES59: YES | ET59: NO | EU59: NO | EV59: NO | EW59: NO | EX59: NO | EY59: NO | EZ59: NO | FA59: NO | FB59: NO | FC59: NO | FD59: NO | FE59: NO | FF59: NO | FM59: 0 | FT59: 0 | GA59: 0 | GH59: 0 | GO59: 0 | GV59: 0 | HA59: 90 | HC59: 90 | HK59: 0 | HL59: 0 | HM59: 0 | HN59: 0 | HO59: 0 | HP59: 90 | HQ59: 0 | HR59: 90 | HW59: 90 | HY59: 90 | IF59: 0 | IM59: 0 | IT59: 0 | JA59: 0 | JB59: 0 | JC59: 0 | JD59: 0 | JE59: 0 | JF59: 90 | JG59: 0 | JH59: 90 | JI59: 0 | JJ59: 0 | JK59: 100 | JT59: 0 | KA59: 0 | KH59: 0 | KO59: 0 | KV59: 0 | LC59: 0 | LJ59: 0 | LR59: 0 | LS59: 0 | LT59: 0 | LU59: 0 | LV59: 0 | LW59: 0 | LX59: 0 | LY59: 0 | OK59: 0 | QW59: 0 | SR59: 90 | ST59: 90 | TG59: 90 | TI59: 90 | VU59: 0 | YG59: 0 | YH59: 1 | YI59: 1 | YJ59: 1 | YK59: Mozilla/5.0 (Windows NT 10.0; WOW64; Trident/7.0; rv:11.0) like Gecko | YL59: 568 | YM59: NVZUM346 | YN59: INREV | YO59: zzzAdditional Record | YS59: http://click.surveylab.co.uk/anrev-inrev-ncreif-capital-raising-2016/?survey=NVZUM346
A60: 87 | B60: NVTYL234 | C60: survey=NVTYL234 | D60: 42423.517 | E60: 42423.521 | F60: 14 | G60: 1|2|3|3|4|5|2|3|4|5|6|7|8|9|2|3|4|5|6|7|8|9|2|2|3|2|2|2|2|2|2|2|3|3|3|4|2|3|4|5|6|7|8|9|2|3|4|5|6|7|8|9|2|3|4|5|6|7|8|9|8|9|5|6|6|7|8|9|3|4|5|6|7|8|9|15|2|3|4|5|4|5|6|4|5|6|7|8|9|3|4|5|6|7|8|9|15| | I60: 194.140.225.246 | J60: INREV | K60: Alex Griffiths | L60: AEW Europe | M60: =VLOOKUP(MID(O60,SEARCH("@",O60,1),LEN(O60)-SEARCH("@",O60,1)+1),[1]Sheet1!$D:$F,3,FALSE) -> M004 | N60: Investor Relations | O60: alex.griffiths@aeweurope.com | P60: 2070164840 | Q60: United Kingdom | R60: EUR | T60: 1 | W60: 733.7 | X60: 401 | Z60: 729 | AC60: 1863.7 | AJ60: 0 | AQ60: 0 | AX60: 0 | BE60: 0 | BL60: 0 | BM60: 733.7 | BN60: 401 | BO60: 0 | BP60: 729 | BQ60: 0 | BR60: 0 | BS60: 1863.7 | BT60: TRUE | BU60: FALSE | BV60: FALSE | BW60: FALSE | BX60: FALSE | BY60: FALSE | BZ60: 5 | CA60: 3 | CC60: 2 | CF60: 10 | CM60: 0 | CT60: 0 | DA60: 0 | DH60: 0 | DO60: 0 | DP60: 5 | DQ60: 3 | DR60: 0 | DS60: 2 | DT60: 0 | DU60: 0 | DV60: 10 | DW60: YES | DX60: YES | DY60: NO | DZ60: YES | EA60: NO | EB60: NO | EC60: NO | ED60: NO | EE60: NO | EF60: NO | EG60: NO | EH60: NO | EI60: NO | EJ60: NO | EK60: NO | EL60: NO | EM60: NO | EN60: NO | EO60: NO | EP60: NO | EQ60: NO | ER60: NO | ES60: NO | ET60: NO | EU60: NO | EV60: NO | EW60: NO | EX60: NO | EY60: NO | EZ60: NO | FA60: NO | FB60: NO | FC60: NO | FD60: NO | FE60: NO | FF60: NO | FG60: 338.1 | FH60: 200 | FJ60: 161 | FM60: 699.1 | FN60: 66.6 | FO60: 151 | FT60: 217.6 | FX60: 568 | GA60: 568 | GB60: 20.6 | GH60: 20.6 | GI60: 5.5 | GO60: 5.5 | GP60: 6.6 | GV60: 6.6 | GW60: 2.5 | HC60: 2.5 | HD60: Bank, Corporate, Retail clients | HE60: 293.8 | HF60: 50 | HK60: 343.8 | HL60: 733.7 | HM60: 401 | HN60: 0 | HO60: 729 | HP60: 0 | HQ60: 0 | HR60: 1863.7 | HS60: 730.1 | HT60: 351 | HY60: 1081.1 | HZ60: 3.6 | IC60: 568 | IF60: 571.6 | IH60: 50 | IJ60: 161 | IM60: 211 | IT60: 0 | JA60: 0 | JB60: 733.7 | JC60: 401 | JD60: 0 | JE60: 729 | JF60: 0 | JG60: 0 | JH60: 1863.7 | JI60: 11 | JK60: 75 | JL60: Retail clients banking network | JM60: 14 | JN60: 338.1 | JO60: 200 | JQ60: 161 | JT60: 699.1 | JU60: 66.6 | JV60: 151 | KA60: 217.6 | KE60: 568 | KH60: 568 | KI60: 20.6 | KO60: 20.6 | KP60: 5.5 | KV60: 5.5 | KW60: 6.6 | LC60: 6.6 | LD60: 2.5 | LJ60: 2.5 | LK60: Banks, corporate, retail clients | LL60: 293.8 | LM60: 50 | LR60: 343.8 | LS60: 733.7 | LT60: 401 | LU60: 0 | LV60: 729 | LW60: 0 | LX60: 0 | LY60: 1863.7 | OK60: 0 | QW60: 0 | TI60: 0 | VU60: 0 | YG60: 0 | YH60: 3 | YI60: 2 | YJ60: 1 | YK60: Mozilla/5.0 (Windows NT 6.1; WOW64; Trident/7.0; rv:11.0) like Gecko | YL60: 20 | YM60: NVTYL234 | YN60: INREV | YO60: AEW Europe LLP | YP60: Alex Griffiths | YQ60: alex.griffiths@aeweurope.com | YS60: http://click.surveylab.co.uk/anrev-inrev-ncreif-capital-raising-2016/?survey=NVTYL234
A61: 88 | B61: CFWVB699 | C61: survey=CFWVB699 | D61: 42417.865 | E61: 42417.885 | F61: 14 | G61: 1|2|2|2|3|4|5|6|7|8|15|3|4|5|6|7|8|3|4|4|4|5|6|7|8|2|2|3|4|3|4|5|5|6|7|8|2|3|4|3|4|5|6|7|8|2|2|3|4|5|4|5|6|7|8|9|9|10|9|10|11|7|4|5|6|7|8|9|10|11|15| | I61: 159.53.174.143 | J61: NCREIF | K61: Paul Summer | L61: J.P.Morgan Asset Management | M61: =VLOOKUP(MID(O61,SEARCH("@",O61,1),LEN(O61)-SEARCH("@",O61,1)+1),[1]Sheet1!$D:$F,3,FALSE) -> M082 | N61: Managing Director | O61: paul.t.summer@jpmorgan.com | Q61: United States | R61: USD | T61: 1 | W61: 371 | AC61: 371 | AG61: 30 | AJ61: 30 | AK61: 2979 | AL61: 857 | AN61: 20 | AO61: 638 | AQ61: 4494 | AX61: 0 | BE61: 0 | BL61: 0 | BM61: 3350 | BN61: 857 | BO61: 0 | BP61: 50 | BQ61: 638 | BR61: 0 | BS61: 4895 | BT61: TRUE | BU61: TRUE | BV61: TRUE | BW61: FALSE | BX61: FALSE | BY61: FALSE | BZ61: 1 | CF61: 1 | CJ61: 1 | CM61: 1 | CN61: 4 | CO61: 3 | CQ61: 1 | CR61: 2 | CT61: 10 | DA61: 0 | DH61: 0 | DO61: 0 | DP61: 5 | DQ61: 3 | DR61: 0 | DS61: 2 | DT61: 2 | DU61: 0 | DV61: 12 | DW61: YES | DX61: NO | DY61: NO | DZ61: NO | EA61: NO | EB61: NO | EC61: NO | ED61: NO | EE61: NO | EF61: YES | EG61: NO | EH61: NO | EI61: YES | EJ61: YES | EK61: NO | EL61: YES | EM61: YES | EN61: NO | EO61: NO | EP61: NO | EQ61: NO | ER61: NO | ES61: NO | ET61: NO | EU61: NO | EV61: NO | EW61: NO | EX61: NO | EY61: NO | EZ61: NO | FA61: NO | FB61: NO | FC61: NO | FD61: NO | FE61: NO | FF61: NO | FG61: 2924 | FH61: 623 | FJ61: 50 | FK61: 638 | FM61: 4235 | FN61: 92 | FT61: 92 | FU61: 307 | GA61: 307 | GH61: 0 | GI61: 17 | GO61: 17 | GP61: 10 | GV61: 10 | HC61: 0 | HD61: Corporation | HF61: 234 | HK61: 234 | HL61: 3350 | HM61: 857 | HN61: 0 | HO61: 50 | HP61: 638 | HQ61: 0 | HR61: 4895 | HY61: 0 | HZ61: 386 | IF61: 386 | IG61: 2964 | IH61: 857 | IJ61: 50 | IK61: 638 | IM61: 4509 | IT61: 0 | JA61: 0 | JB61: 3350 | JC61: 857 | JD61: 0 | JE61: 50 | JF61: 638 | JG61: 0 | JH61: 4895 | JJ61: 50 | JK61: 50 | JN61: 55 | JT61: 55 | JU61: 92 | KA61: 92 | KB61: 207 | KH61: 207 | KO61: 0 | KP61: 17 | KV61: 17 | LC61: 0 | LJ61: 0 | LR61: 0 | LS61: 371 | LT61: 0 | LU61: 0 | LV61: 0 | LW61: 0 | LX61: 0 | LY61: 371 | MC61: 30 | OK61: 30 | OL61: 2869 | OM61: 623 | OO61: 20 | OP61: 638 | OZ61: 100 | PU61: 10 | QI61: Corporation | QK61: 234 | QW61: 4494 | TI61: 0 | VU61: 0 | YG61: 0 | YH61: 1 | YI61: 3 | YJ61: 1 | YK61: Mozilla/5.0 (Windows NT 6.1; WOW64; Trident/7.0; rv:11.0) like Gecko | YL61: 197 | YM61: CFWVB699 | YN61: NCREIF | YO61: JP Morgan Chase | YS61: http://click.surveylab.co.uk/anrev-inrev-ncreif-capital-raising-2016/?survey=CFWVB699
A62: 89 | B62: NVCGE663 | C62: survey=NVCGE663 | D62: 42403.593 | E62: 42403.613 | F62: 14 | G62: 1|2|3|4|4|5|4|5|6|7|8|6|7|8|9|15| | I62: 193.105.111.8 | J62: INREV | K62: MIchiel Kroot | L62: a.s.r. reim | M62: =VLOOKUP(MID(O62,SEARCH("@",O62,1),LEN(O62)-SEARCH("@",O62,1)+1),[1]Sheet1!$D:$F,3,FALSE) -> M278 | N62: manager fund control | O62: michiel.kroot@asr.nl | P62: 0031 6 836 385 96 | Q62: Netherlands | R62: EUR | T62: 1 | W62: 486 | AC62: 486 | AJ62: 0 | AQ62: 0 | AX62: 0 | BE62: 0 | BL62: 0 | BM62: 486 | BN62: 0 | BO62: 0 | BP62: 0 | BQ62: 0 | BR62: 0 | BS62: 486 | BT62: TRUE | BU62: FALSE | BV62: FALSE | BW62: FALSE | BX62: FALSE | BY62: FALSE | BZ62: 2 | CF62: 2 | CM62: 0 | CT62: 0 | DA62: 0 | DH62: 0 | DO62: 0 | DP62: 2 | DQ62: 0 | DR62: 0 | DS62: 0 | DT62: 0 | DU62: 0 | DV62: 2 | DW62: YES | DX62: NO | DY62: NO | DZ62: NO | EA62: NO | EB62: NO | EC62: NO | ED62: NO | EE62: NO | EF62: NO | EG62: NO | EH62: NO | EI62: NO | EJ62: NO | EK62: NO | EL62: NO | EM62: NO | EN62: NO | EO62: NO | EP62: NO | EQ62: NO | ER62: NO | ES62: NO | ET62: NO | EU62: NO | EV62: NO | EW62: NO | EX62: NO | EY62: NO | EZ62: NO | FA62: NO | FB62: NO | FC62: NO | FD62: NO | FE62: NO | FF62: NO | FG62: 120 | FM62: 120 | FN62: 30 | FT62: 30 | GA62: 0 | GH62: 0 | GO62: 0 | GP62: 86 | GV62: 86 | HC62: 0 | HD62: Bank | HE62: 250 | HK62: 250 | HL62: 486 | HM62: 0 | HN62: 0 | HO62: 0 | HP62: 0 | HQ62: 0 | HR62: 486 | HS62: 236 | HY62: 236 | HZ62: 250 | IF62: 250 | IM62: 0 | IT62: 0 | JA62: 0 | JB62: 486 | JC62: 0 | JD62: 0 | JE62: 0 | JF62: 0 | JG62: 0 | JH62: 486 | JI62: 70 | JJ62: 30 | JN62: 120 | JT62: 120 | JU62: 30 | KA62: 30 | KH62: 0 | KO62: 0 | KV62: 0 | KW62: 86 | LC62: 86 | LJ62: 0 | LK62: Bank | LL62: 250 | LR62: 250 | LS62: 486 | LT62: 0 | LU62: 0 | LV62: 0 | LW62: 0 | LX62: 0 | LY62: 486 | OK62: 0 | QW62: 0 | TI62: 0 | VU62: 0 | YG62: 0 | YH62: 2 | YI62: 3 | YJ62: 1 | YK62: Mozilla/5.0 (Windows NT 6.1; WOW64; Trident/7.0; rv:11.0) like Gecko | YL62: 49 | YM62: NVCGE663 | YN62: INREV | YO62: ASR REIM | YP62: Michiel Kroot | YQ62: michiel.kroot@asr.nl | YS62: http://click.surveylab.co.uk/anrev-inrev-ncreif-capital-raising-2016/?survey=NVCGE663
A63: 90 | B63: NVTEX356 | C63: survey=NVTEX356 | D63: 42411.51 | E63: 42411.517 | F63: 14 | G63: 1|2|3|2|3|4|4|4|5|6|7|8|9|15| | I63: 194.151.183.29 | J63: INREV | K63: Patrick Schlump | L63: Bouwfonds Investment Management | M63: =VLOOKUP(MID(O63,SEARCH("@",O63,1),LEN(O63)-SEARCH("@",O63,1)+1),[1]Sheet1!$D:$F,3,FALSE) -> M068 | N63: Senior Manager Investor Services | O63: p.schlump@bouwfondsim.com | P63: 4930590097774 | Q63: Netherlands | R63: EUR | T63: 1 | W63: 140 | X63: 100 | AC63: 240 | AJ63: 0 | AQ63: 0 | AX63: 0 | BE63: 0 | BL63: 0 | BM63: 140 | BN63: 100 | BO63: 0 | BP63: 0 | BQ63: 0 | BR63: 0 | BS63: 240 | BT63: TRUE | BU63: FALSE | BV63: FALSE | BW63: FALSE | BX63: FALSE | BY63: FALSE | BZ63: 3 | CA63: 1 | CF63: 4 | CM63: 0 | CT63: 0 | DA63: 0 | DH63: 0 | DO63: 0 | DP63: 3 | DQ63: 1 | DR63: 0 | DS63: 0 | DT63: 0 | DU63: 0 | DV63: 4 | DW63: YES | DX63: YES | DY63: NO | DZ63: NO | EA63: NO | EB63: NO | EC63: NO | ED63: NO | EE63: NO | EF63: NO | EG63: NO | EH63: NO | EI63: NO | EJ63: NO | EK63: NO | EL63: NO | EM63: NO | EN63: NO | EO63: NO | EP63: NO | EQ63: NO | ER63: NO | ES63: NO | ET63: NO | EU63: NO | EV63: NO | EW63: NO | EX63: NO | EY63: NO | EZ63: NO | FA63: NO | FB63: NO | FC63: NO | FD63: NO | FE63: NO | FF63: NO | FG63: 20 | FH63: 100 | FM63: 120 | FT63: 0 | GA63: 0 | GH63: 0 | GO63: 0 | GV63: 0 | HC63: 0 | HD63: Banks, other | HE63: 120 | HK63: 120 | HL63: 140 | HM63: 100 | HN63: 0 | HO63: 0 | HP63: 0 | HQ63: 0 | HR63: 240 | HS63: 140 | HT63: 100 | HY63: 240 | IF63: 0 | IM63: 0 | IT63: 0 | JA63: 0 | JB63: 140 | JC63: 100 | JD63: 0 | JE63: 0 | JF63: 0 | JG63: 0 | JH63: 240 | JI63: 25 | JK63: 75 | JN63: 20 | JO63: 100 | JT63: 120 | KA63: 0 | KH63: 0 | KO63: 0 | KV63: 0 | LC63: 0 | LJ63: 0 | LK63: Banks, Other | LL63: 120 | LR63: 120 | LS63: 140 | LT63: 100 | LU63: 0 | LV63: 0 | LW63: 0 | LX63: 0 | LY63: 240 | OK63: 0 | QW63: 0 | TI63: 0 | VU63: 0 | YG63: 0 | YH63: 1 | YI63: 2 | YJ63: 1 | YK63: Mozilla/5.0 (Windows NT 6.1; WOW64; Trident/7.0; rv:11.0) like Gecko | YL63: 60 | YM63: NVTEX356 | YN63: INREV | YO63: Bouwfonds Investment Management | YP63: Patrick Schlump | YQ63: p.schlump@bouwfondsim.com | YS63: http://click.surveylab.co.uk/anrev-inrev-ncreif-capital-raising-2016/?survey=NVTEX356
A64: 92 | B64: ANUNV672 | C64: survey=ANUNV672 | D64: 42403.909 | E64: 42403.912 | F64: 14 | G64: 1|2|3|4|5|6|7|8|10|15| | I64: 203.27.87.126 | J64: ANREV | K64: Trent Alston | L64: Challenger | M64: =VLOOKUP(MID(O64,SEARCH("@",O64,1),LEN(O64)-SEARCH("@",O64,1)+1),[1]Sheet1!$D:$F,3,FALSE) -> M0224 | N64: Head of Real Estate | O64: talston@challenger.com.au | P64: 61299947851 | Q64: Australia | R64: AUD | T64: 1 | AC64: 0 | AE64: 1750 | AJ64: 1750 | AQ64: 0 | AX64: 0 | BE64: 0 | BL64: 0 | BM64: 0 | BN64: 1750 | BO64: 0 | BP64: 0 | BQ64: 0 | BR64: 0 | BS64: 1750 | BT64: FALSE | BU64: TRUE | BV64: FALSE | BW64: FALSE | BX64: FALSE | BY64: FALSE | CF64: 0 | CH64: 4 | CM64: 4 | CT64: 0 | DA64: 0 | DH64: 0 | DO64: 0 | DP64: 0 | DQ64: 4 | DR64: 0 | DS64: 0 | DT64: 0 | DU64: 0 | DV64: 4 | DW64: NO | DX64: NO | DY64: NO | DZ64: NO | EA64: NO | EB64: NO | EC64: NO | ED64: YES | EE64: NO | EF64: NO | EG64: NO | EH64: NO | EI64: NO | EJ64: NO | EK64: NO | EL64: NO | EM64: NO | EN64: NO | EO64: NO | EP64: NO | EQ64: NO | ER64: NO | ES64: NO | ET64: NO | EU64: NO | EV64: NO | EW64: NO | EX64: NO | EY64: NO | EZ64: NO | FA64: NO | FB64: NO | FC64: NO | FD64: NO | FE64: NO | FF64: NO | FH64: 750 | FM64: 750 | FO64: 1000 | FT64: 1000 | GA64: 0 | GH64: 0 | GO64: 0 | GV64: 0 | HC64: 0 | HK64: 0 | HL64: 0 | HM64: 1750 | HN64: 0 | HO64: 0 | HP64: 0 | HQ64: 0 | HR64: 1750 | HY64: 0 | IA64: 1750 | IF64: 1750 | IM64: 0 | IT64: 0 | JA64: 0 | JB64: 0 | JC64: 1750 | JD64: 0 | JE64: 0 | JF64: 0 | JG64: 0 | JH64: 1750 | JK64: 100 | JT64: 0 | KA64: 0 | KH64: 0 | KO64: 0 | KV64: 0 | LC64: 0 | LJ64: 0 | LR64: 0 | LS64: 0 | LT64: 0 | LU64: 0 | LV64: 0 | LW64: 0 | LX64: 0 | LY64: 0 | MA64: 750 | MF64: 750 | MH64: 1000 | MM64: 1000 | OF64: 1750 | OG64: 0 | OK64: 1750 | QW64: 0 | TI64: 0 | VU64: 0 | YG64: 0 | YH64: 3 | YI64: 3 | YJ64: 1 | YK64: Mozilla/5.0 (Windows NT 6.1; WOW64; Trident/7.0; rv:11.0) like Gecko | YL64: 80 | YM64: ANUNV672 | YN64: ANREV | YO64: Challenger Ltd | YP64: Trent Alston | YQ64: talston@challenger.com.au | YS64: http://click.surveylab.co.uk/anrev-inrev-ncreif-capital-raising-2016/?survey=ANUNV672
A65: 93 | B65: CFLPF531 | C65: survey=CFLPF531 | D65: 42408.616 | E65: 42408.624 | F65: 14 | G65: 1|2|2|2|2|3|4|5|6|7|8|9|10|11|15| | I65: 108.171.131.166 | J65: NCREIF | K65: Louise McKay | L65: LaSalle Investment Management | M65: =VLOOKUP(MID(O65,SEARCH("@",O65,1),LEN(O65)-SEARCH("@",O65,1)+1),[1]Sheet1!$D:$F,3,FALSE) -> M020 | N65: Associate | O65: louise.mckay@lasalle.com | P65: 2078524479 | Q65: United States | R65: USD | T65: 1 | W65: 581 | X65: 1005 | Y65: 165 | AC65: 1751 | AD65: 120 | AE65: 489 | AG65: 47 | AJ65: 656 | AK65: 783 | AL65: 1488 | AQ65: 2271 | AX65: 0 | BE65: 0 | BL65: 0 | BM65: 1484 | BN65: 2982 | BO65: 165 | BP65: 47 | BQ65: 0 | BR65: 0 | BS65: 4678 | BT65: TRUE | BU65: TRUE | BV65: TRUE | BW65: FALSE | BX65: FALSE | BY65: FALSE | BZ65: 3 | CA65: 3 | CB65: 1 | CF65: 7 | CG65: 2 | CH65: 3 | CJ65: 1 | CM65: 6 | CN65: 3 | CO65: 6 | CT65: 9 | DA65: 0 | DH65: 0 | DO65: 0 | DP65: 8 | DQ65: 12 | DR65: 1 | DS65: 1 | DT65: 0 | DU65: 0 | DV65: 22 | DW65: YES | DX65: YES | DY65: YES | DZ65: NO | EA65: NO | EB65: NO | EC65: YES | ED65: YES | EE65: NO | EF65: YES | EG65: NO | EH65: NO | EI65: YES | EJ65: YES | EK65: NO | EL65: NO | EM65: NO | EN65: NO | EO65: NO | EP65: NO | EQ65: NO | ER65: NO | ES65: NO | ET65: NO | EU65: NO | EV65: NO | EW65: NO | EX65: NO | EY65: NO | EZ65: NO | FA65: NO | FB65: NO | FC65: NO | FD65: NO | FE65: NO | FF65: NO | FG65: 687 | FH65: 2570 | FJ65: 47 | FM65: 3304 | FN65: 76 | FP65: 165 | FT65: 241 | FV65: 412 | GA65: 412 | GH65: 0 | GO65: 0 | GV65: 0 | GW65: 405 | HC65: 405 | HE65: 316 | HK65: 316 | HL65: 1484 | HM65: 2982 | HN65: 165 | HO65: 47 | HP65: 0 | HQ65: 0 | HR65: 4678 | HS65: 581 | HT65: 706 | HU65: 165 | HY65: 1452 | HZ65: 130 | IA65: 489 | IC65: 47 | IF65: 666 | IG65: 773 | IH65: 1787 | IM65: 2560 | IT65: 0 | JA65: 0 | JB65: 1484 | JC65: 2982 | JD65: 165 | JE65: 47 | JF65: 0 | JG65: 0 | JH65: 4678 | JI65: 8 | JK65: 92 | JN65: 296 | JO65: 1005 | JT65: 1301 | JU65: 76 | JW65: 165 | KA65: 241 | KH65: 0 | KO65: 0 | KV65: 0 | LC65: 0 | LJ65: 0 | LL65: 209 | LR65: 209 | LS65: 581 | LT65: 1005 | LU65: 165 | LV65: 0 | LW65: 0 | LX65: 0 | LY65: 1751 | MC65: 47 | MF65: 47 | MO65: 412 | MT65: 412 | NX65: 120 | NY65: 77 | OD65: 197 | OE65: 120 | OF65: 489 | OH65: 47 | OK65: 656 | OL65: 270 | OM65: 1488 | OR65: 1758 | QB65: 405 | QH65: 405 | QJ65: 108 | QP65: 108 | QQ65: 783 | QR65: 1488 | QW65: 2271 | TI65: 0 | VU65: 0 | YG65: 0 | YH65: 1 | YI65: 3 | YJ65: 1 | YK65: Mozilla/5.0 (Windows NT 6.1; WOW64; rv:44.0) Gecko/20100101 Firefox/44.0 | YL65: 212 | YM65: CFLPF531 | YN65: NCREIF | YO65: LaSalle Investment Management, Inc. | YS65: http://click.surveylab.co.uk/anrev-inrev-ncreif-capital-raising-2016/?survey=CFLPF531
A66: 94 | B66: ANQLG947 | C66: survey=ANQLG947 | D66: 42404.254 | E66: 42404.279 | F66: 14 | G66: 1|2|3|3|2|3|4|5|6|7|8|10|3|4|5|6|3|4|5|6|7|8|5|5|6|7|8|10|15| | I66: 117.120.18.135 | J66: ANREV | K66: Chris Moses Zahar | L66: The GPT Group - Funds Management | M66: =VLOOKUP(MID(O66,SEARCH("@",O66,1),LEN(O66)-SEARCH("@",O66,1)+1),[1]Sheet1!$D:$F,3,FALSE) -> M0075 | N66: Senior Fund Analyst GWOF | O66: chris.moses-zahar@gpt.com.ay | P66: 61421447780 | Q66: Australia | R66: AUD | T66: 1 | V66: Strategy | AC66: 0 | AD66: 87 | AJ66: 87 | AQ66: 0 | AX66: 0 | BE66: 0 | BL66: 0 | BM66: 87 | BN66: 0 | BO66: 0 | BP66: 0 | BQ66: 0 | BR66: 0 | BS66: 87 | BT66: FALSE | BU66: TRUE | BV66: FALSE | BW66: FALSE | BX66: FALSE | BY66: FALSE | CF66: 0 | CG66: 2 | CM66: 2 | CT66: 0 | DA66: 0 | DH66: 0 | DO66: 0 | DP66: 2 | DQ66: 0 | DR66: 0 | DS66: 0 | DT66: 0 | DU66: 0 | DV66: 2 | DW66: NO | DX66: NO | DY66: NO | DZ66: NO | EA66: NO | EB66: NO | EC66: YES | ED66: NO | EE66: NO | EF66: NO | EG66: NO | EH66: NO | EI66: NO | EJ66: NO | EK66: NO | EL66: NO | EM66: NO | EN66: NO | EO66: NO | EP66: NO | EQ66: NO | ER66: NO | ES66: NO | ET66: NO | EU66: NO | EV66: NO | EW66: NO | EX66: NO | EY66: NO | EZ66: NO | FA66: NO | FB66: NO | FC66: NO | FD66: NO | FE66: NO | FF66: NO | FG66: 49 | FM66: 49 | FT66: 0 | FU66: 3 | GA66: 3 | GH66: 0 | GO66: 0 | GV66: 0 | HC66: 0 | HD66: Other investors | HE66: 35 | HK66: 35 | HL66: 87 | HM66: 0 | HN66: 0 | HO66: 0 | HP66: 0 | HQ66: 0 | HR66: 87 | HS66: 0.7 | HY66: 0.7 | HZ66: 86.3 | IF66: 86.3 | IM66: 0 | IT66: 0 | JA66: 0 | JB66: 87 | JC66: 0 | JD66: 0 | JE66: 0 | JF66: 0 | JG66: 0 | JH66: 87 | JK66: 100 | JT66: 0 | KA66: 0 | KH66: 0 | KO66: 0 | KV66: 0 | LC66: 0 | LJ66: 0 | LR66: 0 | LS66: 0 | LT66: 0 | LU66: 0 | LV66: 0 | LW66: 0 | LX66: 0 | LY66: 0 | LZ66: 49 | MF66: 49 | MM66: 0 | MN66: 3 | MT66: 3 | NW66: Other Investors | NX66: 35 | OD66: 35 | OE66: 87 | OK66: 87 | QW66: 0 | TI66: 0 | VU66: 0 | YG66: 0 | YH66: 1 | YI66: 3 | YJ66: 1 | YK66: Mozilla/5.0 (Windows NT 6.1; WOW64; Trident/7.0; rv:11.0) like Gecko | YL66: 149 | YM66: ANQLG947 | YN66: ANREV | YO66: GPT Funds Management Limited | YP66: Chris | YQ66: Chris.Moses-Zahar@gpt.com.au | YS66: http://click.surveylab.co.uk/anrev-inrev-ncreif-capital-raising-2016/?survey=ANQLG947
A67: 95 | B67: CFAWD162 | C67: survey=CFAWD162 | D67: 42404.097 | E67: 42404.104 | F67: 14 | G67: 1|2|3|4|5|6|7|8|11|15| | I67: 205.178.91.189 | J67: NCREIF | K67: Michelle Wells | L67: Waterton | M67: =VLOOKUP(MID(O67,SEARCH("@",O67,1),LEN(O67)-SEARCH("@",O67,1)+1),[1]Sheet1!$D:$F,3,FALSE) -> NC014 | N67: Executive Vice President, Investor Relations | O67: michelle.wells@waterton.com | P67: 312-476-2075 | Q67: United States | R67: USD | T67: 1 | AC67: 0 | AJ67: 0 | AK67: 511 | AN67: 245 | AQ67: 756 | AX67: 0 | BE67: 0 | BL67: 0 | BM67: 511 | BN67: 0 | BO67: 0 | BP67: 245 | BQ67: 0 | BR67: 0 | BS67: 756 | BT67: FALSE | BU67: FALSE | BV67: TRUE | BW67: FALSE | BX67: FALSE | BY67: FALSE | CF67: 0 | CM67: 0 | CN67: 1 | CQ67: 2 | CT67: 3 | DA67: 0 | DH67: 0 | DO67: 0 | DP67: 1 | DQ67: 0 | DR67: 0 | DS67: 2 | DT67: 0 | DU67: 0 | DV67: 3 | DW67: NO | DX67: NO | DY67: NO | DZ67: NO | EA67: NO | EB67: NO | EC67: NO | ED67: NO | EE67: NO | EF67: NO | EG67: NO | EH67: NO | EI67: YES | EJ67: NO | EK67: NO | EL67: YES | EM67: NO | EN67: NO | EO67: NO | EP67: NO | EQ67: NO | ER67: NO | ES67: NO | ET67: NO | EU67: NO | EV67: NO | EW67: NO | EX67: NO | EY67: NO | EZ67: NO | FA67: NO | FB67: NO | FC67: NO | FD67: NO | FE67: NO | FF67: NO | FG67: 390 | FJ67: 245 | FM67: 635 | FN67: 75 | FT67: 75 | GA67: 0 | GH67: 0 | GI67: 25 | GO67: 25 | GV67: 0 | GW67: 21 | HC67: 21 | HK67: 0 | HL67: 511 | HM67: 0 | HN67: 0 | HO67: 245 | HP67: 0 | HQ67: 0 | HR67: 756 | HY67: 0 | HZ67: 10 | IF67: 10 | IG67: 501 | IJ67: 245 | IM67: 746 | IT67: 0 | JA67: 0 | JB67: 511 | JC67: 0 | JD67: 0 | JE67: 245 | JF67: 0 | JG67: 0 | JH67: 756 | JI67: 15 | JJ67: 5 | JK67: 75 | JT67: 0 | KA67: 0 | KH67: 0 | KO67: 0 | KV67: 0 | LC67: 0 | LJ67: 0 | LR67: 0 | LS67: 0 | LT67: 0 | LU67: 0 | LV67: 0 | LW67: 0 | LX67: 0 | LY67: 0 | OK67: 0 | OL67: 390 | OR67: 390 | OS67: 75 | OY67: 75 | PN67: 25 | PT67: 25 | QB67: 21 | QH67: 21 | QQ67: 511 | QW67: 511 | TI67: 0 | VU67: 0 | YG67: 0 | YH67: 1 | YI67: 3 | YJ67: 1 | YK67: Mozilla/5.0 (Windows NT 6.1) AppleWebKit/537.36 (KHTML, like Gecko) Chrome/48.0.2564.97 Safari/537.36 | YL67: 359 | YM67: CFAWD162 | YN67: NCREIF | YO67: Waterton Associates | YS67: http://click.surveylab.co.uk/anrev-inrev-ncreif-capital-raising-2016/?survey=CFAWD162
A68: 96 | B68: ANTZF134 | C68: survey=ANTZF134 | D68: 42404.147 | E68: 42404.149 | F68: 14 | G68: 1|2|3|4|5|6|7|8|10|15| | I68: 203.198.145.54 | J68: ANREV | K68: Markus Puusepp | L68: White Peak | M68: =VLOOKUP(MID(O68,SEARCH("@",O68,1),LEN(O68)-SEARCH("@",O68,1)+1),[1]Sheet1!$D:$F,3,FALSE) -> M0128 | N68: Head of Investor Relations | O68: markus.puusepp@wprei.com | P68: 85297392141 | Q68: China | R68: CNY | T68: 1 | AC68: 0 | AD68: 500 | AJ68: 500 | AQ68: 0 | AX68: 0 | BE68: 0 | BL68: 0 | BM68: 500 | BN68: 0 | BO68: 0 | BP68: 0 | BQ68: 0 | BR68: 0 | BS68: 500 | BT68: FALSE | BU68: TRUE | BV68: FALSE | BW68: FALSE | BX68: FALSE | BY68: FALSE | CF68: 0 | CG68: 1 | CM68: 1 | CT68: 0 | DA68: 0 | DH68: 0 | DO68: 0 | DP68: 1 | DQ68: 0 | DR68: 0 | DS68: 0 | DT68: 0 | DU68: 0 | DV68: 1 | DW68: NO | DX68: NO | DY68: NO | DZ68: NO | EA68: NO | EB68: NO | EC68: YES | ED68: NO | EE68: NO | EF68: NO | EG68: NO | EH68: NO | EI68: NO | EJ68: NO | EK68: NO | EL68: NO | EM68: NO | EN68: NO | EO68: NO | EP68: NO | EQ68: NO | ER68: NO | ES68: NO | ET68: NO | EU68: NO | EV68: NO | EW68: NO | EX68: NO | EY68: NO | EZ68: NO | FA68: NO | FB68: NO | FC68: NO | FD68: NO | FE68: NO | FF68: NO | FG68: 450 | FM68: 450 | FT68: 0 | GA68: 0 | GH68: 0 | GO68: 0 | GV68: 0 | GW68: 50 | HC68: 50 | HK68: 0 | HL68: 500 | HM68: 0 | HN68: 0 | HO68: 0 | HP68: 0 | HQ68: 0 | HR68: 500 | HS68: 500 | HY68: 500 | IF68: 0 | IM68: 0 | IT68: 0 | JA68: 0 | JB68: 500 | JC68: 0 | JD68: 0 | JE68: 0 | JF68: 0 | JG68: 0 | JH68: 500 | JK68: 100 | JT68: 0 | KA68: 0 | KH68: 0 | KO68: 0 | KV68: 0 | LC68: 0 | LJ68: 0 | LR68: 0 | LS68: 0 | LT68: 0 | LU68: 0 | LV68: 0 | LW68: 0 | LX68: 0 | LY68: 0 | LZ68: 450 | MF68: 450 | NP68: 50 | NV68: 50 | OE68: 500 | OK68: 500 | QW68: 0 | TI68: 0 | VU68: 0 | YG68: 0 | YH68: 1 | YI68: 2 | YJ68: 1 | YK68: Mozilla/5.0 (Windows NT 6.1; Trident/7.0; rv:11.0) like Gecko | YL68: 363 | YM68: ANTZF134 | YN68: ANREV | YO68: White Peak | YP68: Markus Puusepp | YQ68: markus.puusepp@wprei.com | YS68: http://click.surveylab.co.uk/anrev-inrev-ncreif-capital-raising-2016/?survey=ANTZF134
A69: 97 | B69: ANFMA735 | C69: survey=ANFMA735 | D69: 42404.161 | F69: 1 | G69: 1|2| | I69: 59.167.240.156 | J69: ANREV | M69: =VLOOKUP(MID(O69,SEARCH("@",O69,1),LEN(O69)-SEARCH("@",O69,1)+1),[1]Sheet1!$D:$F,3,FALSE) -> #VALUE! | YK69: Mozilla/5.0 (Windows NT 6.1; WOW64; Trident/7.0; rv:11.0) like Gecko | YL69: 131 | YM69: ANFMA735 | YN69: ANREV | YO69: Fife Capital | YP69: Keir | YQ69: keir.barnes@fifecapital.com.au | YS69: http://click.surveylab.co.uk/anrev-inrev-ncreif-capital-raising-2016/?survey=ANFMA735
A70: 98 | B70: ANVFC883 | C70: survey=ANVFC883 | D70: 42415.236 | E70: 42415.238 | F70: 14 | G70: 1|2|3|4|5|6|7|2|3|4|5|6|7|8|10|10|15| | I70: 203.125.141.130 | J70: ANREV | K70: Viola Chee | L70: SilkRoad Property Partners | M70: =VLOOKUP(MID(O70,SEARCH("@",O70,1),LEN(O70)-SEARCH("@",O70,1)+1),[1]Sheet1!$D:$F,3,FALSE) -> M0182 | N70: VP Financial Controller | O70: viola.chee@silkroadpp.com | P70: 6922 5566 | Q70: Singapore | R70: USD | T70: 1 | AC70: 0 | AD70: 333 | AJ70: 333 | AQ70: 0 | AX70: 0 | BE70: 0 | BL70: 0 | BM70: 333 | BN70: 0 | BO70: 0 | BP70: 0 | BQ70: 0 | BR70: 0 | BS70: 333 | BT70: FALSE | BU70: TRUE | BV70: FALSE | BW70: FALSE | BX70: FALSE | BY70: FALSE | CF70: 0 | CG70: 2 | CM70: 2 | CT70: 0 | DA70: 0 | DH70: 0 | DO70: 0 | DP70: 2 | DQ70: 0 | DR70: 0 | DS70: 0 | DT70: 0 | DU70: 0 | DV70: 2 | DW70: NO | DX70: NO | DY70: NO | DZ70: NO | EA70: NO | EB70: NO | EC70: YES | ED70: NO | EE70: NO | EF70: NO | EG70: NO | EH70: NO | EI70: NO | EJ70: NO | EK70: NO | EL70: NO | EM70: NO | EN70: NO | EO70: NO | EP70: NO | EQ70: NO | ER70: NO | ES70: NO | ET70: NO | EU70: NO | EV70: NO | EW70: NO | EX70: NO | EY70: NO | EZ70: NO | FA70: NO | FB70: NO | FC70: NO | FD70: NO | FE70: NO | FF70: NO | FG70: 163 | FM70: 163 | FN70: 170 | FT70: 170 | GA70: 0 | GH70: 0 | GO70: 0 | GV70: 0 | HC70: 0 | HK70: 0 | HL70: 333 | HM70: 0 | HN70: 0 | HO70: 0 | HP70: 0 | HQ70: 0 | HR70: 333 | HS70: 333 | HY70: 333 | IF70: 0 | IM70: 0 | IT70: 0 | JA70: 0 | JB70: 333 | JC70: 0 | JD70: 0 | JE70: 0 | JF70: 0 | JG70: 0 | JH70: 333 | JI70: 30.9 | JK70: 69.1 | JT70: 0 | KA70: 0 | KH70: 0 | KO70: 0 | KV70: 0 | LC70: 0 | LJ70: 0 | LR70: 0 | LS70: 0 | LT70: 0 | LU70: 0 | LV70: 0 | LW70: 0 | LX70: 0 | LY70: 0 | LZ70: 163 | MF70: 163 | MG70: 170 | MM70: 170 | OE70: 333 | OK70: 333 | QW70: 0 | TI70: 0 | VU70: 0 | YG70: 0 | YH70: 1 | YI70: 3 | YJ70: 2 | YK70: Mozilla/5.0 (Windows NT 6.1; WOW64; Trident/7.0; rv:11.0) like Gecko | YL70: 314 | YM70: ANVFC883 | YN70: ANREV | YO70: SilkRoad Property Partners | YP70: Viola Chee | YQ70: viola.chee@silkroadpp.com | YS70: http://click.surveylab.co.uk/anrev-inrev-ncreif-capital-raising-2016/?survey=ANVFC883
A71: 99 | B71: ANXWG442 | C71: survey=ANXWG442 | D71: 42415.057 | E71: 42415.059 | F71: 14 | G71: 1|2|3|4|5|6|7|8|2|3|4|5|6|7|8|15|2|3|3|3|2|3|15| | I71: 27.96.106.126 | J71: ANREV | K71: Serene Foong | L71: Alpha Investment Partners | M71: =VLOOKUP(MID(O71,SEARCH("@",O71,1),LEN(O71)-SEARCH("@",O71,1)+1),[1]Sheet1!$D:$F,3,FALSE) -> M0106 | N71: SVP Finance | O71: serene.foong@alphaipartners.com | P71: -64437652 | Q71: Singapore | R71: USD | T71: 2 | U71: 6 | V71: Will be raising capital in 2016 | AC71: 0 | AJ71: 0 | AQ71: 0 | AX71: 0 | BE71: 0 | BL71: 0 | BM71: 0 | BN71: 0 | BO71: 0 | BP71: 0 | BQ71: 0 | BR71: 0 | BS71: 0 | BT71: FALSE | BU71: FALSE | BV71: FALSE | BW71: FALSE | BX71: FALSE | BY71: FALSE | CF71: 0 | CM71: 0 | CT71: 0 | DA71: 0 | DH71: 0 | DO71: 0 | DP71: 0 | DQ71: 0 | DR71: 0 | DS71: 0 | DT71: 0 | DU71: 0 | DV71: 0 | DW71: NO | DX71: NO | DY71: NO | DZ71: NO | EA71: NO | EB71: NO | EC71: NO | ED71: NO | EE71: NO | EF71: NO | EG71: NO | EH71: NO | EI71: NO | EJ71: NO | EK71: NO | EL71: NO | EM71: NO | EN71: NO | EO71: NO | EP71: NO | EQ71: NO | ER71: NO | ES71: NO | ET71: NO | EU71: NO | EV71: NO | EW71: NO | EX71: NO | EY71: NO | EZ71: NO | FA71: NO | FB71: NO | FC71: NO | FD71: NO | FE71: NO | FF71: NO | FM71: 0 | FT71: 0 | GA71: 0 | GH71: 0 | GO71: 0 | GV71: 0 | HC71: 0 | HK71: 0 | HL71: 0 | HM71: 0 | HN71: 0 | HO71: 0 | HP71: 0 | HQ71: 0 | HR71: 0 | HY71: 0 | IF71: 0 | IM71: 0 | IT71: 0 | JA71: 0 | JB71: 0 | JC71: 0 | JD71: 0 | JE71: 0 | JF71: 0 | JG71: 0 | JH71: 0 | JT71: 0 | KA71: 0 | KH71: 0 | KO71: 0 | KV71: 0 | LC71: 0 | LJ71: 0 | LR71: 0 | LS71: 0 | LT71: 0 | LU71: 0 | LV71: 0 | LW71: 0 | LX71: 0 | LY71: 0 | OK71: 0 | QW71: 0 | TI71: 0 | VU71: 0 | YG71: 0 | YH71: 1 | YI71: 2 | YJ71: 2 | YK71: Mozilla/5.0 (Windows NT 6.1; WOW64; rv:44.0) Gecko/20100101 Firefox/44.0 | YL71: 420 | YM71: ANXWG442 | YN71: ANREV | YO71: zzzAdditional Record | YS71: http://click.surveylab.co.uk/anrev-inrev-ncreif-capital-raising-2016/?survey=ANXWG442
A72: 100 | B72: NVJPR335 | C72: survey=NVJPR335 | D72: 42404.483 | E72: 42404.51 | F72: 14 | G72: 1|2|3|4|5|6|3|4|5|6|7|8|9|15| | I72: 194.74.217.178 | J72: INREV | K72: Adam Smith | L72: Tristan Capital Partners | M72: =VLOOKUP(MID(O72,SEARCH("@",O72,1),LEN(O72)-SEARCH("@",O72,1)+1),[1]Sheet1!$D:$F,3,FALSE) -> M486 | N72: Director, Client Relations | O72: asmith@tristancap.com | P72: 442034638867 | Q72: United Kingdom | R72: EUR | T72: 1 | W72: 1666.67 | AC72: 1666.67 | AJ72: 0 | AQ72: 0 | AX72: 0 | BE72: 0 | BL72: 0 | BM72: 1666.67 | BN72: 0 | BO72: 0 | BP72: 0 | BQ72: 0 | BR72: 0 | BS72: 1666.67 | BT72: TRUE | BU72: FALSE | BV72: FALSE | BW72: FALSE | BX72: FALSE | BY72: FALSE | BZ72: 2 | CF72: 2 | CM72: 0 | CT72: 0 | DA72: 0 | DH72: 0 | DO72: 0 | DP72: 2 | DQ72: 0 | DR72: 0 | DS72: 0 | DT72: 0 | DU72: 0 | DV72: 2 | DW72: YES | DX72: NO | DY72: NO | DZ72: NO | EA72: NO | EB72: NO | EC72: NO | ED72: NO | EE72: NO | EF72: NO | EG72: NO | EH72: NO | EI72: NO | EJ72: NO | EK72: NO | EL72: NO | EM72: NO | EN72: NO | EO72: NO | EP72: NO | EQ72: NO | ER72: NO | ES72: NO | ET72: NO | EU72: NO | EV72: NO | EW72: NO | EX72: NO | EY72: NO | EZ72: NO | FA72: NO | FB72: NO | FC72: NO | FD72: NO | FE72: NO | FF72: NO | FG72: 823.6 | FM72: 823.6 | FN72: 259 | FT72: 259 | FU72: 58 | GA72: 58 | GB72: 40 | GH72: 40 | GI72: 91.56 | GO72: 91.56 | GP72: 16.5 | GV72: 16.5 | GW72: 82 | HC72: 82 | HD72: Asset Managers | HE72: 296.01 | HK72: 296.01 | HL72: 1666.67 | HM72: 0 | HN72: 0 | HO72: 0 | HP72: 0 | HQ72: 0 | HR72: 1666.67 | HS72: 530.1 | HY72: 530.1 | HZ72: 257.65 | IF72: 257.65 | IG72: 869.66 | IM72: 869.66 | IN72: 9.26 | IT72: 9.26 | IU72: 0 | JA72: 0 | JB72: 1666.67 | JC72: 0 | JD72: 0 | JE72: 0 | JF72: 0 | JG72: 0 | JH72: 1666.67 | JN72: 823.6 | JT72: 823.6 | JU72: 259 | KA72: 259 | KB72: 58 | KH72: 58 | KI72: 40 | KO72: 40 | KP72: 91.56 | KV72: 91.56 | KW72: 16.5 | LC72: 16.5 | LD72: 82 | LJ72: 82 | LK72: Asset Managers | LL72: 296.01 | LR72: 296.01 | LS72: 1666.67 | LT72: 0 | LU72: 0 | LV72: 0 | LW72: 0 | LX72: 0 | LY72: 1666.67 | OK72: 0 | QW72: 0 | TI72: 0 | VU72: 0 | YG72: 0 | YH72: 3 | YI72: 3 | YJ72: 1 | YK72: Mozilla/5.0 (Windows NT 6.1; WOW64) AppleWebKit/537.36 (KHTML, like Gecko) Chrome/47.0.2526.106 Safari/537.36 | YL72: 343 | YM72: NVJPR335 | YN72: INREV | YO72: Tristan Capital Partners | YP72: Adam Smith | YQ72: asmith@tristancap.com | YS72: http://click.surveylab.co.uk/anrev-inrev-ncreif-capital-raising-2016/?survey=NVJPR335
A73: 101 | B73: NVXZA548 | C73: survey=NVXZA548 | D73: 42404.549 | E73: 42404.55 | F73: 14 | G73: 1|2|3|4|5|6|7|2|3|4|5|6|7|8|9|15| | I73: 195.243.133.82 | J73: INREV | K73: Rodney Bysh | L73: Cording Real Estate Group | M73: =VLOOKUP(MID(O73,SEARCH("@",O73,1),LEN(O73)-SEARCH("@",O73,1)+1),[1]Sheet1!$D:$F,3,FALSE) -> M506 | N73: CEO | O73: rodney.bysh@cordinggroup.com | P73: +49 69 7430388-11 | Q73: Germany | R73: EUR | T73: 1 | Z73: 270 | AC73: 270 | AJ73: 0 | AQ73: 0 | AX73: 0 | BE73: 0 | BL73: 0 | BM73: 0 | BN73: 0 | BO73: 0 | BP73: 270 | BQ73: 0 | BR73: 0 | BS73: 270 | BT73: TRUE | BU73: FALSE | BV73: FALSE | BW73: FALSE | BX73: FALSE | BY73: FALSE | CC73: 5 | CF73: 5 | CM73: 0 | CT73: 0 | DA73: 0 | DH73: 0 | DO73: 0 | DP73: 0 | DQ73: 0 | DR73: 0 | DS73: 5 | DT73: 0 | DU73: 0 | DV73: 5 | DW73: NO | DX73: NO | DY73: NO | DZ73: YES | EA73: NO | EB73: NO | EC73: NO | ED73: NO | EE73: NO | EF73: NO | EG73: NO | EH73: NO | EI73: NO | EJ73: NO | EK73: NO | EL73: NO | EM73: NO | EN73: NO | EO73: NO | EP73: NO | EQ73: NO | ER73: NO | ES73: NO | ET73: NO | EU73: NO | EV73: NO | EW73: NO | EX73: NO | EY73: NO | EZ73: NO | FA73: NO | FB73: NO | FC73: NO | FD73: NO | FE73: NO | FF73: NO | FJ73: 95 | FM73: 95 | FT73: 0 | GA73: 0 | GH73: 0 | GO73: 0 | GS73: 145 | GV73: 145 | GZ73: 30 | HC73: 30 | HK73: 0 | HL73: 0 | HM73: 0 | HN73: 0 | HO73: 270 | HP73: 0 | HQ73: 0 | HR73: 270 | HV73: 270 | HY73: 270 | IF73: 0 | IM73: 0 | IT73: 0 | JA73: 0 | JB73: 0 | JC73: 0 | JD73: 0 | JE73: 270 | JF73: 0 | JG73: 0 | JH73: 270 | JI73: 5 | JK73: 95 | JQ73: 95 | JT73: 95 | KA73: 0 | KH73: 0 | KO73: 0 | KV73: 0 | KZ73: 145 | LC73: 145 | LG73: 30 | LJ73: 30 | LR73: 0 | LS73: 0 | LT73: 0 | LU73: 0 | LV73: 270 | LW73: 0 | LX73: 0 | LY73: 270 | OK73: 0 | QW73: 0 | TI73: 0 | VU73: 0 | YG73: 0 | YH73: 1 | YI73: 3 | YJ73: 1 | YK73: Mozilla/5.0 (Windows NT 6.3; WOW64; Trident/7.0; rv:11.0) like Gecko | YL73: 94 | YM73: NVXZA548 | YN73: INREV | YO73: Cording Real Estate Group LLP | YP73: Rodney Bysh | YQ73: rodney.bysh@cordinggroup.com | YS73: http://click.surveylab.co.uk/anrev-inrev-ncreif-capital-raising-2016/?survey=NVXZA548
A74: 102 | B74: NVDUN612 | C74: survey=NVDUN612 | D74: 42416.747 | E74: 42416.751 | F74: 14 | G74: 1|2|3|4|5|6|7|8|9|15| | I74: 37.60.5.66 | J74: INREV | K74: Thorsten Jaeger | L74: PROJECT Investement AG | M74: =VLOOKUP(MID(O74,SEARCH("@",O74,1),LEN(O74)-SEARCH("@",O74,1)+1),[1]Sheet1!$D:$F,3,FALSE) -> M680 | N74: Fundmanager | O74: t.jaeger@project-investment.de | Q74: Germany | R74: EUR | T74: 1 | Y74: 5 | AC74: 5 | AJ74: 0 | AQ74: 0 | AX74: 0 | BE74: 0 | BL74: 0 | BM74: 0 | BN74: 0 | BO74: 5 | BP74: 0 | BQ74: 0 | BR74: 0 | BS74: 5 | BT74: TRUE | BU74: FALSE | BV74: FALSE | BW74: FALSE | BX74: FALSE | BY74: FALSE | CB74: 1 | CF74: 1 | CM74: 0 | CT74: 0 | DA74: 0 | DH74: 0 | DO74: 0 | DP74: 0 | DQ74: 0 | DR74: 1 | DS74: 0 | DT74: 0 | DU74: 0 | DV74: 1 | DW74: NO | DX74: NO | DY74: YES | DZ74: NO | EA74: NO | EB74: NO | EC74: NO | ED74: NO | EE74: NO | EF74: NO | EG74: NO | EH74: NO | EI74: NO | EJ74: NO | EK74: NO | EL74: NO | EM74: NO | EN74: NO | EO74: NO | EP74: NO | EQ74: NO | ER74: NO | ES74: NO | ET74: NO | EU74: NO | EV74: NO | EW74: NO | EX74: NO | EY74: NO | EZ74: NO | FA74: NO | FB74: NO | FC74: NO | FD74: NO | FE74: NO | FF74: NO | FM74: 0 | FP74: 5 | FT74: 5 | GA74: 0 | GH74: 0 | GO74: 0 | GV74: 0 | HC74: 0 | HK74: 0 | HL74: 0 | HM74: 0 | HN74: 5 | HO74: 0 | HP74: 0 | HQ74: 0 | HR74: 5 | HU74: 5 | HY74: 5 | IF74: 0 | IM74: 0 | IT74: 0 | JA74: 0 | JB74: 0 | JC74: 0 | JD74: 5 | JE74: 0 | JF74: 0 | JG74: 0 | JH74: 5 | JI74: 0 | JJ74: 100 | JK74: 0 | JT74: 0 | JW74: 5 | KA74: 5 | KH74: 0 | KO74: 0 | KV74: 0 | LC74: 0 | LJ74: 0 | LR74: 0 | LS74: 0 | LT74: 0 | LU74: 5 | LV74: 0 | LW74: 0 | LX74: 0 | LY74: 5 | OK74: 0 | QW74: 0 | TI74: 0 | VU74: 0 | YG74: 0 | YH74: 1 | YI74: 3 | YJ74: 1 | YK74: Mozilla/5.0 (Windows NT 6.1; WOW64; Trident/7.0; rv:11.0) like Gecko | YL74: 285 | YM74: NVDUN612 | YN74: INREV | YO74: PROJECT Investment AG | YP74: Thorsten Jaeger | YQ74: t.jaeger@project-investment.de | YS74: http://click.surveylab.co.uk/anrev-inrev-ncreif-capital-raising-2016/?survey=NVDUN612
A75: 103 | B75: NVFJC646 | C75: survey=NVFJC646 | D75: 42404.64 | E75: 42404.642 | F75: 14 | G75: 1|2|3|3|15| | I75: 80.86.167.40 | J75: INREV | K75: Bernhard Berg | L75: Hannover Leasing Investment GmbH | M75: M737 | N75: Managing Director | O75: bernhard.berg@hannover-leasing.de | P75: +49 172 2041461 | Q75: Germany | R75: EUR | T75: 2 | U75: 6 | V75: Start Up in the Institutional Fund business | AC75: 0 | AJ75: 0 | AQ75: 0 | AX75: 0 | BE75: 0 | BL75: 0 | BM75: 0 | BN75: 0 | BO75: 0 | BP75: 0 | BQ75: 0 | BR75: 0 | BS75: 0 | BT75: FALSE | BU75: FALSE | BV75: FALSE | BW75: FALSE | BX75: FALSE | BY75: FALSE | CF75: 0 | CM75: 0 | CT75: 0 | DA75: 0 | DH75: 0 | DO75: 0 | DP75: 0 | DQ75: 0 | DR75: 0 | DS75: 0 | DT75: 0 | DU75: 0 | DV75: 0 | DW75: NO | DX75: NO | DY75: NO | DZ75: NO | EA75: NO | EB75: NO | EC75: NO | ED75: NO | EE75: NO | EF75: NO | EG75: NO | EH75: NO | EI75: NO | EJ75: NO | EK75: NO | EL75: NO | EM75: NO | EN75: NO | EO75: NO | EP75: NO | EQ75: NO | ER75: NO | ES75: NO | ET75: NO | EU75: NO | EV75: NO | EW75: NO | EX75: NO | EY75: NO | EZ75: NO | FA75: NO | FB75: NO | FC75: NO | FD75: NO | FE75: NO | FF75: NO | FM75: 0 | FT75: 0 | GA75: 0 | GH75: 0 | GO75: 0 | GV75: 0 | HC75: 0 | HK75: 0 | HL75: 0 | HM75: 0 | HN75: 0 | HO75: 0 | HP75: 0 | HQ75: 0 | HR75: 0 | HY75: 0 | IF75: 0 | IM75: 0 | IT75: 0 | JA75: 0 | JB75: 0 | JC75: 0 | JD75: 0 | JE75: 0 | JF75: 0 | JG75: 0 | JH75: 0 | JT75: 0 | KA75: 0 | KH75: 0 | KO75: 0 | KV75: 0 | LC75: 0 | LJ75: 0 | LR75: 0 | LS75: 0 | LT75: 0 | LU75: 0 | LV75: 0 | LW75: 0 | LX75: 0 | LY75: 0 | OK75: 0 | QW75: 0 | TI75: 0 | VU75: 0 | YG75: 0 | YH75: 1 | YI75: 3 | YJ75: 1 | YK75: Mozilla/5.0 (Windows NT 6.1; WOW64; Trident/7.0; rv:11.0) like Gecko | YL75: 161 | YM75: NVFJC646 | YN75: INREV | YO75: Hannover Leasing Investment GmbH | YP75: Bernhard Berg | YQ75: Bernhard.berg@hannover-leasing.de | YS75: http://click.surveylab.co.uk/anrev-inrev-ncreif-capital-raising-2016/?survey=NVFJC646
A76: 104 | B76: NVFCJ076 | C76: survey=NVFCJ076 | D76: 42404.733 | F76: 1 | G76: 1|2|2|2|2|3|2| | I76: 85.115.52.201 | J76: INREV | M76: =VLOOKUP(MID(O76,SEARCH("@",O76,1),LEN(O76)-SEARCH("@",O76,1)+1),[1]Sheet1!$D:$F,3,FALSE) -> #VALUE! | R76: EUR | T76: 1 | YK76: Mozilla/5.0 (Windows NT 6.1; WOW64) AppleWebKit/537.36 (KHTML, like Gecko) Chrome/48.0.2564.97 Safari/537.36 | YL76: 333 | YM76: NVFCJ076 | YN76: INREV | YO76: The Carlyle Group | YP76: Peter Stoll | YQ76: peter.stoll@carlyle.com | YS76: http://click.surveylab.co.uk/anrev-inrev-ncreif-capital-raising-2016/?survey=NVFCJ076
A77: 105 | B77: ANRHV524 | C77: survey=ANRHV524 | D77: 42404.951 | F77: 2 | G77: 1|2|3| | I77: 59.100.29.190 | J77: ANREV | K77: Felicity Ambler | L77: MaxCap Investment Management | M77: =VLOOKUP(MID(O77,SEARCH("@",O77,1),LEN(O77)-SEARCH("@",O77,1)+1),[1]Sheet1!$D:$F,3,FALSE) -> M0263 | N77: Head of Distribution | O77: felicity@maxcapgroup.com.au | P77: 61429012120 | Q77: Australia | R77: AUD | T77: 1 | YK77: Mozilla/5.0 (Windows NT 6.2; WOW64) AppleWebKit/537.36 (KHTML, like Gecko) Chrome/47.0.2526.111 Safari/537.36 | YL77: 229 | YM77: ANRHV524 | YN77: ANREV | YO77: MaxCap Group | YP77: Felicity | YQ77: felicity@maxcapgroup.com.au | YS77: http://click.surveylab.co.uk/anrev-inrev-ncreif-capital-raising-2016/?survey=ANRHV524
A78: 106 | B78: ANXZF285 | C78: survey=ANXZF285 | D78: 42405.055 | E78: 42405.056 | F78: 14 | G78: 1|2|3|15| | I78: 125.214.249.100 | J78: ANREV | K78: James Fung | L78: CITIC Capital Holdings Limited | M78: =VLOOKUP(MID(O78,SEARCH("@",O78,1),LEN(O78)-SEARCH("@",O78,1)+1),[1]Sheet1!$D:$F,3,FALSE) -> M0107 | N78: Executive Director | O78: jfung@citiccapital.com | P78: 37106834 | Q78: Hong Kong | R78: USD | T78: 2 | U78: 6 | AC78: 0 | AJ78: 0 | AQ78: 0 | AX78: 0 | BE78: 0 | BL78: 0 | BM78: 0 | BN78: 0 | BO78: 0 | BP78: 0 | BQ78: 0 | BR78: 0 | BS78: 0 | BT78: FALSE | BU78: FALSE | BV78: FALSE | BW78: FALSE | BX78: FALSE | BY78: FALSE | CF78: 0 | CM78: 0 | CT78: 0 | DA78: 0 | DH78: 0 | DO78: 0 | DP78: 0 | DQ78: 0 | DR78: 0 | DS78: 0 | DT78: 0 | DU78: 0 | DV78: 0 | DW78: NO | DX78: NO | DY78: NO | DZ78: NO | EA78: NO | EB78: NO | EC78: NO | ED78: NO | EE78: NO | EF78: NO | EG78: NO | EH78: NO | EI78: NO | EJ78: NO | EK78: NO | EL78: NO | EM78: NO | EN78: NO | EO78: NO | EP78: NO | EQ78: NO | ER78: NO | ES78: NO | ET78: NO | EU78: NO | EV78: NO | EW78: NO | EX78: NO | EY78: NO | EZ78: NO | FA78: NO | FB78: NO | FC78: NO | FD78: NO | FE78: NO | FF78: NO | FM78: 0 | FT78: 0 | GA78: 0 | GH78: 0 | GO78: 0 | GV78: 0 | HC78: 0 | HK78: 0 | HL78: 0 | HM78: 0 | HN78: 0 | HO78: 0 | HP78: 0 | HQ78: 0 | HR78: 0 | HY78: 0 | IF78: 0 | IM78: 0 | IT78: 0 | JA78: 0 | JB78: 0 | JC78: 0 | JD78: 0 | JE78: 0 | JF78: 0 | JG78: 0 | JH78: 0 | JT78: 0 | KA78: 0 | KH78: 0 | KO78: 0 | KV78: 0 | LC78: 0 | LJ78: 0 | LR78: 0 | LS78: 0 | LT78: 0 | LU78: 0 | LV78: 0 | LW78: 0 | LX78: 0 | LY78: 0 | OK78: 0 | QW78: 0 | TI78: 0 | VU78: 0 | YG78: 0 | YH78: 2 | YI78: 2 | YJ78: 1 | YK78: Mozilla/5.0 (Windows NT 6.1; WOW64; Trident/7.0; rv:11.0) like Gecko | YL78: 86 | YM78: ANXZF285 | YN78: ANREV | YO78: CITIC Capital Holdings Ltd | YP78: Stanley Ching | YQ78: stanleyching@citiccapital.com | YS78: http://click.surveylab.co.uk/anrev-inrev-ncreif-capital-raising-2016/?survey=ANXZF285
A79: 107 | B79: ANHDG669 | C79: survey=ANHDG669 | D79: 42419.403 | E79: 42419.404 | F79: 14 | G79: 1|2|3|3|15|2|3|15| | I79: 203.192.153.138 | J79: ANREV | K79: Leon Chui | L79: Dymon Asia Real Estate | M79: =VLOOKUP(MID(O79,SEARCH("@",O79,1),LEN(O79)-SEARCH("@",O79,1)+1),[1]Sheet1!$D:$F,3,FALSE) -> N0303 | N79: Analyst | O79: leon.chui@dymonasia.com | P79: 60888301 | Q79: Hong Kong | R79: USD | T79: 2 | U79: 6 | V79: newly formed platform | AC79: 0 | AJ79: 0 | AQ79: 0 | AX79: 0 | BE79: 0 | BL79: 0 | BM79: 0 | BN79: 0 | BO79: 0 | BP79: 0 | BQ79: 0 | BR79: 0 | BS79: 0 | BT79: FALSE | BU79: FALSE | BV79: FALSE | BW79: FALSE | BX79: FALSE | BY79: FALSE | CF79: 0 | CM79: 0 | CT79: 0 | DA79: 0 | DH79: 0 | DO79: 0 | DP79: 0 | DQ79: 0 | DR79: 0 | DS79: 0 | DT79: 0 | DU79: 0 | DV79: 0 | DW79: NO | DX79: NO | DY79: NO | DZ79: NO | EA79: NO | EB79: NO | EC79: NO | ED79: NO | EE79: NO | EF79: NO | EG79: NO | EH79: NO | EI79: NO | EJ79: NO | EK79: NO | EL79: NO | EM79: NO | EN79: NO | EO79: NO | EP79: NO | EQ79: NO | ER79: NO | ES79: NO | ET79: NO | EU79: NO | EV79: NO | EW79: NO | EX79: NO | EY79: NO | EZ79: NO | FA79: NO | FB79: NO | FC79: NO | FD79: NO | FE79: NO | FF79: NO | FM79: 0 | FT79: 0 | GA79: 0 | GH79: 0 | GO79: 0 | GV79: 0 | HC79: 0 | HK79: 0 | HL79: 0 | HM79: 0 | HN79: 0 | HO79: 0 | HP79: 0 | HQ79: 0 | HR79: 0 | HY79: 0 | IF79: 0 | IM79: 0 | IT79: 0 | JA79: 0 | JB79: 0 | JC79: 0 | JD79: 0 | JE79: 0 | JF79: 0 | JG79: 0 | JH79: 0 | JT79: 0 | KA79: 0 | KH79: 0 | KO79: 0 | KV79: 0 | LC79: 0 | LJ79: 0 | LR79: 0 | LS79: 0 | LT79: 0 | LU79: 0 | LV79: 0 | LW79: 0 | LX79: 0 | LY79: 0 | OK79: 0 | QW79: 0 | TI79: 0 | VU79: 0 | YG79: 0 | YH79: 1 | YI79: 1 | YJ79: 1 | YK79: Mozilla/5.0 (Windows NT 6.3; WOW64; Trident/7.0; Touch; rv:11.0) like Gecko | YL79: 115 | YM79: ANHDG669 | YN79: ANREV | YO79: Dymon Asia Capital | YP79: William Lo | YQ79: william.lo@dymonasia.com | YS79: http://click.surveylab.co.uk/anrev-inrev-ncreif-capital-raising-2016/?survey=ANHDG669
A80: 108 | B80: ANJYJ704 | C80: survey=ANJYJ704 | D80: 42417.269 | E80: 42417.272 | F80: 14 | G80: 1|2|3|4|5|6|7|8|10|15| | I80: 202.77.62.76 | J80: ANREV | K80: John LEE | L80: Orion Partners Real Estate Group | M80: =VLOOKUP(MID(O80,SEARCH("@",O80,1),LEN(O80)-SEARCH("@",O80,1)+1),[1]Sheet1!$D:$F,3,FALSE) -> M0035 | N80: Partner and Head of Real Estate Group | O80: jlee@orionpartners.com | P80: +852 2218 2168 | Q80: Hong Kong | R80: USD | T80: 1 | AC80: 0 | AD80: 47 | AE80: 219 | AJ80: 266 | AQ80: 0 | AX80: 0 | BE80: 0 | BL80: 0 | BM80: 47 | BN80: 219 | BO80: 0 | BP80: 0 | BQ80: 0 | BR80: 0 | BS80: 266 | BT80: FALSE | BU80: TRUE | BV80: FALSE | BW80: FALSE | BX80: FALSE | BY80: FALSE | CF80: 0 | CG80: 1 | CH80: 1 | CM80: 2 | CT80: 0 | DA80: 0 | DH80: 0 | DO80: 0 | DP80: 1 | DQ80: 1 | DR80: 0 | DS80: 0 | DT80: 0 | DU80: 0 | DV80: 2 | DW80: NO | DX80: NO | DY80: NO | DZ80: NO | EA80: NO | EB80: NO | EC80: YES | ED80: YES | EE80: NO | EF80: NO | EG80: NO | EH80: NO | EI80: NO | EJ80: NO | EK80: NO | EL80: NO | EM80: NO | EN80: NO | EO80: NO | EP80: NO | EQ80: NO | ER80: NO | ES80: NO | ET80: NO | EU80: NO | EV80: NO | EW80: NO | EX80: NO | EY80: NO | EZ80: NO | FA80: NO | FB80: NO | FC80: NO | FD80: NO | FE80: NO | FF80: NO | FH80: 217 | FM80: 217 | FT80: 0 | GA80: 0 | GH80: 0 | GO80: 0 | GP80: 46 | GV80: 46 | HC80: 0 | HD80: General Partner co-investment | HE80: 1 | HF80: 2 | HK80: 3 | HL80: 47 | HM80: 219 | HN80: 0 | HO80: 0 | HP80: 0 | HQ80: 0 | HR80: 266 | HS80: 39 | HT80: 217 | HY80: 256 | HZ80: 8 | IA80: 2 | IF80: 10 | IM80: 0 | IT80: 0 | JA80: 0 | JB80: 47 | JC80: 219 | JD80: 0 | JE80: 0 | JF80: 0 | JG80: 0 | JH80: 266 | JK80: 100 | JT80: 0 | KA80: 0 | KH80: 0 | KO80: 0 | KV80: 0 | LC80: 0 | LJ80: 0 | LR80: 0 | LS80: 0 | LT80: 0 | LU80: 0 | LV80: 0 | LW80: 0 | LX80: 0 | LY80: 0 | MA80: 217 | MF80: 217 | NI80: 46 | NO80: 46 | NW80: General Partner`s co-investment | NX80: 1 | NY80: 2 | OD80: 3 | OE80: 47 | OF80: 219 | OK80: 266 | QW80: 0 | TI80: 0 | VU80: 0 | YG80: 0 | YH80: 1 | YI80: 1 | YJ80: 1 | YK80: Mozilla/5.0 (Windows NT 6.1; WOW64; Trident/7.0; rv:11.0) like Gecko | YL80: 421 | YM80: ANJYJ704 | YN80: ANREV | YO80: zzzAdditional Record | YS80: http://click.surveylab.co.uk/anrev-inrev-ncreif-capital-raising-2016/?survey=ANJYJ704
A81: 109 | B81: NVZYR182 | C81: survey=NVZYR182 | D81: 42417.315 | E81: 42417.317 | F81: 14 | G81: 1|2|3|2|3|4|5|6|7|8|2|3|4|5|6|7|8|4|5|6|7|8|11|13|2|3|4|5|6|4|5|6|2|3|4|5|6|7|8|11|13|2|3|4|5|6|7|8|11|13|6|2|3|4|5|6|2|3|4|5|6|7|6|7|8|11|13|11|3|4|5|6|7|8|11|13|6|7|8|11|13|2|3|4|5|6|7|8|11|13|15| | I81: 84.14.116.66 | J81: INREV | K81: Dietrich Heidtmann | L81: GTIS Partners | M81: =VLOOKUP(MID(O81,SEARCH("@",O81,1),LEN(O81)-SEARCH("@",O81,1)+1),[1]Sheet1!$D:$F,3,FALSE) -> M401 | N81: MD - Head of International Capital Markets | O81: dheidtmann@gtispartners.com | P81: 33170375880 | Q81: France | R81: USD | T81: 1 | AC81: 0 | AJ81: 0 | AK81: 57.5 | AQ81: 57.5 | AX81: 0 | BA81: 149.2 | BE81: 149.2 | BL81: 0 | BM81: 57.5 | BN81: 0 | BO81: 149.2 | BP81: 0 | BQ81: 0 | BR81: 0 | BS81: 206.7 | BT81: FALSE | BU81: FALSE | BV81: TRUE | BW81: FALSE | BX81: TRUE | BY81: FALSE | CF81: 0 | CM81: 0 | CN81: 1 | CT81: 1 | DA81: 0 | DD81: 1 | DH81: 1 | DO81: 0 | DP81: 1 | DQ81: 0 | DR81: 1 | DS81: 0 | DT81: 0 | DU81: 0 | DV81: 2 | DW81: NO | DX81: NO | DY81: NO | DZ81: NO | EA81: NO | EB81: NO | EC81: NO | ED81: NO | EE81: NO | EF81: NO | EG81: NO | EH81: NO | EI81: YES | EJ81: NO | EK81: NO | EL81: NO | EM81: NO | EN81: NO | EO81: NO | EP81: NO | EQ81: NO | ER81: NO | ES81: NO | ET81: NO | EU81: NO | EV81: NO | EW81: YES | EX81: NO | EY81: NO | EZ81: NO | FA81: NO | FB81: NO | FC81: NO | FD81: NO | FE81: NO | FF81: NO | FG81: 10 | FI81: 105 | FM81: 115 | FT81: 0 | GA81: 0 | GH81: 0 | GI81: 5 | GO81: 5 | GR81: 28 | GV81: 28 | GW81: 37.3 | GY81: 1.4 | HC81: 38.7 | HD81: Manager and Affliates | HE81: 5.2 | HG81: 14.8 | HK81: 20 | HL81: 57.5 | HM81: 0 | HN81: 149.2 | HO81: 0 | HP81: 0 | HQ81: 0 | HR81: 206.7 | HU81: 5.45 | HY81: 5.45 | IF81: 0 | IG81: 57.5 | II81: 142.25 | IM81: 199.75 | IP81: 1.5 | IT81: 1.5 | JA81: 0 | JB81: 57.5 | JC81: 0 | JD81: 149.2 | JE81: 0 | JF81: 0 | JG81: 0 | JH81: 206.7 | JI81: 0 | JJ81: 0 | JK81: 100 | JT81: 0 | KA81: 0 | KH81: 0 | KO81: 0 | KV81: 0 | LC81: 0 | LJ81: 0 | LR81: 0 | LS81: 0 | LT81: 0 | LU81: 0 | LV81: 0 | LW81: 0 | LX81: 0 | LY81: 0 | OK81: 0 | OL81: 10 | PN81: 5 | QB81: 37.3 | QI81: Manager and Affiliates | QJ81: 5.2 | QW81: 57.5 | TI81: 0 | TL81: 105 | UU81: 28 | VB81: 1.4 | VG81: Manager and Affilates | VJ81: 14.8 | VU81: 149.2 | YG81: 0 | YH81: 1 | YI81: 3 | YJ81: 1 | YK81: Mozilla/5.0 (Windows NT 6.1; WOW64; Trident/7.0; rv:11.0) like Gecko | YL81: 155 | YM81: NVZYR182 | YN81: INREV | YO81: GTIS Partners | YP81: William G. Cisneros | YQ81: bcisneros@.gtispartners.com | YS81: http://click.surveylab.co.uk/anrev-inrev-ncreif-capital-raising-2016/?survey=NVZYR182
A82: 110 | B82: ANNPP246 | C82: survey=ANNPP246 | D82: 42418.398 | E82: 42418.406 | F82: 14 | G82: 1|2|3|4|4|5|6|7|8|9|10|11|15|2|3|4|5|6|7|8|2|3|2|3|4|5|6|7|8|10|15| | I82: 125.215.194.145 | J82: ANREV | K82: Loretta Li | M82: =VLOOKUP(MID(O82,SEARCH("@",O82,1),LEN(O82)-SEARCH("@",O82,1)+1),[1]Sheet1!$D:$F,3,FALSE) -> M421 | O82: lli@archcapital.net | Q82: Hong Kong | R82: USD | T82: 1 | AC82: 0 | AD82: 119.7 | AJ82: 119.7 | AQ82: 0 | AX82: 0 | BE82: 0 | BL82: 0 | BM82: 119.7 | BN82: 0 | BO82: 0 | BP82: 0 | BQ82: 0 | BR82: 0 | BS82: 119.7 | BT82: FALSE | BU82: TRUE | BV82: FALSE | BW82: FALSE | BX82: FALSE | BY82: FALSE | CF82: 0 | CG82: 1 | CM82: 1 | CT82: 0 | DA82: 0 | DH82: 0 | DO82: 0 | DP82: 1 | DQ82: 0 | DR82: 0 | DS82: 0 | DT82: 0 | DU82: 0 | DV82: 1 | DW82: NO | DX82: NO | DY82: NO | DZ82: NO | EA82: NO | EB82: NO | EC82: YES | ED82: NO | EE82: NO | EF82: NO | EG82: NO | EH82: NO | EI82: NO | EJ82: NO | EK82: NO | EL82: NO | EM82: NO | EN82: NO | EO82: NO | EP82: NO | EQ82: NO | ER82: NO | ES82: NO | ET82: NO | EU82: NO | EV82: NO | EW82: NO | EX82: NO | EY82: NO | EZ82: NO | FA82: NO | FB82: NO | FC82: NO | FD82: NO | FE82: NO | FF82: NO | FG82: 50 | FM82: 50 | FN82: 50 | FT82: 50 | GA82: 0 | GH82: 0 | GO82: 0 | GV82: 0 | GW82: 4.7 | HC82: 4.7 | HD82: Endowment | HE82: 15 | HK82: 15 | HL82: 119.7 | HM82: 0 | HN82: 0 | HO82: 0 | HP82: 0 | HQ82: 0 | HR82: 119.7 | HY82: 0 | HZ82: 65.7 | IF82: 65.7 | IG82: 54 | IM82: 54 | IT82: 0 | JA82: 0 | JB82: 119.7 | JC82: 0 | JD82: 0 | JE82: 0 | JF82: 0 | JG82: 0 | JH82: 119.7 | JI82: 3.3 | JK82: 0.6 | JL82: our own indirect relationship with investors | JM82: 96.1 | JT82: 0 | KA82: 0 | KH82: 0 | KO82: 0 | KV82: 0 | LC82: 0 | LJ82: 0 | LR82: 0 | LS82: 0 | LT82: 0 | LU82: 0 | LV82: 0 | LW82: 0 | LX82: 0 | LY82: 0 | LZ82: 50 | MF82: 50 | MG82: 50 | MM82: 50 | NP82: 4.7 | NV82: 4.7 | NW82: endowment | NX82: 15 | OD82: 15 | OE82: 119.7 | OK82: 119.7 | QW82: 0 | TI82: 0 | VU82: 0 | YG82: 0 | YH82: 3 | YI82: 3 | YJ82: 2 | YK82: Mozilla/5.0 (Windows NT 6.1; WOW64) AppleWebKit/537.36 (KHTML, like Gecko) Chrome/48.0.2564.103 Safari/537.36 | YL82: 38 | YM82: ANNPP246 | YN82: ANREV | YO82: ARCH Capital Management Company Limited | YP82: Richard Yue | YQ82: ryue@archcapital.net | YS82: http://click.surveylab.co.uk/anrev-inrev-ncreif-capital-raising-2016/?survey=ANNPP246
A83: 111 | B83: NVUVN216 | C83: survey=NVUVN216 | D83: 42405.585 | E83: 42405.592 | F83: 14 | G83: 1|2|3|15| | I83: 89.191.7.26 | J83: INREV | K83: Nils Eivind RIsvand | L83: Steen & Strøm AS | M83: =VLOOKUP(MID(O83,SEARCH("@",O83,1),LEN(O83)-SEARCH("@",O83,1)+1),[1]Sheet1!$D:$F,3,FALSE) -> M676 | N83: Chief Legal Officer | O83: nils.eivind.risvand@steenstrom.com | P83: 4723213505 | Q83: Norway | R83: NOK | T83: 2 | U83: 6 | V83: No need | AC83: 0 | AJ83: 0 | AQ83: 0 | AX83: 0 | BE83: 0 | BL83: 0 | BM83: 0 | BN83: 0 | BO83: 0 | BP83: 0 | BQ83: 0 | BR83: 0 | BS83: 0 | BT83: FALSE | BU83: FALSE | BV83: FALSE | BW83: FALSE | BX83: FALSE | BY83: FALSE | CF83: 0 | CM83: 0 | CT83: 0 | DA83: 0 | DH83: 0 | DO83: 0 | DP83: 0 | DQ83: 0 | DR83: 0 | DS83: 0 | DT83: 0 | DU83: 0 | DV83: 0 | DW83: NO | DX83: NO | DY83: NO | DZ83: NO | EA83: NO | EB83: NO | EC83: NO | ED83: NO | EE83: NO | EF83: NO | EG83: NO | EH83: NO | EI83: NO | EJ83: NO | EK83: NO | EL83: NO | EM83: NO | EN83: NO | EO83: NO | EP83: NO | EQ83: NO | ER83: NO | ES83: NO | ET83: NO | EU83: NO | EV83: NO | EW83: NO | EX83: NO | EY83: NO | EZ83: NO | FA83: NO | FB83: NO | FC83: NO | FD83: NO | FE83: NO | FF83: NO | FM83: 0 | FT83: 0 | GA83: 0 | GH83: 0 | GO83: 0 | GV83: 0 | HC83: 0 | HK83: 0 | HL83: 0 | HM83: 0 | HN83: 0 | HO83: 0 | HP83: 0 | HQ83: 0 | HR83: 0 | HY83: 0 | IF83: 0 | IM83: 0 | IT83: 0 | JA83: 0 | JB83: 0 | JC83: 0 | JD83: 0 | JE83: 0 | JF83: 0 | JG83: 0 | JH83: 0 | JT83: 0 | KA83: 0 | KH83: 0 | KO83: 0 | KV83: 0 | LC83: 0 | LJ83: 0 | LR83: 0 | LS83: 0 | LT83: 0 | LU83: 0 | LV83: 0 | LW83: 0 | LX83: 0 | LY83: 0 | OK83: 0 | QW83: 0 | TI83: 0 | VU83: 0 | YG83: 0 | YH83: 3 | YI83: 3 | YJ83: 1 | YK83: Mozilla/5.0 (Windows NT 6.1; Trident/7.0; rv:11.0) like Gecko | YL83: 324 | YM83: NVUVN216 | YN83: INREV | YO83: Steen & Strøm | YP83: Nils Eivind Risvand | YQ83: nils.eivind.risvand@steenstrom.com | YS83: http://click.surveylab.co.uk/anrev-inrev-ncreif-capital-raising-2016/?survey=NVUVN216
A84: 112 | B84: CFRCL614 | C84: survey=CFRCL614 | D84: 42405.657 | E84: 42405.667 | F84: 14 | G84: 1|2|3|4|5|6|7|8|11|15| | I84: 38.65.203.2 | J84: NCREIF | K84: Patricia Richardson | L84: Guggenheim Real Estate LLC | M84: =VLOOKUP(MID(O84,SEARCH("@",O84,1),LEN(O84)-SEARCH("@",O84,1)+1),[1]Sheet1!$D:$F,3,FALSE) -> NC031 | N84: Director/Controller | O84: prichardson@guggenheimrealestate.com | P84: 6175365542 | Q84: United States | R84: USD | T84: 1 | AC84: 0 | AJ84: 0 | AK84: 54.49 | AQ84: 54.49 | AX84: 0 | BE84: 0 | BL84: 0 | BM84: 54.49 | BN84: 0 | BO84: 0 | BP84: 0 | BQ84: 0 | BR84: 0 | BS84: 54.49 | BT84: FALSE | BU84: FALSE | BV84: TRUE | BW84: FALSE | BX84: FALSE | BY84: FALSE | CF84: 0 | CM84: 0 | CN84: 2 | CT84: 2 | DA84: 0 | DH84: 0 | DO84: 0 | DP84: 2 | DQ84: 0 | DR84: 0 | DS84: 0 | DT84: 0 | DU84: 0 | DV84: 2 | DW84: NO | DX84: NO | DY84: NO | DZ84: NO | EA84: NO | EB84: NO | EC84: NO | ED84: NO | EE84: NO | EF84: NO | EG84: NO | EH84: NO | EI84: YES | EJ84: NO | EK84: NO | EL84: NO | EM84: NO | EN84: NO | EO84: NO | EP84: NO | EQ84: NO | ER84: NO | ES84: NO | ET84: NO | EU84: NO | EV84: NO | EW84: NO | EX84: NO | EY84: NO | EZ84: NO | FA84: NO | FB84: NO | FC84: NO | FD84: NO | FE84: NO | FF84: NO | FG84: 5 | FM84: 5 | FT84: 0 | GA84: 0 | GH84: 0 | GO84: 0 | GP84: 40.85 | GV84: 40.85 | GW84: 8.64 | HC84: 8.64 | HK84: 0 | HL84: 54.49 | HM84: 0 | HN84: 0 | HO84: 0 | HP84: 0 | HQ84: 0 | HR84: 54.49 | HY84: 0 | IF84: 0 | IG84: 54.49 | IM84: 54.49 | IT84: 0 | JA84: 0 | JB84: 54.49 | JC84: 0 | JD84: 0 | JE84: 0 | JF84: 0 | JG84: 0 | JH84: 54.49 | JK84: 100 | JT84: 0 | KA84: 0 | KH84: 0 | KO84: 0 | KV84: 0 | LC84: 0 | LJ84: 0 | LR84: 0 | LS84: 0 | LT84: 0 | LU84: 0 | LV84: 0 | LW84: 0 | LX84: 0 | LY84: 0 | OK84: 0 | OL84: 5 | OR84: 5 | PU84: 40.85 | QA84: 40.85 | QB84: 8.64 | QH84: 8.64 | QQ84: 54.49 | QR84: 0 | QW84: 54.49 | TI84: 0 | VU84: 0 | YG84: 0 | YH84: 1 | YI84: 3 | YJ84: 1 | YK84: Mozilla/5.0 (Windows NT 6.1; WOW64; Trident/7.0; rv:11.0) like Gecko | YL84: 156 | YM84: CFRCL614 | YN84: NCREIF | YO84: Guggenheim Real Estate | YS84: http://click.surveylab.co.uk/anrev-inrev-ncreif-capital-raising-2016/?survey=CFRCL614
A85: 113 | B85: ANZMF541 | C85: survey=ANZMF541 | D85: 42410.598 | E85: 42410.61 | F85: 14 | G85: 1|2|2|3|4|3|4|5|6|7|8|8|2|3|4|5|4|5|6|7|8|9|11|9|9|11|15| | I85: 12.181.68.226 | J85: ANREV | K85: Ashley Haislip | L85: Quadrant Real Estate Advisors | M85: =VLOOKUP(MID(O85,SEARCH("@",O85,1),LEN(O85)-SEARCH("@",O85,1)+1),[1]Sheet1!$D:$F,3,FALSE) -> M0158 | N85: Marketing and Business Development Analyst | O85: ahaislip@quadrantrea.com | P85: 770-752-6738 | Q85: United States | R85: USD | T85: 1 | X85: 246 | AC85: 246 | AJ85: 0 | AL85: 1306 | AQ85: 1306 | AX85: 0 | BE85: 0 | BL85: 0 | BM85: 0 | BN85: 1552 | BO85: 0 | BP85: 0 | BQ85: 0 | BR85: 0 | BS85: 1552 | BT85: TRUE | BU85: FALSE | BV85: TRUE | BW85: FALSE | BX85: FALSE | BY85: FALSE | CA85: 1 | CF85: 1 | CM85: 0 | CO85: 1 | CT85: 1 | DA85: 0 | DH85: 0 | DO85: 0 | DP85: 0 | DQ85: 2 | DR85: 0 | DS85: 0 | DT85: 0 | DU85: 0 | DV85: 2 | DW85: NO | DX85: YES | DY85: NO | DZ85: NO | EA85: NO | EB85: NO | EC85: NO | ED85: NO | EE85: NO | EF85: NO | EG85: NO | EH85: NO | EI85: NO | EJ85: YES | EK85: NO | EL85: NO | EM85: NO | EN85: NO | EO85: NO | EP85: NO | EQ85: NO | ER85: NO | ES85: NO | ET85: NO | EU85: NO | EV85: NO | EW85: NO | EX85: NO | EY85: NO | EZ85: NO | FA85: NO | FB85: NO | FC85: NO | FD85: NO | FE85: NO | FF85: NO | FH85: 246 | FM85: 246 | FO85: 1306 | FT85: 1306 | GA85: 0 | GH85: 0 | GO85: 0 | GV85: 0 | HC85: 0 | HK85: 0 | HL85: 0 | HM85: 1552 | HN85: 0 | HO85: 0 | HP85: 0 | HQ85: 0 | HR85: 1552 | HY85: 0 | IA85: 246 | IF85: 246 | IH85: 1306 | IM85: 1306 | IT85: 0 | JA85: 0 | JB85: 0 | JC85: 1552 | JD85: 0 | JE85: 0 | JF85: 0 | JG85: 0 | JH85: 1552 | JK85: 100 | JO85: 246 | JT85: 246 | KA85: 0 | KH85: 0 | KO85: 0 | KV85: 0 | LC85: 0 | LJ85: 0 | LR85: 0 | LS85: 0 | LT85: 246 | LU85: 0 | LV85: 0 | LW85: 0 | LX85: 0 | LY85: 246 | OK85: 0 | OT85: 1306 | QW85: 1306 | TI85: 0 | VU85: 0 | YG85: 0 | YH85: 1 | YI85: 3 | YJ85: 1 | YK85: Mozilla/5.0 (Windows NT 10.0; WOW64; rv:44.0) Gecko/20100101 Firefox/44.0 | YL85: 292 | YM85: ANZMF541 | YN85: ANREV | YO85: Quadrant Real Estate Advisors | YP85: Michael | YQ85: mwood@quadrantrea.com | YS85: http://click.surveylab.co.uk/anrev-inrev-ncreif-capital-raising-2016/?survey=ANZMF541
A86: 114 | B86: NVYCJ144 | C86: survey=NVYCJ144 | D86: 42405.922 | E86: 42405.925 | F86: 14 | G86: 1|2|3|4|5|6|7|8|9|15| | I86: 89.28.234.19 | J86: INREV | K86: MICHAEL WALTON | L86: RYNDA PROPERTY INVESTORS LLP | M86: =VLOOKUP(MID(O86,SEARCH("@",O86,1),LEN(O86)-SEARCH("@",O86,1)+1),[1]Sheet1!$D:$F,3,FALSE) -> M616 | N86: CHIEF EXECUTIVE | O86: michael.walton@ryndaproperty.com | P86: 020 3328 4700 | Q86: United Kingdom | R86: EUR | T86: 1 | X86: 35 | Z86: 70 | AC86: 105 | AJ86: 0 | AQ86: 0 | AX86: 0 | BE86: 0 | BL86: 0 | BM86: 0 | BN86: 35 | BO86: 0 | BP86: 70 | BQ86: 0 | BR86: 0 | BS86: 105 | BT86: TRUE | BU86: FALSE | BV86: FALSE | BW86: FALSE | BX86: FALSE | BY86: FALSE | CA86: 1 | CC86: 2 | CF86: 3 | CM86: 0 | CT86: 0 | DA86: 0 | DH86: 0 | DO86: 0 | DP86: 0 | DQ86: 1 | DR86: 0 | DS86: 2 | DT86: 0 | DU86: 0 | DV86: 3 | DW86: NO | DX86: YES | DY86: NO | DZ86: YES | EA86: NO | EB86: NO | EC86: NO | ED86: NO | EE86: NO | EF86: NO | EG86: NO | EH86: NO | EI86: NO | EJ86: NO | EK86: NO | EL86: NO | EM86: NO | EN86: NO | EO86: NO | EP86: NO | EQ86: NO | ER86: NO | ES86: NO | ET86: NO | EU86: NO | EV86: NO | EW86: NO | EX86: NO | EY86: NO | EZ86: NO | FA86: NO | FB86: NO | FC86: NO | FD86: NO | FE86: NO | FF86: NO | FM86: 0 | FT86: 0 | FV86: 35 | GA86: 35 | GH86: 0 | GO86: 0 | GV86: 0 | HC86: 0 | HD86: Private Equty Funds | HH86: 70 | HK86: 70 | HL86: 0 | HM86: 35 | HN86: 0 | HO86: 70 | HP86: 0 | HQ86: 0 | HR86: 105 | HT86: 35 | HV86: 20 | HY86: 55 | IF86: 0 | IJ86: 50 | IM86: 50 | IT86: 0 | JA86: 0 | JB86: 0 | JC86: 35 | JD86: 0 | JE86: 70 | JF86: 0 | JG86: 0 | JH86: 105 | JK86: 100 | JT86: 0 | KA86: 0 | KC86: 35 | KH86: 35 | KO86: 0 | KV86: 0 | LC86: 0 | LJ86: 0 | LK86: PRIVATE EQUITY | LO86: 70 | LR86: 70 | LS86: 0 | LT86: 35 | LU86: 0 | LV86: 70 | LW86: 0 | LX86: 0 | LY86: 105 | OK86: 0 | QW86: 0 | TI86: 0 | VU86: 0 | YG86: 0 | YH86: 1 | YI86: 2 | YJ86: 1 | YK86: Mozilla/5.0 (compatible; MSIE 9.0; Windows NT 6.1; WOW64; Trident/5.0) | YL86: 307 | YM86: NVYCJ144 | YN86: INREV | YO86: Rynda Property Investors | YP86: Michael Walton | YQ86: michael.walton@ryndaproperty.com | YS86: http://click.surveylab.co.uk/anrev-inrev-ncreif-capital-raising-2016/?survey=NVYCJ144
A87: 115 | B87: ANPHB454 | C87: survey=ANPHB454 | D87: 42408.145 | E87: 42408.153 | F87: 14 | G87: 1|2|3|4|2|3|4|5|6|7|8|10|10|10|2|3|4|5|6|7|8|10|2|3|4|5|4|5|6|7|8|10|15| | I87: 113.154.121.208 | J87: ANREV | K87: Naoya Nakata | L87: PAG Real Estate | M87: =VLOOKUP(MID(O87,SEARCH("@",O87,1),LEN(O87)-SEARCH("@",O87,1)+1),[1]Sheet1!$D:$F,3,FALSE) -> M0137 | N87: Managing Director | O87: nnakata@pagasia.com | P87: 81 3 5776 1932 | Q87: Hong Kong | R87: USD | T87: 1 | AC87: 0 | AD87: 950 | AJ87: 950 | AQ87: 0 | AX87: 0 | BE87: 0 | BL87: 0 | BM87: 950 | BN87: 0 | BO87: 0 | BP87: 0 | BQ87: 0 | BR87: 0 | BS87: 950 | BT87: FALSE | BU87: TRUE | BV87: FALSE | BW87: FALSE | BX87: FALSE | BY87: FALSE | CF87: 0 | CG87: 1 | CM87: 1 | CT87: 0 | DA87: 0 | DH87: 0 | DO87: 0 | DP87: 1 | DQ87: 0 | DR87: 0 | DS87: 0 | DT87: 0 | DU87: 0 | DV87: 1 | DW87: NO | DX87: NO | DY87: NO | DZ87: NO | EA87: NO | EB87: NO | EC87: YES | ED87: NO | EE87: NO | EF87: NO | EG87: NO | EH87: NO | EI87: NO | EJ87: NO | EK87: NO | EL87: NO | EM87: NO | EN87: NO | EO87: NO | EP87: NO | EQ87: NO | ER87: NO | ES87: NO | ET87: NO | EU87: NO | EV87: NO | EW87: NO | EX87: NO | EY87: NO | EZ87: NO | FA87: NO | FB87: NO | FC87: NO | FD87: NO | FE87: NO | FF87: NO | FG87: 665 | FM87: 665 | FT87: 0 | FU87: 100 | GA87: 100 | GH87: 0 | GO87: 0 | GP87: 185 | GV87: 185 | HC87: 0 | HK87: 0 | HL87: 950 | HM87: 0 | HN87: 0 | HO87: 0 | HP87: 0 | HQ87: 0 | HR87: 950 | HS87: 635 | HY87: 635 | HZ87: 115 | IF87: 115 | IG87: 200 | IM87: 200 | IT87: 0 | JA87: 0 | JB87: 950 | JC87: 0 | JD87: 0 | JE87: 0 | JF87: 0 | JG87: 0 | JH87: 950 | JI87: 100 | JT87: 0 | KA87: 0 | KH87: 0 | KO87: 0 | KV87: 0 | LC87: 0 | LJ87: 0 | LR87: 0 | LS87: 0 | LT87: 0 | LU87: 0 | LV87: 0 | LW87: 0 | LX87: 0 | LY87: 0 | LZ87: 665 | MF87: 665 | MM87: 0 | MN87: 100 | MT87: 100 | NH87: 0 | NI87: 185 | NO87: 185 | OE87: 950 | OK87: 950 | QW87: 0 | TI87: 0 | VU87: 0 | YG87: 0 | YH87: 1 | YI87: 3 | YJ87: 1 | YK87: Mozilla/5.0 (Windows NT 6.3; WOW64) AppleWebKit/537.36 (KHTML, like Gecko) Chrome/48.0.2564.103 Safari/537.36 | YL87: 267 | YM87: ANPHB454 | YN87: ANREV | YO87: PAG | YP87: Naoya Nakata | YQ87: nnakata@pagasia.com | YS87: http://click.surveylab.co.uk/anrev-inrev-ncreif-capital-raising-2016/?survey=ANPHB454
A88: 116 | B88: NVDDV007 | C88: survey=NVDDV007 | D88: 42423.461 | E88: 42417.695 | F88: 6 | G88: 1|2|2|2|3|4|5|2|3|4|5|6|7|8|4|5|6|7|8|9|10|15|2|2|3|4|5|6|6|7|7|8|2|3|4|5|6|7|6|7|8|9|7| | I88: 212.155.238.154 | J88: INREV | K88: Jean-Baptiste LEFIEF | L88: AXA Investment Managers - Real Assets | M88: =VLOOKUP(MID(O88,SEARCH("@",O88,1),LEN(O88)-SEARCH("@",O88,1)+1),[1]Sheet1!$D:$F,3,FALSE) -> M041 | N88: Global Head of Marketing & Communication | O88: jeanbaptiste.lefief@axa-im.com | P88: 33144458311 | Q88: France | R88: EUR | T88: 1 | W88: 1818 | X88: 114 | Z88: 2063 | AB88: 1832 | AC88: 5827 | AE88: 73 | AJ88: 73 | AQ88: 0 | AX88: 0 | BE88: 0 | BL88: 0 | BM88: 1818 | BN88: 187 | BO88: 0 | BP88: 2063 | BQ88: 0 | BR88: 1832 | BS88: 5900 | BT88: TRUE | BU88: TRUE | BV88: FALSE | BW88: FALSE | BX88: FALSE | BY88: FALSE | BZ88: 8 | CA88: 5 | CC88: 8 | CE88: 2 | CF88: 23 | CH88: 1 | CM88: 1 | CT88: 0 | DA88: 0 | DH88: 0 | DO88: 0 | DP88: 8 | DQ88: 6 | DR88: 0 | DS88: 8 | DT88: 0 | DU88: 2 | DV88: 24 | DW88: YES | DX88: YES | DY88: NO | DZ88: YES | EA88: NO | EB88: YES | EC88: NO | ED88: YES | EE88: NO | EF88: NO | EG88: NO | EH88: NO | EI88: NO | EJ88: NO | EK88: NO | EL88: NO | EM88: NO | EN88: NO | EO88: NO | EP88: NO | EQ88: NO | ER88: NO | ES88: NO | ET88: NO | EU88: NO | EV88: NO | EW88: NO | EX88: NO | EY88: NO | EZ88: NO | FA88: NO | FB88: NO | FC88: NO | FD88: NO | FE88: NO | FF88: NO | FG88: 10 | FJ88: 346 | FM88: 356 | FN88: 1107 | FO88: 174 | FQ88: 1025 | FS88: 1752 | FT88: 4058 | FX88: 346 | FZ88: 80 | GA88: 426 | GE88: 346 | GH88: 346 | GO88: 0 | GV88: 0 | HC88: 0 | HD88: Bank`s own accounts | HE88: 5 | HK88: 5 | HL88: 1122 | HM88: 174 | HN88: 0 | HO88: 2063 | HP88: 0 | HQ88: 1832 | HR88: 5191 | HS88: 874 | HT88: 102 | HV88: 913 | HX88: 1832 | HY88: 3721 | HZ88: 71 | IA88: 73 | IC88: 346 | IF88: 490 | IG88: 176 | IJ88: 804 | IM88: 980 | IT88: 0 | JA88: 0 | JB88: 1121 | JC88: 175 | JD88: 0 | JE88: 2063 | JF88: 0 | JG88: 1832 | JH88: 5191 | JN88: 10 | JQ88: 346 | JT88: 356 | JU88: 1107 | JV88: 114 | JX88: 1025 | JZ88: 1752 | KA88: 3998 | KE88: 346 | KG88: 80 | KH88: 426 | KL88: 346 | KO88: 346 | KV88: 0 | LC88: 0 | LJ88: 0 | LK88: Bank`s own accounts or unit linked | LL88: 701 | LR88: 701 | LS88: 1818 | LT88: 114 | LU88: 0 | LV88: 2063 | LW88: 0 | LX88: 1832 | LY88: 5827 | MH88: 73 | MM88: 73 | OF88: 73 | OK88: 73 | QW88: 0 | TI88: 0 | VU88: 0 | YG88: 0 | YH88: 3 | YI88: 3 | YJ88: 2 | YK88: Mozilla/5.0 (Windows NT 6.1; WOW64; Trident/7.0; rv:11.0) like Gecko | YL88: 51 | YM88: NVDDV007 | YN88: INREV | YO88: AXA Real Estate | YP88: Thibault Gautret | YQ88: thibault.gautret@axa-im.com | YS88: http://click.surveylab.co.uk/anrev-inrev-ncreif-capital-raising-2016/?survey=NVDDV007
A89: 117 | B89: NVEAR008 | C89: survey=NVEAR008 | D89: 42408.375 | E89: 42408.44 | F89: 14 | G89: 1|2|3|4|5|4|5|3|4|5|6|7|8|9|15| | I89: 80.113.168.219 | J89: INREV | K89: Mirjam Witteman | L89: Vesteda Investment Management | M89: =VLOOKUP(MID(O89,SEARCH("@",O89,1),LEN(O89)-SEARCH("@",O89,1)+1),[1]Sheet1!$D:$F,3,FALSE) -> M040 | N89: Investor Relations | O89: m.witteman@vesteda.com | P89: 06 15 04 67 51 | Q89: Netherlands | R89: EUR | T89: 1 | W89: 415 | AC89: 415 | AJ89: 0 | AQ89: 0 | AX89: 0 | BE89: 0 | BL89: 0 | BM89: 415 | BN89: 0 | BO89: 0 | BP89: 0 | BQ89: 0 | BR89: 0 | BS89: 415 | BT89: TRUE | BU89: FALSE | BV89: FALSE | BW89: FALSE | BX89: FALSE | BY89: FALSE | BZ89: 1 | CF89: 1 | CM89: 0 | CT89: 0 | DA89: 0 | DH89: 0 | DO89: 0 | DP89: 1 | DQ89: 0 | DR89: 0 | DS89: 0 | DT89: 0 | DU89: 0 | DV89: 1 | DW89: YES | DX89: NO | DY89: NO | DZ89: NO | EA89: NO | EB89: NO | EC89: NO | ED89: NO | EE89: NO | EF89: NO | EG89: NO | EH89: NO | EI89: NO | EJ89: NO | EK89: NO | EL89: NO | EM89: NO | EN89: NO | EO89: NO | EP89: NO | EQ89: NO | ER89: NO | ES89: NO | ET89: NO | EU89: NO | EV89: NO | EW89: NO | EX89: NO | EY89: NO | EZ89: NO | FA89: NO | FB89: NO | FC89: NO | FD89: NO | FE89: NO | FF89: NO | FM89: 0 | FN89: 300 | FT89: 300 | GA89: 0 | GH89: 0 | GO89: 0 | GV89: 0 | HC89: 0 | HD89: Bank | HE89: 115 | HK89: 115 | HL89: 415 | HM89: 0 | HN89: 0 | HO89: 0 | HP89: 0 | HQ89: 0 | HR89: 415 | HS89: 300 | HY89: 300 | HZ89: 115 | IF89: 115 | IM89: 0 | IT89: 0 | JA89: 0 | JB89: 415 | JC89: 0 | JD89: 0 | JE89: 0 | JF89: 0 | JG89: 0 | JH89: 415 | JI89: 100 | JT89: 0 | JU89: 300 | KA89: 300 | KH89: 0 | KO89: 0 | KV89: 0 | LC89: 0 | LJ89: 0 | LK89: bank | LL89: 115 | LR89: 115 | LS89: 415 | LT89: 0 | LU89: 0 | LV89: 0 | LW89: 0 | LX89: 0 | LY89: 415 | OK89: 0 | QW89: 0 | TI89: 0 | VU89: 0 | YG89: 0 | YH89: 2 | YI89: 3 | YJ89: 1 | YK89: Mozilla/5.0 (Windows NT 6.1; WOW64; Trident/7.0; rv:11.0) like Gecko | YL89: 353 | YM89: NVEAR008 | YN89: INREV | YO89: Vesteda Investment Management BV | YP89: Helene Pragt | YQ89: h.pragt@vesteda.com | YS89: http://click.surveylab.co.uk/anrev-inrev-ncreif-capital-raising-2016/?survey=NVEAR008
A90: 118 | B90: NVLZH943 | C90: survey=NVLZH943 | D90: 42408.453 | E90: 42408.461 | F90: 14 | G90: 1|2|3|4|5|6|7|8|9|15| | I90: 194.151.29.210 | J90: INREV | K90: Mark Nieuwenbroek | L90: Amvest | M90: =VLOOKUP(MID(O90,SEARCH("@",O90,1),LEN(O90)-SEARCH("@",O90,1)+1),[1]Sheet1!$D:$F,3,FALSE) -> M015 | N90: Manager Investor Relations | O90: mnieuwenbroek@amvest.nl | P90: 31204301308 | Q90: Netherlands | R90: EUR | T90: 1 | W90: 300 | AC90: 300 | AJ90: 0 | AQ90: 0 | AX90: 0 | BE90: 0 | BL90: 0 | BM90: 300 | BN90: 0 | BO90: 0 | BP90: 0 | BQ90: 0 | BR90: 0 | BS90: 300 | BT90: TRUE | BU90: FALSE | BV90: FALSE | BW90: FALSE | BX90: FALSE | BY90: FALSE | BZ90: 1 | CF90: 1 | CM90: 0 | CT90: 0 | DA90: 0 | DH90: 0 | DO90: 0 | DP90: 1 | DQ90: 0 | DR90: 0 | DS90: 0 | DT90: 0 | DU90: 0 | DV90: 1 | DW90: YES | DX90: NO | DY90: NO | DZ90: NO | EA90: NO | EB90: NO | EC90: NO | ED90: NO | EE90: NO | EF90: NO | EG90: NO | EH90: NO | EI90: NO | EJ90: NO | EK90: NO | EL90: NO | EM90: NO | EN90: NO | EO90: NO | EP90: NO | EQ90: NO | ER90: NO | ES90: NO | ET90: NO | EU90: NO | EV90: NO | EW90: NO | EX90: NO | EY90: NO | EZ90: NO | FA90: NO | FB90: NO | FC90: NO | FD90: NO | FE90: NO | FF90: NO | FG90: 270 | FM90: 270 | FT90: 0 | GA90: 0 | GH90: 0 | GO90: 0 | GV90: 0 | HC90: 0 | HD90: Regulated financial sector institution | HE90: 30 | HK90: 30 | HL90: 300 | HM90: 0 | HN90: 0 | HO90: 0 | HP90: 0 | HQ90: 0 | HR90: 300 | HS90: 300 | HY90: 300 | IF90: 0 | IM90: 0 | IT90: 0 | JA90: 0 | JB90: 300 | JC90: 0 | JD90: 0 | JE90: 0 | JF90: 0 | JG90: 0 | JH90: 300 | JI90: 0 | JJ90: 50 | JK90: 50 | JN90: 270 | JT90: 270 | KA90: 0 | KH90: 0 | KO90: 0 | KV90: 0 | LC90: 0 | LJ90: 0 | LK90: Regulated financial sector institution | LL90: 30 | LR90: 30 | LS90: 300 | LT90: 0 | LU90: 0 | LV90: 0 | LW90: 0 | LX90: 0 | LY90: 300 | OK90: 0 | QW90: 0 | TI90: 0 | VU90: 0 | YG90: 0 | YH90: 1 | YI90: 1 | YJ90: 1 | YK90: Mozilla/5.0 (Windows NT 6.1; WOW64; Trident/7.0; rv:11.0) like Gecko | YL90: 33 | YM90: NVLZH943 | YN90: INREV | YO90: Amvest | YP90: Mark Nieuwenbroek | YQ90: mnieuwenbroek@amvest.nl | YS90: http://click.surveylab.co.uk/anrev-inrev-ncreif-capital-raising-2016/?survey=NVLZH943
A91: 119 | B91: NVPXD253 | C91: survey=NVPXD253 | D91: 42409.368 | E91: 42409.372 | F91: 14 | G91: 1|2|3|4|5|4|5|4|5|6|6|3|4|5|6|7|8|2|3|4|5|6|7|7|8|4|5|6|7|8|9|12|15| | I91: 198.240.213.23 | J91: INREV | K91: Ulrich Braun | L91: Credit Suisse | M91: =VLOOKUP(MID(O91,SEARCH("@",O91,1),LEN(O91)-SEARCH("@",O91,1)+1),[1]Sheet1!$D:$F,3,FALSE) -> M04230 | N91: Head Real Estate Strategies & Advisory | O91: ulrich.braun@credit-suisse.com | P91: +41 44 332 58 08 | Q91: Switzerland | R91: CHF | T91: 1 | W91: 468.79 | X91: 59.4 | Z91: 216 | AC91: 744.19 | AJ91: 0 | AQ91: 0 | AR91: 189.3 | AX91: 189.3 | BE91: 0 | BL91: 0 | BM91: 658.09 | BN91: 59.4 | BO91: 0 | BP91: 216 | BQ91: 0 | BR91: 0 | BS91: 933.49 | BT91: TRUE | BU91: FALSE | BV91: FALSE | BW91: TRUE | BX91: FALSE | BY91: FALSE | BZ91: 5 | CA91: 1 | CC91: 1 | CF91: 7 | CM91: 0 | CT91: 0 | CU91: 1 | DA91: 1 | DH91: 0 | DO91: 0 | DP91: 6 | DQ91: 1 | DR91: 0 | DS91: 1 | DT91: 0 | DU91: 0 | DV91: 8 | DW91: YES | DX91: YES | DY91: NO | DZ91: YES | EA91: NO | EB91: NO | EC91: NO | ED91: NO | EE91: NO | EF91: NO | EG91: NO | EH91: NO | EI91: NO | EJ91: NO | EK91: NO | EL91: NO | EM91: NO | EN91: NO | EO91: YES | EP91: NO | EQ91: NO | ER91: NO | ES91: NO | ET91: NO | EU91: NO | EV91: NO | EW91: NO | EX91: NO | EY91: NO | EZ91: NO | FA91: NO | FB91: NO | FC91: NO | FD91: NO | FE91: NO | FF91: NO | FG91: 510.02 | FH91: 59.4 | FM91: 569.42 | FN91: 69.54 | FT91: 69.54 | GA91: 0 | GH91: 0 | GO91: 0 | GV91: 0 | GW91: 78.53 | GZ91: 216 | HC91: 294.53 | HK91: 0 | HL91: 658.09 | HM91: 59.4 | HN91: 0 | HO91: 216 | HP91: 0 | HQ91: 0 | HR91: 933.49 | HS91: 623.1 | HT91: 59.4 | HY91: 682.5 | IC91: 216 | IF91: 216 | IM91: 0 | IN91: 34.99 | IT91: 34.99 | JA91: 0 | JB91: 658.09 | JC91: 59.4 | JD91: 0 | JE91: 216 | JF91: 0 | JG91: 0 | JH91: 933.49 | JI91: 0 | JJ91: 5 | JK91: 95 | JN91: 390.26 | JO91: 59.4 | JT91: 449.66 | KA91: 0 | KH91: 0 | KO91: 0 | KV91: 0 | LC91: 0 | LD91: 78.53 | LG91: 216 | LJ91: 294.53 | LR91: 0 | LS91: 468.79 | LT91: 59.4 | LU91: 0 | LV91: 216 | LW91: 0 | LX91: 0 | LY91: 744.19 | OK91: 0 | QW91: 0 | QX91: 119.76 | RD91: 119.76 | RE91: 69.54 | RK91: 69.54 | TC91: 189.3 | TI91: 189.3 | VU91: 0 | YG91: 0 | YH91: 1 | YI91: 2 | YJ91: 1 | YK91: Mozilla/5.0 (Windows NT 6.1; WOW64; Trident/7.0; rv:11.0) like Gecko | YL91: 99 | YM91: NVPXD253 | YN91: INREV | YO91: Credit Suisse | YP91: Ulrich Braun | YQ91: ulrich.braun@credit-suisse.com | YS91: http://click.surveylab.co.uk/anrev-inrev-ncreif-capital-raising-2016/?survey=NVPXD253
