Workbook
Name RMITeam: [1]ContactDetails!$B$9:$B$13

Sheet DataCompleted
A1: RecordNo | B1: Version | C1: DateCompleted | D1: qName | E1: qCompany | F1: mnumber | G1: qJobtitle | H1: qEmail | I1: qTelephone | J1: qCountry | K1: qCurrency | L1: qCurrencyOther | M1: q1 | N1: q2 | O1: q2other | P1: q31_1 | Q1: q31_2 | R1: q31_3 | S1: q31_4 | T1: q31_5 | U1: q31_6 | V1: q3ROW1_hidden | W1: q32_1 | X1: q32_2 | Y1: q32_3 | Z1: q32_4 | AA1: q32_5 | AB1: q32_6 | AC1: q3ROW2_hidden | AD1: q33_1 | AE1: q33_2 | AF1: q33_3 | AG1: q33_4 | AH1: q33_5 | AI1: q33_6 | AJ1: q3ROW3_hidden | AK1: q34_1 | AL1: q34_2 | AM1: q34_3 | AN1: q34_4 | AO1: q34_5 | AP1: q34_6 | AQ1: q3ROW4_hidden | AR1: q35_1 | AS1: q35_2 | AT1: q35_3 | AU1: q35_4 | AV1: q35_5 | AW1: q35_6 | AX1: q3ROW5_hidden | AY1: q36_1 | AZ1: q36_2 | BA1: q36_3 | BB1: q36_4 | BC1: q36_5 | BD1: q36_6 | BE1: q3ROW6_hidden | BF1: q3COL1_hidden | BG1: q3COL2_hidden | BH1: q3COL3_hidden | BI1: q3COL4_hidden | BJ1: q3COL5_hidden | BK1: q3COL6_hidden | BL1: q3GRANDTotal_hidden | BM1: q41_1 | BN1: q41_2 | BO1: q41_3 | BP1: q41_4 | BQ1: q41_5 | BR1: q41_6 | BS1: q4ROW1_hidden | BT1: q42_1 | BU1: q42_2 | BV1: q42_3 | BW1: q42_4 | BX1: q42_5 | BY1: q42_6 | BZ1: q4ROW2_hidden | CA1: q43_1 | CB1: q43_2 | CC1: q43_3 | CD1: q43_4 | CE1: q43_5 | CF1: q43_6 | CG1: q4ROW3_hidden | CH1: q44_1 | CI1: q44_2 | CJ1: q44_3 | CK1: q44_4 | CL1: q44_5 | CM1: q44_6 | CN1: q4ROW4_hidden | CO1: q45_1 | CP1: q45_2 | CQ1: q45_3 | CR1: q45_4 | CS1: q45_5 | CT1: q45_6 | CU1: q4ROW5_hidden | CV1: q46_1 | CW1: q46_2 | CX1: q46_3 | CY1: q46_4 | CZ1: q46_5 | DA1: q46_6 | DB1: q4ROW6_hidden | DC1: q4COL1_hidden | DD1: q4COL2_hidden | DE1: q4COL3_hidden | DF1: q4COL4_hidden | DG1: q4COL5_hidden | DH1: q4COL6_hidden | DI1: q4GRANDTotal_hidden | DJ1: Alert41_1 | DK1: Alert41_2 | DL1: Alert41_3 | DM1: Alert41_4 | DN1: Alert41_5 | DO1: Alert41_6 | DP1: Alert42_1 | DQ1: Alert42_2 | DR1: Alert42_3 | DS1: Alert42_4 | DT1: Alert42_5 | DU1: Alert42_6 | DV1: Alert43_1 | DW1: Alert43_2 | DX1: Alert43_3 | DY1: Alert43_4 | DZ1: Alert43_5 | EA1: Alert43_6 | EB1: Alert44_1 | EC1: Alert44_2 | ED1: Alert44_3 | EE1: Alert44_4 | EF1: Alert44_5 | EG1: Alert44_6 | EH1: Alert45_1 | EI1: Alert45_2 | EJ1: Alert45_3 | EK1: Alert45_4 | EL1: Alert45_5 | EM1: Alert45_6 | EN1: Alert46_1 | EO1: Alert46_2 | EP1: Alert46_3 | EQ1: Alert46_4 | ER1: Alert46_5 | ES1: Alert46_6 | ET1: q51_1 | EU1: q51_2 | EV1: q51_3 | EW1: q51_4 | EX1: q51_5 | EY1: q51_6 | EZ1: q5ROW1_hidden | FA1: q52_1 | FB1: q52_2 | FC1: q52_3 | FD1: q52_4 | FE1: q52_5 | FF1: q52_6 | FG1: q5ROW2_hidden | FH1: q53_1 | FI1: q53_2 | FJ1: q53_3 | FK1: q53_4 | FL1: q53_5 | FM1: q53_6 | FN1: q5ROW3_hidden | FO1: q54_1 | FP1: q54_2 | FQ1: q54_3 | FR1: q54_4 | FS1: q54_5 | FT1: q54_6 | FU1: q5ROW4_hidden | FV1: q55_1 | FW1: q55_2 | FX1: q55_3 | FY1: q55_4 | FZ1: q55_5 | GA1: q55_6 | GB1: q5ROW5_hidden | GC1: q56_1 | GD1: q56_2 | GE1: q56_3 | GF1: q56_4 | GG1: q56_5 | GH1: q56_6 | GI1: q5ROW6_hidden | GJ1: q57_1 | GK1: q57_2 | GL1: q57_3 | GM1: q57_4 | GN1: q57_5 | GO1: q57_6 | GP1: q5ROW7_hidden | GQ1: q5other | GR1: q58_1 | GS1: q58_2 | GT1: q58_3 | GU1: q58_4 | GV1: q58_5 | GW1: q58_6 | GX1: q5ROW8_hidden | GY1: q5COL1_hidden | GZ1: q5COL2_hidden | HA1: q5COL3_hidden | HB1: q5COL4_hidden | HC1: q5COL5_hidden | HD1: q5COL6_hidden | HE1: q5GRANDTotal_hidden | HF1: q61_1 | HG1: q61_2 | HH1: q61_3 | HI1: q61_4 | HJ1: q61_5 | HK1: q61_6 | HL1: q6ROW1_hidden | HM1: q62_1 | HN1: q62_2 | HO1: q62_3 | HP1: q62_4 | HQ1: q62_5 | HR1: q62_6 | HS1: q6ROW2_hidden | HT1: q63_1 | HU1: q63_2 | HV1: q63_3 | HW1: q63_4 | HX1: q63_5 | HY1: q63_6 | HZ1: q6ROW3_hidden | IA1: q64_1 | IB1: q64_2 | IC1: q64_3 | ID1: q64_4 | IE1: q64_5 | IF1: q64_6 | IG1: q6ROW4_hidden | IH1: q65_1 | II1: q65_2 | IJ1: q65_3 | IK1: q65_4 | IL1: q65_5 | IM1: q65_6 | IN1: q6ROW5_hidden | IO1: q6COL1_hidden | IP1: q6COL2_hidden | IQ1: q6COL3_hidden | IR1: q6COL4_hidden | IS1: q6COL5_hidden | IT1: q6COL6_hidden | IU1: q6GRANDTotal_hidden | IV1: q7_1 | IW1: q7_2 | IX1: q7_3 | IY1: q7other | IZ1: q7_4 | JA1: q8 | JB1: q9 | JC1: q91 | JD1: ASIA PACIFIC_apac | JE1: q101_1_apac | JF1: q101_2_apac | JG1: q101_3_apac | JH1: q101_4_apac | JI1: q101_5_apac | JJ1: q101_6_apac | JK1: q10ROW1_hidden_apac | JL1: q102_1_apac | JM1: q102_2_apac | JN1: q102_3_apac | JO1: q102_4_apac | JP1: q102_5_apac | JQ1: q102_6_apac | JR1: q10ROW2_hidden_apac | JS1: q103_1_apac | JT1: q103_2_apac | JU1: q103_3_apac | JV1: q103_4_apac | JW1: q103_5_apac | JX1: q103_6_apac | JY1: q10ROW3_hidden_apac | JZ1: q104_1_apac | KA1: q104_2_apac | KB1: q104_3_apac | KC1: q104_4_apac | KD1: q104_5_apac | KE1: q104_6_apac | KF1: q10ROW4_hidden_apac | KG1: q105_1_apac | KH1: q105_2_apac | KI1: q105_3_apac | KJ1: q105_4_apac | KK1: q105_5_apac | KL1: q105_6_apac | KM1: q10ROW5_hidden_apac | KN1: q106_1_apac | KO1: q106_2_apac | KP1: q106_3_apac | KQ1: q106_4_apac | KR1: q106_5_apac | KS1: q106_6_apac | KT1: q10ROW6_hidden_apac | KU1: q107_1_apac | KV1: q107_2_apac | KW1: q107_3_apac | KX1: q107_4_apac | KY1: q107_5_apac | KZ1: q107_6_apac | LA1: q10ROW7_hidden_apac | LB1: q10other_apac | LC1: q108_1_apac | LD1: q108_2_apac | LE1: q108_3_apac | LF1: q108_4_apac | LG1: q108_5_apac | LH1: q108_6_apac | LI1: q10ROW8_hidden_apac | LJ1: q10COL1_hidden_apac | LK1: q10COL2_hidden_apac | LL1: q10COL3_hidden_apac | LM1: q10COL4_hidden_apac | LN1: q10COL5_hidden_apac | LO1: q10COL6_hidden_apac | LP1: q10GRANDTotal_hidden_apac | LQ1: q111_1_apac | LR1: q111_2_apac | LS1: q111_3_apac | LT1: q111_4_apac | LU1: q111_5_apac | LV1: q111_6_apac | LW1: q11ROW1_hidden_apac | LX1: q112_1_apac | LY1: q112_2_apac | LZ1: q112_3_apac | MA1: q112_4_apac | MB1: q112_5_apac | MC1: q112_6_apac | MD1: q11ROW2_hidden_apac | ME1: q113_1_apac | MF1: q113_2_apac | MG1: q113_3_apac | MH1: q113_4_apac | MI1: q113_5_apac | MJ1: q113_6_apac | MK1: q11ROW3_hidden_apac | ML1: q114_1_apac | MM1: q114_2_apac | MN1: q114_3_apac | MO1: q114_4_apac | MP1: q114_5_apac | MQ1: q114_6_apac | MR1: q11ROW4_hidden_apac | MS1: q115_1_apac | MT1: q115_2_apac | MU1: q115_3_apac | MV1: q115_4_apac | MW1: q115_5_apac | MX1: q115_6_apac | MY1: q11ROW5_hidden_apac | MZ1: q11COL1_hidden_apac | NA1: q11COL2_hidden_apac | NB1: q11COL3_hidden_apac | NC1: q11COL4_hidden_apac | ND1: q11COL5_hidden_apac | NE1: q11COL6_hidden_apac | NF1: q11GRANDTotal_hidden_apac | NG1: EUROPE_europe | NH1: q101_1_europe | NI1: q101_2_europe | NJ1: q101_3_europe | NK1: q101_4_europe | NL1: q101_5_europe | NM1: q101_6_europe | NN1: q10ROW1_hidden_europe | NO1: q102_1_europe | NP1: q102_2_europe | NQ1: q102_3_europe | NR1: q102_4_europe | NS1: q102_5_europe | NT1: q102_6_europe | NU1: q10ROW2_hidden_europe | NV1: q103_1_europe | NW1: q103_2_europe | NX1: q103_3_europe | NY1: q103_4_europe | NZ1: q103_5_europe | OA1: q103_6_europe | OB1: q10ROW3_hidden_europe | OC1: q104_1_europe | OD1: q104_2_europe | OE1: q104_3_europe | OF1: q104_4_europe | OG1: q104_5_europe | OH1: q104_6_europe | OI1: q10ROW4_hidden_europe | OJ1: q105_1_europe | OK1: q105_2_europe | OL1: q105_3_europe | OM1: q105_4_europe | ON1: q105_5_europe | OO1: q105_6_europe | OP1: q10ROW5_hidden_europe | OQ1: q106_1_europe | OR1: q106_2_europe | OS1: q106_3_europe | OT1: q106_4_europe | OU1: q106_5_europe | OV1: q106_6_europe | OW1: q10ROW6_hidden_europe | OX1: q107_1_europe | OY1: q107_2_europe | OZ1: q107_3_europe | PA1: q107_4_europe | PB1: q107_5_europe | PC1: q107_6_europe | PD1: q10ROW7_hidden_europe | PE1: q10other_europe | PF1: q108_1_europe | PG1: q108_2_europe | PH1: q108_3_europe | PI1: q108_4_europe | PJ1: q108_5_europe | PK1: q108_6_europe | PL1: q10ROW8_hidden_europe | PM1: q10COL1_hidden_europe | PN1: q10COL2_hidden_europe | PO1: q10COL3_hidden_europe | PP1: q10COL4_hidden_europe | PQ1: q10COL5_hidden_europe | PR1: q10COL6_hidden_europe | PS1: q10GRANDTotal_hidden_europe | PT1: q111_1_europe | PU1: q111_2_europe | PV1: q111_3_europe | PW1: q111_4_europe | PX1: q111_5_europe | PY1: q111_6_europe | PZ1: q11ROW1_hidden_europe | QA1: q112_1_europe | QB1: q112_2_europe | QC1: q112_3_europe | QD1: q112_4_europe | QE1: q112_5_europe | QF1: q112_6_europe | QG1: q11ROW2_hidden_europe | QH1: q113_1_europe | QI1: q113_2_europe | QJ1: q113_3_europe | QK1: q113_4_europe | QL1: q113_5_europe | QM1: q113_6_europe | QN1: q11ROW3_hidden_europe | QO1: q114_1_europe | QP1: q114_2_europe | QQ1: q114_3_europe | QR1: q114_4_europe | QS1: q114_5_europe | QT1: q114_6_europe | QU1: q11ROW4_hidden_europe | QV1: q115_1_europe | QW1: q115_2_europe | QX1: q115_3_europe | QY1: q115_4_europe | QZ1: q115_5_europe | RA1: q115_6_europe | RB1: q11ROW5_hidden_europe | RC1: q11COL1_hidden_europe | RD1: q11COL2_hidden_europe | RE1: q11COL3_hidden_europe | RF1: q11COL4_hidden_europe | RG1: q11COL5_hidden_europe | RH1: q11COL6_hidden_europe | RI1: q11GRANDTotal_hidden_europe | RJ1: NORTH AMERICA_northamerica | RK1: q101_1_northamerica | RL1: q101_2_northamerica | RM1: q101_3_northamerica | RN1: q101_4_northamerica | RO1: q101_5_northamerica | RP1: q101_6_northamerica | RQ1: q10ROW1_hidden_northamerica | RR1: q102_1_northamerica | RS1: q102_2_northamerica | RT1: q102_3_northamerica | RU1: q102_4_northamerica | RV1: q102_5_northamerica | RW1: q102_6_northamerica | RX1: q10ROW2_hidden_northamerica | RY1: q103_1_northamerica | RZ1: q103_2_northamerica | SA1: q103_3_northamerica | SB1: q103_4_northamerica | SC1: q103_5_northamerica | SD1: q103_6_northamerica | SE1: q10ROW3_hidden_northamerica | SF1: q104_1_northamerica | SG1: q104_2_northamerica | SH1: q104_3_northamerica | SI1: q104_4_northamerica | SJ1: q104_5_northamerica | SK1: q104_6_northamerica | SL1: q10ROW4_hidden_northamerica | SM1: q105_1_northamerica | SN1: q105_2_northamerica | SO1: q105_3_northamerica | SP1: q105_4_northamerica | SQ1: q105_5_northamerica | SR1: q105_6_northamerica | SS1: q10ROW5_hidden_northamerica | ST1: q106_1_northamerica | SU1: q106_2_northamerica | SV1: q106_3_northamerica | SW1: q106_4_northamerica | SX1: q106_5_northamerica | SY1: q106_6_northamerica | SZ1: q10ROW6_hidden_northamerica | TA1: q107_1_northamerica | TB1: q107_2_northamerica | TC1: q107_3_northamerica | TD1: q107_4_northamerica | TE1: q107_5_northamerica | TF1: q107_6_northamerica | TG1: q10ROW7_hidden_northamerica | TH1: q10other_northamerica | TI1: q108_1_northamerica | TJ1: q108_2_northamerica | TK1: q108_3_northamerica | TL1: q108_4_northamerica | TM1: q108_5_northamerica | TN1: q108_6_northamerica | TO1: q10ROW8_hidden_northamerica | TP1: q10COL1_hidden_northamerica | TQ1: q10COL2_hidden_northamerica | TR1: q10COL3_hidden_northamerica | TS1: q10COL4_hidden_northamerica | TT1: q10COL5_hidden_northamerica | TU1: q10COL6_hidden_northamerica | TV1: q10GRANDTotal_hidden_northamerica | TW1: q111_1_northamerica | TX1: q111_2_northamerica | TY1: q111_3_northamerica | TZ1: q111_4_northamerica | UA1: q111_5_northamerica | UB1: q111_6_northamerica | UC1: q11ROW1_hidden_northamerica | UD1: q112_1_northamerica | UE1: q112_2_northamerica | UF1: q112_3_northamerica | UG1: q112_4_northamerica | UH1: q112_5_northamerica | UI1: q112_6_northamerica | UJ1: q11ROW2_hidden_northamerica | UK1: q113_1_northamerica | UL1: q113_2_northamerica | UM1: q113_3_northamerica | UN1: q113_4_northamerica | UO1: q113_5_northamerica | UP1: q113_6_northamerica | UQ1: q11ROW3_hidden_northamerica | UR1: q114_1_northamerica | US1: q114_2_northamerica | UT1: q114_3_northamerica | UU1: q114_4_northamerica | UV1: q114_5_northamerica | UW1: q114_6_northamerica | UX1: q11ROW4_hidden_northamerica | UY1: q115_1_northamerica | UZ1: q115_2_northamerica | VA1: q115_3_northamerica | VB1: q115_4_northamerica | VC1: q115_5_northamerica | VD1: q115_6_northamerica | VE1: q11ROW5_hidden_northamerica | VF1: q11COL1_hidden_northamerica | VG1: q11COL2_hidden_northamerica | VH1: q11COL3_hidden_northamerica | VI1: q11COL4_hidden_northamerica | VJ1: q11COL5_hidden_northamerica | VK1: q11COL6_hidden_northamerica | VL1: q11GRANDTotal_hidden_northamerica | VM1: Global_global | VN1: q101_1_global | VO1: q101_2_global | VP1: q101_3_global | VQ1: q101_4_global | VR1: q101_5_global | VS1: q101_6_global | VT1: q10ROW1_hidden_global | VU1: q102_1_global | VV1: q102_2_global | VW1: q102_3_global | VX1: q102_4_global | VY1: q102_5_global | VZ1: q102_6_global | WA1: q10ROW2_hidden_global | WB1: q103_1_global | WC1: q103_2_global | WD1: q103_3_global | WE1: q103_4_global | WF1: q103_5_global | WG1: q103_6_global | WH1: q10ROW3_hidden_global | WI1: q104_1_global | WJ1: q104_2_global | WK1: q104_3_global | WL1: q104_4_global | WM1: q104_5_global | WN1: q104_6_global | WO1: q10ROW4_hidden_global | WP1: q105_1_global | WQ1: q105_2_global | WR1: q105_3_global | WS1: q105_4_global | WT1: q105_5_global | WU1: q105_6_global | WV1: q10ROW5_hidden_global | WW1: q106_1_global | WX1: q106_2_global | WY1: q106_3_global | WZ1: q106_4_global | XA1: q106_5_global | XB1: q106_6_global | XC1: q10ROW6_hidden_global | XD1: q107_1_global | XE1: q107_2_global | XF1: q107_3_global | XG1: q107_4_global | XH1: q107_5_global | XI1: q107_6_global | XJ1: q10ROW7_hidden_global | XK1: q10other_global | XL1: q108_1_global | XM1: q108_2_global | XN1: q108_3_global | XO1: q108_4_global | XP1: q108_5_global | XQ1: q108_6_global | XR1: q10ROW8_hidden_global | XS1: q10COL1_hidden_global | XT1: q10COL2_hidden_global | XU1: q10COL3_hidden_global | XV1: q10COL4_hidden_global | XW1: q10COL5_hidden_global | XX1: q10COL6_hidden_global | XY1: q10GRANDTotal_hidden_global | XZ1: q111_1_global | YA1: q111_2_global | YB1: q111_3_global | YC1: q111_4_global | YD1: q111_5_global | YE1: q111_6_global | YF1: q11ROW1_hidden_global | YG1: q112_1_global | YH1: q112_2_global | YI1: q112_3_global | YJ1: q112_4_global | YK1: q112_5_global | YL1: q112_6_global | YM1: q11ROW2_hidden_global | YN1: q113_1_global | YO1: q113_2_global | YP1: q113_3_global | YQ1: q113_4_global | YR1: q113_5_global | YS1: q113_6_global | YT1: q11ROW3_hidden_global | YU1: q114_1_global | YV1: q114_2_global | YW1: q114_3_global | YX1: q114_4_global | YY1: q114_5_global | YZ1: q114_6_global | ZA1: q11ROW4_hidden_global | ZB1: q115_1_global | ZC1: q115_2_global | ZD1: q115_3_global | ZE1: q115_4_global | ZF1: q115_5_global | ZG1: q115_6_global | ZH1: q11ROW5_hidden_global | ZI1: q11COL1_hidden_global | ZJ1: q11COL2_hidden_global | ZK1: q11COL3_hidden_global | ZL1: q11COL4_hidden_global | ZM1: q11COL5_hidden_global | ZN1: q11COL6_hidden_global | ZO1: q11GRANDTotal_hidden_global | ZP1: SOUTH AMERICA_southamerica | ZQ1: q101_1_southamerica | ZR1: q101_2_southamerica | ZS1: q101_3_southamerica | ZT1: q101_4_southamerica | ZU1: q101_5_southamerica | ZV1: q101_6_southamerica | ZW1: q10ROW1_hidden_southamerica | ZX1: q102_1_southamerica | ZY1: q102_2_southamerica | ZZ1: q102_3_southamerica | AAA1: q102_4_southamerica | AAB1: q102_5_southamerica | AAC1: q102_6_southamerica | AAD1: q10ROW2_hidden_southamerica | AAE1: q103_1_southamerica | AAF1: q103_2_southamerica | AAG1: q103_3_southamerica | AAH1: q103_4_southamerica | AAI1: q103_5_southamerica | AAJ1: q103_6_southamerica | AAK1: q10ROW3_hidden_southamerica | AAL1: q104_1_southamerica | AAM1: q104_2_southamerica | AAN1: q104_3_southamerica | AAO1: q104_4_southamerica | AAP1: q104_5_southamerica | AAQ1: q104_6_southamerica | AAR1: q10ROW4_hidden_southamerica | AAS1: q105_1_southamerica | AAT1: q105_2_southamerica | AAU1: q105_3_southamerica | AAV1: q105_4_southamerica | AAW1: q105_5_southamerica | AAX1: q105_6_southamerica | AAY1: q10ROW5_hidden_southamerica | AAZ1: q106_1_southamerica | ABA1: q106_2_southamerica | ABB1: q106_3_southamerica | ABC1: q106_4_southamerica | ABD1: q106_5_southamerica | ABE1: q106_6_southamerica | ABF1: q10ROW6_hidden_southamerica | ABG1: q107_1_southamerica | ABH1: q107_2_southamerica | ABI1: q107_3_southamerica | ABJ1: q107_4_southamerica | ABK1: q107_5_southamerica | ABL1: q107_6_southamerica | ABM1: q10ROW7_hidden_southamerica | ABN1: q10other_southamerica | ABO1: q108_1_southamerica | ABP1: q108_2_southamerica | ABQ1: q108_3_southamerica | ABR1: q108_4_southamerica | ABS1: q108_5_southamerica | ABT1: q108_6_southamerica | ABU1: q10ROW8_hidden_southamerica | ABV1: q10COL1_hidden_southamerica | ABW1: q10COL2_hidden_southamerica | ABX1: q10COL3_hidden_southamerica | ABY1: q10COL4_hidden_southamerica | ABZ1: q10COL5_hidden_southamerica | ACA1: q10COL6_hidden_southamerica | ACB1: q10GRANDTotal_hidden_southamerica | ACC1: q111_1_southamerica | ACD1: q111_2_southamerica | ACE1: q111_3_southamerica | ACF1: q111_4_southamerica | ACG1: q111_5_southamerica | ACH1: q111_6_southamerica | ACI1: q11ROW1_hidden_southamerica | ACJ1: q112_1_southamerica | ACK1: q112_2_southamerica | ACL1: q112_3_southamerica | ACM1: q112_4_southamerica | ACN1: q112_5_southamerica | ACO1: q112_6_southamerica | ACP1: q11ROW2_hidden_southamerica | ACQ1: q113_1_southamerica | ACR1: q113_2_southamerica | ACS1: q113_3_southamerica | ACT1: q113_4_southamerica | ACU1: q113_5_southamerica | ACV1: q113_6_southamerica | ACW1: q11ROW3_hidden_southamerica | ACX1: q114_1_southamerica | ACY1: q114_2_southamerica | ACZ1: q114_3_southamerica | ADA1: q114_4_southamerica | ADB1: q114_5_southamerica | ADC1: q114_6_southamerica | ADD1: q11ROW4_hidden_southamerica | ADE1: q115_1_southamerica | ADF1: q115_2_southamerica | ADG1: q115_3_southamerica | ADH1: q115_4_southamerica | ADI1: q115_5_southamerica | ADJ1: q115_6_southamerica | ADK1: q11ROW5_hidden_southamerica | ADL1: q11COL1_hidden_southamerica | ADM1: q11COL2_hidden_southamerica | ADN1: q11COL3_hidden_southamerica | ADO1: q11COL4_hidden_southamerica | ADP1: q11COL5_hidden_southamerica | ADQ1: q11COL6_hidden_southamerica | ADR1: q11GRANDTotal_hidden_southamerica | ADS1: AFRICA_africa | ADT1: q101_1_africa | ADU1: q101_2_africa | ADV1: q101_3_africa | ADW1: q101_4_africa | ADX1: q101_5_africa | ADY1: q101_6_africa | ADZ1: q10ROW1_hidden_africa | AEA1: q102_1_africa | AEB1: q102_2_africa | AEC1: q102_3_africa | AED1: q102_4_africa | AEE1: q102_5_africa | AEF1: q102_6_africa | AEG1: q10ROW2_hidden_africa | AEH1: q103_1_africa | AEI1: q103_2_africa | AEJ1: q103_3_africa | AEK1: q103_4_africa | AEL1: q103_5_africa | AEM1: q103_6_africa | AEN1: q10ROW3_hidden_africa | AEO1: q104_1_africa | AEP1: q104_2_africa | AEQ1: q104_3_africa | AER1: q104_4_africa | AES1: q104_5_africa | AET1: q104_6_africa | AEU1: q10ROW4_hidden_africa | AEV1: q105_1_africa | AEW1: q105_2_africa | AEX1: q105_3_africa | AEY1: q105_4_africa | AEZ1: q105_5_africa | AFA1: q105_6_africa | AFB1: q10ROW5_hidden_africa | AFC1: q106_1_africa | AFD1: q106_2_africa | AFE1: q106_3_africa | AFF1: q106_4_africa | AFG1: q106_5_africa | AFH1: q106_6_africa | AFI1: q10ROW6_hidden_africa | AFJ1: q107_1_africa | AFK1: q107_2_africa | AFL1: q107_3_africa | AFM1: q107_4_africa | AFN1: q107_5_africa | AFO1: q107_6_africa | AFP1: q10ROW7_hidden_africa | AFQ1: q10other_africa | AFR1: q108_1_africa | AFS1: q108_2_africa | AFT1: q108_3_africa | AFU1: q108_4_africa | AFV1: q108_5_africa | AFW1: q108_6_africa | AFX1: q10ROW8_hidden_africa | AFY1: q10COL1_hidden_africa | AFZ1: q10COL2_hidden_africa | AGA1: q10COL3_hidden_africa | AGB1: q10COL4_hidden_africa | AGC1: q10COL5_hidden_africa | AGD1: q10COL6_hidden_africa | AGE1: q10GRANDTotal_hidden_africa | AGF1: q111_1_africa | AGG1: q111_2_africa | AGH1: q111_3_africa | AGI1: q111_4_africa | AGJ1: q111_5_africa | AGK1: q111_6_africa | AGL1: q11ROW1_hidden_africa | AGM1: q112_1_africa | AGN1: q112_2_africa | AGO1: q112_3_africa | AGP1: q112_4_africa | AGQ1: q112_5_africa | AGR1: q112_6_africa | AGS1: q11ROW2_hidden_africa | AGT1: q113_1_africa | AGU1: q113_2_africa | AGV1: q113_3_africa | AGW1: q113_4_africa | AGX1: q113_5_africa | AGY1: q113_6_africa | AGZ1: q11ROW3_hidden_africa | AHA1: q114_1_africa | AHB1: q114_2_africa | AHC1: q114_3_africa | AHD1: q114_4_africa | AHE1: q114_5_africa | AHF1: q114_6_africa | AHG1: q11ROW4_hidden_africa | AHH1: q115_1_africa | AHI1: q115_2_africa | AHJ1: q115_3_africa | AHK1: q115_4_africa | AHL1: q115_5_africa | AHM1: q115_6_africa | AHN1: q11ROW5_hidden_africa | AHO1: q11COL1_hidden_africa | AHP1: q11COL2_hidden_africa | AHQ1: q11COL3_hidden_africa | AHR1: q11COL4_hidden_africa | AHS1: q11COL5_hidden_africa | AHT1: q11COL6_hidden_africa | AHU1: q11GRANDTotal_hidden_africa
A2: 121 | B2: ANREV | C2: 42761.069 | D2: Viola Chee | E2: SilkRoad Property Partners | F2: =VLOOKUP(MID(H2,SEARCH("@",H2,1),LEN(H2)-SEARCH("@",H2,1)+1),[2]Sheet1!$D:$F,3,FALSE) -> M0182 | G2: VP Financial Controller | H2: viola.chee@silkroadpp.com | I2: 6569225560 | J2: Singapore | K2: USD | M2: 1 | P2: 109 | V2: 109 | AC2: 0 | AJ2: 0 | AQ2: 0 | AX2: 0 | BE2: 0 | BF2: 109 | BG2: 0 | BH2: 0 | BI2: 0 | BJ2: 0 | BK2: 0 | BL2: 109 | BM2: 2 | BS2: 2 | BZ2: 0 | CG2: 0 | CN2: 0 | CU2: 0 | DB2: 0 | DC2: 2 | DD2: 0 | DE2: 0 | DF2: 0 | DG2: 0 | DH2: 0 | DI2: 2 | DJ2: YES | DK2: NO | DL2: NO | DM2: NO | DN2: NO | DO2: NO | DP2: NO | DQ2: NO | DR2: NO | DS2: NO | DT2: NO | DU2: NO | DV2: NO | DW2: NO | DX2: NO | DY2: NO | DZ2: NO | EA2: NO | EB2: NO | EC2: NO | ED2: NO | EE2: NO | EF2: NO | EG2: NO | EH2: NO | EI2: NO | EJ2: NO | EK2: NO | EL2: NO | EM2: NO | EN2: NO | EO2: NO | EP2: NO | EQ2: NO | ER2: NO | ES2: NO | ET2: 45 | EZ2: 45 | FA2: 47 | FG2: 47 | FN2: 0 | FU2: 0 | GB2: 0 | GI2: 0 | GJ2: 2 | GP2: 2 | GQ2: University | GR2: 15 | GX2: 15 | GY2: 109 | GZ2: 0 | HA2: 0 | HB2: 0 | HC2: 0 | HD2: 0 | HE2: 109 | HF2: 2 | HL2: 2 | HM2: 67 | HS2: 67 | HT2: 40 | HZ2: 40 | IG2: 0 | IN2: 0 | IO2: 109 | IP2: 0 | IQ2: 0 | IR2: 0 | IS2: 0 | IT2: 0 | IU2: 109 | IV2: 100 | JA2: 3 | JB2: 3 | JC2: 2 | JD2: START Asia Pacific: | JE2: 45 | JK2: 45 | JL2: 47 | JR2: 47 | JY2: 0 | KF2: 0 | KM2: 0 | KT2: 0 | KU2: 2 | LA2: 2 | LC2: 15 | LI2: 15 | LJ2: 109 | LK2: 0 | LL2: 0 | LM2: 0 | LN2: 0 | LO2: 0 | LP2: 109 | LQ2: 67 | LW2: 67 | LX2: 2 | MD2: 2 | ME2: 40 | MK2: 40 | MR2: 0 | MY2: 0 | MZ2: 109 | NA2: 0 | NB2: 0 | NC2: 0 | ND2: 0 | NE2: 0 | NF2: 109 | NG2: START Europe: | RJ2: START North America: | VM2: START Global: | ZP2: START SOUTH America: | ADS2: START Africa:
A3: 78 | B3: ANREV | C3: 42780 | D3: Sarah Berg | E3: Heitman | F3: =VLOOKUP(MID(H3,SEARCH("@",H3,1),LEN(H3)-SEARCH("@",H3,1)+1),[2]Sheet1!$D:$F,3,FALSE) -> M107 | G3: Vice President | H3: consultant.services@heitman.com | I3: 312-425-0432 | J3: United States | K3: USD | M3: 1 | V3: 0 | W3: 152 | AC3: 152 | AD3: 911 | AE3: 742 | AI3: 355 | AJ3: 2008 | AQ3: 0 | AX3: 0 | BE3: 0 | BF3: 1063 | BG3: 742 | BH3: 0 | BI3: 0 | BJ3: 0 | BK3: 355 | BL3: 2160 | BS3: 0 | BT3: 1 | BZ3: 1 | CA3: 1 | CB3: 3 | CF3: 2 | CG3: 6 | CN3: 0 | CU3: 0 | DB3: 0 | DC3: 2 | DD3: 3 | DE3: 0 | DF3: 0 | DG3: 0 | DH3: 2 | DI3: 7 | DJ3: NO | DK3: NO | DL3: NO | DM3: NO | DN3: NO | DO3: NO | DP3: YES | DQ3: NO | DR3: NO | DS3: NO | DT3: NO | DU3: NO | DV3: YES | DW3: YES | DX3: NO | DY3: NO | DZ3: NO | EA3: YES | EB3: NO | EC3: NO | ED3: NO | EE3: NO | EF3: NO | EG3: NO | EH3: NO | EI3: NO | EJ3: NO | EK3: NO | EL3: NO | EM3: NO | EN3: NO | EO3: NO | EP3: NO | EQ3: NO | ER3: NO | ES3: NO | ET3: 99 | EZ3: 99 | FA3: 64 | FG3: 64 | FH3: 409 | FN3: 409 | FO3: 294 | FP3: 742 | FT3: 355 | FU3: 1391 | FV3: 10 | GB3: 10 | GC3: 134 | GI3: 134 | GP3: 0 | GQ3: Taft-Hartley | GR3: 53 | GX3: 53 | GY3: 1063 | GZ3: 742 | HA3: 0 | HB3: 0 | HC3: 0 | HD3: 355 | HE3: 2160 | HF3: 400 | HL3: 400 | HM3: 186 | HS3: 186 | HT3: 477 | HU3: 742 | HY3: 355 | HZ3: 1574 | IG3: 0 | IN3: 0 | IO3: 1063 | IP3: 742 | IQ3: 0 | IR3: 0 | IS3: 0 | IT3: 355 | IU3: 2160 | IW3: 5 | IX3: 50 | IY3: new clients from prospecting | IZ3: 45 | JA3: 3 | JB3: 1 | JC3: 1 | JD3: START Asia Pacific: | NG3: START Europe: | RJ3: START North America: | VM3: START Global: | ZP3: START SOUTH America: | ADS3: START Africa:
A4: 161 | B4: ANREV | C4: 42769.068 | D4: Nick Thorn | E4: BPEA Real Estate | F4: =VLOOKUP(MID(H4,SEARCH("@",H4,1),LEN(H4)-SEARCH("@",H4,1)+1),[2]Sheet1!$D:$F,3,FALSE) -> M0149 | G4: Vice President - Investor Relations | H4: nickthorn@bpeasia.com | I4: 85228439312 | J4: Hong Kong | K4: USD | M4: 2 | N4: 6 | O4: Not a fundraising year. Last fund closed in 2015. | V4: 0 | AC4: 0 | AJ4: 0 | AQ4: 0 | AX4: 0 | BE4: 0 | BF4: 0 | BG4: 0 | BH4: 0 | BI4: 0 | BJ4: 0 | BK4: 0 | BL4: 0 | BS4: 0 | BZ4: 0 | CG4: 0 | CN4: 0 | CU4: 0 | DB4: 0 | DC4: 0 | DD4: 0 | DE4: 0 | DF4: 0 | DG4: 0 | DH4: 0 | DI4: 0 | DJ4: NO | DK4: NO | DL4: NO | DM4: NO | DN4: NO | DO4: NO | DP4: NO | DQ4: NO | DR4: NO | DS4: NO | DT4: NO | DU4: NO | DV4: NO | DW4: NO | DX4: NO | DY4: NO | DZ4: NO | EA4: NO | EB4: NO | EC4: NO | ED4: NO | EE4: NO | EF4: NO | EG4: NO | EH4: NO | EI4: NO | EJ4: NO | EK4: NO | EL4: NO | EM4: NO | EN4: NO | EO4: NO | EP4: NO | EQ4: NO | ER4: NO | ES4: NO | EZ4: 0 | FG4: 0 | FN4: 0 | FU4: 0 | GB4: 0 | GI4: 0 | GP4: 0 | GX4: 0 | GY4: 0 | GZ4: 0 | HA4: 0 | HB4: 0 | HC4: 0 | HD4: 0 | HE4: 0 | HL4: 0 | HS4: 0 | HZ4: 0 | IG4: 0 | IN4: 0 | IO4: 0 | IP4: 0 | IQ4: 0 | IR4: 0 | IS4: 0 | IT4: 0 | IU4: 0 | JA4: 1 | JB4: 2 | JC4: 1 | JD4: START Asia Pacific: | NG4: START Europe: | RJ4: START North America: | VM4: START Global: | ZP4: START SOUTH America: | ADS4: START Africa:
A5: 217 | B5: ANREV | C5: 42780 | D5: Charter Hall Group | E5: Charter Hall Group | F5: =VLOOKUP(MID(H5,SEARCH("@",H5,1),LEN(H5)-SEARCH("@",H5,1)+1),[2]Sheet1!$D:$F,3,FALSE) -> M03232 | G5: Analyst | H5: investor@charterhall.com.au | I5: +61 2 8651 9412 | J5: Australia | K5: AUD | M5: 1 | P5: 1004 | S5: 1017 | V5: 2021 | AC5: 0 | AJ5: 0 | AQ5: 0 | AX5: 0 | BE5: 0 | BF5: 1004 | BG5: 0 | BH5: 0 | BI5: 1017 | BJ5: 0 | BK5: 0 | BL5: 2021 | BM5: 6 | BP5: 7 | BS5: 13 | BZ5: 0 | CG5: 0 | CN5: 0 | CU5: 0 | DB5: 0 | DC5: 6 | DD5: 0 | DE5: 0 | DF5: 7 | DG5: 0 | DH5: 0 | DI5: 13 | DJ5: YES | DK5: NO | DL5: NO | DM5: YES | DN5: NO | DO5: NO | DP5: NO | DQ5: NO | DR5: NO | DS5: NO | DT5: NO | DU5: NO | DV5: NO | DW5: NO | DX5: NO | DY5: NO | DZ5: NO | EA5: NO | EB5: NO | EC5: NO | ED5: NO | EE5: NO | EF5: NO | EG5: NO | EH5: NO | EI5: NO | EJ5: NO | EK5: NO | EL5: NO | EM5: NO | EN5: NO | EO5: NO | EP5: NO | EQ5: NO | ER5: NO | ES5: NO | ET5: 152 | EW5: 596 | EZ5: 748 | FA5: 0 | FD5: 92 | FG5: 92 | FH5: 0 | FK5: 5 | FN5: 5 | FO5: 0 | FU5: 0 | FV5: 0 | GB5: 0 | GC5: 37 | GF5: 76 | GI5: 113 | GJ5: 97 | GM5: 0 | GP5: 97 | GQ5: Companies | GR5: 718 | GU5: 248 | GX5: 966 | GY5: 1004 | GZ5: 0 | HA5: 0 | HB5: 1017 | HC5: 0 | HD5: 0 | HE5: 2021 | HF5: 1002 | HI5: 595 | HL5: 1597 | HM5: 2 | HP5: 274 | HS5: 276 | HT5: 0 | HW5: 148 | HZ5: 148 | IA5: 0 | ID5: 0 | IG5: 0 | IH5: 0 | IK5: 0 | IN5: 0 | IO5: 1004 | IP5: 0 | IQ5: 0 | IR5: 1017 | IS5: 0 | IT5: 0 | IU5: 2021 | IX5: 100 | JA5: 1 | JB5: 1 | JC5: 1 | JD5: START Asia Pacific: | JE5: 152 | JH5: 596 | JK5: 748 | JL5: 0 | JO5: 92 | JR5: 92 | JS5: 0 | JV5: 5 | JY5: 5 | JZ5: 0 | KC5: 0 | KF5: 0 | KG5: 0 | KJ5: 0 | KM5: 0 | KN5: 38 | KQ5: 76 | KT5: 114 | KU5: 97 | KX5: 0 | LA5: 97 | LB5: Companies | LC5: 718 | LF5: 247 | LI5: 965 | LJ5: 1005 | LK5: 0 | LL5: 0 | LM5: 1016 | LN5: 0 | LO5: 0 | LP5: 2021 | LQ5: 2 | LT5: 273 | LW5: 275 | LX5: 1002 | MA5: 596 | MD5: 1598 | ME5: 0 | MH5: 148 | MK5: 148 | ML5: 0 | MO5: 0 | MR5: 0 | MS5: 0 | MV5: 0 | MY5: 0 | MZ5: 1004 | NA5: 0 | NB5: 0 | NC5: 1017 | ND5: 0 | NE5: 0 | NF5: 2021 | NG5: START Europe: | RJ5: START North America: | VM5: START Global: | ZP5: START SOUTH America: | ADS5: START Africa:
A6: 83 | B6: ANREV | C6: 42761.108 | D6: Lee, Joseph (Lee, Gyusung) | E6: IGIS Asset Management | F6: =VLOOKUP(MID(H6,SEARCH("@",H6,1),LEN(H6)-SEARCH("@",H6,1)+1),[2]Sheet1!$D:$F,3,FALSE) -> M0333 | G6: Senior Managing Director | H6: joseph.lee@igisam.com | I6: +82 2 6959 3102 | J6: Korea, Republic Of | K6: KRW | M6: 2
A7: 228 | B7: ANREV | C7: 42780 | D7: Wendy Lai | E7: ESR Singapore Pte. Ltd. | F7: =VLOOKUP(MID(H7,SEARCH("@",H7,1),LEN(H7)-SEARCH("@",H7,1)+1),[2]Sheet1!$D:$F,3,FALSE) -> M0231 | G7: Fund Controller | H7: wlai@redwoodgroup.com | I7: 6568500454 | J7: Hong Kong | K7: USD | M7: 1 | P7: 310.8 | Q7: 470 | S7: 477.3 | V7: 1258.1 | AC7: 0 | AJ7: 0 | AQ7: 0 | AX7: 0 | BE7: 0 | BF7: 310.8 | BG7: 470 | BH7: 0 | BI7: 477.3 | BJ7: 0 | BK7: 0 | BL7: 1258.1 | BM7: 1 | BN7: 2 | BP7: 3 | BS7: 6 | BZ7: 0 | CG7: 0 | CN7: 0 | CU7: 0 | DB7: 0 | DC7: 1 | DD7: 2 | DE7: 0 | DF7: 3 | DG7: 0 | DH7: 0 | DI7: 6 | DJ7: YES | DK7: YES | DL7: NO | DM7: YES | DN7: NO | DO7: NO | DP7: NO | DQ7: NO | DR7: NO | DS7: NO | DT7: NO | DU7: NO | DV7: NO | DW7: NO | DX7: NO | DY7: NO | DZ7: NO | EA7: NO | EB7: NO | EC7: NO | ED7: NO | EE7: NO | EF7: NO | EG7: NO | EH7: NO | EI7: NO | EJ7: NO | EK7: NO | EL7: NO | EM7: NO | EN7: NO | EO7: NO | EP7: NO | EQ7: NO | ER7: NO | ES7: NO | ET7: 200 | EU7: 200 | EZ7: 400 | FB7: 250 | FD7: 236.6 | FG7: 486.6 | FN7: 0 | FU7: 0 | GB7: 0 | GI7: 0 | GP7: 0 | GQ7: Institutional investor | GR7: 110.8 | GS7: 20 | GU7: 240.7 | GX7: 371.5 | GY7: 310.8 | GZ7: 470 | HA7: 0 | HB7: 477.3 | HC7: 0 | HD7: 0 | HE7: 1258.1 | HF7: 300 | HG7: 265 | HI7: 477.3 | HL7: 1042.3 | HM7: 10.8 | HS7: 10.8 | HU7: 205 | HZ7: 205 | IG7: 0 | IN7: 0 | IO7: 310.8 | IP7: 470 | IQ7: 0 | IR7: 477.3 | IS7: 0 | IT7: 0 | IU7: 1258.1 | IV7: 23.8 | IX7: 76.2 | JA7: 1 | JB7: 1 | JC7: 2 | JD7: START Asia Pacific: | JE7: 200 | JF7: 200 | JK7: 400 | JM7: 250 | JO7: 236.6 | JR7: 486.6 | JY7: 0 | KF7: 0 | KM7: 0 | KT7: 0 | LA7: 0 | LB7: Institutional investor | LC7: 110.8 | LD7: 20 | LF7: 240.7 | LI7: 371.5 | LJ7: 310.8 | LK7: 470 | LL7: 0 | LM7: 477.3 | LN7: 0 | LO7: 0 | LP7: 1258.1 | LQ7: 10.8 | LW7: 10.8 | LX7: 300 | LY7: 265 | MA7: 477.3 | MD7: 1042.3 | MF7: 205 | MK7: 205 | MR7: 0 | MY7: 0 | MZ7: 310.8 | NA7: 470 | NB7: 0 | NC7: 477.3 | ND7: 0 | NE7: 0 | NF7: 1258.1 | NG7: START Europe: | RJ7: START North America: | VM7: START Global: | ZP7: START SOUTH America: | ADS7: START Africa:
A8: 122 | B8: ANREV | C8: 42780 | D8: Niklas Schelander | E8: PAG Asia | F8: =VLOOKUP(MID(H8,SEARCH("@",H8,1),LEN(H8)-SEARCH("@",H8,1)+1),[2]Sheet1!$D:$F,3,FALSE) -> M0137 | G8: Managing Director, Group Head | H8: nschelander@pagasia.com | I8: +852 3719 6383 | J8: Hong Kong | K8: USD | M8: 1 | P8: 1150 | V8: 1150 | AC8: 0 | AJ8: 0 | AQ8: 0 | AX8: 0 | BE8: 0 | BF8: 1150 | BG8: 0 | BH8: 0 | BI8: 0 | BJ8: 0 | BK8: 0 | BL8: 1150 | BM8: 1 | BS8: 1 | BZ8: 0 | CG8: 0 | CN8: 0 | CU8: 0 | DB8: 0 | DC8: 1 | DD8: 0 | DE8: 0 | DF8: 0 | DG8: 0 | DH8: 0 | DI8: 1 | DJ8: YES | DK8: NO | DL8: NO | DM8: NO | DN8: NO | DO8: NO | DP8: NO | DQ8: NO | DR8: NO | DS8: NO | DT8: NO | DU8: NO | DV8: NO | DW8: NO | DX8: NO | DY8: NO | DZ8: NO | EA8: NO | EB8: NO | EC8: NO | ED8: NO | EE8: NO | EF8: NO | EG8: NO | EH8: NO | EI8: NO | EJ8: NO | EK8: NO | EL8: NO | EM8: NO | EN8: NO | EO8: NO | EP8: NO | EQ8: NO | ER8: NO | ES8: NO | ET8: 645 | EZ8: 645 | FG8: 0 | FH8: 375 | FN8: 375 | FU8: 0 | FV8: 35 | GB8: 35 | GC8: 55 | GI8: 55 | GP8: 0 | GQ8: Corporates + GP Commitment | GR8: 35 | GX8: 35 | GY8: 1145 | GZ8: 0 | HA8: 0 | HB8: 0 | HC8: 0 | HD8: 0 | HE8: 1145 | HF8: 430 | HL8: 430 | HM8: 35 | HS8: 35 | HT8: 680 | HZ8: 680 | IG8: 0 | IN8: 0 | IO8: 1145 | IP8: 0 | IQ8: 0 | IR8: 0 | IS8: 0 | IT8: 0 | IU8: 1145 | IV8: 33 | IX8: 67 | JA8: 1 | JB8: 3 | JC8: 1 | JD8: START Asia Pacific: | JE8: 645 | JK8: 645 | JR8: 0 | JS8: 375 | JY8: 375 | KF8: 0 | KG8: 35 | KM8: 35 | KN8: 55 | KT8: 55 | LA8: 0 | LC8: 35 | LI8: 35 | LJ8: 1145 | LK8: 0 | LL8: 0 | LM8: 0 | LN8: 0 | LO8: 0 | LP8: 1145 | LQ8: 35 | LW8: 35 | LX8: 430 | MD8: 430 | ME8: 680 | MK8: 680 | MR8: 0 | MY8: 0 | MZ8: 1145 | NA8: 0 | NB8: 0 | NC8: 0 | ND8: 0 | NE8: 0 | NF8: 1145 | NG8: START Europe: | RJ8: START North America: | VM8: START Global: | ZP8: START SOUTH America: | ADS8: START Africa:
A9: 162 | B9: ANREV | C9: 42772.408 | D9: Ingrid Nell | E9: Macquarie | F9: =VLOOKUP(MID(H9,SEARCH("@",H9,1),LEN(H9)-SEARCH("@",H9,1)+1),[2]Sheet1!$D:$F,3,FALSE) -> M766 | G9: Senior Vice President | H9: Ingrid.Nell@macquarie.com | I9: 3922-1994 | J9: Australia | K9: USD | M9: 2 | N9: 1 | V9: 0 | AC9: 0 | AJ9: 0 | AQ9: 0 | AX9: 0 | BE9: 0 | BF9: 0 | BG9: 0 | BH9: 0 | BI9: 0 | BJ9: 0 | BK9: 0 | BL9: 0 | BS9: 0 | BZ9: 0 | CG9: 0 | CN9: 0 | CU9: 0 | DB9: 0 | DC9: 0 | DD9: 0 | DE9: 0 | DF9: 0 | DG9: 0 | DH9: 0 | DI9: 0 | DJ9: NO | DK9: NO | DL9: NO | DM9: NO | DN9: NO | DO9: NO | DP9: NO | DQ9: NO | DR9: NO | DS9: NO | DT9: NO | DU9: NO | DV9: NO | DW9: NO | DX9: NO | DY9: NO | DZ9: NO | EA9: NO | EB9: NO | EC9: NO | ED9: NO | EE9: NO | EF9: NO | EG9: NO | EH9: NO | EI9: NO | EJ9: NO | EK9: NO | EL9: NO | EM9: NO | EN9: NO | EO9: NO | EP9: NO | EQ9: NO | ER9: NO | ES9: NO | EZ9: 0 | FG9: 0 | FN9: 0 | FU9: 0 | GB9: 0 | GI9: 0 | GP9: 0 | GX9: 0 | GY9: 0 | GZ9: 0 | HA9: 0 | HB9: 0 | HC9: 0 | HD9: 0 | HE9: 0 | HL9: 0 | HS9: 0 | HZ9: 0 | IG9: 0 | IN9: 0 | IO9: 0 | IP9: 0 | IQ9: 0 | IR9: 0 | IS9: 0 | IT9: 0 | IU9: 0 | JA9: 1 | JB9: 2 | JC9: 2 | JD9: START Asia Pacific: | NG9: START Europe: | RJ9: START North America: | VM9: START Global: | ZP9: START SOUTH America: | ADS9: START Africa:
A10: 226 | B10: ANREV | C10: 42780 | D10: Paul Summer | E10: J.P. Morgan Asset Management | F10: =VLOOKUP(MID(H10,SEARCH("@",H10,1),LEN(H10)-SEARCH("@",H10,1)+1),[2]Sheet1!$D:$F,3,FALSE) -> M082 | G10: Managing Director | H10: paul.t.summer@jpmorgan.com | I10: -2603 | J10: United States | K10: USD | M10: 1 | P10: 500 | S10: 75 | V10: 575 | AC10: 0 | AD10: 1377 | AG10: 500 | AH10: 287 | AI10: 280 | AJ10: 2444 | AQ10: 0 | AX10: 0 | BE10: 0 | BF10: 1877 | BG10: 0 | BH10: 0 | BI10: 575 | BJ10: 287 | BK10: 280 | BL10: 3019 | BM10: 1 | BP10: 1 | BS10: 2 | BZ10: 0 | CA10: 3 | CD10: 1 | CE10: 2 | CF10: 1 | CG10: 7 | CN10: 0 | CU10: 0 | DB10: 0 | DC10: 4 | DD10: 0 | DE10: 0 | DF10: 2 | DG10: 2 | DH10: 1 | DI10: 9 | DJ10: YES | DK10: NO | DL10: NO | DM10: YES | DN10: NO | DO10: NO | DP10: NO | DQ10: NO | DR10: NO | DS10: NO | DT10: NO | DU10: NO | DV10: YES | DW10: NO | DX10: NO | DY10: YES | DZ10: YES | EA10: YES | EB10: NO | EC10: NO | ED10: NO | EE10: NO | EF10: NO | EG10: NO | EH10: NO | EI10: NO | EJ10: NO | EK10: NO | EL10: NO | EM10: NO | EN10: NO | EO10: NO | EP10: NO | EQ10: NO | ER10: NO | ES10: NO | ET10: 1863 | EW10: 575 | EX10: 287 | EZ10: 2725 | FG10: 0 | FN10: 0 | FU10: 0 | FV10: 6 | GB10: 6 | GC10: 8 | GI10: 8 | GP10: 0 | GQ10: Corporation | GW10: 280 | GX10: 280 | GY10: 1877 | GZ10: 0 | HA10: 0 | HB10: 575 | HC10: 287 | HD10: 280 | HE10: 3019 | HK10: 280 | HL10: 280 | HM10: 50 | HS10: 50 | HT10: 1827 | HW10: 575 | HX10: 287 | HZ10: 2689 | IG10: 0 | IN10: 0 | IO10: 1877 | IP10: 0 | IQ10: 0 | IR10: 575 | IS10: 287 | IT10: 280 | IU10: 3019 | IW10: 50 | IX10: 50 | JA10: 1 | JB10: 1 | JC10: 1 | JD10: START Asia Pacific: | JE10: 500 | JH10: 75 | JK10: 575 | JR10: 0 | JY10: 0 | KF10: 0 | KM10: 0 | KT10: 0 | LA10: 0 | LI10: 0 | LJ10: 500 | LK10: 0 | LL10: 0 | LM10: 75 | LN10: 0 | LO10: 0 | LP10: 575 | LQ10: 50 | LW10: 50 | MD10: 0 | ME10: 450 | MH10: 75 | MK10: 525 | MR10: 0 | MY10: 0 | MZ10: 500 | NA10: 0 | NB10: 0 | NC10: 75 | ND10: 0 | NE10: 0 | NF10: 575 | NG10: START Europe: | RJ10: START North America: | RK10: 1363 | RN10: 500 | RO10: 287 | RQ10: 2150 | RX10: 0 | SE10: 0 | SL10: 0 | SM10: 6 | SS10: 6 | ST10: 8 | SZ10: 8 | TG10: 0 | TH10: Corporation | TN10: 280 | TO10: 280 | TP10: 1377 | TQ10: 0 | TR10: 0 | TS10: 500 | TT10: 287 | TU10: 280 | TV10: 2444 | UC10: 0 | UI10: 280 | UJ10: 280 | UK10: 1377 | UN10: 500 | UO10: 287 | UQ10: 2164 | UX10: 0 | VE10: 0 | VF10: 1377 | VG10: 0 | VH10: 0 | VI10: 500 | VJ10: 287 | VK10: 280 | VL10: 2444 | VM10: START Global: | ZP10: START SOUTH America: | ADS10: START Africa:
A11: 77 | B11: ANREV | C11: 42747.281 | D11: Don Tan | E11: KaiLong Investments | F11: =VLOOKUP(MID(H11,SEARCH("@",H11,1),LEN(H11)-SEARCH("@",H11,1)+1),[2]Sheet1!$D:$F,3,FALSE) -> M0226 | G11: VP, Fund Management | H11: don.tan@kailongrei.com | I11: 85237982627 | J11: China | K11: USD | M11: 2 | N11: 6 | O11: We are still in investment period for our other Funds | V11: 0 | AC11: 0 | AJ11: 0 | AQ11: 0 | AX11: 0 | BE11: 0 | BF11: 0 | BG11: 0 | BH11: 0 | BI11: 0 | BJ11: 0 | BK11: 0 | BL11: 0 | BS11: 0 | BZ11: 0 | CG11: 0 | CN11: 0 | CU11: 0 | DB11: 0 | DC11: 0 | DD11: 0 | DE11: 0 | DF11: 0 | DG11: 0 | DH11: 0 | DI11: 0 | DJ11: NO | DK11: NO | DL11: NO | DM11: NO | DN11: NO | DO11: NO | DP11: NO | DQ11: NO | DR11: NO | DS11: NO | DT11: NO | DU11: NO | DV11: NO | DW11: NO | DX11: NO | DY11: NO | DZ11: NO | EA11: NO | EB11: NO | EC11: NO | ED11: NO | EE11: NO | EF11: NO | EG11: NO | EH11: NO | EI11: NO | EJ11: NO | EK11: NO | EL11: NO | EM11: NO | EN11: NO | EO11: NO | EP11: NO | EQ11: NO | ER11: NO | ES11: NO | EZ11: 0 | FG11: 0 | FN11: 0 | FU11: 0 | GB11: 0 | GI11: 0 | GP11: 0 | GX11: 0 | GY11: 0 | GZ11: 0 | HA11: 0 | HB11: 0 | HC11: 0 | HD11: 0 | HE11: 0 | HL11: 0 | HS11: 0 | HZ11: 0 | IG11: 0 | IN11: 0 | IO11: 0 | IP11: 0 | IQ11: 0 | IR11: 0 | IS11: 0 | IT11: 0 | IU11: 0 | JA11: 1 | JB11: 3 | JC11: 1 | JD11: START Asia Pacific: | NG11: START Europe: | RJ11: START North America: | VM11: START Global: | ZP11: START SOUTH America: | ADS11: START Africa:
A12: 117 | B12: ANREV | C12: 42760.369 | D12: Ho Liwen | E12: SC Capital Partners | F12: =VLOOKUP(MID(H12,SEARCH("@",H12,1),LEN(H12)-SEARCH("@",H12,1)+1),[2]Sheet1!$D:$F,3,FALSE) -> M0159 | G12: Director Investor Relations | H12: liwen@recapinvestments.com | I12: -14384 | J12: Singapore | K12: USD | M12: 1 | P12: 280 | V12: 280 | AC12: 0 | AJ12: 0 | AQ12: 0 | AX12: 0 | BE12: 0 | BF12: 280 | BG12: 0 | BH12: 0 | BI12: 0 | BJ12: 0 | BK12: 0 | BL12: 280 | BM12: 1 | BS12: 1 | BZ12: 0 | CG12: 0 | CN12: 0 | CU12: 0 | DB12: 0 | DC12: 1 | DD12: 0 | DE12: 0 | DF12: 0 | DG12: 0 | DH12: 0 | DI12: 1 | DJ12: YES | DK12: NO | DL12: NO | DM12: NO | DN12: NO | DO12: NO | DP12: NO | DQ12: NO | DR12: NO | DS12: NO | DT12: NO | DU12: NO | DV12: NO | DW12: NO | DX12: NO | DY12: NO | DZ12: NO | EA12: NO | EB12: NO | EC12: NO | ED12: NO | EE12: NO | EF12: NO | EG12: NO | EH12: NO | EI12: NO | EJ12: NO | EK12: NO | EL12: NO | EM12: NO | EN12: NO | EO12: NO | EP12: NO | EQ12: NO | ER12: NO | ES12: NO | ET12: 158 | EZ12: 158 | FA12: 18 | FG12: 18 | FH12: 100 | FN12: 100 | FU12: 0 | GB12: 0 | GI12: 0 | GP12: 0 | GQ12: GP Co invest | GR12: 4 | GX12: 4 | GY12: 280 | GZ12: 0 | HA12: 0 | HB12: 0 | HC12: 0 | HD12: 0 | HE12: 280 | HL12: 0 | HM12: 88.5 | HS12: 88.5 | HT12: 191.5 | HZ12: 191.5 | IG12: 0 | IN12: 0 | IO12: 280 | IP12: 0 | IQ12: 0 | IR12: 0 | IS12: 0 | IT12: 0 | IU12: 280 | IV12: 31.6 | IX12: 68.4 | JA12: 2 | JB12: 2 | JC12: 1 | JD12: START Asia Pacific: | NG12: START Europe: | RJ12: START North America: | VM12: START Global: | ZP12: START SOUTH America: | ADS12: START Africa:
A13: 168 | B13: ANREV | C13: 42772.083 | D13: Natalie Barrington | E13: DEXUS Property Group | F13: =VLOOKUP(MID(H13,SEARCH("@",H13,1),LEN(H13)-SEARCH("@",H13,1)+1),[2]Sheet1!$D:$F,3,FALSE) -> M0090 | G13: DWPF Investor Relations and Operations Manager | H13: Natalie.Barrington@dexus.com | I13: +61 290171295 | J13: Australia | K13: AUD | M13: 2 | N13: 1 | V13: 0 | AC13: 0 | AJ13: 0 | AQ13: 0 | AX13: 0 | BE13: 0 | BF13: 0 | BG13: 0 | BH13: 0 | BI13: 0 | BJ13: 0 | BK13: 0 | BL13: 0 | BS13: 0 | BZ13: 0 | CG13: 0 | CN13: 0 | CU13: 0 | DB13: 0 | DC13: 0 | DD13: 0 | DE13: 0 | DF13: 0 | DG13: 0 | DH13: 0 | DI13: 0 | DJ13: NO | DK13: NO | DL13: NO | DM13: NO | DN13: NO | DO13: NO | DP13: NO | DQ13: NO | DR13: NO | DS13: NO | DT13: NO | DU13: NO | DV13: NO | DW13: NO | DX13: NO | DY13: NO | DZ13: NO | EA13: NO | EB13: NO | EC13: NO | ED13: NO | EE13: NO | EF13: NO | EG13: NO | EH13: NO | EI13: NO | EJ13: NO | EK13: NO | EL13: NO | EM13: NO | EN13: NO | EO13: NO | EP13: NO | EQ13: NO | ER13: NO | ES13: NO | EZ13: 0 | FG13: 0 | FN13: 0 | FU13: 0 | GB13: 0 | GI13: 0 | GP13: 0 | GX13: 0 | GY13: 0 | GZ13: 0 | HA13: 0 | HB13: 0 | HC13: 0 | HD13: 0 | HE13: 0 | HL13: 0 | HS13: 0 | HZ13: 0 | IG13: 0 | IN13: 0 | IO13: 0 | IP13: 0 | IQ13: 0 | IR13: 0 | IS13: 0 | IT13: 0 | IU13: 0 | JA13: 1 | JB13: 3 | JC13: 2 | JD13: START Asia Pacific: | NG13: START Europe: | RJ13: START North America: | VM13: START Global: | ZP13: START SOUTH America: | ADS13: START Africa:
A14: 170 | B14: ANREV | C14: 42780 | D14: Loretta Li | E14: ARCH Capital Management Co Ltd | F14: =VLOOKUP(MID(H14,SEARCH("@",H14,1),LEN(H14)-SEARCH("@",H14,1)+1),[2]Sheet1!$D:$F,3,FALSE) -> M421 | G14: CFO | H14: lli@archcapital.net | I14: 22644662 | J14: Hong Kong | K14: USD | M14: 1 | P14: 12.5 | V14: 12.5 | AC14: 0 | AJ14: 0 | AQ14: 0 | AX14: 0 | BE14: 0 | BF14: 12.5 | BG14: 0 | BH14: 0 | BI14: 0 | BJ14: 0 | BK14: 0 | BL14: 12.5 | BM14: 1 | BS14: 1 | BZ14: 0 | CG14: 0 | CN14: 0 | CU14: 0 | DB14: 0 | DC14: 1 | DD14: 0 | DE14: 0 | DF14: 0 | DG14: 0 | DH14: 0 | DI14: 1 | DJ14: YES | DK14: NO | DL14: NO | DM14: NO | DN14: NO | DO14: NO | DP14: NO | DQ14: NO | DR14: NO | DS14: NO | DT14: NO | DU14: NO | DV14: NO | DW14: NO | DX14: NO | DY14: NO | DZ14: NO | EA14: NO | EB14: NO | EC14: NO | ED14: NO | EE14: NO | EF14: NO | EG14: NO | EH14: NO | EI14: NO | EJ14: NO | EK14: NO | EL14: NO | EM14: NO | EN14: NO | EO14: NO | EP14: NO | EQ14: NO | ER14: NO | ES14: NO | EZ14: 0 | FG14: 0 | FN14: 0 | FU14: 0 | GB14: 0 | GI14: 0 | GJ14: 12.5 | GP14: 12.5 | GX14: 0 | GY14: 12.5 | GZ14: 0 | HA14: 0 | HB14: 0 | HC14: 0 | HD14: 0 | HE14: 12.5 | HL14: 0 | HM14: 12.5 | HS14: 12.5 | HZ14: 0 | IG14: 0 | IN14: 0 | IO14: 12.5 | IP14: 0 | IQ14: 0 | IR14: 0 | IS14: 0 | IT14: 0 | IU14: 12.5 | IX14: 100 | JA14: 3 | JB14: 3 | JC14: 2 | JD14: START Asia Pacific: | JK14: 0 | JR14: 0 | JY14: 0 | KF14: 0 | KM14: 0 | KT14: 0 | KU14: 12.5 | LA14: 12.5 | LI14: 0 | LJ14: 12.5 | LK14: 0 | LL14: 0 | LM14: 0 | LN14: 0 | LO14: 0 | LP14: 12.5 | LQ14: 12.5 | LW14: 12.5 | MD14: 0 | MK14: 0 | MR14: 0 | MY14: 0 | MZ14: 12.5 | NA14: 0 | NB14: 0 | NC14: 0 | ND14: 0 | NE14: 0 | NF14: 12.5 | NG14: START Europe: | RJ14: START North America: | VM14: START Global: | ZP14: START SOUTH America: | ADS14: START Africa:
A15: 236 | B15: ANREV | C15: 42780 | D15: Joel Oei | E15: Ascendas-Singbridge | F15: =VLOOKUP(MID(H15,SEARCH("@",H15,1),LEN(H15)-SEARCH("@",H15,1)+1),[2]Sheet1!$D:$F,3,FALSE) -> M0189 | G15: Manager, Fund Development | H15: joel.oei@ascendas-singbridge.com | I15: 6565088808 | J15: Singapore | K15: SGD | M15: 1 | S15: 350 | V15: 350 | AC15: 0 | AJ15: 0 | AQ15: 0 | AX15: 0 | BE15: 0 | BF15: 0 | BG15: 0 | BH15: 0 | BI15: 350 | BJ15: 0 | BK15: 0 | BL15: 350 | BP15: 1 | BS15: 1 | BZ15: 0 | CG15: 0 | CN15: 0 | CU15: 0 | DB15: 0 | DC15: 0 | DD15: 0 | DE15: 0 | DF15: 1 | DG15: 0 | DH15: 0 | DI15: 1 | DJ15: NO | DK15: NO | DL15: NO | DM15: YES | DN15: NO | DO15: NO | DP15: NO | DQ15: NO | DR15: NO | DS15: NO | DT15: NO | DU15: NO | DV15: NO | DW15: NO | DX15: NO | DY15: NO | DZ15: NO | EA15: NO | EB15: NO | EC15: NO | ED15: NO | EE15: NO | EF15: NO | EG15: NO | EH15: NO | EI15: NO | EJ15: NO | EK15: NO | EL15: NO | EM15: NO | EN15: NO | EO15: NO | EP15: NO | EQ15: NO | ER15: NO | ES15: NO | EZ15: 0 | FG15: 0 | FN15: 0 | FU15: 0 | GB15: 0 | GI15: 0 | GP15: 0 | GQ15: Corporate | GU15: 350 | GX15: 350 | GY15: 0 | GZ15: 0 | HA15: 0 | HB15: 350 | HC15: 0 | HD15: 0 | HE15: 350 | HI15: 350 | HL15: 350 | HS15: 0 | HZ15: 0 | IG15: 0 | IN15: 0 | IO15: 0 | IP15: 0 | IQ15: 0 | IR15: 350 | IS15: 0 | IT15: 0 | IU15: 350 | IX15: 100 | JA15: 1 | JB15: 2 | JC15: 1 | JD15: START Asia Pacific: | JK15: 0 | JR15: 0 | JY15: 0 | KF15: 0 | KM15: 0 | KT15: 0 | LA15: 0 | LB15: Corporate | LF15: 350 | LI15: 350 | LJ15: 0 | LK15: 0 | LL15: 0 | LM15: 350 | LN15: 0 | LO15: 0 | LP15: 350 | LW15: 0 | MA15: 350 | MD15: 350 | MK15: 0 | MR15: 0 | MY15: 0 | MZ15: 0 | NA15: 0 | NB15: 0 | NC15: 350 | ND15: 0 | NE15: 0 | NF15: 350 | NG15: START Europe: | RJ15: START North America: | VM15: START Global: | ZP15: START SOUTH America: | ADS15: START Africa:
A16: 115 | B16: ANREV | C16: 42775.332 | D16: Christine Ong | E16: Mapletree Investments Pte Ltd | F16: =VLOOKUP(MID(H16,SEARCH("@",H16,1),LEN(H16)-SEARCH("@",H16,1)+1),[2]Sheet1!$D:$F,3,FALSE) -> M0180 | G16: Head, Private Funds Management | H16: christine.ong@mapletree.com.sg | I16: 6684-7781 | J16: Singapore | K16: USD | M16: 2 | V16: 0 | AC16: 0 | AJ16: 0 | AQ16: 0 | AX16: 0 | BE16: 0 | BF16: 0 | BG16: 0 | BH16: 0 | BI16: 0 | BJ16: 0 | BK16: 0 | BL16: 0 | BS16: 0 | BZ16: 0 | CG16: 0 | CN16: 0 | CU16: 0 | DB16: 0 | DC16: 0 | DD16: 0 | DE16: 0 | DF16: 0 | DG16: 0 | DH16: 0 | DI16: 0 | DJ16: NO | DK16: NO | DL16: NO | DM16: NO | DN16: NO | DO16: NO | DP16: NO | DQ16: NO | DR16: NO | DS16: NO | DT16: NO | DU16: NO | DV16: NO | DW16: NO | DX16: NO | DY16: NO | DZ16: NO | EA16: NO | EB16: NO | EC16: NO | ED16: NO | EE16: NO | EF16: NO | EG16: NO | EH16: NO | EI16: NO | EJ16: NO | EK16: NO | EL16: NO | EM16: NO | EN16: NO | EO16: NO | EP16: NO | EQ16: NO | ER16: NO | ES16: NO | EZ16: 0 | FG16: 0 | FN16: 0 | FU16: 0 | GB16: 0 | GI16: 0 | GP16: 0 | GX16: 0 | GY16: 0 | GZ16: 0 | HA16: 0 | HB16: 0 | HC16: 0 | HD16: 0 | HE16: 0 | HL16: 0 | HS16: 0 | HZ16: 0 | IG16: 0 | IN16: 0 | IO16: 0 | IP16: 0 | IQ16: 0 | IR16: 0 | IS16: 0 | IT16: 0 | IU16: 0 | JA16: 1 | JB16: 2 | JC16: 2 | JD16: START Asia Pacific: | NG16: START Europe: | RJ16: START North America: | VM16: START Global: | ZP16: START SOUTH America: | ADS16: START Africa:
A17: 88 | B17: ANREV | C17: 42780 | D17: Serene Foong | E17: Alpha Investment Partners Limited | F17: =VLOOKUP(MID(H17,SEARCH("@",H17,1),LEN(H17)-SEARCH("@",H17,1)+1),[2]Sheet1!$D:$F,3,FALSE) -> M0106 | G17: SVP Finance | H17: serene.foong@kepcapital.com | I17: -68031736 | J17: Singapore | K17: USD | M17: 1 | P17: 281.52 | Q17: 265 | V17: 546.52 | AC17: 0 | AJ17: 0 | AK17: 132.34 | AQ17: 132.34 | AX17: 0 | BE17: 0 | BF17: 413.86 | BG17: 265 | BH17: 0 | BI17: 0 | BJ17: 0 | BK17: 0 | BL17: 678.86 | BM17: 1 | BN17: 1 | BS17: 2 | BZ17: 0 | CG17: 0 | CH17: 1 | CN17: 1 | CU17: 0 | DB17: 0 | DC17: 2 | DD17: 1 | DE17: 0 | DF17: 0 | DG17: 0 | DH17: 0 | DI17: 3 | DJ17: YES | DK17: YES | DL17: NO | DM17: NO | DN17: NO | DO17: NO | DP17: NO | DQ17: NO | DR17: NO | DS17: NO | DT17: NO | DU17: NO | DV17: NO | DW17: NO | DX17: NO | DY17: NO | DZ17: NO | EA17: NO | EB17: YES | EC17: NO | ED17: NO | EE17: NO | EF17: NO | EG17: NO | EH17: NO | EI17: NO | EJ17: NO | EK17: NO | EL17: NO | EM17: NO | EN17: NO | EO17: NO | EP17: NO | EQ17: NO | ER17: NO | ES17: NO | ET17: 134 | EU17: 265 | EZ17: 399 | FG17: 0 | FN17: 0 | FO17: 20 | FU17: 20 | FV17: 30 | GB17: 30 | GI17: 0 | GP17: 0 | GQ17: Corporates/Banks/Others | GR17: 229.86 | GX17: 229.86 | GY17: 413.86 | GZ17: 265 | HA17: 0 | HB17: 0 | HC17: 0 | HD17: 0 | HE17: 678.86 | HF17: 279.86 | HL17: 279.86 | HM17: 134 | HN17: 265 | HS17: 399 | HZ17: 0 | IG17: 0 | IN17: 0 | IO17: 413.86 | IP17: 265 | IQ17: 0 | IR17: 0 | IS17: 0 | IT17: 0 | IU17: 678.86 | IW17: 100 | JA17: 1 | JB17: 1 | JC17: 2 | JD17: START Asia Pacific: | NG17: START Europe: | RJ17: START North America: | VM17: START Global: | ZP17: START SOUTH America: | ADS17: START Africa:
A18: 114 | B18: ANREV | C18: 42774.097 | D18: David Muren | E18: Angelo, Gordon & Co. | F18: =VLOOKUP(MID(H18,SEARCH("@",H18,1),LEN(H18)-SEARCH("@",H18,1)+1),[2]Sheet1!$D:$F,3,FALSE) -> M0001 | G18: Director | H18: dmuren@angelogordon.com | I18: 212-692-0209 | J18: United States | K18: USD | M18: 1 | P18: 566 | V18: 566 | AC18: 0 | AJ18: 0 | AK18: 361 | AQ18: 361 | AX18: 0 | BE18: 0 | BF18: 927 | BG18: 0 | BH18: 0 | BI18: 0 | BJ18: 0 | BK18: 0 | BL18: 927 | BM18: 1 | BS18: 1 | BZ18: 0 | CG18: 0 | CH18: 1 | CN18: 1 | CU18: 0 | DB18: 0 | DC18: 2 | DD18: 0 | DE18: 0 | DF18: 0 | DG18: 0 | DH18: 0 | DI18: 2 | DJ18: YES | DK18: NO | DL18: NO | DM18: NO | DN18: NO | DO18: NO | DP18: NO | DQ18: NO | DR18: NO | DS18: NO | DT18: NO | DU18: NO | DV18: NO | DW18: NO | DX18: NO | DY18: NO | DZ18: NO | EA18: NO | EB18: YES | EC18: NO | ED18: NO | EE18: NO | EF18: NO | EG18: NO | EH18: NO | EI18: NO | EJ18: NO | EK18: NO | EL18: NO | EM18: NO | EN18: NO | EO18: NO | EP18: NO | EQ18: NO | ER18: NO | ES18: NO | EZ18: 0 | FG18: 0 | FN18: 0 | FU18: 0 | GB18: 0 | GI18: 0 | GP18: 0 | GX18: 0 | GY18: 0 | GZ18: 0 | HA18: 0 | HB18: 0 | HC18: 0 | HD18: 0 | HE18: 0 | HL18: 0 | HS18: 0 | HZ18: 0 | IG18: 0 | IN18: 0 | IO18: 0 | IP18: 0 | IQ18: 0 | IR18: 0 | IS18: 0 | IT18: 0 | IU18: 0 | IV18: 3 | IX18: 97 | JC18: 1 | JD18: START Asia Pacific: | JK18: 0 | JR18: 0 | JY18: 0 | KF18: 0 | KM18: 0 | KT18: 0 | LA18: 0 | LI18: 0 | LJ18: 0 | LK18: 0 | LL18: 0 | LM18: 0 | LN18: 0 | LO18: 0 | LP18: 0 | LW18: 0 | MD18: 0 | MK18: 0 | MR18: 0 | MY18: 0 | MZ18: 0 | NA18: 0 | NB18: 0 | NC18: 0 | ND18: 0 | NE18: 0 | NF18: 0 | NG18: START Europe: | RJ18: START North America: | VM18: START Global: | VT18: 0 | WA18: 0 | WH18: 0 | WO18: 0 | WV18: 0 | XC18: 0 | XJ18: 0 | XR18: 0 | XS18: 0 | XT18: 0 | XU18: 0 | XV18: 0 | XW18: 0 | XX18: 0 | XY18: 0 | YF18: 0 | YM18: 0 | YT18: 0 | ZA18: 0 | ZH18: 0 | ZI18: 0 | ZJ18: 0 | ZK18: 0 | ZL18: 0 | ZM18: 0 | ZN18: 0 | ZO18: 0 | ZP18: START SOUTH America: | ADS18: START Africa:
A19: 110 | B19: ANREV | C19: 42760.141 | D19: Tim Nation | E19: AMP Capital | F19: =VLOOKUP(MID(H19,SEARCH("@",H19,1),LEN(H19)-SEARCH("@",H19,1)+1),[2]Sheet1!$D:$F,3,FALSE) -> M0082 | G19: Head of Real Estate Capital | H19: tim.nation@ampcapital.com | I19: 61292576129 | J19: Australia | K19: AUD | M19: 1 | P19: 1408 | Q19: 30 | T19: 5 | V19: 1443 | AC19: 0 | AJ19: 0 | AQ19: 0 | AX19: 0 | BE19: 0 | BF19: 1408 | BG19: 30 | BH19: 0 | BI19: 0 | BJ19: 5 | BK19: 0 | BL19: 1443 | BM19: 4 | BN19: 1 | BQ19: 1 | BS19: 6 | BZ19: 0 | CG19: 0 | CN19: 0 | CU19: 0 | DB19: 0 | DC19: 4 | DD19: 1 | DE19: 0 | DF19: 0 | DG19: 1 | DH19: 0 | DI19: 6 | DJ19: YES | DK19: YES | DL19: NO | DM19: NO | DN19: YES | DO19: NO | DP19: NO | DQ19: NO | DR19: NO | DS19: NO | DT19: NO | DU19: NO | DV19: NO | DW19: NO | DX19: NO | DY19: NO | DZ19: NO | EA19: NO | EB19: NO | EC19: NO | ED19: NO | EE19: NO | EF19: NO | EG19: NO | EH19: NO | EI19: NO | EJ19: NO | EK19: NO | EL19: NO | EM19: NO | EN19: NO | EO19: NO | EP19: NO | EQ19: NO | ER19: NO | ES19: NO | ET19: 728.17 | EZ19: 728.17 | FA19: 89.78 | FG19: 89.78 | FN19: 0 | FO19: 116.05 | FU19: 116.05 | GB19: 0 | GI19: 0 | GK19: 30 | GP19: 30 | GQ19: Retail investors | GR19: 474 | GV19: 5 | GX19: 479 | GY19: 1408 | GZ19: 30 | HA19: 0 | HB19: 0 | HC19: 5 | HD19: 0 | HE19: 1443 | HF19: 1108.74 | HG19: 30 | HJ19: 5 | HL19: 1143.74 | HM19: 299.26 | HS19: 299.26 | HZ19: 0 | IG19: 0 | IN19: 0 | IO19: 1408 | IP19: 30 | IQ19: 0 | IR19: 0 | IS19: 5 | IT19: 0 | IU19: 1443 | IW19: 22 | IX19: 78 | JA19: 3 | JB19: 3 | JC19: 1 | JD19: START Asia Pacific: | JE19: 728.17 | JK19: 728.17 | JL19: 89.78 | JR19: 89.78 | JY19: 0 | JZ19: 116.05 | KF19: 116.05 | KM19: 0 | KT19: 0 | KV19: 30 | LA19: 30 | LB19: Retail investors | LC19: 474 | LG19: 5 | LI19: 479 | LJ19: 1408 | LK19: 30 | LL19: 0 | LM19: 0 | LN19: 5 | LO19: 0 | LP19: 1443 | LQ19: 299.26 | LW19: 299.26 | LX19: 1143.74 | MD19: 1143.74 | MK19: 0 | MR19: 0 | MY19: 0 | MZ19: 1443 | NA19: 0 | NB19: 0 | NC19: 0 | ND19: 0 | NE19: 0 | NF19: 1443 | NG19: START Europe: | RJ19: START North America: | VM19: START Global: | ZP19: START SOUTH America: | ADS19: START Africa:
A20: 242 | B20: ANREV | C20: 42780 | D20: Nicholas | E20: Investa Property Group | F20: =VLOOKUP(MID(H20,SEARCH("@",H20,1),LEN(H20)-SEARCH("@",H20,1)+1),[2]Sheet1!$D:$F,3,FALSE) -> M0077 | G20: Senior Fund Analyst | H20: nchui@investa.com.au | I20: +61 2 8226 9916 | J20: Australia | K20: AUD | M20: 1 | P20: 469 | R20: 100 | V20: 569 | AC20: 0 | AJ20: 0 | AQ20: 0 | AX20: 0 | BE20: 0 | BF20: 469 | BG20: 0 | BH20: 100 | BI20: 0 | BJ20: 0 | BK20: 0 | BL20: 569 | BM20: 1 | BO20: 1 | BS20: 2 | BZ20: 0 | CG20: 0 | CN20: 0 | CU20: 0 | DB20: 0 | DC20: 1 | DD20: 0 | DE20: 1 | DF20: 0 | DG20: 0 | DH20: 0 | DI20: 2 | DJ20: YES | DK20: NO | DL20: YES | DM20: NO | DN20: NO | DO20: NO | DP20: NO | DQ20: NO | DR20: NO | DS20: NO | DT20: NO | DU20: NO | DV20: NO | DW20: NO | DX20: NO | DY20: NO | DZ20: NO | EA20: NO | EB20: NO | EC20: NO | ED20: NO | EE20: NO | EF20: NO | EG20: NO | EH20: NO | EI20: NO | EJ20: NO | EK20: NO | EL20: NO | EM20: NO | EN20: NO | EO20: NO | EP20: NO | EQ20: NO | ER20: NO | ES20: NO | EZ20: 0 | FG20: 0 | FN20: 0 | FU20: 0 | GB20: 0 | GI20: 0 | GP20: 0 | GX20: 0 | GY20: 0 | GZ20: 0 | HA20: 0 | HB20: 0 | HC20: 0 | HD20: 0 | HE20: 0 | HF20: 427.8 | HH20: 100 | HL20: 527.8 | HM20: 40.5 | HS20: 40.5 | HZ20: 0 | IG20: 0 | IN20: 0 | IO20: 468.3 | IP20: 0 | IQ20: 100 | IR20: 0 | IS20: 0 | IT20: 0 | IU20: 568.3 | JC20: 1 | JD20: START Asia Pacific: | JK20: 0 | JR20: 0 | JY20: 0 | KF20: 0 | KM20: 0 | KT20: 0 | LA20: 0 | LI20: 0 | LJ20: 0 | LK20: 0 | LL20: 0 | LM20: 0 | LN20: 0 | LO20: 0 | LP20: 0 | LQ20: 40.5 | LS20: 100 | LW20: 140.5 | LX20: 427.8 | MD20: 427.8 | MK20: 0 | MR20: 0 | MY20: 0 | MZ20: 468.3 | NA20: 0 | NB20: 100 | NC20: 0 | ND20: 0 | NE20: 0 | NF20: 568.3 | NG20: START Europe: | RJ20: START North America: | VM20: START Global: | ZP20: START SOUTH America: | ADS20: START Africa:
A21: 237 | B21: ANREV | C21: 42780 | D21: Shawn Tsai | E21: Gaw Capital Partners | F21: =VLOOKUP(MID(H21,SEARCH("@",H21,1),LEN(H21)-SEARCH("@",H21,1)+1),[2]Sheet1!$D:$F,3,FALSE) -> M0186 | G21: Associate | H21: shawntsai@gawcapital.com | I21: 25837774 | J21: Hong Kong | K21: USD | M21: 1 | P21: 1252.2 | V21: 1252.2 | AC21: 0 | AJ21: 0 | AQ21: 0 | AX21: 0 | BE21: 0 | BF21: 1252.2 | BG21: 0 | BH21: 0 | BI21: 0 | BJ21: 0 | BK21: 0 | BL21: 1252.2 | BM21: 2 | BS21: 2 | BZ21: 0 | CG21: 0 | CN21: 0 | CU21: 0 | DB21: 0 | DC21: 2 | DD21: 0 | DE21: 0 | DF21: 0 | DG21: 0 | DH21: 0 | DI21: 2 | DJ21: YES | DK21: NO | DL21: NO | DM21: NO | DN21: NO | DO21: NO | DP21: NO | DQ21: NO | DR21: NO | DS21: NO | DT21: NO | DU21: NO | DV21: NO | DW21: NO | DX21: NO | DY21: NO | DZ21: NO | EA21: NO | EB21: NO | EC21: NO | ED21: NO | EE21: NO | EF21: NO | EG21: NO | EH21: NO | EI21: NO | EJ21: NO | EK21: NO | EL21: NO | EM21: NO | EN21: NO | EO21: NO | EP21: NO | EQ21: NO | ER21: NO | ES21: NO | ET21: 520 | EZ21: 520 | FG21: 0 | FH21: 460 | FN21: 460 | FU21: 0 | FV21: 10 | GB21: 10 | GC21: 146.4 | GI21: 146.4 | GJ21: 23 | GP21: 23 | GQ21: General Partner contribution,financial institution, corporate | GR21: 92.8 | GX21: 92.8 | GY21: 1252.2 | GZ21: 0 | HA21: 0 | HB21: 0 | HC21: 0 | HD21: 0 | HE21: 1252.2 | HF21: 589.3 | HL21: 589.3 | HM21: 297.9 | HS21: 297.9 | HT21: 365 | HZ21: 365 | IG21: 0 | IN21: 0 | IO21: 1252.2 | IP21: 0 | IQ21: 0 | IR21: 0 | IS21: 0 | IT21: 0 | IU21: 1252.2 | JA21: 1 | JB21: 2 | JC21: 1 | JD21: START Asia Pacific: | JE21: 520 | JK21: 520 | JR21: 0 | JS21: 460 | JY21: 460 | KF21: 0 | KG21: 10 | KM21: 10 | KN21: 146.4 | KT21: 146.4 | KU21: 23 | LA21: 23 | LB21: General Partner contribution, corporates, financial institution | LC21: 92.8 | LI21: 92.8 | LJ21: 1252.2 | LK21: 0 | LL21: 0 | LM21: 0 | LN21: 0 | LO21: 0 | LP21: 1252.2 | LQ21: 589.3 | LW21: 589.3 | LX21: 297.9 | MD21: 297.9 | ME21: 365 | MK21: 365 | MR21: 0 | MY21: 0 | MZ21: 1252.2 | NA21: 0 | NB21: 0 | NC21: 0 | ND21: 0 | NE21: 0 | NF21: 1252.2 | NG21: START Europe: | RJ21: START North America: | VM21: START Global: | ZP21: START SOUTH America: | ADS21: START Africa:
A22: 71 | B22: ANREV | C22: 42779.144 | D22: James Inwood | E22: Goodman Group | F22: =VLOOKUP(MID(H22,SEARCH("@",H22,1),LEN(H22)-SEARCH("@",H22,1)+1),[2]Sheet1!$D:$F,3,FALSE) -> M065 | G22: Group Head of Investment Management | H22: James.Inwood@goodman.com | I22: 9230 7417 | J22: Australia | K22: AUD | M22: 1 | S22: 1633.92 | V22: 1633.92 | Z22: 684.11 | AC22: 684.11 | AJ22: 0 | AQ22: 0 | AX22: 0 | BE22: 0 | BF22: 0 | BG22: 0 | BH22: 0 | BI22: 2318.03 | BJ22: 0 | BK22: 0 | BL22: 2318.03 | BP22: 3 | BS22: 3 | BW22: 1 | BZ22: 1 | CG22: 0 | CN22: 0 | CU22: 0 | DB22: 0 | DC22: 0 | DD22: 0 | DE22: 0 | DF22: 4 | DG22: 0 | DH22: 0 | DI22: 4 | DJ22: NO | DK22: NO | DL22: NO | DM22: YES | DN22: NO | DO22: NO | DP22: NO | DQ22: NO | DR22: NO | DS22: YES | DT22: NO | DU22: NO | DV22: NO | DW22: NO | DX22: NO | DY22: NO | DZ22: NO | EA22: NO | EB22: NO | EC22: NO | ED22: NO | EE22: NO | EF22: NO | EG22: NO | EH22: NO | EI22: NO | EJ22: NO | EK22: NO | EL22: NO | EM22: NO | EN22: NO | EO22: NO | EP22: NO | EQ22: NO | ER22: NO | ES22: NO | EW22: 2256.75 | EZ22: 2256.75 | FG22: 0 | FK22: 61.28 | FN22: 61.28 | FU22: 0 | GB22: 0 | GI22: 0 | GP22: 0 | GX22: 0 | GY22: 0 | GZ22: 0 | HA22: 0 | HB22: 2318.03 | HC22: 0 | HD22: 0 | HE22: 2318.03 | HL22: 0 | HP22: 587.17 | HS22: 587.17 | HW22: 1730.86 | HZ22: 1730.86 | IG22: 0 | IN22: 0 | IO22: 0 | IP22: 0 | IQ22: 0 | IR22: 2318.03 | IS22: 0 | IT22: 0 | IU22: 2318.03 | IX22: 100 | JA22: 3 | JB22: 3 | JC22: 1 | JD22: START Asia Pacific: | JH22: 1572.64 | JK22: 1572.64 | JR22: 0 | JV22: 61.28 | JY22: 61.28 | KF22: 0 | KM22: 0 | KT22: 0 | LA22: 0 | LI22: 0 | LJ22: 0 | LK22: 0 | LL22: 0 | LM22: 1633.92 | LN22: 0 | LO22: 0 | LP22: 1633.92 | LT22: 245.12 | LW22: 245.12 | MD22: 0 | MH22: 1388.8 | MK22: 1388.8 | MR22: 0 | MY22: 0 | MZ22: 0 | NA22: 0 | NB22: 0 | NC22: 1633.92 | ND22: 0 | NE22: 0 | NF22: 1633.92 | NG22: START Europe: | NK22: 684.11 | NN22: 684.11 | NU22: 0 | OB22: 0 | OI22: 0 | OP22: 0 | OW22: 0 | PD22: 0 | PL22: 0 | PM22: 0 | PN22: 0 | PO22: 0 | PP22: 684.11 | PQ22: 0 | PR22: 0 | PS22: 684.11 | PW22: 342.05 | PZ22: 342.05 | QG22: 0 | QK22: 342.06 | QN22: 342.06 | QU22: 0 | RB22: 0 | RC22: 0 | RD22: 0 | RE22: 0 | RF22: 684.11 | RG22: 0 | RH22: 0 | RI22: 684.11 | RJ22: START North America: | VM22: START Global: | ZP22: START SOUTH America: | ADS22: START Africa:
A23: 184 | B23: ANREV | C23: 42780 | D23: Angel | E23: CLSA | F23: =VLOOKUP(MID(H23,SEARCH("@",H23,1),LEN(H23)-SEARCH("@",H23,1)+1),[2]Sheet1!$D:$F,3,FALSE) -> M0309 | G23: MD | H23: angel.li@clsa.com | I23: na | J23: Hong Kong | K23: USD | M23: 2 | V23: 0 | AC23: 0 | AJ23: 0 | AQ23: 0 | AX23: 0 | BE23: 0 | BF23: 0 | BG23: 0 | BH23: 0 | BI23: 0 | BJ23: 0 | BK23: 0 | BL23: 0 | BS23: 0 | BZ23: 0 | CG23: 0 | CN23: 0 | CU23: 0 | DB23: 0 | DC23: 0 | DD23: 0 | DE23: 0 | DF23: 0 | DG23: 0 | DH23: 0 | DI23: 0 | DJ23: NO | DK23: NO | DL23: NO | DM23: NO | DN23: NO | DO23: NO | DP23: NO | DQ23: NO | DR23: NO | DS23: NO | DT23: NO | DU23: NO | DV23: NO | DW23: NO | DX23: NO | DY23: NO | DZ23: NO | EA23: NO | EB23: NO | EC23: NO | ED23: NO | EE23: NO | EF23: NO | EG23: NO | EH23: NO | EI23: NO | EJ23: NO | EK23: NO | EL23: NO | EM23: NO | EN23: NO | EO23: NO | EP23: NO | EQ23: NO | ER23: NO | ES23: NO | EZ23: 0 | FG23: 0 | FN23: 0 | FU23: 0 | GB23: 0 | GI23: 0 | GP23: 0 | GX23: 0 | GY23: 0 | GZ23: 0 | HA23: 0 | HB23: 0 | HC23: 0 | HD23: 0 | HE23: 0 | HL23: 0 | HS23: 0 | HZ23: 0 | IG23: 0 | IN23: 0 | IO23: 0 | IP23: 0 | IQ23: 0 | IR23: 0 | IS23: 0 | IT23: 0 | IU23: 0 | JC23: 2 | JD23: START Asia Pacific: | NG23: START Europe: | RJ23: START North America: | VM23: START Global: | ZP23: START SOUTH America: | ADS23: START Africa:
A24: 76 | B24: ANREV | C24: 42747.183 | D24: Yosuke Fujioka | E24: Global Logistic Properties Limited | F24: =VLOOKUP(MID(H24,SEARCH("@",H24,1),LEN(H24)-SEARCH("@",H24,1)+1),[2]Sheet1!$D:$F,3,FALSE) -> M0144 | G24: Senior Vice President | H24: yfujioka@glprop.com | I24: +65 6672 5472 | J24: Singapore | K24: USD | M24: 1 | S24: 500 | V24: 500 | AC24: 0 | AD24: 560 | AJ24: 560 | AQ24: 0 | AX24: 0 | BE24: 0 | BF24: 560 | BG24: 0 | BH24: 0 | BI24: 500 | BJ24: 0 | BK24: 0 | BL24: 1060 | BP24: 1 | BS24: 1 | BZ24: 0 | CA24: 1 | CG24: 1 | CN24: 0 | CU24: 0 | DB24: 0 | DC24: 1 | DD24: 0 | DE24: 0 | DF24: 1 | DG24: 0 | DH24: 0 | DI24: 2 | DJ24: NO | DK24: NO | DL24: NO | DM24: YES | DN24: NO | DO24: NO | DP24: NO | DQ24: NO | DR24: NO | DS24: NO | DT24: NO | DU24: NO | DV24: YES | DW24: NO | DX24: NO | DY24: NO | DZ24: NO | EA24: NO | EB24: NO | EC24: NO | ED24: NO | EE24: NO | EF24: NO | EG24: NO | EH24: NO | EI24: NO | EJ24: NO | EK24: NO | EL24: NO | EM24: NO | EN24: NO | EO24: NO | EP24: NO | EQ24: NO | ER24: NO | ES24: NO | ET24: 160 | EW24: 500 | EZ24: 660 | FA24: 150 | FG24: 150 | FH24: 150 | FN24: 150 | FU24: 0 | GB24: 0 | GI24: 0 | GP24: 0 | GQ24: Corporations | GR24: 100 | GX24: 100 | GY24: 560 | GZ24: 0 | HA24: 0 | HB24: 500 | HC24: 0 | HD24: 0 | HE24: 1060 | HF24: 450 | HL24: 450 | HM24: 50 | HS24: 50 | HT24: 60 | HW24: 500 | HZ24: 560 | IG24: 0 | IN24: 0 | IO24: 560 | IP24: 0 | IQ24: 0 | IR24: 500 | IS24: 0 | IT24: 0 | IU24: 1060 | IV24: 100 | JA24: 1 | JB24: 3 | JC24: 1 | JD24: START Asia Pacific: | JH24: 500 | JK24: 500 | JR24: 0 | JY24: 0 | KF24: 0 | KM24: 0 | KT24: 0 | LA24: 0 | LI24: 0 | LJ24: 0 | LK24: 0 | LL24: 0 | LM24: 500 | LN24: 0 | LO24: 0 | LP24: 500 | LW24: 0 | MD24: 0 | MH24: 500 | MK24: 500 | MR24: 0 | MY24: 0 | MZ24: 0 | NA24: 0 | NB24: 0 | NC24: 500 | ND24: 0 | NE24: 0 | NF24: 500 | NG24: START Europe: | RJ24: START North America: | RK24: 160 | RQ24: 160 | RR24: 150 | RX24: 150 | RY24: 150 | SE24: 150 | SL24: 0 | SS24: 0 | SZ24: 0 | TG24: 0 | TH24: Corporations | TI24: 100 | TO24: 100 | TP24: 560 | TQ24: 0 | TR24: 0 | TS24: 0 | TT24: 0 | TU24: 0 | TV24: 560 | TW24: 50 | UC24: 50 | UD24: 450 | UJ24: 450 | UK24: 60 | UQ24: 60 | UX24: 0 | VE24: 0 | VF24: 560 | VG24: 0 | VH24: 0 | VI24: 0 | VJ24: 0 | VK24: 0 | VL24: 560 | VM24: START Global: | ZP24: START SOUTH America: | ADS24: START Africa:
A25: 100 | B25: ANREV | C25: 42752.604 | D25: Simon Lockwood | E25: Cromwell Property Group | F25: =VLOOKUP(MID(H25,SEARCH("@",H25,1),LEN(H25)-SEARCH("@",H25,1)+1),[2]Sheet1!$D:$F,3,FALSE) -> M0267 | G25: Equity Manager | H25: simon.lockwood@valad.co.uk | I25: 7974221882 | J25: United Kingdom | K25: EUR | M25: 1 | V25: 0 | W25: 90 | X25: 612 | AC25: 702 | AJ25: 0 | AQ25: 0 | AX25: 0 | BE25: 0 | BF25: 90 | BG25: 612 | BH25: 0 | BI25: 0 | BJ25: 0 | BK25: 0 | BL25: 702 | BS25: 0 | BT25: 1 | BU25: 9 | BZ25: 10 | CG25: 0 | CN25: 0 | CU25: 0 | DB25: 0 | DC25: 1 | DD25: 9 | DE25: 0 | DF25: 0 | DG25: 0 | DH25: 0 | DI25: 10 | DJ25: NO | DK25: NO | DL25: NO | DM25: NO | DN25: NO | DO25: NO | DP25: YES | DQ25: YES | DR25: NO | DS25: NO | DT25: NO | DU25: NO | DV25: NO | DW25: NO | DX25: NO | DY25: NO | DZ25: NO | EA25: NO | EB25: NO | EC25: NO | ED25: NO | EE25: NO | EF25: NO | EG25: NO | EH25: NO | EI25: NO | EJ25: NO | EK25: NO | EL25: NO | EM25: NO | EN25: NO | EO25: NO | EP25: NO | EQ25: NO | ER25: NO | ES25: NO | ET25: 90 | EZ25: 90 | FG25: 0 | FN25: 0 | FU25: 0 | GB25: 0 | GI25: 0 | GP25: 0 | GQ25: Opp Funds / Inv Banks | GS25: 612 | GX25: 612 | GY25: 90 | GZ25: 612 | HA25: 0 | HB25: 0 | HC25: 0 | HD25: 0 | HE25: 702 | HL25: 0 | HM25: 90 | HN25: 612 | HS25: 702 | HZ25: 0 | IG25: 0 | IN25: 0 | IO25: 90 | IP25: 612 | IQ25: 0 | IR25: 0 | IS25: 0 | IT25: 0 | IU25: 702 | IX25: 100 | JA25: 1 | JB25: 3 | JC25: 1 | JD25: START Asia Pacific: | NG25: START Europe: | NH25: 90 | NN25: 90 | NU25: 0 | OB25: 0 | OI25: 0 | OP25: 0 | OW25: 0 | PD25: 0 | PG25: 612 | PL25: 612 | PM25: 90 | PN25: 612 | PO25: 0 | PP25: 0 | PQ25: 0 | PR25: 0 | PS25: 702 | PT25: 90 | PU25: 612 | PZ25: 702 | QG25: 0 | QN25: 0 | QU25: 0 | RB25: 0 | RC25: 90 | RD25: 612 | RE25: 0 | RF25: 0 | RG25: 0 | RH25: 0 | RI25: 702 | RJ25: START North America: | VM25: START Global: | ZP25: START SOUTH America: | ADS25: START Africa:
A26: 73 | B26: ANREV | C26: 42759.268 | D26: Kenji Kondo | E26: Tokyo Tatemono Investment Advisors Co., Ltd. | F26: =VLOOKUP(MID(H26,SEARCH("@",H26,1),LEN(H26)-SEARCH("@",H26,1)+1),[2]Sheet1!$D:$F,3,FALSE) -> M0239 | G26: Corporate Planning Department Senior Manager | H26: kondokn@tt-ia.com | I26: -6821 | J26: Japan | K26: JPY | M26: 1 | P26: 6140 | Q26: 2622 | T26: 125 | V26: 8887 | AC26: 0 | AJ26: 0 | AQ26: 0 | AX26: 0 | BE26: 0 | BF26: 6140 | BG26: 2622 | BH26: 0 | BI26: 0 | BJ26: 125 | BK26: 0 | BL26: 8887 | BM26: 1 | BN26: 1 | BQ26: 1 | BS26: 3 | BZ26: 0 | CG26: 0 | CN26: 0 | CU26: 0 | DB26: 0 | DC26: 1 | DD26: 1 | DE26: 0 | DF26: 0 | DG26: 1 | DH26: 0 | DI26: 3 | DJ26: YES | DK26: YES | DL26: NO | DM26: NO | DN26: YES | DO26: NO | DP26: NO | DQ26: NO | DR26: NO | DS26: NO | DT26: NO | DU26: NO | DV26: NO | DW26: NO | DX26: NO | DY26: NO | DZ26: NO | EA26: NO | EB26: NO | EC26: NO | ED26: NO | EE26: NO | EF26: NO | EG26: NO | EH26: NO | EI26: NO | EJ26: NO | EK26: NO | EL26: NO | EM26: NO | EN26: NO | EO26: NO | EP26: NO | EQ26: NO | ER26: NO | ES26: NO | EZ26: 0 | FA26: 512 | FG26: 512 | FN26: 0 | FU26: 0 | GB26: 0 | GI26: 0 | GP26: 0 | GQ26: Corporations/Banks | GR26: 5628 | GS26: 2622 | GV26: 125 | GX26: 8375 | GY26: 6140 | GZ26: 2622 | HA26: 0 | HB26: 0 | HC26: 125 | HD26: 0 | HE26: 8887 | HF26: 6140 | HG26: 2622 | HJ26: 125 | HL26: 8887 | HS26: 0 | HZ26: 0 | IG26: 0 | IN26: 0 | IO26: 6140 | IP26: 2622 | IQ26: 0 | IR26: 0 | IS26: 125 | IT26: 0 | IU26: 8887 | IV26: 99 | IX26: 1 | JA26: 3 | JB26: 3 | JC26: 1 | JD26: START Asia Pacific: | JK26: 0 | JL26: 512 | JR26: 512 | JY26: 0 | KF26: 0 | KM26: 0 | KT26: 0 | LA26: 0 | LB26: Corporations/Banks | LC26: 5628 | LD26: 2622 | LG26: 125 | LI26: 8375 | LJ26: 6140 | LK26: 2622 | LL26: 0 | LM26: 0 | LN26: 125 | LO26: 0 | LP26: 8887 | LW26: 0 | LX26: 6140 | LY26: 2622 | MB26: 125 | MD26: 8887 | MK26: 0 | MR26: 0 | MY26: 0 | MZ26: 6140 | NA26: 2622 | NB26: 0 | NC26: 0 | ND26: 125 | NE26: 0 | NF26: 8887 | NG26: START Europe: | RJ26: START North America: | VM26: START Global: | ZP26: START SOUTH America: | ADS26: START Africa:
A27: 74 | B27: ANREV | C27: 42780 | D27: Nicholas Harris | E27: The GPT Group | F27: =VLOOKUP(MID(H27,SEARCH("@",H27,1),LEN(H27)-SEARCH("@",H27,1)+1),[2]Sheet1!$D:$F,3,FALSE) -> M0075 | G27: Head of Funds Management, Group Strategy & Research | H27: nicholas.harris@gpt.com.au | I27: 61282393780 | J27: Australia | K27: AUD | M27: 2 | N27: 6 | O27: No new equity required in 2016 | V27: 0 | AC27: 0 | AJ27: 0 | AQ27: 0 | AX27: 0 | BE27: 0 | BF27: 0 | BG27: 0 | BH27: 0 | BI27: 0 | BJ27: 0 | BK27: 0 | BL27: 0 | BS27: 0 | BZ27: 0 | CG27: 0 | CN27: 0 | CU27: 0 | DB27: 0 | DC27: 0 | DD27: 0 | DE27: 0 | DF27: 0 | DG27: 0 | DH27: 0 | DI27: 0 | DJ27: NO | DK27: NO | DL27: NO | DM27: NO | DN27: NO | DO27: NO | DP27: NO | DQ27: NO | DR27: NO | DS27: NO | DT27: NO | DU27: NO | DV27: NO | DW27: NO | DX27: NO | DY27: NO | DZ27: NO | EA27: NO | EB27: NO | EC27: NO | ED27: NO | EE27: NO | EF27: NO | EG27: NO | EH27: NO | EI27: NO | EJ27: NO | EK27: NO | EL27: NO | EM27: NO | EN27: NO | EO27: NO | EP27: NO | EQ27: NO | ER27: NO | ES27: NO | EZ27: 0 | FG27: 0 | FN27: 0 | FU27: 0 | GB27: 0 | GI27: 0 | GP27: 0 | GX27: 0 | GY27: 0 | GZ27: 0 | HA27: 0 | HB27: 0 | HC27: 0 | HD27: 0 | HE27: 0 | HL27: 0 | HS27: 0 | HZ27: 0 | IG27: 0 | IN27: 0 | IO27: 0 | IP27: 0 | IQ27: 0 | IR27: 0 | IS27: 0 | IT27: 0 | IU27: 0 | JA27: 1 | JB27: 2 | JC27: 1 | JD27: START Asia Pacific: | NG27: START Europe: | RJ27: START North America: | VM27: START Global: | ZP27: START SOUTH America: | ADS27: START Africa:
A28: 182 | B28: ANREV | C28: 42774.168 | D28: Chui Hong Tai | E28: Chelsfield Asia | F28: =VLOOKUP(MID(H28,SEARCH("@",H28,1),LEN(H28)-SEARCH("@",H28,1)+1),[2]Sheet1!$D:$F,3,FALSE) -> M0271 | G28: Investment manager | H28: lchui@chlesfield.com | I28: 60888301 | J28: Hong Kong | K28: USD | M28: 1 | P28: 100 | V28: 100 | AC28: 0 | AJ28: 0 | AQ28: 0 | AX28: 0 | BE28: 0 | BF28: 100 | BG28: 0 | BH28: 0 | BI28: 0 | BJ28: 0 | BK28: 0 | BL28: 100 | BM28: 1 | BS28: 1 | BZ28: 0 | CG28: 0 | CN28: 0 | CU28: 0 | DB28: 0 | DC28: 1 | DD28: 0 | DE28: 0 | DF28: 0 | DG28: 0 | DH28: 0 | DI28: 1 | DJ28: YES | DK28: NO | DL28: NO | DM28: NO | DN28: NO | DO28: NO | DP28: NO | DQ28: NO | DR28: NO | DS28: NO | DT28: NO | DU28: NO | DV28: NO | DW28: NO | DX28: NO | DY28: NO | DZ28: NO | EA28: NO | EB28: NO | EC28: NO | ED28: NO | EE28: NO | EF28: NO | EG28: NO | EH28: NO | EI28: NO | EJ28: NO | EK28: NO | EL28: NO | EM28: NO | EN28: NO | EO28: NO | EP28: NO | EQ28: NO | ER28: NO | ES28: NO | EZ28: 0 | FG28: 0 | FN28: 0 | FU28: 0 | GB28: 0 | GI28: 0 | GJ28: 100 | GP28: 100 | GX28: 0 | GY28: 100 | GZ28: 0 | HA28: 0 | HB28: 0 | HC28: 0 | HD28: 0 | HE28: 100 | HF28: 100 | HL28: 100 | HS28: 0 | HZ28: 0 | IG28: 0 | IN28: 0 | IO28: 100 | IP28: 0 | IQ28: 0 | IR28: 0 | IS28: 0 | IT28: 0 | IU28: 100 | IV28: 0 | IW28: 0 | IX28: 100 | JA28: 2 | JB28: 3 | JC28: 1 | JD28: START Asia Pacific: | JK28: 0 | JR28: 0 | JY28: 0 | KF28: 0 | KM28: 0 | KT28: 0 | KU28: 100 | LA28: 100 | LI28: 0 | LJ28: 100 | LK28: 0 | LL28: 0 | LM28: 0 | LN28: 0 | LO28: 0 | LP28: 100 | LW28: 0 | LX28: 100 | MD28: 100 | MK28: 0 | MR28: 0 | MY28: 0 | MZ28: 100 | NA28: 0 | NB28: 0 | NC28: 0 | ND28: 0 | NE28: 0 | NF28: 100 | NG28: START Europe: | RJ28: START North America: | VM28: START Global: | ZP28: START SOUTH America: | ADS28: START Africa:
A29: 92 | B29: ANREV | C29: 42773.09 | D29: Simon Redman | E29: Invesco Real Estate | F29: =VLOOKUP(MID(H29,SEARCH("@",H29,1),LEN(H29)-SEARCH("@",H29,1)+1),[2]Sheet1!$D:$F,3,FALSE) -> M114 | G29: MD, Global Head of Product Management | H29: simon.redman@invesco.com | I29: +44 2075 433 584 | J29: United States | K29: USD | M29: 1 | P29: 95 | V29: 95 | W29: 748.56 | X29: 742.38 | AC29: 1490.94 | AD29: 994.5 | AE29: 1644.25 | AJ29: 2638.75 | AK29: 15 | AL29: 1101.34 | AQ29: 1116.34 | AX29: 0 | BE29: 0 | BF29: 1853.06 | BG29: 3487.97 | BH29: 0 | BI29: 0 | BJ29: 0 | BK29: 0 | BL29: 5341.03 | BM29: 1 | BS29: 1 | BT29: 3 | BU29: 7 | BZ29: 10 | CA29: 3 | CB29: 9 | CG29: 12 | CH29: 1 | CI29: 2 | CN29: 3 | CU29: 0 | DB29: 0 | DC29: 8 | DD29: 18 | DE29: 0 | DF29: 0 | DG29: 0 | DH29: 0 | DI29: 26 | DJ29: YES | DK29: NO | DL29: NO | DM29: NO | DN29: NO | DO29: NO | DP29: YES | DQ29: YES | DR29: NO | DS29: NO | DT29: NO | DU29: NO | DV29: YES | DW29: YES | DX29: NO | DY29: NO | DZ29: NO | EA29: NO | EB29: YES | EC29: YES | ED29: NO | EE29: NO | EF29: NO | EG29: NO | EH29: NO | EI29: NO | EJ29: NO | EK29: NO | EL29: NO | EM29: NO | EN29: NO | EO29: NO | EP29: NO | EQ29: NO | ER29: NO | ES29: NO | ET29: 1159.77 | EU29: 1702.36 | EZ29: 2862.13 | FA29: 63.98 | FG29: 63.98 | FH29: 203.05 | FI29: 1639.05 | FN29: 1842.1 | FU29: 0 | FV29: 27.57 | GB29: 27.57 | GC29: 259.04 | GI29: 259.04 | GJ29: 3.5 | GP29: 3.5 | GQ29: incl. Corporate, Private Trust and Others | GR29: 136.16 | GS29: 146.55 | GX29: 282.71 | GY29: 1853.07 | GZ29: 3487.96 | HA29: 0 | HB29: 0 | HC29: 0 | HD29: 0 | HE29: 5341.03 | HF29: 382.04 | HG29: 1639.06 | HL29: 2021.1 | HM29: 916.52 | HN29: 753.22 | HS29: 1669.74 | HT29: 554.5 | HU29: 1095.69 | HZ29: 1650.19 | IG29: 0 | IN29: 0 | IO29: 1853.06 | IP29: 3487.97 | IQ29: 0 | IR29: 0 | IS29: 0 | IT29: 0 | IU29: 5341.03 | IV29: 0 | IW29: 0 | IX29: 100 | IZ29: 0 | JA29: 1 | JB29: 2 | JC29: 1 | JD29: START Asia Pacific: | JE29: 50 | JK29: 50 | JR29: 0 | JY29: 0 | KF29: 0 | KM29: 0 | KN29: 20 | KT29: 20 | LA29: 0 | LB29: Corporate | LC29: 25 | LI29: 25 | LJ29: 95 | LK29: 0 | LL29: 0 | LM29: 0 | LN29: 0 | LO29: 0 | LP29: 95 | LQ29: 75 | LW29: 75 | MD29: 0 | ME29: 20 | MK29: 20 | MR29: 0 | MY29: 0 | MZ29: 95 | NA29: 0 | NB29: 0 | NC29: 0 | ND29: 0 | NE29: 0 | NF29: 95 | NG29: START Europe: | NH29: 377.87 | NI29: 690.83 | NN29: 1068.7 | NO29: 61.98 | NU29: 61.98 | NV29: 53.04 | OB29: 53.04 | OI29: 0 | OJ29: 27.57 | OP29: 27.57 | OQ29: 121.74 | OW29: 121.74 | PD29: 0 | PF29: 106.36 | PG29: 51.55 | PL29: 157.91 | PM29: 748.56 | PN29: 742.38 | PO29: 0 | PP29: 0 | PQ29: 0 | PR29: 0 | PS29: 1490.94 | PT29: 684.91 | PU29: 682.38 | PZ29: 1367.29 | QA29: 47.04 | QG29: 47.04 | QH29: 16.61 | QI29: 60 | QN29: 76.61 | QU29: 0 | RB29: 0 | RC29: 748.56 | RD29: 742.38 | RE29: 0 | RF29: 0 | RG29: 0 | RH29: 0 | RI29: 1490.94 | RJ29: START North America: | RK29: 716.9 | RL29: 940.69 | RQ29: 1657.59 | RR29: 2 | RX29: 2 | RY29: 150 | RZ29: 608.56 | SE29: 758.56 | SL29: 0 | SS29: 0 | ST29: 117.3 | SZ29: 117.3 | TA29: 3.5 | TG29: 3.5 | TI29: 4.8 | TJ29: 95 | TO29: 99.8 | TP29: 994.5 | TQ29: 1644.25 | TR29: 0 | TS29: 0 | TT29: 0 | TU29: 0 | TV29: 2638.75 | TW29: 140 | UC29: 140 | UD29: 335 | UE29: 608.56 | UJ29: 943.56 | UK29: 519.5 | UL29: 1035.69 | UQ29: 1555.19 | UX29: 0 | VE29: 0 | VF29: 994.5 | VG29: 1644.25 | VH29: 0 | VI29: 0 | VJ29: 0 | VK29: 0 | VL29: 2638.75 | VM29: START Global: | VN29: 15 | VO29: 70.84 | VT29: 85.84 | WA29: 0 | WC29: 1030.5 | WH29: 1030.5 | WO29: 0 | WV29: 0 | XC29: 0 | XJ29: 0 | XR29: 0 | XS29: 15 | XT29: 1101.34 | XU29: 0 | XV29: 0 | XW29: 0 | XX29: 0 | XY29: 1116.34 | YA29: 70.84 | YF29: 70.84 | YH29: 1030.5 | YM29: 1030.5 | YN29: 15 | YT29: 15 | ZA29: 0 | ZH29: 0 | ZI29: 15 | ZJ29: 1101.34 | ZK29: 0 | ZL29: 0 | ZM29: 0 | ZN29: 0 | ZO29: 1116.34 | ZP29: START SOUTH America: | ADS29: START Africa:
A30: 84 | B30: ANREV | C30: 42780 | D30: Martijn van Eldik | E30: Morgan Stanley Real Estate Investing | F30: =VLOOKUP(MID(H30,SEARCH("@",H30,1),LEN(H30)-SEARCH("@",H30,1)+1),[2]Sheet1!$D:$F,3,FALSE) -> M0045 | G30: na | H30: martijn.van.eldik@morganstanley.com | I30: +65 6834-6338 | J30: United States | K30: USD | M30: 1 | P30: 258 | V30: 258 | X30: 746 | AC30: 746 | AD30: 1950 | AJ30: 1950 | AQ30: 0 | AX30: 0 | BE30: 0 | BF30: 2208 | BG30: 746 | BH30: 0 | BI30: 0 | BJ30: 0 | BK30: 0 | BL30: 2954 | BM30: 1 | BS30: 1 | BU30: 1 | BZ30: 1 | CA30: 1 | CG30: 1 | CN30: 0 | CU30: 0 | DB30: 0 | DC30: 2 | DD30: 1 | DE30: 0 | DF30: 0 | DG30: 0 | DH30: 0 | DI30: 3 | DJ30: YES | DK30: NO | DL30: NO | DM30: NO | DN30: NO | DO30: NO | DP30: NO | DQ30: YES | DR30: NO | DS30: NO | DT30: NO | DU30: NO | DV30: YES | DW30: NO | DX30: NO | DY30: NO | DZ30: NO | EA30: NO | EB30: NO | EC30: NO | ED30: NO | EE30: NO | EF30: NO | EG30: NO | EH30: NO | EI30: NO | EJ30: NO | EK30: NO | EL30: NO | EM30: NO | EN30: NO | EO30: NO | EP30: NO | EQ30: NO | ER30: NO | ES30: NO | ET30: 800 | EZ30: 800 | FA30: 68 | FB30: 107 | FG30: 175 | FN30: 0 | FO30: 66 | FP30: 639 | FU30: 705 | FV30: 129 | GB30: 129 | GI30: 0 | GP30: 0 | GR30: 1145 | GX30: 1145 | GY30: 2208 | GZ30: 746 | HA30: 0 | HB30: 0 | HC30: 0 | HD30: 0 | HE30: 2954 | HF30: 40 | HG30: 639 | HL30: 679 | HM30: 426 | HN30: 107 | HS30: 533 | HT30: 1742 | HZ30: 1742 | IG30: 0 | IN30: 0 | IO30: 2208 | IP30: 746 | IQ30: 0 | IR30: 0 | IS30: 0 | IT30: 0 | IU30: 2954 | IX30: 100 | JA30: 3 | JB30: 3 | JC30: 1 | JD30: START Asia Pacific: | JE30: 200 | JK30: 200 | JR30: 0 | JY30: 0 | JZ30: 58 | KF30: 58 | KM30: 0 | KT30: 0 | LA30: 0 | LI30: 0 | LJ30: 258 | LK30: 0 | LL30: 0 | LM30: 0 | LN30: 0 | LO30: 0 | LP30: 258 | LQ30: 258 | LW30: 258 | MD30: 0 | MK30: 0 | MR30: 0 | MY30: 0 | MZ30: 258 | NA30: 0 | NB30: 0 | NC30: 0 | ND30: 0 | NE30: 0 | NF30: 258 | NG30: START Europe: | NN30: 0 | NP30: 107 | NU30: 107 | OB30: 0 | OD30: 639 | OI30: 639 | OP30: 0 | OW30: 0 | PD30: 0 | PL30: 0 | PM30: 0 | PN30: 746 | PO30: 0 | PP30: 0 | PQ30: 0 | PR30: 0 | PS30: 746 | PU30: 107 | PZ30: 107 | QB30: 639 | QG30: 639 | QN30: 0 | QU30: 0 | RB30: 0 | RC30: 0 | RD30: 746 | RE30: 0 | RF30: 0 | RG30: 0 | RH30: 0 | RI30: 746 | RJ30: START North America: | RK30: 600 | RQ30: 600 | RR30: 68 | RX30: 68 | SE30: 0 | SF30: 8 | SL30: 8 | SM30: 129 | SS30: 129 | SZ30: 0 | TG30: 0 | TI30: 1145 | TO30: 1145 | TP30: 1950 | TQ30: 0 | TR30: 0 | TS30: 0 | TT30: 0 | TU30: 0 | TV30: 1950 | TW30: 168 | UC30: 168 | UD30: 40 | UJ30: 40 | UK30: 1742 | UQ30: 1742 | UX30: 0 | VE30: 0 | VF30: 1950 | VG30: 0 | VH30: 0 | VI30: 0 | VJ30: 0 | VK30: 0 | VL30: 1950 | VM30: START Global: | ZP30: START SOUTH America: | ADS30: START Africa:
A31: 183 | B31: ANREV | C31: 42774.283 | D31: James Fung | E31: CITIC Capital Holdings Limited | F31: =VLOOKUP(MID(H31,SEARCH("@",H31,1),LEN(H31)-SEARCH("@",H31,1)+1),[2]Sheet1!$D:$F,3,FALSE) -> M0107 | G31: Executive Director | H31: jfung@citiccapital.com | I31: 37106834 | J31: Hong Kong | K31: USD | M31: 1 | P31: 36 | V31: 36 | W31: 79 | AC31: 79 | AJ31: 0 | AQ31: 0 | AX31: 0 | BE31: 0 | BF31: 115 | BG31: 0 | BH31: 0 | BI31: 0 | BJ31: 0 | BK31: 0 | BL31: 115 | BM31: 1 | BS31: 1 | BT31: 2 | BZ31: 2 | CG31: 0 | CN31: 0 | CU31: 0 | DB31: 0 | DC31: 3 | DD31: 0 | DE31: 0 | DF31: 0 | DG31: 0 | DH31: 0 | DI31: 3 | DJ31: YES | DK31: NO | DL31: NO | DM31: NO | DN31: NO | DO31: NO | DP31: YES | DQ31: NO | DR31: NO | DS31: NO | DT31: NO | DU31: NO | DV31: NO | DW31: NO | DX31: NO | DY31: NO | DZ31: NO | EA31: NO | EB31: NO | EC31: NO | ED31: NO | EE31: NO | EF31: NO | EG31: NO | EH31: NO | EI31: NO | EJ31: NO | EK31: NO | EL31: NO | EM31: NO | EN31: NO | EO31: NO | EP31: NO | EQ31: NO | ER31: NO | ES31: NO | EZ31: 0 | FA31: 25 | FG31: 25 | FN31: 0 | FU31: 0 | GB31: 0 | GI31: 0 | GP31: 0 | GQ31: Corporations | GR31: 90 | GX31: 90 | GY31: 115 | GZ31: 0 | HA31: 0 | HB31: 0 | HC31: 0 | HD31: 0 | HE31: 115 | HF31: 115 | HL31: 115 | HS31: 0 | HZ31: 0 | IG31: 0 | IN31: 0 | IO31: 115 | IP31: 0 | IQ31: 0 | IR31: 0 | IS31: 0 | IT31: 0 | IU31: 115 | IX31: 100 | JA31: 1 | JB31: 2 | JC31: 1 | JD31: START Asia Pacific: | JK31: 0 | JR31: 0 | JY31: 0 | KF31: 0 | KM31: 0 | KT31: 0 | LA31: 0 | LB31: corporations | LC31: 36 | LI31: 36 | LJ31: 36 | LK31: 0 | LL31: 0 | LM31: 0 | LN31: 0 | LO31: 0 | LP31: 36 | LW31: 0 | LX31: 36 | MD31: 36 | MK31: 0 | MR31: 0 | MY31: 0 | MZ31: 36 | NA31: 0 | NB31: 0 | NC31: 0 | ND31: 0 | NE31: 0 | NF31: 36 | NG31: START Europe: | RJ31: START North America: | VM31: START Global: | ZP31: START SOUTH America: | ADS31: START Africa:
A32: 116 | B32: ANREV | C32: 42760.326 | D32: Cheah Ying Soon | E32: ARA Asset Management Limited | F32: =VLOOKUP(MID(H32,SEARCH("@",H32,1),LEN(H32)-SEARCH("@",H32,1)+1),[2]Sheet1!$D:$F,3,FALSE) -> M0222 | G32: Director, Portfolio Management | H32: yingsooncheah@ara.com.hk | I32: 65 6835 9232 | J32: Singapore | K32: USD | M32: 1 | Q32: 497 | S32: 1699 | V32: 2196 | AC32: 0 | AJ32: 0 | AQ32: 0 | AX32: 0 | BE32: 0 | BF32: 0 | BG32: 497 | BH32: 0 | BI32: 1699 | BJ32: 0 | BK32: 0 | BL32: 2196 | BN32: 1 | BP32: 1 | BS32: 2 | BZ32: 0 | CG32: 0 | CN32: 0 | CU32: 0 | DB32: 0 | DC32: 0 | DD32: 1 | DE32: 0 | DF32: 1 | DG32: 0 | DH32: 0 | DI32: 2 | DJ32: NO | DK32: YES | DL32: NO | DM32: YES | DN32: NO | DO32: NO | DP32: NO | DQ32: NO | DR32: NO | DS32: NO | DT32: NO | DU32: NO | DV32: NO | DW32: NO | DX32: NO | DY32: NO | DZ32: NO | EA32: NO | EB32: NO | EC32: NO | ED32: NO | EE32: NO | EF32: NO | EG32: NO | EH32: NO | EI32: NO | EJ32: NO | EK32: NO | EL32: NO | EM32: NO | EN32: NO | EO32: NO | EP32: NO | EQ32: NO | ER32: NO | ES32: NO | EU32: 497 | EZ32: 497 | FD32: 1274 | FG32: 1274 | FK32: 425 | FN32: 425 | FU32: 0 | GB32: 0 | GI32: 0 | GP32: 0 | GX32: 0 | GY32: 0 | GZ32: 497 | HA32: 0 | HB32: 1699 | HC32: 0 | HD32: 0 | HE32: 2196 | HI32: 1699 | HL32: 1699 | HS32: 0 | HU32: 497 | HZ32: 497 | IG32: 0 | IN32: 0 | IO32: 0 | IP32: 497 | IQ32: 0 | IR32: 1699 | IS32: 0 | IT32: 0 | IU32: 2196 | IX32: 100 | JA32: 1 | JB32: 3 | JC32: 1 | JD32: START Asia Pacific: | JF32: 497 | JK32: 497 | JO32: 1274 | JR32: 1274 | JV32: 425 | JY32: 425 | KF32: 0 | KM32: 0 | KT32: 0 | LA32: 0 | LI32: 0 | LJ32: 0 | LK32: 497 | LL32: 0 | LM32: 1699 | LN32: 0 | LO32: 0 | LP32: 2196 | LW32: 0 | MA32: 1699 | MD32: 1699 | MF32: 497 | MK32: 497 | MR32: 0 | MY32: 0 | MZ32: 0 | NA32: 497 | NB32: 0 | NC32: 1699 | ND32: 0 | NE32: 0 | NF32: 2196 | NG32: START Europe: | RJ32: START North America: | VM32: START Global: | ZP32: START SOUTH America: | ADS32: START Africa:
A33: 85 | B33: ANREV | C33: 42780 | D33: Meghan Lakeland | E33: PGIM Real Estate | F33: =VLOOKUP(MID(H33,SEARCH("@",H33,1),LEN(H33)-SEARCH("@",H33,1)+1),[2]Sheet1!$D:$F,3,FALSE) -> M03210 | G33: Vice President, Business Development | H33: meghan.lakeland@gmail.com | I33: 9737341461 | J33: United States | K33: USD | M33: 1 | P33: 162 | Q33: 476 | V33: 638 | W33: 601 | X33: 174 | AB33: 694 | AC33: 1469 | AD33: 302 | AE33: 275 | AJ33: 577 | AK33: 15 | AQ33: 15 | AX33: 0 | BE33: 0 | BF33: 1080 | BG33: 925 | BH33: 0 | BI33: 0 | BJ33: 0 | BK33: 694 | BL33: 2699 | BM33: 2 | BN33: 1 | BS33: 3 | BT33: 3 | BU33: 1 | BY33: 2 | BZ33: 6 | CA33: 3 | CB33: 1 | CG33: 4 | CH33: 1 | CN33: 1 | CU33: 0 | DB33: 0 | DC33: 9 | DD33: 3 | DE33: 0 | DF33: 0 | DG33: 0 | DH33: 2 | DI33: 14 | DJ33: YES | DK33: YES | DL33: NO | DM33: NO | DN33: NO | DO33: NO | DP33: YES | DQ33: YES | DR33: NO | DS33: NO | DT33: NO | DU33: YES | DV33: YES | DW33: YES | DX33: NO | DY33: NO | DZ33: NO | EA33: NO | EB33: YES | EC33: NO | ED33: NO | EE33: NO | EF33: NO | EG33: NO | EH33: NO | EI33: NO | EJ33: NO | EK33: NO | EL33: NO | EM33: NO | EN33: NO | EO33: NO | EP33: NO | EQ33: NO | ER33: NO | ES33: NO | ET33: 360 | EU33: 245 | EY33: 508 | EZ33: 1113 | FA33: 164 | FB33: 228 | FF33: 37 | FG33: 429 | FH33: 148 | FI33: 442 | FM33: 104 | FN33: 694 | FU33: 0 | FV33: 42 | GA33: 37 | GB33: 79 | GC33: 3 | GH33: 9 | GI33: 12 | GP33: 0 | GR33: 372 | GX33: 372 | GY33: 1089 | GZ33: 915 | HA33: 0 | HB33: 0 | HC33: 0 | HD33: 695 | HE33: 2699 | HF33: 137 | HG33: 34 | HK33: 15 | HL33: 186 | HM33: 675 | HN33: 453.69991 | HR33: 130 | HS33: 1274 | HT33: 277 | HU33: 413 | HY33: 549 | HZ33: 1239 | IG33: 0 | IN33: 0 | IO33: 1089 | IP33: 916 | IQ33: 0 | IR33: 0 | IS33: 0 | IT33: 694 | IU33: 2699 | IV33: 0.5 | IX33: 99.5 | JA33: 1 | JB33: 3 | JC33: 1 | JD33: START Asia Pacific: | NG33: START Europe: | RJ33: START North America: | VM33: START Global: | ZP33: START SOUTH America: | ADS33: START Africa:
A34: 91 | B34: ANREV | C34: 42780 | D34: Piramal Fund Management Pvt. Ltd | E34: Piramal Fund Management Pvt. Ltd | F34: =VLOOKUP(MID(H34,SEARCH("@",H34,1),LEN(H34)-SEARCH("@",H34,1)+1),[2]Sheet1!$D:$F,3,FALSE) -> N0292 | G34: Investor Relations | H34: investors@piramal.com | I34: 2261513460 | J34: India | K34: INR | M34: 1 | P34: 1420 | Q34: 840 | V34: 2260 | AC34: 0 | AJ34: 0 | AQ34: 0 | AX34: 0 | BE34: 0 | BF34: 1420 | BG34: 840 | BH34: 0 | BI34: 0 | BJ34: 0 | BK34: 0 | BL34: 2260 | BM34: 1 | BN34: 1 | BS34: 2 | BZ34: 0 | CG34: 0 | CN34: 0 | CU34: 0 | DB34: 0 | DC34: 1 | DD34: 1 | DE34: 0 | DF34: 0 | DG34: 0 | DH34: 0 | DI34: 2 | DJ34: YES | DK34: YES | DL34: NO | DM34: NO | DN34: NO | DO34: NO | DP34: NO | DQ34: NO | DR34: NO | DS34: NO | DT34: NO | DU34: NO | DV34: NO | DW34: NO | DX34: NO | DY34: NO | DZ34: NO | EA34: NO | EB34: NO | EC34: NO | ED34: NO | EE34: NO | EF34: NO | EG34: NO | EH34: NO | EI34: NO | EJ34: NO | EK34: NO | EL34: NO | EM34: NO | EN34: NO | EO34: NO | EP34: NO | EQ34: NO | ER34: NO | ES34: NO | EZ34: 0 | FG34: 0 | FN34: 0 | FU34: 0 | GB34: 0 | GI34: 0 | GJ34: 2260 | GP34: 2260 | GX34: 0 | GY34: 2260 | GZ34: 0 | HA34: 0 | HB34: 0 | HC34: 0 | HD34: 0 | HE34: 2260 | HF34: 1420 | HG34: 840 | HL34: 2260 | HS34: 0 | HZ34: 0 | IG34: 0 | IN34: 0 | IO34: 1420 | IP34: 840 | IQ34: 0 | IR34: 0 | IS34: 0 | IT34: 0 | IU34: 2260 | IV34: 100 | JA34: 1 | JB34: 1 | JC34: 2 | JD34: START Asia Pacific: | JK34: 0 | JR34: 0 | JY34: 0 | KF34: 0 | KM34: 0 | KT34: 0 | KU34: 2260 | LA34: 2260 | LI34: 0 | LJ34: 2260 | LK34: 0 | LL34: 0 | LM34: 0 | LN34: 0 | LO34: 0 | LP34: 2260 | LW34: 0 | LX34: 2260 | MD34: 2260 | MK34: 0 | MR34: 0 | MY34: 0 | MZ34: 2260 | NA34: 0 | NB34: 0 | NC34: 0 | ND34: 0 | NE34: 0 | NF34: 2260 | NG34: START Europe: | RJ34: START North America: | VM34: START Global: | ZP34: START SOUTH America: | ADS34: START Africa:
A35: 229 | B35: ANREV | C35: 42780 | D35: Peter Wylie | E35: Lendlease Investment Management | F35: =VLOOKUP(MID(H35,SEARCH("@",H35,1),LEN(H35)-SEARCH("@",H35,1)+1),[2]Sheet1!$D:$F,3,FALSE) -> M243 | G35: Business Development Manager - New Equity | H35: peter.wylie@lendlease.com | I35: 61477309659 | J35: Australia | K35: AUD | M35: 2 | N35: 6 | O35: No equity requirement | V35: 0 | AC35: 0 | AJ35: 0 | AQ35: 0 | AX35: 0 | BE35: 0 | BF35: 0 | BG35: 0 | BH35: 0 | BI35: 0 | BJ35: 0 | BK35: 0 | BL35: 0 | BS35: 0 | BZ35: 0 | CG35: 0 | CN35: 0 | CU35: 0 | DB35: 0 | DC35: 0 | DD35: 0 | DE35: 0 | DF35: 0 | DG35: 0 | DH35: 0 | DI35: 0 | DJ35: NO | DK35: NO | DL35: NO | DM35: NO | DN35: NO | DO35: NO | DP35: NO | DQ35: NO | DR35: NO | DS35: NO | DT35: NO | DU35: NO | DV35: NO | DW35: NO | DX35: NO | DY35: NO | DZ35: NO | EA35: NO | EB35: NO | EC35: NO | ED35: NO | EE35: NO | EF35: NO | EG35: NO | EH35: NO | EI35: NO | EJ35: NO | EK35: NO | EL35: NO | EM35: NO | EN35: NO | EO35: NO | EP35: NO | EQ35: NO | ER35: NO | ES35: NO | EZ35: 0 | FG35: 0 | FN35: 0 | FU35: 0 | GB35: 0 | GI35: 0 | GP35: 0 | GX35: 0 | GY35: 0 | GZ35: 0 | HA35: 0 | HB35: 0 | HC35: 0 | HD35: 0 | HE35: 0 | HL35: 0 | HS35: 0 | HZ35: 0 | IG35: 0 | IN35: 0 | IO35: 0 | IP35: 0 | IQ35: 0 | IR35: 0 | IS35: 0 | IT35: 0 | IU35: 0 | JA35: 1 | JB35: 1 | JC35: 1 | JD35: START Asia Pacific: | NG35: START Europe: | RJ35: START North America: | VM35: START Global: | ZP35: START SOUTH America: | ADS35: START Africa:
A36: 235 | B36: ANREV | C36: 42780 | D36: Ryota Nagao | E36: IDERA Capital Management Ltd | F36: =VLOOKUP(MID(H36,SEARCH("@",H36,1),LEN(H36)-SEARCH("@",H36,1)+1),[2]Sheet1!$D:$F,3,FALSE) -> M0124 | G36: Senior Manager | H36: ryota.nagao@idera-capital.com | I36: +81 3 5771 9055 | J36: Japan | K36: JPY | M36: 1 | S36: 25676 | V36: 25676 | AC36: 0 | AJ36: 0 | AQ36: 0 | AX36: 0 | BE36: 0 | BF36: 0 | BG36: 0 | BH36: 0 | BI36: 25676 | BJ36: 0 | BK36: 0 | BL36: 25676 | BP36: 1 | BS36: 1 | BZ36: 0 | CG36: 0 | CN36: 0 | CU36: 0 | DB36: 0 | DC36: 0 | DD36: 0 | DE36: 0 | DF36: 1 | DG36: 0 | DH36: 0 | DI36: 1 | DJ36: NO | DK36: NO | DL36: NO | DM36: YES | DN36: NO | DO36: NO | DP36: NO | DQ36: NO | DR36: NO | DS36: NO | DT36: NO | DU36: NO | DV36: NO | DW36: NO | DX36: NO | DY36: NO | DZ36: NO | EA36: NO | EB36: NO | EC36: NO | ED36: NO | EE36: NO | EF36: NO | EG36: NO | EH36: NO | EI36: NO | EJ36: NO | EK36: NO | EL36: NO | EM36: NO | EN36: NO | EO36: NO | EP36: NO | EQ36: NO | ER36: NO | ES36: NO | EW36: 24500 | EZ36: 24500 | FG36: 0 | FN36: 0 | FU36: 0 | GB36: 0 | GI36: 0 | GP36: 0 | GU36: 1176 | GX36: 1176 | GY36: 0 | GZ36: 0 | HA36: 0 | HB36: 25676 | HC36: 0 | HD36: 0 | HE36: 25676 | HI36: 1176 | HL36: 1176 | HP36: 24500 | HS36: 24500 | HZ36: 0 | IG36: 0 | IN36: 0 | IO36: 0 | IP36: 0 | IQ36: 0 | IR36: 25676 | IS36: 0 | IT36: 0 | IU36: 25676 | IW36: 95.2 | IZ36: 4.8 | JA36: 1 | JB36: 1 | JC36: 1 | JD36: START Asia Pacific: | JH36: 24500 | JK36: 24500 | JR36: 0 | JY36: 0 | KF36: 0 | KM36: 0 | KT36: 0 | LA36: 0 | LF36: 1176 | LI36: 1176 | LJ36: 0 | LK36: 0 | LL36: 0 | LM36: 25676 | LN36: 0 | LO36: 0 | LP36: 25676 | LT36: 24500 | LW36: 24500 | MA36: 1176 | MD36: 1176 | MK36: 0 | MR36: 0 | MY36: 0 | MZ36: 0 | NA36: 0 | NB36: 0 | NC36: 25676 | ND36: 0 | NE36: 0 | NF36: 25676 | NG36: START Europe: | RJ36: START North America: | VM36: START Global: | ZP36: START SOUTH America: | ADS36: START Africa:
A37: 75 | B37: ANREV | C37: 42772.365 | D37: John LEE | E37: Orion Partners Real Estate Group | F37: =VLOOKUP(MID(H37,SEARCH("@",H37,1),LEN(H37)-SEARCH("@",H37,1)+1),[2]Sheet1!$D:$F,3,FALSE) -> M0035 | G37: Partner and Head of Real Estate Group | H37: jlee@orionpartners.com | I37: +852 2218 2168 | J37: Hong Kong | K37: USD | M37: 1 | P37: 70 | Q37: 0 | R37: 0 | S37: 0 | T37: 0 | U37: 0 | V37: 70 | W37: 0 | X37: 0 | Y37: 0 | Z37: 0 | AA37: 0 | AB37: 0 | AC37: 0 | AD37: 0 | AE37: 0 | AF37: 0 | AG37: 0 | AH37: 0 | AI37: 0 | AJ37: 0 | AK37: 0 | AL37: 0 | AM37: 0 | AN37: 0 | AO37: 0 | AP37: 0 | AQ37: 0 | AR37: 0 | AS37: 0 | AT37: 0 | AU37: 0 | AV37: 0 | AW37: 0 | AX37: 0 | AY37: 0 | AZ37: 0 | BA37: 0 | BB37: 0 | BC37: 0 | BD37: 0 | BE37: 0 | BF37: 70 | BG37: 0 | BH37: 0 | BI37: 0 | BJ37: 0 | BK37: 0 | BL37: 70 | BM37: 1 | BS37: 1 | BZ37: 0 | CG37: 0 | CN37: 0 | CU37: 0 | DB37: 0 | DC37: 1 | DD37: 0 | DE37: 0 | DF37: 0 | DG37: 0 | DH37: 0 | DI37: 1 | DJ37: YES | DK37: NO | DL37: NO | DM37: NO | DN37: NO | DO37: NO | DP37: NO | DQ37: NO | DR37: NO | DS37: NO | DT37: NO | DU37: NO | DV37: NO | DW37: NO | DX37: NO | DY37: NO | DZ37: NO | EA37: NO | EB37: NO | EC37: NO | ED37: NO | EE37: NO | EF37: NO | EG37: NO | EH37: NO | EI37: NO | EJ37: NO | EK37: NO | EL37: NO | EM37: NO | EN37: NO | EO37: NO | EP37: NO | EQ37: NO | ER37: NO | ES37: NO | ET37: 70 | EZ37: 70 | FA37: 0 | FG37: 0 | FH37: 0 | FN37: 0 | FO37: 0 | FU37: 0 | FV37: 0 | GB37: 0 | GC37: 0 | GI37: 0 | GJ37: 0 | GP37: 0 | GR37: 0 | GX37: 0 | GY37: 70 | GZ37: 0 | HA37: 0 | HB37: 0 | HC37: 0 | HD37: 0 | HE37: 70 | HF37: 60 | HL37: 60 | HM37: 10 | HS37: 10 | HT37: 0 | HZ37: 0 | IA37: 0 | IG37: 0 | IH37: 0 | IN37: 0 | IO37: 70 | IP37: 0 | IQ37: 0 | IR37: 0 | IS37: 0 | IT37: 0 | IU37: 70 | IV37: 86 | IW37: 14 | IX37: 0 | IZ37: 0 | JA37: 1 | JB37: 3 | JC37: 1 | JD37: START Asia Pacific: | JE37: 70 | JK37: 70 | JL37: 0 | JR37: 0 | JS37: 0 | JY37: 0 | JZ37: 0 | KF37: 0 | KG37: 0 | KM37: 0 | KN37: 0 | KT37: 0 | KU37: 0 | LA37: 0 | LC37: 0 | LI37: 0 | LJ37: 70 | LK37: 0 | LL37: 0 | LM37: 0 | LN37: 0 | LO37: 0 | LP37: 70 | LQ37: 10 | LW37: 10 | LX37: 60 | MD37: 60 | ME37: 0 | MK37: 0 | ML37: 0 | MR37: 0 | MS37: 0 | MY37: 0 | MZ37: 70 | NA37: 0 | NB37: 0 | NC37: 0 | ND37: 0 | NE37: 0 | NF37: 70 | NG37: START Europe: | RJ37: START North America: | VM37: START Global: | ZP37: START SOUTH America: | ADS37: START Africa:
A38: 160 | B38: ANREV | C38: 42769.145 | D38: Tim Simpson | E38: Propertylink Group | F38: =VLOOKUP(MID(H38,SEARCH("@",H38,1),LEN(H38)-SEARCH("@",H38,1)+1),[2]Sheet1!$D:$F,3,FALSE) -> M0220 | G38: General Manager - Funds & Mandates | H38: tsimpson@propertylink.com.au | I38: +61 2 9186 4715 | J38: Australia | K38: AUD | M38: 1 | S38: 115 | V38: 115 | AC38: 0 | AJ38: 0 | AQ38: 0 | AX38: 0 | BE38: 0 | BF38: 0 | BG38: 0 | BH38: 0 | BI38: 115 | BJ38: 0 | BK38: 0 | BL38: 115 | BP38: 2 | BS38: 2 | BZ38: 0 | CG38: 0 | CN38: 0 | CU38: 0 | DB38: 0 | DC38: 0 | DD38: 0 | DE38: 0 | DF38: 2 | DG38: 0 | DH38: 0 | DI38: 2 | DJ38: NO | DK38: NO | DL38: NO | DM38: YES | DN38: NO | DO38: NO | DP38: NO | DQ38: NO | DR38: NO | DS38: NO | DT38: NO | DU38: NO | DV38: NO | DW38: NO | DX38: NO | DY38: NO | DZ38: NO | EA38: NO | EB38: NO | EC38: NO | ED38: NO | EE38: NO | EF38: NO | EG38: NO | EH38: NO | EI38: NO | EJ38: NO | EK38: NO | EL38: NO | EM38: NO | EN38: NO | EO38: NO | EP38: NO | EQ38: NO | ER38: NO | ES38: NO | EZ38: 0 | FG38: 0 | FN38: 0 | FU38: 0 | GB38: 0 | GI38: 0 | GP38: 0 | GQ38: Institutional Investors | GU38: 115 | GX38: 115 | GY38: 0 | GZ38: 0 | HA38: 0 | HB38: 115 | HC38: 0 | HD38: 0 | HE38: 115 | HI38: 23 | HL38: 23 | HP38: 40 | HS38: 40 | HW38: 52 | HZ38: 52 | IG38: 0 | IN38: 0 | IO38: 0 | IP38: 0 | IQ38: 0 | IR38: 115 | IS38: 0 | IT38: 0 | IU38: 115 | IX38: 100 | JA38: 1 | JB38: 3 | JC38: 1 | JD38: START Asia Pacific: | JK38: 0 | JR38: 0 | JY38: 0 | KF38: 0 | KM38: 0 | KT38: 0 | LA38: 0 | LB38: Institutional Investors | LF38: 115 | LI38: 115 | LJ38: 0 | LK38: 0 | LL38: 0 | LM38: 115 | LN38: 0 | LO38: 0 | LP38: 115 | LT38: 40 | LW38: 40 | MA38: 23 | MD38: 23 | MH38: 52 | MK38: 52 | MR38: 0 | MY38: 0 | MZ38: 0 | NA38: 0 | NB38: 0 | NC38: 115 | ND38: 0 | NE38: 0 | NF38: 115 | NG38: START Europe: | RJ38: START North America: | VM38: START Global: | ZP38: START SOUTH America: | ADS38: START Africa:
A39: 86 | B39: ANREV | C39: 42751.079 | D39: Irene Zabala | E39: ISPT Pty. Ltd | F39: =VLOOKUP(MID(H39,SEARCH("@",H39,1),LEN(H39)-SEARCH("@",H39,1)+1),[2]Sheet1!$D:$F,3,FALSE) -> M0269 | G39: Research Analyst, Investor Relations | H39: izabala@ispt.net.au | I39: 03 8601 6646 | J39: Australia | K39: AUD | M39: 1 | Q39: 620 | V39: 620 | AC39: 0 | AJ39: 0 | AQ39: 0 | AX39: 0 | BE39: 0 | BF39: 0 | BG39: 620 | BH39: 0 | BI39: 0 | BJ39: 0 | BK39: 0 | BL39: 620 | BN39: 2 | BS39: 2 | BZ39: 0 | CG39: 0 | CN39: 0 | CU39: 0 | DB39: 0 | DC39: 0 | DD39: 2 | DE39: 0 | DF39: 0 | DG39: 0 | DH39: 0 | DI39: 2 | DJ39: NO | DK39: YES | DL39: NO | DM39: NO | DN39: NO | DO39: NO | DP39: NO | DQ39: NO | DR39: NO | DS39: NO | DT39: NO | DU39: NO | DV39: NO | DW39: NO | DX39: NO | DY39: NO | DZ39: NO | EA39: NO | EB39: NO | EC39: NO | ED39: NO | EE39: NO | EF39: NO | EG39: NO | EH39: NO | EI39: NO | EJ39: NO | EK39: NO | EL39: NO | EM39: NO | EN39: NO | EO39: NO | EP39: NO | EQ39: NO | ER39: NO | ES39: NO | EU39: 620 | EZ39: 620 | FG39: 0 | FN39: 0 | FU39: 0 | GB39: 0 | GI39: 0 | GP39: 0 | GX39: 0 | GY39: 0 | GZ39: 620 | HA39: 0 | HB39: 0 | HC39: 0 | HD39: 0 | HE39: 620 | HG39: 620 | HL39: 620 | HS39: 0 | HZ39: 0 | IG39: 0 | IN39: 0 | IO39: 0 | IP39: 620 | IQ39: 0 | IR39: 0 | IS39: 0 | IT39: 0 | IU39: 620 | IX39: 100 | JA39: 3 | JB39: 2 | JC39: 1 | JD39: START Asia Pacific: | JF39: 620 | JK39: 620 | JR39: 0 | JY39: 0 | KF39: 0 | KM39: 0 | KT39: 0 | LA39: 0 | LI39: 0 | LJ39: 0 | LK39: 620 | LL39: 0 | LM39: 0 | LN39: 0 | LO39: 0 | LP39: 620 | LW39: 0 | LY39: 620 | MD39: 620 | MK39: 0 | MR39: 0 | MY39: 0 | MZ39: 0 | NA39: 620 | NB39: 0 | NC39: 0 | ND39: 0 | NE39: 0 | NF39: 620 | NG39: START Europe: | RJ39: START North America: | VM39: START Global: | ZP39: START SOUTH America: | ADS39: START Africa:
A40: 179 | B40: ANREV | C40: 42779.606 | D40: Nicholas Dempsey | E40: BlackRock | F40: =VLOOKUP(MID(H40,SEARCH("@",H40,1),LEN(H40)-SEARCH("@",H40,1)+1),[2]Sheet1!$D:$F,3,FALSE) -> M181 | G40: Analyst | H40: nicholas.dempsey@blackrock.com | I40: 2077432603 | J40: United States | K40: USD | M40: 1 | P40: 115.2 | Q40: 0 | R40: 0 | S40: 0 | T40: 0 | U40: 0 | V40: 115.2 | W40: 680.2 | X40: 0 | Y40: 0 | Z40: 0 | AA40: 0 | AB40: 0 | AC40: 680.2 | AD40: 103.3 | AE40: 185.8 | AF40: 0 | AG40: 0 | AH40: 0 | AI40: 315 | AJ40: 604.1 | AK40: 0 | AL40: 0 | AM40: 0 | AN40: 0 | AO40: 0 | AP40: 0 | AQ40: 0 | AR40: 0 | AS40: 0 | AT40: 0 | AU40: 0 | AV40: 0 | AW40: 0 | AX40: 0 | AY40: 0 | AZ40: 0 | BA40: 0 | BB40: 0 | BC40: 0 | BD40: 0 | BE40: 0 | BF40: 898.7 | BG40: 185.8 | BH40: 0 | BI40: 0 | BJ40: 0 | BK40: 315 | BL40: 1399.5 | BM40: 2 | BS40: 2 | BT40: 3 | BZ40: 3 | CA40: 1 | CB40: 4 | CF40: 1 | CG40: 6 | CN40: 0 | CU40: 0 | DB40: 0 | DC40: 6 | DD40: 4 | DE40: 0 | DF40: 0 | DG40: 0 | DH40: 1 | DI40: 11 | DJ40: YES | DK40: NO | DL40: NO | DM40: NO | DN40: NO | DO40: NO | DP40: YES | DQ40: NO | DR40: NO | DS40: NO | DT40: NO | DU40: NO | DV40: YES | DW40: YES | DX40: NO | DY40: NO | DZ40: NO | EA40: YES | EB40: NO | EC40: NO | ED40: NO | EE40: NO | EF40: NO | EG40: NO | EH40: NO | EI40: NO | EJ40: NO | EK40: NO | EL40: NO | EM40: NO | EN40: NO | EO40: NO | EP40: NO | EQ40: NO | ER40: NO | ES40: NO | ET40: 747.1 | EU40: 131.4 | EY40: 117.5 | EZ40: 996 | FA40: 91.8 | FF40: 125.5 | FG40: 217.3 | FM40: 54 | FN40: 54 | FU40: 0 | FV40: 8.8 | GB40: 8.8 | GC40: 15 | GH40: 18.1 | GI40: 33.1 | GP40: 0 | GR40: 90.3 | GS40: 0 | GX40: 90.3 | GY40: 953 | GZ40: 131.4 | HA40: 0 | HB40: 0 | HC40: 0 | HD40: 315.1 | HE40: 1399.5 | HF40: 56.7 | HK40: 94 | HL40: 150.7 | HM40: 429.3 | HS40: 429.3 | HT40: 467 | HU40: 131.4 | HY40: 221.1 | HZ40: 819.5 | IG40: 0 | IN40: 0 | IO40: 953 | IP40: 131.4 | IQ40: 0 | IR40: 0 | IS40: 0 | IT40: 315.1 | IU40: 1399.5 | IX40: 100 | JA40: 1 | JB40: 3 | JC40: 1 | JD40: START Asia Pacific: | JE40: 62 | JK40: 62 | JL40: 14.4 | JR40: 14.4 | JY40: 0 | KF40: 0 | KM40: 0 | KT40: 0 | LA40: 0 | LB40: Corporate | LC40: 38.8 | LI40: 38.8 | LJ40: 115.2 | LK40: 0 | LL40: 0 | LM40: 0 | LN40: 0 | LO40: 0 | LP40: 115.2 | LQ40: 57.2 | LW40: 57.2 | LX40: 15.7 | MD40: 15.7 | ME40: 42.3 | MK40: 42.3 | MR40: 0 | MY40: 0 | MZ40: 115.2 | NA40: 0 | NB40: 0 | NC40: 0 | ND40: 0 | NE40: 0 | NF40: 115.2 | NG40: START Europe: | NH40: 608.1 | NN40: 608.1 | NO40: 46.2 | NU40: 46.2 | OB40: 0 | OI40: 0 | OJ40: 8.8 | OP40: 8.8 | OW40: 0 | PD40: 0 | PF40: 17.1 | PL40: 17.1 | PM40: 680.2 | PN40: 0 | PO40: 0 | PP40: 0 | PQ40: 0 | PR40: 0 | PS40: 680.2 | PT40: 372.2 | PZ40: 372.2 | QG40: 0 | QH40: 308 | QN40: 308 | QU40: 0 | RB40: 0 | RC40: 680.2 | RD40: 0 | RE40: 0 | RF40: 0 | RG40: 0 | RH40: 0 | RI40: 680.2 | RJ40: START North America: | RK40: 77 | RL40: 131.4 | RP40: 117.5 | RQ40: 325.9 | RR40: 31.2 | RW40: 125.5 | RX40: 156.7 | SD40: 54 | SE40: 54 | SL40: 0 | SS40: 0 | ST40: 15 | SY40: 18.1 | SZ40: 33.1 | TG40: 0 | TI40: 34.4 | TO40: 34.4 | TP40: 157.6 | TQ40: 131.4 | TR40: 0 | TS40: 0 | TT40: 0 | TU40: 315.1 | TV40: 604.1 | UC40: 0 | UD40: 136.2 | UJ40: 136.2 | UK40: 467.9 | UQ40: 467.9 | UX40: 0 | VE40: 0 | VF40: 604.1 | VG40: 0 | VH40: 0 | VI40: 0 | VJ40: 0 | VK40: 0 | VL40: 604.1 | VM40: START Global: | ZP40: START SOUTH America: | ADS40: START Africa:
A41: 108 | B41: ANREV | C41: 42780 | D41: Zheng Wanshi | E41: CapitaLand Limited | F41: =VLOOKUP(MID(H41,SEARCH("@",H41,1),LEN(H41)-SEARCH("@",H41,1)+1),[2]Sheet1!$D:$F,3,FALSE) -> M0091 | G41: Head, Investment Management | H41: zheng.wanshi@capitaland.com | I41: 6713 3103 | J41: Singapore | K41: USD | M41: 1 | P41: 1500 | V41: 1500 | AC41: 0 | AJ41: 0 | AQ41: 0 | AX41: 0 | BE41: 0 | BF41: 1500 | BG41: 0 | BH41: 0 | BI41: 0 | BJ41: 0 | BK41: 0 | BL41: 1500 | BM41: 1 | BS41: 1 | BZ41: 0 | CG41: 0 | CN41: 0 | CU41: 0 | DB41: 0 | DC41: 1 | DD41: 0 | DE41: 0 | DF41: 0 | DG41: 0 | DH41: 0 | DI41: 1 | DJ41: YES | DK41: NO | DL41: NO | DM41: NO | DN41: NO | DO41: NO | DP41: NO | DQ41: NO | DR41: NO | DS41: NO | DT41: NO | DU41: NO | DV41: NO | DW41: NO | DX41: NO | DY41: NO | DZ41: NO | EA41: NO | EB41: NO | EC41: NO | ED41: NO | EE41: NO | EF41: NO | EG41: NO | EH41: NO | EI41: NO | EJ41: NO | EK41: NO | EL41: NO | EM41: NO | EN41: NO | EO41: NO | EP41: NO | EQ41: NO | ER41: NO | ES41: NO | ET41: 725 | EZ41: 725 | FG41: 0 | FH41: 100 | FN41: 100 | FU41: 0 | GB41: 0 | GI41: 0 | GP41: 0 | GQ41: Corporate and Financial Institutes | GR41: 675 | GX41: 675 | GY41: 1500 | GZ41: 0 | HA41: 0 | HB41: 0 | HC41: 0 | HD41: 0 | HE41: 1500 | HF41: 775 | HL41: 775 | HS41: 0 | HT41: 725 | HZ41: 725 | IG41: 0 | IN41: 0 | IO41: 1500 | IP41: 0 | IQ41: 0 | IR41: 0 | IS41: 0 | IT41: 0 | IU41: 1500 | IV41: 58 | IZ41: 42 | JA41: 1 | JB41: 2 | JC41: 1 | JD41: START Asia Pacific: | JE41: 725 | JK41: 725 | JR41: 0 | JS41: 100 | JY41: 100 | KF41: 0 | KM41: 0 | KT41: 0 | LA41: 0 | LB41: Corporates and Financial Institutes | LC41: 675 | LI41: 675 | LJ41: 1500 | LK41: 0 | LL41: 0 | LM41: 0 | LN41: 0 | LO41: 0 | LP41: 1500 | LW41: 0 | LX41: 775 | MD41: 775 | ME41: 725 | MK41: 725 | MR41: 0 | MY41: 0 | MZ41: 1500 | NA41: 0 | NB41: 0 | NC41: 0 | ND41: 0 | NE41: 0 | NF41: 1500 | NG41: START Europe: | RJ41: START North America: | VM41: START Global: | ZP41: START SOUTH America: | ADS41: START Africa:
A42: 96 | B42: ANREV | C42: 42751.05 | D42: Linh Pham | E42: EG Funds Management | F42: =VLOOKUP(MID(H42,SEARCH("@",H42,1),LEN(H42)-SEARCH("@",H42,1)+1),[2]Sheet1!$D:$F,3,FALSE) -> M0249 | G42: Analyst | H42: lpham@eg.com.au | I42: 02 92207027 | J42: Australia | K42: AUD | M42: 1 | R42: 520 | V42: 520 | AC42: 0 | AJ42: 0 | AQ42: 0 | AX42: 0 | BE42: 0 | BF42: 0 | BG42: 0 | BH42: 520 | BI42: 0 | BJ42: 0 | BK42: 0 | BL42: 520 | BO42: 2 | BS42: 2 | BZ42: 0 | CG42: 0 | CN42: 0 | CU42: 0 | DB42: 0 | DC42: 0 | DD42: 0 | DE42: 2 | DF42: 0 | DG42: 0 | DH42: 0 | DI42: 2 | DJ42: NO | DK42: NO | DL42: YES | DM42: NO | DN42: NO | DO42: NO | DP42: NO | DQ42: NO | DR42: NO | DS42: NO | DT42: NO | DU42: NO | DV42: NO | DW42: NO | DX42: NO | DY42: NO | DZ42: NO | EA42: NO | EB42: NO | EC42: NO | ED42: NO | EE42: NO | EF42: NO | EG42: NO | EH42: NO | EI42: NO | EJ42: NO | EK42: NO | EL42: NO | EM42: NO | EN42: NO | EO42: NO | EP42: NO | EQ42: NO | ER42: NO | ES42: NO | EV42: 503 | EZ42: 503 | FG42: 0 | FN42: 0 | FU42: 0 | GB42: 0 | GI42: 0 | GL42: 17 | GP42: 17 | GX42: 0 | GY42: 0 | GZ42: 0 | HA42: 520 | HB42: 0 | HC42: 0 | HD42: 0 | HE42: 520 | HH42: 505 | HL42: 505 | HO42: 15 | HS42: 15 | HZ42: 0 | IG42: 0 | IN42: 0 | IO42: 0 | IP42: 0 | IQ42: 520 | IR42: 0 | IS42: 0 | IT42: 0 | IU42: 520 | IX42: 100 | JA42: 1 | JB42: 2 | JC42: 1 | JD42: START Asia Pacific: | JG42: 503 | JK42: 503 | JR42: 0 | JY42: 0 | KF42: 0 | KM42: 0 | KT42: 0 | KW42: 17 | LA42: 17 | LI42: 0 | LJ42: 0 | LK42: 0 | LL42: 520 | LM42: 0 | LN42: 0 | LO42: 0 | LP42: 520 | LS42: 15 | LW42: 15 | LZ42: 505 | MD42: 505 | MK42: 0 | MR42: 0 | MY42: 0 | MZ42: 0 | NA42: 0 | NB42: 520 | NC42: 0 | ND42: 0 | NE42: 0 | NF42: 520 | NG42: START Europe: | RJ42: START North America: | VM42: START Global: | ZP42: START SOUTH America: | ADS42: START Africa:
A43: 231 | B43: ANREV | C43: 42780 | D43: Makiko Noda | E43: Japan | F43: =VLOOKUP(MID(H43,SEARCH("@",H43,1),LEN(H43)-SEARCH("@",H43,1)+1),[2]Sheet1!$D:$F,3,FALSE) -> M0007 | G43: Administration Dept. Dupty General Manager | H43: makiko.noda@mc-dream.com | I43: -8851 | J43: Japan | K43: JPY | M43: 1 | P43: 184246 | Q43: 38200 | R43: 5180 | S43: 2230 | T43: 0 | U43: 20878 | V43: 250734 | AC43: 0 | AJ43: 0 | AQ43: 0 | AX43: 0 | BE43: 0 | BF43: 184246 | BG43: 38200 | BH43: 5180 | BI43: 2230 | BJ43: 0 | BK43: 20878 | BL43: 250734 | BM43: 1 | BN43: 1 | BO43: 2 | BP43: 1 | BR43: 3 | BS43: 8 | BZ43: 0 | CG43: 0 | CN43: 0 | CU43: 0 | DB43: 0 | DC43: 1 | DD43: 1 | DE43: 2 | DF43: 1 | DG43: 0 | DH43: 3 | DI43: 8 | DJ43: YES | DK43: YES | DL43: YES | DM43: YES | DN43: NO | DO43: YES | DP43: NO | DQ43: NO | DR43: NO | DS43: NO | DT43: NO | DU43: NO | DV43: NO | DW43: NO | DX43: NO | DY43: NO | DZ43: NO | EA43: NO | EB43: NO | EC43: NO | ED43: NO | EE43: NO | EF43: NO | EG43: NO | EH43: NO | EI43: NO | EJ43: NO | EK43: NO | EL43: NO | EM43: NO | EN43: NO | EO43: NO | EP43: NO | EQ43: NO | ER43: NO | ES43: NO | ET43: 27637 | EY43: 5158 | EZ43: 32795 | FF43: 1205 | FG43: 1205 | FK43: 1784 | FN43: 1784 | FU43: 0 | GB43: 0 | GI43: 0 | GP43: 0 | GR43: 156609 | GS43: 38200 | GT43: 5180 | GU43: 446 | GW43: 14515 | GX43: 214950 | GY43: 184246 | GZ43: 38200 | HA43: 5180 | HB43: 2230 | HC43: 0 | HD43: 20878 | HE43: 250734 | HF43: 184264 | HG43: 38200 | HH43: 5180 | HI43: 2230 | HK43: 20878 | HL43: 250752 | HS43: 0 | HZ43: 0 | IG43: 0 | IN43: 0 | IO43: 184264 | IP43: 38200 | IQ43: 5180 | IR43: 2230 | IS43: 0 | IT43: 20878 | IU43: 250752 | IV43: 77 | IX43: 23 | JA43: 1 | JB43: 3 | JC43: 1 | JD43: START Asia Pacific: | JE43: 27637 | JJ43: 5158 | JK43: 32795 | JQ43: 1205 | JR43: 1205 | JV43: 1784 | JY43: 1784 | KF43: 0 | KM43: 0 | KT43: 0 | LA43: 0 | LC43: 156609 | LD43: 38200 | LE43: 5180 | LF43: 446 | LH43: 14515 | LI43: 214950 | LJ43: 184246 | LK43: 38200 | LL43: 5180 | LM43: 2230 | LN43: 0 | LO43: 20878 | LP43: 250734 | LW43: 0 | LX43: 18246 | LY43: 38200 | LZ43: 5180 | MA43: 2230 | MC43: 20878 | MD43: 84734 | MK43: 0 | MR43: 0 | MY43: 0 | MZ43: 18246 | NA43: 38200 | NB43: 5180 | NC43: 2230 | ND43: 0 | NE43: 20878 | NF43: 84734 | NG43: START Europe: | RJ43: START North America: | VM43: START Global: | ZP43: START SOUTH America: | ADS43: START Africa:
A44: 120 | B44: ANREV | C44: 42761.041 | D44: Minoru Yonekura | E44: Seven Seas Advisors Co. LTD. | F44: =VLOOKUP(MID(H44,SEARCH("@",H44,1),LEN(H44)-SEARCH("@",H44,1)+1),[2]Sheet1!$D:$F,3,FALSE) -> M0235 | G44: CEO | H44: minoru.yonekura@sevenseas-adv.com | I44: +813 3539 1490 | J44: Japan | K44: JPY | M44: 2 | N44: 6 | O44: limited opportunistic deal available | V44: 0 | AC44: 0 | AJ44: 0 | AQ44: 0 | AX44: 0 | BE44: 0 | BF44: 0 | BG44: 0 | BH44: 0 | BI44: 0 | BJ44: 0 | BK44: 0 | BL44: 0 | BS44: 0 | BZ44: 0 | CG44: 0 | CN44: 0 | CU44: 0 | DB44: 0 | DC44: 0 | DD44: 0 | DE44: 0 | DF44: 0 | DG44: 0 | DH44: 0 | DI44: 0 | DJ44: NO | DK44: NO | DL44: NO | DM44: NO | DN44: NO | DO44: NO | DP44: NO | DQ44: NO | DR44: NO | DS44: NO | DT44: NO | DU44: NO | DV44: NO | DW44: NO | DX44: NO | DY44: NO | DZ44: NO | EA44: NO | EB44: NO | EC44: NO | ED44: NO | EE44: NO | EF44: NO | EG44: NO | EH44: NO | EI44: NO | EJ44: NO | EK44: NO | EL44: NO | EM44: NO | EN44: NO | EO44: NO | EP44: NO | EQ44: NO | ER44: NO | ES44: NO | EZ44: 0 | FG44: 0 | FN44: 0 | FU44: 0 | GB44: 0 | GI44: 0 | GP44: 0 | GX44: 0 | GY44: 0 | GZ44: 0 | HA44: 0 | HB44: 0 | HC44: 0 | HD44: 0 | HE44: 0 | HL44: 0 | HS44: 0 | HZ44: 0 | IG44: 0 | IN44: 0 | IO44: 0 | IP44: 0 | IQ44: 0 | IR44: 0 | IS44: 0 | IT44: 0 | IU44: 0 | JA44: 1 | JB44: 3 | JC44: 1 | JD44: START Asia Pacific: | NG44: START Europe: | RJ44: START North America: | VM44: START Global: | ZP44: START SOUTH America: | ADS44: START Africa:
A45: 118 | B45: ANREV | C45: 42760.337 | D45: Markus Puusepp | E45: White Peak | F45: =VLOOKUP(MID(H45,SEARCH("@",H45,1),LEN(H45)-SEARCH("@",H45,1)+1),[2]Sheet1!$D:$F,3,FALSE) -> M0128 | G45: Head of Investor Relations | H45: markus.puusepp@wprei.com | I45: 85297392141 | J45: China | K45: CNY | M45: 1 | P45: 811 | V45: 811 | AC45: 0 | AJ45: 0 | AQ45: 0 | AX45: 0 | BE45: 0 | BF45: 811 | BG45: 0 | BH45: 0 | BI45: 0 | BJ45: 0 | BK45: 0 | BL45: 811 | BM45: 1 | BS45: 1 | BZ45: 0 | CG45: 0 | CN45: 0 | CU45: 0 | DB45: 0 | DC45: 1 | DD45: 0 | DE45: 0 | DF45: 0 | DG45: 0 | DH45: 0 | DI45: 1 | DJ45: YES | DK45: NO | DL45: NO | DM45: NO | DN45: NO | DO45: NO | DP45: NO | DQ45: NO | DR45: NO | DS45: NO | DT45: NO | DU45: NO | DV45: NO | DW45: NO | DX45: NO | DY45: NO | DZ45: NO | EA45: NO | EB45: NO | EC45: NO | ED45: NO | EE45: NO | EF45: NO | EG45: NO | EH45: NO | EI45: NO | EJ45: NO | EK45: NO | EL45: NO | EM45: NO | EN45: NO | EO45: NO | EP45: NO | EQ45: NO | ER45: NO | ES45: NO | ET45: 711 | EZ45: 711 | FG45: 0 | FN45: 0 | FU45: 0 | GB45: 0 | GI45: 0 | GJ45: 100 | GP45: 100 | GX45: 0 | GY45: 811 | GZ45: 0 | HA45: 0 | HB45: 0 | HC45: 0 | HD45: 0 | HE45: 811 | HL45: 0 | HM45: 811 | HS45: 811 | HZ45: 0 | IG45: 0 | IN45: 0 | IO45: 811 | IP45: 0 | IQ45: 0 | IR45: 0 | IS45: 0 | IT45: 0 | IU45: 811 | IV45: 100 | JA45: 2 | JB45: 2 | JC45: 1 | JD45: START Asia Pacific: | JE45: 811 | JK45: 811 | JR45: 0 | JY45: 0 | KF45: 0 | KM45: 0 | KT45: 0 | LA45: 0 | LI45: 0 | LJ45: 811 | LK45: 0 | LL45: 0 | LM45: 0 | LN45: 0 | LO45: 0 | LP45: 811 | LQ45: 811 | LW45: 811 | MD45: 0 | MK45: 0 | MR45: 0 | MY45: 0 | MZ45: 811 | NA45: 0 | NB45: 0 | NC45: 0 | ND45: 0 | NE45: 0 | NF45: 811 | NG45: START Europe: | RJ45: START North America: | VM45: START Global: | ZP45: START SOUTH America: | ADS45: START Africa:
A46: 241 | B46: ANREV | C46: 42780 | D46: TAJIMA MASAHIKO | E46: Kenedix, Inc. | F46: =VLOOKUP(MID(H46,SEARCH("@",H46,1),LEN(H46)-SEARCH("@",H46,1)+1),[2]Sheet1!$D:$F,3,FALSE) -> M0230 | G46: Director CFO Head of Corporate Planning | H46: masahiko_tajima@kenedix.com | I46: 81-3-5623-8460 | J46: Japan | K46: JPY | M46: 1 | P46: 100 | Q46: 300 | V46: 400 | AC46: 0 | AJ46: 0 | AQ46: 0 | AX46: 0 | BE46: 0 | BF46: 100 | BG46: 300 | BH46: 0 | BI46: 0 | BJ46: 0 | BK46: 0 | BL46: 400 | BM46: 2 | BN46: 3 | BS46: 5 | BZ46: 0 | CG46: 0 | CN46: 0 | CU46: 0 | DB46: 0 | DC46: 2 | DD46: 3 | DE46: 0 | DF46: 0 | DG46: 0 | DH46: 0 | DI46: 5 | DJ46: YES | DK46: YES | DL46: NO | DM46: NO | DN46: NO | DO46: NO | DP46: NO | DQ46: NO | DR46: NO | DS46: NO | DT46: NO | DU46: NO | DV46: NO | DW46: NO | DX46: NO | DY46: NO | DZ46: NO | EA46: NO | EB46: NO | EC46: NO | ED46: NO | EE46: NO | EF46: NO | EG46: NO | EH46: NO | EI46: NO | EJ46: NO | EK46: NO | EL46: NO | EM46: NO | EN46: NO | EO46: NO | EP46: NO | EQ46: NO | ER46: NO | ES46: NO | EZ46: 0 | FG46: 0 | FN46: 0 | FU46: 0 | GB46: 0 | GI46: 0 | GP46: 0 | GQ46: corporates/banks | GR46: 100 | GS46: 300 | GX46: 400 | GY46: 100 | GZ46: 300 | HA46: 0 | HB46: 0 | HC46: 0 | HD46: 0 | HE46: 400 | HF46: 100 | HG46: 300 | HL46: 400 | HS46: 0 | HZ46: 0 | IG46: 0 | IN46: 0 | IO46: 100 | IP46: 300 | IQ46: 0 | IR46: 0 | IS46: 0 | IT46: 0 | IU46: 400 | IV46: 10 | IX46: 90 | IZ46: 0 | JA46: 1 | JB46: 3 | JC46: 1 | JD46: START Asia Pacific: | JK46: 0 | JR46: 0 | JY46: 0 | KF46: 0 | KM46: 0 | KT46: 0 | LA46: 0 | LB46: Corporates/Banks | LC46: 100 | LD46: 300 | LI46: 400 | LJ46: 100 | LK46: 300 | LL46: 0 | LM46: 0 | LN46: 0 | LO46: 0 | LP46: 400 | LW46: 0 | LX46: 100 | LY46: 300 | MD46: 400 | MK46: 0 | MR46: 0 | MY46: 0 | MZ46: 100 | NA46: 300 | NB46: 0 | NC46: 0 | ND46: 0 | NE46: 0 | NF46: 400 | NG46: START Europe: | RJ46: START North America: | VM46: START Global: | ZP46: START SOUTH America: | ADS46: START Africa:
A47: 87 | B47: ANREV | C47: 42748.283 | D47: Saleh Afimiwalla | E47: IL&FS Investment Managers Limited | F47: =VLOOKUP(MID(H47,SEARCH("@",H47,1),LEN(H47)-SEARCH("@",H47,1)+1),[2]Sheet1!$D:$F,3,FALSE) -> M0258 | G47: Sr Managing Partner | H47: saleh.afimiwalla@ilfsindia.com | I47: +9122 26593539 | J47: India | K47: USD | M47: 2 | N47: 6 | O47: Completing exits in existing funds | V47: 0 | AC47: 0 | AJ47: 0 | AQ47: 0 | AX47: 0 | BE47: 0 | BF47: 0 | BG47: 0 | BH47: 0 | BI47: 0 | BJ47: 0 | BK47: 0 | BL47: 0 | BS47: 0 | BZ47: 0 | CG47: 0 | CN47: 0 | CU47: 0 | DB47: 0 | DC47: 0 | DD47: 0 | DE47: 0 | DF47: 0 | DG47: 0 | DH47: 0 | DI47: 0 | DJ47: NO | DK47: NO | DL47: NO | DM47: NO | DN47: NO | DO47: NO | DP47: NO | DQ47: NO | DR47: NO | DS47: NO | DT47: NO | DU47: NO | DV47: NO | DW47: NO | DX47: NO | DY47: NO | DZ47: NO | EA47: NO | EB47: NO | EC47: NO | ED47: NO | EE47: NO | EF47: NO | EG47: NO | EH47: NO | EI47: NO | EJ47: NO | EK47: NO | EL47: NO | EM47: NO | EN47: NO | EO47: NO | EP47: NO | EQ47: NO | ER47: NO | ES47: NO | EZ47: 0 | FG47: 0 | FN47: 0 | FU47: 0 | GB47: 0 | GI47: 0 | GP47: 0 | GX47: 0 | GY47: 0 | GZ47: 0 | HA47: 0 | HB47: 0 | HC47: 0 | HD47: 0 | HE47: 0 | HL47: 0 | HS47: 0 | HZ47: 0 | IG47: 0 | IN47: 0 | IO47: 0 | IP47: 0 | IQ47: 0 | IR47: 0 | IS47: 0 | IT47: 0 | IU47: 0 | JA47: 1 | JB47: 1 | JC47: 2 | JD47: START Asia Pacific: | NG47: START Europe: | RJ47: START North America: | VM47: START Global: | ZP47: START SOUTH America: | ADS47: START Africa:
A48: 97 | B48: ANREV | C48: 42780 | D48: Sarah McGeachie | E48: Fife Capital | F48: =VLOOKUP(MID(H48,SEARCH("@",H48,1),LEN(H48)-SEARCH("@",H48,1)+1),[2]Sheet1!$D:$F,3,FALSE) -> N0280 | G48: Executive | H48: sarah@sg.fifecapital.com | I48: 6592469260 | J48: Australia | K48: AUD | M48: 1 | P48: 150 | Q48: 300 | V48: 450 | AC48: 0 | AJ48: 0 | AQ48: 0 | AX48: 0 | BE48: 0 | BF48: 150 | BG48: 300 | BH48: 0 | BI48: 0 | BJ48: 0 | BK48: 0 | BL48: 450 | BM48: 1 | BN48: 2 | BS48: 3 | BZ48: 0 | CG48: 0 | CN48: 0 | CU48: 0 | DB48: 0 | DC48: 1 | DD48: 2 | DE48: 0 | DF48: 0 | DG48: 0 | DH48: 0 | DI48: 3 | DJ48: YES | DK48: YES | DL48: NO | DM48: NO | DN48: NO | DO48: NO | DP48: NO | DQ48: NO | DR48: NO | DS48: NO | DT48: NO | DU48: NO | DV48: NO | DW48: NO | DX48: NO | DY48: NO | DZ48: NO | EA48: NO | EB48: NO | EC48: NO | ED48: NO | EE48: NO | EF48: NO | EG48: NO | EH48: NO | EI48: NO | EJ48: NO | EK48: NO | EL48: NO | EM48: NO | EN48: NO | EO48: NO | EP48: NO | EQ48: NO | ER48: NO | ES48: NO | ET48: 150 | EU48: 300 | EZ48: 450 | FG48: 0 | FN48: 0 | FU48: 0 | GB48: 0 | GI48: 0 | GP48: 0 | GX48: 0 | GY48: 150 | GZ48: 300 | HA48: 0 | HB48: 0 | HC48: 0 | HD48: 0 | HE48: 450 | HF48: 150 | HG48: 300 | HL48: 450 | HS48: 0 | HZ48: 0 | IG48: 0 | IN48: 0 | IO48: 150 | IP48: 300 | IQ48: 0 | IR48: 0 | IS48: 0 | IT48: 0 | IU48: 450 | IX48: 100 | JA48: 1 | JB48: 2 | JC48: 1 | JD48: START Asia Pacific: | JE48: 150 | JF48: 300 | JK48: 450 | JR48: 0 | JY48: 0 | KF48: 0 | KM48: 0 | KT48: 0 | LA48: 0 | LI48: 0 | LJ48: 150 | LK48: 300 | LL48: 0 | LM48: 0 | LN48: 0 | LO48: 0 | LP48: 450 | LQ48: 150 | LW48: 150 | LY48: 300 | MD48: 300 | MK48: 0 | MR48: 0 | MY48: 0 | MZ48: 150 | NA48: 300 | NB48: 0 | NC48: 0 | ND48: 0 | NE48: 0 | NF48: 450 | NG48: START Europe: | RJ48: START North America: | VM48: START Global: | ZP48: START SOUTH America: | ADS48: START Africa:
A49: 181 | B49: ANREV | C49: 42774.347 | D49: Johan Shah | E49: AEP Investment Management | F49: =VLOOKUP(MID(H49,SEARCH("@",H49,1),LEN(H49)-SEARCH("@",H49,1)+1),[2]Sheet1!$D:$F,3,FALSE) -> M0291 | G49: Head, Investor Relations | H49: johan.shah@aep-im.com | I49: 82006982 | J49: Singapore | K49: SGD | M49: 1 | V49: 0 | AC49: 0 | AJ49: 0 | AK49: 72.5 | AQ49: 72.5 | AX49: 0 | BE49: 0 | BF49: 72.5 | BG49: 0 | BH49: 0 | BI49: 0 | BJ49: 0 | BK49: 0 | BL49: 72.5 | BS49: 0 | BZ49: 0 | CG49: 0 | CH49: 1 | CN49: 1 | CU49: 0 | DB49: 0 | DC49: 1 | DD49: 0 | DE49: 0 | DF49: 0 | DG49: 0 | DH49: 0 | DI49: 1 | DJ49: NO | DK49: NO | DL49: NO | DM49: NO | DN49: NO | DO49: NO | DP49: NO | DQ49: NO | DR49: NO | DS49: NO | DT49: NO | DU49: NO | DV49: NO | DW49: NO | DX49: NO | DY49: NO | DZ49: NO | EA49: NO | EB49: YES | EC49: NO | ED49: NO | EE49: NO | EF49: NO | EG49: NO | EH49: NO | EI49: NO | EJ49: NO | EK49: NO | EL49: NO | EM49: NO | EN49: NO | EO49: NO | EP49: NO | EQ49: NO | ER49: NO | ES49: NO | EZ49: 0 | FG49: 0 | FN49: 0 | FO49: 61.7 | FU49: 61.7 | FV49: 10.8 | GB49: 10.8 | GI49: 0 | GP49: 0 | GX49: 0 | GY49: 72.5 | GZ49: 0 | HA49: 0 | HB49: 0 | HC49: 0 | HD49: 0 | HE49: 72.5 | HF49: 72.5 | HL49: 72.5 | HS49: 0 | HZ49: 0 | IG49: 0 | IN49: 0 | IO49: 72.5 | IP49: 0 | IQ49: 0 | IR49: 0 | IS49: 0 | IT49: 0 | IU49: 72.5 | IX49: 100 | JA49: 1 | JB49: 1 | JC49: 1 | JD49: START Asia Pacific: | NG49: START Europe: | RJ49: START North America: | VM49: START Global: | VT49: 0 | WA49: 0 | WH49: 0 | WI49: 61.7 | WO49: 61.7 | WP49: 10.8 | WV49: 10.8 | XC49: 0 | XJ49: 0 | XR49: 0 | XS49: 72.5 | XT49: 0 | XU49: 0 | XV49: 0 | XW49: 0 | XX49: 0 | XY49: 72.5 | YF49: 0 | YG49: 72.5 | YM49: 72.5 | YT49: 0 | ZA49: 0 | ZH49: 0 | ZI49: 72.5 | ZJ49: 0 | ZK49: 0 | ZL49: 0 | ZM49: 0 | ZN49: 0 | ZO49: 72.5 | ZP49: START SOUTH America: | ADS49: START Africa:
A50: 218 | B50: ANREV | C50: 42780 | D50: Singuz Lo | E50: Pamfleet | F50: =VLOOKUP(MID(H50,SEARCH("@",H50,1),LEN(H50)-SEARCH("@",H50,1)+1),[2]Sheet1!$D:$F,3,FALSE) -> M0125 | G50: CFO | H50: singuz.lo@pamfleet.com | I50: 25455828 | J50: Hong Kong | K50: USD | M50: 1 | Q50: 55 | V50: 55 | AC50: 0 | AJ50: 0 | AQ50: 0 | AX50: 0 | BE50: 0 | BF50: 0 | BG50: 55 | BH50: 0 | BI50: 0 | BJ50: 0 | BK50: 0 | BL50: 55 | BN50: 1 | BS50: 1 | BZ50: 0 | CG50: 0 | CN50: 0 | CU50: 0 | DB50: 0 | DC50: 0 | DD50: 1 | DE50: 0 | DF50: 0 | DG50: 0 | DH50: 0 | DI50: 1 | DJ50: NO | DK50: YES | DL50: NO | DM50: NO | DN50: NO | DO50: NO | DP50: NO | DQ50: NO | DR50: NO | DS50: NO | DT50: NO | DU50: NO | DV50: NO | DW50: NO | DX50: NO | DY50: NO | DZ50: NO | EA50: NO | EB50: NO | EC50: NO | ED50: NO | EE50: NO | EF50: NO | EG50: NO | EH50: NO | EI50: NO | EJ50: NO | EK50: NO | EL50: NO | EM50: NO | EN50: NO | EO50: NO | EP50: NO | EQ50: NO | ER50: NO | ES50: NO | EZ50: 0 | FG50: 0 | FN50: 0 | FU50: 0 | GB50: 0 | GD50: 50 | GI50: 50 | GP50: 0 | GQ50: Pamfleet GP | GS50: 5 | GX50: 5 | GY50: 0 | GZ50: 55 | HA50: 0 | HB50: 0 | HC50: 0 | HD50: 0 | HE50: 55 | HG50: 55 | HL50: 55 | HS50: 0 | HZ50: 0 | IG50: 0 | IN50: 0 | IO50: 0 | IP50: 55 | IQ50: 0 | IR50: 0 | IS50: 0 | IT50: 0 | IU50: 55 | IV50: 0 | IX50: 100 | JA50: 1 | JB50: 3 | JC50: 1 | JD50: START Asia Pacific: | JK50: 0 | JR50: 0 | JY50: 0 | KF50: 0 | KM50: 0 | KO50: 50 | KT50: 50 | LA50: 0 | LB50: Pamfleet GP | LD50: 5 | LI50: 5 | LJ50: 0 | LK50: 55 | LL50: 0 | LM50: 0 | LN50: 0 | LO50: 0 | LP50: 55 | LW50: 0 | LY50: 55 | MD50: 55 | MK50: 0 | MR50: 0 | MY50: 0 | MZ50: 0 | NA50: 55 | NB50: 0 | NC50: 0 | ND50: 0 | NE50: 0 | NF50: 55 | NG50: START Europe: | RJ50: START North America: | VM50: START Global: | ZP50: START SOUTH America: | ADS50: START Africa:
A51: 233 | B51: NCREIF | C51: 42780 | D51: Doug Harper | E51: Principal Real Estate Investors | F51: =VLOOKUP(MID(H51,SEARCH("@",H51,1),LEN(H51)-SEARCH("@",H51,1)+1),[2]Sheet1!$D:$F,3,FALSE) -> M03132 | G51: Managing Director | H51: harper.doug@principal.com | I51: 4043955444 | J51: United States | K51: USD | M51: 1 | V51: 0 | AC51: 0 | AD51: 2000 | AE51: 1000 | AI51: 1000 | AJ51: 4000 | AQ51: 0 | AX51: 0 | BE51: 0 | BF51: 2000 | BG51: 1000 | BH51: 0 | BI51: 0 | BJ51: 0 | BK51: 1000 | BL51: 4000 | BS51: 0 | BZ51: 0 | CA51: 3 | CB51: 5 | CF51: 1 | CG51: 9 | CN51: 0 | CU51: 0 | DB51: 0 | DC51: 3 | DD51: 5 | DE51: 0 | DF51: 0 | DG51: 0 | DH51: 1 | DI51: 9 | DJ51: NO | DK51: NO | DL51: NO | DM51: NO | DN51: NO | DO51: NO | DP51: NO | DQ51: NO | DR51: NO | DS51: NO | DT51: NO | DU51: NO | DV51: YES | DW51: YES | DX51: NO | DY51: NO | DZ51: NO | EA51: YES | EB51: NO | EC51: NO | ED51: NO | EE51: NO | EF51: NO | EG51: NO | EH51: NO | EI51: NO | EJ51: NO | EK51: NO | EL51: NO | EM51: NO | EN51: NO | EO51: NO | EP51: NO | EQ51: NO | ER51: NO | ES51: NO | ET51: 1000 | EU51: 1000 | EZ51: 2000 | FA51: 500 | FF51: 500 | FG51: 1000 | FH51: 500 | FN51: 500 | FU51: 0 | FV51: 100 | GB51: 100 | GI51: 0 | GJ51: 50 | GP51: 50 | GQ51: foreign capital | GS51: 350 | GX51: 350 | GY51: 2150 | GZ51: 1350 | HA51: 0 | HB51: 0 | HC51: 0 | HD51: 500 | HE51: 4000 | HF51: 250 | HG51: 250 | HL51: 500 | HM51: 250 | HN51: 250 | HS51: 500 | HT51: 1500 | HU51: 474.5815 | HZ51: 3000 | IG51: 0 | IN51: 0 | IO51: 2000 | IP51: 2000 | IQ51: 0 | IR51: 0 | IS51: 0 | IT51: 0 | IU51: 4000 | IV51: 0 | IW51: 5 | IX51: 95 | JA51: 3 | JB51: 3 | JC51: 2 | JD51: START Asia Pacific: | NG51: START Europe: | RJ51: START North America: | RK51: 1000 | RL51: 1000 | RQ51: 2000 | RR51: 500 | RW51: 500 | RX51: 1000 | RY51: 500 | SE51: 500 | SL51: 0 | SM51: 100 | SS51: 100 | SZ51: 0 | TA51: 50 | TG51: 50 | TH51: Foreign capital | TJ51: 350 | TO51: 350 | TP51: 2150 | TQ51: 1350 | TR51: 0 | TS51: 0 | TT51: 0 | TU51: 500 | TV51: 4000 | TW51: 250 | TX51: 250 | UC51: 500 | UD51: 250 | UE51: 250 | UJ51: 500 | UK51: 1500 | UL51: 1500 | UQ51: 3000 | UX51: 0 | VE51: 0 | VF51: 2000 | VG51: 2000 | VH51: 0 | VI51: 0 | VJ51: 0 | VK51: 0 | VL51: 4000 | VM51: START Global: | ZP51: START SOUTH America: | ADS51: START Africa:
A52: 81 | B52: NCREIF | C52: 42747.76 | D52: Patricia Richardson | E52: Guggenheim Real Estate LLC | F52: =VLOOKUP(MID(H52,SEARCH("@",H52,1),LEN(H52)-SEARCH("@",H52,1)+1),[2]Sheet1!$D:$F,3,FALSE) -> NC031 | G52: Director/Controller | H52: prichardson@guggenheimrealestate.com | I52: 6175365542 | J52: United States | K52: USD | M52: 1 | V52: 0 | AC52: 0 | AD52: 141.33 | AJ52: 141.33 | AQ52: 0 | AX52: 0 | BE52: 0 | BF52: 141.33 | BG52: 0 | BH52: 0 | BI52: 0 | BJ52: 0 | BK52: 0 | BL52: 141.33 | BS52: 0 | BZ52: 0 | CA52: 2 | CG52: 2 | CN52: 0 | CU52: 0 | DB52: 0 | DC52: 2 | DD52: 0 | DE52: 0 | DF52: 0 | DG52: 0 | DH52: 0 | DI52: 2 | DJ52: NO | DK52: NO | DL52: NO | DM52: NO | DN52: NO | DO52: NO | DP52: NO | DQ52: NO | DR52: NO | DS52: NO | DT52: NO | DU52: NO | DV52: YES | DW52: NO | DX52: NO | DY52: NO | DZ52: NO | EA52: NO | EB52: NO | EC52: NO | ED52: NO | EE52: NO | EF52: NO | EG52: NO | EH52: NO | EI52: NO | EJ52: NO | EK52: NO | EL52: NO | EM52: NO | EN52: NO | EO52: NO | EP52: NO | EQ52: NO | ER52: NO | ES52: NO | ET52: 50 | EZ52: 50 | FG52: 0 | FN52: 0 | FU52: 0 | FV52: 1 | GB52: 1 | GC52: 24 | GI52: 24 | GJ52: 16.33 | GP52: 16.33 | GQ52: Foreign Corporate | GR52: 50 | GX52: 50 | GY52: 141.33 | GZ52: 0 | HA52: 0 | HB52: 0 | HC52: 0 | HD52: 0 | HE52: 141.33 | HF52: 50 | HL52: 50 | HS52: 0 | HT52: 91.33 | HZ52: 91.33 | IG52: 0 | IN52: 0 | IO52: 141.33 | IP52: 0 | IQ52: 0 | IR52: 0 | IS52: 0 | IT52: 0 | IU52: 141.33 | IX52: 100 | JA52: 1 | JB52: 1 | JC52: 1 | JD52: START Asia Pacific: | NG52: START Europe: | RJ52: START North America: | RK52: 50 | RQ52: 50 | RX52: 0 | SE52: 0 | SL52: 0 | SM52: 1 | SS52: 1 | ST52: 24 | SZ52: 24 | TA52: 16.33 | TG52: 16.33 | TH52: Foreign Corporate | TI52: 50 | TO52: 50 | TP52: 141.33 | TQ52: 0 | TR52: 0 | TS52: 0 | TT52: 0 | TU52: 0 | TV52: 141.33 | UC52: 0 | UD52: 50 | UJ52: 50 | UK52: 91.33 | UQ52: 91.33 | UX52: 0 | VE52: 0 | VF52: 141.33 | VG52: 0 | VH52: 0 | VI52: 0 | VJ52: 0 | VK52: 0 | VL52: 141.33 | VM52: START Global: | ZP52: START SOUTH America: | ADS52: START Africa:
A53: 68 | B53: NCREIF | C53: 42746.9 | D53: Dan Butler | E53: American Realty Advisors | F53: =VLOOKUP(MID(H53,SEARCH("@",H53,1),LEN(H53)-SEARCH("@",H53,1)+1),[2]Sheet1!$D:$F,3,FALSE) -> NC029 | G53: Director | H53: dbutler@americanreal.com | I53: 8184096565 | J53: United States | K53: USD | M53: 1 | V53: 0 | AC53: 0 | AD53: 600 | AJ53: 600 | AQ53: 0 | AX53: 0 | BE53: 0 | BF53: 600 | BG53: 0 | BH53: 0 | BI53: 0 | BJ53: 0 | BK53: 0 | BL53: 600 | BS53: 0 | BZ53: 0 | CA53: 2 | CG53: 2 | CN53: 0 | CU53: 0 | DB53: 0 | DC53: 2 | DD53: 0 | DE53: 0 | DF53: 0 | DG53: 0 | DH53: 0 | DI53: 2 | DJ53: NO | DK53: NO | DL53: NO | DM53: NO | DN53: NO | DO53: NO | DP53: NO | DQ53: NO | DR53: NO | DS53: NO | DT53: NO | DU53: NO | DV53: YES | DW53: NO | DX53: NO | DY53: NO | DZ53: NO | EA53: NO | EB53: NO | EC53: NO | ED53: NO | EE53: NO | EF53: NO | EG53: NO | EH53: NO | EI53: NO | EJ53: NO | EK53: NO | EL53: NO | EM53: NO | EN53: NO | EO53: NO | EP53: NO | EQ53: NO | ER53: NO | ES53: NO | ET53: 600 | EZ53: 600 | FG53: 0 | FN53: 0 | FU53: 0 | GB53: 0 | GI53: 0 | GP53: 0 | GX53: 0 | GY53: 600 | GZ53: 0 | HA53: 0 | HB53: 0 | HC53: 0 | HD53: 0 | HE53: 600 | HL53: 0 | HM53: 35 | HS53: 35 | HT53: 565 | HZ53: 565 | IG53: 0 | IN53: 0 | IO53: 600 | IP53: 0 | IQ53: 0 | IR53: 0 | IS53: 0 | IT53: 0 | IU53: 600 | IV53: 0 | IW53: 20 | IX53: 80 | JA53: 2 | JB53: 2 | JC53: 1 | JD53: START Asia Pacific: | NG53: START Europe: | RJ53: START North America: | RK53: 600 | RQ53: 600 | RX53: 0 | SE53: 0 | SL53: 0 | SS53: 0 | SZ53: 0 | TG53: 0 | TO53: 0 | TP53: 600 | TQ53: 0 | TR53: 0 | TS53: 0 | TT53: 0 | TU53: 0 | TV53: 600 | TW53: 35 | UC53: 35 | UJ53: 0 | UK53: 565 | UQ53: 565 | UX53: 0 | VE53: 0 | VF53: 600 | VG53: 0 | VH53: 0 | VI53: 0 | VJ53: 0 | VK53: 0 | VL53: 600 | VM53: START Global: | ZP53: START SOUTH America: | ADS53: START Africa:
A54: 180 | B54: NCREIF | C54: 42780 | D54: Brandon Millen | E54: Intercontinental Real Estate Corp. | F54: =VLOOKUP(MID(H54,SEARCH("@",H54,1),LEN(H54)-SEARCH("@",H54,1)+1),[2]Sheet1!$D:$F,3,FALSE) -> NC007 | G54: Assoc Director Performance Measurement | H54: Brandonm@intercontinental.net | I54: 617-779-0490 | J54: United States | K54: USD | M54: 1 | V54: 0 | AC54: 0 | AD54: 616.7 | AJ54: 616.7 | AQ54: 0 | AX54: 0 | BE54: 0 | BF54: 616.7 | BG54: 0 | BH54: 0 | BI54: 0 | BJ54: 0 | BK54: 0 | BL54: 616.7 | BS54: 0 | BZ54: 0 | CA54: 2 | CG54: 2 | CN54: 0 | CU54: 0 | DB54: 0 | DC54: 2 | DD54: 0 | DE54: 0 | DF54: 0 | DG54: 0 | DH54: 0 | DI54: 2 | DJ54: NO | DK54: NO | DL54: NO | DM54: NO | DN54: NO | DO54: NO | DP54: NO | DQ54: NO | DR54: NO | DS54: NO | DT54: NO | DU54: NO | DV54: YES | DW54: NO | DX54: NO | DY54: NO | DZ54: NO | EA54: NO | EB54: NO | EC54: NO | ED54: NO | EE54: NO | EF54: NO | EG54: NO | EH54: NO | EI54: NO | EJ54: NO | EK54: NO | EL54: NO | EM54: NO | EN54: NO | EO54: NO | EP54: NO | EQ54: NO | ER54: NO | ES54: NO | ET54: 609.9 | EZ54: 609.9 | FG54: 0 | FN54: 0 | FU54: 0 | FV54: 6.8 | GB54: 6.8 | GI54: 0 | GP54: 0 | GX54: 0 | GY54: 616.7 | GZ54: 0 | HA54: 0 | HB54: 0 | HC54: 0 | HD54: 0 | HE54: 616.7 | HL54: 0 | HS54: 0 | HT54: 616.7 | HZ54: 616.7 | IG54: 0 | IN54: 0 | IO54: 616.7 | IP54: 0 | IQ54: 0 | IR54: 0 | IS54: 0 | IT54: 0 | IU54: 616.7 | IX54: 100 | JA54: 3 | JB54: 3 | JC54: 1 | JD54: START Asia Pacific: | NG54: START Europe: | RJ54: START North America: | RK54: 609.9 | RQ54: 609.9 | RX54: 0 | SE54: 0 | SL54: 0 | SM54: 6.8 | SS54: 6.8 | SZ54: 0 | TG54: 0 | TO54: 0 | TP54: 616.7 | TQ54: 0 | TR54: 0 | TS54: 0 | TT54: 0 | TU54: 0 | TV54: 616.7 | UC54: 0 | UJ54: 0 | UK54: 616.7 | UQ54: 616.7 | UX54: 0 | VE54: 0 | VF54: 616.7 | VG54: 0 | VH54: 0 | VI54: 0 | VJ54: 0 | VK54: 0 | VL54: 616.7 | VM54: START Global: | ZP54: START SOUTH America: | ADS54: START Africa:
A55: 165 | B55: NCREIF | C55: 42769.956 | D55: David Schenning | E55: PNC | F55: =VLOOKUP(MID(H55,SEARCH("@",H55,1),LEN(H55)-SEARCH("@",H55,1)+1),[2]Sheet1!$D:$F,3,FALSE) -> NC020 | G55: SVP | H55: david.schenning@pnc.com | I55: 202-496-4760 | J55: United States | K55: USD | M55: 1 | V55: 0 | AC55: 0 | AD55: 225 | AJ55: 225 | AQ55: 0 | AX55: 0 | BE55: 0 | BF55: 225 | BG55: 0 | BH55: 0 | BI55: 0 | BJ55: 0 | BK55: 0 | BL55: 225 | BS55: 0 | BZ55: 0 | CA55: 1 | CG55: 1 | CN55: 0 | CU55: 0 | DB55: 0 | DC55: 1 | DD55: 0 | DE55: 0 | DF55: 0 | DG55: 0 | DH55: 0 | DI55: 1 | DJ55: NO | DK55: NO | DL55: NO | DM55: NO | DN55: NO | DO55: NO | DP55: NO | DQ55: NO | DR55: NO | DS55: NO | DT55: NO | DU55: NO | DV55: YES | DW55: NO | DX55: NO | DY55: NO | DZ55: NO | EA55: NO | EB55: NO | EC55: NO | ED55: NO | EE55: NO | EF55: NO | EG55: NO | EH55: NO | EI55: NO | EJ55: NO | EK55: NO | EL55: NO | EM55: NO | EN55: NO | EO55: NO | EP55: NO | EQ55: NO | ER55: NO | ES55: NO | ET55: 225 | EZ55: 225 | FG55: 0 | FN55: 0 | FU55: 0 | GB55: 0 | GI55: 0 | GP55: 0 | GX55: 0 | GY55: 225 | GZ55: 0 | HA55: 0 | HB55: 0 | HC55: 0 | HD55: 0 | HE55: 225 | HL55: 0 | HS55: 0 | HT55: 225 | HZ55: 225 | IG55: 0 | IN55: 0 | IO55: 225 | IP55: 0 | IQ55: 0 | IR55: 0 | IS55: 0 | IT55: 0 | IU55: 225 | IV55: 100 | JA55: 2 | JB55: 2 | JC55: 2 | JD55: START Asia Pacific: | NG55: START Europe: | RJ55: START North America: | RK55: 225 | RQ55: 225 | RX55: 0 | SE55: 0 | SL55: 0 | SS55: 0 | SZ55: 0 | TG55: 0 | TO55: 0 | TP55: 225 | TQ55: 0 | TR55: 0 | TS55: 0 | TT55: 0 | TU55: 0 | TV55: 225 | UC55: 0 | UJ55: 0 | UK55: 225 | UQ55: 225 | UX55: 0 | VE55: 0 | VF55: 225 | VG55: 0 | VH55: 0 | VI55: 0 | VJ55: 0 | VK55: 0 | VL55: 225 | VM55: START Global: | ZP55: START SOUTH America: | ADS55: START Africa:
A56: 65 | B56: NCREIF | C56: 42780 | D56: Lisa Wallis | E56: Sarofim Realty Advisors Co. | F56: =VLOOKUP(MID(H56,SEARCH("@",H56,1),LEN(H56)-SEARCH("@",H56,1)+1),[2]Sheet1!$D:$F,3,FALSE) -> NC003 | G56: Portfolio Controller | H56: lwallis@sraco.com | I56: 214-692-4266 | J56: United States | K56: USD | M56: 2 | N56: 6 | O56: New allocations pursued in 2016 but not approved until first quarter 2017. | V56: 0 | AC56: 0 | AJ56: 0 | AQ56: 0 | AX56: 0 | BE56: 0 | BF56: 0 | BG56: 0 | BH56: 0 | BI56: 0 | BJ56: 0 | BK56: 0 | BL56: 0 | BS56: 0 | BZ56: 0 | CG56: 0 | CN56: 0 | CU56: 0 | DB56: 0 | DC56: 0 | DD56: 0 | DE56: 0 | DF56: 0 | DG56: 0 | DH56: 0 | DI56: 0 | DJ56: NO | DK56: NO | DL56: NO | DM56: NO | DN56: NO | DO56: NO | DP56: NO | DQ56: NO | DR56: NO | DS56: NO | DT56: NO | DU56: NO | DV56: NO | DW56: NO | DX56: NO | DY56: NO | DZ56: NO | EA56: NO | EB56: NO | EC56: NO | ED56: NO | EE56: NO | EF56: NO | EG56: NO | EH56: NO | EI56: NO | EJ56: NO | EK56: NO | EL56: NO | EM56: NO | EN56: NO | EO56: NO | EP56: NO | EQ56: NO | ER56: NO | ES56: NO | EZ56: 0 | FG56: 0 | FN56: 0 | FU56: 0 | GB56: 0 | GI56: 0 | GP56: 0 | GX56: 0 | GY56: 0 | GZ56: 0 | HA56: 0 | HB56: 0 | HC56: 0 | HD56: 0 | HE56: 0 | HL56: 0 | HS56: 0 | HZ56: 0 | IG56: 0 | IN56: 0 | IO56: 0 | IP56: 0 | IQ56: 0 | IR56: 0 | IS56: 0 | IT56: 0 | IU56: 0 | JA56: 1 | JB56: 3 | JC56: 1 | JD56: START Asia Pacific: | NG56: START Europe: | RJ56: START North America: | VM56: START Global: | ZP56: START SOUTH America: | ADS56: START Africa:
A57: 109 | B57: INREV | C57: 42755.969 | D57: David Rückel | E57: PIA Pontis Institutional Advisors GmbH | F57: =VLOOKUP(MID(H57,SEARCH("@",H57,1),LEN(H57)-SEARCH("@",H57,1)+1),[2]Sheet1!$D:$F,3,FALSE) -> M2556 | G57: Managing Partner | H57: david.rueckel@pia-pontis.com | I57: 4989122238961 | J57: Germany | K57: EUR | M57: 1 | V57: 0 | W57: 100 | AC57: 100 | AJ57: 0 | AQ57: 0 | AX57: 0 | BE57: 0 | BF57: 100 | BG57: 0 | BH57: 0 | BI57: 0 | BJ57: 0 | BK57: 0 | BL57: 100 | BS57: 0 | BT57: 2 | BZ57: 2 | CG57: 0 | CN57: 0 | CU57: 0 | DB57: 0 | DC57: 2 | DD57: 0 | DE57: 0 | DF57: 0 | DG57: 0 | DH57: 0 | DI57: 2 | DJ57: NO | DK57: NO | DL57: NO | DM57: NO | DN57: NO | DO57: NO | DP57: YES | DQ57: NO | DR57: NO | DS57: NO | DT57: NO | DU57: NO | DV57: NO | DW57: NO | DX57: NO | DY57: NO | DZ57: NO | EA57: NO | EB57: NO | EC57: NO | ED57: NO | EE57: NO | EF57: NO | EG57: NO | EH57: NO | EI57: NO | EJ57: NO | EK57: NO | EL57: NO | EM57: NO | EN57: NO | EO57: NO | EP57: NO | EQ57: NO | ER57: NO | ES57: NO | EZ57: 0 | FA57: 40 | FG57: 40 | FN57: 0 | FU57: 0 | GB57: 0 | GC57: 20 | GI57: 20 | GJ57: 40 | GP57: 40 | GX57: 0 | GY57: 100 | GZ57: 0 | HA57: 0 | HB57: 0 | HC57: 0 | HD57: 0 | HE57: 100 | HL57: 0 | HM57: 100 | HS57: 100 | HZ57: 0 | IG57: 0 | IN57: 0 | IO57: 100 | IP57: 0 | IQ57: 0 | IR57: 0 | IS57: 0 | IT57: 0 | IU57: 100 | IY57: I am a placement agent | IZ57: 100 | JA57: 1 | JB57: 3 | JC57: 1 | JD57: START Asia Pacific: | NG57: START Europe: | NN57: 0 | NO57: 40 | NU57: 40 | OB57: 0 | OI57: 0 | OP57: 0 | OQ57: 20 | OW57: 20 | OX57: 40 | PD57: 40 | PL57: 0 | PM57: 100 | PN57: 0 | PO57: 0 | PP57: 0 | PQ57: 0 | PR57: 0 | PS57: 100 | PT57: 100 | PZ57: 100 | QG57: 0 | QN57: 0 | QU57: 0 | RB57: 0 | RC57: 100 | RD57: 0 | RE57: 0 | RF57: 0 | RG57: 0 | RH57: 0 | RI57: 100 | RJ57: START North America: | VM57: START Global: | ZP57: START SOUTH America: | ADS57: START Africa:
A58: 169 | B58: INREV | C58: 42772.517 | D58: Anne Schachner | E58: NREP | F58: =VLOOKUP(MID(H58,SEARCH("@",H58,1),LEN(H58)-SEARCH("@",H58,1)+1),[2]Sheet1!$D:$F,3,FALSE) -> M305 | G58: Investor Relations | H58: ansc@nrep.com | I58: +45 30520201 | J58: Denmark | K58: EUR | M58: 1 | V58: 0 | W58: 596 | AC58: 596 | AJ58: 0 | AQ58: 0 | AX58: 0 | BE58: 0 | BF58: 596 | BG58: 0 | BH58: 0 | BI58: 0 | BJ58: 0 | BK58: 0 | BL58: 596 | BS58: 0 | BT58: 1 | BZ58: 1 | CG58: 0 | CN58: 0 | CU58: 0 | DB58: 0 | DC58: 1 | DD58: 0 | DE58: 0 | DF58: 0 | DG58: 0 | DH58: 0 | DI58: 1 | DJ58: NO | DK58: NO | DL58: NO | DM58: NO | DN58: NO | DO58: NO | DP58: YES | DQ58: NO | DR58: NO | DS58: NO | DT58: NO | DU58: NO | DV58: NO | DW58: NO | DX58: NO | DY58: NO | DZ58: NO | EA58: NO | EB58: NO | EC58: NO | ED58: NO | EE58: NO | EF58: NO | EG58: NO | EH58: NO | EI58: NO | EJ58: NO | EK58: NO | EL58: NO | EM58: NO | EN58: NO | EO58: NO | EP58: NO | EQ58: NO | ER58: NO | ES58: NO | ET58: 195.8 | EZ58: 195.8 | FA58: 185.46 | FG58: 185.46 | FN58: 0 | FU58: 0 | GB58: 0 | GC58: 68.175 | GI58: 68.18 | GJ58: 146.56 | GP58: 146.56 | GX58: 0 | GY58: 596 | GZ58: 0 | HA58: 0 | HB58: 0 | HC58: 0 | HD58: 0 | HE58: 596 | HL58: 0 | HM58: 416.49 | HS58: 416.49 | HT58: 170.96 | HZ58: 170.96 | IA58: 8.55 | IG58: 8.55 | IN58: 0 | IO58: 596 | IP58: 0 | IQ58: 0 | IR58: 0 | IS58: 0 | IT58: 0 | IU58: 596 | IV58: 22 | IW58: 4 | IX58: 74 | JA58: 1 | JB58: 3 | JC58: 2 | JD58: START Asia Pacific: | NG58: START Europe: | NH58: 195.8 | NN58: 195.8 | NO58: 185.46 | NU58: 185.46 | OB58: 0 | OI58: 0 | OP58: 0 | OQ58: 68.175 | OW58: 68.18 | OX58: 146.565 | PD58: 146.57 | PL58: 0 | PM58: 596 | PN58: 0 | PO58: 0 | PP58: 0 | PQ58: 0 | PR58: 0 | PS58: 596 | PT58: 416.49 | PZ58: 416.49 | QG58: 0 | QH58: 170.96 | QN58: 170.96 | QO58: 8.55 | QU58: 8.55 | RB58: 0 | RC58: 596 | RD58: 0 | RE58: 0 | RF58: 0 | RG58: 0 | RH58: 0 | RI58: 596 | RJ58: START North America: | VM58: START Global: | ZP58: START SOUTH America: | ADS58: START Africa:
A59: 208 | B59: INREV | C59: 42780 | D59: Michaela Graefe | E59: Deka Immobilien Investment GmbH | F59: =VLOOKUP(MID(H59,SEARCH("@",H59,1),LEN(H59)-SEARCH("@",H59,1)+1),[2]Sheet1!$D:$F,3,FALSE) -> M119 | G59: Head of Fund Management Service Institutional Investors | H59: michaela.graefe@deka.de | I59: 496971473504 | J59: Germany | K59: EUR | M59: 1 | V59: 0 | X59: 867.6 | Y59: 16.5 | Z59: 195 | AA59: 168 | AB59: 148 | AC59: 1395.1 | AJ59: 0 | AQ59: 0 | AX59: 0 | BE59: 0 | BF59: 0 | BG59: 867.6 | BH59: 16.5 | BI59: 195 | BJ59: 168 | BK59: 148 | BL59: 1395.1 | BS59: 0 | BU59: 7 | BV59: 1 | BW59: 1 | BX59: 1 | BY59: 4 | BZ59: 14 | CG59: 0 | CN59: 0 | CU59: 0 | DB59: 0 | DC59: 0 | DD59: 7 | DE59: 1 | DF59: 1 | DG59: 1 | DH59: 4 | DI59: 14 | DJ59: NO | DK59: NO | DL59: NO | DM59: NO | DN59: NO | DO59: NO | DP59: NO | DQ59: YES | DR59: YES | DS59: YES | DT59: YES | DU59: YES | DV59: NO | DW59: NO | DX59: NO | DY59: NO | DZ59: NO | EA59: NO | EB59: NO | EC59: NO | ED59: NO | EE59: NO | EF59: NO | EG59: NO | EH59: NO | EI59: NO | EJ59: NO | EK59: NO | EL59: NO | EM59: NO | EN59: NO | EO59: NO | EP59: NO | EQ59: NO | ER59: NO | ES59: NO | EV59: 16.5 | EZ59: 16.5 | FG59: 0 | FN59: 0 | FU59: 0 | FZ59: 56 | GB59: 56 | GI59: 0 | GP59: 0 | GQ59: Saving banks | GS59: 867.6 | GU59: 195 | GV59: 112 | GW59: 148 | GX59: 1322.6 | GY59: 0 | GZ59: 867.6 | HA59: 16.5 | HB59: 195 | HC59: 168 | HD59: 148 | HE59: 1395.1 | HL59: 0 | HN59: 867.6 | HO59: 16.5 | HP59: 195 | HQ59: 168 | HR59: 148 | HS59: 1395.1 | HZ59: 0 | IG59: 0 | IN59: 0 | IO59: 0 | IP59: 867.6 | IQ59: 16.5 | IR59: 195 | IS59: 168 | IT59: 148 | IU59: 1395.1 | IX59: 100 | JA59: 1 | JB59: 1 | JC59: 1 | JD59: START Asia Pacific: | NG59: START Europe: | NJ59: 16.5 | NN59: 16.5 | NU59: 0 | OB59: 0 | OI59: 0 | ON59: 56 | OP59: 56 | OW59: 0 | PD59: 0 | PE59: Saving banks | PG59: 867.6 | PI59: 195 | PJ59: 112 | PK59: 148 | PL59: 1322.6 | PM59: 0 | PN59: 867.6 | PO59: 16.5 | PP59: 195 | PQ59: 168 | PR59: 148 | PS59: 1395.1 | PU59: 867.6 | PV59: 16.5 | PW59: 195 | PX59: 168 | PY59: 148 | PZ59: 1395.1 | QG59: 0 | QN59: 0 | QU59: 0 | RB59: 0 | RC59: 0 | RD59: 867.6 | RE59: 16.5 | RF59: 195 | RG59: 168 | RH59: 148 | RI59: 1395.1 | RJ59: START North America: | VM59: START Global: | ZP59: START SOUTH America: | ADS59: START Africa:
A60: 203 | B60: INREV | C60: 42779.351 | D60: Oliver Luckey | E60: Hahn Group | F60: =VLOOKUP(MID(H60,SEARCH("@",H60,1),LEN(H60)-SEARCH("@",H60,1)+1),[2]Sheet1!$D:$F,3,FALSE) -> M369 | G60: Head of Fund Management | H60: oluckey@hahnag.de | I60: +49 2204 9490 135 | J60: Germany | K60: EUR | M60: 1 | V60: 0 | W60: 40 | X60: 170 | AC60: 210 | AJ60: 0 | AQ60: 0 | AX60: 0 | BE60: 0 | BF60: 40 | BG60: 170 | BH60: 0 | BI60: 0 | BJ60: 0 | BK60: 0 | BL60: 210 | BS60: 0 | BT60: 1 | BU60: 2 | BZ60: 3 | CG60: 0 | CN60: 0 | CU60: 0 | DB60: 0 | DC60: 1 | DD60: 2 | DE60: 0 | DF60: 0 | DG60: 0 | DH60: 0 | DI60: 3 | DJ60: NO | DK60: NO | DL60: NO | DM60: NO | DN60: NO | DO60: NO | DP60: YES | DQ60: YES | DR60: NO | DS60: NO | DT60: NO | DU60: NO | DV60: NO | DW60: NO | DX60: NO | DY60: NO | DZ60: NO | EA60: NO | EB60: NO | EC60: NO | ED60: NO | EE60: NO | EF60: NO | EG60: NO | EH60: NO | EI60: NO | EJ60: NO | EK60: NO | EL60: NO | EM60: NO | EN60: NO | EO60: NO | EP60: NO | EQ60: NO | ER60: NO | ES60: NO | EU60: 150 | EZ60: 150 | FG60: 0 | FN60: 0 | FU60: 0 | FV60: 40 | FW60: 10 | GB60: 50 | GI60: 0 | GK60: 10 | GP60: 10 | GX60: 0 | GY60: 40 | GZ60: 170 | HA60: 0 | HB60: 0 | HC60: 0 | HD60: 0 | HE60: 210 | HL60: 0 | HM60: 40 | HN60: 170 | HS60: 210 | HZ60: 0 | IG60: 0 | IN60: 0 | IO60: 40 | IP60: 170 | IQ60: 0 | IR60: 0 | IS60: 0 | IT60: 0 | IU60: 210 | IV60: 0 | IW60: 80 | IX60: 20 | JA60: 3 | JB60: 3 | JC60: 1 | JD60: START Asia Pacific: | NG60: START Europe: | NI60: 150 | NN60: 150 | NU60: 0 | OB60: 0 | OI60: 0 | OJ60: 40 | OK60: 10 | OP60: 50 | OW60: 0 | OY60: 10 | PD60: 10 | PL60: 0 | PM60: 40 | PN60: 170 | PO60: 0 | PP60: 0 | PQ60: 0 | PR60: 0 | PS60: 210 | PT60: 40 | PU60: 170 | PZ60: 210 | QG60: 0 | QN60: 0 | QU60: 0 | RB60: 0 | RC60: 40 | RD60: 170 | RE60: 0 | RF60: 0 | RG60: 0 | RH60: 0 | RI60: 210 | RJ60: START North America: | VM60: START Global: | ZP60: START SOUTH America: | ADS60: START Africa:
A61: 202 | B61: INREV | C61: 42780 | D61: Jan Kuhn | E61: CORPUS SIREO Holding AG | F61: =VLOOKUP(MID(H61,SEARCH("@",H61,1),LEN(H61)-SEARCH("@",H61,1)+1),[2]Sheet1!$D:$F,3,FALSE) -> M364 | G61: Head of Business Development | H61: Jan.Kuhn@corpussireo.com | I61: +49 221 39900220 | J61: Germany | K61: EUR | M61: 1 | V61: 0 | W61: 320 | Z61: 132 | AC61: 452 | AJ61: 0 | AQ61: 0 | AX61: 0 | BE61: 0 | BF61: 320 | BG61: 0 | BH61: 0 | BI61: 132 | BJ61: 0 | BK61: 0 | BL61: 452 | BS61: 0 | BT61: 3 | BW61: 2 | BZ61: 5 | CG61: 0 | CN61: 0 | CU61: 0 | DB61: 0 | DC61: 3 | DD61: 0 | DE61: 0 | DF61: 2 | DG61: 0 | DH61: 0 | DI61: 5 | DJ61: NO | DK61: NO | DL61: NO | DM61: NO | DN61: NO | DO61: NO | DP61: YES | DQ61: NO | DR61: NO | DS61: YES | DT61: NO | DU61: NO | DV61: NO | DW61: NO | DX61: NO | DY61: NO | DZ61: NO | EA61: NO | EB61: NO | EC61: NO | ED61: NO | EE61: NO | EF61: NO | EG61: NO | EH61: NO | EI61: NO | EJ61: NO | EK61: NO | EL61: NO | EM61: NO | EN61: NO | EO61: NO | EP61: NO | EQ61: NO | ER61: NO | ES61: NO | ET61: 10 | EZ61: 10 | FA61: 300 | FD61: 132 | FG61: 432 | FN61: 0 | FU61: 0 | GB61: 0 | GC61: 10 | GI61: 10 | GP61: 0 | GX61: 0 | GY61: 320 | GZ61: 0 | HA61: 0 | HB61: 132 | HC61: 0 | HD61: 0 | HE61: 452 | HL61: 0 | HM61: 320 | HP61: 132 | HS61: 452 | HZ61: 0 | IG61: 0 | IN61: 0 | IO61: 320 | IP61: 0 | IQ61: 0 | IR61: 132 | IS61: 0 | IT61: 0 | IU61: 452 | IV61: 0 | IW61: 0 | IX61: 100 | IZ61: 0 | JA61: 1 | JB61: 3 | JC61: 1 | JD61: START Asia Pacific: | NG61: START Europe: | NH61: 10 | NN61: 10 | NO61: 300 | NR61: 132 | NU61: 432 | OB61: 0 | OI61: 0 | OP61: 0 | OQ61: 10 | OW61: 10 | PD61: 0 | PL61: 0 | PM61: 320 | PN61: 0 | PO61: 0 | PP61: 132 | PQ61: 0 | PR61: 0 | PS61: 452 | PT61: 320 | PW61: 132 | PZ61: 452 | QG61: 0 | QN61: 0 | QU61: 0 | RB61: 0 | RC61: 320 | RD61: 0 | RE61: 0 | RF61: 132 | RG61: 0 | RH61: 0 | RI61: 452 | RJ61: START North America: | VM61: START Global: | ZP61: START SOUTH America: | ADS61: START Africa:
A62: 147 | B62: INREV | C62: 42780 | D62: Marina Ferri | E62: Pradera | F62: =VLOOKUP(MID(H62,SEARCH("@",H62,1),LEN(H62)-SEARCH("@",H62,1)+1),[2]Sheet1!$D:$F,3,FALSE) -> M093 | G62: Corporate Marketing | H62: marina.ferri@pradera.com | I62: 0207 539 5432 | J62: United Kingdom | K62: EUR | M62: 1 | S62: 380 | V62: 380 | AC62: 0 | AJ62: 0 | AQ62: 0 | AX62: 0 | BE62: 0 | BF62: 0 | BG62: 0 | BH62: 0 | BI62: 380 | BJ62: 0 | BK62: 0 | BL62: 380 | BP62: 1 | BS62: 1 | BZ62: 0 | CG62: 0 | CN62: 0 | CU62: 0 | DB62: 0 | DC62: 0 | DD62: 0 | DE62: 0 | DF62: 1 | DG62: 0 | DH62: 0 | DI62: 1 | DJ62: NO | DK62: NO | DL62: NO | DM62: YES | DN62: NO | DO62: NO | DP62: NO | DQ62: NO | DR62: NO | DS62: NO | DT62: NO | DU62: NO | DV62: NO | DW62: NO | DX62: NO | DY62: NO | DZ62: NO | EA62: NO | EB62: NO | EC62: NO | ED62: NO | EE62: NO | EF62: NO | EG62: NO | EH62: NO | EI62: NO | EJ62: NO | EK62: NO | EL62: NO | EM62: NO | EN62: NO | EO62: NO | EP62: NO | EQ62: NO | ER62: NO | ES62: NO | EZ62: 0 | FG62: 0 | FK62: 378 | FN62: 378 | FU62: 0 | GB62: 0 | GI62: 0 | GP62: 0 | GX62: 0 | GY62: 0 | GZ62: 0 | HA62: 0 | HB62: 378 | HC62: 0 | HD62: 0 | HE62: 378 | HI62: 380 | HL62: 380 | HS62: 0 | HZ62: 0 | IG62: 0 | IN62: 0 | IO62: 0 | IP62: 0 | IQ62: 0 | IR62: 380 | IS62: 0 | IT62: 0 | IU62: 380 | IX62: 100 | JA62: 1 | JB62: 3 | JC62: 1 | JD62: START Asia Pacific: | JK62: 0 | JR62: 0 | JV62: 380 | JY62: 380 | KF62: 0 | KM62: 0 | KT62: 0 | LA62: 0 | LI62: 0 | LJ62: 0 | LK62: 0 | LL62: 0 | LM62: 380 | LN62: 0 | LO62: 0 | LP62: 380 | LW62: 0 | MA62: 380 | MD62: 380 | MK62: 0 | MR62: 0 | MY62: 0 | MZ62: 0 | NA62: 0 | NB62: 0 | NC62: 380 | ND62: 0 | NE62: 0 | NF62: 380 | NG62: START Europe: | RJ62: START North America: | VM62: START Global: | ZP62: START SOUTH America: | ADS62: START Africa:
A63: 154 | B63: INREV | C63: 42767.386 | D63: Philip Theis Olander | E63: Sparinvest Property Investors | F63: =VLOOKUP(MID(H63,SEARCH("@",H63,1),LEN(H63)-SEARCH("@",H63,1)+1),[2]Sheet1!$D:$F,3,FALSE) -> M180 | G63: Analyst | H63: pto@sparinvest.dk | I63: 36347035 | J63: Denmark | K63: EUR | M63: 1 | P63: 36 | R63: 47 | S63: 32 | V63: 115 | W63: 95 | Z63: 100 | AC63: 195 | AD63: 53 | AF63: 37 | AG63: 105 | AJ63: 195 | AQ63: 0 | AX63: 0 | BE63: 0 | BF63: 184 | BG63: 0 | BH63: 84 | BI63: 237 | BJ63: 0 | BK63: 0 | BL63: 505 | BM63: 2 | BO63: 2 | BP63: 1 | BS63: 5 | BT63: 3 | BW63: 3 | BZ63: 6 | CA63: 2 | CC63: 1 | CD63: 3 | CG63: 6 | CN63: 0 | CU63: 0 | DB63: 0 | DC63: 7 | DD63: 0 | DE63: 3 | DF63: 7 | DG63: 0 | DH63: 0 | DI63: 17 | DJ63: YES | DK63: NO | DL63: YES | DM63: YES | DN63: NO | DO63: NO | DP63: YES | DQ63: NO | DR63: NO | DS63: YES | DT63: NO | DU63: NO | DV63: YES | DW63: NO | DX63: YES | DY63: YES | DZ63: NO | EA63: NO | EB63: NO | EC63: NO | ED63: NO | EE63: NO | EF63: NO | EG63: NO | EH63: NO | EI63: NO | EJ63: NO | EK63: NO | EL63: NO | EM63: NO | EN63: NO | EO63: NO | EP63: NO | EQ63: NO | ER63: NO | ES63: NO | ET63: 166 | EV63: 76 | EW63: 213 | EZ63: 455 | FG63: 0 | FN63: 0 | FU63: 0 | GB63: 0 | GC63: 10 | GE63: 4 | GF63: 11 | GI63: 25 | GJ63: 10 | GL63: 4 | GM63: 11 | GP63: 25 | GX63: 0 | GY63: 186 | GZ63: 0 | HA63: 84 | HB63: 235 | HC63: 0 | HD63: 0 | HE63: 505 | HL63: 0 | HM63: 184 | HO63: 84 | HP63: 237 | HS63: 505 | HZ63: 0 | IG63: 0 | IN63: 0 | IO63: 184 | IP63: 0 | IQ63: 84 | IR63: 237 | IS63: 0 | IT63: 0 | IU63: 505 | IV63: 0 | IW63: 0 | IX63: 100 | JA63: 1 | JB63: 3 | JC63: 1 | JD63: START Asia Pacific: | JE63: 38 | JG63: 17 | JH63: 49 | JK63: 104 | JR63: 0 | JY63: 0 | KF63: 0 | KM63: 0 | KN63: 2 | KP63: 1 | KQ63: 2.5 | KT63: 5.5 | KU63: 2 | KW63: 1 | KX63: 2.5 | LA63: 5.5 | LI63: 0 | LJ63: 42 | LK63: 0 | LL63: 19 | LM63: 54 | LN63: 0 | LO63: 0 | LP63: 115 | LQ63: 42 | LS63: 19 | LT63: 54 | LW63: 115 | MD63: 0 | MK63: 0 | MR63: 0 | MY63: 0 | MZ63: 42 | NA63: 0 | NB63: 19 | NC63: 54 | ND63: 0 | NE63: 0 | NF63: 115 | NG63: START Europe: | NH63: 64 | NJ63: 29 | NK63: 82 | NN63: 175 | NU63: 0 | OB63: 0 | OI63: 0 | OP63: 0 | OQ63: 3 | OS63: 2 | OT63: 5 | OW63: 10 | OX63: 3 | OZ63: 2 | PA63: 5 | PD63: 10 | PL63: 0 | PM63: 70 | PN63: 0 | PO63: 33 | PP63: 92 | PQ63: 0 | PR63: 0 | PS63: 195 | PT63: 71 | PV63: 32 | PW63: 92 | PZ63: 195 | QG63: 0 | QN63: 0 | QU63: 0 | RB63: 0 | RC63: 71 | RD63: 0 | RE63: 32 | RF63: 92 | RG63: 0 | RH63: 0 | RI63: 195 | RJ63: START North America: | RK63: 64 | RM63: 29 | RN63: 82 | RQ63: 175 | RX63: 0 | SE63: 0 | SL63: 0 | SS63: 0 | ST63: 3 | SV63: 2 | SW63: 5 | SZ63: 10 | TA63: 3 | TC63: 2 | TD63: 5 | TG63: 10 | TO63: 0 | TP63: 70 | TQ63: 0 | TR63: 33 | TS63: 92 | TT63: 0 | TU63: 0 | TV63: 195 | TW63: 71 | TY63: 32 | TZ63: 92 | UC63: 195 | UJ63: 0 | UQ63: 0 | UX63: 0 | VE63: 0 | VF63: 71 | VG63: 0 | VH63: 32 | VI63: 92 | VJ63: 0 | VK63: 0 | VL63: 195 | VM63: START Global: | ZP63: START SOUTH America: | ADS63: START Africa:
A64: 189 | B64: INREV | C64: 42780 | D64: Neil Cable | E64: Fidelity International | F64: =VLOOKUP(MID(H64,SEARCH("@",H64,1),LEN(H64)-SEARCH("@",H64,1)+1),[2]Sheet1!$D:$F,3,FALSE) -> M250 | G64: Head of European Real Estate | H64: Neil.Cable@fil.com | I64: 442079614311 | J64: United Kingdom | K64: EUR | M64: 1 | V64: 0 | W64: 120 | X64: 150 | AC64: 270 | AJ64: 0 | AQ64: 0 | AX64: 0 | BE64: 0 | BF64: 120 | BG64: 150 | BH64: 0 | BI64: 0 | BJ64: 0 | BK64: 0 | BL64: 270 | BS64: 0 | BT64: 2 | BU64: 1 | BZ64: 3 | CG64: 0 | CN64: 0 | CU64: 0 | DB64: 0 | DC64: 2 | DD64: 1 | DE64: 0 | DF64: 0 | DG64: 0 | DH64: 0 | DI64: 3 | DJ64: NO | DK64: NO | DL64: NO | DM64: NO | DN64: NO | DO64: NO | DP64: YES | DQ64: YES | DR64: NO | DS64: NO | DT64: NO | DU64: NO | DV64: NO | DW64: NO | DX64: NO | DY64: NO | DZ64: NO | EA64: NO | EB64: NO | EC64: NO | ED64: NO | EE64: NO | EF64: NO | EG64: NO | EH64: NO | EI64: NO | EJ64: NO | EK64: NO | EL64: NO | EM64: NO | EN64: NO | EO64: NO | EP64: NO | EQ64: NO | ER64: NO | ES64: NO | ET64: 60 | EZ64: 60 | FA64: 10 | FG64: 10 | FN64: 0 | FO64: 45 | FU64: 45 | GB64: 0 | GC64: 5 | GI64: 5 | GP64: 0 | GQ64: Bank | GS64: 150 | GX64: 150 | GY64: 120 | GZ64: 150 | HA64: 0 | HB64: 0 | HC64: 0 | HD64: 0 | HE64: 270 | HG64: 150 | HL64: 150 | HM64: 120 | HS64: 120 | HZ64: 0 | IG64: 0 | IN64: 0 | IO64: 120 | IP64: 150 | IQ64: 0 | IR64: 0 | IS64: 0 | IT64: 0 | IU64: 270 | IX64: 100 | JA64: 1 | JB64: 3 | JC64: 1 | JD64: START Asia Pacific: | NG64: START Europe: | NH64: 60 | NN64: 60 | NO64: 10 | NU64: 10 | OB64: 0 | OC64: 45 | OI64: 45 | OP64: 0 | OQ64: 5 | OW64: 5 | PD64: 0 | PE64: Bank | PG64: 150 | PL64: 150 | PM64: 120 | PN64: 150 | PO64: 0 | PP64: 0 | PQ64: 0 | PR64: 0 | PS64: 270 | PT64: 120 | PZ64: 120 | QB64: 150 | QG64: 150 | QN64: 0 | QU64: 0 | RB64: 0 | RC64: 120 | RD64: 150 | RE64: 0 | RF64: 0 | RG64: 0 | RH64: 0 | RI64: 270 | RJ64: START North America: | VM64: START Global: | ZP64: START SOUTH America: | ADS64: START Africa:
A65: 101 | B65: INREV | C65: 42780 | D65: Dietrich Heidtmann | E65: GTIS Partners | F65: =VLOOKUP(MID(H65,SEARCH("@",H65,1),LEN(H65)-SEARCH("@",H65,1)+1),[2]Sheet1!$D:$F,3,FALSE) -> M401 | G65: MD - Head of Intl. Capital Markets | H65: dheidtmann@gtispartners.com | I65: 33170375880 | J65: United States | K65: USD | M65: 1 | V65: 0 | AC65: 0 | AG65: 156 | AJ65: 156 | AQ65: 0 | AR65: 584 | AX65: 584 | BE65: 0 | BF65: 584 | BG65: 0 | BH65: 0 | BI65: 156 | BJ65: 0 | BK65: 0 | BL65: 740 | BS65: 0 | BZ65: 0 | CD65: 2 | CG65: 2 | CN65: 0 | CO65: 1 | CU65: 1 | DB65: 0 | DC65: 1 | DD65: 0 | DE65: 0 | DF65: 2 | DG65: 0 | DH65: 0 | DI65: 3 | DJ65: NO | DK65: NO | DL65: NO | DM65: NO | DN65: NO | DO65: NO | DP65: NO | DQ65: NO | DR65: NO | DS65: NO | DT65: NO | DU65: NO | DV65: NO | DW65: NO | DX65: NO | DY65: YES | DZ65: NO | EA65: NO | EB65: NO | EC65: NO | ED65: NO | EE65: NO | EF65: NO | EG65: NO | EH65: YES | EI65: NO | EJ65: NO | EK65: NO | EL65: NO | EM65: NO | EN65: NO | EO65: NO | EP65: NO | EQ65: NO | ER65: NO | ES65: NO | ET65: 576 | EW65: 25 | EZ65: 601 | FG65: 0 | FN65: 0 | FU65: 0 | FY65: 20 | GB65: 20 | GF65: 77 | GI65: 77 | GJ65: 0.3 | GM65: 31 | GP65: 31.3 | GQ65: GTIS management and employees | GR65: 8 | GU65: 3 | GX65: 11 | GY65: 584.3 | GZ65: 0 | HA65: 0 | HB65: 156 | HC65: 0 | HD65: 0 | HE65: 740.3 | HL65: 0 | HM65: 500 | HP65: 45 | HS65: 545 | HT65: 84 | HW65: 111 | HZ65: 195 | IG65: 0 | IN65: 0 | IO65: 584 | IP65: 0 | IQ65: 0 | IR65: 156 | IS65: 0 | IT65: 0 | IU65: 740 | IX65: 100 | JA65: 1 | JB65: 1 | JC65: 1 | JD65: START Asia Pacific: | NG65: START Europe: | RJ65: START North America: | VM65: START Global: | ZP65: START SOUTH America: | ADS65: START Africa:
A66: 51 | B66: INREV | C66: 42766.359 | D66: Antonello De Filippo | E66: AltaFund General Partner | F66: =VLOOKUP(MID(H66,SEARCH("@",H66,1),LEN(H66)-SEARCH("@",H66,1)+1),[2]Sheet1!$D:$F,3,FALSE) -> M636 | G66: Chief Financial Officer | H66: antonello.defilippo@altafund.lu | I66: 352621346143 | J66: Luxembourg | K66: EUR | M66: 2 | N66: 6 | O66: no new funds | V66: 0 | AC66: 0 | AJ66: 0 | AQ66: 0 | AX66: 0 | BE66: 0 | BF66: 0 | BG66: 0 | BH66: 0 | BI66: 0 | BJ66: 0 | BK66: 0 | BL66: 0 | BS66: 0 | BZ66: 0 | CG66: 0 | CN66: 0 | CU66: 0 | DB66: 0 | DC66: 0 | DD66: 0 | DE66: 0 | DF66: 0 | DG66: 0 | DH66: 0 | DI66: 0 | DJ66: NO | DK66: NO | DL66: NO | DM66: NO | DN66: NO | DO66: NO | DP66: NO | DQ66: NO | DR66: NO | DS66: NO | DT66: NO | DU66: NO | DV66: NO | DW66: NO | DX66: NO | DY66: NO | DZ66: NO | EA66: NO | EB66: NO | EC66: NO | ED66: NO | EE66: NO | EF66: NO | EG66: NO | EH66: NO | EI66: NO | EJ66: NO | EK66: NO | EL66: NO | EM66: NO | EN66: NO | EO66: NO | EP66: NO | EQ66: NO | ER66: NO | ES66: NO | EZ66: 0 | FG66: 0 | FN66: 0 | FU66: 0 | GB66: 0 | GI66: 0 | GP66: 0 | GX66: 0 | GY66: 0 | GZ66: 0 | HA66: 0 | HB66: 0 | HC66: 0 | HD66: 0 | HE66: 0 | HL66: 0 | HS66: 0 | HZ66: 0 | IG66: 0 | IN66: 0 | IO66: 0 | IP66: 0 | IQ66: 0 | IR66: 0 | IS66: 0 | IT66: 0 | IU66: 0 | JA66: 1 | JB66: 1 | JC66: 2 | JD66: START Asia Pacific: | NG66: START Europe: | RJ66: START North America: | VM66: START Global: | ZP66: START SOUTH America: | ADS66: START Africa:
A67: 209 | B67: INREV | C67: 42779.479 | D67: Swati Srivastava | E67: Frogmore | F67: =VLOOKUP(MID(H67,SEARCH("@",H67,1),LEN(H67)-SEARCH("@",H67,1)+1),[2]Sheet1!$D:$F,3,FALSE) -> M490 | G67: Investor Relations and Client Development | H67: swatisrivastava@frogmore.co.uk | I67: +44 (0)2070166016 | J67: United Kingdom | K67: GBP | M67: 1 | V67: 0 | X67: 100 | Z67: 50 | AC67: 150 | AJ67: 0 | AQ67: 0 | AX67: 0 | BE67: 0 | BF67: 0 | BG67: 100 | BH67: 0 | BI67: 50 | BJ67: 0 | BK67: 0 | BL67: 150 | BS67: 0 | BU67: 1 | BW67: 1 | BZ67: 2 | CG67: 0 | CN67: 0 | CU67: 0 | DB67: 0 | DC67: 0 | DD67: 1 | DE67: 0 | DF67: 1 | DG67: 0 | DH67: 0 | DI67: 2 | DJ67: NO | DK67: NO | DL67: NO | DM67: NO | DN67: NO | DO67: NO | DP67: NO | DQ67: YES | DR67: NO | DS67: YES | DT67: NO | DU67: NO | DV67: NO | DW67: NO | DX67: NO | DY67: NO | DZ67: NO | EA67: NO | EB67: NO | EC67: NO | ED67: NO | EE67: NO | EF67: NO | EG67: NO | EH67: NO | EI67: NO | EJ67: NO | EK67: NO | EL67: NO | EM67: NO | EN67: NO | EO67: NO | EP67: NO | EQ67: NO | ER67: NO | ES67: NO | EW67: 8 | EZ67: 8 | FG67: 0 | FN67: 0 | FP67: 100 | FU67: 100 | GB67: 0 | GI67: 0 | GP67: 0 | GQ67: Bank | GU67: 42 | GX67: 42 | GY67: 0 | GZ67: 100 | HA67: 0 | HB67: 50 | HC67: 0 | HD67: 0 | HE67: 150 | HG67: 100 | HL67: 100 | HP67: 42 | HS67: 42 | HW67: 8 | HZ67: 8 | IG67: 0 | IN67: 0 | IO67: 0 | IP67: 100 | IQ67: 0 | IR67: 50 | IS67: 0 | IT67: 0 | IU67: 150 | IV67: 67 | IX67: 33 | JA67: 1 | JB67: 3 | JC67: 2 | JD67: START Asia Pacific: | NG67: START Europe: | NK67: 8 | NN67: 8 | NU67: 0 | OB67: 0 | OD67: 100 | OI67: 100 | OP67: 0 | OW67: 0 | PD67: 0 | PE67: Bank | PI67: 42 | PL67: 42 | PM67: 0 | PN67: 100 | PO67: 0 | PP67: 50 | PQ67: 0 | PR67: 0 | PS67: 150 | PW67: 42 | PZ67: 42 | QB67: 100 | QG67: 100 | QK67: 8 | QN67: 8 | QU67: 0 | RB67: 0 | RC67: 0 | RD67: 100 | RE67: 0 | RF67: 50 | RG67: 0 | RH67: 0 | RI67: 150 | RJ67: START North America: | VM67: START Global: | ZP67: START SOUTH America: | ADS67: START Africa:
A68: 159 | B68: INREV | C68: 42768.642 | D68: Tiffany | E68: Strand | F68: =VLOOKUP(MID(H68,SEARCH("@",H68,1),LEN(H68)-SEARCH("@",H68,1)+1),[2]Sheet1!$D:$F,3,FALSE) -> M086 | G68: Fund Manager | H68: tiffany.strand@areim.se | I68: 46704546546 | J68: Sweden | K68: SEK | M68: 1 | V68: 0 | W68: 2675.8 | AC68: 2675.8 | AJ68: 0 | AQ68: 0 | AX68: 0 | BE68: 0 | BF68: 2675.8 | BG68: 0 | BH68: 0 | BI68: 0 | BJ68: 0 | BK68: 0 | BL68: 2675.8 | BS68: 0 | BT68: 1 | BZ68: 1 | CG68: 0 | CN68: 0 | CU68: 0 | DB68: 0 | DC68: 1 | DD68: 0 | DE68: 0 | DF68: 0 | DG68: 0 | DH68: 0 | DI68: 1 | DJ68: NO | DK68: NO | DL68: NO | DM68: NO | DN68: NO | DO68: NO | DP68: YES | DQ68: NO | DR68: NO | DS68: NO | DT68: NO | DU68: NO | DV68: NO | DW68: NO | DX68: NO | DY68: NO | DZ68: NO | EA68: NO | EB68: NO | EC68: NO | ED68: NO | EE68: NO | EF68: NO | EG68: NO | EH68: NO | EI68: NO | EJ68: NO | EK68: NO | EL68: NO | EM68: NO | EN68: NO | EO68: NO | EP68: NO | EQ68: NO | ER68: NO | ES68: NO | EZ68: 0 | FA68: 1363.2 | FG68: 1363.2 | FH68: 1150 | FN68: 1150 | FU68: 0 | FV68: 100 | GB68: 100 | GI68: 0 | GP68: 0 | GQ68: Investment Manager | GR68: 62.6 | GX68: 62.6 | GY68: 2675.8 | GZ68: 0 | HA68: 0 | HB68: 0 | HC68: 0 | HD68: 0 | HE68: 2675.8 | HF68: 1150 | HL68: 1150 | HM68: 1525.8 | HS68: 1525.8 | HZ68: 0 | IG68: 0 | IN68: 0 | IO68: 2675.8 | IP68: 0 | IQ68: 0 | IR68: 0 | IS68: 0 | IT68: 0 | IU68: 2675.8 | IV68: 18 | IX68: 82 | JA68: 3 | JB68: 3 | JC68: 2 | JD68: START Asia Pacific: | NG68: START Europe: | NN68: 0 | NO68: 1363.2 | NU68: 1363.2 | NV68: 1150 | OB68: 1150 | OI68: 0 | OJ68: 100 | OP68: 100 | OW68: 0 | PD68: 0 | PE68: Investment Manager | PF68: 62.6 | PL68: 62.6 | PM68: 2675.8 | PN68: 0 | PO68: 0 | PP68: 0 | PQ68: 0 | PR68: 0 | PS68: 2675.8 | PT68: 1525.8 | PZ68: 1525.8 | QA68: 1150 | QG68: 1150 | QN68: 0 | QU68: 0 | RB68: 0 | RC68: 2675.8 | RD68: 0 | RE68: 0 | RF68: 0 | RG68: 0 | RH68: 0 | RI68: 2675.8 | RJ68: START North America: | VM68: START Global: | ZP68: START SOUTH America: | ADS68: START Africa:
A69: 50 | B69: INREV | C69: 42766.356 | D69: Nicky Wagner | E69: Prelios | F69: =VLOOKUP(MID(H69,SEARCH("@",H69,1),LEN(H69)-SEARCH("@",H69,1)+1),[2]Sheet1!$D:$F,3,FALSE) -> M087 | G69: Director Business Development | H69: nicky.wagner@prelios.com | I69: 0049 (0) 69 9202085 41 | J69: Germany | K69: EUR | M69: 2 | N69: 6 | O69: start new business in 2016 | V69: 0 | AC69: 0 | AJ69: 0 | AQ69: 0 | AX69: 0 | BE69: 0 | BF69: 0 | BG69: 0 | BH69: 0 | BI69: 0 | BJ69: 0 | BK69: 0 | BL69: 0 | BS69: 0 | BZ69: 0 | CG69: 0 | CN69: 0 | CU69: 0 | DB69: 0 | DC69: 0 | DD69: 0 | DE69: 0 | DF69: 0 | DG69: 0 | DH69: 0 | DI69: 0 | DJ69: NO | DK69: NO | DL69: NO | DM69: NO | DN69: NO | DO69: NO | DP69: NO | DQ69: NO | DR69: NO | DS69: NO | DT69: NO | DU69: NO | DV69: NO | DW69: NO | DX69: NO | DY69: NO | DZ69: NO | EA69: NO | EB69: NO | EC69: NO | ED69: NO | EE69: NO | EF69: NO | EG69: NO | EH69: NO | EI69: NO | EJ69: NO | EK69: NO | EL69: NO | EM69: NO | EN69: NO | EO69: NO | EP69: NO | EQ69: NO | ER69: NO | ES69: NO | EZ69: 0 | FG69: 0 | FN69: 0 | FU69: 0 | GB69: 0 | GI69: 0 | GP69: 0 | GX69: 0 | GY69: 0 | GZ69: 0 | HA69: 0 | HB69: 0 | HC69: 0 | HD69: 0 | HE69: 0 | HL69: 0 | HS69: 0 | HZ69: 0 | IG69: 0 | IN69: 0 | IO69: 0 | IP69: 0 | IQ69: 0 | IR69: 0 | IS69: 0 | IT69: 0 | IU69: 0 | JA69: 1 | JB69: 3 | JC69: 1 | JD69: START Asia Pacific: | NG69: START Europe: | RJ69: START North America: | VM69: START Global: | ZP69: START SOUTH America: | ADS69: START Africa:
A70: 105 | B70: INREV | C70: 42754.41 | D70: Jose Maria Ortiz | E70: ECE Real Estate Partners | F70: =VLOOKUP(MID(H70,SEARCH("@",H70,1),LEN(H70)-SEARCH("@",H70,1)+1),[2]Sheet1!$D:$F,3,FALSE) -> M657 | G70: Managing Director | H70: JoseMaria.Ortiz@ece.com | I70: 26785929 | J70: Germany | K70: EUR | M70: 2 | N70: 6 | O70: Funds are closed ended. Next funds planned for 2018 | V70: 0 | AC70: 0 | AJ70: 0 | AQ70: 0 | AX70: 0 | BE70: 0 | BF70: 0 | BG70: 0 | BH70: 0 | BI70: 0 | BJ70: 0 | BK70: 0 | BL70: 0 | BS70: 0 | BZ70: 0 | CG70: 0 | CN70: 0 | CU70: 0 | DB70: 0 | DC70: 0 | DD70: 0 | DE70: 0 | DF70: 0 | DG70: 0 | DH70: 0 | DI70: 0 | DJ70: NO | DK70: NO | DL70: NO | DM70: NO | DN70: NO | DO70: NO | DP70: NO | DQ70: NO | DR70: NO | DS70: NO | DT70: NO | DU70: NO | DV70: NO | DW70: NO | DX70: NO | DY70: NO | DZ70: NO | EA70: NO | EB70: NO | EC70: NO | ED70: NO | EE70: NO | EF70: NO | EG70: NO | EH70: NO | EI70: NO | EJ70: NO | EK70: NO | EL70: NO | EM70: NO | EN70: NO | EO70: NO | EP70: NO | EQ70: NO | ER70: NO | ES70: NO | EZ70: 0 | FG70: 0 | FN70: 0 | FU70: 0 | GB70: 0 | GI70: 0 | GP70: 0 | GX70: 0 | GY70: 0 | GZ70: 0 | HA70: 0 | HB70: 0 | HC70: 0 | HD70: 0 | HE70: 0 | HL70: 0 | HS70: 0 | HZ70: 0 | IG70: 0 | IN70: 0 | IO70: 0 | IP70: 0 | IQ70: 0 | IR70: 0 | IS70: 0 | IT70: 0 | IU70: 0 | JA70: 1 | JB70: 2 | JC70: 1 | JD70: START Asia Pacific: | NG70: START Europe: | RJ70: START North America: | VM70: START Global: | ZP70: START SOUTH America: | ADS70: START Africa:
A71: 40 | B71: INREV | C71: 42780 | D71: Laura Banks | E71: AEW | F71: =VLOOKUP(MID(H71,SEARCH("@",H71,1),LEN(H71)-SEARCH("@",H71,1)+1),[2]Sheet1!$D:$F,3,FALSE) -> M004 | G71: Investor relations associate | H71: laura.banks@aeweurope.com | I71: 0207 016 4856 | J71: United States | K71: EUR | M71: 1 | P71: 233.02 | S71: 47.52 | V71: 280.54 | W71: 845.7 | X71: 534 | Z71: 443.6 | AB71: 393 | AC71: 2216.3 | AD71: 1203.13 | AE71: 459.01 | AG71: 95.03 | AI71: 71.75 | AJ71: 1828.92 | AQ71: 0 | AX71: 0 | BE71: 0 | BF71: 2281.85 | BG71: 993.01 | BH71: 0 | BI71: 586.15 | BJ71: 0 | BK71: 464.75 | BL71: 4325.76 | BM71: 1 | BP71: 1 | BS71: 2 | BT71: 7 | BU71: 3 | BW71: 3 | BY71: 1 | BZ71: 14 | CA71: 4 | CB71: 5 | CD71: 1 | CF71: 1 | CG71: 11 | CN71: 0 | CU71: 0 | DB71: 0 | DC71: 12 | DD71: 8 | DE71: 0 | DF71: 5 | DG71: 0 | DH71: 2 | DI71: 27 | DJ71: YES | DK71: NO | DL71: NO | DM71: YES | DN71: NO | DO71: NO | DP71: YES | DQ71: YES | DR71: NO | DS71: YES | DT71: NO | DU71: YES | DV71: YES | DW71: YES | DX71: NO | DY71: YES | DZ71: NO | EA71: YES | EB71: NO | EC71: NO | ED71: NO | EE71: NO | EF71: NO | EG71: NO | EH71: NO | EI71: NO | EJ71: NO | EK71: NO | EL71: NO | EM71: NO | EN71: NO | EO71: NO | EP71: NO | EQ71: NO | ER71: NO | ES71: NO | ET71: 1079.61 | EU71: 661.51 | EW71: 277.55 | EY71: 0 | EZ71: 2018.67 | FA71: 222.46 | FB71: 331.5 | FD71: 135 | FF71: 393 | FG71: 1081.96 | FH71: 89.9 | FN71: 89.9 | FO71: 57.02 | FU71: 57.02 | FV71: 121.6 | GA71: 71.75 | GB71: 193.35 | GC71: 1 | GI71: 1 | GJ71: 171.15 | GP71: 171.15 | GQ71: International organisation, LP, LLC, Bank, Registered investment company | GR71: 539.11 | GU71: 173.6 | GX71: 712.71 | GY71: 2281.85 | GZ71: 993.01 | HA71: 0 | HB71: 586.15 | HC71: 0 | HD71: 464.75 | HE71: 4325.76 | HF71: 301.45 | HG71: 108.4 | HI71: 173.6 | HL71: 583.45 | HM71: 883.09 | HN71: 425.6 | HP71: 270 | HR71: 393 | HS71: 1971.69 | HT71: 1097.32 | HU71: 459 | HW71: 142.55 | HY71: 71.75 | HZ71: 1770.62 | IG71: 0 | IN71: 0 | IO71: 2281.86 | IP71: 993 | IQ71: 0 | IR71: 586.15 | IS71: 0 | IT71: 464.75 | IU71: 4325.76 | IV71: 6 | IX71: 94 | JA71: 3 | JB71: 3 | JC71: 1 | JD71: START Asia Pacific: | JE71: 118.79 | JH71: 47.52 | JK71: 166.31 | JL71: 23.76 | JR71: 23.76 | JY71: 0 | KF71: 0 | KM71: 0 | KT71: 0 | LA71: 0 | LB71: Bank, LLP, LC, International organisation, registered investment company | LC71: 90.47 | LI71: 90.47 | LJ71: 233.02 | LK71: 0 | LL71: 0 | LM71: 47.52 | LN71: 0 | LO71: 0 | LP71: 280.54 | LQ71: 137.99 | LW71: 137.99 | MD71: 0 | ME71: 95.03 | MH71: 47.52 | MK71: 142.55 | MR71: 0 | MY71: 0 | MZ71: 233.02 | NA71: 0 | NB71: 0 | NC71: 47.52 | ND71: 0 | NE71: 0 | NF71: 280.54 | NG71: START Europe: | NH71: 419.5 | NI71: 202.5 | NK71: 135 | NN71: 757 | NO71: 187.3 | NP71: 331.5 | NR71: 135 | NT71: 393 | NU71: 1046.8 | NV71: 89.9 | OB71: 89.9 | OI71: 0 | OJ71: 1.1 | OP71: 1.1 | OQ71: 1 | OW71: 1 | OX71: 21 | PA71: 173.6 | PD71: 194.6 | PE71: Bank, LLP, LC, International organisation, registered investment company | PF71: 125.9 | PL71: 125.9 | PM71: 845.7 | PN71: 534 | PO71: 0 | PP71: 443.6 | PQ71: 0 | PR71: 393 | PS71: 2216.3 | PT71: 745.1 | PU71: 425.6 | PW71: 270 | PY71: 393 | PZ71: 1833.7 | QA71: 93.8 | QB71: 108.4 | QD71: 173.6 | QG71: 375.8 | QH71: 6.8 | QN71: 6.8 | QU71: 0 | RB71: 0 | RC71: 845.7 | RD71: 534 | RE71: 0 | RF71: 443.6 | RG71: 0 | RH71: 393 | RI71: 2216.3 | RJ71: START North America: | RK71: 541.31 | RL71: 459.01 | RN71: 95.03 | RQ71: 1095.35 | RR71: 11.4 | RX71: 11.4 | SE71: 0 | SF71: 57.02 | SL71: 57.02 | SM71: 120.51 | SR71: 71.75 | SS71: 192.26 | SZ71: 0 | TA71: 150.06 | TG71: 150.06 | TH71: Bank, LLP, LC, International organisation, registered investment company | TI71: 322.83 | TO71: 322.83 | TP71: 1203.13 | TQ71: 459.01 | TR71: 0 | TS71: 95.03 | TT71: 0 | TU71: 71.75 | TV71: 1828.92 | UC71: 0 | UD71: 207.65 | UJ71: 207.65 | UK71: 995.48 | UL71: 459.01 | UN71: 95.03 | UP71: 71.75 | UQ71: 1621.27 | UX71: 0 | VE71: 0 | VF71: 1203.13 | VG71: 459.01 | VH71: 0 | VI71: 95.03 | VJ71: 0 | VK71: 71.75 | VL71: 1828.92 | VM71: START Global: | ZP71: START SOUTH America: | ADS71: START Africa:
A72: 219 | B72: INREV | C72: 42780 | D72: Patrik Andersson | E72: Brunswick Real Estate | F72: =VLOOKUP(MID(H72,SEARCH("@",H72,1),LEN(H72)-SEARCH("@",H72,1)+1),[2]Sheet1!$D:$F,3,FALSE) -> M319 | G72: Head of Transactions & Fund Raising | H72: patrik.andersson@leimdorfer.se | I72: +46 768 710022 | J72: Sweden | K72: EUR | M72: 1 | P72: 45 | V72: 45 | X72: 100 | Z72: 170 | AB72: 287 | AC72: 557 | AJ72: 0 | AQ72: 0 | AX72: 0 | BE72: 0 | BF72: 45 | BG72: 100 | BH72: 0 | BI72: 170 | BJ72: 0 | BK72: 287 | BL72: 602 | BM72: 1 | BS72: 1 | BU72: 1 | BW72: 1 | BY72: 1 | BZ72: 3 | CG72: 0 | CN72: 0 | CU72: 0 | DB72: 0 | DC72: 1 | DD72: 1 | DE72: 0 | DF72: 1 | DG72: 0 | DH72: 1 | DI72: 4 | DJ72: YES | DK72: NO | DL72: NO | DM72: NO | DN72: NO | DO72: NO | DP72: NO | DQ72: YES | DR72: NO | DS72: YES | DT72: NO | DU72: YES | DV72: NO | DW72: NO | DX72: NO | DY72: NO | DZ72: NO | EA72: NO | EB72: NO | EC72: NO | ED72: NO | EE72: NO | EF72: NO | EG72: NO | EH72: NO | EI72: NO | EJ72: NO | EK72: NO | EL72: NO | EM72: NO | EN72: NO | EO72: NO | EP72: NO | EQ72: NO | ER72: NO | ES72: NO | ET72: 30 | EU72: 100 | EY72: 74 | EZ72: 204 | FF72: 213 | FG72: 213 | FN72: 0 | FU72: 0 | GB72: 0 | GF72: 170 | GI72: 170 | GJ72: 15 | GP72: 15 | GX72: 0 | GY72: 45 | GZ72: 100 | HA72: 0 | HB72: 170 | HC72: 0 | HD72: 287 | HE72: 602 | HL72: 0 | HM72: 45 | HN72: 100 | HP72: 170 | HR72: 287 | HS72: 602 | HZ72: 0 | IG72: 0 | IN72: 0 | IO72: 45 | IP72: 100 | IQ72: 0 | IR72: 170 | IS72: 0 | IT72: 287 | IU72: 602 | IX72: 100 | JA72: 1 | JB72: 1 | JC72: 1 | JD72: START Asia Pacific: | JE72: 30 | JK72: 30 | JR72: 0 | JY72: 0 | KF72: 0 | KM72: 0 | KT72: 0 | KU72: 15 | LA72: 15 | LI72: 0 | LJ72: 45 | LK72: 0 | LL72: 0 | LM72: 0 | LN72: 0 | LO72: 0 | LP72: 45 | LQ72: 45 | LW72: 45 | MD72: 0 | MK72: 0 | MR72: 0 | MY72: 0 | MZ72: 45 | NA72: 0 | NB72: 0 | NC72: 0 | ND72: 0 | NE72: 0 | NF72: 45 | NG72: START Europe: | NI72: 100 | NM72: 83 | NN72: 183 | NT72: 204 | NU72: 204 | OB72: 0 | OI72: 0 | OP72: 0 | OT72: 170 | OW72: 170 | PD72: 0 | PL72: 0 | PM72: 0 | PN72: 100 | PO72: 0 | PP72: 170 | PQ72: 0 | PR72: 287 | PS72: 557 | PU72: 100 | PW72: 170 | PY72: 287 | PZ72: 557 | QG72: 0 | QN72: 0 | QU72: 0 | RB72: 0 | RC72: 0 | RD72: 100 | RE72: 0 | RF72: 170 | RG72: 0 | RH72: 287 | RI72: 557 | RJ72: START North America: | VM72: START Global: | ZP72: START SOUTH America: | ADS72: START Africa:
A73: 57 | B73: INREV | C73: 42780 | D73: Iris Gelten | E73: Bouwinvest | F73: =VLOOKUP(MID(H73,SEARCH("@",H73,1),LEN(H73)-SEARCH("@",H73,1)+1),[2]Sheet1!$D:$F,3,FALSE) -> M660 | G73: Coporate marketing & communication | H73: i.gelten@bouwinvest.nl | I73: 622227735 | J73: Netherlands | K73: EUR | M73: 1 | V73: 0 | AC73: 0 | AJ73: 0 | AK73: 557 | AM73: 279 | AQ73: 836 | AX73: 0 | BE73: 0 | BF73: 557 | BG73: 0 | BH73: 279 | BI73: 0 | BJ73: 0 | BK73: 0 | BL73: 836 | BS73: 0 | BZ73: 0 | CG73: 0 | CH73: 3 | CJ73: 1 | CN73: 4 | CU73: 0 | DB73: 0 | DC73: 3 | DD73: 0 | DE73: 1 | DF73: 0 | DG73: 0 | DH73: 0 | DI73: 4 | DJ73: NO | DK73: NO | DL73: NO | DM73: NO | DN73: NO | DO73: NO | DP73: NO | DQ73: NO | DR73: NO | DS73: NO | DT73: NO | DU73: NO | DV73: NO | DW73: NO | DX73: NO | DY73: NO | DZ73: NO | EA73: NO | EB73: YES | EC73: NO | ED73: YES | EE73: NO | EF73: NO | EG73: NO | EH73: NO | EI73: NO | EJ73: NO | EK73: NO | EL73: NO | EM73: NO | EN73: NO | EO73: NO | EP73: NO | EQ73: NO | ER73: NO | ES73: NO | ET73: 557 | EV73: 279 | EZ73: 836 | FG73: 0 | FN73: 0 | FU73: 0 | GB73: 0 | GI73: 0 | GP73: 0 | GX73: 0 | GY73: 557 | GZ73: 0 | HA73: 279 | HB73: 0 | HC73: 0 | HD73: 0 | HE73: 836 | HL73: 0 | HM73: 557 | HO73: 279 | HS73: 836 | HZ73: 0 | IG73: 0 | IN73: 0 | IO73: 557 | IP73: 0 | IQ73: 279 | IR73: 0 | IS73: 0 | IT73: 0 | IU73: 836 | IX73: 100 | JA73: 1 | JB73: 3 | JC73: 1 | JD73: START Asia Pacific: | NG73: START Europe: | RJ73: START North America: | VM73: START Global: | VN73: 557 | VP73: 279 | VT73: 836 | WA73: 0 | WH73: 0 | WO73: 0 | WV73: 0 | XC73: 0 | XJ73: 0 | XR73: 0 | XS73: 557 | XT73: 0 | XU73: 279 | XV73: 0 | XW73: 0 | XX73: 0 | XY73: 836 | XZ73: 557 | YB73: 279 | YF73: 836 | YM73: 0 | YT73: 0 | ZA73: 0 | ZH73: 0 | ZI73: 557 | ZJ73: 0 | ZK73: 279 | ZL73: 0 | ZM73: 0 | ZN73: 0 | ZO73: 836 | ZP73: START SOUTH America: | ADS73: START Africa:
A74: 64 | B74: INREV | C74: 42780 | D74: Jon Starek | E74: Prologis | F74: =VLOOKUP(MID(H74,SEARCH("@",H74,1),LEN(H74)-SEARCH("@",H74,1)+1),[2]Sheet1!$D:$F,3,FALSE) -> M024 | G74: Director, Global Fund Operations | H74: jstarek@prologis.com | I74: +1 (303) 5675268 | J74: United States | K74: USD | M74: 1 | S74: 750 | V74: 750 | W74: 433.66 | AC74: 433.66 | AD74: 317 | AJ74: 317 | AQ74: 0 | AX74: 0 | BE74: 0 | BF74: 750.66 | BG74: 0 | BH74: 0 | BI74: 750 | BJ74: 0 | BK74: 0 | BL74: 1500.66 | BP74: 1 | BS74: 1 | BT74: 1 | BZ74: 1 | CA74: 1 | CG74: 1 | CN74: 0 | CU74: 0 | DB74: 0 | DC74: 2 | DD74: 0 | DE74: 0 | DF74: 1 | DG74: 0 | DH74: 0 | DI74: 3 | DJ74: NO | DK74: NO | DL74: NO | DM74: YES | DN74: NO | DO74: NO | DP74: YES | DQ74: NO | DR74: NO | DS74: NO | DT74: NO | DU74: NO | DV74: YES | DW74: NO | DX74: NO | DY74: NO | DZ74: NO | EA74: NO | EB74: NO | EC74: NO | ED74: NO | EE74: NO | EF74: NO | EG74: NO | EH74: NO | EI74: NO | EJ74: NO | EK74: NO | EL74: NO | EM74: NO | EN74: NO | EO74: NO | EP74: NO | EQ74: NO | ER74: NO | ES74: NO | ET74: 306.69 | EZ74: 306.69 | FA74: 183.41 | FG74: 183.41 | FK74: 750 | FN74: 750 | FU74: 0 | GB74: 0 | GC74: 247.56 | GI74: 247.56 | GP74: 0 | GQ74: 40 Act Investment Company | GR74: 13 | GX74: 13 | GY74: 750.66 | GZ74: 0 | HA74: 0 | HB74: 750 | HC74: 0 | HD74: 0 | HE74: 1500.66 | HF74: 46.38 | HI74: 750 | HL74: 796.38 | HM74: 541.28 | HS74: 541.28 | HT74: 163 | HZ74: 163 | IG74: 0 | IN74: 0 | IO74: 750.66 | IP74: 0 | IQ74: 0 | IR74: 750 | IS74: 0 | IT74: 0 | IU74: 1500.66 | IX74: 100 | JA74: 1 | JB74: 3 | JC74: 2 | JD74: START Asia Pacific: | JK74: 0 | JR74: 0 | JV74: 750 | JY74: 750 | KF74: 0 | KM74: 0 | KT74: 0 | LA74: 0 | LI74: 0 | LJ74: 0 | LK74: 0 | LL74: 0 | LM74: 750 | LN74: 0 | LO74: 0 | LP74: 750 | LW74: 0 | MD74: 0 | MK74: 0 | MR74: 0 | MV74: 750 | MY74: 750 | MZ74: 0 | NA74: 0 | NB74: 0 | NC74: 750 | ND74: 0 | NE74: 0 | NF74: 750 | NG74: START Europe: | NH74: 77.69 | NN74: 77.69 | NO74: 183.41 | NU74: 183.41 | OB74: 0 | OI74: 0 | OP74: 0 | OQ74: 172.56 | OW74: 172.56 | PD74: 0 | PL74: 0 | PM74: 433.66 | PN74: 0 | PO74: 0 | PP74: 0 | PQ74: 0 | PR74: 0 | PS74: 433.66 | PT74: 387.28 | PZ74: 387.28 | QA74: 46.38 | QG74: 46.38 | QN74: 0 | QU74: 0 | RB74: 0 | RC74: 433.66 | RD74: 0 | RE74: 0 | RF74: 0 | RG74: 0 | RH74: 0 | RI74: 433.66 | RJ74: START North America: | RK74: 229 | RQ74: 229 | RX74: 0 | SE74: 0 | SL74: 0 | SS74: 0 | ST74: 75 | SZ74: 75 | TG74: 0 | TH74: 40 Act Investment Company | TI74: 13 | TO74: 13 | TP74: 317 | TQ74: 0 | TR74: 0 | TS74: 0 | TT74: 0 | TU74: 0 | TV74: 317 | TW74: 154 | UC74: 154 | UJ74: 0 | UK74: 163 | UQ74: 163 | UX74: 0 | VE74: 0 | VF74: 317 | VG74: 0 | VH74: 0 | VI74: 0 | VJ74: 0 | VK74: 0 | VL74: 317 | VM74: START Global: | ZP74: START SOUTH America: | ADS74: START Africa:
A75: 60 | B75: INREV | C75: 42773.714 | D75: Alice Cahill | E75: ICG | F75: =VLOOKUP(MID(H75,SEARCH("@",H75,1),LEN(H75)-SEARCH("@",H75,1)+1),[2]Sheet1!$D:$F,3,FALSE) -> M674 | G75: Analyst | H75: alice.cahill@icgam.com | I75: 7738161512 | J75: United Kingdom | K75: GBP | M75: 1 | V75: 0 | AB75: 304 | AC75: 304 | AJ75: 0 | AQ75: 0 | AX75: 0 | BE75: 0 | BF75: 0 | BG75: 0 | BH75: 0 | BI75: 0 | BJ75: 0 | BK75: 304 | BL75: 304 | BS75: 0 | BY75: 1 | BZ75: 1 | CG75: 0 | CN75: 0 | CU75: 0 | DB75: 0 | DC75: 0 | DD75: 0 | DE75: 0 | DF75: 0 | DG75: 0 | DH75: 1 | DI75: 1 | DJ75: NO | DK75: NO | DL75: NO | DM75: NO | DN75: NO | DO75: NO | DP75: NO | DQ75: NO | DR75: NO | DS75: NO | DT75: NO | DU75: YES | DV75: NO | DW75: NO | DX75: NO | DY75: NO | DZ75: NO | EA75: NO | EB75: NO | EC75: NO | ED75: NO | EE75: NO | EF75: NO | EG75: NO | EH75: NO | EI75: NO | EJ75: NO | EK75: NO | EL75: NO | EM75: NO | EN75: NO | EO75: NO | EP75: NO | EQ75: NO | ER75: NO | ES75: NO | EY75: 225 | EZ75: 225 | FF75: 15 | FG75: 15 | FN75: 0 | FU75: 0 | GB75: 0 | GH75: 9 | GI75: 9 | GP75: 0 | GQ75: Industry body, Bank and Asset Manager | GW75: 55 | GX75: 55 | GY75: 0 | GZ75: 0 | HA75: 0 | HB75: 0 | HC75: 0 | HD75: 304 | HE75: 304 | HK75: 50 | HL75: 50 | HR75: 254 | HS75: 254 | HZ75: 0 | IG75: 0 | IN75: 0 | IO75: 0 | IP75: 0 | IQ75: 0 | IR75: 0 | IS75: 0 | IT75: 304 | IU75: 304 | IX75: 100 | JA75: 1 | JB75: 3 | JC75: 1 | JD75: START Asia Pacific: | JJ75: 225 | JK75: 225 | JQ75: 15 | JR75: 15 | JY75: 0 | KF75: 0 | KM75: 0 | KS75: 9 | KT75: 9 | LA75: 0 | LB75: Industry body | LH75: 55 | LI75: 55 | LJ75: 0 | LK75: 0 | LL75: 0 | LM75: 0 | LN75: 0 | LO75: 304 | LP75: 304 | LV75: 254 | LW75: 254 | MC75: 50 | MD75: 50 | MK75: 0 | MR75: 0 | MY75: 0 | MZ75: 0 | NA75: 0 | NB75: 0 | NC75: 0 | ND75: 0 | NE75: 304 | NF75: 304 | NG75: START Europe: | NM75: 225 | NN75: 225 | NT75: 15 | NU75: 15 | OB75: 0 | OI75: 0 | OP75: 0 | OV75: 9 | OW75: 9 | PD75: 0 | PK75: 55 | PL75: 55 | PM75: 0 | PN75: 0 | PO75: 0 | PP75: 0 | PQ75: 0 | PR75: 304 | PS75: 304 | PY75: 254 | PZ75: 254 | QF75: 50 | QG75: 50 | QN75: 0 | QU75: 0 | RB75: 0 | RC75: 0 | RD75: 0 | RE75: 0 | RF75: 0 | RG75: 0 | RH75: 304 | RI75: 304 | RJ75: START North America: | VM75: START Global: | ZP75: START SOUTH America: | ADS75: START Africa:
A76: 80 | B76: INREV | C76: 42779.598 | D76: Maximilian Schneidler | E76: Quantum Immobilien Kapitalverwaltungsgesellschaft mbH | F76: =VLOOKUP(MID(H76,SEARCH("@",H76,1),LEN(H76)-SEARCH("@",H76,1)+1),[2]Sheet1!$D:$F,3,FALSE) -> M346 | G76: Investor Relations | H76: mas@quantum.ag | I76: +49 (89) 15 90 01 - 336 | J76: Germany | K76: EUR | M76: 1 | V76: 0 | W76: 150.5 | X76: 229 | Z76: 201.3 | AC76: 580.8 | AJ76: 0 | AQ76: 0 | AX76: 0 | BE76: 0 | BF76: 150.5 | BG76: 229 | BH76: 0 | BI76: 201.3 | BJ76: 0 | BK76: 0 | BL76: 580.8 | BS76: 0 | BT76: 1 | BU76: 4 | BW76: 3 | BZ76: 8 | CG76: 0 | CN76: 0 | CU76: 0 | DB76: 0 | DC76: 1 | DD76: 4 | DE76: 0 | DF76: 3 | DG76: 0 | DH76: 0 | DI76: 8 | DJ76: NO | DK76: NO | DL76: NO | DM76: NO | DN76: NO | DO76: NO | DP76: YES | DQ76: YES | DR76: NO | DS76: YES | DT76: NO | DU76: NO | DV76: NO | DW76: NO | DX76: NO | DY76: NO | DZ76: NO | EA76: NO | EB76: NO | EC76: NO | ED76: NO | EE76: NO | EF76: NO | EG76: NO | EH76: NO | EI76: NO | EJ76: NO | EK76: NO | EL76: NO | EM76: NO | EN76: NO | EO76: NO | EP76: NO | EQ76: NO | ER76: NO | ES76: NO | ET76: 35 | EU76: 90 | EW76: 182.05 | EZ76: 307.05 | FA76: 26.5 | FB76: 139 | FD76: 19.25 | FG76: 184.75 | FN76: 0 | FU76: 0 | GB76: 0 | GC76: 46 | GI76: 46 | GP76: 0 | GQ76: Savings banks | GR76: 43 | GX76: 43 | GY76: 150.5 | GZ76: 229 | HA76: 0 | HB76: 201.3 | HC76: 0 | HD76: 0 | HE76: 580.8 | HL76: 0 | HM76: 150.5 | HN76: 229 | HP76: 201.3 | HS76: 580.8 | HZ76: 0 | IG76: 0 | IN76: 0 | IO76: 150.5 | IP76: 229 | IQ76: 0 | IR76: 201.3 | IS76: 0 | IT76: 0 | IU76: 580.8 | IX76: 100 | JA76: 1 | JB76: 3 | JC76: 1 | JD76: START Asia Pacific: | NG76: START Europe: | NH76: 35 | NI76: 90 | NK76: 182.05 | NN76: 307.05 | NO76: 26.5 | NP76: 139 | NR76: 19.25 | NU76: 184.75 | OB76: 0 | OI76: 0 | OP76: 0 | OQ76: 46 | OW76: 46 | PD76: 0 | PE76: Savings banks | PF76: 43 | PL76: 43 | PM76: 150.5 | PN76: 229 | PO76: 0 | PP76: 201.3 | PQ76: 0 | PR76: 0 | PS76: 580.8 | PT76: 150.5 | PU76: 229 | PW76: 201.3 | PZ76: 580.8 | QG76: 0 | QN76: 0 | QU76: 0 | RB76: 0 | RC76: 150.5 | RD76: 229 | RE76: 0 | RF76: 201.3 | RG76: 0 | RH76: 0 | RI76: 580.8 | RJ76: START North America: | VM76: START Global: | ZP76: START SOUTH America: | ADS76: START Africa:
A77: 79 | B77: INREV | C77: 42780 | D77: Marsha Sinninghe | E77: Syntrus Achmea Real Estate & Finance | F77: =VLOOKUP(MID(H77,SEARCH("@",H77,1),LEN(H77)-SEARCH("@",H77,1)+1),[2]Sheet1!$D:$F,3,FALSE) -> M710 | G77: Proposition Manager | H77: marsha.sinninghe@achmeavastgoed.nl | I77: 31610990835 | J77: Netherlands | K77: EUR | M77: 1 | S77: 10 | V77: 10 | W77: 206.4 | X77: 464 | Z77: 16 | AB77: 571.5 | AC77: 1257.9 | AG77: 16 | AJ77: 16 | AQ77: 0 | AX77: 0 | BE77: 0 | BF77: 206.4 | BG77: 464 | BH77: 0 | BI77: 42 | BJ77: 0 | BK77: 571.5 | BL77: 1283.9 | BP77: 1 | BS77: 1 | BT77: 3 | BU77: 3 | BW77: 1 | BY77: 1 | BZ77: 8 | CD77: 1 | CG77: 1 | CN77: 0 | CU77: 0 | DB77: 0 | DC77: 3 | DD77: 3 | DE77: 0 | DF77: 3 | DG77: 0 | DH77: 1 | DI77: 10 | DJ77: NO | DK77: NO | DL77: NO | DM77: YES | DN77: NO | DO77: NO | DP77: YES | DQ77: YES | DR77: NO | DS77: YES | DT77: NO | DU77: YES | DV77: NO | DW77: NO | DX77: NO | DY77: YES | DZ77: NO | EA77: NO | EB77: NO | EC77: NO | ED77: NO | EE77: NO | EF77: NO | EG77: NO | EH77: NO | EI77: NO | EJ77: NO | EK77: NO | EL77: NO | EM77: NO | EN77: NO | EO77: NO | EP77: NO | EQ77: NO | ER77: NO | ES77: NO | ET77: 131.4 | EU77: 464 | EW77: 42 | EY77: 521.5 | EZ77: 1158.9 | FA77: 75 | FF77: 50 | FG77: 125 | FN77: 0 | FU77: 0 | GB77: 0 | GI77: 0 | GP77: 0 | GX77: 0 | GY77: 206.4 | GZ77: 464 | HA77: 0 | HB77: 42 | HC77: 0 | HD77: 571.5 | HE77: 1283.9 | HL77: 0 | HM77: 206.4 | HN77: 464 | HP77: 42 | HR77: 571.5 | HS77: 1283.9 | HZ77: 0 | IG77: 0 | IN77: 0 | IO77: 206.4 | IP77: 464 | IQ77: 0 | IR77: 42 | IS77: 0 | IT77: 571.5 | IU77: 1283.9 | IX77: 100 | JA77: 3 | JB77: 3 | JC77: 1 | JD77: START Asia Pacific: | JH77: 10 | JK77: 10 | JR77: 0 | JY77: 0 | KF77: 0 | KM77: 0 | KT77: 0 | LA77: 0 | LI77: 0 | LJ77: 0 | LK77: 0 | LL77: 0 | LM77: 10 | LN77: 0 | LO77: 0 | LP77: 10 | LT77: 10 | LW77: 10 | MD77: 0 | MK77: 0 | MR77: 0 | MY77: 0 | MZ77: 0 | NA77: 0 | NB77: 0 | NC77: 10 | ND77: 0 | NE77: 0 | NF77: 10 | NG77: START Europe: | NH77: 131.4 | NI77: 464 | NK77: 16 | NM77: 521.5 | NN77: 1132.9 | NO77: 75 | NT77: 50 | NU77: 125 | OB77: 0 | OI77: 0 | OP77: 0 | OW77: 0 | PD77: 0 | PL77: 0 | PM77: 206.4 | PN77: 464 | PO77: 0 | PP77: 16 | PQ77: 0 | PR77: 571.5 | PS77: 1257.9 | PT77: 206.4 | PU77: 464 | PW77: 16 | PY77: 571.5 | PZ77: 1257.9 | QG77: 0 | QN77: 0 | QU77: 0 | RB77: 0 | RC77: 206.4 | RD77: 464 | RE77: 0 | RF77: 16 | RG77: 0 | RH77: 571.5 | RI77: 1257.9 | RJ77: START North America: | RN77: 16 | RQ77: 16 | RX77: 0 | SE77: 0 | SL77: 0 | SS77: 0 | SZ77: 0 | TG77: 0 | TO77: 0 | TP77: 0 | TQ77: 0 | TR77: 0 | TS77: 16 | TT77: 0 | TU77: 0 | TV77: 16 | TZ77: 16 | UC77: 16 | UJ77: 0 | UQ77: 0 | UX77: 0 | VE77: 0 | VF77: 0 | VG77: 0 | VH77: 0 | VI77: 16 | VJ77: 0 | VK77: 0 | VL77: 16 | VM77: START Global: | ZP77: START SOUTH America: | ADS77: START Africa:
A78: 37 | B78: INREV | C78: 42780 | D78: Rebecca Madsen | E78: Grosvenor | F78: =VLOOKUP(MID(H78,SEARCH("@",H78,1),LEN(H78)-SEARCH("@",H78,1)+1),[2]Sheet1!$D:$F,3,FALSE) -> M052 | G78: Analyst, Capital Markets | H78: rebecca.madsen@grosvenor.com | I78: 2073126345 | J78: United Kingdom | K78: GBP | M78: 1 | V78: 0 | Z78: 30.7 | AC78: 30.7 | AJ78: 0 | AQ78: 0 | AX78: 0 | BE78: 0 | BF78: 0 | BG78: 0 | BH78: 0 | BI78: 30.7 | BJ78: 0 | BK78: 0 | BL78: 30.7 | BS78: 0 | BW78: 1 | BZ78: 1 | CG78: 0 | CN78: 0 | CU78: 0 | DB78: 0 | DC78: 0 | DD78: 0 | DE78: 0 | DF78: 1 | DG78: 0 | DH78: 0 | DI78: 1 | DJ78: NO | DK78: NO | DL78: NO | DM78: NO | DN78: NO | DO78: NO | DP78: NO | DQ78: NO | DR78: NO | DS78: YES | DT78: NO | DU78: NO | DV78: NO | DW78: NO | DX78: NO | DY78: NO | DZ78: NO | EA78: NO | EB78: NO | EC78: NO | ED78: NO | EE78: NO | EF78: NO | EG78: NO | EH78: NO | EI78: NO | EJ78: NO | EK78: NO | EL78: NO | EM78: NO | EN78: NO | EO78: NO | EP78: NO | EQ78: NO | ER78: NO | ES78: NO | EZ78: 0 | FG78: 0 | FN78: 0 | FU78: 0 | GB78: 0 | GI78: 0 | GP78: 0 | GQ78: Investment Insitutions | GU78: 30.7 | GX78: 30.7 | GY78: 0 | GZ78: 0 | HA78: 0 | HB78: 30.7 | HC78: 0 | HD78: 0 | HE78: 30.7 | HI78: 30.7 | HL78: 30.7 | HS78: 0 | HZ78: 0 | IG78: 0 | IN78: 0 | IO78: 0 | IP78: 0 | IQ78: 0 | IR78: 30.7 | IS78: 0 | IT78: 0 | IU78: 30.7 | IV78: 0 | IX78: 100 | JA78: 1 | JB78: 3 | JC78: 1 | JD78: START Asia Pacific: | NG78: START Europe: | NN78: 0 | NU78: 0 | OB78: 0 | OI78: 0 | OP78: 0 | OW78: 0 | PD78: 0 | PE78: investment institutions | PI78: 30.7 | PL78: 30.7 | PM78: 0 | PN78: 0 | PO78: 0 | PP78: 30.7 | PQ78: 0 | PR78: 0 | PS78: 30.7 | PZ78: 0 | QD78: 30.7 | QG78: 30.7 | QN78: 0 | QU78: 0 | RB78: 0 | RC78: 0 | RD78: 0 | RE78: 0 | RF78: 30.7 | RG78: 0 | RH78: 0 | RI78: 30.7 | RJ78: START North America: | VM78: START Global: | ZP78: START SOUTH America: | ADS78: START Africa:
A79: 156 | B79: INREV | C79: 42767.561 | D79: KEVIN AITCHISON | E79: KF Investment Management | F79: =VLOOKUP(MID(H79,SEARCH("@",H79,1),LEN(H79)-SEARCH("@",H79,1)+1),[2]Sheet1!$D:$F,3,FALSE) -> M04070 | G79: CEO | H79: kevin.aitchison@kf-im.com | I79: 2078615103 | J79: United Kingdom | K79: GBP | M79: 1 | V79: 0 | W79: 0.3 | X79: 0.3 | AC79: 0.6 | AJ79: 0 | AQ79: 0 | AX79: 0 | BE79: 0 | BF79: 0.3 | BG79: 0.3 | BH79: 0 | BI79: 0 | BJ79: 0 | BK79: 0 | BL79: 0.6 | BS79: 0 | BT79: 1 | BU79: 1 | BZ79: 2 | CG79: 0 | CN79: 0 | CU79: 0 | DB79: 0 | DC79: 1 | DD79: 1 | DE79: 0 | DF79: 0 | DG79: 0 | DH79: 0 | DI79: 2 | DJ79: NO | DK79: NO | DL79: NO | DM79: NO | DN79: NO | DO79: NO | DP79: YES | DQ79: YES | DR79: NO | DS79: NO | DT79: NO | DU79: NO | DV79: NO | DW79: NO | DX79: NO | DY79: NO | DZ79: NO | EA79: NO | EB79: NO | EC79: NO | ED79: NO | EE79: NO | EF79: NO | EG79: NO | EH79: NO | EI79: NO | EJ79: NO | EK79: NO | EL79: NO | EM79: NO | EN79: NO | EO79: NO | EP79: NO | EQ79: NO | ER79: NO | ES79: NO | ET79: 0.3 | EU79: 0.3 | EZ79: 0.6 | FG79: 0 | FN79: 0 | FU79: 0 | GB79: 0 | GI79: 0 | GP79: 0 | GX79: 0 | GY79: 0.3 | GZ79: 0.3 | HA79: 0 | HB79: 0 | HC79: 0 | HD79: 0 | HE79: 0.6 | HL79: 0 | HM79: 0.3 | HN79: 0.3 | HS79: 0.6 | HZ79: 0 | IG79: 0 | IN79: 0 | IO79: 0.3 | IP79: 0.3 | IQ79: 0 | IR79: 0 | IS79: 0 | IT79: 0 | IU79: 0.6 | IV79: 0 | IX79: 100 | JA79: 1 | JB79: 3 | JC79: 1 | JD79: START Asia Pacific: | NG79: START Europe: | NH79: 0.3 | NI79: 0.3 | NN79: 0.6 | NU79: 0 | OB79: 0 | OI79: 0 | OP79: 0 | OW79: 0 | PD79: 0 | PL79: 0 | PM79: 0.3 | PN79: 0.3 | PO79: 0 | PP79: 0 | PQ79: 0 | PR79: 0 | PS79: 0.6 | PT79: 0.3 | PU79: 0.3 | PZ79: 0.6 | QG79: 0 | QN79: 0 | QU79: 0 | RB79: 0 | RC79: 0.3 | RD79: 0.3 | RE79: 0 | RF79: 0 | RG79: 0 | RH79: 0 | RI79: 0.6 | RJ79: START North America: | VM79: START Global: | ZP79: START SOUTH America: | ADS79: START Africa:
A80: 143 | B80: INREV | C80: 42766.407 | D80: Marta Herrero | E80: Altan Capital | F80: =VLOOKUP(MID(H80,SEARCH("@",H80,1),LEN(H80)-SEARCH("@",H80,1)+1),[2]Sheet1!$D:$F,3,FALSE) -> M226 | G80: Executive Director | H80: mherrero@altancapital.com | I80: 91 426 24 47 | J80: Spain | K80: EUR | M80: 2 | N80: 6 | O80: Timing | V80: 0 | AC80: 0 | AJ80: 0 | AQ80: 0 | AX80: 0 | BE80: 0 | BF80: 0 | BG80: 0 | BH80: 0 | BI80: 0 | BJ80: 0 | BK80: 0 | BL80: 0 | BS80: 0 | BZ80: 0 | CG80: 0 | CN80: 0 | CU80: 0 | DB80: 0 | DC80: 0 | DD80: 0 | DE80: 0 | DF80: 0 | DG80: 0 | DH80: 0 | DI80: 0 | DJ80: NO | DK80: NO | DL80: NO | DM80: NO | DN80: NO | DO80: NO | DP80: NO | DQ80: NO | DR80: NO | DS80: NO | DT80: NO | DU80: NO | DV80: NO | DW80: NO | DX80: NO | DY80: NO | DZ80: NO | EA80: NO | EB80: NO | EC80: NO | ED80: NO | EE80: NO | EF80: NO | EG80: NO | EH80: NO | EI80: NO | EJ80: NO | EK80: NO | EL80: NO | EM80: NO | EN80: NO | EO80: NO | EP80: NO | EQ80: NO | ER80: NO | ES80: NO | EZ80: 0 | FG80: 0 | FN80: 0 | FU80: 0 | GB80: 0 | GI80: 0 | GP80: 0 | GX80: 0 | GY80: 0 | GZ80: 0 | HA80: 0 | HB80: 0 | HC80: 0 | HD80: 0 | HE80: 0 | HL80: 0 | HS80: 0 | HZ80: 0 | IG80: 0 | IN80: 0 | IO80: 0 | IP80: 0 | IQ80: 0 | IR80: 0 | IS80: 0 | IT80: 0 | IU80: 0 | JA80: 1 | JB80: 1 | JC80: 1 | JD80: START Asia Pacific: | NG80: START Europe: | RJ80: START North America: | VM80: START Global: | ZP80: START SOUTH America: | ADS80: START Africa:
A81: 141 | B81: INREV | C81: 42766.361 | D81: Charlotte Hultman | E81: Vistra | F81: =VLOOKUP(MID(H81,SEARCH("@",H81,1),LEN(H81)-SEARCH("@",H81,1)+1),[2]Sheet1!$D:$F,3,FALSE) -> M661 | G81: Group Commercial Director Europe | H81: charlotte.hultman@vistra.com | I81: 352621889676 | J81: Hong Kong | K81: EUR | M81: 2 | N81: 6 | O81: We are a service provider and do not raise any funds | V81: 0 | AC81: 0 | AJ81: 0 | AQ81: 0 | AX81: 0 | BE81: 0 | BF81: 0 | BG81: 0 | BH81: 0 | BI81: 0 | BJ81: 0 | BK81: 0 | BL81: 0 | BS81: 0 | BZ81: 0 | CG81: 0 | CN81: 0 | CU81: 0 | DB81: 0 | DC81: 0 | DD81: 0 | DE81: 0 | DF81: 0 | DG81: 0 | DH81: 0 | DI81: 0 | DJ81: NO | DK81: NO | DL81: NO | DM81: NO | DN81: NO | DO81: NO | DP81: NO | DQ81: NO | DR81: NO | DS81: NO | DT81: NO | DU81: NO | DV81: NO | DW81: NO | DX81: NO | DY81: NO | DZ81: NO | EA81: NO | EB81: NO | EC81: NO | ED81: NO | EE81: NO | EF81: NO | EG81: NO | EH81: NO | EI81: NO | EJ81: NO | EK81: NO | EL81: NO | EM81: NO | EN81: NO | EO81: NO | EP81: NO | EQ81: NO | ER81: NO | ES81: NO | EZ81: 0 | FG81: 0 | FN81: 0 | FU81: 0 | GB81: 0 | GI81: 0 | GP81: 0 | GX81: 0 | GY81: 0 | GZ81: 0 | HA81: 0 | HB81: 0 | HC81: 0 | HD81: 0 | HE81: 0 | HL81: 0 | HS81: 0 | HZ81: 0 | IG81: 0 | IN81: 0 | IO81: 0 | IP81: 0 | IQ81: 0 | IR81: 0 | IS81: 0 | IT81: 0 | IU81: 0 | JA81: 1 | JB81: 2 | JC81: 1 | JD81: START Asia Pacific: | NG81: START Europe: | RJ81: START North America: | VM81: START Global: | ZP81: START SOUTH America: | ADS81: START Africa:
A82: 107 | B82: INREV | C82: 42754.49 | D82: Joep Munten | E82: Hartelt Fund Management B.V. | F82: =VLOOKUP(MID(H82,SEARCH("@",H82,1),LEN(H82)-SEARCH("@",H82,1)+1),[2]Sheet1!$D:$F,3,FALSE) -> M2508 | G82: CFO | H82: j.munten@hartelt-fm.com | I82: 31433257100 | J82: Netherlands | K82: EUR | M82: 1 | V82: 0 | W82: 80 | AC82: 80 | AJ82: 0 | AQ82: 0 | AX82: 0 | BE82: 0 | BF82: 80 | BG82: 0 | BH82: 0 | BI82: 0 | BJ82: 0 | BK82: 0 | BL82: 80 | BS82: 0 | BT82: 1 | BZ82: 1 | CG82: 0 | CN82: 0 | CU82: 0 | DB82: 0 | DC82: 1 | DD82: 0 | DE82: 0 | DF82: 0 | DG82: 0 | DH82: 0 | DI82: 1 | DJ82: NO | DK82: NO | DL82: NO | DM82: NO | DN82: NO | DO82: NO | DP82: YES | DQ82: NO | DR82: NO | DS82: NO | DT82: NO | DU82: NO | DV82: NO | DW82: NO | DX82: NO | DY82: NO | DZ82: NO | EA82: NO | EB82: NO | EC82: NO | ED82: NO | EE82: NO | EF82: NO | EG82: NO | EH82: NO | EI82: NO | EJ82: NO | EK82: NO | EL82: NO | EM82: NO | EN82: NO | EO82: NO | EP82: NO | EQ82: NO | ER82: NO | ES82: NO | ET82: 80 | EZ82: 80 | FG82: 0 | FN82: 0 | FU82: 0 | GB82: 0 | GI82: 0 | GP82: 0 | GX82: 0 | GY82: 80 | GZ82: 0 | HA82: 0 | HB82: 0 | HC82: 0 | HD82: 0 | HE82: 80 | HL82: 0 | HM82: 80 | HS82: 80 | HZ82: 0 | IG82: 0 | IN82: 0 | IO82: 80 | IP82: 0 | IQ82: 0 | IR82: 0 | IS82: 0 | IT82: 0 | IU82: 80 | IX82: 100 | JA82: 1 | JB82: 1 | JC82: 2 | JD82: START Asia Pacific: | NG82: START Europe: | NH82: 80 | NN82: 80 | NU82: 0 | OB82: 0 | OI82: 0 | OP82: 0 | OW82: 0 | PD82: 0 | PL82: 0 | PM82: 80 | PN82: 0 | PO82: 0 | PP82: 0 | PQ82: 0 | PR82: 0 | PS82: 80 | PT82: 80 | PZ82: 80 | QG82: 0 | QN82: 0 | QU82: 0 | RB82: 0 | RC82: 80 | RD82: 0 | RE82: 0 | RF82: 0 | RG82: 0 | RH82: 0 | RI82: 80 | RJ82: START North America: | VM82: START Global: | ZP82: START SOUTH America: | ADS82: START Africa:
A83: 153 | B83: INREV | C83: 42766.691 | D83: Giovanni Perin | E83: Threestones Capital | F83: =VLOOKUP(MID(H83,SEARCH("@",H83,1),LEN(H83)-SEARCH("@",H83,1)+1),[2]Sheet1!$D:$F,3,FALSE) -> M751 | G83: Director | H83: g.perin@threestonescapital.com | I83: 3522484711 | J83: Luxembourg | K83: EUR | M83: 1 | V83: 0 | W83: 100 | AC83: 100 | AJ83: 0 | AQ83: 0 | AX83: 0 | BE83: 0 | BF83: 100 | BG83: 0 | BH83: 0 | BI83: 0 | BJ83: 0 | BK83: 0 | BL83: 100 | BS83: 0 | BT83: 1 | BZ83: 1 | CG83: 0 | CN83: 0 | CU83: 0 | DB83: 0 | DC83: 1 | DD83: 0 | DE83: 0 | DF83: 0 | DG83: 0 | DH83: 0 | DI83: 1 | DJ83: NO | DK83: NO | DL83: NO | DM83: NO | DN83: NO | DO83: NO | DP83: YES | DQ83: NO | DR83: NO | DS83: NO | DT83: NO | DU83: NO | DV83: NO | DW83: NO | DX83: NO | DY83: NO | DZ83: NO | EA83: NO | EB83: NO | EC83: NO | ED83: NO | EE83: NO | EF83: NO | EG83: NO | EH83: NO | EI83: NO | EJ83: NO | EK83: NO | EL83: NO | EM83: NO | EN83: NO | EO83: NO | EP83: NO | EQ83: NO | ER83: NO | ES83: NO | ET83: 100 | EZ83: 100 | FG83: 0 | FN83: 0 | FU83: 0 | GB83: 0 | GI83: 0 | GP83: 0 | GX83: 0 | GY83: 100 | GZ83: 0 | HA83: 0 | HB83: 0 | HC83: 0 | HD83: 0 | HE83: 100 | HL83: 0 | HM83: 100 | HS83: 100 | HZ83: 0 | IG83: 0 | IN83: 0 | IO83: 100 | IP83: 0 | IQ83: 0 | IR83: 0 | IS83: 0 | IT83: 0 | IU83: 100 | IV83: 60 | IW83: 30 | IX83: 10 | JA83: 3 | JB83: 3 | JC83: 2 | JD83: START Asia Pacific: | NG83: START Europe: | NH83: 100 | NN83: 100 | NU83: 0 | OB83: 0 | OI83: 0 | OP83: 0 | OW83: 0 | PD83: 0 | PL83: 0 | PM83: 100 | PN83: 0 | PO83: 0 | PP83: 0 | PQ83: 0 | PR83: 0 | PS83: 100 | PT83: 100 | PZ83: 100 | QG83: 0 | QN83: 0 | QU83: 0 | RB83: 0 | RC83: 100 | RD83: 0 | RE83: 0 | RF83: 0 | RG83: 0 | RH83: 0 | RI83: 100 | RJ83: START North America: | VM83: START Global: | ZP83: START SOUTH America: | ADS83: START Africa:
A84: 49 | B84: INREV | C84: 42761.389 | D84: Robbert Zoet | E84: Moorfield Group | F84: =VLOOKUP(MID(H84,SEARCH("@",H84,1),LEN(H84)-SEARCH("@",H84,1)+1),[2]Sheet1!$D:$F,3,FALSE) -> M655 | G84: Head of Capital Markets | H84: robbert.zoet@moorfield.com | I84: 2073991000 | J84: United Kingdom | K84: GBP | M84: 1 | V84: 0 | W84: 200 | AC84: 200 | AJ84: 0 | AQ84: 0 | AX84: 0 | BE84: 0 | BF84: 200 | BG84: 0 | BH84: 0 | BI84: 0 | BJ84: 0 | BK84: 0 | BL84: 200 | BS84: 0 | BT84: 1 | BZ84: 1 | CG84: 0 | CN84: 0 | CU84: 0 | DB84: 0 | DC84: 1 | DD84: 0 | DE84: 0 | DF84: 0 | DG84: 0 | DH84: 0 | DI84: 1 | DJ84: NO | DK84: NO | DL84: NO | DM84: NO | DN84: NO | DO84: NO | DP84: YES | DQ84: NO | DR84: NO | DS84: NO | DT84: NO | DU84: NO | DV84: NO | DW84: NO | DX84: NO | DY84: NO | DZ84: NO | EA84: NO | EB84: NO | EC84: NO | ED84: NO | EE84: NO | EF84: NO | EG84: NO | EH84: NO | EI84: NO | EJ84: NO | EK84: NO | EL84: NO | EM84: NO | EN84: NO | EO84: NO | EP84: NO | EQ84: NO | ER84: NO | ES84: NO | ET84: 135 | EZ84: 135 | FG84: 0 | FN84: 0 | FU84: 0 | FV84: 65 | GB84: 65 | GI84: 0 | GP84: 0 | GX84: 0 | GY84: 200 | GZ84: 0 | HA84: 0 | HB84: 0 | HC84: 0 | HD84: 0 | HE84: 200 | HL84: 0 | HM84: 135 | HS84: 135 | HT84: 65 | HZ84: 65 | IG84: 0 | IN84: 0 | IO84: 200 | IP84: 0 | IQ84: 0 | IR84: 0 | IS84: 0 | IT84: 0 | IU84: 200 | IX84: 100 | JA84: 1 | JB84: 1 | JC84: 1 | JD84: START Asia Pacific: | NG84: START Europe: | NH84: 135 | NN84: 135 | NU84: 0 | OB84: 0 | OI84: 0 | OJ84: 65 | OP84: 65 | OW84: 0 | PD84: 0 | PL84: 0 | PM84: 200 | PN84: 0 | PO84: 0 | PP84: 0 | PQ84: 0 | PR84: 0 | PS84: 200 | PT84: 135 | PZ84: 135 | QG84: 0 | QH84: 65 | QN84: 65 | QU84: 0 | RB84: 0 | RC84: 200 | RD84: 0 | RE84: 0 | RF84: 0 | RG84: 0 | RH84: 0 | RI84: 200 | RJ84: START North America: | VM84: START Global: | ZP84: START SOUTH America: | ADS84: START Africa:
A85: 148 | B85: INREV | C85: 42766.471 | D85: Ian Wimpenny | E85: Altus Group | F85: =VLOOKUP(MID(H85,SEARCH("@",H85,1),LEN(H85)-SEARCH("@",H85,1)+1),[2]Sheet1!$D:$F,3,FALSE) -> M692 | G85: Director | H85: ian.wimpenny@altusgroup.com | I85: 2035515448 | J85: Canada | K85: EUR | M85: 2 | N85: 6 | O85: We are cunsultants | V85: 0 | AC85: 0 | AJ85: 0 | AQ85: 0 | AX85: 0 | BE85: 0 | BF85: 0 | BG85: 0 | BH85: 0 | BI85: 0 | BJ85: 0 | BK85: 0 | BL85: 0 | BS85: 0 | BZ85: 0 | CG85: 0 | CN85: 0 | CU85: 0 | DB85: 0 | DC85: 0 | DD85: 0 | DE85: 0 | DF85: 0 | DG85: 0 | DH85: 0 | DI85: 0 | DJ85: NO | DK85: NO | DL85: NO | DM85: NO | DN85: NO | DO85: NO | DP85: NO | DQ85: NO | DR85: NO | DS85: NO | DT85: NO | DU85: NO | DV85: NO | DW85: NO | DX85: NO | DY85: NO | DZ85: NO | EA85: NO | EB85: NO | EC85: NO | ED85: NO | EE85: NO | EF85: NO | EG85: NO | EH85: NO | EI85: NO | EJ85: NO | EK85: NO | EL85: NO | EM85: NO | EN85: NO | EO85: NO | EP85: NO | EQ85: NO | ER85: NO | ES85: NO | EZ85: 0 | FG85: 0 | FN85: 0 | FU85: 0 | GB85: 0 | GI85: 0 | GP85: 0 | GX85: 0 | GY85: 0 | GZ85: 0 | HA85: 0 | HB85: 0 | HC85: 0 | HD85: 0 | HE85: 0 | HL85: 0 | HS85: 0 | HZ85: 0 | IG85: 0 | IN85: 0 | IO85: 0 | IP85: 0 | IQ85: 0 | IR85: 0 | IS85: 0 | IT85: 0 | IU85: 0 | JA85: 3 | JB85: 1 | JC85: 2 | JD85: START Asia Pacific: | NG85: START Europe: | RJ85: START North America: | VM85: START Global: | ZP85: START SOUTH America: | ADS85: START Africa:
A86: 204 | B86: INREV | C86: 42779.348 | D86: Uwira Jürgen | E86: PROJECT Real Estate Trust (PROJECT Investment AG) | F86: =VLOOKUP(MID(H86,SEARCH("@",H86,1),LEN(H86)-SEARCH("@",H86,1)+1),[2]Sheet1!$D:$F,3,FALSE) -> M680 | G86: Managing Director | H86: j.uwira@project-investment.de | I86: 4989599890861 | J86: Germany | K86: EUR | M86: 1 | V86: 0 | W86: 158 | AC86: 158 | AJ86: 0 | AQ86: 0 | AX86: 0 | BE86: 0 | BF86: 158 | BG86: 0 | BH86: 0 | BI86: 0 | BJ86: 0 | BK86: 0 | BL86: 158 | BS86: 0 | BT86: 2 | BZ86: 2 | CG86: 0 | CN86: 0 | CU86: 0 | DB86: 0 | DC86: 2 | DD86: 0 | DE86: 0 | DF86: 0 | DG86: 0 | DH86: 0 | DI86: 2 | DJ86: NO | DK86: NO | DL86: NO | DM86: NO | DN86: NO | DO86: NO | DP86: YES | DQ86: NO | DR86: NO | DS86: NO | DT86: NO | DU86: NO | DV86: NO | DW86: NO | DX86: NO | DY86: NO | DZ86: NO | EA86: NO | EB86: NO | EC86: NO | ED86: NO | EE86: NO | EF86: NO | EG86: NO | EH86: NO | EI86: NO | EJ86: NO | EK86: NO | EL86: NO | EM86: NO | EN86: NO | EO86: NO | EP86: NO | EQ86: NO | ER86: NO | ES86: NO | ET86: 95 | EZ86: 95 | FA86: 45 | FG86: 45 | FN86: 0 | FU86: 0 | GB86: 0 | GI86: 0 | GJ86: 8 | GP86: 8 | GQ86: Banks (Sparkasse) | GR86: 10 | GX86: 10 | GY86: 158 | GZ86: 0 | HA86: 0 | HB86: 0 | HC86: 0 | HD86: 0 | HE86: 158 | HL86: 0 | HM86: 158 | HS86: 158 | HZ86: 0 | IG86: 0 | IN86: 0 | IO86: 158 | IP86: 0 | IQ86: 0 | IR86: 0 | IS86: 0 | IT86: 0 | IU86: 158 | IV86: 41 | IX86: 59 | JA86: 1 | JB86: 3 | JC86: 1 | JD86: START Asia Pacific: | NG86: START Europe: | NH86: 95 | NN86: 95 | NO86: 45 | NU86: 45 | OB86: 0 | OI86: 0 | OP86: 0 | OW86: 0 | OX86: 8 | PD86: 8 | PE86: Banks (Sparkasse) | PF86: 10 | PL86: 10 | PM86: 158 | PN86: 0 | PO86: 0 | PP86: 0 | PQ86: 0 | PR86: 0 | PS86: 158 | PT86: 158 | PZ86: 158 | QG86: 0 | QN86: 0 | QU86: 0 | RB86: 0 | RC86: 158 | RD86: 0 | RE86: 0 | RF86: 0 | RG86: 0 | RH86: 0 | RI86: 158 | RJ86: START North America: | VM86: START Global: | ZP86: START SOUTH America: | ADS86: START Africa:
A87: 93 | B87: INREV | C87: 42748.532 | D87: Zoltan Szelyes | E87: CS | F87: =VLOOKUP(MID(H87,SEARCH("@",H87,1),LEN(H87)-SEARCH("@",H87,1)+1),[2]Sheet1!$D:$F,3,FALSE) -> M04230 | G87: Head of Global Real Estate Strategy | H87: zoltan.szelyes@credit-suisse.com | I87: 41443320080 | J87: Switzerland | K87: EUR | M87: 1 | V87: 0 | W87: 86 | Z87: 63 | AC87: 149 | AJ87: 0 | AO87: 340 | AQ87: 340 | AX87: 0 | BE87: 0 | BF87: 86 | BG87: 0 | BH87: 0 | BI87: 63 | BJ87: 340 | BK87: 0 | BL87: 489 | BS87: 0 | BT87: 2 | BW87: 3 | BZ87: 5 | CG87: 0 | CL87: 1 | CN87: 1 | CU87: 0 | DB87: 0 | DC87: 2 | DD87: 0 | DE87: 0 | DF87: 3 | DG87: 1 | DH87: 0 | DI87: 6 | DJ87: NO | DK87: NO | DL87: NO | DM87: NO | DN87: NO | DO87: NO | DP87: YES | DQ87: NO | DR87: NO | DS87: YES | DT87: NO | DU87: NO | DV87: NO | DW87: NO | DX87: NO | DY87: NO | DZ87: NO | EA87: NO | EB87: NO | EC87: NO | ED87: NO | EE87: NO | EF87: YES | EG87: NO | EH87: NO | EI87: NO | EJ87: NO | EK87: NO | EL87: NO | EM87: NO | EN87: NO | EO87: NO | EP87: NO | EQ87: NO | ER87: NO | ES87: NO | ET87: 50 | EZ87: 50 | FE87: 340 | FG87: 340 | FN87: 0 | FU87: 0 | GB87: 0 | GI87: 0 | GJ87: 36 | GM87: 63 | GP87: 99 | GX87: 0 | GY87: 86 | GZ87: 0 | HA87: 0 | HB87: 63 | HC87: 340 | HD87: 0 | HE87: 489 | HL87: 0 | HM87: 50 | HQ87: 340 | HS87: 390 | HZ87: 0 | IG87: 0 | IN87: 0 | IO87: 50 | IP87: 0 | IQ87: 0 | IR87: 0 | IS87: 340 | IT87: 0 | IU87: 390 | JA87: 1 | JB87: 3 | JC87: 1 | JD87: START Asia Pacific: | NG87: START Europe: | RJ87: START North America: | VM87: START Global: | ZP87: START SOUTH America: | ADS87: START Africa:
A88: 62 | B88: INREV | C88: 42760.459 | D88: Johan Kamminga | E88: a.s.r. real estate investment management | F88: =VLOOKUP(MID(H88,SEARCH("@",H88,1),LEN(H88)-SEARCH("@",H88,1)+1),[2]Sheet1!$D:$F,3,FALSE) -> M278 | G88: Fund Controller | H88: johan.kamminga@asr.nl | I88: 06 3096 2815 | J88: Netherlands | K88: EUR | M88: 1 | V88: 0 | W88: 250 | AC88: 250 | AJ88: 0 | AQ88: 0 | AX88: 0 | BE88: 0 | BF88: 250 | BG88: 0 | BH88: 0 | BI88: 0 | BJ88: 0 | BK88: 0 | BL88: 250 | BS88: 0 | BT88: 2 | BZ88: 2 | CG88: 0 | CN88: 0 | CU88: 0 | DB88: 0 | DC88: 2 | DD88: 0 | DE88: 0 | DF88: 0 | DG88: 0 | DH88: 0 | DI88: 2 | DJ88: NO | DK88: NO | DL88: NO | DM88: NO | DN88: NO | DO88: NO | DP88: YES | DQ88: NO | DR88: NO | DS88: NO | DT88: NO | DU88: NO | DV88: NO | DW88: NO | DX88: NO | DY88: NO | DZ88: NO | EA88: NO | EB88: NO | EC88: NO | ED88: NO | EE88: NO | EF88: NO | EG88: NO | EH88: NO | EI88: NO | EJ88: NO | EK88: NO | EL88: NO | EM88: NO | EN88: NO | EO88: NO | EP88: NO | EQ88: NO | ER88: NO | ES88: NO | ET88: 40 | EZ88: 40 | FA88: 185 | FG88: 185 | FN88: 0 | FU88: 0 | GB88: 0 | GI88: 0 | GP88: 0 | GQ88: Non-listed real estate fund | GR88: 25 | GX88: 25 | GY88: 250 | GZ88: 0 | HA88: 0 | HB88: 0 | HC88: 0 | HD88: 0 | HE88: 250 | HL88: 0 | HM88: 250 | HS88: 250 | HZ88: 0 | IG88: 0 | IN88: 0 | IO88: 250 | IP88: 0 | IQ88: 0 | IR88: 0 | IS88: 0 | IT88: 0 | IU88: 250 | IX88: 100 | JA88: 3 | JB88: 3 | JC88: 1 | JD88: START Asia Pacific: | NG88: START Europe: | NH88: 40 | NN88: 40 | NO88: 185 | NU88: 185 | OB88: 0 | OI88: 0 | OP88: 0 | OW88: 0 | PD88: 0 | PE88: Non-listed real estate fund | PF88: 25 | PL88: 25 | PM88: 250 | PN88: 0 | PO88: 0 | PP88: 0 | PQ88: 0 | PR88: 0 | PS88: 250 | PT88: 250 | PZ88: 250 | QG88: 0 | QN88: 0 | QU88: 0 | RB88: 0 | RC88: 250 | RD88: 0 | RE88: 0 | RF88: 0 | RG88: 0 | RH88: 0 | RI88: 250 | RJ88: START North America: | VM88: START Global: | ZP88: START SOUTH America: | ADS88: START Africa:
A89: 188 | B89: INREV | C89: 42774.458 | D89: Sloan Wobbeking | E89: Alma Property Partners | F89: =VLOOKUP(MID(H89,SEARCH("@",H89,1),LEN(H89)-SEARCH("@",H89,1)+1),[2]Sheet1!$D:$F,3,FALSE) -> M736 | G89: Partner & CEO | H89: sloan.wobbeking@almaproperty.se | I89: +46 70 227 74 00 | J89: Sweden | K89: EUR | M89: 1 | V89: 0 | W89: 90 | AC89: 90 | AJ89: 0 | AQ89: 0 | AX89: 0 | BE89: 0 | BF89: 90 | BG89: 0 | BH89: 0 | BI89: 0 | BJ89: 0 | BK89: 0 | BL89: 90 | BS89: 0 | BT89: 1 | BZ89: 1 | CG89: 0 | CN89: 0 | CU89: 0 | DB89: 0 | DC89: 1 | DD89: 0 | DE89: 0 | DF89: 0 | DG89: 0 | DH89: 0 | DI89: 1 | DJ89: NO | DK89: NO | DL89: NO | DM89: NO | DN89: NO | DO89: NO | DP89: YES | DQ89: NO | DR89: NO | DS89: NO | DT89: NO | DU89: NO | DV89: NO | DW89: NO | DX89: NO | DY89: NO | DZ89: NO | EA89: NO | EB89: NO | EC89: NO | ED89: NO | EE89: NO | EF89: NO | EG89: NO | EH89: NO | EI89: NO | EJ89: NO | EK89: NO | EL89: NO | EM89: NO | EN89: NO | EO89: NO | EP89: NO | EQ89: NO | ER89: NO | ES89: NO | ET89: 60 | EZ89: 60 | FG89: 0 | FN89: 0 | FU89: 0 | FV89: 10 | GB89: 10 | GI89: 0 | GJ89: 20 | GP89: 20 | GX89: 0 | GY89: 90 | GZ89: 0 | HA89: 0 | HB89: 0 | HC89: 0 | HD89: 0 | HE89: 90 | HL89: 0 | HM89: 90 | HS89: 90 | HZ89: 0 | IG89: 0 | IN89: 0 | IO89: 90 | IP89: 0 | IQ89: 0 | IR89: 0 | IS89: 0 | IT89: 0 | IU89: 90 | IX89: 100 | JA89: 3 | JB89: 3 | JC89: 1 | JD89: START Asia Pacific: | NG89: START Europe: | NH89: 60 | NN89: 60 | NU89: 0 | OB89: 0 | OI89: 0 | OP89: 0 | OQ89: 10 | OW89: 10 | OX89: 20 | PD89: 20 | PL89: 0 | PM89: 90 | PN89: 0 | PO89: 0 | PP89: 0 | PQ89: 0 | PR89: 0 | PS89: 90 | PT89: 90 | PZ89: 90 | QG89: 0 | QN89: 0 | QU89: 0 | RB89: 0 | RC89: 90 | RD89: 0 | RE89: 0 | RF89: 0 | RG89: 0 | RH89: 0 | RI89: 90 | RJ89: START North America: | VM89: START Global: | ZP89: START SOUTH America: | ADS89: START Africa:
A90: 234 | B90: INREV | C90: 42780 | D90: Steffen Uttich | E90: BEOS AG | F90: =VLOOKUP(MID(H90,SEARCH("@",H90,1),LEN(H90)-SEARCH("@",H90,1)+1),[2]Sheet1!$D:$F,3,FALSE) -> M617 | G90: Head of Fund Management | H90: steffen.uttich@beos.net | I90: 4915201528118 | J90: Germany | K90: EUR | M90: 1 | V90: 0 | W90: 135 | AC90: 135 | AJ90: 0 | AQ90: 0 | AX90: 0 | BE90: 0 | BF90: 135 | BG90: 0 | BH90: 0 | BI90: 0 | BJ90: 0 | BK90: 0 | BL90: 135 | BS90: 0 | BT90: 1 | BZ90: 1 | CG90: 0 | CN90: 0 | CU90: 0 | DB90: 0 | DC90: 1 | DD90: 0 | DE90: 0 | DF90: 0 | DG90: 0 | DH90: 0 | DI90: 1 | DJ90: NO | DK90: NO | DL90: NO | DM90: NO | DN90: NO | DO90: NO | DP90: YES | DQ90: NO | DR90: NO | DS90: NO | DT90: NO | DU90: NO | DV90: NO | DW90: NO | DX90: NO | DY90: NO | DZ90: NO | EA90: NO | EB90: NO | EC90: NO | ED90: NO | EE90: NO | EF90: NO | EG90: NO | EH90: NO | EI90: NO | EJ90: NO | EK90: NO | EL90: NO | EM90: NO | EN90: NO | EO90: NO | EP90: NO | EQ90: NO | ER90: NO | ES90: NO | ET90: 120 | EZ90: 120 | FG90: 0 | FN90: 0 | FU90: 0 | FV90: 15 | GB90: 15 | GI90: 0 | GP90: 0 | GX90: 0 | GY90: 135 | GZ90: 0 | HA90: 0 | HB90: 0 | HC90: 0 | HD90: 0 | HE90: 135 | HL90: 0 | HM90: 135 | HS90: 135 | HZ90: 0 | IG90: 0 | IN90: 0 | IO90: 135 | IP90: 0 | IQ90: 0 | IR90: 0 | IS90: 0 | IT90: 0 | IU90: 135 | IX90: 100 | JA90: 1 | JB90: 3 | JC90: 1 | JD90: START Asia Pacific: | NG90: START Europe: | NH90: 120 | NN90: 120 | NU90: 0 | OB90: 0 | OI90: 0 | OJ90: 15 | OP90: 15 | OW90: 0 | PD90: 0 | PL90: 0 | PM90: 135 | PN90: 0 | PO90: 0 | PP90: 0 | PQ90: 0 | PR90: 0 | PS90: 135 | PT90: 135 | PZ90: 135 | QG90: 0 | QN90: 0 | QU90: 0 | RB90: 0 | RC90: 135 | RD90: 0 | RE90: 0 | RF90: 0 | RG90: 0 | RH90: 0 | RI90: 135 | RJ90: START North America: | VM90: START Global: | ZP90: START SOUTH America: | ADS90: START Africa:
A91: 205 | B91: INREV | C91: 42780 | D91: Jamie Kellett | E91: BMO Real Estate Partners | F91: =VLOOKUP(MID(H91,SEARCH("@",H91,1),LEN(H91)-SEARCH("@",H91,1)+1),[2]Sheet1!$D:$F,3,FALSE) -> M213 | G91: Business Development Manager | H91: jkellett@bmorep.com | I91: 2070163564 | J91: United Kingdom | K91: EUR | M91: 1 | V91: 0 | W91: 419 | AC91: 419 | AJ91: 0 | AQ91: 0 | AX91: 0 | BE91: 0 | BF91: 419 | BG91: 0 | BH91: 0 | BI91: 0 | BJ91: 0 | BK91: 0 | BL91: 419 | BS91: 0 | BT91: 3 | BZ91: 3 | CG91: 0 | CN91: 0 | CU91: 0 | DB91: 0 | DC91: 3 | DD91: 0 | DE91: 0 | DF91: 0 | DG91: 0 | DH91: 0 | DI91: 3 | DJ91: NO | DK91: NO | DL91: NO | DM91: NO | DN91: NO | DO91: NO | DP91: YES | DQ91: NO | DR91: NO | DS91: NO | DT91: NO | DU91: NO | DV91: NO | DW91: NO | DX91: NO | DY91: NO | DZ91: NO | EA91: NO | EB91: NO | EC91: NO | ED91: NO | EE91: NO | EF91: NO | EG91: NO | EH91: NO | EI91: NO | EJ91: NO | EK91: NO | EL91: NO | EM91: NO | EN91: NO | EO91: NO | EP91: NO | EQ91: NO | ER91: NO | ES91: NO | ET91: 419 | EZ91: 419 | FG91: 0 | FN91: 0 | FU91: 0 | GB91: 0 | GI91: 0 | GP91: 0 | GX91: 0 | GY91: 419 | GZ91: 0 | HA91: 0 | HB91: 0 | HC91: 0 | HD91: 0 | HE91: 419 | HL91: 0 | HM91: 419 | HS91: 419 | HZ91: 0 | IG91: 0 | IN91: 0 | IO91: 419 | IP91: 0 | IQ91: 0 | IR91: 0 | IS91: 0 | IT91: 0 | IU91: 419 | IX91: 100 | JA91: 1 | JB91: 3 | JC91: 1 | JD91: START Asia Pacific: | NG91: START Europe: | NH91: 419 | NN91: 419 | NU91: 0 | OB91: 0 | OI91: 0 | OP91: 0 | OW91: 0 | PD91: 0 | PL91: 0 | PM91: 419 | PN91: 0 | PO91: 0 | PP91: 0 | PQ91: 0 | PR91: 0 | PS91: 419 | PT91: 419 | PZ91: 419 | QG91: 0 | QN91: 0 | QU91: 0 | RB91: 0 | RC91: 419 | RD91: 0 | RE91: 0 | RF91: 0 | RG91: 0 | RH91: 0 | RI91: 419 | RJ91: START North America: | VM91: START Global: | ZP91: START SOUTH America: | ADS91: START Africa:
A92: 112 | B92: INREV | C92: 42779.492 | D92: Louise McKay | E92: LaSalle Investment Management | F92: =VLOOKUP(MID(H92,SEARCH("@",H92,1),LEN(H92)-SEARCH("@",H92,1)+1),[2]Sheet1!$D:$F,3,FALSE) -> M020 | G92: Associate | H92: louise.mckay@lasalle.com | I92: 0207 852 4479 | J92: United States | K92: USD | M92: 1 | P92: 220 | Q92: 208 | S92: 26 | V92: 454 | W92: 348 | X92: 1006 | AB92: 195 | AC92: 1549 | AD92: 1297 | AE92: 300 | AJ92: 1597 | AL92: 427 | AM92: 271 | AQ92: 698 | AX92: 0 | BE92: 0 | BF92: 1865 | BG92: 1941 | BH92: 271 | BI92: 26 | BJ92: 0 | BK92: 195 | BL92: 4298 | BM92: 1 | BN92: 2 | BP92: 1 | BS92: 4 | BT92: 2 | BU92: 5 | BY92: 2 | BZ92: 9 | CA92: 3 | CB92: 1 | CG92: 4 | CI92: 1 | CJ92: 1 | CN92: 2 | CU92: 0 | DB92: 0 | DC92: 6 | DD92: 9 | DE92: 1 | DF92: 1 | DG92: 0 | DH92: 2 | DI92: 19 | DJ92: YES | DK92: YES | DL92: NO | DM92: YES | DN92: NO | DO92: NO | DP92: YES | DQ92: YES | DR92: NO | DS92: NO | DT92: NO | DU92: YES | DV92: YES | DW92: YES | DX92: NO | DY92: NO | DZ92: NO | EA92: NO | EB92: NO | EC92: YES | ED92: YES | EE92: NO | EF92: NO | EG92: NO | EH92: NO | EI92: NO | EJ92: NO | EK92: NO | EL92: NO | EM92: NO | EN92: NO | EO92: NO | EP92: NO | EQ92: NO | ER92: NO | ES92: NO | ET92: 785 | EU92: 1299 | EY92: 168 | EZ92: 2252 | FA92: 87 | FC92: 271 | FG92: 358 | FH92: 40 | FI92: 458 | FN92: 498 | FU92: 0 | FV92: 134 | FW92: 177 | GB92: 311 | GC92: 120 | GI92: 120 | GJ92: 648 | GK92: 6 | GP92: 654 | GQ92: Banks | GR92: 51 | GS92: 2 | GU92: 26 | GW92: 26 | GX92: 105 | GY92: 1865 | GZ92: 1942 | HA92: 271 | HB92: 26 | HC92: 0 | HD92: 194 | HE92: 4298 | HF92: 120 | HG92: 586 | HI92: 26 | HK92: 96 | HL92: 828 | HM92: 389 | HN92: 1156 | HO92: 271 | HR92: 98 | HS92: 1914 | HT92: 1356 | HU92: 200 | HZ92: 1556 | IG92: 0 | IN92: 0 | IO92: 1865 | IP92: 1942 | IQ92: 271 | IR92: 26 | IS92: 0 | IT92: 194 | IU92: 4298 | IV92: 15 | IX92: 85 | JA92: 3 | JB92: 3 | JC92: 1 | JD92: START Asia Pacific: | JE92: 150 | JF92: 200 | JK92: 350 | JR92: 0 | JS92: 40 | JY92: 40 | KF92: 0 | KM92: 0 | KT92: 0 | KV92: 6 | LA92: 6 | LB92: Corporate | LC92: 30 | LD92: 2 | LF92: 26 | LI92: 58 | LJ92: 220 | LK92: 208 | LL92: 0 | LM92: 26 | LN92: 0 | LO92: 0 | LP92: 454 | LQ92: 65 | LW92: 65 | LY92: 8 | MA92: 26 | MD92: 34 | ME92: 155 | MF92: 200 | MK92: 355 | MR92: 0 | MY92: 0 | MZ92: 220 | NA92: 208 | NB92: 0 | NC92: 26 | ND92: 0 | NE92: 0 | NF92: 454 | NG92: START Europe: | NH92: 270 | NI92: 371 | NM92: 168 | NN92: 809 | NO92: 37 | NU92: 37 | NW92: 458 | OB92: 458 | OI92: 0 | OJ92: 28 | OK92: 177 | OP92: 205 | OQ92: 14 | OW92: 14 | PD92: 0 | PE92: Corporate | PK92: 26 | PL92: 26 | PM92: 349 | PN92: 1006 | PO92: 0 | PP92: 0 | PQ92: 0 | PR92: 194 | PS92: 1549 | PT92: 305 | PU92: 728 | PY92: 98 | PZ92: 1131 | QA92: 44 | QB92: 278 | QF92: 96 | QG92: 418 | QN92: 0 | QU92: 0 | RB92: 0 | RC92: 349 | RD92: 1006 | RE92: 0 | RF92: 0 | RG92: 0 | RH92: 194 | RI92: 1549 | RJ92: START North America: | RK92: 366 | RL92: 300 | RQ92: 666 | RR92: 50 | RX92: 50 | SE92: 0 | SL92: 0 | SM92: 106 | SS92: 106 | ST92: 106 | SZ92: 106 | TA92: 648 | TG92: 648 | TH92: Corporate | TI92: 21 | TO92: 21 | TP92: 1297 | TQ92: 300 | TR92: 0 | TS92: 0 | TT92: 0 | TU92: 0 | TV92: 1597 | TW92: 20 | UC92: 20 | UD92: 76 | UE92: 300 | UJ92: 376 | UK92: 1201 | UQ92: 1201 | UX92: 0 | VE92: 0 | VF92: 1297 | VG92: 300 | VH92: 0 | VI92: 0 | VJ92: 0 | VK92: 0 | VL92: 1597 | VM92: START Global: | VO92: 427 | VT92: 427 | VW92: 271 | WA92: 271 | WH92: 0 | WO92: 0 | WV92: 0 | XC92: 0 | XJ92: 0 | XR92: 0 | XS92: 0 | XT92: 427 | XU92: 271 | XV92: 0 | XW92: 0 | XX92: 0 | XY92: 698 | YA92: 427 | YB92: 271 | YF92: 698 | YM92: 0 | YT92: 0 | ZA92: 0 | ZH92: 0 | ZI92: 0 | ZJ92: 427 | ZK92: 271 | ZL92: 0 | ZM92: 0 | ZN92: 0 | ZO92: 698 | ZP92: START SOUTH America: | ADS92: START Africa:
